{
    "original": "Karlsson\n\n*rb.: 21. Tillv.-värde pr år: 500,000 kr.\n\n—\tFirman etabl. 1870, bolag 1931.\nVerkst. dir.: v. konsul Gustaf Karlson.\nDisp.: Gusten Karlson.\n\n*A. Karlson Metall- och Maskin AB.,\n\nJStockholm.\n\nBolaget driver affärsverksamhet i\nmetaller och maskiner samt tackjärn och\njärnlegeringar.\n\nKontor: Birger Jarlsg. 13. Telegr.-adr.:\nRemin-d, Stockholm. Telefon: 232445.\nPostgiro: 2976. — Akt.-kap.: 585,000 kr.\n\n—\tFirman grundad 1902, ombildad 1923.\nStyrelse: dir. Otto Friman (ordf.),\n\növering. Anton Carlsund, fru L. Friman,\ndir. Anders Håkansson.\nVerkst. dir.: Otto Friman.\n\n*A. Karlsson, Nya\nSnickerifabriken, Gånghester.\n\nSe Nya Snickerifabriken, A.\nKarlsson, Gånghester.\n\n*Alb. Karlsson, Metallfabriksbolag,\n\nEskilstuna.\n\nMetallvarufabrik, förnicklings- och\nför-kromningsverk. Tillverkar\nbyggnadsbeslag, bilbeslag, hushållsvågar samt\nhögtalare för radioindustrien.\n\nTelefon: 30354, 30114 o. 31264.\nPostgiro: 32878. — Antal industriarb.: 140.\n\n—\tFirman etabl. 1890.\nChef: disp. Hugo A. Karre.\nKontorschef: Olof Granlund.\n\nVerkstadschef: ing. Holger Bruneli.\n\n*\tFrans Karlsson, Möbelfabrik, Tibro.\n\nTillverkar enrumsmöbler och\nkompletteringsmöbler vid fabrik i Tibro (Skarab.\n\nTelefon: 33. Postgiro: 12677. —\nArb.-antal: 5. Tillv.-värde pr år: 62,000 kr. —\nFirman etabl. 1909.\n\nÄgare o. chef: fabr. Frans Karlsson.\n\n*\tGottfrid Karlssons Skofabriks AB.,\n\nÖrebro.\n\nTillverkar randsydda herr- och\ndamskor, ago-damskor, becksömsydda\nsport-och skidskor. Varumärken: »Suverän» o.\n»Gekå-Sko».\n\nTelegr.-adr.: Gekåsko. Örebro. Telefon:\n»Suveränsko». Postgiro: 6152.\n\nAkt.-kap.: 100,000 kr. Antal\nindustriarb.: 100. Tillv.-värde pr år: 3,000,000 kr.\n\n—\tBolaget grundat 1936. #\nStyrelse o. disp.: Gottfrid Karlsson.\n\n2hi\n\nCust. Karlsson, Ejo.\n\nSmidesfabrik. Tillverkar\nkullagerskjut-dörrbeslag (märken: »GEKÅ» o.\n»Con-cur») samt spjäll och ventiler m. m.\n\nTelefon: 36. Postgiro: 96947. —\nArb.-antal: 11. Tillv.-värde pr år: 170,000 kr.\n— Firman etabl. 1931.\n\nÄgare o. chef: fabr. Gust. Karlsson.\n\n* Harry Karlsson &amp; C so AB.,\nByggnadsfirma, Lund.\n\nByggnadsentreprenörfirma för\nbostads-och affärshus, industribyggnader m. m.\n\nHuvudkontor: Lund. Telefon: 17350.\nPostgiro: 37611. Avd.-kontor: Göteborg,\nV:a Hamng. 18, telefon: 113316.\n\nAkt.-kap.: 100,000 kr. Prod.-värde pr\når: 8,000,000 kr. — Firman etabl. 1936,\nbolag 1944.\n\nStyrelse: byggm. Harry Karlsson\n(ordf.), fru Marianne Harry-Karlsson (v.\nordf.), kamrer Curt Berg, verkmäst. Albin\nPålsson, adv. Olof Wellmark.\n\nVerkst. dir.: Harry Karlsson.\n\nKamrer o. v. verkst. dir.: Curt Berg.\n\n*K. A. Karlsson, Snickerifabrik,\n\nFagersjö.\n\nTillverkar dörrar, fönster, trappor,\nköksinredningar och enklare\nbutiksinredningar vid fabrik i Fagersjö, Stockholm.\n\nTelefon: Södertörns villastad 160.\nPostgiro: 145976. — Arb.-antal: 3.\nTillv.-värde pr år: 45,000 kr. — Firman etabl.\n1920.\n\nÄgare o. chef: fabr. Karl A. Karlsson.\n\n*K. E. Karlssons Möbelfabrik,\n\nMjölby.\n\nSe Möbelfabriken Kåge, K. G.\nKår-beck, Mjölby.\n\n*AB. K. W. Karlsson, Gällstad.\n\nTrikåfabrik i Gällstad (Älvsb. l.).\nTillverkar badartiklar, herrvästar, jumpers,\nkoftor, strumpor, sportsockor, herr- och\ndamunderkläder av bomull och charmeuse\nsamt herr- och gosskjortor av charmeuse.\nVarumärken: »Kåwe» o. »Crawl».\n\nTelefon: 41 o. 71. Postgiro: 130482.\n\nAkt.-kap.: 300,000 kr. Antal\nindustriarb.: 50 samt 300 hemarb. Tillv.-värde pr\når: 1,700,000 kr. — Bolaget grundat 1923.\n\nStyrelse: dir. Algot Johansson, disp.\nÅke Johansson, fabr. Karl W. Karlsson.\n\nVerkst. dir.: Karl W. Karlsson.\n\nDisp.: Åke Johansson.\n\n3*",
    "structured": {
        "1": {
            "name": "A. Karlson Metall- och Maskin AB.",
            "location": "Stockholm",
            "business": "Affärsverksamhet i metaller och maskiner samt tackjärn och järnlegeringar",
            "contact": {
                "office": "Birger Jarlsg. 13",
                "phone": [
                    "232445"
                ],
                "telegraph": "Remin-d, Stockholm",
                "postgiro": "2976"
            },
            "financials": {
                "capital": "585,000 kr"
            },
            "foundation_year": 1902,
            "corporation_year": 1931,
            "board": [
                {
                    "name": "Otto Friman",
                    "role": "Styrelseordförande"
                },
                {
                    "name": "Anton Carlsund",
                    "role": "Övering"
                },
                {
                    "name": "L. Friman",
                    "role": "Styrelsemedlem"
                },
                {
                    "name": "Anders Håkansson",
                    "role": "Styrelsemedlem"
                }
            ],
            "director": "Gustaf Karlson",
            "managing_director": "Otto Friman"
        },
        "2": {
            "name": "Nya Snickerifabriken, A. Karlsson",
            "location": "Gånghester"
        },
        "3": {
            "name": "Alb. Karlsson, Metallfabriksbolag",
            "location": "Eskilstuna",
            "business": "Metallvarufabrik, förnicklings- och förkromningsverk. Tillverkar byggnadsbeslag, bilbeslag, hushållsvågar samt högtalare för radioindustrien",
            "contact": {
                "phone": [
                    "30354",
                    "30114",
                    "31264"
                ],
                "postgiro": "32878"
            },
            "financials": {
                "employees": {
                    "industriarb": 140
                }
            },
            "foundation_year": 1890
        },
        "4": {
            "name": "Frans Karlsson, Möbelfabrik",
            "location": "Tibro",
            "business": "Tillverkar enrumsmöbler och kompletteringsmöbler",
            "contact": {
                "phone": "33",
                "postgiro": "12677"
            },
            "financials": {
                "capital": "62,000 kr"
            },
            "foundation_year": 1909
        },
        "5": {
            "name": "Gottfrid Karlssons Skofabriks AB.",
            "location": "Örebro",
            "business": "Tillverkar randsydda herr- och damskor, ago-damskor, becksömsydda sport-och skidskor",
            "contact": {
                "telegraph": "Gekåsko",
                "phone": "Suveränsko",
                "postgiro": "6152"
            },
            "financials": {
                "capital": "100,000 kr",
                "employees": {
                    "industriarb": 100
                },
                "annual_turnover": "3,000,000 kr"
            },
            "foundation_year": 1936
        },
        "6": {
            "name": "Cust. Karlsson",
            "location": "Ejo",
            "business": "Smidesfabrik. Tillverkar kullagerskjutdörrbeslag samt spjäll och ventiler m.m",
            "contact": {
                "phone": "36",
                "postgiro": "96947"
            },
            "financials": {
                "capital": "170,000 kr"
            },
            "foundation_year": 1931
        },
        "7": {
            "name": "Harry Karlsson & C so AB., Byggnadsfirma",
            "location": "Lund",
            "business": "Byggnadsentreprenörfirma för bostads- och affärshus, industribyggnader m.m.",
            "contact": {
                "office": "Lund",
                "phone": [
                    "17350"
                ],
                "postgiro": "37611",
                "sales_offices": [
                    {
                        "location": "Göteborg",
                        "phone": "113316"
                    }
                ]
            },
            "financials": {
                "capital": "100,000 kr",
                "annual_production_value": "8,000,000 kr"
            },
            "foundation_year": 1936,
            "corporation_year": 1944,
            "board": [
                {
                    "name": "Harry Karlsson",
                    "role": "Styrelseordförande"
                },
                {
                    "name": "Marianne Harry-Karlsson",
                    "role": "Vice styrelseordförande"
                },
                {
                    "name": "Curt Berg",
                    "role": "Kamrer"
                },
                {
                    "name": "Albin Pålsson",
                    "role": "Verkmästare"
                },
                {
                    "name": "Olof Wellmark",
                    "role": "Advokat"
                }
            ],
            "director": "Harry Karlsson",
            "sales_manager": "Harry Karlsson",
            "manager": "Curt Berg"
        },
        "8": {
            "name": "K. A. Karlsson, Snickerifabrik",
            "location": "Fagersjö",
            "business": "Tillverkar dörrar, fönster, trappor, köksinredningar och enklare butiksinredningar",
            "contact": {
                "phone": "Södertörns villastad 160",
                "postgiro": "145976"
            },
            "financials": {
                "capital": "45,000 kr"
            },
            "foundation_year": 1920
        },
        "9": {
            "name": "AB. K. W. Karlsson",
            "location": "Gällstad",
            "business": "Trikåfabrik i Gällstad (Älvsb. l.). Tillverkar badartiklar, herrvästar, jumpers, koftor, strumpor, sportsockor, herr- och damunderkläder av bomull och charmeuse samt herr- och gosskjortor av charmeuse",
            "contact": {
                "phone": [
                    "41",
                    "71"
                ],
                "postgiro": "130482"
            },
            "financials": {
                "capital": "300,000 kr",
                "employees": {
                    "industriarb": 50,
                    "hemarb": 300
                },
                "annual_turnover": "1,700,000 kr"
            },
            "foundation_year": 1923,
            "board": [
                {
                    "name": "Algot Johansson",
                    "role": "Styrelseordförande"
                },
                {
                    "name": "Åke Johansson",
                    "role": "VD"
                },
                {
                    "name": "Karl W. Karlsson",
                    "role": "Fabriksdirektör"
                }
            ],
            "director": "Karl W. Karlsson"
        }
    }
}