{
    "original": "Förenade\n\narb.: 45. — Bolaget, grundat 1903, driver\njämväl engroshandel med kaffe.\n\nStyrelse: dir. Herman Lindquist\n(ordf.), konsul Tor E. J:son Broström,\ngeneralkonsul Axel Jonsson.\n\nVerJcst. dir.: Herman Lindquist.\n\nVice verJcst. dir.: L. Hill-Lindquist.\n\nKontorschef: V. Keyler.\n\n*\tFörenade Kalkindustrierna,\n\nFalköping.\n\nSe AB. Västergötlands Förenade\nKalk-industrier, Falköping.\n\n\"Förenade Kolsyrefabrikernas AB.,\n\nStockholm.\n\nSe De Förenade Kolsyrefabrikernas\nAB., Stockholm.\n\n*\tFörenade Konservfabrikerna,\n\nGöteborg.\n\nSe AB. Sveriges Förenad©\nKonservfabriker, Göteborg.\n\n\"Förenade Linnefabrikerna,\n\nAlingsås.\n\nSe Sveriges Förenade Linnefabriker»\nAB., Alingsås.\n\n\"AB. Förenade Möbelfabrikerna,\n\nLinköping.\n\nTillverkar möbler. Bolaget driver\njämväl sågverksrörelse och skogshantering.\n\nTelegr.-adr.: Möbelbolag, Linköping.\nTelefon: 20857. Postgiro: 29418. Repr. i\nStockholm: ing. Simon Ericson, Scheeleg.\n12, telefon: 516489.\n\nAkt.-kap.: 475,000 kr. Antal\nindustriarb.: 75. Tillv.-värde pr år: 1,000,000 kr.\n— Bolaget grundat 1918.\n\nStyrelse: disp. J. A. Mörk (ordf.),\ning. E. Simon Ericson, med. lic. Folke\nIsaksson, tandläkare Folke Sandqvist,\nkamrer Sven Walberg.\n\nVerJcst. dir. o. disp.: J. A. Mörk.\n\nKamrer: Sven Walberg.\n\n\"AB. Förenade Piano- &amp;\nOrgelfabriker, Arvika.\n\nBolaget tillverkar flyglar, pianon och\norglar vid följande tre fabriker: J. G.\nMalmsjö AB.. Göteborg, AB. östlind &amp;\nAlmquist, Arvika, samt Pianofabriks AB.\nGustafson &amp; Ljungqvist, Norrköping.\n\nHuvudkontor: Arvika. Telegr.-adr.:\nFörenade, Arvika. Telefon: 752. Postgiro:\n5045. Egna försäljningskontor och\nutställningslokaler: Stockholm, Kungsg. 4,\ntelefon: 105794 och Hamng. 26, telefon:\n106399; Göteborg, Arkaden, telefon:\n132792: Malmö, Österg. 11, telefon: 22638;\nNorrköping, telefon: 20726; Gävle,\ntelefon: 2670; Örebro, telefon: 11304;\nLinköping, telefon: 604,\n\nAkt.-kap.: 2,000,000 kr. Antal\nindustriarb.: 167. — Bolaget grundat 1917.\n\nStyrelse: adv. Fred. Holmgren (ordf.),\ndir. EL S. Bruu, dir. Karl Högberg, med.\ndr T. P. Lunden, dir. Arne Sande, konsul\nJ. E. Sande J:or.\n\nVerJcst. dir.: Karl Högberg.\nFöreståndare för\nförsäljningsmagasinen: i Stockholm: S. H. Lundén-Welden;\ni Göteborg: O. Holmer; i Malmö: Harry\nOrsin; i Norrköping: O.\nLangöe-Con-radsen; i Gävle: Arne Blomqvist; i\nÖrebro: Gösta Flodin; i Linköping: Ernst\nLöfstedt.\n\n\"AB. Förenade Superfosfatfabriker,\n\nHälsingborg.\n\nBolaget äger superfosfatfabriker i\nLandskrona, Limhamn och Malmö,\nmagasin i Göteborg, Norrköping och\nStockholm samt arrenderar Kooperativa\nSuper-fosfatfabriks AB:s fabrik vid Gäddviken,\nStockholm. Tillverkar superfosfat.\n\nHuvudkontor: Hälsingborg.\nTelegr.-adr.: Fosfaten, Hälsingborg. Telefon:\n14880. Postgiro: 170786.\n\nAvd.-kontor: i Landskrona, telegr.-adr.:\nFosfaten, Landskrona; i Limhamn,\ntelegr.-adr.: Fosfaten, Limhamn; i Malmö,\ntelegr.-adr.: Gödningsfabriken, Malmö; i\nGöteborg, Marieholmsmagasinet,\ntelegr.-adr.: Fosfaten, Göteborg; i Stockholm,\nGäddviken, telegr.-adr.: Fosfab,\nStockholm; i Norrköping, telegr.-adr.:\nFosfaten, Norrköping.\n\nEnsamförsäljare för Sverige, Norge och\nFinland: Svenska Superfosfat\nFörsäljnings AB., Hälsingborg, telefon:\n»Fosfatförsäljning», med avd.-kontor: i\nStockholm, Kungsg. 28, telefon: 109886—87;\ni Göteborg: Packhusplatsen 2, telefon:\n131407.\n\nAkt.-kap.: 18,336,000 kr. Antal\nindustriarb. (sammanlagt för samtliga\nfabriker): 740. Tillv.-värde pr år: 39,000,000\nkr. — B olagret bildat 1931.\n\nStyrelse: bankdir. Helmer Stén (ordf.),\ndir. Einar Sjögren (v. ordf.), dir.\nGunnar Forsman, dir. Sven E. Lundberg, dir.\nHans Rydin, dir. Harry Tranchell, dir.\nJan Wingårdh.\n\nVerJcst. dir.: Sven E. Lundberg.",
    "structured": {
        "1": {
            "name": "Förenade arb.",
            "business": "driver jämväl engroshandel med kaffe",
            "board": [
                {
                    "name": "Herman Lindquist",
                    "role": "dir."
                },
                {
                    "name": "Tor E. J:son Broström",
                    "role": "konsul"
                },
                {
                    "name": "Axel Jonsson",
                    "role": "generalkonsul"
                }
            ],
            "director": "Herman Lindquist",
            "vice_managing_director": "L. Hill-Lindquist",
            "contact": {
                "office": "Falköping"
            },
            "foundation_year": 1903
        },
        "2": {
            "name": "AB. Förenade Möbelfabrikerna",
            "products": "Tillverkar möbler. Bolaget driver jämväl sågverksrörelse och skogshantering",
            "contact": {
                "office": "Linköping",
                "phone": [
                    "20857"
                ],
                "postgiro": "29418",
                "head_office": "Stockholm: ing. Simon Ericson, Scheeleg. 12, telefon: 516489"
            },
            "financials": {
                "capital": "475,000 kr",
                "employees": {
                    "industriarb.": 75
                },
                "annual_production_value": "1,000,000 kr"
            },
            "foundation_year": 1918,
            "board": [
                {
                    "name": "J. A. Mörk",
                    "role": "disp."
                },
                {
                    "name": "E. Simon Ericson",
                    "role": "ing."
                },
                {
                    "name": "Folke Isaksson",
                    "role": "med. lic."
                },
                {
                    "name": "Folke Sandqvist",
                    "role": "tandläkare"
                },
                {
                    "name": "Sven Walberg",
                    "role": "kamrer"
                }
            ],
            "director": "J. A. Mörk",
            "manager": "Sven Walberg"
        },
        "3": {
            "name": "AB. Förenade Piano- & Orgelfabriker",
            "products": "tillverkar flyglar, pianon och orglar",
            "contact": {
                "office": "Arvika",
                "phone": [
                    "752"
                ],
                "postgiro": "5045"
            },
            "financials": {
                "capital": "2,000,000 kr",
                "employees": {
                    "industriarb.": 167
                }
            },
            "foundation_year": 1917,
            "board": [
                {
                    "name": "adv. Fred. Holmgren",
                    "role": "ordf."
                },
                {
                    "name": "EL S. Bruu",
                    "role": "dir."
                },
                {
                    "name": "Karl Högberg",
                    "role": "dir."
                },
                {
                    "name": "T. P. Lunden",
                    "role": "med. dr"
                },
                {
                    "name": "Arne Sande",
                    "role": "dir."
                },
                {
                    "name": "J. E. Sande J:or",
                    "role": "konsul"
                }
            ],
            "director": "Karl Högberg",
            "sales_manager": "S. H. Lundén-Welden"
        },
        "4": {
            "name": "AB. Förenade Superfosfatfabriker",
            "products": "Tillverkar superfosfat",
            "contact": {
                "office": "Hälsingborg",
                "phone": [
                    "14880"
                ],
                "postgiro": "170786"
            },
            "financials": {
                "capital": "18,336,000 kr",
                "employees": {
                    "sammanlagt för samtliga fabriker": 740
                },
                "annual_production_value": "39,000,000 kr"
            },
            "foundation_year": 1931,
            "board": [
                {
                    "name": "bankdir. Helmer Stén",
                    "role": "ordf."
                },
                {
                    "name": "Einar Sjögren",
                    "role": "v. ordf."
                },
                {
                    "name": "Gunnar Forsman",
                    "role": "dir."
                },
                {
                    "name": "Sven E. Lundberg",
                    "role": "dir."
                },
                {
                    "name": "Hans Rydin",
                    "role": "dir."
                },
                {
                    "name": "Harry Tranchell",
                    "role": "dir."
                },
                {
                    "name": "Jan Wingårdh",
                    "role": "dir."
                }
            ],
            "director": "Sven E. Lundberg"
        }
    }
}