{
    "original": "Ulfshytte-—Ulvsunda\n\nStyrelse, verkst. dir. o. disp.: W.\nUlän-der.\n\nKamrer: Einar Erlandson.\n\n* Ulfshytte Jern verks AB.,\n\nVikmanshyttan.\n\nJärnverk med gruvor och\nanrikningsverk samt såg, hyvleri och elektr.\nvattenkraftstationer inom Silvberg och Stora\nTuna socknar (Kopparb. l.). Bryter och\nanrikar järnmalm samt tillverkar sågade\noch hyvlade trävaror. Bolaget idkar\njämväl jordbruk och skogshantering.\n\nTelegr.-adr.: Wikmanshyttan,\nHedemora. Telefon: »Wikmanshyttebruk»,\nHedemora o. Borlänge 47014 o. 47021.\nPostgiro: 95825.\n\nAkt.-kap.: 1,750,000 kr. Antal\nindustriarb.: 120. Årstillv.: 35,000 ton slig, 1,200\nå 1,500 stds sågade och hyvlade trävaror.\nTillv.-värde pr år: 1,500,000 kr. —\nBolaget, grundat 1887, äges av Wikmanshytte\nBruks AB.\n\nStyrelse: bankdir. Jacob Wallenberg\n(ordf.), disp. Henrik Arfwedson, disp.\nArvid Olsson.\n\nVerkst. dir. o. disp.: Arvid Olsson.\n\nFörsäljn.-chef: Arthur Törnquist.\n\nInköpschef: Y. Löfstedt.\n\nPlatschef i Ulfshyttan: bergsing.\nWilhelm Sidenvall.\n\n*AB. K. A. Ullholm, Linköping.\n\nTillverkar strumpor. Bolaget driver\näven engroshandel med strumpor.\n\nTelegr.-adr. o. telefon: »Ullholms»,\nLinköping. Postgiro: 6163. — Akt.-kap.:\n810,000 kr. Antal industriarb.: 10.\n\nFirman, etabl. 1916, bolag 1924, äger\nAB. Linköpings Strumpfabrik och\nSvenska Strumpfabriks AB.\n\nStyrelse o. verkst. dir.: v. konsul K. A.\nUllholm.\n\nIHsp.: Bengt Lindström.\n\nKontorschef: kamrer Gustav Olausson.\n\nAB. Ulricehamns Yllefabrik,\n\nUlricehamn.\n\nTillverkar trikå- och yllevaror.\n\nTelegr.-adr.: Yllefabriken, Ulricehamn.\n.Telefon: »Ulricehamns Yllefabrik».\nPostgiro: 32671.\n\nAkt.-kap.: 303,000 kr. Antal\nindustriarb.: 90. Tillv.-värde pr år: 2,000,000 kr.\n— Bolaget grundat 1916.\n\nStyrelse: dir. Johan Ljungberg (ordf.),\ndisp. Anders Gunnarson, disp. Folke\nHultgren.\n\nVerkst. dir. o. disp.: J. Ljungberg.\n\nKontorschef: Sten Bäcken.\n\n*\tUlriksfors Sulfit AB., Stockholm.\n\nSulfitfabrik vid Ulriksfors (Jämtl. l.).\nTillverkar stark sulfitcellulosa. ^\n\nHuvudkontor: Stockholm, Eriksbergsg.\n27. Telegr.-adr.: Ulrikmill, Stockholm.\nTelefon: 103793. Postgiro: 153221.\n\nAkt.-kap.: 700,000 kr. Antal\nindustriarb.: 110. Årstill verkning: 16,000 ton\nsulfitcellulosa. — Bolaget, som grundades\n1915, har under kalenderns tryckning\nförsålts till Svenska Cellulosa AB.\n\nStyrelse: jägmäst. Arvid Carlander\n(ordf.), dir. R. Flygt, kamrer E.\nHele-nius.\n\nVerkst. dir.: Arvid Carlander.\n\nDriftsing.: Tore Eriksson.\n\n*Ulunda Kalkbruk, Värnhem.\n\nSe AB. Västergötlands Förenade\nKalkindustrier, Falköping.\n\n*H. Ulvfors, Stockholm.\n\nSyfabrik. Tillverkar som specialitet\ndamunderkläder i charmeuse och\nkonstsiden. Varumärke: »Pärlemor».\n\nKontor: Götg. 14. Telegr.-adr.:\nUlvfors, Stockholm. Telefon: 415475 o.\n415566. Postgiro: 50519. Ensamförsälj.\nf. Sverige utom Stockholm: Gustaf\nHor-witz, Stockholm, Strandvägen 5 B,\ntelefon: 612650.\n\nAntal industriarb.: 50. Tillv.-värde pr\når: 600,000 kr. — Firman etabl. 1927.\n\nÄgare o. chef: fabr. Henry Ulvfors.\n\n*\tUlvsunda Cummifabriks AB.,\n\nUlv sunda.\n\nGummifabrik i Ulvsunda, Stockholm.\nTillverkar gummislangar för industrien,\ntekniska gummivaror och formgjorda\ngummi detalj er, gummibeläggning av\nvalsar och transporthjul, gummiklackar och\n-sulor, gummiparkettgolv och\ngummimattor, gummiremmar,\nmaskinpackningar, isoleringsband, bakelitvaror m. m.\n\nTelegr.-adr.: Ulvsundagummi.\nStockholm. Telefon: Stockholm 262560.\nPostgiro: 10899.\n\nAkt.-kap.: 381,250 kr. Antal\nindustriarb.: 300. Tillv.-värde pr år: 5,000,000 kr.\n— Bolaget grundat 1917.\n\nStyrelse: disp. Henry Dunker (ordf.),\ndisp. Bror E. Anderson, disp. Artur\nStibe, dir. H. Stählbrandt.\n\nDisp.: Ruben Engvall.\n\nTeknisk ledare: civiling. Folke\nBerg-wall.\n\nKontorschef: Henry Brunell.\n\nFörsäljn.-chef: Anders Key.\n\nInköpschef: Gunnar Nilsson.\n\n600*",
    "structured": {
        "firms": {
            "1": {
                "name": "Ulfshytte Jern verks AB.",
                "location": "Vikmanshyttan",
                "business": "Järnverk med gruvor och anrikningsverk samt såg, hyvleri och elektr. vattenkraftstationer",
                "products": "Bryter och anrikar järnmalm samt tillverkar sågade och hyvlade trävaror. Bolaget idkar jämväl jordbruk och skogshantering.",
                "contact": {
                    "office": "Wikmanshyttan, Hedemora",
                    "phone": [
                        "Hedemora/Borlänge 47014",
                        "Hedemora/Borlänge 47021"
                    ],
                    "postgiro": "95825"
                },
                "financials": {
                    "capital": "1,750,000 kr",
                    "employees": {
                        "industriarb": 120
                    },
                    "annual_turnover": "1,500,000 kr",
                    "annual_production_value": "1,500,000 kr"
                },
                "foundation_year": 1887,
                "owners": [
                    "Wikmanshytte Bruks AB"
                ],
                "board": [
                    {
                        "name": "Jacob Wallenberg",
                        "role": "ordf."
                    },
                    {
                        "name": "Henrik Arfwedson",
                        "role": "disp."
                    },
                    {
                        "name": "Arvid Olsson",
                        "role": "disp."
                    }
                ],
                "director": "W. Ulän-der",
                "sales_manager": "Arthur Törnquist"
            },
            "2": {
                "name": "AB. K. A. Ullholm",
                "location": "Linköping",
                "business": "Tillverkar strumpor. Bolaget driver även engroshandel med strumpor.",
                "contact": {
                    "office": "Linköping",
                    "phone": [
                        "Ullholms Linköping"
                    ],
                    "postgiro": "6163"
                },
                "financials": {
                    "capital": "810,000 kr",
                    "employees": {
                        "industriarb": 10
                    }
                },
                "foundation_year": 1916
            },
            "3": {
                "name": "AB. Ulricehamns Yllefabrik",
                "location": "Ulricehamn",
                "business": "Tillverkar trikå- och yllevaror",
                "contact": {
                    "office": "Ulricehamn",
                    "phone": [
                        "Ulricehamns Yllefabrik"
                    ],
                    "postgiro": "32671"
                },
                "financials": {
                    "capital": "303,000 kr",
                    "employees": {
                        "industriarb": 90
                    },
                    "annual_production_value": "2,000,000 kr"
                },
                "foundation_year": 1916
            },
            "4": {
                "name": "Ulriksfors Sulfit AB.",
                "location": "Stockholm",
                "business": "Tillverkar stark sulfitcellulosa",
                "contact": {
                    "office": "Stockholm, Eriksbergsg. 27",
                    "phone": [
                        "Stockholm 103793"
                    ],
                    "postgiro": "153221"
                },
                "financials": {
                    "capital": "700,000 kr",
                    "employees": {
                        "industriarb": 110
                    },
                    "annual_production_value": "16,000 ton sulfitcellulosa"
                },
                "foundation_year": 1915
            },
            "5": {
                "name": "Ulunda Kalkbruk",
                "location": "Värnhem",
                "predecessor": "AB. Västergötlands Förenade Kalkindustrier, Falköping"
            },
            "6": {
                "name": "H. Ulvfors",
                "location": "Stockholm",
                "business": "Syfabrik. Tillverkar som specialitet damunderkläder i charmeuse och konstsiden.",
                "contact": {
                    "office": "Götg. 14, Stockholm",
                    "phone": [
                        "Stockholm 415475",
                        "Stockholm 415566"
                    ],
                    "postgiro": "50519",
                    "telegraph": "Ulvfors, Stockholm"
                },
                "financials": {
                    "annual_production_value": "600,000 kr"
                },
                "director": "fabr. Henry Ulvfors"
            },
            "7": {
                "name": "Ulvsunda Cummifabriks AB.",
                "location": "Ulv sunda",
                "business": "Gummifabrik i Ulvsunda, Stockholm. Tillverkar gummislangar för industrien, tekniska gummivaror och formgjorda gummi detaljer, gummibeläggning av valsar och transporthjul, gummiklackar och -sulor, gummiparkettgolv och gummimattor, gummiremmar, maskinpackningar, isoleringsband, bakelitvaror m. m.",
                "contact": {
                    "office": "Stockholm",
                    "phone": [
                        "Stockholm 262560"
                    ],
                    "postgiro": "10899"
                },
                "financials": {
                    "capital": "381,250 kr",
                    "employees": {
                        "industriarb": 300
                    },
                    "annual_production_value": "5,000,000 kr"
                },
                "foundation_year": 1917
            }
        }
    }
}