{
    "original": "Svenska\n\nStyrelse: konsul Edw. H. Thomée\n(ordf.), fil. lic. Allan Bäckman, fru Brita\nCrelbjerg-Hansen.\n\n’Svenska Suchard AB., Lidköping.\n\nChoklad- och karamellfabrik i Alingsås.\nTillverkar choklad, konfekt, karameller,\nkola och marmelad m. m. Varumärke:\n»Suchard».\n\nKassakontor: Lidköping. Telegr.-adr.:\nSuchard, Lidköping. Telefon: »Kinnevik».\nFabriks- o. försäljningskontor: Alingsås.\nTelegr.-adr.: Suchard, Alingsås. Telefon:\n»Suchard o. L. K.». Postgiro: 20642.\nAvd.-kontor: Stockholm, Sveavägen 48, telefon:\n233920; Göteborg, ö. Hamng. 52, telefon:\n132090.\n\nAkt.-kap.: 1,000,000 kr. Antal\nindustriarb.: 330. — Bolaget, grundat år 1919,\n^arbetar under gemensam förvaltning med\nAB. Lidköpings Konfektyr Industri,\nLidköping.\n\nStyrelse: hovjägm. frih. Wilh.\nKling-spor (ordf.), adv. Husro Stenbeck (v.\nordf.), dir. Clarence T. Brockman, dir. G.\nPetitpierre, dir. E. Sjöstedt, bankdir.\nSelmer Sten, dir. Folke Stenbeck.\n\nVerkst. dir.: Clarence T. Brockman\n^Alingsås).\n\nEkonomichef: Hilding Johanson\ni Alingsås).\n\nFörsäljn.-chef: Leif Erhardt\n&lt;Alingsås).\n\nFabrikschef: Sten Blixt (Alingsås).\n\nReklamchef: A. Björkegård (Alingsås).\n\nDir. för kassakontoret: H. Björkeroth\n^Lidköping).\n\nAB. Svenska Suckatfabriken,\n\nMalmö.\n\nTillverkar kanderade frukter,\nfruktkon-rserver och sylt. Varumärke: »Diamante\n-suckat».\n\nKontor: Kalendeg. 17. Telegr.-adr.:\nSvensksuckat, Malmö. Telefon: 29066.\nPostgiro: 37936. — Akt.-kap.: 30,000 kr.\nArb.-antal: 9. Tillv.-värde pr år: 330,000\nkr. — Firman etabl. 1932, bolag 1935.\n\nStyrelse: konsul Carl Arvidsson.\n\nVerkst. dir.: Sven Arvidsson.\n\nAB. Svenska Stilfabriken,\n\nGöteborg.\n\nTillverkar inläggssulor till skodon.\nSpecialitet: Getraggsulor. Varumärke:\n»Getmärket».\n\nKontor: Köpmansg. 36—38. Telefon:\n132882. Postgiro: 44112. — Akt.-kap.:\n5,000 kr. Arb.-antal: 12. Tillv.-värde pr\når: 100,000 kr. — Firman etabl. 1931.\n\nVerkst. dir.: fru Alice örnefeldt.\n\nSvenska Superfosfat-Försäljnings\n\nAB., Hälsingborg.\n\nEnsamförsäljare av super fosfat inom\nlandet för AB. Förenade Superfosfat:\nfabriker, Hälsingborg, med fabriker i\nLandskrona, Malmö och Limhamn samt\narrendefabrik vid Gäddviken, Stockholm.\nBolaget driver jämväl handel med\nimporterade gödselmedel.\n\nHuvudkontor: Hälsingborg. Telefon:\n»Fosfatförsäljningen». Postgiro: 14373.\nFilialkontor: Stockholm, Kungsg. 28,\ntelefon: 109886—87; Göteborg, Packhuspl.\n2, telefon: 131407 o. 131490. Telegr.-adr.:\nFosforsyra, Hälsingborg, Stockholm och\nGöteborg.\n\nAkt.-kap.: 3,600,000 kr. — Bolaget\ngrundat 1909.\n\nStyrelse: bergsing. Sven E. Lundberg\n(ordf.), dir. Elis Berglund, dir. Hans\nRy-din.\n\nVerkst. dir.: Elis Berglund.\n\nFörsäljn.-chef: F. Save.\n\nAB. Svenska Syrgasfabriken,\n\nOskarshamn.\n\nTillverkar syrgas, kväve och flytande\nluft.\n\nTelefon: 353. Postgiro: 12773. —\nAkt.-kap.: 264,000 kr. Tillv.-värde pr år:\n120,000 kr. — Firman etabl. 1910.\n\nStyrelse: kabinettskammarh. Rolf v.\nHeidenstam, bergsing. Axel Sandels.\n\nVerkst. dir.: Axel Sandels.\n\n’AB. Svenska Tacksfabriken,\n\nTrollhättan.\n\nSkostiftfabrik med tråddrageri.\nTillverkar skostift (tacks), klackspik,\nskofjädrar (gelänkfjädrar), pappgelänk samt\nhäfttråd, stifttråd och knappnålar.\n\nTelegr.-adr.: Tacksfabriken,\nTrollhättan. Telefon: 10062 o. 10602. Postgiro:\n20661. Representant i Stockholm: AB.\nH. Brunner, Tunnelg. 21, telefon: 232285.\n\nAkt.-kap.: 700,000 kr. Antal\nindustriarb.: 90. — Bolaget grundat 1901.\n\nStyrelse: bergsing. Arne Arlén, dir.\nHugo Dahlgren, fru Hildur Lawson.\n\nVerkst. dir.: Hugo Dahlgren.\n\n’Svenska Tagelspinneri AB.,\n\nKarlstad.\n\nBereder tagel till madrass- och\nmöbelstoppning, tagel för borstbinderier samt\ntagelmattor.\n\nTelegr.-adr.: Svensktagel, Karlstad.\nTelefon: 10453. Postgiro: 71339.",
    "structured": {
        "firms": [
            {
                "name": "AB. Svenska Suchard",
                "location": "Alingsås",
                "business": "Choklad- och karamellfabrik",
                "products": "Tillverkar choklad, konfekt, karameller, kola och marmelad m.m.",
                "contact": {
                    "office": "Lidköping",
                    "phone": [
                        "Kinnevik"
                    ],
                    "postgiro": "20642",
                    "head_office": "Alingsås",
                    "sales_offices": [
                        {
                            "location": "Stockholm",
                            "phone": "233920"
                        },
                        {
                            "location": "Göteborg",
                            "phone": "132090"
                        }
                    ],
                    "telegraph": "Suchard, Alingsås",
                    "factory_office": "Alingsås",
                    "factory_phone": ""
                },
                "financials": {
                    "capital": "1,000,000 kr",
                    "employees": {
                        "industriarb": 330
                    }
                },
                "foundation_year": 1919
            },
            {
                "name": "AB. Svenska Suckatfabriken",
                "location": "Malmö",
                "business": "Tillverkar kanderade frukter, fruktkonserver och sylt",
                "products": "",
                "contact": {
                    "office": "",
                    "phone": [
                        "29066"
                    ],
                    "postgiro": "37936",
                    "head_office": "",
                    "sales_offices": [],
                    "telegraph": "Svensksuckat, Malmö",
                    "factory_office": "",
                    "factory_phone": ""
                },
                "financials": {
                    "capital": "30,000 kr",
                    "employees": {
                        "arbantal": 9
                    },
                    "annual_turnover": "330,000 kr",
                    "annual_production_value": ""
                },
                "foundation_year": 1932,
                "corporation_year": 1935
            },
            {
                "name": "AB. Svenska Stilfabriken",
                "location": "Göteborg",
                "business": "Tillverkar inläggssulor till skodon",
                "products": "Specialitet: Getraggsulor",
                "contact": {
                    "office": "Köpmansg. 36—38",
                    "phone": [
                        "132882"
                    ],
                    "postgiro": "44112",
                    "head_office": "",
                    "sales_offices": [],
                    "telegraph": "",
                    "factory_office": "",
                    "factory_phone": ""
                },
                "financials": {
                    "capital": "5,000 kr",
                    "employees": {
                        "arbantal": 12
                    },
                    "annual_turnover": "",
                    "annual_production_value": "100,000 kr"
                },
                "foundation_year": 1931
            },
            {
                "name": "Svenska Superfosfat-Försäljnings AB.",
                "location": "Hälsingborg",
                "business": "Ensamförsäljare av super fosfat inom landet",
                "products": "",
                "contact": {
                    "office": "Hälsingborg",
                    "phone": [
                        "Fosfatforsaljningen"
                    ],
                    "postgiro": "14373",
                    "head_office": "",
                    "sales_offices": [
                        {
                            "location": "Stockholm",
                            "phone": "109886—87"
                        },
                        {
                            "location": "Göteborg",
                            "phone": "131407 o. 131490"
                        }
                    ],
                    "telegraph": "Fosforsyra, Hälsingborg, Stockholm och Göteborg",
                    "factory_office": "",
                    "factory_phone": ""
                },
                "financials": {
                    "capital": "3,600,000 kr",
                    "employees": {},
                    "annual_turnover": "",
                    "annual_production_value": ""
                },
                "foundation_year": 1909
            },
            {
                "name": "AB. Svenska Syrgasfabriken",
                "location": "Oskarshamn",
                "business": "Tillverkar syrgas, kväve och flytande luft",
                "products": "",
                "contact": {
                    "office": "",
                    "phone": [
                        "353"
                    ],
                    "postgiro": "12773",
                    "head_office": "",
                    "sales_offices": [],
                    "telegraph": "",
                    "factory_office": "",
                    "factory_phone": ""
                },
                "financials": {
                    "capital": "264,000 kr",
                    "employees": {},
                    "annual_turnover": "",
                    "annual_production_value": "120,000 kr"
                },
                "foundation_year": 1910
            },
            {
                "name": "AB. Svenska Tacksfabriken",
                "location": "Trollhättan",
                "business": "Skostiftfabrik med tråddrageri",
                "products": "Tillverkar skostift (tacks), klackspik, skofjädrar (gelänkfjädrar), pappgelänk samt häfttråd, stifttråd och knappnålar",
                "contact": {
                    "office": "",
                    "phone": [
                        "10062 o. 10602"
                    ],
                    "postgiro": "20661",
                    "head_office": "",
                    "sales_offices": [],
                    "telegraph": "Tacksfabriken, Trollhättan",
                    "factory_office": "",
                    "factory_phone": ""
                },
                "financials": {
                    "capital": "700,000 kr",
                    "employees": {
                        "antalindustriarb": 90
                    },
                    "annual_turnover": "",
                    "annual_production_value": ""
                },
                "foundation_year": 1901
            },
            {
                "name": "AB. Svenska Tagelspinneri",
                "location": "Karlstad",
                "business": "Bereder tagel till madrass- och möbelstoppning, tagel för borstbinderier samt tagelmattor",
                "products": "",
                "contact": {
                    "office": "Kalendeg. 17",
                    "phone": [
                        "10453"
                    ],
                    "postgiro": "71339",
                    "head_office": "",
                    "sales_offices": [],
                    "telegraph": "Svensktagel, Karlstad",
                    "factory_office": "",
                    "factory_phone": ""
                },
                "financials": {
                    "capital": "",
                    "employees": {},
                    "annual_turnover": "",
                    "annual_production_value": ""
                },
                "foundation_year": null
            }
        ]
    }
}