{
    "original": "Nordenström—NordisJca\n\nryttm. Nils Berg, greve Gösta Bonde,\növerstelöjtn. Nils Ingvarson.\n\nVerkst. dir.: Gunnar Berg.\n\nKontorschef: Ragnar Rohlin.\n\n\"Gustaf Nordenström &amp; Co.,\n\nNorrköping.\n\nSe Snickerifabriken Kondoren,\nNorrköping.\n\nHerman Nordfors &amp; Co., Lidköping.\n\nOrgelbyggeri i Lidköping (Skarab. l.).\nTillverkar kyrkorglar, utför reparationer\noch stämningar samt insättning av elektr.\nbälgdrift.\n\nTelefon: 20145 o. 20592. — Antal\nindustriarb.: 3. Tillv.-värde pr år: 50,000\nkr. — Firman etabl. 1892.\n\nÄgare: orgelbygg. Herman Nordfors o.\norgelbygg. C. G. Smedman.\n\nChef: Herman Nordfors.\n\nAB. Nordgas, Stockholm.\n\nSe AB. Elga, Stockholm.\n\nNordh’s Kem. &amp; Elektr. Fabrik,\n\nPartille.\n\nKemisk fabrik och elektromek. verkstad\ni Partille (Göteb. o. Bohus L). Tillverkar\nanläggningar och förnödenheter för\nför-nickling, förkromning, kadmiering,\nför-koppring, förmässing, al-oxidering,\nfosfa-tering etc. samt maskiner och\nförnödenheter för slipning och polering av\nmetaller. Firman utför även analyser samt\ndriver konsulterande verksamhet inom\nbranschen.\n\nTelegr.-adr.: Nordkemi, Partille.\nTelefon: 82 o. 132. Postgiro: 36180. Repr. i\nStockholm: ing. G. Strandquist,\nJung-frug. 48, telefon: 600569.\n\nAntal industriarb.: 15. Tillv.-värde pr\når: 500,000 kr. — Firman etabl. 1915.\n\nÄgare: fabr. C.-G. Nordhs sterbhus.\n\nChef: fröken Inga-Britt Nordh.\n\n\"Nordisk Pälsindustri i Göteborg AB.,\n\nGöteborg.\n\nTillverkar dampälsar m. m.\n\nKontor: Vasag. 35. Telegr.-adr.:\nNor-danpels, Göteborg. Telefon: 182211 o.\n161711. Postgiro: 45910.\n\nAkt.-kap.: 10,000 kr. Antal\nindustriarb.: 30. Prod.-värde pr år: 900,000 kr.\n— Bolaget grundat 1939.\n\nStyrelse: fru Karin Tullberg (ordf.),\nfru Ingrid Malmsten, disp. Bertil\nTullberg.\n\nVerkst. dir. o. disp.: Bertil Tullberg.\n\n\"Nordisk Rotogravyr, Stockholm.\n\nBoktryckeri, bokbinderi,\ndjuptrycks-anstalt samt bok- och tidskriftsförlag.\n\nKontor: Sveav. 44—Luntmakarg. 25.\nTelegr.-adr. : Rotogravyr, Stockholm.\nTelefon: »Nordisk Rotogravyr». Postgiro: 940.\n\nArb.-antal: 425. Tillv.-värde pr år:\n6,000,000 kr. — Firman etabl. 1918.\n\nÄgare: kungl. boktr. Simon Söder stam.\n\nFörlagsdir..- C. A. Strömberg.\n\nDisponenter: C.-Th. Thäberg, Gösta\nSöderstam o. Gustaf Samuelsson.\n\n(Jfr annons nr 41.)\n\n\"AB. Nordisk Silkecellulosa,\n\nNorrköping.\n\nTillverkar cellull, korvskinn och\nviskossvamp samt transparenta acetat- och\nviskosfolier i olika färger. Varumärken:\n»Diofan», »Alofan», »Viska» o.\n»Nord-silk».\n\nKontor: Hospitalsg. 70. Telegr.-adr.:\nCellu, Norrköping. Telefon:\n»Silkecellulosa». Postgiro: 56911.\n\nAkt.-kap.: 1,000,000 kr. Antal\nindustriarb.: 450. Årstillv.: 7,000 ton\nviskosprodukter.\n\nBolaget, grundat 1931, tillhör\nKooperativa Förbundet samt drives i samarbete\nmed AB. Cellull, Vålberg.\n\nStyrelse: dir, Albin Johansson (ordf.),\nfil. lic. Mauritz Bonow, dir. Hj.\nDeger-stedt, dir. Hugo Edstam, dir. G. Osvald,\ndir. Ernst Persson.\n\nVerkst. dir.: ing. Curt Lindquist.\n\nFörsäljn.-chef: Folke Eländer.\n\nKamrer: Fredrik Lindkvist.\n\n(Jfr annons nr 86.)\n\n\"Nordiska Ackumulator Fabriken,\n\nMalmö.\n\nSe G. C. Faxe AB., Malmö.\n\n\"AB. Nordiska Affineriet,\n\nHälsingborg.\n\nFramställer ur ädelmetallhaltigt avfall\nsåväl rena ädelmetaller som legeringar i\nform av plåt, rör, band och tråd samt\nmetallsalter såsom silvernitrat och\nklor-silver m. m.\n\nTelegr.-adr.: Platina, Hälsingborg.\nTelefon: 10875 o. 14875. Postgiro: 8900.\nFilialkontor: Stockholm, Humlegårdsg. 8,\ntelefon: 624205.\n\nAkt.-kap.: 150.000 kr. Antal\nindustriarb.: 14. Prod.-värde pr år: 2,200,000 kr.\n— Firman etabl. 1904, bolag 1932.\n\nStyrelse: bankdir. C. D. Billsten\n(ordf.), disp. Lennart Hallbeck, dir.\nWalter Hallbeck.\n\nVerkst. dir.: W. Hallbeck.\n\nDisp.: L. Hallbeck.",
    "structured": {
        "firms": [
            {
                "name": "Gustaf Nordenström & Co.",
                "location": "Norrköping",
                "business": "Snickerifabrik",
                "contact": {
                    "office": "Se Snickerifabriken Kondoren, Norrköping",
                    "phone": [
                        "20145",
                        "20592"
                    ]
                },
                "financials": {
                    "capital": "Okänt",
                    "employees": {
                        "industriarb": 3
                    },
                    "annual_turnover": "Okänt",
                    "annual_production_value": "50 000 kr"
                },
                "foundation_year": 1892,
                "owners": [
                    "orgelbygg. Herman Nordfors",
                    "orgelbygg. C. G. Smedman"
                ],
                "director": "Herman Nordfors"
            },
            {
                "name": "AB. Nordgas",
                "location": "Stockholm",
                "business": "Okänt",
                "contact": {
                    "office": "Se AB. Elga, Stockholm"
                }
            },
            {
                "name": "Nordh’s Kem. & Elektr. Fabrik",
                "location": "Partille",
                "business": "Kemisk fabrik och elektromek. verkstad",
                "contact": {
                    "telegraph": "Nordkemi, Partille",
                    "phone": "82"
                },
                "financials": {
                    "capital": "Okänt",
                    "employees": {
                        "industriarb": 15
                    },
                    "annual_production_value": "500 000 kr"
                },
                "foundation_year": 1915,
                "owners": [
                    "fabr. C.-G. Nordhs sterbhus"
                ],
                "director": "fröken Inga-Britt Nordh"
            },
            {
                "name": "Nordisk Pälsindustri i Göteborg AB.",
                "location": "Göteborg",
                "business": "Tillverkar dampälsar m. m.",
                "contact": {
                    "office": "Kontor: Vasag. 35",
                    "phone": [
                        "182211",
                        "161711"
                    ]
                },
                "financials": {
                    "capital": "10 000 kr",
                    "employees": {
                        "industriarb": 30
                    },
                    "annual_production_value": "900 000 kr"
                },
                "foundation_year": 1939,
                "board": [
                    {
                        "name": "fru Karin Tullberg",
                        "role": "ordf."
                    },
                    {
                        "name": "fru Ingrid Malmsten",
                        "role": ""
                    },
                    {
                        "name": "disp. Bertil Tullberg",
                        "role": ""
                    }
                ],
                "director": "Bertil Tullberg"
            },
            {
                "name": "Nordisk Rotogravyr",
                "location": "Stockholm",
                "business": "Boktryckeri, bokbinderi, djuptrycks-anstalt samt bok- och tidskriftsförlag",
                "contact": {
                    "office": "Kontor: Sveav. 44—Luntmakarg. 25",
                    "phone": [
                        "Okänt"
                    ]
                },
                "financials": {
                    "employees": {
                        "industriarb": 425
                    },
                    "annual_production_value": "6 000 000 kr"
                },
                "foundation_year": 1918,
                "owners": [
                    "kungl. boktr. Simon Söder stam"
                ],
                "director": ""
            },
            {
                "name": "AB. Nordisk Silkecellulosa",
                "location": "Norrköping",
                "business": "Tillverkar cellull, korvskinn och viskossvamp samt transparenta acetat- och viskosfolier i olika färger",
                "contact": {
                    "office": "Kontor: Hospitalsg. 70",
                    "phone": "Okänt"
                },
                "financials": {
                    "capital": "1 000 000 kr",
                    "employees": {
                        "industriarb": 450
                    },
                    "annual_production_value": "7 000 ton viskosprodukter"
                },
                "foundation_year": 1931,
                "board": [
                    {
                        "name": "dir, Albin Johansson",
                        "role": "ordf."
                    },
                    {
                        "name": "fil. lic. Mauritz Bonow",
                        "role": ""
                    }
                ],
                "director": "ing. Curt Lindquist"
            },
            {
                "name": "AB. Nordiska Affineriet",
                "location": "Hälsingborg",
                "business": "Framställer ur ädelmetallhaltigt avfall såväl rena ädelmetaller som legeringar i form av plåt, rör, band och tråd samt metallsalter såsom silvernitrat och klor-silver m. m.",
                "contact": {
                    "telegraph": "Platina, Hälsingborg",
                    "phone": [
                        "10875",
                        "14875"
                    ]
                },
                "financials": {
                    "capital": "150 000 kr",
                    "employees": {
                        "industriarb": 14
                    },
                    "annual_production_value": "2 200 000 kr"
                },
                "foundation_year": 1904,
                "corporation_year": 1932,
                "board": [
                    {
                        "name": "bankdir. C. D. Billsten",
                        "role": "ordf."
                    },
                    {
                        "name": "disp. Lennart Hallbeck",
                        "role": ""
                    }
                ],
                "director": "W. Hallbeck",
                "manager": "L. Hallbeck"
            }
        ]
    }
}