{
    "original": "Wennerlund—Verkstad\n\n\"S. A. Wennerlund, Skofabrik,\n\nÖrebro.\n\nTillverkar såsom specialitet\nsandal-sydda skodon. Varumärke: »Essa».\n\nTelefon: 10869 o. 14769. Postgiro:\n10871. — Antal industriarb.: 55. —\nFirman etabl. 1914.\n\nÄgare o. chef: fabr. S. A. Wennerlund.\n\nDisp.: Evan R. Wennerlund.\n\n\"Ventilator, Ingenjörsfirman, S.\n\nRomedahl, Stockholm.\n\nSe Ingeniörsfirman Ventilator, S.\nRomedahl, Stockholm.\n\nAB. Ventilatorverken, Malmö.\n\nMek. verkstad. Utför anläggningar för\nventilation och luftkonditionering samt\npneumatisk transport. Tillverkar fläktar,\nvarmluftsbatterier,\nluftkonditionerings-apparater, tvättorkar, röksugare,\nvarmvattenberedare, plåtcisterner m. m.\n\nKontor: Idunsg. 19. Telegr.-adr.:\nVen-tilatorverk, Malmö. Telefon: 28057.\nPostgiro: 38476.\n\nAkt.-kap.: 30,000 kr. Antal\nindustriarb.: 37. Tillv.-värde pr år: 410,000 kr. —\nFirman etabl. 1918.\n\nVerkst. dir. o. tehn. chef: ing. Thure\nEricson.\n\n\"Verkstads AB. Haldex, Halmstad.\n\nMek. verkstad. Tillverkar taxametrar,\nvarvtalsmätare, varvräknare,\nhastighets-mätare och andra instrument för\nautomo-biler och marinmotorer, telefonkontrollur,\nmätur (indikatorklockor) m. fl.\nfinmekaniska tillverkningar. Bolaget driver\njämväl försäljning på export av\nplåtbearbet-ningsmaskiner (märke: »Pullmax»),\ntillverkade vid dotterbolaget AB.\nSvets-mekano, Göteborg.\n\nTelegr.-adr,: Haldex, Halmstad.\nTelefon: 3900. Postgiro: 94.\nServiceverkstad: AB. Taxameterverkstaden,\nStockholm, Agneg. 28, telefon: 536804.\n\nAkt.-kap.: 1,000,000 kr. Antal\nindustriarb.: 130. — Firman etabl. 1920 under\nnamn Fabriks AB. Haldataxametern, nuv.\nnamn 1944.\n\nStyrelse: disp. Thorsten Wigelius\n(ordf.), dir. David Arvidsson, dir. Stellan\nBendz, dir. Hugo B. Hintze.\n\nVerkst. dir.: S. Bendz.\n\nKontorschef: K. G. Ekedahl.\n\nInhöpschef: ing. Hugo Andersson.\n\nVerkstads AB* Bernhard Hedlund,\n\nHedemora.\n\nTillverkar cyklar och cykeldelar,\ngrammofondelar, skidbindningar m. m.\nVarumärke: »Brage».\n\nTelegr,-adr.: Bernadis, Hedemora.\nTelefon: 600 o. 613. Postgiro: 33983\n\nAkt.-kap.: 100,000 kr. Antal\nindustriarb.: 50. Tillv.-värde pr år: 800,000 kr.\n\n—\tFirman etabl. 1929, bolag 1941.\n\nVerkst. dir.: Georg Hedlund.\n\nVerkstads AB. Lindqvist, Motala.\n\nMek. verkstad. Tillverkar stålmöbler,\nfotskrapor, räfsor, grepar, brevkorgar,\nvertikalskåp, förvaringsskåp av plåt samt\nelektr. material; utför gassvetsnings- och\npressarbeten samt förnickling och\ngalva-nisering.\n\nTelefon: 2320 o. 2321. Postgiro: 29707.\n\nAkt.-kap.: 50,000 kr. Antal\nindustriarb.: 175. Tillv.-värde pr år: 1,650,000 kr.\n\nFirman grundad 1918 i Borensberg\nunder namn AB. Borensbergs Mek.\nVerkstad, flyttad till Motala 1922, nuv. namn\n1941.\n\nStyrelse: fabr. Tore Lindqvist.\n\nDisp.: Helmer Lindqvist.\n\n\"Verkstads AB. Mekano,\n\nHälsingborg.\n\nTillverkar transportanordningar såsom\nrullbanor, transportabla varuhissar,\nhöj-och sänkbara transportvagnar,\nremtransportörer, elevatorer, stålkätting m. m.,\ndisk- och sköljmaskiner för mejerier och\nbryggerier samt\nmetalltvättningsmaski-ner.\n\nTelegr.-adr.: Mekano, Hälsingborg.\nTelefon: 12600 o. 12659. Postgiro: 30575.\nAvd.-kontor: Stockholm, Klara S. Kyrkog.\n18, telefon: 105750.\n\nAkt.-kap.: 300,000 kr. Antal\nindustriarb.: 65. Tillv.-värde pr år: 1,100,000 kr.\n\n—\tBolaget grundat 1917.\n\nStyrelse: skeppsred. Joh. E. Gorthon\n(ordf.), ing. Fritz Helldov, dir. Ivar\nNyberg.\n\nDisp.: Henning Löwgren.\n\nKontorschef: Eric Swede.\n\n(Jfr annons nr 46.)\n\nVerkstads AB. Tibo, Ulvsunda.\n\nTillverkar rör-svetsmaskiner,\narbetsstolar, klipp- och pressverktyg m. m. vid\nmek. verkstad i Ulvsunda, Stockholm.\n\nTelefon: Stockholm 252545. Postgiro:\n159540. — Akt.-kap. r 150,000 kr. Antal\nindustriarb.: 80. Tillv.-värde pr år:\n\n615*",
    "structured": {
        "1": {
            "name": "S. A. Wennerlund",
            "location": "Örebro",
            "business": "Sandal-sydda skodon",
            "products": "Varumärke: Essa",
            "contact": {
                "office": "Skofabrik",
                "phone": [
                    "10869",
                    "14769"
                ],
                "postgiro": "10871"
            },
            "financials": {
                "capital": null,
                "employees": {
                    "industriarb": 55
                },
                "annual_turnover": null,
                "annual_production_value": null
            },
            "foundation_year": 1914,
            "owner": "S. A. Wennerlund",
            "director": null
        },
        "2": {
            "name": "AB. Ventilatorverken",
            "location": "Malmö",
            "business": "Mek. verkstad",
            "products": "Utför anläggningar för ventilation och luftkonditionering samt pneumatisk transport. Tillverkar fläktar, varmluftsbatterier, luftkonditionerings-apparater, tvättorkar, röksugare, varmvattenberedare, plåtcisterner m. m.",
            "contact": {
                "office": "Idunsg. 19",
                "phone": "28057",
                "postgiro": "38476"
            },
            "financials": {
                "capital": "30,000 kr",
                "employees": {
                    "industriarb": 37
                },
                "annual_turnover": "410,000 kr",
                "annual_production_value": null
            },
            "foundation_year": 1918,
            "director": "Ing. Thure Ericson"
        },
        "3": {
            "name": "Verkstads AB. Haldex",
            "location": "Halmstad",
            "business": "Mek. verkstad",
            "products": "Tillverkar taxametrar, varvtalsmätare, varvräknare, hastighets-mätare och andra instrument för bilar och marinmotorer, telefonkontrollur, mätur (indikatorklockor) m. fl. finmekaniska tillverkningar. Bolaget driver även försäljning på export av plåtbearbetningsmaskiner (märke: Pullmax), tillverkade vid dotterbolaget AB. Svets-mekano, Göteborg.",
            "contact": {
                "office": null,
                "phone": "3900",
                "postgiro": "94"
            },
            "financials": {
                "capital": "1,000,000 kr",
                "employees": {
                    "industriarb": 130
                },
                "annual_turnover": null,
                "annual_production_value": null
            },
            "foundation_year": 1920,
            "board": [
                {
                    "name": "Thorsten Wigelius",
                    "role": "disp."
                },
                {
                    "name": "David Arvidsson",
                    "role": "dir."
                },
                {
                    "name": "Stellan Bendz",
                    "role": "dir."
                },
                {
                    "name": "Hugo B. Hintze",
                    "role": "dir."
                }
            ],
            "director": "S. Bendz"
        },
        "4": {
            "name": "Verkstads AB* Bernhard Hedlund",
            "location": "Hedemora",
            "business": "Tillverkar cyklar och cykeldelar, grammofondelar, skidbindningar m. m.",
            "products": "Varumärke: Brage",
            "contact": {
                "office": null,
                "phone": [
                    "600",
                    "613"
                ],
                "postgiro": "33983"
            },
            "financials": {
                "capital": "100,000 kr",
                "employees": {
                    "industriarb": 50
                },
                "annual_turnover": "800,000 kr",
                "annual_production_value": null
            },
            "foundation_year": 1929,
            "director": "Georg Hedlund"
        },
        "5": {
            "name": "Verkstads AB. Lindqvist",
            "location": "Motala",
            "business": "Mek. verkstad",
            "products": "Tillverkar stålmöbler, fotskrapor, räfsor, grepar, brevkorgar, vertikalskåp, förvaringsskåp av plåt samt elektr. material; utför gassvetsnings- och pressarbeten samt förnickling och galvanisering.",
            "contact": {
                "office": null,
                "phone": [
                    "2320",
                    "2321"
                ],
                "postgiro": "29707"
            },
            "financials": {
                "capital": "50,000 kr",
                "employees": {
                    "industriarb": 175
                },
                "annual_turnover": "1,650,000 kr",
                "annual_production_value": null
            },
            "foundation_year": 1918,
            "director": "Tore Lindqvist"
        },
        "6": {
            "name": "Verkstads AB. Mekano",
            "location": "Hälsingborg",
            "business": "Tillverkar transportanordningar såsom rullbanor, transportabla varuhissar, höj-och sänkbara transportvagnar, remtransportörer, elevatorer, stålkätting m. m., disk- och sköljmaskiner för mejerier och bryggerier samt metalltvättningsmaskiner.",
            "contact": {
                "office": null,
                "phone": [
                    "12600",
                    "12659"
                ],
                "postgiro": "30575"
            },
            "financials": {
                "capital": "300,000 kr",
                "employees": {
                    "industriarb": 65
                },
                "annual_turnover": "1,100,000 kr",
                "annual_production_value": null
            },
            "foundation_year": 1917,
            "board": [
                {
                    "name": "Joh. E. Gorthon",
                    "role": "skeppsred."
                },
                {
                    "name": "Fritz Helldov",
                    "role": "ing."
                },
                {
                    "name": "Ivar Nyberg",
                    "role": "dir."
                }
            ],
            "director": null
        },
        "7": {
            "name": "Verkstads AB. Tibo",
            "location": "Ulvsunda",
            "business": "Tillverkar rör-svetsmaskiner, arbetsstolar, klipp- och pressverktyg m. m. vid mek. verkstad i Ulvsunda, Stockholm.",
            "contact": {
                "office": null,
                "phone": "252545",
                "postgiro": "159540"
            },
            "financials": {
                "capital": "150,000 kr",
                "employees": {
                    "industriarb": 80
                },
                "annual_turnover": "615"
            }
        }
    }
}