{
    "original": "Kommanditbo laget—Konfektion\n\nKommanditbolaget Cleisner &amp; Co-,\n\nÄlghultsby.\n\nGlasbruk vid Björkå och Berghem pr\nÄlghultsby (båda i Kronob. l.).\nTillverkar konservglas, medicinglas och eldfast\nglas.\n\nTelegr.-adr.: Gleisner, Älghultsby.\nTelefon: Älghult 6 a o. 17 a. Postgiro:\n90780.\n\nAntal industriarb.: 140. Tillv.-värde pr\når: 970,000 kr. — Berghems glasbruk\nanlagt 1870, Björkå glasbruk 1872.\n\nDriftschef: disp. Nils Gleisner.\n\nKommanditbolaget Lövträ, Nils\nElner &amp; Co., Arkelstorp.\n\nSågverk i Arkelstorp (Kristianst. l.).\nTillverkar lövträ ämnen och -plank,\nkaramellpinnar, glasskedar och -pinnar,\nsmör-drittlar och andra laggkärl, träband till\ndrittlar samt torkad sågspån.\n\nTelefon: 37. Postgiro: 165614. —\nAntal industriarb.: 70. Tillv.-värde pr år:\n700,000 kr. — Firman etabl. 1934,\nombil-dad 1939.\n\nÄgare: folkskollärare Nils Elner, dir.\nJosef Karlberg o. greve C.-A.\nTrolle-Wachtmeister.\n\nFirmatecknare: Nils Elner.\n\nKommanditbolaget Oskarshamns\nKuvertfabrik, Friberg &amp; C:oM\n\nOskarshamn.\n\nTillverkar kuvert av alla slag,\nkonvolut, provsäckar, myntpåsar m. m.\nSpecialitet: massupplagor av korsbandskuvert.\n\nTelegr.-adr.: Kuvertfriberg,\nOskarshamn. Telefon: 3 o. 633. Postgiro: 34040.\n— Antal industriarb.: 80. — Firman\netabl. 1922, kommanditbolag 1943.\n\nChef: disp. Karl-Axel Friberg.\n\nKommanditbolaget Repslageriet\nHolmlund &amp; Co., Örnsköldsvik.\n\nTillverkar repvaror såsom trossar,\nfisklinor, flagglinor, tömmar, klädlinor,\nsjömansgarn såsom märling och hyssing,\nkabelgarner, maskinförpackningar,\nlin-kabelgarner, lin för rörledningsändamål\nm. m. vid repslageri i Bodum,\nÖrnsköldsvik. Bolaget odlar och bereder hampa.\n\nTelefon: Örnsköldsvik 40133 o. 40075.\nPostgiro: 63150. — Arb.-antal: 16. —\nFirman etabl. 1940.\n\nÄgare o. chef: fabr. Johan Holmlund.\n\n*\tKommunala Elverks AB. i\nKatrineholm, Katrineholm.\n\nDistribuerar elektrisk energi till\nKatrineholms stad med omnejd.\n\nTelefon: »Elverket». — Akt.-kap.:\n30,000 kr. Distrib.-värde pr år: 1,200,000\nkr. — Bolaget grundat 1935.\n\nStyrelse: adv. Julius Lindström (ordf.),\nstationsförm. Emil G. Gustafsson (v.\nordf.), riksdagsm. A. J. Bärg, överläkare\nCarl Ellwyn, överinsp. Ch. Hernblom.\nVerkst. ledamot: Julius Lindström.\nChefsing.: Eldon Bratt.\nKamrer: Carl Ohlsson.\n\n^Kondoren, Snickerifabriken,\n\nNorrköping.\n\nSe Snickerifabriken Kondoren,\nNorrköping.\n\n^Konfektions AB. Anér &amp; Nilsson,\n\nStockholm.\n\nTillverkar damkappor och damdräkter.\nKontor: N. Smedjeg. 28. Telefon:\n112850 o. 206736.\n\nAkt.-kap.: 70,000 kr. Antal\nindustriarb.: 20. Tillv.-värde pr år: 450,000 kr.\n\n—\tFirman etabl. 1913 under namn\nNordiska Kappfabriken, bolag med nuv.\nnamn 1940.\n\nStyrelse: disp. John Nilsson (ordf.),\ntandläkare David Didner, agronom Nils\nDidner, fru L. Didner.\n\nVerkst. dir.: John Nilsson.\n\n*\tKonfektions AB. H. Bengtson,\n\nStockholm.\n\nSe Bengtsons Konfektions AB.,\nStockholm.\n\n*\tKonfektions AB. Bröderna Stern,\n\nNorrköping.\n\nTillverkar herrkläder.\nTelegr.-adr.: Stern, Norrköping.\nTelefon: »Konfektions AB. Bröderna Stern».\nPostgiro: 11146.\n\nAkt.-kap.: 300,000 kr. Antal\nindustriarb.: 40. Tillv.-värde pr år: 400,000 kr.\n\n—\tFirman etabl. 1913, bolag 1924 under\nnamn Svenska Herrkläders AB., nuv.\nbolag 1928.\n\nVerkst. direktörer: Mauritz Stern o.\nKarl Stern.\n\n^Konfektions AB. Drabant,\n\nAlingsås.\n\nTillverkar herrkostymer och\nhögtidskläder. Varumärke: »Drabant».",
    "structured": {
        "1": {
            "name": "Kommanditbolaget Cleisner & Co",
            "location": "Älghultsby",
            "business": "Tillverkning av konservglas, medicinglas och eldfast glas",
            "contact": {
                "office": "Älghultsby",
                "phone": [
                    "Älghult 6",
                    "Älghult 17"
                ],
                "postgiro": "90780",
                "telegraph": "Gleisner, Älghultsby"
            },
            "financials": {
                "annual_turnover": "970,000 kr",
                "annual_production_value": "970,000 kr"
            },
            "foundation_year": 1870,
            "board": [
                {
                    "name": "disp. Nils Gleisner",
                    "role": "Driftschef"
                }
            ]
        },
        "2": {
            "name": "Kommanditbolaget Lövträ, Nils Elner & Co",
            "location": "Arkelstorp",
            "business": "Tillverkning av lövträ ämnen, plank, karamellpinnar, glasskedar, smördrittlar, träband, torkad sågspån",
            "contact": {
                "office": "Arkelstorp",
                "phone": [
                    "37"
                ],
                "postgiro": "165614"
            },
            "financials": {
                "annual_turnover": "700,000 kr"
            },
            "foundation_year": 1934,
            "board": [
                {
                    "name": "Nils Elner",
                    "role": "Firmatecknare"
                }
            ],
            "owners": [
                "folkskollärare Nils Elner",
                "dir. Josef Karlberg",
                "greve C.-A. Trolle-Wachtmeister"
            ]
        },
        "3": {
            "name": "Kommanditbolaget Oskarshamns Kuvertfabrik, Friberg & C:oM",
            "location": "Oskarshamn",
            "business": "Tillverkning av kuvert av alla slag, konvolut, provsäckar, myntpåsar, massupplagor av korsbandskuvert",
            "contact": {
                "office": "Oskarshamn",
                "phone": [
                    "3",
                    "633"
                ],
                "postgiro": "34040",
                "telegraph": "Kuvertfriberg, Oskarshamn"
            },
            "financials": {
                "annual_turnover": "Unknown"
            },
            "foundation_year": 1922,
            "board": [
                {
                    "name": "disp. Karl-Axel Friberg",
                    "role": "Chef"
                }
            ]
        },
        "4": {
            "name": "Kommanditbolaget Repslageriet Holmlund & Co",
            "location": "Örnsköldsvik",
            "business": "Tillverkning av repvaror, hampaodling",
            "contact": {
                "office": "Örnsköldsvik",
                "phone": [
                    "40133",
                    "40075"
                ],
                "postgiro": "63150"
            },
            "financials": {
                "annual_turnover": "Unknown"
            },
            "foundation_year": 1940,
            "board": [
                {
                    "name": "fabr. Johan Holmlund",
                    "role": "Ägare o. chef"
                }
            ]
        },
        "5": {
            "name": "Kommunala Elverks AB i Katrineholm",
            "location": "Katrineholm",
            "business": "Distribuerar elektrisk energi till Katrineholms stad med omnejd",
            "contact": {
                "office": "Katrineholm",
                "phone": [
                    "Elverket"
                ],
                "postgiro": "Unknown"
            },
            "financials": {
                "capital": "30,000 kr",
                "annual_turnover": "1,200,000 kr"
            },
            "foundation_year": 1935,
            "board": [
                {
                    "name": "adv. Julius Lindström",
                    "role": "ordf."
                }
            ],
            "director": "Julius Lindström",
            "managing_director": "Eldon Bratt",
            "manager": "Carl Ohlsson"
        },
        "6": {
            "name": "Konfektions AB. Anér & Nilsson",
            "location": "Stockholm",
            "business": "Tillverkning av damkappor och damdräkter",
            "contact": {
                "office": "N. Smedjeg. 28",
                "phone": [
                    "112850",
                    "206736"
                ]
            },
            "financials": {
                "capital": "70,000 kr",
                "annual_turnover": "450,000 kr"
            },
            "foundation_year": 1913,
            "board": [
                {
                    "name": "disp. John Nilsson",
                    "role": "ordf."
                }
            ],
            "director": "John Nilsson"
        },
        "7": {
            "name": "Konfektions AB. Bröderna Stern",
            "location": "Norrköping",
            "business": "Tillverkning av herrkläder",
            "contact": {
                "office": "Norrköping",
                "phone": [
                    "Konfektions AB. Bröderna Stern"
                ],
                "postgiro": "11146"
            },
            "financials": {
                "capital": "300,000 kr",
                "annual_turnover": "400,000 kr"
            },
            "foundation_year": 1913,
            "board": [
                {
                    "name": "Mauritz Stern",
                    "role": "Verkst. direktör"
                },
                {
                    "name": "Karl Stern",
                    "role": "Verkst. direktör"
                }
            ]
        }
    }
}