{
    "original": "Latexfabriken—Leidesdorffska\n\nLatexfabriken, Nordiska, Torekov.\nSe Nordiska Latexfabriken, Torekov.\n\n\"AB. Lauxein-Casco, Stockholm.\n\nKem. tekn. fabrik i Sickla, Stockholm.\nTillverkar kallim, konsthartslim, färg,\nbonvax, betningsmedel m. m.\nVarumärken: »Casco», »Lauxein», »Lustra» o.\n»Panogen» m. fl.\n\nPostadr.: Stockholm 11. Telegr.-adr.:\nCascobolag, Stockholm. Telefon: 440800.\nPostgiro: 52544.\n\nAkt.-kap.: 700,000 kr. Antal\nindustriarb.: 100. Tillv.-värde pr år: 6,000,000 kr.\n— Firman etabl. 1929, nuv. namn 1930.\n\nStyrelse: disp. Lars Amundsen (ordf.),\ning. Petrus Hellman, adv. Wilhelm\nMoberg, dir. C. A. Sikström.\n\nVerkst. dir.: Petrus Hellman.\n\n\"Lavals Ångturbin, Saltsjö-Järla.\n\nSe AB. de Lavals Ångturbin,\nStockholm.\n\nLavoné-fabriken, AB. Magnus\nJernberg, Karlstad.\n\nKemisk-teknisk fabrik. Tillverkar\ntekniska och kosmetiska artiklar, fria\nläkemedel, bakpulver, malpreparat, tvätt- och\nskurmedel m. m. Varumärke: »Lavoné».\n\nTelegr.-adr. o. telefon: Lavonéfabriken,\nKarlstad. Postgiro: 83985. — Akt.-kap.:\n50,000 kr. Antal industriarb.: 20.\nTillv.-värde pr år: 600,000 kr. — Firman etabl.\n1934.\n\nDisp.: Sven Hellman.\n\nKontorschef: Ragnar Nordquist.\n\nLaxå Bruks AB., Laxå.\n\nJärnbruk med masugn och\nlancashire-smedja, stålsandsverk, slaggullfabrik,\nmek. verkstad och snickerifabrik vid\nRö-fors, sågverk, hyvleri och ångcentral vid\nV:a Laxsjön (samtl. i Örebro l.).\n\nTillverkar lancashiretackjärn,\ngjuteri-tackjärn, smältstycken, stålsand, barends,\nslaggull, sågade och hyvlade trävaror,\nbyggnadssnickerier m. m. Bolaget idkar\njämväl jordbruk och skogshantering, äger\nelektr. kraftstationer samt trafikerar\nLaxå-Röfors järnväg.\n\nHuvudkontor: Laxå. Telegr.-adr.:\nLaxåbolaget, Laxå. Telefon: »Laxåbruk».\nPostgiro: 77827.\n\nAkt.-kap.: 2,000,000 kr. Antal\nindustriarb.: 210. — Bruket anlagt 1642, bolag\n1872, ombildat 1924.\n\nStyrelse o. direktion: dir. Axel\nEmilson, disp. Carl Emilson o. ing. Solve\nEmilson.\n\nFörsäljn.-chef er: för järn: Sture\nOlsson ; för trä o. slaggull: Ivar Stenberg.\n\nInköpschef: Henry Blomqvist.\n\n\"AB. Laxå Pappersbruk, Örebro.\n\nTillverkar oblekt och blekt M.\nG.-sul-fitpapper, blekt M. G.-kraftpapper,\nomslags- och påspapper, butelj- och\ntoalettpapper samt paraffinerat och\nmönster-tryckt papper vid fabrik i Laxå\n(Örebro l.).\n\nHuvudkontor: Örebro. Ensamförsälj.\nJohnson Hill AB., Örebro. Telegr.-adr.\no. telefon: »Johnsonhill, Örebro.\n\nAkt.-kap.: 110,000 kr. Antal industri\narb.: 80. — Bolaget grundat 1938.\n\nStyrelse: disp. Olof Johnson (ordf.),\ndir. Erland Johnson, ing. Sigge\nRuden-gren.\n\nVerkst. dir.: Olof Johnson.\n\nDriftsing.: Sigge Rudengren.\n\nLe Carbone, Svenska AB.,\n\nSundbyberg.\n\nSe Svenska AB. Le Carbone,\nSundbyberg.\n\nAB. Lee Bruk, Ed.\n\nSågverk och hyvleri vid Ed (Lee\nÅngsåg) (Älvsb. l.). Tillverkar sågade och\nhyvlade trävaror. Bolaget driver även\nskogshantering.\n\nKontor: Ed. Telefon: Ed 28. Postgiro:\n70723. — Akt.-kap.: 150,000 kr. Antal\nindustriarb.: 50. Tillv.-värde pr år:\n700,000 kr. — Bolaget grundat 1910.\n\nVerkst. dir.: Ole Anker Rasch (Halden,\nNorge).\n\nFörvalt.: Otto Sinclair.\n\nAB. Leidesdorffska\nFiskredskaps-fabriken, Stockholm.\n\nTillverkar fiskdrag av metall,\nhand-slagna och flätade revar, linor och snören,\nmetspön, håvar och andra fiskredskap,\nmonterar fisknät och skotar m. m.\nVarumärke: »Kaleva».\n\nKontor: Regeringsg. 4. Telegr.-adr.:\nLeidesdorff, Stockholm. Telefon: 102226.\nPostgiro: 1765. — Akt.-kap.: 125,000 kr.\n— Firman etabl. 1861 i Göteborg, bolag\n1898.\n\nStyrelse: civiling. Alb. Höekenström\n(ordf.), grossh. Lars Dahlberg, dir. Carl\nEdw. Leidesdorff.\n\nVerkst. dir.: C. Edw. Leidesdorff.\n\n322*\n",
    "structured": {
        "companies": [
            {
                "name": "Latexfabriken—Leidesdorffska",
                "location": "Nordiska, Torekov",
                "business": "Gummi- och latexprodukter",
                "contact": {
                    "office": "Se Nordiska Latexfabriken, Torekov",
                    "postgiro": "N/A"
                },
                "financials": {
                    "capital": "N/A"
                },
                "foundation_year": 1930,
                "board": [
                    {
                        "name": "disp. Lars Amundsen",
                        "role": "ordf."
                    },
                    {
                        "name": "ing. Petrus Hellman",
                        "role": "N/A"
                    },
                    {
                        "name": "adv. Wilhelm Moberg",
                        "role": "N/A"
                    },
                    {
                        "name": "dir. C. A. Sikström",
                        "role": "N/A"
                    }
                ]
            },
            {
                "name": "AB. Lauxein-Casco",
                "location": "Stockholm",
                "business": "Kemisk-teknisk fabrik",
                "products": "Tillverkar kallim, konsthartslim, färg, bonvax, betningsmedel m.m. Varumärken: »Casco», »Lauxein», »Lustra» o. »Panogen» m. fl.",
                "contact": {
                    "office": "Kem. tekn. fabrik i Sickla, Stockholm",
                    "phone": [
                        "440800"
                    ],
                    "postgiro": "52544",
                    "telegraph": "Cascobolag, Stockholm"
                },
                "financials": {
                    "capital": "700,000 kr",
                    "employees": {
                        "industriarb": 100
                    },
                    "annual_turnover": "6,000,000 kr",
                    "annual_production_value": "6,000,000 kr"
                },
                "foundation_year": 1929,
                "current_name_year": 1930,
                "board": [
                    {
                        "name": "disp. Lars Amundsen",
                        "role": "ordf."
                    },
                    {
                        "name": "ing. Petrus Hellman",
                        "role": "N/A"
                    },
                    {
                        "name": "adv. Wilhelm Moberg",
                        "role": "N/A"
                    },
                    {
                        "name": "dir. C. A. Sikström",
                        "role": "N/A"
                    }
                ]
            },
            {
                "name": "Lavoné-fabriken, AB. Magnus Jernberg",
                "location": "Karlstad",
                "business": "Kemisk-teknisk fabrik",
                "products": "Tillverkar tekniska och kosmetiska artiklar, fria läkemedel, bakpulver, malpreparat, tvätt- och skurmedel m.m. Varumärke: »Lavoné»",
                "contact": {
                    "office": "N/A",
                    "phone": [
                        "N/A"
                    ],
                    "postgiro": "83985"
                },
                "financials": {
                    "capital": "50,000 kr",
                    "employees": {
                        "industriarb": 20
                    },
                    "annual_turnover": "600,000 kr",
                    "annual_production_value": "600,000 kr"
                },
                "foundation_year": 1934,
                "board": [
                    {
                        "name": "Sven Hellman",
                        "role": "Disp."
                    }
                ],
                "manager": "Ragnar Nordquist"
            },
            {
                "name": "Laxå Bruks AB., Laxå",
                "location": "Laxå",
                "business": "Järnbruk",
                "products": "Tillverkar lancashiretackjärn, gjuteri-tackjärn, smältstycken, stålsand, barends, slaggull, sågade och hyvlade trävaror, byggnadssnickerier m.m.",
                "contact": {
                    "office": "N/A",
                    "phone": [
                        "'Laxåbruk'"
                    ],
                    "postgiro": "77827"
                },
                "financials": {
                    "capital": "2,000,000 kr",
                    "employees": {
                        "industriarb": 210
                    }
                },
                "foundation_year": 1872,
                "board": [
                    {
                        "name": "dir. Axel Emilson",
                        "role": "N/A"
                    },
                    {
                        "name": "disp. Carl Emilson",
                        "role": "N/A"
                    },
                    {
                        "name": "ing. Solve Emilson",
                        "role": "N/A"
                    }
                ],
                "sales_manager": "Sture Olsson",
                "manager": "Henry Blomqvist"
            },
            {
                "name": "AB. Laxå Pappersbruk, Örebro",
                "location": "Örebro",
                "business": "Pappersbruk",
                "products": "Tillverkar oblekt och blekt M. G.-sul-fitpapper, blekt M. G.-kraftpapper, omslags- och påspapper, butelj- och toalettpapper samt paraffinerat och mönster-tryckt papper",
                "contact": {
                    "office": "N/A",
                    "phone": [
                        "'Johnsonhill, Örebro'"
                    ],
                    "postgiro": "N/A"
                },
                "financials": {
                    "capital": "110,000 kr",
                    "employees": {
                        "industriarb": 80
                    }
                },
                "foundation_year": 1938,
                "board": [
                    {
                        "name": "disp. Olof Johnson",
                        "role": "ordf."
                    },
                    {
                        "name": "dir. Erland Johnson",
                        "role": "N/A"
                    }
                ],
                "manager": "Olof Johnson",
                "sales_manager": "Sigge Rudengren"
            },
            {
                "name": "AB. Lee Bruk, Ed",
                "location": "Ed",
                "business": "Sågverk och hyvleri",
                "products": "Tillverkar sågade och hyvlade trävaror",
                "contact": {
                    "office": "N/A",
                    "phone": [
                        "Ed 28"
                    ],
                    "postgiro": "70723"
                },
                "financials": {
                    "capital": "150,000 kr",
                    "employees": {
                        "industriarb": 50
                    },
                    "annual_production_value": "700,000 kr"
                },
                "foundation_year": 1910,
                "manager": "Ole Anker Rasch (Halden, Norge)",
                "managing_director": "Otto Sinclair"
            },
            {
                "name": "AB. Leidesdorffska Fiskredskaps-fabriken, Stockholm",
                "location": "Stockholm",
                "business": "Tillverkar fiskredskap",
                "products": "Tillverkar fiskdrag av metall, handslagna och flätade revar, linor och snören, metspön, håvar och andra fiskredskap, monterar fisknät och skotar m.m.",
                "contact": {
                    "office": "N/A",
                    "phone": [
                        "102226"
                    ],
                    "postgiro": "1765",
                    "telegraph": "Leidesdorff, Stockholm"
                },
                "financials": {
                    "capital": "125,000 kr"
                },
                "foundation_year": 1861,
                "board": [
                    {
                        "name": "civiling. Alb. Höekenström",
                        "role": "ordf."
                    },
                    {
                        "name": "grossh. Lars Dahlberg",
                        "role": "N/A"
                    },
                    {
                        "name": "dir. Carl Edw. Leidesdorff",
                        "role": "N/A"
                    }
                ],
                "manager": "C. Edw. Leidesdorff"
            }
        ]
    }
}