{
    "original": "J onsson—Junex\n\nTelefon: Malung 143. Postgiro: 15485.\nRepr. i Stockholm: Folke Lindris,\nSmå-landsg. 10, telefon: 108398.\n\nAntal industriarb.: 10 samt 20\nhemarbetare. Tillv.-värde pr år: 350,000 kr.\n— Firman etabl. 1924.\n\nÄgare o. chef: fabr. Sangsta Erik\nJonsson.\n\n\"Wiktor Jonssons Snickerifabrik,\n\nGisebo.\n\nTillverkar byggnadssnickerier såsom\ndörrar, fönster och trappor samt\nbutiks-och köksinredningar vid fabrik i\nKaxhol-men, Gisebo (Jönköp. l.).\n\nTelefon: Vistakulle 28. — Antal\nindustriarb.: 8. — Firman etabl. 1930.\n\nÄgare o. chefer: fabr. Wiktor Jonsson\no. fabr. Rune Kanerfalk.\n\nÖ. J. Johnsson, Malung.\n\nSkinnklädersfabrik i Malung\n(Kopparb. l.). Tillverkar skinnkläder samt\npromenad-, sport- och arbetshandskar.\n\nTelefon: 43. Postgiro: 32157. — Antal\nindustriarb.: 12. Tillv.-värde pr år:\n205,000 kr. — Firman etabl. 1909.\n\nÄgare o. chef: fabr. öjes Johan\nJohnsson.\n\nAB. Josefsdals Tegelbruk,\n\nStockholm.\n\nTillverkar taktegel och dräneringsrör\nvid tegelbruk i Sala.\n\nKontor: Stockholm, Jakobsbergsg. 2.\nTelegr.-adr.: Josefsdalstegel. Stockholm.\nTelefon: 103456. Postgiro: 22744.\n\nAkt.-kap.: 200,000 kr. Antal\nindustriarb.: 75. Årstillv.: 4 milj. st. taktegel,\n0,5 milj. st. rör. — Bolaget grundat 1926.\n\nStyrelse: dir. Vilhelm Björkman\n(ordf.), dir. K. J. Gendt.\nVerkst. dir.: K. J. Gendt.\nFörsäljn.-chef: C. G. Malmlöf.\n\n\"Josefssons Trikåfabrik, Bröderna,\n\nBorås.\n\nSe Bröderna Josefssons Trikåfabrik,\nBorås.\n\n\"AB. Erik Josefson &amp; Co.,\n\nUlricehamn.\n\nTrikåfabrik. Tillverkar stickade\nyllevaror.\n\nTelefon: 232 o. 608. Postgiro: 9395. —\nAkt.-kap.: 100.000 kr. Antal industriarb.:\n30 (ävensom 100 hemarbetare). — Firman\netabl. 1920, bolag 1938.\n\nStyrelse: grossh. Erik Josef son, disp.\nSten Josefson.\n\nVerkst. dir.: Erik Josef son.\nDisp.: Sten Josef son.\n\nKarl Josefssons Trikåfabrlk,\n\nBorås.\n\nTillverkar trikåvaror såsom pullovers,\njumpers, koftor, underkläder, barnkläder\nm. m.\n\nTelefon: 11310 o. 11311. Postgiro:\n135255. — Antal industriarb.: 25.\nTillv.-värde pr år: 190,000 kr. — Firman etabl.\n1919.\n\nÄgare o. chef: fabr. Karl Josefsson.\n\nAlfr. Jubel &amp; Co. AB.,\n\nLidköping.\n\nSågverk, hyvleri och snickerifabrik.\nTillverkar sågade och hyvlade trävaror\nsamt byggnadssnickerier. Bolaget driver\näven handel med byggnadsvaror.\n\nTelegr.-adr.: Jubels, Lidköping.\nTelefon: 20004, 20188 o. 20350. Postgiro:\n14924.\n\nAkt.-kap.: 320,000 kr. Antal\nindustriarb.: 40. Tillv.-värde pr år: 750,000 kr.\n— Firman etabl. 1870, bolag 1912.\nVerkst. dir.: kapten Eric Möller.\nDisponenter: Oscar G. Carlson o.\nGunnar Hemberg.\n\n*AB. Juneverken, Bankeryd.\n\nMek. verkstad i Bankeryd (Jönköp. l.).\nTelegr.-adr.: Juneverken, Bankeryd.\nTelefon: 18 o. 81. — Akt.-kap.: 200.000 kr.\n\nFirman etabl. 1917. Sedan 1929 drives\nrörelsen av Jönköpings Mek. Werkstads\nAB., som arrenderar verkstäderna och där\ntillverkar vägmaskiner och släpvagnar.\nVarumärke: » June».\n\nStyrelse: dir. Anders Graab, övering.\nB. H. Lundborg, adv. Hans Sundström.\nVerkst. dir.: Anders Graab.\n\n*Junex Konfektlons AB., Huskvarna.\n\nTillverkar herr-, dam- och barnkläder.\n\nSpecialiteter: överplagg, kostymer, jackets\noch sportkläder. Varumärken: »Junex»,\n»Junexior», »Fokker», »Front-Coat»,\n»Clipper» o. »Junex Jacket».\n\nTelegr.-adr. o. telefon: Junex,\nHuskvarna. Postgiro: 5477.\n\nAkt.-kap.: 700,000 kr. Antal\nindustriarb.: 500. Tillv.-värde pr år: 12,000,000\nkr.\n\nFöretaget grundat 1927; till bolaget är\nanslutet bl. a. Konfektions Kompaniet\nAB., Skånes Fagerhult (se detta bolag).\n\n7*",
    "structured": {
        "1": {
            "name": "Wiktor Jonssons Snickerifabrik",
            "location": "Gisebo, Kaxholmen, Gisebo (Jönköp. l.)",
            "business": "Tillverkar byggnadssnickerier såsom dörrar, fönster och trappor samt butiks-och köksinredningar",
            "products": "Beskrivning av produkter som tillverkas saknas",
            "contact": {
                "office": null,
                "phone": [
                    "Vistakulle 28"
                ],
                "postgiro": null,
                "head_office": null,
                "sales_offices": null,
                "telegraph": null,
                "factory_office": null,
                "factory_phone": null
            },
            "financials": {
                "capital": null,
                "employees": {
                    "industriarb": 8
                },
                "annual_turnover": "350,000 kr",
                "annual_production_value": null
            },
            "foundation_year": 1930,
            "current_name_year": null,
            "predecessor": null,
            "original_name": null,
            "corporation_year": null,
            "board": null,
            "owners": [
                "Wiktor Jonsson",
                "Rune Kanerfalk"
            ],
            "director": null,
            "managing_director": null,
            "sales_manager": null,
            "manager": null
        },
        "2": {
            "name": "Ö. J. Johnsson",
            "location": "Malung (Kopparb. l.)",
            "business": "Skinnklädersfabrik",
            "products": "Tillverkar skinnkläder samt promenad-, sport- och arbetshandskar",
            "contact": {
                "office": null,
                "phone": [
                    "43"
                ],
                "postgiro": "32157",
                "head_office": null,
                "sales_offices": null,
                "telegraph": null,
                "factory_office": null,
                "factory_phone": null
            },
            "financials": {
                "capital": null,
                "employees": {
                    "industriarb": 12
                },
                "annual_turnover": "205,000 kr",
                "annual_production_value": null
            },
            "foundation_year": 1909,
            "current_name_year": null,
            "predecessor": null,
            "original_name": null,
            "corporation_year": null,
            "board": null,
            "owners": [
                "Öjes Johan Johnsson"
            ],
            "director": null,
            "managing_director": null,
            "sales_manager": null,
            "manager": null
        },
        "3": {
            "name": "AB. Josefsdals Tegelbruk",
            "location": "Sala",
            "business": "Tillverkar taktegel och dräneringsrör",
            "products": null,
            "contact": {
                "office": "Stockholm, Jakobsbergsg. 2",
                "phone": [
                    "103456"
                ],
                "postgiro": "22744",
                "head_office": null,
                "sales_offices": null,
                "telegraph": "Josefsdalstegel, Stockholm",
                "factory_office": null,
                "factory_phone": null
            },
            "financials": {
                "capital": "200,000 kr",
                "employees": {
                    "industriarb": 75
                },
                "annual_turnover": null,
                "annual_production_value": "4 milj. st. taktegel, 0,5 milj. st. rör"
            },
            "foundation_year": 1926,
            "current_name_year": null,
            "predecessor": null,
            "original_name": null,
            "corporation_year": null,
            "board": [
                {
                    "name": "dir. Vilhelm Björkman",
                    "role": "ordf."
                },
                {
                    "name": "dir. K. J. Gendt",
                    "role": null
                }
            ],
            "owners": null,
            "director": null,
            "managing_director": "K. J. Gendt",
            "sales_manager": "C. G. Malmlöf",
            "manager": null
        },
        "4": {
            "name": "Josefssons Trikåfabrik, Bröderna",
            "location": "Borås",
            "business": "Se Bröderna Josefssons Trikåfabrik",
            "products": null,
            "contact": {
                "office": null,
                "phone": null,
                "postgiro": null,
                "head_office": null,
                "sales_offices": null,
                "telegraph": null,
                "factory_office": null,
                "factory_phone": null
            },
            "financials": {
                "capital": null,
                "employees": null,
                "annual_turnover": null,
                "annual_production_value": null
            },
            "foundation_year": null,
            "current_name_year": null,
            "predecessor": null,
            "original_name": null,
            "corporation_year": null,
            "board": null,
            "owners": null,
            "director": null,
            "managing_director": null,
            "sales_manager": null,
            "manager": null
        },
        "5": {
            "name": "AB. Erik Josefson & Co.",
            "location": "Ulricehamn",
            "business": "Trikåfabrik",
            "products": "Tillverkar stickade yllevaror",
            "contact": {
                "office": null,
                "phone": [
                    "232 o. 608"
                ],
                "postgiro": "9395",
                "head_office": null,
                "sales_offices": null,
                "telegraph": null,
                "factory_office": null,
                "factory_phone": null
            },
            "financials": {
                "capital": "100,000 kr",
                "employees": {
                    "industriarb": 30,
                    "hemarbetare": 100
                },
                "annual_turnover": null,
                "annual_production_value": null
            },
            "foundation_year": 1920,
            "current_name_year": 1938,
            "predecessor": null,
            "original_name": null,
            "corporation_year": null,
            "board": [
                {
                    "name": "grossh. Erik Josefson",
                    "role": "disp."
                },
                {
                    "name": "disp. Sten Josefson",
                    "role": null
                }
            ],
            "owners": null,
            "director": "Erik Josefson",
            "managing_director": "Erik Josefson",
            "sales_manager": null,
            "manager": null
        },
        "6": {
            "name": "Karl Josefssons Trikåfabrik",
            "location": "Borås",
            "business": "Tillverkar trikåvaror såsom pullovers, jumpers, koftor, underkläder, barnkläder m. m.",
            "products": null,
            "contact": {
                "office": null,
                "phone": [
                    "11310 o. 11311"
                ],
                "postgiro": "135255",
                "head_office": null,
                "sales_offices": null,
                "telegraph": null,
                "factory_office": null,
                "factory_phone": null
            },
            "financials": {
                "capital": null,
                "employees": {
                    "industriarb": 25
                },
                "annual_turnover": "190,000 kr",
                "annual_production_value": null
            },
            "foundation_year": 1919,
            "current_name_year": null,
            "predecessor": null,
            "original_name": null,
            "corporation_year": null,
            "board": null,
            "owners": [
                "Karl Josefsson"
            ],
            "director": null,
            "managing_director": null,
            "sales_manager": null,
            "manager": null
        },
        "7": {
            "name": "Alfr. Jubel & Co. AB.",
            "location": "Lidköping",
            "business": "Sågverk, hyvleri och snickerifabrik",
            "products": "Tillverkar sågade och hyvlade trävaror samt byggnadssnickerier. Bolaget driver även handel med byggnadsvaror.",
            "contact": {
                "office": null,
                "phone": [
                    "20004",
                    "20188",
                    "20350"
                ],
                "postgiro": "14924",
                "head_office": null,
                "sales_offices": null,
                "telegraph": "Jubels, Lidköping",
                "factory_office": null,
                "factory_phone": null
            },
            "financials": {
                "capital": "320,000 kr",
                "employees": {
                    "industriarb": 40
                },
                "annual_turnover": null,
                "annual_production_value": "750,000 kr"
            },
            "foundation_year": 1912,
            "current_name_year": null,
            "predecessor": null,
            "original_name": null,
            "corporation_year": 1870,
            "board": null,
            "owners": null,
            "director": null,
            "managing_director": "kapten Eric Möller",
            "sales_manager": null,
            "manager": null
        },
        "8": {
            "name": "AB. Juneverken",
            "location": "Bankeryd (Jönköp. l.)",
            "business": "Mek. verkstad",
            "products": "Tillverkar vägmaskiner och släpvagnar. Varumärke: » June».",
            "contact": {
                "office": null,
                "phone": [
                    "18 o. 81"
                ],
                "postgiro": null,
                "head_office": null,
                "sales_offices": null,
                "telegraph": "Juneverken, Bankeryd",
                "factory_office": null,
                "factory_phone": null
            },
            "financials": {
                "capital": "200,000 kr",
                "employees": null,
                "annual_turnover": null,
                "annual_production_value": null
            },
            "foundation_year": 1917,
            "current_name_year": 1929,
            "predecessor": null,
            "original_name": null,
            "corporation_year": null,
            "board": [
                {
                    "name": "dir. Anders Graab",
                    "role": "övering."
                },
                {
                    "name": "adv. Hans Sundström",
                    "role": null
                }
            ],
            "owners": null,
            "director": null,
            "managing_director": null,
            "sales_manager": null,
            "manager": "Anders Graab"
        },
        "9": {
            "name": "Junex Konfektlons AB.",
            "location": "Huskvarna",
            "business": "Tillverkar herr-, dam- och barnkläder",
            "products": "Specialiteter: överplagg, kostymer, jackets och sportkläder. Varumärken: »Junex», »Junexior», »Fokker», »Front-Coat», »Clipper» o. »Junex Jacket».",
            "contact": {
                "office": null,
                "phone": null,
                "postgiro": "5477",
                "head_office": null,
                "sales_offices": null,
                "telegraph": "Junex, Huskvarna",
                "factory_office": null,
                "factory_phone": null
            },
            "financials": {
                "capital": "700,000 kr",
                "employees": {
                    "industriarb": 500
                },
                "annual_turnover": "12,000,000 kr",
                "annual_production_value": null
            },
            "foundation_year": 1927,
            "current_name_year": null,
            "predecessor": null,
            "original_name": null,
            "corporation_year": null,
            "board": null,
            "owners": null,
            "director": null,
            "managing_director": null,
            "sales_manager": null,
            "manager": null
        }
    }
}