{
    "original": "Bergshamra—Bergson\n\nBergshamra Ångkvarns, Sågverks &amp;\nSnickeri-AB., Utanbro.\n\nSågverk, hyvleri och snickerifabrik i\nUtanbro (Sthlms l.). Tillverkar hyvlade\noch ohyvlade trävaror samt\nbyggnadssnickerier. Bolaget driver även\nkvarnrörelse.\n\nTelefon: Bergshamra 8. Postgiro:\n282841. — Akt.-kap.: 27,400 kr. Antal\nindustriarb.: 25. Tillv.-värde pr år:\n200,000 kr. — Firman etabl. 1893.\n\nDisp.: Carl Axel Engström.\n\nBergsjöverken AB-, Bergsjö.\n\nSnickeri, mek. verkstad, såg och\nhyvleri samt elektr. kraftverk i Bergsjö\n(Gäyleb. l.).\n\nTillverkar monteringsfärdiga trähus,\ntröskverk, hö- och halmfläktar, höpressar\nsamt rikthyvlar och vedkapar.\n\nTelegr.-adr.: Reformverk, Bergsjö.\nTelefon: »Bergsjöverken». Postgiro: 265597.\nFörsäljn.-kontor Stockholm: AB. Gunnar\nWestholm, Kungsg. 2, telefon: 230380.\n\nAkt.-kap.: 78,000 kr. Antal\nindustriarb.: 35. Tillv.-värde pr år: 400,000 kr.\n— Firman grundad 1912, bolag 1916,\nnuv. namn 1945.\n\nVerkst. dir.: Gunnar Westholm\n(Stockholm).\n\nDisp.: Curt Westholm.\n\n* Bergslagens Bryggeri AB., Västerås.\n\nTillverkar maltdrycker av kl. I och II\nvid bryggeri i Norberg (Västmanl. l.).\n\nHuvudkontor: Västerås. Telefon: 30003\no. 30070. Bryggerikontor: Norberg.\nTelefon: 18. — Akt.-kap.: 60,000 kr.\nArb.-antal: 5. — Bolaget grundat 1892.\n\nStyrelse: dir. Joel Widén (ordf.), disp.\nHugo Anderson.\n\nVerkst. dir.: ing. Curt R. Widén.\n\nKamrer: Torsten Wahlberg.\n\nPlatschef: fabr. Nils Ny.\n\nAB. Bergslagens Gemensamma\nKraftförvaltning, Västerås.\n\nTransformatorstationer för\nKrångede-kraft vid Norberg, Ramnäs och\nRiddar-hyttan (samtl. i Västmanl. l.).\nDistribuerar elektr. energi inom Bergslagen.\n\nKontor: Västerås. Telegr.-adr.:\nBergslagskraft, Västerås. Telefon: 32003.\nPostgiro: 75462. — Akt.-kap.: 4,500,000 kr.\nDistrib.-värde pr år: 4,000,000 kr. —\nBolaget grundat 1918.\n\nStyrelse: dir. Thorsten Ericson, disp.\nCarl G. Granström, disp. John E. Hedin,\ndir. Carl A. Jacobsson, fil. dr Mogens\nMatell, disp. William Nisser, bruksdisp.\nThorsten Wigelius.\n\nVerkst. dir.: Mogens Matell.\n\nAB. Bergslagernas Kättingfabrik,\n\nSmedjebacken.\n\nTillverkar elektrosvetsad kätting vid\nfabrik i Filipstad (Värml. l.).\n\nKontor: Smedjebacken. Telegr.-adr. o.\ntelefon: Valsverket, Smedjebacken.\nPostgiro: 85405.\n\nAkt.-kap.: 15,400 kr. Antal\nindustriarb.: 10. Tillv.-värde pr år: 100,000 kr.\n— Bolaget grundat 1926.\n\nStyrelse: disp. Rutger Wijkander\n(ordf.), ing. Ragnar Forsberg,\nförsäljn.-chef Eric Westerfors.\n\nVerkst. dir.: Rutger Wijkander.\n\nDriftsing. i Filipstad: Ragnar\nForsberg.\n\nBergslagernas Tegel- &amp; Kalkbruks\n\nAB., Ludvika.\n\nKalksandstegelbruk i Ludvika\n(Kopparb. l.).\n\nTillverkar kalksandtegel och\nånghärda-de koksslaggplattor.\n\nKontor: Ludvika. Telefon: 6. Postgiro:\n94088.\n\nAkt.-kap.: 150,500 kr. Antal\nindustriarb.: 25. Årstillv.: 4 milj. st.\nkalksandtegel, 60,000 m2 koksslaggplattor. —\nBolaget grundat 1903.\n\nStyrelse: dir. Sture Axdorph (ordf.),\nkapten Rune Axdorph, disp. Ludv. Ålund.\n\nVerkst. dir.: Sture Axdorph (Sthlm).\n\nFörvalt.: disp. Ludv. Ålund.\n\n*AB. B. Bergson &amp; Söner,\n\nKarlstad.\n\nKonfektionsfabrik. Tillverkar\nherrkläder, damkappor och damdräkter.\nVarumärken: »Omkläder» o. »Eagle».\n\nTelegr.-adr.: Bergsons, Karlstad.\nTelefon: 15070. Postgiro: 34172. —\nAkt.-kap.: 377,500 kr. Antal industriarb.: 230.\nTillv.-värde pr år: 3,000,000 kr. —\nFirman grundad 1900, bolag 1932.\n\nStyrelse: grossh. Abel Bergson, grossh.\nIsak Bergson, dir. Samuel Bergson.\n\nVerkst. dir.: S. Bergson.\n\nKontorschef: Harald Munnich.",
    "structured": {
        "1": {
            "name": "Bergshamra Ångkvarns, Sågverks & Snickeri-AB",
            "location": "Utanbro",
            "business": "Sågverk, hyvleri och snickerifabrik",
            "products": "Hyvlade och ohyvlade trävaror, byggnadssnickerier, samt kvarnrörelse",
            "contact": {
                "office": "Bergshamra",
                "phone": [
                    "Bergshamra 8"
                ],
                "postgiro": "282841",
                "sales_offices": [],
                "factory_phone": ""
            },
            "financials": {
                "capital": "27,400 kr",
                "employees": {
                    "industriarb": 25
                },
                "annual_turnover": "200,000 kr"
            },
            "foundation_year": 1893,
            "director": "Carl Axel Engström"
        },
        "2": {
            "name": "Bergsjöverken AB",
            "location": "Bergsjö",
            "business": "Snickeri, mek. verkstad, såg och hyvleri, elektr. kraftverk",
            "products": "Monteringsfärdiga trähus, tröskverk, hö- och halmfläktar, höpressar, rikthyvlar, vedkapar",
            "contact": {
                "telegraph": "Reformverk, Bergsjö",
                "phone": [
                    "Bergsjöverken"
                ],
                "postgiro": "265597",
                "sales_offices": [
                    {
                        "location": "Stockholm",
                        "phone": "230380"
                    }
                ],
                "factory_phone": ""
            },
            "financials": {
                "capital": "78,000 kr",
                "employees": {
                    "industriarb": 35
                },
                "annual_turnover": "400,000 kr"
            },
            "foundation_year": 1912,
            "corporation_year": 1916,
            "current_name_year": 1945,
            "director": "Gunnar Westholm"
        },
        "3": {
            "name": "Bergslagens Bryggeri AB.",
            "location": "Västerås",
            "business": "Tillverkar maltdrycker",
            "products": "Maltdrycker av kl. I och II",
            "contact": {
                "office": "Västerås",
                "phone": [
                    "30003",
                    "30070"
                ],
                "postgiro": "",
                "head_office": "",
                "factory_phone": "18"
            },
            "financials": {
                "capital": "60,000 kr",
                "employees": {
                    "Arb.-antal": 5
                },
                "annual_turnover": ""
            },
            "foundation_year": 1892,
            "board": [
                {
                    "name": "Joel Widén",
                    "role": "ordf"
                },
                {
                    "name": "Hugo Anderson",
                    "role": "disp"
                }
            ],
            "director": "Curt R. Widén",
            "kamrer": "Torsten Wahlberg",
            "sales_manager": "fabr. Nils Ny"
        },
        "4": {
            "name": "AB. Bergslagens Gemensamma Kraftförvaltning",
            "location": "Västerås",
            "business": "Transformatorstationer för Krångede-kraft",
            "contact": {
                "office": "Västerås",
                "phone": [
                    "32003"
                ],
                "postgiro": "75462",
                "head_office": "",
                "factory_phone": ""
            },
            "financials": {
                "capital": "4,500,000 kr",
                "employees": {},
                "annual_turnover": "4,000,000 kr"
            },
            "foundation_year": 1918,
            "board": [
                {
                    "name": "Thorsten Ericson",
                    "role": "dir"
                },
                {
                    "name": "Carl G. Granström",
                    "role": "disp"
                },
                {
                    "name": "John E. Hedin",
                    "role": "disp"
                },
                {
                    "name": "Carl A. Jacobsson",
                    "role": "dir"
                },
                {
                    "name": "Mogens Matell",
                    "role": "fil. dr"
                },
                {
                    "name": "William Nisser",
                    "role": "disp"
                },
                {
                    "name": "Thorsten Wigelius",
                    "role": "bruksdisp"
                }
            ],
            "director": "Mogens Matell"
        },
        "5": {
            "name": "AB. Bergslagernas Kättingfabrik",
            "location": "Smedjebacken",
            "business": "Tillverkar elektrosvetsad kätting",
            "products": "Elektrosvetsad kätting",
            "contact": {
                "office": "Smedjebacken",
                "phone": [],
                "postgiro": "85405",
                "head_office": "",
                "factory_phone": ""
            },
            "financials": {
                "capital": "15,400 kr",
                "employees": {
                    "industriarb": 10
                },
                "annual_turnover": "100,000 kr"
            },
            "foundation_year": 1926,
            "board": [
                {
                    "name": "Rutger Wijkander",
                    "role": "disp"
                },
                {
                    "name": "Ragnar Forsberg",
                    "role": "ing. "
                },
                {
                    "name": "Eric Westerfors",
                    "role": "försäljn.-chef"
                }
            ],
            "director": "Rutger Wijkander"
        },
        "6": {
            "name": "Bergslagernas Tegel- & Kalkbruks AB.",
            "location": "Ludvika",
            "business": "Kalksandstegelbruk",
            "products": "Kalksandtegel, ånghärdade koksslaggplattor",
            "contact": {
                "office": "Ludvika",
                "phone": [
                    "6"
                ],
                "postgiro": "94088",
                "head_office": "",
                "factory_phone": ""
            },
            "financials": {
                "capital": "150,500 kr",
                "employees": {
                    "industriarb": 25
                },
                "annual_turnover": ""
            },
            "foundation_year": 1903,
            "board": [
                {
                    "name": "Sture Axdorph",
                    "role": "ordf"
                },
                {
                    "name": "Rune Axdorph",
                    "role": "kapten"
                },
                {
                    "name": "Ludv. Ålund",
                    "role": "disp"
                }
            ],
            "director": "Sture Axdorph",
            "sales_manager": "Ludv. Ålund"
        },
        "7": {
            "name": "AB. B. Bergson & Söner",
            "location": "Karlstad",
            "business": "Konfektionsfabrik",
            "products": "Herrkläder, damkappor, damdräkter",
            "contact": {
                "telegraph": "Bergsons, Karlstad",
                "phone": [
                    "15070"
                ],
                "postgiro": "34172",
                "head_office": "",
                "factory_phone": ""
            },
            "financials": {
                "capital": "377,500 kr",
                "employees": {
                    "industriarb": 230
                },
                "annual_turnover": "3,000,000 kr"
            },
            "foundation_year": 1900,
            "corporation_year": 1932,
            "board": [
                {
                    "name": "Abel Bergson",
                    "role": "grossh."
                },
                {
                    "name": "Isak Bergson",
                    "role": "grossh."
                },
                {
                    "name": "Samuel Bergson",
                    "role": "dir."
                }
            ],
            "director": "S. Bergson",
            "manager": "Harald Munnich"
        }
    }
}