{
    "original": "Gullaskruf-—Gallringen\n\nty palatset). Telegr.-adr.:\nGuldvafubola-get, Stockholm; telefon: 231065.\n\nAkt.-kap.: 1,200,000 kr. Antal\nindustriarb.: 130. Tillv.-värde pr år: 3,600,000 kr.\n\n—\tFirman etabl. 1845, bolag 1906.\n\nStyrelse: jur. dr Axel Roos (ordf.),\n\nfröken G. Holm, fru G. Nyström, dir.\nCarl-Sigvard Roos, fru G. Roos.\n\nVerkst. dir.; Carl-Sigvard Roos.\n\nGullaskrufs Glasbruks AB.,\n\nGullaskruv.\n\nGlasbruk vid Gullaskruv (Kronob. l.).\nTillverkar pressat och blåst hushållsglas,\nkristall- och konstglas samt\nstrålkastar-glas och tekniskt glas.\n\nTelegr.-adr.: Gullglas, Kalmar.\nTelefon: Orrefors 42. Postgiro: 165600. Repr.\ni Stockholm: W. Isacsson, Smedsbacksg.\n3, telefon: 612602.\n\nAkt.-kap.: 87,000 kr. Antal\nindustriarb.: 80. Tillv.-värde pr år: 900,000 kr.\n\n—\tGlasbruket anlagt 1893 som\nfönsterglasbruk, bolaget grundat 1927.\n\nStyrelse: ing. William Stenberg (ordf.),\ngodsäg. Carl Andersson, disp. Tage\nStenberg.\n\nDisp.: William Stenberg.\n\nKamrer: Göte Holmberg.\n\nCullbergs Maskinfabriks AB.,\n\nStockholm.\n\nGjuteri och mek. verkstad i Lindås\n(Kalmar l.). Tillverkar maskiner för\nbyggnadsindustrien såsom\nbetongblan-dare och lyftkranar, sågverksmaskiner\nsåsom balanskapsågar och justerverk,\ntransportanordningar såsom rem- och\nkätti ngtransportörer.\n\nHuvudkontor: Stockholm,\nFörmansvägen 19, postadr.: Stockholm 9.\nTelegr.-adr.: Lind verk, Stockholm. Telefon:\n452760. Postgiro: 191512.\nVerkstadskontor: Lindås, telegr.-adr.: Gullbergs,\nLind-ås, telefon: Emmaboda 4 o. 277.\n\nAkt.-kap.: 93,000 kr. Antal\nindustriarb.: 100.\n\nFirman etabl. 1871, bolag 1904 under\nnamn AB. Gullbergs &amp; Co., nuv. namn\n1938.\n\nStyrelse: ing. Walter Hesselman, ing.\nGottfrid Mattsson, civiling. Carl-Olof\nStråhle.\n\nVerkst. dir.: WalteT Hesselman\n(Stockholm).\n\nPlatschef: disp. Rickard Kempe.\n\n* Gullbergs Skofabrik, Mosas.\n\nTillverkar ago, randsydda,\nklammer-rand, pliggade och sandalsydda skodon\n\nsamt sandaler och tofflor vid fabrik i\nMosås (Örebro l.). Varumärke: »Eges».\n\nTelefon: Örebro 75150. Postgiro: 92992.\n— Antal industriarb.: 74. Tillv.-värde\npr år: 1,200,000 kr. — Firman etabl.\n1919.\n\nÄgare: fru L. M. Gullberg.\nDisp.: fabr. Erik Gullberg.\n\n\"Cullebo Snickerifabrik, Gunnar\nPetersson, Rottne.\n\nTillverkar möbler vid fabrik i Rottne\n(Kronob. l.).\n\nTelefon: 29. Postgiro: 95365. Repr.: i\nStockholm: Köpm. R. Artoft,\nMälartorget 19, telefon: 206668; för södra\nSverige: KÖpm. Jerker Christensen,\nSkva-dronsg. 27, Malmö, telefon: 78782.\n\nAntal industriarb.: 18. Tillv.-värde pr\når: 200,000 kr. — Firman etabl. 1920.\n\nÄgare o. chef: fabr. Gunnar Petersson.\n\n*AB. Gullhögens Bruk, Skövde.\n\nCementfabrik och kalkbruk. Tillverkar\ncement och bränd kalk. Bolaget driver\näven jordbruk.\n\nTelegr.-adr. o. telefon: Gullhögen,\nSkövde. Postgiro: 26865.\n\nAkt.-kap.: 1,000,000 kr. Antal\nindustriark: 244. Prod.-värde pr år: §&gt;100,000 kr.\n— Bolaget grundat 1916.\n\nStyrelse: v. konsul Aug. Wingårdh\n(ordf.), v. konsul Gustaf Wingårdh, disp.\nErik Wingårdh, agronom Henning\nWingårdh, agronom Åke Wingårdh.\n\nVerkst. dir.: Aug. Wingårdh.\n\nDisp.: Erik Wingårdh.\n\nDriftsing.: ing. L. Hj. Glise.\n\nKamrer: Lennart Bergström.\n\nFörsäljn.-chef: Roland Sandberg.\n\nGullringens Träförädling,\n\nGullringen.\n\nSnickerifabrik i Gullringen (Kalmar\n1.). Tillverkar monteringsfärdiga trähus\nsamt byggnadssnickerier. Varumärke:\n»Gull rings-Hus».\n\nTelegr.-adr.: Ansgarius, Gullringen.\nTelefon: 18, 20 o. 28. Postgiro: 23470.\n\nAntal industriarb.: 150. Tillv.-värde\npr år: 2,000,000 kr. — Firman etabl.\n1930.\n\nÄgare: Ansgarius Svenssons Sterbhus.\nDir.: Stig Ansg. Svensson.\nDisp,: Martin Jakobsson.\nDriftsing.: Erik Nystedt.\nKamrer: John Sonnerby.",
    "structured": {
        "1": {
            "name": "Gullaskruf-—Gallringen",
            "location": "Gallringen",
            "business": "Glasbruk",
            "products": "Tillverkar pressat och blåst hushållsglas, kristall- och konstglas samt strålkastar-glas och tekniskt glas.",
            "contact": {
                "head_office": "Gullaskruf, Kalmar",
                "phone": [
                    "Orrefors 42"
                ],
                "postgiro": "165600",
                "sales_offices": [
                    {
                        "location": "Stockholm",
                        "phone": "612602"
                    }
                ]
            },
            "financials": {
                "capital": "1,200,000 kr",
                "employees": {
                    "industriarb": 130
                },
                "annual_turnover": "3,600,000 kr",
                "annual_production_value": "3,600,000 kr"
            },
            "foundation_year": 1845,
            "corporation_year": 1906,
            "board": [
                {
                    "name": "jur. dr Axel Roos",
                    "role": "ordf."
                },
                {
                    "name": "fröken G. Holm",
                    "role": ""
                },
                {
                    "name": "fru G. Nyström",
                    "role": ""
                },
                {
                    "name": "dir. Carl-Sigvard Roos",
                    "role": ""
                }
            ],
            "manager": "Carl-Sigvard Roos"
        },
        "2": {
            "name": "Gullaskrufs Glasbruks AB.",
            "location": "Gullaskruv",
            "business": "Glasbruk",
            "products": "Tillverkar pressat och blåst hushållsglas, kristall- och konstglas samt strålkastar-glas och tekniskt glas.",
            "contact": {
                "office": "Gullaskruf, Kalmar",
                "phone": [
                    "Orrefors 42"
                ],
                "postgiro": "165600",
                "sales_offices": [
                    {
                        "location": "Stockholm",
                        "phone": "612602"
                    }
                ]
            },
            "financials": {
                "capital": "87,000 kr",
                "employees": {
                    "industriarb": 80
                },
                "annual_turnover": "900,000 kr",
                "annual_production_value": "900,000 kr"
            },
            "foundation_year": 1893,
            "corporation_year": 1927,
            "board": [
                {
                    "name": "ing. William Stenberg",
                    "role": "ordf."
                },
                {
                    "name": "godsäg. Carl Andersson",
                    "role": ""
                },
                {
                    "name": "disp. Tage Stenberg",
                    "role": ""
                }
            ],
            "manager": "William Stenberg"
        },
        "3": {
            "name": "Cullbergs Maskinfabriks AB.",
            "location": "Stockholm",
            "business": "Gjuteri och mek. verkstad",
            "products": "Tillverkar maskiner för byggnadsindustrien såsom betongblandare och lyftkranar, sågverksmaskiner såsom balanskapsågar och justerverk, transportanordningar såsom rem- och kättingtransportörer.",
            "contact": {
                "office": "Förmansvägen 19, Stockholm",
                "phone": [
                    "452760"
                ],
                "postgiro": "191512",
                "sales_offices": [
                    {
                        "location": "Lindås",
                        "phone": "Emmaboda 4 o. 277"
                    }
                ]
            },
            "financials": {
                "capital": "93,000 kr",
                "employees": {
                    "industriarb": 100
                }
            },
            "foundation_year": 1871,
            "corporation_year": 1904,
            "current_name_year": 1938,
            "board": [
                {
                    "name": "ing. Walter Hesselman",
                    "role": ""
                },
                {
                    "name": "ing. Gottfrid Mattsson",
                    "role": ""
                },
                {
                    "name": "civiling. Carl-Olof Stråhle",
                    "role": ""
                }
            ],
            "manager": "Walter Hesselman",
            "sales_manager": "Rickard Kempe"
        },
        "4": {
            "name": "Gullbergs Skofabrik",
            "location": "Mosas",
            "business": "Tillverkar skodon",
            "products": "Tillverkar ago, randsydda, klammerrand, pliggade och sandalsydda skodon samt sandaler och tofflor.",
            "contact": {
                "phone": [
                    "Örebro 75150"
                ],
                "postgiro": "92992"
            },
            "financials": {
                "employees": {
                    "industriarb": 74
                },
                "annual_turnover": "1,200,000 kr"
            },
            "foundation_year": 1919,
            "owners": [
                "fru L. M. Gullberg"
            ],
            "director": "Erik Gullberg"
        },
        "5": {
            "name": "Cullebo Snickerifabrik",
            "location": "Rottne",
            "business": "Tillverkar möbler",
            "products": "Tillverkar möbler",
            "contact": {
                "phone": [
                    "29"
                ],
                "postgiro": "95365",
                "sales_offices": [
                    {
                        "location": "Stockholm",
                        "phone": "206668"
                    },
                    {
                        "location": "södra Sverige",
                        "phone": "78782"
                    }
                ]
            },
            "financials": {
                "employees": {
                    "industriarb": 18
                },
                "annual_turnover": "200,000 kr"
            },
            "foundation_year": 1920,
            "manager": "Gunnar Petersson"
        },
        "6": {
            "name": "AB. Gullhögens Bruk",
            "location": "Skövde",
            "business": "Cementfabrik och kalkbruk",
            "products": "Tillverkar cement och bränd kalk. Bolaget driver även jordbruk.",
            "contact": {
                "phone": [
                    "Gullhögen, Skövde"
                ],
                "postgiro": "26865"
            },
            "financials": {
                "capital": "1,000,000 kr",
                "employees": {
                    "industriarb": 244
                },
                "annual_turnover": "§ 100,000 kr"
            },
            "foundation_year": 1916,
            "board": [
                {
                    "name": "v. konsul Aug. Wingårdh",
                    "role": "ordf."
                },
                {
                    "name": "v. konsul Gustaf Wingårdh",
                    "role": ""
                },
                {
                    "name": "disp. Erik Wingårdh",
                    "role": ""
                },
                {
                    "name": "agronom Henning Wingårdh",
                    "role": ""
                },
                {
                    "name": "agronom Åke Wingårdh",
                    "role": ""
                }
            ],
            "manager": "Aug. Wingårdh"
        },
        "7": {
            "name": "Gullringens Träförädling",
            "location": "Gullringen",
            "business": "Snickerifabrik",
            "products": "Tillverkar monteringsfärdiga trähus samt byggnadssnickerier.",
            "contact": {
                "telegraph": "Ansgarius, Gullringen",
                "phone": [
                    "18",
                    "20",
                    "28"
                ],
                "postgiro": "23470"
            },
            "financials": {
                "employees": {
                    "industriarb": 150
                },
                "annual_turnover": "2,000,000 kr"
            },
            "foundation_year": 1930,
            "manager": "Stig Ansg. Svensson",
            "sales_manager": "Martin Jakobsson"
        }
    }
}