{
    "original": "O b b o la—O Ijeraffinaderiet\n\n* utmärker till Sveriges Industriförbund anslutna företag.\n\n*Obbola Sulfatfabrik, Obbola.\n\nSe Holmsunds AB., Holmsund.\n\n*AB. Ocke Ångsåg, Ocke.\n\nSågverk vid Ocke (Jämtl. l.).\nTillverkar sågade trävaror, props, pappersved,\nhackflis m. m.\n\nTelegr.-adr.: Ångsågen, Ocke.\nTelefon: 7. Postgiro: 165873.\n\nAkt.-kap.: 165,000 kr. Antal\nindustriarb.: 25. Årstillv.: 2,000 stds trävaror.\n— Sågverket anlagt 1880, nuv. bolag\ngrundat 1925.\n\nStyrelse: disp. John Ocklind (ordf.),\nköpm. Nils Pettersson, hemmansäg. Olle\nStrandberg.\n\nDisp.: John Ocklind.\n\nOdatverken, Eksjö.\n\nMek. verkstad. Tillverkar\nbränslekrossar, ben-, kött-, gröp-, hö- och\nspånkvar-nar, foderblandare, trätuggare, vädurar\nm. m. Varumärke: »Odal».\n\nTelegr.-adr.: Odalverken, Eksjö.\nTelefon: 279. Postgiro: 30401. — Antal\nindustriarb.: 20. Tillv.-värde pr år: 250,000\nkr. — Firman etabl. 1897, nuv. namn\n1923. ’\n\nÄgare o. chef: ing. E. I. Wohlfart.\n*0dell &amp; Ekberg, Pälsboda.\n\nGjuteri och mek. verkstad i Pålsboda\n(Örebro l.). Tillverkar vattenringpumpar\n(märke: »FOKE»). Specialitet:\nmassproduktion av maskinformat gjutgods, såväl\narbetat som oarbetat.\n\nTelegr.-adr. o. telefon: Odell &amp; Ekberg,\nPålsboda. Postgiro: 265530.\n\nAntal industriarb.: 70. Tillv.-värde pr\når: 1,200,000 kr. — Firman etabl. 1936.\n\nÄgare o. chefer: ing. Filip Odell o.\ndisp. Karl Ekberg.\n\nFörsäljn.-chef f. pumpar: Bror\nSjön-wall.\n\n*Ohs Bruk, AB., Osbruk.\n\nSulfitfabrik, sågverk och hyvleri samt\nvattenkraftstation vid Osbruk,\nvattenkraftstationer vid Långö och vid Ivars\n(samtl. i Jönköp. l.), sågverk och\ntegelbruk vid Almnäs, Hjo.\n\nTillverkar blekt sulfitcellulosa för\nfinpapper och konstsilketillverkning, sågade\noch hyvlade trävaror samt tegel. Firman\nidkar jämväl jordbruk, skogshantering,\nmejeri- och kvarnrörelse.\n\nTelefon: Värnamo 51023. Postgiro:\n75692.\n\nAkt.-kap.: 1,175,000 kr. Antal\nindustriarb.: 55. Årstillv.: 4,200 ton helblekt\nsulfitcellulosa, 2,000 stds sågade och hyvlade\nträvaror. — Firman etabl. 1883, bolag\n1913.\n\nStyrelse: dir. Erik Berglund (ordf.),\ndisp. Anders Berglund, fröken Karin\nBerglund.\n\nVerkst. dir. o. disp.: Erik Berglund.\n\nDir.-assist.: civiling. Stig Berglund.\n\nFörvaltare: vid Osbruk: W. Lindskog;\nvid Almnäs: G. Fägervall.\n\nOljefabrlks-AB. Merkantil,\n\nKristianstad.\n\nOljeslageri. Tillverkar rå och kokt\nlinolja samt linfrökakor och linfrömjöl.\n\nTelegr.-adr.: Oljefabriken,\nKristianstad. Telefon: 11469. Postgiro: 72130. —\nAkt.-kap.: 300,000 kr. Antal industriarb.:\n15. — Bolaget grundat 1919.\n\nStyrelse: v. konsul Carl Nilsson\n(ordf.), grossh. Anders Andersson, dir.\nHj. Carlborn, dir. O. W. Öländer, grossh»\nThure Persson.\n\nVerkst. dir.: Hj. Carlborn.\n\nVice verkst. dir.: Carl Nilsson.\n\nDisp.: Henning Nilson.\n\nAB. Oljeraffinaderiet Ceres,\n\nMalmö.\n\nTillverkar taktjära,\nimpregneringsme-del, färger, skosmörja, bon vax, läcker och\nfernissor, mineralfodersalt,\ninsektsbe-sprutningsmedel, desinfektionsmedel m. m.\nBolaget idkar jämväl handel med\nsmörjoljor, trätjära, torsklevertran,\nbyggnadsma-teriel m. m.\n\nKontor: S. Förstadsg. 18. Telegr.-adr.:\nOljeceres, Malmö. Telefon: 21347.\nPostgiro: 14093. — Akt.-kap.: 270,000 kr.\nAntal industriarb.: 10. — Bolaget\ngrundat 1898.\n\nVerkst. dir.: Holger Balk-Möller.\n\nDisp.: Erik Balk-Möller.\n\n424*",
    "structured": {
        "1": {
            "name": "Obbola Sulfatfabrik",
            "location": "Obbola",
            "business": "Sulfatfabrik",
            "contact": {
                "telegraph": "Ångsågen, Obbola",
                "phone": [
                    "7"
                ],
                "postgiro": "165873"
            },
            "financials": {
                "capital": "165,000 kr",
                "employees": {
                    "industriarb": 25
                },
                "annual_turnover": "N/A",
                "annual_production_value": "2,000 stds trävaror"
            },
            "foundation_year": 1925
        },
        "2": {
            "name": "Odatverken",
            "location": "Eksjö",
            "business": "Mek. verkstad",
            "products": "bränslekrossar, ben-, kött-, gröp-, hö- och spånkvarnar, foderblandare, trätuggare, vädurar m. m.",
            "contact": {
                "telegraph": "Odalverken, Eksjö",
                "phone": "279",
                "postgiro": "30401"
            },
            "financials": {
                "employees": {
                    "industriarb": 20
                },
                "annual_production_value": "250,000 kr"
            },
            "foundation_year": 1897,
            "current_name_year": 1923,
            "owner": "ing. E. I. Wohlfart"
        },
        "3": {
            "name": "Odell & Ekberg",
            "location": "Pälsboda",
            "business": "Gjuteri och mek. verkstad",
            "products": "massproduktion av maskinformat gjutgods, såväl arbetat som oarbetat",
            "contact": {
                "telegraph": "Odell & Ekberg, Pälsboda",
                "phone": "N/A",
                "postgiro": "265530"
            },
            "financials": {
                "employees": {
                    "industriarb": 70
                },
                "annual_production_value": "1,200,000 kr"
            },
            "foundation_year": 1936,
            "owner": [
                "ing. Filip Odell",
                "disp. Karl Ekberg"
            ],
            "sales_manager": "Bror Sjönwall"
        },
        "4": {
            "name": "Ohs Bruk, AB.",
            "location": "Osbruk",
            "business": "Sulfitfabrik, sågverk, hyvleri, vattenkraftstationer, tegelbruk",
            "products": "blekt sulfitcellulosa för finpapper och konstsilketillverkning, sågade och hyvlade trävaror samt tegel",
            "description": "Firman idkar jämväl jordbruk, skogshantering, mejeri- och kvarnrörelse",
            "contact": {
                "telegraph": "N/A",
                "phone": "Värnamo 51023",
                "postgiro": "75692"
            },
            "financials": {
                "capital": "1,175,000 kr",
                "employees": {
                    "industriarb": 55
                },
                "annual_turnover": "N/A",
                "annual_production_value": "4,200 ton helblekt sulfitcellulosa, 2,000 stds sågade och hyvlade trävaror"
            },
            "foundation_year": 1913,
            "board": [
                {
                    "name": "dir. Erik Berglund",
                    "role": "ordf."
                },
                {
                    "name": "disp. Anders Berglund"
                },
                {
                    "name": "fröken Karin Berglund"
                }
            ],
            "director": "Erik Berglund"
        },
        "5": {
            "name": "Oljefabriks-AB. Merkantil",
            "location": "Kristianstad",
            "business": "Oljeslageri",
            "products": "rå och kokt linolja, linfrökakor, linfrömjöl",
            "contact": {
                "telegraph": "Oljefabriken, Kristianstad",
                "phone": "11469",
                "postgiro": "72130"
            },
            "financials": {
                "capital": "300,000 kr",
                "employees": {
                    "industriarb": 15
                }
            },
            "foundation_year": 1919,
            "board": [
                {
                    "name": "v. konsul Carl Nilsson",
                    "role": "ordf."
                },
                {
                    "name": "grossh. Anders Andersson"
                },
                {
                    "name": "dir. Hj. Carlborn"
                },
                {
                    "name": "dir. O. W. Öländer"
                },
                {
                    "name": "grossh. Thure Persson"
                }
            ],
            "director": "Hj. Carlborn"
        },
        "6": {
            "name": "AB. Oljeraffinaderiet Ceres",
            "location": "Malmö",
            "business": "Tillverkar taktjära, impregneringsmedel, färger, skosmörja, bön vax, läcker och fernissor, mineralfodersalt, insektsbeparutingsmedel m. m.",
            "description": "Bolaget idkar jämväl handel med smörjoljor, trätjära, torsklevertran, byggnadsmaterial m. m.",
            "contact": {
                "office": "S. Förstadsg. 18",
                "telegraph": "Oljeceres, Malmö",
                "phone": "21347",
                "postgiro": "14093"
            },
            "financials": {
                "capital": "270,000 kr",
                "employees": {
                    "industriarb": 10
                }
            },
            "foundation_year": 1898,
            "board": [
                {
                    "name": "Holger Balk-Möller",
                    "role": "Verkst. dir."
                },
                {
                    "name": "Erik Balk-Möller",
                    "role": "Disp."
                }
            ]
        }
    }
}