{
    "original": "Fabriken—Fabriks\n\nFabriks AB. Isacsönerna,\n\nMalmbäck.\n\nTillverkar möbler, speciellt\nbarnsängar och sängkammarmöbler vid fabrik i\nMalmbäck (Jönköp. l.).\n\nTelefon: 19 o. 119. Postgiro: 34837.\n\nAkt.-kap.: 40,000 kr. Antal\nindustri-arb.: 26. Tillv.-värde pr år: 475,000 kr. —\nFirman etabl. 1927, bolag 1938.\n\nDisp.: Carl II. Isacson.\n\nKamrer: Dennis Wikstrand.\n\n*\tFabriks AB. Kronsilver, Lidingö.\n\nNysilverfabrik och kem.-tekn. fabrik\nsamt elektro-galvanisk verksamhet vid\nGåshaga, Lidingö. Tillverkar\nkuvertnysilver och fat, samt smärgel-, slip- och\npo-lérvaxer för aluminium, mässing, nickel,\nnysilver och rostfritt; utför\nhårdförkrom-ning av verktyg och maskindelar, vanlig\nförkromning, förnickling, anodoxidering\noch kadmiering samt regenerering av\nfilar.\n\nKontor: Gåshaga, postadr.: Lidingö 3.\nTelegr.-adr.: Kronsilver, Stockholm.\nTelefon: 656900 o. 656902—03. Postgiro:\n52121.\n\nAkt.-kap.: 850,000 kr. Antal\nindustri-arb.: 45. —Bolaget grundat 1927.\n\nStyrelse: civiling. Olof Drakenberg\n(ordf.), dir. Ivar H. Arnfelt.\n\nVerkst. dir.: Ivar H. Arnfelt.\n\n*Fabriks AB. P. O. Lundgren, Borås.\n\nTrikåfabrik. Tillverkar herr- och\ndamstrumpor samt stickade yllevaror.\n\nTelefon: 18544. Postgiro: 263040. —\nAkt.-kap.: 100,000 kr. Antal industriarb.:\n38. Tillv.-värde pr år: 1,200,000 kr. —\nBolaget grundat 1942.\n\nStyrelse: köpm. Josef Lundgren (ordf.),\nfabr. Per-Olov Lundgren.\n\nVerkst. dir.: Per-Olov Lundgren.\n\n*\tFabriks AB. Osmund, Uppsala.\n\nMek. verkstad. Tillverkar ugnar för\nindustriändamål (även elektr.),\noljebrän-nare, högtrycksfläktar,\ntemperaturregulatorer, evakueringsventiler, transportrullar\nsamt tegelsågar m. m. Varumärke:\n»Osmund».\n\nTelegr.-adr.: Osmund, Uppsala.\nTelefon: 39555. Postgiro: 26688. — Akt.-kap.:\n257,500 kr. Antal industriarb.: 50. —\nBolaget grundat 1912.\n\nStyrelse: ing. Walter Hesselman, ing.\nKarl Einar Lundberg, kamrer J. F.\nThorslund.\n\nVerkst. dir.: K. E. Lundberg.\n\n(Jfr annons nr 86.)\n\nFabriks AB. Rudberg &amp; Co.,\n\nFalköping.\n\nDamkonfektionsfabrik. Tillverkar\nchar-meuseunderkläder samt blusar i siden och\nylle. Varumärke: »Farco».\n\nTelefon: 48. Postgiro: 160063. Repr. i\nStockholm: Erik Rudberg, Sveavägen 88,\ntelefon: 320408. — Akt.-kap.: 25,000 kr.\nAntal industriarb.: 40. — Bolaget\ngrundat 1939.\n\nVerkst. dir.: Nils Rudberg.\n\nFabriks AB. Säpo, Hälsingborg.\n\nKem. tekn. fabrik. Tillverkar\ntvättmedel såsom såpa, tvålflingor,\ntvättpulver samt kristallsoda.\n\nTelegr.-adr.: Säpo, Hälsingborg.\nTelefon: 11222. Postgiro: 14396. —\nAkt.-kap.: 25,000 kr. Arb.-antal: 7. — Firman\netabl. 1909.\n\nVerkst. dir.: fru O. Christell.\n\nDisp.: Einar Christell.\n\n*Fabriks AB. Skandiahus, Stockholm.\n\nSe Olsson &amp; Rosenlunds AB.,\nStockholm.\n\nFabriks AB. Skandinavien,\n\nMalmö.\n\nBand- och spetsfabrik med färgeri samt\nknappfabrik. Tillverkar band, käng- och\nskosnören, spetsar, tyg- och\nmetallknappar m. m.\n\nKontor: Barkg. 5. Telegr.-adr.:\nSkandinavien, Malmö. Telefon: 20780 o. 22780.\nPostgiro: 14113.\n\nAkt.-kap.: 700,000 kr. Antal\nindustriarb.: 170. — Bolaget grundat 1894.\n\nStyrelse: dir. C. Steenhoff Eriksen\n(ordf.), grossh. H. Laage-Petersen, dir.\nSven-Aage Rydgaard.\n\nVerkst. dir.: S.-A. Rydgaard.\n\n* Fabriks AB. Swebe, Borås.\n\nKonfektionsfabrik. Tillverkar\ndam-klänningar, kjolar och blusar.\nVarumärke: »Swebe».\n\nTelefon: 12928. Postgiro: 36281.\n\nAkt.-kap.: 50,000 kr. Antal\nindustriarb.: 30. Tillv.-värde pr år: 300,000 kr.\n— Firman grundad 1929, nuv. namn\n1935.\n\nStyrelse: dir. Edvin Johansson (ordf.),\ndir. Arvid Claesson.\n\nVerkst. dir.: Edvin Johansson.",
    "structured": {
        "1": {
            "name": "Fabriks AB. Isacsönerna",
            "location": "Malmbäck",
            "business": "Tillverkar möbler, speciellt barnsängar och sängkammarmöbler",
            "contact": {
                "office": "Malmbäck (Jönköp. l.)",
                "phone": [
                    "19",
                    "119"
                ],
                "postgiro": "34837"
            },
            "financials": {
                "capital": "40,000 kr",
                "employees": {
                    "industri-arb": 26
                },
                "annual_turnover": "475,000 kr"
            },
            "foundation_year": 1927,
            "corporation_year": 1938,
            "board": [
                {
                    "name": "Carl II. Isacson",
                    "role": "Disp."
                }
            ],
            "director": "Carl II. Isacson"
        },
        "2": {
            "name": "Fabriks AB. Kronsilver",
            "location": "Lidingö",
            "business": "Nysilverfabrik och kem.-tekn. fabrik samt elektro-galvanisk verksamhet",
            "products": "Tillverkar kuvertnysilver, fat, smärgel-, slip- och po-lérvaxer för aluminium, mässing, nickel, nysilver och rostfritt; utför hårdförkrom-ning av verktyg och maskindelar, vanlig förkromning, förnickling, anodoxidering och kadmiering samt regenerering av fara.",
            "contact": {
                "office": "Gåshaga, Lidingö",
                "phone": [
                    "656900",
                    "656902-03"
                ],
                "postgiro": "52121"
            },
            "financials": {
                "capital": "850,000 kr",
                "employees": {
                    "industri-arb": 45
                }
            },
            "corporation_year": 1927,
            "board": [
                {
                    "name": "Olof Drakenberg",
                    "role": "civiling."
                },
                {
                    "name": "Ivar H. Arnfelt",
                    "role": "dir."
                }
            ],
            "director": "Ivar H. Arnfelt"
        },
        "3": {
            "name": "Fabriks AB. P. O. Lundgren",
            "location": "Borås",
            "business": "Trikåfabrik",
            "products": "Tillverkar herr- och damstrumpor samt stickade yllevaror",
            "contact": {
                "phone": [
                    "18544"
                ],
                "postgiro": "263040"
            },
            "financials": {
                "capital": "100,000 kr",
                "employees": {
                    "industriarb": 38
                },
                "annual_turnover": "1,200,000 kr"
            },
            "corporation_year": 1942,
            "board": [
                {
                    "name": "Josef Lundgren",
                    "role": "köpm."
                },
                {
                    "name": "Per-Olov Lundgren",
                    "role": "fabr."
                }
            ],
            "director": "Per-Olov Lundgren"
        },
        "4": {
            "name": "Fabriks AB. Osmund",
            "location": "Uppsala",
            "business": "Mek. verkstad",
            "products": "Tillverkar ugnar för industriändamål (även elektr.), oljebrännare, högtrycksfläktar, temperaturregulatorer, evakueringsventiler, transportrullar samt tegelsågar m. m.",
            "contact": {
                "telegraph": "Osmund, Uppsala",
                "phone": [
                    "39555"
                ],
                "postgiro": "26688"
            },
            "financials": {
                "capital": "257,500 kr",
                "employees": {
                    "industriarb": 50
                }
            },
            "corporation_year": 1912,
            "board": [
                {
                    "name": "Walter Hesselman",
                    "role": "ing."
                },
                {
                    "name": "Karl Einar Lundberg",
                    "role": "ing."
                },
                {
                    "name": "J. F. Thorslund",
                    "role": "kamrer"
                }
            ],
            "director": "K. E. Lundberg"
        },
        "5": {
            "name": "Fabriks AB. Rudberg & Co.",
            "location": "Falköping",
            "business": "Damkonfektionsfabrik",
            "products": "Tillverkar charmeuseunderkläder samt blusar i siden och ylle",
            "contact": {
                "phone": [
                    "48"
                ],
                "postgiro": "160063"
            },
            "financials": {
                "capital": "25,000 kr",
                "employees": {
                    "industriarb": 40
                }
            },
            "corporation_year": 1939,
            "director": "Nils Rudberg"
        },
        "6": {
            "name": "Fabriks AB. Säpo",
            "location": "Hälsingborg",
            "business": "Kem. tekn. fabrik",
            "products": "Tillverkar tvättmedel såsom såpa, tvålflingor, tvättpulver samt kristallsoda",
            "contact": {
                "telegraph": "Säpo, Hälsingborg",
                "phone": "11222",
                "postgiro": "14396"
            },
            "financials": {
                "capital": "25,000 kr",
                "employees": {
                    "arb-antal": 7
                }
            },
            "foundation_year": 1909,
            "director": "fru O. Christell"
        },
        "7": {
            "name": "Fabriks AB. Skandinavien",
            "location": "Malmö",
            "business": "Band- och spetsfabrik med färgeri samt knappfabrik",
            "products": "Tillverkar band, käng- och skosnören, spetsar, tyg- och metallknappar m. m.",
            "contact": {
                "office": "Barkg. 5",
                "phone": [
                    "20780",
                    "22780"
                ],
                "postgiro": "14113"
            },
            "financials": {
                "capital": "700,000 kr",
                "employees": {
                    "industriarb": 170
                }
            },
            "corporation_year": 1894,
            "board": [
                {
                    "name": "C. Steenhoff Eriksen",
                    "role": "dir."
                },
                {
                    "name": "H. Laage-Petersen",
                    "role": "grossh."
                },
                {
                    "name": "Sven-Aage Rydgaard",
                    "role": "dir."
                }
            ],
            "director": "S.-A. Rydgaard"
        },
        "8": {
            "name": "Fabriks AB. Swebe",
            "location": "Borås",
            "business": "Konfektionsfabrik",
            "products": "Tillverkar damklännningar, kjolar och blusar",
            "contact": {
                "phone": [
                    "12928"
                ],
                "postgiro": "36281"
            },
            "financials": {
                "capital": "50,000 kr",
                "employees": {
                    "industriarb": 30
                },
                "annual_turnover": "300,000 kr"
            },
            "corporation_year": 1935,
            "board": [
                {
                    "name": "Edvin Johansson",
                    "role": "dir."
                },
                {
                    "name": "Arvid Claesson",
                    "role": "dir."
                }
            ],
            "director": "Edvin Johansson"
        }
    }
}