{
    "original": "Kirudd—Kla c k fa b riken\n\n\"Kirudds AB., Vänersborg.\n\nDamkonfektionsfabrik. Tillverkar\nkappor, dräkter, blazers, pälsar och\nbadkappor.\n\nTelefon: 863 o. 864. Postgiro: 29009. —\nAkt.-kap.: 400,000 kr. Antal industriarb.:\n\nBolaget grundat 1917 under namn AB.\nGunnar Wiborg, nuv. namn 1940.\n\nStyrelse o. verkst. dir.: grossh. Bror\nKirudd.\n\n*Kirudds Byxfabrik, Vänersborg.\n\nSe AB. Svenkonfektion, Vänersborg.\n\n\"Kiruna Ölbryggeri AB., Kiruna.\n\nTillverkar maltdrycker, mineralvatten\noch läskedrycker vid bryggeri i Kiruna\n(Norrbott. l.).\n\nTelegr.-adr.: ölbryggeriet, Kiruna.\nPostgiro: 61679. — Akt.-kap.: 100,000 kr.\nArb.-antal: 12. — Bolaget grundat 1905.\n\nStyrelse: arkitekt John Wikberg\n{ordf.), apot. Erik Georgii.\n\nVerkst. dir.: Erik Georgii (Sthlm).\n\nPlatschef: bryggm. Karl Erik\nSand-t)erg.\n\n\"Kirurgiska Instrument Fabriks AB.\nKifa, Stockholm.\n\nFinmek. verkstad och instrumentfabrik\ni Solna. Tillverkar kirurgiska\ninstrument i rostfritt stål, operationsmöbler,\nsteriliseringsapparater, elektromedicinska\napparater, konstgjorda lemmar,\nortopediska bandage, laboratorieartiklar, elektr.\n&lt;^ntrifuger m. m. Varumärke: »Kifa».\n\nKontor: Stockholm, Regeringsg. 31.\nT«legr.-adr.: Kifa, Stockholm. Telefon:\n^Instrument-Kifa». Postgiro: 2103.\n\nAkt.-kap.: 550,000 kr. Antal\nindustriarb.: 90. — Bolaget grundat 1911.\n\nStyrelse: med. dr Carl S. Samnuelsson\n(ordf.), ing. Arvid Bergman, dir. Erich\nDingel, dir. Gustaf V. Ljungberg,\növerläkare Svante Orell.\n\nVerkst. dir.: Erich Dingel.\n\nKontorschef: Allan Jonson.\n\nDriftsing.: Nils Lundgren.\n\n\"Kisa Bryggeri, Kisa.\n\nSe AB. Nya Centralbryggeriet,\nLinköping.\n\n\"AB. Kjells Armaturfabrik,\n\nBäckefors.\n\nTillverkar armatur för gas, vatten och\n;ånga, metallgjutgods samt botten- och\n\n:19\n\nmellanventilen »Källan» vid fabrik i\nBäckefors (Älvsb. l.).\n\nTelefon: 4. Postgiro: 87350. —\nAkt.-kap.: 120,000 kr. Antal industriarb.: 50.\nTillv.-värde pr år: 470,000 kr. — Bolaget\ngrundat 1918.\n\nStyrelse: dir. Axel Calvert, fabr. C. J.\nKjell, disp. H. Kjell, kontorschef K. R.\nSahlberg, civiling. A. Weilenmann.\nVerkst. dir.: Axel Calvert.\nDisp.: Halfdan Kjell.\n\nKjellander &amp; Co., Vetlanda.\n\nUtför slipning, gravering och annan\nkonstindustrien bearbetning av glas vid\nglassliperi i Vetlanda (Jönköp. l.).\n\nTelefon: 296. Postgiro: 88316. —\nAntal industriarb.: 8. — Firman etabl. 1925\nunder namn Vetlanda Kristallförädling,\nnuv. namn 1934.\n\nÄgare o. chefer: fabr. Åke Kjellander\no. fabr. Nils Kjellander.\n\n\"A. P. Kjellgrens Brödfabrik AB.,\n\nÖrebro.\n\nTillverkar mjukbröd, skorpor och\nknäckebröd.\n\nTelefon: »Apk». Postgiro: 27907.\nAkt.-kap.: 160,000 kr. Antal\nindustriarb.: 180. Tillv.-värde pr år: 5,370,000 kr.\n\n—\tBolaget grundat 1911.\n\nStyrelse: adv. H. Almer (ordf.), disp.\nErnst Kjellgren, kassör Harald\nKjellgren, verkm. Karl August Kjellgren,\nkamrer Carl-Gustaf Lindström.\nDisp.: Ernst Kjellgren.\n\nKjellströms Mek. Verkstad, Kvänum.\n\nMek. verkstad och tunnplåtslageri i\nKvänum (Skarab. l.).\n\nTillverkar lantbruksmaskiner såsom\nfoderhissar, injektioner, halmfläktar och\ngröpkvarnar. Varunamn: »Kjällve».\n\nTelefon: 25 o. 59. — Antal\nindustriarb.: 45. Tillv.-värde pr år: 950,000 kr.\n–Firman etabl. 1890.\n\nÄgare o. chef: fabr. Sven Kjällström.\nKontorschef: Allan Johansson.\nVerkstadsing.: Arne Ericson.\n\nAB. Klackfabriken, Virserum.\n\nTillverkar träklackar och träsulor för\ndamskodon vid fabrik i Virserum\n(Kalmar l.).\n\nTelegr.-adr.: Klackfabriken, Virserum.\nTelefon: 21. Postgiro: 26744.\n\nAkt.-kap.: 120,000 kr. Antal\nindustriarb.: 35. Tillv.-värde pr år: 325,000 kr.\n\n—\tFirman etabl. 1918, bolag 1944.\nDisp.: Josef Danielson.\n\n*",
    "structured": {
        "1": {
            "name": "Kirudds AB.",
            "location": "Vänersborg",
            "business": "Damkonfektionsfabrik",
            "products": "Tillverkar kappor, dräkter, blazers, pälsar och badkappor.",
            "contact": {
                "phone": [
                    "863",
                    "864"
                ],
                "postgiro": "29009"
            },
            "financials": {
                "capital": "400,000 kr"
            },
            "foundation_year": 1917,
            "current_name_year": 1940,
            "board": [
                {
                    "name": "grossh. Bror Kirudd",
                    "role": "Styrelse o. verkst. dir."
                }
            ]
        },
        "2": {
            "name": "Kiruna Ölbryggeri AB.",
            "location": "Kiruna",
            "business": "Tillverkar maltdrycker, mineralvatten och läskedrycker",
            "contact": {
                "telegraph": "ölbryggeriet, Kiruna",
                "postgiro": "61679"
            },
            "financials": {
                "capital": "100,000 kr"
            },
            "foundation_year": 1905,
            "board": [
                {
                    "name": "arkitekt John Wikberg",
                    "role": "Styrelse"
                },
                {
                    "name": "apot. Erik Georgii",
                    "role": "Styrelse"
                },
                {
                    "name": "Erik Georgii",
                    "role": "Verkst. dir."
                },
                {
                    "name": "bryggm. Karl Erik Sand-t)erg",
                    "role": "Platschef"
                }
            ]
        },
        "3": {
            "name": "Kirurgiska Instrument Fabriks AB.",
            "location": "Stockholm",
            "business": "Finmek. verkstad och instrumentfabrik",
            "products": "Tillverkar kirurgiska instrument i rostfritt stål, operationsmöbler, steriliseringsapparater, elektromedicinska apparater, konstgjorda lemmar, ortopediska bandage, laboratorieartiklar, elektr. centrifuger m. m. Varumärke: »Kifa».",
            "contact": {
                "office": "Regeringsg. 31",
                "telegraph": "Kifa, Stockholm",
                "phone": "Instrument-Kifa",
                "postgiro": "2103"
            },
            "financials": {
                "capital": "550,000 kr"
            },
            "foundation_year": 1911,
            "board": [
                {
                    "name": "med. dr Carl S. Samnuelsson",
                    "role": "Styrelse (ordf.)"
                },
                {
                    "name": "ing. Arvid Bergman",
                    "role": "Styrelse"
                },
                {
                    "name": "dir. Erich Dingel",
                    "role": "Styrelse"
                },
                {
                    "name": "dir. Gustaf V. Ljungberg",
                    "role": "Styrelse"
                },
                {
                    "name": "överläkare Svante Orell",
                    "role": "Styrelse"
                }
            ],
            "director": "Erich Dingel",
            "manager": "Allan Jonson",
            "sales_manager": "Nils Lundgren"
        },
        "4": {
            "name": "AB. Kjells Armaturfabrik",
            "location": "Bäckefors",
            "business": "Tillverkar armatur för gas, vatten och ånga, metallgjutgods samt botten- och mellanventilen »Källan»",
            "contact": {
                "phone": "4",
                "postgiro": "87350"
            },
            "financials": {
                "capital": "120,000 kr"
            },
            "foundation_year": 1918,
            "board": [
                {
                    "name": "dir. Axel Calvert",
                    "role": "Styrelse"
                },
                {
                    "name": "fabr. C. J. Kjell",
                    "role": "Styrelse"
                },
                {
                    "name": "disp. H. Kjell",
                    "role": "Styrelse"
                },
                {
                    "name": "kontorschef K. R. Sahlberg",
                    "role": "Styrelse"
                },
                {
                    "name": "civiling. A. Weilenmann",
                    "role": "Styrelse"
                }
            ],
            "director": "Axel Calvert",
            "sales_manager": "Halfdan Kjell"
        },
        "5": {
            "name": "Kjellander & Co.",
            "location": "Vetlanda",
            "business": "Utför slipning, gravering och annan konstindustrien bearbetning av glas",
            "contact": {
                "phone": "296",
                "postgiro": "88316"
            },
            "foundation_year": 1925,
            "owners": [
                "fabr. Åke Kjellander",
                "fabr. Nils Kjellander"
            ]
        },
        "6": {
            "name": "A. P. Kjellgrens Brödfabrik AB.",
            "location": "Örebro",
            "business": "Tillverkar mjukbröd, skorpor och knäckebröd",
            "contact": {
                "telegraph": "Apk",
                "postgiro": "27907"
            },
            "financials": {
                "capital": "160,000 kr"
            },
            "foundation_year": 1911,
            "board": [
                {
                    "name": "adv. H. Almer",
                    "role": "Styrelse"
                },
                {
                    "name": "disp. Ernst Kjellgren",
                    "role": "Styrelse"
                },
                {
                    "name": "kassör Harald Kjellgren",
                    "role": "Styrelse"
                },
                {
                    "name": "verkm. Karl August Kjellgren",
                    "role": "Styrelse"
                },
                {
                    "name": "kamrer Carl-Gustaf Lindström",
                    "role": "Styrelse"
                }
            ],
            "director": "Ernst Kjellgren"
        },
        "7": {
            "name": "Kjellströms Mek. Verkstad",
            "location": "Kvänum",
            "business": "Mek. verkstad och tunnplåtslageri",
            "products": "Tillverkar lantbruksmaskiner såsom foderhissar, injektioner, halmfläktar och gröpkvarnar. Varunamn: »Kjällve»",
            "contact": {
                "phone": [
                    "25",
                    "59"
                ]
            },
            "foundation_year": 1890,
            "owners": [
                "fabr. Sven Kjällström"
            ]
        },
        "8": {
            "name": "AB. Klackfabriken",
            "location": "Virserum",
            "business": "Tillverkar träklackar och träsulor för damskodon",
            "contact": {
                "phone": "21",
                "postgiro": "26744"
            },
            "financials": {
                "capital": "120,000 kr"
            },
            "foundation_year": 1918,
            "board": [
                {
                    "name": "Josef Danielson",
                    "role": "Disp."
                }
            ]
        }
    }
}