{
    "original": "Löfving—MaacJc\n\narb.: 40. Årstillv.: 2,000 stds trävaror,\nvarav 1,000 stds hyvlade. — Bolaget\ngrundat 1912.\n\nStyrelse: dir. Georg Sjödin (ordf.),\nadv. Gust. Sjödin, dir. Karl Sjödin.\n\nVerJcst. dir.: Karl Sjödin.\n\n*Aug. Löfvings Möbelfabrik, Tibro.\n\nTillverkar sovrums- och enrumsmöbler\nvid fabrik i Tibro (Skarab. l.).\n\nTelefon: 115. Postgiro: 21349. —\nArb.-antal: 16. Tillv.-värde pr år: 300,000 kr.\n— Firman etabl. 1894.\n\nÄgare o. chefer: fabr. Aug. Löfving o.\nfabr. Folke Löfving.\n\nH. Lönnqvist, Osbyverken, Osby.\nSe Osbyverken, H. Lönnqvist, Osby.\n\nLönsboda Träförädling, Pella\nPersson, Lönsboda.\n\nSe AB. Johan Perssons Byggnadsvaror,\nLönsboda.\n\nLörstrands Sågverks AB., Lör strand.\n\nTillverkar stav till silltunnor samt\nsågade trävaror vid sågverk i Lörstrand\n(Gävleb. l.).\n\nTelegr.-adr.: Lörstrandssåg, Lörstrand.\nTelefon: 20. Postgiro: 94970. —\nAkt.-kap.: 51,000 kr. Antal industriarb.: 20.\nÅrstillv.: 500 stds trävaror. — Bolaget\ngrundat 1918.\n\nVerJcst. dir. o. disp.: Eric Jonsson.\n\n* Ernst Löwe &amp; Co., Handels- &amp;\nFabriks AB., Göteborg.\n\nSängklädersfabrik, vadd- och\ntrassel-fabrik. Tillverkar madrasser, kuddar,\ntäcken och sovsäckar, stoppade möbler,\n\nvadd, trassel samt fjäder och dun.\nVarumärke: »Texella». Bolaget driver även\nengroshandel med manufakturvaror och\nstoppningsartiklar.\n\nKontor: Stallmästareg. 5. Telegr.-adr.:\nTextor, Göteborg. Telefon: 159505—06\nPostgiro: 40825.\n\nAkt.-kap.: 100,000 kr. Antal\nindustriarb.: 50. Tillv.-värde pr år: 1,000,000 kr.\n— Firman etabl. 1928, bolag 1931,\nfabriksbolag 1935.\n\nStyrelse o. verJcst. dir.: Ernst Löwe.\n\nDisp.: Gösta Kruse.\n\n* Löv holmens Sågverk o.\nTrä-destillationsverk, Piteå.\n\nSe AB. Statens Skogsindustrier,\nStockholm.\n\nLövträ, Kommanditbolaget,\n\nArTcelstorp.\n\nSe Kommanditbolaget Lövträ, Nils\nElner &amp; Co., Arkelstorp.\n\n*AB. Lövträförädling, Åseda.\n\nSågverk och tunnfabrik i Näsum,\nsågverk i Skäralid (båda i Kristianst. l.)\noch i Ljungbyholm (Kalmar l.), sågverk\ni Skottorp (Hallands l.). Tillverkar\nek-och bokfat, sågade ämnen av lövträ,\nblocksågad ek, träkol m. m.\n\nKontor: Åseda. Telefon: 34. Postgiro:\n84935. — Akt.-kap.: 160,000 kr. Antal\nindustriarb.: 155. Tillv.-värde pr år:\n3,500,000 kr. — Firman etabl. 1906,\nbolag 1920.\n\nStyrelse: disp. Albert Nilsson, disp.\nErnst Nilsson, disp. Gunnar Nilsson.\n\nVerkst. dir.: Ernst Nilsson.\n\nDisponenter: i Näsum: forstm. Torsten\nHallberg; i Ljungbyholm: Gunnar\nNilsson; i Skottorp: Albert Nilsson.\n\nM\n\n* utmärker till Sveriges Industriförbund anslutna företag.\n\nMaack &amp; Wennberg AB.,\n\nSölvesborg.\n\nSkofabrik. Tillverkar arbets- och\nsportlågskor, rem- och snörsandaler,\ntennisskor samt skinntofflor.\n\nTelefon: 10163. Postgiro: 12959. —\nAkt.-kap.: 16,000 kr. Antal industriarb.:\n19. Tillv.-värde pr år: 260,000 kr. —\nFirman etabl. 1935, bolag 1946.\n\nVerJcst. direktörer: fabr. Levi Maack o.\nfabr. Elof Wennberer.\n\n354*",
    "structured": {
        "1": {
            "name": "Löfving—MaacJc",
            "business": "Sågverk och Träförädling",
            "products": "Tillverkar sovrums- och enrumsmöbler, stav till silltunnor, sågade trävaror",
            "location": "Tibro, Skarab. l.",
            "contact": {
                "phone": [
                    "115"
                ],
                "postgiro": "21349"
            },
            "financials": {
                "capital": "Okänt",
                "employees": {
                    "Arb.-antal": 16
                },
                "annual_turnover": "300,000 kr",
                "annual_production_value": "Okänt"
            },
            "foundation_year": 1894,
            "board": [
                {
                    "name": "dir. Georg Sjödin",
                    "role": "ordf."
                },
                {
                    "name": "adv. Gust. Sjödin",
                    "role": "Okänt"
                },
                {
                    "name": "dir. Karl Sjödin",
                    "role": "Okänt"
                }
            ],
            "owners": [
                "fabr. Aug. Löfving",
                "fabr. Folke Löfving"
            ],
            "director": "Karl Sjödin"
        },
        "2": {
            "name": "Lörstrands Sågverks AB.",
            "business": "Sågverk och Träförädling",
            "products": "Tillverkar stav till silltunnor, sågade trävaror",
            "location": "Lörstrand, Gävleb. l.",
            "contact": {
                "office": "Eric Jonsson"
            },
            "financials": {
                "capital": "51,000 kr",
                "employees": {
                    "Antal industriarb.": 20
                },
                "annual_turnover": "Okänt",
                "annual_production_value": "Okänt"
            },
            "foundation_year": 1918
        },
        "3": {
            "name": "Ernst Löwe & Co., Handels- & Fabriks AB.",
            "business": "Sängklädersfabrik och Engroshandel med Manufakturvaror",
            "products": "Tillverkar madrasser, kuddar, täcken, sovsäckar, stoppade möbler, vadd, trassel, fjäder och dun",
            "location": "Göteborg",
            "contact": {
                "office": "Stallmästareg. 5",
                "phone": [
                    "159505-06"
                ],
                "postgiro": "40825"
            },
            "financials": {
                "capital": "100,000 kr",
                "employees": {
                    "Antal industriarb.": 50
                },
                "annual_turnover": "1,000,000 kr",
                "annual_production_value": "Okänt"
            },
            "foundation_year": 1928,
            "current_name_year": 1931,
            "board": [
                {
                    "name": "Ernst Löwe",
                    "role": "Okänt"
                },
                {
                    "name": "Gösta Kruse",
                    "role": "Disp."
                }
            ]
        },
        "4": {
            "name": "Lövträförädling",
            "business": "Sågverk och Tunnsnickerier",
            "products": "Tillverkar ek- och bokfat, sågade ämnen av lövträ, blocksågad ek, träkol m.m.",
            "location": "Näsum, Skäralid, Ljungbyholm, och Skottorp",
            "contact": {
                "factory_office": "Ernst Nilsson",
                "factory_phone": "Okänt"
            },
            "financials": {
                "capital": "160,000 kr",
                "employees": {
                    "Antal industriarb.": 155
                },
                "annual_turnover": "3,500,000 kr",
                "annual_production_value": "Okänt"
            },
            "foundation_year": 1906,
            "corporation_year": 1920,
            "board": [
                {
                    "name": "disp. Albert Nilsson",
                    "role": "Okänt"
                },
                {
                    "name": "disp. Ernst Nilsson",
                    "role": "Okänt"
                },
                {
                    "name": "disp. Gunnar Nilsson",
                    "role": "Okänt"
                }
            ]
        },
        "5": {
            "name": "Maack & Wennberg AB.",
            "business": "Skofabrik",
            "products": "Tillverkar arbets- och sportlågskor, rem- och snörsandaler, tennisskor samt skinntofflor",
            "location": "Sölvesborg",
            "contact": {
                "phone": "10163",
                "postgiro": "12959"
            },
            "financials": {
                "capital": "16,000 kr",
                "employees": {
                    "Antal industriarb.": 19
                },
                "annual_turnover": "260,000 kr",
                "annual_production_value": "Okänt"
            },
            "foundation_year": 1935,
            "corporation_year": 1946,
            "owners": [
                "fabr. Levi Maack",
                "fabr. Elof Wennberg"
            ],
            "manager": "Okänt"
        }
    }
}