{
    "original": "Kristinedal—Kritbrulcsbolaget\n\nAB. Kristinedals Fabriker,\n\nLidköping.\n\nStreich- och kamgarnsspinneri, färgeri\nsamt strumpfabrik. Tillverkar finare och\ngrövre väv- och trikågarner, stick- och\nhemslöjdsgarner samt herr strumpor.\nSpecialiteter: hemslöjdsgarner (märke: »\nMora») o. stickgarner (märke:\n»Höglands-garn»).\n\nTelefon: 20600. Postgiro: 5574. —\nAkt.-kap.: 300,000 kr. Antal industriarb.: 50.\n— Firman etabl. 1840, nuv. bolag 1930.\n\nStyrelse: disp. J. Douglas Keiller\n(ordf.), herr Bertil Gustafson.\n\nDisp.: J. D. Keiller.\n\n* Kristinehamns Bryggeri AB.,\n\nKristinehamn.\n\nTillverkar malt- och läskedrycker.\nTelefon: 15371—72. Postgiro: 31540.\n— Akt.-kap.: 360,000 kr. Arb.-antal: 15.\nTillv.-värde pr år: 500,000 kr. — Bolaget\ngrundat 1906.\n\nStyrelse; kommunalborgm. Stig\nAll-sing, dir. Nils G. Arvedson, disp. Sven\nJansson, disp. John Löfgren, disp. Dan\nWallin.\n\nVerkst. dir.: Sven Jansson (Karlstad).\nDisp.: Dan Wallin.\n\nAB. Kristinehamns Cementgjuter i,\n\nKristinehamn.\n\nByggnadsentreprenörfirma och\nbetong-varufabrik i Kristinehamn (Värml. l.),\nUtför bostads- och industribyggnader,\nbro- och vattenbyggnader m. m. samt\ntillverkar betongrör, kulvertar, vibroblock\nm. m.\n\nTelefon: 15415—15418. Postgiro: 27999.\n— Akt.-kap.: 300,000 kr. Antal\nindustriarb.: 75. — Firman etabl. 1906, bolag\n1945.\n\nStyrelse: fabr. Amandus Jonsson (ordf.),\ning. Gustaf Gudmundson, fabr. Gustav\nKarlsson, kamrer Karl-Axel Sohlberg,\nfabr. Carl Törnkvist.\n\nVerkst. dir.: ing. Gustaf Gudmundson.\n\nKamrer; Karl-Axel Sohlberg.\n\n*AB. Kristinehamns Läske- &amp;\nMaltdrycksfabrik, Kristinehamn.\n\nTillverkar svagdricka.\n\nTelefon: 10125. Postgiro: 263905. —\nAkt.-kap.: 64,000 kr. Arb.-antal: 8.\nTillv.-värde pr år: 110,000 kr. — Firman, etabl.\n1900, bolag 1907, äges av Kristinehamns\nBryggeri AB.\n\nStyrelse: dir. Nils G. Arvedson (ordf.),\ndisp. Sven Jansson, disp. Dan Wallin.\nVerkst. dir.: Sven Jansson (Karlstad).\nBryggeriförest.: Hilding Petterson.\n\n* Kristinehamns Träförädlingsfabrik,\n\nKristinehamn.\n\nSnickerifabrik med hyvleri. Tillverkar\nsågade och hyvlade trävaror,\nmonteringsfärdiga trähus, byggnadssnickerier såsom\ndörrar och fönster (även av svensk\nstandardtyp), paneler och listverk,\ninredningar m. m.\n\nTelefon: 10158 o. 11000. Postgiro:\n28616. — Antal industriarb.: 50.\nTillv.-värde pr år: 900,000 kr. — Firman etabl.\n1895.\n\nÄgare o. chef: disp. Gösta Olsson.\nKamrer: Hugo Ny len.\n\nKristinelunds Angöra-Ullspinneri,\n\nSödra Valbo.\n\nTillverkar angoragarner vid\nullspinneri i Södra Valbo (Gävleb. l.).\n\nKontor: Södra Valbo. Telegr.-adr.:\nKaus, Valbo. Telefon: Valbo 20.\nPostgiro: 173645. Repr. i Stockholm: AB.\nHenning Schale, V. Trädgårdsg. 15,\ntelefon: 111072,\n\nAntal industriarb.: 12. — Firman\netabl. 1941.\n\nÄgare o. chef: fru G. Wahlman.\n\n*V. Kriström, Johannesbergs\nLådfabrik, Stockholm.\n\nSe Johannesbergs Lådfabrik, V.\nKriström, Stockholm.\n\n*AB. Kritbruksbolaget i Malmö,\n\nKvarnby.\n\nBolaget äger f. d. Hörstedts, Hjorths,\nSjöbergs, Murmans, Mathiassons, Per\nOhlssons och Nya Svenskas kritbruk i\nKvarnby (Malmöh. l.). Tillverkar\nslammad krita.\n\nHuvudkontor: Kvarnby. Telegr.-adr.:\nMalmökrita, Malmö. Telefon: Malmö\n490551 o. 490552. Postgiro: 38778.\n\nRepresentanter: i Stockholm: C. M.\nPersson, Nybrokajen 7; i Göteborg: Erik\nRöing, ö. Hamng. 2; i Sundsvall:\nGrug-gels Agenturaffär; i Norrköping: Gust.\nKjellberg AB.\n\nAkt.-kap.: 1,710,000 kr. Antal\nindustriarb.: 65.\n\nBolaget grundades 1914 samt är\nhuvudintressent i AB. Svenska Färg- &amp;\nKrit-verken, Göteborg, och Kvarnby Jordbruks\nAB.",
    "structured": {
        "firms": [
            {
                "name": "Kristinedal—Kritbrulcsbolaget AB. Kristinedals Fabriker",
                "location": "Lidköping",
                "business": "Streich- och kamgarnsspinneri, färgeri samt strumpfabrik",
                "products": "Tillverkar finare och grövre väv- och trikågarner, stick- och hemslöjdsgarner samt herr strumpor. Specialiteter: hemslöjdsgarner (märke: » Mora») o. stickgarner (märke: »Höglands-garn»)",
                "contact": {
                    "office": "Kristinedals Fabriker, Lidköping",
                    "phone": [
                        "20600"
                    ],
                    "postgiro": "5574",
                    "sales_offices": [],
                    "factory_office": "Kristinedals Fabriker, Lidköping"
                },
                "financials": {
                    "capital": "300,000 kr",
                    "employees": {
                        "industriarb": 50
                    },
                    "annual_turnover": "N/A",
                    "annual_production_value": "N/A"
                },
                "foundation_year": 1840,
                "current_name_year": 1930,
                "board": [
                    {
                        "name": "J. Douglas Keiller",
                        "role": "ordf."
                    },
                    {
                        "name": "herr Bertil Gustafson",
                        "role": "N/A"
                    }
                ]
            },
            {
                "name": "* Kristinehamns Bryggeri AB.",
                "location": "Kristinehamn",
                "business": "Tillverkar malt- och läskedrycker",
                "contact": {
                    "phone": [
                        "15371—72"
                    ],
                    "postgiro": "31540"
                },
                "financials": {
                    "capital": "360,000 kr",
                    "employees": {
                        "Arb.-antal": 15
                    },
                    "annual_turnover": "N/A",
                    "annual_production_value": "500,000 kr"
                },
                "foundation_year": 1906,
                "board": [
                    {
                        "name": "kommunalrådm.",
                        "role": "ordf."
                    },
                    {
                        "name": "dir. Nils G. Arvedson",
                        "role": "N/A"
                    },
                    {
                        "name": "disp. Sven Jansson",
                        "role": "N/A"
                    },
                    {
                        "name": "disp. John Löfgren",
                        "role": "N/A"
                    },
                    {
                        "name": "disp. Dan Wallin",
                        "role": "N/A"
                    }
                ]
            },
            {
                "name": "AB. Kristinehamns Cementgjuteri",
                "location": "Kristinehamn",
                "business": "Byggnadsentreprenörfirma och betong-varufabrik",
                "contact": {
                    "phone": [
                        "15415—15418"
                    ],
                    "postgiro": "27999"
                },
                "financials": {
                    "capital": "300,000 kr",
                    "employees": {
                        "industriarb": 75
                    },
                    "annual_turnover": "N/A",
                    "annual_production_value": "N/A"
                },
                "foundation_year": 1906,
                "board": [
                    {
                        "name": "fabr. Amandus Jonsson",
                        "role": "ordf."
                    },
                    {
                        "name": "ing. Gustaf Gudmundson",
                        "role": "N/A"
                    },
                    {
                        "name": "fabr. Gustav Karlsson",
                        "role": "N/A"
                    },
                    {
                        "name": "kamrer Karl-Axel Sohlberg",
                        "role": "N/A"
                    },
                    {
                        "name": "fabr. Carl Törnkvist",
                        "role": "N/A"
                    }
                ]
            },
            {
                "name": "*AB. Kristinehamns Läske- & Maltdrycksfabrik",
                "location": "Kristinehamn",
                "business": "Tillverkar svagdricka",
                "contact": {
                    "phone": [
                        "10125"
                    ],
                    "postgiro": "263905"
                },
                "financials": {
                    "capital": "64,000 kr",
                    "employees": {
                        "Arb.-antal": 8
                    },
                    "annual_turnover": "N/A",
                    "annual_production_value": "110,000 kr"
                },
                "foundation_year": 1900,
                "board": [
                    {
                        "name": "dir. Nils G. Arvedson",
                        "role": "ordf."
                    },
                    {
                        "name": "disp. Sven Jansson",
                        "role": "N/A"
                    },
                    {
                        "name": "disp. Dan Wallin",
                        "role": "N/A"
                    }
                ]
            },
            {
                "name": "Kristinehamns Träförädlingsfabrik",
                "location": "Kristinehamn",
                "business": "Snickerifabrik med hyvleri",
                "contact": {
                    "phone": [
                        "10158 o. 11000"
                    ],
                    "postgiro": "28616"
                },
                "financials": {
                    "employees": {
                        "industriarb": 50
                    },
                    "annual_production_value": "900,000 kr"
                },
                "foundation_year": 1895
            },
            {
                "name": "Kristinelunds Angöra-Ullspinneri",
                "location": "Södra Valbo",
                "business": "Tillverkar angoragarner vid ullspinneri",
                "contact": {
                    "phone": [
                        "Valbo 20"
                    ],
                    "telegraph": "Kaus, Valbo",
                    "postgiro": "173645",
                    "sales_offices": [
                        {
                            "location": "Stockholm",
                            "phone": "111072"
                        }
                    ]
                },
                "financials": {
                    "employees": {
                        "industriarb": 12
                    }
                },
                "foundation_year": 1941,
                "owners": [
                    "fru G. Wahlman"
                ]
            },
            {
                "name": "*V. Kriström, Johannesbergs Lådfabrik",
                "location": "Stockholm",
                "business": "Se Johannesbergs Lådfabrik, V. Kriström, Stockholm"
            },
            {
                "name": "AB. Kritbruksbolaget i Malmö",
                "location": "Kvarnby",
                "business": "Tillverkar slammad krita",
                "contact": {
                    "phone": [
                        "Malmö 490551 o. 490552"
                    ],
                    "postgiro": "38778"
                },
                "financials": {
                    "capital": "1,710,000 kr",
                    "employees": {
                        "industriarb": 65
                    }
                },
                "foundation_year": 1914,
                "owners": [
                    "AB. Svenska Färg- & Krit-verken, Göteborg",
                    "Kvarnby Jordbruks AB"
                ],
                "board": [
                    {
                        "name": "C. M. Persson",
                        "role": "N/A"
                    },
                    {
                        "name": "Erik Röing",
                        "role": "N/A"
                    },
                    {
                        "name": "Gruggels Agenturaffär",
                        "role": "N/A"
                    },
                    {
                        "name": "Gust. Kjellberg AB",
                        "role": "N/A"
                    }
                ]
            }
        ]
    }
}