{
    "original": "Hansson—Harmsen\n\nPostgiro: 4811. — Akt.-kap.: 200,000 kr.\nAntal industriarb.: 40. — Firman etabl.\n1921, bolag 1938.\n\nVerkst. dir.: Sven Hansson.\n\nDisp.: Bertil Hennéus.\n\n* Viktor H anson, Stockholm.\n\nByggnadsentreprenörf irma för\nhusbyggnader.\n\nKontor: Sveavägen 29. Telefon: 115747\no. 116987. Postgiro: 53884. — Firman\netabl. 1914.\n\nÄgare o. chef: byggnadsing. Viktor\nHanson.\n\nAB. Hansy, Ystad.\n\nMek. verkstad. Tillverkar specialartiklar\nför butiksinredningar, industrier m. fl.\nsamt stålmöbler. Varumärke:\n»Hansy-Möbler».\n\nTelefon: 190. Postgiro: 281715 —\nAkt.-kap. :; 10,000 kr. Antal industriarb.: 20.\nTillv.-värde pr år: 200,000 kr. — Firman\netabl. 1929, bolag 1944.\n\nStyrelse: dir. William Raihle (ordf.),\ndisp. Harry Raihle, disp. Ossian Raihle.\n\nVerkst. dir. o. disp.: Ossian Raihle.\n\nReklamchef: Carl Eskil Sjöstedt.\n\nVerkstadschéf: Henry Wahlström.\n\nHanås, Henrik Anderson, Malmö.\n\nKonsthartspresseri. Tillverkar pressade\ndetaljer i konstharts. Specialitet:\ntangent-knappar för skriv- och räknemaskiner.\n\nKontor: Per Weijersgatan 3. Telefon:\n32085. Postgiro: 148353. — Antal\nindustriarb.: 9. Tillv.-värde pr år: 120,000 kr.\n— Firman etabl. 1942.\n\nÄgare o. chef: fabr. Henrik Anderson.\n\n*Happachs Såpfabrik, Malmö.\n\nSe Malmö Oljeslageri &amp; Happachs\nSåpfabriks AB., Malmö.\n\n*Ernst Harbeck AB., Partille.\n\nSe Kemiska Fabriken Dr Ernst\nHarbeck AB., Partille.\n\n*Hardeberga Stenindustri ABLund.\n\nMakadamfabrik i Hardeberga, grustag\ni Stävie, Kinnevad och Sularp (samtl. i\nMalmöh. l.) samt makadamfabrik i\nForserum (Jönköp. l.).\n\nFramställer murbruk och lerbetong,\nmakadam, packsten, filler, stenmjöl, vit\nsingel, stenplattor, råkantsten m. m. för\nträdgårdar etc., kvartsitprodukter för\nstålgjuterier, kopparverk, glasbruk m. fl.\n\nTelefon: 17190. Postgiro: 99501. —\nAkt.-kap.: 200,000 kr. Antal industriarb.:\n120. Prod.-värde pr år: 1,500,000 kr. —\nFirman etabl. 1936.\n\nStyrelse: dir. Ernst Wehtje (ordf.),\ndir. Oscar Ohlson, dir. Fredrik Wehtje,\nryttm. Hugo Wehtje, dir. Walter Wehtje.\n\nVerkst. dir. o. disp.: Oscar Ohlson.\n\n*AB. Harge Bruk, Hammar.\n\nTegelbruk och pulveriseringsverk samt\nkalkstensbrott vid Bastedalen, Hammar\n(Askersund). Tillverkar mur- och\ntaktegel samt dräneringsrör; bryter och\nförmaler kalksten, fältspat, kvarts m. m.\n\nTelegr.-adr.: Harge, Askersund.\nTelefon: Hammar 6. Postgiro: 23914.\n\nAkt.-kap.: 90,000 kr. Antal\nindustriarb.: 70. — Firman etabl. 1880, bolag\n1926.\n\nStyrelse: dir. Oscar Molander (ordf.),\ning. Harald Giöbel, grossh. R. Rylander.\n\nVerkst. dir.; Harald GiöbeL\n\nHargs Bruk, Harg.\n\nSågverk och hyvleri vid Harg\n(Stockholms l.). Tillverkar sågade och hyvlade\nträvaror. Vid bruket drives även\njordbruk och skogshantering.\n\nTelefon: Harg 1. Postgiro: 36653.\nFörsälj, av trävaror: Jacob Versteegh,\nStockholm, Birger Jarlsg. 24, telefon:\n232050.\n\nAntal industriarb.: 80. Årstillv. av\nträvaror: 1,500 stds. — Bruket anlagt på\n1600-talet.\n\nÄgare: frih. Carl Beek-Friis.\n\nSkogschef: jägm. G. Grantinger.\n\n* Hargs Fabrikers AB., Nyköping.\n\nBomullsspinneri, väveri och\nsytrådsfabrik. Tillverkar garn och lakansväv av\nbomull samt sytråd. Varumärke: Gripen.\n\nTelegr.-adr. o. telefon: Hargsbolaget,\nNyköping. Postgiro: 9951.\n\nAkt.-kap.: 500,000 kr. Antal\nindustriarb.: 300. Tillv.-värde pr år: 3,500,000 kr.\n— Bolaget, grundat 1843, är dotterbolag\ntill Stockholms Bomullsspinneri och\nVäfveri AB.\n\nStyrelse: ad v. Emil Heijne (ordf.),\ndisp. Bo Ericsson, disp. Folke Ericsson,\ndir. Sven Ericsson, dir. Torsten Ericsson.\n\nVerkst. dir.: Torsten Ericsson.\n\nAB. Wilh. Harmsen, Stockholm.\n\nMek. verkstad i Spånga (Stockholms\n1.). Tillverkar maskiner för kvarnar,\nbagerier och spannmålsilos, transp^rtanord-",
    "structured": {
        "firms": [
            {
                "name": "Hansson—Harmsen",
                "financials": {
                    "capital": "200,000 kr",
                    "employees": {
                        "industriarb": 40
                    },
                    "foundation_year": 1921,
                    "corporation_year": 1938
                },
                "director": "Sven Hansson"
            },
            {
                "name": "Viktor Hanson",
                "location": "Stockholm",
                "business": "Byggnadsentreprenörfirma för husbyggnader",
                "contact": {
                    "office": "Sveavägen 29",
                    "phone": [
                        "115747",
                        "116987"
                    ],
                    "postgiro": "53884"
                },
                "foundation_year": 1914,
                "director": "Viktor Hanson"
            },
            {
                "name": "AB. Hansy",
                "location": "Ystad",
                "business": "Mek. verkstad. Tillverkar specialartiklar för butiksinredningar, industrier m. fl. samt stålmöbler",
                "products": "Varumärke: Hansy-Möbler",
                "contact": {
                    "phone": "190",
                    "postgiro": "281715"
                },
                "financials": {
                    "capital": "10,000 kr",
                    "employees": {
                        "industriarb": 20
                    },
                    "annual_production_value": "200,000 kr",
                    "foundation_year": 1929,
                    "corporation_year": 1944
                },
                "board": [
                    {
                        "name": "William Raihle",
                        "role": "dir."
                    },
                    {
                        "name": "Harry Raihle",
                        "role": "disp."
                    },
                    {
                        "name": "Ossian Raihle",
                        "role": "disp."
                    }
                ],
                "director": "Ossian Raihle",
                "sales_manager": "Carl Eskil Sjöstedt",
                "manager": "Henry Wahlström"
            },
            {
                "name": "Hanås, Henrik Anderson",
                "location": "Malmö",
                "business": "Konsthartspresseri. Tillverkar pressade detaljer i konstharts. Specialitet: tangent-knappar för skriv- och räknemaskiner",
                "contact": {
                    "office": "Per Weijersgatan 3",
                    "phone": "32085",
                    "postgiro": "148353"
                },
                "financials": {
                    "employees": {
                        "industriarb": 9
                    },
                    "annual_production_value": "120,000 kr",
                    "foundation_year": 1942
                },
                "director": "Henrik Anderson"
            },
            {
                "name": "Harge Bruk",
                "location": "Hammar",
                "business": "Tegelbruk och pulveriseringsverk samt kalkstensbrott. Tillverkar mur- och taktegel samt dräneringsrör; bryter och förmaler kalksten, fältspat, kvarts m. m.",
                "contact": {
                    "telegraph": "Harge, Askersund",
                    "phone": "Hammar 6",
                    "postgiro": "23914"
                },
                "financials": {
                    "capital": "90,000 kr",
                    "employees": {
                        "industriarb": 70
                    },
                    "foundation_year": 1880,
                    "corporation_year": 1926
                },
                "board": [
                    {
                        "name": "Oscar Molander",
                        "role": "dir."
                    },
                    {
                        "name": "Harald Giöbel",
                        "role": "ing."
                    }
                ],
                "director": "Harald Giöbel"
            },
            {
                "name": "Hargs Bruk",
                "location": "Harg",
                "business": "Sågverk och hyvleri. Tillverkar sågade och hyvlade trävaror. Vid bruket drives även jordbruk och skogshantering",
                "contact": {
                    "phone": "Harg 1",
                    "postgiro": "36653"
                },
                "financials": {
                    "employees": {
                        "industriarb": 80
                    }
                },
                "owner": "frih. Carl Beek-Friis",
                "sales_manager": "Jacob Versteegh"
            },
            {
                "name": "Hargs Fabrikers AB.",
                "location": "Nyköping",
                "business": "Bomullsspinneri, väveri och sytrådsfabrik. Tillverkar garn och lakansväv av bomull samt sytråd",
                "products": "Varumärke: Gripen",
                "contact": {
                    "telegraph": "Hargsbolaget, Nyköping",
                    "phone": "Hargsbolaget, Nyköping",
                    "postgiro": "9951"
                },
                "financials": {
                    "capital": "500,000 kr",
                    "employees": {
                        "industriarb": 300
                    },
                    "annual_production_value": "3,500,000 kr"
                },
                "board": [
                    {
                        "name": "Emil Heijne",
                        "role": "ad v."
                    },
                    {
                        "name": "Bo Ericsson",
                        "role": "disp."
                    },
                    {
                        "name": "Folke Ericsson",
                        "role": "disp."
                    },
                    {
                        "name": "Sven Ericsson",
                        "role": "dir."
                    }
                ],
                "director": "Torsten Ericsson"
            },
            {
                "name": "AB. Wilh. Harmsen",
                "location": "Stockholm",
                "business": "Mek. verkstad. Tillverkar maskiner för kvarnar, bagerier och spannmålsilos, transp^rtanord-"
            }
        ]
    }
}