{
    "original": "liössberga—Sala.\n\n\"Rössberga Kalkbruk, V alt ar p.\n\nBe AB. Västergötlands Förenade\nKalk-industrier, Falköping.\n\nÄB. Rötmotaverken, Korsnäs.\n\nFärg- och fernissfabrik i Korsnäs\n(Kopparb. l.). Tillverkar träkonserveringsoljor\noch -färger, asfalt- oeli\nbetongisolerings-mediel, indiistrifärger, kallvattenfärger,\nrostskyddsfärger m. m., fernissor , samt\nfärdigiagad äkta Falu rödfärg. Varumär-\n\nken: »llöt mota», »Fiberol» o. »Falu\nVapen» in. fl.\n\nTelegr.-adr.: Rötmota, Korsnäs*\nTelefon: »Rötmotaverken».\n\nAkt.-kap.: 22,000 kr. Antal\nindustriarb.: 20. — Firman etabl. 1926, bolag\n1931.\n\nStyrelse: dir. FransfBernftröpt,(ff#-)»\nkamrer Folke Bergegård, ing. Olof\nFern-ström.\n\nVerkst. dir.; O. Fernström.\n\nKamrer: F. Bergegård.\n\n* utmärker till Sveriges Industriförbund anslutna företag.\n\n\"Sahlins Konfektions AB., Eslöv.\n\nTillverkar damkappor, dräkter, kjolar,\ngpss- och flickkläder.\n\nTelegr.-adr.: Sahlins. Eslöv. Telefon:\n»Sahlins Konfektion». Postgiro: 84442.\n\nAkt.-kap.: 500,000 kr. Antal\nindustriarb.:.250. Tillv.-värde pr år: 2,200,000 kr.\n\n—\tFirman grundad 1858, bolag 1918.\nStyrelse: doktor Bo Sahlin, fru\nKerstin Sahlin. :■\n\nVerkst. dir.: Bo Sahlin.\n\n\"Sala Maskinfabriks AB., Sala.\n\n’/.Mek. verkstad^ gjuteri och plåtslageri.\nTillverkar maskiner för hus- och\nvägbyggnader, maskiner för sågverk, gruvor,\nanrikningsverk m. m.\n\nTelegr.-adr.: Maskinfabriken, Sala.\nTelefon: 45. Postgiro: 6233. Ensamförsälj.\nför maskiner till byggnads-, och\nsågverksindustrien: Tornborg &amp; Lundberg AB.,\nÅrstadal, Stockholm. Telefon: Tornborg\n&amp; Lundberg.\n\nAkt.-kap.: 300,000 kr. Antal\nindustriarb.: 250. Tillv.-värde pr år: 3,500,000 kr.\n\n—\tÉolaget grundat 1889.\n\nStyrelse: ing. Walter Hesselman, ing.\nEdv, B. Johanson, ing. Gottfrid\nMattsson.\n\nVerkst. dir.: Walter Hesselman. .\nDisp;: Ed v. B. Johanson.\n\n\"Sala Möbelfabriks AB., Stockholm.\n\nTillverkar möbler och inredningar vid\nmöbelfabrik i Sala.\n\nKontor: Stockholm, Strandvägen 7 0.\nTelefon: 621008—09. Postgiro: 2825.\nAkt.-kap.: 50,000 kr; Antal industri-\n\narb.: 20. Tillv.-värde pr år: 150,000 kr.\n— Bolaget grundat 1932 under namn\nDavid Blombergs Verkstads AB., nuv.\nnamn 1941.\n\nStyrelse: arkitekt David Blomberg\n(ordf.), disp. Erik Bergman,\ninredningsarkitekt CUrt Blomberg.\n\nVerkst. dir.: David Blomberg.\n\nVerkstadschef: Erik Bergnian.\n\n\"Sala Silvergruva, Sala.\n\nSe Avesta Jernverks AB., Avesta.\n\n\"Sala Tegelbruks AB., Sala.\n\nTillverkar högporöst murtegel,\nlättmurtegel och taktegel m. m.\n\nTelegr.-adr. o. telefon: Salategel, Sala.\nPostgiro: 8998.\n\nAkt.-kap.: 144,000 kr. Antal\nindustriarb.: 80. Årstillv.: 10 milj. st. tegel, —\nFirman etabl. 1882.\n\nVerkst. dir.: major Curt Camitz.\n\nSala Trävaru AB., Sala.\n\nSågverk och hyvleri. Tillverkar sågade\noch hyvlade trävaror samt listVerk.\n\nTelefon: 468. Postgiro: 82305.. —\nAkt.-kap.: 50,000 kr. Antal iiiduétriarb.: 20.\nTillv.-värde pr år: 700,000 kr. — Bolaget\ngrundat 1929.\n\nVerkst. dir,: Erik C. G. Bolinder.\n\nDisp.: Helmer Wiklander.\n\n\"Sala Ångbryggeri AB., Sala.\n\nTillverkar maltdrycker, mineralvatten\noch läskedrycker.\n\nTelefon: »Ångbryggeriet». Postgriro •\n\n404*",
    "structured": {
        "1": {
            "name": "Rössberga Kalkbruk, V alt ar p. Be AB",
            "location": "Västergötlands Förenade Kalk-industrier, Falköping",
            "business": "Kalkproduktion och tillverkning av färg- och fernissprodukter",
            "contact": {
                "office": "Rötmotaverken, Korsnäs (Kopparb. l.)",
                "phone": [
                    "Rötmotaverken"
                ],
                "telegraph": "Rötmota, Korsnäs",
                "factory_office": "Rötmotaverken, Korsnäs",
                "factory_phone": "Rötmotaverken"
            },
            "financials": {
                "capital": "22,000 kr",
                "employees": {
                    "industriarb": 20
                },
                "annual_turnover": "N/A",
                "annual_production_value": "N/A"
            },
            "foundation_year": 1926,
            "corporation_year": 1931,
            "board": [
                {
                    "name": "FransfBernftröpt",
                    "role": "Direktör"
                },
                {
                    "name": "Folke Bergegård",
                    "role": "Kamrer"
                },
                {
                    "name": "Olof Fern-ström",
                    "role": "Ingenjör"
                }
            ]
        },
        "2": {
            "name": "Sahlins Konfektions AB., Eslöv",
            "location": "Eslöv",
            "business": "Tillverkning av damkappor, dräkter, kjolar, gpss- och flickkläder",
            "contact": {
                "office": "Sahlins. Eslöv",
                "phone": [
                    "Sahlins Konfektion"
                ],
                "postgiro": "84442"
            },
            "financials": {
                "capital": "500,000 kr",
                "employees": {
                    "industriarb": 250
                },
                "annual_turnover": "2,200,000 kr",
                "annual_production_value": "N/A"
            },
            "foundation_year": 1858,
            "corporation_year": 1918,
            "board": [
                {
                    "name": "Bo Sahlin",
                    "role": "Doktor"
                },
                {
                    "name": "Kerstin Sahlin",
                    "role": "N/A"
                }
            ],
            "managing_director": "Bo Sahlin"
        },
        "3": {
            "name": "Sala Maskinfabriks AB., Sala",
            "location": "Sala",
            "business": "Tillverkning av maskiner för hus- och vägbyggnader, sågverk, gruvor, anrikningsverk m. m.",
            "contact": {
                "office": "Maskinfabriken, Sala",
                "phone": [
                    "45"
                ],
                "postgiro": "6233"
            },
            "financials": {
                "capital": "300,000 kr",
                "employees": {
                    "industriarb": 250
                },
                "annual_turnover": "3,500,000 kr",
                "annual_production_value": "N/A"
            },
            "foundation_year": 1889,
            "board": [
                {
                    "name": "Walter Hesselman",
                    "role": "Ingenjör"
                },
                {
                    "name": "Edv, B. Johanson",
                    "role": "Ingenjör"
                },
                {
                    "name": "Gottfrid Mattsson",
                    "role": "N/A"
                }
            ],
            "manager": "Walter Hesselman"
        },
        "4": {
            "name": "Sala Möbelfabriks AB., Stockholm",
            "location": "Stockholm",
            "business": "Tillverkning av möbler och inredningar vid möbelfabrik i Sala",
            "contact": {
                "office": "Stockholm, Strandvägen 7 0",
                "phone": [
                    "621008",
                    "09"
                ],
                "postgiro": "2825"
            },
            "financials": {
                "capital": "50,000 kr",
                "employees": {
                    "industriarb": 20
                },
                "annual_turnover": "150,000 kr",
                "annual_production_value": "N/A"
            },
            "foundation_year": 1932,
            "corporation_year": 1941,
            "board": [
                {
                    "name": "David Blomberg",
                    "role": "Arkitekt"
                },
                {
                    "name": "Erik Bergman",
                    "role": "Designchef"
                },
                {
                    "name": "Curt Blomberg",
                    "role": "Inredningsarkitekt"
                }
            ],
            "managing_director": "David Blomberg"
        },
        "5": {
            "name": "Sala Tegelbruks AB., Sala",
            "location": "Sala",
            "business": "Tillverkning av högporöst murtegel, lättmurtegel och taktegel m. m.",
            "contact": {
                "office": "Salategel, Sala",
                "phone": [
                    "Salategel"
                ],
                "postgiro": "8998"
            },
            "financials": {
                "capital": "144,000 kr",
                "employees": {
                    "industriarb": 80
                },
                "annual_turnover": "N/A",
                "annual_production_value": "10 milj. st. tegel"
            },
            "foundation_year": 1882,
            "board": [
                {
                    "name": "Major Curt Camitz",
                    "role": "N/A"
                }
            ],
            "manager": "Major Curt Camitz"
        },
        "6": {
            "name": "Sala Trävaru AB., Sala",
            "location": "Sala",
            "business": "Sågverk och hyvleri. Tillverkning av sågade och hyvlade trävaror samt listVerk",
            "contact": {
                "phone": [
                    "468"
                ],
                "postgiro": "82305"
            },
            "financials": {
                "capital": "50,000 kr",
                "employees": {
                    "industriarb": 20
                },
                "annual_turnover": "700,000 kr",
                "annual_production_value": "N/A"
            },
            "foundation_year": 1929,
            "manager": "Erik C. G. Bolinder"
        },
        "7": {
            "name": "Sala Ångbryggeri AB., Sala",
            "location": "Sala",
            "business": "Tillverkning av maltdrycker, mineralvatten och läskedrycker",
            "contact": {
                "phone": [
                    "Ångbryggeriet"
                ],
                "postgiro": "404"
            }
        }
    }
}