{
    "original": "Wezätar—Vibro\n\nAkt.-kap.: 50.500 kr. Arb.-antal: 10.\nTillv.-värde pr år: 500.000 kr. — Bolaget\ngrundat 1920.\n\nStyrelse o. verkst. dir.: kapten Gustaf\nSvedberg.\n\n\"Wezäta-Göteborgsiitografen AB.,\n\nGöteborg.\n\nLitografiskt tryckeri, boktryckeri,\nstål-tryckeri, bokbinderi, kliché- och\nretusch-anstalt, reklam- och katalogredaktion.\n\nSpecialiteter: reklamtryck,\nmassupplagor i litografi, offset- och boktryck,\nbroschyrer, industrikataloger, etiketter och\nomslag, tidskriftstryck, blankettryck,\nbrevpapper i alla utföranden, fakturor,\nvärdepapperstryck, klichéer och retuscher.\n\nHuvudkontor: Göteborg, Lasarettsg. 4\n—6. Telegr.-adr.: Wezäta, Göteborg.\nTelefon: »Esselte». Postgiro: 41206.\nAvd.-kontor: Stockholm, Drottningg. 20,\ntelefon: 209698, 104972 o. 118022; Malmö:\nVilla Hill, Bellevuevägen, telefon: 26493.\n\nBolaget bildades 1938 genom\nsammanslagning av Göteborgs Litografiska AB.,\netabl. 1882, och Wald. Zachrissons\nBoktryckeri AB., etabl. 1886. Bolaget är\nanslutet till Esseltes Göteborgsindustrier\nAB., Göteborg. (Se detta bolag.)\n\nStyrelse: dir. Nils J. Åhlund (ordf.),\ndisp. Sam Widenfelt, disp. Bruno\nZach-risson.\n\nVerkst. dir.: Nils J. Åhlund.\n\nDisponenter: Bruno Zachrisson o. Sam\nWidenfelt.\n\nKontorschef: Nils G. Englund.\n\n\"Thure B. Wiberg AB., Malmö.\n\nKonfektionsfabrik. Tillverkar\ndamulst-rar, damdräkter och kappor. Varumärke:\n» Te-Be-We».\n\nKontor: Celsiusg. 31. Telefon: 71875.\nPostgiro: 38087. — Akt.-kap.: 300,000 kr.\nAntal industriarb.: 250. Tillv.-värde pr\når: 3,500,000 kr. — Firman etabl. 1933,\nbolag 1941.\n\nStyrelse o. verkst. dir.: Thure B.\nWiberg.\n\n\"AB. C. M. Wibergs Vagn- &amp;\nRedskapsfabrik, llansta.\n\nMek. verkstad i Ransta (Västmanl. l.).\nTillverkar harvredskap, benkrossar m. m.\nsamt telefon- och kraftledningssmiden\nsåsom reglar för telefonlinjer, bär- och\nspännreglar för högspänningsledningar.\nVarumärke: »W-R».\n\nTelefon: 3. Postgiro: 83900.\n\nAkt.-kap.: 156,200 kr. Antal\nindustriarb.: 40. Tillv.-värde pr år: 1,000,000 kr.\n— Bolaget grundat 1898.\n\nStyrelse: dir. Aug. Kjellén (ordf.), dir.\n\nH.\tBrynge, disp. Birger Wlkerg.\n\nVerkst. dir.: Birger Wiberg.\n\nKamrer: F. Lejdström.\n\nE. A. Wibergs Industrier, Halmstad.\n\nMek. verkstad och stålmöbelfabrik.\nTillverkar stålmöbler, hydrauliska\nfrisörstolar, rostfria inredningar för charkuterier\nm. m., mjölkpallar (märke: »Wiber»)\nsamt stålfönster och -dörrar.\n\nTelefon: 1252 o. 4352. Postgiro: 28782.\n\nAntal industriarb.: 45. Tillv.-värde pr\når: 550,000 kr. — Firman etabl. 1915.\n\nÄgare o. chef: fabr. Erik A. Wiberg.\n\nFörsäljn.-chef: Hilding Sandberg.\n\nInköpschef: Nils Wesström.\n\nAB. Vibohus, Södra Vi.\n\nSågverk, hyvleri och snickerifabrik i\nSödra Vi (Kalmar l.). Tillverkar sågade\noch hyvlade trävaror, järnvägssliprar,\nlådbräder, dörrar och fönster samt\ninredningar.\n\nTelefon: 100. Postgiro: 24524. —\nAkt.-kap.: 30,000 kr. Antal industriarb.: 40.\nTillv.-värde pr år: 450,000 kr. —\nBolaget grundat 1937.\n\nFabrikschef: disp. Simon Hjerpe.\n\n\"AB. Gunnar Wiborg, Vänersborg.\n\nSe Kirudds AB., Vänersborg.\n\n\"AB. Vibro-Verken, Stockholm.\n\nMek. verkstad i Stockholm samt mek.\nverkstad och gjuteri i Ljungby (Kronob-\n\nI.).\tTillverkar vibratorer (varumärke:\n»Vibro») och tillhörande utrustningar för\nbetonggjutningsändamål ävensom för ett\nflertal andra industriella\nanvändningsområden samt verktygsmaskiner, spec.\nkipp-hyvlar (märke: »Malma-Vibro»).\n\nKontor: Luntmakarg. 29. Telegr.-adr.:\nVibro, Stockholm. Telefon: 235430.\nPostgiro: 154690. Repr. i Göteborg för\nbyggnadsfacket: Göteborgs Sand AB.,\nMarie-holmsg. 42, telefon: »Sandbolaget».\n\nAkt.-kap.: 200,000 kr. Antal\nindustriarb.: 120.\n\nBolaget grundades 1940 såsom\ndotterbolag till AB. Vibro-Betong, vars\ntillverkning och försäljning av vibratorer\nm. m. övertogs fr. o. m. 1941.\n\nStyrelse: övering. Donovan Werner\n(ordf.), disp. Ivar Strömberg (v. ordf.),,\ndir. Stig Giertz-Hedström.\n\nVerkst. dir.: Stig Giertz-Hedström.\n\nKamrer: Jonas Hedström.\n\nFörsäljn.-chef: ing. Bengt E.\nWahlberg.\n\nVerkstadschef: disp. Carl G. Lindgren.-\n\n(Jfr annons nr 5.)",
    "structured": {
        "1": {
            "name": "Wezäta-Göteborgsiitografen AB.",
            "location": "Göteborg",
            "business": "Litografiskt tryckeri, boktryckeri, stål-tryckeri, bokbinderi, kliché- och retusch-anstalt, reklam- och katalogredaktion",
            "products": "Reklamtryck, massupplagor i litografi, offset- och boktryck, broschyrer, industrikataloger, etiketter och omslag, tidskriftstryck, blankettryck, brevpapper i alla utföranden, fakturor, värdepapperstryck, klichéer och retuscher",
            "contact": {
                "office": "Göteborg, Lasarettsg. 4—6",
                "phone": [
                    "209698",
                    "104972",
                    "118022"
                ],
                "postgiro": "41206",
                "head_office": "Göteborg, Lasarettsg. 4—6",
                "sales_offices": [
                    {
                        "location": "Stockholm",
                        "phone": "209698, 104972, 118022"
                    },
                    {
                        "location": "Malmö",
                        "phone": "26493"
                    }
                ],
                "telegraph": "Wezäta, Göteborg"
            },
            "financials": {
                "capital": "50.500 kr",
                "employees": {
                    "total": 10
                }
            },
            "foundation_year": 1938,
            "board": [
                {
                    "name": "Nils J. Åhlund",
                    "role": "ordf."
                },
                {
                    "name": "Sam Widenfelt",
                    "role": "disp."
                },
                {
                    "name": "Bruno Zach-risson",
                    "role": "disp."
                }
            ]
        },
        "2": {
            "name": "Thure B. Wiberg AB.",
            "location": "Malmö",
            "business": "Konfektionsfabrik",
            "products": "Damulsterar, damdräkter och kappor",
            "contact": {
                "office": "Celsiusg. 31",
                "phone": "71875",
                "postgiro": "38087"
            },
            "financials": {
                "capital": "300,000 kr",
                "employees": {
                    "total": 250
                }
            },
            "foundation_year": 1933
        },
        "3": {
            "name": "AB. C. M. Wibergs Vagn- &amp; Redskapsfabrik",
            "location": "Ransta",
            "business": "Mek. verkstad",
            "products": "Harvredskap, benkrossar m. m. samt telefon- och kraftledningssmiden såsom reglar för telefonlinjer, bär- och spännreglar för högspänningsledningar",
            "contact": {
                "phone": "3",
                "postgiro": "83900"
            },
            "financials": {
                "capital": "156,200 kr",
                "employees": {
                    "total": 40
                },
                "annual_production_value": "1,000,000 kr"
            },
            "foundation_year": 1898,
            "board": [
                {
                    "name": "Aug. Kjellén",
                    "role": "ordf."
                },
                {
                    "name": "H. Brynge",
                    "role": "dir."
                },
                {
                    "name": "Birger Wlkerg",
                    "role": "disp."
                }
            ]
        },
        "4": {
            "name": "E. A. Wibergs Industrier",
            "location": "Halmstad",
            "business": "Mek. verkstad och stålmöbelfabrik",
            "products": "Stålmöbler, hydrauliska frisörstolar, rostfria inredningar för charkuterier, mjölkpallar samt stålfönster och -dörrar",
            "contact": {
                "phone": "1252, 4352",
                "postgiro": "28782"
            },
            "financials": {
                "employees": {
                    "total": 45
                },
                "annual_production_value": "550,000 kr"
            },
            "foundation_year": 1915,
            "owners": [
                "Erik A. Wiberg"
            ],
            "sales_manager": "Hilding Sandberg",
            "manager": "Nils Wesström"
        },
        "5": {
            "name": "AB. Vibohus",
            "location": "Södra Vi",
            "business": "Sågverk, hyvleri och snickerifabrik",
            "products": "Sågade och hyvlade trävaror, järnvägssliprar, lådbräder, dörrar, fönster och inredningar",
            "contact": {
                "phone": "100",
                "postgiro": "24524"
            },
            "financials": {
                "capital": "30,000 kr",
                "employees": {
                    "total": 40
                },
                "annual_production_value": "450,000 kr"
            },
            "fabrikschef": "disp. Simon Hjerpe"
        },
        "6": {
            "name": "AB. Vibro-Verken",
            "location": "Stockholm",
            "business": "Mek. verkstad och gjuteri",
            "products": "Vibratorer och tillhörande utrustningar för betonggjutningsändamål samt för ett flertal andra industriella användningsområden samt verktygsmaskiner, spec. kipp-hyvlar",
            "contact": {
                "office": "Luntmakarg. 29",
                "phone": "235430",
                "postgiro": "154690"
            },
            "financials": {
                "capital": "200,000 kr",
                "employees": {
                    "total": 120
                }
            },
            "foundation_year": 1940,
            "board": [
                {
                    "name": "Donovan Werner",
                    "role": "övering."
                },
                {
                    "name": "Ivar Strömberg",
                    "role": "disp."
                },
                {
                    "name": "Stig Giertz-Hedström",
                    "role": "dir."
                }
            ],
            "managing_director": "Stig Giertz-Hedström",
            "sales_manager": "ing. Bengt E. Wahlberg"
        }
    }
}