{
    "original": "Ve tlanda—Weyde\n\n\"Vetlanda Ullspinneri AB.,\n\nV etlanda.\n\nUllspinneri, väveri och färgeri i\nSjun-nen, Vetlanda. Tillverkar ullgarn, filtar\noch möbeltyg. Varumärken:\n»Vetlandafilt» o. »Njudungsfilt».\n\nTelegr.-adr. o. telefon:\n»Spinneribolaget», Vetlanda. Postgiro: 24013.\n\nAkt.-kap.: 450,000 kr. Antal\nindustriarb.: 117. — Firman etabl. 1889.\n\nStyrelse: disp. John F. Bergfeldt,\nchefsassist. Johan G. Bergfeldt, mäklare\nH. Biilow, bankkamrer B. Netterbladt,\nhandl. A. Thunborg.\n\nDisp.: John F. Bergfeldt.\n\n\"AB. J. A. Wettergren &amp; Co.,\n\nGöteborg.\n\nKonfektionsfabrik. Tillverkar dam- och\nbackfisehkappor, dräkter samt\npälskappor.\n\nHuvudkontor: Göteborg, Wollins\nTrappor. Telegr.-adr. o. telefon: Wettergrens,\nGöteborg. Postgiro: 7500. Offertkontor:\nOscarsg. 4.\n\nAkt.-kap.: 3,000,000 kr. Antal\nindustriarb.: 660. Tillv.-värde pr år: 12,000,000\nkr. — Firman grundad 1836, bolag 1896.\n\nStyrelse: bankdir. Ebbe Lundberg\n(ordf.), aktuarie Conrad Ankarcrona,\ndir. Fredrik Holm, dir. Thorbjörn Holm,\ndir. Henning Settergren.\n\nVerkst. dir.: Thorbjörn Holm.\nV. verkst. dir.: Fredrik Holm.\nKontorschef: Torsten Lindros.\n\n\"S. A. Wetterlings Manufaktur AB.,\n\nStorvik.\n\nYxfabrik i Storvik (Gävleb. l.).\nTillverkar hand- och huggyxor, timmermans-,\nskogs- och slaktbilor, släggyxor och\nvedkilar m. fl. typer. Varumärken:\n»Vallfors» o. »EX».\n\nTelefon: 22. Postgiro: 36487. —\nAkt.-kap.: 150,000 kr. Antal industriarb.: 30.\nTillv.-värde pr år: 450,000 kr. — Firman\netabl. 1880, bolag 1917.\n\nStyrelse: dir. S. M. Liliebladh (ordf.),\njärnhandl. P. Herman Jonsson, dir.\nGustav J ungefors.\n\nVerkst. dir.: Gustav Jungefors.\nKontorschef: Erik Högström.\n\n\"AB. Wexiö Bayerska Bryggeri,\n\nVäxjö.\n\nTillverkar malt- och läskedrycker.\nTelefon: » Bayerska». Postgiro: 23075.\n-Akt.-kap.: 499,000 kr. Antal\nindustriarb.: 40. Tillv.-värde pr år: 1,500,000 kr.\n\nBryggeriet anlagt 1864, bolag 1905.\nBolaget äger Kronobergs Bryggeri AB.\n\nStyrelse: speditör Hj. Samuelson\n(ordf.), överste C.-O. Agell, bryggmäst.\nG. H:son Peters, disp. Oscar Samuelson.\nVerkst. dir.: major Georg Agell.\n\nWexiö.\n\n\"Wäxjö Elektromek. Verkstad,\n\nVäxjö.\n\nUtför omlindningar, reparationer och\nprovningar av elektr. maskiner och\napparater samt reparerar och laddar\nackumulatorbatterier.\n\nTelefon: 2826. Postgiro: 30249. —\nArb.-antal: 6. Tillv.-värde pr år: 40,000\nkr. — Firman etabl. 1919.\n\nÄgare o. chef: fabr. Kurt A. Sjölin.\n\nWexiö.\n\nAB. Växjö Konfektionsfabrik,\n\nBäppe.\n\nTillverkar barn:, flick- och damkappor\nsamt gossrockar vid fabrik i Räppe\n(Kronob. l.). Varumärke: »Allkapp».\n\nTelefon: Växjö 6090. Postgiro: 285240.\nRepr. i Stockholm: Stig Bollö,\nBran-tingsg. 18, telefon: 673747. — Akt.-kap.:\n100,000 kr. Antal industriarb.: 40.\nTillv.-värde pr år: 500,000 kr. — Bolaget\ngrundat 1944.\n\nVerkst. dir.: Inge Distner (Karlshamn;.\nDisp.: Sune Nyman.\n\nAB. Wexiö Mek. Verkstad, Växjö.\n\nTillverkar charkuteri- och\nlivsmedelsmaskiner samt gjutgods.\n\nTelegr.-adr.: Verkstaden, Växjö.\nTelefon: 1508 o. 2156. Postgiro: 9719.\n\nAkt.-kap.: 400,000 kr. Antal\nindustriarb.: 120. Tillv.-värde pr år: 1,900,000 kr.\n— Bolaget grundat 1911.\n\nStyrelse: dir, K. Leube, dir. J. Schytt,\ndir. H. Thaning.\n\nPlatschef: disp. Johan Schindeler.\n(Jfr annons nr 42.)\n\n\"Weydes Tekn. Fabriks AB.,\n\nNorrköping.\n\nTillverkar såpa, tvål,\ntråddragningsme-del samt kem. tekn. preparat.\nVarumärken: »Flipp» samt »Bosistos»\neucalyp-tusolja o. -tabletter.\n\nTelegr.-adr.: Wetefa, Norrköping.\nTelefon: 29790. Postgiro: 11694.\nAgenturkontor: Stockholm, Drottningg. 102,\ntelefon: 109474.",
    "structured": {
        "firms": [
            {
                "name": "Vetlanda Ullspinneri AB.",
                "location": "Vetlanda",
                "business": "Ullspinneri, väveri och färgeri",
                "products": "Tillverkar ullgarn, filtar och möbeltyg. Varumärken: »Vetlandafilt» o. »Njudungsfilt».",
                "contact": {
                    "office": "Sjunnenn, Vetlanda",
                    "phone": [
                        "Spinneribolaget"
                    ],
                    "postgiro": "24013"
                },
                "financials": {
                    "capital": "450,000 kr",
                    "employees": {
                        "industriarb": 117
                    },
                    "annual_turnover": "Unknown",
                    "annual_production_value": "Unknown"
                },
                "foundation_year": 1889,
                "board": [
                    {
                        "name": "John F. Bergfeldt",
                        "role": "disp."
                    },
                    {
                        "name": "Johan G. Bergfeldt",
                        "role": "chefsassist."
                    },
                    {
                        "name": "H. Biilow",
                        "role": "mäklare"
                    },
                    {
                        "name": "B. Netterbladt",
                        "role": "bankkamrer"
                    },
                    {
                        "name": "A. Thunborg",
                        "role": "handl."
                    }
                ],
                "director": "John F. Bergfeldt"
            },
            {
                "name": "AB. J. A. Wettergren & Co.",
                "location": "Göteborg",
                "business": "Konfektionsfabrik",
                "products": "Tillverkar dam- och backfisehkappor, dräkter samt pälskappor.",
                "contact": {
                    "office": "Wollins Trappor, Göteborg",
                    "phone": [
                        "Wettergrens"
                    ],
                    "postgiro": "7500",
                    "head_office": "Oscarsg. 4"
                },
                "financials": {
                    "capital": "3,000,000 kr",
                    "employees": {
                        "industriarb": 660
                    },
                    "annual_turnover": "12,000,000 kr",
                    "annual_production_value": "Unknown"
                },
                "foundation_year": 1836,
                "board": [
                    {
                        "name": "Ebbe Lundberg",
                        "role": "bankdir."
                    },
                    {
                        "name": "Conrad Ankarcrona",
                        "role": "aktuarie"
                    },
                    {
                        "name": "Fredrik Holm",
                        "role": "dir."
                    },
                    {
                        "name": "Thorbjörn Holm",
                        "role": "dir."
                    },
                    {
                        "name": "Henning Settergren",
                        "role": "dir."
                    }
                ],
                "director": "Thorbjörn Holm",
                "managing_director": "Fredrik Holm",
                "sales_manager": "Torsten Lindros"
            },
            {
                "name": "S. A. Wetterlings Manufaktur AB.",
                "location": "Storvik",
                "business": "Yxfabrik",
                "products": "Tillverkar hand- och huggyxor, timmermans-, skogs- och slaktbilor, släggyxor och vedkilar m. fl. typer. Varumärken: »Vallfors» o. »EX».",
                "contact": {
                    "phone": [
                        "22"
                    ],
                    "postgiro": "36487"
                },
                "financials": {
                    "capital": "150,000 kr",
                    "employees": {
                        "industriarb": 30
                    },
                    "annual_turnover": "450,000 kr",
                    "annual_production_value": "Unknown"
                },
                "foundation_year": 1880,
                "board": [
                    {
                        "name": "S. M. Liliebladh",
                        "role": "dir."
                    },
                    {
                        "name": "P. Herman Jonsson",
                        "role": "järnhandl."
                    },
                    {
                        "name": "Gustav Jungefors",
                        "role": "dir."
                    }
                ],
                "director": "Gustav Jungefors",
                "manager": "Erik Högström"
            },
            {
                "name": "AB. Wexiö Bayerska Bryggeri",
                "location": "Växjö",
                "business": "Bryggeri",
                "products": "Tillverkar malt- och läskedrycker.",
                "contact": {
                    "phone": [
                        " Bayerska"
                    ],
                    "postgiro": "23075"
                },
                "financials": {
                    "capital": "499,000 kr",
                    "employees": {
                        "industriarb": 40
                    },
                    "annual_turnover": "1,500,000 kr",
                    "annual_production_value": "Unknown"
                },
                "foundation_year": 1864,
                "board": [
                    {
                        "name": "Hj. Samuelson",
                        "role": "speditör"
                    },
                    {
                        "name": "C.-O. Agell",
                        "role": "överste"
                    },
                    {
                        "name": "G. H:son Peters",
                        "role": "bryggmäst."
                    },
                    {
                        "name": "Oscar Samuelson",
                        "role": "disp."
                    }
                ],
                "director": "major Georg Agell"
            },
            {
                "name": "Wäxjö Elektromek. Verkstad",
                "location": "Växjö",
                "business": "Elektronikverkstad",
                "products": "Utför omlindningar, reparationer och provningar av elektr. maskiner och apparater samt reparerar och laddar ackumulatorbatterier.",
                "contact": {
                    "phone": [
                        "2826"
                    ],
                    "postgiro": "30249"
                },
                "financials": {
                    "employees": {
                        "arb-antal": 6
                    },
                    "annual_turnover": "40,000 kr",
                    "annual_production_value": "Unknown"
                },
                "foundation_year": 1919,
                "owner": "Kurt A. Sjölin"
            },
            {
                "name": "AB. Växjö Konfektionsfabrik",
                "location": "Bäppe",
                "business": "Konfektionsfabrik",
                "products": "Tillverkar barn-, flick- och damkappor samt gossrockar.",
                "contact": {
                    "phone": [
                        "Växjö 6090"
                    ],
                    "postgiro": "285240",
                    "sales_office": {
                        "location": "Stockholm",
                        "phone": "673747"
                    }
                },
                "financials": {
                    "capital": "100,000 kr",
                    "employees": {
                        "industriarb": 40
                    },
                    "annual_turnover": "500,000 kr",
                    "annual_production_value": "Unknown"
                },
                "owner": "Inge Distner",
                "director": "Sune Nyman"
            },
            {
                "name": "AB. Wexiö Mek. Verkstad",
                "location": "Växjö",
                "business": "Maskintillverkning",
                "products": "Tillverkar charkuteri- och livsmedelsmaskiner samt gjutgods.",
                "contact": {
                    "phone": [
                        "1508",
                        "2156"
                    ],
                    "postgiro": "9719"
                },
                "financials": {
                    "capital": "400,000 kr",
                    "employees": {
                        "industriarb": 120
                    },
                    "annual_turnover": "1,900,000 kr",
                    "annual_production_value": "Unknown"
                },
                "foundation_year": 1911,
                "board": [
                    {
                        "name": "K. Leube",
                        "role": "dir."
                    },
                    {
                        "name": "J. Schytt",
                        "role": "dir."
                    },
                    {
                        "name": "H. Thaning",
                        "role": "dir."
                    }
                ],
                "manager": "Johan Schindeler"
            },
            {
                "name": "Weydes Tekn. Fabriks AB.",
                "location": "Norrköping",
                "business": "Tillverkning av tekniska produkter",
                "products": "Tillverkar såpa, tvål, tråddragningsmedel samt kem. tekn. preparat. Varumärken: »Flipp» samt »Bosistos» eucalyptusolja o. -tabletter.",
                "contact": {
                    "telegraph": "Wetefa, Norrköping",
                    "phone": [
                        "29790"
                    ],
                    "postgiro": "11694",
                    "sales_offices": [
                        {
                            "location": "Stockholm",
                            "phone": "109474"
                        }
                    ]
                }
            }
        ]
    }
}