{
    "original": "Tranås—Tre lleborg\n\nkap.: 47,000 kr. Antal industriarb.: 45.\nTillv.-värde pr år: 225,000 kr. — Firman\netabl.1897, bolag 1932.\n\nDisp.: Knut Frithioff.\n\n*Tranås Väveri AB., Tranås.\n\nUllspinneri, ylleväveri och färgeri.\nTillverkar filtar och vadmal.\n\nTelegr.-adr.: Yllefabriken, Tranås.\nTelefon: 2047 o. 4447. Postgiro: 30726.\n\nAkt.-kap.: 325,000 kr. Antal\nindustriarb.: 55. Tillv.-värde pr år: 600,000 kr.\n\n—\tBolaget grundat 1887.\n\nStyrelse: disp. Ernst Brandel, disp.\nElis Crossner, f. postassist. John\nSvensson.\n\nDisp.: Elis Crossner.\n\nTreco Fabriks- &amp; Handels AB.,\n\nGöteborg.\n\nMadrassfabrik. Tillverkar madrasser,\nmöbler, täckvadd och stoppmateriel.\nVarumärke: »Treco».\n\nKontor: Maj viken, Göteborg.\nTelegr.-adr.: Trecofab, Göteborg. Telefon: 148174.\nPostgiro: 44552.\n\nAkt.-kap.: 40,000 kr. Antal\nindustriarb.: 20. Tillv.-värde pr år: 300,000 kr.\n\n—\tBolaget grundat 1936.\n\nVerkst. dir.: Knut Jenssen.\n\n*Tregeindustri AB., Trekanten.\n\nMöbelfabrik i Trekanten (Kalmar l.).\nTillverkar kompletteringsmöbler.\nSpecialitet : pelarbord.\n\nTelefon: 88. Postgiro: 285566. -\nAkt.-kap.: 15,800 kr. Antal industriarb.: 10.\nTillv.-värde pr år: 100,000 kr. — Bolaget\ngrundat 1945.\n\nStyrelse: disp. Alf Älgne (ordf.),\nsnickare Arnold Älgne, fabr. Harald Älgne.\n\nDisp.: Alf Älgne.\n\n*Trehörningsjö Såg &amp; Hyvleri,\n\nTrehörningsjö.\n\nTillverkar sågade och hyvlade trävaror\nsamt träull vid sågverk, hyvleri och\nträ-ullfabrik i Trehörningsjö ( Västernorrl. l.).\n\nTelegr.-adr.: Trehörningsåg,\nTrehörningsjö. Telefon: 54. Postgiro: 64450.\n\nAntal industriarb.: 12. Årstillv.: 500\nstds trävaror, 600 ton träull. — Firman\netabl. 1943.\n\nÄgare: disp. Hjalmar Näslund o.\nstads-förm. Jonas Stenman.\n\nDisp.: Hjalmar Näslund.\n\n*Tre Kronor, Kvarn AB., Stockholm.\n\nSe Kvarn AB. Tre Kronor, Stockholm.\n\n*AB. Tre Lejon, Göteborg.\n\nElektr. valskvarn. Tillverkar mjöl.\n\nHuvudkontor: Kvarnholmen,\nStockholm. Telefon: »Kooperativa».\nFabrikskontor: Göteborg. Telegr.-adr.: Kvarnen,\nGöteborg. Telefon: »Kooperativa».\n\nAkt.-kap.: 3,500,000 kr. Antal\nindustriarb.: 135. Prod.-värde pr år: 15,000,000\nkr. — Bolaget, grundat 1925, äges av\nKooperativa Förbundet.\n\nStyrelse: dir. Albin Johansson (ordf.),\nfil. lic. Mauritz Bonow, dir. Hj.\nDeger-stedt, dir. Hugo Edstam, dir. G. Osvald,\ndir. Ernst Persson.\n\nKvarnchef: dir. Emil Hamring.\n\nDisp.: Nils Göransson.\n\nTrelleborgs Bryggeri AB.,\n\nTrelleborg.\n\nTillverkar malt, maltdrycker,\nläskedrycker samt konstgjord is.\n\nTelefon: 78 o. 378. Postgiro: 77075.\n\nAkt.-kap.: 360,000 kr. Antal\nindustriarb.: 20. Tillv.-värde pr år: 700,000 kr.\n— Bolaget grundat 1894.\n\nStyrelse: borgm. C. J. Reventberg\n(ordf.), dir. Erik Malmquist, grossh.\nErnst Rickard, disp. Ernst Thidholm.\n\nVerkst. dir.: Ernst Thidholm.\n\nTrelleborgs Glasindustri, Joh. Kock,\n\nTrelleborg.\n\nTillverkar hushållsglas av soda- och\nkristallglas, emballageglas såsom konserv-,\nhonungs- och syltburkar, karamellburkar,\nskyltglas, medicin- och kem.-tekn. glas,\nbuteljer samt isoleringsflaskor.\n\nTelegr.-adr.: Glasindustri, Trelleborg.\nTelefon: 496 o. 1418. Postgiro: .29760.\nRepr. i Stockholm: G. Ad. Ringheim, S:t\nEriksg. 75, telefon: 302333.\n\nAntal industriarb.: 185. Tillv.-värde pr\når: 1,900,000 kr. — Firman etabl. 1919.\n\nÄgare: Greta och Johan Kocks\nstiftelser.\n\nKamrer: Wilh. Eborn.\n\nTrelleborgs Cummifabriks AB.,\n\nTrelleborg.\n\nTillverkar automobil- och\nvelocipedringar, ringar för flygplan och\nskottkärrehjul, massivringar, ebonit, bakelit,\nregnkappor och gummivävnader,\nskyddskläder av gummerad väv, tekn.\ngummivaror såsom remmar, slangar,\ntransportband, valsar för pappersmaskiner,\npackningar m. m. samt gummisulor och\ngummimattor m. m.\n\nTelegr.-adr. o. telefon: Gummifabriken,\nTrelleborg. Postgiro: 20700.",
    "structured": {
        "firms": [
            {
                "name": "Tranås Väveri AB.",
                "location": "Tranås",
                "products": "Ullspinneri, ylleväveri och färgeri. Tillverkar filtar och vadmal.",
                "contact": {
                    "office": "Tranås",
                    "phone": [
                        "2047",
                        "4447"
                    ],
                    "postgiro": "30726",
                    "telegraph": "Yllefabriken, Tranås"
                },
                "financials": {
                    "capital": "325,000 kr",
                    "employees": {
                        "industriarb": 55
                    },
                    "annual_turnover": "600,000 kr"
                },
                "foundation_year": 1897,
                "board": [
                    {
                        "name": "Ernst Brandel",
                        "role": "disp."
                    },
                    {
                        "name": "Elis Crossner",
                        "role": "disp."
                    },
                    {
                        "name": "John Svensson",
                        "role": "f. postassist."
                    }
                ],
                "manager": "Knut Frithioff"
            },
            {
                "name": "Treco Fabriks- & Handels AB.,",
                "location": "Göteborg",
                "products": "Madrassfabrik. Tillverkar madrasser, möbler, täckvadd och stoppmateriel. Varumärke: »Treco».",
                "contact": {
                    "office": "Majviken, Göteborg",
                    "phone": [
                        "148174"
                    ],
                    "postgiro": "44552",
                    "telegraph": "Trecofab, Göteborg"
                },
                "financials": {
                    "capital": "40,000 kr",
                    "employees": {
                        "industriarb": 20
                    },
                    "annual_turnover": "300,000 kr"
                },
                "foundation_year": 1936,
                "director": "Knut Jenssen"
            },
            {
                "name": "Tregeindustri AB.,",
                "location": "Trekanten (Kalmar l.)",
                "products": "Möbelfabrik i Trekanten. Tillverkar kompletteringsmöbler. Specialitet: pelarbord.",
                "contact": {
                    "phone": "88",
                    "postgiro": "285566"
                },
                "financials": {
                    "capital": "15,800 kr",
                    "employees": {
                        "industriarb": 10
                    },
                    "annual_turnover": "100,000 kr"
                },
                "foundation_year": 1945,
                "board": [
                    {
                        "name": "Alf Älgne",
                        "role": "ordf."
                    },
                    {
                        "name": "Arnold Älgne",
                        "role": "snickare"
                    },
                    {
                        "name": "Harald Älgne",
                        "role": "fabr."
                    }
                ],
                "manager": "Alf Älgne"
            },
            {
                "name": "Trehörningsjö Såg & Hyvleri,",
                "location": "Trehörningsjö (Västernorrland l.)",
                "products": "Tillverkar sågade och hyvlade trävaror samt träull vid sågverk, hyvleri och trä-ullfabrik.",
                "contact": {
                    "telegraph": "Trehörningsåg, Trehörningsjö",
                    "phone": "54",
                    "postgiro": "64450"
                },
                "financials": {
                    "employees": {
                        "industriarb": 12
                    },
                    "annual_production_value": "500 stds trävaror, 600 ton träull"
                },
                "foundation_year": 1943,
                "board": [
                    {
                        "name": "Hjalmar Näslund",
                        "role": "disp."
                    },
                    {
                        "name": "Jonas Stenman",
                        "role": "stads-förm."
                    }
                ],
                "manager": "Hjalmar Näslund"
            },
            {
                "name": "AB. Tre Lejon,",
                "location": "Göteborg",
                "products": "Elektr. valskvarn. Tillverkar mjöl.",
                "contact": {
                    "main_office": "Kvarnholmen, Stockholm",
                    "office": "Göteborg",
                    "phone": [
                        "Kooperativa"
                    ],
                    "postgiro": "N/A",
                    "telegraph": "Kvarnen, Göteborg"
                },
                "financials": {
                    "capital": "3,500,000 kr",
                    "employees": {
                        "industriarb": 135
                    },
                    "annual_production_value": "15,000,000 kr"
                },
                "corporation_year": 1925,
                "owners": [
                    "Kooperativa Förbundet"
                ],
                "board": [
                    {
                        "name": "Albin Johansson",
                        "role": "dir."
                    },
                    {
                        "name": "Mauritz Bonow",
                        "role": "fil. lic."
                    },
                    {
                        "name": "Hj. Degerstedt",
                        "role": "dir."
                    },
                    {
                        "name": "Hugo Edstam",
                        "role": "dir."
                    },
                    {
                        "name": "G. Osvald",
                        "role": "dir."
                    },
                    {
                        "name": "Ernst Persson",
                        "role": "dir."
                    }
                ],
                "manager": "Nils Göransson"
            },
            {
                "name": "Trelleborgs Bryggeri AB.,",
                "location": "Trelleborg",
                "products": "Tillverkar malt, maltdrycker, läskedrycker samt konstgjord is.",
                "contact": {
                    "phone": [
                        "78",
                        "378"
                    ],
                    "postgiro": "77075"
                },
                "financials": {
                    "capital": "360,000 kr",
                    "employees": {
                        "industriarb": 20
                    },
                    "annual_turnover": "700,000 kr"
                },
                "foundation_year": 1894,
                "board": [
                    {
                        "name": "C. J. Reventberg",
                        "role": "borgm. (ordf.)"
                    },
                    {
                        "name": "Erik Malmquist",
                        "role": "dir."
                    },
                    {
                        "name": "Ernst Rickard",
                        "role": "grossh."
                    },
                    {
                        "name": "Ernst Thidholm",
                        "role": "disp."
                    }
                ],
                "manager": "Ernst Thidholm"
            },
            {
                "name": "Trelleborgs Glasindustri, Joh. Kock,",
                "location": "Trelleborg",
                "products": "Tillverkar hushållsglas av soda- och kristallglas, emballageglas samt isoleringsflaskor.",
                "contact": {
                    "telegraph": "Glasindustri, Trelleborg",
                    "phone": [
                        "496",
                        "1418"
                    ],
                    "postgiro": "29760",
                    "representative": "Stockholm: G. Ad. Ringheim, S:t Eriksg. 75, telefon: 302333"
                },
                "financials": {
                    "employees": {
                        "industriarb": 185
                    },
                    "annual_turnover": "1,900,000 kr"
                },
                "foundation_year": 1919,
                "owners": [
                    "Greta och Johan Kocks stiftelser"
                ],
                "director": "Wilh. Eborn"
            },
            {
                "name": "Trelleborgs Cummifabriks AB.,",
                "location": "Trelleborg",
                "products": "Tillverkar automobil- och velocipedringar, gummivävnader, tekn. gummivaror samt gummisulor och gummimattor.",
                "contact": {
                    "telegraph": "Gummifabriken, Trelleborg",
                    "phone": "N/A",
                    "postgiro": "20700"
                }
            }
        ]
    }
}