{
    "original": "Bofors—Bohman\n\nKrutbruk och kem. industri.\nTillverkar nitrocellulosa, nitroglycerinkrut\n(»Nobelkrut»), nitrocellulosakrut, trotyl,\ntetryl, pen ty 1, dynamit och\nsäkerhets-sprängämnen, tändmedel och\nammunition, lacknitrocellulosa samt kem. och\nfarm. prod. såsom eter, kollodium,\nklora-min, sackarin, anilin, acetanilid,\nacetyl-salicylsyra m. m. (se tillv.-register).\n\nTelegr.-adr.: Nobelkrut, Bofors.\nTelefon: »Bofors», Karlskoga.\n\nAkt.-kap.: 33,000,000 kr. Antal\nindustriarb.: 5,800. Tillv.-värde pr år:\n105,000,000 kr.\n\nJärnverket anlades i mitten av\n1600-talet, övertogs år 1873 av AB.\nBofors-Gullspång; nuvarande namn och\nbolagsordning 1919. Bolaget har år 1935 i sig\nupptagit f. d. AB. Bofors Nobelkrut,\ngrundat 1898.\n\nStyrelse: konteramiral Erik Wetter\n(ordf.), dir. Einar Glimstedt, fil. dr\nSigurd Nauckhoff, dir. Gust. J. Sahlin,\ndisp. Evert Wijkander.\n\nVerkst. dir.: Evert Wijkander.\n\nVice verkst. dir.: Sverre R:son\nSohl-man.\n\nJärnverket o. mek.\nverkstäderna:\n\nArtilleridir.: kapten O. Linden.\n\nTeknisk chef: dir. A. Wahlsteen.\n\nEkonomichef: kamrer H. Nordqvist.\n\nFörsäljn.-chef för järn o. stål:\nbergsing. P. Odelberg.\n\nInköpschef: civiling. H. Kignell.\n\nKrutbruket o. kem.\nfabrikerna:\n\nChef: dir. Sverre R:son Sohiman.\n\nTekn. chef: övering. Arvid H.\nWahl-quist.\n\nFörsäljn.-chef: övering. J. E. Jullander.\n\nInköpschef: civiling. H. Kignell.\n\n(Jfr annons nr 73.)\n\n*AB. Bofors Nobel krut, Bofors.\n\nSe AB. Bofors, Bofors.\n\n*S. Bogeryds Möbelfabrik, Tibro.\n\nTillverkar matsalsmöbler vid fabrik i\nTibro (Skarab. l.).\n\nTelefon: 248. ^ Postgiro: 174874. —\n\nAntal industriarb.: 15. — Firman\netabl. 1934 under namn Samuel\nJohansson, Möbelfabrik, nuv. namn 1945.\n\nÄgare o. chef: fabr. S. Bogeryd.\n\n* Bogesunds Väveri AB.,\n\nUlricehamn.\n\nTillverkar möbel- och draperityger\nsamt ottomanöver kast.\n\nTelegr.-adr.: Bogesundväveri, Ulrice-\n\nhamn. Telefon: 9 o. 929. Postgiro: 91455.\n\n—\tAkt.-kap.: 200,000 kr. Antal\nindustriarb.: 50. Tillv.-värde pr år: 1,000,000 kr.\n\n—\tBolaget grundat 1934.\n\nStyrelse: ing. Hans Philipp (ordf.),\ndisp. Gunnar Gardell, stadsfogde Per\nLarsson-Edfeldt.\n\nVerkst. dir.: Hans Philipp.\n\n*Alb. Bohlin &amp; C:os AB., Göteborg.\n\nMössfabrik. Tillverkar alla slag av\nmössor. Varumärke: »N. P. U.»\n\nKontor: Stampg. 60. Telegr.-adr.:\nBohlinco, Göteborg. Telefon: 151106 o.\n151133. Postgiro: 40710. Repr. i\nStockholm: Knut Rencrantz, Tegnérg. 18,\ntelefon: 315029.\n\nAkt.-kap.: 50,000 kr. Antal\nindustriarb.: 35. Tillv.-värde pr år: 500,000 kr.\n\n—\tFirman etabl. 1894, nuv. bolag bildat\n1925.\n\nStyrelse: dir. Oscar Berndtson, verkm.\nBror W. Hansson.\n\nVerkst. dir.: Oscar Berndtson.\n\nEinar Bohms Modellfabrik,\n\nKristinehamn.\n\nTillverkar gjuterimodeller.\n\nTelefon: 10776. Postgiro: 36167. —\nAntal industriarb.: 40. Tillv.-värde pr år:\n260,000 kr. — Firman etabl. 1918.\n\nÄgare o. chef: ing. Einar Bohm.\n\nBohman, Boman.\n\n*AB. Bohmans Fanérfabrik,\n\nOskarshamn.\n\nFanérfabrik och sågverk. Tillverkar\nfaner. Bolaget driver jämväl handel med\nutländska träslag.\n\nTelegr.-adr.: Fanérbohman,\nOskarshamn. Telefon: 444 o. 34. Postgiro:\n133675. — Akt.-kap.: 150,000 kr. Antal\nindustriarb.: 30. — Bolaget grundat 1930.\n\nStyrelse: konsul Axel Bohman (ordf.),\nfru Beda Bohman, försäljn.-chef Oscar\nFahlén.\n\nVerkst. dir.: Axel Bohman.\n\nFörsäljn.-chef: Oscar Fahlén.\n\n*AB. Bohman &amp; Johansson,\n\nBlomstermäla.\n\nFanérfabrik och sågverk i\nBlomster-måla (Kalmar l.). Tillverkar faner,\nparkettstav och möbelämnen. Firman driver\näven handel med utländska träslag.\n\nTelegr.-adr.: Fanérfabriken, Blomster-",
    "structured": {
        "1": {
            "name": "AB. Bofors Nobel Krut",
            "business": "Krutbruk och kem. industri",
            "products": "Tillverkar nitrocellulosa, nitroglycerinkrut (»Nobelkrut»), nitrocellulosakrut, trotyl, tetryl, pen ty 1, dynamit och säkerhets-sprängämnen, tändmedel och ammunition, lacknitrocellulosa samt kem. och farm. prod. såsom eter, kollodium, klora-min, sackarin, anilin, acetanilid, acetyl-salicylsyra m. m.",
            "contact": {
                "telegraph": "Nobelkrut, Bofors",
                "phone": [
                    "Bofors, Karlskoga"
                ]
            },
            "financials": {
                "capital": "33,000,000 kr",
                "employees": {
                    "industriarb": 5800
                },
                "annual_turnover": "105,000,000 kr",
                "annual_production_value": "105,000,000 kr"
            },
            "foundation_year": 1873,
            "current_name_year": 1919,
            "predecessor": "f. d. AB. Bofors Nobelkrut, grundat 1898",
            "board": [
                {
                    "name": "konteramiral Erik Wetter",
                    "role": "ordf."
                },
                {
                    "name": "dir. Einar Glimstedt",
                    "role": null
                },
                {
                    "name": "fil. dr Sigurd Nauckhoff",
                    "role": null
                },
                {
                    "name": "dir. Gust. J. Sahlin",
                    "role": "disp."
                },
                {
                    "name": "Evert Wijkander",
                    "role": "disp."
                }
            ],
            "owners": [],
            "director": "Evert Wijkander",
            "managing_director": "Evert Wijkander",
            "sales_manager": "Sverre R:son Sohlman",
            "manager": null
        },
        "2": {
            "name": "S. Bogeryds Möbelfabrik",
            "location": "Tibro",
            "business": "Tillverkar matsalsmöbler"
        },
        "3": {
            "name": "Bogesunds Väveri AB",
            "location": "Ulricehamn",
            "business": "Tillverkar möbel- och draperityger samt ottomanöver kast",
            "contact": {
                "telegraph": "Bogesundväveri, Ulricehamn",
                "phone": [
                    "9",
                    "929"
                ]
            },
            "financials": {
                "capital": "200,000 kr",
                "employees": {
                    "industriarb": 50
                },
                "annual_turnover": "1,000,000 kr",
                "annual_production_value": "1,000,000 kr"
            },
            "foundation_year": 1934
        },
        "4": {
            "name": "Alb. Bohlin & C:os AB",
            "location": "Göteborg",
            "business": "Mössfabrik",
            "products": "Tillverkar alla slag av mössor",
            "contact": {
                "office": "Stampg. 60",
                "telegraph": "Bohlinco, Göteborg",
                "phone": [
                    "151106",
                    "151133"
                ]
            },
            "financials": {
                "capital": "50,000 kr",
                "employees": {
                    "industriarb": 35
                },
                "annual_turnover": "500,000 kr"
            },
            "foundation_year": 1894,
            "corporation_year": 1925
        },
        "5": {
            "name": "Einar Bohms Modellfabrik",
            "location": "Kristinehamn",
            "business": "Tillverkar gjuterimodeller",
            "contact": {
                "phone": [
                    "10776"
                ],
                "postgiro": "36167"
            },
            "financials": {
                "employees": {
                    "industriarb": 40
                },
                "annual_production_value": "260,000 kr"
            },
            "foundation_year": 1918
        },
        "6": {
            "name": "AB. Bohmans Fanérfabrik",
            "location": "Oskarshamn",
            "business": "Fanérfabrik och sågverk",
            "products": "Tillverkar faner. Bolaget driver jämväl handel med utländska träslag",
            "contact": {
                "telegraph": "Fanérbohman, Oskarshamn",
                "phone": [
                    "444",
                    "34"
                ],
                "postgiro": "133675"
            },
            "financials": {
                "capital": "150,000 kr",
                "employees": {
                    "industriarb": 30
                }
            },
            "foundation_year": 1930,
            "board": [
                {
                    "name": "konsul Axel Bohman",
                    "role": "ordf."
                },
                {
                    "name": "fru Beda Bohman",
                    "role": null
                },
                {
                    "name": "Oscar Fahlén",
                    "role": "försäljn.-chef"
                }
            ],
            "director": "Axel Bohman",
            "sales_manager": "Oscar Fahlén"
        },
        "7": {
            "name": "AB. Bohman & Johansson",
            "location": "Blomstermåla",
            "business": "Fanérfabrik och sågverk",
            "products": "Tillverkar faner, parkettstav och möbelämnen. Firman driver även handel med utländska träslag",
            "contact": {
                "telegraph": "Fanérfabriken, Blomster-"
            },
            "financials": {
                "employees": {
                    "industriarb": 30
                }
            },
            "foundation_year": 1934
        }
    }
}