{
    "original": "Arb o ga—A rist o\n\nAkt.-kap.: 712,500 kr. Antal\nindustriarb.: 205. Tillv.-värde pr år: 3,200,000 kr.\n\n—\tFirman etabl. 1856, bolag 1888.\nStyrelse: f. bankdir. Gust. Ekman\n\n(ordf.), dir. Lars Y. Blume, disp. Per G.\nEkman, dir. Assar Grönwall, dir. Sven\nG. Lind.\n\nVerkst. dir.: Per G. Ekman.\nKamrer: Ragnar Birath.\nÖvering.: Erik Sandberg.\nFörsäljn.-chef: Eugen G. Strömberg.\nRitkontorschef: Helge O. Olsson.\nInköpschef: Henry Becker.\n\nArboga Tegelbruk, P. 0. Gustafsson,\n\nArboga.\n\nTillverkar mur- och taktegel samt\ndräneringsrör.\n\nTelefon: 60. Postgiro: 85145. — Antal\nindustriarb.: 20. Årstillv.: 2 milj. st.\nte-gelvaror.\n\nÄgare o. chef: disp. Per Ossian\nGustafsson.\n\n*Arbrå Verkstads AB., Arbrå.\n\nMek. verkstad och gjuteri i Arbrå\n(Gävleb. l.). Tillverkar krossar för sten\noch andra material, sorterverk, elevatorer,\nbandtransportörer, släpskrapspel,\nlastan-ordn., snöplogar, väghyvlar, vägsladdar,\nvattenturbiner och regulatorer,\nmaskingods för sågverk, cellulosa- och\nwallboard-fabriker, plåtarbeten samt gjutgods.\n\nTelegr.-adr.: Arbråverkstad, Arbrå.\nTelefon: Arbrå 33 o. 113. Postgiro: 90350.\n\n—\tAkt.-kap.: 100,000 kr. Antal\nindustriarb.: 175. Tillv.-värde pr år: 3,500,000 kr.\n\n—\tFirman grundad 1902, nuv. bolag 1922.\nStyrelse: övering. Thorild C. Folin\n\n(ordf.), ing. And. R. Bremmer,\nkommu-nalnämndsordf. Jonas Hanson.\nVerkst. dir.: And. R. Bremmer.\nOffert- o. inköpschef: ing. Per\nSter-ning.\n\nKonstruktionschef o. chefsassist.:\ncivil-ing. G. Bremmer.\n\nVerkstadsing.: Lars Anbo.\nKamrer: K. öhrn.\n(Jfr annons nr 74.)\n\n*AB. Area Regulatorer, Stockholm.\n\nMek. verkstad. Tillverkar hydrauliska\noch elektriska regulatorer för hållande av\nkonstant ångtryck, gastryck, lufttryck,\nvattentryck, temperatur, fuktighetshalt,\nelektr. spänning etc. Varumärke: »Area».\n\nKontor: Kungsg. 7 B. Telegr.-adr.:\nArea, Stockholm. Telefon: 117231 o.\n117232. Postgiro: 3611.\n\nAkt.-kap.: 750,000 kr. Antal\nindustriarb.: 15. Tillv.-värde pr år: 400,000 kr.\n\n—\tBolaget grundat 1918.\n\nStyrelse: ad v. H. W. Dahlin (ordf.),\ning. Börje Carlstedt, ing. Ragnar\nCarl-stedt.\n\nVerkst. dir.: Ragnar Carlstedt.\n*AB. Archimedes, Stockholm.\n\nMek. verkstad och motorfabrik i\nSundbyberg. Tillverkar utombordsmotorer.\n\nFörsäljn.-kontor: Stockholm, S:t\nEriksg. 63. Telegr.-adr.: Archimedes,\nStockholm. Telefon: 522000. Postgiro:\n2521. Utställningslokal: Stockholm,\nBirger Jarlsg. 15, telefon: 234345.\nFabrikskontor: Sundbyberg, telefon: Stockholm\n282520.\n\nAkt.-kap.: 750,000 kr. Antal\nindustriarb.: 140. — Bolaget, grundat 1907,\ntillhör Elektrolux-koncernen.\n\nStyrelse: dir. Gust. J. Sahlin (ordf.),\ndir. Axel O. Engberg, dir. Sten Widell.\n\nFörsäljn.-chef: Harry Eriksson.\n\nVerkstads chef: övering. Erik Engdahl.\n\n*AB. Arctic, Motala.\n\nSe AB. Elektrolux, Stockholm.\n\n*AB. Cerh. Arehns Mek. Verkstad,\n\nStockholm.\n\nSe Arenco AB., Stockholm.\n\n*Arenco AB., Stockholm.\n\nMek. verkstad. Tillverkar maskiner\nför tobaks- och tändsticksindustrierna,\npacknings- och vägningsmaskiner,\ntub-och burkfyllningsmaskiner,\nfiskrens-ningsmaskiner, verktygsmaskiner såsom\nlångfräsmaskiner, vertikala grov- och\nfin-borrverk, radialborrmaskiner,\nrundslip-maskiner samt drivväxlar för\nverktygsmaskiner. Varumärken: »Arenco» o.\n»Formator».\n\nKontor: Alströmerg. 20. Telegr.-adr.:\nArenco, Stockholm. Telefon: 520020.\nPostgiro: 1647.\n\nAkt.-kap.: 3,600,000 kr. Antal\nindustriarb.: 700. Tillv.-värde pr år: 10,000,000 kr.\n\nFirman etabl. 1880, bolag 1896 under\nnamn AB. Gerh. Arehns Mek. Verkstad,\nnuv. namn 1943.\n\nStyrelse: dir. Axel Brandin (ordf.),\ning. Ruben Dahlström, ing. Gunnar\nEkström, ing. Ernst v. Segebaden.\n\nVerkst. dir.: Gunnar Ekström.\n\nDisp.: Ernst v. Segebaden.\n\nVerkstadschef: ing. Wilh. Engström.\n\n(Jfr annons nr 15.)\n\nAB. Aristo, Falköping.\n\nReseffektfabrik. Tillverkar reseffekter\nav läder och konstläder, varubackar samt\n\n25*",
    "structured": {
        "1": {
            "name": "Arboga Tegelbruk, P. 0. Gustafsson, Arboga",
            "business": "Manufacturing",
            "products": "Produces bricks and drainage pipes.",
            "contact": {
                "office": "P. 0. Gustafsson, Arboga",
                "phone": [
                    "60"
                ],
                "postgiro": "85145"
            },
            "financials": {
                "capital": "712,500 kr",
                "employees": {
                    "industriarb": 205
                },
                "annual_turnover": "3,200,000 kr"
            },
            "foundation_year": 1856,
            "corporation_year": 1888,
            "board": [
                {
                    "name": "Gust. Ekman",
                    "role": "Chairman of the Board"
                },
                {
                    "name": "Lars Y. Blume",
                    "role": "Director"
                },
                {
                    "name": "Per G. Ekman",
                    "role": "Managing Director"
                },
                {
                    "name": "Assar Grönwall",
                    "role": "Director"
                },
                {
                    "name": "Sven G. Lind",
                    "role": "Director"
                }
            ],
            "owners": [
                "P. 0. Gustafsson, Arboga"
            ]
        },
        "2": {
            "name": "AB. Area Regulatorer, Stockholm",
            "business": "Manufacturing",
            "products": "Produces hydraulic and electrical regulators for maintaining constant pressure and temperature.",
            "contact": {
                "office": "Kungsg. 7 B, Stockholm",
                "phone": [
                    "117231",
                    "117232"
                ],
                "postgiro": "3611"
            },
            "financials": {
                "capital": "750,000 kr",
                "employees": {
                    "industriarb": 15
                },
                "annual_turnover": "400,000 kr"
            },
            "corporation_year": 1918,
            "board": [
                {
                    "name": "H. W. Dahlin",
                    "role": "Chairman of the Board"
                },
                {
                    "name": "Börje Carlstedt",
                    "role": "Director"
                },
                {
                    "name": "Ragnar Carlstedt",
                    "role": "Director"
                }
            ]
        },
        "3": {
            "name": "AB. Archimedes, Stockholm",
            "business": "Manufacturing",
            "products": "Manufactures outboard motors.",
            "contact": {
                "office": "Sundbyberg, Stockholm",
                "phone": [
                    "522000"
                ],
                "postgiro": "2521",
                "factory_office": "Stockholm 282520"
            },
            "financials": {
                "capital": "750,000 kr",
                "employees": {
                    "industriarb": 140
                }
            },
            "corporation_year": 1907,
            "board": [
                {
                    "name": "Gust. J. Sahlin",
                    "role": "Chairman of the Board"
                },
                {
                    "name": "Axel O. Engberg",
                    "role": "Director"
                },
                {
                    "name": "Sten Widell",
                    "role": "Director"
                }
            ]
        },
        "4": {
            "name": "AB. Arctic, Motala",
            "predecessor": "AB. Elektrolux, Stockholm"
        },
        "5": {
            "name": "AB. Cerh. Arehns Mek. Verkstad, Stockholm",
            "predecessor": "Arenco AB., Stockholm"
        },
        "6": {
            "name": "Arenco AB., Stockholm",
            "business": "Manufacturing",
            "products": "Manufactures various machines for industries.",
            "contact": {
                "office": "Alströmerg. 20, Stockholm",
                "phone": [
                    "520020"
                ],
                "postgiro": "1647"
            },
            "financials": {
                "capital": "3,600,000 kr",
                "employees": {
                    "industriarb": 700
                },
                "annual_turnover": "10,000,000 kr"
            },
            "foundation_year": 1880,
            "corporation_year": 1896,
            "current_name_year": 1943,
            "board": [
                {
                    "name": "Axel Brandin",
                    "role": "Chairman of the Board"
                },
                {
                    "name": "Ruben Dahlström",
                    "role": "Director"
                },
                {
                    "name": "Gunnar Ekström",
                    "role": "Director"
                },
                {
                    "name": "Ernst v. Segebaden",
                    "role": "Director"
                }
            ]
        },
        "7": {
            "name": "AB. Aristo, Falköping",
            "business": "Manufacturing",
            "products": "Produces leather and synthetic leather travel goods and containers."
        }
    }
}