{
    "original": "Nyström\n\n*AB. Nyströms Snickerifabrik,\n\nKristianstad.\n\nTillverkar byggnadssnickerier såsom\nfönster, dörrar, inredningar, trappor m.\nm. vid fabrik i Everöd, Kristianstad.\n\nTelefon: 11556. — Akt.-kap.: 40,000\nkr. Antal industriarb.: 15. Tillv.-värde\npr år: 150,000 kr. — Bolaget grundat\n1944.\n\nStyrelse: byggm. Einar Nyström\n(ordf.), kassör Gudrun Lund.\n\nVerkst. dir.: Einar Nyström.\n\n*AB. C. C. Nyström &amp; Go., Solna.\n\nChokladfabrik i Hagalund, Solna\n(Sthlms l.). Tillverkar choklad och\nkon-fektyrer samt fruktmos. Varumärke:\n»Nyco».\n\nTelegr.-adr.: Nyco, Stockholm. Telefon:\nStockholm 272221. Postgiro: 3683.\n\nAkt.-kap.: 100,000 kr. Antal\nindustriarb.: 50. Tillv.-värde pr år: 1,360,000 kr.\n\nFirman etabl. 1917, bolag 1923.\nDotterbolag: AB. Nyco, Stockholm, och AB.\nAdeceka, Hagalund.\n\nStyrelse o. verkst. dir.: C. G. Nyström.\n\n*F. O. Nyströms Bieckkärisfabrik AB.,\n\nTorshälla.\n\nBleckvarufabrik och smidesverkstad.\nTillverkar emballage av bleckplåt, blank\noch dekorerad, samt av svart och\ngalvani-serad järnplåt såsom burkar, flaskor,\ndunkar och cisterner för färger, oljor,\nfernissor m. m., pressade och svetsade\ntunnplåtsarbeten, askar, lådor o. d.,\nfläskkor gar, självreglerande vilstolar (»Park»),\nregnmätare (»Pluvius»), dokumentskrin,\nbadrums- och toalettskåp, bränsle- och\noljebehållare m. m.\n\nTelefon: Eskilstuna 55031 o. 55231.\nPostgiro: 23827. Representant i\nStockholm: Ernst Sahlberg, Mäster Samuelsg.\n27, telefon: 112570.\n\nAkt.-kap.: 150,000 kr. Antal\nindustriarb.: 36. Tillv.-värde pr år: 620,000 kr.\n— Firman etabl. 1874, bolag 1937.\n\nStyrelse: fru S. Nyström (ordf.), disp.\nErland Anderson, köpm. Ernst V.\nJansson.\n\nVerkst. dir.: fru S. Nyström.\n\nDisp.: Erland Anderson.\n\nVerkstadsing.: Gösta Holmqvist.\n\n\"C. Nyströms Karosserifabrik,\n\nUmeå.\n\nTillverkar bilkarosserier,\nbärgningsverktyg för lastbilar samt fjädrande\nrörstolar. Specialitet: 3-mans lastbilshytter.\n\nTelefon: 203 o. 2331. Postgiro: 63312.\n\n—\tAntal industriarb.: 40. Tillv.-värde pr\når: 1,700,000 kr. — Firman etabl. 1935.\n\nÄgare o. chef: fabr. Gösta Nyström.\n\nAB. Ivar Nyström, Borås.\n\nKnappfabrik. Tillverkar knappar och\nspännen av konsthorn för damkonfektion.\n\nTelegr.-adr.: Knappmode, Borås.\nTelefon: 48070. Postgiro: 37259.\n\nAkt.-kap.: 30,000 kr. Arb.-antal: 12.\nTillv.-värde pr år: 120,000 kr. — Firman\netabl. 1929, bolag 1939.\nStyrelse o. verkst. dir.: Ivar Nyström.\n\nJ. Nyströms Metallfabrik, Gnosjö.\n\nTillverkar byggnadsbeslag vid fabrik i\nGnosjö (Jönköp. l.).\n\nTelefon: 142. Postgiro: 73773. —\nAntal industriarb.: 30. — Firman etabl.\n1929.\n\nÄgare o. chef: fabr. Justus Nyström.\n\n*AB. J. P. Nyströms Orgel- &amp;\nPianofabrik, Karlstad.\n\nTillverkar flyglar, pianon och orglar.\nVarumärken: »Apollo» o. »Kabinett».\n\nTelegr.-adr.: Pianoorgel, Karlstad.\nTelefon: 10020 o. 12646. Postgiro: 74850.\n\nAkt.-kap.: 100,000 kr. Antal\nindustriarb.: 100. Tillv.-värde pr år: 1,000,000 kr.\n\n—\tFirman etabl. 1865, bolag 1901.\nStyrelse: konsul Boo Nyström (ordf.),\n\ndir. George Lindahl, fru Anna Nyström,\ndisp. Sören Nyström, konsul Curt\nWennberg.\n\nVerkst. dir.: Boo Nyström.\n\nAB. Rud. Nyströms &amp; Co.,\n\nStockholm.\n\nMek. verkstäder i Örebro och\nStockholm. Tillverkar maskiner för sko- och.\nreseffektfabriker samt tygskärmaskiner\nför sömnadsindustrien. Varunamn:\n»Ru-no». Bolaget driver även handel med\nmaskiner av utländsk tillverkning samt med\ngarvämnen och garvextrakter.\n\nKontor : Stockholm, St. Nygatan 10—12.\nTelegr.-adr.: Rudnycomp, Stockholm.\nTelefon: 231040. Postgiro: 4878.\nAvd.-kon-tor: Malmö, Borås och Örebro.\n\nAkt.-kap.: 165,000 kr. Antal\nindustriarb.: 40. — Bolaget grundat 1929.\n\nStyrelse: dir. Helge Arvidson (ordf.),\nadv. Axel Nilsson, dir. Rudolf Nyström.\nVerkst. dir.: Rudolf Nyström.\nKamrer: Filip Nilsson.\nDisponenter: i Örebro: Åke Elfdahl; i\nStockholm.- Åke Forsberg.",
    "structured": {
        "1": {
            "name": "AB. Nyströms Snickerifabrik",
            "location": "Kristianstad",
            "business": "Tillverkar byggnadssnickerier",
            "products": "fönster, dörrar, inredningar, trappor m.m.",
            "contact": {
                "office": "Fabrik i Everöd, Kristianstad",
                "phone": [
                    "11556"
                ],
                "postgiro": null,
                "head_office": null,
                "sales_offices": null,
                "telegraph": null,
                "factory_office": null,
                "factory_phone": null
            },
            "financials": {
                "capital": "40,000 kr",
                "employees": {
                    "industriarb": 15
                },
                "annual_turnover": "150,000 kr",
                "annual_production_value": null
            },
            "foundation_year": 1944,
            "current_name_year": null,
            "predecessor": null,
            "original_name": null,
            "corporation_year": null,
            "board": [
                {
                    "name": "Einar Nyström",
                    "role": "byggm."
                },
                {
                    "name": "Gudrun Lund",
                    "role": "kassör"
                }
            ],
            "owners": null,
            "director": null,
            "managing_director": "Einar Nyström",
            "sales_manager": null,
            "manager": null
        },
        "2": {
            "name": "AB. C. C. Nyström & Go.",
            "location": "Solna",
            "business": "Chokladfabrik",
            "products": "choklad, konfektyrer, fruktmos",
            "contact": {
                "office": "Hagalund, Solna (Sthlms l.)",
                "phone": [
                    "Stockholm 272221"
                ],
                "postgiro": "3683",
                "head_office": null,
                "sales_offices": [
                    {
                        "location": "Stockholm",
                        "phone": "112570"
                    }
                ],
                "telegraph": "Nyco, Stockholm",
                "factory_office": null,
                "factory_phone": null
            },
            "financials": {
                "capital": "100,000 kr",
                "employees": {
                    "industriarb": 50
                },
                "annual_turnover": "1,360,000 kr",
                "annual_production_value": null
            },
            "foundation_year": 1917,
            "current_name_year": 1923,
            "predecessor": null,
            "original_name": null,
            "corporation_year": null,
            "board": [
                {
                    "name": "C. G. Nyström",
                    "role": "verkst. dir."
                }
            ],
            "owners": null,
            "director": null,
            "managing_director": null,
            "sales_manager": null,
            "manager": null
        },
        "3": {
            "name": "F. O. Nyströms Bieckkärisfabrik AB.",
            "location": "Torshälla",
            "business": "Bleckvarufabrik",
            "products": "emballage av bleckplåt, svart och galvaniserad järnplåt, pressade och svetsade tunnplåtsarbeten, askar, lådor, fläskkorgar, vilstolar, regnmätare, dokumentskrin, badrums- och toalettskåp, bränsle- och oljebehållare",
            "contact": {
                "office": null,
                "phone": [
                    "Eskilstuna 55031",
                    "55231"
                ],
                "postgiro": "23827",
                "head_office": null,
                "sales_offices": [
                    {
                        "location": "Stockholm",
                        "phone": null
                    }
                ],
                "telegraph": null,
                "factory_office": null,
                "factory_phone": null
            },
            "financials": {
                "capital": "150,000 kr",
                "employees": {
                    "industriarb": 36
                },
                "annual_turnover": "620,000 kr",
                "annual_production_value": null
            },
            "foundation_year": 1874,
            "current_name_year": 1937,
            "predecessor": null,
            "original_name": null,
            "corporation_year": null,
            "board": [
                {
                    "name": "fru S. Nyström",
                    "role": "ordf."
                },
                {
                    "name": "Erland Anderson",
                    "role": "disp."
                },
                {
                    "name": "Ernst V. Jansson",
                    "role": "köpm."
                }
            ],
            "owners": null,
            "director": null,
            "managing_director": null,
            "sales_manager": null,
            "manager": null
        },
        "4": {
            "name": "C. Nyströms Karosserifabrik",
            "location": "Umeå",
            "business": "Tillverkar bilkarosserier, bärgningsverktyg för lastbilar samt fjädrande rörstolar",
            "products": "3-mans lastbilshytter",
            "contact": {
                "office": null,
                "phone": [
                    "203",
                    "2331"
                ],
                "postgiro": "63312",
                "head_office": null,
                "sales_offices": null,
                "telegraph": null,
                "factory_office": null,
                "factory_phone": null
            },
            "financials": {
                "capital": null,
                "employees": {
                    "industriarb": 40
                },
                "annual_turnover": "1,700,000 kr",
                "annual_production_value": null
            },
            "foundation_year": 1935,
            "current_name_year": null,
            "predecessor": null,
            "original_name": null,
            "corporation_year": null,
            "board": null,
            "owners": null,
            "director": null,
            "managing_director": "fabr. Gösta Nyström",
            "sales_manager": null,
            "manager": null
        },
        "5": {
            "name": "AB. Ivar Nyström",
            "location": "Borås",
            "business": "Knappfabrik",
            "products": "knappar och spännen av konsthorn för damkonfektion",
            "contact": {
                "office": null,
                "phone": [
                    "48070"
                ],
                "postgiro": "37259",
                "head_office": null,
                "sales_offices": null,
                "telegraph": "Knappmode, Borås",
                "factory_office": null,
                "factory_phone": null
            },
            "financials": {
                "capital": "30,000 kr",
                "employees": {
                    "industriarb": 12
                },
                "annual_turnover": "120,000 kr",
                "annual_production_value": null
            },
            "foundation_year": 1929,
            "current_name_year": 1939,
            "predecessor": null,
            "original_name": null,
            "corporation_year": null,
            "board": [
                {
                    "name": "Ivar Nyström",
                    "role": "verkst. dir."
                }
            ],
            "owners": null,
            "director": null,
            "managing_director": null,
            "sales_manager": null,
            "manager": null
        },
        "6": {
            "name": "J. Nyströms Metallfabrik",
            "location": "Gnosjö",
            "business": "Tillverkar byggnadsbeslag",
            "products": null,
            "contact": {
                "office": "Gnosjö (Jönköp. l.)",
                "phone": [
                    "142"
                ],
                "postgiro": "73773",
                "head_office": null,
                "sales_offices": null,
                "telegraph": null,
                "factory_office": null,
                "factory_phone": null
            },
            "financials": {
                "capital": null,
                "employees": {
                    "industriarb": 30
                },
                "annual_turnover": null,
                "annual_production_value": null
            },
            "foundation_year": 1929,
            "current_name_year": null,
            "predecessor": null,
            "original_name": null,
            "corporation_year": null,
            "board": null,
            "owners": null,
            "director": null,
            "managing_director": "fabr. Justus Nyström",
            "sales_manager": null,
            "manager": null
        },
        "7": {
            "name": "AB. J. P. Nyströms Orgel & Pianofabrik",
            "location": "Karlstad",
            "business": "Tillverkar flyglar, pianon och orglar",
            "products": null,
            "contact": {
                "office": null,
                "phone": [
                    "10020",
                    "12646"
                ],
                "postgiro": "74850",
                "head_office": null,
                "sales_offices": null,
                "telegraph": "Pianoorgel, Karlstad",
                "factory_office": null,
                "factory_phone": null
            },
            "financials": {
                "capital": "100,000 kr",
                "employees": {
                    "industriarb": 100
                },
                "annual_turnover": "1,000,000 kr",
                "annual_production_value": null
            },
            "foundation_year": 1865,
            "current_name_year": 1901,
            "predecessor": null,
            "original_name": null,
            "corporation_year": null,
            "board": [
                {
                    "name": "konsul Boo Nyström",
                    "role": "ordf."
                },
                {
                    "name": "fru Anna Nyström",
                    "role": null
                },
                {
                    "name": "disp. Sören Nyström",
                    "role": null
                },
                {
                    "name": "konsul Curt Wennberg",
                    "role": null
                }
            ],
            "owners": null,
            "director": null,
            "managing_director": "Boo Nyström",
            "sales_manager": null,
            "manager": null
        },
        "8": {
            "name": "AB. Rud. Nyströms & Co.",
            "location": "Stockholm",
            "business": "Mek. verkstäder",
            "products": "maskiner för sko- och reseffektfabriker, tygskärmaskiner, handel med maskiner av utländsk tillverkning, garvämnen och garvextrakter",
            "contact": {
                "office": "Örebro och Stockholm",
                "phone": [
                    "231040"
                ],
                "postgiro": "4878",
                "head_office": "Stockholm, St. Nygatan 10—12",
                "sales_offices": [
                    {
                        "location": "Malmö",
                        "phone": null
                    },
                    {
                        "location": "Borås",
                        "phone": null
                    },
                    {
                        "location": "Örebro",
                        "phone": null
                    }
                ],
                "telegraph": "Rudnycomp, Stockholm",
                "factory_office": null,
                "factory_phone": null
            },
            "financials": {
                "capital": "165,000 kr",
                "employees": {
                    "industriarb": 40
                },
                "annual_turnover": null,
                "annual_production_value": null
            },
            "foundation_year": null,
            "current_name_year": null,
            "predecessor": null,
            "original_name": null,
            "corporation_year": 1929,
            "board": [
                {
                    "name": "dir. Helge Arvidson",
                    "role": "ordf."
                },
                {
                    "name": "adv. Axel Nilsson",
                    "role": null
                },
                {
                    "name": "dir. Rudolf Nyström",
                    "role": null
                }
            ],
            "owners": null,
            "director": null,
            "managing_director": "Rudolf Nyström",
            "sales_manager": null,
            "manager": null
        }
    }
}