{
    "original": "Borgström—Borås\n\n*Lars Borgström, Malmö.\n\nByggnadsentreprenörfirma för\nbostads-och affärshus, industribyggnader m. m.\n\nKontor: Fersens väg 10 B. Telefon:\n29649. Postgiro: 149566. — Prod.-värde\npr år: 1,500,000 kr. — Firman etabl.\n1980.\n\nÄgare o. chef: byggm. Lars Borgström.\n\nBorgviks AB., Borgviksbruk.\n\nSnickerifabrik, kvarn med grynverk\nsamt elektr. kraftstation vid\nBorgviksbruk, såg och kvarn i Brunsberg,\nävensom kvarn i östra Malsjö (samtl. i\nVärml. l.).\n\nTillverkar byggnadssnickerier och\nträtuber. Bolaget driver jämväl jordbruk\noch skogshantering.\n\nHuvudkontor: Säffle. Avd.-kontor:\nBorgviksbruk. Telefon: Borgviksbruk 9\no. 20. Postgiro: 85080. — Akt.-kap.:\n1,550,000 kr. Antal industriarb.: 20.\n\nBruket anlagt på 1600-talet; nuv. bolag,\ngrundat 1863, äges av Billeruds AB.,\nSäffle.\n\nStyrelse: disp. Chr. Storjohann (ordf.),\ndir. H. Dyster1-Aas, dir. E. A.\nVerm-crantz.\n\nVerkst. dir.: Chr. Storjohann.\n\nV. verkst. dir.: H. Dyster-Aas.\n\nBruks för v al t.: S. Hedström.\n\nKassör: Oscar Johansson.\n\nAB. Borohus, Stockholm.\n\nSågverk, snickeri- och trähusfabriker i\nLandsbro och Sävsjö (båda i Jönköp. l.).\nTillverkar monteringsfärdiga bostadshus\n(Boro-hus) samt byggnadssnickerier.\n\nHuvudkontor: Stockholm, Flemingg.\n41, telefon: »HSB». Postgiro: 151460.\nFabrikskontor: Landsbro; telefon:\n»Bo-rohus».\n\nAkt.-kap.: 1,000,000 kr. Antal\nindustriarb.: 300. Tillv.-värde pr år: 8,800,000 kr.\n\nBolaget, grundat 1936, äges av\nHyresgästernas Sparkasse- &amp;\nByggnadsföreningars Riksförbund u. p. a. (HSB).\n\nStyrelse: ombudsm. Fritjof Ekman\n(ordf.), folkskollärare Anders\nAndréas-son, ombudsm. Oskar F. Bengtsson,\narkitekt Sven Wallander, byggm. Hugo Åberg.\n\nVerkst. dir.: Sven Wallander.\n\nV. verkst. dir.: Bertil Adolfsson.\n\nFabrikschef: disp. Ingvar Lindberg.\n\n(Jfr annons nr 3.)\n\n*Bors Bobinfabrik, J. Bolander &amp; Co.,\n\nBor.\n\nBobinfabrik i Bor (Jönköp. l.).\nTillverkar trådrullar och tvättklämmor.\n\nTelegr.-adr.: Bobbins, Bor. Telefon:\n20. — Antal industriarb.: 35. Tillv.-värde\npr år: 250,000 kr. — Firman etabl. 1919.\n\nÄgare: fabr. Janne Bolander o. fabr.\nDavid Bauréus.\n\nChef: Janne Bolander.\n\n*Borstbinderibolagets Fabriks AB.,\n\nVinslöv.\n\nTillverkar tandborstar, hår-,\nklädes-och rotborstar, piassavakvastar m. m. vid\nfabrik i Vinslöv (Kristianst. l.).\n\nTelefon: 99. Postgiro: 30440.\nEnsam-försälj.: Stockholms Borstbinderi AB.,\nStockholm, Stureg. 4, telefon: 679085.\n\nAkt.-kap.: 100,000 kr. Antal\nindustriarb.: 80. Tillv.-värde pr år: 800,000 kr.\n— Fabriken anlagd 1924, bolag 1935.\nBolaget är dotterbolag till Stockholms\nBorstbinderi AB.\n\nStyrelse: dir. Bengt Ahlberg (ordf.),\nfru Sally Ahlberg, disp. Sven Anderson.\n\nVerkst. dir.: Bengt Ahlberg.\n\nDisp.: Sven Anderson.\n\n*AB. Borst- &amp; Penselfabriken,\n\nKristinehamn.\n\nTillverkar alla slags borstar och\npenslar, även för industriella ändamål.\n\nTelegr.-adr.: Borstbolaget,\nKristinehamn. Telefon: 10288, 10370. Postgiro:\n28800. Försäljn.-kontor: Stockholm,\nPäl-sundsg. 1 A, telefon: 415809.\n\nAkt.-kap.: 36,000 kr. Antal\nindustriarb.: 100. — Bolaget grundat 1910.\n\nStyrelse: fabr. K. A. Fredholm, fabr.\nO. W. Pettersson, fabr. K. J. Sundqvist,\nf. d. bankdir. Carl Thor.\n\nVerkst. dir.: Carl Thor.\n\n*AB. Borås Appreturmedelfabrik,\n\nBorås.\n\nTillverkar preparat för textilindustrien\nsåsom textiloljor, nättjemedel,\ntextiltvål-och tvättmedel, bykoljor,\negaliseringsme-del, appreturmedel samt preparat för\nskinnberederier och läderindustrier vid\nfabrik i Källbäcksryd, Borås.\n\nTelefon: Borås 48140 o. 48141.\nPostgiro: 33468. Repr.: AB. Nils Holmberg,\nHalmstad, telefon: 1044.\n\nAkt.-kap.: 50,000 kr. Arb.-antal: 6. —\nFirman etabl. 1900, bolag 1929.\n\nStyrelse: ing. Oskar Billig (ordf.), ing.\nGustaf A. Billig.\n\nVerkst. dir.: O. Billig. ,\n\nDriftsing.: G. A. Billig.",
    "structured": {
        "1": {
            "name": "Borgström—Borås",
            "location": "Malmö",
            "business": "Byggnadsentreprenörfirma för bostads-och affärshus, industribyggnader m. m.",
            "contact": {
                "office": "Fersens väg 10 B",
                "phone": [
                    "29649"
                ],
                "postgiro": "149566"
            },
            "financials": {
                "capital": "1,500,000 kr",
                "annual_production_value": "1,500,000 kr"
            },
            "foundation_year": 1980,
            "manager": "Lars Borgström"
        },
        "2": {
            "name": "Borgviks AB., Borgviksbruk",
            "business": "Snickerifabrik, kvarn med grynverk samt elektr. kraftstation vid Borgviksbruk, såg och kvarn i Brunsberg, ävensom kvarn i östra Malsjö",
            "location": "Säffle",
            "contact": {
                "phone": [
                    "Borgviksbruk 9",
                    "Borgviksbruk 20"
                ],
                "postgiro": "85080"
            },
            "financials": {
                "capital": "1,550,000 kr",
                "employees": {
                    "industriarb": 20
                }
            },
            "foundation_year": "1863",
            "owners": "Billeruds AB."
        },
        "3": {
            "name": "AB. Borohus, Stockholm",
            "business": "Sågverk, snickeri- och trähusfabriker",
            "location": "Stockholm",
            "contact": {
                "phone": "»HSB»",
                "postgiro": "151460"
            },
            "financials": {
                "capital": "1,000,000 kr",
                "employees": {
                    "industriarb": 300
                },
                "annual_turnover": "8,800,000 kr"
            },
            "foundation_year": 1936,
            "owners": "Hyresgästernas Sparkasse- & Byggnadsföreningars Riksförbund u.p.a. (HSB)"
        },
        "4": {
            "name": "Bors Bobinfabrik, J. Bolander & Co.",
            "business": "Bobinfabrik",
            "location": "Bor",
            "contact": {
                "phone": "20"
            },
            "financials": {
                "employees": {
                    "industriarb": 35
                },
                "annual_production_value": "250,000 kr"
            },
            "foundation_year": 1919,
            "owners": [
                "fabr. Janne Bolander",
                "fabr. David Bauréus"
            ],
            "manager": "Janne Bolander"
        },
        "5": {
            "name": "Borstbinderibolagets Fabriks AB., Vinslöv",
            "business": "Tillverkar tandborstar, hår-, klädes- och rotborstar, piassavakvastar m. m.",
            "location": "Vinslöv",
            "contact": {
                "phone": "99",
                "postgiro": "30440"
            },
            "financials": {
                "capital": "100,000 kr",
                "employees": {
                    "industriarb": 80
                },
                "annual_production_value": "800,000 kr"
            },
            "foundation_year": 1935
        },
        "6": {
            "name": "AB. Borst- & Penselfabriken, Kristinehamn",
            "business": "Tillverkar alla slags borstar och penslar, även för industriella ändamål",
            "location": "Kristinehamn",
            "contact": {
                "phone": [
                    "10288",
                    "10370"
                ],
                "postgiro": "28800"
            },
            "financials": {
                "capital": "36,000 kr",
                "employees": {
                    "industriarb": 100
                }
            },
            "foundation_year": 1910
        },
        "7": {
            "name": "AB. Borås Appreturmedelfabrik, Borås",
            "business": "Tillverkar preparat för textilindustrien såsom textiloljor, nättjemedel, textiltvål-och tvättmedel, bykoljor, egaliseringsmedel, appreturmedel samt preparat för skinnberederier och läderindustrier",
            "location": "Källbäcksryd, Borås",
            "contact": {
                "phone": [
                    "48140",
                    "48141"
                ],
                "postgiro": "33468",
                "repre": "AB. Nils Holmberg, Halmstad, telefon: 1044"
            },
            "financials": {
                "capital": "50,000 kr",
                "employees": {
                    "number": 6
                }
            },
            "foundation_year": 1929
        }
    }
}