{
    "original": "Hälsingborg\n\ngymnastikskor, textilskodon med gummi-,\nläder- eller velvasula, lädersandaler med\ngummi- eller velvasula, badskor, tofflor\noch andra gummiskodon, badmössor,\ngummiklackar och -sulor.^ sul- och\nklack-gummi i plattor, gummihandskar,\nfotbolls-blåsor, gummibollar och tennisbollar.\nVarumärke: »Tretorn».\n\nFörsäljningsbolag i Sverige: Svenska\nGaloschförsäljn. AB., Stockholm;\nGöteborgs Galoschförsäljn. AB; Gefle\nGa-losch- &amp; Skoförsäljn. AB.; Örebro\nGa-losch &amp; Skoförsäljn. AB. samt AB.\nGa-loscher, Malmö. Bolaget äger därjämte\nfabriksbolag i Danmark och Tyskland\nsamt försäljningsbolag i Norge, Finland,\nSchweiz och Rumänien.\n\nTelegr.-adr.: Tretorn, Hälsingborg.\nTelefon: »Gummifabriken». Postgiro: 14333.\n\nAkt.-kap.: 15,000,000 kr. Antal\nindustriarb.: 2,600. — Bolaget grundat 1891.\n\nIStyrelsej disp. Henry Dunker (ordf.),\nbankdir. Åke Belfrage, prof. Erik\nFahl-beck, adv. Henry Ljunggren, ryttm. Ulf\nOlsson, disp. C. G. Schultz, disp. Artur\nStibe.\n\nVerkst. direktörer: disp. Henry\nDunker o. disp. Artur Stibe.\n\nV. verkst. dir.: övering. Otto Svensson.\n\nKassadir.: Hadar II: son Hallström.\n\nHälsingborg.\n\n\"Helsingborgs Jacquard Väfveri AB.,\n\nHälsingborg.\n\nYlle- och sidenväveri, färgeri och\nappreturverk. Tillverkar klännings- och\nkonfektionstyger av ylle och konstsilke\nsamt konstsilkefoder.\n\nTelegr.-adr.: Jacquard. Hälsingborg.\nTelefon: 10123, 10409 o. 14023. Postgiro:\n84700.\n\nAkt.-kap.: 1,000,000 kr. Antal\nindustriarb.: 190. Tillv.-värde pr år: 5,000,000 kr.\n— Bolaget grundat 1898.\n\nStyrelse: jur. dr Axel Roos (ordf.),\ndir. II. Kirsebom, bankdir. S. Lundblad,\nskeppsred. J. W. Malmros.\n\nVerkst. dir.: H. Kirsebom.\n\nBitr. dir.: O. Klintegård.\n\nKamrer: O. Lenell.\n\nProd.-chef: P. Bauer.\n\nFörsäljn.-chef: H. Nilsson.\n\nHälsingborgs Järnindustri,\n\nHälsingborg.\n\nGjuteri. Tillverkar tackjärns- och\nme-tallgjutgods, gas- och\nvattenledningsartiklar samt gatugjutgods.\n\nTelegr.-adr.: Järnindustri.\nHälsingborg. Telefon: 10069. Postgiro: 900U9.\nAntal industriarb.: 12.\n\nVerksamheten startad 1878, nuv. firma\netabl. 1913 under namn AB. Järnindustri,\nnamnförändring 1931.\nÄgare: fru Carin Pape.\nKamrer: Gunnar Hörteli.\n\n\"Hälsingborgs Kopparverk,\n\nHälsingborg.\n\nSe Reymersholms Gamla Industri AB.,\nHälsingborg.\n\nHälsingborgs Litografiska AB.,\n\nHälsingborg.\n\nTillverkar kartonger, affischer,\nbroschyrer, kartonnage och reklamartiklar\nsamt förpackningar i litografi, offset och\nboktryck. Specialiteter: klädkartonger\n(märke: »Perfekt») och bakelsekartonger\n(märke: »Hansa»).\n\nTelefon: »Litografen». Postgiro: 14303.\n\nAkt.-kap.: 150,000 kr. Antal\nindustriarb.: 200. Tillv.-värde pr år: 2,000,000 kr.\n— Firman etabl. 1876, bolag 1910.\n\nStyrelse o. verkst. dir.: Erland\nBorne-busch.\n\nFabrihschef: Joel Heddelin.\n\nHälsingborg.\n\n\"AB. Helsingborgs Maskinaffär,\n\nHälsingborg.\n\nVelociped- och bleckvarufabrik.\nTillverkar velocipeder och bleckemballage.\n\nTelefon: 10371 o. 14571. Postgiro:\n31900.\n\nAkt.-kap.: 122,000 kr. Antal\nindustriarb.: 15. Tillv.-värde pr år: 500,000 kr.\n\n—\tBolaget grundat 1908.\n\nStyrelse o. verkst. dir.: Harwey\nBoh-lin.\n\nVerkstadschef: Gustaf Ekström.\n\n\"AB. Hälsingborgs Pälsberederi,\n\nRaus.\n\n^ Beredning och färgning av pälsskinn\nvid fabrik i Raus, Hälsingborg.\n\nTelegr.-adr.: Pelsberederiet, Raus.\nTelefon: Hälsingborg 90379. Postgiro:\n26552.\n\nAkt.-kap.: 100,000 kr. Antal\nindustriarb.: 40. Tillv.-värde pr år: 500.000 kr.\n\n—\tFirman etabl. 1935, bolag 1940,\nombildat 1945.\n\nStyrelse: adv. E. Halbert, dir. Andreas\nMöller, dir. Frans Möller.\n\nVerkst. dir.: Andreas Möller.\n\n241*\n\n16",
    "structured": {
        "firms": {
            "0": {
                "name": "Helsingborgs Gummi Aktiebolag",
                "location": "Hälsingborg",
                "business": "Tillverkning av gymnastikskor, textilskodon med gummi- eller lädersula, lädersandaler med gummi- eller lädersula, badskor, tofflor, badmössor, gummiklackar och -sulor, gummihandskar, fotbolls- och tennisbollar.",
                "products": "Varumärke: »Tretorn»",
                "contact": {
                    "office": "Hälsingborg",
                    "phone": [
                        "Gummifabriken"
                    ],
                    "postgiro": "14333",
                    "telegraph": "Tretorn, Hälsingborg"
                },
                "financials": {
                    "capital": "15,000,000 kr",
                    "employees": {
                        "industriarb": 2600
                    },
                    "annual_turnover": "N/A",
                    "annual_production_value": "N/A"
                },
                "foundation_year": 1891,
                "board": [
                    {
                        "name": "Henry Dunker",
                        "role": "Disponent"
                    },
                    {
                        "name": "Åke Belfrage",
                        "role": "Bankdirektör"
                    },
                    {
                        "name": "Erik Fahlbeck",
                        "role": "Professor"
                    },
                    {
                        "name": "Henry Ljunggren",
                        "role": "Advokat"
                    },
                    {
                        "name": "Ulf Olsson",
                        "role": "Ryttmästare"
                    },
                    {
                        "name": "C. G. Schultz",
                        "role": "Disponent"
                    },
                    {
                        "name": "Artur Stibe",
                        "role": "Disponent"
                    }
                ],
                "owners": [
                    "N/A"
                ],
                "director": "N/A",
                "managing_director": "Henry Dunker",
                "sales_manager": "N/A",
                "manager": "Artur Stibe"
            },
            "1": {
                "name": "Helsingborgs Jacquard Väfveri AB.",
                "location": "Hälsingborg",
                "business": "Ylle- och sidenväveri, färgeri och appreturverk. Tillverkar klännings- och konfektionstyger av ylle och konstsilke samt konstsilkefoder.",
                "products": "N/A",
                "contact": {
                    "office": "Hälsingborg",
                    "phone": [
                        "10123",
                        "10409",
                        "14023"
                    ],
                    "postgiro": "84700",
                    "telegraph": "Jacquard, Hälsingborg"
                },
                "financials": {
                    "capital": "1,000,000 kr",
                    "employees": {
                        "industriarb": 190
                    },
                    "annual_turnover": "5,000,000 kr",
                    "annual_production_value": "N/A"
                },
                "foundation_year": 1898,
                "board": [
                    {
                        "name": "Axel Roos",
                        "role": "Jurist"
                    },
                    {
                        "name": "H. Kirsebom",
                        "role": "Direktör"
                    },
                    {
                        "name": "S. Lundblad",
                        "role": "Bankdirektör"
                    },
                    {
                        "name": "J. W. Malmros",
                        "role": "Skeppsredare"
                    }
                ],
                "owners": [
                    "N/A"
                ],
                "director": "N/A",
                "managing_director": "H. Kirsebom",
                "sales_manager": "N/A",
                "manager": "N/A"
            },
            "2": {
                "name": "Hälsingborgs Järnindustri",
                "location": "Hälsingborg",
                "business": "Tillverkar tackjärns- och metallgjutgods, gas- och vattenledningsartiklar samt gatugjutgods.",
                "products": "N/A",
                "contact": {
                    "office": "Hälsingborg",
                    "phone": [
                        "10069"
                    ],
                    "postgiro": "900U9",
                    "telegraph": "Järnindustri, Hälsingborg"
                },
                "financials": {
                    "capital": "N/A",
                    "employees": {
                        "industriarb": 12
                    },
                    "annual_turnover": "N/A",
                    "annual_production_value": "N/A"
                },
                "foundation_year": 1913,
                "board": [
                    "N/A"
                ],
                "owners": [
                    "fru Carin Pape"
                ],
                "director": "N/A",
                "managing_director": "N/A",
                "sales_manager": "N/A",
                "manager": "N/A"
            },
            "3": {
                "name": "Hälsingborgs Litografiska AB.",
                "location": "Hälsingborg",
                "business": "Tillverkar kartonger, affischer, broschyrer, kartonnage och reklamartiklar samt förpackningar i litografi, offset och boktryck. Specialiteter: klädkartonger (märke: »Perfekt») och bakelsekartonger (märke: »Hansa»).",
                "products": "N/A",
                "contact": {
                    "office": "Hälsingborg",
                    "phone": [
                        "Litografen"
                    ],
                    "postgiro": "14303",
                    "telegraph": "N/A"
                },
                "financials": {
                    "capital": "150,000 kr",
                    "employees": {
                        "industriarb": 200
                    },
                    "annual_turnover": "2,000,000 kr",
                    "annual_production_value": "N/A"
                },
                "foundation_year": 1910,
                "board": [
                    "N/A"
                ],
                "owners": [
                    "N/A"
                ],
                "director": "N/A",
                "managing_director": "Erland Bornebusch",
                "sales_manager": "N/A",
                "manager": "Erland Bornebusch"
            },
            "4": {
                "name": "AB. Helsingborgs Maskinaffär",
                "location": "Hälsingborg",
                "business": "Velociped- och bleckvarufabrik. Tillverkar velocipeder och bleckemballage.",
                "products": "N/A",
                "contact": {
                    "office": "Hälsingborg",
                    "phone": [
                        "10371",
                        "14571"
                    ],
                    "postgiro": "31900",
                    "telegraph": "N/A"
                },
                "financials": {
                    "capital": "122,000 kr",
                    "employees": {
                        "industriarb": 15
                    },
                    "annual_turnover": "500,000 kr",
                    "annual_production_value": "N/A"
                },
                "foundation_year": 1908,
                "board": [
                    "N/A"
                ],
                "owners": [
                    "N/A"
                ],
                "director": "N/A",
                "managing_director": "Harwey Bohlin",
                "sales_manager": "N/A",
                "manager": "Harwey Bohlin"
            },
            "5": {
                "name": "AB. Hälsingborgs Pälsberederi",
                "location": "Raus",
                "business": "Beredning och färgning av pälsskinn vid fabrik i Raus, Hälsingborg.",
                "products": "N/A",
                "contact": {
                    "office": "N/A",
                    "phone": [
                        "Hälsingborg 90379"
                    ],
                    "postgiro": "26552",
                    "telegraph": "Pelsberederiet, Raus"
                },
                "financials": {
                    "capital": "100,000 kr",
                    "employees": {
                        "industriarb": 40
                    },
                    "annual_turnover": "500,000 kr",
                    "annual_production_value": "N/A"
                },
                "foundation_year": 1940,
                "board": [
                    "N/A"
                ],
                "owners": [
                    "N/A"
                ],
                "director": "N/A",
                "managing_director": "Andreas Möller",
                "sales_manager": "N/A",
                "manager": "Andreas Möller"
            }
        }
    }
}