{
    "original": "Upperud—Upsala\n\nAkt.-kap.: 37,500 kr. Antal\nindustriarb.: 18. Årskapacitet: 5,000 ton våt vit\nmek. trämassa. — Bolaget grundat 1885.\n\nStyrelse: f. d. konsul Axel H.\nLundberg, fru Gerda Lundberg, agronom Leif\nLundberg.\n\nVerkst. dir.: Axel H. Lundberg.\n\n*Upperuds Valskvarn, Upperud.\n\nSe Nya AB. Upperuds Valskvarn,\nUpperud.\n\n\"Uppsala Armaturfabrik AB.,\n\nStockholm.\n\nMetallvarufabrik i Stockholm.\nTillverkar elektrisk belysningsarmatur,\nkandelabrar, kronor, lampetter, lampskärmar,\nljusstakar samt utför metalltryckning\noch metallpressning.\n\nKontor: Malmgårdsvägen 22.\nTelegr.-adr.: Elektroarmatur, Stockholm.\nTelefon: 440630. Postgiro: 12990.\n\nAkt.-kap.: 115,000 kr. Antal\nindustriarb.: 75. Tillv.-värde pr år: 1,500,000 kr.\n—- Firman etabl. 1915, bolag 1932.\n\nStyrelse: civiling. Sten Westerberg\n(ordf.), civiling. Henrik Lamby, dir. G.\nRosenqvist.\n\nVerkst. dir.: G. Rosenqvist.\n\n\"Upsala Bayerska Bryggeri AB.,\n\nU ppsala.\n\nTillverkar malt- och läskedrycker.\n\nTelefon: »Bryggeribolaget». Postgiro:\n85213. — Akt.-kap.: 1,080,000 kr. Antal\nindustriarb.: 60. Försälj.-värde pr år:\n3,000,000 kr.\n\nBolaget grundat 1865.\nAktiemajoriteten i bolaget innehaves av AB. Stockholms\nBryggerier.\n\nStyrelse: överbibliotekarie Anders\nGrape (ordf.), dir. Harald Engström,\ndir. Sven Schwartz, dir. Henrik Svanfeldt.\n\nVerkst. dir.: Teodor Carling.\n\nBry g gm.: ing. Sven Hallström.\n\nKamrer: Göte Bergström.\n\nAB. Upsala Bröd, Uppsala.\n\nTillverkar spis- och knäckebröd.\n\nTelefon: 35032. Postgiro: 21438.\n\nAkt.-kap.: 150,000 kr. Antal\nindustriarb.: 60. Prod.-värde pr år: 1,200,000 kr.\n— Bolaget grundat 1919.\n\nDisp.: Ragnar Åkerblom.\n\n\"Upsala-Ekeby AB., Ekebybruk.\n\nFajans- och väggplattfabriker vid\nEkebybruk (Uppsala l.) och Skattmansö,\nVittinge (Västmanl. l.). Bedriver fajans-,\n\nkakel- och taktegelfabrikation och i\nsamband därmed stående industriell\nverksamhet.\n\nHuvudkontor: Ekebybruk.\nTelegr.-adr.: Ekeby, Uppsala. Telefon: »Ekeby\nbruk», Uppsala. Postgiro: 23032.\nAvd.-kontor o. utställning: Stockholm,\nDö-belnsg. 1, telefon: 104726 o. 104772;\nGöteborg: O. Hamngat. 14, telefon: 132174\no. 114274.\n\nAkt.-kap.: 2,449,800 kr. Antal\nindustriarb.: 612 (inkl. dotterbolagen 1,900).\nTillv.-värde pr år: 10,500,000 kr.\nModer-och dotterbolagens sammanlagda\nomsättning: 20,000,000 kr.\n\nBolaget, grundat 1886, äger Gefle\nPorslinsfabriks AB., AB. Karlskrona\nPorslinsfabrik, AB. Upsala\nByggnadsvaror och AB. Byggnadsvaror, Stockholm,\nsamt Skattmansö Tegelbruk, Vittinge.\n\nStyrelse: f. d. fältläkare E. O. v. Bahr\n(ordf.), prof. Folke Wetter (v. ordf.),\nciviling. Carl v. Bahr, dir. Nils V.\nSterner, dir. H. W. Söderman, tekn. dr R.\nWinbladh.\n\nVerkst. dir.: Nils V. Sterner.\n\nKontors- o. personalchef: E. Ahlm.\n\nDriftsing.: K. Merkelbach.\n\nFörsäljn.-chef: I. Kullander.\n\nInköpschef: C. Monie.\n\n\"AB. Upsala Kappfabrik, Uppsala.\n\nTillverkar damkappor. Varumärke:\n»Larella».\n\nTelefon: »Uppsala Kappfabrik».\nPostgiro: 91660. Avd.-kontor: Stockholm,\nDrottningg. 11. Telefon: 114342.\n\nAkt.-kap.: 300,000 kr. Antal\nindustriarb.: 350. Tillv.-värde pr år: 5,000,000 kr.\n— Bolaget grundat 1917.\n\nStyrelse: dir. J. Anér (ordf.), bankdir.\nG. E. Didner, dir. Josef W. Larsson, fru\nBritta Larsson, disp. Sven Svensson.\nVerkst. dir.: fru Britta Larsson.\nDisp. o. v. verkst. dir.: Sven Svensson.\nKamrer: Lennart Larsson.\n\nUpsala Kartongfabriks AB.,\n\nUppsala.\n\nTillverkar kartonger och etuier.\nTelefon: 30985 o. 35385. Postgiro:\n97210.\n\nAkt.-kap.: 50,000 kr. Antal\nindustriarb.: 25. — Firman etabl. 1903, bolag\n1931.\n\nVerkst. dir.: Richard Wenngren.\nDisp.: Bengt Wenngren.\n\n738*",
    "structured": {
        "firms": [
            {
                "name": "Upperuds Valskvarn",
                "location": "Upperud",
                "business": "Tillverkar elektrisk belysningsarmatur, kandelabrar, kronor, lampetter, lampskärmar, ljusstakar samt utför metalltryckning och metallpressning.",
                "contact": {
                    "office": "Malmgårdsvägen 22",
                    "phone": [
                        "440630"
                    ],
                    "postgiro": "12990",
                    "telegraph": "Elektroarmatur, Stockholm"
                },
                "financials": {
                    "capital": "115,000 kr",
                    "employees": {
                        "industriarb": 75
                    },
                    "annual_production_value": "1,500,000 kr"
                },
                "foundation_year": 1915,
                "board": [
                    {
                        "name": "civiling. Sten Westerberg",
                        "role": "ordf."
                    },
                    {
                        "name": "civiling. Henrik Lamby",
                        "role": "dir."
                    },
                    {
                        "name": "dir. G. Rosenqvist",
                        "role": "v. ordf."
                    }
                ],
                "manager": "G. Rosenqvist"
            },
            {
                "name": "Uppsala Armaturfabrik AB.",
                "location": "Stockholm",
                "business": "Metallvarufabrik",
                "contact": {
                    "office": "Malmgårdsvägen 22",
                    "phone": [
                        "440630"
                    ],
                    "postgiro": "12990",
                    "telegraph": "Elektroarmatur, Stockholm"
                },
                "financials": {
                    "capital": "115,000 kr",
                    "employees": {
                        "industriarb": 75
                    },
                    "annual_production_value": "1,500,000 kr"
                },
                "foundation_year": 1915,
                "board": [
                    {
                        "name": "civiling. Sten Westerberg",
                        "role": "ordf."
                    },
                    {
                        "name": "civiling. Henrik Lamby",
                        "role": "dir."
                    },
                    {
                        "name": "dir. G. Rosenqvist",
                        "role": "v. ordf."
                    }
                ],
                "manager": "G. Rosenqvist"
            },
            {
                "name": "Upsala Bayerska Bryggeri AB.",
                "location": "Uppsala",
                "business": "Tillverkar malt- och läskedrycker",
                "contact": {
                    "phone": [
                        "Bryggeribolaget"
                    ],
                    "postgiro": "85213"
                },
                "financials": {
                    "capital": "1,080,000 kr",
                    "employees": {
                        "industriarb": 60
                    },
                    "annual_turnover": "3,000,000 kr"
                },
                "foundation_year": 1865,
                "board": [
                    {
                        "name": "överbibliotekarie Anders Grape",
                        "role": "ordf."
                    },
                    {
                        "name": "dir. Harald Engström",
                        "role": "dir."
                    },
                    {
                        "name": "dir. Sven Schwartz",
                        "role": "dir."
                    },
                    {
                        "name": "dir. Henrik Svanfeldt",
                        "role": "dir."
                    }
                ],
                "manager": "Göte Bergström",
                "sales_manager": "ing. Sven Hallström"
            },
            {
                "name": "AB. Upsala Bröd",
                "location": "Uppsala",
                "business": "Tillverkar spis- och knäckebröd",
                "contact": {
                    "phone": [
                        "35032"
                    ],
                    "postgiro": "21438"
                },
                "financials": {
                    "capital": "150,000 kr",
                    "employees": {
                        "industriarb": 60
                    },
                    "annual_production_value": "1,200,000 kr"
                },
                "foundation_year": 1919,
                "director": "Ragnar Åkerblom"
            },
            {
                "name": "Upsala-Ekeby AB.",
                "location": "Ekebybruk",
                "business": "Fajans- och väggplattfabriker",
                "contact": {
                    "office": "Ekebybruk",
                    "phone": [
                        "Ekeby bruk"
                    ],
                    "postgiro": "23032"
                },
                "financials": {
                    "capital": "2,449,800 kr",
                    "employees": {
                        "industriarb": 612
                    },
                    "annual_production_value": "10,500,000 kr"
                },
                "foundation_year": 1886,
                "board": [
                    {
                        "name": "f. d. fältläkare E. O. v. Bahr",
                        "role": "ordf."
                    },
                    {
                        "name": "prof. Folke Wetter",
                        "role": "v. ordf."
                    },
                    {
                        "name": "civiling. Carl v. Bahr",
                        "role": "dir."
                    },
                    {
                        "name": "dir. Nils V. Sterner",
                        "role": "dir."
                    },
                    {
                        "name": "dir. H. W. Söderman",
                        "role": "dir."
                    },
                    {
                        "name": "tekn. dr R. Winbladh",
                        "role": "dir."
                    }
                ],
                "manager": "C. Monie",
                "director": "E. Ahlm",
                "managing_director": "K. Merkelbach",
                "sales_manager": "I. Kullander"
            },
            {
                "name": "AB. Upsala Kappfabrik",
                "location": "Uppsala",
                "business": "Tillverkar damkappor",
                "contact": {
                    "phone": [
                        "Uppsala Kappfabrik"
                    ],
                    "postgiro": "91660"
                },
                "financials": {
                    "capital": "300,000 kr",
                    "employees": {
                        "industriarb": 350
                    },
                    "annual_production_value": "5,000,000 kr"
                },
                "foundation_year": 1917,
                "board": [
                    {
                        "name": "dir. J. Anér",
                        "role": "ordf."
                    },
                    {
                        "name": "bankdir. G. E. Didner",
                        "role": "dir."
                    },
                    {
                        "name": "dir. Josef W. Larsson",
                        "role": "dir."
                    },
                    {
                        "name": "fru Britta Larsson",
                        "role": "dir."
                    },
                    {
                        "name": "disp. Sven Svensson",
                        "role": "dir."
                    }
                ],
                "managing_director": "fru Britta Larsson",
                "manager": "Lennart Larsson"
            },
            {
                "name": "Upsala Kartongfabriks AB.",
                "location": "Uppsala",
                "business": "Tillverkar kartonger och etuier",
                "contact": {
                    "phone": [
                        "30985",
                        "35385"
                    ],
                    "postgiro": "97210"
                },
                "financials": {
                    "capital": "50,000 kr",
                    "employees": {
                        "industriarb": 25
                    }
                },
                "foundation_year": 1903,
                "manager": "Bengt Wenngren"
            }
        ]
    }
}