{
    "original": "Gemla—Gentele\n\nTelegr.-adr. o. telefon: Gemax,\nRosers-berg. Postgiro: 157255.\n\nAkt.-kap.: 25,000 kr. Antal\nindustriarb.: 12. Tillv.-värde pr år: 200,000 kr.\n\n—\tBolaget grundat 1938.\n\nVerkst. dir.: ing. Gustaf A. Erikson.\n\n*Cemla Fabrikers AB., Diö.\n\nSnickeri- och möbelfabrik vid Diö\n(Kronob. l.). Tillverkar\nkompletteringsmöbler, biograf- och teaterstolar,\nstoppmöbler, lasaretts- och sjukhusmöbler,\nkontorsstolar, rullstolar, tennisrackets,\nsvarvgods m. m. Bolaget driver jämväl\nsågverks- och kvarnrörelse.\n\nHuvudkontor: Diö. Telegr.-adr.:\nGem-labolaget, Hässleholm. Telefon: Diö\n»Gemlabolaget». Postgiro: 8400.\nFör-säljn.-kontor: Stockholm, Grevtureg. 7,\ntelefon: 626722 o. 675522; Göteborg,\nRingön, telefon: 222920.\n\nAkt.-kap.: 528,000 kr. Antal\nindustriarb.: 150. Tillv.-värde pr år: 1,800,000 kr.\n\n—\tFirman grundades 1870, bolag 1884.\n\nStyrelse: disp. Olof Biesért, assessor\n\nRobert Broms, ing. Andr. H. Holden,\nkamrer Finn Holden, fru Siri Hölden.\n\nVerkst. dir. o. disp.: Andr. H. Holden.\n\nAB. Gemla Leksaksfabrik, Gemla.\n\nTräförädlingsfabrik i Gemla (Kronob.\n1.). Tillverkar massartiklar av trä,\nbarnmöbler, undervisningsmateriel, svarvade\nträsaker m. m. samt såsom specialitet\nträ-leksaker.\n\nTelefon: Växjö 67104. Postgiro: 12791.\n\n—\tAkt.-kap.: 50,000 kr. Antal\nindustriarb.: 30. Tillv.-värde pr år: 200,000 kr.\n\nFirman etabl. 1892, bolag 1921.\n\nStyrelse: dir. Erik Wäsström (ordf.),\nfru Elisabeth Wäsström, fröken Gertrud\nWäsström.\n\nVerkst. dir. o. disp.: Erik Wäsström\n(Norrköping).\n\n* General Motors Nordiska AB.,\n\nStockholm.\n\nAutomobilfabrik. Tillverkar\nperson-och lastautomobiler, spårvagnar,\nrälsbussar, person- och busskarosserier,\nförarhytter, lastflak, skåpvagnar, släpvagnar samt\nkylskåp och kylanläggningar. Bolaget\ndriver även tillverkning och försäljning av\nreservdelar, tillbehör för automobiler,\noljeeldningsapparater med\nvarmvattenpannor, elektr. pumpar, elektricitetsverk\nför villor, lantgårdar m. m. samt\ndammsugare.\n\nKontor: Hammarbyvägen 13—25;\npostadr.: Stockholm 20. Telegr.-adr.: Stokau-\n\n1\n\n12\n\ntoex, Stockholm. Telefon: »General\nMotors». Postgiro: 2131.\n\nAkt.-kap.: 9,600,000 kr. Antal\nindustriarb.: 510. — Bolaget grundat 1927.\n\nStyrelse: dir. G. K. Howard, kamrer G.\nRagnar Möller, dir. R. W. Seeley, dir.\nC. O. Skriver, ing. Bengt Welin, ing.\nAlbert Vennerholm.\n\nVerkst. dir.: R. W. Seeley.\n\nDir.: C. C. Skriver.\n\nFörsäljn.-chef: S. V. Pedersen.\n\nKamrer: G. R. Möller.\n\nFabrihschef: B. Welin.\n\nDisp. (inköp): Viking Wennerholm.\n\n* Generalstabens Litografiska Anstalt,\n\nStockholm.\n\nSe A. Börtzells Tryckeri AB.,\nStockholm.\n\n*AB. Cense, Eskilstuna.\n\nTillverkar kuvert- och hushållsartiklar\nsamt restaurantartiklar i försilvrad\nal-pacca och rostfritt stål. Varunamn:\n»Gense».\n\nTelegr.-adr.: Gense, Eskilstuna.\nTelefon: »Gense metall». Postgiro: 10703.\n\nAkt.-kap.: 600,000 kr. Antal\nindustriarb.: 425. Tillv.-värde pr år: 6,000,000 kr.\n— Fabriken grundad 1856, bolag 1898\nunder namn AB. Gustaf Erikssons\nMetallfabrik, nuv. namn 1946. — Bolaget äger\nAB. A. Th. Broms, Eskilstuna.\n\nStyrelse: fru I. Hedlund (ordf.), fru\nGreta Broms, disp. Lars Hedlund.\n\nVerkst. dir. o. disp.: Lars Hedlund.\n\nKontorschef: Abel östlund.\n\n*AB. Gentele &amp; Co., Stockholm.\n\nFärg- och fernissfabrik vid\nMidsommarkransen, Stockholm.\n\nTillverkar kopal-, cellulosa- och\nspritfernissor, lack-, emulsions- och oljefärger,\nglasyrer, bonvax m. m. Varumärken:\n»Sjulack», »Minutlack», »Diamantlack»,\n»Tellus», »Domus», »Long-John»,\n»Momentfärg», »Gobeläng» o. »City».\n\nKontor: Midsommarkransen. Postadr.:\nStockholm 9. Telegr.-adr. o. telefon:\nGen-telecompani, Stockholm. Postgiro: 117.\n\nAkt.-kap.: 550,000 kr. Antal\nindustriarb.: 50. — Firman grundad 1911, bolag\n1917.\n\nStyrelse: kapten Raguel Essen, dir.\nHerman W. Gentele, fröken Käthy\nGentele, v. konsul Adolf Heljestrand, fröken\nTatjana Heljestrand.\n\nVerkst. direktörer: Herman W.\nGentele o. Adolf Heljestrand.\n\nFabrihschef: Josef W. Gentele.\n\nKamrer: Orvar Borg.",
    "structured": {
        "firms": [
            {
                "name": "Gemla Fabrikers AB",
                "location": "Diö",
                "business": "Snickeri- och möbelfabrik",
                "products": "Kompletteringsmöbler, biograf- och teaterstolar, stoppmöbler, lasaretts- och sjukhusmöbler, kontorsstolar, rullstolar, tennisrackets, svarvgods m. m.",
                "contact": {
                    "office": "Diö",
                    "phone": [
                        "Gemlabolaget"
                    ],
                    "postgiro": "8400",
                    "head_office": "Diö",
                    "sales_offices": [
                        {
                            "location": "Stockholm",
                            "phone": "626722 o. 675522"
                        },
                        {
                            "location": "Göteborg",
                            "phone": "222920"
                        }
                    ]
                },
                "financials": {
                    "capital": "528,000 kr",
                    "employees": {
                        "industriarb": 150
                    },
                    "annual_turnover": "1,800,000 kr"
                },
                "foundation_year": 1870,
                "board": [
                    {
                        "name": "disp. Olof Biesért",
                        "role": ""
                    },
                    {
                        "name": "assessor Robert Broms",
                        "role": ""
                    },
                    {
                        "name": "ing. Andr. H. Holden",
                        "role": ""
                    },
                    {
                        "name": "kamrer Finn Holden",
                        "role": ""
                    },
                    {
                        "name": "fru Siri Hölden",
                        "role": ""
                    }
                ],
                "manager": "Andr. H. Holden"
            },
            {
                "name": "AB. Gemla Leksaksfabrik",
                "location": "Gemla",
                "business": "Träförädlingsfabrik",
                "products": "Massartiklar av trä, barnmöbler, undervisningsmateriel, svarvade träsaker m. m., trä-leksaker",
                "contact": {
                    "phone": [
                        "Växjö 67104"
                    ],
                    "postgiro": "12791"
                },
                "financials": {
                    "capital": "50,000 kr",
                    "employees": {
                        "industriarb": 30
                    },
                    "annual_turnover": "200,000 kr"
                },
                "foundation_year": 1892,
                "owner": [
                    "Erik Wäsström",
                    "fru Elisabeth Wäsström",
                    "fröken Gertrud Wäsström"
                ],
                "manager": "Erik Wäsström"
            },
            {
                "name": "General Motors Nordiska AB",
                "location": "Stockholm",
                "business": "Automobilfabrik",
                "products": "Person-och lastautomobiler, spårvagnar, rälsbussar, person-och busskarosserier, förarhytter, lastflak, skåpvagnar, släpvagnar, kylskåp, kylanläggningar, reservdelar, tillbehör för automobiler, oljeeldningsapparater, elektr. pumpar, elektricitetsverk, dammsugare",
                "contact": {
                    "office": "Hammarbyvägen 13—25",
                    "postgiro": "2131"
                },
                "financials": {
                    "capital": "9,600,000 kr",
                    "employees": {
                        "industriarb": 510
                    }
                },
                "foundation_year": 1927,
                "board": [
                    {
                        "name": "dir. G. K. Howard",
                        "role": ""
                    },
                    {
                        "name": "kamrer G. Ragnar Möller",
                        "role": ""
                    },
                    {
                        "name": "dir. R. W. Seeley",
                        "role": ""
                    },
                    {
                        "name": "dir. C. O. Skriver",
                        "role": ""
                    },
                    {
                        "name": "ing. Bengt Welin",
                        "role": ""
                    },
                    {
                        "name": "ing. Albert Vennerholm",
                        "role": ""
                    }
                ],
                "director": "R. W. Seeley",
                "manager": "C. O. Skriver",
                "sales_manager": "S. V. Pedersen",
                "fabrihschef": "B. Welin",
                "disp.": "Viking Wennerholm"
            },
            {
                "name": "AB. Cense",
                "location": "Eskilstuna",
                "business": "Tillverkar kuvert- och hushållsartiklar samt restaurantartiklar i försilvrad al-pacca och rostfritt stål. Varunamn: »Gense».",
                "contact": {
                    "telegraph": "Gense, Eskilstuna",
                    "phone": [
                        "Gense metall"
                    ],
                    "postgiro": "10703"
                },
                "financials": {
                    "capital": "600,000 kr",
                    "employees": {
                        "industriarb": 425
                    },
                    "annual_turnover": "6,000,000 kr"
                },
                "foundation_year": 1898,
                "original_name": "AB. Gustaf Erikssons Metallfabrik",
                "corporation_year": 1946,
                "owner": [
                    "fru I. Hedlund",
                    "fru Greta Broms",
                    "disp. Lars Hedlund"
                ],
                "manager": "Lars Hedlund",
                "kontorschef": "Abel östlund"
            },
            {
                "name": "AB. Gentele & Co.",
                "location": "Stockholm",
                "business": "Färg- och fernissfabrik",
                "products": "Kopal-, cellulosa- och spritfernissor, lack-, emulsions- och oljefärger, glasyrer, bonvax, varumärken: »Sjulack», »Minutlack», »Diamantlack», »Tellus», »Domus», »Long-John», »Momentfärg», »Gobeläng» o. »City»",
                "contact": {
                    "office": "Midsommarkransen",
                    "postgiro": "117"
                },
                "financials": {
                    "capital": "550,000 kr",
                    "employees": {
                        "industriarb": 50
                    }
                },
                "foundation_year": 1917,
                "board": [
                    {
                        "name": "kapten Raguel Essen",
                        "role": ""
                    },
                    {
                        "name": "dir. Herman W. Gentele",
                        "role": ""
                    },
                    {
                        "name": "fröken Käthy Gentele",
                        "role": ""
                    },
                    {
                        "name": "v. konsul Adolf Heljestrand",
                        "role": ""
                    },
                    {
                        "name": "fröken Tatjana Heljestrand",
                        "role": ""
                    }
                ],
                "managing_director": "Herman W. Gentele",
                "manager": "Adolf Heljestrand",
                "fabrihschef": "Josef W. Gentele",
                "kamrer": "Orvar Borg"
            }
        ]
    }
}