{
    "original": "Va Ide ma rsvtk— Wallenb e rg\n\n* Valdemarsviks Läderfabrik,\n\nValdemarsvik.\n\nSe O. J. Lundbergs Läderfabriks AB.,\nValdemarsvik.\n\nValdemarsviks Slip &amp; Båtvarv,\n\nValdemarsvik.\n\nTillverkar båtar och mindre fartyg i\nsåväl järn som trä vid varv i\nValdemars-vik (Östergötl. l.).\n\nTelefon: 90. Postgiro: 280940. —\nAntal industriarb.: 30. Tillv.-värde pr år:\n350,000 kr. — Firman etabl. 1937.\n\nÄgare o. chefer: fabr. Emil O.\nPettersson, ing. Olof B. Pettersson o. fabr. Erik\nW. Pettersson.\n\nWalfridsons Metallfabrik, Nässjö.\nSe Bröderna Walfridson, Nässjö.\n\n*Valinders Ramfabrik, Göteborg.\n\nTillverkar ramlister och ovala ramar.\n\nKontor: l:sta Långgatan 9. Telefon:\n145454. Postgiro: 40365. — Antal\nindustriarb.: 12. Tillv.-värde pr år: 100,000\nkr. — Fabriken anlagd 1916.\n\nÄgare o. chef: fabr. Aron Valinder.\n\n*Walla-Katrineholm, Tegelbruks AB.,\n\nKatrineholm.\n\nSe Tegelbruks AB. Walla-Katrineholm,\nKatrineholm.\n\n*Valla Tegelbruk, Stallarholmen.\n\nSe AB. Mälardalens Tegelbruk, Sthlm.\n\nAB. Walla Tröskmaskiner,\n\nKatrineholm.\n\nMek. verkstad och snickerifabrik i Valla\n(Södermanl. l.). Tillverkar\nlantbruksmaskiner såsom stallgödsel- och\nkonstgödsel-spridare, sädesrensningsmaskiner,\nsläp-räfsor, spannmålstorkar m. m.\n\nEnsamförsälj. o. huvudkontor:\nKullberg &amp; Oo. AB., Katrineholm. Telefon:\n»Kullbergs». Fabrikskontor: Valla.\n\nAkt.-kap.: 125,000 kr. Antal\nindustriarb.: 55. Tillv.-värde pr år: 800,000 kr.\n— Bolaget grundat 1913.\n\nStyrelse: dir. Carl Kihlgren (ordf.),\ndir. Sv. Alwerud, ing. H. Dalin.\n\nVerkst. dir.: Sv. Alwerud.\n\nV ericstads chef: H. Dalin.\n\n\"Wallbergs Fabriks AB., Halmstad.\n\nUllspinneri, ylleväveri, appreturverk\noch färgeri, maskinfiltfabrik och\ntrikåfabrik samt tegelbruk (Slottsmöllans\nTegelbruk) .\n\nTillverkar klädesvaror, trikåvaror,\nfiltar för pappers-, cellulosa- och\nträmasseindustrien samt tegel.\n\nTelegr.-adr.: Wallbergs, Halmstad.\nTelefon: »Wallbergs Bolag». Postgiro:\n14894.\n\nRepresentanter: för klädesfabriken: i\nStockholm: Fredrik Victorin, Svartmang.\n6, telefon: 209707; för trikåfabriken: i\nGöteborg: Henning Malmborg, Magasinsg.\n12, telefon: 136709; för filtfabriken: i\nSundsvall: AB. Åkesson &amp; Blomquist,\ntelefon: 1677 o. 1577.\n\nAkt.-kap.: 2,136,000 kr. Antal\nindustriarb.: 700, varav vid tegelbruket 60.\nTillv.-värde pr år: 10,000,000 kr. — Firman\netabl. 1823, bolag 1857.\n\nStyrelse: dir. Bengt Skånsberg (ordf.),\ndir. G. Göthlin, fru I. Wallberg.\n\nJourh. styrelseled.: fru I. Wallberg.\n\nVerkst. dir.: Per Göthlin.\n\nFabrikschef: F. Zschiedrich.\n\nAB. Walldén-Verken, Köping.\n\nGjuteri och mek. verkstad. Tillverkar\nmaskiner för gruvor, anrikningsverk och\njärnverk, grövre\nplåtbearbetningsmaski-ner, fackverkskonstruktioner och\ntack-järnsgjutgods.\n\nTelefon: 1100. Postgiro: 91152.\nFörsäljn.-kontor: Stockholm, Regeringsg. 18,\ntelefon: 214130.\n\nAkt.-kap.: 200,000 kr. Antal\nindustriarb.; 50. Tillv.-värde pr år: 600,000 kr.\n\nFirman etabl. 1932 under namn\nHögfors Gjuteri &amp; Mek. Verkstad,\nHögforsbruk, verksamheten överflyttad 1943 till\nKöping, bolag 1944.\n\nVerkst. dir. o. disp.: Ragnar Walldén.\n\nFörsäljn.-chef i Stockholm: civiling.\nCurt Marcus.\n\nKamrer: Sixten Hansson.\n\nVerkstadsing.-. Axel Nystedt.\n\n(Jfr annons före Alfabet.\nVaruförteck-ning.)\n\n*AB. L. O. Wallenbergs Skofabrik,\n\nMalmö.\n\nTillverkar herr- och damskodon.\n\nKontor: Skolgatan 21. Telefon: 12712\no. 20275. Postgiro: 38412.\n\nAkt.-kap.: 400,000 kr. Antal\nindustriarb.: 70. Tillv.-värde pr år: 1,000,000 kr.\n— Bolaget grundat 1912.\n\ni*",
    "structured": {
        "0": {
            "name": "Valdemarsviks Läderfabrik",
            "location": "Valdemarsvik",
            "contact": {
                "phone": [
                    "90"
                ],
                "postgiro": "280940"
            },
            "financials": {
                "capital": "N/A",
                "employees": {
                    "industriarb": 30
                },
                "annual_turnover": "350,000 kr",
                "annual_production_value": "N/A"
            },
            "foundation_year": 1937,
            "owners": [
                "fabr. Emil O. Pettersson",
                "ing. Olof B. Pettersson",
                "fabr. Erik W. Pettersson"
            ]
        },
        "1": {
            "name": "Valdemarsviks Slip & Båtvarv",
            "location": "Valdemarsvik",
            "products": "Tillverkar båtar och mindre fartyg i såväl järn som trä vid varv i Valdemarsvik (Östergötl. l.)",
            "contact": {
                "phone": [
                    "N/A"
                ],
                "postgiro": "N/A"
            },
            "financials": {
                "capital": "N/A",
                "employees": {
                    "industriarb": "N/A"
                },
                "annual_turnover": "N/A",
                "annual_production_value": "350,000 kr"
            },
            "foundation_year": "N/A",
            "owners": [
                "N/A"
            ]
        },
        "2": {
            "name": "Valinders Ramfabrik",
            "location": "Göteborg",
            "products": "Tillverkar ramlister och ovala ramar",
            "contact": {
                "phone": [
                    "145454"
                ],
                "postgiro": "40365"
            },
            "financials": {
                "capital": "N/A",
                "employees": {
                    "industriarb": 12
                },
                "annual_turnover": "100,000 kr",
                "annual_production_value": "N/A"
            },
            "foundation_year": 1916,
            "owners": [
                "fabr. Aron Valinder"
            ]
        },
        "3": {
            "name": "Valla Tegelbruk",
            "location": "Stallarholmen",
            "products": "Se AB. Mälardalens Tegelbruk, Sthlm",
            "contact": {
                "phone": [
                    "N/A"
                ],
                "postgiro": "N/A"
            },
            "financials": {
                "capital": "N/A",
                "employees": {
                    "industriarb": "N/A"
                },
                "annual_turnover": "N/A",
                "annual_production_value": "N/A"
            },
            "foundation_year": "N/A",
            "owners": [
                "N/A"
            ]
        },
        "4": {
            "name": "Wallbergs Fabriks AB.",
            "location": "Halmstad",
            "products": "Ullspinneri, ylleväveri, appreturverk och färgeri, maskinfiltfabrik och trikåfabrik samt tegelbruk (Slottsmöllans Tegelbruk)",
            "contact": {
                "phone": [
                    "N/A"
                ],
                "postgiro": "14894",
                "telegraph": "Wallbergs, Halmstad"
            },
            "financials": {
                "capital": "2,136,000 kr",
                "employees": {
                    "industriarb": 700,
                    "tegelbruket": 60
                },
                "annual_turnover": "10,000,000 kr",
                "annual_production_value": "N/A"
            },
            "foundation_year": 1823,
            "board": [
                {
                    "name": "dir. Bengt Skånsberg",
                    "role": "ordf."
                },
                {
                    "name": "dir. G. Göthlin",
                    "role": "N/A"
                },
                {
                    "name": "fru I. Wallberg",
                    "role": "N/A"
                }
            ],
            "owners": [
                "N/A"
            ],
            "director": "N/A",
            "managing_director": "Per Göthlin"
        },
        "5": {
            "name": "AB. Walldén-Verken",
            "location": "Köping",
            "products": "Gjuteri och mek. verkstad. Tillverkar maskiner för gruvor, anrikningsverk och järnverk, grövre plåtbearbetningsmaski-ner, fackverkskonstruktioner och tack-järnsgjutgods",
            "contact": {
                "phone": [
                    "1100"
                ],
                "postgiro": "91152"
            },
            "financials": {
                "capital": "200,000 kr",
                "employees": {
                    "industriarb": 50
                },
                "annual_turnover": "600,000 kr",
                "annual_production_value": "N/A"
            },
            "foundation_year": 1932,
            "owners": [
                "N/A"
            ],
            "director": "N/A",
            "managing_director": "Ragnar Walldén",
            "sales_manager": "N/A",
            "manager": "N/A"
        },
        "6": {
            "name": "AB. L. O. Wallenbergs Skofabrik",
            "location": "Malmö",
            "products": "Tillverkar herr- och damskodon",
            "contact": {
                "phone": [
                    "12712",
                    "20275"
                ],
                "postgiro": "38412"
            },
            "financials": {
                "capital": "400,000 kr",
                "employees": {
                    "industriarb": 70
                },
                "annual_turnover": "1,000,000 kr",
                "annual_production_value": "N/A"
            },
            "foundation_year": 1912,
            "owners": [
                "N/A"
            ],
            "director": "N/A",
            "managing_director": "N/A",
            "sales_manager": "N/A",
            "manager": "N/A"
        }
    }
}