{
    "original": "Å Jceholm—Åkers\n\nkemikalier samt gjuteriförnödenheter,\njärn och metaller m. m.\n\nHuvudkontor: Göteborg, Kungsg. 4.\nTelegr.-adr.: Ågren, Göteborg. Telefon:\n»Axel H. Ågren». Postgiro: 12128.\nAvd.-kontor: Stockholm, Kungsg. 46—48.\nTe-legr.-adr.: Rawmaterial, Stockholm,\ntelefon: 232930.\n\nAkt.-kap.: 800,000 kr. Antal\nindustriarb.: 60. — Firman etabl. 1887, bolag\n1933.\n\nStyrelse: ryttm. Ragnar Schéle, ing.\nErik G. Ågren, kapten Gustaf Ågren.\n\nVerkst. dir.: vakant.\n\n\"Åkeholms Spinneri, Åkeholm.\n\nSe Karlshamns Yllefabriks AB.,\nÅke-tiolm.\n\n*M. F. Åkerdahl, Stockholm.\n\nBokbinderi.\n\nKontor: Skomakarg. 13. Telefon: 100530\no. 101330. Postgiro: 2706. — Antal\nindustriarb.: 32. — Firman etabl. 1928.\n\nÄgare o. chef: bokbindaremäst. M. F.\nÅkerdahl.\n\n*AB. Åkerlund &amp; Rausing, Lund.\n\nFabrik för förpackningar av papper,\nkartong, papp, transparent material och\naluminiumfolier, vaxpappersfabrik samt\nlitografiskt tryckeri.\n\nVarumärken: »Vita Kraft» (fyrkantiga\nförpackningar för mjöl, socker, kaffe m.\nm.), »Snap Quick» (flata uppställbara\nkartonger för textilvaror, choklad m. m.),\n»Transofan» (transparenta\nförpackningar), »Protector» (äggförpackningar),\n»Pertinex» (förpackningsmetod för mjukt\nbröd), »Multico» (papperssäckar),\n»Super-twist» (specialbehandlat emballagepapper\nför sötvaror) o. »Satello» (runda burkar\nav papp och plåt).\n\nBolaget driver även konsulterande\nverksamhet för marknadsundersökningar och\nförpackningsfrågor.\n\nHuvudkontor: Lund. Telegr.-adr. o.\ntelefon: Åkerlundrausing, Lund. Post-\n\nåiro: 14100. Försäljn.-kontor: Stockholm,\n\negeringsg. 20, telegr.-adr.:\nÅkerlundrausing, Stockholm, telefon: 232250;\nGöteborg, Centrum, telefon: 132080; Gävle,\ntelefon: 2937; Eskilstuna, telefon: 36555.\n\nAkt.-kap.: 1,200,000 kr. Antal\nindustriarb.: 515. — Bolaget, grundat 1928,.\ndriver östanå Pappersbruk, Glimminge (se\ndetta företag).\n\nStyrelse: dir. Ruben Rausing (ordf.),\n-dir. Holger Crafoord, bankdir. Göte\nEng-fors.\n\nVerkst. dir.: Holger Crafoord.\n\nFörsäljn.-dir.: Gunnar Brime.\n\n\"Åkerlunds Bomullsspinneri AB.,\n\nBorås.\n\nTillverkar oblekt och melerat\nbomullsgarn samt cellull- och effektgarn.\n\nTelegr.-adr.: Otto, Borås. Telefon:\n12034, 10651 o. 10280. Postgiro: 98110.\n\nAkt.-kap.: 1,400,000 kr. Antal\nindustriarb.: 150. — Bolaget grundat 1898.\n\nStyrelse: dir. Carl Eiserman (ordf.),\nfru Andrea Eiserman, disp. Johan\nNilson.\n\nVerkst. dir.: Carl Eiserman.\n\nDisp. o. tehn. ledare: Johan Nilson.\n\n\"AB. Sj. Åkerlunds Borstfabrik,\n\nLandskrona.\n\nSe AB. B. Bergströms Borstfabrik,\nLandskrona.\n\n\"AB. Åkermans Gjuteri &amp; Mek.\nVerkstad, Eslöv.\n\nGjuteri och mek. verkstad. Tillverkar\nsåsom specialiteter grävmaskiner,\ndik-ningsmaskiner, motorvältar,\ntraktorskopor, torvmaskiner, förvärmaren och\nmotströmsapparaten »Topsy»,\nångpanneroster, bläster rost anläggningar och gjutna\njärnfönster m. m.\n\nTelegr.-adr.: Åkermans, Eslöv. Telefon:\n81 o. 303. Postgiro: 30605. — Akt.-kap.:\n500,000 kr. Tillv.-värde pr år: 1,500,000\nkr. — Bolaget grundat 1923.\n\nStyrelse: dir. Ivar M. G. Sandberg\n(ordf.), fru Greta Linander,\nbankom-budsm. Eric Paulson, disp. B. L. Åkesson.\n\nDisp. o. verkst. dir.: B. L. Åkesson.\n\n(Jfr annons nr 75.)\n\n\"Åkerman &amp; Lunds Nya Orgelfabriks\n\nAB., Stockholm.\n\nTillverkar kyrko- och konsertorglar vid\nfabrik i Hölö (Södermanl. l.).\n\nKontor: Stockholm, Grevg. 5. Telefon:\n600768. Postgiro: 28102.\n\nAkt.-kap.: 60,500 kr. Antal\nindustriarb.: 20. Tillv.-värde pr år: 200,000 kr.\n— Firman etabl. 1860.\n\nStyrelse: disp. Helge W. Johansson\n(ordf.), fru J. Johansson.\n\nVerkst. dir.: Helge W. Johansson.\n\n\"Åkersberga Snickerifabrik,\n\nÅkersberga.\n\nSe Lundqvists Snickerier, Stockholm.\n\n\"AB. Åkers Styckebruk,\n\nÅkers styckebruk.\n\nMasugn, gjuteri, mek. verkstad, elektr.\nvattenkraftverk, järnmalmsgruvor, kalk-",
    "structured": {
        "1": {
            "name": "Å Jceholm—Åkers",
            "location": "Göteborg",
            "business": "kemikalier samt gjuteriförnödenheter, järn och metaller m. m.",
            "contact": {
                "office": "Kungsg. 4",
                "phone": [
                    "Axel H. Ågren"
                ],
                "postgiro": "12128",
                "head_office": "Göteborg, Kungsg. 4",
                "sales_offices": [
                    {
                        "location": "Stockholm",
                        "phone": "232930"
                    }
                ],
                "telegraph": "Ågren, Göteborg",
                "factory_office": "N/A",
                "factory_phone": "N/A"
            },
            "financials": {
                "capital": "800,000 kr",
                "employees": {
                    "industriarb": 60
                },
                "annual_turnover": "N/A",
                "annual_production_value": "N/A"
            },
            "foundation_year": 1887,
            "corporation_year": 1933,
            "board": [
                {
                    "name": "ryttm. Ragnar Schéle",
                    "role": "N/A"
                },
                {
                    "name": "ing. Erik G. Ågren",
                    "role": "N/A"
                },
                {
                    "name": "kapten Gustaf Ågren",
                    "role": "N/A"
                }
            ]
        },
        "2": {
            "name": "M. F. Åkerdahl",
            "location": "Stockholm",
            "business": "Bokbinderi",
            "contact": {
                "office": "Skomakarg. 13",
                "phone": [
                    "100530",
                    "101330"
                ],
                "postgiro": "2706",
                "head_office": "N/A",
                "sales_offices": [],
                "telegraph": "N/A",
                "factory_office": "N/A",
                "factory_phone": "N/A"
            },
            "financials": {
                "capital": "N/A",
                "employees": {
                    "industriarb": 32
                },
                "annual_turnover": "N/A",
                "annual_production_value": "N/A"
            },
            "foundation_year": 1928,
            "corporation_year": "N/A",
            "board": [],
            "owners": [
                "bokbindaremäst. M. F. Åkerdahl"
            ],
            "director": "N/A",
            "managing_director": "N/A",
            "sales_manager": "N/A",
            "manager": "N/A"
        },
        "3": {
            "name": "AB. Åkerlund & Rausing",
            "location": "Lund",
            "business": "Fabrik för förpackningar av papper, kartong, papp, transparent material och aluminiumfolier, vaxpappersfabrik samt litografiskt tryckeri.",
            "contact": {
                "office": "N/A",
                "phone": [],
                "postgiro": "14100",
                "head_office": "Lund",
                "sales_offices": [
                    {
                        "location": "Stockholm",
                        "phone": "232250"
                    },
                    {
                        "location": "Göteborg",
                        "phone": "132080"
                    },
                    {
                        "location": "Gävle",
                        "phone": "2937"
                    },
                    {
                        "location": "Eskilstuna",
                        "phone": "36555"
                    }
                ],
                "telegraph": "Åkerlundrausing, Lund",
                "factory_office": "N/A",
                "factory_phone": "N/A"
            },
            "financials": {
                "capital": "1,200,000 kr",
                "employees": {
                    "industriarb": 515
                },
                "annual_turnover": "N/A",
                "annual_production_value": "N/A"
            },
            "foundation_year": 1928,
            "corporation_year": "N/A",
            "board": [
                {
                    "name": "dir. Ruben Rausing",
                    "role": "ordf."
                },
                {
                    "name": "dir. Holger Crafoord",
                    "role": "N/A"
                },
                {
                    "name": "bankdir. Göte Eng-fors",
                    "role": "N/A"
                }
            ],
            "owners": [],
            "director": "N/A",
            "managing_director": "Holger Crafoord",
            "sales_manager": "Gunnar Brime",
            "manager": "N/A"
        },
        "4": {
            "name": "Åkerlunds Bomullsspinneri AB.",
            "location": "Borås",
            "business": "Tillverkar oblekt och melerat bomullsgarn samt cellull- och effektgarn.",
            "contact": {
                "office": "N/A",
                "phone": [
                    "12034",
                    "10651",
                    "10280"
                ],
                "postgiro": "98110",
                "head_office": "N/A",
                "sales_offices": [],
                "telegraph": "Otto, Borås",
                "factory_office": "N/A",
                "factory_phone": "N/A"
            },
            "financials": {
                "capital": "1,400,000 kr",
                "employees": {
                    "industriarb": 150
                },
                "annual_turnover": "N/A",
                "annual_production_value": "N/A"
            },
            "foundation_year": 1898,
            "corporation_year": "N/A",
            "board": [
                {
                    "name": "dir. Carl Eiserman",
                    "role": "ordf."
                },
                {
                    "name": "fru Andrea Eiserman",
                    "role": "N/A"
                },
                {
                    "name": "disp. Johan Nilson",
                    "role": "N/A"
                }
            ],
            "owners": [],
            "director": "N/A",
            "managing_director": "Carl Eiserman",
            "sales_manager": "N/A",
            "manager": "N/A"
        },
        "5": {
            "name": "AB. Åkermans Gjuteri & Mek. Verkstad",
            "location": "Eslöv",
            "business": "Gjuteri och mek. verkstad.",
            "contact": {
                "office": "N/A",
                "phone": [
                    "81",
                    "303"
                ],
                "postgiro": "30605",
                "head_office": "N/A",
                "sales_offices": [],
                "telegraph": "Åkermans, Eslöv",
                "factory_office": "N/A",
                "factory_phone": "N/A"
            },
            "financials": {
                "capital": "500,000 kr",
                "employees": {},
                "annual_turnover": "N/A",
                "annual_production_value": "1,500,000 kr"
            },
            "foundation_year": 1923,
            "corporation_year": "N/A",
            "board": [
                {
                    "name": "dir. Ivar M. G. Sandberg",
                    "role": "ordf."
                },
                {
                    "name": "fru Greta Linander",
                    "role": "N/A"
                },
                {
                    "name": "bankom-budsm. Eric Paulson",
                    "role": "N/A"
                },
                {
                    "name": "disp. B. L. Åkesson",
                    "role": "N/A"
                }
            ],
            "owners": [],
            "director": "N/A",
            "managing_director": "B. L. Åkesson",
            "sales_manager": "N/A",
            "manager": "N/A"
        },
        "6": {
            "name": "Åkerman & Lunds Nya Orgelfabriks AB.",
            "location": "Stockholm",
            "business": "Tillverkar kyrko- och konsertorglar.",
            "contact": {
                "office": "Grevg. 5",
                "phone": [
                    "600768"
                ],
                "postgiro": "28102",
                "head_office": "N/A",
                "sales_offices": [],
                "telegraph": "N/A",
                "factory_office": "N/A",
                "factory_phone": "N/A"
            },
            "financials": {
                "capital": "60,500 kr",
                "employees": {
                    "industriarb": 20
                },
                "annual_turnover": "200,000 kr",
                "annual_production_value": "N/A"
            },
            "foundation_year": 1860,
            "corporation_year": "N/A",
            "board": [
                {
                    "name": "disp. Helge W. Johansson",
                    "role": "ordf."
                },
                {
                    "name": "fru J. Johansson",
                    "role": "N/A"
                }
            ],
            "owners": [],
            "director": "N/A",
            "managing_director": "Helge W. Johansson",
            "sales_manager": "N/A",
            "manager": "N/A"
        },
        "7": {
            "name": "Åkers Styckebruk",
            "location": "Åkers styckebruk",
            "business": "Masugn, gjuteri, mek. verkstad, elektr. vattenkraftverk, järnmalmsgruvor, kalk.",
            "contact": {
                "office": "N/A",
                "phone": [
                    "N/A"
                ],
                "postgiro": "N/A",
                "head_office": "N/A",
                "sales_offices": [],
                "telegraph": "N/A",
                "factory_office": "N/A",
                "factory_phone": "N/A"
            },
            "financials": {
                "capital": "N/A",
                "employees": {},
                "annual_turnover": "N/A",
                "annual_production_value": "N/A"
            },
            "foundation_year": "N/A",
            "corporation_year": "N/A",
            "board": [],
            "owners": [],
            "director": "N/A",
            "managing_director": "N/A",
            "sales_manager": "N/A",
            "manager": "N/A"
        }
    }
}