{
    "original": "Kalle—Köping\n\nTelefon: 42. Postgiro: 89145.\nRepresentanter: Stockholm: AB. Georg Wibeck\n&amp; Co., Walling. 12, telefon: 110155;\nGöteborg: Knut Nyström, Påskbergsg. 18,\ntelefon: 183824.\n\nAkt.-kap.: 60,000 kr. Antal\nindustriarb.: 15. Tillv.-värde pr år: 400,000 kr.\n\n—\tFirman etabl. 1931, bolag 1943.\n\nVerkst. dir.: Hans Rassmussen.\n\nKamrer: Per Rassmussen.\n\nDriftsing.: Sigvard Wikersfors.\n\nAB. Källe-Regulatorer, Säffle.\n\nFinmek. verkstad i Säffle (Värml. l.).\n\nTillverkar regulatorer och instrument\nför automatisk driftskontroll för bl. a.\npappers- och cellulosaindustrier såsom\nautomat, regulatorer för konstant\nångtryck, gastryck, temperatur, nivå,\nkonsistens, effekt, vattenhalt etc.,\nmatarvat-tenregulatorer, eldningsregulatorer,\nång-kylare; fjärrnivåvisare m. m.\n\nTelegr.-adr.: Källo, Säffle. Telefon:\n369 o. 549. Postgiro: 96320.\n\nRepresentant: AB. C. A. Mörck,\nGöteborg, Kungsg. 46, telefon: 132540—42.\n\nAkt.-kap.: 500,000 kr. Arb.-antal: 40.\n\n—\tFirman etabl. 1922.\n\nVerkst. dir.: civiling. Torsten Källe.\n\nKäpp- &amp; Paraplyfabriken AB.,\nSvenska, Stockholm.\n\nSe Svenska Käpp- &amp; Paraplyfabriken\nAB., Stockholm.\n\nKärnan, Margarinfabriken,\n\nHälsingborg.\n\nSe Margarinfabriken Kärnan AB.,\nHälsingborg.\n\n*Kärnbolaget AB., Stockholm.\n\nBiokemisk industri. Tillverkar\nläkemedel, livsmedel och fodermedel samt\nindustrihjälpmedel och halvfabrikat för\nläkemedelsfabriker, bryggerier, bagerier,\nkonditorier, konfityrfabriker, garverier,\nskofabriker, gjuterier och textilfabriker.\n\nKontor: Nordenflychtsvägen 53,\nHornsberg. Telegr.-adr.: Kärnbolaget,\nStockholm. Telefon: 520450. Postgiro: 58002.\n\nAkt.-kap.: 200,000 kr. Antal anställda:\n150. Tillv.-värde pr år: 3,900,000 kr.\n\nBolaget, grundat 1931, äges av AB.\nStockholms Bryggerier.\n\nStyrelse: dir. Sven Schwartz (ordf.),\ndir. Martin Ahlstrand, dir. Harald\nEngström, fil. dr Harry Lundin.\n\no\n\nO.\n\nVerkst. dir.: S. Schwartz.\n\nV. verkst. dir.: D. Isaksson.\n\növering.: E. Branell.\n\nFörsäljn.-chef: civiling. T. Börresen.\n\nInköpschef: civiling. J. Delin.\n\nKontorschef: T. Lyth.\n\n*Kävlinge Clacéläderfabrik,\n\nKävlinge.\n\nSe AB. Glacéläderfabriken, Kävlinge.\n\n*Kävlinge Väveri AB., Kävlinge.\n\nVäveri, blekeri och appreturverk i\nKävlinge (Malmöh. l.). Tillverkar linne- och\nsidenvävnader. Varumärke:\n»Granit-linne».\n\nTelefon: 1 o. 35. Postgiro: 93427. —\nAkt.-kap.: 560,000 kr. Antal industriarb.:\n150. Tillv.-värde pr år: 3,500,000 kr. —\nBolaget grundat 1935.\n\nStyrelse: dir. Ingemar Ekblom (ordf.),\nkamrer B. Engzell, köpm. Filip\nHenrikson, disp. Ernst Scholtz, ing. Oscar\nScholtz, köpm. Gösta Skoglund.\n\nVerkst. dir.: I. Ekblom.\n\nDriftsing.: Oscar Scholtz.\n\nKölefors Vaddfabrik, Kölefors.\n\nTillverkar flock och vadd till täcken\noch madrasser samt för stoppning av\nmöbler vid fabrik i Kölefors (Östergötl.\n1.).\n\nTelefon: Kisa 36. Postgiro: 25990. —\nAntal industriarb.: 2. — Firman etabl.\n1937.\n\nÄgare o. chef: Karl Erik Fransson.\n\n*AB. Köpings Armaturfabrik,\n\nKöping.\n\nTillverkar armatur för gas, vatten,\nvärme och ånga, förnicklad och förkromad\nsanitetsarmatur samt metallgjutgods.\n\nTelefon: 406 o. 806. Postgiro: 13099.\n\nAkt.-kap.: 300,000 kr. Antal\nindustriarb.: 200. Tillv.-värde pr år: 2,400,000 kr.\n— Fabriken anlagd 1920, nuv. bolag\ngrundat 1941.\n\nStyrelse: ombudsm. Carl Nyqvist\n(ordf.), ing. P. Ekström, dir. Ewert\nJohnsson, ing. Birger Nyqvist, jur. kand.\nA. Vanas.\n\nVerkst. dir.: Ewert Johnsson.\n\n*Köpings Bryggeri AB., Köping.\n\nSkattepliktigt bryggeri. Tillverkar\nmalt-och läskedrycker.\n\nTelegr.-adr.: Bryggeribolaget, Köping.\nTelefon: 5. Postgiro: 80618. — Akt.-kap.:",
    "structured": {
        "1": {
            "name": "AB. Källe-Regulatorer",
            "location": "Säffle",
            "business": "Finmek. verkstad",
            "products": "Tillverkar regulatorer och instrument för automatisk driftskontroll för bl. a. pappers- och cellulosaindustrier såsom automat, regulatorer för konstant ångtryck, gastryck, temperatur, nivå, konsistens, effekt, vattenhalt etc., matarvat-tenregulatorer, eldningsregulatorer, ång-kylare; fjärrnivåvisare m. m.",
            "contact": {
                "office": "Säffle",
                "phone": [
                    "369",
                    "549"
                ],
                "postgiro": "96320",
                "telegraph": "Källo"
            },
            "financials": {
                "capital": "60,000 kr",
                "employees": {
                    "industriarb": 15
                },
                "annual_production_value": "400,000 kr"
            },
            "foundation_year": 1931,
            "corporation_year": 1943,
            "director": "Hans Rassmussen",
            "manager": "Sigvard Wikersfors"
        },
        "2": {
            "name": "AB. C. A. Mörck",
            "location": "Göteborg",
            "business": "Biokemisk industri",
            "products": "Tillverkar läkemedel, livsmedel och fodermedel samt industrihjälpmedel och halvfabrikat för läkemedelsfabriker, bryggerier, bagerier, konditorier, konfityrfabriker, garverier, skofabriker, gjuterier och textilfabriker.",
            "contact": {
                "office": "Göteborg, Kungsg. 46",
                "phone": "132540—42"
            },
            "financials": {
                "capital": "500,000 kr",
                "employees": {
                    "arb.-antal": 40
                }
            },
            "foundation_year": 1922,
            "director": "civiling. Torsten Källe"
        },
        "3": {
            "name": "Kärnbolaget AB.",
            "location": "Stockholm",
            "business": "Biokemisk industri",
            "products": "Tillverkar läkemedel, livsmedel och fodermedel samt industrihjälpmedel och halvfabrikat för läkemedelsfabriker, bryggerier, bagerier, konditorier, konfityrfabriker, garverier, skofabriker, gjuterier och textilfabriker.",
            "contact": {
                "office": "Nordenflychtsvägen 53, Hornsberg",
                "phone": "520450",
                "postgiro": "58002"
            },
            "financials": {
                "capital": "200,000 kr",
                "employees": {
                    "anställda": 150
                },
                "annual_production_value": "3,900,000 kr"
            },
            "foundation_year": 1931,
            "owners": [
                "AB. Stockholms Bryggerier"
            ],
            "board": [
                {
                    "name": "Sven Schwartz",
                    "role": "ordf."
                },
                {
                    "name": "Martin Ahlstrand",
                    "role": "dir."
                },
                {
                    "name": "Harald Engström",
                    "role": "dir."
                },
                {
                    "name": "Harry Lundin",
                    "role": "fil. dr"
                }
            ],
            "director": "S. Schwartz",
            "managing_director": "D. Isaksson",
            "sales_manager": "E. Branell"
        },
        "4": {
            "name": "Kävlinge Clacéläderfabrik",
            "location": "Kävlinge",
            "business": "Läderfabrik"
        },
        "5": {
            "name": "Kävlinge Väveri AB.",
            "location": "Kävlinge",
            "business": "Väveri, blekeri och appreturverk",
            "products": "Tillverkar linne- och sidenvävnader. Varumärke: \"Granit-linne\".",
            "contact": {
                "phone": [
                    "1",
                    "35"
                ],
                "postgiro": "93427"
            },
            "financials": {
                "capital": "560,000 kr",
                "employees": {
                    "industriarb.": 150
                },
                "annual_production_value": "3,500,000 kr"
            },
            "foundation_year": 1935,
            "board": [
                {
                    "name": "Ingemar Ekblom",
                    "role": "ordf."
                },
                {
                    "name": "B. Engzell",
                    "role": "kamrer"
                },
                {
                    "name": "Filip Henrikson",
                    "role": "köpm."
                },
                {
                    "name": "Ernst Scholtz",
                    "role": "disp."
                },
                {
                    "name": "Oscar Scholtz",
                    "role": "ing."
                },
                {
                    "name": "Gösta Skoglund",
                    "role": "köpm."
                }
            ],
            "director": "I. Ekblom",
            "managing_director": "Oscar Scholtz"
        },
        "6": {
            "name": "Kölefors Vaddfabrik",
            "location": "Kölefors",
            "business": "Vaddfabrik",
            "products": "Tillverkar flock och vadd till täcken och madrasser samt för stoppning av möbler vid fabrik i Kölefors (Östergötl. 1.).",
            "contact": {
                "phone": "Kisa 36",
                "postgiro": "25990"
            },
            "employees": {
                "industriarb.": 2
            },
            "foundation_year": 1937,
            "manager": "Karl Erik Fransson"
        },
        "7": {
            "name": "AB. Köpings Armaturfabrik",
            "location": "Köping",
            "business": "Tillverkar armatur för gas, vatten, värme och ånga",
            "products": "Förnicklad och förkromad sanitetsarmatur samt metallgjutgods.",
            "contact": {
                "phone": [
                    "406",
                    "806"
                ],
                "postgiro": "13099"
            },
            "financials": {
                "capital": "300,000 kr",
                "employees": {
                    "industriarb.": 200
                },
                "annual_production_value": "2,400,000 kr"
            },
            "corporation_year": 1941,
            "board": [
                {
                    "name": "Carl Nyqvist",
                    "role": "ombudsm."
                },
                {
                    "name": "P. Ekström",
                    "role": "ing."
                },
                {
                    "name": "Ewert Johnsson",
                    "role": "dir."
                },
                {
                    "name": "Birger Nyqvist",
                    "role": "ing."
                },
                {
                    "name": "A. Vanas",
                    "role": "jur. kand."
                }
            ],
            "director": "Ewert Johnsson"
        },
        "8": {
            "name": "Köpings Bryggeri AB.",
            "location": "Köping",
            "business": "Bryggeri",
            "products": "Tillverkar malt-och läskedrycker.",
            "contact": {
                "telegraph": "Bryggeribolaget",
                "phone": "5",
                "postgiro": "80618"
            }
        }
    }
}