{
    "original": "Goes—Gotland\n\nGoés Rltbyrå &amp; Klichéanstalt,\n\nGöteborg.\n\nTillverkar klichéer, teckningar,\nre-tuscher, # kopparfällningar och gravyrer\nför grafiskt ändamål.\n\nKontor: Postg. 15. Telefon: 136829 o.\n138640. Postgiro: 40201. — Antal\nindn-striarb.: 26. — Firman etabl. 1905.\n\nÄgare chef: fabr. Gustaf Hagelqvist.\n\nGokef, Gas- o. Koksverkens\nEkonomiska Förening u. p. a.,\n\nStockholm.\n\nFöreningen utgör försaljningsorganisar\ntion för gas- och koksverkens biprodukter\nsåsom stenkolstjära och tjäroljor, beck,\nkreosotolja, bensol, toluol, solventnafta,\nxylol, ammoniumsulfat, kaustik ammoniak\noch naftalin m. fl. Varumärke: »Gökef».\n\nKontor: Florag. 14; postadr.: Box\n5044, Stockholm 5. Telegr.-adr.: Gokef,\nStockholm. Telefon: 233565. Postgiro:\n2035.\n\nInsatskap.: 200,550 kr. Försäljn.-värde\npr år: 10,200,000 kr. — Föreningen\nbildad, 1918.\n\nStyrelse: borgarrådet Harald\nGöransson (ordf.), dir. Sven A. Andersson,\növering. Bengt Dahlman, driftsing. Valter\nFredriksson, dir. Ivar Kull, dir. Hildor\nMedin, dir. Harry Tham.\n\nVerkst. dir*: Folke Bjurner.\n\n(Jfr annons nr 52.)\n\n*Gonäs Gruvor, Gonäs.\n\nSe Gruf AB. Dalarne, Falun.\n\n*Goodyear Gummi Fabriks AB.,\n\nStockholm.\n\nTillverkar automobilringar (ytterdäck\noch innerslangar) samt klackar ock sulor\nav gummi vid fabrik i Norrköping.\n\nKontor: Stockholm, Jungfrug. 58.\nTe-legr.-adr.: Goodyear, Stockholm. Telefon:\n670530. Postgiro: 4604.\n\nAkt.-kap.: 6,500,000 kr. Antal\nindustriarb.: 240.\n\nBolaget grundat 1920 under namn\nGummi AB. Goodyear, fabriken anlagd\noch nuv. namn antaget 1939.\n\nStyrelse: landshövd. Bo Hammarskjöld\n(ordf.), försäljn.-chef Birger Asplund,\ndir. P. W. Litchfield, dir. Thure\nHelander, adv. Axel T. Nilsson, bankdir.\nHarens, Wallenberg.\n\nVerkst. dir.: Thure Helander.\n\nKassadir.: Willard R. Booth.\n\nDisp.: John J. Hoesly.\n\nFörsäljn.-chef: Birger Asplund.\n\n*Gothla Maskinfabrik, Höör.\n\nSe Maskinfabriks AB. Gothia, Höör.\n\n*tl. A. Gothnells Fabriks- &amp;\nHandels-Bölag, Vännåsby.\n\nHöbelfabrik i Vännäsby (Västerb. l.).\nTillverkar herrums-, matsals- och\nsovrumsmöbler samt inredningar.\n\nHuvudkontor: Vännäsby. Telegr.-adr.:\nGothnell, Vännäsby. Telefon: 11 o. 34.\nPostgiro: 62140. Avd.-kontor:\nHalmberget, Piteå, Umeå, Östersund o. Kiruna.\n\nTillv.-värde pr år: 500,000 kr. —\nFirman etabl. 1921.\n\nÄgare o. chef: disp. J. A. Gothnell.\n\nKontorschef: kamrer H. Emanuelson.\n\n*AB. Gotlands Katfcterk, SUté.\n\nKalkstensbrott i Storugns (postadr.:\nLärbro), Hide och S:t Olofsholm\n(postadr.: Hellvi), samtliga på Gotland med\negna hamnar, varifrån levereras rå\nkalksten för olika ändamål.\n\nHuvudkontor: Slité. Telefon: »Slite\ncement». Avd.-kontor: Stockholm, Norr\nHälarstrand 22. Telegr.-adr.:\nKalkbrotten, Stockholm. Telefon: »Karta-Oaxen».\n\nAkt.-kap.: 800,000 kr. Antal\nindustriarb.: 115. Prod.-värde pr år: 700,000 kr.\n— Bolaget grundades 1906.\n\nStyrelse: dir. Ernst Wehtje (ordf.),\ndir. Axel Norman, dir. A. Rothstein, dir.\nHalte Ström.\n\nVerkst. dir.: A. Rothstein (Stockholm).\n\nTehn. dir.: Arendt de Jounge (Slite).\n\nGotlandsmarmor, Nya AB., Visby.\n\nSe Nya AB. Gotlandsmarmor, Visby.\n\n*Gotlands Nya Tegelbruks AB.y\n\nVisby.\n\nTillverkar murtegel och dräneringsrör.\n\nTelefon: »Centralföreningen». —\nAkt.-kap.: 43,000 kr. Antal industriarb.: 25.\nÅrsprod.: 2 milj. st. tegelvaror. —\nBolaget grundat 1915.\n\nVerkst. dir.: Gustaf Nelson.\n\nGotlands Slipstensbolag, Hugo\nHansén &amp; Co., Burgsvik.\n\nTillverkar slipstenar och brynstenar\nvid fabrik i Burgsvik (Gottl, l.).\n\nTelegr.-adr.: Slipstenbolaget, Visby.\nTelefon: Burgsvik 1. Postgiro: 70853. —\nAntal industriarb.: 40. Prod.-värde pr år:\n300,000 kr. — Firman etabl. 1873.\n\nÄgare o. chef: grosshandl. Victor\nHansén.",
    "structured": {
        "1": {
            "name": "Goés Rltbyrå & Klichéanstalt",
            "location": "Göteborg",
            "business": "Tillverkar klichéer, teckningar, re-tuscher, kopparfällningar och gravyrer för grafiskt ändamål",
            "contact": {
                "office": "Postg. 15",
                "phone": [
                    "136829",
                    "138640"
                ],
                "postgiro": "40201"
            },
            "financials": {
                "employees": {
                    "industriarb": 26
                },
                "capital": "Ej tillgänglig",
                "annual_turnover": "Ej tillgänglig",
                "annual_production_value": "Ej tillgänglig"
            },
            "foundation_year": 1905,
            "current_name_year": null,
            "predecessor": null,
            "original_name": null,
            "corporation_year": null,
            "board": null,
            "owners": null,
            "director": "Gustaf Hagelqvist",
            "managing_director": null,
            "sales_manager": null,
            "manager": null
        },
        "2": {
            "name": "Gokef, Gas- o. Koksverkens Ekonomiska Förening u. p. a.",
            "location": "Stockholm",
            "business": "Försaljningsorganisar tion för gas- och koksverkens biprodukter",
            "contact": {
                "office": "Florag. 14",
                "phone": [
                    "233565"
                ],
                "postgiro": "2035",
                "telegraph": "Gokef, Stockholm"
            },
            "financials": {
                "employees": {
                    "industriarb": "Ej tillgänglig"
                },
                "capital": "200,550 kr",
                "annual_turnover": "10,200,000 kr",
                "annual_production_value": "Ej tillgänglig"
            },
            "foundation_year": 1918,
            "current_name_year": null,
            "predecessor": null,
            "original_name": null,
            "corporation_year": null,
            "board": [
                {
                    "name": "borgarrådet Harald Göransson",
                    "role": "ordf"
                },
                {
                    "name": "dir. Sven A. Andersson",
                    "role": null
                },
                {
                    "name": "övering. Bengt Dahlman",
                    "role": null
                },
                {
                    "name": "driftsing. Valter Fredriksson",
                    "role": null
                },
                {
                    "name": "dir. Ivar Kull",
                    "role": null
                },
                {
                    "name": "dir. Hildor Medin",
                    "role": null
                },
                {
                    "name": "dir. Harry Tham",
                    "role": null
                }
            ],
            "owners": null,
            "director": null,
            "managing_director": "Folke Bjurner",
            "sales_manager": null,
            "manager": null
        },
        "3": {
            "name": "AB. Gotlands Katfcterk",
            "location": "SUté",
            "business": "Kalkstensbrott i Storugns, Hide och S:t Olofsholm samtliga på Gotland med egna hamnar, varifrån levereras rå kalksten för olika ändamål",
            "contact": {
                "office": "Ej tillgänglig",
                "phone": [
                    "Ej tillgänglig"
                ],
                "postgiro": "Ej tillgänglig"
            },
            "financials": {
                "employees": {
                    "industriarb": 115
                },
                "capital": "800,000 kr",
                "annual_turnover": "Ej tillgänglig",
                "annual_production_value": "700,000 kr"
            },
            "foundation_year": 1906,
            "current_name_year": null,
            "predecessor": null,
            "original_name": null,
            "corporation_year": null,
            "board": [
                {
                    "name": "dir. Ernst Wehtje",
                    "role": "ordf"
                },
                {
                    "name": "dir. Axel Norman",
                    "role": null
                },
                {
                    "name": "dir. A. Rothstein",
                    "role": null
                },
                {
                    "name": "dir. Halte Ström",
                    "role": null
                }
            ],
            "owners": null,
            "director": null,
            "managing_director": null,
            "sales_manager": null,
            "manager": null
        },
        "4": {
            "name": "Gotlands Nya Tegelbruks AB.",
            "location": "Visby",
            "business": "Tillverkar murtegel och dräneringsrör",
            "contact": {
                "office": "Ej tillgänglig",
                "phone": [
                    "Ej tillgänglig"
                ],
                "postgiro": "Ej tillgänglig"
            },
            "financials": {
                "employees": {
                    "industriarb": 25
                },
                "capital": "43,000 kr",
                "annual_turnover": "Ej tillgänglig",
                "annual_production_value": "Ej tillgänglig"
            },
            "foundation_year": 1915,
            "current_name_year": null,
            "predecessor": null,
            "original_name": null,
            "corporation_year": null,
            "board": null,
            "owners": null,
            "director": null,
            "managing_director": "Gustaf Nelson",
            "sales_manager": null,
            "manager": null
        },
        "5": {
            "name": "Gotlands Slipstensbolag, Hugo Hansén & Co.",
            "location": "Burgsvik",
            "business": "Tillverkar slipstenar och brynstenar",
            "contact": {
                "office": "Ej tillgänglig",
                "phone": [
                    "Burgsvik 1"
                ],
                "postgiro": "70853"
            },
            "financials": {
                "employees": {
                    "industriarb": 40
                },
                "capital": "Ej tillgänglig",
                "annual_turnover": "Ej tillgänglig",
                "annual_production_value": "300,000 kr"
            },
            "foundation_year": 1873,
            "current_name_year": null,
            "predecessor": null,
            "original_name": null,
            "corporation_year": null,
            "board": null,
            "owners": null,
            "director": "grosshandl. Victor Hansén",
            "managing_director": null,
            "sales_manager": null,
            "manager": null
        }
    }
}