{
    "original": "Pershytte—Persson\n\nAkt,-kap.: 141,500 kr. Antal\nindustriarb.: 50. Tilly.-värde pr år: 500,000 kr.\n— Bruket anlagt på 1600-talet, nuv.\nbolag grundat 1910.\n\nStyrelse: generalkonsul Axel Ax:son\nJohnson (ordf.), dir. Vilhelm Björkman,\nkamrer Axel R. Johansson.\n\nVerkst. dir.: Axel Ax:son Johnson.\n\nFörvalt,: Erik Strömberg.\n\n\"Pershytte Grufvebolag, Nora.\n\nJärnmalmsgruvor i Pershyttefältet\njämte anrikningsverk i Pershyttan\n(Örebro l.). Bryter och anrikar järnmalm.\n\nKontor: Pershyttan, Nora. Telefon:\nNora 376 o. 528. Postgiro: 145342.\n\nAntal industriarb.: 80. Prod.-värde pr\når: 450,000 kr. — Bolaget började sin\nverksamhet 1867.\n\nStyrelse: disp. Walfrid Eriksson\n(ordf.), disp. Axel L:son Alarik, ing.\nErik Frykholm, bergsing. Axel Ax:son\nJohnson J:or.\n\nGruvförvalt.: Erik Frykholm.\n\nPerspektivfönster AB., Sundsvalls,\n\nStockholm.\n\nSe Sundsvalls Perspektivfönster AB.,\nStockholm.\n\nPerson, Pehrson, Persson, Pehrsson.\n\nAlfred Perssons Snickerifabrik,\n\nMalmö.\n\nTillverkar möbler och\naffärsinredningar.\n\nKontor: Baltzarsg. 16. Telefon: 23991.\nPostgiro: 148914. — Arb.-antal: 6.\nTillv.-värde pr år: 70,000 kr. — Firman\netabl. 1908.\n\nÄgare o. chef: fabr. Alfred Persson.\n\n\"Anders Perssons Skidfabrik,\n\nBollnäs.\n\nTillverkar spec. björk- och\nhickoryski-dor vid fabrik i Bollnäs (Gävleb. l.).\n\nTelefon: 10441 o. 11391. Postgiro:\n96300. — Antal industriarb.: 20. —\nFirman etabl. 1914.\n\nÄgare: Anders Perssons sterbhus.\n\nChef: fabr. Valdemar Persson.\n\n\"AB. August Perssons\nEkmöbel-fabrik, Bjärnum.\n\nTillverkar matsalsmöbler i ek samt\nskrivbord vid fabrik i Bjärnum\n(Kristianst. l.).\n\nTelefon: 40. Postgiro: 86272. — Akt.-\n\nkap.: 11,600 kr. Arb.-antal: 11.\nTillv.-värde pr år: 100,000 kr. — Firman etabl.\n1913, bolag 1925.\n\nStyrelse o. verkst. dir.: Gunnar\nLindberg.\n\n\"Bernh. Perssons Cjuteri, Malmö.\n\nTillverkar gjutgods, spec. golvbrunnar,\ngolvbrunnsförlängningar, b ak vatten\nventiler och vattenlås (märke: »B. P.»).\n\nKontor: Västanforsg. Telefon: 23775.\nPostgiro: 38524. — Antal industriarb.:\n50. Tillv.-värde pr år: 450,000 kr. —\nFirman etabl. 1921.\n\nÄgare o. chef: fabr. Bernh. Persson.\n\n\"Birger Pehrsons Byggnads AB„\n\nBoras’.\n\n1\n\nByggnadsentreprenörfirma för\nbostads-och affärshus, industribyggnader m. m.\nsamt snickerifabrik för eget behov.\n\nTelefon: 17630. Postgiro: 140857.\n\nAkt.-kap.: 150,000 kr. — Firman etabl.\n1921, bolag 1939.\n\nStyrelse: byggm. Birger Pehrson\n(ordf.), disp. Axel Hellers, civiling.\nGustaf Hellers.\n\nVerkst. dir.: Birger Pehrson.\n\n*B. E. Persson, Skofabrik, Malung.\n\nSkofabrik i Malung (Kopparb. l.).\nTillverkar handgjorda grövre skodon,\norienteringskängor och spikskor (»Malung»)\nsamt skidpjäxor (märken: »Lake Placid»\no. »Vasaloppspjäxan»).\n\nTelefon: 99. Postgiro: 73617. Repr.:\nköpman Folke Anderson, Smålandsg. 10,\nStockholm, telefon: 108398 o. 108598;\nFilipstad: köpman Harald Carlsson,\ntelefon: 399.\n\nAntal industriarb.: 35. Tillv.-värde pr\når: 500,000 kr. — Firman etabl. 1900.\n\nÄgare o. chef: fabr. B. Erik Persson.\n\n*Carl Persson &amp; Söner AB., Ystad.\n\nSorterings- och förädlingsanstalt för\nalla slags avfallsråvaror såsom textila,\njärn, metall, gummi, papper etc.,\nkonstull-fabrik och metallsmälteri, s vinhår\nsbered-ning för stoppningsändamål. Tillverkar\nkonstull (shoddy). Firman driver även\nengroshandel . med textilförnödenheter,\nsäckar, byggnadsjärn och räls.\n\nTelegr.-adr. o. telefon: Persöner, Ystad.\nPostgiro: 75085.\n\nAkt.-kap.: 1,500,000 kr. Antal\nindustriarb. : 235. — Firman etabl. 1B95, nuv.\nbolag 1929. Bolaget äger AB.\nAvfallsråvaror.\n\n436*",
    "structured": {
        "1": {
            "name": "Pershytte—Persson",
            "location": "Nora",
            "business": "Järnmalmsgruvor i Pershyttefältet jämte anrikningsverk i Pershyttan (Örebro l.). Bryter och anrikar järnmalm.",
            "contact": {
                "office": "Pershyttan, Nora",
                "phone": [
                    "Nora 376",
                    "Nora 528"
                ],
                "postgiro": "145342"
            },
            "financials": {
                "capital": "141,500 kr",
                "employees": {
                    "industriarb": 50
                },
                "annual_turnover": "500,000 kr"
            },
            "foundation_year": 1910,
            "board": [
                {
                    "name": "generalkonsul Axel Ax:son Johnson",
                    "role": "ordf."
                },
                {
                    "name": "dir. Vilhelm Björkman",
                    "role": null
                },
                {
                    "name": "kamrer Axel R. Johansson",
                    "role": null
                }
            ],
            "director": "Axel Ax:son Johnson"
        },
        "2": {
            "name": "Pershytte Grufvebolag",
            "location": "Nora",
            "business": "Järnmalmsgruvor i Pershyttefältet jämte anrikningsverk i Pershyttan (Örebro l.). Bryter och anrikar järnmalm.",
            "contact": {
                "office": "Pershyttan, Nora",
                "phone": [
                    "Nora 376",
                    "Nora 528"
                ],
                "postgiro": "145342"
            },
            "financials": {
                "employees": {
                    "industriarb": 80
                },
                "annual_turnover": "450,000 kr"
            },
            "foundation_year": 1867,
            "board": [
                {
                    "name": "disp. Walfrid Eriksson",
                    "role": "ordf."
                },
                {
                    "name": "disp. Axel L:son Alarik",
                    "role": null
                },
                {
                    "name": "ing. Erik Frykholm",
                    "role": null
                },
                {
                    "name": "bergsing. Axel Ax:son Johnson J:or",
                    "role": null
                }
            ],
            "director": null,
            "managing_director": null
        },
        "3": {
            "name": "Alfred Perssons Snickerifabrik",
            "location": "Malmö",
            "business": "Tillverkar möbler och affärsinredningar.",
            "contact": {
                "office": "Baltzarsg. 16",
                "phone": [
                    "23991"
                ],
                "postgiro": "148914"
            },
            "financials": {
                "capital": null,
                "employees": {
                    "total": 6
                },
                "annual_turnover": "70,000 kr"
            },
            "foundation_year": 1908,
            "owner": "fabr. Alfred Persson",
            "manager": "Alfred Persson"
        },
        "4": {
            "name": "Anders Perssons Skidfabrik",
            "location": "Bollnäs",
            "business": "Tillverkar spec. björk- och hickoryski-dor vid fabrik i Bollnäs (Gävleb. l.).",
            "contact": {
                "phone": [
                    "10441",
                    "11391"
                ],
                "postgiro": "96300"
            },
            "financials": {
                "employees": {
                    "total": 20
                }
            },
            "foundation_year": 1914,
            "owner": "Anders Perssons sterbhus",
            "manager": "Valdemar Persson"
        },
        "5": {
            "name": "AB. August Perssons Ekmöbelfabrik",
            "location": "Bjärnum",
            "business": "Tillverkar matsalsmöbler i ek samt skrivbord vid fabrik i Bjärnum (Kristianst. l.).",
            "contact": {
                "phone": [
                    "40"
                ],
                "postgiro": "86272"
            },
            "financials": {
                "capital": "11,600 kr",
                "employees": {
                    "total": 11
                },
                "annual_turnover": "100,000 kr"
            },
            "foundation_year": 1913,
            "director": null,
            "owner": null
        },
        "6": {
            "name": "Bernh. Perssons Cjuteri",
            "location": "Malmö",
            "business": "Tillverkar gjutgods, spec. golvbrunnar, golvbrunnsförlängningar, b ak vatten ventiler och vattenlås (märke: »B. P.»).",
            "contact": {
                "office": "Västanforsg.",
                "phone": [
                    "23775"
                ],
                "postgiro": "38524"
            },
            "financials": {
                "employees": {
                    "total": 50
                },
                "annual_turnover": "450,000 kr"
            },
            "foundation_year": 1921,
            "owner": "fabr. Bernh. Persson",
            "manager": "Bernh. Persson"
        },
        "7": {
            "name": "Birger Pehrsons Byggnads AB",
            "location": "Boras",
            "business": "Byggnadsentreprenörfirma för bostads-och affärshus, industribyggnader m. m. samt snickerifabrik för eget behov.",
            "contact": {
                "phone": [
                    "17630"
                ],
                "postgiro": "140857"
            },
            "financials": {
                "capital": "150,000 kr"
            },
            "foundation_year": 1921,
            "board": [
                {
                    "name": "byggm. Birger Pehrson",
                    "role": "ordf."
                },
                {
                    "name": "disp. Axel Hellers",
                    "role": null
                },
                {
                    "name": "civiling. Gustaf Hellers",
                    "role": null
                }
            ],
            "manager": "Birger Pehrson"
        },
        "8": {
            "name": "B. E. Persson, Skofabrik",
            "location": "Malung",
            "business": "Tillverkar handgjorda grövre skodon, orienteringskängor och spikskor (»Malung») samt skidpjäxor (märken: »Lake Placid» o. »Vasaloppspjäxan»).",
            "contact": {
                "phone": [
                    "99"
                ],
                "postgiro": "73617"
            },
            "financials": {
                "employees": {
                    "total": 35
                },
                "annual_turnover": "500,000 kr"
            },
            "foundation_year": 1900,
            "owner": "fabr. B. Erik Persson",
            "manager": "B. Erik Persson"
        },
        "9": {
            "name": "Carl Persson & Söner AB",
            "location": "Ystad",
            "business": "Sorterings- och förädlingsanstalt för alla slags avfallsråvaror såsom textila, järn, metall, gummi, papper etc., konstullfabrik och metallsmälteri, s vinhår sberedning för stoppningsändamål. Tillverkar konstull (shoddy). Firman driver även engroshandel med textilförnödenheter, säckar, byggnadsjärn och räls.",
            "contact": {
                "telegraph": "Persöner, Ystad",
                "phone": null,
                "postgiro": "75085"
            },
            "financials": {
                "capital": "1,500,000 kr",
                "employees": {
                    "total": 235
                }
            },
            "foundation_year": 1895
        }
    }
}