{
    "original": "B e rg l öf—Be rgsb n 11111 a\n\nAB. Gustaf A. Berglöf Trikåfabrik,\n\nUppsala.\n\nTillverkar trikåvaror såsom jumpers,\nkoftor, pullovers, slipovers, bäddjackor,\nbaddräkter, barnkläder, äkta\nkamelhårs-artiklar ^imt sydda dam- och barnblusar.\nVarumärke: Gabu.\n\nTelefon: 39675. Postgiro: 36160. —\nAkt.-kap.: 50,000 kr. Antal industriarb.:\n60. Tillv.-värde pr år: 700.000 kr. —\nFirman etabl. 1865, bolag 1935, nuv.\nfirmanamn 1940.\n\nStyrelse: köpm. Ernst Berglöf, notarie\nGunnar Berglöf, disp. Sten A. Berglöf.\nfru K. M. Brodd, frn K. E. Olovson.\n\nChef: disp. Sten A. Berglöf.\n\n*AB. Berglöfs Verkstäder,\n\nKopparberg.\n\nMek. verkstad i Kopparberg (Örebro\n1.). Tillverkar järnkonstruktioner, grövre\nplåtarbeten, järnfönster, svetsade rör\noch rördelar.\n\nTelefon: »Berglöfs Verkstäder».\nPostgiro: 132520.\n\nAkt.-kap.: 250,000 kr. Antal\nindustriarb.: 55. Tillv.-värde pr år: 1,000,000 kr.\n\n—\tFirman etabl. omkr. 1890 under namn\nGuillaumes Verkstäder, nuv. bolag\ngrundat 1936.\n\nStyrelse: dir. Sven G. Lind (ordf.),\ning. Gösta Berglöf, fru Inga Lind.\n\nVerkst. dir.: Gösta, Berglöf.\n\nKamrer: L. Fel dt.\n\nInköps- o. försäljn.-chef: Rune\nMagnuson.\n\n*AB. Bergmans Chuckfabrik,\n\nTyringe.\n\nMek. verkstad i Tyringe (Kristianst.\n1.). Tillverkar svarv- och borrchuckar,\nbackskivor, fräsar, brotchar, skruvstycken,\nskruv u td ragare in. m. Varumärken:\n»Bergmans» o. »Riina» (Käiigkloppor o.\ngängbackar).\n\nTelegr.-adr.: Chuckfabriken, Tyringe.\nTelefon: 69 o. 309. Postgiro: 11360.\n\n—\tAkt.-kap.: 100,000 kr. Antal\nindustriarb.: 75. Tillv.-värde pr år: 850,000 kr.\n\nStyrelse o. verkst. dir.: Petrus W.\nBergman.\n\nDisp.: Åke Bergman.\n\nKamrer: Bertil Bergman.\n\nAB. A. U. Bergmans Enka,\n\nStockholm.\n\nSpis- och knäckebrödsfabrik.\n\nKontor: Högbergsg. 62. Telegr.-adr.:\n\nBergmansbröd, Stockholm. Telefon:\n401203 o. 433105.\n\nAkt.-kap.: 5,000 kr. Antal industriarb.:\n160. Tillv.-värde pr år: 3,500,000 kr. —\nFirman etabl. 1850, bolag 1941, äges av\nAB. Wasa Spisbrödsfabrik.\n\nVerkst. dir.: konsul K. E. Lundström.\n\nDisp.: A. Lindström.\n\n*C. J. Bergmans Eftr. Möbel\nverkstäder AB., Malmö.\n\nTillverkar möbler i antika och moderna\nstilar samt utför rumsinredningar.\n\nKontor: Djäkneg. 5. Telefon: 20315,\n13297 o. 10789. — Akt.-kap.: 54,000 kr.\nArb.-antal: 10. — Firman etabl. 1848,\nbolag 1944.\n\nStyrelse: möbelark. Oscar Palmkvist\n(ordf.), fabr. Ture Palmkvist.\n\nVerkst. dir.: Oscar Palmkvist.\n\nHj. Bergman, Skobandfabrik,\n\nÖrebro.\n\nTillverkar sko- och pjäxband samt\nkängsnören.\n\nTelefon: 14082. Postgiro: 91566. —\nAntal industriarb.: 6. — Firman etabl.\n1935.\n\nÄgare o. chef: fabr. Hjalmar Bergman.\n\nDisp.: C. Gösta Bergman.\n\n*AB. W. Dan Bergman, Södertälje.\n\nAluminium- och elektrongjuteri,\npresssmedja samt mek. verkstad. Specialiteter:\nelektron, hydronalium, hiduminium\nRR-legeringar, värmebehandlat\naluminium-och elektrongjutgods av hög hållfasthet i\nsand och kokill samt pressgjutgöds,\n\nTelegr.-adr.: Wedametall, Södertälje.\nTelefon: »Wedaverken». Postgiro: 1245.\n\nAkt.-kap.: 3,000,000 kr. Antal\nindustriarb.: 350. Tillv.-värde pr år: 6.000,000 kr.\n— Firman, etabl. 1919, bolag 1939, äges\nav AB. Bofors.\n\nStyrelse: disp. Evert Wijkander (ordf.),\nciviling. W. Dan Bergman, dir. Gustaf\nLarson, dir. Sven G. Lind. dir. A.\nWahl-steen, konteramiral E. Wetter.\n\nVerkst. dir.: Sven G. Lind.\n\nÖvering.: Gösta Lindh.\n\nInköpschef: Enar Löfroth.\n\nLaboratoriechef: Einar öhman.\n\nKamrer: Åke Flock.\n\n* Bergsbrunna Tegelbruk,\n\nBergsbrunna.\n\nSe AB. Mälardalens Tegelbruk,\nStockholm.\n\n41*",
    "structured": {
        "firms": [
            {
                "name": "Gustaf A. Berglöf Trikåfabrik",
                "location": "Uppsala",
                "business": "Trikåvaror manufacturing",
                "products": "Jumpers, koftor, pullovers, slipovers, bäddjackor, baddräkter, barnkläder, äkta kamelhårs-artiklar and sydda dam- and barnblusar.",
                "contact": {
                    "office": "Not provided",
                    "phone": [
                        "39675"
                    ],
                    "postgiro": "36160",
                    "head_office": "Not provided",
                    "telegraph": "Not provided"
                },
                "financials": {
                    "capital": "50,000 kr",
                    "employees": {
                        "industrial workers": 60
                    },
                    "annual_turnover": "700,000 kr"
                },
                "foundation_year": 1865,
                "current_name_year": 1940,
                "board": [
                    {
                        "name": "köpm. Ernst Berglöf",
                        "role": "Not provided"
                    },
                    {
                        "name": "notarie Gunnar Berglöf",
                        "role": "Not provided"
                    },
                    {
                        "name": "disp. Sten A. Berglöf",
                        "role": "Not provided"
                    },
                    {
                        "name": "fru K. M. Brodd",
                        "role": "Not provided"
                    },
                    {
                        "name": "frn K. E. Olovson",
                        "role": "Not provided"
                    }
                ],
                "director": "disp. Sten A. Berglöf"
            },
            {
                "name": "Berglöfs Verkstäder",
                "location": "Kopparberg",
                "business": "Mek. verkstad",
                "products": "Järnkonstruktioner, grövre plåtarbeten, järnfönster, svetsade rör and rördelar.",
                "contact": {
                    "office": "Not provided",
                    "phone": [
                        "Berglöfs Verkstäder"
                    ],
                    "postgiro": "132520",
                    "head_office": "Not provided",
                    "telegraph": "Not provided"
                },
                "financials": {
                    "capital": "250,000 kr",
                    "employees": {
                        "industrial workers": 55
                    },
                    "annual_turnover": "1,000,000 kr"
                },
                "foundation_year": "Not provided",
                "corporation_year": 1936,
                "board": [
                    {
                        "name": "dir. Sven G. Lind",
                        "role": "ordf."
                    },
                    {
                        "name": "ing. Gösta Berglöf",
                        "role": "Not provided"
                    },
                    {
                        "name": "fru Inga Lind",
                        "role": "Not provided"
                    }
                ],
                "director": "Gösta Berglöf"
            },
            {
                "name": "Bergmans Chuckfabrik",
                "location": "Tyringe",
                "business": "Mek. verkstad",
                "products": "Svarv- and borrchuckar, backskivor, fräsar, brotchar, skruvstycken, skruv u td ragare in. m.",
                "contact": {
                    "office": "Not provided",
                    "phone": [
                        "69",
                        "309"
                    ],
                    "postgiro": "11360",
                    "head_office": "Not provided",
                    "telegraph": "Chuckfabriken, Tyringe"
                },
                "financials": {
                    "capital": "100,000 kr",
                    "employees": {
                        "industrial workers": 75
                    },
                    "annual_turnover": "850,000 kr"
                },
                "foundation_year": "Not provided",
                "corporation_year": "Not provided",
                "board": [
                    {
                        "name": "Petrus W. Bergman",
                        "role": "Not provided"
                    },
                    {
                        "name": "Åke Bergman",
                        "role": "disp."
                    },
                    {
                        "name": "Bertil Bergman",
                        "role": "Not provided"
                    }
                ]
            },
            {
                "name": "A. U. Bergmans Enka",
                "location": "Stockholm",
                "business": "Spis- and knäckebrödsfabrik",
                "contact": {
                    "office": "Högbergsg. 62",
                    "phone": [
                        "401203",
                        "433105"
                    ],
                    "postgiro": "Not provided",
                    "head_office": "Not provided",
                    "telegraph": "Bergmansbröd, Stockholm"
                },
                "financials": {
                    "capital": "5,000 kr",
                    "employees": {
                        "industrial workers": 160
                    },
                    "annual_turnover": "3,500,000 kr"
                },
                "foundation_year": 1850,
                "corporation_year": 1941,
                "owner": "AB. Wasa Spisbrödsfabrik",
                "director": "konsul K. E. Lundström",
                "disp": "A. Lindström"
            },
            {
                "name": "C. J. Bergmans Eftr. Möbel verkstäder AB.",
                "location": "Malmö",
                "business": "Möbel manufacturing",
                "products": "Möbler in antika and moderna stilar and rumsinredningar.",
                "contact": {
                    "office": "Djäkneg. 5",
                    "phone": [
                        "20315",
                        "13297",
                        "10789"
                    ],
                    "postgiro": "Not provided",
                    "head_office": "Not provided"
                },
                "financials": {
                    "capital": "54,000 kr",
                    "employees": {
                        "industrial workers": 10
                    }
                },
                "foundation_year": 1848,
                "corporation_year": 1944,
                "board": [
                    {
                        "name": "möbelark. Oscar Palmkvist",
                        "role": "ordf."
                    },
                    {
                        "name": "fabr. Ture Palmkvist",
                        "role": "Not provided"
                    }
                ],
                "director": "Oscar Palmkvist"
            },
            {
                "name": "Hj. Bergman, Skobandfabrik",
                "location": "Örebro",
                "business": "Tillverkar sko- and pjäxband samt kängsnören.",
                "contact": {
                    "office": "Not provided",
                    "phone": [
                        "14082"
                    ],
                    "postgiro": "91566",
                    "head_office": "Not provided"
                },
                "financials": {
                    "employees": {
                        "industrial workers": 6
                    }
                },
                "foundation_year": 1935,
                "owner": "fabr. Hjalmar Bergman",
                "disp": "C. Gösta Bergman"
            },
            {
                "name": "W. Dan Bergman, Södertälje",
                "location": "Södertälje",
                "business": "Aluminium- and elektrongjuteri, presssmedja samt mek. verkstad",
                "products": "elektron, hydronalium, hiduminium, värmebehandlat aluminium-och elektrongjutgods in sand and kokill samt pressgjutgöds.",
                "contact": {
                    "office": "Not provided",
                    "phone": [
                        "Wedaverken"
                    ],
                    "postgiro": "1245",
                    "head_office": "Not provided",
                    "telegraph": "Wedametall, Södertälje"
                },
                "financials": {
                    "capital": "3,000,000 kr",
                    "employees": {
                        "industrial workers": 350
                    },
                    "annual_turnover": "6,000,000 kr"
                },
                "foundation_year": 1919,
                "corporation_year": 1939,
                "owner": "AB. Bofors",
                "board": [
                    {
                        "name": "disp. Evert Wijkander",
                        "role": "ordf."
                    },
                    {
                        "name": "civiling. W. Dan Bergman",
                        "role": "Not provided"
                    },
                    {
                        "name": "dir. Gustaf Larson",
                        "role": "Not provided"
                    },
                    {
                        "name": "dir. Sven G. Lind",
                        "role": "Not provided"
                    },
                    {
                        "name": "dir. A. Wahl-steen",
                        "role": "Not provided"
                    },
                    {
                        "name": "konteramiral E. Wetter",
                        "role": "Not provided"
                    }
                ],
                "director": "Sven G. Lind",
                "overing": "Gösta Lindh",
                "inköpschef": "Enar Löfroth",
                "laboratoriechef": "Einar öhman",
                "kamrer": "Åke Flock"
            }
        ]
    }
}