{
    "original": "8 mith—S måland\n\nT. D. Smith AB^ SUchholm.\n\nRadiofabrik. Tillverkar radioapparater,\nförstärkareanläggningar och\nsnabbtelefoner. Varumärke: »Smith Radio».\n\nKontor: Humlegårdsg. 17. Telegr.-adr.:\nRadiosmith, Stockholm. Telefon: 600404\no. 600421. Postgiro: 194700.\n\nAkt.-kap.: 75,000 kr. Antal\nindustriarb.: 14. — Bolaget grundat ’1943.\n\nStyrelse o. verkst. dir.: Tom Smith.\n\nFörsäljn.-chef: Sture Hedlund.\n\nDriftsing.: Claes Jansson.\n\n*Småland, Tryckeri AB., Jönköping.\n\nSe Tryckeri AB. Småland, Jönköping.\n\n*Smålands Bandfabrik, Lemke &amp;\nSöner, Skillingaryd.\n\nTillverkar bomulls- och eellullband\nsåsom axelband, korsettband, garnering- och\nspensband, spetsar, möbel- och\nlampskärmsband, band för reseffekter,\nindiaband, möbelsnören m. m. vid fabrik i\nSkillingaryd (Jönköp. l.).\n\nTelefon: 47. Postgiro: 92433. —\nAntal industriarb.: 10. Tillv.-värde pr år:\n120,000 kr. — Firman grundad 1934.\n\nÄgare o. chefer: fabr. Otto Lemke,\nverkm. Ernst Lemke, textiltekniker\nWaldemar Lemke o. kontorist Rolf Lemke.\n\n*A B. Smålands Bryggerier,\n\nJ önköping.\n\nBryggeri och läskedrycksfabrik i\nJönköping och Eksjö. Tillverkar\nmaltdrycker, kolsyrade vatten och söta\nläskedrycker.\n\nTelefon: Jönköping »Krönleins\nBryggeri» ; Eksjö 24 o. 116. Postgiro:\n134420.\n\nAkt.-kap.: 1,300,000 kr. Antal\nindustriarb.: i Jönköping 47, i Eksjö 17.\nTillv.-värde pr år: 2,000,000 kr.\n\nBolaget bildat 1929 genom\nsammanslagning av Krönleins Bryggeri AB.,\nJönköping, grundat 1902, och Egnells\nBryggeri. Eksjö, errundat 1914.\n\nStyrelse: disp. Franz Hartmann (ordf.),\nfru Maj Egnell, bryggm. Per-Gösta Egnell,\nfil. lic. John Lennart Hartmann.\n\nVerkst. dir.: Harry Rosander.\n\nBryggm.: i Jönköping: K.-A. Bjärle; i\nEksjö: Gösta Jonsson.\n\nSmålands Kraft AB., Nässjö.\n\nElektr. kraftverk vid Klinte,\nBrunns-hult, Ädelfors, Axelfors, Aneby, Stalpet\no. Högebro (samtl. i Jönköp. l.),\nViss-kvarn och Ånestad (Östergötl. l.) samt\n\n32\n\nBrännebro (Kalmar l.), Distribuerar\n\nelektr4 energi.\n\nKontor: Nässjö. Telegr.-adr.:\nSmålandskraft, Nässjö. Telefon: Nässjö 523.\nPostgiro: 30880.\n\nAkt.-kap.: 5,400,000 kr. Distrib.-värde\npr år: 2,900,000 kr.\n\nBolaget, grundat 1918, äges av AB.\nSkandinaviska Elektricitetsverk.\n\nStyrelse: dir, Gustaf Ekström, dir.\nThorsten Ericson, dir. John Lindström,\növering. T. Staaf, dir. Emil Sundberg.\nVerkst. dir.: Gustaf Ekström.\nKamrer: Olof Stenström.\nDriftsing.: E. Brenke.\n\nAB. Smålands Skoindustri,\n\nLjungby.\n\nTillverkar skodon. Varumärke:\n»Bull-doggskor».\n\nTelefon: 306 o. 616. Postgiro: 76181.\nAkt.-kap.: 60,000 kr. Antal\nindustriarb.: 40. Tillv.-värde pr år: 700,000 kr.\n\n—\tBolaget grundat 1931.\n\nChefer: disp. Gustaf Magnusson o. fabr.\nGunnar Peterson.\n\n*AB. Smålands Taberg, Hedemora.\n\nGruvdrift vid Smålands Taberg\n(Jönköp. l.). Bryter järnmalm.\n\nKontor: Hedemora. Telefon: 749.\nPostgiro: 159006.\n\nAkt.-kap.: 800,000 kr. Antal\nindustriarb.: 15. — Bolaget grundat 1939.\n\nStyrelse: disp. Algot Goldkuhl (ordf.),\nombudsm. Birger Barth-Magnus.\n\nSmålands Vaddindustri, Eksjö.\n\nTillverkar vadd, flock, madrasser m. m.\nvid fabrik i Eksjö (Jönköp. l.).\n\nTelefon: 244. Postgiro: 98165. —\nAntal industriarb.: 4. Tillv.-värde pr år:\n30,000 kr. — Firman etabl. 1929.\nÄgare o. chef: fabr. Arvid Forsgren.\n\n*Smålands Yllefabriks AB., Lagan.\n\nUllspinneri, väveri, färgeri, vadd-,\ntäck-och madrassfabrik i Lagan (Kronob. l.).\nTillverkar garner, ylletyger, filtar, vadd,\ntäcken och madrasser m. m. Varumärke:\n»Lagans».\n\nTelegr.-adr.: Yllefabriken, Lagan.\nTelefon: 1, 25, 50 o. 75. Postgiro: 14900.\nKontor i Stockholm: Sveavägen 25—27,\ntelefon: 116228 o. 111312.\n\nAkt.-kap.: 390,000 kr. Antal\nindustriarb.: 200. Tillv.-värde pr år: 3,000,000 kr.\n\n—\tBolaget grundat 1914.",
    "structured": {
        "1": {
            "name": "T. D. Smith AB",
            "location": "Stockholm",
            "business": "Radiofabrik",
            "products": "Tillverkar radioapparater, förstärkareanläggningar och snabbtelefoner",
            "contact": {
                "office": "Humlegårdsg. 17",
                "phone": [
                    "600404",
                    "600421"
                ],
                "postgiro": "194700",
                "telegraph": "Radiosmith, Stockholm"
            },
            "financials": {
                "capital": "75,000 kr",
                "employees": {
                    "industriarb": 14
                },
                "annual_turnover": "N/A",
                "annual_production_value": "N/A"
            },
            "foundation_year": 1943,
            "board": [
                {
                    "name": "Tom Smith",
                    "role": "Verkst. dir."
                },
                {
                    "name": "Sture Hedlund",
                    "role": "Försäljn.-chef"
                },
                {
                    "name": "Claes Jansson",
                    "role": "Driftsing."
                }
            ]
        },
        "2": {
            "name": "Smålands Bandfabrik, Lemke & Söner",
            "location": "Skillingaryd",
            "business": "Tillverkar bomulls- och eellullband",
            "products": "axelband, korsettband, garnering- och spensband, spetsar, möbel- och lampskärmsband, band för reseffekter, indiaband, möbelsnören m. m.",
            "contact": {
                "phone": "47",
                "postgiro": "92433"
            },
            "financials": {
                "employees": {
                    "industriarb": 10
                },
                "annual_production_value": "120,000 kr"
            },
            "foundation_year": 1934,
            "owners": [
                "fabr. Otto Lemke",
                "verkm. Ernst Lemke",
                "textiltekniker Waldemar Lemke",
                "kontorist Rolf Lemke"
            ]
        },
        "3": {
            "name": "A B. Smålands Bryggerier",
            "location": "Jönköping",
            "business": "Bryggeri och läskedrycksfabrik",
            "products": "Tillverkar maltdrycker, kolsyrade vatten och söta läskedrycker",
            "contact": {
                "phone": "Krönleins Bryggeri: N/A, Eksjö: 24, 116",
                "postgiro": "134420"
            },
            "financials": {
                "capital": "1,300,000 kr",
                "employees": {
                    "i Jönköping": 47,
                    "i Eksjö": 17
                },
                "annual_turnover": "2,000,000 kr"
            },
            "corporation_year": 1929,
            "board": [
                {
                    "name": "disp. Franz Hartmann",
                    "role": "ordf."
                },
                {
                    "name": "fru Maj Egnell",
                    "role": "N/A"
                },
                {
                    "name": "bryggm. Per-Gösta Egnell",
                    "role": "N/A"
                },
                {
                    "name": "fil. lic. John Lennart Hartmann",
                    "role": "N/A"
                }
            ]
        },
        "4": {
            "name": "Smålands Kraft AB",
            "location": "Nässjö",
            "business": "Elektr. kraftverk",
            "products": "Distribuerar elektr. energi",
            "contact": {
                "office": "Nässjö",
                "phone": "Nässjö 523",
                "postgiro": "30880"
            },
            "financials": {
                "capital": "5,400,000 kr",
                "annual_turnover": "2,900,000 kr"
            },
            "foundation_year": 1918,
            "owners": [
                "AB. Skandinaviska Elektricitetsverk"
            ]
        },
        "5": {
            "name": "AB. Smålands Skoindustri",
            "location": "Ljungby",
            "business": "Tillverkar skodon",
            "products": "N/A",
            "contact": {
                "phone": "306, 616",
                "postgiro": "76181"
            },
            "financials": {
                "capital": "60,000 kr",
                "employees": {
                    "industriarb": 40
                },
                "annual_turnover": "700,000 kr"
            },
            "foundation_year": 1931,
            "board": [
                {
                    "name": "disp. Gustaf Magnusson",
                    "role": "N/A"
                },
                {
                    "name": "fabr. Gunnar Peterson",
                    "role": "N/A"
                }
            ]
        },
        "6": {
            "name": "AB. Smålands Taberg",
            "location": "Hedemora",
            "business": "Gruvdrift",
            "products": "Bryter järnmalm",
            "contact": {
                "phone": "749",
                "postgiro": "159006"
            },
            "financials": {
                "capital": "800,000 kr",
                "employees": {
                    "industriarb": 15
                }
            },
            "foundation_year": 1939,
            "board": [
                {
                    "name": "disp. Algot Goldkuhl",
                    "role": "ordf."
                },
                {
                    "name": "ombudsm. Birger Barth-Magnus",
                    "role": "N/A"
                }
            ]
        },
        "7": {
            "name": "Smålands Vaddindustri",
            "location": "Eksjö",
            "business": "Tillverkar vadd, flock, madrasser m. m.",
            "products": "N/A",
            "contact": {
                "phone": "244",
                "postgiro": "98165"
            },
            "financials": {
                "employees": {
                    "industriarb": 4
                },
                "annual_production_value": "30,000 kr"
            },
            "foundation_year": 1929,
            "owners": [
                "fabr. Arvid Forsgren"
            ]
        },
        "8": {
            "name": "Smålands Yllefabriks AB",
            "location": "Lagan",
            "business": "Ullspinneri, väveri, färgeri, vadd-",
            "products": "Tillverkar garner, ylletyger, filtar, vadd, täcken och madrasser m. m.",
            "contact": {
                "phone": "1, 25, 50, 75",
                "postgiro": "14900"
            },
            "financials": {
                "capital": "390,000 kr",
                "employees": {
                    "industriarb": 200
                },
                "annual_production_value": "3,000,000 kr"
            },
            "foundation_year": 1914
        }
    }
}