{
    "original": "Malmö\n\nStyrelse: dir. Henry Dnnker (ordf.),\ndir. Wilhelm Bahrke, greve Pontus De\nla Gardie, dir. C. F. Tranchell, bankdir.\nIvar Åkerman.\n\nVerkst. dir.: Wilhelm Bahrke.\n\nDisp.: Fredrik Jerndorf.\n\nKontorschef: Anton Holmgren.\n\nFörsäljn.-chef: J. E. Leander.\n\nInköpschef: Bertil Brohagen.\n\n*AB. Malmö Skolästfabrik, Limhamn.\n\nSkolästfabrik, sågverk, ^\nträförädlingsfabrik samt stansknivfabrik i Limhamn\n(Malmöh. l.). Tillverkar skoläster,\nskoblock, pappläster, träspännen, kilklackar,\nprecisionssvarvade träsulor, galoschläster\nav aluminium och trä, sågade trävaror av\nbok, skrin och andra massartiklar av\nlövträ samt stansknivar.\n\nTelegr.-adr.: Lästfabriken, Limhamn.\nTelefon: 71805. Postgiro: 11075.\nFilialkontor: Örebro, telefon: 13027.\n\nAkt.-kap.: 60,000 kr. Antal\nindustriarb.: 125. —Bolaget grundat 1915.\n\nStyrelse: adv. Rolf Nordenstedt\n(ordf.), disp. Christian Madsen, dir. Oluf\nMadsen.\n\nVerkst. dir.: Oluf Madsen.\n\n* Malmö Spikfabriks AB.,\n\nLimhamn.\n\nTråddrageri och spikfabrik i Limhamn,\nMalmö. Tillverkar blank, förkopprad,\nglödgad och förzinkad järntråd, spik,\nstift, krampor och taggtråd.\n\nTelegr.-adr.: Spikfabriken, Malmö.\nTelefon: Malmö 50742. Postgiro: 39032.\n\nAkt.-kap.: 106,000 kr. Antal\nindustriarb.: 16. — Bolaget grundat 1922.\n\nStyrelse: ing. Nils Kärfve (ordf.), dir.\nHarry Johnson, dir. Harry Nicklasson.\nVerkst. dir.: Nils Kärfve.\n\n*AB. Malmö Stora Valskvarn, Malmö.\n\nTillverkar mjöl av råg och vete samt\nkli. Varunamn för vetemjöl:\n»Kungsörnen» m. fl.\n\nTelegr.-adr.: Valskvarnen, Malmö.\nTelefon: »Kvarnkontoret». Postgiro: 13100.\n\nAkt.-kap.: 3,600,000 kr. Antal\nindustriarb.: 138. Prod.-värde pr år: 25,250,000\nkr.\n\nBolaget, grundat 1875, tillhör AB.\nKvarnintressenter, Malmö.\n\nStyrelse: dir. Mauritz Carlson (ordf.),\ndir. Sven Malmberg, dir. Edvin Åberg.\n\nVerkst. dir.: S. Malmberg.\n\n*AB. Malmö Strumpfabrik, Malmö.\n\nTrikåfabrik. Tillverkar dam- och\nbarnstrumpor. Varumärken: »Nivella» o.\n»Vogue».\n\nKontor: Trelleborgsvägen. Telegr.-adr.:\nMalmöstrump, Malmö. Telefon: »Malmö\nStrumpfabrik». Postgiro: 24413.\n\nAkt.-kap.: 1,400,000 kr. Antal\nindustriarb.: 765. Tillv.-värde pr år: 12,300,000\nkr.\n\nBolaget, grundat 1926, har i sig\nupptagit f. d. AB. Färgeriindustri och AB.\nVictor Samuelsons Tricotfabrik.\n\nStyrelse: konsul Magnus Wiberg, dir.\nÅke Wiberg.\n\nVerkst. dir.: Åke Wiberg.\n\nKontorschef: J. A. Tancred.\n\n*AB. Malmö Stråhattfabrik, Malmö.\n\nTillverkar damhattar i strå, filt och\nsammet m. m. Bolaget driver jämväl\nengroshandel med modevaror.\n\nKontor: Baltzarsg. 41. Telegr.-adr.:\nAmastro, Malmö. Telefon: 71260.\nPostgiro: 38178. Avd.-kontor: Stockholm,\nKungsg. 53, telefon: 101548; Göteborg,\nKungsg. 31—33, telefon: 136458.\n\nAkt.-kap.: 300,000 kr. Antal\nindustriarb.: 110. Försäljn.-värde pr år: 2,300,000\nkr. — Firman etabl. 1874.\n\nStyrelse: bankdir. Ivar Åkerman (ordf.),\ndir. Carl Hanström, dir.-assist. Curt\nMalmberg, disp. C.-E. Åkerman.\n\nVerkst. dir.: Carl Hanström.\n\nKamrer: Klas Ringius.\n\nDisp.: Einar Grauers.\n\nAB. Malmö Vattenfabriker,\n\nMalmö.\n\nTillverkar läskedrycker och medicinska\nmineralvatten samt kristall-is.\n\nKontor: Möllevångsg. 36 C. Telefon:\n20180, 21229 o. 23387. Postgiro: 39233.\n\nAkt.-kap.: 420,000 kr. Antal\nindustriarb.: 25. Tillv.-värde pr år: 700,000 kr.\n— Bolaget grundat 1913.\n\nStyrelse: dir. L. W. Malmquist (ordf.),\ndir. Fredrik Jungbeck, adv. Svante\nMalmquist, målarmäst. Anders Olsson.\n\nVerkst. dir.: Fredrik Jungbeck.\n\n*Malmö Yllefabriks AB., Malmö.\n\nUll- och kamgarnsspinnerier samt\nylle-väveri i Malmö, kammeri, färgeri och\nappreturverk i Furulund (Malmöh. l.),\nstrumpfabrik i Lund samt\nbomullsspinneri och -väveri i Varberg.\n\nTillverkar hel- och halvyllevävnader,\n\noblekt och färgat kardullsgarn och kam-\n\n*",
    "structured": {
        "1": {
            "name": "AB. Malmö Skolästfabrik, Limhamn",
            "location": "Limhamn, Malmö",
            "contact": {
                "office": "Skolästfabriken, Limhamn",
                "phone": [
                    "71805"
                ],
                "postgiro": "11075"
            },
            "business": "Tillverkar skoläster, skoblock, pappläster, träspännen, kilklackar, precisionssvarvade träslor, galoschläster av aluminium och trä, sågade trävaror av bok, skrin och andra massartiklar av lövträ samt stansknivar.",
            "financials": {
                "capital": "60,000 kr",
                "employees": {
                    "industriarb": 125
                },
                "foundation_year": 1915
            }
        },
        "2": {
            "name": "Malmö Spikfabriks AB",
            "location": "Limhamn, Malmö",
            "contact": {
                "office": "Spikfabriken, Malmö",
                "phone": "Malmö 50742",
                "postgiro": "39032"
            },
            "business": "Tillverkar blank, förkopprad, glödgad och förzinkad järntråd, spik, stift, krampor och taggtråd.",
            "financials": {
                "capital": "106,000 kr",
                "employees": {
                    "industriarb": 16
                },
                "foundation_year": 1922
            }
        },
        "3": {
            "name": "AB. Malmö Stora Valskvarn",
            "location": "Malmö",
            "contact": {
                "office": "Valskvarnen, Malmö",
                "phone": "Kvarnkontoret",
                "postgiro": "13100"
            },
            "business": "Tillverkar mjöl av råg och vete samt kli. Varunamn för vetemjöl: »Kungsörnen» m. fl.",
            "financials": {
                "capital": "3,600,000 kr",
                "employees": {
                    "industriarb": 138
                },
                "annual_turnover": "25,250,000 kr",
                "foundation_year": 1875
            }
        },
        "4": {
            "name": "AB. Malmö Strumpfabrik",
            "location": "Malmö",
            "contact": {
                "office": "Malmöstrump, Malmö",
                "phone": [
                    "Malmö Strumpfabrik"
                ],
                "postgiro": "24413"
            },
            "business": "Tillverkar dam- och barnstrumpor. Varumärken: »Nivella» o. »Vogue».",
            "financials": {
                "capital": "1,400,000 kr",
                "employees": {
                    "industriarb": 765
                },
                "annual_production_value": "12,300,000 kr",
                "foundation_year": 1926
            }
        },
        "5": {
            "name": "AB. Malmö Stråhattfabrik",
            "location": "Malmö",
            "contact": {
                "office": "Amastro, Malmö",
                "phone": "71260",
                "postgiro": "38178",
                "sales_offices": [
                    {
                        "location": "Stockholm",
                        "phone": "101548"
                    },
                    {
                        "location": "Göteborg",
                        "phone": "136458"
                    }
                ]
            },
            "business": "Tillverkar damhattar i strå, filt och sammet m. m. Driver även engroshandel med modevaror.",
            "financials": {
                "capital": "300,000 kr",
                "employees": {
                    "industriarb": 110
                },
                "annual_turnover": "2,300,000 kr"
            }
        },
        "6": {
            "name": "AB. Malmö Vattenfabriker",
            "location": "Malmö",
            "contact": {
                "office": "Möllevångsg. 36 C",
                "phone": [
                    "20180",
                    "21229",
                    "23387"
                ],
                "postgiro": "39233"
            },
            "business": "Tillverkar läskedrycker och medicinska mineralvatten samt kristall-is.",
            "financials": {
                "capital": "420,000 kr",
                "employees": {
                    "industriarb": 25
                },
                "annual_production_value": "700,000 kr",
                "foundation_year": 1913
            }
        },
        "7": {
            "name": "Malmö Yllefabriks AB.",
            "location": "Malmö",
            "contact": {
                "office": "Ull- och kamgarnsspinnerier samt ylle-väveri, Malmö",
                "phone": "»Kvarnkontoret»",
                "postgiro": "13100",
                "sales_offices": [
                    {
                        "location": "Lund",
                        "phone": "phone_number"
                    },
                    {
                        "location": "Varberg",
                        "phone": "phone_number"
                    }
                ]
            },
            "business": "Tillverkar hel- och halvyllevävnader, oblekt och färgat kardullsgarn och kam",
            "financials": {
                "capital": "11,987,400 kr",
                "employees": {
                    "industriarb": 500
                },
                "annual_turnover": "53,200,000 kr"
            }
        }
    }
}