{
    "original": "Thorell—Thulinverken\n\nStyrelse: ing. Henry Thorburn (ordf.),\ndisp. Nils Dreijer, disp. David Thorburn.\n\nVerkst. dir.: David Thorburn.\n\nKamrer: Sven Ryberg.\n\nAB. Erik Thorell, Malmö.\n\nDamhattfabrik. Tillverkar damhattar i\nstrå och filt.\n\nKontor: Jacob Nilsg. 24. Telef ou:\n14014. Postgiro: 37979.—Akt.-kap.: 7,000\nkr. Antal industriarb.: 7. Tillv.-värde pr\når: 40,000 kr. — Bolaget grundat 1933.\n\nDisp.: Erik Thorell.\n\n*Thorsviks AB., Norrahammar.\n\nPappersbruk, wellpapp- och\nkartongfabrik 4 km. från Norrahammar (Jönköp.\n1.). Tillverkar papper, wellpapp och\nwellpappkartonger, hopfällbara lådor\n(»ller-kules»-, »Columbus»- o. »Te-Ve»-lådor)\nsamt »Te-Ve»-äggförpackning.\n\nTelegr.-adr.: Thorsviks. Jönköping.\nTelefon: Norrahammar 370, 371 o. 372.\nPostgiro: 13902. — Akt.-kap.: 10,000 kr.\nAntal industriarb.: 180.\n\nFirman etabl. 1879, bolag 1905.\nBolaget är anslutet till AB. Sveriges\nLitogra-fiska Tryckerier (se detta bolag).\nStyrelse o. disp.: Einar H. Janson.\nFörsäljnings- o. kontorschef: Pehr\nSjöstrand.\n\n*AB. L. Thrysins Mek. Verkstad,\n\nStockholm.\n\nTillverkar slirkopplingar (märke:\n»Gy-ros»), spårskivor för kilremdrift,\nkedjehjul och backslag för marinmotorer samt\nutför mek. arbeten, kuggfräsning m. m.\n\nKontor: Ulvsunda. Post- och godsadr.:\nUlvsunda 1. Telegr.-adr.: Gyrosko,\nStockholm. Telefon: 256722 o. 260424. Post\ngiro: 57183.\n\nAkt.-kap.: 93,000 kr. Antal\nindustriarb.: 20. Tillv.-värde pr år: 300,000 kr.\n— Bolaget grundat 1934.\n\nStyrelse: ing. Ludvig Thrysin (ordf.),\ning. John Danielsson, ing. Nils\nGustavson.\n\nVerkst. dir.: Ludvig Thrysin.\n\n*Thule Maskinfabrik, Malmö.\nSe Maskinfabriks AB. Thule, Malmö.\n\n*Thule, Tryckeri AB., Stockholm.\nSe Tryckeri AB. Thule, Stockholm.\n\n57\n\n*Thulins Vagnfabrik AB.,\n\nSkillingaryd.\n\nVagn-, karosseri- och redskapsfabrik,\nmåleri och sadelmakeri i Skillingaryd\n(Jönköp. l.).\n\nTillverkar hästfordon med stålsko-\n\nnings- och gummiringshjul såsom\narbetsvagnar, släpvagnar, åk- och lastslädar,\narbets- och timmerkälkar, bilsläp-kälkar,\nselar och seldon, karosserier, förarhytter\noch flak, beteskultivatorer (»Rivbjörn»)\noch skogskulturplogar (»Skogsbjörn»),\nträdgårdsmöbler såsom fjädrande\nstålfåtöljer samt limknektar och -tvingar av\nstål, vagnshjul, -axlar och rullageraxlar.\n\nTelegr.-adr.: Thulins, Skillingaryd.\nTelefon: 1 o. 233. Postgiro: 8155.\n\nAkt.-kap.: 45,000 kr. Antal\nindustriarb.: 30. Tillv.-värde pr år: 500,000 kr.\n\n—\tFirman etabl. 1875, bolag 1942.\nStyrelse: dir. N. Georg Thulin (ordf.),\n\nkamrer David Thulin, fru Elsa Thulin,\nfröken Hanna Thulin, bankkamrer Ruben\nThulin.\n\nVerkst. dir.: N. G. Thulin.\nKontorschef: David Thulin.\n\n*lvar Thulin, Krylbo.\n\nKonstullfabrik och metallsmälteri samt\nsorteringsanstalt för avfallsråvaror i\nKrylbo (Kopparb. l.). Firman driver\njämväl engrosrörelse med järn- och\nmetallskrot, textilavfall m. m.\n\nTelefon: 1515. Postgiro: 33971. —\nAntal industriarb.: 48. — Firman etabl.\n1914.\n\nÄgare o. chef: grosshandl. Ivar Thulin.\n\n*AB. John A. Thulin &amp; C:o.,\n\nNorrköping.\n\nTillverkar bobiner och behållare av\npapper, stålsolv, vävskedstråd, vävskedar,\nlameller, kem.-tekn. preparat m. m.\n\nTelegr.-adr.: Jat, Norrköping. Telefon:\n»Thulin &amp; Co.» Postgiro: 29404.\n\nAkt.-kap.: 200,000 kr. Antal\nindustriarb.: 180. Tillv.-värde pr år: 2,200,000 kr.\n\n—\tFirman etabl. 1892, bolag 1941.\nStyrelse o. verkst. dir.: Nils Kindahl.\nV. verkst. dir.: Olof Segercrantz.\nEkonomichef: Karl Henrik Pahlberg.\n\nAB. Thulin ver ken, Landskrona.\n\nMek. verkstad. Tillverkar\nspecialapparater för bromsar till rälsfordon,\ntryck-luftbromsar för landsvägsfordon,\nfläkt-och ventilationsapparater samt\nverktygsmaskiner och livsmedelsmaskiner.\n\nTelegr.-adr.: Thulinverken, Landskrona.\n\n*",
    "structured": {
        "1": {
            "name": "AB. Erik Thorell",
            "location": "Malmö",
            "business": "Damhattfabrik",
            "products": "Tillverkar damhattar i strå och filt",
            "contact": {
                "office": "Jacob Nilsg. 24",
                "phone": [
                    "14014"
                ],
                "postgiro": "37979"
            },
            "financials": {
                "capital": "7,000 kr",
                "employees": {
                    "antal industriarb.": 7
                },
                "annual_turnover": "40,000 kr",
                "annual_production_value": "40,000 kr"
            },
            "foundation_year": 1933
        },
        "2": {
            "name": "Thorsviks AB.",
            "location": "Norrahammar",
            "business": "Pappersbruk, wellpapp- och kartongfabrik",
            "products": "Tillverkar papper, wellpapp och wellpappkartonger, hopfällbara lådor (»ller-kules»-, »Columbus»- o. »Te-Ve»-lådor) samt »Te-Ve»-äggförpackning",
            "contact": {
                "telegraph": "Thorsviks. Jönköping",
                "phone": [
                    "Norrahammar 370",
                    "Norrahammar 371",
                    "Norrahammar 372"
                ],
                "postgiro": "13902"
            },
            "financials": {
                "capital": "10,000 kr",
                "employees": {
                    "antal industriarb.": 180
                }
            },
            "foundation_year": 1879,
            "corporation_year": 1905,
            "board": [
                {
                    "name": "Einar H. Janson",
                    "role": "Styrelse o. disp."
                },
                {
                    "name": "Pehr Sjöstrand",
                    "role": "Försäljnings- o. kontorschef"
                }
            ]
        },
        "3": {
            "name": "AB. L. Thrysins Mek. Verkstad",
            "location": "Stockholm",
            "business": "Mek. verkstad",
            "products": "Tillverkar slirkopplingar (märke: »Gy-ros»), spårskivor för kilremdrift, kedjehjul och backslag för marinmotorer samt utför mek. arbeten, kuggfräsning m. m.",
            "contact": {
                "office": "Ulvsunda",
                "telegraph": "Gyrosko, Stockholm",
                "phone": "256722 o. 260424",
                "postgiro": "57183"
            },
            "financials": {
                "capital": "93,000 kr",
                "employees": {
                    "antal industriarb.": 20
                },
                "annual_turnover": "300,000 kr"
            },
            "foundation_year": 1934,
            "board": [
                {
                    "name": "Ing. Ludvig Thrysin",
                    "role": "Styrelse"
                },
                {
                    "name": "Ing. John Danielsson",
                    "role": "Styrelse"
                },
                {
                    "name": "Ing. Nils Gustavson",
                    "role": "Styrelse"
                }
            ],
            "director": "Ludvig Thrysin"
        },
        "4": {
            "name": "Thulins Vagnfabrik AB.",
            "location": "Skillingaryd",
            "business": "Vagn-, karosseri- och redskapsfabrik",
            "products": "Tillverkar hästfordon med stålsko-nings- och gummiringshjul såsom arbetsvagnar, släpvagnar, åk- och lastslädar, arbets- och timmerkälkar, bilsläp-kälkar, selar och seldon, karosserier, förarhytter och flak, beteskultivatorer (»Rivbjörn») och skogskulturplogar (»Skogsbjörn»), trädgårdsmöbler såsom fjädrande stålfåtöljer samt limknektar och -tvingar av stål, vagnshjul, -axlar och rullageraxlar",
            "contact": {
                "telegraph": "Thulins, Skillingaryd",
                "phone": [
                    "1",
                    "233"
                ],
                "postgiro": "8155"
            },
            "financials": {
                "capital": "45,000 kr",
                "employees": {
                    "antal industriarb.": 30
                },
                "annual_turnover": "500,000 kr"
            },
            "foundation_year": 1875,
            "corporation_year": 1942,
            "board": [
                {
                    "name": "Dir. N. Georg Thulin",
                    "role": "Styrelse"
                },
                {
                    "name": "David Thulin",
                    "role": "Styrelse"
                },
                {
                    "name": "Fru Elsa Thulin",
                    "role": "Styrelse"
                },
                {
                    "name": "Fröken Hanna Thulin",
                    "role": "Styrelse"
                },
                {
                    "name": "Bankkamrer Ruben Thulin",
                    "role": "Styrelse"
                }
            ],
            "director": "N. G. Thulin",
            "manager": "David Thulin"
        },
        "5": {
            "name": "lvar Thulin",
            "location": "Krylbo",
            "business": "Konstullfabrik och metallsmälteri samt sorteringsanstalt för avfallsråvaror",
            "contact": {
                "phone": "1515",
                "postgiro": "33971"
            },
            "employees": {
                "antal industriarb.": 48
            },
            "foundation_year": 1914,
            "owners": [
                "grosshandl. Ivar Thulin"
            ]
        },
        "6": {
            "name": "AB. John A. Thulin & C:o.",
            "location": "Norrköping",
            "business": "Tillverkar bobiner och behållare av papper, stålsolv, vävskedstråd, vävskedar, lameller, kem.-tekn. preparat m. m.",
            "contact": {
                "telegraph": "Jat, Norrköping",
                "phone": "»Thulin & Co.",
                "postgiro": "29404"
            },
            "financials": {
                "capital": "200,000 kr",
                "employees": {
                    "antal industriarb.": 180
                },
                "annual_turnover": "2,200,000 kr"
            },
            "foundation_year": 1892,
            "corporation_year": 1941,
            "board": [
                {
                    "name": "Nils Kindahl",
                    "role": "Styrelse"
                },
                {
                    "name": "Olof Segercrantz",
                    "role": "V. verkst. dir."
                }
            ]
        },
        "7": {
            "name": "AB. Thulin verken",
            "location": "Landskrona",
            "business": "Mek. verkstad",
            "products": "Tillverkar specialapparater för bromsar till rälsfordon, tryck-luftbromsar för landsvägsfordon, fläkt-och ventilationsapparater samt verktyg"
        }
    }
}