{
    "original": "Berg—B er glo o lagen\n\n*E. A. Bergs Fabriks AB.,\n\nEskilstuna.\n\nJärn- och stålmanufakturfabrik.\nTillverkar tänger, snickeri verktyg,\nhushålls-knivar, skomakar- och gummiknivar,\nslakt- och andra yrkesknivar,\nträdgårdssaxar, bleck-, plåt- och bultsaxar samt\nhejarsmide. Varumärke: »Hajen».\n\nTelegr.-adr.: Bergsbol, Eskilstuna.\nTelefon: »Bergs bolag». Postgiro: 10713.\n\nAkt.-kap.: 1,000,000 kr. Antal\nindustriarb.: 290. Tillv.-värde pr år: 3,000,000 kr.\n— Firman etabl. 1880, bolag 1900.\n\nStyrelse: fru K. M. Alderin, f. Berg,\nciviling. G. Gust. Andersson, ing. Torkel\nBerg, fru E. Berlin, f. Berg, fru G. E.\nCarlsson, f. Berg, fru M. O. Carlsson, f.\nBerg, fru I. Olsson, f. Berg.\n\nVerkst. dir.: C. Gust. Andersson.\n\nFörsäljn.-chef: U. Krantz.\n\nFr. d. Berg, Matematisk\nInstrumentfabrik, AB., Stockholm.\n\nTillverkar optiska och finmekaniska\nprecisionsarbeten såsom geodetiska\ninstrument samt gruv- och\nmalmletnings-instrument. Bolaget innehar jämväl\nagentur för geodetiska instrument av\nutländsk tillverkning.\n\nKontor: Kungstensgatan 18. Telefon:\n307660. Postgiro: 1968. — Akt.-kap.:\n50,000 kr. — Firman etabl. 1850, bolag\n1933.\n\nVerkst. dir.: kapten Anders Berg.\n\nK. A. Bergs Redskapsfabrik,\n\nOemla.\n\nTillverkar redskap och verktyg såsom\nhammare, släggor, stenverktyg,\ngruvred-skap, skogs- och trädgårdsredskap,\nhackor m. m. vid fabrik i Gemla\n(Kronob. l.).\n\nTelefon: Växjö 67116. Postgiro: 8800.\n— Antal industriarb.: 50. Tillv.-värde pr\når: 600,000 kr. — Firman etabl. 1868.\n\nÄgare o. chef: fabr. Karl Allan Berg.\n\n*Berga Kalkbruk, Torbjörntorp.\n\nSe AB. Västergötlands Förenade\nKalk-industrier, Falköping.\n\nAB. Berga Snickerifabrik, Berga.\n\nTillverkar byggnadssnickerier, listverk,\nsågade och hyvlade trävaror, lådbräder,\nlaths, träkol m. m. vid fabrik i Berga\n(Kalmar l.). Specialitet: dörrar för\nexport.\n\nTelegr.-adr.: Exportsnickeri,\nOskarshamn. Telefon: Berga 2. Postgiro: 23681.\n\nAkt.-kap.: 100,000 kr. Antal\nindustriarb.: 50. Tillv.-värde pr år: 450,000 kr.\n— Firman etabl. 1896, bolag 1899,\nom-bildad 1923.\n\nVerkst. dir.: Josef Jarelid.\n\nKamrer: Robert Forsberg.\n\nBerga Sten huggeri AB.,\n\nHällabrottet.\n\nFramställer byggnadssten av kalksten\noch marmor vid stenhuggeri i\nHällabrottet (Örebro l.).\nTelefon: Örebro 72001. Postgiro: 77465.\n\n—\tAkt.-kap.: 90,000 kr. Antal\nindustriarb.: 75. Prod.-värde pr år: 600,000 kr.\n\n—\tFirman etabl. 1906.\n\nChefer: fabr. Carl Th. Eriksson o. fabr.\nUno Persson.\n\n*AB. Berga Tegelbruk, Kalmar.\n\nTeerelbruk vid Berga Gård, Högsby\n(Kalmar l.). Tillverkar murtegel,\nradial-och håltegel samt dräneringsrör; uppför\nskorstenar.\n\nHuvudkontor: Kalmar. Telegr.-adr.:\nNy gärde, Kalmar. Telefon: 452 o. 1204.\nBrukskontor: Högsby, telefon: 27.\n\nAkt.-kap.: 200,000 kr. Antal\nindustriarb.: 42. Årstillv.: 3,5 milj. st. tegelvaror.\n— Tegelbruket anlagt 1899. Ny gärde\nTegelbruks AB. är huvudintressent i\nbolaget.\n\nStyrelse: dir. Allan Jeansson,\ntegelmästare Björn Jeansson, kassör Sigfr.\nJeansson.\n\nVerkst. dir.: Allan Jeansson.\n\nTegelmäst.: Claes Agurell.\n\nAB. Berga Träindustri, Berga.\n\nTillverkar byggnadssnickerier vid\nfabrik i Berga (Kalmar l.). Bolaget driver\näven försäljning av sågade och hyvlade\nträvaror.\n\nTelefon: 34. Postgiro: 23682. —\nAkt.-kap.: 25,500 kr. Antal industriarb.: 45.\nTillv.-värde pr år: 400,000 kr. — Bolaget\ngrundat 1920.\n\nVerkst. dir.: disp. John Gustafsson.\n\n* Bergbolagen AB., Lindesberg.\n\nMek. verkstad i Lindesberg (f. d. Berg\n&amp; C:o Mek. Verkstad AB.), mek. verkstad\noch gjuteri (»Skandiaverken») i Lysekil\nsamt gjuteri, mek. verkstad och\nredskapsfabrik (»Stenborgs Fabriker») i Tierp\n(Uppsala l.).",
    "structured": {
        "companies": [
            {
                "name": "E. A. Bergs Fabriks AB.",
                "location": "Eskilstuna",
                "business": "Järn- och stålmanufakturfabrik",
                "products": "Tillverkar tänger, snickeri verktyg, hushålls-knivar, skomakar- och gummiknivar, slakt- och andra yrkesknivar, trädgårdssaxar, bleck-, plåt- och bultsaxar samt hejarsmide. Varumärke: »Hajen».",
                "contact": {
                    "office": "Eskilstuna",
                    "phone": [
                        "Bergs bolag"
                    ],
                    "postgiro": "10713",
                    "telegraph": "Bergsbol",
                    "factory_office": "Eskilstuna"
                },
                "financials": {
                    "capital": "1,000,000 kr",
                    "employees": {
                        "industriarb": 290
                    },
                    "annual_turnover": "3,000,000 kr"
                },
                "foundation_year": 1880,
                "corporation_year": 1900,
                "board": [
                    {
                        "name": "fru K. M. Alderin",
                        "role": null
                    },
                    {
                        "name": "civiling. G. Gust. Andersson",
                        "role": null
                    },
                    {
                        "name": "ing. Torkel Berg",
                        "role": null
                    },
                    {
                        "name": "fru E. Berlin",
                        "role": null
                    },
                    {
                        "name": "fru G. E. Carlsson",
                        "role": null
                    },
                    {
                        "name": "fru M. O. Carlsson",
                        "role": null
                    },
                    {
                        "name": "fru I. Olsson",
                        "role": null
                    }
                ],
                "director": "C. Gust. Andersson",
                "sales_manager": "U. Krantz"
            },
            {
                "name": "Fr. d. Berg, Matematisk Instrumentfabrik, AB.",
                "location": "Stockholm",
                "products": "Tillverkar optiska och finmekaniska precisionsarbeten såsom geodetiska instrument samt gruv- och malmletnings-instrument. Bolaget innehar jämväl agentur för geodetiska instrument av utländsk tillverkning.",
                "contact": {
                    "office": "Stockholm",
                    "phone": [
                        "307660"
                    ],
                    "postgiro": "1968"
                },
                "financials": {
                    "capital": "50,000 kr"
                },
                "foundation_year": 1850,
                "corporation_year": 1933,
                "board": null,
                "director": "kapten Anders Berg"
            },
            {
                "name": "K. A. Bergs Redskapsfabrik",
                "location": "Oemla",
                "business": null,
                "products": "Tillverkar redskap och verktyg såsom hammare, släggor, stenverktyg, gruvred-skap, skogs- och trädgårdsredskap, hackor m. m.",
                "contact": {
                    "phone": [
                        "Växjö 67116"
                    ],
                    "postgiro": "8800"
                },
                "financials": {
                    "capital": null,
                    "employees": {
                        "industriarb": 50
                    },
                    "annual_turnover": "600,000 kr"
                },
                "foundation_year": 1868,
                "director": "fabr. Karl Allan Berg"
            },
            {
                "name": "Berga Kalkbruk",
                "location": "Torbjörntorp",
                "predecessor": "AB. Västergötlands Förenade Kalk-industrier",
                "original_name": null,
                "business": null,
                "products": null,
                "contact": null,
                "financials": null,
                "foundation_year": null
            },
            {
                "name": "AB. Berga Snickerifabrik",
                "location": "Berga",
                "business": "Tillverkar byggnadssnickerier, listverk, lådbräder, laths, träkol m. m. vid fabrik i Berga (Kalmar l.). Specialitet: dörrar för export.",
                "products": "Tillv.-värde pr år: 450,000 kr.",
                "contact": {
                    "phone": [
                        "Berga 2"
                    ],
                    "postgiro": "23681"
                },
                "financials": {
                    "capital": "100,000 kr",
                    "employees": {
                        "industriarb": 50
                    }
                },
                "foundation_year": 1896,
                "corporation_year": 1899,
                "current_name_year": 1923,
                "board": null,
                "director": "Josef Jarelid",
                "manager": "Robert Forsberg"
            },
            {
                "name": "Berga Stenhuggeri AB.",
                "location": "Hällabrottet",
                "business": "Framställer byggnadssten av kalksten och marmor vid stenhuggeri i Hällabrottet (Örebro l.)",
                "contact": {
                    "phone": [
                        "Örebro 72001"
                    ],
                    "postgiro": "77465"
                },
                "financials": {
                    "capital": "90,000 kr",
                    "employees": {
                        "industriarb": 75
                    },
                    "annual_turnover": "600,000 kr"
                },
                "foundation_year": 1906,
                "board": null,
                "director": "fabr. Carl Th. Eriksson"
            },
            {
                "name": "AB. Berga Tegelbruk",
                "location": "Kalmar",
                "business": "Tillverkar murtegel, radial-och håltegel samt dräneringsrör; uppför skorstenar.",
                "products": "Årstillv.: 3,5 milj. st. tegelvaror.",
                "contact": {
                    "phone": [
                        "Kalmar 452",
                        "Kalmar 1204",
                        "Högsby 27"
                    ],
                    "postgiro": null,
                    "telegraph": "Ny gärde"
                },
                "financials": {
                    "capital": "200,000 kr",
                    "employees": {
                        "industriarb": 42
                    }
                },
                "foundation_year": 1899,
                "board": null
            },
            {
                "name": "AB. Berga Träindustri",
                "location": "Berga",
                "business": "Tillverkar byggnadssnickerier vid fabrik i Berga (Kalmar l.). Bolaget driver även försäljning av sågade och hyvlade trävaror.",
                "products": "Tillv.-värde pr år: 400,000 kr",
                "contact": {
                    "phone": [
                        "34"
                    ],
                    "postgiro": "23682"
                },
                "financials": {
                    "capital": "25,500 kr",
                    "employees": {
                        "industriarb": 45
                    }
                },
                "foundation_year": 1920,
                "board": null,
                "director": "disp. John Gustafsson"
            },
            {
                "name": "Bergbolagen AB.",
                "location": "Lindesberg",
                "business": "Mek. verkstad i Lindesberg",
                "products": null,
                "contact": null,
                "financials": null,
                "foundation_year": null
            }
        ]
    }
}