{
    "original": "Gällstad—Gävle\n\nAB. Gällstads Textiltryck, Vegby.\n\nUtför handtryck av gardin-,\ndraperi-och möbeltyger, klänningstyger samt\nscar-ves vid fabrik i Vegby (Älvsb. l.).\n\nTelefon: Gällstad 22. — Akt.-kap.:\n120,000 kr. Antal industriarb.: 20.\nTillv.-värde pr år: 500,000 kr. — Bolaget\ngrundat 1944,\n\nVerkst. dir.: Assar Sanden.\n\nFabrikschef: Tore de Paulis.\n\n*Cällsta-Lundby Snickerifabrik,\n\nSjögestad.\n\nSågverk, hyvleri och snickerifabrik i\nSjögestad (Östergötl. l.). Tillverkar\nsågade och hyvlade trävaror, laths, takspån,\nträullsplattor m. m. samt\nbyggnadssnickerier.\n\nTelegr.-adr.: Snickeriträ, Linköping.\nTelefon: Sjögestad 39 o. Brink 45.\nPostgiro: 26242.\n\nAntal industriarb.: 40. Tillv.-värde pr\når: 600,000 kr. Årstillv.: 1,200 stds\nträvaror.— Firman etabl. 1901,\nsnickerifabriken anlagd 1912.\n\nÅgare o. chef: disp. Värner Lassmark.\n\nKontorschef: ing. Einar Karlén.\n\nCäliö Ångsågs AB., Gällö.\n\nSågverk och hyvleri i Gällö (Jämtl.\nL). Tillverkar ,sågade och hyvlade\nträvaror, läkt och stav samt träkol.\n\nTelegr.-adr.: Sågverket, Gällö.\nTelefon: 1. Postgiro: 87490.\n\nAkt.-kap.; 60,400 kr. Antal\nindustriarb.: 60. Årstillv.: 3,500 stds sågade o.\nhyvlade trävaror, 3,000 läster träkol. —\nBolaget grundat 1923.\n\nStyrelse: ad v. Adolf Sjöberg (ordf.),\ndisp. Ernst Pettersson.\ni .Verkst. dir.: Ernst Pettersson.\n\n*Cärsnäs Snickerifabrik, M. C.\nJohansson, Gärsnäs.\n\nTillverkar byggnads- och\ninredningssnickerier såsom fönster, dörrar, trappor,\nbutiks-’ och köksinredningar m. m. vid\nfabrik i Gärsnäs (Kristianst. l.).\n\nTelefon: 112. — Antal industriarb.: 8.\nTillv.-värde pr år: 80,000 kr. — Firman\netabl. 1934.\n\nÄgare o. chef: fabr. Malte Johansson.\n\n*AB. Gästriklands Yllefabrik, Järbo.\n\nSpinneri, vävöri och färgeri i Järbo\n(Gävleb. l.). Tillverkar hel- och\nhalvyllevävnader samt filtar.\n\nTelefon: 1 o. 2. Postgiro: 70236. —\nAkt.-kap.: 600,000 kr. Antal industriarb.:\n\n252. Tillv.-värde pr år: 3,000,000 kr. —\nBolaget grundat 1902.\n\nStyrelse: disp. Gunnar Höglund (ordf.),\ngrossh. Gustaf Delin, disp. Carl V.\nLarsson.\n\nDisp.: Carl V. Larsson.\nKontorschef: Sten Helldal.\n\nGävle.\n\n*Cefle Bryggeri AB., Gävle.\n\nSe AB. Gefle Förenade Bryggerier,\n\nGävle.\n\nGävle.\n\n*AB. Gefle Förenade Bryggerier,\n\nGävle.\n\nTillverkar malt och maltdrycker,\nmineralvatten och läskedrycker genom\nföljande företag: Gefle Bryggeri AB.,\nPor-terbryggeri AB. i Gefle, Wadmans Bryg-\n\nferi AB., Ångbryggeri AB. i Gävle, och\nandvikens Bryggeri AB., Sandviken.\n\nKontor: Gustafsbro, Gävle.\nTelegr.-adr.: Gustafsbro, Gävle. Telefon: »Gävle\nBryggerier». Postgiro: 262905.\n\nAkt.-kap.: 3,000,000 kr. Antal\nindustriarb.: 90. — Bolaget grundat 1942.\n\nStyrelse: major Oscar A. Thollén\n(ordf.), kassör Tore Lindbom,\nkontorschef Birger Lundeberg, dir. Bertil A.\nMatton, dir. Wald. Meyer,\nriksbankskamrer Erik Wadman, disp. Walter Wadman.\n\nVerkst. dir. o. disp.: Walter Wadman.\n\nKontorschef: Birger Lundeberg.\n\n*Cävle Galvaniseringsfabrik AB.,\n\nGävle.\n\nGalvaniseringsfabrik samt mek.\nverkstad och plåtslageri.^\n\nUtför varmgalvanisering av\njärnmaterial; tillverkar helsvetsade\nkraftledningsstolpar, galvaniserat flätverksstängsel,\nte-legrafsmiden, kraftledningssmiden,\njärnstaket och järngrindar, fotskrapsmattor,\ncykelställ samt plåtkärl såsom\nkonserveringsapparater, baljor, vatten- och\nmurbrukshinkar, vattenvärmare, sop- och\nlatrinkärl m. m.\n\nPostadr.: Box 108, Gävle. Telefon:\n»Gävle galvan». Postgiro: 170040. —\nAkt.-kap.: 175,000 kr. Antal\nindustriarb.: 250. Tillv.-värde pr år: 4,500,000\nkr. — Firman etabl. 1936, bolag 1946.\n\nStyrelse: dir. Bengt Eiserman, bankdir.\nGunnar Hedberg, fabr. Arne Sjöström.\n\nVerkst. dir.: Arne Sjöström.\n\nDriftsing.: Artur Forsberg.",
    "structured": {
        "1": {
            "name": "AB. Gällstads Textiltryck",
            "location": "Vegby",
            "business": "Handtryck av gardin-, draperi-och möbeltyger, klänningstyger samt scar-ves",
            "products": "utför handtryck av textilprodukter",
            "contact": {
                "office": "Vegby",
                "phone": [
                    "Gällstad 22"
                ],
                "postgiro": null,
                "head_office": null,
                "sales_offices": null,
                "telegraph": null,
                "factory_office": null,
                "factory_phone": null
            },
            "financials": {
                "capital": "120,000 kr",
                "employees": {
                    "industriarb": 20
                },
                "annual_turnover": "500,000 kr",
                "annual_production_value": null
            },
            "foundation_year": 1944,
            "current_name_year": null,
            "predecessor": null,
            "original_name": null,
            "corporation_year": null,
            "board": [
                {
                    "name": "Assar Sanden",
                    "role": "Verkst. dir."
                }
            ],
            "owners": null,
            "director": null,
            "managing_director": null,
            "sales_manager": null,
            "manager": null
        },
        "2": {
            "name": "Cällsta-Lundby Snickerifabrik",
            "location": "Sjögestad",
            "business": "Sågverk, hyvleri och snickerifabrik",
            "products": "sågade och hyvlade trävaror, laths, takspån, träullsplattor m.m.",
            "contact": {
                "office": null,
                "phone": [
                    "Sjögestad 39",
                    "Brink 45"
                ],
                "postgiro": "26242",
                "head_office": null,
                "sales_offices": null,
                "telegraph": "Snickeriträ, Linköping",
                "factory_office": null,
                "factory_phone": null
            },
            "financials": {
                "capital": null,
                "employees": {
                    "industriarb": 40
                },
                "annual_turnover": "600,000 kr",
                "annual_production_value": "1,200 stds trävaror"
            },
            "foundation_year": 1901,
            "current_name_year": null,
            "predecessor": null,
            "original_name": null,
            "corporation_year": null,
            "board": [
                {
                    "name": "disp. Värner Lassmark",
                    "role": "Ågare o. chef"
                },
                {
                    "name": "ing. Einar Karlén",
                    "role": "Kontorschef"
                }
            ],
            "owners": null,
            "director": null,
            "managing_director": null,
            "sales_manager": null,
            "manager": null
        },
        "3": {
            "name": "Cäliö Ångsågs AB.",
            "location": "Gällö",
            "business": "Sågverk och hyvleri",
            "products": "sågade och hyvlade trävaror, läkt och stav samt träkol",
            "contact": {
                "office": null,
                "phone": [
                    "1"
                ],
                "postgiro": "87490",
                "head_office": null,
                "sales_offices": null,
                "telegraph": "Sågverket, Gällö",
                "factory_office": null,
                "factory_phone": null
            },
            "financials": {
                "capital": "60,400 kr",
                "employees": {
                    "industriarb": 60
                },
                "annual_turnover": null,
                "annual_production_value": "3,500 stds sågade o. hyvlade trävaror, 3,000 läster träkol"
            },
            "foundation_year": 1923,
            "current_name_year": null,
            "predecessor": null,
            "original_name": null,
            "corporation_year": null,
            "board": [
                {
                    "name": "disp. Adolf Sjöberg",
                    "role": "Styrelse: ad v."
                },
                {
                    "name": "disp. Ernst Pettersson",
                    "role": "Verkst. dir."
                }
            ],
            "owners": null,
            "director": null,
            "managing_director": null,
            "sales_manager": null,
            "manager": null
        },
        "4": {
            "name": "Cärsnäs Snickerifabrik",
            "location": "Gärsnäs",
            "business": "Tillverkar byggnads- och inredningssnickerier",
            "products": "fönster, dörrar, trappor, butiks-’ och köksinredningar m.m.",
            "contact": {
                "office": null,
                "phone": [
                    "112"
                ],
                "postgiro": null,
                "head_office": null,
                "sales_offices": null,
                "telegraph": null,
                "factory_office": null,
                "factory_phone": null
            },
            "financials": {
                "capital": null,
                "employees": {
                    "industriarb": 8
                },
                "annual_turnover": "80,000 kr",
                "annual_production_value": null
            },
            "foundation_year": 1934,
            "current_name_year": null,
            "predecessor": null,
            "original_name": null,
            "corporation_year": null,
            "board": null,
            "owners": null,
            "director": null,
            "managing_director": null,
            "sales_manager": null,
            "manager": "fabr. Malte Johansson"
        },
        "5": {
            "name": "AB. Gästriklands Yllefabrik",
            "location": "Järbo",
            "business": "Spinneri, vävöri och färgeri",
            "products": "hel- och halvyllevävnader samt filtar",
            "contact": {
                "office": null,
                "phone": [
                    "1 o. 2"
                ],
                "postgiro": "70236",
                "head_office": null,
                "sales_offices": null,
                "telegraph": null,
                "factory_office": null,
                "factory_phone": null
            },
            "financials": {
                "capital": "600,000 kr",
                "employees": {
                    "industriarb": 252
                },
                "annual_turnover": "3,000,000 kr",
                "annual_production_value": null
            },
            "foundation_year": 1902,
            "current_name_year": null,
            "predecessor": null,
            "original_name": null,
            "corporation_year": null,
            "board": [
                {
                    "name": "disp. Gunnar Höglund",
                    "role": "Styrelse: disp."
                },
                {
                    "name": "grossh. Gustaf Delin",
                    "role": "Styrelse: disp."
                },
                {
                    "name": "disp. Carl V. Larsson",
                    "role": "Disp."
                }
            ],
            "owners": null,
            "director": null,
            "managing_director": null,
            "sales_manager": null,
            "manager": null
        },
        "6": {
            "name": "AB. Gefle Förenade Bryggerier",
            "location": "Gävle",
            "business": "Tillverkar malt och maltdrycker, mineralvatten och läskedrycker",
            "products": "malt och maltdrycker, mineralvatten, läskedrycker",
            "contact": {
                "office": "Gustafsbro",
                "phone": [
                    "Gävle Bryggerier"
                ],
                "postgiro": "262905",
                "head_office": null,
                "sales_offices": null,
                "telegraph": "Gustafsbro, Gävle",
                "factory_office": null,
                "factory_phone": null
            },
            "financials": {
                "capital": "3,000,000 kr",
                "employees": {
                    "industriarb": 90
                },
                "annual_turnover": null,
                "annual_production_value": null
            },
            "foundation_year": 1942,
            "current_name_year": null,
            "predecessor": null,
            "original_name": null,
            "corporation_year": null,
            "board": [
                {
                    "name": "major Oscar A. Thollén",
                    "role": "Styrelse"
                },
                {
                    "name": "kassör Tore Lindbom",
                    "role": "Styrelse"
                },
                {
                    "name": "kontorschef Birger Lundeberg",
                    "role": "Kontorschef"
                },
                {
                    "name": "dir. Bertil A. Matton",
                    "role": "Dir."
                },
                {
                    "name": "dir. Wald. Meyer",
                    "role": "Dir."
                },
                {
                    "name": "riksbankskamrer Erik Wadman",
                    "role": "Riksbankskamrer"
                },
                {
                    "name": "disp. Walter Wadman",
                    "role": "Verkst. dir. o. disp."
                }
            ],
            "owners": null,
            "director": null,
            "managing_director": null,
            "sales_manager": null,
            "manager": null
        },
        "7": {
            "name": "Cävle Galvaniseringsfabrik AB.",
            "location": "Gävle",
            "business": "Galvaniseringsfabrik samt mek. verkstad och plåtslageri",
            "products": "varmgalvanisering av järnmaterial, diverse plåtprodukter",
            "contact": {
                "office": "Box 108, Gävle",
                "phone": [
                    "Gävle galvan"
                ],
                "postgiro": "170040",
                "head_office": null,
                "sales_offices": null,
                "telegraph": null,
                "factory_office": null,
                "factory_phone": null
            },
            "financials": {
                "capital": "175,000 kr",
                "employees": {
                    "industriarb": 250
                },
                "annual_turnover": "4,500,000 kr",
                "annual_production_value": null
            },
            "foundation_year": 1946,
            "current_name_year": null,
            "predecessor": null,
            "original_name": null,
            "corporation_year": null,
            "board": [
                {
                    "name": "bankdir. Gunnar Hedberg",
                    "role": "Styrelse"
                },
                {
                    "name": "fabr. Arne Sjöström",
                    "role": "Styrelse"
                },
                {
                    "name": "dir. Bengt Eiserman",
                    "role": "Styrelse"
                },
                {
                    "name": "dir. Bengt Eiserman",
                    "role": "Driftsing."
                }
            ],
            "owners": null,
            "director": null,
            "managing_director": null,
            "sales_manager": null,
            "manager": null
        }
    }
}