{
    "original": "Forsgård—Forss\n\nKontor: Stockholm, Skeppsbron 36.\nTelegr.-adr.: Iron, Stockholm. Telefon:\n209317—18. Postgiro: 58868.\n\nAkt.-kap.: 150,000 kr. Antal\nindustriarb.: 25. Tillv.-värde pr år: 400,000 kr.\n— Firman etabl. 1914 under namn\nForserums Smidesfabrik, bolag med nuv.\nnamn 1941.\n\nStyrelse o. verkst. dir.: Gösta\nLindström.\n\nPlatschef: Gustaf Forsberg.\n\nForsgårds AB., Klippan.\n\nBandfabrik i Klippan (Kristianst. l.).\nTillverkar fransar, kantband och\ndragband för markiser, möbelband och\nmöbelsnören, fransar och kantband för mattor,\nlampskärmsgaraityr, sidenband m. m.\n\nTelefon: 19061. Postgiro: 99466. —\nAkt.-kap.: 35,300 kr. Arb.-antal: 12.\nTillv.-värde pr år: 150,000 kr. — Bolaget\ngrundat 1936.\n\nVerkst. dir. o. disp.: Ewald Stridh.\n\n*\tForshaga Llnoleum AB., Göteborg.\n\nSe Linoleum AB. Forshaga, Göteborg.\n\n*\tForshaga Sulfit AB., Forshaga.\n\nSe AB. Mölnbacka-Trysil, Forshaga.\n\n*AB. Forshammars Bergverk,\n\nKöping.\n\nFältspatbrott och malverk vid\nForshammar, Ramsberg (Örebro l.) och i\nRå-danefors (Älvsb. l.). Bryter och förmaler\nfältspat och kvarts.\n\nKontor: Köping. Telefon: 112.\nPostgiro: 132892. Bergverket: telefon:\nSkinn-skatteberg 3114.\n\nAkt.-kap.: 100,000 kr. Antal\nindustriarb.: 55. Prod.-värde pr år: 750,000 kr. —\nFältspat.brytningen upptagen 1907.\n\nStyrelse: ing. Eric Olson, ing, Hj.\nOlson, dir. Jonn H. Olson.\n\nVerkst. dir.: Jonn H. Olson.\n\nForshedaverken, Bröderna\nPetersson, Forsheda.\n\nManufakturverk i Forsheda (Jönköp.\nL). Tillverkar uniformsknappar, söljor,\nringar och beslag för seldon och\nsport-artiklar, skidbeslag, hakar, spännen,\nknäppen och andra massartiklar av tråd\noch plåt.\n\nTelegr.-adr.: Forshedaverken, Forsheda.\nTelefon: 6. Postgiro: 13371. — Antal\nindustriarb.: 45. Tillv.-värde pr år:\n850,000 kr. — Firman etabl. 1920.\n\nÄgare o. chefer: disp. David Petersson\no. ing. Natanael Petersson.\n\nForslund &amp; Co., Fabriks AB.,\n\nSkellefteå.\n\nSe Fabriks AB. Forslund &amp; Co.,\nSkellefteå.\n\nAB. Forslunds Verkstäder,\n\nLinköping.\n\nMek. verkstad, bilreparations- och\ngummiverkstäder. Utför bilservicearbeten\n(specialitet: motorrenoveringar),\nmetallsprutning m. m. samt tillverkar\nbygg-nads- och konstsmiden.\n\nTelefon: »Forslunds verkstäder».\nPostgiro: 29426. — Akt.-kap.: 130,000 kr.\nAntal industriarb.: 75. Omsättning pr\når: 2,500,000 kr. — Firman etabl. 1899,\nbolag 1937.\n\nStyrelse: ing. Melker Forslund (ordf.),\ning. Folke Forslund, ing. Helge\nForslund, ing. Olof Forslund.\n\nChefer: Melker Forslund o. Helge\nForslund.\n\n*AB. Forsnäs Snickerifabrik,\n\nForsnäs.\n\nTillverkar möbler vid fabrik i Forsnäs\n(Östergötl. l.).\n\nTelefon: Ydre 8. Postgiro: 71261. —\nAkt.-kap.: 27,200 kr. Antal industriarb.:\n23. Tillv.-värde pr år: 250,000 kr. —\nFirman etabl. 1916, bolag 1923.\n\nStyrelse: disp. L. J. Edward, kamrer\nLennart Edward, fabr. David Morhagen.\nVerkst. dir.: disp. L. J. Edward. .\n\n* Forss AB», Köpmanhohnen.\n\nSågverk, hyvleri, sulfitfabrik,\nsulfitspritfabrik, sulfatfabrik samt blekeri i\nKöpmanholmen (Västernorrl. l.).\nTillverkar sågade och hyvlade trävaror, blekt\noch oblekt sulfit- och sulfatcellulosa samt\nviscosmassa och sulfitsprit.\n\nHuvudkontor: Köpmanholmen.\nTelegr.-adr.: Forss, Köpmanholmen. Telefon:\nÖrnsköldsvik 2475, Bjästa 1 o. 54 samt\nKöpmanholmen 27. Postgiro: 133433.\n\nAkt.-kap.: 3,600,000 kr. Antal\nindustriarb.: 800. Årstillv.: 17,000 stds sågade o.\n3,000 stds hyvlade trävaror, 18,000 ton\nsulfitcellulosa o. 30,000 ton\nsulfatcellulosa. —- Bolaget grundat 1877.\n\nStyrelse: dir. Theodor Hedberg (ordf.),\nkapten Hj. Hedberg, dir. Oscar Hedberg,\ndir. Em. Högberg, bankdir. Ernst Åberg.\n\nVerkst. dir.: Theodor Hedberg.\n\nDisp.: John Sundberg.\n\nSkogschef: Nils Bergfeldt.",
    "structured": {
        "firms": [
            {
                "name": "Forsgård—Forss",
                "location": "Stockholm, Skeppsbron 36",
                "contact": {
                    "telegraph": "Iron, Stockholm",
                    "phone": [
                        "209317",
                        "18"
                    ],
                    "postgiro": "58868"
                },
                "financials": {
                    "capital": "150,000 kr",
                    "employees": {
                        "industriarb": 25
                    },
                    "annual_turnover": "400,000 kr",
                    "annual_production_value": "400,000 kr"
                },
                "foundation_year": 1914,
                "current_name_year": 1941,
                "board": [
                    {
                        "name": "Gösta Lindström",
                        "role": "Styrelse o. verkst. dir."
                    }
                ]
            },
            {
                "name": "Forsgårds AB., Klippan",
                "location": "Klippan (Kristianst. l.)",
                "products": "Tillverkar fransar, kantband och dragband för markiser, möbelband och möbelsnören, fransar och kantband för mattor, lampskärmsgaraityr, sidenband m. m.",
                "contact": {
                    "phone": "19061",
                    "postgiro": "99466"
                },
                "financials": {
                    "capital": "35,300 kr",
                    "employees": {
                        "arb-antal": 12
                    },
                    "annual_turnover": "150,000 kr"
                },
                "foundation_year": 1936,
                "board": [
                    {
                        "name": "Ewald Stridh",
                        "role": "Verkst. dir. o. disp."
                    }
                ]
            },
            {
                "name": "AB. Forshammars Bergverk, Köping",
                "location": "Köping",
                "business": "Fältspatbrott och malverk",
                "contact": {
                    "phone": "112",
                    "postgiro": "132892"
                },
                "financials": {
                    "capital": "100,000 kr",
                    "employees": {
                        "industriarb": 55
                    },
                    "annual_turnover": "750,000 kr"
                },
                "foundation_year": "1907",
                "board": [
                    {
                        "name": "ing. Eric Olson",
                        "role": "Styrelse"
                    },
                    {
                        "name": "ing, Hj. Olson",
                        "role": "Styrelse"
                    },
                    {
                        "name": "dir. Jonn H. Olson",
                        "role": "Styrelse"
                    }
                ],
                "director": "Jonn H. Olson"
            },
            {
                "name": "Forshedaverken, Bröderna Petersson, Forsheda",
                "location": "Forsheda (Jönköp L)",
                "products": "Tillverkar uniformsknappar, söljor, ringar och beslag för seldon och sport-artiklar, skidbeslag, hakar, spännen, knäppen och andra massartiklar av tråd och plåt",
                "contact": {
                    "telegraph": "Forshedaverken, Forsheda",
                    "phone": "6",
                    "postgiro": "13371"
                },
                "financials": {
                    "employees": {
                        "industriarb": 45
                    },
                    "annual_turnover": "850,000 kr"
                },
                "foundation_year": 1920,
                "owners": [
                    "disp. David Petersson",
                    "ing. Natanael Petersson"
                ]
            },
            {
                "name": "AB. Forslunds Verkstäder, Linköping",
                "location": "Linköping",
                "business": "Mek. verkstad, bilreparations- och gummiverkstäder",
                "contact": {
                    "phone": "Forslunds verkstäder",
                    "postgiro": "29426"
                },
                "financials": {
                    "capital": "130,000 kr",
                    "employees": {
                        "industriarb": 75
                    },
                    "annual_turnover": "2,500,000 kr"
                },
                "foundation_year": 1899,
                "corporation_year": 1937,
                "board": [
                    {
                        "name": "ing. Melker Forslund",
                        "role": "Styrelse"
                    },
                    {
                        "name": "ing. Folke Forslund",
                        "role": "Styrelse"
                    },
                    {
                        "name": "ing. Helge Forslund",
                        "role": "Styrelse"
                    },
                    {
                        "name": "ing. Olof Forslund",
                        "role": "Styrelse"
                    }
                ],
                "manager": "Melker Forslund",
                "managing_director": "Helge Forslund"
            },
            {
                "name": "AB. Forsnäs Snickerifabrik, Forsnäs",
                "location": "Forsnäs (Östergötl. l.)",
                "business": "Tillverkar möbler",
                "contact": {
                    "phone": "Ydre 8",
                    "postgiro": "71261"
                },
                "financials": {
                    "capital": "27,200 kr",
                    "employees": {
                        "industriarb": 23
                    },
                    "annual_turnover": "250,000 kr"
                },
                "foundation_year": 1916,
                "corporation_year": 1923,
                "board": [
                    {
                        "name": "disp. L. J. Edward",
                        "role": "Styrelse"
                    },
                    {
                        "name": "kamrer Lennart Edward",
                        "role": "Styrelse"
                    },
                    {
                        "name": "fabr. David Morhagen",
                        "role": "Styrelse"
                    }
                ],
                "managing_director": "disp. L. J. Edward"
            },
            {
                "name": "Forss AB», Köpmanhohnen",
                "location": "Köpmanholmen (Västernorrl. l.)",
                "business": "Sågverk, hyvleri, sulfitfabrik, sulfitspritfabrik, sulfatfabrik samt blekeri",
                "contact": {
                    "telegraph": "Forss, Köpmanholmen",
                    "phone": [
                        "Örnsköldsvik 2475",
                        "Bjästa 1 o. 54",
                        "Köpmanholmen 27"
                    ],
                    "postgiro": "133433"
                },
                "financials": {
                    "capital": "3,600,000 kr",
                    "employees": {
                        "industriarb": 800
                    },
                    "annual_turnover": "17,000 stds sågade o. 3,000 stds hyvlade trävaror, 18,000 ton sulfitcellulosa o. 30,000 ton sulfatcellulosa"
                },
                "foundation_year": 1877,
                "board": [
                    {
                        "name": "dir. Theodor Hedberg",
                        "role": "Styrelse"
                    },
                    {
                        "name": "kapten Hj. Hedberg",
                        "role": "Styrelse"
                    },
                    {
                        "name": "dir. Oscar Hedberg",
                        "role": "Styrelse"
                    },
                    {
                        "name": "dir. Em. Högberg",
                        "role": "Styrelse"
                    },
                    {
                        "name": "bankdir. Ernst Åberg",
                        "role": "Styrelse"
                    }
                ],
                "managing_director": "Theodor Hedberg",
                "director": "John Sundberg",
                "sales_manager": "Nils Bergfeldt"
            }
        ]
    }
}