{
    "original": "Margarinfabriken—Marieholm\n\nMargarinfabriken Örnen AB.,\n\nStockholm.\n\nTillverkar margarin, konstister,\nmatolja, fettemulsion samt glassmassa vid\nfabrik i Sickla, Nacka (Sthlms l.).\nVarumärken: »Lyran», »Tre Vapen» o.\n»Wirgo».\n\nPostadr.: Stockholm 4. Telegr.-adr.:\nörnmargarin, Stockholm. Telefon: 440880.\nPostgiro: 56970. — Akt.-kap.: 10,000 kr.\nArb.-antal: 6. — Fabriken anlagd 1934,\nbolag 1942.\n\nVerkst. dir.: Malte Göransson.\n\nMargretelunds Cruv AB.,\n\nÅkersberga.\n\nFältspatgruvor vid Margretelund,\nÅkersberga (Sthlms l.). Bryter fältspat\noch kvarts för kemiska industriens och\njärnhanteringens behov.\n\nTelegr.-adr.: Margretelunds,\nStockholm. Telefon: Härsbacka 51.\nEnsamför-sälj.: P. Bergendorff, Stockholm,\nArse-nalsg. 2; telefon: 110815.\n\nAkt.-kap.: 200,000 kr. Antal\nindustriarb.: 25. Prod.-värde pr år: 275,000 kr.\n— Bolaget grundat 1915.\n\nStyrelse: ryttm. frih. G. G. Falkenberg\n(ordf.), frih. Erik Adelswärd, disp. Josef\nBerglund.\n\nVerkst. dir. o. disp.: Josef Berglund.\n\nMarianneiunds Gjuteri &amp; Mek.\nVerkstad, Mariannelund.\n\nTillverkar cirkelsågverk, rikthyvlar,\ntimmerspel för sågverk samt trallvagnar\nför brädgårdar och torvindustri vid\nverkstad i Mariannelund (Jönköp. l.).\n\nTelefon: 32. Postgiro: 27883. —\nAntal industriarb.: 10. Tillv.-värde pr år:\n100,000 kr. — Firman etabl. 1880.\n\nÄgare o. chef: fabr. Julius Nilsson.\n\n\"Mariebergs Sågverk, Eöjaviken.\n\nSe Kungsgården-Mariebergs AB.,\nStockholm.\n\n*AB. Mariedahls Bruk, Falerum.\n\nPappersbruk samt ullspinneri\n(Göters-fors ullspinneri) vid Mariedal, Falerum\n(Kalmar l.). Tillverkar hand- och\nma-skingjord bokbinderipapp, matrispapp,\nkonstläderpapp samt svenskullsgarner.\n\nTelefon: 25. Postgiro: 34815.\nEnsam-försälj. för papp: Edvard Schneidler,\nStockholm, Malmskillnadsg. 54; telefon:\n232420.\n\nAkt.-kap.: 40,000 kr. Antal\nindustriarb.: 10. Årstillv.: 300 ton papp.\nTillv.-värde för ullspinneriet: 70,000 kr. —\nBruket anlagt 1815, bolag 1942.\n\nStyrelse: fabr. Axel Söderquist, fabr.\nSam. Söderquist, fabr. Sven Söderquist.\n\nVerkst. dir.: Axel Söderquist.\n\n\"Mariedals Tegel AB., Lundsbrunn.\n\nTillverkar mur- och taktegel samt\ndräneringsrör vid tegelbruk i Lundsbrunn\n(Skarab. l.).\n\nTelefon: 108. Ensamförsälj.:\nSkaraborgs läns Tegelförsäljningsförening\nu. p. a., Skövde.\n\nAkt.-kap.: 30,000 kr. Antal\nindustriarb.: 15. Årstillv.: 2,5 milj. st. tegelvaror.\n— Tegelbruket anlagt 1900.\n\nStyrelse o. verkst. dir.: kapten Ivar\nVirgin.\n\nMariefors Bruks AB., Stockholm.\n\nMek. verkstad och slipskivefabrik i\nMariefors, Torskors (Blekinge l.).\nTillverkar träförädlingsmaskiner och slipskivor.\nVarumärke: »Mabu».\n\nKontor: o. ensamförsälj.: AB. Milton\n&amp; Co., Stockholm, Blasieholmstorg 11.\nTelefon: 232355. Postgiro: 51012. —\nAkt.-kap.: 30,000 kr. Antal industriarb.: 18.\nTillv.-värde pr år: 175,000 kr. —\nVerkstaden anlagd omkr. år 1864, bolag 1942.\n\nVerkst. dir.: A. H. E. Milton (Sthlm).\n\nFabrikschef: Carl Olsson.\n\nMariehoims Bruk Järnverks AB.,\n\nGöteborg.\n\nGjuteri, mek. verkstad, såg och\nsnickerifabrik vid Marieholmsbruk (Jönköp. l.).\nTillverkar lantbruksmaskiner,\nhandels-gjutgods samt sågade och hyvlade\nträvaror. Vid bruket drives även jordbruk\noch skogshantering.\n\nHuvudkontor: Göteborg, Skeppsbron 1.\nTelefon: 111894 o. 134236.\nVerkstadskontor: Marieholmsbruk; telefon: 10;\npostgiro: 49215. — Akt.-kap.: 60,000 kr.\nAntal industriarb.: 40. — Bruket anlagt\n1836, bolag 1942.\n\nVerkst. dir.: civiling. Uno Särnmark.\n\n\"Marieholms Nya Industri AB.,\n\nGöteborg.\n\nKem. teknisk fabrik å Marieholm,\nGöteborg. Tillverkar såpa och utför fogfria\ngolv (märke: »Litosilo»). Försäljer\nbi-tuminösa preparat och isoleringsmaterial\nsamt utför arbeten därmed.\n\n365*",
    "structured": {
        "1": {
            "name": "Margarinfabriken Örnen AB.",
            "location": "Stockholm",
            "business": "Tillverkar margarin, konstister, matolja, fettemulsion samt glassmassa vid fabrik i Sickla, Nacka (Sthlms l.)",
            "products": "Varumärken: »Lyran», »Tre Vapen» o. »Wirgo».",
            "contact": {
                "office": "Stockholm 4",
                "phone": [
                    "440880"
                ],
                "postgiro": "56970",
                "head_office": "",
                "sales_offices": [],
                "telegraph": "örnmargarin, Stockholm"
            },
            "financials": {
                "capital": "10,000 kr",
                "employees": {
                    "Arb.-antal": 6
                },
                "annual_turnover": "",
                "annual_production_value": ""
            },
            "foundation_year": 1934,
            "current_name_year": 1942,
            "predecessor": "",
            "original_name": "",
            "corporation_year": "",
            "board": [],
            "owners": [],
            "director": "Malte Göransson",
            "managing_director": "",
            "sales_manager": "",
            "manager": ""
        },
        "2": {
            "name": "Margretelunds Cruv AB.",
            "location": "Åkersberga",
            "business": "Fältspatgruvor vid Margretelund, Åkersberga (Sthlms l.). Bryter fältspat och kvarts för kemiska industriens och järnhanteringens behov.",
            "products": "",
            "contact": {
                "office": "",
                "phone": [
                    "Härsbacka 51"
                ],
                "postgiro": "",
                "head_office": "",
                "sales_offices": [],
                "telegraph": "Margretelunds, Stockholm"
            },
            "financials": {
                "capital": "200,000 kr",
                "employees": {
                    "Antal industriarb.": 25
                },
                "annual_turnover": "275,000 kr",
                "annual_production_value": ""
            },
            "foundation_year": 1915,
            "current_name_year": "",
            "predecessor": "",
            "original_name": "",
            "corporation_year": "",
            "board": [
                {
                    "name": "freih. G. G. Falkenberg",
                    "role": "ordf."
                },
                {
                    "name": "frih. Erik Adelswärd",
                    "role": ""
                },
                {
                    "name": "disp. Josef Berglund",
                    "role": ""
                }
            ],
            "owners": [],
            "director": "",
            "managing_director": "Josef Berglund",
            "sales_manager": "",
            "manager": ""
        },
        "3": {
            "name": "Marianneiunds Gjuteri & Mek. Verkstad",
            "location": "Mariannelund",
            "business": "Tillverkar cirkelsågverk, rikthyvlar, timmerspel för sågverk samt trallvagnar för brädgårdar och torvindustri vid verkstad i Mariannelund (Jönköp. l.)",
            "products": "",
            "contact": {
                "office": "",
                "phone": [
                    "32"
                ],
                "postgiro": "27883",
                "head_office": "",
                "sales_offices": [],
                "telegraph": ""
            },
            "financials": {
                "capital": "",
                "employees": {
                    "Antal industriarb.": 10
                },
                "annual_turnover": "100,000 kr",
                "annual_production_value": ""
            },
            "foundation_year": 1880,
            "current_name_year": "",
            "predecessor": "",
            "original_name": "",
            "corporation_year": "",
            "board": [],
            "owners": [
                "fabr. Julius Nilsson"
            ],
            "director": "",
            "managing_director": "",
            "sales_manager": "",
            "manager": ""
        },
        "4": {
            "name": "AB. Mariedahls Bruk",
            "location": "Falerum",
            "business": "Pappersbruk samt ullspinneri (Göters-fors ullspinneri) vid Mariedal, Falerum (Kalmar l.). Tillverkar hand- och maskingjord bokbinderipapp, matrispapp, konstläderpapp samt svenskullsgarner.",
            "products": "",
            "contact": {
                "office": "",
                "phone": [
                    "25"
                ],
                "postgiro": "34815",
                "head_office": "",
                "sales_offices": [],
                "telegraph": ""
            },
            "financials": {
                "capital": "40,000 kr",
                "employees": {
                    "Antal industriarb.": 10
                },
                "annual_turnover": "",
                "annual_production_value": "300 ton papp"
            },
            "foundation_year": 1815,
            "current_name_year": 1942,
            "predecessor": "",
            "original_name": "",
            "corporation_year": "",
            "board": [
                {
                    "name": "fabr. Axel Söderquist",
                    "role": ""
                },
                {
                    "name": "fabr. Sam. Söderquist",
                    "role": ""
                },
                {
                    "name": "fabr. Sven Söderquist",
                    "role": ""
                }
            ],
            "owners": [],
            "director": "",
            "managing_director": "Axel Söderquist",
            "sales_manager": "",
            "manager": ""
        },
        "5": {
            "name": "Mariedals Tegel AB.",
            "location": "Lundsbrunn",
            "business": "Tillverkar mur- och taktegel samt dräneringsrör vid tegelbruk i Lundsbrunn (Skarab. l.)",
            "products": "",
            "contact": {
                "office": "",
                "phone": [
                    "108"
                ],
                "postgiro": "",
                "head_office": "",
                "sales_offices": [],
                "telegraph": ""
            },
            "financials": {
                "capital": "30,000 kr",
                "employees": {
                    "Antal industriarb.": 15
                },
                "annual_turnover": "",
                "annual_production_value": "2,5 milj. st. tegelvaror"
            },
            "foundation_year": 1900,
            "current_name_year": "",
            "predecessor": "",
            "original_name": "",
            "corporation_year": "",
            "board": [],
            "owners": [],
            "director": "",
            "managing_director": "",
            "sales_manager": "",
            "manager": "kapten Ivar Virgin"
        },
        "6": {
            "name": "Mariefors Bruks AB.",
            "location": "Stockholm",
            "business": "Mek. verkstad och slipskivefabrik i Mariefors, Torskors (Blekinge l.). Tillverkar träförädlingsmaskiner och slipskivor.",
            "products": "Varumärke: »Mabu».",
            "contact": {
                "office": "",
                "phone": [
                    "232355"
                ],
                "postgiro": "51012",
                "head_office": "",
                "sales_offices": [],
                "telegraph": ""
            },
            "financials": {
                "capital": "30,000 kr",
                "employees": {
                    "Antal industriarb.": 18
                },
                "annual_turnover": "",
                "annual_production_value": "175,000 kr"
            },
            "foundation_year": "",
            "current_name_year": 1942,
            "predecessor": "",
            "original_name": "",
            "corporation_year": "",
            "board": [],
            "owners": [],
            "director": "",
            "managing_director": "",
            "sales_manager": "",
            "manager": "A. H. E. Milton (Sthlm)"
        },
        "7": {
            "name": "Mariehoims Bruk Järnverks AB.",
            "location": "Göteborg",
            "business": "Gjuteri, mek. verkstad, såg och snickerifabrik vid Marieholmsbruk (Jönköp. l.). Tillverkar lantbruksmaskiner, handelsgjutgods samt sågade och hyvlade trävaror. Vid bruket drives även jordbruk och skogshantering.",
            "products": "",
            "contact": {
                "office": "Göteborg, Skeppsbron 1",
                "phone": [
                    "111894",
                    "134236"
                ],
                "postgiro": "49215",
                "head_office": "",
                "sales_offices": [],
                "telegraph": ""
            },
            "financials": {
                "capital": "60,000 kr",
                "employees": {
                    "Antal industriarb.": 40
                },
                "annual_turnover": "",
                "annual_production_value": ""
            },
            "foundation_year": 1836,
            "current_name_year": 1942,
            "predecessor": "",
            "original_name": "",
            "corporation_year": "",
            "board": [],
            "owners": [],
            "director": "civiling. Uno Särnmark",
            "managing_director": "",
            "sales_manager": "",
            "manager": ""
        },
        "8": {
            "name": "Marieholms Nya Industri AB.",
            "location": "Göteborg",
            "business": "Kem. teknisk fabrik å Marieholm, Göteborg. Tillverkar såpa och utför fogfria golv (märke: »Litosilo»). Försäljer bituminösa preparat och isoleringsmaterial samt utför arbeten därmed.",
            "products": "",
            "contact": {
                "office": "Marieholm, Göteborg",
                "phone": [],
                "postgiro": "",
                "head_office": "",
                "sales_offices": [],
                "telegraph": ""
            },
            "financials": {
                "capital": "",
                "employees": {},
                "annual_turnover": "",
                "annual_production_value": ""
            },
            "foundation_year": "",
            "current_name_year": "",
            "predecessor": "",
            "original_name": "",
            "corporation_year": "",
            "board": [],
            "owners": [],
            "director": "",
            "managing_director": "",
            "sales_manager": "",
            "manager": ""
        }
    }
}