{
    "original": "Metallfabrik—Mey er\n\nMetallfabriks AB. Knut Eriksson\n&amp; Co., Eskilstuna.\n\nTillverkar prydnadssaker i tenn samt\nhusgerådsartiklar i koppar och\naluminium.\n\nTelegr.-adr.: Metalleriksson, Eskilstuna.\nTelefon: 30304. Postgiro: 10790.\n\nAkt.-kap.: 250,000 kr. Antal\nindustriarb.: 15. Tillv.-värde pr år: 310,000 kr.\n— Firman etabl. 1906 under namn Knut\nEriksson &amp; Co., nuv. namn o. bolag 1946.\n\nStyrelse: fru Elsa Björkman, disp.\nWik-tor Björkman, änkefru M. Eriksson,\nbankkassör Bror Olsson, fru Signe Olsson.\n\nVerkst. dir.: Wiktor Björkman.\n\n* Metallfabriks AB. C. G. Sporrong &amp;\nCo., Stockholm.\n\nMetallvaru- och knappfabrik.\nTillverkar knappar och andra uniformseffekter\nav metall, förgyllda, försilvrade,\nförnick-lade, oxiderade och bronserade, medaljer\noch märken, med och utan emalj,\npolletter m. m. samt utför kall- och\nvarmpressning, dragning av koppar, mässing, brons\noch aluminium jämte torrförzinkning av\nmassartiklar av järn.\n\nKontor o. butik: Kungsg. 17.\nTelegr.-adr.: Sporrongs, Stockholm. Telefon:\n»Sporrong &amp; Co». Postgiro: 1405.\n\nAkt.-kap.: 787,500 kr. Antal\nindustriarb.: 215. Tillv.-värde pr år: 4,000,000 kr.\n\nDen av firman bedrivna verksamheten\nhar fortgått oavbrutet sedan år 1666. Det\nSporrongska namnet är knutet till\nverksamheten sedan 1842, aktiebolag 1891.\n\nStyrelse: överstelöjtn. Erik Holmquist,\nfrih. Bror af Klinteberg.\n\nVerkst. dir.: civiling. Mats Hede.\n\nV. verkst. dir.: Tage Swedberg.\n\nKamrer: Otto Järnulf.\n\nMetallförädling AB., Svensk,\n\nSundbyberg.\n\nSe Svensk Metallförädling AB.,\nSundbyberg.\n\nMetallhyttans AB., Anderstorp.\n\nMetallverk med valsverk,\nmässingstråd-drageri och pressgjuteri i Anderstorp\n(Jönköp. l.). Tillverkar nit, spik, skruv,\nmuttrar och brickor av metall,\nknapp-och hårnålar, sängkätting, spiralfjädrar,\nställbara gardinstänger m. m.\n\nTelefon: 11. Postgiro: 10412.—\nAkt.-kap.: 100,000 kr. Antal industriarb.: 80.\nTillv.-värde pr år: 1,000,000 kr. —\nFirman etabl. 1863, bolag 1923.\n\nChefer: disp. Filip Magnusson o. ing.\nGustaf Magnusson.\n\nAB. Metallmanufaktur, Merna,\n\nLidköping.\n\nSe Mema, AB. Metallmanufaktur,\nLidköping.\n\n\"AB. Metallurgisk Industri,\n\nTrollhättan.\n\nSe AB. Ferrolegeringar, Stockholm.\n\n\"Metallverken, AB., Svenska,\n\nVästerås.\n\nSe AB. Svenska Metallverken, Västerås.\n\nAB. Metaverken, Jönköping.\n\nKem. teknisk fabrik. Tillverkar\ntvätt-och rengöringsmedel, tvål, industriella\nav-fettningsmedel, desinfektionsmedel samt\nfärger m. m.\n\nTelefon: 4796 o. 5950. Postgiro: 263530.\n\nAkt.-kap.: 55,000 kr. Antal\nindustriarb.: 8. Tillv.-värde pr år: 500,000 kr. —\nBolaget grundat 1942.\n\nVerkst. dir.: ing. Erik Gustavii.\n\nDisp.: Gösta Blomqvist.\n\nEskil Metzén, Nya AB., Malmö.\nSe Nya AB. Eskil Metzén, Malmö.\n\n\"Otto Meyers Konst-, Metall- &amp;\nZink-gjuteri, Stockholm.\n\nUtför i olika metaller konstgjutningar\nsåsom statyer och statyetter, byster,\nreliefer, belysningsartiklar m. m.; tillverkar\nbyggnadsbeslag såsom handtag, räcken,\nbarriärer m. m., butiksmontrar samt\nskylt-ställ av metall.\n\nKontor: Västmannag. 81. Telegr.-adr.:\nMeyers konstgjuteri, Stockholm. Telefon:\n339385. Postgiro: 977.\n\nArb.-antal: 10. Tillv.-värde pr år:\n170,000 kr. — Firman etabl. 1872.\nÄgare o. chef: fabr. Arne Spanier.\n\nVilh. Mey er, Etui- &amp; Kartongfabrik,\n\nOnesta.\n\nTillverkar etuier, kartonger och\nskylt-ställ vid fabrik i Gnesta (Södermanl. l.).\n\nTelefon: 95. Försäljn.-kontor:\nSödertälje. Telefon: 31381. Postgiro: 28592.\n\nAntal industriarb.: 35. Tillv.-värde pr\når: 150,000 kr. — Firman, etabl. 1924,",
    "structured": {
        "1": {
            "name": "Metallfabriks AB. Knut Eriksson & Co.",
            "location": "Eskilstuna",
            "business": "Tillverkar prydnadssaker i tenn samt husgerådsartiklar i koppar och aluminium.",
            "contact": {
                "office": "Eskilstuna",
                "phone": [
                    "30304"
                ],
                "postgiro": "10790",
                "telegraph": "Metalleriksson, Eskilstuna"
            },
            "financials": {
                "capital": "250,000 kr",
                "employees": {
                    "industriarb": 15
                },
                "annual_turnover": "310,000 kr"
            },
            "foundation_year": 1906,
            "current_name_year": 1946,
            "board": [
                {
                    "name": "fru Elsa Björkman",
                    "role": "disp."
                },
                {
                    "name": "Wiktor Björkman",
                    "role": "disp."
                },
                {
                    "name": "änkefru M. Eriksson",
                    "role": null
                },
                {
                    "name": "bankkassör Bror Olsson",
                    "role": null
                },
                {
                    "name": "fru Signe Olsson",
                    "role": null
                }
            ],
            "director": "Wiktor Björkman"
        },
        "2": {
            "name": "Metallfabriks AB. C. G. Sporrong & Co.",
            "location": "Stockholm",
            "business": "Metallvaru- och knappfabrik. Tillverkar knappar och andra uniformseffekter av metall...",
            "contact": {
                "office": "Kungsg. 17",
                "phone": [
                    "Sporrong & Co"
                ],
                "postgiro": "1405",
                "telegraph": "Sporrongs, Stockholm"
            },
            "financials": {
                "capital": "787,500 kr",
                "employees": {
                    "industriarb": 215
                },
                "annual_turnover": "4,000,000 kr"
            },
            "foundation_year": 1666,
            "current_name_year": 1891,
            "board": [
                {
                    "name": "överstelöjtn. Erik Holmquist",
                    "role": null
                },
                {
                    "name": "frih. Bror af Klinteberg",
                    "role": null
                }
            ],
            "director": "civiling. Mats Hede",
            "managing_director": "Tage Swedberg",
            "manager": "Otto Järnulf"
        },
        "3": {
            "name": "Metallhyttans AB.",
            "location": "Anderstorp",
            "business": "Metallverk med valsverk, mässingstråd-drageri och pressgjuteri...",
            "contact": {
                "office": "Anderstorp (Jönköp. l.)",
                "phone": [
                    "11"
                ],
                "postgiro": "10412"
            },
            "financials": {
                "capital": "100,000 kr",
                "employees": {
                    "industriarb": 80
                },
                "annual_turnover": "1,000,000 kr"
            },
            "foundation_year": 1863,
            "corporation_year": 1923,
            "director": "disp. Filip Magnusson",
            "manager": "ing. Gustaf Magnusson"
        },
        "4": {
            "name": "AB. Metaverken",
            "location": "Jönköping",
            "business": "Kem. teknisk fabrik. Tillverkar tvätt-och rengöringsmedel, tvål, industriella av-fettningsmedel...",
            "contact": {
                "phone": [
                    "4796",
                    "5950"
                ],
                "postgiro": "263530"
            },
            "financials": {
                "capital": "55,000 kr",
                "employees": {
                    "industriarb": 8
                },
                "annual_turnover": "500,000 kr"
            },
            "foundation_year": 1942,
            "director": "ing. Erik Gustavii",
            "manager": "Gösta Blomqvist"
        },
        "5": {
            "name": "Otto Meyers Konst-, Metall- & Zink-gjuteri",
            "location": "Stockholm",
            "business": "Utför i olika metaller konstgjutningar såsom statyer och statyetter, byster, reliefer, belysningsartiklar m. m...",
            "contact": {
                "office": "Västmannag. 81",
                "phone": [
                    "339385"
                ],
                "postgiro": "977",
                "telegraph": "Meyers konstgjuteri, Stockholm"
            },
            "financials": {
                "employees": {
                    "arb.-antal": 10
                },
                "annual_turnover": "170,000 kr"
            },
            "foundation_year": 1872,
            "director": "fabr. Arne Spanier"
        },
        "6": {
            "name": "Vilh. Meyer, Etui- & Kartongfabrik",
            "location": "Onesta",
            "business": "Tillverkar etuier, kartonger och skylt-ställ vid fabrik i Gnesta (Södermanl. l.)",
            "contact": {
                "phone": [
                    "95"
                ],
                "postgiro": "28592"
            },
            "financials": {
                "employees": {
                    "industriarb": 35
                },
                "annual_turnover": "150,000 kr"
            },
            "foundation_year": 1924
        }
    }
}