{
    "original": "Gillberg—Gjuteri\n\nGillberg &amp; Co., Mek. Verkstad,\n\nStockholm.\n\nTillverkar rörskridskor och utför\npressningsarbeten.\n\nKontor: Wollmar Yxkullsg. 34.\nTelefon: 411209. Postgiro: 155585.\n\nArb.-antal: 15. Tillv.-värde pr år:\n150,000 kr. — Firman etabl. 1926.\n\nÄgare o. chefer: fabr. Georg Gillberg\no. fabr. Nils Thervin.\n\nCillbergs Etui- &amp; Portföljfabrik,\n\nStockholm.\n\nTillverkar etuier för smycken,\nsilvervaror, provkollektioner m. m., schatull för\nmatsilver samt skyltställ för juvelerare.\n\nKontor: Hamng. 36. Telefon: 101314.\nPostgiro: 57844. — Arb.-antal: 11. —\nFirman etabl. 1886.\n\nÄgare o. chef: fabr. Carl Rydin.\n\nAB. Ciltströms Mek. Verkstad,\n\nStockholm.\n\nTillverkar såsom specialitet\nsjälvsmörjande glidlager. Varumärke: »Glissa».\n\nKontor: Tuleg. 15. Telefon: 320844.\nPostgiro: 159569.\n\nAkt.-kap.: 100,000 kr. Antal\nindustriarb.: 20. Tillv.-värde pr år: 350,000 kr.\n\n—\tFirman etabl. 1910, bolag 1940.\n\nVerkst. dir.: fil. dr Josef Heuberger.\n\nGimo AB., Gävle.\n\nTegelbruk, snickerifabrik och\nanläggning för impregnering av trä i Gimo\n(Uppsala l.) samt torvströfabrik i Valö\n(Stockholms l.). Tillverkningen drives av\nKorsnäs Sågverks AB.\n\nHuvudkontor: Gävle; postadr.: Gävle\n2. Telefon: »Korsnäsverken». Postgiro:\n13001. Brukskontor: Gimo. — Akt.-kap.:\n11,000,000 kr. Antal industriarb.: 65.\n\nBolaget grundat 1893, nuv.\nbolagsordning 1937.\n\nStyrelse: kabinettskammarh. Robert v.\nHorn (ordf.), dir. Sven Engwall, dir.\nErik W. Eriksson, frih. Wilh. Klingspor,\növerfyring. Folke Lundeberg, överste\nGunnar Salander, adv. Hueo Stenbeck.\n\nVerkst. dir.: Erik W. Eriksson.\n\nAB. Gimo Trikåindustri, Gimo.\n\nTillverkar damunderkläder, sportblusar\noch -skjortor av charmeuse vid fabrik i\nGimo (Uppsala l.).\n\nTelefon: 33. Postgiro: 32182. —\nAkt.-kap.: 45,300 kr. Antal industriarb.: 25.\n\n—\tBolaget grundat 1934.\n\nFabriks för est.: Tage Johansson.\n\n\"Cislaveds CummJfabrik, Gislaved.\n\nSe Svenska Gummifabriks AB.,\nGisla-ved.\n\nGislaveds Mek. Verkstad,\n\nGislaved.\n\nMek. verkstad i Gislaved (Jönköp. l.).\nTillverkar snabbsvarvar och\nexceriter-pressar samt maskiner för gummi v ar\nu-industrien.\n\nTelefon: 22. — Antal industriarb.: 15.\n— Firman etabl. 1885.\n\nÄgare o. chef: fabr. Gunnar Malkner.\n\n*\tGislaveds Tråddrager i, Gislaved.\n\nTråddrageri och spikfabrik i Gislaved\n(Jönköp. l.). Tillverkar blank,\nförkopp-rad, glödgad, förtent och galvaniserad,\nrätad och öglad järntråd, häfttråd,\nresår-bottentråd, taggtråd, trådspik och\nkrampor. Firman driver jämväl kvarn och\nelektr. kraftstation.\n\nTelefon: 22 o. 464. Postgiro: 23383.—\nAntal industriarb.: 50. Tillv.-värde pr år:\n1,200,000 kr. — Firman etabl. 1907.\n\nÄgare o. chef: fabr. Gunnar Malkner.\n\n*Cisslarbo Järnbruk, Gisslarbo.\n\nSe Riddarhytte AB., Riddarhyttan.\n\nGjuteribolaget Berggren &amp; Olsson,\n\nFalkenberg.\n\nTackjärnsgjuteri och mek. verkstad,\nTillverkar tackjärns^ och metallgjutgods\nupp till 300 kg.\n\nTelefon: 172. Postgiro: 322902. —\nAntal industriarb.: 8. — Firman etabL 1946,\narrenderar och driver rörelsen av AB.\nElektrogjuteriet, Falkenberg, som\ngrundades 1937.\n\nDriftschef: gjutm. Carl Berggren.\n\n*\tGjuter! AB. Fundator, Sundbyberg.\n\nPressgjnteri och presseri. Tillverkar\npressgjutgods av aluminium-, zink- och\nmagnesiumlegering samt mässing; utför\npressade artiklar av bakelit, pollopas,\nthermopas m. m. samt pressgjutning av\ntermoplastiska massor; detaljer för skilda\nindustriella ändamål såsom sifferhjul,\ndelar^ till gasbrännare, rakhyvlar,\nräknemaskiner, motorer, magnetapparater*\ndörrstängare, dörrtrycken,\nbyggnadsbeslag, elektriska apparater, detaljer för ra~\ndio- och grammofonindustriens behov^\nslangar av syntetiskt gummi m. m.\n\nTelegr.-adr.: Fundator, Stockholm.\nTelefon: Stockholm 282700. Postgiro: 2160.",
    "structured": {
        "1": {
            "name": "Gillberg—Gjuteri",
            "location": "Stockholm",
            "business": "Tillverkar rörskridskor och utför pressningsarbeten.",
            "contact": {
                "office": "Wollmar Yxkullsg. 34",
                "phone": [
                    "411209"
                ],
                "postgiro": "155585"
            },
            "financials": {
                "capital": null,
                "employees": {
                    "total": 15
                },
                "annual_turnover": "150,000 kr",
                "annual_production_value": null
            },
            "foundation_year": 1926,
            "owners": [
                "fabr. Georg Gillberg",
                "fabr. Nils Thervin"
            ]
        },
        "2": {
            "name": "Cillbergs Etui- & Portföljfabrik",
            "location": "Stockholm",
            "business": "Tillverkar etuier för smycken, silvervaror, provkollektioner m. m., schatull för matsilver samt skyltställ för juvelerare.",
            "contact": {
                "office": "Hamng. 36",
                "phone": [
                    "101314"
                ],
                "postgiro": "57844"
            },
            "financials": {
                "capital": null,
                "employees": {
                    "total": 11
                },
                "annual_turnover": null,
                "annual_production_value": null
            },
            "foundation_year": 1886,
            "owners": [
                "fabr. Carl Rydin"
            ]
        },
        "3": {
            "name": "AB. Ciltströms Mek. Verkstad",
            "location": "Stockholm",
            "business": "Tillverkar såsom specialitet självsmörjande glidlager. Varumärke: »Glissa».",
            "contact": {
                "office": "Tuleg. 15",
                "phone": [
                    "320844"
                ],
                "postgiro": "159569"
            },
            "financials": {
                "capital": "100,000 kr",
                "employees": {
                    "total": 20
                },
                "annual_turnover": "350,000 kr",
                "annual_production_value": null
            },
            "foundation_year": 1910,
            "corporation_year": 1940,
            "director": "fil. dr Josef Heuberger"
        },
        "4": {
            "name": "Gimo AB.",
            "location": "Gävle",
            "business": "Tegelbruk, snickerifabrik och anläggning för impregnering av trä i Gimo (Uppsala l.) samt torvströfabrik i Valö (Stockholms l.). Tillverkningen drives av Korsnäs Sågverks AB.",
            "contact": {
                "head_office": "Gävle",
                "phone": "Korsnäsverken",
                "postgiro": "13001",
                "sales_offices": [
                    {
                        "location": "Gimo",
                        "phone": null
                    }
                ]
            },
            "financials": {
                "capital": "11,000,000 kr",
                "employees": {
                    "total": 65
                },
                "annual_turnover": null,
                "annual_production_value": null
            },
            "foundation_year": 1893,
            "board": [
                {
                    "name": "kabinettskammarh. Robert v. Horn",
                    "role": "ordf."
                },
                {
                    "name": "dir. Sven Engwall",
                    "role": null
                },
                {
                    "name": "dir. Erik W. Eriksson",
                    "role": null
                },
                {
                    "name": "frih. Wilh. Klingspor",
                    "role": null
                },
                {
                    "name": "överfyring. Folke Lundeberg",
                    "role": null
                },
                {
                    "name": "överste Gunnar Salander",
                    "role": null
                },
                {
                    "name": "adv. Hueo Stenbeck",
                    "role": null
                }
            ],
            "director": "Erik W. Eriksson"
        },
        "5": {
            "name": "AB. Gimo Trikåindustri",
            "location": "Gimo",
            "business": "Tillverkar damunderkläder, sportblusar och -skjortor av charmeuse vid fabrik i Gimo (Uppsala l.).",
            "contact": {
                "phone": "33",
                "postgiro": "32182"
            },
            "financials": {
                "capital": "45,300 kr",
                "employees": {
                    "total": 25
                },
                "annual_turnover": null,
                "annual_production_value": null
            },
            "foundation_year": 1934,
            "manager": "Tage Johansson"
        },
        "6": {
            "name": "Gislaveds Mek. Verkstad",
            "location": "Gislaved",
            "business": "Mek. verkstad i Gislaved (Jönköp. l.). Tillverkar snabbsvarvar och exceriter-pressar samt maskiner för gummi v aru-industrien.",
            "contact": {
                "phone": "22"
            },
            "financials": {
                "capital": null,
                "employees": {
                    "total": 15
                },
                "annual_turnover": null,
                "annual_production_value": null
            },
            "foundation_year": 1885,
            "owner": "fabr. Gunnar Malkner"
        },
        "7": {
            "name": "Gislaveds Tråddrager i",
            "location": "Gislaved",
            "business": "Tråddrageri och spikfabrik i Gislaved (Jönköp. l.). Tillverkar blank, förkopp-rad, glödgad, förtent och galvaniserad, rätad och öglad järntråd, häfttråd, resår-bottentråd, taggtråd, trådspik och krampor.",
            "contact": {
                "phone": [
                    "22",
                    "464"
                ],
                "postgiro": "23383"
            },
            "financials": {
                "capital": null,
                "employees": {
                    "total": 50
                },
                "annual_turnover": "1,200,000 kr",
                "annual_production_value": null
            },
            "foundation_year": 1907,
            "owner": "fabr. Gunnar Malkner"
        },
        "8": {
            "name": "Gjuteribolaget Berggren &amp; Olsson",
            "location": "Falkenberg",
            "business": "Tackjärnsgjuteri och mek. verkstad, Tillverkar tackjärns^ och metallgjutgods upp till 300 kg.",
            "contact": {
                "phone": "172",
                "postgiro": "322902"
            },
            "financials": {
                "capital": null,
                "employees": {
                    "total": 8
                },
                "annual_turnover": null,
                "annual_production_value": null
            },
            "foundation_year": 1946,
            "director": "gjutm. Carl Berggren"
        },
        "9": {
            "name": "Gjuter! AB. Fundator",
            "location": "Sundbyberg",
            "business": "Pressgjnteri och presseri. Tillverkar pressgjutgods av aluminium-, zink- och magnesiumlegering samt mässing; utför pressade artiklar av bakelit, pollopas, thermopas m. m. samt pressgjutning av termoplastiska massor; detaljer för skilda industriella ändamål såsom sifferhjul, delar^ till gasbrännare, rakhyvlar, räknemaskiner, motorer, magnetapparater* dörrstängare, dörrtrycken, byggnadsbeslag, elektriska apparater, detaljer för ra~ dio- och grammofonindustriens behov^ slangar av syntetiskt gummi m. m.",
            "contact": {
                "telegraph": "Fundator, Stockholm",
                "phone": "Stockholm 282700",
                "postgiro": "2160"
            }
        }
    }
}