{
    "original": "J ohansson\n\narb.: 15. — Firman etabl. 1894, bolag\n1927.\n\nStyrelse: ing. Olle Vällfors (ordf.), fru\nS. Johansson, fabr. Erik Vällfors.\n\nVerkst? dir.: Erik Vällfors.\n\nA.\tC. Johansons Metallfabrik AB.,\n\nVästerås.\n\nMetallfabrik med gjuteri och mek.\nverkstad. Tillverkar mejeriarmatur av\nmässing och rostfritt stål, metallarmatur för\ngas, vatten och ånga, mjölkpumpar samt\nsnabbkopplingar.\n\nTelefon: 30155 o. 30408. Postgiro:\n90555. Representanter: för\nmejeriutensilier: AB, Separator, Stockholm, o.\nWed-holms AB., Nyköping; för kopplingar:\nHarald Pihlblads Maskinaffär,\nStockholm, Norrtullsg. 53, telefon: 331943.\n\nAkt.-kap.: 50,000 kr. Antal\nindustriarb.: 40. Tillv.-värde pr år: 500,000 kr.\n— Firman etabl. 1870, bolag 1941.\n\nVerkst. dir.: fabr. Carl Holmqvist.\n\nB.\tJohansson, Töreboda\nKeramikfabrik, Töreboda.\n\nSe Töreboda Keramikfabrik, B.\nJohanason, Töreboda.\n\nBertil Johanson, Industrikompaniet,\n\nSkillingaryd.\n\nSe Industrikompaniet Bertil Johanson,\nSkillingaryd.\n\nCarl Johansson Mek. Verkstad AB.,\n\nStockholm.\n\nTillverkar pressverktyg,\nbesiktningsverktyg, borrgiggar m. m.\n\nKontor: N. Smedjeg. 30—32. Telefon:\n200556 o. 102256. Postgiro: 3441. —\nAkt.-kap.: 100,000 kr. Antal industriarb.: 20.\nTillv.-värde pr år: 200,000 kr. — Firman\netabl. 1925, bolag 1932.\n\nVerkst. dir.. Fred A. Johansson.\n\nVerkstadschef: ing. Oswald Gustafsson.\n\n*Claes Johansson &amp; Co:s Väfveri AB.,\n\nGöteborg.\n\nSe Mölnlycke Väfveri AB., Göteborg.\n\n*AB. C. E» Johansson, Eskilstuna.\n\nMek. verkstad. Tillverkar måttsatser,\ntillbehörssatser, normal- och\ntoleransmät-verktyg, toleransindikatorer och\nmätinstrument, gängmätverktyg,\nmikrometrar och stickmått, borrchuckar,\ngänghuvuden och gängbackar, gängtappar och\n\ngängsnitt, gängstål, cykelkedjor m. m.\nVarumärke: »CEJ».\n\nTelegr.-adr.: Combination, Eskilstuna.\nTelefon: 37470. Postgiro: 9979.\n\nAkt.-kap.: 3,000,000 kr. Antal\nindustriarb.: 500. Tillv.-värde pr år: 6,000,000\nkr. — Bolaget grundat 1911, nuv.\nbolagsordning 1941.\n\nStyrelse: borgmäst. Wilhelm Hallin\n(ordf.), dir. Richard Dahlgren, dir. Algot\nDomellöf, dir. Rudolf Domellöf, ing. Edv.\nJ ohansson, dir. Helge Norlander, dir.\nErik G. Pehrsson.\n\nVerkst. dir.: Rudolf Domellöf.\n\nKamrer: Oscar Kjellberg.\n\nVerkstadschef: Iwar Eriksson.\n\nAB. C. E. Johanssons Metallduks-\n\nfabrik, Anderstorp.\n\nTillverkar järntrådduk,\nmässingstrådduk och stängselnät vid fabrik i\nAnderstorp (Jönköp. l.).\n\nTelefon: 118. Postgiro: 131529. —\nAkt.-kap.: 42,000 kr. Antal industriarb.:\n15. Tillv.-värde pr år: 250,000 kr. —\nFirman etabl. 1889, bolag 1936.\n\nVerkst. dir.: Fredr. Petersson.\n\nKamrer: Eric Wilhelmsson.\n\nE. Johansson &amp; C. Bohmans\nLervarufabrik, Töreboda,\n\nTillverkar oglaserade trädgårdskrukor\nvid lervarufabrik i Töreboda. (Skarab. l.).\n\nTelefon: 329 o. 199. Postgiro: 142601.\n— Akt.-kap.: 10,000 kr. Antal\nindustriarb.: 14. Tillv.-värde pr år: 90,000 kr. —\nFirman etabl. 1933.\n\nChef: fabr. Georg Bohman.\n\nErik Johanssons Elektro-Mek.\nVerkstad, Stockholm.\n\nTillverkar biografteknisk^ apparatur,\nsnäckväxlar och spel,\nregleringstransformatorer och reostater, scenställverk och\nstrålkastare.\n\nKontor: Huvudstavägen 49. Telefon:\n530824 o. 538486. Postgiro: 53752. —\nAntal industriarb.: 20. Tillv.-värde pr år:\n250,000 kr. — Firman etabl. 1918.\n\nChef: Olle Johansson.\n\nKamrer: Henning Collin.\n\nAB. E. C. Johanssons Boktryckeri,\n\nKarlshamn.\n\nTidnings-, bok- och accidenstryckeri,\nbokbinderi och kontorsbokfabrik. Utför\ntidnings- och boktryck, blanketter och\nkontorsböcker.",
    "structured": {
        "1": {
            "name": "A. C. Johansons Metallfabrik AB",
            "location": "Västerås",
            "business": "Metallfabrik med gjuteri och mek. verkstad",
            "products": "Tillverkar mejeriarmatur av mässing och rostfritt stål, metallarmatur för gas, vatten och ånga, mjölkpumpar samt snabbkopplingar",
            "contact": {
                "office": null,
                "phone": [
                    "30155",
                    "30408"
                ],
                "postgiro": "90555",
                "head_office": null,
                "sales_offices": null,
                "telegraph": null,
                "factory_office": null,
                "factory_phone": null
            },
            "financials": {
                "capital": "50,000 kr",
                "employees": {
                    "industriarb": 40
                },
                "annual_turnover": "500,000 kr",
                "annual_production_value": "500,000 kr"
            },
            "foundation_year": 1894,
            "corporation_year": 1927,
            "board": [
                {
                    "name": "ing. Olle Vällfors",
                    "role": "ordf."
                },
                {
                    "name": "fru S. Johansson",
                    "role": null
                },
                {
                    "name": "fabr. Erik Vällfors",
                    "role": null
                }
            ]
        },
        "2": {
            "name": "Carl Johansson Mek. Verkstad AB.",
            "location": "Stockholm",
            "business": null,
            "products": "Tillverkar pressverktyg, besiktningsverktyg, borrgiggar m. m.",
            "contact": {
                "office": "N. Smedjeg. 30—32",
                "phone": [
                    "200556",
                    "102256"
                ],
                "postgiro": "3441",
                "head_office": null,
                "sales_offices": null,
                "telegraph": null,
                "factory_office": null,
                "factory_phone": null
            },
            "financials": {
                "capital": "100,000 kr",
                "employees": {
                    "industriarb": 20
                },
                "annual_turnover": "200,000 kr",
                "annual_production_value": "200,000 kr"
            },
            "foundation_year": 1925,
            "corporation_year": 1932,
            "board": null
        },
        "3": {
            "name": "AB. C. E» Johansson",
            "location": "Eskilstuna",
            "business": "Mek. verkstad",
            "products": "Tillverkar måttsatser, tillbehörssatser, normal- och toleransmät-verktyg, toleransindikatorer och mätinstrument, gängmätverktyg, mikrometrar och stickmått, borrchuckar, gänghuvuden och gängbackar, gängtappar och gängsnitt, gängstål, cykelkedjor m. m.",
            "contact": {
                "office": null,
                "phone": [
                    "37470"
                ],
                "postgiro": "9979",
                "head_office": null,
                "sales_offices": null,
                "telegraph": "Combination, Eskilstuna",
                "factory_office": null,
                "factory_phone": null
            },
            "financials": {
                "capital": "3,000,000 kr",
                "employees": {
                    "industriarb": 500
                },
                "annual_turnover": "6,000,000 kr",
                "annual_production_value": "6,000,000 kr"
            },
            "foundation_year": 1911,
            "corporation_year": 1941,
            "board": [
                {
                    "name": "borgmäst. Wilhelm Hallin",
                    "role": "ordf."
                },
                {
                    "name": "dir. Richard Dahlgren",
                    "role": null
                },
                {
                    "name": "dir. Algot Domellöf",
                    "role": null
                },
                {
                    "name": "dir. Rudolf Domellöf",
                    "role": null
                },
                {
                    "name": "ing. Edv. J ohansson",
                    "role": null
                },
                {
                    "name": "dir. Helge Norlander",
                    "role": null
                },
                {
                    "name": "dir. Erik G. Pehrsson",
                    "role": null
                }
            ]
        },
        "4": {
            "name": "AB. E. C. Johanssons Metallduksfabrik",
            "location": "Anderstorp",
            "business": null,
            "products": "Tillverkar järntrådduk, mässingstrådduk och stängselnät",
            "contact": {
                "office": null,
                "phone": [
                    "118"
                ],
                "postgiro": "131529",
                "head_office": null,
                "sales_offices": null,
                "telegraph": null,
                "factory_office": null,
                "factory_phone": null
            },
            "financials": {
                "capital": "42,000 kr",
                "employees": {
                    "industriarb": 15
                },
                "annual_turnover": "250,000 kr",
                "annual_production_value": "250,000 kr"
            },
            "foundation_year": 1889,
            "corporation_year": 1936,
            "board": [
                {
                    "name": "Fredr. Petersson",
                    "role": "Verkst. dir."
                }
            ]
        },
        "5": {
            "name": "E. Johansson & C. Bohmans Lervarufabrik",
            "location": "Töreboda",
            "business": "Tillverkar oglaserade trädgårdskrukor",
            "products": null,
            "contact": {
                "office": null,
                "phone": [
                    "329",
                    "199"
                ],
                "postgiro": "142601",
                "head_office": null,
                "sales_offices": null,
                "telegraph": null,
                "factory_office": null,
                "factory_phone": null
            },
            "financials": {
                "capital": "10,000 kr",
                "employees": {
                    "industriarb": 14
                },
                "annual_turnover": "90,000 kr",
                "annual_production_value": "90,000 kr"
            },
            "foundation_year": 1933,
            "corporation_year": null,
            "board": [
                {
                    "name": "fabr. Georg Bohman",
                    "role": "Chef"
                }
            ]
        },
        "6": {
            "name": "Erik Johanssons Elektro-Mek. Verkstad",
            "location": "Stockholm",
            "business": "Tillverkar biografteknisk^ apparatur, snäckväxlar och spel, regleringstransformatorer och reostater, scenställverk och strålkastare.",
            "products": null,
            "contact": {
                "office": "Huvudstavägen 49",
                "phone": [
                    "530824",
                    "538486"
                ],
                "postgiro": "53752",
                "head_office": null,
                "sales_offices": null,
                "telegraph": null,
                "factory_office": null,
                "factory_phone": null
            },
            "financials": {
                "capital": null,
                "employees": {
                    "industriarb": 20
                },
                "annual_turnover": "250,000 kr",
                "annual_production_value": "250,000 kr"
            },
            "foundation_year": 1918,
            "corporation_year": null,
            "board": [
                {
                    "name": "Olle Johansson",
                    "role": "Chef"
                }
            ]
        },
        "7": {
            "name": "AB. E. C. Johanssons Boktryckeri",
            "location": "Karlshamn",
            "business": "Tidnings-, bok- och accidenstryckeri, bokbinderi och kontorsbokfabrik",
            "products": "Utför tidnings- och boktryck, blanketter och kontorsböcker",
            "contact": {
                "office": null,
                "phone": null,
                "postgiro": null,
                "head_office": null,
                "sales_offices": null,
                "telegraph": null,
                "factory_office": null,
                "factory_phone": null
            },
            "financials": {
                "capital": null,
                "employees": null,
                "annual_turnover": null,
                "annual_production_value": null
            },
            "foundation_year": null,
            "corporation_year": null,
            "board": null
        }
    }
}