{
    "original": "Björn ha m mur—Blomberg\n\nTillverkar kallblåst träkolstackjärn för\ngjuteriändamål, ånghammar- och\nmanu-faktursmiden samt hejarsmiden,\ntack-järnsgjutgods såsom cylindergods, finare\nmaskingods, kokillhärdade valsar,\neldhär-digt och syrafast gjutgods etc., sten- och\nsmidesredskap m. m.\n\nTelegr.-adr.: Björneborg, Kristinehamn.\nTelefon: 100—04. Postgiro: 29800.\n\nAkt.-kap.: 1,500,000 kr. Antal\nindustriarb.: 400. Tillv.-värde pr år: 6,500,000\nkr. — Bruket anlagt 1656, nuv. bolag\ngrundat 1925.\n\nStyrelse. disp. N. Arvid Ericsson\n(ordf.), bankdir. Richard Julin, bankdir.\nMarcus Wallenberg, dir. Walter Wehtje.\n\nDisp.: Nils Årmann.\n\n*Björnhammars Tråddragerl,\n\n11 j or t kvarn.\n\nSe AB. Gryts Bruk, Hjortkvarn.\nAB. J. F. Björsell, Borås.\n\nBoktryckeri med bokbinderi. Utför\naffärs- och reklamtryck. Bolaget driver\näven pappershandel och\nkontorsmöbelförsäljning.\n\nTelefon: 10020. Postgiro: 8652. —\nAkt.-kap.: 89,000 kr. Antal anställda: 21.\n— Firman etabl. 1888, bolag 1915.\n\nDisp.: Allan Björsell.\n\nBleck- &amp; Plåtemballage AB.,\n\nSundbyberg.\n\nBleckemballagefabrik. Tillverkar\nemballage och andra artiklar av bleckplåt,\nsvartplåt och galvaniserad plåt.\n\nKontor: Karlsbodavägen 206. Telefon:\nStockholm 283636. Postgiro: 172578. —\nAkt.-kap.: 60,000 kr. Antal industriarb.:\n12. Tillv.-värde pr år: 160,000 kr. —\nBolaget grundat 1940.\n\nVerkst. dir.: Gunnar Bernhard.\n\n*AB. Bleckvarufabriken, Malmö.\n\nBleckvarufabrik och litografiskt\nplåttryckeri. Tillverkar bleckemballage,\nmassartiklar av järn- och metallplåt,\nstålplomber m. m. Specialitet: konservemballage.\n\nKontor: Fagerstagatan 1. Telegr.-adr.:\nBleckemballage, Malmö. Telefon:\n»Plåtmanufaktur». Postgiro: 14147. Huvud- o.\nförsäljn.-kontor: AB. Plåtmanufaktur,\nStockholm, Biblioteksg. 26, telefon:\n235700 (se detta bolag).\n\nAntal industriarb.: 360. Tillv.-värde\npr år: 8,000,000 kr. — Bolaget, som\ngrundades 1898, är anslutet till AB.\nPlåtmanufaktur, Stockholm.\n\nDisp.: Axel Laurin.\n\nFabrihschef: J. F. Denell.\n\nB likstorps Silkeindustri, Rittfeldt &amp;\nCo., Blikstorp.\n\nTrikåfabrik i Blikstorp (Skarab. l.).\nTillverkar charmeuse- och\nbomullstrikå-vävnader samt damunderkläder och\nklänningar.\n\nTelefon: Fridene 1. Postgiro: 73506. —\nAntal industriarb.: 23. Tillv.-värde pr år:\n700,000 kr. — Fabriken grundad 1930.\n\nChef: C. F. Rittfeldt.\n\nAB. Blockmetall, Malmö.\n\nSe AB. Ny by Metallverk, Nybybruk.\n\nLinkoln Bloms Boktryckeri AB.,\n\nStockholm.\n\nUtför boktryck, tidnings- och\nblanketttryck. Bolaget förlägger tidningarna\nStockholms Förstadsblad, Lidingö\nTidning, Saltsjöbaden, Södra Förstadsbladet\noch Vaxholms Tidning.\n\nHuvudkontor: Gamla Brog. 38. Telefon:\n232040. Postgiro: 3540. Filialkontor:\nSundbyberg, telefon: Stockholm 280122.\n\nAkt.-kap.: 25,000 kr. Antal\nindustriarb.: 20. Tillv.-värde pr år: 200,000 kr.\n— Firman etabl. 1898, bolag 1902.\n\nVerkst. dir.: Gösta Blom.\n\n* Blombacka AB., Lindfors.\n\nTråddrageri, linslageri och\ntrådspik-fabrik vid Lindfors (Värml. l.). Tillverkar\ndragen järn- och ståltråd, ståltrådslinor\nför gruvor, hissar och kranar m. fl.,\ngal-vaniserade linor, rostfria linor samt\ntrådspik (även rostfri) jämte formstift för\ngjuterier. Bolaget idkar jämväl jordbruk\noch skogshantering.\n\nTelegr.-adr.: Blombackabolag, Karlstad.\nTelefon: Molkom 300. Postgiro: 27200.\n\nAkt.-kap.: 1,440,000 kr. Antal\nindustriarb.: 130. Tillv.-värde pr år: 3,000,000 kr.\n— Bolaget, grundat 1882, äges av\nUddeholms AB.\n\nStyrelse: disp. N. Danielsen (ordf.),\ndir. Edvin Fornander, dir. Kjell\nÅker-hielm.\n\nPlatschef: Einar Pettersson.\n\nKontorschef: Ragnar Sundberg.\n\n*David Blombergs Verkstads AB.,\n\nStockholm.\n\nSe Sala Möbelfabriks AB., Stockholm.",
    "structured": {
        "1": {
            "name": "Björnhammars Tråddrageri",
            "location": "Björneborg, Kristinehamn",
            "business": "Tillverkar kallblåst träkolstackjärn för gjuteriändamål, ånghammar- och manufaktursmiden samt hejarsmiden, tackjärnsgjutgods såsom cylindergods, finare maskingods, kokillhärdat valsar, eldhärdigt och syrafast gjutgods etc., sten- och smidesredskap m.m.",
            "contact": {
                "office": "Björneborg, Kristinehamn",
                "phone": [
                    "100-04"
                ],
                "postgiro": "29800"
            },
            "financials": {
                "capital": "1,500,000 kr",
                "employees": {
                    "industriarb": 400
                },
                "annual_turnover": "6,500,000 kr",
                "annual_production_value": "6,500,000 kr"
            },
            "foundation_year": 1925,
            "board": [
                {
                    "name": "N. Arvid Ericsson",
                    "role": "ordf."
                },
                {
                    "name": "Richard Julin",
                    "role": "bankdir."
                },
                {
                    "name": "Marcus Wallenberg",
                    "role": "bankdir."
                },
                {
                    "name": "Walter Wehtje",
                    "role": "dir."
                }
            ],
            "director": "Nils Årmann"
        },
        "2": {
            "name": "AB. J. F. Björsell",
            "location": "Borås",
            "business": "Boktryckeri med bokbinderi. Utför affärs- och reklamtryck. Bolaget driver även pappershandel och kontorsmöbelförsäljning.",
            "contact": {
                "office": "Borås",
                "phone": [
                    "10020"
                ],
                "postgiro": "8652"
            },
            "financials": {
                "capital": "89,000 kr",
                "employees": {
                    "anställda": 21
                }
            },
            "foundation_year": 1915,
            "director": "Allan Björsell"
        },
        "3": {
            "name": "Bleck- & Plåtemballage AB.",
            "location": "Sundbyberg",
            "business": "Bleckemballagefabrik. Tillverkar emballage och andra artiklar av bleckplåt, svartplåt och galvaniserad plåt.",
            "contact": {
                "office": "Karlsbodavägen 206, Stockholm",
                "phone": [
                    "Stockholm 283636"
                ],
                "postgiro": "172578"
            },
            "financials": {
                "capital": "60,000 kr",
                "employees": {
                    "industriarb": 12
                },
                "annual_production_value": "160,000 kr"
            },
            "foundation_year": 1940,
            "director": "Gunnar Bernhard"
        },
        "4": {
            "name": "AB. Bleckvarufabriken",
            "location": "Malmö",
            "business": "Bleckvarufabrik och litografiskt plåttryckeri. Tillverkar bleckemballage, massartiklar av järn- och metallplåt, stålplomber m.m.",
            "contact": {
                "office": "Fagerstagatan 1, Malmö",
                "phone": [
                    "Plåtmanufaktur"
                ],
                "postgiro": "14147"
            },
            "financials": {
                "employees": {
                    "industriarb": 360
                },
                "annual_production_value": "8,000,000 kr"
            },
            "foundation_year": 1898,
            "director": "Axel Laurin",
            "factory_office": "AB. Plåtmanufaktur, Stockholm, Biblioteksg. 26, Stockholm",
            "factory_phone": "235700 (se detta bolag)"
        },
        "5": {
            "name": "Blikstorps Silkeindustri, Rittfeldt & Co.",
            "location": "Blikstorp (Skarab. l.)",
            "business": "Trikåfabrik. Tillverkar charmeuse- och bomullstrikåvävnader samt damunderkläder och klänningar.",
            "contact": {
                "office": "Blikstorp (Skarab. l.)",
                "phone": [
                    "Fridene 1"
                ],
                "postgiro": "73506"
            },
            "financials": {
                "employees": {
                    "industriarb": 23
                },
                "annual_production_value": "700,000 kr"
            },
            "foundation_year": 1930,
            "director": "C. F. Rittfeldt"
        },
        "6": {
            "name": "AB. Blockmetall",
            "location": "Malmö",
            "description": "Se AB. Ny by Metallverk, Nybybruk"
        },
        "7": {
            "name": "Linkoln Bloms Boktryckeri AB.",
            "location": "Stockholm",
            "business": "Utför boktryck, tidnings- och blanketttryck. Bolaget förlägger tidningarna Stockholms Förstadsblad, Lidingö Tidning, Saltsjöbaden, Södra Förstadsbladet och Vaxholms Tidning.",
            "contact": {
                "office": "Gamla Brog. 38, Stockholm",
                "phone": [
                    "232040"
                ],
                "postgiro": "3540",
                "filialkontor": "Sundbyberg, Stockholm"
            },
            "financials": {
                "capital": "25,000 kr",
                "employees": {
                    "industriarb": 20
                },
                "annual_production_value": "200,000 kr"
            },
            "foundation_year": 1902,
            "director": "Gösta Blom"
        },
        "8": {
            "name": "Blombacka AB.",
            "location": "Lindfors",
            "business": "Tråddrageri, linslageri och trådspikfabrik vid Lindfors (Värml. l.). Tillverkar dragen järn- och ståltråd, ståltrådslinor för gruvor, hissar och kranar m.fl., galvaniserade linor, rostfria linor samt trådspik (även rostfri) jämte formstift för gjuterier. Bolaget idkar även jordbruk och skogshantering.",
            "contact": {
                "office": "Blombackabolag, Karlstad",
                "phone": [
                    "Molkom 300"
                ],
                "postgiro": "27200"
            },
            "financials": {
                "capital": "1,440,000 kr",
                "employees": {
                    "industriarb": 130
                },
                "annual_production_value": "3,000,000 kr"
            },
            "foundation_year": 1882
        },
        "9": {
            "name": "David Blombergs Verkstads AB.",
            "location": "Stockholm",
            "description": "Se Sala Möbelfabriks AB., Stockholm."
        }
    }
}