{
    "original": "Skelleftehamn—Skinnkonfektion\n\nSkelleftehamns Golvparkett AB.,\n\nSkellefteharnn.\n\nTillverkar parkettstav av ek, björk och\nfuru, trappledstänger samt\nbyggnadssnickerier och butiksinredningar vid fabrik i\nSkellefteharnn (Västerb. l.).\n\nTelefon: 31078. Postgiro: 61534. —\nAkt.-kap.: 151,800 kr. Tillv.-värde pr år:\n400,000 kr. Bolaget grundat 1937.\n\nVerkst. dir.: Herman Andersson.\n\n*Skellefteå Gruv AB., Skellefteharnn.\n\nSe Bolidens Gruv AB., Skellefteharnn.\n\n*AB. Skellefteå Spisbrödsfabrik,\n\nSkellefteå.\n\nTillverkar spis-, knäöke- och\ndelikatess-bröd.\n\nTelegr.-adr. o. telefon:\nSpisbrödsfabriken, Skellefteå. Postgiro: 21466.\n\nAkt.-kap.: 2;0öD,000 kr. Antal\nindustriarb.: 141. Tillv.-värde pr år: 4,000,000 kr.\n\nBolaget, grundat 1919, äger AB. Wasa\nSpisbrödsfabrik, Filipstad.\n\nStyrelse: konsul Karl Lundström\n(ordf.), borgm. Thomas Lundquist, fru G.\nLundström.\n\nVerkst. dir.: Karl Lundström (Sthlm).\n\nDisp.: Sten Utterström.\n\n\"Skellefteå Trämassefabrik,\n\nUrsviken.\n\nSe AB. Scharins Söner, Klemensnäs.\n\n\"Skellefteå Ångbryggeri AB.,\n\nSkellefteå.\n\nTillverkar malt- och läskedrycker.\n\nTelegr.-adr. o. telefon: Ångbryggeriet,\nSkellefteå. Postgiro: 61926.\n\nAkt.-kap.: 150,000 kr. Antal\nindustriarb.: 28. Tillv.-värde pr år: 975,000 kr.\n— Bolaget grundat 1893.\n\nStyrelse: disp. Otto Nyberg (ordf.),\ndisp. Carl Birger Carlsson, adv. A. Rehn.\n\nVerkst. dir. o. disp.: O. B. Carlsson.\n\nKassör: J. M. Nygren.\n\n*Skeppshults Bruks AB.,\n\nSkeppshult.\n\nTråddrageri och spikfabrik i\nSkepps-hult samt tråddrageri i Smålandsstenar\n(båda i Jönköp. l.). Tillverkar järntråd,\ntrådspik, krampor och taggtråd. Firman\ndriver jämväl sågverk, kvarn och elektr.\nkraftstation samt jordbruk.\n\nKontor: Skeppshult. Telegr.-adr.:\nBruket, Skeppshult. Telefon: 1. Postgiro:\n75120.\n\nAkt.-kap.: 250,000 kr. Antal\nindustriarb.: i Skeppshult 40, i Smålandsstenar\n4. Tillv.-värde pr år: 900,000 kr. —\nBolaget grundat 1916, ombildat med nuv.\nnamn 1928.\n\nStyrelse: disp. Kaleb Petterson (ordf.),\nhandl. Enock Anderson, disp. Hugo\nPettersson.\n\nDisp.: Hugo Pettersson.\n\nKamrer: Gunnar Nygren.\n\nSkillingaryds Gjuteri AB.,\n\nSkillingaryd.\n\nTillverkar kokspisar och vattenvärmare\nvid gjuteri i Skillingaryd (Jönköp. l.).\n\nTelefon: 96. Postgiro: 137831. —\nAkt.-kap.: 40,500 kr. Antal industriarb.: 22.\n— Firman etabl. 1920, bolag 1938.\n\nVerkst. direktörer: fabr. Ernst\nFagerkvist o. fabr. Thor Petersson.\n\nSkillingaryds Träförädlingsverk,\n\n# Skillingaryd.\n\nTillverkar sågade och hyvlade trävaror\nvid sågverk med hyvleri i Skillingaryd\n(Jönköp. l.).\n\nTelefon: 148. Postgiro: 269409. —\nArb.-antal: 4. Tillv.-värde pr år: 250,000\nkr. — Firman etabl. 1911.\n\nÄgare o. chef: trävaruhandl. Leander\nJohansson.\n\nSkinnbeklädnadsbolaget, Malung.\n\nTillverkar skinntröjor, skinnrockar och\nvästar, promenadhandskar, sport- och\narbetshandskar, militär- och lottapälsar,\ndampälsar, capes och kragar m. m. samt\nbarnpälsar vid fabrik i Malung\n(Kopparb. l.).\n\nTelefon: 123. Postgiro: 27410.\nFilialkontor: Göteborg, Hvitfeldtspl. 1 C;\ntelefon: 114310. — Antal industriarb.: 30.\nTillv.-värde pr år: 500,000 kr. — Firman\netabl. 1927.\n\nÄgare o. chefer: fabr. André Eriksson\no. civiljägmäst. Bror Eriksson.\n\nAB. Skinnkonfektion, Borås.\n\nTillverkar skinnkläder, handskar och\npälsvaror.\n\nTelegr.-adr.: Skinnkonfektion, Borås.\nTelefon: 18910 o. 12650. Postgiro: 138585.\n\nAkt.-kap.: 60,000 kr. Antal\nindustriarb.: 70. Tillv.-\"värde pr år: 1,500,000 kr.\n— Firman etabl. 1937, bolag 1942.\n\nDisp.: Erik Ekdahl.\n",
    "structured": {
        "1": {
            "name": "Skelleftehamns Golvparkett AB.",
            "location": "Skelleftehamn",
            "business": "Tillverkar parkettstav av ek, björk och furu, trappledstänger samt byggnadssnickerier och butiksinredningar",
            "contact": {
                "phone": [
                    "31078"
                ],
                "postgiro": "61534"
            },
            "financials": {
                "capital": "151,800 kr",
                "annual_turnover": "400,000 kr"
            },
            "foundation_year": 1937,
            "director": "Herman Andersson"
        },
        "2": {
            "name": "AB. Skellefteå Spisbrödsfabrik",
            "location": "Skellefteå",
            "business": "Tillverkar spis-, knäöke- och delikatess-bröd",
            "contact": {
                "telegraph": "Spisbrödsfabriken, Skellefteå",
                "postgiro": "21466"
            },
            "financials": {
                "capital": "2,000,000 kr",
                "employees": {
                    "industriarb": 141
                },
                "annual_turnover": "4,000,000 kr"
            },
            "foundation_year": 1919,
            "owners": [
                "AB. Wasa Spisbrödsfabrik, Filipstad"
            ],
            "board": [
                {
                    "name": "konsul Karl Lundström",
                    "role": "ordf."
                },
                {
                    "name": "borgm. Thomas Lundquist"
                },
                {
                    "name": "fru G. Lundström"
                }
            ],
            "director": "Karl Lundström",
            "managing_director": "Karl Lundström"
        },
        "3": {
            "name": "Skellefteå Ångbryggeri AB.",
            "location": "Skellefteå",
            "business": "Tillverkar malt- och läskedrycker",
            "contact": {
                "telegraph": "Ångbryggeriet, Skellefteå",
                "postgiro": "61926"
            },
            "financials": {
                "capital": "150,000 kr",
                "employees": {
                    "industriarb": 28
                },
                "annual_turnover": "975,000 kr"
            },
            "foundation_year": 1893,
            "board": [
                {
                    "name": "disp. Otto Nyberg",
                    "role": "ordf."
                },
                {
                    "name": "disp. Carl Birger Carlsson"
                },
                {
                    "name": "adv. A. Rehn"
                }
            ],
            "director": "O. B. Carlsson",
            "sales_manager": "O. B. Carlsson"
        },
        "4": {
            "name": "Skeppshults Bruks AB.",
            "location": "Skeppshult",
            "business": "Tråddrageri och spikfabrik",
            "contact": {
                "telegraph": "Bruket, Skeppshult",
                "phone": "1",
                "postgiro": "75120"
            },
            "financials": {
                "capital": "250,000 kr",
                "employees": {
                    "Skeppshult": 40,
                    "Smålandsstenar": 4
                },
                "annual_turnover": "900,000 kr"
            },
            "foundation_year": 1916,
            "board": [
                {
                    "name": "disp. Kaleb Petterson",
                    "role": "ordf."
                },
                {
                    "name": "handl. Enock Anderson"
                },
                {
                    "name": "disp. Hugo Pettersson"
                }
            ],
            "director": "Hugo Pettersson"
        },
        "5": {
            "name": "Skillingaryds Gjuteri AB.",
            "location": "Skillingaryd",
            "business": "Tillverkar kokspisar och vattenvärmare",
            "contact": {
                "phone": "96",
                "postgiro": "137831"
            },
            "financials": {
                "capital": "40,500 kr",
                "employees": {
                    "industriarb": 22
                }
            },
            "corporation_year": 1938,
            "board": [
                {
                    "name": "fabr. Ernst Fagerkvist"
                },
                {
                    "name": "fabr. Thor Petersson"
                }
            ]
        },
        "6": {
            "name": "Skillingaryds Träförädlingsverk",
            "location": "Skillingaryd",
            "business": "Tillverkar sågade och hyvlade trävaror",
            "contact": {
                "phone": "148",
                "postgiro": "269409"
            },
            "financials": {
                "annual_turnover": "250,000 kr"
            },
            "board": [
                {
                    "name": "trävaruhandl. Leander Johansson"
                }
            ]
        },
        "7": {
            "name": "Skinnbeklädnadsbolaget",
            "location": "Malung",
            "business": "Tillverkar skinntröjor, skinnrockar och västar, promenadhandskar, sport- och arbetshandskar, militär- och lottapälsar, dampälsar, capes och kragar m. m. samt barnpälsar",
            "contact": {
                "phone": "123",
                "postgiro": "27410",
                "factory_phone": "114310"
            },
            "financials": {
                "capital": "Not available",
                "employees": {
                    "industriarb": 30
                },
                "annual_turnover": "500,000 kr"
            },
            "board": [
                {
                    "name": "fabr. André Eriksson"
                },
                {
                    "name": "civiljägmäst. Bror Eriksson"
                }
            ]
        },
        "8": {
            "name": "AB. Skinnkonfektion",
            "location": "Borås",
            "business": "Tillverkar skinnkläder, handskar och pälsvaror",
            "contact": {
                "telegraph": "Skinnkonfektion, Borås",
                "phone": [
                    "18910",
                    "12650"
                ],
                "postgiro": "138585"
            },
            "financials": {
                "capital": "60,000 kr",
                "employees": {
                    "industriarb": 70
                },
                "annual_turnover": "1,500,000 kr"
            },
            "corporation_year": 1942,
            "board": [
                {
                    "name": "Erik Ekdahl",
                    "role": "Disp."
                }
            ]
        }
    }
}