{
    "original": "Ekparkett—Ekström\n\nHuvudkontor: Stockholm, Dalag. 56 B.\nTelefon: 335631 o. 323807. Postgiro:\n53258. Brukskontoret: Ekolsund,\ntelefon: 9.\n\nAntal industriarb.: 50. Årstillv.: 2,5\nmilj. st. tegelvaror, 500 stds trävaror. —\nFirman etabl. 1913.\n\nÄgare o. chefer: ing. Oscar Johansson\no. ing. Axel Johansson.\n\n*AB. Ekparkett, Falkenberg.\n\nTillverkar ek-, bok- och furuparkett.\nSpecialitet: ekparkett.\n\nTelegr.-adr.: Parkettfabriken,\nFalkenberg. Telefon: 1213—14. Postgiro: 96191.\nHepr.: i Stockholm: AB. Olof Hermelin,\nKungsg. 39; telefon: 234655; Göteborg:\nBröderna Randen, Västerg. 4 a, telefon:\n117393; Malmö: Bröderna Randen,\nRön-neholmsv. 79, telefon: 23482.\n\nAkt.-kap.: 105,000 kr. Antal\nindustriarb.: 70. Tillv.-värde pr år: 2,000,000 kr.\n\n—\tFirman etabl. 1933 under namn\nBur-seryds Parkett AB., Smål. Burseryd,\n^överflyttad till Falkenberg under nuv.\nnamn 1943.\n\nStyrelse: disp. Martin Randen (ordf.),\ngrossh. Gustaf A. Johansson, disp. Oarl\nF. Randen.\n\nVerkst. dir. o. disp.: Martin Randen.\n\n* Eksjö Fabriks Bolag, Skillingaryd.\n\nFabrik i Skillingaryd (Jönköp. l.) för\ntillverkning av vadd, alla slag, samt\nsängkläder m. m.\n\nTelegr.-adr.: Bolaget, Skillingaryd.\nTelefon: 157. Postgiro: 34232. — Antal\nindustriarb.: 10. Tillv.-värde pr år:\n200,000 kr. — Firman etabl, 1926.\n\nÄgare o. chef: ing. Gust. E. Sönne.\n\nEksjö Industri AB., Eksjö.\n\nTrähus- och snickerifabrik. Tillverkar\ninonteringsfärdiga trähus samt\nbyggnads-snickerier. Varunamn: »Svea-hus».\n\nKontor: Eksjö. Telefon: 1074—75.\nPostgiro: 174290.\n\nAkt.-kap.: 165,000 kr. Antal\nindustriarb.: 75. Tillv.-värde pr år: 2,000,000 kr.\n\n—\tBolaget grundat 1941.\n\nDisp.: Gösta Ewerman.\n\n*AB. Eksjö Mek. Verkstad, Eksjö.\n\nGjuteri och mek. verkstad. Tillverkar\nvärmepannor, gjutgods, gjuteri- och\nsha-pingmaskiner samt nitade och svetsade\nplåtarbeten.\n\nTelegr.-adr.: Mekaniska, Eksjö.\nTelefon: 160 o. 991. Postgiro: 81822. Repr.:\ni Stockholm: Maskin AB. Karlebo,\nKungsg. 33, telefon: 231430; i Malmö:\nSkandinaviska Maskin AB., Stormg. 14,\ntelefon: 33020.\n\nAkt.-kap.: 240,000 kr. Antal\nindustriarb.: 100. Tillv.-värde pr år: 1,500,000 kr.\n\n—\tBolaget grundat 1905.\n\nStyrelse: ing. Alf Ståhlbrand (ordf.),\nadv. H. Månsson, dir. M. Rind.\n\nVerkst. dir.: A. Ståhlbrand.\n\nAB. Eksjö Möbelfabrik, Eksjö.\n\nTillverkar möbler.\n\nTelefon: 737. Postgiro: 91025. —\nAkt.-kap.: 67,200 kr. Antal industriarb.: 40.\nTillv.-värde pr år: 375,000 kr. —\nFabriken anlagd 1907, bolaget grundat 1931.\n\nDisp.: Axel L. Bäck.\n\n^Ekskogens Träförädlingsfabrik,\n\nStockholm.\n\nTillverkar monteringsfärdiga villor och\n\nsportstugor samt byggnadssnickerier\nm. m. vid fabrik i Ekskogen (Sthlms L).\nFirman bedriver jämväl\nbyggnadsverksamhet i samband med\nmaterialleveranser.\n\nKontor: Norrtullsg. 29. Telefon: 300898\no. 310482. Postgiro: 2618. — Antal\nindustriarb.: 15. Tillv.-värde pr år: 600,000\nkr. — Firman etabl. 1905.\n\nÄgare o. chefer: ing. Bertil Knutson\no. fru Wiva Gezelius.\n\nKontorschef: Jeanna Ericson.\n\n* Ekstrands Snickares Ekonomiska\nFörening, u. p. a., Stockholm.\n\nTillverkar div. snickerier, spec.\ngym-nastikmateriel.\n\nKontor: Midsommarkransen; postadr.:\nStockholm 32. Telefon: 452655.\nPostgiro: 5575.\n\nAndelskap.: 130,000 kr. Antal\nindustriarb.: 25. Tillv.-värde pr år: 400,000 kr.\n\n—\tSnickerifabrikationen, startad 1872 av\nfabr. E. G. Ekstrand, övertogs 1921 av\nnuv. förening.\n\nStyrelse: disp. Eric W. Ericsson (ordf.),\nsnickare Bror Bergman, snickare Gustav\nJohansson.\n\nDisp.: Eric W. Ericsson.\n\nKamrer: Eric Blomquist.\n\nEkström &amp; Blohm AB., Falköping.\n\nGuldvarufabrik. Tillverkar guld- och\nsilverbijouterier. Specialiteter: Ringar\n\noch manschettknappar.\n*",
    "structured": {
        "1": {
            "name": "Ekparkett—Ekström",
            "location": "Stockholm, Dalag. 56 B",
            "business": "Parkettfabrik",
            "contact": {
                "office": "Stockholm, Dalag. 56 B",
                "phone": [
                    "335631",
                    "323807"
                ],
                "postgiro": "53258",
                "head_office": "Ekolsund"
            },
            "financials": {
                "capital": "105,000 kr",
                "employees": {
                    "industriarb": 50
                },
                "annual_turnover": "2,000,000 kr",
                "annual_production_value": "2,000,000 kr"
            },
            "foundation_year": 1913,
            "owners": [
                "Oscar Johansson",
                "Axel Johansson"
            ]
        },
        "2": {
            "name": "AB. Ekparkett, Falkenberg",
            "location": "Falkenberg",
            "business": "Parkettfabrik",
            "products": "Tillverkar ek-, bok- och furuparkett. Specialitet: ekparkett.",
            "contact": {
                "office": "Falkenberg",
                "phone": [
                    "1213",
                    "14"
                ],
                "postgiro": "96191"
            },
            "financials": {
                "capital": "105,000 kr",
                "employees": {
                    "industriarb": 70
                },
                "annual_production_value": "2,000,000 kr"
            },
            "foundation_year": 1933,
            "original_name": "Burseryds Parkett AB",
            "corporation_year": 1943,
            "owners": [
                "AB. Olof Hermelin",
                "Bröderna Randen"
            ]
        },
        "3": {
            "name": "Eksjö Fabriks Bolag, Skillingaryd",
            "location": "Skillingaryd",
            "business": "Vadd- och sängklädestillverkning",
            "contact": {
                "office": "Skillingaryd",
                "phone": "157",
                "postgiro": "34232"
            },
            "financials": {
                "capital": "165,000 kr",
                "employees": {
                    "industriarb": 10
                },
                "annual_production_value": "200,000 kr"
            },
            "foundation_year": 1926,
            "owners": [
                "ing. Gust. E. Sönne"
            ]
        },
        "4": {
            "name": "Eksjö Industri AB., Eksjö",
            "location": "Eksjö",
            "business": "Trähus- och snickerifabrik",
            "products": "Tillverkar inonteringsfärdiga trähus samt byggnads-snickerier. Varunamn: »Svea-hus»",
            "contact": {
                "office": "Eksjö",
                "phone": [
                    "1074",
                    "75"
                ],
                "postgiro": "174290"
            },
            "financials": {
                "capital": "165,000 kr",
                "employees": {
                    "industriarb": 75
                },
                "annual_production_value": "2,000,000 kr"
            },
            "foundation_year": 1941,
            "owner": "Gösta Ewerman"
        },
        "5": {
            "name": "AB. Eksjö Mek. Verkstad, Eksjö",
            "location": "Eksjö",
            "business": "Gjuteri och mek. verkstad",
            "products": "Tillverkar värmepannor, gjutgods, gjuteri- och shapingmaskiner samt nitade och svetsade plåtarbeten",
            "contact": {
                "office": "Eksjö",
                "phone": [
                    "160",
                    "991"
                ],
                "postgiro": "81822"
            },
            "financials": {
                "capital": "240,000 kr",
                "employees": {
                    "industriarb": 100
                },
                "annual_production_value": "1,500,000 kr"
            },
            "foundation_year": 1905,
            "owners": [
                "ing. Alf Ståhlbrand",
                "adv. H. Månsson",
                "dir. M. Rind"
            ]
        },
        "6": {
            "name": "AB. Eksjö Möbelfabrik, Eksjö",
            "location": "Eksjö",
            "business": "Möbeltillverkning",
            "contact": {
                "office": "Eksjö",
                "phone": "737",
                "postgiro": "91025"
            },
            "financials": {
                "capital": "67,200 kr",
                "employees": {
                    "industriarb": 40
                },
                "annual_production_value": "375,000 kr"
            },
            "foundation_year": 1931,
            "owner": "Axel L. Bäck"
        },
        "7": {
            "name": "Ekskogens Träförädlingsfabrik, Stockholm",
            "location": "Ekskogen (Sthlms L)",
            "business": "Monteringsfärdiga villor och sportstugor tillverkning",
            "products": "Tillverkar monteringsfärdiga villor och sportstugor samt byggnadssnickerier m. m. vid fabrik i Ekskogen (Sthlms L). Firman bedriver jämväl byggnadsverksamhet i samband med materialleveranser",
            "contact": {
                "office": "Norrtullsg. 29",
                "phone": [
                    "300898",
                    "310482"
                ],
                "postgiro": "2618"
            },
            "financials": {
                "employees": {
                    "industriarb": 15
                },
                "annual_production_value": "600,000 kr"
            },
            "foundation_year": 1905,
            "owners": [
                "ing. Bertil Knutson",
                "fru Wiva Gezelius"
            ]
        },
        "8": {
            "name": "Ekstrands Snickares Ekonomiska Förening, u. p. a., Stockholm",
            "location": "Midsommarkransen",
            "business": "Snickeritillverkning",
            "products": "Tillverkar div. snickerier, spec. gym-nastikmateriel",
            "contact": {
                "office": "Midsommarkransen",
                "phone": "452655",
                "postgiro": "5575"
            },
            "financials": {
                "capital": "130,000 kr",
                "employees": {
                    "industriarb": 25
                },
                "annual_production_value": "400,000 kr"
            },
            "foundation_year": 1921,
            "owners": [
                "fabr. E. G. Ekstrand"
            ]
        },
        "9": {
            "name": "Ekström & Blohm AB., Falköping",
            "location": "Falköping",
            "business": "Guldvarufabrik",
            "products": "Tillverkar guld- och silverbijouterier. Specialiteter: Ringar och manschettknappar.",
            "financials": {
                "employees": {
                    "industriarb": 0
                }
            }
        }
    }
}