{
    "original": "Svenska\n\n\"Svenska Turbinfabriks AB.\nLjungström (STAL), Finspång.\n\nMek. verkstadsindustri i Finspång\n(Östergötl. l.). Tillverkar\nångturbingene-ratorer, turboelektriska och\nturbomekaniska fartygsmaskiner,\ncentrifugalpum-par, högtryckskompressorer och\nkylma-skiner, kylanordningar och\nkylanläggningar av olika slag samt\nspecialslipma-skiner och andra specialverktygsmaskiner.\n\nTelegr.-adr.: Stalturbin, Finspång.\nTelefon: »Stal». Postgiro: 28900.\n\nAkt.-kap.: 3,000,000 kr. Antal\nindustriarb.: 950. Tillv.-värde pr år: 12,400,000kr.\n\nBolaget grundat 1913. Allmänna Svem\nska Elektriska AB. är huvudintressent i\nbolaget.\n\nStyrelse: dir. J. S. Edström (ordf.),\ndir. Thorsten Ericson, dir. G. Leire, dir.\nE. D. Lindblom, prof. Edy Veländer.\n\nVerkst. dir.: E. D. Lindblom.\n\növering.: Oscar A. Wiberg.\n\nVerkstadschef: Birger Otterbeck.\n\nFörsäljn.-chef : John Hallin.\n\nKamrer: Clarence H. Johansson.\n\n\"Svenska Tändsticks AB., Jönköping.\n\nBolaget utgör holding company för\nJönköpings och Vuicans\nTändsticksfabriks AB., AB. Förenade Svenska\nTändsticksfabriker m. fl. företag.\n\nTelegr.-adr.: Matchco, Jönköping.\nTelefon: »Tändsticksbolaget». — Akt.-kap.:\n117,500,000 kr. — Bolaget grundat 1917.\n\nStyrelse: bankdir. Jacob Wallenberg\n(ordf.), dir. Assar Gabrielsson (v. ordf.),\ndir. Axel Brandin, bankdir. P. Brundell,\nmr Walter Carter, the hon. Hugh\nKin-dersley, adv. Torsten Setterberg,\ngeneral-dir. Rudolphe Speich, bankdir. Gustaf\nSöderlund, adv. Sune Wetter.\n\nVerkst. dir.: Axel Brandin.\n\nOmbudsman: Sune Wetter.\n\nSvenska Waddfabriken, Bröderna\nEngberg, Jönköping.\n\nTillverkar täck- och möbelvadd,\nlimvadd, mjuka avpassade mattor,\nvadd-madrasser, axelvaddar för\nkonfektions-indusiirien samt inläggssulor för skodon.\n\nTelefon: 1343 o. 5370. Postgiro: 140660.\n— Antal industriarb.: 15. Tillv.-värde pr\når: 220,000 kr. — Firman etabl. 1920.\n\nÄgare o. chefer: fabr. Eric Engberg o.\nfabr. Berndt Engberg.\n\n\"AB. Svenska Warner Kompaniet,\n\nStockholm.\n\nSyfabrik. Tillverkar korsetter och\nbysthållare. Varumärken: »Warner’s»,\n»War-nerette» o. »Sta-Up-Top» m. fl.\n\nKontor: Regeringsg. 32. Telegr.-adr.:\nWarnercorsets, Stockholm. Telefon:\n209093 o. 119093. Postgiro: 150175.\n\nAkt.-kap.: 50,000 kr. Antal\nindustriarb.: 65 samt 15 hemarbetare. Tillv.-värde\npr år: 2,000,000 kr. — Firman etabl. 1936.\n\nStyrelse: adv. Eric Wennerholm\n(ordf.), köpm. Nils-Eric Larsson, disp.\nErnst Leiser.\n\nDisp.: Ernst Leiser.\n\n\"Svenska AB. Vato, Halmstad.\n\nLivsmedelsfabrik. Tillverkar och\nkonserverar färdiglagade maträtter m. m.\nVarumärken: »Vato-snabbmat» o. »Vato\nbarnmat».\n\nTelegr.-adr.: Svevato, Halmstad.\nTelefon: 5120—21. Postgiro: 158589.\n\nAkt.-kap.: 500,000 kr. Antal\nindustriarb.: 65. Tillv.-värde pr år: 2,000,000 kr.\n\n—\tBolaget, grundat 1940, äger AB.\nHaust-rups Fabriker, Halmstad.\n\nStyrelse: bankdir. C. Bert Lilja\n(ordf.), ing. Sten Lilja, dir. Herbert\nTak-man.\n\nVerkst. dir.: civiling. Gösta Hallin.\n\n\"Svenska Vaxduks AB.,\n\nSmålands Anneberg.\n\nTillverkar vaxduk vid fabrik i\nSmålands Anneberg (Jönköp. l.).\n\nTelegr.-adr.: Vaxbolag, Smålands\nAnneberg. Telefon: 49. Postgiro: 131052.\nFörsäljningskontor: Stockholm, V.\nTräd-gårdsg. 15, telefon: 102838.\n\nAkt.-kap.: 550,000 kr. Antal\nindustriarb.: 135. Tillv.-värde pr år: 3,000,000 kr.\n\n—\tBolaget grundat 1936.\n\nStyrelse: dir. Torsten Jung (ordf.),\növering. P. W. Dietmann, dir. H. E.\nHelmerson, dir. Carl Sandkvist.\n\nVerkst. dir.: civiling. Thore Ericsson.\n\nDriftsing.: E. Richardson.\n\nKontorschef: Erik Kasslert.\n\nFörsäljn.-chef: Hugo Ringqvist\n(Stockholm).\n\nAB. Svenska Welipappfabriken,\n\nKinnahult.\n\nWellpappfabrik i Kinnahult (Älvsb. l.).\nTillverkar wellpapp i rullar samt\nwellpappkartonger. Varumärken:\n»Kinna-Kartong» o. »Kinna-well».\n\nTelegr.-adr.: Wellpapp, Kinna.\nTelefon: Kinna 10248 o. 10313. Postgiro:\n74990.\n\nAkt.-kap.: 150,000 kr. Tillv.-värde pr\når: 2,500,000 kr. — Bolaget grundat\n1929.\n\nVerkst. dir.: Severin Eliason.\n\nDisp.: Gustaf A. Eliason.",
    "structured": {
        "firms": {
            "1": {
                "name": "Svenska Turbinfabriks AB",
                "location": "Finspång",
                "business": "Mek. verkstadsindustri",
                "products": "ångturbingene-ratorer, turboelektriska och turbomekaniska fartygsmaskiner, centrifugalpum-par, högtryckskompressorer, kylma-skiner, kylanläggningar, specialslipma-skiner, specialverktygsmaskiner",
                "contact": {
                    "office": "Finspång",
                    "phone": [
                        "Stal"
                    ],
                    "postgiro": "28900",
                    "head_office": "Ljungström (STAL), Finspång",
                    "telegraph": "Stalturbin, Finspång",
                    "factory_office": "",
                    "factory_phone": ""
                },
                "financials": {
                    "capital": "3,000,000 kr",
                    "employees": {
                        "industriarb": 950
                    },
                    "annual_turnover": "12,400,000 kr",
                    "annual_production_value": "12,400,000kr"
                },
                "foundation_year": 1913,
                "board": [
                    {
                        "name": "J. S. Edström",
                        "role": "ordf."
                    },
                    {
                        "name": "Thorsten Ericson",
                        "role": "dir."
                    },
                    {
                        "name": "G. Leire",
                        "role": "dir."
                    },
                    {
                        "name": "E. D. Lindblom",
                        "role": "dir."
                    },
                    {
                        "name": "Edy Veländer",
                        "role": "prof."
                    }
                ],
                "owners": [
                    "Allmänna Svem ska Elektriska AB"
                ],
                "director": "E. D. Lindblom",
                "managing_director": "Oscar A. Wiberg",
                "sales_manager": "John Hallin",
                "manager": "Clarence H. Johansson"
            },
            "2": {
                "name": "AB. Svenska Warner Kompaniet",
                "location": "Stockholm",
                "business": "Syfabrik",
                "products": "korsetter, bysthållare",
                "contact": {
                    "office": "Stockholm",
                    "phone": [
                        "209093",
                        "119093"
                    ],
                    "postgiro": "150175",
                    "head_office": "",
                    "telegraph": "Warnercorsets, Stockholm",
                    "factory_office": "",
                    "factory_phone": ""
                },
                "financials": {
                    "capital": "50,000 kr",
                    "employees": {
                        "industriarb": 65,
                        "hemarbetare": 15
                    },
                    "annual_turnover": "2,000,000 kr",
                    "annual_production_value": "2,000,000 kr"
                },
                "foundation_year": 1936,
                "board": [
                    {
                        "name": "Eric Wennerholm",
                        "role": "ordf."
                    },
                    {
                        "name": "Nils-Eric Larsson",
                        "role": "köpm."
                    },
                    {
                        "name": "Ernst Leiser",
                        "role": "disp."
                    }
                ],
                "owners": [],
                "director": "",
                "managing_director": "",
                "sales_manager": "",
                "manager": ""
            },
            "3": {
                "name": "Svenska Drifting",
                "location": "Smålands Anneberg",
                "business": "Vaxdukfabrik",
                "products": "vaxduk",
                "contact": {
                    "office": "Smålands Anneberg",
                    "phone": [
                        "49"
                    ],
                    "postgiro": "131052",
                    "head_office": "",
                    "telegraph": "Vaxbolag, Smålands Anneberg",
                    "factory_office": "",
                    "factory_phone": ""
                },
                "financials": {
                    "capital": "550,000 kr",
                    "employees": {
                        "industriarb": 135
                    },
                    "annual_turnover": "3,000,000 kr",
                    "annual_production_value": "3,000,000 kr"
                },
                "foundation_year": 1936,
                "board": [
                    {
                        "name": "Torsten Jung",
                        "role": "ordf."
                    },
                    {
                        "name": "P. W. Dietmann",
                        "role": "övering."
                    },
                    {
                        "name": "H. E. Helmerson",
                        "role": "dir."
                    },
                    {
                        "name": "Carl Sandkvist",
                        "role": "dir."
                    }
                ],
                "owners": [],
                "director": "",
                "managing_director": "",
                "sales_manager": "",
                "manager": ""
            }
        }
    }
}