{
    "original": "Mix in—M jölby\n\nStyrelse: bankdir. Ivar Åkerman\n(ordf.), dir. Nils Flyekt, försäljn.-chef\nBengt Johanson, dir. Arne Mörck.\n\nVerkst. dir.: Arne Mörck.\n\nAB. Mixin, Göteborg.\n\nKemisk teknisk fabrik. Tillverkar\nef-terrättspulver, pudding-, sås- och\nkrämpulver samt konserveringsmedel.\nVarumärke: »Mixin».\n\nKontor: S. Hamng. 25. Telefon:\n134971. Postgiro: 46934.\n\nAkt.-kap.: 5,000 kr. Antal industriarb.:\n20. — Firman etabl. 1941.\n\nVerkst. dir.: Carl A. Schröder.\n\nMJ-hattar AB., Stockholm.\n\nTillverkar barn- och damhattar samt\nmössor.\n\nKontor: Högbergsg. 59. Telefon:\n409931. Postgiro: 156479.\n\nAkt.-kap.: 25,000 kr. Antal\nindustriarb.: 20. — Firman etabl. 1934, bolag\n1942.\n\nVerkst. dir.: Fredric Hellberg.\n\n*AB Mjöbäcks Träindustri,\n\nMjöbäck.\n\nTillverkar monteringsfärdiga\nbostadshus och sportstugor, byggnadssnickerier,\nköks- och butiksinredningar vid sågverk\noch snickerifabrik i Mjöback (Älvsb. l.).\n\nTelefon: 36. Postgiro: 84699. —\nAkt.-kap.: 50,300 kr. Antal industriarb.- 28.\nTillv.-värde pr år: 400,000 kr. — Firman\netabl. 1933, bolag 1943.\n\nStyrelse: dir. Pontus Nilsson (ordf.),\ndisp. Arthur Nilsson.\n\nVerkst. dir.: Pontus Nilsson.\n\nDisp.: Arthur Nilsson.\n\nDriftsing.: Daniel Andersson.\n\n*Mjöiby Bryggeri, Mjölby.\n\nSe AB. Nya Centralbryggeriet,\nLinköping.\n\n*Mjölby Cjuteri &amp; Mek. Verkstads\nAB. (Primoverken), Mjölby.\n\nJärn- och metallgjuteri, maskin-,\nsmi-des-, reparations- och modellverkstad.\nTillverkar byggnads- och maskingjutgods,\nverktygsmaskiner, plansvarvar,\ntransmissioner, kilrepskivor, fasta och\nfrik-tionsremskivor, fasta och\nfriktionskopplingar, stå- och hänglager m. m. samt\nmaskiner för kvarnindustrien; utför\nslip-ning och räffling av kvarnvalsar.\n\nTelegr.-adr.: Primoverken, Mjölby.\nTelefon: 83 o. 583. Postgiro: 8673.\n\nAkt.-kap.: 200,000 kr. Antal\nindustriarb.: 25. Tillv.-värde pr år: 300,000 kr.\n\n—\tFirman etabl. 1896, bolag 1918.\nStyrelse: kamrer Einar Håkanson\n\n(ordf.), ing. Erik Bergvall, verkstadschef\nGunnar Mattisson.\n\nVerkst. dir.: Erik Bergvall.\nVerkstadschef: Gunnar Mattisson.\nKontorschef: Einar Håkanson.\n\n*Mjölby Golvindustri, Mjölby.\n\nParkettfabrik i Mjölby (Östergötl. l.).\nTillverkar ekparkett.\n\nTelegr.-adr.: Golvindustri, Mjölby.\nTelefon: 788 o. 789. Postgiro: 280371.\nRepresentanter: AB. Svenska\nGolvunderhållet, Stockholm, Göteborg o. Malmö;\nAB. Olof Henrikssons Byggnadsvaror,\nJönköping o. Tenhult.\n\nAntal industriarb.: 27. Tillv.-värde pr\når: 1,300,000 kr. — Firman etabl. 1944.\nÄgare o. chef: fabr. Arthur Johansson.\nKamrer: Henning Thernberg.\n\nAB. Mjölby intarsia, Mjölby.\n\nFinsnickeriverkstäder och\narkitektkontor för tillverkning av\nintarsiadekoratio-ner.\n\nTelegr.-adr. o. telefon: »Mjölbyintarsia».\nPostgiro: 34122. — Akt.-kap.: 42,000 kr.\nAntal industriarb.: 60. Tillv.-värde pr år:\n650,000 kr. — Firman etabl. 1909, bolag\n1937.\n\nVerkst. dir.: Gösta Dahlström.\n*AB. Mjölby Karamellfabrik, Mjölby.\n\nTillverkar karameller, konfekt, kola och\ntabletter. Varumärke för kola: »MK».\n\nTelefon: 245. Postgiro: 11740. —\nAkt.-kap.: 80,000 kr. Antal industriarb.: 35.\nTillv.-värde pr år: 750,000 kr. — Firman\netabl. 1921, bolag 1944.\n\nStyrelse o. disp.: C. K. Printzell.\n\nAB. Mjölby Mössfabrik, Mjölby.\n\nTillverkar herr-, dam- och barnmössor.\nSpecialitet: Uniformsmössor. Varumärke:\n»Capsy». Bolaget driver även handel med\nherrhattar av utländsk tillverkning.\n\nHuvudkontor: Mjölby. Telefon: 654.\nPostgiro: 76738. Avd.-kontor: Stockholm,\nöstgötag. 93, telefon: 405211; Göteborg,\növra Husarg. 9, telefon: 175587.\n\nAkt.-kap.: 60,300 kr. Antal\nindustriarb.: 50. Tillv.-värde pr år: 400,000 kr.\n\n—\tBolaget grundat 1934.\nDisp.: Torsten R. Norman.",
    "structured": {
        "1": {
            "name": "AB. Mixin",
            "location": "Göteborg",
            "business": "Kemisk teknisk fabrik",
            "products": "Tillverkar ef-terrättspulver, pudding-, sås- och krämpulver samt konserveringsmedel. Varumärke: »Mixin».",
            "contact": {
                "office": "S. Hamng. 25",
                "phone": [
                    "134971"
                ],
                "postgiro": "46934"
            },
            "financials": {
                "capital": "5,000 kr",
                "employees": {
                    "industriarb": 20
                },
                "annual_turnover": "Information saknas",
                "annual_production_value": "Information saknas"
            },
            "foundation_year": 1941
        },
        "2": {
            "name": "MJ-hattar AB.",
            "location": "Stockholm",
            "business": "Tillverkar barn- och damhattar samt mössor",
            "contact": {
                "office": "Högbergsg. 59",
                "phone": [
                    "409931"
                ],
                "postgiro": "156479"
            },
            "financials": {
                "capital": "25,000 kr",
                "employees": {
                    "industriarb": 20
                },
                "annual_turnover": "Information saknas",
                "annual_production_value": "Information saknas"
            },
            "foundation_year": 1934,
            "corporation_year": 1942
        },
        "3": {
            "name": "AB Mjöbäcks Träindustri",
            "location": "Mjöbäck",
            "business": "Tillverkar monteringsfärdiga bostadshus och sportstugor, byggnadssnickerier, köks- och butiksinredningar",
            "contact": {
                "phone": "36",
                "postgiro": "84699"
            },
            "financials": {
                "capital": "50,300 kr",
                "employees": {
                    "industriarb": 28
                },
                "annual_turnover": "Information saknas",
                "annual_production_value": "400,000 kr"
            },
            "foundation_year": 1933,
            "corporation_year": 1943
        },
        "4": {
            "name": "Mjölby Bryggeri",
            "location": "Mjölby",
            "predecessor": "AB. Nya Centralbryggeriet, Linköping"
        },
        "5": {
            "name": "Mjölby Cjuteri & Mek. Verkstads AB.",
            "location": "Mjölby",
            "business": "Järn- och metallgjuteri, maskin-, smi-des-, reparations- och modellverkstad",
            "products": "Tillverkar byggnads- och maskingjutgods, verktygsmaskiner, plansvarvar, transmissioner, kilrepskivor, fasta och friktionsremskivor, fasta och friktionskopplingar, stå- och hänglager m. m. samt maskiner för kvarnindustrien; utför slipning och räffling av kvarnvalsar.",
            "contact": {
                "telegraph": "Primoverken, Mjölby",
                "phone": [
                    "83",
                    "583"
                ],
                "postgiro": "8673"
            },
            "financials": {
                "capital": "200,000 kr",
                "employees": {
                    "industriarb": 25
                },
                "annual_turnover": "Information saknas",
                "annual_production_value": "300,000 kr"
            },
            "foundation_year": 1896,
            "corporation_year": 1918
        },
        "6": {
            "name": "Mjölby Golvindustri",
            "location": "Mjölby",
            "business": "Parkettfabrik",
            "products": "Tillverkar ekparkett",
            "contact": {
                "telegraph": "Golvindustri, Mjölby",
                "phone": [
                    "788",
                    "789"
                ],
                "postgiro": "280371"
            },
            "financials": {
                "employees": {
                    "industriarb": 27
                },
                "annual_turnover": "Information saknas",
                "annual_production_value": "1,300,000 kr"
            },
            "foundation_year": 1944
        },
        "7": {
            "name": "AB. Mjölby intarsia",
            "location": "Mjölby",
            "business": "Finsnickeriverkstäder och arkitektkontor",
            "products": "Tillverkning av intarsiadekorationer",
            "contact": {
                "telegraph": "Mjölbyintarsia",
                "postgiro": "34122"
            },
            "financials": {
                "capital": "42,000 kr",
                "employees": {
                    "industriarb": 60
                },
                "annual_turnover": "Information saknas",
                "annual_production_value": "650,000 kr"
            },
            "foundation_year": 1909,
            "corporation_year": 1937
        },
        "8": {
            "name": "AB. Mjölby Karamellfabrik",
            "location": "Mjölby",
            "business": "Tillverkar karameller, konfekt, kola och tabletter",
            "products": "Varumärke för kola: »MK».",
            "contact": {
                "phone": "245",
                "postgiro": "11740"
            },
            "financials": {
                "capital": "80,000 kr",
                "employees": {
                    "industriarb": 35
                },
                "annual_turnover": "Information saknas",
                "annual_production_value": "750,000 kr"
            },
            "foundation_year": 1921,
            "corporation_year": 1944
        },
        "9": {
            "name": "AB. Mjölby Mössfabrik",
            "location": "Mjölby",
            "business": "Tillverkar herr-, dam- och barnmössor",
            "products": "Specialitet: Uniformsmössor. Bolaget driver även handel med herrhattar av utländsk tillverkning.",
            "contact": {
                "phone": "654",
                "postgiro": "76738"
            },
            "financials": {
                "capital": "60,300 kr",
                "employees": {
                    "industriarb": 50
                },
                "annual_turnover": "Information saknas",
                "annual_production_value": "400,000 kr"
            },
            "foundation_year": 1934
        }
    }
}