{
    "original": "Mölntorp—Neglingevarvet\n\n\"Mölntorps Verkstäder AB., Kolbäck.\n\nPlåtpressningsverkstad och\nsmides-fabrik i Mölntorp, Kolbäck (Västmanl.\n1.). Tillverkar pressade och svetsade\narbeten av rostfri plåt såsom kokkärl,\nsjukhuskärl, disklådor, diskbänkar,\nslasktrattar m. m., förtenta plåtkärl såsom\nskopor, silar, mjölkflaskor, oljekannor,\nspiralborrar för trä (navare), besman,\nstrykjärn m. m.; utför räck- och\nhejar-smiden, plåtpressningsarbeten samt\nförtenning.\n\nKontor: Kolbäck. Telefon: »Mölntorps\nverkstäder». Postgiro: 36398.\nHuvudkontor: AB. Plåtmanufaktur, Stockholm,\nBiblioteksg. 26, telefon: 235700 (se detta\nbolag).\n\nAntal industriarb.: 100. Tillv.-värde\npr år: 2,000,000 kr.\n\nFabriken anlagd 1870, bolag 1927.\nBolaget är anslutet till AB. Plåtmanufaktur,\nStockholm (se detta bolag).\n\nDisp.: Gustaf Lundberg.\n\nDriftschéf: bergsing. Lars Lundberg.\n\n\"Mönsterås Bryggeri AB.,\n\nMönsterås.\n\nSe Kalmar Bryggeri AB., Kalmar.\n\n\"Mönsterås Tändsticksfabrik,\n\nMönsterås.\n\nSe Jönköping och Vulcans\nTändsticksfabriks AB., Jönköping.\n\nMörbyiånga Konservfabriks AB.,\n\nStockholm.\n\nKonservfabrik i Mörbyiånga (Kalm. l.)\nför inläggning av rödbetor, gurkor m. m.\n\nKontor o. ensamförsälj.: AB. Th.\nWin-borg &amp; Co., Saltsjö-Järla; postadr.:\nStockholm 11. Telefon: »Winborgsfabriker».\n\nAkt.-kap.: 100,000 kr. Antal\nindustriarb.: 43. Tillv.-värde pr år: 500,000 kr.\n— Bolaget grundat år 1932 under namn\nAB. Flytande Frukt, nuv. namn 1944,\näges av AB. Th. Winborg &amp; Co.\n\nStyrelse o. verkst. dir.: Boris Meyerson.\nPlatschef: Bror Carlqvist.\n\nN\n\n* utmärker till Sveriges Industriförbund anslutna företag.\n\n\"AB. Nabbensbergs Tegelbruk,\n\nVänersborg.\n\nTillverkar mur- och taktegel samt\ndräneringsrör.\n\nTelegr.-adr.: Nabbensberg, Vänersborg.\nTelefon: 5. Postgiro: 77142. —\nAkt.-kap.: 300,000 kr. Antal industriarb.: 75.\nÅrstillv.: 8 milj. st. tegelvaror. —\nBolaget grundat 1906.\n\nVerkst. dir.: Einar Ström.\n\nVice verkst. dir.: kapten Hilding\nStröm.\n\nDisp.: Joel Svensson.\n\nAB. Nautic, Göteborg.\n\nTunnplåts- och kopparslageri samt\nin-strumentmakareverkstad. Tillverkar\nlanternor, nautiska instrument samt\nbelysningsarmatur.\n\nKontor: Skeppsbron 2. Telegr.-adr.:\nSverre, Göteborg. Telefon: 112421 o.\n136960. Postgiro: 40703.\n\nAkt.-kap.: 50,000 kr. Antal\nindustriarb.: 30. Tillv.-värde pr år: 250,000 kr.\n— Bolaget grundat 1915.\n\nVerkst. dir.: kapten Olof Traung.\n\nDriftsing.: Jan-Olof Traung.\n\n\"Naxos, Västervik.\n\nSe AB. Slipmaterial-Naxos, Västervik.\n\n\"Necks Verkstäder, Nossebro.\n\nJärnmanufakturverk och\ngalvanise-ringsfabrik i Nossebro (Skarab. l.).\nTillverkar smiden för elektr. ledningar, klena\noch medelgrova smiden, sop- och\nlatrinkärl, fotskrapor m. m.; utför\nvarmgalva-nisering.\n\nHuvudkontor: Nossebro. Telegr.-adr.:\nNeck, Nossebro, Telefon: »Necks\nverkstäder». Postgiro: 33235. Avd.-kontor:\nGöteborg, Marieholmsg. 7, telefon: 159218.\n\nAntal industriarb.: 190. Tillv.-värde pr\når: 3,500,000 kr. — Firman etabl. 1919.\n\nÄgare: fru S. Neck.\n\nProhurist: fabr. Carl Gustav Neck.\n\n\"AB. Neglingevarvet,\n\nSaltsjöbaden.\n\nBåtbyggeri och varv i Saltsjöbaden\n(Sthlms l.). Bygger segel- och\nmotor-yachter samt utför ombyggnader och\nreparationer av dylika.\n\n389*",
    "structured": {
        "firms": [
            {
                "name": "Mölntorps Verkstäder AB",
                "location": "Kolbäck",
                "business": "Plåtpressningsverkstad och smides-fabrik",
                "contact": {
                    "office": "Kolbäck",
                    "phone": [
                        "Mölntorps verkstäder"
                    ],
                    "postgiro": "36398",
                    "head_office": "AB. Plåtmanufaktur, Stockholm, Biblioteksg. 26, telefon: 235700"
                },
                "financials": {
                    "capital": "not specified",
                    "employees": {
                        "industriarb": 100
                    },
                    "annual_turnover": "2,000,000 kr",
                    "annual_production_value": "not specified"
                },
                "foundation_year": 1870,
                "corporation_year": 1927,
                "board": [
                    {
                        "name": "Gustaf Lundberg",
                        "role": "not specified"
                    }
                ]
            },
            {
                "name": "Mönsterås Bryggeri AB",
                "location": "Mönsterås",
                "business": "Bryggeri",
                "financials": {
                    "capital": "not specified",
                    "employees": {
                        "industriarb": "not specified"
                    },
                    "annual_turnover": "not specified",
                    "annual_production_value": "not specified"
                },
                "board": [
                    {
                        "name": "not specified",
                        "role": "not specified"
                    }
                ]
            },
            {
                "name": "Mönsterås Tändsticksfabrik",
                "location": "Mönsterås",
                "business": "Tändsticksfabrik",
                "financials": {
                    "capital": "not specified",
                    "employees": {
                        "industriarb": "not specified"
                    },
                    "annual_turnover": "not specified",
                    "annual_production_value": "not specified"
                },
                "board": [
                    {
                        "name": "not specified",
                        "role": "not specified"
                    }
                ]
            },
            {
                "name": "Mörbyiånga Konservfabriks AB",
                "location": "Stockholm",
                "business": "Konservfabrik",
                "contact": {
                    "office": "AB. Th. Win-borg & Co., Saltsjö-Järla",
                    "phone": [
                        "Winborgsfabriker"
                    ],
                    "postgiro": "not specified"
                },
                "financials": {
                    "capital": "100,000 kr",
                    "employees": {
                        "industriarb": 43
                    },
                    "annual_turnover": "500,000 kr",
                    "annual_production_value": "not specified"
                },
                "foundation_year": 1932,
                "board": [
                    {
                        "name": "Boris Meyerson",
                        "role": "Styrelse o. verkst. dir."
                    }
                ]
            },
            {
                "name": "AB. Nabbensbergs Tegelbruk",
                "location": "Vänersborg",
                "business": "Mur- och taktegel samt dräneringsrör",
                "contact": {
                    "office": "Nabbensberg, Vänersborg",
                    "phone": [
                        "not specified"
                    ],
                    "postgiro": "77142"
                },
                "financials": {
                    "capital": "300,000 kr",
                    "employees": {
                        "industriarb": 75
                    },
                    "annual_turnover": "not specified",
                    "annual_production_value": "8 milj. st. tegelvaror"
                },
                "corporation_year": 1906,
                "board": [
                    {
                        "name": "not specified",
                        "role": "not specified"
                    }
                ]
            },
            {
                "name": "AB. Nautic",
                "location": "Göteborg",
                "business": "Tunnplåts- och kopparslageri samt instrumentmakareverkstad",
                "contact": {
                    "office": "Skeppsbron 2",
                    "telegraph": "Sverre, Göteborg",
                    "phone": [
                        "112421",
                        "136960"
                    ],
                    "postgiro": "40703"
                },
                "financials": {
                    "capital": "50,000 kr",
                    "employees": {
                        "industriarb": 30
                    },
                    "annual_turnover": "250,000 kr",
                    "annual_production_value": "not specified"
                },
                "corporation_year": 1915,
                "board": [
                    {
                        "name": "not specified",
                        "role": "not specified"
                    }
                ]
            },
            {
                "name": "Necks Verkstäder",
                "location": "Nossebro",
                "business": "Järnmanufakturverk och galvaniseringsfabrik",
                "contact": {
                    "office": "Nossebro",
                    "phone": [
                        "Necks verkstäder"
                    ],
                    "postgiro": "33235",
                    "head_office": "Göteborg, Marieholmsg. 7, telefon: 159218"
                },
                "financials": {
                    "capital": "not specified",
                    "employees": {
                        "industriarb": 190
                    },
                    "annual_turnover": "3,500,000 kr",
                    "annual_production_value": "not specified"
                },
                "foundation_year": 1919,
                "board": [
                    {
                        "name": "fru S. Neck",
                        "role": "Prohurist"
                    }
                ]
            },
            {
                "name": "AB. Neglingevarvet",
                "location": "Saltsjöbaden",
                "business": "Båtbyggeri och varv",
                "financials": {
                    "capital": "not specified",
                    "employees": {
                        "industriarb": "not specified"
                    },
                    "annual_turnover": "not specified",
                    "annual_production_value": "not specified"
                },
                "corporation_year": "not specified",
                "board": [
                    {
                        "name": "not specified",
                        "role": "not specified"
                    }
                ]
            }
        ]
    }
}