{
    "original": "Carlsson\n\n*Carlssons Möbelfabrik, AB.Bröderna,\n\nVirserum.\n\nSe AB. Bröderna Carlssons\nMöbelfabrik, Virserum.\n\nCarlson &amp; Palm, Ulricehamn.\n\nTrikåfabrik i Ulricehamn (Älvsb. l.).\nTillverkar herrvästar, slipovers,\npullo-vers, jumpers och koftor samt baddräkter.\n\nTelefon: 680. Postgiro: 136909. —\nAntal industriarb.: 8 .— Firman etabl. 1936.\nÄgare o. chefer: fabr. Kuben Carlson\n\n0.\tciviling. Erik Palm.\n\n*AB. Carlsson &amp; Westerberg\nVerktygsfabrik, Eskilstuna.\n\nTillverkar gäng- och pressverktyg,\ngig-gar, fixturer m. m. samt utför\nprecisionsarbeten. Varumärke: CW.\n\nTelefon: 31870 o. 30772. Postgiro:\n10783. — Akt.-kap.: \" 250,000 kr. Antal\nindustriarb.: 50. Tillv.-värde pr år:\n500,000 kr. — Firman etabl. 1917, bolag\n1943.\n\nStyrelse: fabr. Erik Carlsson (ordf.),\nfru Anna Lisa Carlsson, fru Hildur\nCarlsson.\n\nVerkst. dir.: Erik Carlsson.\nKontorschef: fröken Birgit Adolfsson.\n\n*AB. A. F. Carlssons Skofabrik,\n\nVänersborg.\n\nSko- och läderfabrik i Vänersborg.\nTillverkar skodon samt bottenläder.\nVarumärken: »Crispin», »Merkur», »Bore»,\n»Webe» o. »Svala».\n\nTelegr.-adr.: Skofabrik, Vänersborg.\nTelefon: »Skofabriken». Postgiro: 33000.\n\nRepresentanter: i Stockholm: Carl\nKarlsson, Kungsg. 32, telefon: 207474; i\nGöteborg: Carl Corneliusson, Drottningg.\n30, telefon: 131450; i Malmö: John\nJohnsson, S:t Gertrudsg. 4, telefon: 28525; i\nNorrköping: Gunnar Andersson, Broddg.\n\n1,\ttelefon: 23974; i Sundsvall: AB.\nVänersborgs Skodon, telefon: 3971; i\nArvika: Eric Svenson, telefon: 60.\n\nAkt.-kap.: 2,400,000 kr. Antal\nindustriarb.: 408. Till v.-värden pr år: för\nskofabriken: 6,225,000 kr.; för garveriet:\n1,542,000 kr. — Fabriken anlagd 1860,\nbolag 1898.\n\nStyrelse: f. d. president K. H. M.\nHög-stedt (ordf.), disp. Carl Anders Carlsson,\nfabr. Carl-Gustaf Carlsson, disp. Elof\nCarlsson, f. d. kammarrättsrådet Per G.\nWidén.\n\nVerkst. dir.: Carl Anders Carlsson.\n\nAB. Arne Carlsson, Gällstad.\n\nTillverkar yllevaror såsom jumpers och\ntröjor samt strumpor och vantar vid\ntrikåfabrik i Gällstad (Älvsb. l.).\nSpecialiteter: barn- och fotbollsstrumpor.\n\nKontor: Gällstad. Telefon: Påbo 14.\nPostgiro: 179336.\n\nAkt.-kap.: 35,000 kr. Antal\nindustriarb.: 35. Tillv.-värde pr år: 500,000 kr.\n— Firman etabl. 1937, bolag 1943.\n\nStyrelse o. verkst. dir.: fabr. Arne\nCarlsson.\n\n* Birger Carlsons Fabriks AB.,\n\nStockholm.\n\nTillverkar gasmasker,\narbetareskydds-materiel m. m. Varumärke: »Bicapa».\n\nKontor: Stockholm, Kaptensg. 6.\nTelegr.-adr.: Bicapa, Stockholm. Telefon:\n679130. Postgiro: 155119. Ensamförsälj.:\nBirger Carlson &amp; Co. AB., Stockholm,\nKaptensg. 6.\n\nAkt.-kap.: 500,000 kr. — Bolaget\ngrundat 1937.\nStyrelse: fru Elsa J. Carlson.\nDisp.: civiling. Karl Teodor Andersson.\n\n*C. A. Carlson &amp; C:o i Arboga AB.,\n\nArboga.\n\nMek. verkstad och gjuteri. Tillverkar\nlantbruksmaskiner och -redskap såsom\nharvar, vältar, kultivatorer, släpräfsor,\nhackelsemaski ner, gödselvattenpumpar,\nsades- och foderkakskrossar m. m. samt\ntackjärnsgjutgods.\n\nTelegr.-adr.: Carlsons, Arboga.\nTelefon: 10 o. 210. Postgiro: 72300. —\nAkt.-kap.: 200,000 kr. Antal industriarb.: 25.\nTillv.-värde pr år: 600,000 kr. — Firman\netabl. 1865, bolag 1933.\n\nStyrelse: kamrer G. Rohlander, dir.\nRichard Stridsberg.\n\nVerkst. dir.: Richard Stridsberg.\nKamrer: G. Rohlander.\n\n*C. E. Carlsson, Skofabrik, Örebro.\n\nTillverkar damskodon. Varumärke:\n»CEC».\n\nTelefon: 11406. Postgiro: 75863. —\nAntal industriarb.: 25. Tillv.-värde pr år:\n400,000 kr. — Firman etabl. 1900.\n\nÄgare o. chefer: fabr. Martin Carlsson\no. fabr. Herbert Carlsson.\n\nAB. C. C. Carlsson, Norrköping.\n\nSyfabrik. Tillverkar skjortor,\nsport-och skyddskläder. Varumärke: »Cegece».",
    "structured": {
        "1": {
            "name": "Carlssons Möbelfabrik, AB",
            "location": "Virserum",
            "business": "Möbelfabrik",
            "contact": {
                "office": "Bröderna, Virserum",
                "phone": [
                    "680"
                ],
                "postgiro": "136909"
            },
            "financials": {
                "capital": "N/A",
                "employees": {
                    "industriarb": 8
                },
                "annual_turnover": "N/A",
                "annual_production_value": "N/A"
            },
            "foundation_year": 1936,
            "board": [
                {
                    "name": "fabr. Kuben Carlson",
                    "role": "N/A"
                },
                {
                    "name": "civiling. Erik Palm",
                    "role": "N/A"
                }
            ],
            "owners": [
                "N/A"
            ],
            "director": "N/A",
            "managing_director": "N/A",
            "sales_manager": "N/A",
            "manager": "N/A"
        },
        "2": {
            "name": "AB. Carlsson & Westerberg Verktygsfabrik",
            "location": "Eskilstuna",
            "business": "Verktygsfabrik",
            "contact": {
                "office": "N/A",
                "phone": [
                    "31870",
                    "30772"
                ],
                "postgiro": "10783"
            },
            "financials": {
                "capital": "250,000 kr",
                "employees": {
                    "industriarb": 50
                },
                "annual_turnover": "N/A",
                "annual_production_value": "500,000 kr"
            },
            "foundation_year": 1917,
            "corporation_year": 1943,
            "board": [
                {
                    "name": "fabr. Erik Carlsson",
                    "role": "ordf."
                },
                {
                    "name": "fru Anna Lisa Carlsson",
                    "role": "N/A"
                },
                {
                    "name": "fru Hildur Carlsson",
                    "role": "N/A"
                }
            ],
            "owners": [
                "N/A"
            ],
            "director": "Erik Carlsson",
            "managing_director": "N/A",
            "sales_manager": "N/A",
            "manager": "fröken Birgit Adolfsson"
        },
        "3": {
            "name": "AB. A. F. Carlssons Skofabrik",
            "location": "Vänersborg",
            "business": "Sko- och läderfabrik",
            "contact": {
                "office": "N/A",
                "phone": [
                    "N/A"
                ],
                "postgiro": "33000"
            },
            "financials": {
                "capital": "2,400,000 kr",
                "employees": {
                    "industriarb": 408
                },
                "annual_turnover": "N/A",
                "annual_production_value": "för skofabriken: 6,225,000 kr.; för garveriet: 1,542,000 kr."
            },
            "foundation_year": 1860,
            "corporation_year": 1898,
            "board": [
                {
                    "name": "f. d. president K. H. M. Högstedt",
                    "role": "ordf."
                },
                {
                    "name": "disp. Carl Anders Carlsson",
                    "role": "N/A"
                },
                {
                    "name": "fabr. Carl-Gustaf Carlsson",
                    "role": "N/A"
                },
                {
                    "name": "disp. Elof Carlsson",
                    "role": "N/A"
                },
                {
                    "name": "f. d. kammarrättsrådet Per G. Widén",
                    "role": "N/A"
                }
            ],
            "owners": [
                "N/A"
            ],
            "director": "Carl Anders Carlsson",
            "managing_director": "N/A",
            "sales_manager": "N/A",
            "manager": "N/A"
        },
        "4": {
            "name": "AB. Arne Carlsson",
            "location": "Gällstad",
            "business": "Trikåfabrik",
            "contact": {
                "office": "Gällstad",
                "phone": [
                    "Påbo 14"
                ],
                "postgiro": "179336"
            },
            "financials": {
                "capital": "35,000 kr",
                "employees": {
                    "industriarb": 35
                },
                "annual_turnover": "N/A",
                "annual_production_value": "500,000 kr"
            },
            "foundation_year": 1937,
            "corporation_year": 1943,
            "board": [
                {
                    "name": "fabr. Arne Carlsson",
                    "role": "N/A"
                }
            ],
            "owners": [
                "N/A"
            ],
            "director": "N/A",
            "managing_director": "N/A",
            "sales_manager": "N/A",
            "manager": "N/A"
        },
        "5": {
            "name": "Birger Carlsons Fabriks AB.",
            "location": "Stockholm",
            "business": "Tillverkar gasmasker, arbetarskyddsmateriel m. m.",
            "contact": {
                "office": "Kaptensg. 6",
                "phone": [
                    "679130"
                ],
                "postgiro": "155119"
            },
            "financials": {
                "capital": "500,000 kr",
                "employees": {
                    "industriarb": "N/A"
                },
                "annual_turnover": "N/A",
                "annual_production_value": "N/A"
            },
            "foundation_year": 1937,
            "board": [
                {
                    "name": "fru Elsa J. Carlson",
                    "role": "N/A"
                },
                {
                    "name": "civiling. Karl Teodor Andersson",
                    "role": "disp."
                }
            ],
            "owners": [
                "N/A"
            ],
            "director": "N/A",
            "managing_director": "N/A",
            "sales_manager": "N/A",
            "manager": "N/A"
        },
        "6": {
            "name": "C. A. Carlson & C:o i Arboga AB.",
            "location": "Arboga",
            "business": "Mek. verkstad och gjuteri",
            "contact": {
                "office": "N/A",
                "phone": [
                    "10",
                    "210"
                ],
                "postgiro": "72300"
            },
            "financials": {
                "capital": "200,000 kr",
                "employees": {
                    "industriarb": 25
                },
                "annual_turnover": "N/A",
                "annual_production_value": "600,000 kr"
            },
            "foundation_year": 1865,
            "corporation_year": 1933,
            "board": [
                {
                    "name": "kamrer G. Rohlander",
                    "role": "N/A"
                },
                {
                    "name": "dir. Richard Stridsberg",
                    "role": "N/A"
                }
            ],
            "owners": [
                "N/A"
            ],
            "director": "N/A",
            "managing_director": "Richard Stridsberg",
            "sales_manager": "N/A",
            "manager": "G. Rohlander"
        },
        "7": {
            "name": "C. E. Carlsson, Skofabrik",
            "location": "Örebro",
            "business": "Tillverkar damskodon",
            "contact": {
                "office": "N/A",
                "phone": [
                    "11406"
                ],
                "postgiro": "75863"
            },
            "financials": {
                "capital": "N/A",
                "employees": {
                    "industriarb": 25
                },
                "annual_turnover": "N/A",
                "annual_production_value": "400,000 kr"
            },
            "foundation_year": 1900,
            "board": [
                {
                    "name": "fabr. Martin Carlsson",
                    "role": "N/A"
                },
                {
                    "name": "fabr. Herbert Carlsson",
                    "role": "N/A"
                }
            ],
            "owners": [
                "N/A"
            ],
            "director": "N/A",
            "managing_director": "N/A",
            "sales_manager": "N/A",
            "manager": "N/A"
        }
    }
}