{
    "original": "Bryggeri—Bryntesson\n\n*\tBryggeri AB. Falken, Falkenberg.\n\nBryggeri och mineralvattenfabrik.\nTillverkar malt och maltdrycker,\nmineralvatten och läskedrycker.\n\nTelegr.-adr. o. telefon: Falken,\nFalkenberg. Postgiro: 7975.\n\nAkt.-kap.: 800,000 kr. Antal\nindustriarb.: 60. Tillv.-värde pr år; 2,500,000 kr.\n— Bolaget grundat 1896.\n\nStyrelse: häradshövd. John Samuelson\n(ordf.), disp. Robert Schwartzman, v.\nkonsul Erland Skantze, bryggmästare\nOlof Skantze, landstingsman Victor\nSkantze.\n\nVerkst dir.: Erland Skantze.\n\n*\tBryggeri AB. Fryksdalen, Torsby.\n\nTillverkar malt- och läskedrycker vid\nskattepliktiga bryggerier i Sunne och\nTorsby (båda i Värml. l.).\n\nHuvudkontor: Torsby. Telefon: 48 o.\n16. Postgiro: 13977. - Akt.-kap.: 200,000\nkr. Arb.-antal: Torsby 18, Sunne 6.\nTillv.-värde pr år: 600,000 kr. — Bolaget\ngrundat 1906.\n\nStyrelse: disp. John Lofgren (ordf.),\nfru E. Egnell, disp. Sven Jansson.\n\nDisp.: Gunnar Kolthoff.\n\nBryggeri AB. Kronan,\n\nSundbyberg.\n\nTillverkar malt- och läskedrycker.\n\nTelefon: 282655. Postgiro: 15087. —\nAkt.-kap.: 387,600 kr. Antal industriarb.:\n50. Tillv.-värde pr år: 1,500,000 kr. —\nBolaget grundat 1903, ombildat 1926.\n\nStyrelse: dir. Robert Bunge (ordf.),\nfru Elin Johansson, kamrer O. W. Mesch.\n\nVerkst. dir.: R. Bunge.\n\nKamrer: Yngve Jödahl.\n\n*\tBryggeri AB. Nordstjernan,\n\nSundsvall.\n\nTillverkar malt och maltdrycker samt\nmineralvatten och läskedrycker.\n\nTelefon: 3091, 3092 o. 4884. Postgiro:\n8559. — Akt.-kap.: 900,000 kr. Antal\nindustriarb.: 30. Tillv.-värde pr år: 900,000\nkr. — Bolaget grundat 1892.\n\nStyrelse: ing. G. Rosfors, konsul Erik\nStrömberg, dir. L. Valentin.\n\nVerkst. dir.: L. Valentin.\n\nDisp.: G. Rosfors.\n\n*\tBryggeriet Grönskog, Nybro.\n\nTillverkar malt samt malt- och\nläskedrycker vid bryggeri i Nybro (Kalmar l.).\n\nTelegr.-adr.: Grönskog, Nybro. Telefon:\n\n»Bryggeriet Grönskog» Postgiro: 281228.\n\n—\tAntal industriarb.: 20. Tillv.-värde pr\når: 500,000 kr. — Firman, etabl. 1874,\näges av Kalmar Bryggeri AB.\n\nChef: dir. Germ. Weiner.\n\n*\tBryggeriet Nordstjernan i Skövde\nAB., Skövde.\n\nTillverkar malt- och läskedrycker.\nTelegr.-adr.: Nordstjernan, Skövde.\nTelefon: 553. Postgiro: 91977.,—\nAkt.-kap.: 500,000 kr. Antal industriarb.: 30.\n\n—\tFirman etabl. 1872, bolag 1946.\nStyrelse: bankdir. R. Selander (ordf.),\n\nkörsnär H. Englund, disp. Oscar\nEriksson, disp. W. Nilson-Dag, rådman Tage\nRudstedt.\n\nVerkst. dir.: Oscar Eriksson.\nKamrer: Ingvar G. Svensson.\n\n*\tBryggeriet Victoria, Falköping.\n\nSkattepliktigt bryggeri. Tillverkar\nmalt-och läskedrycker.\n\nTelefon: 58 o. 536. Postgiro: 81079. —\nAntal industriarb.: 20. Tillv.-värde pr\når: 400,000 kr. — Bryggeriet anlagt 1860.\nÄgare: fru G. S. Schortz.\nDisp. o. bryggm.: Åke Schortz.\n\nAB. Bryggerimaskiner, Malmö.\n\nMek. verkstad. Tillverkar\nbryggerimaskiner.\n\nKontor: Trelleborgsvägen 16.\nTelegr.-adr.: Bryggerimaskiner. Malmö. Telefon:\n28736 o. 31853. Postgiro: 39655.\nEnsam-försälj.: Christian Berner, Göteborg,\nStockholm, Malmö, Oslo, Helsingfors o.\nKöpenhamn.\n\nAkt.-kap.: 100,000 kr. Antal\nindustriarb.: 90. — Bolaget grundat 1927.\n\nStyrelse: generalkonsul Christian\nBerner (ordf.), civiling. Fridthjof Berner,\ndir. Anton Broms.\n\nVerkst. dir.: Ivar Hallström.\n\nDisp.: N. C. Nielsen.\n\n*AB. J. Bryntesson &amp; C:o, Skara.\n\nSkofabrik. Tillverkar damskodon.\n\nTelefon: 901—04. Postgiro: 98500. —\nAkt.-kap.: 300,000 kr. Antal\nindustriarb.: 75. Tillv.-värde pr år: 1,050,000 kr.\n\nBolaget grundat 1912 under namn\nSkara Nya Skofabriks AB., nuv. namn\n1926.\n\nStyrelse: disp. A. Brynteson, disp.\nJohan Bryntesson, fru A. L. Fast.\n\nVerkst. dir.: J. Bryntesson.",
    "structured": {
        "1": {
            "name": "Bryggeri AB. Falken",
            "location": "Falkenberg",
            "business": "Bryggeri och mineralvattenfabrik",
            "products": "Tillverkar malt och maltdrycker, mineralvatten och läskedrycker",
            "contact": {
                "office": "Falken, Falkenberg",
                "phone": [
                    "Falken"
                ],
                "postgiro": "7975",
                "head_office": "",
                "sales_offices": [],
                "telegraph": "",
                "factory_office": "",
                "factory_phone": ""
            },
            "financials": {
                "capital": "800,000 kr",
                "employees": {
                    "industriarb": 60
                },
                "annual_turnover": "2,500,000 kr",
                "annual_production_value": "2,500,000 kr"
            },
            "foundation_year": 1896,
            "board": [
                {
                    "name": "häradshövd. John Samuelson",
                    "role": "ordf."
                },
                {
                    "name": "disp. Robert Schwartzman",
                    "role": "v."
                },
                {
                    "name": "konsul Erland Skantze",
                    "role": ""
                },
                {
                    "name": "bryggmästare Olof Skantze",
                    "role": ""
                },
                {
                    "name": "landstingsman Victor Skantze",
                    "role": ""
                }
            ],
            "director": "",
            "managing_director": "Erland Skantze",
            "owners": []
        },
        "2": {
            "name": "Bryggeri AB. Fryksdalen",
            "location": "Torsby",
            "business": "Tillverkar malt- och läskedrycker",
            "products": "Tillverkar malt- och läskedrycker vid skattepliktiga bryggerier i Sunne och Torsby (båda i Värml. l.)",
            "contact": {
                "office": "Torsby",
                "phone": [
                    "48",
                    "16"
                ],
                "postgiro": "13977",
                "head_office": "",
                "sales_offices": [],
                "telegraph": "",
                "factory_office": "",
                "factory_phone": ""
            },
            "financials": {
                "capital": "200,000 kr",
                "employees": {
                    "Torsby": 18,
                    "Sunne": 6
                },
                "annual_turnover": "600,000 kr",
                "annual_production_value": "600,000 kr"
            },
            "foundation_year": 1906,
            "board": [
                {
                    "name": "disp. John Lofgren",
                    "role": "ordf."
                },
                {
                    "name": "fru E. Egnell",
                    "role": ""
                },
                {
                    "name": "disp. Sven Jansson",
                    "role": ""
                }
            ],
            "director": "",
            "managing_director": "",
            "owners": []
        },
        "3": {
            "name": "Bryggeri AB. Kronan",
            "location": "Sundbyberg",
            "business": "Tillverkar malt- och läskedrycker",
            "products": "Tillverkar malt- och läskedrycker",
            "contact": {
                "office": "Sundbyberg",
                "phone": [
                    "282655"
                ],
                "postgiro": "15087",
                "head_office": "",
                "sales_offices": [],
                "telegraph": "",
                "factory_office": "",
                "factory_phone": ""
            },
            "financials": {
                "capital": "387,600 kr",
                "employees": {
                    "industriarb": 50
                },
                "annual_turnover": "1,500,000 kr",
                "annual_production_value": "1,500,000 kr"
            },
            "foundation_year": 1903,
            "board": [
                {
                    "name": "dir. Robert Bunge",
                    "role": "ordf."
                },
                {
                    "name": "fru Elin Johansson",
                    "role": ""
                },
                {
                    "name": "kamrer O. W. Mesch",
                    "role": ""
                }
            ],
            "director": "",
            "managing_director": "R. Bunge",
            "owners": []
        },
        "4": {
            "name": "Bryggeri AB. Nordstjernan",
            "location": "Sundsvall",
            "business": "Tillverkar malt och maltdrycker samt mineralvatten och läskedrycker",
            "products": "Description of products manufactured or services offered.",
            "contact": {
                "office": "Sundsvall",
                "phone": [
                    "3091",
                    "3092",
                    "4884"
                ],
                "postgiro": "8559",
                "head_office": "",
                "sales_offices": [],
                "telegraph": "",
                "factory_office": "",
                "factory_phone": ""
            },
            "financials": {
                "capital": "900,000 kr",
                "employees": {
                    "industriarb": 30
                },
                "annual_turnover": "900,000 kr",
                "annual_production_value": "900,000 kr"
            },
            "foundation_year": 1892,
            "board": [
                {
                    "name": "ing. G. Rosfors",
                    "role": ""
                },
                {
                    "name": "konsul Erik Strömberg",
                    "role": ""
                },
                {
                    "name": "dir. L. Valentin",
                    "role": ""
                }
            ],
            "director": "",
            "managing_director": "L. Valentin",
            "owners": []
        },
        "5": {
            "name": "Bryggeriet Grönskog",
            "location": "Nybro",
            "business": "Tillverkar malt samt malt- och läskedrycker",
            "products": "Description of products manufactured or services offered.",
            "contact": {
                "office": "Nybro",
                "phone": [],
                "postgiro": "281228",
                "head_office": "",
                "sales_offices": [],
                "telegraph": "Grönskog, Nybro",
                "factory_office": "",
                "factory_phone": ""
            },
            "financials": {
                "capital": "",
                "employees": {
                    "industriarb": 20
                },
                "annual_turnover": "500,000 kr",
                "annual_production_value": "500,000 kr"
            },
            "foundation_year": 1874,
            "board": [],
            "director": "",
            "managing_director": "dir. Germ. Weiner",
            "owners": []
        },
        "6": {
            "name": "Bryggeriet Nordstjernan i Skövde AB.",
            "location": "Skövde",
            "business": "Tillverkar malt- och läskedrycker",
            "products": "Description of products manufactured or services offered.",
            "contact": {
                "office": "Skövde",
                "phone": [
                    "553"
                ],
                "postgiro": "91977",
                "head_office": "",
                "sales_offices": [],
                "telegraph": "Nordstjernan, Skövde",
                "factory_office": "",
                "factory_phone": ""
            },
            "financials": {
                "capital": "500,000 kr",
                "employees": {
                    "industriarb": 30
                },
                "annual_turnover": "",
                "annual_production_value": ""
            },
            "foundation_year": 1872,
            "board": [
                {
                    "name": "bankdir. R. Selander",
                    "role": "ordf."
                },
                {
                    "name": "körsnär H. Englund",
                    "role": ""
                },
                {
                    "name": "disp. Oscar Eriksson",
                    "role": ""
                },
                {
                    "name": "disp. W. Nilson-Dag",
                    "role": ""
                },
                {
                    "name": "rådman Tage Rudstedt",
                    "role": ""
                }
            ],
            "director": "",
            "managing_director": "Oscar Eriksson",
            "owners": []
        },
        "7": {
            "name": "Bryggeriet Victoria",
            "location": "Falköping",
            "business": "Tillverkar malt-och läskedrycker",
            "products": "Description of products manufactured or services offered.",
            "contact": {
                "office": "Falköping",
                "phone": [
                    "58",
                    "536"
                ],
                "postgiro": "81079",
                "head_office": "",
                "sales_offices": [],
                "telegraph": "",
                "factory_office": "",
                "factory_phone": ""
            },
            "financials": {
                "capital": "",
                "employees": {
                    "industriarb": 20
                },
                "annual_turnover": "400,000 kr",
                "annual_production_value": "400,000 kr"
            },
            "foundation_year": 1860,
            "board": [],
            "director": "",
            "managing_director": "",
            "owners": [
                "fru G. S. Schortz"
            ]
        },
        "8": {
            "name": "AB. Bryggerimaskiner",
            "location": "Malmö",
            "business": "Mek. verkstad",
            "products": "Tillverkar bryggerimaskiner",
            "contact": {
                "office": "Trelleborgsvägen 16",
                "phone": [
                    "28736",
                    "31853"
                ],
                "postgiro": "39655",
                "head_office": "",
                "sales_offices": [
                    "Christian Berner, Göteborg",
                    "Stockholm",
                    "Malmö",
                    "Oslo",
                    "Helsingfors",
                    "Köpenhamn"
                ],
                "telegraph": "Bryggerimaskiner, Malmö",
                "factory_office": "",
                "factory_phone": ""
            },
            "financials": {
                "capital": "100,000 kr",
                "employees": {
                    "industriarb": 90
                },
                "annual_turnover": "",
                "annual_production_value": ""
            },
            "foundation_year": 1927,
            "board": [
                {
                    "name": "generalkonsul Christian Berner",
                    "role": "ordf."
                },
                {
                    "name": "civiling. Fridthjof Berner",
                    "role": ""
                },
                {
                    "name": "dir. Anton Broms",
                    "role": ""
                }
            ],
            "director": "",
            "managing_director": "Ivar Hallström",
            "owners": []
        },
        "9": {
            "name": "AB. J. Bryntesson & C:o",
            "location": "Skara",
            "business": "Skofabrik",
            "products": "Tillverkar damskodon",
            "contact": {
                "office": "Skara",
                "phone": [
                    "901—04"
                ],
                "postgiro": "98500",
                "head_office": "",
                "sales_offices": [],
                "telegraph": "",
                "factory_office": "",
                "factory_phone": ""
            },
            "financials": {
                "capital": "300,000 kr",
                "employees": {
                    "industriarb": 75
                },
                "annual_turnover": "1,050,000 kr",
                "annual_production_value": "1,050,000 kr"
            },
            "foundation_year": 1912,
            "current_name_year": 1926,
            "board": [
                {
                    "name": "disp. A. Brynteson",
                    "role": ""
                },
                {
                    "name": "disp. Johan Bryntesson",
                    "role": ""
                },
                {
                    "name": "fru A. L. Fast",
                    "role": ""
                }
            ],
            "director": "",
            "managing_director": "J. Bryntesson",
            "owners": []
        }
    }
}