{
    "original": "Lundh—Lund berg\n\n*AB. Nils P. Lundh, Malmö.\n\nByggnadsentreprenörfirma för\nvägbyggnads- och vägbeläggningsarbeten.\n\nKontor: Disponentg. 6. Telefon:\n71195. Postgiro: 39033.\n\nAkt.-kap.: -300,000 kr. Prod.-värde pr\når: 3,000,000 kr. — Firman etabl. 1895,\nbolag 1935.\n\nStyrelse: t. f. landskamrer Sigurd\nDahlrup (ordf.), ing. Axel Jepsson, dir.\nNils P. Lundh, fru W. Mårtensson,\nciviling. Gunnar Priitz.\n\nVerkst. dir.: Nils P. Lundh.\n\nArbetschefer: Axel Jepsson, Gunnar\nPriitz o. Birger Mårtensson.\n\nKamrer: G.-G. Fahl.\n\nJoh. Lundahl, Hjo.\n\nLädervarufabrik. Tillverkar plånböcker\noch portmonnäer samt mindre artiklar i\nläder och skinn.\n\nTelefon: 261. Postgiro: 30123. —\nAntal industriarb.: 12. Tillv.-värde pr år:\n120,000 kr. — Firman etabl. 1923.\n\nÄgare o. chef: fabr. Johan Lundahl.\n\nDisp.: Bertil Lundahl.\n\n*AB. H. Lundbeck &amp; Co., Malmö.\n\nLäkemedelsfabrik. Tillverkar läkemedel,\nspeciellt sulfonamid-, hormon- och\nsvavelpreparat.\n\nKontor: Drottningtorget 1.\nTelegr.-adr.: Axelman, Malmö. Telefon: 11974.\n— Akt.-kap.: 15,000 kr. Antal\nindustriarb.: 11. Tillv.-värde pr år: 600,000 kr.—\nBolaget grundat 1941.\n\nVerkst. dir.: Axel Hultman.\n\nDir.-assist.: Peder Hammarskiöld.\n\nLundberg &amp; Co., Smides AB.\nBröderna, Stockholm.\n\nSe Smides AB. Bröderna Lundberg &amp;\nCo., Stockholm.\n\n* Lundberg &amp; Schäders Eftr.,\n\nUmeå.\n\nSnickerifabrik. Tillverkar\nbyggnads-snickerier och inredningar.\n\nTelefon: 4480—81. Postgiro: 63590. —\nAntal industriarb.: 35. — Firman etabl.\n1929.\n\nÄgare o. chefer: fabr. K.-E. Olsson o.\nfabr. E. J. Nordberg.\n\n*C. J. Lundbergs Läderfabriks AB.,\n\nValdemarsvik.\n\nTillverkar kips-, smor-, svecia- och\nres-effektläder samt boxkalv, mocca, boxsidor,\n\nvaldikid, ruzziakrom, niagaraläder,\nalpläder samt arbetshandskar, ränder m. m.\n\nTelegr.-adr.: Lundbergsläder,\nValdemarsvik. Telefon: Läderfabriken.\nPostgiro: 23194. — Akt.-kap.: 2,800,000 kr.\nAntal industriarb.: 500. Tillv.-värde pr\når: 16,000,000 kr. — Firman etabl. 1869,\nbolag 1897.\n\nStyrelse: fabrikschef Folke Lundberg,\ndir. Nils Lundberg, fru S. Lundberg, dir.\nSven K. J. Lundberg.\n\nVerkst. dir.: Sven K. J. Lundberg.\n\nVice verkst. dir.: Nils Lundberg.\n\nFabrihschef: Folke Lundberg.\n\nInköpschef: Rune Winnerström.\n\n*AB. Fritz Lundberg, Tranås.\n\nPälsvarufabrik. Tillverkar pälskappor,\nkragar, baretter och pälsmössor m. m.\n\nHuvudkontor: Tranås. Telegr.-adr.:\nSkinn, Tranås. Telefon: »Fritz\nLundberg». Postgiro: 6049. Avd.-kontor o.\nrepresentanter: N. Haskel, Stockholm,\nKungsg. 51, telefon: 105912; Erik\nLunden, Göteborg, Kungsg. 46, telefon:\n111594.\n\nAkt.-kap.: 270,000 kr. Antal\nindustriarb.: 70. Tillv.-värde pr år: 2,000,000 kr.\n\n—\tFirman etabl. 1904, bolag 1917.\n\nStyrelse: bankdir. Gösta Ljungmark,\n\ndisp. Bengt Lundberg, dir. Fritz\nLundberg.\n\nVerkst. dir.: Fritz Lundberg.\n\nFritz Lundbergs Skinnberederi* &amp;\nFärgeri AB., Tranås.\n\nUtför beredning och färgning av\npälsskinn.\n\nTelegr.-adr.: Skinn, Tranås. Telefon:\n»Fritz Lundberg». Postgiro: 281727.\nRepresentanter: N. Haskel, Stockholm,\nKungsg. 51, telefon: 105912; Erik\nLunden, Göteborg, Kungsg. 46, telefon:\n111594.\n\nAkt.-kap.: 225,000 kr. Antal\nindustriarb.: 120. Tillv.-värde pr år: 1,500,000 kr.\n\n—\tFirman etabl. 1904, bolag 1944, är\ndotterbolag till AB. Fritz Lundberg,\nTranås.\n\nStyrelse: bankdir. Gösta Ljungmark,\ndisp. Bengt Lundberg, dir. Fritz\nLundberg.\n\nVerkst. dir.: Fritz Lundberg.\n\nJoh. Lundbergs Eftr., Limhamn,\n\nTillverkar transportanordningar,\ngrävmaskiner, gripskopor, järnkonstruktioner\noch tankanläggningar vid mek. verkstad\ni Limhamn, Malmö.",
    "structured": {
        "1": {
            "name": "Lundh—Lundberg AB",
            "location": "Malmö",
            "business": "Byggnadsentreprenörfirma för vägbyggnads- och vägbeläggningsarbeten",
            "contact": {
                "office": "Disponentg. 6",
                "phone": [
                    "71195"
                ],
                "postgiro": "39033"
            },
            "financials": {
                "capital": "-300,000 kr",
                "annual_turnover": "3,000,000 kr",
                "annual_production_value": "3,000,000 kr"
            },
            "foundation_year": 1895,
            "corporation_year": 1935,
            "board": [
                {
                    "name": "t. f. landskamrer Sigurd Dahlrup",
                    "role": "ordf."
                },
                {
                    "name": "ing. Axel Jepsson",
                    "role": null
                },
                {
                    "name": "dir. Nils P. Lundh",
                    "role": null
                },
                {
                    "name": "fru W. Mårtensson",
                    "role": null
                },
                {
                    "name": "civiling. Gunnar Priitz",
                    "role": null
                }
            ],
            "director": "Nils P. Lundh",
            "managing_director": "Nils P. Lundh",
            "sales_manager": null
        },
        "2": {
            "name": "Joh. Lundahl",
            "location": "Hjo",
            "business": "Lädervarufabrik",
            "contact": {
                "phone": [
                    "261"
                ],
                "postgiro": "30123"
            },
            "financials": {
                "annual_production_value": "120,000 kr"
            },
            "foundation_year": 1923,
            "owners": [
                "fabr. Johan Lundahl"
            ],
            "director": null,
            "managing_director": null,
            "sales_manager": null
        },
        "3": {
            "name": "AB. H. Lundbeck & Co.",
            "location": "Malmö",
            "business": "Läkemedelsfabrik",
            "contact": {
                "office": "Drottningtorget 1",
                "telegraph": "Axelman, Malmö",
                "phone": [
                    "11974"
                ],
                "postgiro": null
            },
            "financials": {
                "capital": "15,000 kr",
                "annual_production_value": "600,000 kr"
            },
            "corporation_year": 1941,
            "board": [
                {
                    "name": "Axel Hultman",
                    "role": "Verkst. dir."
                },
                {
                    "name": "Peder Hammarskiöld",
                    "role": "Dir.-assist."
                }
            ],
            "director": null,
            "managing_director": null,
            "sales_manager": null
        },
        "4": {
            "name": "Lundberg & Schäders Eftr.",
            "location": "Umeå",
            "business": "Snickerifabrik",
            "contact": {
                "phone": [
                    "4480—81"
                ],
                "postgiro": "63590"
            },
            "financials": {
                "annual_production_value": null
            },
            "foundation_year": 1929,
            "owners": [
                "fabr. K.-E. Olsson",
                "fabr. E. J. Nordberg"
            ],
            "director": null,
            "managing_director": null,
            "sales_manager": null
        },
        "5": {
            "name": "C. J. Lundbergs Läderfabriks AB.",
            "location": "Valdemarsvik",
            "business": "Tillverkar kips-, smor-, svecia- och res-effektläder samt boxkalv, mocca, boxsidor, valdikid, ruzziakrom, niagaraläder, alpläder samt arbetshandskar, ränder m. m.",
            "contact": {
                "telegraph": "Lundbergsläder, Valdemarsvik",
                "phone": [
                    "Läderfabriken"
                ],
                "postgiro": "23194"
            },
            "financials": {
                "capital": "2,800,000 kr",
                "annual_production_value": "16,000,000 kr"
            },
            "corporation_year": 1897,
            "board": [
                {
                    "name": "fabrikschef Folke Lundberg",
                    "role": null
                },
                {
                    "name": "dir. Nils Lundberg",
                    "role": null
                },
                {
                    "name": "fru S. Lundberg",
                    "role": null
                },
                {
                    "name": "dir. Sven K. J. Lundberg",
                    "role": null
                }
            ],
            "director": "Sven K. J. Lundberg",
            "managing_director": "Nils Lundberg",
            "sales_manager": null
        },
        "6": {
            "name": "AB. Fritz Lundberg",
            "location": "Tranås",
            "business": "Pälsvarufabrik",
            "contact": {
                "phone": [
                    "»Fritz Lundberg»"
                ],
                "postgiro": "6049"
            },
            "financials": {
                "capital": "270,000 kr",
                "annual_production_value": "2,000,000 kr"
            },
            "corporation_year": 1917,
            "board": [
                {
                    "name": "bankdir. Gösta Ljungmark",
                    "role": null
                },
                {
                    "name": "disp. Bengt Lundberg",
                    "role": null
                },
                {
                    "name": "dir. Fritz Lundberg",
                    "role": null
                }
            ],
            "director": "Fritz Lundberg",
            "managing_director": "Fritz Lundberg",
            "sales_manager": null
        },
        "7": {
            "name": "Fritz Lundbergs Skinnberederi & Färgeri AB.",
            "location": "Tranås",
            "business": "Utför beredning och färgning av pälsskinn",
            "contact": {
                "telegraph": "Skinn, Tranås",
                "phone": [
                    "»Fritz Lundberg»"
                ],
                "postgiro": "281727"
            },
            "financials": {
                "capital": "225,000 kr",
                "annual_production_value": "1,500,000 kr"
            },
            "corporation_year": 1944,
            "board": [
                {
                    "name": "bankdir. Gösta Ljungmark",
                    "role": null
                },
                {
                    "name": "disp. Bengt Lundberg",
                    "role": null
                },
                {
                    "name": "dir. Fritz Lundberg",
                    "role": null
                }
            ],
            "director": "Fritz Lundberg",
            "managing_director": "Fritz Lundberg",
            "sales_manager": null
        },
        "8": {
            "name": "Joh. Lundbergs Eftr.",
            "location": "Limhamn",
            "business": "Tillverkar transportanordningar, grävmaskiner, gripskopor, järnkonstruktioner och tankanläggningar vid mek. verkstad i Limhamn, Malmö.",
            "contact": {
                "phone": null,
                "postgiro": null
            },
            "financials": {
                "annual_production_value": null
            },
            "owners": null,
            "director": null,
            "managing_director": null,
            "sales_manager": null
        }
    }
}