{
    "original": "Sandsjö—Sandv iken\n\nStyrelse: dir. Gustaf Kalim (ordf.),\ndisp. Sten Hasselberg, ing. Bo Zaclirisson.\n\nDisp. o. försäljn.-chef: Sten Hasselberg.\n\nVerkstadschef: Bo Zachrisson.\n\nAB. Sandsjö Möbelfabrik, Bodafors.\n\nTillverkar kontorsmöbler samt hotell-,\nsjukhus- och butiksinredningar vid fabrik\ni Bodafors (Jönköp. l.).\n\nTelegr.-adr.: Askmi, Bodafors. Telefon:\n28. Postgiro: 93954. Ensamförsälj.: AB.\nSvenska Kontorsmöbelindustrier,\nStockholm, Brunkebergstorg 11. Telefon:\n234055.\n\nAkt.-kap.: 150,000 kr. Antal\nindustriarb.: 90. Tillv.-värde pr år: 1,000,000 kr.\n— Bolaget grundat 1919.\n\nStyrelse: bankdir. Carl Berndt,\ntandläkare Allan Buden, dir. Folke Rudén.\n\nVerkst. dir. o. disp.: Folke Rudén\n(Sthlm).\n\nVerkstadschef: Karl Lengqvist.\n\nKassör: Roland Jonsson.\n\n\"Sandsjöfors Borstträfabrik,\n\nBodafors.\n\nTillverkar borstträn vid fabrik i\nSandsjöfors, Bodafors (Jönköp. l.).\n\nTelefon: Sandsjöfors 13. Postgiro:\n22791. — Antal industriarb.: 80. —\nFirman etabl. 1922.\n\nÄgare o. chef: fabr. Josua Patriksson.\n\n\"Sandslätts Möbel- &amp; Industri AB.,\n\nAlsterbro.\n\nSnickerifabrik och sågverk vid\nAlster-bro (Kalmar l.). Tillverkar möbler och\ninredningsarbeten.\n\nTelefon: 12. Postgiro: 77445. —\nAkt.-kap.: 116,000 kr. Antal industriarb.: 90.\nTillv.-värde pr år: 1,000,000 kr. —\nBolaget grundat 1920.\n\nStyrelse: riksdagsm. Arvid Jonsson\n(ordf.), nämndem. John Andersson, disp.\nF. Barklund, nämndem. A. Bern, lantbr.\nHugo Jonsson.\n\nDisp.: F. Barklund.\n\n\"Sandstens Tryckeri, Bröderna,\n\nGöteborg.\n\nSe Bröderna Sandstens Tryckeri,\nGöteborg.\n\n\"Sandströms Skidfabrik, AB.,\n\nStockholm.\n\nSe Bröderna Sandströms Skidfabrik,\nAB., Stockholm.\n\n46\n\n\"AB. Sandwalls Angbryggeri, Borås.\n\nTillverkar maltdrycker, mineralvatten\noch läskedrycker.\n\nTelefon: 10007 o. »Sandwalls».\nPostgiro: 97494.\n\nAkt.-kap.: 500,000 kr. Antal\nindustriarb.: 32. Tillv.-värde pr år: 1,000,000 kr.\n— Firman etabl. 1862, bolag 1944.\n\nStyrelse: fabr. Sven Sandwall (ordf.),\nbankdir. Elof Björck, adv. Erik Grenfors.\n\nVerkst. dir.: Sven Sandwall.\n\nKamrer: A. Wilhelm Andersson.\n\n\"Sandviks Sågverk, Holmsmid o.\nSeskarö.\n\nSe AB. Statens Skogsindustrier,\nStockholm.\n\nSandvikens Cellulosa AB.,\n\nDynäs.\n\nSulfatfabrik i Dynäs (Västernorrl. L).\nTillverkar stark sulfatcellulosa, s. k.\nkraftmassa. Bolaget idkar jämväl\nskogshantering.\n\nHuvudkontor: Dynäs. Telegr.-adr.;\nSandviken, Kramfors. Telefon:\nKramfors 5. För säljn.-kontor: Graninge verkens\nFörsäljningskontor, Stockholm, Stureplän\n6, telefon: 600312 o. 600344. Telegr.-adr.:\nGevabus, Stockholm.\n\nAkt.-kap.: 3,500,000 kr. Antal\nindustriarb.: 200. Årstillv.: 30,000 ton\nsulfatmassa.\n\nBolaget grundat 1869 under namn\nSandvikens Sågverks AB., nuv. namn\n1927.\n\nStyrelse: adv. Tom Forssner (ordf.),\ndir. G. J. Versteegh (v. ordf.), fru H.\nNordin.\n\nVerkst. dir.: G. J. Versteegh\n(Stockholm).\n\növering. o. platschef: B. Nyquist.\n\nFörsäljn.-chef i Stockholm: int. Karl\nWingstedt.\n\nSandvikens Dissousgas AB.,\n\nSandviken.\n\nTillverkar dissousgas, syrgas och\nkvävgas vid fabriker i Sandviken (Gävleb. l.).\n\nTelefon: 4374. Postgiro: 6470. —\nAkt.-kap.: 600,000 kr. Arb.-antal: 16.\nTillv.-värde pr år: 800,000 kr. — Bolaget\ngrundat 1916.\n\nStyrelse: disp. Nils J. Gille (ordf.),\ndir. R. W. Betts, dir. Gunnar Dalen.\n\nDisp.: Nils J. Gille.\n\n•&lt;r",
    "structured": {
        "1": {
            "name": "AB. Sandsjö Möbelfabrik",
            "location": "Bodafors",
            "business": "Tillverkar kontorsmöbler samt hotell-, sjukhus- och butiksinredningar",
            "products": "Description of products manufactured or services offered.",
            "contact": {
                "office": "N/A",
                "phone": [
                    "N/A"
                ],
                "postgiro": "93954",
                "head_office": "N/A",
                "sales_offices": [
                    {
                        "location": "Stockholm",
                        "phone": "234055"
                    }
                ],
                "telegraph": "Askmi, Bodafors",
                "factory_office": "N/A",
                "factory_phone": "N/A"
            },
            "financials": {
                "capital": "150,000 kr",
                "employees": {
                    "industriarb": 90
                },
                "annual_turnover": "N/A",
                "annual_production_value": "1,000,000 kr"
            },
            "foundation_year": 1919,
            "current_name_year": "N/A",
            "predecessor": "N/A",
            "original_name": "N/A",
            "corporation_year": "N/A",
            "board": [
                {
                    "name": "Gustaf Kalim",
                    "role": "dir."
                },
                {
                    "name": "Sten Hasselberg",
                    "role": "disp."
                },
                {
                    "name": "Bo Zaclirisson",
                    "role": "ing."
                }
            ],
            "owners": [
                "AB. Svenska Kontorsmöbelindustrier"
            ],
            "director": "N/A",
            "managing_director": "N/A",
            "sales_manager": "Sten Hasselberg",
            "manager": "N/A"
        },
        "2": {
            "name": "Sandsjöfors Borstträfabrik",
            "location": "Bodafors",
            "business": "Tillverkar borstträn",
            "products": "N/A",
            "contact": {
                "office": "N/A",
                "phone": [
                    "Sandsjöfors 13"
                ],
                "postgiro": "22791",
                "head_office": "N/A",
                "sales_offices": [],
                "telegraph": "N/A",
                "factory_office": "N/A",
                "factory_phone": "N/A"
            },
            "financials": {
                "capital": "N/A",
                "employees": {
                    "industriarb": 80
                },
                "annual_turnover": "N/A",
                "annual_production_value": "N/A"
            },
            "foundation_year": 1922,
            "current_name_year": "N/A",
            "predecessor": "N/A",
            "original_name": "N/A",
            "corporation_year": "N/A",
            "board": [
                {
                    "name": "Josua Patriksson",
                    "role": "ägare o. chef"
                }
            ],
            "owners": [
                "N/A"
            ],
            "director": "N/A",
            "managing_director": "N/A",
            "sales_manager": "N/A",
            "manager": "N/A"
        },
        "3": {
            "name": "Sandslätts Möbel- & Industri AB.",
            "location": "Alsterbro",
            "business": "Tillverkar möbler och inredningsarbeten",
            "products": "N/A",
            "contact": {
                "office": "N/A",
                "phone": [
                    "12"
                ],
                "postgiro": "77445",
                "head_office": "N/A",
                "sales_offices": [],
                "telegraph": "N/A",
                "factory_office": "N/A",
                "factory_phone": "N/A"
            },
            "financials": {
                "capital": "116,000 kr",
                "employees": {
                    "industriarb": 90
                },
                "annual_turnover": "N/A",
                "annual_production_value": "1,000,000 kr"
            },
            "foundation_year": 1920,
            "current_name_year": "N/A",
            "predecessor": "N/A",
            "original_name": "N/A",
            "corporation_year": "N/A",
            "board": [
                {
                    "name": "Arvid Jonsson",
                    "role": "riksdagsm."
                },
                {
                    "name": "John Andersson",
                    "role": "nämndem."
                },
                {
                    "name": "F. Barklund",
                    "role": "disp."
                },
                {
                    "name": "A. Bern",
                    "role": "nämndem."
                },
                {
                    "name": "Hugo Jonsson",
                    "role": "lantbr."
                }
            ],
            "owners": [
                "N/A"
            ],
            "director": "N/A",
            "managing_director": "N/A",
            "sales_manager": "N/A",
            "manager": "N/A"
        },
        "4": {
            "name": "AB. Sandwalls Angbryggeri",
            "location": "Borås",
            "business": "Tillverkar maltdrycker, mineralvatten och läskedrycker",
            "products": "N/A",
            "contact": {
                "office": "N/A",
                "phone": [
                    "10007 o. 'Sandwalls'"
                ],
                "postgiro": "97494",
                "head_office": "N/A",
                "sales_offices": [],
                "telegraph": "N/A",
                "factory_office": "N/A",
                "factory_phone": "N/A"
            },
            "financials": {
                "capital": "500,000 kr",
                "employees": {
                    "industriarb": 32
                },
                "annual_turnover": "N/A",
                "annual_production_value": "1,000,000 kr"
            },
            "foundation_year": 1862,
            "current_name_year": 1944,
            "predecessor": "N/A",
            "original_name": "N/A",
            "corporation_year": "N/A",
            "board": [
                {
                    "name": "Sven Sandwall",
                    "role": "fabr."
                },
                {
                    "name": "Elof Björck",
                    "role": "bankdir."
                },
                {
                    "name": "Erik Grenfors",
                    "role": "adv."
                }
            ],
            "owners": [
                "N/A"
            ],
            "director": "N/A",
            "managing_director": "N/A",
            "sales_manager": "N/A",
            "manager": "N/A"
        },
        "5": {
            "name": "Sandvikens Cellulosa AB.",
            "location": "Dynäs",
            "business": "Sulfatfabrik",
            "products": "N/A",
            "contact": {
                "office": "N/A",
                "phone": [
                    "Kramfors 5"
                ],
                "postgiro": "6470",
                "head_office": "N/A",
                "sales_offices": [
                    {
                        "location": "Stockholm",
                        "phone": "600312 o. 600344"
                    }
                ],
                "telegraph": "Sandviken, Kramfors",
                "factory_office": "N/A",
                "factory_phone": "N/A"
            },
            "financials": {
                "capital": "3,500,000 kr",
                "employees": {
                    "industriarb": 200
                },
                "annual_turnover": "N/A",
                "annual_production_value": "30,000 ton sulfatmassa"
            },
            "foundation_year": 1869,
            "current_name_year": 1927,
            "predecessor": "Sandvikens Sågverks AB",
            "original_name": "N/A",
            "corporation_year": "N/A",
            "board": [
                {
                    "name": "Tom Forssner",
                    "role": "adv."
                },
                {
                    "name": "G. J. Versteegh",
                    "role": "dir."
                },
                {
                    "name": "H. Nordin",
                    "role": "fru"
                }
            ],
            "owners": [
                "N/A"
            ],
            "director": "N/A",
            "managing_director": "G. J. Versteegh",
            "sales_manager": "int. Karl Wingstedt",
            "manager": "B. Nyquist"
        },
        "6": {
            "name": "Sandvikens Dissousgas AB.",
            "location": "Sandviken",
            "business": "Tillverkar dissousgas, syrgas och kvävgas",
            "products": "N/A",
            "contact": {
                "office": "N/A",
                "phone": [
                    "4374"
                ],
                "postgiro": "N/A",
                "head_office": "N/A",
                "sales_offices": [],
                "telegraph": "N/A",
                "factory_office": "N/A",
                "factory_phone": "N/A"
            },
            "financials": {
                "capital": "600,000 kr",
                "employees": {
                    "arb.-antal": 16
                },
                "annual_turnover": "N/A",
                "annual_production_value": "800,000 kr"
            },
            "foundation_year": 1916,
            "current_name_year": "N/A",
            "predecessor": "N/A",
            "original_name": "N/A",
            "corporation_year": "N/A",
            "board": [
                {
                    "name": "Nils J. Gille",
                    "role": "disp."
                },
                {
                    "name": "R. W. Betts",
                    "role": "dir."
                },
                {
                    "name": "Gunnar Dalen",
                    "role": "dir."
                }
            ],
            "owners": [
                "N/A"
            ],
            "director": "N/A",
            "managing_director": "Nils J. Gille",
            "sales_manager": "N/A",
            "manager": "N/A"
        }
    }
}