{
    "original": "Sverige—Sverre\n\nTelefon: 28 o. 66. Postgiro: 86767.\nEn-samförsälj.: Riksförbundet Lin och\nHampa, Stockholm, Valhallavägen 132,\ntelefon: 602235.\n\nAntal industriarb.: 80. Prod.-värde pr\når: 1,200,000 kr. — Föreningen bildades\n1941.\n\nDisp.: vakant.\nKamrer: Börje Aronsson.\nDriftsing.: Arne Krall.\n\n*AB. Sveriges Litografiska\nTryckerier (»S. L. T.»), Stockholm.\n\nTill bolaget äro följande företag\nanslutna :\n\nBengtsons Litografiska AB., Sthlm.\nA. Börtzells Tryckeri AB., Sthlm.\nCederquists Grafiska AB., Sthlm.\nAB. Centraltryckeriet i Stockholm.\nAB. Ellte Uppslagslitteratur, Sthlm.\nEsselte AB., Sthlm.\nFörlags AB. Iduna, Stockholm.\nAB. 1. M. Göthe, Sthlm.\nAB. P. Herzog &amp; Söner, Sthlm.\nIduns Tryckeri AB., Sthlm.\nAB. Kartografiska Institutet, Sthlm.\nAB. Katalog- och Tidskriftstryck,\nSthlm.\n\nAB. Konsumenttjänst, Stockholm.\nAB. Ljus, Sthlm.\n\nIsaac Marcus Boktryckeri AB., Sthlm.\nNeuer Verlag AB., Sthlm.\nAB. P. A. Norstedt &amp; Söner, Sthlm.\nP. A. Norstedt &amp; Söners Bokbinderi\n\nAB., Sthlm.\nPappemballage AB., Sthlm.\nParagon AB., Sthlm.\nStockholm Kartong- &amp; Litogr. AB.,\nSthlm.\n\nFr. Svanström &amp; Co., Pappershandels\n\nAB., Sthlm.\nAB. Svanströms Pappersagentur, Sthlm.\nAB. Svensk Bildmätning, Stockholm.\nAB. Svensk Litteratur, Sthlm.\nAB. Hasse W. Tullberg, Sthlm.\nEsseltes Göteborgsindustrier AB.,\nGöteborg.\n\nBorås Pappersförädlings AB., Göteborg.\nHugo Brusewitz AB., Göteborg.\nGustaf Melins AB., Göteborg.\nAB. Esselte Kartonnage i Göteborg,\nGöteborg.\n\nGöteborgs Wellpappfabriks AB.,\nGöteborg.\n\nWezät a-Göteborgslit ogr af en AB.,\nGöteborg.\n\nAB. Köhnkes Kartongfabrik. Malmö.\nSkånska Litografiska AB., Malmö.\nSkriv- &amp; Ritboks AB. i Arlöv, Gävle,\n\nGöteborg och Nässjö.\nSv. Skolmateriel AB. Gevalia, Gävle.\nAB. Borås Tryckeri &amp; Kartongfabrik,\nBorås.\n\nHanssons Tryckeri AB., Eskilstuna.\n\nAB. J. O. Öberg &amp; Son, Eskilstuna.\n\nJohnsons Pappersind. AB., Hälsingborg.\n\nAB. Tengwall, Hälsingborg.\n\nAB. Kassablock, Isidor Svahn\nPappersindustri, Hälsingborg.\n\nJönköpings Litografiska AB.,\nJönköping.\n\nLinköpings Litografiska AB.,\nLinköping.\n\nLithografiska AB. Norrköping.\n\nNya AB. Lundbergs Bokh., Norrköping.\n\nKullbergs Bok- &amp; Pappershandel AB.,\nNyköping.\n\nThorsviks AB., Norrahammar.\n\nÖrebro Pappersbruks AB., Örebro.\n\nBates Paper Säck AB., Örebro.\n\nFrövifors Bruks AB., Frövi.\n\nBolaget utför genom anslutna firmor\nalla slags tryckalster, boktryck, djuptryck,\nljustryck, litografi och offsettryck,\nkoppartryck, paragon tryck, klichéer och\nbok-binderiarbeten samt tillverkar alla slags\nkontorsutensilier, album, kontors- ^ och\nskrivböeker. askar, kartonger, kortregister,\nkortpärmar, kortaskar och -lådor,\nkartfodral, spelkort, hyllremsor, tårtpapper,\npappersservetrer, kuvert och påsar,\ncello-fanemballMLre kautschukstämplar m. m.\nsamt sulfatcellulosa, kraft- och\nspinnpapper, kraftpapp, byggnadspapp,\nkraft-papperssäckar, wellpapp och s. k.\nColum-buskartonger.\n\nKontor: Stockholm, Vasagatan 16.\nTelegr.-adr.: Esselte. Stockholm. Telefon:\n»Esselte». Postgiro: 78.\n\nAkt.-kap.: 43,395,000 kr. Sammanlagda\nantalet anställda vid koncernen: 7,368\n(excl. Örebro Pappersbruks AB.). —\nBolaget grundat 1913.\n\nStyrelse: generalkonsul Ragnar\nSöderberg (ordf.), tankdir. Petrus Brundell (v.\nordf.), hovauditör Birger Barre, kapten\nTore Bendz, disp. Gunnar Björkman, f. d.\nhovrättsrådet Johan Nordenfalk, dir.\nKnut Östberg.\n\nVerkst. dir.: Knut Östberg.\n\nV. verkst. dir.: civiling. Sven Dahlbäck.\n\nDir-assist.: disp. Arne Engström.\n\nKamrerare: Daniel Wester o. Chr.\nYll-ner.\n\nAB. Sverre, Göteborg.\n\nMek. verkstad och båtvarv. Tillverkar\nnautiska instrument, lanternor, modeller\nav fartyg och industriella anläggningar\nm. m. samt konstruerar och bygger\nlustyachter, fiskefartyg och mindre\nbruksfartyg av trä och järn.\n\nKontor: Skeppsbron 2. Telegr.-adr.:\nSverre, Göteborg. Telefon: 174138.\n\nAkt.-kap.: 100,000 kr. Antal industri-",
    "structured": {
        "firms": [
            {
                "name": "Sverige—Sverre",
                "location": "Stockholm",
                "business": "En-samförsälj. - Riksförbundet Lin och Hampa",
                "contact": {
                    "phone": [
                        "28",
                        "66"
                    ],
                    "postgiro": "86767",
                    "sales_offices": [
                        {
                            "location": "Stockholm",
                            "phone": "602235"
                        }
                    ]
                },
                "financials": {
                    "employees": {
                        "industriarb": 80
                    },
                    "annual_production_value": "1,200,000 kr"
                },
                "foundation_year": 1941,
                "board": [
                    {
                        "name": "vakant",
                        "role": "Disp."
                    },
                    {
                        "name": "Börje Aronsson",
                        "role": "Kamrer"
                    },
                    {
                        "name": "Arne Krall",
                        "role": "Driftsing."
                    }
                ]
            },
            {
                "name": "AB. Sveriges Litografiska Tryckerier (»S. L. T.»)",
                "location": "Stockholm",
                "business": "Litografisk Tryckning",
                "products": "Tryckalster, boktryck, djuptryck, ljustryck, litografi och offsettryck, koppartryck, paragon tryck, klichéer och bok-binderiarbeten samt tillverkar kontorsutensilier, album, kontors- och skrivböeker, askar, kartonger, kortregister, kortpärmar, kortaskar och -lådor, kartfodral, spelkort, hyllremsor, tårtpapper, pappersservetrer, kuvert och påsar, cello-fanemballage, kautschukstämplar m.m., sulfatcellulosa, kraft- och spinnpapper, kraftpapp, byggnadspapp, kraft-papperssäckar, wellpapp och Columbia-kartonger",
                "contact": {
                    "office": "Vasagatan 16",
                    "telegraph": "Esselte. Stockholm",
                    "phone": [
                        "Esselte"
                    ],
                    "postgiro": "78"
                },
                "financials": {
                    "capital": "43,395,000 kr",
                    "employees": {
                        "total": 7368
                    },
                    "foundation_year": 1913
                },
                "board": [
                    {
                        "name": "Ragnar Söderberg",
                        "role": "Generalkonsul (ordf.)"
                    },
                    {
                        "name": "Petrus Brundell",
                        "role": "Tankdir. (v. ordf.)"
                    },
                    {
                        "name": "Birger Barre",
                        "role": "Hovauditör"
                    },
                    {
                        "name": "Tore Bendz",
                        "role": "Kapten"
                    },
                    {
                        "name": "Gunnar Björkman",
                        "role": "Disp."
                    },
                    {
                        "name": "Johan Nordenfalk",
                        "role": "F.d. Hovrättsrådet"
                    },
                    {
                        "name": "Knut Östberg",
                        "role": "Dir."
                    }
                ],
                "director": "Knut Östberg",
                "managing_director": "Knut Östberg"
            },
            {
                "name": "AB. Sverre",
                "location": "Göteborg",
                "business": "Mek. verkstad och båtvarv",
                "products": "Tillverkar nautiska instrument, lanternor, modeller av fartyg och industriella anläggningar m.m., samt konstruerar och bygger lustyachter, fiskefartyg och mindre bruksfartyg av trä och järn",
                "contact": {
                    "office": "Skeppsbron 2",
                    "telegraph": "Sverre, Göteborg",
                    "phone": "174138"
                },
                "financials": {
                    "capital": "100,000 kr"
                },
                "manager": "Arne Krall"
            }
        ]
    }
}