{
    "original": "Svenska\n\nKontor: Fridhemsg. 43. Telegr.-adr.:\nSpiralfabriken, Stockholm. Telefon:\n505045 o. 505042. Postgiro: 52100.\n\nAkt.-kap.: 745,200 kr. Antal\nindustriarb.: 130. Tillv.-värde pr år: 2,800,000 kr.\n\n—\tBolaget grundat 1886.\n\nStyrelse: dir. Lars Blume (ordf.), med.\ndr Einar Belfrage, kapten Åke Gylling,\növering. Einar Sjögren.\n\nVerkst. dir.: Åke Gylling.\n\nDir.-assist.: Gunnar Sjögren.\n\nOfferting.: ing. E. Bondeson.\n\n(Jfr annons i Annonsörförteckningen.)\n\nSvenska Sportfabriks AB.,\n\nStockholm.\n\nTillverkar badmintonbollar.\nVarumärken: »Oyklon», »Komet», »Indian» o.\n»Svalan».\n\nKontor: Kungsg. 48. Telegr.-adr.:\nSvensksportab, Stockholm. Telefon:\n117395 o. 117360. Postgiro: 159797.\n\nAkt.-kap.: 15,000 kr. Antal\nindustriarb.: 20. Tillv.-värde pr år: 75,000 kr.\n\n—\tBolaget grundat 1940.\n\nVerkst. dir.: Ludv. T. Hagberg.\n\nSvenska Stansknivfabriken, Örebro.\n\nTillverkar stansknivar för olika\nändamål.\n\nTelefon: 11763. Postgiro: 70896. Repr.\ni Stockholm: AB. Praktiska Nyheter,\nLinnég. 51, telefon: 622208.\n\nAntal industriarb.: 5. Tillv.-värde pr\når: 35,000 kr. — Firman etabl. 1915.\n\nÄgare o. chef: fabr. Harry Andersson.\n\nAB. Svenska Strebelverken,\n\nVästervik.\n\nGjuteri och mek. verkstad. Tillverkar\nvärmeledningspannor samt specialpannor\nför eldning med koks, stokerkol, ved och\nolja. Varumärke: »Strebel».\n\nTelegr.-adr.: Strebel, Västervik.\nTelefon: 1150 o. 1111. Postgiro: 82450.\nEn-samförsälj.: AB. Gustavsbergs Fabriker,\nGustavsberg, telefon: »Porslinsfabriken»,\nGustavsberg.\n\nAkt.-kap.: 200,000 kr. Antal\nindustriarb.: 90. Tillv.-värde pr år: 1,500,000 kr.\n\nFirman grundad 1924, nuv. namn 1933.\n\nStyrelse: dir. Pehr Carlson, adv. Yngve\nSchartau.\n\nVerkst. dir.: G. Miinster.\n\nDisp.: Jörgen Drachmann.\n\nSvenska Strumpfabriks AB.,\n\nLinköping.\n\nStrumpfabrik i Partille. Tillverkar\ndamstrumpor.\n\nTelefon: »Ullholms», Linköping. —\nAkt.-kap.: 250,000 kr. Antal industriarb.:\n30. Tillv.-värde pr år: 500,000 kr. —\nBolaget, grundat 1940, är dotterbolag till\nAB. K. A. Ullholm.\n\nStyrelse: v. konsul K. A. Ullholm\n(ordf.), disp. Wald. Johanson,\nförsäljn.-chef Bengt Lindström.\n\nVerkst. dir.: K. A. Ullholm.\n\n\"AB. Svenska Stållinor,\n\nKristinehamn.\n\nSe Hellefors Bruks AB., Hällefors.\n\n\"Svenska Stålpressnings AB.\nOlofström, Olof ström.\n\nPress verk, plåt- och bleckslageri,\ngalva-niseringsverk samt mek. verkstad vid\nOlof ström (Blekinge l.).\n\nTillverkar emaljerade plåtbadkar, kok-,\nhushålls- och sanitetskärl samt disklådor\noch diskbänksbeklädnader av rostfri\nstålplåt, bykgrytor och vattenvärmarq,\ntvätt apparater, foder kokare, mullskopor,\nseparatordelar, gjuteriskänkar,\nautomobil-materiel m. m. Bolaget idkar jämväl\nlantbruk.\n\nHuvudkontor: Olof ström. Telegr.-adr.:\nOlof ström, Karlshamn. Telefon:\n»Bruket», Olofström. Postgiro: 7841.\n\nAkt.-kap.: 1,500,000 kr. Antal\nindustriarb.: 1,200.\n\nBolaget grundat 1887. AB. Separator,\nStockholm, är huvudintressent i bolaget.\n\nStyrelse: dir. E. Brändström, dir. Folke\nHellstedt, dir. Gösta Runnquist, dir.\nAxel Wästfelt.\n\nVerkst. dir.: Gösta Runnquist.\n\nTekn. dir.: Karl Granfors.\n\nFörsäljn.-chef: N. v. Holten.\n\növering.: John Svensson.\n\nEkonomichef: C.-G. Aspegren.\n\n(Jfr annons nr 76.)\n\n\"Svenska Stålsolffabriken, Borås.\n\nSe AB. Hugo Hennig, Borås.\n\n\"Svenska Stängselnäts AB., Malmö.\n\nTillverkar galvaniserat stängselnät, s. k.\nhönsnät, galvaniserad slät och korrugerad\nplåt, pannplåt m. m., utför\nlegogalvanise-ring.\n\nKontor o. ensamförsälj.: Edw. H.\nTho-mée AB., Malmö, Engelbrektsg. 11.\nTelegr.-adr.: Edwin, Malmö. Telefon:\n»Tho-mée’s Järn». Postgiro: 38788.\n\nAkt.-kap.: 432,000 kr. Antal\nindustriarb.: 40. Tillv.-värde pr år: 2,500,000 kr.\n— Bolaget grundat 1897.",
    "structured": {
        "1": {
            "name": "Svenska Sportfabriks AB.",
            "location": "Stockholm",
            "business": "Tillverkar badmintonbollar.",
            "products": "Varumärken: »Oyklon», »Komet», »Indian» o. »Svalan».",
            "contact": {
                "office": "Kungsg. 48",
                "phone": [
                    "117395",
                    "117360"
                ],
                "postgiro": "159797"
            },
            "financials": {
                "capital": "15,000 kr",
                "employees": {
                    "industriarb": 20
                },
                "annual_turnover": "75,000 kr"
            },
            "foundation_year": 1940,
            "board": [
                {
                    "name": "Ludv. T. Hagberg",
                    "role": "Verkst. dir."
                }
            ]
        },
        "2": {
            "name": "Svenska Stansknivfabriken",
            "location": "Örebro",
            "business": "Tillverkar stansknivar för olika ändamål.",
            "contact": {
                "phone": "11763",
                "postgiro": "70896",
                "sales_offices": [
                    {
                        "location": "AB. Praktiska Nyheter, Linnég. 51",
                        "phone": "622208"
                    }
                ]
            },
            "financials": {
                "employees": {
                    "industriarb": 5
                },
                "annual_production_value": "35,000 kr"
            },
            "foundation_year": 1915,
            "owners": [
                "fabr. Harry Andersson"
            ]
        },
        "3": {
            "name": "AB. Svenska Strebelverken",
            "location": "Västervik",
            "business": "Gjuteri och mek. verkstad.",
            "products": "Tillverkar värmeledningspannor samt specialpannor för eldning med koks, stokerkol, ved och olja. Varumärke: »Strebel».",
            "contact": {
                "telegraph": "Strebel, Västervik",
                "phone": [
                    "1150",
                    "1111"
                ],
                "postgiro": "82450",
                "sales_offices": [
                    {
                        "location": "AB. Gustavsbergs Fabriker, Gustavsberg",
                        "phone": "»Porslinsfabriken»"
                    }
                ]
            },
            "financials": {
                "capital": "200,000 kr",
                "employees": {
                    "industriarb": 90
                },
                "annual_turnover": "1,500,000 kr"
            },
            "foundation_year": 1924,
            "current_name_year": 1933,
            "board": [
                {
                    "name": "Pehr Carlson",
                    "role": "Styrelse dir."
                },
                {
                    "name": "Yngve Schartau",
                    "role": "adv."
                }
            ],
            "director": "Åke Gylling",
            "managing_director": "G. Miinster",
            "sales_manager": "Jörgen Drachmann"
        },
        "4": {
            "name": "Svenska Strumpfabriks AB.",
            "location": "Linköping",
            "business": "Strumpfabrik i Partille.",
            "products": "Tillverkar damstrumpor.",
            "contact": {
                "phone": "»Ullholms», Linköping"
            },
            "financials": {
                "capital": "250,000 kr",
                "employees": {
                    "industriarb": 30
                },
                "annual_turnover": "500,000 kr"
            },
            "foundation_year": 1940,
            "owners": [
                "AB. K. A. Ullholm"
            ],
            "board": [
                {
                    "name": "K. A. Ullholm",
                    "role": "Styrelse dir."
                },
                {
                    "name": "Wald. Johanson",
                    "role": "disp."
                },
                {
                    "name": "Bengt Lindström",
                    "role": "försäljn.-chef"
                }
            ],
            "manager": "K. A. Ullholm"
        },
        "5": {
            "name": "AB. Svenska Stållinor",
            "location": "Kristinehamn",
            "predecessor": "Hellefors Bruks AB., Hällefors"
        },
        "6": {
            "name": "Svenska Stålpressnings AB.",
            "location": "Olofström",
            "business": "Press verk, plåt- och bleckslageri, galva-niseringsverk samt mek. verkstad vid Olof",
            "products": "ström (Blekinge l.). Tillverkar emaljerade plåtbadkar, kok-, hushålls- och sanitetskärl samt disklådor och diskbänksbeklädnader av rostfri stålplåt, bykgrytor och vattenvärmarq, tvätt apparater, foder kokare, mullskopor, separatordelar, gjuteriskänkar, automobil-materiel m. m. Bolaget idkar jämväl lantbruk.",
            "contact": {
                "office": "Olof ström",
                "phone": "»Bruket», Olofström",
                "postgiro": "7841"
            },
            "financials": {
                "capital": "1,500,000 kr",
                "employees": {
                    "industriarb": 1,
                    " 1": "200"
                }
            },
            "foundation_year": 1887,
            "board": [
                {
                    "name": "E. Brändström",
                    "role": "dir."
                },
                {
                    "name": "Folke Hellstedt",
                    "role": "dir."
                },
                {
                    "name": "Gösta Runnquist",
                    "role": "dir."
                },
                {
                    "name": "Axel Wästfelt",
                    "role": "dir."
                },
                {
                    "name": "Gösta Runnquist",
                    "role": "Verkst. dir."
                },
                {
                    "name": "Karl Granfors",
                    "role": "Tekn. dir."
                },
                {
                    "name": "N. v. Holten",
                    "role": "Försäljn.-chef"
                },
                {
                    "name": "John Svensson",
                    "role": "övering."
                }
            ]
        },
        "7": {
            "name": "Svenska Stålsolffabriken",
            "location": "Borås",
            "predecessor": "AB. Hugo Hennig, Borås"
        },
        "8": {
            "name": "Svenska Stängselnäts AB.",
            "location": "Malmö",
            "business": "Tillverkar galvaniserat stängselnät, s. k. hönsnät, galvaniserad slät och korrugerad plåt, pannplåt m. m., utför legogalvanise-ring.",
            "contact": {
                "office": "Edw. H. Thomée AB., Malmö, Engelbrektsg. 11",
                "phone": "»Thomée’s Järn»",
                "postgiro": "38788"
            },
            "financials": {
                "capital": "432,000 kr",
                "employees": {
                    "industriarb": 40
                },
                "annual_turnover": "2,500,000 kr"
            },
            "foundation_year": 1897
        }
    }
}