{
    "original": "Ldstfabriken-\n\ni—Löfudden\n\nLästfabriken Winkle AB.,\n\nÖrebro.\n\nTillverkar läster för skofabrikation,\nträsulor, klackar, skoblock och\ncelluloid-fylläster. Firman driver även\nengros-handel med stansknivar och träklackar.\n\nTelegr.-adr.: Lästfabriken, Örebro.\nTelefon: 14170 o. 18270. Postgiro: 176336.\n\nAkt.-kap.: 50,000 kr. Antal\nindustriarb.: 37. — Bolaget grundat 1923.\n\nStyrelse o. verkst. dir.: ing. Eugen\nWinkle.\n\n*AB. Lödöse Yarf, Lödöse.\n\nSkeppsvarv, mek. verkstad och gjuteri\nvid Lödöse (Älvsb. l.). Utför\nnybyggnader och reparationer av fartyg samt\ngrov-plåtsarbeten.\n\nKontor: Lödöse. Telefon: 11 o. 17.\nPostgiro: 21497.\n\nAkt.-kap.: 702,000 kr. Antal\nindustriarb.; 150. Tillv.-värde pr år: 1,500,000 kr.\n— Bolaget grundat 1899.\n\nStyrelse: kammarh. G. A. Bratt (ordf.),\ndir. Torsten Petterson, dir. C. Lennart\nReuterskiöld.\n\nVerkst. dir.: ing. H. Rich. Elf ström.\n\nDir.: Erik Petterson.\n\nAB. a. P. Löfbergs Pianofabrik,\n\nStockholm.\n\nTillverkar pianinon, flyglar och\nkammar-pianon.\n\nKontor o. utställning: Malmskillnadsg.\n34 A. Telefon: 109439 o. 200695.\nPostgiro: 50133.\n\nAkt.-kap.: 75,000 kr. Arb.-antal: 18.\nTillv.-värde pr år: 200,000 kr. — Firman\netabl. 1881, bolag 1912.\n\nStyrelse: bankdir. Allan Carlsten\n(ordf.), dir. Martin Ström, fru Agnes\nSvanström.\n\nVerkst. direktörer: Agnes Svanström o.\nMartin Ström.\n\nAB. Löfgren &amp; Wahlberg,\n\nSkellefteå.\n\nMek. verkstad. Tillverkar hydrauliska\nbiltippningsanordningar och domkrafter,\nprofilbockningsmaskiner,\navfettningstan-kar, verktyg m. m.\n\nTelefon: 12455. Repr.: Amerikanska\nGummi AB., Stockholm o. Malmö.\n\nAkt.-kap.: 55,000 kr. Antal\nindustriarb.: 60. Tillv.-värde pr år: 300,000 kr.\n— Firman etabl. 1934, bolag 1939.\n\nVerkst. dir.: William Löfgren.\n\n35\n\n\"Gust. Löfquist AB., Visby.\n\nTapetserare- och snickeriverkstäder.\nTillverkar möbler. Bolaget har egna\nmöbelaffärer i Visby, Hemse och Slite.\n\nKontor: Visby. Telefon:\n»Löfquist-Möbler». Postgiro: 189083. - Akt.-kap.:\n44,600 kr. Antal industriarb.: 12. —\nFirman etabl. 1895, bolag 1940.\n\nStyrelse: dir. Gustaf Löfquist (ordf.),\nfru Siv Belfrage, disp. Anders\nMagnusson, fru Anna-Greta Mellgren, fru\nGunvor Rosengren.\n\nVerkst. dir.: Gustaf Löfquist.\n\nDisp.: Anders Magnusson.\n\n*AB. Löfsko, Jönköping.\n\nTillverkar hand- och maskinsydda\nlyx-och promenadskodon. Specialitet:\nhand-sydda, rand-, ago- och vändsydda\nskodon. Varumärken: »Löfsko», »Nordsko»\no. »Eksko».\n\nTelegr.-adr. o. telefon: Löfsko,\nJönköping. Postgiro: 11531. Representanter: i\nJönköping: Löf sko-Nordsko Handels- &amp;\nFabriks AB., telefon: »Löfsko»; i\nStockholm: Löfsko-Nordsko Handels- &amp; Fabriks\nAB., Grevtureg. 13 A, telefon: 629382\n—84.\n\nAkt.-kap.: 675,000 kr. Antal\nindustriarb.: 140. — Bolaget grundat 1909 under\nnamn AB. John Löfquist Skomanufaktur,\nnuv. namn 1945.\n\nStyrelse: disp. Harald Westerlund\n(ordf.), disp. Lennart Eklöf (v. ordf.),\nmodellör Bengt Eklöf, konsulinnan Elsa\nEklöf, dir. Thure Grafström.\n\nVerkst. dir.: Lennart Eklöf.\n\nKontorschef: Gustaf Alm.\n\n*dohn Löfström AB., Göteborg.\n\nTrikåfabrik. Tillverkar\ncharmeuseväv-nader och damunderkläder.\n\nKontor: Stampg. 52. Telegr.-adr.:\nSilk-mill, Göteborg. Telefon: 153020.\nPostgiro: 40239.\n\nAkt.-kap.: 140,000 kr. Antal\nindustriarb.: 21. Tillv.-värde pr år: 350,000 kr.\n— Bolaget grundat 1929.\n\nStyrelse: dir. John Löfström, fru\nNanny Löfström, fru Märta Sjösten.\n\nVerkst. dir.: John Löfström.\n\n* Löf uddens AB., Härnösand.\n\nSågverk och hyvleri vid Löfudden,\nHärnösand. Tillverkar sågade och\nhyvlade trävaror.\n\nTelegr.-adr.: Löfudden, Härnösand.\nTelefon: 2262 o. 2712. Postgiro: 81185.\n\nAkt.-kap.: 264,000 kr. Antal industri-\n\n3*\n\n23",
    "structured": {
        "1": {
            "name": "Lästfabriken Winkle AB",
            "location": "Örebro",
            "business": "Tillverkar läster för skofabrikation, träsulor, klackar, skoblock och celluloid-fylläster. Driver även engros-handel med stansknivar och träklackar.",
            "contact": {
                "office": "Lästfabriken, Örebro",
                "phone": [
                    "14170",
                    "18270"
                ],
                "postgiro": "176336"
            },
            "financials": {
                "capital": "50,000 kr",
                "employees": {
                    "industriarb": 37
                },
                "annual_turnover": "N/A",
                "annual_production_value": "N/A"
            },
            "foundation_year": 1923,
            "board": [
                {
                    "name": "ing. Eugen Winkle",
                    "role": "Styrelse o. verkst. dir."
                }
            ],
            "directors": {
                "director": "N/A",
                "managing_director": "N/A",
                "sales_manager": "N/A",
                "manager": "N/A"
            }
        },
        "2": {
            "name": "AB. Lödöse Yarf",
            "location": "Lödöse",
            "business": "Utför nybyggnader och reparationer av fartyg samt grov-plåtsarbeten.",
            "contact": {
                "office": "Lödöse",
                "phone": [
                    "11",
                    "17"
                ],
                "postgiro": "21497"
            },
            "financials": {
                "capital": "702,000 kr",
                "employees": {
                    "industriarb": 150
                },
                "annual_turnover": "1,500,000 kr",
                "annual_production_value": "1,500,000 kr"
            },
            "foundation_year": 1899,
            "board": [
                {
                    "name": "kammarh. G. A. Bratt",
                    "role": "Styrelse"
                },
                {
                    "name": "Torsten Petterson",
                    "role": "Styrelse"
                },
                {
                    "name": "C. Lennart Reuterskiöld",
                    "role": "Styrelse"
                }
            ],
            "directors": {
                "director": "Erik Petterson",
                "managing_director": "ing. H. Rich. Elfström",
                "sales_manager": "N/A",
                "manager": "N/A"
            }
        },
        "3": {
            "name": "AB. a. P. Löfbergs Pianofabrik",
            "location": "Stockholm",
            "business": "Tillverkar pianinon, flyglar och kammar-pianon.",
            "contact": {
                "office": "Malmskillnadsg. 34 A",
                "phone": [
                    "109439",
                    "200695"
                ],
                "postgiro": "50133"
            },
            "financials": {
                "capital": "75,000 kr",
                "employees": {
                    "Arb.-antal": 18
                },
                "annual_turnover": "200,000 kr",
                "annual_production_value": "200,000 kr"
            },
            "foundation_year": 1881,
            "current_name_year": 1912,
            "board": [
                {
                    "name": "bankdir. Allan Carlsten",
                    "role": "Styrelse"
                },
                {
                    "name": "Martin Ström",
                    "role": "Styrelse"
                },
                {
                    "name": "fru Agnes Svanström",
                    "role": "Styrelse"
                }
            ],
            "directors": {
                "director": "N/A",
                "managing_director": "Agnes Svanström o. Martin Ström",
                "sales_manager": "N/A",
                "manager": "N/A"
            }
        },
        "4": {
            "name": "AB. Löfgren &amp; Wahlberg",
            "location": "Skellefteå",
            "business": "Tillverkar hydrauliska biltippningsanordningar och domkrafter, profilbockningsmaskiner, avfettningstan-kar, verktyg m. m.",
            "contact": {
                "phone": "12455"
            },
            "financials": {
                "capital": "55,000 kr",
                "employees": {
                    "industriarb": 60
                },
                "annual_turnover": "300,000 kr",
                "annual_production_value": "300,000 kr"
            },
            "foundation_year": 1934,
            "board": [],
            "directors": {
                "director": "N/A",
                "managing_director": "William Löfgren",
                "sales_manager": "N/A",
                "manager": "N/A"
            }
        },
        "5": {
            "name": "Gust. Löfquist AB",
            "location": "Visby",
            "business": "Tillverkar möbler.",
            "contact": {
                "office": "Visby"
            },
            "financials": {
                "capital": "44,600 kr",
                "employees": {
                    "industriarb": 12
                },
                "annual_turnover": "N/A",
                "annual_production_value": "N/A"
            },
            "foundation_year": 1895,
            "current_name_year": 1940,
            "board": [
                {
                    "name": "dir. Gustaf Löfquist",
                    "role": "Styrelse"
                },
                {
                    "name": "fru Siv Belfrage",
                    "role": "Styrelse"
                },
                {
                    "name": "disp. Anders Magnusson",
                    "role": "Styrelse"
                },
                {
                    "name": "fru Anna-Greta Mellgren",
                    "role": "Styrelse"
                },
                {
                    "name": "fru Gunvor Rosengren",
                    "role": "Styrelse"
                }
            ],
            "directors": {
                "director": "Gustaf Löfquist",
                "managing_director": "Gustaf Löfquist",
                "sales_manager": "N/A",
                "manager": "N/A"
            }
        },
        "6": {
            "name": "AB. Löfsko",
            "location": "Jönköping",
            "business": "Tillverkar hand- och maskinsydda lyx-och promenadskodon. Specialitet: hand-sydda, rand-, ago- och vändsydda skodon. Varumärken: »Löfsko», »Nordsko» o. »Eksko».",
            "contact": {
                "office": "Löfsko, Jönköping",
                "phone": [
                    "Löfsko",
                    "Löfsko-Nordsko Handels- & Fabriks AB., telefon: »Löfsko»"
                ]
            },
            "financials": {
                "capital": "675,000 kr",
                "employees": {
                    "industriarb": 140
                },
                "annual_turnover": "N/A",
                "annual_production_value": "N/A"
            },
            "foundation_year": 1909,
            "current_name_year": 1945,
            "board": [
                {
                    "name": "disp. Harald Westerlund",
                    "role": "Styrelse"
                },
                {
                    "name": "disp. Lennart Eklöf",
                    "role": "Styrelse"
                },
                {
                    "name": "modellör Bengt Eklöf",
                    "role": "Styrelse"
                },
                {
                    "name": "konsulinnan Elsa Eklöf",
                    "role": "Styrelse"
                },
                {
                    "name": "dir. Thure Grafström",
                    "role": "Styrelse"
                }
            ],
            "directors": {
                "director": "N/A",
                "managing_director": "Lennart Eklöf",
                "sales_manager": "N/A",
                "manager": "Gustaf Alm"
            }
        },
        "7": {
            "name": "Johu Löfström AB",
            "location": "Göteborg",
            "business": "Tillverkar charmeuseväv-nader och damunderkläder.",
            "contact": {
                "office": "Stampg. 52",
                "phone": "153020",
                "postgiro": "40239"
            },
            "financials": {
                "capital": "140,000 kr",
                "employees": {
                    "industriarb": 21
                },
                "annual_turnover": "350,000 kr",
                "annual_production_value": "350,000 kr"
            },
            "foundation_year": 1929,
            "board": [
                {
                    "name": "dir. John Löfström",
                    "role": "Styrelse"
                },
                {
                    "name": "fru Nanny Löfström",
                    "role": "Styrelse"
                },
                {
                    "name": "fru Märta Sjösten",
                    "role": "Styrelse"
                }
            ],
            "directors": {
                "director": "John Löfström",
                "managing_director": "John Löfström",
                "sales_manager": "N/A",
                "manager": "N/A"
            }
        },
        "8": {
            "name": "Löfuddens AB",
            "location": "Härnösand",
            "business": "Tillverkar sågade och hyvlade trävaror.",
            "contact": {
                "office": "Löfudden, Härnösand",
                "phone": [
                    "2262",
                    "2712"
                ],
                "postgiro": "81185"
            },
            "financials": {
                "capital": "264,000 kr",
                "employees": {
                    "industriarb": "N/A"
                },
                "annual_turnover": "N/A",
                "annual_production_value": "N/A"
            },
            "foundation_year": "N/A",
            "board": [
                {
                    "name": "N/A",
                    "role": "N/A"
                }
            ],
            "directors": {
                "director": "N/A",
                "managing_director": "N/A",
                "sales_manager": "N/A",
                "manager": "N/A"
            }
        }
    }
}