{
    "original": "GranhuUaviken—Gren\n\n\"Grankullavikens Sågverk, B öda.\n\nSe AB. Statens Skogsindustrier,\nStockholm.\n\n\"Gransholms AB., Gemla.\n\nFinpappersbruk och\npappersförädlings-fabriker vid Gransholm, Gemla (Kronob.\n\nTillverkar finare tryck-, broschyr-,\npost-, skriv-, skrivmaskins- och\nduplice-ringspapper, läsk- och filtrerpapper,\npa-peterier, kasetter, postblock, kuvert,\nmynt-, prov- och korsbandspåsar,\npappersvaror för skolbruk m. m.\n\nHuvudkontor: Gransholms Bruk,\nGemla. Telegr.-adr.: Gransholm, Växjö.\nTelefon: Växjö, »Gransholms Bruk».\nPostgiro: 8343. Avd.-kontor: Stockholm,\nKungstensg. 7, telefon: 104044.\n\nAkt.-kap.: 687,500 kr. Antal\nindustriarb.: 100. Årstillv.: 1,500 ton finpapper\noch förädlade pappersvaror. —\nPappersbruket anlagt 1790, bolaget grundat 1901.\n\nStyrelse: bruksäg. Arvid W. Myhrman\n(ordf.), ing. Magnus Myhrman, fru M.\nMyhrman, kapten L. F. Wiik,\növerste-löjtn. Filip Wijkström.\n\nVerJcst. dir.: Arvid W. Myhrman.\n\nGranstrand &amp; Co., Gnosjö.\n\nSe Metallbolaget Granstrand &amp; Co.,\nGnosjö.\n\n\"Granstrands Möbelfabrik,\n\nSkillingaryd.\n\nTillverkar möbler, speciellt\nstoppstommar och fåtöljstommar vid fabrik i\nSkil-lingaryd (Jönköp. l.).\n\nTelefon: 146. Postgiro: 172833. —\nArb.-antal: 10. — Firman grundad 1938.\n\nÄgare o. chef: fabr. Harry Granstrand.\n\n\"Grantorpets Fabriks AB., Västervik.\n\nKarosserifabrik. Tillverkar karosserier\nför lastbilar, skåpvagnar, möbel\ntransportvagnar, brandbilar och ambulanser m. m.\n\nTelegr.-adr.: Gefa, Västervik. Telefon:\n1340 o. 1040. Postgiro: 141291.\n\nAkt.-kap.: 160,000 kr. Antal\nindustriarb.: 80. Tillv.-värde pr år: 1,500,000 kr.\n— Firman etabl. 1937.\n\nStyrelse: hamnkamrer Hans Norberg,\ndisp. Eric Paues, dir. Edvin Söderlind.\n\nFabriksledning: E. Paues.\n\nH. Crauers, Partille.\n\nSe Aronsdals Färgeri, H. Grauers,\nPartille.\n\nCravarnes Konservfabrik, Bröderna\nSanne &amp; Co., Gravarne.\n\nTillverkar sillkonserver och kaviar vid\nfabrik i Gravarne (Göteb. o. Bohus l.).\n\nTelegr.-adr.: Gekonserv, Gravarne.\nTelefon: 113. Postgiro: 146305. — Antal\nindustriarb.: 25. Tillv.-värde pr år:\n300,000 kr. — Firman etabl. 1938.\n\nChef: fabr. J. Wärner Sanne.\n\n*Rudolph Grave AB., Stockholm.\n\nTillverkar laboratorieapparater för\ntekn. och vetenskapliga ändamål såsom\ntermometrar, pyrometrar, luftpumpar,\ntorkskåp etc. samt elektr.\nlaboratorieugnar.\n\nKontor: Malmskillnadsg. 48 O.\nTelegr.-adr.: Grave, Stockholm. Telefon: 233780.\nPostgiro: 1456.\n\nAkt.-kap.: 400,000 kr. Antal\nindustriarb.: 35. Tillv.-värde pr år: 260,000 kr.\n— Firman etabl. 1874, bolag 1931.\n\nStyrelse: fabr. Rudolph Grave, disp.\nRud. G. Grave.\n\nVerkst. dir.: Rudolph Grave.\n\nGrawensteinerfabriken AB.,\n\nStockholm.\n\nTillverkar alkoholsvaga lättviner, safter\nsamt likörextrakter. Varumärke: »Pubac»\n(punschextrakt).\n\nKontor: Grevg. 14. Telefon: 622526.\nPostgiro: 4571. — Akt.-kap.: 35,000 kr.\nArb.-antal: 9. Tillv.-värde pr år: 180,000\nkr. — Firman etabl. 1909, bolag 1940.\n\nStyrelse o. verkst. dir.: Gösta\nHerr-mann.\n\n*Greflunda Tegelbruk, Skarhult\n\nTillverkar tegel och tegelrör vid\ntegelbruk i Grevlunda, Skarhult (Malmöh. l.).\n\nTelefon: Hurva 6. — Antal\nindustriarb.: 10. Årstillv.: 0,6 milj. st. tegelvaror.\n\nÄgare o. chef: dir. Magnus Jönsson.\n\n*Creisz &amp; Söner, Norrtälje.\n\nSe Norrtelje Gjuteri, Greisz &amp; Söner,\nNorrtälje.\n\n\"AB. Gren &amp; Anderssons\nBleckkärls-fabrik, Sävsjö.\n\nBleckkärlsfabrik i Sävsjö (Jönköp. l.).\nTillverkar bleckkärl och\nhusgerådsartik-lar såsom transportflaskor,\nfotogenkannor, dunkar och cisterner, krönta\nmålkärl och oljemått, trädgårdskannor, hus-",
    "structured": {
        "1": {
            "name": "Gransholms AB.",
            "location": "Gemla",
            "business": "Finpappersbruk och pappersförädlings-fabriker",
            "products": "Tillverkar finare tryck-, broschyr-, post-, skriv-, skrivmaskins- och duplice-ringspapper, läsk- och filtrerpapper, pa-peterier, kasetter, postblock, kuvert, mynt-, prov- och korsbandspåsar, pappersvaror för skolbruk m. m.",
            "contact": {
                "office": "Gransholms Bruk, Gemla",
                "phone": [
                    "Växjö, »Gransholms Bruk»"
                ],
                "postgiro": "8343",
                "head_office": "Gransholms Bruk, Gemla",
                "sales_offices": [
                    {
                        "location": "Stockholm",
                        "phone": "104044"
                    }
                ],
                "telegraph": "Gransholm, Växjö",
                "factory_office": "Gransholms Bruk, Gemla",
                "factory_phone": "Not available"
            },
            "financials": {
                "capital": "687,500 kr",
                "employees": {
                    "industriarb": 100
                },
                "annual_turnover": "Not available",
                "annual_production_value": "1,500 ton finpapper"
            },
            "foundation_year": 1901,
            "board": [
                {
                    "name": "Arvid W. Myhrman",
                    "role": "ordf."
                },
                {
                    "name": "Magnus Myhrman",
                    "role": "Not available"
                },
                {
                    "name": "fru M. Myhrman",
                    "role": "Not available"
                },
                {
                    "name": "kapten L. F. Wiik",
                    "role": "Not available"
                },
                {
                    "name": "överste-löjtn. Filip Wijkström",
                    "role": "Not available"
                }
            ],
            "current_name_year": "Not available"
        },
        "2": {
            "name": "Granstrand & Co.",
            "location": "Gnosjö",
            "business": "Not available"
        },
        "3": {
            "name": "Granstrands Möbelfabrik",
            "location": "Skillingaryd",
            "business": "Tillverkar möbler, speciellt stoppstommar och fåtöljstommar"
        },
        "4": {
            "name": "Grantorpets Fabriks AB.",
            "location": "Västervik",
            "business": "Karosserifabrik",
            "products": "Tillverkar karosserier för lastbilar, skåpvagnar, möbel transportvagnar, brandbilar och ambulanser m. m.",
            "contact": {
                "office": "Not available",
                "phone": [
                    "1340",
                    "1040"
                ],
                "postgiro": "141291",
                "head_office": "Not available",
                "sales_offices": [],
                "telegraph": "Gefa, Västervik",
                "factory_office": "Not available",
                "factory_phone": "Not available"
            },
            "financials": {
                "capital": "160,000 kr",
                "employees": {
                    "industriarb": 80
                },
                "annual_turnover": "1,500,000 kr",
                "annual_production_value": "Not available"
            },
            "foundation_year": 1937,
            "board": [
                {
                    "name": "hamnkamrer Hans Norberg",
                    "role": "Not available"
                },
                {
                    "name": "disp. Eric Paues",
                    "role": "Not available"
                },
                {
                    "name": "dir. Edvin Söderlind",
                    "role": "Not available"
                }
            ],
            "current_name_year": "Not available"
        },
        "5": {
            "name": "Cravarnes Konservfabrik, Bröderna Sanne & Co.",
            "location": "Gravarne",
            "business": "Tillverkar sillkonserver och kaviar"
        },
        "6": {
            "name": "Rudolph Grave AB.",
            "location": "Stockholm",
            "business": "Tillverkar laboratorieapparater för tekn. och vetenskapliga ändamål"
        },
        "7": {
            "name": "Grawensteinerfabriken AB.",
            "location": "Stockholm",
            "business": "Tillverkar alkoholsvaga lättviner, safter samt likörextrakter",
            "contact": {
                "office": "Grevg. 14",
                "phone": [
                    "622526"
                ],
                "postgiro": "4571",
                "head_office": "Not available",
                "sales_offices": [],
                "telegraph": "Not available",
                "factory_office": "Not available",
                "factory_phone": "Not available"
            },
            "financials": {
                "capital": "35,000 kr",
                "employees": {
                    "industriarb": 9
                },
                "annual_turnover": "Not available",
                "annual_production_value": "180,000 kr"
            },
            "foundation_year": 1940,
            "board": [],
            "current_name_year": "Not available"
        },
        "8": {
            "name": "Greflunda Tegelbruk",
            "location": "Skarhult",
            "business": "Tillverkar tegel och tegelrör"
        },
        "9": {
            "name": "AB. Gren & Anderssons Bleckkärlsfabrik",
            "location": "Sävsjö",
            "business": "Bleckkärlsfabrik",
            "products": "Tillverkar bleckkärl och husgerådsartiklar såsom transportflaskor, fotogenkannor, dunkar och cisterner, krönta målkärl och oljemått, trädgårdskannor, hus-."
        }
    }
}