{
    "original": "Dahlkarlshytte—• Dala\n\n*\tDahl kar Ishytte AB., Ludvika.\n\nKalkugn, dolomitbrytning samt elektr.\nvattenkraftstation vid Dalkarlshyttan\n(Örebro l.). Bolaget idkar jämväl\njordbruk, sågverks- och kvarnrörelse.\n\nHuvudkontor: Ludvika. Telegr.-adr.:\nDalkarlshytta, Ludvika. Telefon:\nLudvika 2006—09 o. Lindesberg 18 o. 1019.\nPostgiro: 77759.\n\nAkt.-kap.: 700,000 kr. Antal\nindustriarb.: 70. — Bruket anlagt på 1500-talet,\nnuv! bolag grundat 1898.\n\nStyrelse: majoren frih. Carl S:spn\nLeijonhufvud (ordf.), överstelöjtn. frih.\nGustaf v. Friesendorff (v. ordf.), adv.\nHugo Stenbeck.\n\nVerkst. dir. o. disp.: B. Stein.\n\nAB. Dahlqvist &amp; Co., Borås.\n\nSängfabrik. Tillverkar turistsängar,\nsoffor, schäslonger samt ottomaner med\nrostfria ståltrådsbottnar.\n\nTelefon: 10830. Postgiro: 10630. —\nAkt.-kap.: 40,000 kr. Antal industriarb.:\n30. — Firman etabl. 1920, bolag 1932.\n\nStyrelse: disp. Eric V. Magnusson\n(ordf.), byggm. Arvid Andersson.\n\nDisp.: Torsten Arvidson.\n\nKontorschef: Bengt Arvidson.\n\n*Dahlqvist &amp; Co., Snickerifabrik,\n\nBurträsk.\n\nTillverkar fönster, dörrar och\ninredningar samt överbyggnader för lastbilar\nvid fabrik i Burträsk (Västerb. l.).\n\nTelefon: 59. — Antal industriarb.: 15.\nTillv.-värde pr år: 200,000 kr. — Firman\netabl. 1921.\n\nÄgare o. chef: fabr. Karl Viktor\nDahlqvist.\n\nHans Dahlstedts Kassaskåpsfabrik,\n\nEskilstuna.\n\nKassaskåpsfabrik i Kungsör\n(Västmanl. l.). Tillverkar kassaskåp,\narkiv-och inmurningsskåp, förvaringsskåp,\nhyllor och inredningar i stål, brand-,\narkiv-och kassavalvsdörrar m. m. Varumärke:\n»Hadak».\n\nKontor: Eskilstuna. Telefon: 35054 o.\n34382. Postgiro: 264261. — Antal\nindustriarb.: 20. Tillv.-värde pr år: 350,000\nkr, — Firman etabl. 1944.\n\nÄgare o. chef: fabr. Hans Dahlstedt.\n\n*\tDahlström &amp; Löfgren, Motala\n\nverkstad.\n\nTillverkar gjutmodeller, karosserier för\n\nrälsbussar och skåpvagnar m. m. vid\nfabrik i Motala verkstad (Östergötl. l.).\n\nTelefon: Motala 219. Postgiro: 28358.\n\n—\tAntal industriarb.: 26. — Firman\netabl. 1908.\n\nÄgare: fabr. Oscar Löfgrens sterbhus.\nChef: Olof Löfgren.\n\nAB. Dakrysol, Malmö.\n\nKem. teknisk fabrik. Tillverkar\nhårvatten. Varumärke: »Dakrysol».\n\nKontor: Slussg. 1. Telefon: 10526.\n\n—\tAkt.-kap.: 30,000 kr. Arb.-antal: 10.\nTillv.-värde pr år: 120,000 kr. — Bolaget\ngrundat 1932.\n\nVerkst. dir.: kamrer Fredrik Jonson.\n\n*Dala Flöda Snickerifabrik,\n\nDala-Floda.\n\nSe Axel Eriksson &amp; Co. Snickeri AB.,\nDala-Floda.\n\nAB. Dala Mek. Spisbrödsbageri,\n\nSäter.\n\nTillverkar spisbröd och knäckebröd.\n\nTelegr.-adr.: Dalabageriet, Säter.\nTelefon: »Säterbröd». Postgiro: 21480. Repr.\ni Gävle: Ludvig Ericsson &amp; Co. AB.,\ntelefon: 1113.\n\nAkt.-kap.: 200,000 kr. Antal\nindustriarb.: 30. Årstillv.: 1,000,000 kg bröd. —\nBolaget grundat 1902.\n\nStyrelse: bankkamrer Johannes\nOhlsson (ordf.), disp. J. Gråhns, fabr.\nBernhard Johansson, byggm. Evald\nLindström.\n\nVerkst. dir.: J. Gråhns.\n\nAB. Dala Skinnindustri, Säter.\n\nTillverkar handskar, skinnkläder,\nportföljer, shoppingväskor, sadelskydd för\ncyklar m. m.\n\nTelefon: 203. Postgiro: 84767. —\nAkt.-kap.: 50,000 kr. Antal industriarb.: 15.\nTillv.-värde pr år: 225,000 kr. — Firman\netabl. 1931, bolag 1938.\n\nDisp.: E. Ljusterdal.\n\nDala Spegelfabrik AB., Falun.\n\nTillverkar spegelglas, speglar samt\nramlister och ramar.\n\nTelefon: 3100. Postgiro: 164173. Repr.\ni Stockholm: Harald Swedberg AB.,\nBö-belnsg. 16 B; telefon: 305650.\n\nAkt.-kap.: 50,600 kr. Antal\nindustriarb.: 15. Tillv.-värde pr år: 160,000 kr.\n— Bolaget grundat 1939.\n\nVerkst. dir.: Nestor Eriksson.",
    "structured": {
        "1": {
            "name": "AB. Dahlkarlshytte",
            "location": "Ludvika",
            "business": "Kalkugn, dolomitbrytning samt elektr. vattenkraftstation vid Dalkarlshyttan (Örebro l.). Bolaget idkar jämväl jordbruk, sågverks- och kvarnrörelse.",
            "contact": {
                "office": "Ludvika",
                "phone": [
                    "2006-09",
                    "18",
                    "1019"
                ],
                "postgiro": "77759",
                "head_office": "Dalkarlshytta, Ludvika",
                "telegraph": "Dalkarlshytta, Ludvika",
                "factory_phone": "700,000 kr",
                "sales_offices": [
                    {
                        "location": "Ludvika 2006-09",
                        "phone": "2006-09"
                    },
                    {
                        "location": "Lindesberg 18",
                        "phone": "18"
                    },
                    {
                        "location": "Lindesberg 1019",
                        "phone": "1019"
                    }
                ]
            },
            "financials": {
                "capital": "700,000 kr",
                "employees": {
                    "industriarb": 70
                },
                "annual_turnover": "700,000 kr",
                "annual_production_value": "1500-talet"
            },
            "foundation_year": 1898,
            "board": [
                {
                    "name": "majoren frih. Carl S:spn Leijonhufvud",
                    "role": "ordf."
                },
                {
                    "name": "överstelöjtn. frih. Gustaf v. Friesendorff",
                    "role": "v. ordf."
                },
                {
                    "name": "adv. Hugo Stenbeck",
                    "role": null
                }
            ]
        },
        "2": {
            "name": "AB. Dahlqvist & Co.",
            "location": "Borås",
            "business": "Sängfabrik. Tillverkar turistsängar, soffor, schäslonger samt ottomaner med rostfria ståltrådsbottnar.",
            "contact": {
                "phone": [
                    "10830"
                ],
                "postgiro": "10630"
            },
            "financials": {
                "capital": "40,000 kr",
                "employees": {
                    "industriarb": 30
                }
            },
            "foundation_year": 1920,
            "board": [
                {
                    "name": "disp. Eric V. Magnusson",
                    "role": "ordf."
                },
                {
                    "name": "byggm. Arvid Andersson",
                    "role": null
                }
            ],
            "director": "Torsten Arvidson",
            "manager": "Bengt Arvidson"
        },
        "3": {
            "name": "Dahlqvist & Co.",
            "location": "Burträsk",
            "business": "Tillverkar fönster, dörrar och inredningar samt överbyggnader för lastbilar vid fabrik i Burträsk (Västerb. l.).",
            "contact": {
                "phone": [
                    "59"
                ]
            },
            "financials": {
                "employees": {
                    "industriarb": 15
                },
                "annual_production_value": "200,000 kr"
            },
            "foundation_year": 1921,
            "manager": "Karl Viktor Dahlqvist"
        },
        "4": {
            "name": "Hans Dahlstedts Kassaskåpsfabrik",
            "location": "Eskilstuna",
            "business": "Kassaskåpsfabrik i Kungsör (Västmanl. l.). Tillverkar kassaskåp, arkiv-och inmurningsskåp, förvaringsskåp, hyllor och inredningar i stål, brand-, arkiv-och kassavalvsdörrar m. m.",
            "contact": {
                "office": "Eskilstuna",
                "phone": [
                    "35054",
                    "34382"
                ],
                "postgiro": "26426"
            },
            "financials": {
                "employees": {
                    "industriarb": 20
                },
                "annual_production_value": "350,000 kr"
            },
            "foundation_year": 1944,
            "manager": "Hans Dahlstedt"
        },
        "5": {
            "name": "Dahlström & Löfgren",
            "location": "Motala verkstad",
            "business": "Tillverkar gjutmodeller, karosserier för rälsbussar och skåpvagnar m. m. vid fabrik i Motala verkstad (Östergötl. l.).",
            "contact": {
                "phone": [
                    "Motala 219"
                ],
                "postgiro": "28358"
            },
            "financials": {
                "employees": {
                    "industriarb": 26
                }
            },
            "foundation_year": 1908,
            "manager": "Olof Löfgren"
        },
        "6": {
            "name": "AB. Dakrysol",
            "location": "Malmö",
            "business": "Kem. teknisk fabrik. Tillverkar hårvatten.",
            "contact": {
                "office": "Slussg. 1",
                "phone": [
                    "10526"
                ],
                "postgiro": "30,000 kr"
            },
            "financials": {
                "capital": "30,000 kr",
                "employees": {
                    "arb": 10
                },
                "annual_production_value": "120,000 kr"
            },
            "foundation_year": 1932,
            "manager": "kamrer Fredrik Jonson"
        },
        "7": {
            "name": "Dala Flöda Snickerifabrik",
            "location": "Dala-Floda",
            "business": "Se Axel Eriksson & Co. Snickeri AB., Dala-Floda"
        },
        "8": {
            "name": "AB. Dala Mek. Spisbrödsbageri",
            "location": "Säter",
            "business": "Tillverkar spisbröd och knäckebröd.",
            "contact": {
                "telegraph": "Dalabageriet, Säter",
                "phone": [
                    "Säterbröd"
                ],
                "postgiro": "21480"
            },
            "financials": {
                "capital": "200,000 kr",
                "employees": {
                    "industriarb": 30
                },
                "annual_production_value": "1,000,000 kg bröd"
            },
            "foundation_year": 1902,
            "board": [
                {
                    "name": "bankkamrer Johannes Ohlsson",
                    "role": "ordf."
                },
                {
                    "name": "disp. J. Gråhns",
                    "role": null
                },
                {
                    "name": "fabr. Bernhard Johansson",
                    "role": null
                },
                {
                    "name": "byggm. Evald Lindström",
                    "role": null
                }
            ],
            "manager": "J. Gråhns"
        },
        "9": {
            "name": "AB. Dala Skinnindustri",
            "location": "Säter",
            "business": "Tillverkar handskar, skinnkläder, portföljer, shoppingväskor, sadelskydd för cyklar m. m.",
            "contact": {
                "phone": [
                    "203"
                ],
                "postgiro": "84767"
            },
            "financials": {
                "capital": "50,000 kr",
                "employees": {
                    "industriarb": 15
                },
                "annual_production_value": "225,000 kr"
            },
            "foundation_year": 1938,
            "manager": "E. Ljusterdal"
        },
        "10": {
            "name": "Dala Spegelfabrik AB.",
            "location": "Falun",
            "business": "Tillverkar spegelglas, speglar samt ramister och ramar.",
            "contact": {
                "phone": [
                    "3100"
                ],
                "postgiro": "164173"
            },
            "financials": {
                "capital": "50,600 kr",
                "employees": {
                    "industriarb": 15
                },
                "annual_production_value": "160,000 kr"
            },
            "foundation_year": 1939,
            "manager": "Nestor Eriksson"
        }
    }
}