{
    "original": "Husinrede—Hvetlanda\n\n*AB. Husinrede, Ulricehamn.\n\nSnickerifabrik. Tillverkar fönster,\ndörrar, skåp och trappor. Telefon: 574.\nPostgiro: 73178.\n\nAkt.-kap.: 10,000 kr. Arb.-antal: 9.\nTillv.-värde pr år: 140,000 kr. — Bolaget\ngrundat 1934.\n\nStyrelse: disp. J. F. Helge (ordf.),\nverkm. Anders Helge, stenarb. Svante\nMattsson.\n\nDisp.: J. F. Helge.\n\n\"AB. Husqvarna Borstfabrik,\n\nHuskvarna.\n\nTillverkar borstar och penslar alla slag\n(speciellt för industriella behov)\npolér-skivor, gevärsputskäppar m. m.\n\nTelefon: »Huskvarna borstfabrik».\nPostgiro: 5419. Avd.-kontor: Stockholm,\nKungs g. 3, telefon: 205110 o. 205116.\n\nAkt.-kap.: 156,750 kr. Antal\nindustriarb.: 275. Tillv.-värde pr år: 4,000,000 kr.\n— Firman etabl. 1896, bolag 1911.\n\nStyrelse: dir. G. Emil Nilsson (ordf.),\ndisp. Ragnar N:son Corenius, herr G. A.\nOxelqvist.\n\nVerkst. dir.: G. Emil Nilsson.\n\nDisp.: Ragnar N:son Corenius.\n\nKamrer: Per Ljung.\n\nDriftsing.: Erik W. Asp.\n\n\"Husqvarna Vapenfabriks AB.,\n\nHuskvarna.\n\nGevärsfaktori, symaskins-^ och\ncykelfabrik, gjuteri med emaljerings- och\nförtenningsverk, mek. verkstad m. m. i\nHuskvarna; aduceringsverk, gjuteri och\nmek. verkstad i Norrahammar (se\nNorrahammars Bruk) samt gjuteri i Åminne\n(se Åminne Bruk).\n\nGjutgodsti 11 verkningen omfattar bl. a.\nbyggnads- och handelsgjutgods, ved-,\ngas- och elspisar, kaminer,\nvärmeledningspannor, värmeledningsradiatorer,\nsanitetsgods, förnicklade, förtenta och\nemaljerade hushållsartiklar samt\nel-artiklar.\n\nTelegr.-adr.: Vapenfabriken,\nHuskvarna. Telefoner: Huskvarna o. Jönköping:\n»Vapenfabriken». Postgiro: 8474.\n\nRepresentanter: i Stockholm:\nHusqvarna Generaldepots AB., Brunnsg. 6—\n8, telefon: »Husqvarna Generaldepot»; i\nMalmö: Husqvarna Malmö Depots AB.,\nSöderg. 13, telefon: »Husqvarna Depot»;\ni Göteborg: Husqvarna Fabrikslager AB.,\nKungsportsavenyen 3, telefon: 170580; i\n&lt;jrävle: Husqvarna Gävle Depots AB.,\ntelefon: 6590; i Norrköping: Husqvarna\nNorrköpings Depots AB., telefon: 20210;\n\ni Sundsvall: Husqvarna Sundsvalls\nDepots AB., telefon: 3226.\n\nAkt.-kap.: 15,000,000 kr. Antal\nindustriarb. i Huskvarna: 3,671. Tillv.-värde\når 1945: 45,000,000 kr.\n\nFabriken grundad 1689, bolag 1867.\nStyrelse: dir. Gustaf Tham (ordf.),\nadv. Sten S:son Ankarcrona, f. d.\nhovrättsrådet Johan Nordenfalk, bankdir.\nGustaf Söderlund, jägmäst. Gustaf H:son\nTamm, civiling. Stig Tham, dir. Thure\nÖberg.\n\nVerkst. dir.: Thure Öberg.\nV. verkst. dir.: Stig Tham.\nKassadir.: Sven Bergmark.\nFörsäljn.-chef er: för Sverige: bitr. dir.\nT. Nordenfelt; för export: bitr. dir. R.\nWinqvist.\n\nÖveringenjörer: A. Hulthén o. H. F:son\nNauckhoff.\nInköpschef: Axel E. Carlzon.\n\n\"Husums Sulfatfabrik, Husum.\n\nSe Mo och Domsjö AB., Stockholm och\nHärnösand.\n\n*Hvens Tegelbruks AB., S:t Ibb.\n\nTillverkar byggnadstegel vid tegelbruk\nå Ven (Malmöh. l.).\n\nKontor: S:t Ibb. Telefon: Hven 2.\nPostgiro: 92590. Ensamförsälj.: Malmö\nGrus AB., Malmö, Baltzarsg. 25, telefon:\n29113 o. 25234.\n\nAkt.-kap.: 600,000 kr. Antal\nindustriarb.: 60. Årstillv.: 6 milj. st. tegel. —\nBolaget grundat 1884.\n\nStyrelse: adv. Gunnar Wihlborg\n(ordf.), dir. H. W. Boserup, kamrer Chr.\nAug. Lassen.\n\nVerkst. dir.: H. W. Boserup\n(Köpenhamn).\n\nTegelmäst.: Ivan Andersson.\n\n\"Hvetlanda Mek. Verkstad, Vetlanda.\n\nTillverkar träbearbetningsmaskiner.\nTelegr.-adr.: Verkstaden, Vetlanda.\nTelefon: 40 o. 400. Postgiro: 89988. —\nAntal industriarb.: 15. Tillv.-värde pr år:\n150,000 kr. — Firman etabl. 1904.\nÄgare o. chef: ing. Oscar Sollin.\n\nAB. Hvetlanda Saft- &amp; Syltfabrik,\n\nVetlanda.\n\nTillverkar fruktsafter, sylter och\nmarmelad. Varumärke: »Blå Bäret».\n\nTelegr.-adr.: Saftfabriken, Vetlanda.\nTelefon: 240. Postgiro: 15442.\n\nAkt.-kap.: 30,050 kr. Antal\nindustriarb.: 16. Tillv.-värde pr år: 213,000 kr.\n— Bolaget grundat 1919.\n\nVerkst. dir.: disp. Arvid Ahlinder.",
    "structured": {
        "1": {
            "name": "AB. Husinrede",
            "location": "Ulricehamn",
            "business": "Snickerifabrik",
            "products": "Tillverkar fönster, dörrar, skåp och trappor",
            "contact": {
                "office": "Husinrede, Ulricehamn",
                "phone": [
                    "574"
                ],
                "postgiro": "73178"
            },
            "financials": {
                "capital": "10,000 kr",
                "employees": {
                    "Arb.-antal": 9
                },
                "annual_turnover": "140,000 kr",
                "annual_production_value": "140,000 kr"
            },
            "foundation_year": 1934,
            "board": [
                {
                    "name": "disp. J. F. Helge",
                    "role": "ordf."
                },
                {
                    "name": "verkm. Anders Helge",
                    "role": ""
                },
                {
                    "name": "stenarb. Svante Mattsson",
                    "role": ""
                }
            ],
            "director": "J. F. Helge"
        },
        "2": {
            "name": "AB. Husqvarna Borstfabrik",
            "location": "Huskvarna",
            "business": "Tillverkar borstar och penslar",
            "products": "Alla slag (speciellt för industriella behov), polér-skivor, gevärsputskäppar m.m.",
            "contact": {
                "telegraph": "Huskvarna borstfabrik",
                "postgiro": "5419",
                "sales_offices": [
                    {
                        "location": "Stockholm",
                        "phone": "205110 o. 205116"
                    }
                ]
            },
            "financials": {
                "capital": "156,750 kr",
                "employees": {
                    "Antal industriarb.": 275
                },
                "annual_turnover": "4,000,000 kr",
                "annual_production_value": "4,000,000 kr"
            },
            "foundation_year": 1896,
            "corporation_year": 1911,
            "board": [
                {
                    "name": "dir. G. Emil Nilsson",
                    "role": "ordf."
                },
                {
                    "name": "disp. Ragnar N:son Corenius",
                    "role": ""
                },
                {
                    "name": "herr G. A. Oxelqvist",
                    "role": ""
                }
            ],
            "director": "G. Emil Nilsson",
            "sales_manager": "Ragnar N:son Corenius",
            "manager": "G. A. Oxelqvist",
            "managing_director": "G. Emil Nilsson"
        },
        "3": {
            "name": "Husqvarna Vapenfabriks AB.",
            "location": "Huskvarna",
            "business": "Gevärsfaktori, symaskins-^ och cykelfabrik, gjuteri med emaljerings- och förtenningsverk, mek. verkstad m. m.",
            "products": "Gjutgodsti 11 verkningen omfattar bl. a. byggnads- och handelsgjutgods, ved-, gas- och elspisar, kaminer, värmeledningspannor, värmeledningsradiatorer, sanitetsgods, förnicklade, förtenta och emaljerade hushållsartiklar samt el-artiklar",
            "contact": {
                "telegraph": "Vapenfabriken, Huskvarna",
                "phone": "Huskvarna o. Jönköping: »Vapenfabriken»",
                "postgiro": "8474"
            },
            "financials": {
                "capital": "15,000,000 kr",
                "employees": {
                    "Antal industriarb. i Huskvarna": 671
                },
                "annual_turnover": "45,000,000 kr"
            },
            "foundation_year": 1689,
            "corporation_year": 1867,
            "board": [
                {
                    "name": "dir. Gustaf Tham",
                    "role": "ordf."
                },
                {
                    "name": "adv. Sten S:son Ankarcrona",
                    "role": ""
                },
                {
                    "name": "f. d. hovrättsrådet Johan Nordenfalk",
                    "role": ""
                },
                {
                    "name": "bankdir. Gustaf Söderlund",
                    "role": ""
                },
                {
                    "name": "jägmäst. Gustaf H:son Tamm",
                    "role": ""
                },
                {
                    "name": "civiling. Stig Tham",
                    "role": ""
                },
                {
                    "name": "dir. Thure Öberg",
                    "role": ""
                }
            ],
            "director": "Thure Öberg",
            "managing_director": "Thure Öberg"
        },
        "4": {
            "name": "Husums Sulfatfabrik",
            "location": "Husum"
        },
        "5": {
            "name": "Hvens Tegelbruks AB.",
            "location": "S:t Ibb",
            "business": "Tillverkar byggnadstegel",
            "contact": {
                "office": "S:t Ibb",
                "phone": [
                    "Hven 2"
                ],
                "postgiro": "92590"
            },
            "financials": {
                "capital": "600,000 kr",
                "employees": {
                    "Antal industriarb.": 60
                },
                "annual_production_value": "6 milj. st. tegel"
            },
            "foundation_year": 1884,
            "board": [
                {
                    "name": "adv. Gunnar Wihlborg",
                    "role": "ordf."
                },
                {
                    "name": "dir. H. W. Boserup",
                    "role": ""
                },
                {
                    "name": "kamrer Chr. Aug. Lassen",
                    "role": ""
                }
            ],
            "director": "H. W. Boserup"
        },
        "6": {
            "name": "Hvetlanda Mek. Verkstad",
            "location": "Vetlanda",
            "business": "Tillverkar träbearbetningsmaskiner",
            "contact": {
                "office": "Verkstaden, Vetlanda",
                "phone": [
                    "40 o. 400"
                ],
                "postgiro": "89988"
            },
            "financials": {
                "employees": {
                    "Antal industriarb.": 15,
                    " 25 milj. st. tegel": null
                },
                "annual_production_value": "150,000 kr"
            },
            "foundation_year": 1904,
            "director": "ing. Oscar Sollin"
        },
        "7": {
            "name": "AB. Hvetlanda Saft- & Syltfabrik",
            "location": "Vetlanda",
            "business": "Tillverkar fruktsafter, sylter och marmelad",
            "products": "Varumärke: »Blå Bäret»",
            "contact": {
                "telegraph": "Saftfabriken, Vetlanda",
                "phone": "240",
                "postgiro": "15442"
            },
            "financials": {
                "capital": "30,050 kr",
                "employees": {
                    "Antal industriarb.": 16
                },
                "annual_production_value": "213,000 kr"
            },
            "foundation_year": 1919,
            "director": "disp. Arvid Ahlinder"
        }
    }
}