{
    "original": "Munkte 11—Mustad\n\nbott. l.), trämassefabrik i Byske\n(Västerbott. l.).\n\nTillverkar sågade och hyvlade trävaror,\nkubbgolv, monteringsfärdiga trähus,\nbyggnads- och kökssnickerier (byggbara kök),\nsulfatcellulosa (kraft-massa), våt mek.\nträmassa, råterpentin och harts. Bolaget\nidkar även skogsbruk.\n\nHuvudkontor: Luleå. Telegr.-adr.:\nMunksundeo, Luleå. Telefon: 4600—\n4607 el. »Munksunds bolag». Postgiro:\n61701. Ensamförsälj. för mek. trämassa o.\nsulfatcellulosa: Svenska Cellulosa AB.,\nStockholm, V:a Trädgårdsg. 15, telefon:\n»Cellulosabolaget».\n\nAkt.-kap.: 15,000,000 kr. Antal\nindustriarb.: 830. Årstillv.: 20,000 stds\nträvaror, 47,000 ton kraftcellulosa, 90,000\nton våt, vit mek. trämassa.\n\nBolaget, grundat 1926, har i sig\nupptagit större delen av den industri- och\nskogsrörelse, som tidigare bedrivits av\nAB. Ytterstfors-Munksund.\nAktiemajoriteten i bolaget innehaves av Svenska\nCellulosa AB.\n\nStyrelse: dir. Torsten Hérnod (ordf.),\ndir. Bure Holmbäck, dir. K. Erik\nNyberg, dir. Gust. J. Sahlin, bankdir. P. F.\nWåhlin.\n\nVerkst. dir.: Bure Holmbäck.\n\nDisp. o. försäljn.-chef: Knut Ronge.\n\növering.: civiling. Harald Norre.\n\nDriftsingenjörer: i Munksund: Yngve\nSundfeldt; i Byske o. Luleå: A. Alf sen.\n\nSJcogschef: jägm. F. v. Heideken.\n\nSäg v er fes för valt.: Gunnar Hammarberg.\n\nMunkteils Mek. Verkstads AB.,\n\nEskilstuna.\n\nBolaget utgör ett försäljningsbolag\nför AB. Bolinder-Munktell, Eskilstuna,\nsamt är dotterbolag till detsamma (se\nvidare under nämnda bolag).\n\nKontor: Eskilstuna. — Akt.-kap.:\n50,000 kr.\n\n*J. H. Munkteils Pappersfabriks AB.,\n\nGrycksbo.\n\nSe Grycksbo Pappersbruk AB.,\nGrycksbo.\n\nMunters Industri AB., Stockholm.\n\nWellpappfabrik i Gävle. ^ Tillverkar\nwellpappemballage och isolationsmateriel.\nVarumärke: »Wellit».\n\nKontor: Stockholm, N. Mälarstrand 56.\nTelegr.-adr.: Muntersindustri, Stockholm.\nTelefon: 520385. Postgiro: 156500.\n\nAkt.-kap.: 300,000 kr. Antal\nindustriarb.: 100. — Bolaget grundat 1938.\n\nStyrelse: civiling. Carl Munters (ordf.),\nbankdir. John Bergström, dir. Birger\nMunters.\n\nVerkst. dir.: Birger Munters.\n\nMurbruksfabrikens i Stockholm AB.,\n\nStockholm.\n\nSe Nya Murbruksfabrikens i Stockholm\nAB., Stockholm.\n\n*AB. Mursten, Norrköping.\n\nTillverkar murtegel, beklädnadstegel\nsamt högporöst tegel.\n\nTelefon: 20101. Postgiro: 29413. —\nAkt.-kap.: 224,000 kr. Antal\nindustriarb.: 20. Årstillv.: 2,5 milj. st. tegelvaror.\n\n—\tBolaget grundat 1898.\n\nStyrelse: fru Britta Nylin, dir. Stig\nNylin, kapten Sture Nylin.\n\nVerkst. dir.: Sture Nylin.\n\nV. verkst. dir.: Stig Nylin.\n\n*AB. Murtegel, Stockholm.\n\nTegelbruk vid Mariefred. Tillverkar\nmurtegel.\n\nKontor o. ensamförsäljn.: Tegelbrukens\nFörsäljn. AB., Stockholm, Norrlandsg.\n11; telefon: 233115; postgiro: 156711.\n\nAkt.-kap.: 70,000 kr. Antal\nindustriarb.: 20. Årstillv.: 2 milj. st. tegelvaror.\n\n—\tBolaget grundat 1924.\n\nDisp.: Arne Gustafson.\n\n*AB. O. Mustad &amp; Son, Göteborg.\n\nMargarinfabrik i Mölndal (Göteb. o.\nBohus l.). Tillverkar margarin,\nkonst-ister och kokossmör.\n\nHuvudkontor: Göteborg. Telegr.-adr.:\nMustads, Göteborg. Telefon: 130172.\nPostgiro: 42445. Försäljningen sker\ngenom Margarinbolaget\nMargarinfabrikernas Försäljnings AB. (se detta bolag).\n\nAkt.-kap.: 3,500,000 kr. Antal\nindustriarb.: 50. — Bolaget grundat 1904.\n\nStyrelse: adv. Torsten Setterberg\n(ordf.), kamrer Conrad Kjellman, dir. H.\nMustad.\n\n*AB. 0. Mustad &amp; Son, Dals Långed.\n\nSpik- och sömfabrik vid Mustadfors,\nDals Långed (Älvsb. l.). Tillverkar spik,\nklippspik, extranubb, hästskosöm och\nbroddsöm samt hårspännen.\n\nHuvudkontor: Göteborg.\nFabrikskontor: Dals Långed. Telegr.-adr.: Mustads,\nVänersborg. Telefon: Dals Långed 5. —\nAntal industriarb.: 300. — Fabriken\nanlagd 1899.",
    "structured": {
        "1": {
            "name": "Munksunds Mekaniska Verkstads AB",
            "location": "Luleå",
            "business": "Tillverkning av sågade och hyvlade trävaror, kubbgolv, monteringsfärdiga trähus, byggnads- och kökssnickerier (byggbara kök), samt tillverkning av sulfatcellulosa (kraft-massa), våt mekanisk trämassa, råterpentin och hartssubsidierad skogsbruk.",
            "contact": {
                "office": "Luleå",
                "phone": [
                    "4600",
                    "4601",
                    "4602",
                    "4603",
                    "4604",
                    "4605",
                    "4606",
                    "4607"
                ],
                "postgiro": "61701",
                "head_office": "Luleå",
                "telegraph": "Munksundeo, Luleå",
                "factory_office": "Byske",
                "factory_phone": "Byske",
                "sales_offices": [
                    {
                        "location": "Stockholm, Västra Trädgårdsgatan 15",
                        "phone": "Cellulosabolaget"
                    }
                ]
            },
            "financials": {
                "capital": "15,000,000 kr",
                "employees": {
                    "industriarb": 830
                },
                "annual_turnover": "Not available",
                "annual_production_value": "20,000 stds trävaror, 47,000 ton kraftcellulosa, 90,000 ton våt, vit mekanisk trämassa"
            },
            "foundation_year": 1926,
            "predecessor": "AB. Ytterstfors-Munksund",
            "owners": [
                "Svenska Cellulosa AB"
            ],
            "board": [
                {
                    "name": "Torsten Hénnod",
                    "role": "Ordförande"
                },
                {
                    "name": "Bure Holmbäck",
                    "role": "Styrelsemedlem"
                },
                {
                    "name": "K. Erik Nyberg",
                    "role": "Styrelsemedlem"
                },
                {
                    "name": "Gust. J. Sahlin",
                    "role": "Styrelsemedlem"
                },
                {
                    "name": "P. F. Wåhlin",
                    "role": "Bankdirektör"
                }
            ],
            "director": "Torsten Hénnod",
            "managing_director": "Bure Holmbäck",
            "sales_manager": "Knut Ronge"
        },
        "2": {
            "name": "Munkteils Mekaniska Verkstads AB",
            "location": "Eskilstuna",
            "business": "Försäljningsbolag för AB. Bolinder-Munktell, Eskilstuna, samt dotterbolag till detsamma.",
            "contact": {
                "office": "Eskilstuna"
            },
            "financials": {
                "capital": "50,000 kr"
            }
        },
        "3": {
            "name": "Munkteils Pappersfabriks AB",
            "location": "Grycksbo",
            "business": "See Grycksbo Pappersbruk AB., Grycksbo"
        },
        "4": {
            "name": "Munters Industri AB",
            "location": "Stockholm",
            "products": "Wellpappemballage och isolationsmateriel med varumärket »Wellit«.",
            "contact": {
                "office": "Stockholm, N. Mälarstrand 56",
                "telegraph": "Muntersindustri, Stockholm",
                "phone": "520385",
                "postgiro": "156500"
            },
            "financials": {
                "capital": "300,000 kr",
                "employees": {
                    "industriarb": 100
                }
            }
        },
        "5": {
            "name": "Murbruksfabrikens i Stockholm AB",
            "location": "Stockholm",
            "business": "See Nya Murbruksfabrikens i Stockholm AB., Stockholm"
        },
        "6": {
            "name": "AB. Mursten",
            "location": "Norrköping",
            "business": "Tillverkning av murtegel, beklädnadstegel samt högporöst tegel."
        },
        "7": {
            "name": "AB. Murtegel",
            "location": "Stockholm",
            "business": "Tillverkning av murtegel vid Mariefred."
        },
        "8": {
            "name": "AB. O. Mustad & Son",
            "location": "Göteborg",
            "business": "Tillverkning av margarin, konst-ister och kokossmör.",
            "contact": {
                "office": "Göteborg",
                "telegraph": "Mustads, Göteborg",
                "phone": "130172",
                "postgiro": "42445"
            },
            "financials": {
                "capital": "3,500,000 kr",
                "employees": {
                    "industriarb": 50
                }
            }
        },
        "9": {
            "name": "AB. O. Mustad & Son",
            "location": "Dals Långed",
            "business": "Tillverkning av spik, klippspik, extranubb, hästskosöm, broddsöm och hårspännen.",
            "contact": {
                "office": "Göteborg",
                "factory_office": "Dals Långed",
                "telegraph": "Mustads, Vänersborg",
                "phone": "Dals Långed 5"
            },
            "financials": {
                "employees": {
                    "industriarb": 300
                }
            }
        }
    }
}