{
    "original": "Bero l—Be tongindustri\n\n*AB. Berol-Produkter, Göteborg.\n\nKem.-teknisk fabrik. Tillverkar\nhjälp-produkter för textil- och\nläderindustrien, appreturmedel, impregneringsmedel,\nmjukriingsmedel samt emulgatorer.\n\nPostadr.: Göteborg 14. Telegr.-adr.:\nBerolproducts, Göteborg. Telefon: 272200.\nPostgiro; 58031.\n\nAkt.-kap.: 100.000 kr. Arb.-antal: 10.\n\n—\tFirman etabl. 1936.\n\nStyrelse: dir. Carl Kempe (ordf.), fil.\ndr Erik Kempe, dir. Ragnar Lagergren,\ndir. Gunnar Rising.\n\nVerkst. dir.: Magnus Bernström.\n\n*E. V. Beronius Mek. Verkstads AB.,\n\nEskilstuna.\n\nSe AB. Bolinder-Munktell, Eskilstuna.\n\n*Berte Qvarn AB., Slöinge.\n\nValskvarn vid Berte, Slöinge (Hallands\n1.). Tillverkar vete- och rågmjöl samt kli.\nBolaget idkar jämväl jordbruk.\n\nTelegr.-adr.: Berte, Slöinge. Telefon:\nSlöinge 1. Postgiro: 5555.\n\nAkt.-kap.: 660,000 kr. Antal\nindustriarb.: 17. Prod.-värde pr år: 1,000,000 kr.\n\n—\tBolaget grundat 1895.\n\nStyrelse: ad v. Gösta Stenström (ordf.),\nkamrer Otto Johansson, dir. Olof\nStenström.\n\nVerkst. dir.: Olof Stenström.\n\nJulius Berteisen &amp; Co., AB.,\n\nGöteborg.\n\nKravattfabrik. Tillverkar herrhalsdu-\n\nKontor: Lilla Korsg. 1. Telefon: 131675.\nPostgiro: 40740. — Akt.-kap.: 100,000 kr.\nAntal industriarb.: 50. — Firman etabl.\n1889.\n\nStyrelse: grossh. N. Norling (ordf.),\ndisp. E. Berring, dir. O. F. Berteisen.\nVerkst. dir.: O. F. Berteisen.\n\nBerzelius Konfektions AB.,\n\nMotala verkstad.\n\nHerrkonfektionsfabrik vid Motala\nverkstad (Östergötl. l.). Tillverkar herrkläder\nsåsom kostymer, paletåer, gabardinrockar,\ntrenchcoats, samt skid-, sport- och\ngolfbyxor. Varumärke: »Berko».\n\nTelefon: Motala 588. Postgiro: 5580.\n\n—\tAkt.-kap.: 150,000 kr. Anta!\nindustriarb.: 140. — Firman etabl. 1912, nuv.\nbolag 1931.\n\nStyrelse: stadsfiskal Conrad Sterner\n(ordf.), kamrer Eric Almgren, disp.\nHarald Hjalmarsson.\n\nDisp.: Harald Hjalmarsson.\n\n*Beton AB. Vestra Sverige,\n\nGöteborg.\n\nByggnadsentreprenörfirma och ce~\nmentgjuteri. Utför bostads- och\naffärshus, industribyggnader, väg- och\nvattenbyggnadsarbeten samt tillverkar\ntrappsteg av mosaik och cement, brunnsringar\nm. m.\n\nKontor: Skeppsbrohuset. Telegr.-adr.:\nBeton, Göteborg. Telefon: 131881—82 o.\n131884. Postgiro: 45204.\n\nAkt.-kap.: 150,000 kr. — Bolaget\ngrundat 1909.\n\nStyrelse: major N. August Svensson\n(ordf.), civiling. Bengt Landby.\n\nVerkst. dir.: N. A. Svensson.\n\nBetong, Kommanditbolaget, Sander\n&amp; Co., Hednoret.\n\nSe Kommanditbolaget Betong, Sander\n&amp; Co., Hednoret.\n\nBetongbolaget, Varbergs\nBetong-varu AB., Varberg.\n\nBetongvarufabriker i Varberg och\nHalmstad. Tillverkar betongvaror med\ndetaljer speciellt för lantbruket såsom\nrör, AlV-silor, rotfruktskällare,\nurinbrunnar m. m.\n\nKontor: Varberg. Telegr.-adr. o.\ntelefon: Betongbolaget, Varberg. Postgiro:\n162160.\n\n. Akt.-kap.: 55,000 kr. Antal\nindustriarb.: 80, varav 30 montörer. Tillv.-värde\npr år: 1,000,000 kr. — Bolaget grundat\n1939.\n\nVerkst. dir.: Lennart Hermanson.\n\nKonsult, ing.: civiling. J. Ingelf.\n\nKamrer: Einar Bäckman.\n\n* Betongbyggnadsbyrån, Allmänna\n\nStockholm.\n\nSe Allmänna Betongbyggnadsbyrån,\nStockholm.\n\n*AB. Betongindustri, Stockholm.\n\nTillverkar betong och strån erbetong\nsamt distribuerar fabriksblandad betong i\nStockholm med omnejd.\n\nKontor: Hornsbergsv. 16. Telefon:\n520265. Postgiro: 2453. — Akt.-kap.:\n2,200,000 kr. Antal industriarb.: 170.\nTillv.-värde pr år: 4,500,000 kr. —\nBolaget grundat 1930.\n\nStyrelse: byggm. G. Anders Svensson\n(ordf.), byggm. Olle Engkvist, tekn. dr\nAxel Eriksson, ing. Hilding Jehander.\n\nVerkst. dir.: Axel Eriksson.\n\nKamrer: Berthel Mordström.",
    "structured": {
        "1": {
            "name": "AB. Berol-Produkter",
            "location": "Göteborg",
            "business": "Kem-teknisk fabrik",
            "products": "hjälp-produkter för textil- och läderindustrien, appreturmedel, impregneringsmedel, mjukriingsmedel samt emulgatorer",
            "contact": {
                "office": "Göteborg 14",
                "phone": [
                    "272200"
                ],
                "postgiro": "58031"
            },
            "financials": {
                "capital": "100,000 kr",
                "employees": {
                    "Arb.-antal": 10
                }
            },
            "foundation_year": 1936,
            "board": [
                {
                    "name": "dir. Carl Kempe",
                    "role": "ordf."
                },
                {
                    "name": "fil. dr Erik Kempe",
                    "role": ""
                },
                {
                    "name": "dir. Ragnar Lagergren",
                    "role": ""
                },
                {
                    "name": "dir. Gunnar Rising",
                    "role": ""
                }
            ],
            "director": "Magnus Bernström"
        },
        "2": {
            "name": "E. V. Beronius Mek. Verkstads AB.",
            "location": "Eskilstuna",
            "business": "Mekanisk verkstad",
            "description": "Se AB. Bolinder-Munktell, Eskilstuna"
        },
        "3": {
            "name": "Berte Qvarn AB.",
            "location": "Slöinge",
            "business": "Valskvarn",
            "products": "vete- och rågmjöl, kli, jordbruk",
            "contact": {
                "telegraph": "Berte, Slöinge",
                "phone": "Slöinge 1",
                "postgiro": "5555"
            },
            "financials": {
                "capital": "660,000 kr",
                "employees": {
                    "antal industriarb": 17
                },
                "annual_production_value": "1,000,000 kr"
            },
            "foundation_year": 1895,
            "board": [
                {
                    "name": "ad v. Gösta Stenström",
                    "role": "ordf."
                },
                {
                    "name": "kamrer Otto Johansson",
                    "role": ""
                },
                {
                    "name": "dir. Olof Stenström",
                    "role": ""
                }
            ],
            "director": "Olof Stenström"
        },
        "4": {
            "name": "Julius Berteisen & Co., AB.",
            "location": "Göteborg",
            "business": "Kravattfabrik",
            "products": "herrhalsdukar",
            "contact": {
                "office": "Lilla Korsg. 1",
                "phone": [
                    "131675"
                ],
                "postgiro": "40740"
            },
            "financials": {
                "capital": "100,000 kr",
                "employees": {
                    "Antal industriarb": 50
                }
            },
            "foundation_year": 1889,
            "board": [
                {
                    "name": "grossh. N. Norling",
                    "role": "ordf."
                },
                {
                    "name": "disp. E. Berring",
                    "role": ""
                },
                {
                    "name": "dir. O. F. Berteisen",
                    "role": ""
                }
            ],
            "director": "O. F. Berteisen"
        },
        "5": {
            "name": "Berzelius Konfektions AB.",
            "location": "Motala verkstad",
            "business": "Herrkonfektionsfabrik",
            "products": "herrkläder såsom kostymer, paletåer, gabardinrockar, trenchcoats, samt skid-, sport- och golfbyxor",
            "contact": {
                "phone": "Motala 588",
                "postgiro": "5580"
            },
            "financials": {
                "capital": "150,000 kr",
                "employees": {
                    "Antal industriarb": 140
                }
            },
            "foundation_year": 1912,
            "current_name_year": 1931,
            "board": [
                {
                    "name": "stadsfiskal Conrad Sterner",
                    "role": "ordf."
                },
                {
                    "name": "kamrer Eric Almgren",
                    "role": ""
                },
                {
                    "name": "disp. Harald Hjalmarsson",
                    "role": ""
                }
            ],
            "director": "Harald Hjalmarsson"
        },
        "6": {
            "name": "Beton AB. Vestra Sverige",
            "location": "Göteborg",
            "business": "Byggnadsentreprenörfirma och cementgjuteri",
            "products": "bostads- och affärshus, industribyggnader, väg- och vattenbyggnadsarbeten samt trappsteg av mosaik och cement, brunnsringar",
            "contact": {
                "office": "Skeppsbrohuset",
                "phone": [
                    "131881-82",
                    "131884"
                ],
                "postgiro": "45204"
            },
            "financials": {
                "capital": "150,000 kr"
            },
            "corporation_year": 1909,
            "board": [
                {
                    "name": "major N. August Svensson",
                    "role": "ordf."
                },
                {
                    "name": "civiling. Bengt Landby",
                    "role": ""
                }
            ],
            "director": "N. A. Svensson"
        },
        "7": {
            "name": "Betongbolaget, Varbergs Betong-varu AB.",
            "location": "Varberg",
            "business": "Betongvarufabriker",
            "products": "betongvaror med detaljer speciellt för lantbruket såsom rör, AlV-silor, rotfruktskällare, urinbrunnar m. m.",
            "contact": {
                "office": "Varberg",
                "phone": "Betongbolaget, Varberg",
                "postgiro": "162160"
            },
            "financials": {
                "capital": "55,000 kr",
                "employees": {
                    "Antal industriarb": 80,
                    "varav 30 montörer": 30
                },
                "annual_production_value": "1,000,000 kr"
            },
            "foundation_year": 1939,
            "director": "Lennart Hermanson",
            "manager": "Einar Bäckman"
        },
        "8": {
            "name": "AB. Betongindustri",
            "location": "Stockholm",
            "business": "Tillverkar betong och strålerbetong samt distribuerar fabriksblandad betong i Stockholm med omnejd",
            "contact": {
                "office": "Hornsbergsv. 16",
                "phone": "520265",
                "postgiro": "2453"
            },
            "financials": {
                "capital": "2,200,000 kr",
                "employees": {
                    "Antal industriarb": 170
                },
                "annual_production_value": "4,500,000 kr"
            },
            "corporation_year": 1930,
            "board": [
                {
                    "name": "byggm. G. Anders Svensson",
                    "role": "ordf."
                },
                {
                    "name": "byggm. Olle Engkvist",
                    "role": ""
                },
                {
                    "name": "tekn. dr Axel Eriksson",
                    "role": ""
                },
                {
                    "name": "ing. Hilding Jehander",
                    "role": ""
                }
            ],
            "director": "Axel Eriksson",
            "manager": "Berthel Mordström"
        }
    }
}