{
    "original": "Slutarp—Smith\n\nA B. Slutarps Snickerifabrik,\n\nSlutarp.\n\nTillverkar likkistor vid fabrik i\nSlutarp (Skarab. l.).\n\nTelefon: Kinnarp 108. Postgiro: 74930.\n— Akt.-kap.: 60,000 kr. Arb.-antal: 12.\nTillv.-värde pr år: 115,000 kr. — Firman\netabl. 1920, bolag 1945.\n\nVerJcst. dir.: Tage Norrländer.\n\n*Slöinge Träförädlings AB., Slöinge.\n\nTillverkar byggnadssnickerier, dörrar\noch fönster, trappor samt köks- och\nbutiksinredningar vid fabrik i Slöinge\n(Hallands l.).\n\nTelegr.-adr.: Träförädlingen, Slöinge.\nTelefon: 6. Postgiro: 135495.\n\nAkt.-kap.: 19,500 kr. Arb.-antal: 15.\nTillv.-värde pr år: 250,000 kr. —\nBolaget grundat 1901.\n\nStyrelse: dir. Sven-Erik Christiansson\n(ordf.), lantbr. Sven-Ivar Christiansson,\nbyggm. Ernst Isberg, ombudsm. Karl\nKarlsson, godsäg. Johannes Olsson.\n\nVerJcst. dir.: S.-E. Christiansson.\n\nSmedby Mek. Verkstad,\n\nM almköping.\n\nTillverkar grövre byggnadssmiden och\ncisterner; utför gas- och elektr.\nsvetsningsarbeten samt metallisering vid mek.\nverkstad i Malmköping (Södermanl. l.).\n\nTelefon: 126. Postgiro: 1$3$09. —\nArb.-antal: 8. — Firman etabl. 1933.\n\nÄgare o. chefer: fabr. Martin\nCarlsson o. fabr. Olof M. Andersson.\n\n\"Smedjebackens Valsverks AB.,\n\nSmedjebacken.\n\nJärnverk med martinverk, stålgjuteri,\nvalsverk, drageri, kallvalsvérk,\nkätting-fabrik, pressyerk, mek. verkstad och\nsågverk i Smedjebacken (Kopparb. l.).\n\nTillverkar martingöt, valsat järn och\nstål, dragen tråd, kallvalsade bänd,\nsvetsade armeringsnät, stålgjutgods,\nelektro-och maskinsmidd kätting,\nmanufaktur-smiden samt trävaror.\n\nTelegr.-adr. o. telefon: Valsverket,\nSmedjebacken. Postgiro: 24671.\n\nAkt.-kap.: 2,000,000 kr. Antal\nindustriarb.: 670. Tillv.-värde pr år: 16,000,000\nkr. — Bolaget grundat 1854.\n\nStyrelse: bruksdisp. Wiking Johnsson\n(ordf.), adv. Gösta Grönberg, civiling.\nHenry Tham, byrådir. John Udd, disp.\nRutger Wijkander.\n\nVerJcst. dir. o. disp.: Rutger\nWijkander.\n\nIngenjörer: H. Nore, J. Tägtström, S.\nNordgren, O. Knös, R. Moberg, S.\nGranhed, Sven Arwidson o. Arne Hallin.\n\nKamrer: Gust. Fredbäck.\n\nFörsäljare: Eric Westerfors.\n\nSmides AB. Bröderna Lundberg &amp;\nCo., Stockholm.\n\nTillverkar järnkonstruktioner och\ntransportanordningar; utför räck- och\nbyggnadssmiden samt elektr.\nsvetsningsarbeten. Varumärke: »Järnbröderna».\n\nKontor: Virkesvägen, Hammarby\nIndustriområde. Telegr.-adr.: Järnbröderna,\nStockholm. Telefon: 400041—42.\nPostgiro: 566.\n\nAkt.-kap.: 50,000 kr. Antal\nindustriarb.: 28. Prod.-värde pr år: 510,000 kr.\n\n—\tFirman etabl. 1877, bolag 1909.\n\nVerJcst. dir.: Sven Ohrstedt.\n\n*Smidesfabriken Standard, Carl E.\nBladh, Hjo.\n\nTillverkar manufaktursmide såsom\ngångjärn, lastbilsflaklås, limknektar och\nskruvtvingar, limhjul samt\nfoglimmaski-ner.\n\nTelefon: 250. Postgiro: 74923. —\nArb.-antal: 15. Tillv.-värde pr år: 250,000 kr.\n\n—\tFirman etabl. 1921.\n\nÄgare o. chef: fabr. Carl E. Bladh.\n\n\"Smidesfirman O. A. Möller,\n\nGöteborg.\n\nSe Bröderna Lönn, Göteborg.\n\n\"Smides- &amp; Järnsängsfabriks AB.,\n\nÖrbyhus.\n\nJärnsängs- och snickerifabrik i\nörbyhus (Uppsala l.). Tillverkar järn- o.\nträsängar samt stålrörsmöbler. Specialitet:\nsjukhussängar.\n\nTelefon: »Sängfabriken».\nEnsamförsälj.: AB. Sängfabriken, Stockholm,\nNorrlandsg. 16. Telefon: 101295.\n\nAkt.-kap.: 250,000 kr. Antal\nindustriarb.: 192. Tillv.-värde pr år: 1,640,000 kr.\n\nBolaget, grundat 1911, äges av AB.\nSängfabriken.\n\nStyrelse: dir. Eric Ericsson, dir. Tore\nEricsson, adv. Clas Östberg.\n\nVerkst. dir.: Tore Ericsson.\n\n\"Sigurd Smiths AB., Göteborg.\n\nSe AB. Plåtmanufaktur,\nGöteborgsfabrikerna, Göteborg.",
    "structured": {
        "1": {
            "name": "A B. Slutarps Snickerifabrik",
            "location": "Slutarp",
            "business": "Tillverkar likkistor vid fabrik i Slutarp (Skarab. l.)",
            "contact": {
                "office": "Slutarp",
                "phone": [
                    "Kinnarp 108"
                ],
                "postgiro": "74930"
            },
            "financials": {
                "capital": "60,000 kr",
                "employees": {
                    "Arb.-antal": 12
                },
                "annual_turnover": "115,000 kr",
                "annual_production_value": "115,000 kr"
            },
            "foundation_year": 1920,
            "corporation_year": 1945,
            "director": "Tage Norrländer"
        },
        "2": {
            "name": "Slöinge Träförädlings AB.",
            "location": "Slöinge",
            "business": "Tillverkar byggnadssnickerier, dörrar och fönster, trappor samt köks- och butiksinredningar vid fabrik i Slöinge (Hallands l.)",
            "contact": {
                "telegraph": "Träförädlingen, Slöinge",
                "phone": "6",
                "postgiro": "135495"
            },
            "financials": {
                "capital": "19,500 kr",
                "employees": {
                    "Arb.-antal": 15
                },
                "annual_turnover": "250,000 kr"
            },
            "foundation_year": 1901,
            "board": [
                {
                    "name": "Sven-Erik Christiansson",
                    "role": "dir. (ordf.)"
                },
                {
                    "name": "Sven-Ivar Christiansson",
                    "role": "lantbr."
                },
                {
                    "name": "Ernst Isberg",
                    "role": "byggm."
                },
                {
                    "name": "Karl Karlsson",
                    "role": "ombudsm."
                },
                {
                    "name": "Johannes Olsson",
                    "role": "godsäg."
                }
            ],
            "director": "S.-E. Christiansson"
        },
        "3": {
            "name": "Smedby Mek. Verkstad",
            "location": "Malmköping",
            "business": "Tillverkar grövre byggnadssmiden och cisterner; utför gas- och elektr. svetsningsarbeten samt metallisering vid mek. verkstad i Malmköping (Södermanl. l.)",
            "contact": {
                "phone": "126",
                "postgiro": "1$3$09"
            },
            "financials": {
                "employees": {
                    "Arb.-antal": 8
                }
            },
            "foundation_year": 1933,
            "owners": [
                "fabr. Martin Carlsson",
                "fabr. Olof M. Andersson"
            ]
        },
        "4": {
            "name": "Smedjebackens Valsverks AB.",
            "location": "Smedjebacken",
            "business": "Järnverk med martinverk, stålgjuteri, valsverk, drageri, kallvalsvérk, kätting-fabrik, pressyerk, mek. verkstad och sågverk i Smedjebacken (Kopparb. l.)",
            "contact": {
                "telegraph": "Valsverket, Smedjebacken",
                "phone": "Valsverket, Smedjebacken",
                "postgiro": "24671"
            },
            "financials": {
                "capital": "2,000,000 kr",
                "employees": {
                    "Antal industriarb.": 670
                },
                "annual_turnover": "16,000,000 kr"
            },
            "foundation_year": 1854,
            "board": [
                {
                    "name": "Wiking Johnsson",
                    "role": "bruksdisp. (ordf.)"
                },
                {
                    "name": "Gösta Grönberg",
                    "role": "adv."
                },
                {
                    "name": "Henry Tham",
                    "role": "civiling."
                },
                {
                    "name": "John Udd",
                    "role": "byrådir."
                },
                {
                    "name": "Rutger Wijkander",
                    "role": "disp."
                }
            ],
            "director": "Rutger Wijkander"
        },
        "5": {
            "name": "Smides AB. Bröderna Lundberg & Co.",
            "location": "Stockholm",
            "business": "Tillverkar järnkonstruktioner och transportanordningar; utför räck- och byggnadssmiden samt elektr. svetsningsarbeten. Varumärke: »Järnbröderna»",
            "contact": {
                "office": "Virkesvägen, Hammarby Industriområde",
                "phone": [
                    "400041-42"
                ],
                "postgiro": "566"
            },
            "financials": {
                "capital": "50,000 kr",
                "employees": {
                    "Antal industriarb.": 28
                },
                "annual_turnover": "510,000 kr"
            },
            "foundation_year": 1877,
            "corporation_year": 1909,
            "director": "Sven Ohrstedt"
        },
        "6": {
            "name": "Smidesfabriken Standard, Carl E. Bladh",
            "location": "Hjo",
            "business": "Tillverkar manufaktursmide såsom gångjärn, lastbilsflaklås, limknektar och skruvtvingar, limhjul samt foglimmaski-ner",
            "contact": {
                "phone": "250",
                "postgiro": "74923"
            },
            "financials": {
                "employees": {
                    "Arb.-antal": 15
                },
                "annual_turnover": "250,000 kr"
            },
            "foundation_year": 1921,
            "manager": "Carl E. Bladh"
        },
        "7": {
            "name": "Smidesfirman O. A. Möller",
            "location": "Göteborg",
            "predecessor": "Bröderna Lönn, Göteborg"
        },
        "8": {
            "name": "Smides- & Järnsängsfabriks AB.",
            "location": "Örbyhus",
            "business": "Järnsängs- och snickerifabrik i Örbyhus (Uppsala l.). Tillverkar järn- o. träsängar samt stålrörsmöbler. Specialitet: sjukhussängar",
            "contact": {
                "phone": "»Sängfabriken»",
                "postgiro": "250,000 kr"
            },
            "financials": {
                "employees": {
                    "Antal industriarb.": 192
                },
                "annual_turnover": "1,640,000 kr"
            },
            "foundation_year": 1911,
            "owners": [
                "AB. Sängfabriken"
            ],
            "board": [
                {
                    "name": "Eric Ericsson",
                    "role": "dir."
                },
                {
                    "name": "Tore Ericsson",
                    "role": "dir."
                },
                {
                    "name": "Clas Östberg",
                    "role": "adv."
                }
            ],
            "director": "Tore Ericsson"
        },
        "9": {
            "name": "Sigurd Smiths AB.",
            "location": "Göteborg",
            "predecessor": "AB. Plåtmanufaktur, Göteborgsfabrikerna, Göteborg"
        }
    }
}