{
    "original": "Kvårnshammar—Kyl\n\nKvarnshammars därnbruk, Begerön.\n\nSe AB. Qvarnshammars Jernbruk,\nDegerön.\n\nKvarnströms £abrNc$ Ä1l&lt;,\n\nStockholm.\n\nSliperi och förnicklingsfal^rik. . Utför\nförnicklingar och förkromnikgar m. m.\n\nKontor: Huvudstav. 49. Butik o.\nserviceverkstad: Kungsg. 75. Telegr.-adr.:\nKafab, Stockholm. Telefon: 520140.\nPostgiro: 3294.\n\nAkk-kap.: 100,000 kr. Antal\nindustriarb.: 80. Tillv.-värde pr år: 1,000,000 kr.\n— Firman etabl. 1901, bolag 1927.\n\nChef: dir. Helle Qvarnström.\n\nFabriks- o. försäljn.-chef: ing. Johan\nBlomqvist.\n\n’Kvarnsvedens Pappersbruk,\n\nKvarnsveden.\n\nPappersbruk med träsliperi och\nsulfitfabrik vid Kvarnsveden, Borlänge.\nTillverkar tidnings- och tidskriftspapper,\nbyggnadspapp (märke: »Dalpilen») och\nsulfitsprit; sulfitcellulosa och mek.\nträmassa för eget behov.\n\nTelefon: Borlänge 32200. —\nFörsäljningen sker genom Stora Kopparbergs\nBergslags AB., Falun. Telefon:\n»Bergslaget», Falun.\n\nAntal industriarb.: 800. Årstillv.:\n110,000 ton papper.\n\nPappersbruket, anlagt 1898—1900, äges\nav Stora Kopparbergs Bergslags AB. (Se\ndetta bolag.)\t-\n\nPlatschef: vakant.\n\nFörsäljn.-chef (Falun): dir. H. G.\nGullander.\n\nKvarnäs Tegelbruks AB. i Viby,\n\nKristianstad.\n\nTegelbruk vid Skånes Viby\n(Kristianst. l.). Tillverkar mur- och taktegel\nsamt dräneringsrör. Firman driver även\njordbruk.\n\nKontor: Kristianstad. Telefon: 13919.\nPostgiro: 91124. — Akt.-kapo.: 150,000 kr.\nAntal industriarb.: 40. Årstillv.: 2,7\nmilj. st. tegel varor. — Bolaget grundat\n1918.\n\nVerkst. dir.: Bertil Ewe.\n\nTegelmäst.: Rune Håkansson.\n\n* Kvillsfors Boblnfabrik, Kvillsfors.\n\nSe Nyboholms AB., Göteborg.\n\nAB. Kvillsfors Möbler, Kvillsfors.\n\nTillverkar möbler vid fabrik i\nKvillsfors (Jönköp. l.).\n\nTelefon: 5. Postgiro: 23466. —\nAkt.-kap.: 36,500 kr. Antal industriarb.: 25.\nTillv.-värde pr år: 200,000 kr. — Firman\netabl. 1926* mm bolag 1942,\n\nDisp.: Henry Wärre.\n\nKvänums Fläktfabrik, Gustavsson &amp;\nKarlsson, Kvänum,\n\nMek. verkstad i Kvänum (Skarab. L).\nTillverkar hö-, halm- och\nspannmålsfläktar, sammälds- och gröpkvarnar samt\nbe-tongblandare.\n\nTelefon: 111. Postgiro: 174954. —\nAntal industriarb.: 10. Tillv.-värde pr år:\n300,000 kr. — Firman etabl. 1939.\n\nÄgare o. chefer: fabr. Håkan\nGustavsson o. fabr. Arthur Karlsson.\n\n*Kurzels Fabriker AB., Malmö.\n\nSpinneri, väveri, färgeri och\nappretur-anstalt. Tillverkar väv-, trikå- och\nhemslöjdsgarner, dräkt-, kapp- och\nklänningstyger, mattor, skur-, damm- och\ndiskdukar.\n\nPostadr.: Malmö 7. Telegr.-adr.:\nKiir-zels, Malmö. Telefon: »Kiirzels Fabriker».\nPostgiro: 37825.\n\nAkt.-kap.: 1,000,000 kr. Antal\nindustriarb.: 600. — Firman etabl. 1896, bolag\n1919 under namn av AB. Fr. Kurzel,\nnuv. namn 1945.\n\nStyrelse: försäljn.-chef H. V. Hetling,\ndisp. Gerhard G. Nyebölle, adv. Bo\nPfan-nenstill.\n\nVerkst. dir.: Gerhard G. Nyebölle.\n\nFörsäljn.- o. inköpschef: H. V.\nHetling.\n\n* Hermann Kurzel, Spinneri AB.,\n\nGöteborg.\n\nSe Spinneri AB. Hermann Kurzel,\nGöteborg.\n\nKyl-Automatik Fabriks AB.,\n\nMjölby.\n\nFinmek. verkstad i Mjölby (Östergötl.\n1.). Tillverkar detaljer för\nkylanläggningar och kylskåp såsom varmpressade\nmässingsdetaljer, filter, torkare,\nav-stängnings- och backventiler,\nautomatiska och termostatiska\néxpansionsven-tiler, konstanttryckventiler, automatiska\nvattenventiler, termostater m. m.\n\nTelefon: 332. Postgiro: 267332.\n\nAkt.-kap.: 48,000 kr. Antal industri-\n\n313*",
    "structured": {
        "1": {
            "name": "Kvarnshammars därnbruk, Begerön. Se AB. Qvarnshammars Jernbruk",
            "location": "Degerön",
            "business": "Sliperi och förnicklingsfabrik. Utför förnicklingar och förkromningar m. m.",
            "contact": {
                "office": "Huvudstav. 49",
                "phone": [
                    "520140"
                ],
                "telegraph": "Kafab, Stockholm",
                "postgiro": "3294"
            },
            "financials": {
                "capital": "100,000 kr",
                "employees": {
                    "industriarb": 80
                },
                "annual_turnover": "1,000,000 kr",
                "annual_production_value": "1,000,000 kr"
            },
            "foundation_year": 1901,
            "corporation_year": 1927,
            "director": "dir. Helle Qvarnström",
            "factory_office": "Säljkontor: Kungsg. 75"
        },
        "2": {
            "name": "Kvarnströms £abrNc$ Ä1l<, Stockholm",
            "business": "Utför förnicklingar och förkromningar m. m."
        },
        "3": {
            "name": "Kvarnsvedens Pappersbruk, Kvarnsveden",
            "location": "Borlänge",
            "business": "Tillverkar tidnings- och tidskriftspapper, byggnadspapp (märke: »Dalpilen») och sulfitsprit; sulfitcellulosa och mek. trämassa för eget behov.",
            "contact": {
                "phone": [
                    "Borlänge 32200"
                ],
                "sales_offices": [
                    {
                        "location": "Falun",
                        "phone": "»Bergslaget», Falun"
                    }
                ]
            },
            "financials": {
                "employees": {
                    "industriarb": 800
                },
                "annual_production_value": "110,000 ton papper"
            }
        },
        "4": {
            "name": "Kvarnäs Tegelbruks AB. i Viby, Kristianstad",
            "location": "Skånes Viby (Kristianst. l.)",
            "business": "Tillverkar mur- och taktegel samt dräneringsrör. Firman driver även jordbruk.",
            "contact": {
                "office": "Kristianstad",
                "phone": [
                    "13919"
                ],
                "postgiro": "91124"
            },
            "financials": {
                "capital": "150,000 kr",
                "employees": {
                    "industriarb": 40
                },
                "annual_production_value": "2,700,000 st. tegel varor"
            }
        },
        "5": {
            "name": "AB. Kvillsfors Möbler, Kvillsfors",
            "location": "Kvillsfors (Jönköp. l.)",
            "business": "Tillverkar möbler vid fabrik i Kvillsfors (Jönköp. l.).",
            "phone": [
                "5"
            ],
            "postgiro": "23466",
            "financials": {
                "capital": "36,500 kr",
                "employees": {
                    "industriarb": 25
                },
                "annual_production_value": "200,000 kr"
            }
        },
        "6": {
            "name": "Kvänums Fläktfabrik, Gustavsson & Karlsson, Kvänum",
            "location": "Kvänum (Skarab. L)",
            "business": "Tillverkar hö-, halm- och spannmålsfläktar, samt sammälds- och gröpkvarnar, samt betongblandare.",
            "contact": {
                "phone": [
                    "111"
                ],
                "postgiro": "174954"
            },
            "financials": {
                "employees": {
                    "industriarb": 10
                },
                "annual_production_value": "300,000 kr"
            }
        },
        "7": {
            "name": "Kurzels Fabriker AB., Malmö",
            "business": "Tillverkar väv-, trikå- och hemslöjdsgarner, dräkt-, kapp- och klänningstyger, mattor, skur-, damm- och diskdukar.",
            "contact": {
                "postgiro": "37825"
            },
            "financials": {
                "capital": "1,000,000 kr",
                "employees": {
                    "industriarb": 600
                }
            }
        },
        "8": {
            "name": "Kyl-Automatik Fabriks AB., Mjölby",
            "location": "Mjölby (Östergötl. 1.)",
            "business": "Tillverkar detaljer för kylanläggningar och kylskåp såsom varmpressade mässingsdetaljer, filter, torkare, avstängnings- och backventiler, automatiska och termostatiska expansionsventiler, konstanttryckventiler, automatiska vattenventiler, termostater m. m.",
            "contact": {
                "phone": [
                    "332"
                ],
                "postgiro": "267332"
            },
            "financials": {
                "capital": "48,000 kr",
                "employees": {
                    "industriarb": 313
                }
            }
        }
    }
}