{
    "original": "S:t Erih—8’B Bygge\n\n*AB. S:t Eriks Lervarufabriker,\n\nU ppsala.\n\nTegelbruk med betongvarufabrik.\nTillverkar mur-, fasad-, golv-,\nfasadbeklädnads- och håltegel (även högporöst),\ntaktegel (falsat och ofalsat), kabeltegel,\ndräneringsrör, mellanväggsplattor, öppna\nspisar, byggnadskeramik såsom\nomfattningstegel, reliefer m. m.; betongrör\nbrunnsringar, kulvertar, trottoarplattor,\ntrappsteg, hålsten, vattenbassänger,\nstag-skivor m. m. Bolaget driver även\nförsäljning av byggnadsmateriel.\n\nTelefon: 30210, 32810 o. 32820.\nPostgiro: 34153.\n\nAkt.-kap.: 337,500 kr. Antal\nindustriarb.: 60. Tillv.-värde pr år: 800,000 kr.\n— Bolaget grundat 1907.\n\nStyrelse: arkitekt Sven Wallander\n(ordf.), hantverkare Curt Dalhagen, herr\nDavid Frisell, ombudsm. Erik Persson,\naffärschef Hj. Wedholm.\n\nVerkst. dir.: Erik Persson.\n\nDisp.: Erik Sintring.\n\n*Sannes Söners AB-, Uddevalla,\n\nSe Hånsfors Bruks AB., Göteborg.\n\n*K. D. Santesson AB., Eslöv.\n\nSkofabrik. Tillverkar som specialitet\nhandgjorda skodon.\n\nTelegr.-adr.: Santesson, Eslöv. Telefon:\n414 o. 355. Postgiro: 79406.\n\nAkt.-kap.: 170,000 kr. Antal\nindustriarb.: 40. — Firman etabl. 1904, bolag\n1934.\n\nStyrelse: fabr. Kristian D. Santesson\n(ordf.), adv. P. I. Hedener, adv. Wilh.\nPenser, disp. Arvid Santesson, disp.\nGustaf D. Santesson.\n\nVerkst. direktörer: Arvid Santesson o.\nGustaf D. Santesson.\n\n*Santorin-Verken AB., Stockholm,\n\nTillverkar mellanväggsplattor av\nslaggbetong vid fabriker i Stockholm,\nGöteborg, Trelleborg och Jungfrusund samt\nträullsplattor vid fabrik i Vallentuna (de\nbåda sistnämnda i Sthlms l.).\nVarumärken: »TBG»-slaggplattor och\n»ABT»-trä-ullsplattor» Bolaget driver även\nförsäljning av elektr. lödkolvar (»Vici»).\n\nHuvudkontor: Stockholm, Kungsg. 27.\nTelegr.-adr.: Elam, Stockholm. Telefon:\n112242, 102242 o. 102281. Postgiro:\n155372.\n\nAkt.-kap.: 250.000 kr. Antal\nindustriarb.: 70. Tillv.-värde pr år: 2,000,000 kr.\n\nBolaget grundat 1935, ombildat 1939.\n\nStyrelse: civiling. Georg Ehrenborg\n(ordf.), dir. P.-C. af Buren, dir. Alfred\nNordlund.\n\nVerkst. dir.: Alfred Nordlund,\n\nV. verkst. dir.: P.-C. af Burén.\n\nSäpo, Fabriks AB., Hälsingborg.\n\nSe Fabriks AB. Säpo, Hälsingborg.\n\nSaturnus, AB. Fabriken, Malmö.\n\nSe AB. Fabriken Saturnus, Malmö.\n\nSaxon &amp; Lindströms Förlags AB.,\n\nStockholm.\n\nTidnings- och boktryckeri. Bolaget\nidkar huvudsakligen förlagsrörelse och\nutgiver böcker och tidskrifter.\n\nKontor: Sveavägen 98. Telefon: »Saxon\n&amp; Lindströms». Postgiro: 1698.\n\nAkt.-kap.: 750,000 kr. — Bolaget\ngrundat 1928.\n\nStyrelse: dir. Edvard Lindström,\nbokförläggare David Lindström, red. Lars\nSaxon.\n\nVerkst. direktörer: E. Lindström o. D.\nLindström.\n\nChefred.: L. Saxon.\n\n*Saxtorps Murbruksfabriks AB.,\n\nLandskrona.\n\nSe J. M. Lindelöf Träförädlingsfabrik,\nLandskrona.\n\n*Saxvikens Sågverk, Mora.\n\nSe AB. Statens Skogsindustrier,\nStockholm.\n\n*AB, S-B Bygge, Växjö.\n\nSågverk, hyvleri-, snickeri- och\nlådfabrik i Sävsjöström (Kronob. l.).\nTillverkar monteringsfärdiga trähus, lådor\nsamt sågade och hyvlade trävaror.\nVarumärke: »SB bygge».\n\nHuvudkontor: Växjö. Telefon: 2557,\n2558 o. 2758. Avd.-kontor: Göteborg,\nKungsg. 4, telefon: 119357; Malmö,\nStortorget 21, telefon: 79915.\n\nAkt.-kap.: 45,000 kr. Antal\nindustriarb.: 50. Tillv.-värde pr år: 1,700,000 kr.\n— Firman etabl. 1932, under namn\nSäv-sjöströms Lådfabrik, bolag o. nuv. namn\n1943.\n\nStyrelse: ing. Conrad Persson (ordf.),\nkamrer Magnus Norberg, inköpschef\nGustav Svensson.\n\nVerkst. dir.: Magnus Norberg.\n\nFörsäljn.-chef: Conrad Persson.\n\nInköpschef: Gustav Svensson.",
    "structured": {
        "1": {
            "name": "S:t Eriks Lervarufabriker AB",
            "location": "Uppsala",
            "business": "Tegelbruk med betongvarufabrik",
            "products": "Tillverkar mur-, fasad-, golv-, fasadbeklädnads- och håltegel (även högporöst), taktegel (falsat och ofalsat), kabeltegel, dräneringsrör, mellanväggsplattor, öppna spisar, byggnadskeramik såsom omfattningstegel, reliefer m. m.; betongrör, brunnsringar, kulvertar, trottoarplattor, trappsteg, hålsten, vattenbassänger, stag-skivor m. m. Bolaget driver även försäljning av byggnadsmateriel.",
            "contact": {
                "phone": [
                    "30210",
                    "32810",
                    "32820"
                ],
                "postgiro": "34153"
            },
            "financials": {
                "capital": "337,500 kr",
                "employees": {
                    "industriarb": 60
                },
                "annual_turnover": "800,000 kr",
                "annual_production_value": "800,000 kr"
            },
            "foundation_year": 1907,
            "board": [
                {
                    "name": "arkitekt Sven Wallander",
                    "role": "ordf."
                },
                {
                    "name": "hantverkare Curt Dalhagen",
                    "role": null
                },
                {
                    "name": "herr David Frisell",
                    "role": null
                },
                {
                    "name": "ombudsm. Erik Persson",
                    "role": null
                },
                {
                    "name": "affärschef Hj. Wedholm",
                    "role": null
                }
            ],
            "director": "Erik Persson"
        },
        "2": {
            "name": "K. D. Santesson AB",
            "location": "Eslöv",
            "business": "Skofabrik",
            "products": "Tillverkar som specialitet handgjorda skodon",
            "contact": {
                "phone": [
                    "414",
                    "355"
                ],
                "postgiro": "79406"
            },
            "financials": {
                "capital": "170,000 kr",
                "employees": {
                    "industriarb": 40
                }
            },
            "foundation_year": 1904,
            "corporation_year": 1934,
            "board": [
                {
                    "name": "fabr. Kristian D. Santesson",
                    "role": "ordf."
                },
                {
                    "name": "adv. P. I. Hedener",
                    "role": null
                },
                {
                    "name": "adv. Wilh. Penser",
                    "role": null
                },
                {
                    "name": "disp. Arvid Santesson",
                    "role": null
                },
                {
                    "name": "disp. Gustaf D. Santesson",
                    "role": null
                }
            ],
            "director": "Arvid Santesson",
            "managing_director": "Arvid Santesson"
        },
        "3": {
            "name": "Santorin-Verken AB",
            "location": "Stockholm",
            "business": "Tillverkar mellanväggsplattor av slaggbetong och träullsplattor",
            "products": "Varumärken: »TBG»-slaggplattor och »ABT»-trä-ullsplattor. Bolaget driver även försäljning av elektr. lödkolvar (»Vici»).",
            "contact": {
                "phone": [
                    "112242",
                    "102242",
                    "102281"
                ],
                "postgiro": "155372"
            },
            "financials": {
                "capital": "250,000 kr",
                "employees": {
                    "industriarb": 70
                },
                "annual_turnover": "2,000,000 kr",
                "annual_production_value": "2,000,000 kr"
            },
            "foundation_year": 1935,
            "corporation_year": 1939,
            "board": [
                {
                    "name": "civiling. Georg Ehrenborg",
                    "role": "ordf."
                },
                {
                    "name": "dir. P.-C. af Buren",
                    "role": null
                },
                {
                    "name": "dir. Alfred Nordlund",
                    "role": null
                }
            ],
            "director": "Alfred Nordlund",
            "managing_director": "Alfred Nordlund"
        },
        "4": {
            "name": "S-B Bygge AB",
            "location": "Växjö",
            "business": "Sågverk, hyvleri-, snickeri- och lådfabrik",
            "products": "Tillverkar monteringsfärdiga trähus, lådor samt sågade och hyvlade trävaror. Varumärke: »SB bygge».",
            "contact": {
                "phone": [
                    "2557",
                    "2558",
                    "2758"
                ],
                "postgiro": null
            },
            "financials": {
                "capital": "45,000 kr",
                "employees": {
                    "industriarb": 50
                },
                "annual_turnover": "1,700,000 kr",
                "annual_production_value": "1,700,000 kr"
            },
            "foundation_year": 1932,
            "corporation_year": 1943,
            "board": [
                {
                    "name": "ing. Conrad Persson",
                    "role": "ordf."
                },
                {
                    "name": "kamrer Magnus Norberg",
                    "role": null
                },
                {
                    "name": "inköpschef Gustav Svensson",
                    "role": null
                }
            ],
            "director": null,
            "managing_director": "Magnus Norberg",
            "sales_manager": "Conrad Persson",
            "manager": "Gustav Svensson"
        }
    }
}