{
    "original": "Eck—Edgren\n\n*Eck, Elektriska AB., Partille.\n\nSe Elektriska AB. Morén, Partille.\n\nF. Eck’s Fabriker AB., Nacka.\n\nMek. verkstad i Sickla, Nacka (Sthlms\n1.). Tillverkar värmeledningsradiatorer\nav plåt (märke: »X-radiatorer»),\nflyttbara, fotogeneldade och elektriska\nvärmeradiatorer (märke: »Calex»),\nvarmlufts-batterier, expansionskärl, svetsnings- och\npressningsarbeten m. m.\n\nTelefon: Stockholm 404111—12 o.\n404160. Postgiro: 1212.\n\nAkt.-kap.: 500,000 kr. Antal\nindustriarb.: 106. Tillv.-värde pr år: 2,300,000 kr.\n\n—\tFirman etabl. 1925, bolag 1943.\n\nVerkst. dir.: H. Befrits.\n\nDriftsing.: E. Cedervall.\n\n*Eds Cellulosafabriks ABEdsbruk.\n\nSulfatfabrik vid Edsbruk (Kalmar l.).\nTillverkar sulfatcellulosa, flytande harts\noch råterpentin. Bolaget idkar jämväl\njordbruk och kvarnrörelse.\n\nTelegr.-adr.: Edsfabrik, Gamleby.\nTelefon: Västra Ed 37.\n\nAkt.-kap.: 900,000 kr. Antal\nindustriarb.: 109. Årstillv.: 9,000 ton torr\nsulfatcellulosa. — Bolaget grundat 1888.\n\nStyrelse: bergsing. T. An. Tesch (ordf.),\nadv. Thure Essen, övering, Ernst\nHåkansson.\n\nBruksint.: V. A. Kotilainen.\n\nTekn. chef: disp. Tage Hobro.\n\nKassör: Carl Svensson.\n\n*Eds Tegel AB., Edsbruk.\n\nTillverkar mur- och taktegel samt rör\nvid tegelbruk i Edsbruk (Kalm. l.).\n\nTelefon: Västra Ed 70. — Akt.-kap.:\n60,000 kr. Antal industriarb.: 20.\nÅrstillv.: 0,8 milj. st. tegelvaror. — Bolaget\ngrundat 1915.\n\nStyrelse: kommunalkamrer Axel\nMilton (ordf.), tegelmäst. Adolf Holmgren,\nhemmansäg. David Larsson.\n\nVerkst. dir.: Axel Milton.\n\nTegelmäst.: Adolf Holmgren.\n\nEda AB., Eda.\n\nSågverk, träullfabrik, kvarn och\nelektrisk kraftstation vid Eda (Värml. l.).\nTillverkar plank, bräder och träull.\n\nTelegr.-adr.: Edaträ, Eda. Telefon: 1.\n\n—\tAkt.-kap.: 55,000 kr. Antal\nindustriarb.: 20. Tillv.-värde pr år: 150,000 kr.\n\n—\tBolaget grundat 1867.\n\nStyrelse: f. d. landsfiskal G. H.\nLöfven-holm (ordf.), disp. Anders Ohlsson,\ncivilek. Gunnar Ohlsson.\n\nVerkst. styrelseled.: A. Ohlsson.\n\nAB. Eda Glasbruk, Eda.\n\nTillverkar hushållsglas, kristallglas oeb\nkonservglas samt kem.-tekn. glas vid\nglasbruk i Eda (Värml. l.).\n\nTelegr.-adr.: Edaglas, Eda. Telefon: 41.\nPostgiro: 274212.\n\nAkt.-kap.: 60,000 kr. Antal\nindustriarb.: 100. Tillv.-värde pr år: 650,000 kr.\n\n—\tBolaget grundat 1943.\n\nStyrelse: dir. Carl Svensson (ordf.),\ngenéralkonsul Harry Bratt, disp. Birger\nEklundh, försäljningschef Axel Nystadius.\nVerkst. dir.: Birger Eklundh.\nFörsäljn.-chef: Axel Nystadius.\n\nEdeby Marmorbrott AB., Eölö.\n\nMarmorbrott vid Edeby, Hölö\n(Södermanl. l.). Bryter och förädlar såväl\nvitgrön som grön marmor.\n\nTelefon: Hölö 22 o. 130. Postgiro:\n»29162. Avd.-kontor: Stockholm,\nNorr-landsg. 18, telefon: 108691. — Akt.-kap.:\n50,000 kr. Antal industriarb.: 60.\nTillv.-värde pr år: 700,000 kr. —\nMarmorbrytningen upptogs 1922, nuv. bolag grundat\n1945.\n\nVerkst. dir.: Georg Lundberg.\n\n*J. A. Edenholm, Culdlistfabrik,\n\nGustafs.\n\nTillverkar ram- och tapetlister,\ngardinstänger, kornischer och speglar vid\nfabrik i Gustafs (Kopparb. l.).\n\nTelefon: Borlänge 40021. Postgiro:\n12718. Avd.-kontor: Stockholm,\nHerku-lesg. 26, telefon: 109254. — Antal\nindustriarb.: 42, Tillv.-värde pr år: 500,000\nkr. — Firman etabl. 1905.\n\nÄgare o. chef: fabr. J\". A. Edenholm.\nChefer för Stockholmskontoret: H. P.\nMyren o. Martin Lindahl.\n\n*Edfasts Skofabrik, Råneå.\nSe Bröderna Edfasts Skofabrik, Råneå.\n\n*AB. Edfeldt &amp; Karlssons\nMöbelfabrik, T annefors.\nSe AB. Tanneforsmöbler, Tannefors.\n\n*Paul Edgren, Eskilsäter.\n\nSågverk, hyvleri och lådfabrik samt\nce-mentvarufabrik vid Gaperhult, Eskilsäter\n(Värml. l.). Tillverkar sågade och\nhyvlade trävaror, lådbräder, props och\nrundvirke samt cementtaktegel. Firman\nbedriver även jordbruk och skogshantering.\n\nTelegr.-adr.: Edgren, Säffle. Telefon:\nGaperhult 2. Postgiro: 83143. —\nArb.-antal: 12. Tillv.-värde pr år; 40,000 kr.\n\n—\tFirman etabl. 1884.\n\nÄgare o. chef: godsäg. Paul Edgren.",
    "structured": {
        "1": {
            "name": "Eck, Elektriska AB.",
            "location": "Partille",
            "business": "Tillverkar värmeledningsradiatorer av plåt, flyttbara, fotogeneldade och elektriska värmeradiatorer, varmlufts-batterier, expansionskärl, svetsnings- och pressningsarbeten m. m.",
            "contact": {
                "office": "Mek. verkstad i Sickla, Nacka (Sthlms 1.)",
                "phone": [
                    "Stockholm 404111",
                    "Stockholm 404112",
                    "Stockholm 404160"
                ],
                "postgiro": "1212"
            },
            "financials": {
                "capital": "500,000 kr",
                "employees": {
                    "industriarb": 106
                },
                "annual_turnover": "2,300,000 kr",
                "annual_production_value": "2,300,000 kr"
            },
            "foundation_year": 1925,
            "corporation_year": 1943,
            "board": [
                {
                    "name": "H. Befrits",
                    "role": "Verkst. dir."
                }
            ]
        },
        "2": {
            "name": "Eds Cellulosafabriks AB",
            "location": "Edsbruk",
            "business": "Tillverkar sulfatcellulosa, flytande harts och råterpentin. Bolaget idkar jämväl jordbruk och kvarnrörelse.",
            "contact": {
                "telegraph": "Edsfabrik, Gamleby",
                "phone": "Västra Ed 37"
            },
            "financials": {
                "capital": "900,000 kr",
                "employees": {
                    "industriarb": 109
                },
                "annual_production_value": "9,000 ton torr sulfatcellulosa"
            },
            "foundation_year": 1888,
            "board": [
                {
                    "name": "T. An. Tesch",
                    "role": "bergsing."
                },
                {
                    "name": "Thure Essen",
                    "role": "adv."
                },
                {
                    "name": "Ernst Håkansson",
                    "role": "övering"
                }
            ]
        },
        "3": {
            "name": "Eds Tegel AB.",
            "location": "Edsbruk",
            "business": "Tillverkar mur- och taktegel samt rör vid tegelbruk i Edsbruk (Kalm. l.)",
            "contact": {
                "phone": "Västra Ed 70"
            },
            "financials": {
                "capital": "60,000 kr",
                "employees": {
                    "industriarb": 20
                },
                "annual_production_value": "0,8 milj. st. tegelvaror"
            },
            "foundation_year": 1915,
            "board": [
                {
                    "name": "Axel Milton",
                    "role": "kommalkamrer"
                },
                {
                    "name": "Adolf Holmgren",
                    "role": "tegelmäst."
                },
                {
                    "name": "David Larsson",
                    "role": "hemmansäg."
                }
            ]
        },
        "4": {
            "name": "Eda AB.",
            "location": "Eda",
            "business": "Sågverk, träullfabrik, kvarn och elektrisk kraftstation vid Eda (Värml. l.). Tillverkar plank, bräder och träull.",
            "contact": {
                "telegraph": "Edaträ, Eda",
                "phone": "1"
            },
            "financials": {
                "capital": "55,000 kr",
                "employees": {
                    "industriarb": 20
                },
                "annual_turnover": "150,000 kr"
            },
            "foundation_year": 1867,
            "board": [
                {
                    "name": "G. H. Löfvenholm",
                    "role": "f. d. landsfiskal"
                },
                {
                    "name": "Anders Ohlsson",
                    "role": "disp."
                },
                {
                    "name": "Gunnar Ohlsson",
                    "role": "civilek."
                }
            ]
        },
        "5": {
            "name": "AB. Eda Glasbruk",
            "location": "Eda",
            "business": "Tillverkar hushållsglas, kristallglas oeb konservglas samt kem.-tekn. glas vid glasbruk i Eda (Värml. l.).",
            "contact": {
                "telegraph": "Edaglas, Eda",
                "phone": "41",
                "postgiro": "274212"
            },
            "financials": {
                "capital": "60,000 kr",
                "employees": {
                    "industriarb": 100
                },
                "annual_production_value": "650,000 kr"
            },
            "foundation_year": 1943,
            "board": [
                {
                    "name": "Carl Svensson",
                    "role": "dir."
                },
                {
                    "name": "Harry Bratt",
                    "role": "genéralkonsul"
                },
                {
                    "name": "Birger Eklundh",
                    "role": "disp."
                },
                {
                    "name": "Axel Nystadius",
                    "role": "försäljningschef"
                }
            ],
            "director": "Birger Eklundh",
            "sales_manager": "Axel Nystadius"
        },
        "6": {
            "name": "Edeby Marmorbrott AB.",
            "location": "Eölö",
            "business": "Bryter och förädlar såväl vitgrön som grön marmor.",
            "contact": {
                "phone": [
                    "Hölö 22",
                    "Hölö 130"
                ],
                "postgiro": "29162",
                "factory_office": "Avd.-kontor: Stockholm, Norr-landsg. 18, telefon: 108691"
            },
            "financials": {
                "capital": "50,000 kr",
                "employees": {
                    "industriarb": 60
                },
                "annual_production_value": "700,000 kr"
            },
            "foundation_year": 1945,
            "board": [
                {
                    "name": "Georg Lundberg",
                    "role": "Verkst. dir."
                }
            ]
        },
        "7": {
            "name": "J. A. Edenholm, Culdlistfabrik",
            "location": "Gustafs",
            "business": "Tillverkar ram- och tapetlister, gardinstänger, kornischer och speglar vid fabrik i Gustafs (Kopparb. l.)",
            "contact": {
                "phone": "Borlänge 40021",
                "postgiro": "12718",
                "head_office": "Avd.-kontor: Stockholm, Herku-lesg. 26, telefon: 109254"
            },
            "employees": {
                "industriarb": 42
            },
            "annual_production_value": "500,000 kr",
            "foundation_year": 1905,
            "owner": "fabr. J. A. Edenholm",
            "manager": "fabr. J. A. Edenholm",
            "sales_manager": "H. P. Myren"
        },
        "8": {
            "name": "Paul Edgren",
            "location": "Eskilsäter",
            "business": "Sågverk, hyvleri och lådfabrik samt cementvarufabrik vid Gaperhult, Eskilsäter (Värml. l.). Tillverkar sågade och hyvlade trävaror, lådbräder, props och rundvirke samt cementtaktegel.",
            "contact": {
                "telegraph": "Edgren, Säffle",
                "phone": "Gaperhult 2",
                "postgiro": "83143"
            },
            "employees": {
                "industriarb": 12
            },
            "annual_production_value": "40,000 kr",
            "foundation_year": 1884,
            "owner": "godsäg. Paul Edgren",
            "manager": "godsäg. Paul Edgren"
        }
    }
}