{
    "original": "Skogsägarna—-S kr af\n\n* Skogsägarnas Industri AB. (SIAB),\n\nVäxjö.\n\nTräimp regnerings verk i Hultsfred\n(Kalmar l.) och i Vislanda (Kronob. l.)\nsamt sågverk i Hallabro (Blek. l.), Horn\n(österg. l.), Ljungby och Vislanda\n(Kronob. l.) samt i Godegård (österg. l.).\nTillverkar sågade och hyvlade trävaror samt\nimpregnerade stolpar, slipérs m. m.\n\nKontor: Växjö. Telegr.-adr.: Siab,\nVäxjö. Telefon: 3560. Postgiro: 271675.\n\nAkt.-kap.: 500,000 kr. Tillv.-värde pr\når: 5,000,000 kr. — Bolaget, grundat\n1943, äger Hultsfreds Träförädlings AB.\nmed AB. Standardhus och AB. Svenska\nIdealhus, Hultsfred, Restad AB.,\nNorrköping, Lantmännens Byggnads AB.,\nLund samt Westerviks Trävaru AB.,\nVästervik.\n\nStyrelse: godsäg. Hadar Hedborg\n(ordf.), ryttm. Björn Hyltén-Cavallius,\nlandstingsm. David Johansson, godsäg.\nErik v. Kantzow, kapten Axel\nManner-skantz, godsäg. Arvid Nilsson,\nlandstingsm. Karl Nilsson, lantbr. Yngve\nPagels, frih. Gösta Rappe, frih. Louis\nWrede.\n\nVerkst. dir.: Gösta Edström.\n\nS. J. Skohgs Verkstäder, Örebro.\n\nKoppar- och grovplåtslageri, mek.\nvétk-stad och metallgjuteri. Tillverkar\nvarmvattenberedare och badkaminer,\nmotströmsapparater, värmeledningspannor\noch genomströmningsvarmvattenberedare\n(märke: »ESVE»), elektr.\nvarmvattenberedare^ (märke: »El-ESVE»),\nångfördel-ningslådor samt golvslipningsmaskiner.\n\nTelegr.-adr.: Skohgs, Örebro. Telefon:\n10272. Postgiro: 28211.\n\nAntal industriarb.: 20. Tillv.-värde pr\når: 500,000 kr. — Firman etabl. 1874.\n\nÄgare: fru A. Skohg.\n, Verkmäst.: Karl Skohg.\n\n*Skokompaniet, Mjällom.\n\nTillverkar skidkangor, arbetsskor,\nvand-rarskor och sandaler vid fabrik i Mjällom\n(Västernorrl. l.).\n\nTelefon: 16. Postgiro: 132021. — Antal\narb.: 26. Tillv.-värde pr år: 740,000 kr.\n— Firman etabl. 1937.\n\nÄgare o. chefer: fabr. Sven Melinder,\nfabr. Sigurd Melinder o. fabr. Ingemar\nMelinder.\n\n*Skotästfabriken, Svenska, JWréÉiad.\n\nSe AB. Svenska Skolästfabrikcn,\nJärre-stad.\n\nAB* Skorna-Borst, Malmö.\n\nTillverkar syntetisk skomakeriborst\n(märke: »Skoma-Borst»).\n\nKontor: Söderg. 14. Telegr.-adr.:\nSko-maborst, Malmö. Telefon: 78335.\nPostgiro: 148482.\n\nAkt.-kap.: 20,000 kr. Tillv.-värde pr år:\n40,000 kr. — Bolaget grundat 1942.\nVerkst. dir.: Edgar Nathan.\t£\n\nDisp.: Olof Malmström.\n\nSkoogs Motorfabrik, Bröderna,\n\nBorlänge.\n\nSe Bröd. Skoogs Motorfabrik, Borlänge.\n\nAB. Skorpeds Trävaruindustri,\n\nSkorped.\n\nTillverkar sågade och hyvlade trävaror\nvid sågverk i Skorped (Västernorrl. l.).\n\nTelefon: 54. Postgiro: 31614. -\nAkt.-kap.: 100,000 kr. Antal industriarb.: 40.\nTillv.-värde pr år: 250,000 kr. Årstillv.:\n700 stds trävaror. — Firman etabl. 1942,\nnuv. bolag 1945.\n\nVerkst. dir..- Ture Larsson (Sthlm).\nPlatschef: And. Andersson.\n\n*Skriv- &amp; Ritboks-AB., Årlöv.\n\nBokbinderi och tryckeri i Arlöv\n(Malmöh. l.), Gävle och Nässjö. Tillverkar\nskriv- och ritbÖcker, utför bokbinderi- och\ntryckeri arbeten.\n\nHuvudkontor: Arlöv. Telegr.-adr.:\nSkrivrit, Malmö. Telefon; Malmö 430489.\nPostgiro: 5278. Avd.-kontor: Gävle,\ntelefon: 5206; Nässjö, telefon: 95. Nederlag:\nStockholm, Vattug. 9, telefon: 230505;\nGöteborg, Köpmansg. 50, telefon: 113681.\n\nBolaget, grundat 1920, är anslutet till\nAB. Sveriges Litografiska Tryckerier,\nStockholm. (Se detta bolag.)\nStyrelse o. verkst. dir.: Helge\nÅkerlund-Disponenter: i Gävle: Per Mandell; i\nNässjö: H. A. Liickander.\n\nKontorschefer: i Arlöv: Alfr.\nAndersson; i Stockholm: disp. G. Åhlstrom; i\nGöteborg: disp. J. Alb. Munther.\n\n*Skrombergaverken, Ekeby.\nSe Höganäs-Billesholms AB., Höganäs.\n\nSkrufs Nya Glasbruks AB.,\n\nSkruv.\n\nGlasbruk vid Skruv (Kronob. l.).\nTillverkar som specialitet servis- och\nrestauran tglas samt kristallglas.\n\nTelegr.-adr.: Glasbruket. Skruv.\nTelefon: 1 o. 31. Postgiro: 99700.",
    "structured": {
        "1": {
            "name": "Skogsägarnas Industri AB. (SIAB)",
            "location": "Växjö",
            "business": "Träimpregneringsverk, sågverk",
            "products": "Tillverkar sågade och hyvlade trävaror samt impregnerade stolpar, slipérs m. m.",
            "contact": {
                "office": "Växjö",
                "phone": [
                    "3560"
                ],
                "postgiro": "271675",
                "telegraph": "Siab, Växjö",
                "factory_office": "Hultsfred (Kalmar l.), Vislanda (Kronob. l.)"
            },
            "financials": {
                "capital": "500,000 kr",
                "annual_turnover": "5,000,000 kr",
                "annual_production_value": "5,000,000 kr"
            },
            "foundation_year": 1943,
            "board": [
                {
                    "name": "Hadar Hedborg",
                    "role": "ordf."
                },
                {
                    "name": "Björn Hyltén-Cavallius",
                    "role": "ryttm."
                },
                {
                    "name": "David Johansson",
                    "role": "landstingsm."
                },
                {
                    "name": "Erik v. Kantzow",
                    "role": "godsäg."
                },
                {
                    "name": "Axel Manner-skantz",
                    "role": "kapten"
                },
                {
                    "name": "Arvid Nilsson",
                    "role": "godsäg."
                },
                {
                    "name": "Karl Nilsson",
                    "role": "landstingsm."
                },
                {
                    "name": "Yngve Pagels",
                    "role": "lantbr."
                },
                {
                    "name": "Gösta Rappe",
                    "role": "frih."
                },
                {
                    "name": "Louis Wrede",
                    "role": "frih."
                }
            ],
            "director": "Gösta Edström"
        },
        "2": {
            "name": "S. J. Skohgs Verkstäder",
            "location": "Örebro",
            "products": "Tillverkar varmvattenberedare och badkaminer, motströmsapparater, värmeledningspannor och genomströmningsvarmvattenberedare (märke: »ESVE»), elektr. varmvattenberedare^ (märke: »El-ESVE»), ångfördelningslådor samt golvslipningsmaskiner.",
            "contact": {
                "office": "Örebro",
                "phone": [
                    "10272"
                ],
                "postgiro": "28211"
            },
            "financials": {
                "annual_production_value": "500,000 kr"
            },
            "foundation_year": 1874
        },
        "3": {
            "name": "Skokompaniet",
            "location": "Mjällom",
            "products": "Tillverkar skidkängor, arbetsskor, vandrarskor och sandaler",
            "contact": {
                "phone": [
                    "16"
                ],
                "postgiro": "132021"
            },
            "financials": {
                "annual_production_value": "740,000 kr"
            },
            "foundation_year": 1937
        },
        "4": {
            "name": "AB. Skorna-Borst",
            "location": "Malmö",
            "products": "Tillverkar syntetisk skomakeriborst (märke: »Skoma-Borst»)",
            "contact": {
                "office": "Söderg. 14",
                "phone": [
                    "78335"
                ],
                "postgiro": "148482"
            },
            "financials": {
                "capital": "20,000 kr",
                "annual_production_value": "40,000 kr"
            },
            "foundation_year": 1942,
            "director": "Edgar Nathan"
        },
        "5": {
            "name": "Skoogs Motorfabrik, Bröderna",
            "location": "Borlänge",
            "products": "",
            "contact": {
                "phone": [
                    "<contact phone number>"
                ],
                "postgiro": "<postgiro number>"
            }
        },
        "6": {
            "name": "AB. Skorpeds Trävaruindustri",
            "location": "Skorped",
            "products": "Tillverkar sågade och hyvlade trävaror",
            "contact": {
                "phone": [
                    "54"
                ],
                "postgiro": "31614"
            },
            "financials": {
                "capital": "100,000 kr",
                "annual_production_value": "250,000 kr"
            },
            "foundation_year": 1942
        },
        "7": {
            "name": "Skriv- & Ritboks-AB.",
            "location": "Årlöv",
            "products": "Tillverkar skriv- och ritböcker, utför bokbinderi- och tryckeriarbeten",
            "contact": {
                "office": "Arlöv",
                "phone": [
                    "Malmö 430489"
                ],
                "postgiro": "5278"
            },
            "foundation_year": 1920
        }
    }
}