{
    "original": "Vingåker—Vina gron\n\nTillverkar hel- och halvyllevävnader,\nbomulls- och konstsilkevävnader samt\nbomulls-, ull- och vigognegarner. Firman\nidkar jämväl jordbruk.\n\nTelegr.-adr.: Wingqvist, Fritsla.\nTelefon: Kinna 70210. Postgiro: 80791.\n\nAntal industriarb.: 525. Tillv.-värde pr\når:: 6,000,000 kr. — Firman etabl. 1860.\n\nÄgare o. chef: fabr. Ignar Anden.\n\nVingåkers Konfektions AB.,\n\nVingåker.\n\nHerrkonfektionsfabrik i Vingåker\n(Södermanl. l.). Tillverkar kostymer och\növerrockar.\n\nTelefon: 155. Postgiro: 32577. —\nAkt.-Jkap.: 46,700 kr. Antal industriarb.: 50.\n— Bolaget grundat 1923.\n\nVerkst. dir.: Erik J. Andersson.\n\n*AB. Vingåkers Spisbrödsfabrik,\n\nVingåker.\n\nSpisbrödsfabrik och kvarn i Vingåker\n(Södermanl. l.). Tillverkar spis- och\nIknäckebröd samt mjöl.\n\nTelegr.-adr.: Vingåkersbröd, Vingåker.\nTelefon: 188 o. 241. Postgiro: 36409.\n\nAkt.-kap.: 170,000 kr. Antal\nindustriarb.: 40. Tillv.-värde pr år: 1,000,000 kr.\n\nFirman, etabl. 1929, har 1933 i sig\nupptagit f. d. Vingåkers Kvarn- &amp; Handels\nAB., grundat 1922.\n\nStyrelse: kammarh. Fredrik v.\nMecklenburg (ordf.), dir. Georg Andersson,\ngods-^arrend. Ragnar Andersson, godsäg.\nGunnar Santesson, agronom Konstans\nSchör-ling.\n\nVerkst. dir. o. disp.: Georg Andersson.\n\nKamrer: Bengt Bergstrand.\n\nAB. Winkelcentrifug, Stockholm.\n\nMek. verkstad. Tillverkar för\nvetenskapliga och industriella laboratorier\navledda elektr. vinkelcentrifuger,\nskakapparater m. m. Firman driver även handel\nmed laboratorieglas.\n\nKontor: Norrtullsg. 23. Telegr.-adr.:\nWifug, Stockholm. Telefon: 313833 o.\n:319307. Postgiro: 153978.\n\nAkt.-kap.: 70,000 kr. Arb.-antal: 20. —\nBolaget grundat 1933.\n\nVerkst. dir.: civiling. Gunnar\nBeckman.\n\n*Winkle AB., Lästfabriken, Örebro.\n\nSe Lästfabriken Winkle AB., Örebro.\n\n6\n\n&lt;40\n\n*AB. Vin- &amp; Spritcentralen,\n\nStockholm.\n\nFabriker och filialer i Eslöv,\nGöteborg, Karlshamn, Reimersholm (Sthlm),\nSundsvall, Södertälje, Åhus, Rödaled\n(Kristianst. l.) och ödåkra (Malmöh. l.)\nmed distributionslager i Malmö.\nFramställer, förädlar och bereder sprit,\nbrännvin och andra alkoholhaltiga drycker.\nBolaget driver jämväl partihandel med\nvin- och spritdrycker samt med skattefri\nsprit.\n\nHuvudkontor: Stockholm, S:t Eriksg.\n121; postadr.: Stockholm 6. Telegr.-adr.\no. telefon: Spritcentralen, Stockholm.\nPostgiro: 86.\n\nAkt.-kap.: 15,000,000 kr. Antal\nindustriarb.: 632. Tillverkning år 1945: 35\nmilj. liter 50 % brännvin och sprit.\n\nBolaget, som grundades 1917 och då\növertog samtliga spritförädlingsverk inom\nlandet, har sedermera fått på sig\növerlåten all partihandel med vin- och\nspritdrycker samt med skattefri sprit.\nBolaget äger agenturbolag, representerande\nutländska firmor inom vin- och\nspritdryckshandeln.\n\nStyrelse: riksdagsman L. A.\nBjörklund (ordf.), riksdagsman J. B.\nJohansson, riksdagsman Erik Fast och\nexpeditionschefen Carl Romberg (av Kungl.\nMaj:t utsedda), dir. J. L. Ekman\npresident A. Lindhagen, envoyé Stig Sahlin\noch assuransdir. Iwar Sjögren (av\nbolagsstämman valda).\n\nVerkst. dir.: Stig Sahlin.\n\nV. verkst. dir.: Gustaf Bergendal.\n\nJourh. revisor (utsedd av Kungl.\nMaj:t): S. A. H. Hagström.\n\nChefer: för fabriker o. filialer:\nciviling. Gunnar Bergman; för vinlagret i\nStockholm: Gustaf Bergendal; för avd.\nskattefri sprit: Åke Svennbeck; för\nMa-cleirakontoret: C. Andreasen.\n\nAvd.-chefer vid huvudkontoret:\nassu-rans- och befraktn.-avd.: Sven Lundbäck\n(kontorschef); katalogred.: Hjalmar\nLeff-ler; kontrollavd.: Albin Zetterberg;\nkor-respondensavd.: Georg Ohlson:\nmaterial-a,vd.: Hj. Arne; order och expedition: C.\nE. Nissen; räkenskapsavd.: S. Meyer;\nvin- o. spirituosaavd.: Bengt Risberg.\n\nFabriks- och filialchefer: Eslöv: Malte\nNilsson: Göteborg: G. H. öcken;\nKarlshamn: Nils Hagstad; Reimersholm: B.\nThorbj örnson; Sundsvall: Rolf\nEngström; Södertälje: vakant; Åhus: Eric\nNilsson; ödåkra: Eric Stenberg; Malmö:\nWilh. Johansson.\n\nAB. Vinägron, Göteborg.\n\nKem. teknisk fabrik. Tillverkar\nattik-sprit, senap, soja samt gurkinläggningar.",
    "structured": {
        "firms": [
            {
                "name": "Vingåker—Vina gron",
                "location": "Vingåker",
                "business": "Tillverkar hel- och halvyllevävnader, bomulls- och konstsilkevävnader samt bomulls-, ull- och vigognegarner. Firman idkar jämväl jordbruk.",
                "contact": {
                    "telegraph": "Wingqvist, Fritsla",
                    "phone": [
                        "Kinna 70210"
                    ],
                    "postgiro": "80791"
                },
                "financials": {
                    "employees": {
                        "industriarb": 525
                    },
                    "annual_turnover": "6,000,000 kr",
                    "annual_production_value": "6,000,000 kr"
                },
                "foundation_year": 1860,
                "owners": [
                    "fabr. Ignar Anden"
                ]
            },
            {
                "name": "Vingåkers Konfektions AB.",
                "location": "Vingåker",
                "business": "Herrkonfektionsfabrik i Vingåker (Södermanl. l.). Tillverkar kostymer och överrockar.",
                "contact": {
                    "phone": "155",
                    "postgiro": "32577"
                },
                "financials": {
                    "capital": "46,700 kr",
                    "employees": {
                        "industriarb": 50
                    }
                },
                "foundation_year": 1923,
                "director": "Erik J. Andersson"
            },
            {
                "name": "AB. Vingåkers Spisbrödsfabrik",
                "location": "Vingåker",
                "business": "Spisbrödsfabrik och kvarn i Vingåker (Södermanl. l.). Tillverkar spis- och knäckebröd samt mjöl.",
                "contact": {
                    "telegraph": "Vingåkersbröd, Vingåker",
                    "phone": [
                        "188",
                        "241"
                    ],
                    "postgiro": "36409"
                },
                "financials": {
                    "capital": "170,000 kr",
                    "employees": {
                        "industriarb": 40
                    },
                    "annual_production_value": "1,000,000 kr"
                },
                "corporation_year": 1929,
                "board": [
                    {
                        "name": "kammarh. Fredrik v. Mecklenburg",
                        "role": "ordf."
                    },
                    {
                        "name": "dir. Georg Andersson",
                        "role": ""
                    },
                    {
                        "name": "gods-^arrend. Ragnar Andersson",
                        "role": ""
                    },
                    {
                        "name": "godsäg. Gunnar Santesson",
                        "role": ""
                    },
                    {
                        "name": "agronom Konstans Schör-ling",
                        "role": ""
                    }
                ],
                "director": "Georg Andersson",
                "sales_manager": "Bengt Bergstrand"
            },
            {
                "name": "AB. Winkelcentrifug",
                "location": "Stockholm",
                "business": "Mek. verkstad. Tillverkar för vetenskapliga och industriella laboratorier avledda elektr. vinkelcentrifuger, skakapparater m. m. Firman driver även handel med laboratorieglas.",
                "contact": {
                    "office": "Norrtullsg. 23",
                    "telegraph": "Wifug, Stockholm",
                    "phone": [
                        "313833",
                        "319307"
                    ],
                    "postgiro": "153978"
                },
                "financials": {
                    "capital": "70,000 kr",
                    "employees": {
                        "Arb.-antal": 20
                    }
                },
                "corporation_year": 1933,
                "director": "civiling. Gunnar Beckman"
            },
            {
                "name": "AB. Vin- &amp; Spritcentralen",
                "location": "Stockholm",
                "business": "Fabriker och filialer i Eslöv, Göteborg, Karlshamn, Reimersholm (Sthlm), Sundsvall, Södertälje, Åhus, Rödaled (Kristianst. l.) och ödåkra (Malmöh. l.) med distributionslager i Malmö. Framställer, förädlar och bereder sprit, brännvin och andra alkoholhaltiga drycker.",
                "contact": {
                    "head_office": "Stockholm, S:t Eriksg. 121",
                    "telegraph": "Spritcentralen, Stockholm",
                    "phone": [
                        "Stockholm"
                    ],
                    "postgiro": "86"
                },
                "financials": {
                    "capital": "15,000,000 kr",
                    "employees": {
                        "industriarb": 632
                    }
                },
                "corporation_year": 1917,
                "board": [
                    {
                        "name": "riksdagsman L. A. Björklund",
                        "role": "ordf."
                    },
                    {
                        "name": "riksdagsman J. B. Johansson",
                        "role": ""
                    },
                    {
                        "name": "riksdagsman Erik Fast",
                        "role": ""
                    },
                    {
                        "name": "expeditionschefen Carl Romberg",
                        "role": "av Kungl. Maj:t utsedda"
                    },
                    {
                        "name": "dir. J. L. Ekman",
                        "role": ""
                    },
                    {
                        "name": "president A. Lindhagen",
                        "role": ""
                    },
                    {
                        "name": "envoyé Stig Sahlin",
                        "role": ""
                    },
                    {
                        "name": "assuransdir. Iwar Sjögren",
                        "role": "av bolagsstämman valda"
                    }
                ],
                "director": "Stig Sahlin",
                "manager": "Gustaf Bergendal"
            },
            {
                "name": "AB. Vinägron",
                "location": "Göteborg",
                "business": "Kem. teknisk fabrik. Tillverkar attik-sprit, senap, soja samt gurkinläggningar."
            }
        ]
    }
}