{
    "original": "Nissafors—Nitroglycerin\n\nKontor: Drottningtorget 6. Telefon:\n23075. Postgiro: 39459. Prod.-värde pr\når: 980,000 kr. — Firman etabl. 1916.\nÄgare o. chef: byggm. Åke Nilsson.\n\nNissafors Pappersförädling AB.,\n\nNissafors.\n\nFörädlar papper vid fabrik i Nissafors\n(Jönköp. l.). Specialitet: Idealbärkassar.\n\nTelefon: 30. Postgiro: 167770. —\nAkt.-kap.: 20,000 kr. Antal industriarb.: 60.\nTillv.-värde pr år: 1,000,000 kr. —\nFirman etabl. 1939, bolag 1943.\nDisp.: Leif Thilén.\n\n\"Nissafors Träsliperi, G. Lord &amp; Co.,\n\nNissafors.\n\nTräsliperi vid Nissafors (Jönköp. l.).\nTillverkar mek. trämassa.\n\nTelegr.-adr.: Träsliperiet, Nissafors.\nTelefon: 8. — Arb.-antal: 12. Årstillv.:\n4,000 ton våt, vit mek. trämassa. —\nFirman etabl. 1909.\n\nÄgare o. chef: disp. Gustaf Lord.\n\nNissans Pås- &amp; Pappers AB.,\n\nHalmstad.\n\nTillverkar papperspåsar.\nTelefon: 847. Postgiro: 22606. —\nAkt.-kap.: 45,000 kr. Arb.-antal: 5.\nTillv.-värde pr år: 135,000 kr. — Bolaget\ngrundat 1925.\n\nVerkst. dir.: disp. Bror Göransson.\n\n\"Nissaströms Bruks och Kraft AB.,\n\nHalmstad.\n\nPappfabrik med träsliperi vid\nNissa-ström, Johansfors (Hallands l.).\nTillverkar brun papp, glanspapp samt mek.\nträmassa.\n\nFörsäljningskontor: Halmstad.\nTelegr.-adr.: Nissaström, Halmstad. Telefon:\n3075.\n\nAkt.-kap.: 5,000,000 kr. Antal\nindustriarb.: 75. Årstillv.: 4,000 ton papp, 2,000\nton våt brun trämassa. — Bolaget\ngrundat 1889.\n\nStyrelse: dir. Edw. Berger (ordf.),\nkommendörkapt. Gunvald Berger, disp.\nKurt Berger.\n\nVerkst. dir.: Edw. Berger.\nFörsäljn.-chef: v. konsul Oscar Hill.\nFabriks förest.: Hugo Häägg.\n\n\"AB. Nissens Manufacturlng,\n\nNorrköping.\n\nChoklad- och konfektfabrik. Tillverkar\nchoklad, konfekt, karameller, marmelad\noch lakrits.\n\nHuvudkontor: Norrköping.\nTelegr.-adr.: Nissens, Norrköping. Telefon:\n22193. Postgiro: 11096. Avd.-kontor\no. lager: Stockholm, Engelbrektsg. 6,\ntelefon: 102615; Göteborg, Surbrunnsg. 4,\ntelefon: 119987.\n\nAkt.-kap.: 300,000 kr. Antal\nindustriarb.: 100. — Bolaget grundat 1898.\n\nStyrelse: dir. Alex. Melchior (ordf.),\nf. kapten B. Billsten, disp. Hjalmar\nSvenfelt.\n\nVerkst. dir.: Alex. Melchior.\n\nNitfabriken Wulkan, Ture Emilsson\n&amp; Co., Anderstorp.\n\nNummerplåts- och bromsbandsnitar,\nremplattor och remnitar, remlås, massiva\nnitar, såväl glödgade som ytbehandlade,\nbyxfästen (cykel), skärptrissor för\nav-skärning av slipskivor samt pressade och\nklippta plåtdetaljer vid mek. verkstad i\nAnderstorp (Jönköp. l.).\n\nTelefon: 54. Postgiro: 93515. —\nTillv.-värde pr år: 500,000 kr. — Firman etabl.\n1933.\n\nChef: dir. Ture Emilsson.\n\nNitor AB., Tekniska Fabriken,\n\nStockholm.\n\nSe Tekniska Fabriken Nitor AB.,\nStockholm.\n\n\"Nitroglycerin AB., Oyttorp.\n\nSprängämnesfabrik vid Gyttorp\n(Örebro l.). Tillverkar dynamit och andra\nsprängämnen, säkerhetssprängämnen\n(Ni-trolit, Car Isonit o. Territ), svartkrut,\njaktpatroner och hagel.\n\nHuvudkontor: Gyttorp. Telegr.-adr.:\nNitroglycerin, Nora. Telefon: Nora.\n»Nitroglycerinbolaget». Postgiro: 587.\nAvd.-kontor: Stockholm, Arsenalsg. 9.\nTelefon: 208948.\n\nAkt.-kap.: 5,000,000 kr. Antal\nindustriarb.: 500. — Bolaget grundat 1864 av dr\nAlfred Nobel.\n\nStyrelse: fil. dr Harald Nordenson\n(ordf.), disp. J. Kempe, fil. dr Sigurd\nNauckhoff, disp. Ejnar Rodling, dir.\nHans Rydin.\n\nVerkst. dir.: Torsten Edlund.\n\nKontorschef: J. Tysén.\n\nFabriks föreståndare: för\ndynamitfabriken: O var Bergström; för krutbruket\no. ammunitionsfabriken: kapten G. Bark.\n\nInköpschef: Nils Elwin.\n\n(Jfr annons nr 55.)\n\n393*",
    "structured": {
        "1": {
            "name": "Nissafors—Nitroglycerin",
            "location": "Nissafors",
            "business": "Nitroglycerin AB",
            "contact": {
                "office": "Drottningtorget 6",
                "phone": [
                    "23075"
                ],
                "postgiro": "39459"
            },
            "financials": {
                "capital": "5,000,000 kr",
                "employees": {
                    "industriarb": 500
                },
                "annual_turnover": "N/A",
                "annual_production_value": "N/A"
            },
            "foundation_year": 1864,
            "predecessor": "N/A",
            "board": [
                {
                    "name": "fil. dr Harald Nordenson",
                    "role": "ordf."
                },
                {
                    "name": "disp. J. Kempe",
                    "role": "N/A"
                },
                {
                    "name": "fil. dr Sigurd Nauckhoff",
                    "role": "N/A"
                },
                {
                    "name": "disp. Ejnar Rodling",
                    "role": "N/A"
                },
                {
                    "name": "dir. Hans Rydin",
                    "role": "N/A"
                }
            ]
        },
        "2": {
            "name": "Nissafors Pappersförädling AB.",
            "location": "Nissafors",
            "business": "Pappersförädling",
            "products": "Idealbärkassar",
            "contact": {
                "phone": [
                    "30"
                ],
                "postgiro": "167770"
            },
            "financials": {
                "capital": "20,000 kr",
                "employees": {
                    "industriarb": 60
                },
                "annual_turnover": "N/A",
                "annual_production_value": "N/A"
            },
            "foundation_year": 1939
        },
        "3": {
            "name": "Nissafors Träsliperi, G. Lord & Co.",
            "location": "Nissafors",
            "business": "Träsliperi",
            "products": "Mekanisk trämassa",
            "contact": {
                "phone": [
                    "8"
                ]
            },
            "foundation_year": 1909
        },
        "4": {
            "name": "Nissans Pås- & Pappers AB.",
            "location": "Halmstad",
            "business": "Tillverkning papperspåsar",
            "contact": {
                "phone": [
                    "847"
                ],
                "postgiro": "22606"
            },
            "financials": {
                "capital": "45,000 kr",
                "employees": {
                    "industriarb": 5
                },
                "annual_turnover": "N/A",
                "annual_production_value": "N/A"
            },
            "foundation_year": 1925
        },
        "5": {
            "name": "Nissaströms Bruks och Kraft AB.",
            "location": "Halmstad",
            "business": "Pappfabrik",
            "products": "Brun papp, glanspapp, mekanisk trämassa",
            "contact": {
                "sales_offices": [
                    {
                        "location": "Halmstad",
                        "phone": "3075"
                    }
                ]
            },
            "financials": {
                "capital": "5,000,000 kr",
                "employees": {
                    "industriarb": 75
                },
                "annual_turnover": "N/A",
                "annual_production_value": "N/A"
            },
            "foundation_year": 1889
        },
        "6": {
            "name": "AB. Nissens Manufacturlng",
            "location": "Norrköping",
            "business": "Choklad- och konfektfabrik",
            "products": "Choklad, konfekt, karameller, marmelad och lakrits",
            "contact": {
                "office": "Norrköping",
                "phone": [
                    "22193"
                ],
                "postgiro": "11096"
            },
            "financials": {
                "capital": "300,000 kr",
                "employees": {
                    "industriarb": 100
                },
                "annual_turnover": "N/A",
                "annual_production_value": "N/A"
            },
            "foundation_year": 1898
        },
        "7": {
            "name": "Nitfabriken Wulkan, Ture Emilsson & Co.",
            "location": "Anderstorp",
            "business": "Mekanisk verkstad",
            "products": "Nummerplåts- och bromsbandsnitar, remplattor, remlås, ytbehandlade och glödgade nitar, skärptrissor, pressade och klippta plåtdetaljer",
            "contact": {
                "phone": [
                    "54"
                ],
                "postgiro": "93515"
            },
            "financials": {
                "annual_turnover": "N/A",
                "annual_production_value": "500,000 kr"
            },
            "foundation_year": 1933
        }
    }
}