{
    "original": "Ret-±-Ri(fkä/rd\n\nmöbelfabrikation, resårbottensängar,\nresårnät, kedjebottnar, ottöffianstommäi?,\nschäslonger, madrasskedjor, spiralfjädrar\nm. m.\n\nTelefon: 10780 o. 13413. Postgiro: 6959.\nAkt.-kap.: 162,000 kr. Antal\nindustriarb.: 40. Tillv.-värde pr år: 600,000 kr.\n\n—\tFirman etabl. 1913.\n\nStyrelse: dir. Karl A. Jakobson (ordf.),\nmekaniker Wictor Bengtson,\nseminarielärare Anders Grumstedt.\n\nChef: dir. Karl A. Jakobson.\n\n*Ret-Cé Konfektions AB., Stockholm.\n\nTillverkar klänningar, kjolar och\nblusar.\n\nKontor: Hantverkarg. 11. Telefon:\n52003Q. Postgiro: 4020.\n\nAkt.-kap.: 250,000 kr. Antal\nindustriarb.: 105, Tillv.-värde pr år: 1,500,000 kr.\n\n—\tBolaget grundat 1942.\n\nStyrelse: adv. Wilhelm Kjellström\n(ordf.), kontorschef ^ Anders Broman,\ndisp. Gunnar Wadstein, dir. Gustaf\nWad-stein.\n\nDisp.: Gunnar Wadstein.\n\n*Réx, AB. Maskinfabriken,\n\nHalmstad.\n\nSe AB. Maskinfabriken Ilex, Halmstad.\n\n*Rex, AB. Skofabriken, Örebro.\nSe AB. Skofabriken Rex, Örebro.\n\nRexolin Fabriken AB.,\n\nHälsingborg.\n\nKem. teknisk fabrik. Tillverkar\nbon-vax, kitt, lackfärger, tvätt- och\navfett-ningsmedel, antimalbeliandling^medel\n(märke: »Fenosal») ni. m. ..,’..■•..\n\nTelegr.-adr.: Rexolinfabriken,\nHälsingborg. Telefon: 14360. Postgiro: 14397.\n\nAkt.-kap.: 60,600 kr. Arb.-antal: 6.\nTillv.-värde pr år: 300,000 kr. — Firman\netabl. 1960, bolag 1924.\n\nStyrelse o. verkst. dir.: Sven Swärdh.\n\nRexor-Industri, Mulhjö.\n\nMetallvarufabrik i Mullsjö (Skarab. l.).\nTillverkar kontakttermomotrar för\nvärmeledningspannor, pann- och\nugnstermometrar, rumstermometrar samt mekaniska\nleksaker; utför revolversvarvning,\npressning, nitning och punktsvetsning av\nmassartiklar.\n\nTelefon: 230. Postgiro: 288611. Repr. i\nStockholm: Gösta Lindstrand, Baltzar v.\nPia ten sg. 11. — Antal industriarb.: 10\n\nin;\n\nävensom 20 hemarbetare. Ti liv.-värde pr\når: ;150,Ö00 kr. — Firman etabl. 1Ä45.\n\nÄgare ö. chefer: fabr. Lats Pettersort,\nfabr. Sture Rimbäck o. fabr: Carl Nordh.\n\n*Reymersholms Gamla industri AB.,\n\nHälsingborg.\n\nFabriker i Hälsingborg och\nOskarshamn.\t• ’ i \"\n\nTillverkar ackumulatorsyrå* &gt; konc.\nsvavelsyra, rykande svavelsyra (oleum),\nsaltsyra, klorsulfonsyra, fosforsyra,\naluminiumsulfat, kalialun, natriumsnlfat, kale.\noch krist., natrium- och kalciumfosfater,\nklorkalcium, koboltprodukter,,\nraffinad-koppar, purple-ore och\npurple^ore-bri-ketter.\n\nHuvudkontor: Hälsingborg.\nTelegr.-adr. o. telefon: Reymersholms,\nHälsingborg. Postgiro: 32139. Fabrikskontor:\nHälsingborg o. Oskarshamn.\n\nAkt.-kap.: 12,000,000 kr. Antal\nindustriarb. : 700. Tillv.-värde - pr år:\n20,000,000 kr.\n\nStyrelse t bankdir. Helmer Sten (ordf.),\ndir. Sven E. Lundberg, skeppsred. Sven\nRedig, dir. Hans Rydin» jur&lt;? Qarl\nSjunnesson.\n\nVerkst. dir.: Sven E. Lundberg.\n\nÖvering.: Edw. Schön.\n\nKontorschef: Nils Ph. Påhlsson.\n\nFörsäljn.-chef: H. Manners.\n\n(Jfr annons nr 2.)\n\nAB. Reymersholms Livsmedel,\n\nHälsingborg.\n\nTillverkar matolja (»Kronolja»),\nplåt-olja för bagerier, majonnäs, laxmajonnäs,\nsmörgåssallad, legymsallad, remoulade,\nsalladsås samt taffelsås och ^kärpsås (för\nfisk, kött och sallader) vid fabrik i\nKarlshamn.\n\nHuvudkontor: Hälsingborg, Telegr.-adr.\no. telefon: Reymersholms, Hälsingborg.\nPostgiro: 80995,\n\nAkt.-kap.: 300,000 kr. Tillv.-värde pr\når: 4,000,000 kr. — Bolaget grundat 1932.\n\nStyrelse: dir. Sven E. Lnndberg (ordf.),\ndisp. Albert Bredmark, intendent Nils Ph.\nPåhlsson.\t, , . ;\n\nVerkst. dir.: Sven.E. Lindberg.\n\nVice verkst. dir.: Albert Bredmark.\n\n\"Erling Richard AB., Stockholm.\n\nDamkonfektionsfabrik. Tillverkar\ndam-och flickklänningar, stranddräkter, shorts,\nmorgonrockar, skyddsrockar m. ni.\nVarumärken : » Colorita», » A lila&gt;&gt;,. »\nCamp-Ahla». »Richard», »B. B.» m. fl.\n\nKontor: Pipersg. 27. Telefon: 520040.\nPostgiro: 50222. \"\tj:’.-.",
    "structured": {
        "1": {
            "name": "Ret-±-Ri(fkä/rd möbelfabrikation",
            "location": null,
            "business": "Resårbottensängar, resårnät, kedjebottnar, ottöffianstommäi?, schäslonger, madrasskedjor, spiralfjädrar m. m.",
            "products": null,
            "contact": {
                "office": null,
                "phone": [
                    "10780",
                    "13413"
                ],
                "postgiro": "6959",
                "head_office": null,
                "sales_offices": null,
                "telegraph": null,
                "factory_office": null,
                "factory_phone": null
            },
            "financials": {
                "capital": "162,000 kr",
                "employees": {
                    "industriarb": 40
                },
                "annual_turnover": "600,000 kr",
                "annual_production_value": null
            },
            "foundation_year": 1913,
            "current_name_year": null,
            "predecessor": null,
            "original_name": null,
            "corporation_year": null,
            "board": [
                {
                    "name": "Karl A. Jakobson",
                    "role": "ordf."
                },
                {
                    "name": "Wictor Bengtson",
                    "role": "mekaniker"
                },
                {
                    "name": "Anders Grumstedt",
                    "role": "seminarielärare"
                }
            ],
            "owners": null,
            "director": "Karl A. Jakobson",
            "managing_director": null,
            "sales_manager": null,
            "manager": null
        },
        "2": {
            "name": "Ret-Cé Konfektions AB.",
            "location": "Stockholm",
            "business": "Tillverkar klänningar, kjolar och blusar",
            "products": null,
            "contact": {
                "office": "Hantverkarg. 11",
                "phone": [
                    "52003Q"
                ],
                "postgiro": "4020",
                "head_office": null,
                "sales_offices": null,
                "telegraph": null,
                "factory_office": null,
                "factory_phone": null
            },
            "financials": {
                "capital": "250,000 kr",
                "employees": {
                    "industriarb": 105
                },
                "annual_turnover": "1,500,000 kr",
                "annual_production_value": null
            },
            "foundation_year": 1942,
            "current_name_year": null,
            "predecessor": null,
            "original_name": null,
            "corporation_year": null,
            "board": [
                {
                    "name": "Wilhelm Kjellström",
                    "role": "ordf."
                },
                {
                    "name": "Anders Broman",
                    "role": "kontorschef"
                },
                {
                    "name": "Gunnar Wadstein",
                    "role": "disp."
                },
                {
                    "name": "Gustaf Wadstein",
                    "role": "dir."
                }
            ],
            "owners": null,
            "director": null,
            "managing_director": null,
            "sales_manager": null,
            "manager": null
        },
        "3": {
            "name": "Rexolin Fabriken AB.",
            "location": "Hälsingborg",
            "business": "Kem. teknisk fabrik. Tillverkar bon-vax, kitt, lackfärger, tvätt- och avfett-ningsmedel, antimalbeliandling^medel (märke: »Fenosal») ni.",
            "products": null,
            "contact": {
                "office": null,
                "phone": [
                    "14360"
                ],
                "postgiro": "14397",
                "head_office": null,
                "sales_offices": null,
                "telegraph": "Rexolinfabriken, Hälsingborg",
                "factory_office": null,
                "factory_phone": null
            },
            "financials": {
                "capital": "60,600 kr",
                "employees": {
                    "Arb.-antal": 6
                },
                "annual_turnover": "300,000 kr",
                "annual_production_value": null
            },
            "foundation_year": 1960,
            "current_name_year": 1924,
            "predecessor": null,
            "original_name": null,
            "corporation_year": null,
            "board": [
                {
                    "name": "Sven Swärdh",
                    "role": "verkst. dir."
                }
            ],
            "owners": null,
            "director": null,
            "managing_director": null,
            "sales_manager": null,
            "manager": null
        },
        "4": {
            "name": "Rexor-Industri",
            "location": "Mullsjö",
            "business": "Metallvarufabrik i Mullsjö (Skarab. l.). Tillverkar kontakttermomotrar för värmeledningspannor, pann- och ugnstermometrar, rumstermometrar samt mekaniska leksaker; utför revolversvarvning, pressning, nitning och punktsvetsning av massartiklar.",
            "products": null,
            "contact": {
                "office": null,
                "phone": [
                    "230"
                ],
                "postgiro": "288611",
                "head_office": null,
                "sales_offices": null,
                "telegraph": null,
                "factory_office": null,
                "factory_phone": null
            },
            "financials": {
                "capital": null,
                "employees": {
                    "industriarb": 10
                },
                "annual_turnover": "150,Ö00 kr",
                "annual_production_value": null
            },
            "foundation_year": 1945,
            "current_name_year": null,
            "predecessor": null,
            "original_name": null,
            "corporation_year": null,
            "board": [
                {
                    "name": "Lats Pettersort",
                    "role": "fabr."
                },
                {
                    "name": "Sture Rimbäck",
                    "role": "fabr."
                },
                {
                    "name": "Carl Nordh",
                    "role": "fabr."
                }
            ],
            "owners": null,
            "director": null,
            "managing_director": null,
            "sales_manager": null,
            "manager": null
        },
        "5": {
            "name": "Reymersholms Gamla industri AB.",
            "location": "Hälsingborg",
            "business": "Tillverkar ackumulatorsyrå* &gt; konc. svavelsyra, rykande svavelsyra (oleum), saltsyra, klorsulfonsyra, fosforsyra, aluminiumsulfat, kalialun, natriumsnlfat, kale. och krist., natrium- och kalciumfosfater, klorkalcium, koboltprodukter, raffinad-koppar, purple-ore och purple^ore-bri-ketter.",
            "products": null,
            "contact": {
                "office": "Hälsingborg",
                "phone": null,
                "postgiro": "32139",
                "head_office": null,
                "sales_offices": null,
                "telegraph": "Reymersholms, Hälsingborg",
                "factory_office": null,
                "factory_phone": null
            },
            "financials": {
                "capital": "12,000,000 kr",
                "employees": {
                    "industriarb": 700
                },
                "annual_turnover": "20,000,000 kr",
                "annual_production_value": null
            },
            "foundation_year": null,
            "current_name_year": null,
            "predecessor": null,
            "original_name": null,
            "corporation_year": null,
            "board": [
                {
                    "name": "Helmer Sten",
                    "role": "bankdir."
                },
                {
                    "name": "Sven E. Lundberg",
                    "role": "dir."
                },
                {
                    "name": "Sven Redig",
                    "role": "skeppsred."
                },
                {
                    "name": "Hans Rydin",
                    "role": "jur&lt;? Qarl"
                }
            ],
            "owners": null,
            "director": null,
            "managing_director": "Sven E. Lundberg",
            "sales_manager": null,
            "manager": null
        },
        "6": {
            "name": "AB. Reymersholms Livsmedel",
            "location": "Hälsingborg",
            "business": "Tillverkar matolja (»Kronolja»), plåt-olja för bagerier, majonnäs, laxmajonnäs, smörgåssallad, legymsallad, remoulade, salladsås samt taffelsås och ^kärpsås (för fisk, kött och sallader) vid fabrik i Karlshamn.",
            "products": null,
            "contact": {
                "office": "Hälsingborg",
                "phone": null,
                "postgiro": "80995",
                "head_office": null,
                "sales_offices": null,
                "telegraph": "Reymersholms, Hälsingborg",
                "factory_office": null,
                "factory_phone": null
            },
            "financials": {
                "capital": "300,000 kr",
                "employees": null,
                "annual_turnover": "4,000,000 kr",
                "annual_production_value": null
            },
            "foundation_year": 1932,
            "current_name_year": null,
            "predecessor": null,
            "original_name": null,
            "corporation_year": null,
            "board": [
                {
                    "name": "Sven E. Lnndberg",
                    "role": "ordf."
                },
                {
                    "name": "Albert Bredmark",
                    "role": "disp."
                }
            ],
            "owners": null,
            "director": null,
            "managing_director": "Sven.E. Lindberg",
            "sales_manager": null,
            "manager": null
        },
        "7": {
            "name": "Erling Richard AB.",
            "location": "Stockholm",
            "business": "Damkonfektionsfabrik. Tillverkar dam-och flickklänningar, stranddräkter, shorts, morgonrockar, skyddsrockar m. ni. Varumärken : » Colorita», » A lila&gt;&gt;,. » Camp-Ahla». »Richard», »B. B.» m. fl.",
            "products": null,
            "contact": {
                "office": "Pipersg. 27",
                "phone": [
                    "520040"
                ],
                "postgiro": "50222",
                "head_office": null,
                "sales_offices": null,
                "telegraph": null,
                "factory_office": null,
                "factory_phone": null
            },
            "financials": {
                "capital": null,
                "employees": null,
                "annual_turnover": null,
                "annual_production_value": null
            },
            "foundation_year": null,
            "current_name_year": null,
            "predecessor": null,
            "original_name": null,
            "corporation_year": null,
            "board": null,
            "owners": null,
            "director": null,
            "managing_director": null,
            "sales_manager": null,
            "manager": null
        }
    }
}