{
    "original": "Norma—Norrahammar\n\n\"AB. Norma Projektilfabrik,\n\nÅmotfors.\n\nAmmunitionsfabrik vid Åmotfors\n(Värml. l.). Tillverkar projektiler och\nladdade patroner för handvapen.\n\nTelefon: 12. Postgiro: 70133.\n\nAkt.-kap.: 125,000 kr. Antal\nindustriarb.: 465. — Fabriken anlagd 1902, nuv.\nbolag grundat 1918.\n\nStyrelse: f. d. överste C. G. Wibeck\n(ordf.), fröken Wivi Dahlström, ing.\nAmund Enger.\n\nDisp.: major Andreas Torp.\n\nNorma Skoindustri Eftr., John\nJansson &amp; Co., Hudiksvall.\n\nTillverkar handgjorda sport- och\narbets-skodon vid fabrik i Hudiksvall (Gävleb.\n1.).\n\nTelefon: 692. Postgiro: 324446. —\nArb.-antal: 10. Tillv.-värde pr år: 75,000\nkr. — Firman etabl. 1918 under namn\nHudiksvalls Skoindustri, nuv. namn 1940.\n\nÄgare o. chefer: fabr. Erik Jansson o.\nfabr. John Jansson.\n\nNormalrör, Cjuterl AB.,\n\nÅkers styckebruk.\n\nSe Gjuter i AB. Normalrör, Åkers\nstyckebruk.\n\n\"Normans Bokbinderi AB.,\n\nStockholm.\n\nBokbinderi, kartongfabrik, litografiskt\ntryckeri och accidenstryckeri. Tillverkar\naskar, kartonger och kapslar, med och\nutan tryck, samt utför bokbinderiarbeten,\nlitografiskt tryck och accidenstryck.\n\nKontor: Luntmakarg. 68. Telefon:\n300191—92 o. 300188. Postgiro: 51837.\n\nAkt.-kap.: 300,000 kr. Antal\nindustriarb.: 120. Tillv.-värde pr år: 1,200,000 kr.\n— Firman etabl. 1863, bolag 1906.\n\nStyrelse o. direktörer: Allan Norman o.\nKnut Lindström.\n\nNormans Skogs- &amp; Sågverks AB.,\n\nSömmen.\n\nSågverk i Sömmen (Jönköp. l.), i\nLak-vik, V:a Harg, Godegård och Karlsby\n(samtl. i Östergötl. l.), i Loftahammar\n(Kalmar l.), sågverk i Västervik samt\nsågverk i Sveg (Jämtl. l.) m. fl. platser.\n\nTillverkar sågade, hyvlade och bilade\nträvaror samt stolpar, pålar, slipers och\nmastspiror.\n\nTelefon: 33 o. 9. Postgiro: 25184. —\nAkt.-kap.: 100,000 kr. Antal industriarb.:\n200. Årstillv.: 6,000 stds trävaror. —\nFirman etabl. 1921, bolag 1934.\n\nVerkst. direktörer: grossh. Rudolf\nNorman o. forstmästare Oscar Norman.\n\nKnuth Normarks Tegelbruk,\n\nSkellefteå.\n\nTillverkar murtegel vid tegelbruk vid\nDegerbyn, Skellefteå (Västerbott. l.).\n\nPostadr.: Box 28, Skellefteå. Telefon:\n10358. Postgiro: 66354. — Antal\nindustriarb.: 15. Årstillv.: 800,000 st.\nmurtegel. — Firman etabl. 1924.\n\nÄgare o. chef: fabr. Knuth A.\nNormark.\n\nAB. Norra Kinds Hemindustri,\n\nGällstad.\n\nTillverkar strumpor, sockor, vantar,\njumpers, gensare, dam- och barntröjor i\nylle och bomull vid trikåfabrik i Gällstad\n(Älvsb. l.).\n\nTelefon: 52. Postgiro: 72585. —\nAkt.-kap.: 45,000 kr. Antal industriarb.: 10\nävensom 20 hemarbetare. Tillv.-värde pr\når: 175,000 kr. — Firman etabl. 1931,\nbolag 1935.\n\nVerkst. dir.: Axel Bolander.\n\n\"Norra Tororps &amp; Kungs Norrby\nTegelbruk, Klockrike.\n\nSe Klockrike Tegelbruk, Klockrike.\n\n\"Norrahammars Bruk, Norrahammar.\n\nTackjärnsgjuteri, aduceringsverk, mek.\nverkstad, plåtslageri, svetsningsverkstad,\nsnickeriverkstad och såg samt elektr.\nvattenkraftstationer vid Norrahammar\n(Jönköp. l.).\n\nTillverkar tackjärns- och\nhandelsgjut-gods såsom värmeledningspannor ^ för\nvarmvatten och ånga, stokrar, spisar,\nkaminer, huhållskärl m. m., elspisar,\nel-kokhällar och elugnar, plåtradiatorer,\naduceringsgjutgods, sanitetsgods,\nemalje-rade kokkärl, manglar, gräsklippare,\ndiskmaskiner, plåtmanufaktur m. m. Vid\nbruket drives jämväl jordbruk och\nskogshantering.\n\nKontor: Norrahammar. Telegr.-adr.:\nBruket, Norrahammar. Telefon:\nJönköping: »Norrahammars Bruk». Postgiro:\n5289.\n\nAntal industriarb.: 1,100. Tillv.-värde\npr år: 20,000,000 kr.\n\nBruket grundades 1877 och äges av\nHusqvarna Vapenfabriks AB.\n\n403*",
    "structured": {
        "1": {
            "name": "AB. Norma Projektilfabrik",
            "location": "Åmotfors",
            "business": "Tillverkar projektiler och laddade patroner för handvapen",
            "contact": {
                "office": "Telefon: 12",
                "phone": [
                    "12"
                ],
                "postgiro": "70133"
            },
            "financials": {
                "capital": "125,000 kr",
                "employees": {
                    "industriarb": 465
                },
                "foundation_year": 1918,
                "original_name": "Fabriken anlagd 1902",
                "corporation_year": 1918
            }
        },
        "2": {
            "name": "Norma Skoindustri Eftr., John Jansson & Co.",
            "location": "Hudiksvall",
            "business": "Tillverkar handgjorda sport- och arbets-skodon",
            "contact": {
                "phone": "692",
                "postgiro": "324446"
            },
            "financials": {
                "annual_production_value": "75,000 kr",
                "foundation_year": 1918,
                "current_name_year": 1940
            },
            "owners": [
                "fabr. Erik Jansson",
                "fabr. John Jansson"
            ]
        },
        "3": {
            "name": "Normans Bokbinderi AB.",
            "location": "Stockholm",
            "business": "Tillverkar askar, kartonger och kapslar, samt utför bokbinderiarbeten",
            "contact": {
                "office": "Kontor: Luntmakarg. 68",
                "phone": [
                    "300191-92",
                    "300188"
                ],
                "postgiro": "51837"
            },
            "financials": {
                "capital": "300,000 kr",
                "employees": {
                    "industriarb": 120
                },
                "annual_turnover": "1,200,000 kr",
                "foundation_year": 1863,
                "corporation_year": 1906
            },
            "board": [
                {
                    "name": "Allan Norman",
                    "role": "direktör"
                },
                {
                    "name": "Knut Lindström",
                    "role": "direktör"
                }
            ]
        },
        "4": {
            "name": "Normans Skogs- & Sågverks AB.",
            "location": "Sömmen",
            "business": "Tillverkar sågade, hyvlade och bilade trävaror samt stolpar, pålar, slipers och mastspiror",
            "contact": {
                "phone": "33",
                "postgiro": "25184"
            },
            "financials": {
                "capital": "100,000 kr",
                "employees": {
                    "industriarb": 200
                },
                "annual_production_value": "6,000 stds trävaror",
                "foundation_year": 1921,
                "corporation_year": 1934
            },
            "director": "grossh. Rudolf Norman",
            "managing_director": "forstmästare Oscar Norman"
        },
        "5": {
            "name": "Knuth Normarks Tegelbruk",
            "location": "Skellefteå",
            "business": "Tillverkar murtegel",
            "contact": {
                "office": "Postadr.: Box 28, Skellefteå",
                "phone": "10358",
                "postgiro": "66354"
            },
            "financials": {
                "employees": {
                    "industriarb": 15
                },
                "annual_production_value": "800,000 st. murtegel",
                "foundation_year": 1924
            },
            "owner": "fabr. Knuth A. Normark"
        },
        "6": {
            "name": "AB. Norra Kinds Hemindustri",
            "location": "Gällstad",
            "business": "Tillverkar strumpor, sockor, vantar, jumpers, gensare, dam- och barntröjor i ylle och bomull",
            "contact": {
                "phone": "52",
                "postgiro": "72585"
            },
            "financials": {
                "capital": "45,000 kr",
                "employees": {
                    "industriarb": 10,
                    "hemarbetare": 20
                },
                "annual_production_value": "175,000 kr",
                "foundation_year": 1931,
                "corporation_year": 1935
            },
            "manager": "Axel Bolander"
        },
        "7": {
            "name": "Norrahammars Bruk",
            "location": "Norrahammar",
            "business": "Tillverkar tackjärns- och handelsgjutgods, elspisar, el-kokhällar och elugnar, plåtradiatorer, aduceringsgjutgods, sanitetsgods",
            "contact": {
                "office": "Kontor: Norrahammar",
                "telegraph": "Telegr.-adr.: Bruket, Norrahammar",
                "phone": "Jönköping: »Norrahammars Bruk»",
                "postgiro": "5289"
            },
            "financials": {
                "employees": {
                    "industriarb": 1100
                },
                "annual_turnover": "20,000,000 kr"
            },
            "foundation_year": 1877
        }
    }
}