{
    "original": "Palm—Papyrus\n\nmössor samt huvor. Varumärken:\n»Tip-Top» o. »Tola».\n\nTelefon: »Palms fabriker». Postgiro:\n90900. — Antal industriarb.: 45. —\nFirman etabl. 1886.\n\nÄgare o. chef: fabr. Gösta Palm.\n\n*AB. Martin Palm, Borås.\n\nKonfektionsfabrik. Tillverkar\ndamkon-fektionsartiklar, arbetskläder, skjortor\nsamt hemstickade yllevaror. Varumärke:\n»Palma». Firman driver även\nengroshan-del med trikåvaror och strumpor.\n\nTelegr.-adr.: Palma, Borås. Telefon:\n13732. Postgiro: 84929. — Akt.-kap.:\n150,000 kr. Antal industriarb.: 35.\nTillv.-värde pr år: 900,000 kr. — Bolaget\ngrundat 1931.\n\nStyrelse: dir. Martin Palm (ordf.),\nlagerchef Arvid Knutson.\n\nVerkst. dir.: Martin Palm.\n\nAB. Arvid Palmgrens Mekaniska\nWerkstad, Norrköping.\n\nMek. verkstad och kopparslageri samt\nkonstruktionsbyrå. Tillverkar maskiner\noch apparater för apotekslaboratorier\n(även för^elektrisk drift), för bryggerier,\ntextilfabriker, karamellfabriker,\nbadinrättningar m. m. Bolaget är jämväl\nvärme-, gas- och\nvattenledningsentreprenör.\n\nTelegr.-adr.: Arvid, Norrköping.\nTelefon: 20057 o. 25721. Postgiro: 29420. —\nAkt.-kap.: 50,000 kr. Antal industriarb.:\n35. Tillv.-värde pr år: 750,000 kr. —\nBolaget grundat 1870.\n\nStyrelse: ing. Henrik Berg, adv. S.\nLe-vander, verkstadschef Eric Swensson.\n\nVerkst. dir.: H. Berg.\n\nJoh. Palmgren AB., Stockholm.\n\nSadehnakeri i Stockholm. Tillverkar\nsa-delmakeriartiklar såsom sadlar, seldon\nm. m., reseffekter m. fl. lädervaror, spec.\nhandgjorda. Firman driver även detalj\n-och engroshandel med lädervaror.\n\nHuvudkontor: Stockholm, Sibylleg. 17.\nTelegr.-adr.: Sadel, Stockholm. Telefon:\n610473, 620485 o. 625467. Postgiro: 50204.\nFilialkontor: Hälsingborg, telefon: 19079.\n\nAkt.-kap.: 375,000 kr. Arb.-antal: 75.\nTillv.-värde pr år: 770,000 kr — Firman,\netabli 1&amp;96, äger Ullersäter Lädervaru AB.\n\nStyrelse: hovsadelmakare Joh.\nPalmgren (ordf.), sadelmakaremästare Mårten\nPalmgren, kamrer Knut Jällgård.\n\nVerkst. dir.: sadelmakaremäst. Mårten\nPalmgren.\n\n569*\n\nInköpschef: Nils Palmgren.\nFilialförest, i Hälsingborg: Erik\nPalmgren.\n\nKamrer: Knut Jällgård.\n\n\"AB. Palmqvist &amp; Holm, Halmstad.\nSe J. A. Holms AB., Halmstad.\n\nPappemballage AB., Stockholm.\n\nBolaget representerar följande företag:\nThorsviks AB., Norrahammar, Stockholms\nKartong- &amp; Litografiska AB. (avd. för\nColumbus-kartonger), samt Göteborgs\nWellpappfabriks AB., Göteborg.\n\nBolaget utför genom anslutna firmor\nwellpappfabrikat av olika slag.\nVarumärken: »Columbus»- o. »Teve»-kartonger\n(av korrugerad papp).\n\nKontor: Stockholm, Vasag. 16.\nTelegr.-adr.: Pappemballage, Stockholm. Telefon:\n»Stockholms Kartong o. Lito». Postgiro:\n4549. Avd.-kontor: Göteborg, Mölndalsv.,\ntelefon: 163541; Malmö, Bassing. 4,\ntelefon: 23062.\n\nBolaget, grundat 1928, är anslutet till\nAB. Sveriges Litografiska Tryckerier.,\nStockholm (se detta bolag).\n\nStyrelse o. verkst. dir.: major C. G.\nÅhlund.\n\nDisp.: John Holm.\n\nFörsäljn.-chef er: Göteborg: O. Gerle;\nMalmö: K. Lindskog.\n\n\"Pappersindustri Birger Petraeus,\n\nStockholm.\n\nTillverkar marmorerat och färgat pap\nper och kartong for bokindustrien.\nFirman driver även handel med emulsioner\nför kartongindustrien samt pappers- och\nkartonglack.\n\nKontor: Kungstensg. 18. Telegr.-adr.:\nPetreus, Stockholm. Telefon: 304730.\nPostgiro: 54188. — Antal industriarb.:\n15. — Firman etabl. 1919.\n\nÄgare o. chef: fabr. Birger Petraeus.\nAssistent: Tore Petrseus.\n\n\"AB. Papyrus, Mölndal.\n\nPappersbruk med sulfitfabrik och\nträ-sliperi vid Mölndal (Göteb. o. Bohus l.).\nTillverkar skriv-, post-, tryck-,\nkuvert-och omslagspapper, kromopapper,\nläderimitation, fantasipapper och kartong\nsamt sulfitcellulosa och slipmassa för\neget bruk.\n\nTelegr.-adr. o. telefon: Papyrus,\nGöteborg. Postgiro: 11880.\n\nRepresentanter: i Stockholm: AB.\nSvanströms Pappersagentur, Stadsgår-",
    "structured": {
        "1": {
            "name": "Palm—Papyrus",
            "location": "Borås",
            "business": "Mössor samt huvor",
            "contact": {
                "phone": [
                    "Palms fabriker"
                ],
                "postgiro": "90900"
            },
            "financials": {
                "capital": "Not available",
                "employees": {
                    "industriarb": 45
                }
            },
            "foundation_year": 1886,
            "current_name_year": null,
            "predecessor": null,
            "original_name": null,
            "corporation_year": null,
            "board": [
                {
                    "name": "Gösta Palm",
                    "role": "Ägare o. chef"
                }
            ],
            "owners": null,
            "director": null,
            "managing_director": null,
            "sales_manager": null,
            "manager": null
        },
        "2": {
            "name": "AB. Martin Palm",
            "location": "Borås",
            "business": "Konfektionsfabrik",
            "contact": {
                "phone": [
                    "13732"
                ],
                "postgiro": "84929"
            },
            "financials": {
                "capital": "150,000 kr",
                "employees": {
                    "industriarb": 35
                },
                "annual_production_value": "900,000 kr"
            },
            "foundation_year": 1931,
            "current_name_year": null,
            "predecessor": null,
            "original_name": null,
            "corporation_year": null,
            "board": [
                {
                    "name": "Martin Palm",
                    "role": "dir. (ordf.)"
                },
                {
                    "name": "Arvid Knutson",
                    "role": "lagerchef"
                }
            ],
            "owners": null,
            "director": "Martin Palm",
            "managing_director": "Martin Palm",
            "sales_manager": null,
            "manager": null
        },
        "3": {
            "name": "AB. Arvid Palmgrens Mekaniska Werkstad",
            "location": "Norrköping",
            "business": "Mek. verkstad och kopparslageri",
            "contact": {
                "phone": [
                    "20057",
                    "25721"
                ],
                "postgiro": "29420"
            },
            "financials": {
                "capital": "50,000 kr",
                "employees": {
                    "industriarb": 35
                },
                "annual_production_value": "750,000 kr"
            },
            "foundation_year": 1870,
            "current_name_year": null,
            "predecessor": null,
            "original_name": null,
            "corporation_year": null,
            "board": [
                {
                    "name": "Henrik Berg",
                    "role": "ing."
                },
                {
                    "name": "S. Le-vander",
                    "role": "adv."
                },
                {
                    "name": "Eric Swensson",
                    "role": "verkstadschef"
                }
            ],
            "owners": null,
            "director": "H. Berg",
            "managing_director": null,
            "sales_manager": null,
            "manager": null
        },
        "4": {
            "name": "Joh. Palmgren AB.",
            "location": "Stockholm",
            "business": "Sadehnakeri",
            "contact": {
                "phone": [
                    "610473",
                    "620485",
                    "625467"
                ],
                "postgiro": "50204"
            },
            "financials": {
                "capital": "375,000 kr",
                "employees": {
                    "Arb.-antal": 75
                },
                "annual_production_value": "770,000 kr"
            },
            "foundation_year": 1896,
            "current_name_year": null,
            "predecessor": null,
            "original_name": "Ullersäter Lädervaru AB",
            "corporation_year": null,
            "board": [
                {
                    "name": "Joh. Palmgren",
                    "role": "hovsadelmakare (ordf.)"
                },
                {
                    "name": "Mårten Palmgren",
                    "role": "sadelmakaremästare"
                },
                {
                    "name": "Knut Jällgård",
                    "role": "kamrer"
                }
            ],
            "owners": null,
            "director": "sadelmakaremäst. Mårten Palmgren",
            "managing_director": null,
            "sales_manager": "Nils Palmgren",
            "manager": "Erik Palmgren"
        },
        "5": {
            "name": "AB. Palmqvist & Holm",
            "location": "Halmstad",
            "business": "Not available"
        },
        "6": {
            "name": "Pappemballage AB.",
            "location": "Stockholm",
            "business": "Wellpappfabrikat"
        },
        "7": {
            "name": "Pappersindustri Birger Petraeus",
            "location": "Stockholm",
            "business": "Tillverkar marmorerat och färgat pap per och kartong"
        },
        "8": {
            "name": "AB. Papyrus",
            "location": "Mölndal",
            "business": "Pappersbruk med sulfitfabrik och trä-sliperi"
        }
    }
}