{
    "original": "Bröderna\n\nBröderna Lindqvist, Säter.\n\nMek. verkstad i Säter (Kopparb. l.).\nTillverkar sågverksmaskiner såsom\ncirkelsågverk, dubbla kantverk, kapsågar,\nspånfläktar samt slipmaskiner för klingor.\nFirman driver även maskinaffär.\n\nTelefon: 210. Postgiro: 98159. —\nAntal industriarb.: 25. Tillv.-värde pr år:\n500,000 kr. — Firman etabl. 1933.\n\nÄgare o. chefer: fabr. Nils Lindqvist,\nfabr. Olof Lindqvist o. fabr. Pontus\nLindqvist.\n\nAB. Bröderna Ljungdell, Malmö.\n\nGjuteri och mek. verkstad. Tillverkar\njärn- och aluminiumgjutgods, hattformar,\nsmides- och plåtarbeten m. m.\n\nKontor: Fosievägen; postadr.: Malmö\n7. Telegr.-adr.: Ljungdells, Malmö.\nTelefon: 22666. Postgiro: 38144.\n\nAkt.-kap.: 90,900 kr. Antal\nindustriarb.: 45. Tillv.-värde pr år: 400,000 kr.\n— Bolaget grundat 1909.\n\nDisp.: Hjalmar Larsson.\n\nKamrer: Nils Neymark.\n\nBröderna Ljungquist, Jönköping.\n\nBleckkärisfabrik. Tillverkar\nhushållskärl i bleckplåt, aluminium och rostfritt,\nlackerade artiklar samt leksaker. Firman\ndriver även engroshandel med\nfrämmande fabrikat inom branschen.\n\nTelefon: 1314, 1373 o. 1399. Postgiro:\n29000. — Antal industriarb.: 35.\nTillv.-värde pr år: 650,000 kr. — Firman etabl.\n1919.\n\nÄgare o. chefer: fabr. Josef\nLjungquist o. fabr. Nils Ljungquist.\n\nBröderna Lundberg &amp; Co-, Smides\nAB., Stockholm.\n\nSe Smides AB. Bröderna Lundberg &amp;\nCo., Stockholm.\n\n* Bröderna Lönn, Göteborg.\n\nTillverkar järnkonstruktioner,\nbyggnads- och skeppssmiden samt\ngrovplåts-arbeten.\n\nKontor: Tredje Långg. 26. Telefon:\n141877 o. 144074. Postgiro: 41366.\n\nAntal industriarb.: 20. Tillv.-värde pr\når: 300,000 kr. — Firman etabl. 1897\nunder namn Smidesfirman O. A. Möller,\nnuv. namn 1946.\n\nÄgare: fabr. Harry Lönn, verkm.\nGunnar Lönn o. verkm. Lennart Lönn.\n\nVerkstadschef: Gunnar Lönn.\n\n\"Bröderna Magnusson, Borås.\n\nDamkonfektionsfabrik. Tillverkar\nklänningar, blusar och kjolar samt städrockar\nm. m.\n\nTelefon: 17495. Postgiro: 86809. —\nAntal industriarb.: 75 (excl.\nhemarbetare). — Firman, etabl. 1934, äger AB.\nYmakonfektion, Göteborg.\n\nÄgare o. chefer: köpm. Yngve\nMagnusson o. köpm. Tage Magnusson.\n\n*AB. Bröderna Magnusson Trä &amp;\nMetallindustri, Gnosjö.\n\nTillverkar skoblock, leksaker samt\nsvar-veriartiklar i trä och pressade artiklar i\nmetall vid trä- och metallmanufakturverk\ni Gnosjö (Jönköp. l.).\n\nTelefon: 65. Postgiro: 93309. —\nAkt.-kap.: 50,000 kr. Antal industriarb.: 13.\nTillv.-värde pr år: 150,000 kr. — Firman\netabl. 1933, bolag 1946.\n\nStyrelse: fabr. Oscar Magnusson (ordf.),\nfabr. Anton Magnusson, fabr. Einar\nMagnusson.\n\nDisp.: Oscar Magnusson.\n\nAB. Bröderna Malmqvlsts\nMöbelfabrik, Malmbäck.\n\nSe Industri AB. Mbk.-W., Malmbäck.\n\nBröderna Malmströms\nMetallvaru-fabrik, Malmö.\n\nMetallgjuteri och metallvarufabrik.\nTillverkar elektrisk belysningsarmatur,\nstålrörsmöbler, askurnor, massartiklar,\njärnvägstekniska armaturer och\napparater samt lamphållare; utför\nmetallpressning, metall tryckning, förnickling,\nförkromning, udylitisering, metallisering\nm. m.\n\nHuvudkontor: Porslinsg. 3.\nTelegr.-adr.: Metallmalmström, Malmö. Telefon:\n26002—03. Avd.-kontor: Stockholm,\nBirger Jarlsg. 55, telefon: 109897. — Antal\nindustriarb.: 100. — Firman etabl. 1926.\n\nÄgare o. chef: civiling. K. G.\nLindesvärd.\n\n* Bröderna Melinders Skofabrik,\n\nMjällom.\n\nTillverkar grövre skodon vid fabrik i\nMjällom (Västernorrl. l.).\n\nTelefon: 6 o 7. Postgiro: 70258. —\nAntal industriarb.: 50. Tillv.-värde pr år:\n1,200,000 kr. — Firman etabl. 1930.\n\nÄgare o. chefer: fabr. Helmer\nMelin-der o. fabr. Erland Melinder.",
    "structured": {
        "firms": [
            {
                "name": "Bröderna Lindqvist",
                "location": "Säter",
                "business": "Mekanisk verkstad",
                "products": "Tillverkar sågverksmaskiner såsom cirkelsågverk, dubbla kantverk, kapsågar, spånfläktar samt slipmaskiner för klingor. Firman driver även maskinaffär.",
                "contact": {
                    "office": "Undefined",
                    "phone": [
                        "210"
                    ],
                    "postgiro": "98159",
                    "head_office": "Undefined",
                    "telegraph": "Undefined",
                    "factory_office": "Undefined",
                    "factory_phone": "Undefined"
                },
                "financials": {
                    "capital": "Undefined",
                    "employees": {
                        "industriarb": 25
                    },
                    "annual_turnover": "500,000 kr",
                    "annual_production_value": "Undefined"
                },
                "foundation_year": 1933,
                "owners": [
                    "fabr. Nils Lindqvist",
                    "fabr. Olof Lindqvist",
                    "fabr. Pontus Lindqvist"
                ]
            },
            {
                "name": "AB Bröderna Ljungdell",
                "location": "Malmö",
                "business": "Gjuteri och mekanisk verkstad",
                "products": "Tillverkar järn- och aluminiumgjutgods, hattformar, smides- och plåtarbeten m.m.",
                "contact": {
                    "office": "Fosievägen",
                    "phone": [
                        "22666"
                    ],
                    "postgiro": "38144",
                    "telegraph": "Ljungdells, Malmö",
                    "factory_phone": "Undefined"
                },
                "financials": {
                    "capital": "90,900 kr",
                    "employees": {
                        "industriarb": 45
                    },
                    "annual_turnover": "400,000 kr",
                    "annual_production_value": "Undefined"
                },
                "foundation_year": 1909,
                "board": [
                    {
                        "name": "Hjalmar Larsson",
                        "role": "Disp."
                    }
                ],
                "owner": "Nils Neymark"
            },
            {
                "name": "Bröderna Ljungquist",
                "location": "Jönköping",
                "business": "Bleckkärisfabrik",
                "products": "Tillverkar hushållskärl i bleckplåt, aluminium och rostfritt, lackerade artiklar samt leksaker. Firman driver även engroshandel med främmande fabrikat inom branschen.",
                "contact": {
                    "phone": [
                        "1314",
                        "1373",
                        "1399"
                    ],
                    "postgiro": "29000",
                    "factory_office": "Undefined",
                    "factory_phone": "Undefined"
                },
                "financials": {
                    "capital": "Undefined",
                    "employees": {
                        "industriarb": 35
                    },
                    "annual_turnover": "650,000 kr",
                    "annual_production_value": "Undefined"
                },
                "foundation_year": 1919,
                "owners": [
                    "fabr. Josef Ljungquist",
                    "fabr. Nils Ljungquist"
                ]
            },
            {
                "name": "AB Bröderna Lönn",
                "location": "Göteborg",
                "business": "Tillverkar järnkonstruktioner, byggnads- och skeppssmiden samt grovplåtsarbeten"
            },
            {
                "name": "Bröderna Magnusson",
                "location": "Borås",
                "business": "Damkonfektionsfabrik",
                "products": "Tillverkar klänningar, blusar och kjolar samt städrockar m.m.",
                "contact": {
                    "phone": [
                        "17495"
                    ],
                    "postgiro": "86809"
                },
                "financials": {
                    "capital": "Undefined",
                    "employees": "Undefined",
                    "annual_turnover": "Undefined",
                    "annual_production_value": "Undefined"
                },
                "foundation_year": 1934,
                "owners": [
                    "köpm. Yngve Magnusson",
                    "köpm. Tage Magnusson"
                ]
            },
            {
                "name": "AB Bröderna Magnusson Trä & Metallindustri",
                "location": "Gnosjö",
                "business": "Tillverkar skoblock, leksaker samt svartverksartiklar i trä och pressade artiklar i metall vid trä- och metallmanufakturverk i Gnosjö (Jönköp. l.).",
                "contact": {
                    "phone": [
                        "65"
                    ],
                    "postgiro": "93309"
                },
                "financials": {
                    "capital": "50,000 kr",
                    "employees": {
                        "industriarb": 13
                    },
                    "annual_turnover": "150,000 kr",
                    "annual_production_value": "Undefined"
                },
                "board": [
                    {
                        "name": "fabr. Oscar Magnusson",
                        "role": "ordf."
                    },
                    {
                        "name": "fabr. Anton Magnusson",
                        "role": "Undefined"
                    },
                    {
                        "name": "fabr. Einar Magnusson",
                        "role": "Undefined"
                    }
                ],
                "owner": "Oscar Magnusson"
            },
            {
                "name": "AB Bröderna Malmqvists Möbelfabrik",
                "location": "Malmbäck",
                "business": "Undefined"
            },
            {
                "name": "Bröderna Malmströms Metallvarufabrik",
                "location": "Malmö",
                "business": "Metallgjuteri och metallvarufabrik",
                "products": "Tillverkar elektrisk belysningsarmatur, stålrörsmöbler, askurnor, massartiklar, järnvägstekniska armaturer och apparater samt lamphållare; utför metallpressning, metalltryckning, förnickling, förkromning, udylitisering, metallisering m.m.",
                "contact": {
                    "office": "Porslinsg. 3",
                    "telegraph": "Metallmalmström, Malmö",
                    "phone": [
                        "26002-03"
                    ]
                },
                "financials": {
                    "capital": "Undefined",
                    "employees": {
                        "industriarb": 100
                    },
                    "annual_turnover": "Undefined",
                    "annual_production_value": "Undefined"
                },
                "owner": "civiling. K. G. Lindesvärd"
            },
            {
                "name": "Bröderna Melinders Skofabrik",
                "location": "Mjällom",
                "business": "Tillverkar grövre skodon vid fabrik i Mjällom (Västernorrl. l.).",
                "contact": {
                    "phone": [
                        "6",
                        "7"
                    ],
                    "postgiro": "70258"
                },
                "financials": {
                    "capital": "Undefined",
                    "employees": {
                        "industriarb": 50
                    },
                    "annual_turnover": "1,200,000 kr",
                    "annual_production_value": "Undefined"
                },
                "owners": [
                    "fabr. Helmer Melinder",
                    "fabr. Erland Melinder"
                ]
            }
        ]
    }
}