{
    "original": "N orrbaclwn^—N orrhiM\n\nDisp.: E. Heden blad.\n\nTeJcn. dir. o. övering.: R. Malcolm.\n\nKontorschef: E. Törnqvist.\n\nKamrer: Sven Ek.\n\nFörsäljn.-chef er: för gjutgods: E.\nTörnqvist; för elartiklar: Göte Persson; för\nvärmeledn.-artiklar: A, Gustafsson o.\nJacob Engqvist.\n\nChefer för tekniska avd.: M.\nAxmac-her, C.-G. Söderlund o. E. G. Sjögren.\n\n\"Norrbacken, Maskinfabriks AB.,\n\nBlomster måla.\n\nSe Maskinfabriks AB. Norrbacken,\nBlomstermåla.\n\n\"AB. Norrborns Tegelbruk,\n\nBollnäs.\n\nTegelbruk i Bollnäs (Norrbornsbruket)\n, och i Söräng (Sör ängsbruket) (båda i\nGävleb. l.). Tillverkar mur- och taktegel,\nmellanväggsplattor samt dräneringsrör.\n\nFörsäljningskontor: Bollnäs, telefon:\n10870, postgiro: 142844.\nt Akt.-kap.: 80,000 kr. Årstillv.: 2 milj.\n1 st. ’tegelvaror. — Bolaget grundat 1927.\n\nStyrelse: tegelm. Oskar Gustafsson, dir.\nDavid Sköld, kamrer Gustaf Sköld.\n\nVerkst. dir.: David Sköld.\n\n\"AB. Norrbottens Cementgjuteri,\n\nÖjehyn.\n\nBetongvarufabrik och entreprenörfirma\ni öjebyn (Norrb. l.). Tillverkar\navloppsrör, kulvertar, vibroblock, grundtegel,\ntrottoarplattor samt betong och murbruk.\n\nKontor: öjebyn. Telefon: Piteå 60041.\nPostgiro: 67913. — Akt.-kap.: 25,000 kr.\n. Antal industriarb.: 40. Prod.-värde pr år:\n500,000 kr. — Firman etabl. 1920, bolag\n1945.\n\nVerkst. dir.: ing. Ivan Hedlund.\nNorrbottens Järnverk AB., Luleå.\n\nElektriskt tackjärnsverk och elektriskt\nstålverk. Tillverkar martintackjärn,\nhe-matittaekjärn och gjuteri tack järn samt\nelektrostålgöt. Varumärke: NJA.\n\nTelegr.-adr. o. telefon: Norrbottens\nJärnverk, Luleå. Postgiro: 65311.\n\nAkt.-kap.: 26,500,000 kr. Antal\nindustriarb.: 225. Tillv.-värde pr år:\n12.000,000 kr. — Bolaget, grundat 1940,\näges av svenska staten.\n\nStyrelse: dir. Sverre R:son Sohlman\n(ordf.), riksdagsm. Oscar Lövgren (v.\nordf.), frih. Gerard De Geer, bruksäg. R.\nv. Seth, sekr. Gust. Vahlberg, förbunds-\n\nordf. Oscar Westerlund, dir. Bertil\nÅs t r öm.\n\nVerkst. dir.: Bertil Åström.\n\növering.: Sven Hjerdin.\n\nIntendent: Gottfrid Öjeby.\n\nNorrbottens Träförädlings AB.,\n\nLuleå.\n\nSågverk, hyyleri, trähusfabrik och\nträ-mjölsfabrik. Tillverkar sågade och hyvlade\nträvaror, monteringsfärdiga trähus samt\nträmjöl för linoleum- och\nbakelitindustrierna m. fl. tekniska ändamål.\n\nTelegr.-adr,: Norrbottensträ, Luleå.\nTelefon: 3630, 3631 o. 3632. Postgiro:\n65092. Exportförsäljn.: Förenade\nTrähusfabriker, Förening u. p. a., Stockholm,\nSveavägen 39, telefon: 202416.\n\nAkt.-kap.: 330,000 kr. Antal\nindustriarb.: 50. Tillv.-värde pr år; 1,300,000 kr.\n\n—\tBolaget grundat 1941.\nVerkst. dir.: Fritz Forsberg.\nInköpschef: Tage Forsberg.\n\n\"Norrby Nya AB., Borås.\n\nSågverk, hyvleri och snickerifabrik.\nTillverkar sågade och hyvlade trävaror\nsamt byggnadssnickerier och inredningar.\n\nTelefon: 10275. Postgiro: 170853. —\nAkt.-kap.: 50,000 kr. Antal industriarb.:\n30. Tillv.-värde pr år: 700,000 kr. —\nFirman grundad 1898, bolag 1921.\n\nStyrelse o. verkst. dir.: disp. Eric\nMagnusson.\n\n\"Norrfors Snickerifabrik, Norrfors.\nSe AB, Norrlandsmöbler, Umeå.\n\nAB. Norrhults Cjuteri, Norrhult.\n\nGjuteri och mek. verkstad i Norrhult\n(Kronob. l.). Tillverkar\nbyggnadsgjut-srods, kokspisar, vattenvärmare,\nvärmeledningspannor samt slussventiler.\nVarumärke: »N.H.G.».\n\nTelegr.-adr.: Gjuteriet, Norrhult.\nTelefon: 9 o. 135. Postgiro: 8854.\n\nRepresentanter för\nvärmeledningspannor: i Stockholm: AB. Rör &amp; Värme,\ntelefon: 234900; i Göteborg o. Kalmar:\nAB. Hill &amp; Co., telefon: Göteborg 155390\no, Kalmar: Namnanrop »Hill &amp; Co».\n\nAkt.-kap.: 178,200 kr. Antal\nindustriarb.: 60. Tillv.-värde pr år: 700,000 kr.\n\n—\tFirman etabl. 1900, bolag 1935.\nStyrelse: fru S. Alm, stationsinsp. A.\n\nHjälm, disp. Alfr. Johansson, disp. Yngve\nJohansson, gjutm. Edvin Ståhl.\nVerkst. dir.: Alfr. Johansson.",
    "structured": {
        "1": {
            "name": "AB. Norrborns Tegelbruk",
            "location": "Bollnäs",
            "business": "Tegelbruk i Bollnäs (Norrbornsbruket) , och i Söräng (Sör ängsbruket) (båda i Gävleb. l.). Tillverkar mur- och taktegel, mellanväggsplattor samt dräneringsrör.",
            "contact": {
                "office": "Bollnäs",
                "phone": "10870",
                "postgiro": "142844"
            },
            "financials": {
                "capital": "80,000 kr",
                "annual_turnover": "2 milj. 1 st. ’tegelvaror"
            },
            "foundation_year": 1927,
            "board": [
                {
                    "name": "tegelm. Oskar Gustafsson",
                    "role": "styrelse"
                },
                {
                    "name": "dir. David Sköld",
                    "role": "verkst. dir."
                },
                {
                    "name": "kamrer Gustaf Sköld",
                    "role": "styrelse"
                }
            ]
        },
        "2": {
            "name": "AB. Norrbottens Cementgjuteri",
            "location": "Öjehyn",
            "business": "Betongvarufabrik och entreprenörfirma i öjebyn (Norrb. l.). Tillverkar avloppsrör, kulvertar, vibroblock, grundtegel, trottoarplattor samt betong och murbruk.",
            "contact": {
                "office": "öjebyn",
                "phone": "Piteå 60041",
                "postgiro": "67913"
            },
            "financials": {
                "capital": "25,000 kr",
                "employees": {
                    "industriarb.": 40
                },
                "annual_production_value": "500,000 kr"
            },
            "foundation_year": 1920,
            "corporation_year": 1945,
            "director": "ing. Ivan Hedlund"
        },
        "3": {
            "name": "Norrbottens Järnverk AB.",
            "location": "Luleå",
            "business": "Elektriskt tackjärnsverk och elektriskt stålverk. Tillverkar martintackjärn, hematittaekjärn och gjuteri tackjärn samt elektrostålgöt.",
            "contact": {
                "office": "Luleå",
                "phone": "Norrbottens Järnverk, Luleå",
                "postgiro": "65311"
            },
            "financials": {
                "capital": "26,500,000 kr",
                "employees": {
                    "industriarb.": 225
                },
                "annual_turnover": "12,000,000 kr"
            },
            "corporation_year": 1940,
            "board": [
                {
                    "name": "dir. Sverre R:son Sohlman",
                    "role": "styrelse"
                },
                {
                    "name": "riksdagsm. Oscar Lövgren",
                    "role": "styrelse"
                },
                {
                    "name": "frih. Gerard De Geer",
                    "role": "styrelse"
                },
                {
                    "name": "bruksäg. R. v. Seth",
                    "role": "styrelse"
                },
                {
                    "name": "sekr. Gust. Vahlberg",
                    "role": "styrelse"
                },
                {
                    "name": "förbundsordf. Oscar Westerlund",
                    "role": "styrelse"
                }
            ],
            "director": "Bertil Åström",
            "managing_director": "Bertil Åström"
        },
        "4": {
            "name": "Norrbottens Träförädlings AB.",
            "location": "Luleå",
            "business": "Sågverk, hyyleri, trähusfabrik och trä-mjölsfabrik. Tillverkar sågade och hyvlade trävaror, monteringsfärdiga trähus samt trämjöl för linoleum- och bakelitindustrierna m.fl. tekniska ändamål.",
            "contact": {
                "office": "Luleå",
                "phone": "3630, 3631 o. 3632",
                "postgiro": "65092"
            },
            "financials": {
                "capital": "330,000 kr",
                "employees": {
                    "industriarb.": 50
                },
                "annual_production_value": "1,300,000 kr"
            },
            "foundation_year": 1941,
            "board": [
                {
                    "name": "Fritz Forsberg",
                    "role": "verkst. dir."
                },
                {
                    "name": "Tage Forsberg",
                    "role": "inköpschef"
                }
            ]
        },
        "5": {
            "name": "Norrfors Snickerifabrik",
            "location": "Norrfors",
            "business": "Se AB, Norrlandsmöbler, Umeå."
        },
        "6": {
            "name": "AB. Norrhults Cjuteri",
            "location": "Norrhult",
            "business": "Gjuteri och mek. verkstad i Norrhult (Kronob. l.). Tillverkar byggnadsgjutprods, kokspisar, vattenvärmare, värmeledningspannor samt slussventiler."
        }
    }
}