{
    "original": "Salarider—Sanda\n\n27762. — Akt.-kap.: 200,000 kr. Antal\nindustriarb.: 24. — Bolaget grundat 1875.\n\nStyrelse o. verkst. dir..; Frithiof\nHammar.\n\nDisp.: 0. G. Hammar.\n*Sa!anders Fabriks AB., Lund.\n\nFärgeri, ullspinneri och väveri.\nTillverkar ullgarner, filtar, damulstertyger\noch mattor.\n\nTelefon: 17355. Postgiro: 72324.\n\nAkt.-kap.: 166,000 kr. Antal\nindustriarb.: 136. Tillv.-värde pr år: 3,500,000 kr.\n— Firman etabl. 1850, bolag 1904.\n\nStyrelse: disp. P. A. Meynert (ordf.),\nadv. Carl-Eric Ingelgren, fru F. Larsson,\nfru M. Meynert.\n\nVerkst. dir. o. disp.: P. A. Meynert.\n\n\"Saléns Konfektionsfabrik,\n\nStockholm.\n\nSe Konfektions AB. Salén, Stockholm.\n\nSalpeterverken, AB. Svenska,\n\nKöping.\n\nSe AB. Svenska Salpeterverken,\nKöping.\n\n\"AB. Saltsjöqvarn, Stockholm.\n\nKvarn vid Saltsjökvarn (Sthlms l.).\nTillverkar vetemjöl, rågsikt, rågmjöl och\nmannagryn samt fodervaror. Varunamn\nför vetemjöl: »Kejsarkronan» m. fl.\n\nHuvudkontor: Stockholm, Skeppsbron\n22. Telegr.-adr. o. telefon: Saltsjöqvarn,\nStockholm. Postgiro: 500. Fabrikskontor\nvid Saltsjökvarn.\n\nAkt.-kap.: 5,000,000 kr. Antal\nindustriarb.: 191, Prod.-värde pr år: 21,000,000\nkr.\n\nKvarnen anlagd 1889, nuvarande bolag\ngrundat 1923.\n\nStyrelse: landshövd. Joh. Nilsson\n(ordf.), dir. Hjalmar Carlborn, civiling.\nGunnar Molin, v. konsul Carl Nilsson,\nciviling. Sten Westerberg.\n\nVerkst. dir.: Hj. Carlborn.\n\nV. verkst. dir.: Gunnar Molin.\n\nSalsta-Wattholma Tegelbruk,\n\nVattholma.\n\nTillverkar mur- och taktegel samt\ndräneringsrör vid tegelbruk tillhörande\nSal-sta-Wattholms egendomar vid Vattholma\n(Uppsala l.).\n\nTelefon: 4. Postgiro: 166070. — Antal\n\n30\n\nindustriarb.: 24. Årstillv.: 0,6 milj. st.\ntegelvaror. — Tegelbruket anlagt 1873.\n\nÄgare o. chef: frih. Per Erik v. Essen.\n\nKassör: Th. Thunell.\n\nSaltviks Slip &amp; Varv, E. Björkman,\n\nOskarshamn.\n\nBygger och reparerar träfartyg såsom\nmotorseglare, motorfiskebåtar och\nlivbåtar.\n\nTelefon: 204. Postgiro: 144490.\nAntal industriarb.: 25. Tillv.-värde pr år:\n200,000 kr. — Firman etabl. 1899.\n\nÄgare o. chef: ing. Efraim Björkman.\n\nSalubrinfabriken, Eslöv.\n\nSe AB. P. Håkansson, Eslöv.\n\nAlbert Samuelsson &amp; C:o.,\n\nSkeppshult.\n\nTillverkar cyklar vid fabrik i\nSkepps-hult (Jönköp. l.). Varumärken:\n»Smålands Original», »Record Original»,\n»Skeppshult» o. »S».\n\nTelefon: 8. Postgiro: 8120. — Antal\nindustriarb.: 45. Tillv.-värde pr år:\n600,000 kr. — Firman etabl. 1920.\n\nÄgare: Albert Samuelssons sterbhus o.\nfabr. Arvid Samuelson.\n\nChef: Arvid Samuelson.\n\n\"AB. Victor Samuelsons\nStrumpfabrik, Mölndal.\n\nTillverkar strumpor.\n\nKontor: Mölndal. Telefon: Göteborg\n272030. Postgiro: 40770.\n\nAkt.-kap.: 500,000 kr. Antal\nindustri-arb.: 260. Tillv.-värde pr år: 3,500,000 kr.\n\n—\tBolaget grundat 1935.\n\nStyrelse o. verkst. dir.: Victor\nSamuelson.\n\nAB. Sana Trikåfabrik,\n\nNorrköping.\n\nTillverkar herrunderkläder.\nVarumärke: »Sana».\n\nTelegr.-adr.: Sana, Norrköping.\nTelefon: 20604. Postgiro: 161036. —\nAkt.-kap.: 10,000 kr. Antal industriarb.: 30.\n\n—\tFirman etabl. 1908, bolag 1918.\n\nStyrelse o. verkst. dir.: Lennart\nAllberg.\n\n\"AB. Sanda Tegelbruk, Stockholm.\n\nSe Nya AB. Sanda Tegel, Stockholm.",
    "structured": {
        "1": {
            "name": "Salarider—Sanda",
            "location": "Lund",
            "business": "Färgeri, ullspinneri och väveri",
            "products": "Tillverkar ullgarner, filtar, damulstertyger och mattor.",
            "contact": {
                "office": "Sanda, Lund",
                "phone": [
                    "17355"
                ],
                "postgiro": "72324",
                "head_office": "Lund",
                "telegraph": "",
                "factory_office": "",
                "factory_phone": ""
            },
            "financials": {
                "capital": "166,000 kr",
                "employees": {
                    "industriarb": 136
                },
                "annual_turnover": "3,500,000 kr",
                "annual_production_value": ""
            },
            "foundation_year": 1875,
            "board": [
                {
                    "name": "Frithiof Hammar",
                    "role": "Styrelse o. verkst. dir.."
                }
            ],
            "owner": "",
            "director": "Frithiof Hammar",
            "managing_director": ""
        },
        "2": {
            "name": "Sa!anders Fabriks AB",
            "location": "Lund",
            "business": "",
            "contact": {
                "office": "",
                "phone": [],
                "postgiro": "",
                "head_office": "",
                "telegraph": "",
                "factory_office": "",
                "factory_phone": ""
            },
            "financials": {
                "capital": "200,000 kr",
                "employees": {
                    "industriarb": 24
                },
                "annual_turnover": "",
                "annual_production_value": ""
            },
            "foundation_year": 1850,
            "board": [
                {
                    "name": "disp. P. A. Meynert",
                    "role": "Styrelse"
                },
                {
                    "name": "adv. Carl-Eric Ingelgren",
                    "role": "Styrelse"
                },
                {
                    "name": "fru F. Larsson",
                    "role": "Styrelse"
                },
                {
                    "name": "fru M. Meynert",
                    "role": "Styrelse"
                }
            ],
            "owner": "",
            "director": "P. A. Meynert",
            "managing_director": "P. A. Meynert"
        },
        "3": {
            "name": "AB. Saltsjöqvarn",
            "location": "Stockholm",
            "business": "Kvarn vid Saltsjökvarn (Sthlms l.). Tillverkar vetemjöl, rågsikt, rågmjöl och mannagryn samt fodervaror.",
            "products": "",
            "contact": {
                "office": "Stockholm, Skeppsbron 22",
                "phone": [
                    "Saltsjöqvarn, Stockholm"
                ],
                "postgiro": "500",
                "head_office": "",
                "telegraph": "Saltsjöqvarn, Stockholm",
                "factory_office": "Saltsjökvarn",
                "factory_phone": ""
            },
            "financials": {
                "capital": "5,000,000 kr",
                "employees": {
                    "industriarb": 191
                },
                "annual_turnover": "21,000,000 kr",
                "annual_production_value": ""
            },
            "foundation_year": 1889,
            "board": [
                {
                    "name": "landshövd. Joh. Nilsson",
                    "role": "Styrelse"
                },
                {
                    "name": "dir. Hjalmar Carlborn",
                    "role": "Styrelse"
                },
                {
                    "name": "civiling. Gunnar Molin",
                    "role": "Styrelse"
                },
                {
                    "name": "v. konsul Carl Nilsson",
                    "role": "Styrelse"
                },
                {
                    "name": "civiling. Sten Westerberg",
                    "role": "Styrelse"
                }
            ],
            "owner": "",
            "director": "Hj. Carlborn",
            "managing_director": "Hj. Carlborn"
        },
        "4": {
            "name": "Salsta-Wattholma Tegelbruk",
            "location": "Vattholma",
            "business": "Tillverkar mur- och taktegel samt dräneringsrör vid tegelbruk tillhörande Sal-sta-Wattholms egendomar vid Vattholma (Uppsala l.)",
            "products": "",
            "contact": {
                "office": "",
                "phone": [
                    "4"
                ],
                "postgiro": "166070",
                "head_office": "",
                "telegraph": "",
                "factory_office": "",
                "factory_phone": ""
            },
            "financials": {
                "capital": "",
                "employees": {
                    "industriarb": 24
                },
                "annual_turnover": "",
                "annual_production_value": "0,6 milj. st. tegelvaror"
            },
            "foundation_year": 1873,
            "board": [],
            "owner": "frih. Per Erik v. Essen",
            "director": "",
            "managing_director": ""
        },
        "5": {
            "name": "Saltviks Slip &amp; Varv",
            "location": "Oskarshamn",
            "business": "Bygger och reparerar träfartyg såsom motorseglare, motorfiskebåtar och livbåtar.",
            "products": "",
            "contact": {
                "office": "",
                "phone": [
                    "204"
                ],
                "postgiro": "144490",
                "head_office": "",
                "telegraph": "",
                "factory_office": "",
                "factory_phone": ""
            },
            "financials": {
                "capital": "",
                "employees": {
                    "industriarb": 25
                },
                "annual_turnover": "",
                "annual_production_value": "200,000 kr"
            },
            "foundation_year": 1899,
            "board": [],
            "owner": "ing. Efraim Björkman",
            "director": "",
            "managing_director": "ing. Efraim Björkman"
        },
        "6": {
            "name": "Albert Samuelsson &amp; C:o.",
            "location": "Skeppshult",
            "business": "Tillverkar cyklar vid fabrik i Skepps-hult (Jönköp. l.). Varumärken: »Smålands Original», »Record Original», »Skeppshult» o. »S».",
            "products": "",
            "contact": {
                "office": "",
                "phone": [
                    "8"
                ],
                "postgiro": "8120",
                "head_office": "",
                "telegraph": "",
                "factory_office": "",
                "factory_phone": ""
            },
            "financials": {
                "capital": "",
                "employees": {
                    "industriarb": 45
                },
                "annual_turnover": "",
                "annual_production_value": "600,000 kr"
            },
            "foundation_year": 1920,
            "board": [],
            "owner": "Albert Samuelssons sterbhus o. fabr. Arvid Samuelson",
            "director": "",
            "managing_director": "Arvid Samuelson"
        },
        "7": {
            "name": "AB. Victor Samuelsons Strumpfabrik",
            "location": "Mölndal",
            "business": "Tillverkar strumpor.",
            "products": "",
            "contact": {
                "office": "Mölndal",
                "phone": [
                    "Göteborg 272030"
                ],
                "postgiro": "40770",
                "head_office": "",
                "telegraph": "",
                "factory_office": "",
                "factory_phone": ""
            },
            "financials": {
                "capital": "500,000 kr",
                "employees": {
                    "industriarb": 260
                },
                "annual_turnover": "3,500,000 kr",
                "annual_production_value": ""
            },
            "foundation_year": 1935,
            "board": [],
            "owner": "",
            "director": "Victor Samuelson",
            "managing_director": "Victor Samuelson"
        },
        "8": {
            "name": "AB. Sana Trikåfabrik",
            "location": "Norrköping",
            "business": "Tillverkar herrunderkläder. Varumärke: »Sana».",
            "products": "",
            "contact": {
                "office": "Norrköping",
                "phone": [
                    "20604"
                ],
                "postgiro": "161036",
                "head_office": "",
                "telegraph": "Sana, Norrköping",
                "factory_office": "",
                "factory_phone": ""
            },
            "financials": {
                "capital": "10,000 kr",
                "employees": {
                    "industriarb": 30
                },
                "annual_turnover": "",
                "annual_production_value": ""
            },
            "foundation_year": 1918,
            "board": [],
            "owner": "",
            "director": "Lennart Allberg",
            "managing_director": "Lennart Allberg"
        }
    }
}