{
    "original": "Nya\n\nTillv.-värde pr år: 500,000 kr. —Firman\n■etabl. 1911.\n\nStyrelse: dir. Emil Sundberg (ordf.),\ndisp. Carl-Olof Fogelberg, disp. Ernst\nKarlson.\n\nVerkst. dir.: Carl-Olof Fogelberg.\n\n\"Nya Fabriken Zig-Zag,\n\nMalmköping.\n\nTräförädlingsfabrik i Malmköping\n(Södermanl. l.). Tillverkar massartiklar i trä.\nSpecialitet: bygglådan »Zig-Zag».\n\nTelegr.-adr.: Zigzag, Malmköping.\nTelefon: 133. Postgiro: 163260.\n\nAntal industriarb.: 40. Tillv.-värde pr\nåi: 250,000 kr. — Fabriken anlagd 1910,\nnuv. firma etabl. 1939.\n\nÄgare o. chef: Ragnar Nordqvist.\n\nAB. Nya Fajansfabriken, Förlösa.\n\nTillverkar blomkrukor vid fabrik i\nFörlösa (Kalmar l.).\n\nTelefon: 15. Postgiro: 82742. —\nAkt.-kap.: 25,000 kr. Antal industriarb.: 5.\nÅrstillv.: 800,000 st. blomkrukor. —\nFirman etabl. 1908, bolag 1936.\n\nVerkst. dir.: fabr. Gust. Josefsson.\n\n\"Nya AB. Fermia, Hälsingborg.\n\nGlykos- och kulörfabrik i Hälsingborg\n®amt stärkelsefabrik vid Ingelstorp\nLjungbyhed (Kristianst. l.).\n\nTillverkar glykos, druvsocker, maltos,\ninvertsocker, konsthonung och\nsockerpre-parat (»Fermilin») för karamell- och\neho-kladfabriker samt konditorier, socker-,\nsprit-, vin- och ölkulörer,\nporterkulör-extrakt samt driver handel med\nkapsel-kork (»Idealkork») och sackarin.\n\nHuvudkontor: Hälsingborg.\nTelegr.-.adr.: Fermia, Hälsingborg. Telefon:\n10441, 10600 o. 17737. Postgiro: 13908.\n\nAkt.-kap.: 250,000 kr. Antal\nindustriarb.: 20. — Bolaget grundat 1907.\n\n■Styrelse: v. konsul O. Löfwall (ordf.)y\ndir. Ernst Iacobi, övering. Edward Schön.\n; Verkst. dir.: Ernst Iacobi.\n\n\"Nya AB. Fougstedts Pälsvarufabrik,\n\nMalmö.\n\nTillverkar pälsvaror. Bolaget idkar\njämväl handel med pälsskinn.\n\nKontor: S. Förstadsg. 23 A; postadr.:\nMalmö 4. Telegr.-adr.: Pelsfougstedts,\nMalmö. Telefon: 71620. Postgiro: 38222.\n\nAkt.-kap.: 100,000 kr. Antal\nindustriarb.: 25. Omsättn.-värde pr år: 700,000\nkr. — Firman etabl. 1896.\n\nStyrelse o. verkst. dir.: konsul Rolf\nWinroth.\n\nNya AB. Gotlandsmarmor, Visby.\n\nBryter och förädlar Gotlandsmarmor\nsamt tillverkar byggnadsmarmor och\nbyggnadskalksten.\n\nTelefon: 1213. Postgiro: 189023. —\nAkt.-kap.: 15,000 kr. Antal industriarb.:\n30. Tillv.-värde pr år: 180,000 kr. —\nBolaget grundat 1934.\n\nVerkst. dir.: ing. Bror Fritz.\n\nNya Kartong AB., Stockholm.\n\nTillverkar kartonger för bagerier och\nkonfektfabriiker, för manufaktur- och\n\nkonfektiousaffärer, industrier m. m.\n\nKontor: Industriområdet, Hagalund,\nSolna. Postadr.: Stockholm 6. Telefon:\n272650. Postgiro: 1402.\n\nAkt.-kap.: 80,000 kr. Antal\nindustriarb.: 40. Tillv.-värde pr år: 490,000kr. —\nFabriken grundad 1885, bolag 1908, nuv.\nnamn 1934.\n\nVerkst. dir.: Nils E. Erlandsson\n(Kvidinge).\n\nKamrer o. fabrikschef: C. Oscar\nJohansson.\n\n\"Nya AB. Kolbäcks Cementgjuter i,\n\nKolbäck.\n\nBetongvaruf abrik i Kolbäck\n(Västmanl. l.). Tillverkar massartiklar av\nbetong.\n\nTelefon: 88. Postgiro: 81751. Repr. i\nStockholm: Wald. Waldén AB.,\nTrie-waldsgränd 2, telefon: 100656.\n\nAkt.-kap.: 50,000 kr. Antal\nindustriarb.: 20. Tillv.-värde pr år: 400,000 kr.\n— Bolaget, grundat 1917, ombildat 1923,\näger Svenska Pool-stens AB., Kolbäck.\n\nStyrelse: byggm. Edv. Karlsson (ordf.),\nbanm. Oscar Andersson, godsäg. Harald\nWallin.\n\nVerkst. dir.: Torsten Edvardsson.\n\nAB. Nya Konfektionsfabriken,\n\nUddevalla.\n\nTillverkar herr- och damkonfektion\nsåsom kostymer, överrockar, damdräkter\noch kappor. Varumärke: »Roy».\n\nTelefon: 10866. Postgiro: 134740.—\nAkt.-kap.: 160,000 kr. Antal industriarb.:\n50. Tillv.-värde ,pr år: 700,000 kr. —\nFirman etabl. 1921, bolag 1945.\n\nVerkst. dir.: Abr. Warkol.\n\n\"AB. Nya Kopparbergs Bergslag,\n\nFalun.\n\nBolaget äger sulfidmalmsgruvor i\nÖrebro län, vilka äro utarrenderade till AB.\n\nI*",
    "structured": {
        "1": {
            "name": "Nya Fabriken Zig-Zag",
            "location": "Malmköping",
            "business": "Träförädlingsfabrik",
            "products": "Massartiklar i trä, Specialitet: bygglådan »Zig-Zag»",
            "contact": {
                "office": "Malmköping",
                "phone": [
                    "133"
                ],
                "postgiro": "163260",
                "telegraph": "Zigzag, Malmköping"
            },
            "financials": {
                "capital": "Not available",
                "employees": {
                    "industriarb": 40
                },
                "annual_turnover": "250,000 kr",
                "annual_production_value": "Not available"
            },
            "foundation_year": 1910,
            "current_name_year": 1939,
            "director": "Carl-Olof Fogelberg",
            "owners": [
                "Ragnar Nordqvist"
            ]
        },
        "2": {
            "name": "AB. Nya Fajansfabriken",
            "location": "Förlösa",
            "business": "Förlag för tillverkning av blomkrukor",
            "products": "Blomkrukor",
            "contact": {
                "phone": "15",
                "postgiro": "82742"
            },
            "financials": {
                "capital": "25,000 kr",
                "employees": {
                    "industriarb": 5
                },
                "annual_turnover": "800,000 kr",
                "annual_production_value": "Not available"
            },
            "foundation_year": 1908,
            "corporation_year": 1936,
            "director": "Gust. Josefsson"
        },
        "3": {
            "name": "AB. Nya Fermia",
            "location": "Hälsingborg",
            "business": "Glykos- och kulörfabrik",
            "products": "Glykos, druvsocker, maltos, invertsocker, konsthonung, sockerpreparat (»Fermilin»), kapselkork (»Idealkork»), sackarin",
            "contact": {
                "office": "Hälsingborg",
                "telegraph": "Fermia, Hälsingborg",
                "phone": [
                    "10441",
                    "10600",
                    "17737"
                ],
                "postgiro": "13908"
            },
            "financials": {
                "capital": "250,000 kr",
                "employees": {
                    "industriarb": 20
                },
                "annual_turnover": "Not available",
                "annual_production_value": "Not available"
            },
            "foundation_year": 1907,
            "board": [
                {
                    "name": "O. Löfwall",
                    "role": "ordf."
                },
                {
                    "name": "Ernst Iacobi",
                    "role": "dir."
                },
                {
                    "name": "Edward Schön",
                    "role": "övering."
                }
            ],
            "director": "Ernst Iacobi"
        },
        "4": {
            "name": "AB. Nya Fougstedts Pälsvarufabrik",
            "location": "Malmö",
            "business": "Pälsvarufabrik",
            "products": "Pälsvaror, pälsskinn",
            "contact": {
                "office": "S. Förstadsg. 23 A, Malmö 4",
                "telegraph": "Pelsfougstedts, Malmö",
                "phone": "71620",
                "postgiro": "38222"
            },
            "financials": {
                "capital": "100,000 kr",
                "employees": {
                    "industriarb": 25
                },
                "annual_turnover": "700,000 kr",
                "annual_production_value": "Not available"
            },
            "foundation_year": 1896,
            "director": "Rolf Winroth"
        },
        "5": {
            "name": "Nya AB. Gotlandsmarmor",
            "location": "Visby",
            "business": "Gotlandsmarmorbrytning och -förädling",
            "products": "Byggnadsmarmor, byggnadskalksten",
            "contact": {
                "phone": "1213",
                "postgiro": "189023"
            },
            "financials": {
                "capital": "15,000 kr",
                "employees": {
                    "industriarb": 30
                },
                "annual_turnover": "180,000 kr",
                "annual_production_value": "Not available"
            },
            "foundation_year": 1934,
            "director": "ing. Bror Fritz"
        },
        "6": {
            "name": "Nya Kartong AB.",
            "location": "Stockholm",
            "business": "Tillverkning av kartonger",
            "products": "Kartonger för bagerier, konfektfabriker, manufaktur- och konfektiousaffärer, industrier m.m.",
            "contact": {
                "office": "Industriområdet, Hagalund, Solna",
                "phone": "272650",
                "postgiro": "1402"
            },
            "financials": {
                "capital": "80,000 kr",
                "employees": {
                    "industriarb": 40
                },
                "annual_turnover": "490,000 kr",
                "annual_production_value": "Not available"
            },
            "original_name": "Stockholm 6",
            "corporation_year": 1934,
            "director": "Nils E. Erlandsson (Kvidinge)",
            "manager": "C. Oscar Johansson"
        },
        "7": {
            "name": "AB. Nya Kolbäcks Cementgjuteri",
            "location": "Kolbäck",
            "business": "Betongvarufabrik",
            "products": "Massartiklar av betong",
            "contact": {
                "phone": "88",
                "postgiro": "81751"
            },
            "financials": {
                "capital": "50,000 kr",
                "employees": {
                    "industriarb": 20
                },
                "annual_turnover": "400,000 kr",
                "annual_production_value": "Not available"
            },
            "corporation_year": 1923,
            "board": [
                {
                    "name": "Edv. Karlsson",
                    "role": "byggm."
                },
                {
                    "name": "Oscar Andersson",
                    "role": "banm."
                },
                {
                    "name": "Harald Wallin",
                    "role": "godsäg."
                }
            ],
            "director": "Torsten Edvardsson"
        },
        "8": {
            "name": "AB. Nya Konfektionsfabriken",
            "location": "Uddevalla",
            "business": "Tillverkning av herr- och damkonfektion",
            "products": "Kostymer, överrockar, damdräkter, kappor, Varumärke: »Roy»",
            "contact": {
                "phone": "10866",
                "postgiro": "134740"
            },
            "financials": {
                "capital": "160,000 kr",
                "employees": {
                    "industriarb": 50
                },
                "annual_turnover": "700,000 kr",
                "annual_production_value": "Not available"
            },
            "corporation_year": 1945,
            "director": "Abr. Warkol"
        }
    }
}