{
    "original": "Bröderna—Burseryd\n\nKontor: Riddarg. 16. Telegr.-adr.:\nByggwiklund, Stockholm. Telefon: 670345.\nPostgiro: 151788.\n\nAkt.-kap.: 100,000 kr. — Bolaget\ngrundat 1937.\n\nStyrelse: ing. Bertil Wiklund (ordf.),\nbyggm. Birger Wiklund, ing. Carl\nWiklund, ing. Ragnar Wiklund.\n\nVerkst. dir.: Bertil Wiklund.\n\nArbetschef: Carl Wiklund.\n\n’Bröderna Wästlund &amp; Co., Earlstad.\n\nSe Spadfabriken Karlstad, Bröderna\nWästlund &amp; Co., Karlstad.\n\n’Bultfabriks AB., Eallstahammar.\n\nBultfabrik med galvaniseringsverk i\nHallstahämmar (Västmanl. l.).\n\nTillverkar bult, mutter, skruv och nit\nav järn i svart eller blankt utförande samt\ni rostfritt och syrafast material, rälsspik\noch rälsskarvbult, smiden för elektr.\nhög-och lågspänningsledningar samt\nbygg-nadssmiden.\n\nHuvudkontor: Hallstahammar.\nTelegr.-adr. o. telefon: Bultfabriken,\nHallstahammar. Postgiro: 10242. Nederlag: i\nStockholm, Kammakarg. 11, telefon:\n118819-20; i Göteborg, Göteborgs Lagerhus,\ntelefon: 133921; i Malmö, Carlsg. 14, telefon:\n10235; i Sundsvall, telefon: 1484.\n\nAkt.-kap.: 8,460,000 kr. Antal\nindustriarb.: 1,400. Tillv.-värde pr år: 22,000,000\nkr.\n\nBolaget grundat 1873, nuv.\nbolagsordning antagen 1923. Bolaget äger AB.\nKanthal, Hallstahammar, och Ramnäs\nBruks AB., Ramnäs.\n\nStyrelse: civiling. Bengt Ingeström\n(ordf.), bergsing. Hans v. Kantzow,\ngeneralkonsul Ragnar Söderberg.\n\nVerkst. dir. o. disp.: Hans v. Kantzow.\n\növering.: John Ingeström.\n\nOmbudsm.: Åke Lindstedt.\n\nFnrsäljn.-rhp.f: E. Malmgren.\n\nEkonomichef: Bo Brundin.\n\nB unge AB., Kolborstfabriken,\n\nStockholm.\n\nSe Kolborstfabriken Bunge AB.,\nStockholm.\n\nAB. Bungenäs Kalkbrott, Malmö.\n\nKalkstensbrott och kalkbruk vid\nBungenäs, Kappelshamn och Smöjen m. fl.\nplatser på Gotland. Bryter och bereder\nkalksten för olika industriella ändamål,\nframställer kalkstensmjöl för\nsulfitspritfabriker och jordbruket, foderkalk för\n\nhusdjuren; tillverkar bränd kalk för\njordbruks- och byggnadsändamål samt\nför kemisk-tekniska behov. Bolaget\ndriver även rederirörelse. Varumärken för\nfoderkalk: »Bungekalk» o. »Gotlandsör».\n\nHuvudkontor: Malmö, Fersensväg 9.\nTelegr.-adr.: Bungekalk, Malmö.\nTelefon: 26588. Postgiro: 38302.\nAvd.-kon-tor: Bungenäs, Fårösund, telegr.-adr.:\nBungenäs, Visby, telefon: Fårösund 7.\n\nAkt.-kap.: 600,000 kr. — Antal\nindustriarb.: 75 i Bungenäs, 75 i Smöjen.\nProd.-värde pr år: 1,220,000 kr.\n\nKalkbruket i Bungenäs anlagt 1906, i\nSmöjen omkr. 1900, nuv. bolag bildat\n1921. Bolaget äges av Svenska\nSockerfabriks AB.\n\nStyrelse: dir. C. F. Tranchell (ordf.),\ndir. N. W. Lundblad, bankdir. Ivar\nÅkerman.\n\nVerkst. dir.: N. W. Lundblad.\n\nDisp. i Malmö: ing. Erik Wollert.\n\nKamrer i Malmö: Elis G. Larson.\n\nFörvalt. i Bungenäs: P. O. P:son\nBerthon.\n\n*Bure AB., Bureå.\n\nSågverk, hyvleri, trämassefabrik ocfe\nkolugn i Bureå (Västerb. l.). Tillverkar\nsågade och hyvlade trävaror, lådbräderr\nsplitved och våt mek. trämassa samt\ngengaskol och trätjära.\n\nTelegr.-adr. o. telefon: Burebolagr\nSkellefteå. Försälj, av trämassa: Ekman*\n&amp; Co., AB., Göteborg.\n\nAkt.-kap.: 1,800,000 kr. Antal\nindustriarb.: 300. Årstillv.: 18,000 stds trävaror,\n55,000 ton våt vit trämassa.\n\nSågverksrörelsen grundad 1796, bolag\n1873, nuv. bolag stiftat 1920,\nträmassefabriken anlagd 1928.\n\nStyrelse: v. konsul F. Sverdrup\n(ordf.), dir. Lars Landmark (v. ordf.),\ndisp. Simon A. Boman, skogsförvalt. E.\nLandmark.\n\nVerkst. dir.: L. Landmark.\n\nDisp.: Martin Söderlind.\ti\n\nDriftsin g.: G. Sverdrup.\n\nBurseryds Parkettfabrik AB.,\n\nSmala/rids Burseryd.\n\nTillverkar ekparkettstav vid fabrik r\nSmålands Burseryd (Jönköp. l.).\n\nTelegr.-adr.: Parkettfabriken, Smål.\nBurseryd. Telefon: 49 o. 112. Postgiro:\n275963.^ — Akt.-kap.: 60,000 kr. Antal:\nindustriarb.: 28. Prod.-värde pr år::\n900,000 kr. — Bolaget grundat 1944.\n\nVerkst. dir.: Ragnar Hultqvist.",
    "structured": {
        "1": {
            "name": "Bröderna—Burseryd",
            "location": "Riddarg. 16, Stockholm",
            "contact": {
                "office": "Riddarg. 16",
                "phone": [
                    "670345"
                ],
                "postgiro": "151788",
                "telegraph": "Byggwiklund, Stockholm"
            },
            "financials": {
                "capital": "100,000 kr",
                "foundation_year": 1937
            },
            "board": [
                {
                    "name": "ing. Bertil Wiklund",
                    "role": "ordf."
                },
                {
                    "name": "byggm. Birger Wiklund",
                    "role": ""
                },
                {
                    "name": "ing. Carl Wiklund",
                    "role": ""
                },
                {
                    "name": "ing. Ragnar Wiklund",
                    "role": ""
                }
            ],
            "director": "Bertil Wiklund",
            "managing_director": "Bertil Wiklund",
            "sales_manager": "N/A",
            "manager": "Carl Wiklund"
        },
        "2": {
            "name": "Bultfabriks AB., Eallstahammar",
            "location": "Hallstahammar",
            "contact": {
                "office": "Hallstahammar",
                "phone": [
                    "N/A"
                ],
                "postgiro": "10242"
            },
            "financials": {
                "capital": "8,460,000 kr",
                "employees": {
                    "industrial_workers": 1400
                },
                "annual_turnover": "22,000,000 kr",
                "annual_production_value": "N/A"
            },
            "foundation_year": 1873,
            "current_name_year": 1923,
            "predecessor": "N/A",
            "corporation_year": "N/A",
            "board": [
                {
                    "name": "civiling. Bengt Ingeström",
                    "role": "ordf."
                },
                {
                    "name": "bergsing. Hans v. Kantzow",
                    "role": ""
                },
                {
                    "name": "generalkonsul Ragnar Söderberg",
                    "role": ""
                }
            ],
            "owners": [
                "AB. Kanthal, Hallstahammar",
                "Ramnäs Bruks AB., Ramnäs"
            ],
            "director": "Hans v. Kantzow",
            "managing_director": "Hans v. Kantzow",
            "sales_manager": "E. Malmgren",
            "manager": "Bo Brundin"
        },
        "3": {
            "name": "AB. Bungenäs Kalkbrott, Malmö",
            "location": "Malmö, Fersensväg 9",
            "contact": {
                "office": "Malmö, Fersensväg 9",
                "phone": [
                    "26588"
                ],
                "postgiro": "38302"
            },
            "financials": {
                "capital": "600,000 kr",
                "employees": {
                    "industrial_workers": 75
                },
                "annual_turnover": "1,220,000 kr",
                "annual_production_value": "N/A"
            },
            "foundation_year": "N/A",
            "current_name_year": "N/A",
            "predecessor": "N/A",
            "corporation_year": "N/A",
            "board": [
                {
                    "name": "dir. C. F. Tranchell",
                    "role": "ordf."
                },
                {
                    "name": "dir. N. W. Lundblad",
                    "role": ""
                },
                {
                    "name": "bankdir. Ivar Åkerman",
                    "role": ""
                }
            ],
            "owners": [
                "Svenska Sockerfabriks AB."
            ],
            "director": "N. W. Lundblad",
            "managing_director": "N. W. Lundblad",
            "sales_manager": "N/A",
            "manager": "N/A"
        },
        "4": {
            "name": "Bure AB., Bureå",
            "location": "Bureå, Västerbotten",
            "contact": {
                "office": "N/A",
                "phone": [
                    "N/A"
                ],
                "postgiro": "N/A",
                "telegraph": "N/A"
            },
            "financials": {
                "capital": "1,800,000 kr",
                "employees": {
                    "industrial_workers": 300
                },
                "annual_turnover": "N/A",
                "annual_production_value": "N/A"
            },
            "foundation_year": "N/A",
            "current_name_year": "N/A",
            "predecessor": "N/A",
            "corporation_year": 1920,
            "board": [
                {
                    "name": "v. konsul F. Sverdrup",
                    "role": "ordf."
                },
                {
                    "name": "dir. Lars Landmark",
                    "role": "v. ordf."
                },
                {
                    "name": "disp. Simon A. Boman",
                    "role": ""
                },
                {
                    "name": "skogsförvalt. E. Landmark",
                    "role": ""
                }
            ],
            "owners": [
                "Ekman* & Co., AB., Göteborg"
            ],
            "director": "L. Landmark",
            "managing_director": "L. Landmark",
            "sales_manager": "N/A",
            "manager": "N/A"
        },
        "5": {
            "name": "Burseryds Parkettfabrik AB., Smala/rids Burseryd",
            "location": "Smålands Burseryd, Jönköping",
            "contact": {
                "office": "Smala/rids Burseryd",
                "phone": [
                    "49",
                    "112"
                ],
                "postgiro": "275963",
                "telegraph": "Parkettfabriken, Smål. Burseryd"
            },
            "financials": {
                "capital": "60,000 kr",
                "employees": {
                    "industrial_workers": 28
                },
                "annual_turnover": "900,000 kr",
                "annual_production_value": "N/A"
            },
            "foundation_year": 1944,
            "current_name_year": "N/A",
            "predecessor": "N/A",
            "corporation_year": "N/A",
            "director": "Ragnar Hultqvist",
            "managing_director": "N/A",
            "sales_manager": "N/A",
            "manager": "N/A"
        }
    }
}