{
    "original": "Isola—J aeger\n\nIsola Gruvindustri, Stockholm.\n\nBryter kvarts och fältspat vid\nfyndig-heter i olika delar av Sverige.\n\nKontor: Stockholm, Kaptensg. 6.\nTelegr.-adr.: Micanite, Stockholm. Telefon:\n679200.\n\nAntal industriarb.: 70. Prod.-värde pr\når: 400,000 kr. — Bolaget grundat 1943.\n\nÄgare o. chef: dir. Bo Andrén.\n\nKamrer: Wolfgang Oettinger.\n\n\"isolerings AB. Cementol,\n\nGöteborg.\n\nTillverkar isoleringsfilt och\nisoleringsmassor samt utför isoleringsarbeten.\n\nKontor: Lindholmsvägen. Telegr.-adr.:\nCementol, Göteborg. Telefon: 221191.\nPostgiro: 12277.\n\nAkt.-kap.: 34,750 kr. Antal\nindustriarb.: 30. Tillv.-värde pr år: 600,000 kr.\n— Firman etabl. 1918.\n\nStyrelse: dir. Anders Sylvan (ordf.),\nclisp. Birger Sylvan, ing. Gunnar Sylvan,\n\nVerkst. dir.: Anders Sylvan.\n\nIsoleringsflaskfabriken, Svenska,\n\nJ önköping.\n\nSe AB. Termoverken, Jönköping.\n\n\"Ivarsson AB., Bröderna, Osby.\n\nSe Bröderna Ivarsson AB., Osby.\n\"Ivarssons Skofabrik AB., Örebro.\n\nTillverkar finare randsydda herr- och\ndamskodon. Varumärken: »Ivarssons»,\n»Everton» o. »Garmisch».\n\nTelefon: 14353. Postgiro: 26309.\n\nAkt.-kap.: 177,000 kr. Antal\nindustriarb.: 70. — Firman etabl. 1924, bolag\n1929.\n\nStyrelse o. verkst. dir.: And. Ivarsson.\n\nKamrer: Edmund Kjellin.\n\nIvar Iverson &amp; C:o, AB., Malmö.\n\nBokbinderi, kontorsboks- och\nkartong-fabrik samt linjeringsanstalt. Tillverkar\naskar och kartonger, kontorsböcker,\nbok-binderiarbeten m. m.\n\nKontor: Gråbrödersg. 8. Telefon: 71835.\nPostgiro: 39605. — Akt.-kap.: 100,000 kr.\nAntal industriarb.: 75. Tillv.-värde pr år:\n335,000 kr. — Firman etabl. 1900, bolag\n1945.\n\nVerkst. dir.: bokbindarmäst. Oscar\nGustafson.\n\n* utmärker till Sveriges Industriförbund anslutna företag.\n\n\"Hjalmar Jackson, Stockholm.\n\nSnickeriverkstad. Tillverkar möbler och\nfinare inredningsarbeten.\n\nKontor: Tuleg. 19. Telefon: 327278.\nPostgiro: 192494. — Arb.-antal: 10.\nTillv.-värde pr år: 150,000 kr. — Firman\netabl. 1916.\n\nÄgare o. chef: snickaremäst. Hjalmar\nJ ackson.\n\nJac. Jacobsen AB., Göteborg.\n\nLampfabrik. Tillverkar arbetslampor\n(»Luxo 1001»), solljuslampor,\nvärmekaminer och skrivmaskinsbord m. m.\n\nKontor: Mölndalsvägen 91; postadr.:\nGöteborg 5. Telegr.-adr.: Jacjac,\nGöteborg. Telefon: 181162 o. 181181.\nPostgiro: 45986.\n\nAkt.-kap.: 5,000 kr. Antal industriarb.:\n20. — Bolaget grundat 1939.\n\nStyrelse: bankkamrer Göran\nGylien-svärd (ordf.), disp. Åke Arvidius.\n\nVerkst. dir.: Göran Gyllensvärd.\n\nDisp.: Åke Fischer.\n\nAB. G. L. Jacoby, Stockholm.\n\nInstrumentfabrik och mek. verkstad.\nTillverkar kirurgi ska instrument,\nartiklar för djurvård och djursjukvård samt\napparater för frökontroll. Specialitet:\nveterinärinstrument.\n\nKontor: Lästmakarg. 27 B. Telefon:\n202702. Postgiro: 942. — Akt.-kap.:\n60,000 kr. Antal industriarb.: 20. —\nFirman grundad 1860.\n\nVerkst. dir.: Gösta Jacobsson.\n\nJacobsson, se Jakobsson.\n\n\"AB. Jaeger Konfektyrindustri,\n\nFalköping.\n\nTillverkar tabletter, dragéer, kola m. m.\n\nTelefon: 824. Postgiro: 37092. —\nAkt.-kap.: 90,000 kr. Antal industriarb.: 30.\n\n256*",
    "structured": {
        "1": {
            "name": "Isola Gruvindustri",
            "location": "Stockholm",
            "business": "Bryter kvarts och fältspat vid fyndigheter i olika delar av Sverige.",
            "contact": {
                "office": "Kaptensg. 6",
                "telegraph": "Micanite, Stockholm",
                "phone": [
                    "679200"
                ]
            },
            "financials": {
                "capital": "Not available",
                "employees": {
                    "industriarb": 70
                },
                "annual_turnover": "400,000 kr",
                "annual_production_value": "Not available"
            },
            "foundation_year": 1943,
            "owners": [
                "dir. Bo Andrén"
            ],
            "board": [
                {
                    "name": "Wolfgang Oettinger",
                    "role": "Kamrer"
                }
            ]
        },
        "2": {
            "name": "Isolerings AB. Cementol",
            "location": "Göteborg",
            "business": "Tillverkar isoleringsfilt och isoleringsmassor samt utför isoleringsarbeten.",
            "contact": {
                "office": "Lindholmsvägen",
                "telegraph": "Cementol, Göteborg",
                "phone": [
                    "221191"
                ],
                "postgiro": "12277"
            },
            "financials": {
                "capital": "34,750 kr",
                "employees": {
                    "industriarb": 30
                },
                "annual_turnover": "600,000 kr",
                "annual_production_value": "Not available"
            },
            "foundation_year": 1918,
            "owners": [
                "Not available"
            ],
            "board": [
                {
                    "name": "Anders Sylvan",
                    "role": "Verkst. dir."
                },
                {
                    "name": "Birger Sylvan",
                    "role": "clisp."
                },
                {
                    "name": "Gunnar Sylvan",
                    "role": "ing."
                }
            ]
        },
        "3": {
            "name": "Ivarsson AB., Bröderna",
            "location": "Osby",
            "business": "Se Bröderna Ivarsson AB., Osby",
            "foundation_year": "Not available",
            "owners": [
                "Not available"
            ]
        },
        "4": {
            "name": "Ivarssons Skofabrik AB.",
            "location": "Örebro",
            "business": "Tillverkar finare randsydda herr- och damskodon. Varumärken: »Ivarssons», »Everton» o. »Garmisch».",
            "contact": {
                "phone": [
                    "14353"
                ],
                "postgiro": "26309"
            },
            "financials": {
                "capital": "177,000 kr",
                "employees": {
                    "industriarb": 70
                },
                "annual_turnover": "Not available",
                "annual_production_value": "Not available"
            },
            "foundation_year": 1924,
            "owners": [
                "Not available"
            ],
            "board": [
                {
                    "name": "And. Ivarsson",
                    "role": "Styrelse o. verkt. dir."
                },
                {
                    "name": "Edmund Kjellin",
                    "role": "Kamrer"
                }
            ]
        },
        "5": {
            "name": "Ivar Iverson & Co, AB.",
            "location": "Malmö",
            "business": "Bokbinderi, kontorsboksoch kartong-fabrik samt linjeringsanstalt. Tillverkar askar och kartonger, kontorsböcker, bok-binderiarbeten m. m.",
            "contact": {
                "office": "Gråbrödersg. 8",
                "phone": [
                    "71835"
                ],
                "postgiro": "39605"
            },
            "financials": {
                "capital": "100,000 kr",
                "employees": {
                    "industriarb": 75
                },
                "annual_turnover": "335,000 kr",
                "annual_production_value": "Not available"
            },
            "foundation_year": 1900,
            "owners": [
                "Not available"
            ],
            "board": [
                {
                    "name": "Oscar Gustafson",
                    "role": "Verkst. dir."
                }
            ],
            "director": "Not available"
        },
        "6": {
            "name": "Hjalmar Jackson",
            "location": "Stockholm",
            "business": "Snickeriverkstad. Tillverkar möbler och finare inredningsarbeten.",
            "contact": {
                "office": "Tuleg. 19",
                "phone": [
                    "327278"
                ],
                "postgiro": "192494"
            },
            "financials": {
                "capital": "Not available",
                "employees": {
                    "antal": 10
                },
                "annual_turnover": "150,000 kr",
                "annual_production_value": "Not available"
            },
            "foundation_year": 1916,
            "owners": [
                "Not available"
            ],
            "board": [
                {
                    "name": "Hjalmar Jackson",
                    "role": "Ägare o. chef"
                }
            ],
            "director": "Not available"
        },
        "7": {
            "name": "Jac. Jacobsen AB.",
            "location": "Göteborg",
            "business": "Tillverkar arbetslampor (»Luxo 1001»), solljuslampor, värmekaminer och skrivmaskinsbord m. m.",
            "contact": {
                "office": "Mölndalsvägen 91",
                "postadr": "Göteborg 5",
                "telegraph": "Jacjac, Göteborg",
                "phone": [
                    "181162",
                    "181181"
                ],
                "postgiro": "45986"
            },
            "financials": {
                "capital": "5,000 kr",
                "employees": {
                    "industriarb": 20
                },
                "annual_turnover": "Not available",
                "annual_production_value": "Not available"
            },
            "foundation_year": 1939,
            "owners": [
                "Not available"
            ],
            "board": [
                {
                    "name": "Göran Gyllensvärd",
                    "role": "Verkst. dir."
                },
                {
                    "name": "Åke Arvidius",
                    "role": "disp."
                },
                {
                    "name": "Åke Fischer",
                    "role": "Disp."
                }
            ]
        },
        "8": {
            "name": "AB. G. L. Jacoby",
            "location": "Stockholm",
            "business": "Tillverkar kirurgi ska instrument, artiklar för djurvård och djursjukvård samt apparater för frökontroll. Specialitet: veterinärinstrument.",
            "contact": {
                "office": "Lästmakarg. 27 B",
                "phone": [
                    "202702"
                ],
                "postgiro": "942"
            },
            "financials": {
                "capital": "60,000 kr",
                "employees": {
                    "industriarb": 20
                },
                "annual_turnover": "Not available",
                "annual_production_value": "Not available"
            },
            "foundation_year": 1860,
            "owners": [
                "Not available"
            ],
            "board": [
                {
                    "name": "Gösta Jacobsson",
                    "role": "Verkst. dir."
                }
            ]
        },
        "9": {
            "name": "AB. Jaeger Konfektyrindustri",
            "location": "Falköping",
            "business": "Tillverkar tabletter, dragéer, kola m. m.",
            "contact": {
                "phone": [
                    "824"
                ],
                "postgiro": "37092"
            },
            "financials": {
                "capital": "90,000 kr",
                "employees": {
                    "antal": 30
                },
                "annual_turnover": "Not available",
                "annual_production_value": "Not available"
            }
        }
    }
}