{
    "original": "Astra—Augustsson\n\n\"Astra, Silkefabriks AB., Smålands\nAnneberg.\n\nSe Silkefabriks AB. Astra, Smålands\nAnneberg.\n\n*Atermo, Elektrofirman, Göteborg.\n\nSe Elektrofirman Atermo, Lindberg &amp;\nCo., Göteborg.\n\nAB. Athena, Ystad,\n\nMetallvarufabrik. Tillverkar\npappers-rullställ, inredningar och specialartiklar\nför butiker samt konstsmide och\nkonstföremål i tenn och brons.\n\nTelegr.-adr.: Athena, Ystad. Telefon:\n1228. Postgiro: 99020.\n\nAkt.-kap.: 20,500 kr. Antal\nindustriarb.: 50. — Bolaget grundat 1936.\n\nVerkst. dir.: fabr. Anton Persson.\n\nKamrer: Nils Söderman.\n\n\"Atlantic, Konserverings AB.,\n\nM örrum.\n\nSe Konserverings AB. Atlantic,\nMör-rum.\n\n\"AB. Atlas Diesel, Stockholm.\n\nMek. verkstad i Sickla (Stockholms l.).\nTillverkar: under märket »Atlas»:\nstationära och transportabla luftkompressorer,\ntryckluftdrivna lastningsmaskiner,\nbergborrmaskiner, tryckluftverktyg, elektriska\nhögfrekvensverktyg och elektriska\nuniversalverktyg; under märket »Ecco»:\nfärg-sprutningsutrustningar; under märket\n»Polar»: stationära och marina\ndieselmotorer; hydrauliska växlar (system\n»Lys-holm-Smith»).\n\nHuvudkontor: Sickla; postadr.:\nStockholm 1. Telegr.-adr.: Atlasdisel,\nStockholm. Telefon: »Atlas Diesel». Postgiro:\n1526.\n\nAkt.-kap.: 10,159,500 kr. Antal\nindustriarb.: 1,300.\n\nBolaget, som bildades 1917, utgör en\nsammanslutning av Nya AB. Atlas,\ngrundat 1873, och AB. Diesels Motorer,\ngrundat 1898.\n\nStyrelse: bankdir. Marcus Wallenberg\n(ordf.), civiling. Frans G. Liljenroth, dir.\nH. Pyk, generaldir. Tarras Sällfors, dir.\nWalter Wehtje.\n\nVerkst. dir.: W. Wehtje.\n\nV. verkst. dir.: H. Pyk.\n\nElconomidir.: P. Prydz.\n\nExportchef: ing. O. Nibell.\n\nVerkstadschef: övering. John Janson.\n\nFörsäljn.-chef er: för tryckluftavd.: ing.\nE. Ryd; för marinmotorer: ing. U.\nGa-well; för stationära motorer: ing. E.\nBäckman; för hydrauliska växlar: ing. P.\nRinman.\n\nInköpschef: E. Bergman.\n\nAB. Atsa, Gävle.\n\nMek. verkstad och stålpresseri.\nTillverkar lantbruksmaskiner såsom\nradsånings-maskiner och hästräfsor samt\nmjölkningsmaskiner och separatorer. Varunamn:\n»Atsa», »Champion», »Gloria», »Labor»\no. »Thule».\n\nTelegr.-adr.: Atsa, Gävle. Telefon: 2195.\nPostgiro: 93217. — Akt.-kap.: 200,000 kr.\nAntal industriarb.: 60. — Firman etabl.\n1897, nuv. namn 1931.\n\nStyrelse o. disp.: Per-Ulf Gustafsson.\n\n\"Atög Chokladfabrik AB., Göteborg.\n\nTillverkar choklad, karameller, kola,\nkonfekt och pastiller. Varumärke:\n»Atög».\n\nKontor: Krokslätt; postadr.:\nGöteborg-14. Telefon: 272140. Postgiro: 12188.\n\nAkt.-kap.: 300,000 kr. Antal\nindustriarb.: 85. Tillv.-värde pr år: 1,500,000 kr.\n— Firman etabl. 1910, bolag 1924,\nnamnförändringen 1932.\n\nStyrelse o. verkst. dir.: Verner Nordin.\n\nAB. Augustendals Industrier,\n\nStockholm.\n\nSe AB. Svenska Bilfabriken,\nStockholm.\n\n*L. Augustsons Bleckvarufabrik,\n\nGöteborg.\n\nTillverkar bleckemballage.\n\nKontor: Gamla Tuvevägen. Postadr.:\nGöteborg 8. Telefon: 220023. Postgiro:\n12393. — Antal industriarb.: 41.\nTillv.-värde pr år: 1,000,000 kr. — Firman\netabl. 1909.\n\nÄgare: fru Ellen Augustson.\n\nChef: fröken Elin Augustson.\n\n\"AB. P. A. Augustsson &amp; Son\nGranit-Industri, Immeln.\n\nGranitbrott i Immeln (Kristianst. l.)\noch i Virbo (Kalmar l.). Tillverkar\nrå-block.\n\nKontor: Immeln. Telefon: 48.\nPostgiro: 93910. — Akt.-kap.: 56,750 kr. A nr\ntal industriarb.: 15. Prod.-värde pr år:\n150,000 kr. — Firman grundades 1929,\nnuv. bolag 1935.",
    "structured": {
        "0": {
            "name": "AB. Athena",
            "location": "Ystad",
            "business": "Metallvarufabrik",
            "products": "Pappers-rullställ, inredningar, specialartiklar för butiker, konstsmide, konstföremål i tenn och brons",
            "contact": {
                "office": "Athena, Ystad",
                "phone": [
                    "1228"
                ],
                "postgiro": "99020"
            },
            "financials": {
                "capital": "20,500 kr",
                "employees": {
                    "industrial": 50
                },
                "annual_turnover": "Not available"
            },
            "foundation_year": 1936,
            "board": [
                {
                    "name": "fabr. Anton Persson",
                    "role": "Verkstdirigent"
                },
                {
                    "name": "Nils Söderman",
                    "role": "Kamrer"
                }
            ]
        },
        "1": {
            "name": "AB. Atlas Diesel",
            "location": "Stockholm",
            "business": "Mek. verkstad",
            "products": "Luftkompressorer, lastningsmaskiner, bergborrmaskiner, tryckluftverktyg, elektriska verktyg, dieselmotorer, hydrauliska växlar",
            "contact": {
                "office": "Sickla",
                "phone": [
                    "Not available"
                ],
                "postgiro": "1526",
                "head_office": "Stockholm 1"
            },
            "financials": {
                "capital": "10,159,500 kr",
                "employees": {
                    "industrial": 1300
                },
                "annual_turnover": "Not available"
            },
            "foundation_year": 1917,
            "corporation_year": 1917,
            "board": [
                {
                    "name": "Marcus Wallenberg",
                    "role": "bankdir."
                },
                {
                    "name": "Frans G. Liljenroth",
                    "role": "civiling."
                },
                {
                    "name": "H. Pyk",
                    "role": "dir."
                },
                {
                    "name": "Tarras Sällfors",
                    "role": "generaldir."
                },
                {
                    "name": "Walter Wehtje",
                    "role": "dir."
                }
            ],
            "director": "W. Wehtje",
            "managing_director": "Not available",
            "sales_manager": "Not available",
            "manager": "Not available"
        },
        "2": {
            "name": "AB. Atsa",
            "location": "Gävle",
            "business": "Mek. verkstad och stålpresseri",
            "products": "Lantbruksmaskiner, mjölkningsmaskiner, separatorer",
            "contact": {
                "office": "Atsa, Gävle",
                "phone": [
                    "2195"
                ],
                "postgiro": "93217"
            },
            "financials": {
                "capital": "200,000 kr",
                "employees": {
                    "industrial": 60
                },
                "annual_turnover": "Not available"
            },
            "foundation_year": 1897,
            "board": [
                {
                    "name": "Per-Ulf Gustafsson",
                    "role": "Styrelse o. disp."
                }
            ]
        },
        "3": {
            "name": "Atög Chokladfabrik AB.",
            "location": "Göteborg",
            "business": "Chokladtillverkning",
            "products": "Choklad, karameller, kola, konfekt, pastiller",
            "contact": {
                "office": "Krokslätt",
                "phone": [
                    "272140"
                ],
                "postgiro": "12188"
            },
            "financials": {
                "capital": "300,000 kr",
                "employees": {
                    "industrial": 85
                },
                "annual_turnover": "1,500,000 kr"
            },
            "foundation_year": 1910,
            "board": [
                {
                    "name": "Verner Nordin",
                    "role": "Styrelse o. verkst. dir."
                }
            ]
        },
        "4": {
            "name": "AB. P. A. Augustsson & Son Granit-Industri",
            "location": "Immeln",
            "business": "Granitbrott och tillverkning av råblock",
            "contact": {
                "office": "Immeln",
                "phone": [
                    "48"
                ],
                "postgiro": "93910"
            },
            "financials": {
                "capital": "56,750 kr",
                "employees": {
                    "industrial": 15
                },
                "annual_turnover": "150,000 kr"
            },
            "foundation_year": 1929
        },
        "5": {
            "name": "L. Augustsons Bleckvarufabrik",
            "location": "Göteborg",
            "business": "Tillverkning av bleckemballage",
            "contact": {
                "office": "Gamla Tuvevägen",
                "phone": [
                    "220023"
                ],
                "postgiro": "12393"
            },
            "financials": {
                "capital": "Not available",
                "employees": {
                    "industrial": 41
                },
                "annual_turnover": "1,000,000 kr"
            },
            "foundation_year": 1909,
            "owners": [
                "fru Ellen Augustson"
            ],
            "manager": "fröken Elin Augustson"
        }
    }
}