{
    "original": "Grammofonindustri—Granit\n\nStyrelse: dir. I. L. la Cour (ordf.),\ndir. Hjalmar Olsson, civiling. Herman\nWernekinck.\n\nVerkst. dir.: Herman Wernekinck.\n\nKontorschef: E. G. Larsson.\n\nVerkstadschef: Olof Lodén.\n\nGrammofonindustri, AB. Svensk,\n\nStockholm.\n\nSe AB. Svensk Grammofonindustri,\nStockholm.\n\n*Granefors Bruk, Asarum.\n\nSe AB. Svenska Metallverken, Västerås.\n\nAB. Grangärde Ångsåg, Grangärde.\n\nTillverkar sågade och hyvlade trävaror\nvid sågverk och hyvleri i Grangärde\n(Kopparb. l.).\n\nTelefon: 7. Postgiro: 139221. —\nAkt.-kap.: 80.200 kr. Antal industriarb.: 40.\nTillv.-värde pr år: 650,000 kr. — Bolaget\ngrundat 1935.\n\nVerkst. dir.: disp. Karl Hedin.\n\nDisponenter: Anders Pettersson o.\nAlfred Pettersson.\n\nGraningeverkens AB.,\n\nBollstabruk.\n\nSågverk och hyvleri vid Bollsta,\nBollstabruk, träsliperi vid Forsse, österforsa,\nsamt tråddrageri vid Graninge Bruk,\nGraninge (samtl. i Västernorrl. l.).\nTillverkar sågade och hyvlade trävaror, torr\nmek. trämassa samt dragen tråd;\nlevererar elektr. energi från Forsse\nvattenkraftstation.\n\nHuvudkontor: Bollstabruk.\nTelegr.-adr.: Graningeverken, Nyland. Telefon:\nNyland 4. Försäljn.-kontor:\nGraningeverkens Försäljningskontor, Stockholm,\nStureplan 6-, Telegr.-adr.: Gevabus,\nStockholm. Telefon: 600312, 600344 o.\n620634.\n\nAkt.-kap.: 10,530,000 kr. Antal\nindustriarb.: 400. Årstillv.: 20,000 stds\nträvaror, varav 5,000 stds hyvlade, 18,000\nton torr mek. trämassa. — Bolaget\ngrundat 1873.\n\nStyrelse: adv. Tom Forssner (ordf.),\nfrih. C. v. Essen, dir. Nils H. Qvist, dir.\nG. J. Versteegh.\n\nVerkst dir.: G. J. Versteegh\n(Stockholm).\n\nPlatschefer: för Bollsta Bruk: disp. J.\nGotthard Janson; för Forsse Bruk: disp.\nO. Wasend.\n\nFörsäljn.-chef er i Stockholm: för\nträvaror: Folke Peters; för trämassa: Karl\nWingstedt.\n\nGranit AB. C. A. Kuilgrens Enka,\n\nUddevalla.\n\nGranitbrott och stenhuggerier vid\nflera platser inom Bohuslän, Halland,\nSmåland och Skåne. Tillverkar gatsten,\nkantsten, byggnadssten, gravvårdar,\nrå-block m. m. samt polerade och slipade\ngranit arbeten.\n\nTelegr.-adr.: Kullgrens, Uddevalla.\nTelefon: 10058 o. 11782. Postgiro: 77042,\n\nAkt.-kap.: 1,050,000 kr. Antal\nindustriarb.: 350. Prod.-värde pr år: 3,000,000 kr.\n— Firman grundad 1842.\n\nStyrelse: f. borgm. Karl S. Rasmussen\n(ordf.), dir. Victor Kullgren, dir. William\nG. Thorburn.\n\nVerkst. dir.: Victor Kullgren.\n\nKontorschef: A. Rönnau.\n\nDriftsing.: Kurt Berghman.\n\n*Granit AB. Georg Liittensee,\n\nStrömstad.\n\nSe AB. Förenade Granitindustrier,\n\nKarlshamn.\n\n*Granit AB., Skandinaviska,\n\nGöteborg.\n\nSe Skandinaviska Granit AB.,\nGöteborg.\n\nGranitindustri AB., Svenska,\n\nKarlshamn.\n\nSe Svenska Granitindustri AB.,\nKarlshamn.\n\n*Granitindustrier, AB. Förenade,\n\nStrömstad.\n\nSe AB. Förenade Granitindustrier,\nKarlshamn.\n\n*Granit och Beton AB., Stochholm.\n\nUtför väg- och vattenbyggnader,\nhus-och fabriksbyggnader, armerade och\noarmerade betongarbeten, schaktnings- och\nsprängningsarbeten, terrasseringar,\npål-ningar, grundläggningar m. m.\n\nKontor: Linnég. 3. Telegr.-adr.:\nGranit, Stockholm. Telefon: 67-0120.\nPostgiro: 1641.\n\nAkt.-kap.: 400,000 kr. Prod.-värde pr\når: 10,000,000 kr. — Bolaget grundat\n1910.\n\nStyrelse: ing. And. Olby (ordf.), ing.\nKarl Bergquist, jur. kand. Sven\nBjörkenstam, dir. Erik Brändström.\n\nVerkst. dir.: And. Olby.\n\nArbetschefer: för väg- o.\nvattenbyggn.-avd.: ing. E. Rosén, för husbyggnadsavd.:\ning. E. H. Ehrlin.",
    "structured": {
        "1": {
            "name": "Grammofonindustri AB Svenska",
            "location": "Stockholm",
            "business": "Grammofonindustri",
            "contact": {
                "telegraph": "Grammofonindustri, AB.",
                "office": "Stockholm",
                "postgiro": "139221"
            },
            "financials": {
                "capital": "80,200 kr",
                "employees": {
                    "industriarb.": 40
                },
                "annual_production_value": "650,000 kr"
            },
            "foundation_year": 1935,
            "board": [
                {
                    "name": "I. L. la Cour",
                    "role": "ordf."
                },
                {
                    "name": "Hjalmar Olsson",
                    "role": "dir."
                },
                {
                    "name": "Herman Wernekinck",
                    "role": "civiling."
                }
            ],
            "director": "Herman Wernekinck",
            "sales_manager": "E. G. Larsson"
        },
        "2": {
            "name": "AB Grangärde Ångsåg",
            "location": "Grangärde",
            "business": "Tillverkar sågade och hyvlade trävaror",
            "contact": {
                "phone": "7",
                "postgiro": "139221"
            },
            "financials": {
                "capital": "80,200 kr",
                "employees": {
                    "industriarb.": 40
                },
                "annual_production_value": "650,000 kr"
            },
            "foundation_year": 1935,
            "director": "disp. Karl Hedin",
            "managing_director": "disp. Karl Hedin",
            "owners": [
                "Anders Pettersson",
                "Alfred Pettersson"
            ]
        },
        "3": {
            "name": "Graningeverkens AB",
            "location": "Bollstabruk",
            "business": "Tillverkar sågade och hyvlade trävaror, torr mek. trämassa samt dragen tråd; levererar elektr. energi",
            "contact": {
                "head_office": "Bollstabruk",
                "telegraph": "Graningeverken, Nyland",
                "phone": "Nyland 4",
                "sales_offices": [
                    {
                        "location": "Stockholm",
                        "phone": "600312, 600344, 620634"
                    }
                ]
            },
            "financials": {
                "capital": "10,530,000 kr",
                "employees": {
                    "industriarb.": 400
                },
                "annual_turnover": "20,000 stds trävaror, varav 5,000 stds hyvlade, 18,000 ton torr mek. trämassa"
            },
            "foundation_year": 1873,
            "board": [
                {
                    "name": "Tom Forssner",
                    "role": "adv."
                },
                {
                    "name": "C. v. Essen",
                    "role": "frih."
                },
                {
                    "name": "Nils H. Qvist",
                    "role": "dir."
                },
                {
                    "name": "G. J. Versteegh",
                    "role": "dir."
                }
            ],
            "director": "G. J. Versteegh",
            "sales_manager": "Karl Wingstedt"
        },
        "4": {
            "name": "Granit AB C. A. Kuilgrens Enka",
            "location": "Uddevalla",
            "business": "Tillverkar gatsten, kantsten, byggnadssten, gravvårdar, rå-block m. m. samt polerade och slipade granit arbeten",
            "contact": {
                "telegraph": "Kullgrens, Uddevalla",
                "phone": "10058, 11782",
                "postgiro": "77042"
            },
            "financials": {
                "capital": "1,050,000 kr",
                "employees": {
                    "industriarb.": 350
                },
                "annual_production_value": "3,000,000 kr"
            },
            "foundation_year": 1842,
            "board": [
                {
                    "name": "Karl S. Rasmussen",
                    "role": "f. borgm."
                },
                {
                    "name": "Victor Kullgren",
                    "role": "dir."
                },
                {
                    "name": "William G. Thorburn",
                    "role": "dir."
                }
            ],
            "director": "Victor Kullgren",
            "contact_officer": "A. Rönnau",
            "managing_director": "Victor Kullgren",
            "sales_manager": "Not Available"
        },
        "5": {
            "name": "Granit och Beton AB.",
            "location": "Stochholm",
            "business": "Utför väg- och vattenbyggnader, hus-och fabriksbyggnader, armerade och oarmerade betongarbeten, schaktnings- och sprängningsarbeten, terrasseringar, pål-ningar, grundläggningar m. m.",
            "contact": {
                "office": "Linnég. 3",
                "telegraph": "Granit, Stockholm",
                "phone": "67-0120",
                "postgiro": "1641"
            },
            "financials": {
                "capital": "400,000 kr",
                "annual_production_value": "10,000,000 kr"
            },
            "foundation_year": 1910,
            "board": [
                {
                    "name": "And. Olby",
                    "role": "ing."
                },
                {
                    "name": "Karl Bergquist",
                    "role": "ing."
                },
                {
                    "name": "Sven Björkenstam",
                    "role": "jur. kand."
                },
                {
                    "name": "Erik Brändström",
                    "role": "dir."
                }
            ],
            "director": "And. Olby",
            "managing_director": "Not Available"
        }
    }
}