{
    "original": "Hallberg—Hallstahammar\n\nindustriarb.: 37. Årstillv.: 1,7 milj. st.\ntegelvaror. — Tegelbruket anlagt 1902.\n\nÄgare: fabr. Eric Mattelin o. fröken\nElin Mattelin.\n\nChef: Eric Mattelin.\n\nHallbergs Industri AB.,\n\nMölndal.\n\nTillverkar spiralfjädrar för\nindustriella ändamål, möbelresårer,\nspiralstommar och spiralmadrasser. Varumärke:\n»Peerless».\n\nKontor: Göteborgsvägen. Telefon:\n272220. Postgiro: 40927. — Akt.-kap.:\n150,000 kr. Antal industriarb.: 50.\nTillv.-värde pr år: 900,000 kr.\n\nFirman etabl. 1922 under namn\nGöteborgs Resårindustri, Hjalmar A.\nHallberg, bolag under nuv. namn 1943.\n\nVerkst. dir.: fabr. Hjalmar A.\nHallberg.\n\nDisp.: Rolf Hallberg.\n\nFabrihschef: Per Hallberg.\n\nKamrer.- Göran Bångstad.\n\n*C. C. Hallbergs Guldsmeds AB.,\n\nStockholm.\n\nTillverkar juvel-, guld-, silver- och\nemalj arbeten, kuvert-, bosättnings-,\nprydnads- och nyttoföremål i silver och\nnysilver, prydnads- och nyttoföremål i tenn.\n\nKontor: S:t Eriksg. 48; postadr.:\nStockholm 1. Telegr.-adr.: Hallbergs,\nStockholm. Telefon: »Hof juvelerare\nHallberg». Postgiro: 2442. Bolaget idkar\njämväl detaljhandel genom egna\nminut-affärer.\n\nAkt.-kap.: 5,000,000 kr. Antal\nindustriarb.: 400. Tillv.-värde pr år: 8,000,000 kr.\n— Firman etabl. 1860, bolag 1896.\n\nStyrelse: disp. N. Adlerstam, dir. Otto\nDecker, disp. E. Wedelin.\n\nVerkst. dir.: Otto Decker.\n\nAB. Halidéns Bleckvarufabrik,\n\nJönköping.\n\nTillverkar hylsor och beslag för\ntermosflaskor samt stankproppar och\nstänkflaskor.\n\nTelefon: 1781. Postgiro: 277988. —\nAkt.-kap.: 25,000 kr. Antal industriarb.:\n15. Tillv.-värde pr år: 140,000 kr. —\nFirman etabl. 1909, bolag 1945.\n\nVerkst. dir.: Stig Thorén.\n\n*Otto Halidéns Fabriks o. Handels\n\nA B., Stockholm.\n\nAteljéer för tillverkning av klänningar,\nkjolar och blusar m. m.\n\nKontor: Hornsg. 36. Telegr.-adr.:\nHalldénsbolag, Stockholm. Telefon:\n440030. Postgiro: 652.\n\nAkt.-kap.: 450,000 kr. Antal\nindustriarb.: 105. Tillv.-värde pr år: 1,795,000 kr.\n— Bolaget grundat 1898.\n\nStyrelse: disp. Georg Engel (ordf.),\nadv. Gösta Grönberg, dir. Ivar Valldor.\n\nVerkst. dir.; Ivar Valldor.\n\nDisp.: Hans Ohlsson.\n\nKamrer: Ture Jarlsrud.\n\nAB. Hugo Hallgrens\nKonservfabriker, Stockholm.\n\nSe Skandiakonserv, Hugo Hallgrens\nKonservfabriker AB., Stockholm.\n\n\"Hallsbergs Läderindustri AB.,\n\nHallsberg.\n\nGarveri i Hallsberg (Örebro l.).\nTillverkar bottenläder. Varumärken: »Behrns\nEkläder» o. »Gröna oxen».\n\nTelefon: Hallsberg 5. — Akt.-kap.:\n100,000 kr. Antal industriarb.: 25.\nTillv.-värde pr år: 2,000,000 kr. — Fabriken\ngrundad 1898.\n\nStyrelse: dir. Johan Behrn, fröken Olga\nOlsson.\n\nVerkst. dir.; Johan Behrn.\n\n*AB. Hallsbergs Tegelbruk,\n\nHallsberg.\n\nTillverkar mur- och taktegel,\ndräneringsrör m. m. vid tegelbruk i Hallsberg\n(Örebro l.).\n\nTelefon: 113. Postgiro: 135587. —\nAkt.-kap.: 60,000 kr. Antal industriarb.:\n30. Årsprod.: 3 milj. st. tegelvaror. —\nBolaget grundat 1899.\n\nStyrelse: disp. Alfred Thermaenius\n(ordf.), dir. Gottfrid Thermaenius.\n\nVerkst. dir.: Alfred Thermaenius\n(Örebro).\n\nKontors- o. driftschef; Eric Sunne.\n\n*Hallsta Pappersbruk, Hallstavik.\n\nSe Holmens Bruks &amp; Fabriks AB.,\nNorrköping.\n\n*Hallstahammars AB.,\n\nHallstahammar.\n\nJärnverk med martin- och valsverk,\ntråddrageri, axelfabrik och elektrisk\nvattenkraftstation i Hallstahammar\n(Västmanl. l.).\n\nTillverkar martingöt, valsat järn och\nstål, maskinriktade axelämnen,\nblank-rullat stål, svarvade, slipade och kompri-",
    "structured": {
        "firms": [
            {
                "name": "Hallbergs Industri AB.",
                "location": "Mölndal",
                "business": "Tillverkar spiralfjädrar för industriella ändamål, möbelresårer, spiralstommar och spiralmadrasser",
                "products": "Varumärke: »Peerless»",
                "contact": {
                    "office": "Göteborgsvägen",
                    "phone": [
                        "272220"
                    ],
                    "postgiro": "40927",
                    "sales_offices": [],
                    "telegraph": null,
                    "factory_office": null,
                    "factory_phone": null
                },
                "financials": {
                    "capital": "150,000 kr",
                    "employees": {
                        "industriarb": 50
                    },
                    "annual_turnover": "900,000 kr",
                    "annual_production_value": "900,000 kr"
                },
                "foundation_year": 1922,
                "current_name_year": 1943,
                "director": "Eric Mattelin",
                "board": [
                    {
                        "name": "Hjalmar A. Hallberg",
                        "role": "Verkst. dir."
                    },
                    {
                        "name": "Rolf Hallberg",
                        "role": "Disp."
                    },
                    {
                        "name": "Per Hallberg",
                        "role": "Fabrihschef"
                    },
                    {
                        "name": "Göran Bångstad",
                        "role": "Kamrer"
                    }
                ],
                "owners": [
                    "fabr. Eric Mattelin",
                    "fröken Elin Mattelin"
                ]
            },
            {
                "name": "C. C. Hallbergs Guldsmeds AB.",
                "location": "Stockholm",
                "business": "Tillverkar juvel-, guld-, silver- och emalj arbeten, kuvert-, bosättnings-, prydnads- och nyttoföremål i silver och nysilver, prydnads- och nyttoföremål i tenn",
                "products": null,
                "contact": {
                    "office": "S:t Eriksg. 48",
                    "phone": [
                        "Hof juvelerare Hallberg"
                    ],
                    "postgiro": "2442",
                    "sales_offices": [],
                    "telegraph": "Hallbergs, Stockholm"
                },
                "financials": {
                    "capital": "5,000,000 kr",
                    "employees": {
                        "industriarb": 400
                    },
                    "annual_turnover": "8,000,000 kr",
                    "annual_production_value": "8,000,000 kr"
                },
                "foundation_year": 1860,
                "corporation_year": 1896,
                "board": [
                    {
                        "name": "N. Adlerstam",
                        "role": "disp."
                    },
                    {
                        "name": "Otto Decker",
                        "role": "dir."
                    },
                    {
                        "name": "E. Wedelin",
                        "role": "disp."
                    }
                ],
                "owners": []
            },
            {
                "name": "AB. Halidéns Bleckvarufabrik",
                "location": "Jönköping",
                "business": "Tillverkar hylsor och beslag för termosflaskor samt stankproppar och stänkflaskor",
                "products": null,
                "contact": {
                    "phone": [
                        "1781"
                    ],
                    "postgiro": "277988",
                    "sales_offices": []
                },
                "financials": {
                    "capital": "25,000 kr",
                    "employees": {
                        "industriarb": 15
                    },
                    "annual_turnover": "140,000 kr",
                    "annual_production_value": "140,000 kr"
                },
                "foundation_year": 1909,
                "corporation_year": 1945,
                "board": [],
                "owners": [],
                "director": "Stig Thorén"
            },
            {
                "name": "Otto Halidéns Fabriks o. Handels A B.",
                "location": "Stockholm",
                "business": "Ateljéer för tillverkning av klänningar, kjolar och blusar m. m.",
                "products": null,
                "contact": {
                    "office": "Hornsg. 36",
                    "phone": [
                        "440030"
                    ],
                    "postgiro": "652",
                    "sales_offices": []
                },
                "financials": {
                    "capital": "450,000 kr",
                    "employees": {
                        "industriarb": 105
                    },
                    "annual_turnover": "1,795,000 kr",
                    "annual_production_value": "1,795,000 kr"
                },
                "foundation_year": 1898,
                "board": [],
                "owners": [],
                "director": "Ivar Valldor",
                "manager": "Hans Ohlsson",
                "managing_director": "Ivar Valldor",
                "sales_manager": "Hans Ohlsson"
            },
            {
                "name": "Hallsbergs Läderindustri AB.",
                "location": "Hallsberg",
                "business": "Garveri i Hallsberg (Örebro l.). Tillverkar bottenläder",
                "products": "Varumärken: »Behrns Ekläder» o. »Gröna oxen»",
                "contact": {
                    "phone": [
                        "Hallsberg 5"
                    ],
                    "sales_offices": []
                },
                "financials": {
                    "capital": "100,000 kr",
                    "employees": {
                        "industriarb": 25
                    },
                    "annual_turnover": "2,000,000 kr",
                    "annual_production_value": "2,000,000 kr"
                },
                "foundation_year": 1898,
                "director": "Johan Behrn",
                "board": [
                    {
                        "name": "Johan Behrn",
                        "role": "dir."
                    },
                    {
                        "name": "Olga Olsson",
                        "role": "fröken"
                    }
                ]
            },
            {
                "name": "AB. Hallsbergs Tegelbruk",
                "location": "Hallsberg",
                "business": "Tillverkar mur- och taktegel, dräneringsrör m. m. vid tegelbruk i Hallsberg (Örebro l.)",
                "products": null,
                "contact": {
                    "phone": [
                        "113"
                    ],
                    "postgiro": "135587",
                    "sales_offices": []
                },
                "financials": {
                    "capital": "60,000 kr",
                    "employees": {
                        "industriarb": 30
                    },
                    "annual_turnover": null,
                    "annual_production_value": "3 milj. st. tegelvaror"
                },
                "foundation_year": 1899,
                "board": [
                    {
                        "name": "Alfred Thermaenius",
                        "role": "disp. (ordf.)"
                    },
                    {
                        "name": "Gottfrid Thermaenius",
                        "role": "dir."
                    }
                ],
                "owners": [
                    "Eric Sunne"
                ]
            },
            {
                "name": "Hallsta Pappersbruk",
                "location": "Hallstavik",
                "business": "Se Holmens Bruks & Fabriks AB., Norrköping"
            },
            {
                "name": "Hallstahammars AB.",
                "location": "Hallstahammar",
                "business": "Järnverk med martin- och valsverk, tråddrageri, axelfabrik och elektrisk vattenkraftstation i Hallstahammar (Västmanl. l.). Tillverkar martingöt, valsat järn och stål, maskinriktade axelämnen, blank-rullat stål, svarvade, slipade och komprim"
            }
        ]
    }
}