{
    "original": "Hårenfors—Hässleholm\n\ngrimmor och grimskaft, klädlinor,\nflagglinor m. m.\n\nTelefon: 32. Postgiro: 133952.\nTillv.-värde pr år: 120.000 kr. — Firman etabl.\n1936.\n\nÄgare o. chef: fabr. Verner Lindwall.\n\nAB. Härenfars Metallverk, Karda.\n\nMetallvarufabrik i Karda (Jönköp. l.).\nTillverkar biltillbehör, spegelbeslag,\nleksaker m. m.\n\nTelefon: Värnamo 28035 o. 28031.\nPostgiro: 94295. — Akt.-kap.: 30,000 kr.\nAntal industriarb.: 40. Tillv.-värde pr år:\n300,000 kr. — Firman etabl. 1932, bolag\n1946.\n\nVerkst. dir.: fabr. Gunnar Ilärenfors.\n\n*Härnö Bryggeri AB., Härnösand.\n\nSe Hernö Bryggeri AB., Härnösand.\n\n\"Härnösands Fanérfabrik, Härnösand.\n\nSe Torsviks Sågverks AB., Härnösand.\n\n\"Härnösands Svagdricksbryggeri,\nAB., Härnösand.\n\nTillverkar svagdricka.\n\nTelefon: 2951. Postgiro: 263097. —\nAkt.-kap.:o 15,000 kr. Arb.-antal: 4. Tillv.-\n\nvärde pr år: 70,000 kr. — Bolaget\ngrundat 1932.\n\nStyrelse: disp. L. Valentin (ordf.),\nkamrer A. Häggquist, konsul Herman\nRamström,\n\nVerkst. dir.: A. Häggquist.\n\n\"Härnösands Verkstads AB.,\n\nHärnösand.\n\nSe AB. Härnöverken, Härnösand.\n\"AB. Härnöverken, Härnösand.\n\nMek. verkstad, gjuteri och plåtslageri.\nTillverkar trefasmotorer, kuggväxlar och\nkuggväxelmotorer, snäckväxlar och\nsnäck-växelmotorer, specialväxlar,\nmagnetkopp-1 ingår, hissar, spelmaskiner,\ntransportanordningar, maskiner för\ncellulosaindustrin samt allmänna maskinarbeten och\njärnkonstruktioner.\n\nTelegr.-adr. o. telefon: Härnöverken,\nHärnösand. Postgiro: 28848.\n\nRepresentanter: i Stockholm: H.\nEr-bings Maskinaffär, Klarabergsg. 60; i\nGöteborg: ing. Robert Hellström,\nSkeppsbro-platsen 1; i Malmö: »Elektromekano»; i\nHälsingborg: Svenska Elektromekaniska\nIndustri AB., telefon: »Elektromekano».\n\nAkt.-kap.: 600,000 kr. Antal\nindustriarb.: 225. Tillv.-värde pr år: 2,750,000 kr.\n\nVerkstaden anlagd 1872, bolag 1890\nunder namn Härnösands Verkstads AB.,\nnuv. namn 1944.\n\nStyrelse: bankdir. Hugo Huldt (ordf.),\nkonsul Herman Ramström (v. ordf.), dir.\nNils Ramqvist.\n\nVerkst. dir.: Nils Ramqvist.\n\nKamrer: Birger Larsson.\n\nIngenjörer: avd. för trefas- o.\nkuggväxelmotorer: H. Trangius; avd. för\nhissar o. snäckväxlar, allm. maskinarbeten\no. järnkonstr.: Oscar Johansson;\nverkstaden: A. Olof Olsson; ritkontoret:\nMartin Blomquist.\n\n(Jfr annons nr 51.)\n\nHärryda Fabriks AB., Härryda.\n\nMek. verkstad i Härryda (Göteb. o.\nBohus l.). Tillverkar klädskåp och\nverktygsskåp av stål samt cykelgarage m. m.\n\nTelefon: 11 o. 18. Postgiro: 81275. —\nAkt.-kap.: 45,000 kr. Antal industriarb.:\n40. Tillv.-värde pr år: 350,000 kr. —\nBolaget grundat 1925.\n\nStyrelse o. verkst. dir.: ing. Martin\nHallin.\n\n\"AB. Hässle, Apotekare Paul\nNordströms Fabriker, Hässleholm.\n\nKemisk-teknisk fabrik. Tillverkar\nfar-maceutiska preparat och\nkonserveringsmedel.\n\nTelegr.-adr.: Pano, Hässleholm.\nTelefon: »AB. Hässle». Postgiro: 13663.\n\nAkt.-kap.: 450,000 kr. Antal\nindustriarb.: 58. — Bolaget grundat 1942.\n\nStyrelse: apot. Paul Nordström (ordf.),,\ndir. Börje Gabrielsson, dir. Gösta\nLagergren, dir. Tore Norlander.\n\nVerkst. dir.: Tore Norlander.\n\n\"AB. Hässleholms Bryggeri &amp; Malt-\n\nfabrik, Hässleholm.\n\nTillverkar malt, karamellmalt samt\nmalt- och läskedrycker.\n\nTelefon: 73 o. 310. Postgiro: 88850. —\nAkt.-kap.: 450,000 kr. Antal industriarb.:\n30. Tillv.-värde pr år: 1,230,000 kr. —\nBolaget grundat 1928.\n\nStyrelse: riksdagsm. Anton Björklund!\n(ordf.), disp. Hugo Aspegrén, disp. Erik\nEkström, dir. Karl-Erik Löfwall, v.\nkonsul O. Löfwall.\n\nVerkst. dir.: Erik Ekström.\n\nAB. Hässleholms Kapsylfabrik,\n\nHässleholm.\n\nTillverkar kapsyler av bly och tenn\nsamt vattenflaskkapsyler av aluminium.",
    "structured": {
        "1": {
            "name": "Hårenfors—Hässleholm",
            "location": "Karda",
            "business": "Metallvarufabrik",
            "products": "Tillverkar biltillbehör, spegelbeslag, leksaker m. m.",
            "contact": {
                "office": "Telefon: Värnamo 28035 o. 28031",
                "phone": [
                    "Värnamo 28035",
                    "Värnamo 28031"
                ],
                "postgiro": "Postgiro: 94295"
            },
            "financials": {
                "capital": "Akt.-kap.: 30,000 kr",
                "employees": {
                    "industriarb": 40
                },
                "annual_turnover": "Tillv.-värde pr år: 300,000 kr"
            },
            "foundation_year": 1932,
            "corporation_year": 1946,
            "director": "Verkst. dir.: fabr. Gunnar Ilärenfors"
        },
        "2": {
            "name": "AB. Härenfars Metallverk",
            "location": "Karda",
            "business": "Metallvarufabrik",
            "products": "Tillverkar biltillbehör, spegelbeslag, leksaker m. m.",
            "contact": {
                "phone": "Telefon: 32",
                "postgiro": "Postgiro: 133952"
            },
            "financials": {
                "annual_production_value": "Tillv.-värde pr år: 120.000 kr"
            },
            "foundation_year": 1936,
            "owner": "Ägare o. chef: fabr. Verner Lindwall"
        },
        "3": {
            "name": "Härnö Bryggeri AB.",
            "location": "Härnösand",
            "business": "Bryggeri",
            "contact": {
                "phone": "Telefon: Härnöverken, Härnösand",
                "postgiro": "Postgiro: 28848"
            },
            "financials": {
                "capital": "Akt.-kap.: 600,000 kr",
                "employees": {
                    "industriarb": 225
                },
                "annual_turnover": "Tillv.-värde pr år: 2,750,000 kr"
            },
            "corporation_year": 1890,
            "board": [
                {
                    "name": "bankdir. Hugo Huldt",
                    "role": "ordf."
                },
                {
                    "name": "konsul Herman Ramström",
                    "role": "v. ordf."
                },
                {
                    "name": "dir. Nils Ramqvist"
                }
            ],
            "manager": "Kamrer: Birger Larsson"
        },
        "4": {
            "name": "Härryda Fabriks AB.",
            "location": "Härryda",
            "business": "Mek. verkstad",
            "products": "Tillverkar klädskåp och verktygsskåp av stål samt cykelgarage m. m.",
            "contact": {
                "phone": "Telefon: 11 o. 18",
                "postgiro": "Postgiro: 81275"
            },
            "financials": {
                "capital": "Akt.-kap.: 45,000 kr",
                "employees": {
                    "industriarb": 40
                },
                "annual_turnover": "Tillv.-värde pr år: 350,000 kr"
            },
            "foundation_year": 1925,
            "manager": "Styrelse o. verkst. dir.: ing. Martin Hallin"
        },
        "5": {
            "name": "AB. Hässle, Apotekare Paul Nordströms Fabriker",
            "location": "Hässleholm",
            "business": "Kemisk-teknisk fabrik",
            "products": "Tillverkar farmaceutiska preparat och konserveringsmedel",
            "contact": {
                "phone": "Telefon: »AB. Hässle»",
                "postgiro": "Postgiro: 13663"
            },
            "financials": {
                "capital": "Akt.-kap.: 450,000 kr",
                "employees": {
                    "industriarb": 58
                }
            },
            "foundation_year": 1942,
            "board": [
                {
                    "name": "apot. Paul Nordström",
                    "role": "ordf."
                },
                {
                    "name": "dir. Börje Gabrielsson"
                },
                {
                    "name": "dir. Gösta Lagergren"
                },
                {
                    "name": "dir. Tore Norlander"
                }
            ],
            "manager": "Verkst. dir.: Tore Norlander"
        },
        "6": {
            "name": "AB. Hässleholms Bryggeri & Maltfabrik",
            "location": "Hässleholm",
            "business": "Malt- och läskedrycker tillverkare",
            "contact": {
                "phone": "Telefon: 73 o. 310",
                "postgiro": "Postgiro: 88850"
            },
            "financials": {
                "capital": "Akt.-kap.: 450,000 kr",
                "employees": {
                    "industriarb": 30
                },
                "annual_turnover": "Tillv.-värde pr år: 1,230,000 kr"
            },
            "foundation_year": 1928,
            "board": [
                {
                    "name": "riksdagsm. Anton Björklund",
                    "role": "ordf."
                },
                {
                    "name": "disp. Hugo Aspegrén"
                },
                {
                    "name": "disp. Erik Ekström"
                },
                {
                    "name": "dir. Karl-Erik Löfwall"
                },
                {
                    "name": "v. konsul O. Löfwall"
                }
            ],
            "manager": "Verkst. dir.: Erik Ekström"
        },
        "7": {
            "name": "AB. Hässleholms Kapsylfabrik",
            "location": "Hässleholm",
            "business": "Tillverkar kapsyler av bly och tenn samt vattenflaskkapsyler av aluminium",
            "contact": {
                "phone": "Telefon: Hässleholm 73 o. 310",
                "postgiro": "Postgiro: 88850"
            },
            "financials": {
                "capital": "Akt.-kap.: 450,000 kr",
                "employees": {
                    "industriarb": 30
                },
                "annual_turnover": "Tillv.-värde pr år: 1,230,000 kr"
            },
            "foundation_year": 1928,
            "board": [
                {
                    "name": "riksdagsm. Anton Björklund",
                    "role": "ordf."
                },
                {
                    "name": "disp. Hugo Aspegrén"
                },
                {
                    "name": "disp. Erik Ekström"
                },
                {
                    "name": "dir. Karl-Erik Löfwall"
                },
                {
                    "name": "v. konsul O. Löfwall"
                }
            ],
            "manager": "Verkst. dir.: Erik Ekström"
        }
    }
}