{
    "original": "Borg—Borgström\n\n*AB. C. O. Borgs Söners Fabriker,\n\nLund.\n\nUllspinneri, väveri, färgeri,\nappretur-verk samt kem. tvättanstalt. Tillverkar\nullgarner, boj, kapp- och klänningstyger,\nkostym- och ulstertyger m. m. samt\nutför löngodsarbeten och kem. tvätt.\n\nTelegr.-adr.: Borgs, Lund. Telefon:\n»Aktiebolaget Borgs». Postgiro: 24411.\n\nAkt.-kap.: 383,600 kr. Antal\nindustriarb.: 168. Tillv.-värde pr år: 2,394,000\nkr. — Firman etabl. 1734, bolag 1897,\nombildat 1913.\n\nStyrelse: dir. Otto W. Borg (ordf.),\nsjökapten O. August Borg, adv. Sigfrid\nLindström.\n\nVerkst. dir.: O. W. Borg.\n\nDisp.: Tage W:son Stigen.\n\n*Borgeby Tegelbruk, Flädie.\n\nTillverkar murtegel och tegelrör vid\ntegelbruk i Borgeby, Flädie (Malmöh. l.).\n\nTelefon: Löddeköpinge 4 o. 102.\nPostgiro: 87920. — Antal industriarb.: 20.\nArstillv.: 2,5 milj. st. tegelvaror. —\nFirman etabl. 1893.\n\nÄgare o. chefer: nämndem. Nils Ferd.\nNilsson o. tegelbruksäg. Einar Nilsson.\n\n* Bertil Borgenstierna &amp; Co. AB.,\n\nStockholm.\n\nMek. verkstad i Vagnhärad\n(Södermanl. l.). Tillverkar verktyg, speciellt\nför -bil-, flyg- och mek.\nverkstadsindustrier såsom hylsverktyg, specialnycklar,\ntolvkantnycklar, skruvutdragare,\npinn-bultsutdragare, dornar, mejslar,\nkann-ringskompressorer, riktverktyg, hjul- och\nkullageravdragare m. m. Bolaget driver\nsåsom huvudrörelse engroshandel med\nsvenska och utländska yerktyg,\nlagermetall, sintrade självsmörjande lager,\npressade detaljer av sintrat stål samt\nverktygsmaskiner.\n\nKontor: Stockholm, Oxtorgsg. 5.\nTelegr.-adr.: Borgis, Stockholm. Telefon:\n233985. Postgiro: 3158.\n\nAkt.-kap.: 50,000 kr. Antal\nindustriarb.: 18. Tillv.-värde pr år (egen tillv.):\n250,000 kr. — Firman etabl. 1909, bolag\n1922.\n\nStyrelse: grossh. Harald Frestadius\n(ordf.), ing. Eric Frestadius, med. dr\nGöran Nordenson.\n\nVerkst. dir.: H. Frestadius.\n\nV. verkst. dir.: E. Frestadius.\n\nVerkstadschef: ing. E. Cavalie.\n\n*AB. Borggårds Bruk, Borggård.\n\nJärnmanufakturverk, plåtslageri och\nsnickerifabrik vid Borggård (Ostergötl.\n1.). Tillverkar skruvkrok och skruvstift,\nsöljor, karbinhakar, sportartikelbeslag,\nhandverktyg, nit m. m. samt snickeri-,\nplåtslageri- och rörarbeten för\nkylindu-strien. Bolaget bedriver även skogsbruk\noch sågverksrörelse.\n\nTelefon: Finspång 2, 3 A, 4 A o.\nHällestad 5 A. Postgiro: 7991. — Akt.-kap.:\n370,000 kr. Antal industriarb.: 140.\nTillv.-värde pr år: 1,600,000 kr.\n\nBorggårds Bruk anlades i slutet av\n1500-talet; nuvarande\nmanufakturtillverkning började 1890, bolag 1922.\n\nStyrelse: övering. Oscar A. Wiberg\n(ordf.), kamrer K. G. Helin,\nbruksför-valt. Axel Marions, ing. John A. Nordin.\n\nVerkst. dir.: O. A. Wiberg.\n\nBruksförvalt. o. försäljn.-chef: A.\nMarions.\n\nKamrer: K. G. Helin.\n\nAB. Borghamns Kalkstensbrott,\n\nBorghamn.\n\nKalkstensbrott och stenhuggeri i\nBorghamn (Östergötl. l.). Tillverkar\nbyggnadssten, gravvårdar m. m.\n\nTelefon: Rogslösa 15. Postgiro: 99101.\n\n—\tAkt.-kap.: 58,000 kr. Antal\nindustriarb.: 32. Prod.-värde pr år: 250,000 kr.\n\n—\tBolaget grundat 1933.\nChef: verkm. Oskar Ericsson.\n\n* Borgstena Trikåfabrik, Borgstena.\n\nTillverkar herr-, dam- och\nbarnunderkläder i Lahmann-, interlock- och\nribb-kvaliteer vid fabrik i Borgstena (Älvsb.\n1J.\n\nTelefon: Borås 63015. Postgiro: 178887.\n— Antal industriarb.: 15. Tillv.-värde pr\når: 250,000 kr. — Firman etabl. 1925.\nÄgare o. chef: fabr. Gustav Johansson.\n\n* Frans Borgströms Möbelfabrik,\n\nMalmö.\n\nSnickeri- och möbelfabrik. Tillverkar\nmöbler samt butiks-, kontors- och\nbankinredningar.\n\nKontor: Rundelsg. 21. Telefon: 24953.\nPostgiro: 38056. — Antal industriarb.:\n25. Tillv.-värde pr år: 230,000 kr. —\nFirman etabl. 1918.\n\nÄgare o. chef: fabr. Frans Borgström.",
    "structured": {
        "firms": [
            {
                "name": "AB. C. O. Borgs Söners Fabriker",
                "location": "Lund",
                "business": "Ullspinneri, väveri, färgeri",
                "products": "Tillverkar ullgarner, boj, kapp- och klänningstyger, kostym- och ulstertyger m. m. samt utför löngodsarbeten och kem. tvätt",
                "contact": {
                    "office": "",
                    "phone": [],
                    "postgiro": "24411",
                    "head_office": "",
                    "sales_offices": [],
                    "telegraph": "Borgs, Lund",
                    "factory_office": "",
                    "factory_phone": ""
                },
                "financials": {
                    "capital": "383,600 kr",
                    "employees": {
                        "industriarb": 168
                    },
                    "annual_turnover": "2,394,000 kr",
                    "annual_production_value": ""
                },
                "foundation_year": 1734,
                "current_name_year": 1913,
                "predecessor": "",
                "original_name": "",
                "corporation_year": 1897,
                "board": [
                    {
                        "name": "Otto W. Borg",
                        "role": "ordf."
                    },
                    {
                        "name": "O. August Borg",
                        "role": "sjökapten"
                    },
                    {
                        "name": "Sigfrid Lindström",
                        "role": "adv."
                    }
                ],
                "owners": [],
                "director": "",
                "managing_director": "O. W. Borg",
                "sales_manager": "",
                "manager": ""
            },
            {
                "name": "Borgeby Tegelbruk",
                "location": "Flädie",
                "business": "Tillverkar murtegel och tegelrör",
                "products": "",
                "contact": {
                    "office": "",
                    "phone": [
                        "Löddeköpinge 4",
                        "102"
                    ],
                    "postgiro": "87920",
                    "head_office": "",
                    "sales_offices": [],
                    "telegraph": "",
                    "factory_office": "",
                    "factory_phone": ""
                },
                "financials": {
                    "capital": "",
                    "employees": {},
                    "annual_turnover": "",
                    "annual_production_value": ""
                },
                "foundation_year": 1893,
                "current_name_year": 0,
                "predecessor": "",
                "original_name": "",
                "corporation_year": 0,
                "board": [],
                "owners": [
                    "nämndem. Nils Ferd. Nilsson",
                    "tegelbruksäg. Einar Nilsson"
                ],
                "director": "",
                "managing_director": "",
                "sales_manager": "",
                "manager": ""
            },
            {
                "name": "Bertil Borgenstierna & Co. AB.",
                "location": "Stockholm",
                "business": "Mek. verkstad",
                "products": "Tillverkar verktyg, speciellt för -bil-, flyg- och mek. verkstadsindustrier",
                "contact": {
                    "office": "Stockholm, Oxtorgsg. 5",
                    "phone": [
                        "233985"
                    ],
                    "postgiro": "3158",
                    "head_office": "",
                    "sales_offices": [],
                    "telegraph": "Borgis, Stockholm",
                    "factory_office": "",
                    "factory_phone": ""
                },
                "financials": {
                    "capital": "50,000 kr",
                    "employees": {},
                    "annual_turnover": "250,000 kr",
                    "annual_production_value": ""
                },
                "foundation_year": 1909,
                "current_name_year": 1922,
                "predecessor": "",
                "original_name": "",
                "corporation_year": 0,
                "board": [
                    {
                        "name": "Harald Frestadius",
                        "role": "ordf."
                    },
                    {
                        "name": "Eric Frestadius",
                        "role": "ing."
                    },
                    {
                        "name": "Göran Nordenson",
                        "role": "med. dr"
                    }
                ],
                "owners": [],
                "director": "",
                "managing_director": "H. Frestadius",
                "sales_manager": "",
                "manager": ""
            },
            {
                "name": "AB. Borggårds Bruk",
                "location": "Borggård",
                "business": "Järnmanufakturverk, plåtslageri och snickerifabrik",
                "products": "Tillverkar skruvkrok och skruvstift, söljor, karbinhakar, sportartikelbeslag, handverktyg, nit m. m.",
                "contact": {
                    "office": "",
                    "phone": [
                        "Finspång 2",
                        "3 A",
                        "4 A",
                        "Hällestad 5 A"
                    ],
                    "postgiro": "7991",
                    "head_office": "",
                    "sales_offices": [],
                    "telegraph": "",
                    "factory_office": "",
                    "factory_phone": ""
                },
                "financials": {
                    "capital": "370,000 kr",
                    "employees": {},
                    "annual_turnover": "1,600,000 kr",
                    "annual_production_value": ""
                },
                "foundation_year": 1500,
                "current_name_year": 1922,
                "predecessor": "",
                "original_name": "",
                "corporation_year": 0,
                "board": [
                    {
                        "name": "Oscar A. Wiberg",
                        "role": "ordf."
                    },
                    {
                        "name": "K. G. Helin",
                        "role": "kamrer"
                    }
                ],
                "owners": [],
                "director": "",
                "managing_director": "O. A. Wiberg",
                "sales_manager": "",
                "manager": "A. Marions"
            },
            {
                "name": "AB. Borghamns Kalkstensbrott",
                "location": "Borghamn",
                "business": "Kalkstensbrott och stenhuggeri",
                "products": "Tillverkar byggnadssten, gravvårdar m. m.",
                "contact": {
                    "office": "",
                    "phone": [
                        "Rogslösa 15"
                    ],
                    "postgiro": "99101",
                    "head_office": "",
                    "sales_offices": [],
                    "telegraph": "",
                    "factory_office": "",
                    "factory_phone": ""
                },
                "financials": {
                    "capital": "58,000 kr",
                    "employees": {},
                    "annual_turnover": "250,000 kr",
                    "annual_production_value": ""
                },
                "foundation_year": 1933,
                "current_name_year": 0,
                "predecessor": "",
                "original_name": "",
                "corporation_year": 0,
                "board": [],
                "owners": [],
                "director": "",
                "managing_director": "Oskar Ericsson",
                "sales_manager": "",
                "manager": ""
            },
            {
                "name": "Borgstena Trikåfabrik",
                "location": "Borgstena",
                "business": "Tillverkar herr-, dam- och barnunderkläder",
                "products": "Tillverkar herr-, dam- och barnunderkläder i Lahmann-, interlock- och ribb-kvaliteer",
                "contact": {
                    "office": "",
                    "phone": [
                        "Borås 63015"
                    ],
                    "postgiro": "178887",
                    "head_office": "",
                    "sales_offices": [],
                    "telegraph": "",
                    "factory_office": "",
                    "factory_phone": ""
                },
                "financials": {
                    "capital": "",
                    "employees": {},
                    "annual_turnover": "",
                    "annual_production_value": ""
                },
                "foundation_year": 1925,
                "current_name_year": 0,
                "predecessor": "",
                "original_name": "",
                "corporation_year": 0,
                "board": [],
                "owners": [
                    "fabr. Gustav Johansson"
                ],
                "director": "",
                "managing_director": "",
                "sales_manager": "",
                "manager": ""
            },
            {
                "name": "Frans Borgströms Möbelfabrik",
                "location": "Malmö",
                "business": "Snickeri- och möbelfabrik",
                "products": "Tillverkar möbler samt butiks-, kontors- och bankinredningar",
                "contact": {
                    "office": "Rundelsg. 21",
                    "phone": [
                        "24953"
                    ],
                    "postgiro": "38056",
                    "head_office": "",
                    "sales_offices": [],
                    "telegraph": "",
                    "factory_office": "",
                    "factory_phone": ""
                },
                "financials": {
                    "capital": "",
                    "employees": {},
                    "annual_turnover": "230,000 kr",
                    "annual_production_value": ""
                },
                "foundation_year": 1918,
                "current_name_year": 0,
                "predecessor": "",
                "original_name": "",
                "corporation_year": 0,
                "board": [],
                "owners": [
                    "fabr. Frans Borgström"
                ],
                "director": "",
                "managing_director": "",
                "sales_manager": "",
                "manager": ""
            }
        ]
    }
}