{
    "original": "Kalhindustrie r—Kalmar\n\nKontor: Stockholm, Riddarg. 9.\nTele-.igr.-adr.: Kalkbränneribol., Stockholm.\nTelefon: 600622 o. 600607. Postgiro:\n3913.\n\nAkt.-kap.: 205,000 kr. Antal\nindustri-rarb.: 45. — Bolaget grundat 1927.\n\nStyrelse: dir. Aug. Jenning (ordf.),\ning. Bo Carlsson, fru Ester Carlsson, dir.\nMune Carlsson, disp. Sten Carlsson.\nVerkst. dir.: Rune Carlsson.\n\n\"Kalkindustrier, Västergötlands\nFörenade, Falköping.\n\nSe AB. Västergötlands Förenade\nKalk-jindustrier, Falköping.\n\n\"Kallenbergs AB., Uppsala.\n\nSågverk och hyvleri. Tillverkar sågade\n•och hyvlade trävaror. Bolaget driver\näven handel med byggnadsvaror samt\n^vättanstalt (Upsala Tvätt).\n\nTelefon: »Kallenbergs AB». Postgiro:\n\n4)045.\n\nAkt.-kap.: 200,000 kr. Antal\nindustriarb.: 55. — Sågverket anlagt 1878,\ntvätt-anstalten 1865 av Joh. Kallenberg, nuv.\ni&gt;olag grundat 1940.\n\nStyrelse o. verkst. dir.: Hj.\nKallen-ifc&amp;rg.\n\n*KalIerstads Tegelbruk, Linköping.\n\nSe AB. Förenade Tegelbruken,\nLinköping. *\n\n\"Kallhälls Gjuter i, Kallhäll\nSe Bolinders Fabriks AB., Kallhäll.\n\n\"Kallnar Bobbin C:o AB., Kalmar.\n\nBobbin- och lackeringsfabrik i Påryd\n-(Kalmar l.). Tillverkar svarvade\nmassartiklar av olika slag. Specialiteter:\nskruvkapslar, tablettrör och hylsor för\nkem.-tekniska preparat samt handtag till\nverktyg och hushållsartiklar.\n\nKontor: Kalmar. Telegr.-adr.:\nBobbin-fabrik, Kalmar. Telefon: 2770 o. 2233.\nPostgiro: 71718.\n\nAkt.-kap.: 228,000 kr. Antal\nindustriarb.: 135, varav 100 i bobbinfabriken.\nTillv.-värde pr år: 1,000,000 kr. —\nBolaget grundat 1922.\n\nStyrelse: fil. dr Ivar Anderson (ordf.),\n•disp. Frits Elfverson, disp. E. E.\nGull-brandsson.\n\nVerkst. dir.: Frits Elfverson.\nDisp.: E. E. Gullbrandsson.\n\n\"Kalmar Bryggeri AB., Kalmar.\n\nTillverkar maltdrycker, mineralvatten\noch läskedrycker.\n\nTelefon: »Bryggeribolaget». Postgiro:\n277898. — Akt.-kap.: 645,000 kr. Antal\nindustriarb.: 50. Tillv.-värde pr år:\n1,500,000 kr.\n\nBryggeriet anlagt 1852 under namn av\nAnderssons Bryggeri, bolag 1923, nuv.\nnamn 1935. Bolaget, som äger Mönsterås\nBryggeri AB., är dotterbolag till AB.\nStockholms Bryggerier.\n\nStyrelse: dir. Sven Schwartz (ordf.),\ndir. Harald Engström, dir. Germ. Weiner.\n\nVerkst. dir.: Germ. Weiner.\n\nDisp.: Inge Sjövall.\n\nKamrer: Artur Peterson.\n\n\"AB. Kalmar Chokladfabrik,\n\nKalmar.\n\nTillverkar choklad, konfityrer och\nkarameller.\n\nTelegr.-adr.: Choklad, Kalmar.\nTelefon: 2550—55. Postgiro: 11504.\nNederlag: Stockholm, Göteborg, Malmö, Visby\noch Borås.\n\nAkt.-kap.: 240,000 kr. Antal\nindustriarb.: 150.\n\nFirman grundad 1903, nuv. namn 1926.\nStyrelse: v. auditör Olof Swensson\n(ordf.), grossh. G. L. Anderzén, disp.\nGösta Edgren, civiling. Folke Edgren,\ndisp. Knut Linnér.\n\nVerkst. direktörer: Gösta Edgren o\nFolke Edgren.\n\nAB. Kalmar Konservfabrik,\n\nMörrum.\n\nKonservfabriker i Mörrum (Blekinge l.)\noch i Mörbylånga (Kalmar l.). Tillverkar\nkonserver av fisk, kött, frukt och\ngrönsaker, sylter och syltade frukter för\nhus-hålls- och konditoriändamål samt senap.\nVarumärke: »Lovers».\n\nKontor: Mörrum. Telegr.-adr.:\nKalmarkonserv, Mörrum. Telefon: 160—62.\nPostgiro: 73069.\n\nAkt.-kap.: 78,100 kr. Antal\nindustriarb.: 50. Tillv.-värde pr år: 1,000,000 kr.\n— Bolaget grundat 1930.\n\nStyrelse: kapten Torsten Lundell\n(ordf.), adv. R. Allmér, dir. Axel Mejåre.\nVerkst. dir.: Axel Mejåre.\n\n\"AB. Kalmar Lådfabrik, Kalmar.\n\nTillverkar lådämnen.\nTelegr.-adr.: Brynolf, Kalmar. Telefon:\n857 o. 2758. Postgiro: 160862.\n\n273*\n\n17",
    "structured": {
        "1": {
            "name": "Kalhindustrie r",
            "location": "Kalmar",
            "business": "Kalkindustri",
            "contact": {
                "office": "Stockholm, Riddarg. 9",
                "telegraph": "Kalkbränneribol., Stockholm",
                "phone": [
                    "600622",
                    "600607"
                ],
                "postgiro": "3913"
            },
            "financials": {
                "capital": "205,000 kr",
                "employees": {
                    "industri-rarb.": 45
                },
                "annual_turnover": "not available",
                "annual_production_value": "not available"
            },
            "foundation_year": 1927,
            "directors": {
                "board": [
                    {
                        "name": "Aug. Jenning",
                        "role": "ordf."
                    },
                    {
                        "name": "Bo Carlsson",
                        "role": "ing."
                    },
                    {
                        "name": "Ester Carlsson",
                        "role": "fru"
                    },
                    {
                        "name": "Mune Carlsson",
                        "role": "dir."
                    },
                    {
                        "name": "Sten Carlsson",
                        "role": "disp."
                    },
                    {
                        "name": "Rune Carlsson",
                        "role": "verkst. dir."
                    }
                ],
                "director": "Rune Carlsson"
            }
        },
        "2": {
            "name": "Kallenbergs AB., Uppsala",
            "location": "Uppsala",
            "business": "Sågverk och hyvleri",
            "contact": {
                "phone": [
                    "Kallenbergs AB."
                ],
                "postgiro": "4045"
            },
            "financials": {
                "capital": "200,000 kr",
                "employees": {
                    "industriarb.": 55
                },
                "annual_turnover": "not available",
                "annual_production_value": "not available"
            },
            "foundation_year": 1940,
            "owners": []
        },
        "3": {
            "name": "Kallnar Bobbin C:o AB., Kalmar",
            "location": "Kalmar",
            "business": "Bobbin- och lackeringsfabrik",
            "contact": {
                "office": "Kalmar",
                "telegraph": "Bobbin-fabrik, Kalmar",
                "phone": [
                    "2770",
                    "2233"
                ],
                "postgiro": "71718"
            },
            "financials": {
                "capital": "228,000 kr",
                "employees": {
                    "industriarb.": 135
                },
                "annual_turnover": "not available",
                "annual_production_value": "1,000,000 kr"
            },
            "foundation_year": 1922,
            "directors": {
                "board": [
                    {
                        "name": "Ivar Anderson",
                        "role": "fil. dr (ordf.)"
                    },
                    {
                        "name": "Frits Elfverson",
                        "role": "disp."
                    },
                    {
                        "name": "E. E. Gullbrandsson",
                        "role": "disp."
                    }
                ],
                "director": "Frits Elfverson"
            }
        },
        "4": {
            "name": "Kalmar Bryggeri AB., Kalmar",
            "location": "Kalmar",
            "business": "Tillverkar maltdrycker, mineralvatten och läskedrycker",
            "contact": {
                "phone": [
                    "Bryggeribolaget"
                ],
                "postgiro": "277898"
            },
            "financials": {
                "capital": "645,000 kr",
                "employees": {
                    "industriarb.": 50
                },
                "annual_turnover": "1,500,000 kr",
                "annual_production_value": "not available"
            },
            "foundation_year": 1935,
            "owners": [
                "AB. Stockholms Bryggerier"
            ]
        },
        "5": {
            "name": "AB. Kalmar Chokladfabrik",
            "location": "Kalmar",
            "business": "Tillverkar choklad, konfityrer och karameller",
            "contact": {
                "telegraph": "Choklad, Kalmar",
                "phone": [
                    "2550—55"
                ],
                "postgiro": "11504"
            },
            "financials": {
                "capital": "240,000 kr",
                "employees": {
                    "industriarb.": 150
                },
                "annual_turnover": "not available",
                "annual_production_value": "not available"
            },
            "foundation_year": 1926,
            "owners": []
        },
        "6": {
            "name": "AB. Kalmar Konservfabrik, Mörrum",
            "location": "Mörrum",
            "business": "Konservfabriker",
            "contact": {
                "telegraph": "Kalmarkonserv, Mörrum",
                "phone": [
                    "160—62"
                ],
                "postgiro": "73069"
            },
            "financials": {
                "capital": "78,100 kr",
                "employees": {
                    "industriarb.": 50
                },
                "annual_turnover": "1,000,000 kr",
                "annual_production_value": "not available"
            },
            "foundation_year": 1930,
            "owners": []
        },
        "7": {
            "name": "AB. Kalmar Lådfabrik, Kalmar",
            "location": "Kalmar",
            "business": "Tillverkar lådämnen",
            "contact": {
                "telegraph": "Brynolf, Kalmar",
                "phone": [
                    "857",
                    "2758"
                ],
                "postgiro": "160862"
            },
            "financials": {
                "capital": "not available",
                "employees": {
                    "not available": "not available"
                },
                "annual_turnover": "not available",
                "annual_production_value": "not available"
            },
            "foundation_year": "not available",
            "owners": [
                "not available"
            ],
            "directors": {
                "names": "not available"
            }
        }
    }
}