{
    "original": "Nya\n\nvedkapsågar. Varumärken: »Svea» o.\n»Omega».\n\nTelegr.-adr.: Sveaverken, Eskilstuna.\nTelefon: 31800. Postgiro: 27791.\n\nAkt.-kap.: 50,000 kr. Antal\nindustriarb.: 40. Tillv.-värde pr år: 575,000 kr.\n— Firman etabl. 1911, bolag 1917,\nom-bildat under nuv. namn 1925.\n\nStyrelse: disp. Gustaf Widén (ordf.),\ndisp. Elis Ericsson, verkstadschef\nManfred Lundqvist.\n\nVerkst. dir. o. disp.: Gustaf Widén.\n\n\"Nya Svenska Möbeltygs- &amp;\nMattfabriks AB., Göteborg.\n\nVäverier med färgerier och\nappretur-verk i Göteborg samt mattfabrik i\nChar-lottenberg (Värml. l.). Tillverkar\nmöbeltyger, mattor, gardiner, överkast m. m.\nVarumärke: »Atlas».\n\nKontor: Göteborg, Trycksg.; postadr.:\nGöteborg 5. Telegr.-adr.: Mattfabriken,\nGöteborg. Telefon: 161930. Postgiro:\n9536.\n\nAkt.-kap.: 375,000 kr. Antal\nindustriarb.: 180. Tillv.-värde pr år: 3,500,000 kr.\n\nFabriken grundad 1895, bolaget 1914.\nBolaget har i sig upptagit f. d. AB.\nBohus Mattfabriker.\n\nStyrelse: dir. Helge Andresen (ordf.),\ndir. Carl A. Carlsson.\n\nVerkst. dir.: Helge Andresen.\n\nKontorschef: Allan Andresen.\n\nFörsäljn.-chef: Börge Andresen.\n\nDriftsing.: Lars-Åke Koriander.\n\n\"Nya AB. Sörby Tegelbruk,\n\nNorrköping.\n\nTegelbruk i Sörby, Kummelby\n(Östergötl. l.). Tillverkar murtegel,\nreveterings-tegel och dräneringsrör.\n\nKontor: Norrköping. Telefon: 20101 o.\n42078. Postgiro: 33375. — Akt.-kap.:\n30,000 kr. Antal industriarb.: 20.\nÅrstillv.: 2,5 milj. st. tegelvaror. — Bolaget\ngrundat 1929.\n\nVerkst. dir.: kapten Sture Nylin.\n\nV. verkst. dir.: Stig Nylin.\n\n\"Nya Tagelspinneriet, Janson &amp;\nArnold, Köping.\n\nTagelspinneri, fjäderrenseri och\nsäng-klädersfabrik. Tillverkar spunnet tagel,\nfjäder och dun, tagelmadrasser,\nduntäcken och kuddar, resårmadrasser m. m.\n\nTelegr.-adr.: Ny tagel, Köping. Telefon:\n552 o. 852. Postgiro: 11122.\n\nRepresentanter: Stockholm: Axel E.\nMalmqvist, Drottningg. 50—52, telefon:\n\n203251; Göteborg: Oscar Samvik,\nHvit-feldtsg. 14, telefon: 111143.\n\nAntal industriarb.: 75. Tillv.-värde pr\når: 1,750,000 kr. — Firman etabl. 1917.\n\nÄgare: fabr. David S. Janson, fabr.\nBirger Arnold, fabr. Georg Arnold o.\nstud. Tore Arnold.\n\nChef: David S. Janson.\n\n\"AB. Nya Tråd- &amp; Spikfabriken,\n\nVärnamo.\n\nTillverkar trådspik, stängselkrampor,\nblank, förkopprad och galvaniserad\njärntråd, glödgad svart järntråd samt\nfönster-stifttråd.\n\nTelefon: 10363. Postgiro: 76355.\nRepresentanter: AB. Aug. Hall, Alvesta,\ntelefon: 101; Hj. Edwards &amp; Co. AB.,\nGöteborg, St. Badhusg. 20, telefon: 110656.\n\nAkt.-kap.: 63,000 kr. Antal\nindustriarb.: 20. Tillv.-värde pr år: 600,000 kr.\n\n—\tBolaget grundat 1925.\n\nStyrelse: fabr. Helmer Rosenqvist\n(ordl), fabr. Axel Haag, fabr. Gunnar\nNord.\n\nVerkst. dir.: Helmer Rosenqvist.\n\n\"Nya AB. Upperuds Valsqvarn,\n\nUpperud.\n\nValskvarn vid Upperud (Älvsb. l.).\nTillverkar vete- och rågmjöl samt kli.\n\nTelegr.-adr.: Upperudkvarn,\nVänersborg. Telefon: Mellerud 1 samt\nÅsensbruk 35 o. 36. Postgiro: 70907.\n\nAkt.-kap.: 260,000 kr. Antal\nindustriarb.: 15. Prod.-värde pr år: 1,200,000 kr.\n\n—\tBolaget grundat 1898.\n\nStyrelse: prof. Gustaf Ising (ordf.),\nkapten Carl-Gustaf Carlsson, disp. Sven\nDeshayes, bruksäg. Axel Lundberg,\nbankdir. Malcolm Paulsson.\n\nVerkst. dir. o. disp.: Sven Deshayes.\n\n\"AB. Nya Vaddfabriken,\n\nLiljeholmen.\n\nSe AB. Stockholms Vaddfabrik,\nLiljeholmen.\n\n\"Nya Wermlands-Tidningens AB.,\n\nKarlstad.\n\nTidnings- och boktryckeri. Bolaget\ndriver även förlagsverksamhet.\n\nTelegr.-adr.: Änwete, Karlstad.\nTelefon: »Wermlandstidningen». Postgiro:\n5040.\n\nAkt.-kap.: 178,000 kr. Antal\nindustriarb.: 41. — Verksamheten grundad 1836.\n\nStyrelse: godsäg. Petrus Johansson",
    "structured": {
        "0": {
            "namn": "Nya Sveaverken",
            "plats": "Eskilstuna",
            "affärsidé": "Tillverkning av vedsågar",
            "produktbeskrivning": "Varumärken: »Svea» och »Omega»",
            "kontakt": {
                "kontor": "Sveaverken, Eskilstuna",
                "telefon": [
                    "31800"
                ],
                "postgiro": "27791",
                "huvudkontor": "",
                "försäljningskontor": [],
                "telegraf": "",
                "fabrikskontor": "",
                "fabrikstelefon": ""
            },
            "finansiella_uppgifter": {
                "kapital": "50,000 kr",
                "anställda": {
                    "industriarb": 40
                },
                "årsomsättning": "575,000 kr",
                "årligt_produktionsvärde": "575,000 kr"
            },
            "grundades_året": 1911,
            "nuvarande_namn_året": 1925,
            "föregångare": "",
            "ursprungliga_namn": "",
            "bildades_året": 1917,
            "styrelse": [
                {
                    "namn": "Gustaf Widén",
                    "roll": "ordförande"
                },
                {
                    "namn": "Elis Ericsson",
                    "roll": "disp."
                },
                {
                    "namn": "Manfred Lundqvist",
                    "roll": "verkstadschef"
                }
            ],
            "ägare": [],
            "direktör": "",
            "verkställande_direktör": "Gustaf Widén",
            "försäljningschef": "",
            "chef": ""
        },
        "1": {
            "namn": "Nya Svenska Möbeltygs- & Mattfabriks AB.",
            "plats": "Göteborg",
            "affärsidé": "Tillverkning av möbeltyger, mattor, gardiner, överkast m.m.",
            "produktbeskrivning": "Varumärke: »Atlas»",
            "kontakt": {
                "kontor": "Göteborg, Trycksg.",
                "telefon": [
                    "161930"
                ],
                "postgiro": "9536",
                "huvudkontor": "",
                "försäljningskontor": [],
                "telegraf": "",
                "fabrikskontor": "",
                "fabrikstelefon": ""
            },
            "finansiella_uppgifter": {
                "kapital": "375,000 kr",
                "anställda": {
                    "industriarb": 180
                },
                "årsomsättning": "3,500,000 kr",
                "årligt_produktionsvärde": "3,500,000 kr"
            },
            "grundades_året": 1895,
            "nuvarande_namn_året": "",
            "föregångare": "f.d. AB. Bohus Mattfabriker",
            "ursprungliga_namn": "",
            "bildades_året": 1914,
            "styrelse": [
                {
                    "namn": "Helge Andresen",
                    "roll": "ordförande"
                },
                {
                    "namn": "Carl A. Carlsson",
                    "roll": "disp."
                }
            ],
            "ägare": [
                "Halge Andresen",
                "Carl A. Carlsson"
            ],
            "direktör": "",
            "verkställande_direktör": "Helge Andresen",
            "försäljningschef": "Börge Andresen",
            "chef": "Allan Andresen"
        },
        "2": {
            "namn": "Nya AB. Sörby Tegelbruk",
            "plats": "Norrköping",
            "affärsidé": "Tillverkning av murtegel, reveteringstegel och dräneringsrör",
            "produktbeskrivning": "",
            "kontakt": {
                "kontor": "Norrköping",
                "telefon": [
                    "20101",
                    "42078"
                ],
                "postgiro": "33375",
                "huvudkontor": "",
                "försäljningskontor": [],
                "telegraf": "",
                "fabrikskontor": "",
                "fabrikstelefon": ""
            },
            "finansiella_uppgifter": {
                "kapital": "30,000 kr",
                "anställda": {
                    "industriarb": 20
                },
                "årsomsättning": "",
                "årligt_produktionsvärde": "2,500,000 kr"
            },
            "grundades_året": 1929,
            "nuvarande_namn_året": "",
            "föregångare": "",
            "ursprungliga_namn": "",
            "bildades_året": "",
            "styrelse": [],
            "ägare": [],
            "direktör": "kapten Sture Nylin",
            "verkställande_direktör": "Stig Nylin",
            "försäljningschef": "",
            "chef": ""
        },
        "3": {
            "namn": "Nya Tagelspinneriet, Janson & Arnold",
            "plats": "Köping",
            "affärsidé": "Tillverkning av spunnet tagel, fjäder och dun, tagelmadrasser, duntäcken och kuddar, resårmadrasser m.m.",
            "produktbeskrivning": "",
            "kontakt": {
                "kontor": "Köping",
                "telefon": [
                    "552",
                    "852"
                ],
                "postgiro": "11122",
                "huvudkontor": "",
                "försäljningskontor": [],
                "telegraf": "Ny tagel, Köping",
                "fabrikskontor": "",
                "fabrikstelefon": ""
            },
            "finansiella_uppgifter": {
                "kapital": "",
                "anställda": {
                    "industriarb": 75
                },
                "årsomsättning": "1,750,000 kr",
                "årligt_produktionsvärde": "1,750,000 kr"
            },
            "grundades_året": 1917,
            "nuvarande_namn_året": "",
            "föregångare": "",
            "ursprungliga_namn": "",
            "bildades_året": "",
            "styrelse": [],
            "ägare": [
                "David S. Janson",
                "Birger Arnold",
                "Georg Arnold",
                "Tore Arnold"
            ],
            "direktör": "David S. Janson",
            "verkställande_direktör": "",
            "försäljningschef": "",
            "chef": ""
        },
        "4": {
            "namn": "Nya AB. Sörby Tegelbruk",
            "plats": "Värnamo",
            "affärsidé": "Tillverkning av trådspik, stängselkrampor, blank, förkopprad och galvaniserad järntråd, glödgad svart järntråd samt fönsterstifttråd",
            "produktbeskrivning": "",
            "kontakt": {
                "kontor": "",
                "telefon": [
                    "10363"
                ],
                "postgiro": "76355",
                "huvudkontor": "",
                "försäljningskontor": [],
                "telegraf": "",
                "fabrikskontor": "",
                "fabrikstelefon": ""
            },
            "finansiella_uppgifter": {
                "kapital": "63,000 kr",
                "anställda": {
                    "industriarb": 20
                },
                "årsomsättning": "600,000 kr",
                "årligt_produktionsvärde": "600,000 kr"
            },
            "grundades_året": 1925,
            "nuvarande_namn_året": "",
            "föregångare": "",
            "ursprungliga_namn": "",
            "bildades_året": "",
            "styrelse": [
                {
                    "namn": "Helmer Rosenqvist",
                    "roll": "ordförande"
                },
                {
                    "namn": "Axel Haag",
                    "roll": "fabrikör"
                },
                {
                    "namn": "Gunnar Nord",
                    "roll": "fabrikör"
                }
            ],
            "ägare": [],
            "direktör": "",
            "verkställande_direktör": "Helmer Rosenqvist",
            "försäljningschef": "",
            "chef": ""
        },
        "5": {
            "namn": "Nya AB. Upperuds Valsqvarn",
            "plats": "Upperud",
            "affärsidé": "Tillverkning av vete- och rågmjöl samt kli",
            "produktbeskrivning": "",
            "kontakt": {
                "kontor": "",
                "telefon": [
                    "Mellerud 1",
                    "Åsensbruk 35",
                    "36"
                ],
                "postgiro": "70907",
                "huvudkontor": "",
                "försäljningskontor": [],
                "telegraf": "Upperudkvarn, Vänersborg",
                "fabrikskontor": "",
                "fabrikstelefon": ""
            },
            "finansiella_uppgifter": {
                "kapital": "260,000 kr",
                "anställda": {
                    "industriarb": 15
                },
                "årsomsättning": "",
                "årligt_produktionsvärde": "1,200,000 kr"
            },
            "grundades_året": 1898,
            "nuvarande_namn_året": "",
            "föregångare": "",
            "ursprungliga_namn": "",
            "bildades_året": "",
            "styrelse": [
                {
                    "namn": "Gustaf Ising",
                    "roll": "ordförande"
                },
                {
                    "namn": "Carl-Gustaf Carlsson",
                    "roll": "kapten"
                },
                {
                    "namn": "Sven Deshayes",
                    "roll": "disp."
                },
                {
                    "namn": "Axel Lundberg",
                    "roll": "bruksägare"
                },
                {
                    "namn": "Malcolm Paulsson",
                    "roll": "bankdirektör"
                }
            ],
            "ägare": [],
            "direktör": "Sven Deshayes",
            "verkställande_direktör": "",
            "försäljningschef": "",
            "chef": ""
        },
        "6": {
            "namn": "Nya AB. Nya Vaddfabriken",
            "plats": "Liljeholmen",
            "affärsidé": "",
            "produktbeskrivning": "",
            "kontakt": {
                "kontor": "AB. Stockholms Vaddfabrik, Liljeholmen",
                "telefon": [],
                "postgiro": "",
                "huvudkontor": "",
                "försäljningskontor": [],
                "telegraf": "",
                "fabrikskontor": "",
                "fabrikstelefon": ""
            },
            "finansiella_uppgifter": {
                "kapital": "",
                "anställda": {},
                "årsomsättning": "",
                "årligt_produktionsvärde": ""
            },
            "grundades_året": "",
            "nuvarande_namn_året": "",
            "föregångare": "",
            "ursprungliga_namn": "",
            "bildades_året": "",
            "styrelse": [],
            "ägare": [],
            "direktör": "",
            "verkställande_direktör": "",
            "försäljningschef": "",
            "chef": ""
        },
        "7": {
            "namn": "Nya AB. Wermlands-Tidningens AB.",
            "plats": "Karlstad",
            "affärsidé": "Tidnings- och boktryckeri samt förlagsverksamhet",
            "produktbeskrivning": "",
            "kontakt": {
                "kontor": "",
                "telefon": [
                    "Wermlandstidningen"
                ],
                "postgiro": "5040",
                "huvudkontor": "",
                "försäljningskontor": [],
                "telegraf": "Änwete, Karlstad",
                "fabrikskontor": "",
                "fabrikstelefon": ""
            },
            "finansiella_uppgifter": {
                "kapital": "178,000 kr",
                "anställda": {
                    "industriarb": 41
                },
                "årsomsättning": "",
                "årligt_produktionsvärde": ""
            },
            "grundades_året": 1836,
            "nuvarande_namn_året": "",
            "föregångare": "",
            "ursprungliga_namn": "",
            "bildades_året": "",
            "styrelse": [],
            "ägare": [],
            "direktör": "",
            "verkställande_direktör": "",
            "försäljningschef": "",
            "chef": ""
        }
    }
}