{
    "original": "Essvik—Ewos\n\n*Essviks AB., Sundsvall.\n\nSulfitfabrik och sulfitspritfabrik vid\nEssvik (Västernorrl. l.). Tillverkar\nsulfitcellulosa och sulfitsprit. Bolaget idkar\njämväl skogshantering.\n\nHuvudkontor: Sundsvall (se\nSundsvallsbolagen). Ensamförsälj. f. cellulosa:\nSvenska Cellulosa AB., Stockholm, V.\nTrädgårdsg. 15, telefon:\n»Cellulosabolaget».\n\nAkt.-kap.: 7,500,000 kr. Antal\nindustriarb.: 350. Årskapacitet: 38,000 ton\nsul-fiteellulosa, 3,5 milj. liter sulfitsprit.\n\nBolaget grundat 1898 under namn\nSundsvalls Cellulosa AB., nuv. namn\n1939. Bolaget äges av Svartviks AB.,\ntillhörande Svenska Cellulosa AB.,\nStockholm.\n\nStyrelse: dir. Torsten Hérnod (ordf.),\ndir. Gust. Göranson, dir. Gust. J.\nSahlin, bankdir. Per F. Wåhlin.\n\nVerkst. dir.: Gust. Göranson.\n\nIng.: L. B. Schibbye.\n\nEsterna Konfektions AB., Stockholm.\n\nTillverkar impregnerade och\ngumme-rade regnplagg samt sportjackor.\n\nKontor: Igeldammsg. 24. Telegr.-adr.:\nEstemasto, Stockholm. Telefon: 516006.\nPostgiro: 154980.\n\nAkt.-kap.: 50,000 kr. Antal\nindustriarb.: 60. Tillv.-värde pr år: 900,000 kr.\n— Bolaget grundat 1938.\n\nChef: fru I. M. Lindstrand.\n\n*AB. Esti (Ekenäs Skid- &amp;\nTräindustri), Ekenässjön.\n\nTillverkar möbler vid fabrik vid\nEkenässjön (Jönköp. l.). Specialitet: bord.\n\nTelefon: 38. Postgiro: 166542. —\nAkt.-kap.: 40,000 kr. Antal industriarb.: 12.\nTillv.-värde pr år: 200,000 kr. — Firman\netabl. 1938, bolag 1942.\n\nStyrelse: greve Gösta Bielke (ordf.),\nfabr. Arthur Carlstrom, disp. Sixten\nCarlström.\n\nVerkst. dir.: Sixten Carlstrom.\n\n*Eternit-Bolaget, Lomma.\n\nSe Skandinaviska Eternit ÄB., Lomma.\n\nAB. Etsade Skyltar, Stockholm.\n\nTillverkar etsade och tryckta skyltar\nsamt skalor; utför maskingravering.\n\nKontor: Arbetarg. 33 A. Telefon:\n520855. Postgiro: 158586. — Akt.-kap.:\n15.000 kr. Antal industriarb.: 35.\nTillv.-värde pr år: 500,000 kr. — Firman etabl.\n1916, nuv. namn 1940.\n\nVerkst. dir.: Sture Danielsson.\n\n*AB. Europa Film, Stockholm.\n\nFilminspelningsateljéer i Nya\nMarie-häll, Bromma. Producerar och uthyr\nspelfilmer; tillverkar och ombesörjer\nvisningar av industri- och\npropagandafilmer samt annonsfilmer. Firman driver\näven biografrörelse.\n\nKontor: Kungsg. 24. Telegr.-adr. o.\ntelefon: Europafilm. Postgiro: 52490.\n\nAkt.-kap.: 1,000,000 kr. Antal\nanställda: 175. — Bolaget grundat 1930.\n\nStyrelse o. verkst. dir.: G. Scheutz.\n\nDirektörer: P. Scheutz o. E. Brynjer.\n\nKamrer: E. Gunnerholm.\n\nTekn. chef: civiling. Harry Holm.\n\nChef för industri- o. annonsfilmavd. :\nPehr-Olof Nuhma.\n\nChef för filmuthyrning: Seth Karlsson.\n\nEvers &amp; Co. ABHälsingborg.\n\nTillverkar tak- och övrig impr.\nbyggnadspapp, asfalt- och tjärpreparat,\nisole-ringsmateriel mot väta och fukt,\nträkonserveringsmedel, fruktträdskarbolineum,\n\nslamfärg, tak- och aluminiumfärger,\npreparat för uppsättning av väggplattor\n(märke: »Kakelfix») m. m. Varumärken:\n»Solidol», »Herkules», »Goudronit»,\n»ECO» m. fl. Firman driver även\nen-grosshandel med träullsplattor och andra\nbyggnadsmateriel samt\nentreprenadverksamhet i taktäckningar och isoleringar\nm. m.\n\nHuvudkontor: Hälsingborg.\nTelegr.-adr.: Eversco, Hälsingborg. Telefon:\n»Evers &amp; Co.». Postgiro: 11505.\nNederlag: Stockholm, Henriksdal, telefon:\n440065; Göteborg, Mårten Krakowsg. 1 A,\ntelefon: 154135 o. 155085; Örebro,\ntelefon: 19760.\n\nAkt.-kap.: 750,000 kr. Antal\nindustriarb.: 110. Tillv.-värde pr år: 5,000,000\nkr. — Firman etabl. 1893, nuv. bolag\n1944.\n\nDisp.: Algot Olsson.\n\nKamrer: Jonny I. Nilsson.\n\nAB. Ewos, Södertälje.\n\nKem. teknisk fabrik. Tillverkar kem.\nprodukter för lantbruk och industri\nsåsom vitamin- och mineralämnespreparat,\nbetnings-, besprutnings- och\nutrotningsmedel, desinfektions- och\nrengöringsmedel, sårsalva och sårolja,\nimpregnerings-medel för slipmassa samt\nmejerikemikalier.\n\nTelegr.-adr.: Ewos, Södertälje.\nTelefon: 32382. Postgiro: 4773. — Akt.-kap.:\n180,000 kr. Antal industriarb.: 45. —\nBolaget grundat 1935.",
    "structured": {
        "firms": [
            {
                "name": "Essviks AB",
                "location": "Sundsvall",
                "business": "Sulfitfabrik och sulfitspritfabrik",
                "contact": {
                    "office": "Sundsvall",
                    "phone": [],
                    "postgiro": null,
                    "head_office": null,
                    "sales_offices": [],
                    "telegraph": null,
                    "factory_office": null,
                    "factory_phone": null
                },
                "financials": {
                    "capital": "7,500,000 kr",
                    "employees": {
                        "industriarb": 350
                    },
                    "annual_turnover": null,
                    "annual_production_value": null
                },
                "foundation_year": 1898,
                "current_name_year": 1939,
                "predecessor": "Sundsvalls Cellulosa AB",
                "original_name": "Sundsvalls Cellulosa AB",
                "corporation_year": null,
                "board": [
                    {
                        "name": "Torsten Hérnod",
                        "role": "ordf."
                    },
                    {
                        "name": "Gust. Göranson",
                        "role": "dir."
                    },
                    {
                        "name": "Gust. J. Sahlin",
                        "role": "dir."
                    },
                    {
                        "name": "Per F. Wåhlin",
                        "role": "bankdir."
                    }
                ],
                "owners": [
                    "Svartviks AB"
                ],
                "director": "Gust. Göranson",
                "managing_director": null,
                "sales_manager": null,
                "manager": "L. B. Schibbye"
            },
            {
                "name": "Esterna Konfektions AB",
                "location": "Stockholm",
                "business": "Tillverkar impregnerade och gummierade regnplagg samt sportjackor",
                "contact": {
                    "office": "Igeldammsg. 24",
                    "phone": [
                        "516006"
                    ],
                    "postgiro": "154980",
                    "head_office": null,
                    "sales_offices": [],
                    "telegraph": "Estemasto",
                    "factory_office": null,
                    "factory_phone": null
                },
                "financials": {
                    "capital": "50,000 kr",
                    "employees": {
                        "industriarb": 60
                    },
                    "annual_turnover": "900,000 kr",
                    "annual_production_value": null
                },
                "foundation_year": 1938,
                "current_name_year": null,
                "predecessor": null,
                "original_name": null,
                "corporation_year": 1942,
                "board": [],
                "owners": [],
                "director": "fru I. M. Lindstrand",
                "managing_director": null,
                "sales_manager": null,
                "manager": null
            },
            {
                "name": "AB. Esti (Ekenäs Skid- & Träindustri)",
                "location": "Ekenässjön",
                "business": "Tillverkar möbler",
                "contact": {
                    "office": null,
                    "phone": [
                        "38"
                    ],
                    "postgiro": "166542",
                    "head_office": null,
                    "sales_offices": [],
                    "telegraph": null,
                    "factory_office": null,
                    "factory_phone": null
                },
                "financials": {
                    "capital": "40,000 kr",
                    "employees": {
                        "industriarb": 12
                    },
                    "annual_turnover": "200,000 kr",
                    "annual_production_value": null
                },
                "foundation_year": 1938,
                "current_name_year": 1942,
                "predecessor": null,
                "original_name": null,
                "corporation_year": null,
                "board": [
                    {
                        "name": "greve Gösta Bielke",
                        "role": "ordf."
                    },
                    {
                        "name": "fabr. Arthur Carlstrom",
                        "role": null
                    },
                    {
                        "name": "disp. Sixten Carlström",
                        "role": null
                    }
                ],
                "owners": [],
                "director": null,
                "managing_director": null,
                "sales_manager": null,
                "manager": "Sixten Carlstrom"
            },
            {
                "name": "Eternit-Bolaget",
                "location": "Lomma",
                "business": null,
                "contact": {
                    "office": null,
                    "phone": [],
                    "postgiro": null,
                    "head_office": null,
                    "sales_offices": [],
                    "telegraph": null,
                    "factory_office": null,
                    "factory_phone": null
                },
                "financials": {
                    "capital": null,
                    "employees": null,
                    "annual_turnover": null,
                    "annual_production_value": null
                },
                "foundation_year": null,
                "current_name_year": null,
                "predecessor": "Skandinaviska Eternit ÄB.",
                "original_name": null,
                "corporation_year": null,
                "board": [],
                "owners": [],
                "director": null,
                "managing_director": null,
                "sales_manager": null,
                "manager": null
            },
            {
                "name": "AB. Etsade Skyltar",
                "location": "Stockholm",
                "business": "Tillverkar etsade och tryckta skyltar samt skalor; utför maskingravering",
                "contact": {
                    "office": "Arbetarg. 33 A",
                    "phone": [
                        "520855"
                    ],
                    "postgiro": "158586",
                    "head_office": null,
                    "sales_offices": [],
                    "telegraph": null,
                    "factory_office": null,
                    "factory_phone": null
                },
                "financials": {
                    "capital": "15,000 kr",
                    "employees": {
                        "industriarb": 35
                    },
                    "annual_turnover": "500,000 kr",
                    "annual_production_value": null
                },
                "foundation_year": 1916,
                "current_name_year": 1940,
                "predecessor": null,
                "original_name": null,
                "corporation_year": null,
                "board": [],
                "owners": [],
                "director": null,
                "managing_director": "Sture Danielsson",
                "sales_manager": null,
                "manager": null
            },
            {
                "name": "AB. Europa Film",
                "location": "Stockholm",
                "business": "Filminspelningsateljéer i Nya Mariehäll, Bromma. Producerar och uthyr spelfilmer; tillverkar och ombesörjer visningar av industri- och propagandafilmer samt annonsfilmer. Firman driver även biografrörelse",
                "contact": {
                    "office": "Kungsg. 24",
                    "phone": [],
                    "postgiro": "52490",
                    "head_office": null,
                    "sales_offices": [],
                    "telegraph": "Europafilm",
                    "factory_office": null,
                    "factory_phone": null
                },
                "financials": {
                    "capital": "1,000,000 kr",
                    "employees": {
                        "anställda": 175
                    },
                    "annual_turnover": null,
                    "annual_production_value": null
                },
                "foundation_year": 1930,
                "current_name_year": null,
                "predecessor": null,
                "original_name": null,
                "corporation_year": null,
                "board": [],
                "owners": [],
                "director": null,
                "managing_director": null,
                "sales_manager": null,
                "manager": null
            },
            {
                "name": "Evers & Co. AB",
                "location": "Hälsingborg",
                "business": "Tillverkar tak- och övrig impr. byggnadspapp, asfalt- och tjärpreparat, isoleringsmateriel mot väta och fukt, träkonserveringsmedel, fruktträdskarbolineum, slamfärg, tak- och aluminiumfärger, preparat för uppsättning av väggplattor (märke: »Kakelfix») m. m. Varumärken: »Solidol», »Herkules», »Goudronit», »ECO» m. fl. Firman driver även engrosshandel med träullsplattor och andra byggnadsmateriel samt entrepenadverksamhet i taktäckningar och isoleringar m. m.",
                "contact": {
                    "office": "Hälsingborg",
                    "phone": [
                        "Evers & Co."
                    ],
                    "postgiro": "11505",
                    "head_office": null,
                    "sales_offices": [
                        {
                            "location": "Stockholm",
                            "phone": "440065"
                        },
                        {
                            "location": "Göteborg",
                            "phone": "154135 o. 155085"
                        },
                        {
                            "location": "Örebro",
                            "phone": "19760"
                        }
                    ],
                    "telegraph": "Eversco",
                    "factory_office": null,
                    "factory_phone": null
                },
                "financials": {
                    "capital": "750,000 kr",
                    "employees": {
                        "industriarb": 110
                    },
                    "annual_turnover": "5,000,000 kr",
                    "annual_production_value": null
                },
                "foundation_year": 1893,
                "current_name_year": 1944,
                "predecessor": null,
                "original_name": null,
                "corporation_year": null,
                "board": [],
                "owners": [],
                "director": null,
                "managing_director": null,
                "sales_manager": null,
                "manager": null
            },
            {
                "name": "AB. Ewos",
                "location": "Södertälje",
                "business": "Kem. teknisk fabrik. Tillverkar kem. produkter för lantbruk och industri såsom vitamin- och mineralämnespreparat, betnings-, besprutnings- och utrotningsmedel, desinfektions- och rengöringsmedel, sårsalva och sårolja, impregneringsmedel för slipmassa samt mejerikemikalier",
                "contact": {
                    "office": "Södertälje",
                    "phone": [
                        "32382"
                    ],
                    "postgiro": "4773",
                    "head_office": null,
                    "sales_offices": [],
                    "telegraph": "Ewos",
                    "factory_office": null,
                    "factory_phone": null
                },
                "financials": {
                    "capital": "180,000 kr",
                    "employees": {
                        "industriarb": 45
                    },
                    "annual_turnover": null,
                    "annual_production_value": null
                },
                "foundation_year": 1935,
                "current_name_year": null,
                "predecessor": null,
                "original_name": null,
                "corporation_year": null,
                "board": [],
                "owners": [],
                "director": null,
                "managing_director": null,
                "sales_manager": null,
                "manager": null
            }
        ]
    }
}