{
    "original": "Nyqvist—Nyköping\n\nD. Nyqvist, Ljungby Trikåindustri,\n\nLjungby.\n\nSe Ljungby Trikåindustri, D.\nNyqvist, Ljungby.\n\nAB. Nyköpings Automobilfabrik,\n\nNyköping.\n\nHopsätter och monterar person- och\nlastbilar. Varumärke: »ANA». Bolaget är\nrepresentant för bl. a. Chrysler\nCorporation, Detroit, U.S.A., The Standard Motor\nCo., Ltd, Coventry, England och The\nSkodaworks, Prag, Tjeckoslovakien.\n\nTelegr.-adr.: Aena, Nyköping. Telefon:\n2700. Postgiro: 135265.\n\nAkt.-kap.: 1,500,000 kr. Antal\nindustriarb.: 150. — Bolaget grundat 1937.\n\nStyrelse: dir. Wilhelm Josephson (ordf.),\ndir. Gunnar K. H. Andersson, adv. C. M.\nFallenius, bergsing. Carl J. Kjellberg,\nadv. Ivar Philipson.\n\nVerkst. dir.: C. J. Kjellberg.\n\nFörsäljn.-chef: Arne Granström.\n\n\"Nyköpings Bryggeri AB.,\n\nNyköping.\n\nTillverkar malt, maltdrycker samt\nkol-syrade läskedrycker och mineralvatten.\n\nTelefon: »Bryggeribolaget». Postgiro:\n11777. — Akt.-kap.: 450,000 kr. Antal\nindustriarb.: 40. Tillv.-värde pr år:\n1,400,000 kr. — Bolaget grundat 1905.\n\nStyrelse: dir. Otto Lindeberg (ordf.),\ndisp. Carl Axel Anderson, dir. Bure\nHolmbäck.\n\nVerkst. dir.: Carl Axel Anderson.\n\nAB. Nyköpings Ekmöbelfabrik,\n\nNyköping.\n\nTillverkar vardagsrumsmöbler av björk,\nalm och mahogny.\n\nTelefon: 292. Postgiro: 28356. —\nAkt.-kap.: 52,900 kr. Antal industriarb.:\n22. Tillv.-värde pr år: 220,000 kr. —\nBolaget grundat 1909.\n\nDisp.: Carl Johan Johansson.\n\n\"Nyköpings Entreprenad AB.,\n\nNyköping.\n\nByggnadsentreprenörfirma för\nbostads-och industribyggnader.\n\nTelegr.-adr.: Neab, Nyköping. Telefon:\n»Entreprenadbolaget». Postgiro: 70821. —\nAkt.-kap.: 75,000 kr. Prod.-värde pr år:\n3,000,000 kr. — Bolaget grundat 1945.\n\nStyrelse: adv. Herman Heilborn (ordf.),\ndisp. Carl-Axel Andersson, ing. Thage\nAndersson.\n\nVerkst. dir.: Thage Andersson.\n\n\"Nyköpings Exportlistfabrik,\n\nNyköping.\n\nSe AB. Exportlist, Nyköping.\n\nAB. Nyköpings Culdlistfabrik,\n\nNyköping.\n\nTillverkar fotografiramar, hörnramar,\nramlister samt kilramar.\n\nTelefon: 1661. Postgiro: 132498. Repr.\ni Stockholm: Herm. Bornemann AB.,\nSlussplan 5, telefon: 112730.\n\nAkt.-kap.: 25,000 kr. Tillv.-värde pr\når: 550,000 kr. — Firman etabl. 1937,\nbolag 1939.\n\nDisp.: Hilmer A. Andersson.\n\nNyköpings Metallfabriks AB.,\n\nNyköping.\n\nTillverkar metallinredningar for\nbadhus, bank-, post- och affärslokaler.\n\nTelefon: 114. Postgiro: 26136. —\nAkt.-kap.: 30,000 kr. Antal industriarb.: 21.\nTillv.-värde pr år: 120,000 kr. — Bolaget\ngrundat 1921.\n\nChef: verkm. Göte Blomdahl.\n\nNyköpings Nya Möblerings AB.,\n\nNyköping.\n\nMöbelfabrik. Tillverkar\nbostadsmöbler, kontorsmöbler, paneler och\ninredningar.\n\nTelefon: 700. — Akt.-kap.: 15,000 kr.\nAntal industriarb.: 50. Tillv.-värde pr år:\n480,000 kr. — Fabriken anlagd 1917, nuv.\nbolag 1933.\n\nDisp.: John Tapper.\n\n\"AB. Nyköpings Storhusqvarn,\n\nNyköping.\n\nValskvarn. Tillverkar råg- och\nvetemjöl.\n\nTelegr.-adr.: Storhusqvarn, Nyköping.\nTelefon: 360. Postgiro: 10287.\n\nAkt.-kap.: 600,000 kr. Antal\nindustriarb.: 19. Prod.-värde pr år: 2,000,000 kr.\n— Bolaget grundat 1888.\n\nStyrelse: v. konsul Carl Nilsson\n(ordf.), dir. Hj. Carlborn, kontorschef\nTeodor Ceder, dir. Sidney Holm,\nciviling. Gunnar Molin.\n\nVerkst. dir.: Hj. Carlborn.",
    "structured": {
        "1": {
            "name": "D. Nyqvist, Ljungby Trikåindustri",
            "location": "Ljungby",
            "business": "Trikåindustri",
            "contact": {
                "office": "Ljungby",
                "telegraph": "Aena, Nyköping"
            },
            "financials": {
                "capital": "1,500,000 kr",
                "employees": {
                    "industriarb": 150
                }
            },
            "foundation_year": 1937,
            "board": [
                {
                    "name": "dir. Wilhelm Josephson",
                    "role": "ordf."
                },
                {
                    "name": "dir. Gunnar K. H. Andersson",
                    "role": ""
                },
                {
                    "name": "adv. C. M. Fallenius",
                    "role": ""
                },
                {
                    "name": "bergsing. Carl J. Kjellberg",
                    "role": ""
                },
                {
                    "name": "adv. Ivar Philipson",
                    "role": ""
                }
            ],
            "manager": "C. J. Kjellberg",
            "sales_manager": "Arne Granström"
        },
        "2": {
            "name": "Nyköpings Bryggeri AB.",
            "location": "Nyköping",
            "business": "Bryggeri",
            "contact": {
                "telephone": "Bryggeribolaget",
                "postgiro": "11777"
            },
            "financials": {
                "capital": "450,000 kr",
                "employees": {
                    "industriarb": 40
                },
                "annual_turnover": "1,400,000 kr"
            },
            "foundation_year": 1905,
            "board": [
                {
                    "name": "dir. Otto Lindeberg",
                    "role": "ordf."
                },
                {
                    "name": "disp. Carl Axel Anderson",
                    "role": ""
                },
                {
                    "name": "dir. Bure Holmbäck",
                    "role": ""
                }
            ],
            "manager": "Carl Axel Anderson"
        },
        "3": {
            "name": "AB. Nyköpings Ekmöbelfabrik",
            "location": "Nyköping",
            "business": "Ekmöbelfabrik",
            "contact": {
                "telephone": "292",
                "postgiro": "28356"
            },
            "financials": {
                "capital": "52,900 kr",
                "employees": {
                    "industriarb": 22
                },
                "annual_production_value": "220,000 kr"
            },
            "foundation_year": 1909,
            "manager": "Carl Johan Johansson"
        },
        "4": {
            "name": "Nyköpings Entreprenad AB.",
            "location": "Nyköping",
            "business": "Byggnadsentreprenörfirma",
            "contact": {
                "telegraph": "Neab, Nyköping",
                "telephone": "Entreprenadbolaget",
                "postgiro": "70821"
            },
            "financials": {
                "capital": "75,000 kr",
                "annual_production_value": "3,000,000 kr"
            },
            "foundation_year": 1945,
            "board": [
                {
                    "name": "adv. Herman Heilborn",
                    "role": "ordf."
                },
                {
                    "name": "disp. Carl-Axel Andersson",
                    "role": ""
                },
                {
                    "name": "ing. Thage Andersson",
                    "role": ""
                }
            ],
            "manager": "Thage Andersson"
        },
        "5": {
            "name": "AB. Nyköpings Culdlistfabrik",
            "location": "Nyköping",
            "business": "Tillverkning av fotografiramar",
            "contact": {
                "telephone": "1661",
                "postgiro": "132498",
                "stockholm_representative": {
                    "company": "Herm. Bornemann AB.",
                    "telephone": "112730"
                }
            },
            "financials": {
                "capital": "25,000 kr",
                "annual_production_value": "550,000 kr"
            },
            "foundation_year": 1939,
            "manager": "Hilmer A. Andersson"
        },
        "6": {
            "name": "Nyköpings Metallfabriks AB.",
            "location": "Nyköping",
            "business": "Tillverkning av metallinredningar",
            "contact": {
                "telephone": "114",
                "postgiro": "26136"
            },
            "financials": {
                "capital": "30,000 kr",
                "employees": {
                    "industriarb": 21
                },
                "annual_production_value": "120,000 kr"
            },
            "foundation_year": 1921,
            "manager": "Göte Blomdahl"
        },
        "7": {
            "name": "Nyköpings Nya Möblerings AB.",
            "location": "Nyköping",
            "business": "Möbelfabrik",
            "contact": {
                "telephone": "700"
            },
            "financials": {
                "capital": "15,000 kr",
                "employees": {
                    "industriarb": 50
                },
                "annual_production_value": "480,000 kr"
            },
            "foundation_year": 1933,
            "manager": "John Tapper"
        },
        "8": {
            "name": "AB. Nyköpings Storhusqvarn",
            "location": "Nyköping",
            "business": "Valskvarn",
            "contact": {
                "telegraph": "Storhusqvarn, Nyköping",
                "telephone": "360",
                "postgiro": "10287"
            },
            "financials": {
                "capital": "600,000 kr",
                "employees": {
                    "industriarb": 19
                },
                "annual_production_value": "2,000,000 kr"
            },
            "foundation_year": 1888,
            "board": [
                {
                    "name": "v. konsul Carl Nilsson",
                    "role": "ordf."
                },
                {
                    "name": "dir. Hj. Carlborn",
                    "role": ""
                },
                {
                    "name": "kontorschef Teodor Ceder",
                    "role": ""
                },
                {
                    "name": "dir. Sidney Holm",
                    "role": ""
                },
                {
                    "name": "civiling. Gunnar Molin",
                    "role": ""
                }
            ],
            "manager": "Hj. Carlborn"
        }
    }
}