{
    "original": "Brödenia\n\n\" Bröderna Sterner, Leksand:\n\nTillverkar skogs- och sportkängor samt\nvandrarskor vid fabrik i Leksand\n(Kopparb. l.). Firman driver även handel med\nhudar och skinn.\n\nTelefon: 123 o. 456. Postgiro: 91923.\n\n—\tAntal industriarb.: 57. Tillv.-värde pr\når: 1,400,000 kr. — Firman etabl. 1928.\n\nÄgare o. chefer: fabr. Johan Sterner\n\n0.\tfabr. Fredrik Sterner.\n\n*\tBröderna Styrenius Stenhuggeri AB.,\n\nVästervik.\n\nStenbrott i Törnsfall och Lofta (båda i\nKalmar l.), stenhuggeri och sliperi i\nVästervik. Tillverkar såsom specialitet\ngravvårdar av svart granit.\n\nTelefon: 91. Postgiro: 6083. —\nAkt.-kap.: 110,000 kr. Antal industriarb.: 65.\nProd.-värde pr år: 750,000 kr. — Firman\netabl. 1897, bolag 1913.\n\nStyrelse: fru Elna Anderson, dir. David\nStyrenius, disp. Erik Styrenius, kamrer\nJosef Styrenius, fabr. Olof Styrenius.\nDisp.: Erik Styrenius.\n\n*\tBröderna Svenson, Svenljunga.\n\nSågverk och hyvleri i Mobacka,\nSvenljunga (Älvsb. l.). Tillverkar sågade och\nhyvlade trävaror. Firman driver även\njordbruk och skogshantering.\n\nTelefon: 1015. — Antal industriarb.:\n20. Årstillv.: 130,000 kbf trävaror. —\nFirman etabl. 1922.\n\nÄgare o. chefer: trävaruhandl. Ragnar\nSvenson o. trävaruhandl. Jerker Svenson.\n\nAB. Bröderna Svenssons\nStenhuggeri, Emmaboda.\n\nStenhuggeri och stensliperi i\nEmmaboda (Kalmar l.) och Nättraby (Blekinge\n\n1.),\tstenbrott i Snöfleboda pr Vilshult\n(Blekinge l.) samt i Bondeskog pr Skruf\n(Kronob. l.). Tillverkar som specialiteter\ngravvårdar och askurnor.\n\nTelegr.-adr.: Monumentsten,\nEmmaboda. Telefon: 22 o. 225. Postgiro: 22489.\n\n—\tAkt.-kap.: 85,000 kr. Antal\nindustriarb.: 55. Tillv.-värde pr år: 800,000 kr.\n\n—\tFirman etabl. 1907, bolag 1927.\nStyrelse: disp. Gustaf A. Swedeborg\n\n(ordf.), kassörska Seri Philipsson, fabr.\nArvid Svensson.\n\nDisp.: G. A. Swedeborg.\n\n*\tBröderna Söderbergs Metallgjuteri,\n\nEskilstuna.\n\nMetallgjuteri och mek. verkstad. Utför\ngjutningar i metall och aluminium i så-\n\n6\n\nväl sand som kokill. Tillverkar\nmaskindelar i speciallegeringar (»Sicobrons»,\n»Argal» samt »Ceraluminer»),\naffärsm-redningar av lättmetall, förkromat\nnysilver, rostfritt material för charkuterier\noch konditorier samt båt- och\nbyggnadsbeslag. Varumärke: »BSM».\n\nTelegr.-adr.: Metallgjuteriet,\nEskilstuna. Telefon: »Bröderna Söderberg».\nPostgiro: 10709.\n\nAntal industriarb.: 185. Tillv.-värde pr\når: 3,500,000 kr. — Firman etabl. 1905.\n\nÄgare o. chef: fabr. Carl N. Söderberg.\n\nKamrer: Eric G. Andersson.\n\nGjuteriing.: R. Jernell.\n\nVerkstadsing.: G. B. Westerfeldt.\n\nAB. Bröderna Thörner, Kumla.\n\nTillverkar durksydda och sandalsydda\nskodon.\n\nTelefon: 70371. Postgiro: 24868. —\nAkt.-kap.: 50,000 kr. Antal industriarb.:\n40. Tillv.-värde pr år: 300,000 kr. —\nFirman etabl. 1927, bolag 1945.\n\nVerkst. direktörer: fabr. Theodor\nThor-ner o. fabr. Ragnar Thörner.\n\nBröderna Timander, Lastad.\n\nSågverk och hyvleri i Böja, Låstad\n(Skarab. l.). Tillverkar sågade och\nhyvlade trävaror. Firman driver även\njordbruk och skogshantering.\n\nTelefon: Låstadby 4. Postgiro: 97313.\n— Antal industriarb.: 25. Tillv.-värde pr\når: 350,000 kr. — Sågverket anlagt 1922.\n\nÄgare o. chefer: sågverksäg. Birger\nTimander o. sågverksäg. Valdemar\nTimander.\n\n*AB. Bröderna Troedson, Bjärnum.\n\nMöbelfabrik och sågverk i Bjärnum\n(Kristianst. l.). Tillverkar\nstandardbokhyllor, enrums- och sovrumsmöbler,\nköksmöbler samt sågade trävaror.\n\nTelefon: 3. Postgiro: 94138. —\nAkt.-kap.: 42,000 kr. Antal industriarb.: 25.\nTillv.-värde för möbler: 275,000 kr. —\nFirman etabl. 1900, nuv. bolag 1938,\n\nStyrelse: disp. Ernst Troedson (ordf.),\nadv. Tage Troedson.\n\nDisp.: Ernst Troedson.\n\nBröderna Tysklind AB., Insjön.\n\nFiskredskapsfabrik vid Insjön\n(Kopparb. l.). Tillverkar fisknät, ryssjor,\nno-tar, håvar, kräftredskap, fiskmjärdar\n(märke: »Galvano») samt\nsportfiskeredskap.",
    "structured": {
        "firms": [
            {
                "name": "Bröderna Sterner",
                "location": "Leksand",
                "business": "Tillverkar skogs- och sportkängor samt vandrarskor vid fabrik i Leksand (Kopparb. l.). Firman driver även handel med hudar och skinn.",
                "contact": {
                    "phone": [
                        "123",
                        "456"
                    ],
                    "postgiro": "91923"
                },
                "financials": {
                    "employees": {
                        "industriarb": 57
                    },
                    "annual_production_value": "1,400,000 kr",
                    "foundation_year": 1928
                },
                "owners": [
                    "fabr. Johan Sterner",
                    "fabr. Fredrik Sterner"
                ]
            },
            {
                "name": "Bröderna Styrenius Stenhuggeri AB.",
                "location": "Västervik",
                "business": "Stenbrott i Törnsfall och Lofta (båda i Kalmar l.), stenhuggeri och sliperi i Västervik. Tillverkar såsom specialitet gravvårdar av svart granit.",
                "contact": {
                    "phone": "91",
                    "postgiro": "6083"
                },
                "financials": {
                    "capital": "110,000 kr",
                    "employees": {
                        "industriarb": 65
                    },
                    "annual_production_value": "750,000 kr",
                    "foundation_year": 1897,
                    "corporation_year": 1913
                },
                "board": [
                    {
                        "name": "fru Elna Anderson",
                        "role": "Styrelse"
                    },
                    {
                        "name": "dir. David Styrenius",
                        "role": "Styrelse"
                    },
                    {
                        "name": "disp. Erik Styrenius",
                        "role": "Styrelse"
                    },
                    {
                        "name": "kamrer Josef Styrenius",
                        "role": "Styrelse"
                    },
                    {
                        "name": "fabr. Olof Styrenius",
                        "role": "Styrelse"
                    },
                    {
                        "name": "Erik Styrenius",
                        "role": "Disp."
                    }
                ]
            },
            {
                "name": "Bröderna Svenson",
                "location": "Svenljunga",
                "business": "Sågverk och hyvleri i Mobacka, Svenljunga (Älvsb. l.). Tillverkar sågade och hyvlade trävaror. Firman driver även jordbruk och skogshantering.",
                "contact": {
                    "phone": "1015"
                },
                "financials": {
                    "employees": {
                        "industriarb": 20
                    },
                    "annual_turnover": "130,000 kbf trävaror",
                    "foundation_year": 1922
                },
                "owners": [
                    "trävaruhandl. Ragnar Svenson",
                    "trävaruhandl. Jerker Svenson"
                ]
            },
            {
                "name": "AB. Bröderna Svenssons Stenhuggeri",
                "location": "Emmaboda",
                "business": "Stenhuggeri och stensliperi i Emmaboda (Kalmar l.) och Nättraby (Blekinge 1.), stenbrott i Snöfleboda pr Vilshult (Blekinge l.) samt i Bondeskog pr Skruf (Kronob. l.). Tillverkar som specialiteter gravvårdar och askurnor.",
                "contact": {
                    "telegraph": "Monumentsten, Emmaboda",
                    "phone": [
                        "22",
                        "225"
                    ],
                    "postgiro": "22489"
                },
                "financials": {
                    "capital": "85,000 kr",
                    "employees": {
                        "industriarb": 55
                    },
                    "annual_production_value": "800,000 kr",
                    "foundation_year": 1907,
                    "corporation_year": 1927
                },
                "board": [
                    {
                        "name": "disp. Gustaf A. Swedeborg",
                        "role": "Styrelse"
                    },
                    {
                        "name": "kassörska Seri Philipsson",
                        "role": "Styrelse"
                    },
                    {
                        "name": "fabr. Arvid Svensson",
                        "role": "Styrelse"
                    },
                    {
                        "name": "G. A. Swedeborg",
                        "role": "Disp."
                    }
                ]
            },
            {
                "name": "Bröderna Söderbergs Metallgjuteri",
                "location": "Eskilstuna",
                "business": "Metallgjuteri och mek. verkstad. Utför gjutningar i metall och aluminium i såväl sand som kokill. Tillverkar maskindelar i speciallegeringar (»Sicobrons», »Argal» samt »Ceraluminer»), affärsm-redningar av lättmetall, förkromat nysilver, rostfritt material för charkuterier och konditorier samt båt- och byggnadsbeslag. Varumärke: »BSM».",
                "contact": {
                    "telegraph": "Metallgjuteriet, Eskilstuna",
                    "phone": "Bröderna Söderberg",
                    "postgiro": "10709"
                },
                "financials": {
                    "employees": {
                        "industriarb": 185
                    },
                    "annual_production_value": "3,500,000 kr",
                    "foundation_year": 1905
                },
                "owners": [
                    "fabr. Carl N. Söderberg"
                ],
                "board": [
                    {
                        "name": "Eric G. Andersson",
                        "role": "Kamrer"
                    },
                    {
                        "name": "R. Jernell",
                        "role": "Gjuteriing."
                    },
                    {
                        "name": "G. B. Westerfeldt",
                        "role": "Verkstadsing."
                    }
                ]
            },
            {
                "name": "AB. Bröderna Thörner",
                "location": "Kumla",
                "business": "Tillverkar durksydda och sandalsydda skodon.",
                "contact": {
                    "phone": "70371",
                    "postgiro": "24868"
                },
                "financials": {
                    "capital": "50,000 kr",
                    "employees": {
                        "industriarb": 40
                    },
                    "annual_production_value": "300,000 kr",
                    "foundation_year": 1927,
                    "corporation_year": 1945
                },
                "owners": [
                    "fabr. Theodor Thörner",
                    "fabr. Ragnar Thörner"
                ]
            },
            {
                "name": "Bröderna Timander",
                "location": "Lastad",
                "business": "Sågverk och hyvleri i Böja, Låstad (Skarab. l.). Tillverkar sågade och hyvlade trävaror. Firman driver även jordbruk och skogshantering.",
                "contact": {
                    "phone": "Låstadby 4",
                    "postgiro": "97313"
                },
                "financials": {
                    "employees": {
                        "industriarb": 25
                    },
                    "annual_production_value": "350,000 kr"
                },
                "owners": [
                    "sågverksäg. Birger Timander",
                    "sågverksäg. Valdemar Timander"
                ]
            },
            {
                "name": "AB. Bröderna Troedson",
                "location": "Bjärnum",
                "business": "Möbelfabrik och sågverk i Bjärnum (Kristianst. l.). Tillverkar standardbokhyllor, enrums- och sovrumsmöbler, köksmöbler samt sågade trävaror.",
                "contact": {
                    "phone": "3",
                    "postgiro": "94138"
                },
                "financials": {
                    "capital": "42,000 kr",
                    "employees": {
                        "industriarb": 25
                    },
                    "annual_production_value": "275,000 kr",
                    "foundation_year": 1900,
                    "corporation_year": 1938
                },
                "board": [
                    {
                        "name": "disp. Ernst Troedson",
                        "role": "Styrelse"
                    },
                    {
                        "name": "adv. Tage Troedson",
                        "role": "Styrelse"
                    },
                    {
                        "name": "Ernst Troedson",
                        "role": "Disp."
                    }
                ]
            },
            {
                "name": "Bröderna Tysklind AB.",
                "location": "Insjön",
                "business": "Fiskredskapsfabrik vid Insjön (Kopparb. l.). Tillverkar fisknät, ryssjor, no-tar, håvar, kräftredskap, fiskmjärdar (märke: »Galvano») samt sportfiskeredskap.",
                "financials": {
                    "employees": {
                        "industriarb": 0
                    },
                    "foundation_year": 0
                }
            }
        ]
    }
}