{
    "original": "Midnäs—Minnesb e rg\n\nliar 1945 i sig upptagit f. d. Fahléns\nEtui-«&amp; Kartongfabrik, Gnesta.\n\nÄgare: grossh. Vilh. Meyer\n(Södertälje).\n\nFabrikschef: Gunnar Fahlén.\n* Midnäs Industri AB., Bollnäs.\n\nSågverk, hyvleri och wallboardfabrik\nwiå Höjen, Rengsjö (Gävleb. l.).\nTillverkar sågade och hyvlade trävaror samt\nträfiberplattor. Varumärke: »Fibrex».\n\nKontor: Rengsjö, Bollnäs. Telegr.-adr.\no. telefon: Midnäs, Bollnäs. Postgiro:\n76441.\n\nRepresentanter: AB. Varjag,\nStockholm, Kungsg. 27, telefon: 207926; AB.\nOubic, Hagalund, telefon: Stockholm\n274300; för södra Sverige o. Danmark:\nAB. N. Johnson &amp; Co., Eslöv, telefon:\n»Johnson &amp; Co».\n\nAkt.-kap.: 200,000 kr. Antal\nindustriarb.: vid sågverket: 55; vid\nwallboard-fabriken: 155. Årstillv.: 2,500 stds\nsågade och hyvlade trävaror, 12,000 ton\nwallboard. — Bolaget grundat 1928 under\nmamn Midnäs Nya Trävaru AB., nuv.\nnamn 1946.\n\nStyrelse: bankdir. Erik Stenberg\n(ordf.), landsfiskal E. G. Bjöörn, förvalt.\nH. Freudenthal, bruksförvalt. W. E.\nFreu-denthal, dir. John R. Jonsson.\n\nVerkst. dir. o. disp.: John R. Jonsson.\n\nKamrer: Konrad Jonsson.\n\nDriftsing. o. fabrikschef: ing. Arne\nJonsson.\n\n(Jfr annons nr 92.)\n\nAB. Mikro-Verktyg, Södertälje.\n\nMek. verkstad i Södertälje (Sthlms l.).\nTillverkar precisionsverktyg, såsom\nkontrollverktyg, mätverktyg, passbitsmått,\ntolkar, jiggar, formstål, mallar och\nfix-turer samt pressverktyg,\npressgjutnings-verktyg, bakelitverktyg och\ntablettverktyg.\n\nTelefon: 31103 o. 31106. Postgiro:\n31113. — Akt.-kap.: 12,000 kr. Antal\nin-dustriarb.: 30. Tillv.-värde pr år: 250,000\nkr. — Bolaget grundat 1943.\n\nVerkst. dir.: Sven Gustafson.\n\nKamrer: Göte Wirenhed.\n\nDriftsing.: Gunnar Gustavson.\n\n*Mildens Elektr. Motor AB.,\n\nSpånga.\n\nMek. verkstad i Spånga (Stockholms l.).\nTillverkar elektr. borr- och slipmaskiner,\nmotorer samt specialmaskiner för elektr.\ndrift; utför mekaniska arbeten.\nVarumärke : » Mema ».\n\n511*\n\nTelegr.-adr.: Mema, Stockholm.\nTelefon: Stockholm 362397—98 o. 362409.\nPostgiro: 3058.\n\nAkt.-kap.: 84,000 kr. Antal\nindustriarb.: 50. Tillv.-värde pr år: 900,000 kr.\n— Firman etabl. 1902 under namn Mek.\nVerkstaden Fram, bolag 1925.\n\nStyrelse: adv. Knut Strömberg (ordf.),\nadv. Ragnar Gottfarb, ing. Harry\nMil-den.\n\nVerkst. dir.: Harry Milden.\n\nMiles &amp; Warnberg AB.,\n\nGöteborg.\n\nLädervaru- och reseffektfabrik.\nTillverkar damväskor, plånböcker och\nportföljer. Varumärke: »Miwa».\n\nKontor: Stadsskrivareg. 3. Telegr.-adr.:\nMiwabags, Göteborg. Telefon: 194812—\n13. Postgiro: 41454.\n\nAkt.-kap.: 44,500 kr. Antal\nindustriarb.: 75. Tillv.-värde pr år: 1,500,000 kr.\n— Firman etabl. 1923, bolag 1939.\n\nVerkst. dir.: Ingvar Warnberg.\n\nMiller, Bröderna, Bankeryd.\nSe Bröderna Miller, Bankeryd.\n\n*Millers Stämplar, Sunne.\n\nTillverkar dessinvalsar för anilin- och\noljefärgstryck, gummiklichéer för\nanilin-och boktryck, zinkklichéer samt stämplar\noch stämpelfärger vid stämpelfabrik o.\nklichéanstalt i Sunne (Värml. l.).\n\nTelefon: 294. Postgiro: 70028. —\nArb.-antal: 9. — Firman etabl. 1932.\n\nÄgare o. chefer: fabr. Gösta E:son\nMiller o. fabr. Erik Thorell.\n\n* Minnesbergs Tegelbruks AB.,\n\nMinnesberg.\n\nTillverkar tegel, alla slag,\nreveterings-plattor och dräneringsrör vid tre fabriker\ni Minnesberg (Malmöh. l.) samt utför\nskorstensbyggen. Specialiteter: glaserat\noch rött taktegel, handslaget fasad- och\nfasontegel.\n\nTelegr.-adr.: Minnesberg, Svedala.\nTelefon: Svedala 36 o. 636. Postgiro: 96166.\nRepresentanter: i Stockholm: C. Gottfrid\nRystedt, AB., Vasag. 38, telefon: 232700;\ni Göteborg: Söderberg &amp; Haak AB.,\nCentralposthuset, telefon: »Söderberg—\nyj a ak »\n\nAkt.-kap.: 700,000 kr. Antal\nindustriarb.: 80. Tillv.-värde pr år: 700,000 kr.\n— Bolaget grundat 1888.",
    "structured": {
        "1": {
            "name": "Midnäs Industri AB",
            "location": "Bollnäs",
            "business": "Sågverk, hyvleri och wallboardfabrik",
            "products": "Tillverkar sågade och hyvlade trävaror samt träfiberplattor. Varumärke: »Fibrex».",
            "contact": {
                "office": "Rengsjö, Bollnäs",
                "phone": [
                    "Midnäs, Bollnäs"
                ],
                "postgiro": "76441",
                "sales_offices": [
                    {
                        "location": "Stockholm",
                        "phone": "207926"
                    },
                    {
                        "location": "Hagalund",
                        "phone": "Stockholm 274300"
                    }
                ]
            },
            "financials": {
                "capital": "200,000 kr",
                "employees": {
                    "vid sågverket": 55,
                    "vid wallboard-fabriken": 155
                },
                "annual_turnover": "2,500 stds sågade och hyvlade trävaror, 12,000 ton wallboard"
            },
            "foundation_year": 1928,
            "current_name_year": 1946,
            "board": [
                {
                    "name": "Erik Stenberg",
                    "role": "bankdir."
                },
                {
                    "name": "E. G. Bjöörn",
                    "role": "landsfiskal"
                },
                {
                    "name": "H. Freudenthal",
                    "role": "förvalt."
                },
                {
                    "name": "W. E. Freudenthal",
                    "role": "bruksförvalt."
                },
                {
                    "name": "John R. Jonsson",
                    "role": "dir."
                }
            ]
        },
        "2": {
            "name": "AB. Mikro-Verktyg",
            "location": "Södertälje",
            "business": "Mek. verkstad",
            "products": "Tillverkar precisionsverktyg, såsom kontrollverktyg, mätverktyg, passbitsmått, tolkar, jiggar, formstål, mallar och fixturer samt pressverktyg, pressgjutningsverktyg, bakelitverktyg och tablettverktyg.",
            "contact": {
                "phone": [
                    "31103",
                    "31106"
                ],
                "postgiro": "31113"
            },
            "financials": {
                "capital": "12,000 kr",
                "employees": 30,
                "annual_turnover": "250,000 kr"
            },
            "foundation_year": 1943,
            "manager": "Sven Gustafson"
        },
        "3": {
            "name": "Mildens Elektr. Motor AB.",
            "location": "Spånga",
            "business": "Mek. verkstad",
            "products": "Tillverkar elektr. borr- och slipmaskiner, motorer samt specialmaskiner för elektr. drift.",
            "contact": {
                "telegraph": "Mema, Stockholm",
                "phone": "Stockholm 362397—98 o. 362409",
                "postgiro": "3058"
            },
            "financials": {
                "capital": "84,000 kr",
                "employees": 50,
                "annual_turnover": "900,000 kr"
            },
            "corporation_year": 1925,
            "board": [
                {
                    "name": "Knut Strömberg",
                    "role": "adv."
                },
                {
                    "name": "Ragnar Gottfarb",
                    "role": "adv."
                },
                {
                    "name": "Harry Milden",
                    "role": "ing."
                }
            ],
            "director": "Harry Milden"
        },
        "4": {
            "name": "Miles &amp; Warnberg AB.",
            "location": "Göteborg",
            "business": "Lädervaru- och reseffektfabrik",
            "products": "Tillverkar damväskor, plånböcker och portföljer. Varumärke: »Miwa».",
            "contact": {
                "office": "Stadsskrivareg. 3",
                "phone": [
                    "194812—13"
                ],
                "postgiro": "41454"
            },
            "financials": {
                "capital": "44,500 kr",
                "employees": 75,
                "annual_turnover": "1,500,000 kr"
            },
            "director": "Ingvar Warnberg"
        },
        "5": {
            "name": "Millers Stämplar",
            "location": "Sunne",
            "business": "Tillverkar dessinvalsar för anilin- och oljefärgstryck, gummiklichéer för anilin- och boktryck, zinkklichéer samt stämplar och stämpelfärger",
            "contact": {
                "phone": "294",
                "postgiro": "70028"
            },
            "employees": 9,
            "owners": [
                "fabr. Gösta E:son Miller",
                "fabr. Erik Thorell"
            ]
        },
        "6": {
            "name": "Minnesbergs Tegelbruks AB.",
            "location": "Minnesberg",
            "business": "Tillverkar tegel, alla slag, reveteringsplattor och dräneringsrör samt utför skorstensbyggen. Specialiteter: glaserat och rött taktegel, handslaget fasad- och fasontegel.",
            "contact": {
                "telegraph": "Minnesberg, Svedala",
                "phone": [
                    "Svedala 36 o. 636"
                ],
                "postgiro": "96166"
            },
            "financials": {
                "capital": "700,000 kr",
                "employees": 80,
                "annual_turnover": "700,000 kr"
            },
            "foundation_year": 1888
        }
    }
}