{
    "original": "Ödeshög—Öland\n\nAB. Ödeshögs Snickerifabrik,\n\nÖdeshög.\n\nTillverkar byggnadssnickerier vid\nfabrik i ödeshög (Östergötl. l.).\n\nTelefon: 19. Postgiro; 70528. —\nAkt.-kap.: 50,000 kr. Antal industriarb.: 20.\nTillv.-värde pr år: 335,000 kr. — Bolaget\ngrundat 1917.\n\nDisp.: Henrik Arvidsson.\n\nÖdeshögsverken AB., ödeshög.\n\nMek. verkstad, plåtslageri och\ntack-järnsgjuteri i Ödeshög (Östergötl. l.).\n\nTillverkar transport anläggningar,\njärnkonstruktioner, grovplåtsarbeten,\ntackjärns- och kokillgjutgods, trä- och\nmetallmodeller m. m. Specialiteter:\nremtransportörer, skopelevatorer, transport- och\ntippvagnar, lastfickor, stapelapparater\noch betongblandare.\n\nTelegr.-adr.: överken, Ödeshög.\nTelefon: »ödeshögsverken». Postgiro: 70135.\n\nAkt.-kap.: 100,000 kr. Antal\nindustriarb.: 100. Tillv.-värde pr år: 2,000,000 kr.\n\n—\tFirman etabl. 1900, bolag 1925.\n\nStyrelse: adv. H. Utterström (ordf.),\n\ning. Gunnar W. Johansson, herr Lennart\nJohansson.\n\nVerkst. dir.: Gunnar W. Johansson.\n\nVerkstadschef: H. Arvelius.\n\nKontorschef: P. Sjöberg.\n\nKonstruhtionschef: ing. G. Hellner.\n\n*Öfverums Bruk, Överum.\n\nSe AB. överums Bruk, överum.\n\nA. B. öhnbergs Konservfabrik,\n\nLysekil.\n\nTillverkar ansjovis, sillinläggningar och\nkaviar. Varumärken: Ejdern, Ejdersill,\nDrott o. Florett.\n\nTelegr.-adr.: Ejdern, Lysekil. Telefon:\n55. Postgiro: 36062. — Antal\nindustriarb.: 15. Tillv.-värde pr år: 450,000 kr.\n\n—\tFirman etabl. 1898.\n\nÄgare: fru Charlotta öhnberg.\n\nFöreståndare: Johan öhnberg.\n\nPatrik Öhnbergs Konservfabrik,\n\nLysekil.\n\nTillverkar ansjovis och\nsillinläggningar, kaviar, sardiner m. m. Varumärken:\n»Riddaren», »Husmodern» o. »Polo».\n\nTelefon: 131. Postgiro: 72932. —\nAntal industriarb.: 15. Tillv.-värde pr år:\n300,000 kr. — Firman etabl. 1905.\n\nÄgare: Albert Anderssons sterbhus.\n\nDisp.: Hedly Ferm.\n\n\"Öhrvikens AB., Köpmanholmen.\n\nSulfitfabrik i örviken (Västerb. l.).\nTillverkar sulfitcellulosa.\n\nHuvudkontor: Köpmanholmen.\nTelegr.-adr.: Forss, Köpmanholmen. Telefon:\nKöpmanholmen 27 o. 165, Bjästa 1 o. 54,\nÖrnsköldsvik 2475. Brukskontor:\nörviken. Telegr.-adr.: öhrviken, Skellefteå.\nPostgiro: 61112.\n\nAkt.-kap.: 3,600,000 kr. Antal\nindustriarb.: 300. Årstillv.: 35,000 ton stark\nsulfitcellulosa. — Bolaget grundat 1893.\n\nStyrelse: dir. Theodor Hedberg (ordf.),,\nkapten Hj. Hedberg, dir. Oscar Hedbergs\ndir. Em. Högberg, bankdir. Ernst Åberg.\n\nVerkst. dir. o. disp.: Theodor Hedberg.\n\növering.: Birger Everitt.\n\n\"Ölands Cement A Degerhamn.\n\nCementfabrik, kalkstensbrott och\nkalkbruk samt mek. verkstad för eget\nbehov vid Degerhamn å Öland (Kalmar\n1.). Tillverkar standardportlandcement,.\n\nE-cement, osläekt och släckt kalk, osläckt.\nmålen säckkalk samt släckt murkalk.\n\nKontor: Degerhamn. Telegr.-adr.:\nInsula, Degerhamn. Telefon: Degerhamn 2„\n4 o. 77. Postgiro: 11302. Ensamförsälj. för\ncement: Cementa, Svenska Cement\nFörsäljnings AB., Malmö (se detta bolag).\n\nAkt.-kap.: 1,687,500 kr. Antal\nindustriarb.: 170. Tillv.-värde pr år: 5,000,000 kr.\n—- Fabriken anlagd 1887, nuv. bolag 1916.\n\nStyrelse: frih. Erik Stiernstedt (ordf.)„\nrevisor Arne Henrikson, fil. dr Fr.\nKil-lig, dir. Malte Ström, civiling.\nCarl-Gustaf Toll, dir. Ernst Wehtje.\n\nVerkst. dir.: Fr. Killig.\n\nÖlands Ytong AB., Ventlinge.\n\nTillverkar lättbetong (»Ytong») samt\nbränd kalk för jordbruks- och\nbyggnadsändamål vid lättbetongfabrik och\nkalkbränner i i Ventlinge, Oland (Kalmar l.).\n\nTelefon: Grönhögen 49 o. 50. Postgiror\n165270. Repr. i Stockholm: Yxhults\nFör-säljn.-AB., Lagerlöfsg. 4, telefon: 520915.\n\nAkt.-kap.: 500,000 kr. Antal\nindustriarb.: 170. Prod.-värde pr år: 3,000,000 kr.\n— Bolaget grundat 1939 under namn\nÖlands Gasbetong AB., nuv. namn 1946.\n\nStyrelse: dir. C. Aug. Carlén (ordf.),,\ning. Bertil Carlén, disp. Erik Carlén,.\növering. Birger Sundfeldt, ing. Ernst\nWranne.\n\nVerkst. dir.: Bertil Carlén\n(Hällabrottet).\n\nDisp. o. driftsing.: Ebbe Bäck.",
    "structured": {
        "1": {
            "name": "AB. Ödeshögs Snickerifabrik",
            "location": "Ödeshög",
            "business": "Tillverkning av byggnadssnickerier",
            "products": "Byggnadssnickerier",
            "contact": {
                "office": "Ödeshög",
                "phone": [
                    "19"
                ],
                "postgiro": "70528",
                "head_office": "Ödeshög",
                "telegraph": "",
                "factory_office": "Ödeshög",
                "factory_phone": ""
            },
            "financials": {
                "capital": "50,000 kr",
                "employees": {
                    "industriarb": 20
                },
                "annual_turnover": "",
                "annual_production_value": "335,000 kr"
            },
            "foundation_year": 1917
        },
        "2": {
            "name": "Ödeshögsverken AB.",
            "location": "Ödeshög",
            "business": "Mekanisk verkstad, plåtslageri och tack-järnsgjuteri",
            "products": "Transportanläggningar, järnkonstruktioner, grovplåtsarbeten, tackjärnsgjutgods, trä- och metallmodeller",
            "contact": {
                "office": "Ödeshög",
                "phone": [
                    "ödeshögsverken"
                ],
                "postgiro": "70135",
                "head_office": "",
                "sales_offices": [],
                "telegraph": "överken, Ödeshög",
                "factory_office": "",
                "factory_phone": ""
            },
            "financials": {
                "capital": "100,000 kr",
                "employees": {
                    "industriarb": 100
                },
                "annual_turnover": "",
                "annual_production_value": "2,000,000 kr"
            },
            "foundation_year": 1900,
            "corporation_year": 1925,
            "board": [
                {
                    "name": "adv. H. Utterström",
                    "role": "ordf."
                },
                {
                    "name": "ing. Gunnar W. Johansson",
                    "role": ""
                },
                {
                    "name": "herr Lennart Johansson",
                    "role": ""
                }
            ],
            "director": "",
            "sales_manager": "",
            "manager": ""
        },
        "3": {
            "name": "A. B. öhnbergs Konservfabrik",
            "location": "Lysekil",
            "business": "Tillverkning av ansjovis, sillinläggningar och kaviar",
            "products": "Ansjovis, sillinläggningar, kaviar",
            "contact": {
                "office": "Lysekil",
                "phone": [
                    "55"
                ],
                "postgiro": "36062",
                "head_office": "",
                "sales_offices": [],
                "telegraph": "Ejdern, Lysekil",
                "factory_office": "",
                "factory_phone": ""
            },
            "financials": {
                "capital": "",
                "employees": {},
                "annual_turnover": "",
                "annual_production_value": "450,000 kr"
            },
            "foundation_year": 1898,
            "owners": [
                "fru Charlotta öhnberg"
            ],
            "director": "",
            "sales_manager": "",
            "manager": ""
        },
        "4": {
            "name": "Patrik Öhnbergs Konservfabrik",
            "location": "Lysekil",
            "business": "Tillverkning av ansjovis, sillinläggningar, kaviar, sardiner",
            "products": "Ansjovis, sillinläggningar, kaviar, sardiner",
            "contact": {
                "office": "Lysekil",
                "phone": [
                    "131"
                ],
                "postgiro": "72932",
                "head_office": "",
                "sales_offices": [],
                "telegraph": "",
                "factory_office": "",
                "factory_phone": ""
            },
            "financials": {
                "capital": "",
                "employees": {},
                "annual_turnover": "",
                "annual_production_value": "300,000 kr"
            },
            "foundation_year": 1905,
            "owners": [
                "Albert Anderssons sterbhus"
            ],
            "director": ""
        },
        "5": {
            "name": "Öhrvikens AB.",
            "location": "Köpmanholmen",
            "business": "Tillverkning av sulfitcellulosa",
            "products": "Sulfitcellulosa",
            "contact": {
                "office": "Köpmanholmen",
                "phone": [
                    "Köpmanholmen 27",
                    "165",
                    "Bjästa 1",
                    "54",
                    "Örnsköldsvik 2475"
                ],
                "postgiro": "61112",
                "head_office": "Köpmanholmen",
                "sales_offices": [
                    {
                        "location": "Örnsköldsvik",
                        "phone": ""
                    }
                ],
                "telegraph": "Forss, Köpmanholmen",
                "factory_office": "örviken",
                "factory_phone": ""
            },
            "financials": {
                "capital": "3,600,000 kr",
                "employees": {
                    "industriarb": 300
                },
                "annual_turnover": "",
                "annual_production_value": "35,000 ton stark sulfitcellulosa"
            },
            "foundation_year": 1893,
            "board": [
                {
                    "name": "dir. Theodor Hedberg",
                    "role": "ordf."
                },
                {
                    "name": "kapten Hj. Hedberg",
                    "role": ""
                },
                {
                    "name": "dir. Oscar Hedbergs dir. Em. Högberg",
                    "role": ""
                },
                {
                    "name": "bankdir. Ernst Åberg",
                    "role": ""
                }
            ],
            "director": ""
        },
        "6": {
            "name": "Ölands Cement A Degerhamn",
            "location": "Degerhamn",
            "business": "Tillverkning av cement, kalk och mekanisk verkstad",
            "products": "Standardportlandcement, E-cement, osläekt och släckt kalk, osläckt målkalk, släckt murkalk",
            "contact": {
                "office": "Degerhamn",
                "phone": [
                    "Degerhamn 2",
                    "4",
                    "77"
                ],
                "postgiro": "11302",
                "head_office": "",
                "sales_offices": [],
                "telegraph": "Insula, Degerhamn",
                "factory_office": "",
                "factory_phone": ""
            },
            "financials": {
                "capital": "1,687,500 kr",
                "employees": {
                    "industriarb": 170
                },
                "annual_turnover": "",
                "annual_production_value": "5,000,000 kr"
            },
            "foundation_year": 1887,
            "corporation_year": 1916,
            "board": [
                {
                    "name": "frih. Erik Stiernstedt",
                    "role": "ordf."
                },
                {
                    "name": "revisor Arne Henrikson",
                    "role": ""
                },
                {
                    "name": "fil. dr Fr. Killig",
                    "role": ""
                },
                {
                    "name": "dir. Malte Ström",
                    "role": ""
                },
                {
                    "name": "civiling. Carl-Gustaf Toll",
                    "role": ""
                },
                {
                    "name": "dir. Ernst Wehtje",
                    "role": ""
                }
            ],
            "director": ""
        },
        "7": {
            "name": "Ölands Ytong AB.",
            "location": "Ventlinge",
            "business": "Tillverkning av lättbetong och bränd kalk",
            "products": "Lättbetong, bränd kalk",
            "contact": {
                "office": "Ventlinge",
                "phone": [
                    "Grönhögen 49",
                    "50"
                ],
                "postgiro": "165270",
                "head_office": "",
                "sales_offices": [],
                "telegraph": "",
                "factory_office": "",
                "factory_phone": ""
            },
            "financials": {
                "capital": "500,000 kr",
                "employees": {
                    "industriarb": 170
                },
                "annual_turnover": "",
                "annual_production_value": "3,000,000 kr"
            },
            "foundation_year": 1939,
            "current_name_year": 1946,
            "board": [
                {
                    "name": "dir. C. Aug. Carlén",
                    "role": "ordf."
                },
                {
                    "name": "ing. Bertil Carlén",
                    "role": ""
                },
                {
                    "name": "disp. Erik Carlén",
                    "role": ""
                },
                {
                    "name": "övering. Birger Sundfeldt",
                    "role": ""
                },
                {
                    "name": "ing. Ernst Wranne",
                    "role": ""
                }
            ],
            "director": ""
        }
    }
}