{
    "original": "Andersson\n\nTelegr.-adr.: Mattfabriken, Kinna.\nTelefon: 10010 o. 10610. Postgiro: 24632.\nRepr. i Stockholm: Walther Vetterleins\nSöner, Gentralpalatset, telefon: 102686.\n\nAkt.-kap.: 650,000 kr. Antal\nindustriarb.: 135. Tillv.-värde pr år: 1,500,000 kr.\n— Firman etabl. 1889, bolag 1925.\n\nStyrelse: disp. John Thanell (ordf.),\nkontorist Erik Ludvig Anderson,\ngross-handl. Gunnar Vetterlein.\n\nDisp.: John Thanell.\n\nFörsäljn.-chef: Rudolf Melin (Borås).\n\n*N. Bernh. Anderssons Bokbinderi\n\nAB., Stockholm.\n\nTillverkar biblioteksband, lyxband,\nadresspärmar i maroquin, kalvskinn m.\nfl. skinnsorter, utför montering av\nspel-och skrivbord, pulpeter m. m.\n\nKontor: Mästersamuelsg. 23. Telefon:\n109384. Postgiro: 1639.\n\nAkt.-kap.: 50.000 kr.. Antal\nindustriarb.: 20. Tillv.-värde pr år: 140,000 kr.\n\nFirman etabl. 1887, bolag 1917.\nBolaget äges av AB. Nordiska Kompaniet.\n\nStyrelse: dir. Rudolf Kalderén, dir.\nRagnar Sachs, intendent O. Wickbom.\n\nVerkstadschef: Karl Andersson.\n\nN. E. Andersson, Malung.\n\nPälsberederi och skinnvarutillverkning\ni Malung (Kopparb. l.). Tillverkar\nmilitär-, sport- och bilpälsar, pälsmössor,\nskinntröjor och skinnkläder, handskar,\nskinnfällar och sovsäckar, tofflor av\npälslammskinn, babyskor av skinn m. m.\n\nTelefon: 15. Postgiro: 96800. — Antal\nindustriarb.: 25. Tillv.-värde pr år:\n375,000 kr. — Firman etabl. 1885.\n\nDisp. o. chef: Nygårds Anders\nEriksson.\n\n*0. Andersson, Möbelfabrik, Tihro.\n\nTillverkar möbler såsom bord, byråar,\nskåp, sekretärer, divanbord, hörnskåp och\nbokhyllor vid fabrik i Björkhamra, Tibro\n(Skarab. l.).\n\nTelefon: 478. Postgiro: 265588. —\nAntal industriarb.: 5. Tillv.-värde pr år:\n50 000 kr. — Firman etabl. 1942.\n\nÄgare o. chef:- fabr. Oskar Andersson.\n\n*R. Anderssons Snickerifabrik, Skara.\n\nTillverkar inredningssnickerier,\nfönster och dörrar, köksinredningar, trappor\nm. m.\n\nTelefon: 190. Postgiro: 266021. —\nAntal industriarb.: 7. — Firman etabl. 1924.\n\nÄgare o. chef: fabr. Ernst Rich.\nAndersson.\n\n*AB. Robert Anderssons\nKonst-svarveri, Värnamo.\n\nTillverkar svarveri artiklar och\nslöjd-alster. Specialiteter: träljusstakar,\nleksaker och handdukshängare.\n\nTelefon: 10109. Postgiro: 269988. Repr.\ni Stockhol m: Gustaf W. Jonsson AB.&gt;\nSchéeleg. 17, telefon: 530948.\t)\n\nAkt.-kap.: 60,000 kr. Antal\nindustriarb.: 25. Tillv.-värde pr år: 300,000 kr. —\nFirman etabl. 1907, bolag 1944.\n\nStyrelse: fabr. Robert Andersson,\nlagerchef Karl-Erik Aspler, kontorschef\nMauritz Svensson.\n\nVerkst. dir.: Robert Andersson.\n\n*Samuei Andersson, Tibro.\n\nTillverkar möbler vid fabrik i Tibro\n(Skarab. l.). Specialitet: björkmöbler.\n\nTelefon: 72. Postgiro: 135720. — Ant\ntal industriarb.: 13. Tillv.-värde pr år:\n290,000 kr. — Firman etabl. 1898.\n\nÄgare o. chef: fabr, Samuel\nAnders-son.\n\n*Sven Andersson, Ljungskile.\n\nTillverkar strumpor vid fabrik i\nLjungskile (Göteb. o. Bohus l.).\n\nTelesr.-adr.: Svenand, Ljungskile.\nTelefon: 32. Postgiro: 83951. — Antal\nindustriarb.: 65. — Firman etabl. 1932.\nÄgare o. chef: dir. Sven Andersson.\n\n*Th. Andersson, Dalsjöfors.\n\nTillverkar herrunderkläder i Lahmanns\noch interlockkvaliteter vid fabrik i\nDalsjöfors (Älvsb. l.).\n\nTelefon: Borås 70021. Postgiro: 91260.\nRepresentanter: i Stockholm: A. S.\nMuller, Birger Jnrlser. 55, telefon: 112906:\nGöteborg: J. E. Carlsson, Burgårdsg. 13,\ntelefon: 165177.\n\nAntal industriarb.: 20. Tillv.-värde pr\når: 300,000 kr. — Firman etabl. 19*28.\n\nÄgare o. chef: fabr. Theodor\nAndersson.\n\n*Thure Andersson, Möbelfabrik,\n\nTibro.\n\nTillverkar matsals- och\nsängkammarmöbler samt kompletteringsmöbler vid\nfabrik i Tibro (Skarab. l.).\n\nTelefon: 225. Postgiro: 85765. -\nAntal industriarb.: 15. Tillv.-värde pr år:\n250,000 kr. — Firman etabl. 1931.\n\nÄgare o. chef: fabr. Thure Andersson»",
    "structured": {
        "0": {
            "name": "Andersson",
            "contact": {
                "telegraph": "Mattfabriken, Kinna",
                "phone": [
                    "10010",
                    "10610"
                ],
                "postgiro": "24632",
                "sales_offices": [
                    {
                        "location": "Stockholm",
                        "phone": "102686"
                    }
                ]
            },
            "financials": {
                "capital": "650,000 kr",
                "employees": {
                    "industriarb": 135
                },
                "annual_turnover": "1,500,000 kr"
            },
            "foundation_year": 1889,
            "corporation_year": 1925,
            "board": [
                {
                    "name": "John Thanell",
                    "role": "disp."
                },
                {
                    "name": "Erik Ludvig Anderson",
                    "role": "kontorist"
                },
                {
                    "name": "Gunnar Vetterlein",
                    "role": "gross-handl."
                }
            ],
            "director": "John Thanell",
            "managing_director": "Rudolf Melin (Borås)"
        },
        "1": {
            "name": "N. Bernh. Anderssons Bokbinderi AB.",
            "location": "Stockholm",
            "products": "Tillverkar biblioteksband, lyxband, adresspärmar i maroquin, kalvskinn m. fl. skinnsorter, utför montering av spel-och skrivbord, pulpeter m. m.",
            "contact": {
                "office": "Mästersamuelsg. 23",
                "phone": "109384",
                "postgiro": "1639"
            },
            "financials": {
                "capital": "50,000 kr",
                "employees": {
                    "industriarb": 20
                },
                "annual_turnover": "140,000 kr"
            },
            "foundation_year": 1887,
            "corporation_year": 1917,
            "owners": [
                "AB. Nordiska Kompaniet"
            ],
            "board": [
                {
                    "name": "Rudolf Kalderén",
                    "role": "dir."
                },
                {
                    "name": "Ragnar Sachs",
                    "role": "dir."
                },
                {
                    "name": "O. Wickbom",
                    "role": "intendent"
                }
            ],
            "manager": "Karl Andersson"
        },
        "2": {
            "name": "N. E. Andersson",
            "location": "Malung",
            "products": "Pälsberederi och skinnvarutillverkning i Malung (Kopparb. l.). Tillverkar militär-, sport- och bilpälsar, pälsmössor, skinntröjor och skinnkläder, handskar, skinnfällar och sovsäckar, tofflor av pälslammskinn, babyskor av skinn m. m.",
            "contact": {
                "phone": [
                    "15"
                ],
                "postgiro": "96800"
            },
            "financials": {
                "employees": {
                    "industriarb": 25
                },
                "annual_turnover": "375,000 kr"
            },
            "foundation_year": 1885,
            "director": "Nygårds Anders Eriksson"
        },
        "3": {
            "name": "O. Andersson, Möbelfabrik",
            "location": "Tibro",
            "products": "Tillverkar möbler såsom bord, byråar, skåp, sekretärer, divanbord, hörnskåp och bokhyllor vid fabrik i Björkhamra, Tibro (Skarab. l.)",
            "contact": {
                "phone": "478",
                "postgiro": "265588"
            },
            "financials": {
                "employees": {
                    "industriarb": 5
                },
                "annual_turnover": "50,000 kr"
            },
            "foundation_year": 1942,
            "manager": "Oskar Andersson"
        },
        "4": {
            "name": "R. Anderssons Snickerifabrik",
            "location": "Skara",
            "products": "Tillverkar inredningssnickerier, fönster och dörrar, köksinredningar, trappor m. m.",
            "contact": {
                "phone": "190",
                "postgiro": "266021"
            },
            "financials": {
                "employees": {
                    "industriarb": 7
                }
            },
            "foundation_year": 1924,
            "manager": "Ernst Rich. Andersson"
        },
        "5": {
            "name": "AB. Robert Anderssons Konst-svarveri",
            "location": "Värnamo",
            "products": "Tillverkar svarveri artiklar och slöjd-alster. Specialiteter: träljusstakar, leksaker och handdukshängare",
            "contact": {
                "phone": "10109",
                "postgiro": "269988",
                "sales_offices": [
                    {
                        "location": "Stockholm",
                        "phone": "530948"
                    }
                ]
            },
            "financials": {
                "capital": "60,000 kr",
                "employees": {
                    "industriarb": 25
                },
                "annual_turnover": "300,000 kr"
            },
            "foundation_year": 1907,
            "corporation_year": 1944,
            "board": [
                {
                    "name": "Robert Andersson",
                    "role": "fabr."
                },
                {
                    "name": "Karl-Erik Aspler",
                    "role": "lagerchef"
                },
                {
                    "name": "Mauritz Svensson",
                    "role": "kontorschef"
                }
            ],
            "director": "Robert Andersson"
        },
        "6": {
            "name": "Samuel Andersson",
            "location": "Tibro",
            "products": "Tillverkar möbler vid fabrik i Tibro (Skarab. l.). Specialitet: björkmöbler",
            "contact": {
                "phone": "72",
                "postgiro": "135720"
            },
            "financials": {
                "employees": {
                    "industriarb": 13
                },
                "annual_turnover": "290,000 kr"
            },
            "foundation_year": 1898,
            "manager": "Samuel Andersson"
        },
        "7": {
            "name": "Sven Andersson",
            "location": "Ljungskile",
            "products": "Tillverkar strumpor vid fabrik i Ljungskile (Göteb. o. Bohus l.)",
            "contact": {
                "telegraph": "Svenand, Ljungskile",
                "phone": "32",
                "postgiro": "83951"
            },
            "financials": {
                "employees": {
                    "industriarb": 65
                }
            },
            "foundation_year": 1932,
            "manager": "Sven Andersson"
        },
        "8": {
            "name": "Th. Andersson",
            "location": "Dalsjöfors",
            "products": "Tillverkar herrunderkläder i Lahmanns och interlockkvaliteter vid fabrik i Dalsjöfors (Älvsb. l.)",
            "contact": {
                "phone": "Borås 70021",
                "postgiro": "91260"
            },
            "financials": {
                "employees": {
                    "industriarb": 20
                },
                "annual_turnover": "300,000 kr"
            },
            "foundation_year": 1928,
            "manager": "Theodor Andersson"
        },
        "9": {
            "name": "Thure Andersson, Möbelfabrik",
            "location": "Tibro",
            "products": "Tillverkar matsals- och sängkammarmöbler samt kompletteringsmöbler vid fabrik i Tibro (Skarab. l.)",
            "contact": {
                "phone": "225",
                "postgiro": "85765"
            },
            "financials": {
                "employees": {
                    "industriarb": 15
                },
                "annual_turnover": "250,000 kr"
            },
            "foundation_year": 1931,
            "manager": "Thure Andersson"
        }
    }
}