{
    "original": "Vollsjö—Wst\n\nAB. Vollsjö Toffelfabrik, Vollsjö.\n\nTillverkar toffelbottnar vid fabrik i\nNösdala, Tormestorp (Kristianst. l.).\n\nKontor: Vollsjö. Telefon: 21. Postgiro:\n71815. — Akt.-kap.: 45,000 kr. Antal\nindustriarb.: 12. Tillv.-värde pr år: 130,000\nkr. — Bolaget grundat 1922.\n\nVerkst. dir.: handl. Bonde Andersson.\n\n\"AB. Volvo, Göteborg.\n\nMek. verkstäder i Göteborg och i\nSkövde (Pentaverken).\n\nTillverkar: i Göteborg: person- och\nlastautomobiler samt bussar och\ntraktorer (varumärke: »Volvo»); i Skövde:\nbilmotorer, motorer för marina ändamål\n(inombordsmotorer) samt stationära\nmotorer (varumärke: »Penta»).\n\nHuvudkontor: Göteborg; postadr.:\nGöteborg 1. Telegr.-adr.: Volvo,- Göteborg.\nTelefon: 222000. Postgiro: 42880.\n\nAkt.-kap.: 37,500,000 kr. Antal\nindustriarb.: 2,300, varav i Göteborg 800, i\nSkövde 1,500.\n\nBolaget grundat 1915, verkstaden i\nSkövde anlagd 1868.\n\nStyrelse: landshövd. Bror Hasselrot\n(ordf.), dir. Assar Gabrielsson, dir. Hadar\nH:son Hallström, dir. Gustaf Larson,\ning. Erik Magnus, dr Hilding\nTörnebohm, dr Sven Wingquist.\n\nVerkst. dir.: Assar Gabrielsson.\tj\n\nV. verkst. dir.: Gustaf Larson.\nChef i Skövde: dir. Gustav Pettersson.\nFörsäljn.-chef: Åke Högman.\nInköpschef: Åke Reifors.\n\n\"Woxna Järnverk, Voxna.\nSe Ljusne-Woxna AB., Ljusne.\n\n\"Ernst Wranne, Byggnads AB.,\n\nKalmar.\n\nEntreprenadfirma för husbyggnader;\nutför byggnadstekniska utredningar,\nbyggnadskontroll samt värderingar.\nTelefon: 834 o. 2906. Postgiro: 171403.\nAkt.-kap.: 175,000 kr. — Firman etabl.\n1913, bolag 1945.\n\nVerkst. dir.: byggnadsing. Ernst\nWranne.\n\nArbetschef: ing. Börje Nordmark.\n\n* V ren a Sågverk o. Tegelbruk,\n\nVrena.\n\nSe Backa-Hosjö AB., Sparreholm.\n\nWretmans Boktryckeri AB.,\n\nUppsala.\n\nUtför bok-, affärs- och tidskriftstryck.\nTelefon: 30191 o. 30i919. Postgiro:\n13062. — Akt.-kap.: 75,000 kr. Antal\nindustriarb.: 27. Tillv.-värde pr år: 250,000\nkr. — Firman etabl. 1889, bolag 1925.\nVerkst. dir.: boktr. Emil Sjögren.\n\nAB. Vretstorps Tröskmaskiner,\n\nVretstorp.\n\nMek. verkstad i Vretstorp (Örebro l.).\nTillverkar tröskverk, bossfläktar och\nhalm-fläktar. Varumärken: »Vretstorps\nTröskverk» o. »Viby Tröskverk».\n\nTelefon: 70. Postgiro: 13991. Repr.:\nAB. Nilssén &amp; Westbergs Maskinaffär,\nKarlstad, telefon: 15685.\n\nAkt.-kap.: 200,000 kr. Antal\nindustriarb.: 73. — Bolaget grundat 1923.\n\nVerkst. dir.: Nils Westberg (Karlstad).\nDisp.: Karl Neider.\n\n\"Vrigstads Skofabrik, Vrigstad.\n\nTillverkar sandalsydda skodon vid\nfabrik i Vrigstad (Jönköp. l.). Varumärke:\n»V. S. Vrigstad».\nTelefon: 45. —1 Antal industriarb.: 50.\n\n—\tFirman etabl. 1928.\n\nÄgare: Mandli Svenssons sterbhus.\n\n\"AB. WST-hus, Forserum.\n\nTrähusfabrik, hyvleri och\nsnickerifabrik i Forserum (Jönköp. l.).\nTillverkar monteringsfärdiga trähus, fönster\noch dörrar, trappor, köksinredningar\nsamt sågade och hyvlade trävaror.\nVarumärke: »WST-hus».\n\nHuvudkontor: Jönköping. Telegr.-adr.:\nWST-hus, Jönköping. Telefon: 5461,\n7190—91. Postgiro: 81728. Inköpsavd. o.\nritkontor: Forserum, telegr.-adr. o.\ntelefon: WST-hus, Forserum. Exportrepr.:\nFörenade Trähusfabriker, Förening\nu. p. a., Stockholm, Kungsg. 39, telefon:\n202416.\n\nAkt.-kap.: 300,000 kr. Antal\nindustriarb.: 125. Tillv.-värde pr år: 5,000,000 kr.\n\n—\tFirman etabl. 1922, bolag 1943.\nStyrelse: dir. Werner Svensson (ordf.),\n\nkamrer Bengt Werneskog, inköpschef\nFolke Werneskog.\n\nVerkst. dir.: fabr. Werner Svensson,\n(Forserum).\n\nKamrer o. försäljn.-chef: Bernt\nWerneskog (Jönköping).\n\nInköpschef: Folke Werneskog\n(Forserum) .\n\n628*",
    "structured": {
        "firms": [
            {
                "name": "Vollsjö Toffelfabrik AB",
                "location": "Vollsjö",
                "business": "Tillverkning av toffelbottnar",
                "contact": {
                    "office": "Vollsjö",
                    "phone": [
                        "21"
                    ],
                    "postgiro": "71815"
                },
                "financials": {
                    "capital": "45,000 kr",
                    "employees": {
                        "industriarb": 12
                    },
                    "annual_turnover": "130,000 kr",
                    "annual_production_value": "130,000 kr"
                },
                "foundation_year": 1922,
                "director": "handl. Bonde Andersson"
            },
            {
                "name": "AB. Volvo",
                "location": "Göteborg",
                "business": "Tillverkning av person- och lastautomobiler, bussar, traktorer, bilmotorer, inombordsmotorer, stationära motorer",
                "contact": {
                    "office": "Göteborg",
                    "phone": [
                        "222000"
                    ],
                    "head_office": "Göteborg",
                    "sales_offices": [
                        {
                            "location": "Göteborg",
                            "phone": "222000"
                        },
                        {
                            "location": "Skövde",
                            "phone": "N/A"
                        }
                    ],
                    "telegraph": "Volvo,- Göteborg",
                    "postgiro": "42880"
                },
                "financials": {
                    "capital": "37,500,000 kr",
                    "employees": {
                        "industriarb": 2,
                        "Göteborg": 800,
                        "Skövde": 1,
                        "total": 2300
                    },
                    "corporation_year": 1915
                },
                "foundation_year": 1915,
                "board": [
                    {
                        "name": "landshövd. Bror Hasselrot",
                        "role": "ordförande"
                    },
                    {
                        "name": "dir. Assar Gabrielsson",
                        "role": "verkställande direktör"
                    },
                    {
                        "name": "dir. Hadar H:son Hallström",
                        "role": "direktör"
                    },
                    {
                        "name": "dir. Gustaf Larson",
                        "role": "direktör"
                    },
                    {
                        "name": "ing. Erik Magnus",
                        "role": "ingenjör"
                    },
                    {
                        "name": "dr Hilding Törnebohm",
                        "role": "direktör"
                    },
                    {
                        "name": "dr Sven Wingquist",
                        "role": "direktör"
                    }
                ],
                "owner": "AB. Volvo",
                "director": "Assar Gabrielsson",
                "managing_director": "Gustaf Larson",
                "sales_manager": "Åke Högman",
                "manager": "Åke Reifors"
            },
            {
                "name": "Ernst Wranne, Byggnads AB",
                "location": "Kalmar",
                "business": "Entreprenadfirma för husbyggnader",
                "contact": {
                    "phone": [
                        "834",
                        "2906"
                    ],
                    "postgiro": "171403"
                },
                "financials": {
                    "capital": "175,000 kr"
                },
                "foundation_year": 1913,
                "current_name_year": 1945,
                "director": "byggnadsing. Ernst Wranne",
                "sales_manager": "ing. Börje Nordmark"
            },
            {
                "name": "Woxna Järnverk",
                "location": "Voxna",
                "description": "Se Ljusne-Woxna AB., Ljusne."
            },
            {
                "name": "Ernst Wranne, Byggnads AB.",
                "location": "Kalmar",
                "business": "Entreprenadfirma för husbyggnader",
                "contact": {
                    "phone": [
                        "834",
                        "2906"
                    ],
                    "postgiro": "171403"
                },
                "financials": {
                    "capital": "175,000 kr"
                },
                "foundation_year": 1913,
                "current_name_year": 1945,
                "director": "byggnadsing. Ernst Wranne",
                "sales_manager": "ing. Börje Nordmark"
            },
            {
                "name": "Vrena Sågverk o. Tegelbruk",
                "location": "Vrena",
                "description": "Se Backa-Hosjö AB., Sparreholm."
            },
            {
                "name": "Wretmans Boktryckeri AB",
                "location": "Uppsala",
                "business": "Utför bok-, affärs- och tidskriftstryck",
                "contact": {
                    "phone": [
                        "30191",
                        "301919"
                    ],
                    "postgiro": "13062"
                },
                "financials": {
                    "capital": "75,000 kr",
                    "employees": {
                        "industriarb": 27
                    },
                    "annual_turnover": "250,000 kr"
                },
                "foundation_year": 1889,
                "current_name_year": 1925,
                "director": "boktr. Emil Sjögren"
            },
            {
                "name": "AB. Vretstorps Tröskmaskiner",
                "location": "Vretstorp",
                "business": "Tillverkning av tröskverk, bossfläktar och halm-fläktar",
                "contact": {
                    "phone": "70",
                    "postgiro": "13991"
                },
                "financials": {
                    "capital": "200,000 kr",
                    "employees": {
                        "industriarb": 73
                    }
                },
                "foundation_year": 1923,
                "director": "Nils Westberg (Karlstad)",
                "sales_manager": "Karl Neider"
            },
            {
                "name": "Vrigstads Skofabrik",
                "location": "Vrigstad",
                "business": "Tillverkning av sandalsydda skodon",
                "contact": {
                    "phone": "45"
                },
                "foundation_year": 1928,
                "owners": [
                    "Mandli Svenssons sterbhus"
                ]
            },
            {
                "name": "AB. WST-hus",
                "location": "Forserum",
                "business": "Trähusfabrik, hyvleri och snickerifabrik",
                "contact": {
                    "head_office": "Jönköping",
                    "phone": [
                        "5461",
                        "7190-91"
                    ],
                    "postgiro": "81728",
                    "sales_offices": [
                        {
                            "location": "Forserum",
                            "phone": "WST-hus, Forserum"
                        }
                    ]
                },
                "financials": {
                    "capital": "300,000 kr",
                    "employees": {
                        "industriarb": 125
                    },
                    "annual_production_value": "5,000,000 kr"
                },
                "foundation_year": 1922,
                "corporation_year": 1943,
                "board": [
                    {
                        "name": "dir. Werner Svensson",
                        "role": "ordförande"
                    },
                    {
                        "name": "kamrer Bengt Werneskog",
                        "role": "kamrer"
                    },
                    {
                        "name": "inköpschef Folke Werneskog",
                        "role": "inköpschef"
                    }
                ],
                "director": "fabr. Werner Svensson",
                "sales_manager": "Bernt Werneskog",
                "manager": "Folke Werneskog"
            }
        ]
    }
}