{
    "original": "Torsvik—Trafik\n\n\"Torsviks Sågverks AB.,\n\nHärnösand.\n\nSågverk och hyvleri vid Ramvik\n(Västernorrl. l.), wallboard- och fanérfabrik i\nHärnösand.\n\nTillverkar sågade och hyvlade trävaror,\nwallboard (»Hernit»), kryssfanér,\nblock-lamell (»Härnösands») samt lamellträ\n(»Titus»-lamellträ).\n\nHuvudkontor: Härnösand. Telegr.-adr.:\nPlyboard, Härnösand. Telefon:\n»Tors-vik». Postgiro: 28839.\n\nAvd.-kontor: Ramvik. Telegr.-adr.:\n\"Torsviksåg, Ramvik. Telefon: Ramvik 33\no. 77. Skogskontor: Sollefteå, telefon:\n211. Försäljn.-kontor: Malmö, telefon:\n11401; Göteborg, telefon: 111446; Nässjö,\ntelefon: 1533, Karlstad, telefon: 17100.\nFörsäljare för trävaror: Firma A. J.\nNorberg, Härnösand; telefon: 2056.\n\nAkt.-kap.: 500,000 kr. Antal\nindustriarb.: 330, varav i Härnösand 230.\nÅrstillv.: 8,000 stds sågade och hyvlade\nträvaror, 15,000 ton wallboard, 12,000 kbm\nkryssfanér och lamellträ.\n\nBolaget grundat 1922.\n\nStyrelse: disp. Abraham Hellström\n&lt;ordf.), grossh. Emil Eriksson, ing. Kurt\nHellström, skogschef Olof Hellström, dir.\nHobert Högberg.\n\nVerkst. dir. o. disp.: Abraham\nHellström.\n\n\"Torsåkers Linnefabriks AB.,\n\nTorsåker.\n\nLinneväveri, blekeri och färgeri i\nTorsåker (Gävleb. l.). Tillverkar\nlinnevävna-der samt lin- och towgarner för hemslöjd.\nVarumärke: Tor med hammaren.\n\nTelefon: 85 o. 185. Postgiro: 9005.\nRepr.: i Stockholm: Fritz Altschul,\nDö-belnsg. 43, telefon: 328887; i Göteborg:\nKöpm. L. Gust Bohman, Sotenäsv. 20,\nSävedalen, telefon: 260428.\n\nAkt.-kap.: 270,000 kr. Antal\nindustriarb.: 100. Tillv.-värde pr år: 1,500,000 kr.\n— Firman etabl. 1920, bolag 1924, nuv.\nnamn 1932.\n\nStyrelse; dir. Carl Larsson (ordf.),\nvdir. Lars Larsson, köpman Arvid Olsson,\nfabr. H. Svantesson, köpman Y. Tjerneld.\n\nChefer: Carl Larsson o. Lars Larsson.\n\nTorsås Träförädlings AB., Torsås.\n\nTillverkar verktygsskaft såsom yx-,\njslägg-, korp-, hammar- och spadskaft,\n.sågade ämnen av lövträ och blockvara av\n&lt;ek samt lastbilshytter och\nkarosseriom-byggnader vid fabrik i Torsås\n(Kalmar l.).\n\nTelegr.-adr.: Totab, Torsås. Telefon:\n115 o. 119. Postgiro: 13829. — Akt.-kap.:\n30,000 kr. Antal industriarb.: 75. —\nBolaget grundat 1935.\n\nVerkst. dir.: disp. Göte Carlwig.\n\nTorvströ AB. Ryttaren,\n\nSandhem.\n\nTorvströ- och träullsfabrik i Sandhem\n(Skarab. l.). Tillverkar torvströ och\ntorvmull samt träull och träullsplattor.\n\nKontor: Sandhem. Telefon: 12.\n—Akt.-kap.: 140,000 kr. Tillv.-värde pr år:\n300,000 kr. — Bolaget grundat 1906.\n\nStyrelse o. disp.: Nils Hartelius.\n\n\"Tostarps Träförädlings AB.,\n\nUdd et o.\n\nBobinfabrik i Tranemo (Älvsb. l.).\nTillverkar bobiner, skaft för redskap och\nverktyg, delar till leksaker, träaskar och\nandra svarvade träarbeten. Specialitet:\nsvarvade, fernissade massartiklar av trä.\n\nKontor: Uddebo. Telegr.-adr.: Tostarps,\nUddebo. Telefon: Svenljunga 27071.\nPostgiro: 9759.\n\nAkt.-kap.: 300,000 kr. Antal\nindustriarb.: 40. Tillv.-värde pr år: 450,000 kr.\n— Bolaget grundat 1905.\n\nStyrelse: fabr. Rich. Claeson (ordf.),\ndisp. Helge Claeson, ing. Ragnar\nClaeson.\n\nVerkst. dir.: Helge Claeson.\n\nDisp.-assist.: Erling Kylenfelt.\n\n\"Totebo Hjulfabrik, C. 0. Larsson &amp;\nSöner, Totebo.\n\nSnickerifabrik, fanérfabrik och sågverk\ni Totebo (Kalmar l.).\n\nTillverkar vagnshjul, radiolådor och\nskåp för radiogrammofoner samt faner.\n\nTelefon: 1 o. 7. Postgiro: 36464. —\nAntal industriarb.: 225. Tillv.-värde pr\når: 2,000,000 kr. — Firman etabl. 1912\nunder namn Virums Hjulfabrik, nuv.\nnamn 1925.\n\nÄgare o. chefer: fabr. Valter Larsson\no. disp. Ariel Larsson.\n\nDriftsing.: Carl-Herbert Larsson.\n\nKontorschef: Henry Lövgren.\n\nInköpschef: Ragnar Persson.\n\n\"Trafik AB. Grängesberg-Oxelösund,\n\nStockholm.\n\nIdkar gruvdrift vid järnmalmsfält i\nGrängesberg (Kopparb. l.) samt driver\njärnvägs- och rederirörelse.",
    "structured": {
        "1": {
            "name": "Torsviks Sågverks AB.",
            "location": "Härnösand",
            "business": "Sågverk och hyvleri vid Ramvik (Västernorrl. l.), wallboard- och fanérfabrik i Härnösand.",
            "products": "Tillverkar sågade och hyvlade trävaror, wallboard (»Hernit»), kryssfanér, block-lamell (»Härnösands») samt lamellträ (»Titus»-lamellträ).",
            "contact": {
                "office": "Härnösand",
                "phone": [
                    "Ramvik 33",
                    "Ramvik 77",
                    "Sollefteå 211",
                    "Malmö 11401",
                    "Göteborg 111446",
                    "Nässjö 1533",
                    "Karlstad 17100"
                ],
                "postgiro": "28839",
                "head_office": "Härnösand",
                "sales_offices": [
                    {
                        "location": "Ramvik",
                        "phone": "Ramvik 33 o. 77"
                    },
                    {
                        "location": "Sollefteå",
                        "phone": "211"
                    },
                    {
                        "location": "Malmö",
                        "phone": "11401"
                    },
                    {
                        "location": "Göteborg",
                        "phone": "111446"
                    },
                    {
                        "location": "Nässjö",
                        "phone": "1533"
                    },
                    {
                        "location": "Karlstad",
                        "phone": "17100"
                    }
                ],
                "telegraph": "Plyboard, Härnösand",
                "factory_office": "Torsvik",
                "factory_phone": "Torsvik"
            },
            "financials": {
                "capital": "500,000 kr",
                "employees": {
                    "Härnösand": 230,
                    "Total": 330
                },
                "annual_turnover": "8,000 stds sågade och hyvlade trävaror, 15,000 ton wallboard, 12,000 kbm kryssfanér och lamellträ",
                "annual_production_value": "8,000 stds sågade och hyvlade trävaror, 15,000 ton wallboard, 12,000 kbm kryssfanér och lamellträ"
            },
            "foundation_year": 1922,
            "board": [
                {
                    "name": "disp. Abraham Hellström",
                    "role": "ordf."
                },
                {
                    "name": "grossh. Emil Eriksson"
                },
                {
                    "name": "ing. Kurt Hellström"
                },
                {
                    "name": "skogschef Olof Hellström"
                },
                {
                    "name": "dir. Hobert Högberg"
                }
            ],
            "director": "Abraham Hellström"
        },
        "2": {
            "name": "Torsåkers Linnefabriks AB.",
            "location": "Torsåker",
            "business": "Linneväveri, blekeri och färgeri i Torsåker (Gävleb. l.).",
            "products": "Tillverkar linnevävna-der samt lin- och towgarner för hemslöjd. Varumärke: Tor med hammaren.",
            "contact": {
                "phone": [
                    "85",
                    "185"
                ],
                "postgiro": "9005",
                "sales_offices": [
                    {
                        "location": "Stockholm",
                        "phone": "328887"
                    },
                    {
                        "location": "Göteborg",
                        "phone": "260428"
                    }
                ]
            },
            "financials": {
                "capital": "270,000 kr",
                "employees": 100,
                "annual_turnover": "1,500,000 kr"
            },
            "foundation_year": 1920,
            "current_name_year": 1932,
            "board": [
                {
                    "name": "dir. Carl Larsson",
                    "role": "ordf."
                },
                {
                    "name": "vdir. Lars Larsson"
                },
                {
                    "name": "köpman Arvid Olsson"
                },
                {
                    "name": "fabr. H. Svantesson"
                },
                {
                    "name": "köpman Y. Tjerneld"
                }
            ],
            "director": "Carl Larsson",
            "managing_director": "Lars Larsson"
        },
        "3": {
            "name": "Torsås Träförädlings AB.",
            "location": "Torsås",
            "business": "Tillverkar verktygsskaft såsom yx-, jslägg-, korp-, hammar- och spadskaft, sågade ämnen av lövträ och blockvara av <ek samt lastbilshytter och karosseriomb- byggnader vid fabrik i Torsås (Kalmar l.).",
            "contact": {
                "phone": [
                    "115",
                    "119"
                ],
                "postgiro": "13829"
            },
            "financials": {
                "capital": "30,000 kr",
                "employees": 75
            },
            "foundation_year": 1935,
            "board": [
                {
                    "name": "disp. Göte Carlwig",
                    "role": "Verkst. dir."
                }
            ]
        },
        "4": {
            "name": "Torvströ AB. Ryttaren",
            "location": "Sandhem",
            "business": "Torvströ- och träullsfabrik i Sandhem (Skarab. l.).",
            "products": "Tillverkar torvströ och torvmull samt träull och träullsplattor.",
            "contact": {
                "phone": "12",
                "postgiro": "140,000 kr"
            },
            "financials": {
                "capital": "140,000 kr",
                "annual_turnover": "300,000 kr"
            },
            "foundation_year": 1906,
            "board": [
                {
                    "name": "Nils Hartelius",
                    "role": "Styrelse o. disp."
                }
            ]
        },
        "5": {
            "name": "Tostarps Träförädlings AB.",
            "location": "Udd et o.",
            "business": "Bobinfabrik i Tranemo (Älvsb. l.).",
            "products": "Tillverkar bobiner, skaft för redskap och verktyg, delar till leksaker, träaskar och andra svarvade träarbeten.",
            "contact": {
                "phone": "Svenljunga 27071",
                "postgiro": "9759"
            },
            "financials": {
                "capital": "300,000 kr",
                "employees": 40,
                "annual_turnover": "450,000 kr"
            },
            "foundation_year": 1905,
            "board": [
                {
                    "name": "fabr. Rich. Claeson",
                    "role": "ordf."
                },
                {
                    "name": "disp. Helge Claeson"
                },
                {
                    "name": "ing. Ragnar Claeson"
                }
            ],
            "director": "Helge Claeson",
            "manager": "Erling Kylenfelt"
        },
        "6": {
            "name": "Totebo Hjulfabrik, C. 0. Larsson & Söner",
            "location": "Totebo",
            "business": "Snickerifabrik, fanérfabrik och sågverk i Totebo (Kalmar l.).",
            "products": "Tillverkar vagnshjul, radiolådor och skåp för radiogrammofoner samt faner.",
            "contact": {
                "phone": [
                    "1",
                    "7"
                ],
                "postgiro": "36464"
            },
            "financials": {
                "employees": 225,
                "annual_turnover": "2,000,000 kr"
            },
            "current_name_year": 1925,
            "owners": [
                "Valter Larsson",
                "Ariel Larsson"
            ],
            "director": "Valter Larsson",
            "managing_director": "Ariel Larsson",
            "sales_manager": "Ragnar Persson"
        },
        "7": {
            "name": "Trafik AB. Grängesberg-Oxelösund",
            "location": "Stockholm",
            "business": "Idkar gruvdrift vid järnmalmsfält i Grängesberg (Kopparb. l.) samt driver järnvägs- och rederirörelse."
        }
    }
}