{
    "original": "Nensjö—Nihlmark\n\nTelefon: 171237 o. 171253. Postgiro:\n29044. — Akt.-kap.: 100,000 kr. Antal\nindustriarb.: 30. Tillv.-värde pr år: 300,000\nkr.\n\nFirman etabl. 1893 under namn\nStockholms Båtbyggeri AB., nuv. namn 1941.\n\nStyrelse: civiling. Paul Vestergren\n(ordf.), dir. J. Järpe, dir. Yngve\nPehrs-son, civiling. Bengt Plym, civiling.\nGustaf Plym, civiling. Oscar Plym.\nVerkst. dir.: Bengt Plym.\n\n*Nensjö Cellulosa AB., Kramfors.\nSe Strömnäs AB., Kramfors.\n\n*Nermans Stämplar, Åke Nerman,\n\nKarlstad.\n\nTillverkar alla slags stämplar av\ngummi och metall samt stämpelfärger.\nSpecialitet: stämplar för märkning av\nemballage och trävaror.\n\nTelegr.-adr.: Åkenerman, Karlstad.\nTelefon: 10012 o. 13032. Postgiro: 96711.\nAntal industriarb.: 18. — Firman\ngrundad 1921.\n\nÄgare: konsul Åke Nerman.\nFörsäljn.-chef: Manne Christiansen.\nDriftsledare: Gunnar Sundström.\n\nNermans Trycksaker, Åke Nerman,\n\nKarlstad.\n\nUtför bok- och affärstryck.\nSpecialiteter: reklam- och katalogtryck.\n\nTelegr.-adr.: Åkenerman, Karlstad.\nTelefon: 15610. Postgiro: 96712.\n\nAntal industriarb.: 50. Tillv.-värde pr\når: 525,000 kr. — Firman etabl. 1920.\nÄgare o. chef: konsul Åke Nerman.\nTrycheriförest.: Carl O. Persson.\nKamrer: Ingvar Janson.\n\n*Nils Nessen AB., Byggnadsfirman,\n\nStockholm.\n\nByggnadsentreprenörfirma för\nbostads-och affärshus, industribyggnader m. m.\n\nKontor: Bergsg. 1. Telefon: 520500.\nPostgiro: 2517. — Akt.-kap.: 250,000 kr.\nProd.-värde pr år: 5,000,000 kr.\n— Firman etabl. 1930, bolag 1942.\n\nStyrelse o. verkst. dir.: ing. Nils\nNes-sen.\n\nArbetschef: ing. Axel Hallmans.\n\n*Aug. Netz, Byggnads AB.,\n\nLinköping.\n\nSe Byggnads AB. Aug. Netz,\nLinköping.\n\n\"Anders Nevsten AB., Malmö.\n\nByggnadsentreprenörfirma för\nbostads-och affärshus, industribyggnader m. m.\n\nKontor: Davidhallsg. 21. Telefon:\n23585, 19735 o. 23957. Postgiro: 38936.\n\nAkt.-kap.: 120,000 kr. Prod.-värde pr\når: 3,000,000 kr. — Firman etabl. 1933,\nbolag 1940.\n\nStyrelse o. verkst. dir.: byggm. Anders\nNevsten.\n\nArbetschef: ing. Gunnar Karyd.\n\n* Nickelfabriks AB. Gottfrid Carlsson,\n\nEskilstuna.\n\nMetallvarufabrik och\nförnicklingsan-stalt. Tillverkar husgerådsartiklar av\nmässing, koppar och nysilver, kokkärl av\naluminium samt pressade, tryckta och\nsvarvade metalldelar efter ritningar och\nmodeller. Varumärke: »Svea».\n\nTelegr.-adr.: Nickel, Eskilstuna.\nTelefon: 30280. Postgiro: 8636.\n\nAkt.-kap.: 225,000 kr. Antal\nindustriarb.: 80. Tillv.-värde pr år: 1,200,000 kr.\n— Bolaget grundat 1891.\n\nStyrelse: dir. Abel Bergström (ordf.),\nkassör Ruth Carlsson, stationsinsp. O. W.\nStrutz.\n\nVerkst. dir.: A. Bergström.\n\nAB. Nickel- &amp; Metallindustri,\n\nKarlshamn.\n\nTillverkar lås och beslag för\nreseffek-ter, beslag för glasindustrin, smörjkannor\nm. m.\n\nKontor: Karlshamn. Telegr.-adr.:\nNickelmetall, Karlshamn. Telefon: 1750—51.\nPostgiro: 263916. — Akt.-kap.: 20,000 kr.\nAntal industriarb.: 70. — Firman etabl.\n1938 under namn AB. Lås &amp; Beslag, nuv.\nnamn 1942.\n\nVerkst. dir.: Hugo Lindeberg.\n\nDriftschef: Valter Hellberg.\n\nKamrer: Arne Löfgren.\n\n*AB. Nielsens Stenhuggerier,\n\nGöteborg.\n\nSe AB. Förenade Granitindustrier,\nGöteborg.\n\n*AB. Gustaf Nihlmarks Trävaruaffär,\n\nGöteborg.\n\nSnickerifabrik. Tillverkar\nbyggnadssnickerier. Firman driver jämväl\nhandelsrörelse med trävaror och\nbyggnads-materiel.",
    "structured": {
        "1": {
            "name": "Nensjö—Nihlmark",
            "foundation_year": 1893,
            "current_name_year": 1941,
            "financials": {
                "capital": "100,000 kr",
                "employees": {
                    "industriarb": 30
                },
                "annual_turnover": "300,000 kr",
                "annual_production_value": "300,000 kr"
            },
            "board": [
                {
                    "name": "civiling. Paul Vestergren",
                    "role": "ordf."
                },
                {
                    "name": "dir. J. Järpe",
                    "role": "dir."
                },
                {
                    "name": "dir. Yngve Pehrs-son",
                    "role": "dir."
                },
                {
                    "name": "civiling. Bengt Plym",
                    "role": "civiling."
                },
                {
                    "name": "civiling. Gustaf Plym",
                    "role": "civiling."
                },
                {
                    "name": "civiling. Oscar Plym",
                    "role": "civiling."
                }
            ],
            "manager": "Bengt Plym"
        },
        "2": {
            "name": "Nermans Stämplar",
            "location": "Åke Nerman, Karlstad",
            "products": "Tillverkar alla slags stämplar av gummi och metall samt stämpelfärger. Specialitet: stämplar för märkning av emballage och trävaror.",
            "contact": {
                "phone": [
                    "10012",
                    "13032"
                ],
                "postgiro": "96711",
                "sales_offices": [
                    {
                        "location": "Åke Nerman, Karlstad",
                        "phone": "10012"
                    }
                ],
                "telegraph": "Åkenerman, Karlstad"
            },
            "owners": [
                "konsul Åke Nerman"
            ],
            "sales_manager": "Manne Christiansen",
            "director": "Åke Nerman",
            "manager": "Gunnar Sundström"
        },
        "3": {
            "name": "Nermans Trycksaker",
            "location": "Åke Nerman, Karlstad",
            "products": "Utför bok- och affärstryck. Specialiteter: reklam- och katalogtryck.",
            "contact": {
                "phone": "15610",
                "postgiro": "96712"
            },
            "owners": [
                "konsul Åke Nerman"
            ],
            "director": "Åke Nerman",
            "managing_director": "Carl O. Persson",
            "manager": "Ingvar Janson"
        },
        "4": {
            "name": "Nils Nessen AB.",
            "location": "Byggnadsfirman, Stockholm",
            "business": "Byggnadsentreprenörfirma för bostads-och affärshus, industribyggnader m. m.",
            "contact": {
                "phone": "520500",
                "postgiro": "2517"
            },
            "financials": {
                "capital": "250,000 kr",
                "employees": {
                    "industriarb": 0
                },
                "annual_turnover": "5,000,000 kr",
                "annual_production_value": "5,000,000 kr"
            },
            "board": [
                {
                    "name": "ing. Nils Nessen",
                    "role": "verkst. dir."
                },
                {
                    "name": "ing. Axel Hallmans",
                    "role": "arbetschef"
                }
            ]
        },
        "5": {
            "name": "Aug. Netz, Byggnads AB.",
            "location": "Linköping",
            "business": "Byggnadsentreprenörfirma för bostads-och affärshus, industribyggnader m. m.",
            "contact": {
                "phone": [
                    "23585",
                    "19735",
                    "23957"
                ],
                "postgiro": "38936"
            },
            "financials": {
                "capital": "120,000 kr",
                "employees": {
                    "industriarb": 0
                },
                "annual_turnover": "3,000,000 kr",
                "annual_production_value": "3,000,000 kr"
            },
            "board": [
                {
                    "name": "byggm. Anders Nevsten",
                    "role": "verkst. dir."
                },
                {
                    "name": "ing. Gunnar Karyd",
                    "role": "arbetschef"
                }
            ]
        },
        "6": {
            "name": "Nickelfabriks AB. Gottfrid Carlsson",
            "location": "Eskilstuna",
            "business": "Metallvarufabrik och förnicklingsan-stalt. Tillverkar husgerådsartiklar av mässing, koppar och nysilver, kokkärl av aluminium samt pressade, tryckta och svarvade metalldelar efter ritningar och modeller. Varumärke: »Svea».",
            "contact": {
                "phone": "30280",
                "postgiro": "8636"
            },
            "financials": {
                "capital": "225,000 kr",
                "employees": {
                    "industriarb": 80
                },
                "annual_turnover": "1,200,000 kr"
            },
            "board": [
                {
                    "name": "dir. Abel Bergström",
                    "role": "ordf."
                },
                {
                    "name": "kassör Ruth Carlsson",
                    "role": "kassör"
                },
                {
                    "name": "stationsinsp. O. W. Strutz",
                    "role": "stationsinsp."
                }
            ],
            "manager": "A. Bergström"
        },
        "7": {
            "name": "AB. Nickel- & Metallindustri",
            "location": "Karlshamn",
            "business": "Tillverkar lås och beslag för reseffek-ter, beslag för glasindustrin, smörjkannor m. m.",
            "contact": {
                "phone": [
                    "1750",
                    "1751"
                ],
                "postgiro": "263916"
            },
            "financials": {
                "capital": "20,000 kr",
                "employees": {
                    "industriarb": 70
                }
            },
            "board": [
                {
                    "name": "Hugo Lindeberg",
                    "role": "verkst. dir."
                },
                {
                    "name": "Valter Hellberg",
                    "role": "driftschef"
                },
                {
                    "name": "Arne Löfgren",
                    "role": "kamrer"
                }
            ]
        }
    }
}