{
    "original": "Elektromagneter—Elf ström\n\ntransportvagnar; utför ytbehandlingar\nsåsom bonderisering, galvanisering,\nkadmie-ring, förtenning, förzinkning,\nbrännlackering m. m.\n\nHuvudkontor o. försäljningskontor:\nStockholm, S:t Eriksg. 63. Telegr.-adr. o.\ntelefon: Elektrolux, Stockholm. Postgiro:\n2030.\n\nAkt.-kap.: 45,000,000 kr. Antal\nindustriarb. : 2,400.\n\nBolaget, grundat 1910, har år 1941\növertagit rörelsen vid AB. Arctic,\nMotala (grundat 1923), och AB. Lux,\nStockholm (grundat 1901) samt är\nhuvudintressent i Bohus Mek. Verkstads AB.,\nGöteborg, och AB. Archimedes, Sundbyberg.\n\nStyrelse: kommerserådet Axel F.\nEn-ström (ordf.), prof. K. M. G. Siegbahn\n(v. ordf.), dir. Axel O. Engberg, dir.\nGust. J. Sahlin, adv. Sven Salmonson,\nsir Harold Wernher, dir. Sten Widell.\n\nVerkst. dir.: Gust. J. Sahlin.\n\nV. verkst. direktörer: Sten Widell o.\nAxel O. Engberg.\n\nVerkstadschefer: i Stockholm: övering.\nFred Deijfen; i Motala: övering. Ebbe\nSvensson.\n\n(Jfr annons nr 8 o. 9.)\n\n\"Elektromagneter, Åmål.\n\nSe AB. Svenska Elektromagneter, Åmål.\n\n\"Elektromekano, Hälsingborg.\n\nSe Svenska Elektromekaniska Industri\nAB., Hälsingborg.\n\n* Elek tro- Metall, Malmö.\n\nMetallvarufabrik. Tillverkar elektr.\nbelysningsarmatur samt utför\nmetalltryckning, förkoppring och förmässing.\n\nKontor: Almedalsg. 3. Telefon: 29597.\nPostgiro: 38504. — Arb.-antal: 10. —\nFirman etabl. 1921.\n\nÄgare o. chef: fabr. Joh. Johansson.\n\nAB. Elektro-Metallisator, Stockholm.\n\nUtför sandblästring och\nsprutmetalli-sering med bl. a. zink, aluminium och\nstål dels såsom rostskydd dels för\nuppbyggnad av slitna maskindelar.\n\nKontor: Norrlandsg. 12. Telegr.-adr.:\nElmetallisator, Stockholm. Telefon: 113517\no. 212080. Postgiro: 159300.\n\nAkt.-kap.: 31,000 kr. Antal\nindustriarb.: 8. Tillv.-värde pr år: 100,000 kr. —\nBolaget grundat 1940.\n\nVerkst. dir.: Bo Löfgren.\n\n(Jfr annons nr 48.)\n\nElektronrör, AB. Svenska,\n\nStockholm.\n\nSe AB. Svenska Elektronrör,\nStockholm.\n\n\"AB. Elektrosvets, Göteborg.\n\nSe AB. Svetsmekano, Göteborg.\n\n\"AB. Elektr o-Värme, Borås.\n\nElektromek. verkstad. Tillverkar elektr.\nbageriugnar, storköksapparater, kokare,\ngenomströmningsapparater, elektr.\nångpannor, kaminer, torkskåp och\nlackeringsugnar samt härd- och glödgningsugnar.\nVarumärke: »Elvärme».\n\nTelegr.-adr.: Elvärme, Borås. Telefon:\n17185. Postgiro: 98308.\nFörsäljn.-kon-tor: Stockholm, Malmskillnadsg. 39,\ntelefon: 233800.\n\nAkt.-kap.: 50,000 kr. Antal\nindustriarb.: 65. Tillv.-värde pr år: 1,200,000 kr.\n\n—\tBolaget grundat 1932.\n\nStyrelse o. chefer: fabr. Axel\nAndersson (ordf.), verkstadschef Karl-Edvard\nDahlén, dir. Allan Holmqvist.\n\n\"AB. Elevator, Stockholm.\n\nSe Graham Brothers AB., Stockholm.\n\nElfsborg, Konfektions AB., Borås.\n\nSe Konfektions AB. Elfsborg, Borås.\n\nAB. Elfsborgs Mek. Verkstad,\n\nGöteborg.\n\nTillverkar metallsprutor,\nfartygsartiklar, plåtarbeten m. m. samt utför\nmetalli-seringsarbeten. Bolaget driver även\nhandel med pumpar av utländsk tillverkning.\n\nKontor: Kanaltorget 1. Telefon:\n116519. — Akt.-kap.: 150,000 kr. Antal\nindustriarb.: 30. Tillv.-värde pr år:\n300,000 kr. — Bolaget grundat 1912.\n\nVerkst. dir.: kapten Rudolf Hedberg.\n\nAB. Elfströms Tekniska Fabrik,\n\nGävle.\n\nTillverkar toalett- och tvättvål,\ntvätt-och lutpulver, såplut, såpa, hudkräm,\nflytande champo, ljus m. m. Varumärken:\n»Reporia», »Profyl», »Mimosa», »Blixt»\no. »Kosmin».\n\nTelegr.-adr.: Elfströmsf abrik, Gävle.\nTelefon: 1054 o. 3929. Postgiro: 21414.\n\nAkt.-kap.: 154,200 kr. Antal\nindustriarb.: 21. Tillv.-värde pr år: 2,000,000 kr.\n\n—\tFirman grundad 1912, bolag 1927.\n\nStyrelse o. verkst. dir.: Öarl A. Elf-\n\nström.\n\n124*",
    "structured": {
        "1": {
            "name": "Elektromagneter—Elf ström transportvagnar",
            "location": "Stockholm",
            "business": "Ytbehandlingar",
            "contact": {
                "office": "S:t Eriksg. 63, Stockholm",
                "telegraph": "Elektrolux, Stockholm",
                "postgiro": "2030"
            },
            "financials": {
                "capital": "45,000,000 kr",
                "employees": {
                    "industriarb": 2400
                }
            },
            "foundation_year": 1910,
            "predecessor": "AB Arctic, Motala (grundat 1923), and AB Lux, Stockholm (grundat 1901)",
            "corporation_year": 1941,
            "board": [
                {
                    "name": "kommerserådet Axel F. En-ström",
                    "role": "ordf."
                },
                {
                    "name": "prof. K. M. G. Siegbahn",
                    "role": "v. ordf."
                },
                {
                    "name": "dir. Axel O. Engberg",
                    "role": null
                },
                {
                    "name": "dir. Gust. J. Sahlin",
                    "role": null
                },
                {
                    "name": "adv. Sven Salmonson",
                    "role": null
                },
                {
                    "name": "sir Harold Wernher",
                    "role": null
                },
                {
                    "name": "dir. Sten Widell",
                    "role": null
                }
            ],
            "director": "Gust. J. Sahlin",
            "managing_director": "Gust. J. Sahlin",
            "sales_manager": null,
            "manager": null
        },
        "2": {
            "name": "Elektro-Metallisator",
            "location": "Stockholm",
            "business": "Sandblästring och sprutmetallisering",
            "contact": {
                "office": "Norrlandsg. 12, Stockholm",
                "telegraph": "Elmetallisator, Stockholm",
                "phone": [
                    "113517",
                    "212080"
                ],
                "postgiro": "159300"
            },
            "financials": {
                "capital": "31,000 kr",
                "employees": {
                    "industriarb": 8
                }
            },
            "foundation_year": 1940,
            "director": "Bo Löfgren",
            "board": [],
            "owners": []
        },
        "3": {
            "name": "Elektr o-Värme",
            "location": "Borås",
            "business": "Elektriskt bageriutrustning och elvärme",
            "contact": {
                "office": "Almedalsg. 3, Borås",
                "phone": "29597",
                "postgiro": "38504",
                "sales_offices": [
                    {
                        "location": "Stockholm",
                        "phone": "17185"
                    }
                ]
            },
            "financials": {
                "capital": "50,000 kr",
                "employees": {
                    "industriarb": 65
                }
            },
            "foundation_year": 1932,
            "director": null,
            "board": [
                {
                    "name": "fabr. Axel Andersson",
                    "role": "ordf."
                },
                {
                    "name": "verkstadschef Karl-Edvard Dahlén",
                    "role": null
                },
                {
                    "name": "dir. Allan Holmqvist",
                    "role": null
                }
            ],
            "managing_director": null,
            "sales_manager": null,
            "manager": null
        },
        "4": {
            "name": "Elfsborgs Mek. Verkstad",
            "location": "Göteborg",
            "business": "Metallsprutor och plåtarbeten",
            "contact": {
                "office": "Kanaltorget 1, Göteborg",
                "phone": "116519"
            },
            "financials": {
                "capital": "150,000 kr",
                "employees": {
                    "industriarb": 30
                }
            },
            "foundation_year": 1912,
            "director": "kapten Rudolf Hedberg",
            "board": [],
            "owners": []
        },
        "5": {
            "name": "Elfströms Tekniska Fabrik",
            "location": "Gävle",
            "business": "Tillverkning av tvättvål och ljus",
            "contact": {
                "office": "N/A",
                "telegraph": "Elfströmsfabrik, Gävle",
                "postgiro": "21414"
            },
            "financials": {
                "capital": "154,200 kr",
                "employees": {
                    "industriarb": 21
                }
            },
            "foundation_year": 1912,
            "corporation_year": 1927,
            "director": "Öarl A. Elfström",
            "board": [],
            "owners": []
        }
    }
}