{
    "original": "Kylhammar—Källdalen\n\narb.: 25. Tillv.-värde pr år: 400,000 kr.\n— Firman etabl. 1942.\n\nVerkst. dir.: disp. Aage\nBorup-Jörgen-sen.\n\nDriftsing.: Svend Hoffmann.\n\n\"Kylhammars Nysilverfabrik,\n\nNacka.\n\nMetallvarufabrik i Sickla (Sthlms l.).\nTillverkar bordsbestick i nysilver och\nrostfritt stål.\n\nPostadr.: Nacka. Telefon: 421098 o.\n424411. Postgiro: 3035. — Antal\nindustriarb.: 50. Tillv.-värde pr år: 500,000\nkr. — Firman etabl. 1925.\n\nÄgare o. chef: fabr. Thure Kylhammar.\nKamrer: Josef Kylhammar.\n\n*Kyrkebyns Sulfitfabrik, Segmon.\nSe Billeruds AB.. Säffle.\n\n*AB. Kåbergs Tapetfabrik,\n\nStockholm.\n\nTillverkar tapeter och bårder vid fabrik\ni Handen (Sthlms l.). Specialitet:\noljefärgstapeten »Sanatin».\n\nHuvudkontor: Handen; postadr.:\nStockholm 1. Telegr.-adr.: Kåbergs, Stockholm.\nTelefon: Handen 303. Postgiro: 3710.\nUtställnings- o. försäljn.-lokal:\nStockholm, Malmskillnadsg. 30; telefon:\n100436.\n\nAkt.-kap.: 100,000 kr. Antal\nindustriarb.: 30. Tillv.-värde pr år: 500,000 kr.\n\n—\tFirman grundades 1856.\n\nStyrelse: dir. Carl Hagberg (ordf.), v.\nhovaudjtör N. A. Erdmann, med. kand.\nIng-Britt Hagberg.\n\nVerkst. dir.: Carl Hagberg.\n(Jfr annons nr 20.)\n\n*AB. E. Kågström &amp; Co., Skellefteå.\n\nGarveri och skofabrik. Tillverkar\npjäx-läder, pjäxor och sportskodon samt\narbetshandskar. Bolaget driver även\nengroshandel med läder, skodon, galoscher oeh\nandra ytter skor av gummi.\n\nTelegr.-adr.: Kågströms, Skellefteå.\nTelefon: 10086. Postgiro: 10509.\n\nAkt.-kap.: 110,000 kr. Antal\nindustriarb.: 20. Tillv.-värde pr år: 365,000 kr.\n\n—\tFirman etabl. 1881, bolag 1942.\nStyrelse: fabr. Simon Kågström (ordf.),\n\nfru Greta Kågström, fru Signhild\nKågström.\n\nVerkst. dir.: Simon Kågström.\nKamrer: O. Häggbom.\n\n*Kårbergs Manufakturverk,\n\nSkyllberg.\n\nSe Skyllbergs Bruks AB., Skyllberg.\n\nKåwe, Elektriska AB., Sundbyberg.\n\nSe Elektriska AB. Kåwe, Sundbyberg.\n\n*KåällmÖbler AB., Anneberg.\n\nTillverkar möbler vid fabrik i\nAnne-berg (Hallands l.).\n\nTelefon: »Kåällmöbler». Postgiro:\n145719. — Akt.-kap.: 15,000 kr. Antal\nindustriarb.: 30. — Fabriken anlagd\n1918, bolag 1940.\n\nStyrelse o. verkst. dir.: Knut\nLandquist.\n\n*AB. Gustaf Kähr, Nybro.\n\nTräförädlingsfabrik i Nybro (Kalmar\n1.). Tillverkar lamelldörrar, lamellgolv,\ndäcksplank, lamellträ för fartyg, möbler\noch leksaker.\n\nTelegr.-adr.: Kähr, Nybro. Telefon:\n»Kährs fabriker». Postgiro: 13090.\n\nAkt.-kap.: 450,000 kr. Antal\nindustriarb.: 225. — Fabriken anlagd 1857,\nbolag 1919.\n\nStyrelse o. verkst. dir.: Gustaf Kähr.\n\nDisp.: Olof Kähr.\n\n*Källans Vattenfabrik, Karlshamn.\n\nSe Carlshamns Bryggeri AB.,\nKarlshamn.\n\n*Källbergs Industri AB., Töreboda.\n\nLivsmedels- och kem. tekn. fabrik.\nTillverkar mjölkkonserver och kemikalier.\n\nTelegr.-adr.: Kibol, Töreboda. Telefon:\n370. Postgiro: 97719.\n\nAkt.-kap.: 200,000 kr. Antal\nindustriarb.: 15. Tillv.-värde pr år: 2,000,000 kr.\n— Bolaget grundat 1945.\n\nStyrelse: dir. Lennart Källberg, disp.\nStig\" Källberg.\n\nVerkst. dir.: Lennart Källberg.\n\nDisp.: Stig Källberg.\n\nDriftsledare: ing. Erik Knudsen.\n\nAB. Källdalens Industrier,\n\nFridhemsberg.\n\nTrävaru- och metallindustri samt\ngal-vaniseringsanstalt i Fridhemsberg\n(Hallands l.). Tillverkar byggnadssnickerier\n(spec. dörrar och inredningar) samt\nmetall-lister. Bolaget driver även handel\nmed trävaror och byggnadsmateriel.",
    "structured": {
        "firms": [
            {
                "name": "Kylhammars Nysilverfabrik",
                "location": "Nacka",
                "business": "Metallvarufabrik",
                "products": "Tillverkar bordsbestick i nysilver och rostfritt stål",
                "contact": {
                    "office": "Nacka",
                    "phone": [
                        "421098",
                        "424411"
                    ],
                    "postgiro": "3035",
                    "head_office": "Nacka",
                    "industrial_office": "Sthlms l.",
                    "factory_phone": "500,000 kr"
                },
                "financials": {
                    "capital": "500,000 kr",
                    "employees": {
                        "industriarb": 50
                    },
                    "annual_turnover": "500,000 kr",
                    "annual_production_value": "500,000 kr"
                },
                "foundation_year": 1925
            },
            {
                "name": "AB. Kåbergs Tapetfabrik",
                "location": "Stockholm",
                "business": "Tillverkar tapeter och bårder",
                "products": "Specialitet: oljefärgstapeten »Sanatin»",
                "contact": {
                    "office": "Handen",
                    "phone": "Stockholm, Malmskillnadsg. 30; telefon: 100436",
                    "postgiro": "3710",
                    "head_office": "Handen",
                    "industrial_office": "Sthlms l."
                },
                "financials": {
                    "capital": "100,000 kr",
                    "employees": {
                        "industriarb": 30
                    },
                    "annual_turnover": "500,000 kr"
                },
                "foundation_year": 1856
            },
            {
                "name": "AB. E. Kågström & Co.",
                "location": "Skellefteå",
                "business": "Garveri och skofabrik",
                "products": "Tillverkar pjäxläder, pjäxor och sportskodon samt arbetshandskar. Driver engroshandel med läder, skodon, galoscher och andra ytterskor av gummi",
                "contact": {
                    "office": "Skellefteå",
                    "phone": "10086",
                    "postgiro": "10509"
                },
                "financials": {
                    "capital": "110,000 kr",
                    "employees": {
                        "industriarb": 20
                    },
                    "annual_turnover": "365,000 kr"
                },
                "foundation_year": 1881
            },
            {
                "name": "Kåällmöbler AB.",
                "location": "Anneberg",
                "business": "Tillverkar möbler",
                "contact": {
                    "phone": "»Kåällmöbler»",
                    "postgiro": "145719"
                },
                "financials": {
                    "capital": "15,000 kr",
                    "employees": {
                        "industriarb": 30
                    }
                },
                "foundation_year": 1918
            },
            {
                "name": "AB. Gustaf Kähr",
                "location": "Nybro",
                "business": "Träförädlingsfabrik",
                "products": "Tillverkar lamelldörrar, lamellgolv, däcksplank, lamellträ för fartyg, möbler och leksaker",
                "contact": {
                    "phone": "»Kährs fabriker»",
                    "postgiro": "13090"
                },
                "financials": {
                    "capital": "450,000 kr",
                    "employees": {
                        "industriarb": 225
                    }
                },
                "foundation_year": 1857
            },
            {
                "name": "Källbergs Industri AB.",
                "location": "Töreboda",
                "business": "Livsmedels- och kem. tekn. fabrik",
                "products": "Tillverkar mjölkkonserver och kemikalier",
                "contact": {
                    "phone": "370",
                    "postgiro": "97719"
                },
                "financials": {
                    "capital": "200,000 kr",
                    "employees": {
                        "industriarb": 15
                    },
                    "annual_turnover": "2,000,000 kr"
                },
                "foundation_year": 1945
            },
            {
                "name": "AB. Källdalens Industrier",
                "location": "Fridhemsberg",
                "business": "Trävaru- och metallindustri samt galvaniseringsanstalt",
                "products": "Tillverkar byggnadssnickerier (spec. dörrar och inredningar) samt metallister. Driver även handel med trävaror och byggmaterial",
                "foundation_year": 1945
            }
        ]
    }
}