{
    "original": "Eelde—Ehrriberg\n\nAkt.-kap.: 2,400,000 kr. Antal\nindustriarb.: 180. Årstillv.: 20,000 ton torr\nsulfitcellulosa, pappersmassa o.\nkonstsilkes-massa. — Bolaget grundat 1903.\n\nStyrelse: disp. B. Oulie (ordf.),\nkamrer Gust. Larsson, generaldir. A. Meidell.\n\nDisp.: B. Oulie.\n\nKamrer: Gust. Larsson.\n\nDriftsing.: P. Lidby.\n\nAB. C. Fritz Eelde &amp; Co.,\n\nStockholm.\n\nLimfabrik. Tillverkar ljumlim och\nkall-lim.\n\nKontor: Dalag. 4. Telefon: 210294.\nPostgiro: 55467. — Akt.-kap.: 35,000 kr.\nTillv.-värde pr år: 100,000 kr. — Firman\netabl. 1936, bolag 1942.\n\nVerkst. dir.: disp. O. Fritz Eelde.\n\nKamrer: Nils H. Legnell.\n\n*Ege Färg- &amp; Fernissindustri,\n\nGöteborg.\n\nTillverkar olje- och spritfernissor,\nkom-binationslacker (»Torco 2-lack»),\noljefärger, pansar-, maskin- och redskapsfärger,\nemulsionsfärger (»Torcomatt»),\nmaskeringsfärger, mörkläggningsfärger,\nspackelfärger, kitt m. m. Varumärke: »Ege».\n\nKontor: Tuvevägen, postadr.: Göteborg\nH. Telegr.-adr. o. telefon: Egefärg,\nGöteborg. Postgiro: 44816. Avd.-kontor:\nStockholm, Pontonjärg. 36, telefon:\n516974 o. 516045; Malmö, N. Vallg. 82,\ntelefon; 31980; Sundsvall, telefon: 56285.\n• Antal industriarb.: 15. Tillv.-värde pr\når: 1,500,000 kr. — Firman etabl. 1937.\n\nÄgare o. chef: dir. Sven A. Höglund.\n\nEgelin &amp; Nilsson, Stockholm.\n\nModell- och snickerifabrik. Tillverkar\ngjutmodeller av trä, byggnadssnickerier\nm. m.\n\nKontor: Brännkyrkag. 124. Telefon:\n407458—59. Postgiro: 52302. — Antal\nindustriarb.: 28. Tillv.-värde pr år:\n360,000 kr. — Firman etabl. 1897.\n\nÄgare o. chef: fabr. Einar Egelin.\n\n*AB. Egna Hem Vetlandahus,\n\nVetlanda.\n\nTillverkar monteringsfärdiga trähus.\nTelefon: »Vetlandahus». Exportrepr.:\nFörenade Trähusfabriker, Förening u.p.a.,\nStockholm, Kungsg. 39, telefon: 202416.\n\nAkt.-kap.: 50,400 kr. Antal\nindustriarb.: 125. Tillv.-värde pr år: 7,000,000 kr.\n— Firman etabl. 1930, nuv. namn 1935.\n\nStyrelse: disp. Bertil Anderson (ordf.),\ngodsäg. Joel Hallert, kamrer O. L.\nSkärlén.\n\nDisp.: Bertil Anderson.\nKamrer: O. L. Skärlén.\n\n*Egnell &amp; Co., Väveri AB.y\n\nNorrköping.\n\nSe Väveri AB. Egnell &amp; Co., Norrköp.\n\n*Egnetls Bryggeri, Eksjö.\n\nSe AB. Smålands Bryggerier,\nJönköping.\n\n*AB. Egneilska Boktryckeriet,\n\nStockholm.\n\nBok- och ståltryckeri samt bokbinderi.\nUtför boktryck, bank- och\nförsäkringstryck, affärstryck, ståltryck, illustr.\nkataloger, tidskrifter, självkopierings- och\nkortsystem m. m.\n\nKontor: Artillerig. 8. Telegr.-adr.:\nEbe-tryck, Stockholm. Telefon: 601383—84.\nPostgiro: 151400.\n\nAkt.-kap.: 85,000 kr. Arb.-antal: 10.\nTillv.-värde pr år: 200,000 kr. — Firman\netabl. 1919, bolag 1920.\n\nStyrelse: dir. Göran Boije af Gennäs\n(ordf.), fru Lalla Boije af Gennäs, ryttm.\nChrister Boije af Gennäs.\n\nVerkst. dir.: Göran Boije af Gennäs.\n\n(Jfr annons nr 100.)\n\n*AB. Alfr. Ehrlin, Tranås.\n\nTillverkar möbler vid snickerifabrik i\nTranås (Jönköp. l.).\n\nTelefon: 2146. Postgiro: 143563. —\nAkt.-kap.: 31,500 kr. Antal industriarb.:\n14. Tillv.-värde pr år: 250,000 kr. —\nFirman etabl. 1923, bolag 1944.\n\nStyrelse: fabr. Tage Ehrlin (ordf.),\nfabr. Knut Ehrlin, fabr. Olof Ehrlin.\n\nChef: fabr. Tage Ehrlin.\n\n*AB. Ehrnberg &amp; Sons Läderfabrik,\n\nSimrishamn.\n\nTillverkar botten-, platt-, rem- och\nrandläder, vegetabiliskt och kromgarvat\novanläder, reseffekt-, sandal-, bokbinderi-,\nmöbel- och automobilläder,\nbeklädnadsläder, handskläder och andra färgade\nläderslag samt pegamoid. Varunamn:\n»Ehrnbergsläder», »Cimbria» o.\n»Scania».\n\nTelegr.-adr. o. telefon:\n»Ehrnbergsläder», Simrishamn. Postgiro: 71300.",
    "structured": {
        "1": {
            "name": "Eelde-Ehrriberg",
            "financials": {
                "capital": "2,400,000 kr",
                "employees": {
                    "industriarb": 180
                },
                "annual_turnover": "20,000 ton torr sulfitcellulosa, pappersmassa o. konstsilkes-massa"
            },
            "foundation_year": 1903,
            "board": [
                {
                    "name": "B. Oulie",
                    "role": "ordf."
                },
                {
                    "name": "Gust. Larsson",
                    "role": "kamrer"
                },
                {
                    "name": "A. Meidell",
                    "role": "generaldir."
                }
            ],
            "director": "B. Oulie",
            "contact": {
                "office": "Dalag. 4",
                "phone": [
                    "210294"
                ],
                "postgiro": "55467"
            }
        },
        "2": {
            "name": "AB. C. Fritz Eelde & Co.",
            "location": "Stockholm",
            "business": "Limfabrik",
            "products": "Tillverkar ljumlim och kall-lim",
            "financials": {
                "capital": "35,000 kr",
                "annual_production_value": "100,000 kr"
            },
            "foundation_year": 1936,
            "owner": "O. Fritz Eelde",
            "contact": {
                "office": "Pontonjärg. 36",
                "phone": "516974 o. 516045",
                "postgiro": "55467"
            }
        },
        "3": {
            "name": "Ege Färg- & Fernissindustri",
            "location": "Göteborg",
            "business": "Tillverkar olje- och spritfernissor, kombinationslacker",
            "products": "oljefärger, pansar-, maskin- och redskapsfärger, emulsionsfärger (»Torcomatt»), maskeringsfärger, mörkläggningsfärger, spackelfärger, kitt m. m.",
            "contact": {
                "office": "Tuvevägen",
                "phone": "Egefärg, Göteborg",
                "postgiro": "44816"
            },
            "financials": {
                "employees": {
                    "industriarb": 15
                },
                "annual_production_value": "1,500,000 kr"
            },
            "owner": "Sven A. Höglund"
        },
        "4": {
            "name": "Egelin & Nilsson",
            "location": "Stockholm",
            "business": "Modell- och snickerifabrik",
            "products": "Tillverkar gjutmodeller av trä, byggnadssnickerier m. m.",
            "contact": {
                "office": "Brännkyrkag. 124",
                "phone": "407458—59",
                "postgiro": "52302"
            },
            "financials": {
                "employees": {
                    "industriarb": 28
                },
                "annual_production_value": "360,000 kr"
            },
            "owner": "Einar Egelin"
        },
        "5": {
            "name": "AB. Egna Hem Vetlandahus",
            "location": "Vetlanda",
            "business": "Tillverkar monteringsfärdiga trähus",
            "contact": {
                "phone": "Vetlandahus"
            },
            "financials": {
                "capital": "50,400 kr",
                "employees": {
                    "industriarb": 125
                },
                "annual_production_value": "7,000,000 kr"
            },
            "foundation_year": 1930,
            "current_name_year": 1935,
            "board": [
                {
                    "name": "Bertil Andersson",
                    "role": "ordf."
                },
                {
                    "name": "Joel Hallert",
                    "role": "godsäg."
                },
                {
                    "name": "O. L. Skärlén",
                    "role": "kamrer"
                }
            ],
            "director": "Bertil Andersson"
        },
        "6": {
            "name": "Egnell & Co., Väveri AB",
            "location": "Norrköping",
            "business": "Se Väveri AB. Egnell & Co."
        },
        "7": {
            "name": "Egnetls Bryggeri, Eksjö",
            "location": "Se AB. Smålands Bryggerier, Jönköping"
        },
        "8": {
            "name": "AB. Egneilska Boktryckeriet",
            "location": "Stockholm",
            "business": "Bok- och ståltryckeri samt bokbinderi",
            "products": "Utför boktryck, bank- och försäkringstryck, affärstryck, ståltryck, illustr. kataloger, tidskrifter, självkopierings- och kortsystem m. m.",
            "contact": {
                "office": "Artillerig. 8",
                "phone": "601383—84",
                "postgiro": "151400"
            },
            "financials": {
                "capital": "85,000 kr",
                "employees": {
                    "arb.-antal": 10
                },
                "annual_production_value": "200,000 kr"
            },
            "foundation_year": 1919,
            "corporation_year": 1920,
            "board": [
                {
                    "name": "Göran Boije af Gennäs",
                    "role": "ordf."
                },
                {
                    "name": "Lalla Boije af Gennäs",
                    "role": "fru"
                },
                {
                    "name": "Christer Boije af Gennäs",
                    "role": "ryttm."
                }
            ],
            "director": "Göran Boije af Gennäs"
        },
        "9": {
            "name": "AB. Alfr. Ehrlin",
            "location": "Tranås",
            "business": "Tillverkar möbler vid snickerifabrik i Tranås (Jönköp. l.)",
            "contact": {
                "phone": "2146",
                "postgiro": "143563"
            },
            "financials": {
                "capital": "31,500 kr",
                "employees": {
                    "industriarb": 14
                },
                "annual_production_value": "250,000 kr"
            },
            "foundation_year": 1923,
            "corporation_year": 1944,
            "board": [
                {
                    "name": "Tage Ehrlin",
                    "role": "fabr."
                },
                {
                    "name": "Knut Ehrlin",
                    "role": "fabr."
                },
                {
                    "name": "Olof Ehrlin",
                    "role": "fabr."
                }
            ],
            "director": "Tage Ehrlin"
        },
        "10": {
            "name": "AB. Ehrnberg & Sons Läderfabrik",
            "location": "Simrishamn",
            "business": "Tillverkar botten-, platt-, rem- och randläder",
            "products": "vegetabiliskt och kromgarvat ovanläder, reseffekt-, sandal-, bokbinderi-, möbel- och automobilläder, beklädnadsläder, handskläder och andra färgade läderslag samt pegamoid"
        }
    }
}