{
    "original": "Rami ösa—-Ranten\n\n*AB. Ram lösa Hälsobrunn,\n\nRamlösabrunn.\n\nTappning av naturligt alkaliskt vatten\n(Ramlösavatten) vid Ramlösabrunn\n(Malmöh. l.). Bolaget driver även\nhälsobrunns-rorelse och jordbruk.\n\nTelegr.-adr.: Alkäl, Hälsingborg.\nTelefon: »Ramlösa Hälsobrunn», Hälsingborg.\nPostgiro: 6255. — Akt.-kap.: 889,000 kr.\nAntal industriarb. r 25. Produktionsvärde\npr år: 2,160,000 kr.\n\nRamlösa Hälsobrunn kom under\nmedicinsk Ifedning är IfOf; firman- ombildädes\ntill aktiebolag 1896.\n\nStyrelse: disp. Henry Dunker (ordf.),\ndir. §ven Schwartz (v. ordf.), disp. Nils\nG. Arvedson, dir. Harald Engström, disp.\nFredrik Jungbeck, dir. Erik Malmquist,\nciviling. Erik Olson.\n\nVerkst. dir.: ryttm. Ulf G. Olsson.\n\nKamrer: Ewert Ekblom.\n\n*\tRamlösa Skofabrik, Ramlösa.\n\nSe Malmgrens Skofabriks AB.,\nRamlösa.\n\n*\tRamnäs Bruks A B., Ra mnäs.\n\nJärnverk med lancashiresmedja,\nvalsverk, kättingfabrik, pressverkstad och\nmek. verkstad samt sågverk vid Ramnäs\n(Västmanl. l.).\n\nTillverkar lancashirejärn, kätting,\npressgods, sågade trävaror och träkol;\nspecialiteter: svetsad ankarkätting och rostfria\ndiskbänkar. Bolaget idkar jämväl\njordbruk och skogshantering.\n\nTelegr.-adr.: Ramnäsbolag, Kolbäck.\nTelefon: Ramnäs 5, 41 o. 96. Postgiro:\n(»433. .\n\nAkt.-kap.: 3.393,000 kr. Antal\nindustriarb.: 220. Tillv.-värde pr år: 4,500,000 kr.\n\nBruket, anlagt på 1500-talet, övertogs\nav nuv. bolag 1874, ny bolagsordning\n1912, ändrad 1929. Bolaget äger\nWirsbo-Ramnäs Kraft AB. och Ferna Bruks AB.\n\nStyrelse: dir. Bengt Ingeström (ordf.),\ndisp. Hans v. Kantzow, generalkonsul\nRagnar Söderberg, disp. Bertil\nTilländer. ;\n\nVerkst. dir. o. disp.: Bertil Tilländer.\n\nKamrer: Ivar Jonasson.\n\nRamonafabriken, Stockholm.\n\nMusikinstrumentfabrik. Tillverkar\nstränginstrument samt grammofoner.\nVarumärken: »Ramona», »Cremona Rex» o.\n»Caruso».\t&lt;\n\nKöntor: Wollmar Yxkullsgatan 89.\nTelegr.-adr.: Ramona, Stockholm. Telefon:\n419510 o. 419531. Postgiro: 56515.\n\nAntal industriarb.: 10. Tillv.-värdé /pr\når: 250,000 kr. — Firman etabl. 1933,\n\nÄgare o. chef: fabr. Harry Svalfors:\n\nW. Ramsays Torrbatterifabrik»\n\nLinköping.\n\nSe Svenska AB. Lé Carbone,\nSundbyberg.\ti\n\n* AB. Ranaverken, Göteborg.\n\nKonstharts- och metallvaruf abrik.\nTillverkar konsthartsprodukter i bakelit,\npo-lyvinylklorid oéh Éndrä preSsinasior;\nSpecialitet: kompletta, monterade elektr.\ndetaljer.\n\nKontor: Kungälvs vägen; postadr.:\nGöteborg II. Telefon: 22544Ö. Postgiro:\n45882.\n\nAkt.-kap.: 45,000 kr. Antal\nindustri-arb.: 68. Tillv.-värde pr år: 1,870,000 kr.\n\n- Bolaget grundat 1939.\n\nStyrelse o. verkst. dir.: disp. G. Th.\nAhlström.\n\nDriftsing en jörW) Lars Hellströöi o.\nHarry Järnebratt.\n\n*AB. Randfabriken Cimbria,\n\nSimrishamn.\n\nLädeijvaruf abrik. Tillverkar arbets- och\ncliaufförhandskar, cykelhandskar,\nutrustningsartiklar för hundar och hästar,\njakt-utrustningsartikiar, kart- och\nkamera-fodral, bagage- och livremmar,\nlädermanschetter och -packningar, motoristhuvor\noch motoristremmar, éadélmkkeriartiklar,\nsportväskor, skidbindningar,\nskidhand-skar, skridskoremmar m. m.\ti\n\nTelegr.-adr.: Randfabriken,\nSimrishamn. Telefon: 222 o. 666. Postgiro:\n33430.\n\nAkt.-kap.: 225,000 kr. Antal\nindustriarb.: 40. — Bolaget grundat 1920.\n\nStyrelse: dir. Gösta Ehrnberg (ordf.),\nbankdir. A. Ehrnberg, fröken Anna-Lisa\nEhrnberg.\n\nDisp.: E. Pfrunder.\n\n*AB. Rantens Hattfabrik,\n\nStockholm.\n\nHattfabriker i Stockholm och\nFalköping. Tillverkar strå-, filt- och tyghattar.\nVarumärke: »R. H.». Firman driver även\nengroshandel med modevaror.\n\nHuvudkontor: Stockholm, Kungsg. 32.\nTelegr.-adr.: Rantenshatt, Stockholm; ;Te-",
    "structured": {
        "1": {
            "name": "Ramlösa Hälsobrunn",
            "location": "Ramlösabrunn",
            "business": "Tappning av naturligt alkaliskt vatten",
            "products": "Ramlösavatten, hälsobrunns-rorelse och jordbruk",
            "contact": {
                "office": "Ramlösa Hälsobrunn, Hälsingborg",
                "phone": [
                    "Ramlösa Hälsobrunn, Hälsingborg"
                ],
                "postgiro": "6255",
                "head_office": "Alkäl, Hälsingborg",
                "telegraph": "Alkäl, Hälsingborg"
            },
            "financials": {
                "capital": "889,000 kr",
                "employees": {
                    "industriarb": 25
                },
                "annual_turnover": "2,160,000 kr",
                "annual_production_value": "2,160,000 kr"
            },
            "foundation_year": 1896,
            "board": [
                {
                    "name": "Henry Dunker",
                    "role": "ordf."
                },
                {
                    "name": "Sven Schwartz",
                    "role": "v. ordf."
                },
                {
                    "name": "Nils G. Arvedson",
                    "role": "disp."
                },
                {
                    "name": "Harald Engström",
                    "role": "dir."
                },
                {
                    "name": "Fredrik Jungbeck",
                    "role": "disp."
                },
                {
                    "name": "Erik Malmquist",
                    "role": "dir."
                },
                {
                    "name": "Erik Olson",
                    "role": "civiling."
                }
            ],
            "director": "ryttm. Ulf G. Olsson",
            "manager": "Ewert Ekblom"
        },
        "2": {
            "name": "Ramlösa Skofabrik",
            "location": "Ramlösa"
        },
        "3": {
            "name": "Ramnäs Bruks A B",
            "location": "Ramnäs",
            "business": "Järnverk med lancashiresmedja, valsverk, kättingfabrik, pressverkstad och mek. verkstad samt sågverk",
            "products": "lancashirejärn, kätting, pressgods, trävaror, träkol, svetsad ankarkätting, rostfria diskbänkar, jordbruk och skogshantering",
            "contact": {
                "office": "Wirsbo-Ramnäs Kraft AB, Ferna Bruks AB, Kolbäck",
                "phone": [
                    "Ramnäs 5",
                    "Ramnäs 41",
                    "Ramnäs 96"
                ]
            },
            "financials": {
                "capital": "3,393,000 kr",
                "employees": {
                    "industriarb": 220
                },
                "annual_turnover": "4,500,000 kr",
                "annual_production_value": "4,500,000 kr"
            },
            "predecessor": "övertogs av nuv. bolag 1874",
            "board": [
                {
                    "name": "Bengt Ingeström",
                    "role": "ordf."
                },
                {
                    "name": "Hans v. Kantzow",
                    "role": "disp."
                },
                {
                    "name": "Ragnar Söderberg",
                    "role": "generalkonsul"
                },
                {
                    "name": "Bertil Tilländer",
                    "role": "disp."
                }
            ],
            "director": "Bertil Tilländer",
            "manager": "Ivar Jonasson"
        },
        "4": {
            "name": "Ramonafabriken",
            "location": "Stockholm",
            "business": "Musikinstrumentfabrik",
            "products": "stränginstrument, grammofoner"
        },
        "5": {
            "name": "AB. Ranaverken",
            "location": "Göteborg",
            "business": "Konstharts- och metallvaruf abrik",
            "products": "konsthartsprodukter i bakelit, polyvinylklorid och andra pressformar; kompletta, monterade elektr. detaljer",
            "contact": {
                "office": "Göteborg II",
                "phone": [
                    "22544Ö"
                ]
            },
            "financials": {
                "capital": "45,000 kr",
                "employees": {
                    "industriarb": 68
                },
                "annual_turnover": "1,870,000 kr"
            },
            "corporation_year": 1939,
            "board": [
                {
                    "name": "G. Th. Ahlström",
                    "role": "disp."
                }
            ]
        },
        "6": {
            "name": "AB. Randfabriken Cimbria",
            "location": "Simrishamn",
            "business": "Lädeijvaruf abrik",
            "products": "arbets- och chiaufförhandskar, cykelhandskar, utrustningsartiklar för hundar och hästar, jaktutrustningsartiklar, kart- och kamerafodral, bagage- och livremmar, lädermanschetter och -packningar, motoristhuvor och motoristremmar, éadélmkkeriartiklar, sportväskor, skidbindningar, skidhandskar, skridskoremmar m. m."
        },
        "7": {
            "name": "AB. Rantens Hattfabrik",
            "location": "Stockholm",
            "business": "Hattfabriker",
            "products": "strå-, filt- och tyghattar",
            "contact": {
                "office": "Stockholm, Kungsg. 32",
                "phone": [
                    "419510",
                    "419531"
                ]
            },
            "manager": "fabr. Harry Svalfors"
        }
    }
}