{
    "original": "Industri—Industripapp\n\nIndustri Iwo AB., Mariestad.\n\nArmaturfabrik. Tillverkar elektr.\narmatur (spee. lysrörsarmatur) och\nmetallvaror samt utför svarvning.\n\nTelefon: 555 o. 575. Postgiro: 72379.\n\nAkt.-kap.: 10,000 kr. Antal\nindustriarb.: 72. Tillv.-värde pr år: 1,500,000 kr.\n— Firman etabl. 1938, nuv. bolag 1942.\n\nVerkst. dir.: fabr. Ivar Fransson.\n\n\"Industrikemikalier, Malmö.\n\nKemisk fabrik. Tillverkar sparbetmedel\nför järn och stål, fosfateringslösningar,\nkemikalier för glansförzinkning samt\nanalysrent natriumkromat. Varumärke för\nsparbetmedlen: »Ferripax».\n\nKontor: Rönneholmsvägen 28. Telefon:\n77240. Postgiro: 39740. Énsamförsälj. av\nsparbetmedel: A. Strejffert, Malmö,\nKristinelundsvägen 27 F, telefon: 17980.\n\nArb.-antal: 4. Tillv.-värde pr år:\n250,000 kr. — Firman etabl. 1937.\n\nÄgare o. chef: fil. lic. Claes\nHommer-berg.\n\n\"Industrikemiska AB., Stockholm.\n\nIngenjörsfirma. Exploaterar patenter\nå apparater och anläggningar för speciellt\nden kemiska industrien såsom\nindunst-ningsapparater, kolonnapparater,\nluft-nings- och absorptionsanläggningar,\nvattenrening, kolning, värmeväxlare,\nvarmgasapparater samt ugnar, vilka apparater\noch anläggningar tillverkas vid olika\nmek. verkstäder.\n\nKontor: Regeringsg. 109. Telegr.-adr.;\nInka, Stockholm. Telefon: 112411, 112450\no. 112482. Postgiro: 154928.\n\nAkt.-kap.: 165,000 kr. — Firman\ngrundad 1928.\n\nStyrelse: civiling. Reinhold Nauclér\n(ordf.), civiling. J. O. Nauclér, disp.\nRuben Persson, dir. Gustav Raabe, disp.\nGösta Schotte.\n\nVerkst. dir.: Ruben Persson.\n\növering.: J. O. Nauclér.\n\nIndustrikompaniet, Bertil Johanson,\n\nSkillingaryd.\n\nLädervarufabrik i Skillingaryd\n(Jönköp. l.). Tillverkar läderbälten, portföljer,\nshoppingväskor, ryggsäckar och\nsportväskor m. m., halvfabrikat i läder och\nskinn samt stansade massartiklar i läder.\n\nTelefon: 118. Postgiro: 73398. —\nAntal industriarb.: 25. — Firman etabl.\n1931.\n\nÄgare o. chef: fabr. Bertil Johanson.\n\nAB. Industrikompaniet King,\n\nHälsingborg.\n\nVelocipedfabrik. Varumärke: »King».\nFirman driver även engroshandel med\ncykeldelar.\n\nTelegr.-adr.: Industrikompani,\nHälsingborg. Telefon: 13795. Postgiro: 7994.\n\n—\tAkt.-kap.: 1,500,000 kr. Antal\nindustriarb.: 20. — Firman etabl. 1917, bolag\n1943.\n\nVerkst. dir.: Ernst I. Pålsson.\n\nI ndustri-Companiet,\nKonstharts-Produkter, Gemla.\n\nTillverkar massartiklar i bakelit och\nandra konsthartser vid fabrik i Gemla\n(Kronob. l.). Specialiteter:\nmaskintillbe-hör, elektr. installationsdetaljer och\nga-lanterivaror.\n\nTelefon: Växjö 67132. Postgiro: 84333.\n\n—\tAntal industriarb.: 12. Tillv.-värde pr\når: 100,000 kr. — Firman etbl. 1945.\n\nÄgare o. chefer: fabr. Tuve Törnqvist o.\nfabr. Lars Törnqvist.\n\n\"Industri &amp; Handels AB. Oscar\nLjungbergh, Jönköping.\n\nSnickerifabrik i Bergfors, Åker,\nmålnings och tapetserareverkstäder i\nSkillingaryd (båda i Jönköp. l.). Tillverkar\nmöbler, hjul, även med helböjda lötar samt\nåk- och seldonsartiklar.\n\nKontor: Jönköping. Telegr.-adr.:\nOljungbergh, Jönköping. Telefon: 3717\n—18—19. Postgiro: 23487.\n\nAkt.-kap.: 375,000 kr. Antal\nindustriarb.: 15. — Firman etabl. 1.882, bolag\n1935.\n\nStyrelse: dir. Oscar Ljungbergh (ordf.),\ndisp. Carl Ljungbergh, avd.-chef Nils\nLjungbergh.\n\nVerkst. dir.: Oscar Ljungbergh.\n\n\"AB. Industripapp, Mariestad.\n\nPappfabrik vid Sävenäs, Göteborg.\n\nTillverkar hårdpapp och\nkonstläder-papp (fibre boards) för tillverkning av\nreseffekter, boxar, spinnkannor m. m.,\nbokbinderipapp, papp för skoindustrien\nm. m. samt wellpapper.\n\nHuvud- o. försäljn.-kontor: Mariestad.\nTelegr.-adr. o. telefon: Industripapp,\nMariestad. Postgiro: 42169.\n\nAkt.-kap.: 350,000 kr. Antal\nindustriarb.: 200. Årstillv.: 5,500 ton papp o.\n3,500 ton papper. — Bolaget, grundat\n1916, äges av Katrinefors AB., Mariestad.\nBolaget äger E. J. Jonssons Pappers AB.,\nGöteborg.\n\n251*",
    "structured": {
        "1": {
            "name": "Industri Iwo AB.",
            "location": "Mariestad",
            "business": "Armaturfabrik",
            "products": "Tillverkar elektr. armatur (spee. lysrörsarmatur) och metallvaror samt utför svarvning",
            "contact": {
                "office": "Not provided",
                "phone": [
                    "555",
                    "575"
                ],
                "postgiro": "72379",
                "head_office": "Not provided",
                "sales_offices": [],
                "telegraph": "Not provided",
                "factory_office": "Not provided",
                "factory_phone": "Not provided"
            },
            "financials": {
                "capital": "10,000 kr",
                "employees": {
                    "industriarb": 72
                },
                "annual_turnover": "1,500,000 kr",
                "annual_production_value": "Not provided"
            },
            "foundation_year": 1938,
            "current_name_year": 1942,
            "predecessor": "Not provided",
            "original_name": "Not provided",
            "corporation_year": 1942
        },
        "2": {
            "name": "Industrikemikalier",
            "location": "Malmö",
            "business": "Kemisk fabrik",
            "products": "Tillverkar sparbetmedel för järn och stål, fosfateringslösningar, kemikalier för glansförzinkning samt analysrent natriumkromat",
            "contact": {
                "office": "Rönneholmsvägen 28",
                "phone": [
                    "77240"
                ],
                "postgiro": "39740",
                "head_office": "Not provided",
                "sales_offices": [
                    {
                        "location": "A. Strejffert, Malmö, Kristinelundsvägen 27 F",
                        "phone": "17980"
                    }
                ],
                "telegraph": "Not provided",
                "factory_office": "Not provided",
                "factory_phone": "Not provided"
            },
            "financials": {
                "capital": "Not provided",
                "employees": {
                    "industriarb": 4
                },
                "annual_turnover": "250,000 kr",
                "annual_production_value": "Not provided"
            },
            "foundation_year": 1937,
            "current_name_year": 1937,
            "predecessor": "Not provided",
            "original_name": "Not provided",
            "corporation_year": "Not provided"
        },
        "3": {
            "name": "Industrikemiska AB.",
            "location": "Stockholm",
            "business": "Ingenjörsfirma",
            "products": "Exploaterar patenter å apparater och anläggningar för speciellt den kemiska industrien",
            "contact": {
                "office": "Regeringsg. 109",
                "phone": [
                    "112411",
                    "112450",
                    "112482"
                ],
                "postgiro": "154928",
                "head_office": "Not provided",
                "sales_offices": [],
                "telegraph": "Inka, Stockholm",
                "factory_office": "Not provided",
                "factory_phone": "Not provided"
            },
            "financials": {
                "capital": "165,000 kr",
                "employees": {
                    "industriarb": "Not provided"
                },
                "annual_turnover": "Not provided",
                "annual_production_value": "Not provided"
            },
            "foundation_year": 1928,
            "current_name_year": 1928,
            "predecessor": "Not provided",
            "original_name": "Not provided",
            "corporation_year": "Not provided"
        },
        "4": {
            "name": "Industrikompaniet, Bertil Johanson",
            "location": "Skillingaryd",
            "business": "Lädervarufabrik",
            "products": "Tillverkar läderbälten, portföljer, shoppingväskor, ryggsäckar och sportväskor m. m., halvfabrikat i läder och skinn samt stansade massartiklar i läder",
            "contact": {
                "office": "Not provided",
                "phone": [
                    "118"
                ],
                "postgiro": "73398",
                "head_office": "Not provided",
                "sales_offices": [],
                "telegraph": "Not provided",
                "factory_office": "Not provided",
                "factory_phone": "Not provided"
            },
            "financials": {
                "capital": "Not provided",
                "employees": {
                    "industriarb": 25
                },
                "annual_turnover": "Not provided",
                "annual_production_value": "Not provided"
            },
            "foundation_year": 1931,
            "current_name_year": "Not provided",
            "predecessor": "Not provided",
            "original_name": "Not provided",
            "corporation_year": "Not provided"
        },
        "5": {
            "name": "AB. Industrikompaniet King",
            "location": "Hälsingborg",
            "business": "Velocipedfabrik",
            "products": "Firman driver även engroshandel med cykeldelar",
            "contact": {
                "office": "Not provided",
                "phone": [
                    "13795"
                ],
                "postgiro": "7994",
                "head_office": "Not provided",
                "sales_offices": [],
                "telegraph": "Industrikompani, Hälsingborg",
                "factory_office": "Not provided",
                "factory_phone": "Not provided"
            },
            "financials": {
                "capital": "1,500,000 kr",
                "employees": {
                    "industriarb": 20
                },
                "annual_turnover": "Not provided",
                "annual_production_value": "Not provided"
            },
            "foundation_year": 1917,
            "current_name_year": 1943,
            "predecessor": "Not provided",
            "original_name": "Not provided",
            "corporation_year": "Not provided"
        },
        "6": {
            "name": "Industri-Companiet",
            "location": "Gemla",
            "business": "Konstharts-Produkter",
            "products": "Tillverkar massartiklar i bakelit och andra konsthartser vid fabrik i Gemla (Kronob. l.)",
            "contact": {
                "office": "Not provided",
                "phone": [
                    "Växjö 67132"
                ],
                "postgiro": "84333",
                "head_office": "Not provided",
                "sales_offices": [],
                "telegraph": "Not provided",
                "factory_office": "Not provided",
                "factory_phone": "Not provided"
            },
            "financials": {
                "capital": "Not provided",
                "employees": {
                    "industriarb": 12
                },
                "annual_turnover": "100,000 kr",
                "annual_production_value": "Not provided"
            },
            "foundation_year": 1945,
            "current_name_year": "Not provided",
            "predecessor": "Not provided",
            "original_name": "Not provided",
            "corporation_year": "Not provided"
        },
        "7": {
            "name": "Industri & Handels AB. Oscar Ljungbergh",
            "location": "Jönköping",
            "business": "Snickerifabrik",
            "products": "Tillverkar möbler, hjul, även med helböjda lötar samt åk- och seldonsartiklar",
            "contact": {
                "office": "Not provided",
                "phone": [
                    "3717",
                    "18",
                    "19"
                ],
                "postgiro": "23487",
                "head_office": "Not provided",
                "sales_offices": [],
                "telegraph": "Oljungbergh, Jönköping",
                "factory_office": "Not provided",
                "factory_phone": "Not provided"
            },
            "financials": {
                "capital": "375,000 kr",
                "employees": {
                    "industriarb": 15
                },
                "annual_turnover": "Not provided",
                "annual_production_value": "Not provided"
            },
            "foundation_year": 1882,
            "current_name_year": 1935,
            "predecessor": "Not provided",
            "original_name": "Not provided",
            "corporation_year": "Not provided"
        },
        "8": {
            "name": "AB. Industripapp",
            "location": "Mariestad",
            "business": "Pappfabrik",
            "products": "Tillverkar hårdpapp och konstläderpapp (fibre boards) för tillverkning av reseffekter, boxar, spinnkannor m. m., bokbinderipapp, papp för skoindustrien m. m. samt wellpapper",
            "contact": {
                "office": "Mariestad",
                "phone": [],
                "postgiro": "42169",
                "head_office": "Not provided",
                "sales_offices": [],
                "telegraph": "Industripapp, Mariestad",
                "factory_office": "Not provided",
                "factory_phone": "Not provided"
            },
            "financials": {
                "capital": "350,000 kr",
                "employees": {
                    "industriarb": 200
                },
                "annual_turnover": "Not provided",
                "annual_production_value": "5,500 ton papp o. 3,500 ton papper"
            },
            "foundation_year": 1916,
            "current_name_year": "Not provided",
            "predecessor": "Not provided",
            "original_name": "Not provided",
            "corporation_year": "Not provided"
        }
    }
}