{
    "original": "Tunell—Tvätt\n\nAB. Gösta Tunell, Stockholm.\n\nMotor-mek. verkstad i Solna (Sthlms l.).\nTillverkar motorreservdelar, speciellt\nmotorkolvar av tackjärn och lättmetall samt\ncylinderfoder; utför renoveringar av\nförbränningsmotorer. Varumärke: »Ge-Te».\n\nPostadr.: Box 6053, Stockholm 6.\nTelegr.-adr.: Getekolv, Stockholm. Telefon:\n272670. Postgiro: 151720.\n\nAkt.-kap.: 130,000 kr. Antal\nindustriarb.: 100. Tillv.-värde pr år: 1,500,000 kr.\n— Bolaget grundat 1937.\n\nVerkst. dir.: Gösta Tunell.\n\nVerkstadschef: Nils Lindstam.\n\nFörsäljn.-chef: Sven Callerfelt.\n\n’Tuolluvaara Gruv AB., Tuolluvaara.\n\nJärnmalmsfält i Tuolluvaara\n(Norrbott. l.). Bryter järnmalm (magnetit).\n\nGruv- o. försäljn.-kontor: Tuolluvaara.\nTelegr.-adr.: Tuolluvaara, Kiruna.\nTelefon: Kiruna 91 o. 719 a. Direktörskontor:\nStockholm, Regeringsg. 1—3, telefon:\n107382,\n\nAkt.-kap.: 2,880,000 kr. — Bolaget\ngrundat 1900.\n\nStyrelse: disp. Einar Troili (ordf.),\ndir. Mauritz Carlson, dir. Erik G.\nPehrsson, disp. Evert Wijkander, disp. Hj.\nÅselius.\n\nVerkst. dir.: Mauritz Carlson (Sthlm).\n\nDisp.: Börje Grafström.\n\n*Turbinfabviks AB. Ljungström,\n\nFinspång.\n\nSe Svenska Turbinfabriks AB.\nLjungström, Finspång.\n\n*Turbo Sulfitfabrik, Vikmanshyttan.\n\nSe Wikmanshytte Bruks AB.,\nVikmanshyttan.\n\n’Turebergs Snickerifabrik,\n\nTureberg.\n\nTillverkar byggnadssnickerier, trappor\noch inredningar vid fabrik i Tureberg\n(Sthlms l.).\n\nTelefon: 350690. Postgiro: 138831. —\nAntal industriarb.: 12. Tillv.-värde pr år:\n200,000 kr. — Firman etabl. 1938.\n\nÄgare o. chef: fabr. Erik Andersson.\n\n’AB. Turion, Göteborg.\n\nChoklad- och konfektyrfabrik.\nTillverkar tabletter, konfektyrer, blockchoklad\nm. m. Varunamn: »Turion».\n\nKontor: S. Gubberog. 20. Telegr.-adr.:\n\nTurion, Göteborg. Telefon: 154551—53.\nPostgiro: 42425.\n\nAkt.-kap.: 110,000 kr. Antal\nindustriarb.: 50. Tillv.-värde pr år: 1,000,000 kr.\n\n—\tBolaget grundat 1913.\n\nStyrelse: adv. W. Kristensen (ordf.),\ndir. Carl Särner, disp. Gösta Särner.\n\nVerkst. dir.: Carl Särner.\n\nDisp.: Gösta Särner.\n\nHerman Twede AB., Malmö.\n\nFärg- och kem. teknisk fabrik.\nTillverkar färger, mineralfoder, medel mot\nogräs och skadedjur, antiseptiska medel,\nrengörings- och desinfektionsmedel,\nvitaminpreparat m. m.\n\nKontor: Botildenborgsvägen; postadr.:\nMalmö 13. Telegr.-adr.: Twedeoil, Malmö.\nTelefon: 12376 o. 20140. Postgiro: 147477.\n\nAkt.-kap.: 190,000 kr. Antal\nindustriarb.: 9. Tillv.-värde pr år: 110,000 kr. —\nBolaget grundat 1938.\n\nVerkst. dir.: Herman Twede.\n\nTvings Träindustri AB., Tving.\n\nSnickerifabrik i Tving (Blekinge l.).\nTillverkar byggnadssnickerier och\nhusinredningar m. m., spec. dörrar för export.\n\nTelegr.-adr.: Träindustrien, Tving.\nTelefon: 17. Postgiro: 74757.\n\nAkt.-kap.: 50,000 kr. Antal\nindustriarb.: 25. — Firman etabl. 1917, bolag\n1937.\n\nDisp.: Tor Brunberg.\n\n’Tvål- &amp; Parfymfabriken Viola AB.,\n\nGöteborg.\n\nKem.-tekn. fabrik. Tillverkar tvål, såpa,\nparfymer, ljus, såp- och tvättpulver samt\nandra kem.-tekn. preparater.\n\nKontor: Mölndalsv. 32. Telegr.-adr.:\nViola, Göteborg. Telefon: 161502.\nPostgiro: 12046.\n\nAkt.-kap.: 100,000 kr. Antal\nindustriarb.: 25. Tillv.-värde pr år: 1,000,000 kr.\n\n—\tFirman etabl. 1893, bolag 1913.\n\nStyrelse: dir. Birger Andersson, adv.\n\nG. Dellborg, fru Jane Jönsson, adv.\nJohan Ramberg, fru Dagny Welander.\n\nVerkst. dir.: Birger Andersson.\n\nKontorschef: Liss Kjellgren.\n\nAB. Tvätt- &amp; Pressningsmaskiner,\n\nStockholm.\n\nMek. verkstad å Stora Essingen,\nStockholm. Tillverkar konfektionsmaskiner\noch kostympressar. Varumärke:\n»Tri-Plex».\n\nKontor o. ensamförsälj.: Maskin AB.",
    "structured": {
        "1": {
            "name": "Tunell—Tvätt AB",
            "location": "Stockholm",
            "business": "Motor-mek. verkstad",
            "products": "Tillverkar motorreservdelar, speciellt motorkolvar av tackjärn och lättmetall samt cylinderfoder; utför renoveringar av förbränningsmotorer. Varumärke: »Ge-Te»",
            "contact": {
                "office": "Box 6053, Stockholm 6",
                "phone": [
                    "272670"
                ],
                "postgiro": "151720",
                "telegraph": "Getekolv, Stockholm"
            },
            "financials": {
                "capital": "130,000 kr",
                "employees": {
                    "industriarb": 100
                },
                "annual_turnover": "1,500,000 kr",
                "annual_production_value": "1,500,000 kr"
            },
            "foundation_year": 1937,
            "director": "Gösta Tunell",
            "manager": "Nils Lindstam",
            "sales_manager": "Sven Callerfelt"
        },
        "2": {
            "name": "Tuolluvaara Gruv AB",
            "location": "Tuolluvaara",
            "business": "Järnmalmsfält",
            "products": "Bryter järnmalm (magnetit)",
            "contact": {
                "office": "Tuolluvaara",
                "phone": "107382",
                "telegraph": "Tuolluvaara, Kiruna",
                "head_office": "Stockholm, Regeringsg. 1—3"
            },
            "financials": {
                "capital": "2,880,000 kr"
            },
            "foundation_year": 1900,
            "board": [
                {
                    "name": "Einar Troili",
                    "role": "disp."
                },
                {
                    "name": "Mauritz Carlson",
                    "role": "dir."
                },
                {
                    "name": "Erik G. Pehrsson",
                    "role": "dir."
                },
                {
                    "name": "Evert Wijkander",
                    "role": "disp."
                },
                {
                    "name": "Hj. Åselius",
                    "role": "disp."
                }
            ],
            "director": "Mauritz Carlson",
            "manager": "Börje Grafström"
        },
        "3": {
            "name": "Turebergs Snickerifabrik",
            "location": "Tureberg",
            "business": "Tillverkar byggnadssnickerier",
            "products": "Tillverkar byggnadssnickerier, trappor och inredningar vid fabrik i Tureberg (Sthlms l.)",
            "contact": {
                "phone": "350690",
                "postgiro": "138831"
            },
            "financials": {
                "employees": {
                    "industriarb": 12
                },
                "annual_production_value": "200,000 kr"
            },
            "foundation_year": 1938,
            "owner": "Erik Andersson"
        },
        "4": {
            "name": "AB. Turion",
            "location": "Göteborg",
            "business": "Choklad- och konfektyrfabrik",
            "products": "Tillverkar tabletter, konfektyrer, blockchoklad m. m. Varunamn: »Turion»",
            "contact": {
                "office": "S. Gubberog. 20",
                "phone": [
                    "154551",
                    "154552",
                    "154553"
                ],
                "postgiro": "42425"
            },
            "financials": {
                "capital": "110,000 kr",
                "employees": {
                    "industriarb": 50
                },
                "annual_production_value": "1,000,000 kr"
            },
            "foundation_year": 1913,
            "board": [
                {
                    "name": "W. Kristensen",
                    "role": "adv."
                },
                {
                    "name": "Carl Särner",
                    "role": "dir."
                },
                {
                    "name": "Gösta Särner",
                    "role": "disp."
                }
            ],
            "director": "Carl Särner",
            "manager": "Gösta Särner"
        },
        "5": {
            "name": "Herman Twede AB",
            "location": "Malmö",
            "business": "Färg- och kem. teknisk fabrik",
            "products": "Tillverkar färger, mineralfoder, medel mot ogräs och skadedjur, antiseptiska medel, rengörings- och desinfektionsmedel, vitaminpreparat m. m.",
            "contact": {
                "office": "Botildenborgsvägen, Malmö 13",
                "phone": [
                    "12376",
                    "20140"
                ],
                "postgiro": "147477",
                "telegraph": "Twedeoil, Malmö"
            },
            "financials": {
                "capital": "190,000 kr",
                "employees": {
                    "industriarb": 9
                },
                "annual_production_value": "110,000 kr"
            },
            "foundation_year": 1938,
            "director": "Herman Twede"
        },
        "6": {
            "name": "Tvings Träindustri AB",
            "location": "Tving",
            "business": "Snickerifabrik",
            "products": "Tillverkar byggnadssnickerier och husinredningar m. m., spec. dörrar för export",
            "contact": {
                "phone": "17",
                "postgiro": "74757",
                "telegraph": "Träindustrien, Tving"
            },
            "financials": {
                "capital": "50,000 kr",
                "employees": {
                    "industriarb": 25
                }
            },
            "foundation_year": 1917,
            "corporation_year": 1937,
            "manager": "Tor Brunberg"
        },
        "7": {
            "name": "Tvål- & Parfymfabriken Viola AB",
            "location": "Göteborg",
            "business": "Kem.-tekn. fabrik",
            "products": "Tillverkar tvål, såpa, parfymer, ljus, såp- och tvättpulver samt andra kem.-tekn. preparater",
            "contact": {
                "office": "Mölndalsv. 32",
                "phone": [
                    "161502"
                ],
                "postgiro": "12046",
                "telegraph": "Viola, Göteborg"
            },
            "financials": {
                "capital": "100,000 kr",
                "employees": {
                    "industriarb": 25
                },
                "annual_production_value": "1,000,000 kr"
            },
            "foundation_year": 1913,
            "board": [
                {
                    "name": "Birger Andersson",
                    "role": "dir."
                },
                {
                    "name": "G. Dellborg",
                    "role": "adv."
                },
                {
                    "name": "Jane Jönsson",
                    "role": "fru"
                },
                {
                    "name": "Johan Ramberg",
                    "role": "adv."
                },
                {
                    "name": "Dagny Welander",
                    "role": "fru"
                }
            ],
            "director": "Birger Andersson",
            "manager": "Liss Kjellgren"
        },
        "8": {
            "name": "AB. Tvätt- & Pressningsmaskiner",
            "location": "Stockholm",
            "business": "Mek. verkstad",
            "products": "Tillverkar konfektionsmaskiner och kostympressar. Varumärke: »Tri-Plex»",
            "contact": {
                "office": "Stora Essingen, Stockholm"
            }
        }
    }
}