{
    "original": "Tabergsmöbler—Tången\n\nSmålands Taberg. Telefon: 9.\nTelegr.-adr. : Maskinfabriken, Smålands Taberg.\nPostgiro: 163450.\n\nAkt.-kap.: 120,000 kr. Antal\nindustriarb.: 60. Tillv.-värde pr år: 700,000 kr.\n\n—\tBolaget grundat 1902.\n\nStyrelse: bergsing. T. An. Tesch (ordf.),\növering. Ernst Håkansson, ing. Edvin\nJohansson.\n\nVerkst. dir.: Ernst Håkansson (Sthlm).\n\nVerkstadschef: ing. Alef Järnesten.\n\n*AB. Tabergsmöbler,\n\nSmålands Taberg.\n\nTillverkar matsalsmöbler och\nkompletteringsmöbler vid fabrik i Smål. Taberg\n(Jönköp. l.). Specialitet: höj- och\nsänk-bara bord (märke: »Tabergsbordet»).\n\nTelefon: 65. Postgiro: 23425. —\nAkt.-kap.: 50,000 kr. Antal industriarb.: 30.\nTillv.-värde pr år: 400,000 kr. — Firman\netabl. 1921, bolag 1928.\n\nStyrelse: fabr. Frans Johansson\n(ordf.), fabr. Arvid Andersson, fabr.\nHilding Andersson.\n\nVerkst. dir.: Frans Johansson.\n\nTabergs Vadd- &amp; Madrassfabrik, B.\nJohansson &amp; Co., Smålands Taberg.\n\nTillverkar madrasser vid fabrik i\nSmålands Taberg (Jönköp. l.).\n\nTelefon: 93. Postgiro: 24965. — Antal\nindustriarb.: 5. — Firman etabl. 1933.\n\nÄgare: fabr. Bertil Johansson, fabr.\nErik Persson o. fabr. Gunnar Grahn.\n\nChef: Bertil Johansson.\n\n\"Tabergs Yllefabriks AB.,\n\nSmålands Taberg.\n\nYllefabrik med spinneri, väveri,\nberedningsverk och färgeri i Smålands Taberg\n(Jönköp. l.). Tillverkar möbeltyger,\nmattor (»Tabergsmattan»), filtar m. m.\n\nTelegr.-adr. o. telefon: Yllefabriken,\nSmålands Taberg. Postgiro: 23424.\n\nAkt.-kap.: 450,000 kr. Antal\nindustriarb.: 300. Tillv.-värde pr år: 3,000,000 kr.\n\n—\tBolaget grundat 1905.\n\nStyrelse: dir. J. Blomdahl (ordf.),\nbruksdisp. E. Hedenblad, kamrer M.\nHen-delberg.\n\nVerkst. dir. o. disp.: J. Blomdahl.\n\nKamrer: M. Hendelberg.\n\nDriftsing.: N. Börrisson.\n\n\"Tagelspinneri AB., Karlstad.\n\nSe Svenska Tagelspinneri AB.,\nKarlstad.\n\n\"Tagelspinneriet, Nya, Köping.\n\nSe Nya Tagelspinneriet, Janson &amp;\nArnold, Köping.\n\nAB. Takoleum, Stockholm.\n\nFabrik för tillverkning av\nbyggnadspapp i Trelleborg. Tillverkar\nasfalttakpapp, underhållsfri papp,\nförhydnings-papp m. m. Varumärke: »Takolit».\n\nHuvudkontor: Stockholm, Nybrog. 60.\nTelegr.-adr.: Takoleum, Stockholm.\nTelefon-. 600299. Postgiro: 156851.\nFabrikskontor: Trelleborg, telefon: 150.\n\nAkt.-kap.: 225,000 kr. Antal\nindustriarb.: 15. Tillv.-värde pr år: 500,000 kr.\n— Bolaget grundat 1935.\n\nStyrelse: herr Ivar Suneson (ordf.),\ndir. Bo Huldt, fru Dagmar Huldt.\n\nVerkst. dir.: Bo Huldt.\n\nPlatschef: F. Ljungh.\n\nTalcum, Fabriks AB., Strömsund.\n\nSe Fabriks AB. Talcum, Strömsund.\n\n\"AB. Tallåsens Fabriker, Tallåsen.\n\nTillverkar tävlings-, turist- och\nbarnskidor samt stolar, kompletteringsmöbler,\nträdgårdsmöbler och snickerier samt\nsvarvade trävaror vid fabrik i Tallåsen\n(Gävleb. l.).\n\nTelefon: »Tallåsens fabriker».\nPostgiro: 166391. — Akt.-kap.: 400,000 kr.\nAntal industriarb.: 150. Tillv.-värde pr\når: 1,600,000 kr.\n\nRörelsen har tidigare bedrivits under\nnamn Mikael Larssons Skidfabrik,\nHudiksvall; bolag under nuv. namn 1939.\n\nStyrelse: dir. N. Osk. Jonsson,\nförsäljn.-chef Alfred Strömbäck.\n\nVerkst. dir.: N. Osk. Jonsson.\n\n\"Tallåsens Snickerifabrik, Nordström\n&amp; Co., AB., Tallåsen.\n\nTillverkar byggnadssnickerier och\ninredningar vid fabrik i Tallåsen\n(Gävleb. l.).\n\nTelefon: 7. Postgiro: 130537. —\nAkt.-kap.: 75,500 kr. Antal industriarb.: 20.\nTillv.-värde pr år: 280,000 kr. — Firman\netabl. 1936, bolag 1942.\n\nStyrelse: dir. Helmer Nordström\n(ordf.), verkmäst. Gustaf Nilsson,\nförman Olov Norén.\n\nVerkst. dir.: Helmer Nordström.\n\n\"Tångens Gardinfabrik AB.,\n\nStockholm.\n\nTillverkar tyllgardiner, trådgardiner\noch konstsilkegardiner, draperityger,",
    "structured": {
        "1": {
            "name": "AB. Tabergsmöbler",
            "location": "Smålands Taberg",
            "business": "Matsalsmöbler och kompletteringsmöbler",
            "products": "Tillverkar matsalsmöbler och kompletteringsmöbler vid fabrik i Smål. Taberg (Jönköp. l.). Specialitet: höj- och sänk-bara bord (märke: »Tabergsbordet»).",
            "contact": {
                "office": "Smålands Taberg",
                "phone": [
                    "65"
                ],
                "postgiro": "23425"
            },
            "financials": {
                "capital": "50,000 kr",
                "employees": {
                    "industriarb": 30
                },
                "annual_turnover": "400,000 kr"
            },
            "foundation_year": 1921
        },
        "2": {
            "name": "Tabergs Vadd- & Madrassfabrik, B. Johansson & Co.",
            "location": "Smålands Taberg",
            "products": "Tillverkar madrasser vid fabrik i Smålands Taberg (Jönköp. l.).",
            "contact": {
                "office": "Smålands Taberg",
                "phone": [
                    "93"
                ],
                "postgiro": "24965"
            },
            "financials": {
                "employees": {
                    "industriarb": 5
                }
            },
            "foundation_year": 1933
        },
        "3": {
            "name": "Tabergs Yllefabriks AB.",
            "location": "Smålands Taberg",
            "products": "Yllefabrik med spinneri, väveri, beredningsverk och färgeri i Smålands Taberg (Jönköp. l.). Tillverkar möbeltyger, mattor (»Tabergsmattan»), filtar m. m.",
            "contact": {
                "office": "Smålands Taberg",
                "phone": [
                    "Yllefabriken"
                ],
                "postgiro": "23424"
            },
            "financials": {
                "capital": "450,000 kr",
                "employees": {
                    "industriarb": 300
                },
                "annual_turnover": "3,000,000 kr"
            },
            "foundation_year": 1905
        },
        "4": {
            "name": "AB. Takoleum",
            "location": "Stockholm",
            "products": "Fabrik för tillverkning av byggnadspapp i Trelleborg. Tillverkar asfalttakpapp, underhållsfri papp, förhydnings-papp m. m. Varumärke: »Takolit».",
            "contact": {
                "office": "Stockholm, Nybrog. 60",
                "phone": [
                    "600299"
                ],
                "postgiro": "156851",
                "factory_office": "Trelleborg",
                "factory_phone": "150"
            },
            "financials": {
                "capital": "225,000 kr",
                "employees": {
                    "industriarb": 15
                },
                "annual_turnover": "500,000 kr"
            },
            "corporation_year": 1935
        },
        "5": {
            "name": "AB. Tallåsens Fabriker",
            "location": "Tallåsen",
            "business": "Tävlings-, turist- och barnskidor samt stolar, kompletteringsmöbler, trädgårdsmöbler och snickerier samt svarvade trävaror",
            "products": "Tillverkar tävlings-, turist- och barnskidor samt stolar, kompletteringsmöbler, trädgårdsmöbler och snickerier samt svarvade trävaror vid fabrik i Tallåsen (Gävleb. l.).",
            "contact": {
                "office": "Tallåsens fabriker",
                "postgiro": "166391"
            },
            "financials": {
                "capital": "400,000 kr",
                "employees": {
                    "industriarb": 150
                },
                "annual_turnover": "1,600,000 kr"
            },
            "corporation_year": 1939
        },
        "6": {
            "name": "Tallåsens Snickerifabrik, Nordström & Co., AB.",
            "location": "Tallåsen",
            "business": "Byggnadssnickerier och inredningar",
            "products": "Tillverkar byggnadssnickerier och inredningar vid fabrik i Tallåsen (Gävleb. l.).",
            "contact": {
                "office": "Tallåsens fabriker",
                "phone": [
                    "7"
                ],
                "postgiro": "130537"
            },
            "financials": {
                "capital": "75,500 kr",
                "employees": {
                    "industriarb": 20
                },
                "annual_turnover": "280,000 kr"
            },
            "corporation_year": 1942
        },
        "7": {
            "name": "Tångens Gardinfabrik AB.",
            "location": "Stockholm",
            "business": "Tyllgardiner, trådgardiner och konstsilkegardiner, draperityger",
            "products": "Tillverkar tyllgardiner, trådgardiner och konstsilkegardiner, draperityger."
        }
    }
}