{
    "original": "Eskilstuna—Espagnolett fabriken\n\n^Eskilstuna Stålindustri, Eskilstuna.\n\nTillverkar rostfria bordsknivar och\ngafflar samt kaffekvarnar. Varumärke:\n»E S »\n\nTelefon: 30805. Postgiro: 10789. —\nAntal industriarb.: 23. Tillv.-värde pr år:\n240,000 kr. — Firman etabl. 1913.\n\nÄgare o. chef: fabr. W. L. Jernström.\n\n* Eskilstuna Stålpressnings AB.\nPressbolaget-Esklistuna,\n\nEskilstuna.\n\nPress-, förtennings- och\ngalvanise-ringsverk i Eskilstuna samt plåtvalsverk\noch elektr. vattenkraftstation vid\nSkogstorp (Södermanl. l.).\n\nTillverkar pressgods av järn- och\nstålplåt samt rostfritt material såsom delar\ntill separatorer, mjölktransportflaskor,\nmjölksilar, hushållskärl, renhållningskärl,\nväg- och reklamskyltar, stålhyllor m. m.;\ntunnplåt, särskilt pressplåt och\nanti-magnetisk järnplåt.\n\nTelegr.-adr. o. telefon: Pressbolaget,\nEskilstuna. Postgiro: 10712.\n\nAntal industriarb.: 580. Tillv.-värde pr\når: 12,000,000 kr. — Firman, etabl. 1893,\näges av AB. Separator, Stockholm.\n\nStyrelse: dir. Axel Wästfelt (ordf.),\ndir. Erik Brändström, dir. Richard\nDahlgren, dir. Folke Hellstedt.\n\nVerkst. dir.: Richard Dahlgren.\n\nKontorschef: S. E. Edwards.\n\nValsverksing.: Oscar Nilsson.\n\nEskilstuna Termometerfabrik,\n\nEskilstuna.\n\nTillverkar termometrar såsom\nfebertermometrar, rums- och\nfönstertermometrar, minimitermometrar,\nreklamtermometrar samt enklare glasinstrument och\nvattenpasslibellor.\n\nTelefon: 35125. Postgiro: 278246. —\nAntal industriarb.: 20. Tillv.-värde pr\når: 150,000 kr. — Firman etabl. 1941.\n\nÄgare o. chef: fabr. Fritz Feingold.\n\nEskilstuna Vattenpassfabrik,\n\nEskilstuna.\n\nVattenpassfabrik och\naluminiumgjute-ri. Tillverkar vattenpass av trä och\naluminium samt maskinvattenpass av\naluminium.\n\nTelefon: 32802. Postgiro: 90627. —\nArb.-antal: 11. Tillv.-värde pr år: 105,000\nkr. — Firman etabl. 1923.\n\nÄgare o. chef: fabr. Ax. Ridderström.\n\n*\tEslövs Bryggeri, Eslöv.\n\nSe AB. Skånebryggerier, Hälsingborg.\n\n*\tEslövs Korkfabrik, Eslöv.\n\nTillverkar butelj- och kapselkork samt\nkorkplattor för isoleringsändamål.\n\nTelefon: 115. Postgiro: 36571. —\nAntal industriarb.: 20. — Firman etabl.\n1891.\n\nÄgare o. chef: disp. Gösta Kock.\n\n*\tEslövs Skofabriks AB., Eslöv.\n\nTillverkar randsydda skodon.\nVarumärke: »Gyllene Gripen».\n\nHuvudkontor: Eslöv. Telegr.-adr.:\nSkofabriken, Eslöv. Telefon: 3, 119 o. 925.\nPostgiro: 32868. Försäljn.-kontor:\nStockholm, Kungsg. 37, telefon: 107962;\nGöteborg: V. Hamng. 20, telefon: 138873.\n\nAkt.-kap.: 300,000 kr. Antal\nindustriarb.: 115. Tillv.-värde pr år: 2,000,000 kr.\n— Bolaget grundat 1900, ombildat 1934.\n\nStyrelse: disp. Henry Dunker (ordf.),\ndir. Wilhelm Bahrke, greve Pontus De la\nGardie, dir. C. F. Tranchell, bankdir.\nIvar Åkerman.\n\nVerkst. dir.: Wilhelm Bahrke.\n\nDisp.: Karl Hedström.\n\nKamrer: Frans Cronvall.\n\n*\tEslövs Yllefabriks AB., Eslöv.\n\nUllspinneri, väveri och appreturverk.\nTillverkar hel- och halvylletyger samt\nfiltar.\n\nTelegr.-adr.: Eslövsylle, Eslöv.\nTelefon: 110 o. 127. Postgiro: 6503. —\nAkt.-kap.: 250,000 kr. Antal industriarb.: 85.\nTillv.-värde pr år: 1,000,000 kr. —\nFirman etabl. 1905, bolag 1929.\n\nStyrelse: disp. Albert Herrmann, disp.\nGerhard Herrmann, adv. Wilh. Penser.\n\nDisponenter: A. Herrmann o. G.\nHerrmann.\n\nAB. Esma, Malmö.\n\nKem. tekn. fabrik. Tillverkar\nhand-pasta, flytande tvål, bonvax m. m.\nBolaget utför även industritvätt, speciellt av\ntrassel och putsdukar samt arbetskläder.\n\nKontor: N. Långgatan 14—16.\nTelegr.-adr.: Esma, Malmö. Telefon: 72270.\nPostgiro: 148103. —Akt.-kap.: 30,000kr.\nArb.-antal: 9. Tillv.-värde pr år: 110,000\nkr. — Bolaget grundat 1938.\n\nVerkst. dir.: Göte Åkesson.\n\nAB. Espagnolettfabriken Fix, Gbg.\n\nSe AB. Fixfabriken, Göteborg.",
    "structured": {
        "1": {
            "name": "Eskilstuna Stålindustri",
            "location": "Eskilstuna",
            "business": "Tillverkar rostfria bordsknivar och gafflar samt kaffekvarnar.",
            "contact": {
                "phone": [
                    "30805"
                ],
                "postgiro": "10789"
            },
            "financials": {
                "employees": {
                    "industriarb": 23
                },
                "annual_turnover": "240,000 kr"
            },
            "foundation_year": 1913,
            "owner": "fabr. W. L. Jernström"
        },
        "2": {
            "name": "Eskilstuna Stålpressnings AB",
            "location": "Eskilstuna",
            "business": "Press-, förtennings- och galvaniseringsverk i Eskilstuna samt plåtvalsverk och elektr. vattenkraftstation vid Skogstorp (Södermanl. l.).",
            "contact": {
                "phone": "Eskilstuna",
                "postgiro": "10712",
                "sales_offices": [
                    {
                        "location": "Eskilstuna",
                        "phone": "Pressbolaget"
                    }
                ]
            },
            "financials": {
                "employees": {
                    "industriarb": 580
                },
                "annual_turnover": "12,000,000 kr"
            },
            "foundation_year": 1893,
            "owners": "AB. Separator, Stockholm",
            "board": [
                {
                    "name": "dir. Axel Wästfelt",
                    "role": "ordf."
                },
                {
                    "name": "dir. Erik Brändström",
                    "role": null
                },
                {
                    "name": "dir. Richard Dahlgren",
                    "role": null
                },
                {
                    "name": "dir. Folke Hellstedt",
                    "role": null
                }
            ],
            "director": "Richard Dahlgren",
            "sales_manager": "S. E. Edwards",
            "manager": "Oscar Nilsson"
        },
        "3": {
            "name": "Eskilstuna Termometerfabrik",
            "location": "Eskilstuna",
            "business": "Tillverkar termometrar såsom febertermometrar, rums- och fönstertermometrar, minimitermometrar, reklamtermometrar samt enklare glasinstrument och vattenpasslibellor.",
            "contact": {
                "phone": [
                    "35125"
                ],
                "postgiro": "278246"
            },
            "financials": {
                "employees": {
                    "industriarb": 20
                },
                "annual_turnover": "150,000 kr"
            },
            "foundation_year": 1941,
            "owner": "fabr. Fritz Feingold"
        },
        "4": {
            "name": "Eskilstuna Vattenpassfabrik",
            "location": "Eskilstuna",
            "business": "Vattenpassfabrik och aluminiumgjuteri. Tillverkar vattenpass av trä och aluminium samt maskinvattenpass av aluminium.",
            "contact": {
                "phone": [
                    "32802"
                ],
                "postgiro": "90627"
            },
            "financials": {
                "employees": {
                    "arb.-antal": 11
                },
                "annual_turnover": "105,000 kr"
            },
            "foundation_year": 1923,
            "owner": "fabr. Ax. Ridderström"
        },
        "5": {
            "name": "Eslövs Korkfabrik",
            "location": "Eslöv",
            "business": "Tillverkar butelj- och kapselkork samt korkplattor för isoleringsändamål.",
            "contact": {
                "phone": [
                    "115"
                ],
                "postgiro": "36571"
            },
            "employees": "20",
            "foundation_year": 1891,
            "owner": "disp. Gösta Kock"
        },
        "6": {
            "name": "Eslövs Skofabriks AB.",
            "location": "Eslöv",
            "business": "Tillverkar randsydda skodon.",
            "contact": {
                "phone": [
                    "3, 119",
                    "925"
                ],
                "postgiro": "32868",
                "sales_offices": [
                    {
                        "location": "Stockholm",
                        "phone": "107962"
                    },
                    {
                        "location": "Göteborg",
                        "phone": "138873"
                    }
                ]
            },
            "financials": {
                "capital": "300,000 kr",
                "employees": {
                    "industriarb": 115
                },
                "annual_turnover": "2,000,000 kr"
            },
            "board": [
                {
                    "name": "disp. Henry Dunker",
                    "role": "ordf."
                },
                {
                    "name": "dir. Wilhelm Bahrke",
                    "role": null
                },
                {
                    "name": "greve Pontus De la Gardie",
                    "role": null
                },
                {
                    "name": "dir. C. F. Tranchell",
                    "role": null
                },
                {
                    "name": "bankdir. Ivar Åkerman",
                    "role": null
                }
            ],
            "director": "Wilhelm Bahrke",
            "manager": "Karl Hedström"
        },
        "7": {
            "name": "Eslövs Yllefabriks AB.",
            "location": "Eslöv",
            "business": "Ullspinneri, väveri och appreturverk. Tillverkar hel- och halvylletyger samt filtar.",
            "contact": {
                "phone": [
                    "110",
                    "127"
                ],
                "postgiro": "6503"
            },
            "financials": {
                "capital": "250,000 kr",
                "employees": {
                    "industriarb": 85
                },
                "annual_turnover": "1,000,000 kr"
            },
            "foundation_year": 1905,
            "owners": "disp. Albert Herrmann, disp. Gerhard Herrmann, adv. Wilh. Penser",
            "managers": [
                "A. Herrmann",
                "G. Herrmann"
            ]
        },
        "8": {
            "name": "AB. Esma",
            "location": "Malmö",
            "business": "Kem. tekn. fabrik. Tillverkar hand-pasta, flytande tvål, bonvax m. m.",
            "contact": {
                "phone": [
                    "72270"
                ],
                "postgiro": "148103"
            },
            "financials": {
                "capital": "30,000 kr",
                "employees": {
                    "arb.-antal": 9
                },
                "annual_turnover": "110,000 kr"
            },
            "foundation_year": 1938,
            "manager": "Göte Åkesson"
        },
        "9": {
            "name": "AB. Espagnolettfabriken Fix",
            "location": "Gbg",
            "business": null
        }
    }
}