{
    "original": "Bolinder—Bong\n\nAB., E. V. Beronius Mek. Verkstads AB.\noch AB. Avancemotor.\n\nStyrelse: bankdir. Ernfrid Browaldh\n(ordf.), disp. Arvid H. Nilsson (v. ordf.),\ndir. Thorsten P. Ericsson, dir. Anders\nHåkansson, disp. Bror Lagercrantz.\n\nV erkst. dir.: Thorsten P. Ericsson.\n\nFörsäljn.-dir.: Bengt Larnell.\n\nEhonomidir.: Nils Ahlbom.\n\nÖveringenjörer: för tillverkn.: B. H.\nLundborg-r för konstruktioner: K. Evrell.\n\nInköpschef: Anders Lindquist.\n\nTekn. konsult.: dir. Gunnar Wallgren\n(Stockholm).\n\n(Jfr annons nr 59.)\n\n*Bolinders Fabriks AB., Kallhäll.\n\nMek. verkstad och gjuteri i Kallhäll\n(Sthlms l.).\n\nTillverkar spisar, gasartiklar,\nköttkvarnar, elektr. kaffekvarnar,\nhushållsartiklar och diskmaskiner,\nrestaurant-köksartiklar, handelsgjutgods,\nsanitets-gjutgods, byggnadsgjutgods och\nlegogjut-gods.\n\nHuvudkontor: Kallhäll. Telegr.-adr.:\nBofa, Stockholm. Telefon: (8)50180 eller\nStaket: »Bolinders Fabriksbolag».\nPostgiro: 1270. Filialkontor, lager o.\nut-ställn.: Stockholm, Bolinders Plan 2,\ntelefon: »Bolinders Fabriksbolag»; Göteborg.\nKarl Gustavsg. 1 B, telefon: 170830;\nMalmö, Stortorget 9, telefon: 15818.\n\nAkt.-kap.: 3,600,000 kr. Antal\nindustriarb.: 500.\n\nBolaget grundat 1933 efter övertagande\nav J. &amp; C. G. Bolinders Mek. Verkstads\nAB:s anläggningar i Kallhäll och därmed\nsammanhängande rörelse i Stockholm.\n\nStyrelse: dir. Josef Anér (ordf.),\nciviling. Birger Dahlerus, överstelöjtn. Edvard\nDahlerus, rådman Martin Hammar.\n\nVerkst. dir.: Birger Dahlerus.\n\nKassa dir.: G. B. Kviberg.\n\nFörsäljn.-chef: Lars Elvefors.\n\n«i. 8l G. G. Bolinders Mek. Verkstads\n\nAB., Eskilstuna.\n\nBolaget utgör ett försäljningsbolag för\nAB. Bolinder-Munktell, Eskilstuna, samt\när dotterbolag till detsamma. —\nAkt.-kap.: 50,000 kr. — (Se vidare under\nnämnda bolag.)\n\nA. E. Boll ing, Gränna.\n\nMetallvarufabrik. Tillverkar\nbelysningsarmatur i antika stilar.\n\nTelefon: 48. Postgiro: 138703. —\nArb.-antal: 7. Tillv.-värde pr år: 56,000 kr.\n— Firman etabl. 1895.\n\nÄgare o. chef: fabr. Axel E. Bolling.\n\n* Bollnäs Nya Bryggeri AB.,\n\nBollnäs.\n\nTillverkar maltdrycker, läskedrycker\noch mineralvatten vid bryggeri i Bollnäs\n(Gävleb. l.).\n\nTelegr.-adr.: Bryggeriet, Bollnäs.\nTelefon: 11100. Postgiro: 90880. - Akt.-kap.:\n300,000 kr. Antal industriarb.: 25.\nTillv.-värde pr år: 700,000 kr. — Bolaget\ngrundat 1882.\n\nStyrelse: major Sven E. Hellsten\n(ordf.), disp. A. E. Dahm, landsfiskal P.\nF. Isberg.\n\nVerkst. dir.: Olof Wallertz.\n\nKamrer: A. G. Läckström.\n\nBollnäs Trävaru AB., Bollnäs.\n\nSågverk, hyvleri och snickerifabrik i\nBollnäs (Gävleb. l.). Tillverkar sågade och\nhyvlade trävaror samt byggnadssnickerier.\n\nTelegr.-adr.: Trävarubolaget, Bollnäs.\nTelefon: 11115—16. Postgiro: 80216. —\nAkt.-kap.: 150,000 kr. Antal industriarb.:\n65. Årstillv.: 3,500 stds trävaror. —\nFirman etabl. 1917, nuvarande bolag 1920.\n\nStyrelse: disp. Wiktor Modin (ordf.),\ngrossh. David Larsson, inspekt. Fredrik\nModin, disp. Karl Modin, fabr. Vilhelm\nPersson.\n\nDisp.: Wiktor Modin.\n\nBollsta Sågverk, Bollstabruk.\n\nSe Graningeverkens AB., Bollstabruk.\n\nBoman, se Bohman.\n\nBongs Fabriker AB., Kristianstad.\n\nTillverkar kontorsböcker, kuvert,\nkartonger m. m.\n\nTelegr.-adr.: Bong, Kristianstad.\nTelefon: 10222 o. 10226. Postgiro: 30640.\nAvdelningskontor: Stockholm, Kungsg. 65,\ntelefon: 211584; Göteborg, Stamp gatan\n38 B, telefon: 155562.\n\nAkt.-kap.: 150,000 kr. Antal\nindustriarb.: 90. Tillv.-värde pr år: 1,000,000 kr.\n— Firman grundad 1737, bolag 1935.\n\nStyrelse: kommendörkapten Harry\nBong (ordf.), dipl.-ing. Gunnar Bong,\nfru Anna-Brita Sigfrid, civiling. Åke\nSigfrid.\n\nVerkst. dir.: Gunnar Bong.\n\nGustaf Bong AB., Ystad.\n\nKonservfabrik. Tillverkar\ngrönsaks-och fraktkonserver, sillkonserver, safter,\nmarmelader, geléer m. m. Firman driver\njämväl grönsaks- och fruktodling.",
    "structured": {
        "1": {
            "name": "AB. Bolinders Fabriks AB",
            "location": "Kallhäll",
            "business": "Mekanisk verkstad och gjuteri",
            "products": "Spisar, gasartiklar, köttkvarnar, elektr. kaffekvarnar, hushållsartiklar och diskmaskiner, restaurant-köksartiklar, handelsgjutgods, sanitets-gjutgods, byggnadsgjutgods och legogjut-gods",
            "contact": {
                "office": "Kallhäll",
                "phone": [
                    "(8)50180",
                    "Staket: \"Bolinders Fabriksbolag\""
                ],
                "postgiro": "1270",
                "head_office": "Kallhäll",
                "sales_offices": [
                    {
                        "location": "Stockholm",
                        "phone": "\"Bolinders Fabriksbolag\""
                    },
                    {
                        "location": "Göteborg",
                        "phone": "170830"
                    },
                    {
                        "location": "Malmö",
                        "phone": "15818"
                    }
                ],
                "telegraph": "Bofa, Stockholm"
            },
            "financials": {
                "capital": "3,600,000 kr",
                "employees": {
                    "industriarb": 500
                }
            },
            "foundation_year": 1933,
            "board": [
                {
                    "name": "Josef Anér",
                    "role": "ordf."
                },
                {
                    "name": "Birger Dahlerus",
                    "role": "civiling."
                },
                {
                    "name": "Edvard Dahlerus",
                    "role": "överstelöjtn."
                },
                {
                    "name": "Martin Hammar",
                    "role": "rådman"
                }
            ]
        },
        "2": {
            "name": "A. E. Bolling",
            "location": "Gränna",
            "business": "Metallvarufabrik",
            "products": "Belysningsarmatur i antika stilar",
            "contact": {
                "phone": "48",
                "postgiro": "138703"
            },
            "financials": {
                "employees": {
                    "Arb.-antal": 7
                },
                "annual_production_value": "56,000 kr"
            },
            "foundation_year": 1895
        },
        "3": {
            "name": "Bollnäs Nya Bryggeri AB.",
            "location": "Bollnäs",
            "products": "Maltdrycker, läskedrycker och mineralvatten",
            "contact": {
                "telegraph": "Bryggeriet, Bollnäs",
                "phone": "11100",
                "postgiro": "90880"
            },
            "financials": {
                "capital": "300,000 kr",
                "employees": {
                    "industriarb": 25
                },
                "annual_turnover": "700,000 kr"
            },
            "foundation_year": 1882,
            "board": [
                {
                    "name": "Sven E. Hellsten",
                    "role": "major"
                },
                {
                    "name": "A. E. Dahm",
                    "role": "disp."
                },
                {
                    "name": "P. F. Isberg",
                    "role": "landsfiskal"
                }
            ]
        },
        "4": {
            "name": "Bollnäs Trävaru AB.",
            "location": "Bollnäs",
            "business": "Sågverk, hyvleri och snickerifabrik",
            "products": "Sågade och hyvlade trävaror samt byggnadssnickerier",
            "contact": {
                "telegraph": "Trävarubolaget, Bollnäs",
                "phone": "11115—16",
                "postgiro": "80216"
            },
            "financials": {
                "capital": "150,000 kr",
                "employees": {
                    "industriarb": 65
                },
                "annual_production_value": "3,500 stds trävaror"
            },
            "foundation_year": 1917
        },
        "5": {
            "name": "Bongs Fabriker AB.",
            "location": "Kristianstad",
            "business": "Tillverkning av kontorsböcker, kuvert, kartonger m.m.",
            "contact": {
                "telegraph": "Bong, Kristianstad",
                "phone": "10222 o. 10226",
                "postgiro": "30640",
                "sales_offices": [
                    {
                        "location": "Stockholm",
                        "phone": "211584"
                    },
                    {
                        "location": "Göteborg",
                        "phone": "155562"
                    }
                ]
            },
            "financials": {
                "capital": "150,000 kr",
                "employees": {
                    "industriarb": 90
                },
                "annual_production_value": "1,000,000 kr"
            },
            "foundation_year": 1737,
            "board": [
                {
                    "name": "Harry Bong",
                    "role": "kommendörkapten"
                },
                {
                    "name": "Gunnar Bong",
                    "role": "dipl.-ing."
                }
            ]
        },
        "6": {
            "name": "Gustaf Bong AB.",
            "location": "Ystad",
            "business": "Konservfabrik",
            "products": "Grönsaks- och fraktkonserver, sillkonserver, safter, marmelader, geléer m.m.",
            "contact": {
                "phone": "N/A",
                "postgiro": "N/A"
            },
            "financials": {
                "employees": {
                    "Arb.-antal": "N/A"
                }
            },
            "foundation_year": "N/A"
        }
    }
}