{
    "original": "Henriksson—Hemia\n\nAkt.-kap.: 150,000 kr. Antal industriarb.:\n10. — Firman grundad 1905, ombildad\ntill bolag 1919.\n\nStyrelse: ing. Hugo Hennig (ordf.),\nhandl. Bror A. Lindgren, handl. Gustaf\nLindgren.\n\nVerkst. dir.: Hugo Hennig.\n\nV. verkst. dir.: ing. Kurt Hennig.\n\n* Henrikssons Brandredskap,\n\nStockholm.\n\nSe Handels AB. Henrikssons\nBrandredskap, Stockholm.\n\nHenrikssons Tekn. Fabriks AB.,\n\nÖrebro.\n\nKem,-tekn. fabrik. Tillverkar tvål,\nsåpa och parfymer, antiseptiska preparat,\nmejeripreparat, skur- och tvättmedel,\nskosmörja m. m.\n\nTelegr.-adr.: Henrikssons, Örebro.\nTelefon: 10672. Postgiro: 11649.\n\nAkt.-kap.: 300,000 kr. Antal\nindustriarb.: 70. Tillv.-värde pr år: 2,000,000 kr.\n\n—\tBolaget grundat 1907.\n\nVerkst. dir.: Bengt Orrvik.\n\nBirger Henricsson, Hjo.\n\nMek. verkstad. Tillverkar pakethållare\nför velocipeder samt möbelbeslag.\n\nTelefon: 103. Postgiro: 92497. —\nAntal industriarb.: 15. — Firman etabl.\n1901, ombildad 1935.\n\nÅgare o. chef: fabr. Birger Henricsson.\n\nOlof Henrikssons Byggnadsvaror,\n\nAB., Tenhult.\n\nBetowgvarufabrik i Tenhult (Jönköp.\n1.). Tillverkar betong och mosaiktrappor\noch -plattor. Bolaget idkar jämväl handel\nmed byggnadsmateriel.\n\nTelegr.-adr.: Byggnadsvaror, Tenhult.\nTelefon: Tenhult 62, 89 o. Jönköping\n2922 o. 3952. Postgiro: 136655.\n\nAkt.-kap.: 225,000 kr. Antal\nindustriarb.: 30. Tillv.-värde pr år: 350,000 kr.\n\n—\tFirman etabl. 1915, bolag 1930.\n\nVerkst. dir.: Hj. Forssberg.\n\n*Hercules, Ler- &amp; Tegelindustri AB.,\n\nKristianstad.\n\nSe Ler- &amp; Tegelindustri AB. Hercules,\nKristianstad.\n\nHerdins Färgeri &amp; Kemiska Tvätt,\nAnders Herdin AB., Falun.\n\nUtför färgning, kem. tvätt och\nim-pregnering.\n\nTelegr.-adr.: Aherdin, Falun.\n\nTelefon: 2920. Postgiro: 170062.\n—-Akt.-kap.: 100,000 kr. Antal industriarb.:\n60. — Bolaget grundat 1944.\n\nVerkst. dir.: disp. Anders Herdin.\n\nA. W. Herdins Färgverk AB.,\n\nFalun.\n\nFärgfabrik och kem. tekn. fabrik.\nTillverkar hemfärger, betsfärger,\nanilin-tryckfärger och malpreparat m. m.\nVarumärken för hemfärger: »Härvan» o.\n»Fe-nix».\n\nTelegr.-adr.: Färgverket, Falun.\nTelefon: 3351. Postgiro: 11020.\n\nAkt.-kap.: 55,000 kr. Antal\nindustriarb.: 40. — Firman grundlagd på\n1750-talet, bolag 1937.\n\nVerkst. dir.: fabr. Sivert Herdin.\n\nV. verkst. dir.: Olle Herdin.\n\n*AB. C. M. Hermanson, Stockholm.\n\nHerrkonfektionsfabrik. Tillverkar\nkostymer, överrockar, blazers och\nsportkostymer. Varumärke: »Hermansons».\n\nKontor: Hornsg. 54; postadr.:\nStockholm 17. Telegr.-adr.: Femtiosex,\nStockholm. Telefon: 406020 o. 433377.\nPostgiro: 150001.\n\nAkt.-kap.: 250,500 kr. Antal\nindustriarb.: 85. — Firman etabl. 1859, bolag\n1918.\n\nStyrelse: dir. Gustaf Ohlin (ordf.),\nherr Sven Janson, fru Ruth Sandström.\n\nVerkst. dir.: Gustaf Ohlin.\n\nAB. Th. Hermanssons Metallfabrik,\n\nStockholm.\n\nTillverkar automobilkylare, kylelement\nför explosionsmotorer, värmeelement m. m.\nsamt butiksinredningar, skylt- och\nfasad-anläggningar, båtbeslag; utför\nförnick-lings- och förkromningsarbeten.\n\nKontor: Hagagatan 16. Telefon: 332808\no. 317275. Postgiro: 157534. Avd.-kontor:\nGöteborg, Hedåsg. 6, telefon: 161437.\n\nAkt.-kap.: 130,000 kr. Antal\nindustriarb.: 40. Tillv.-värde pr år: 600,000 kr.\n— Firman etabl. 1910, bolag 1945.\n\nVerkst. dir.: fabr. Thure Hermansson.\n\n*Hernia, Limfirman AB., Norrköping.\n\nDextrin- och lim ämnesfabrik i\nNorrköping, limämnesfabriker i Stockholm,\nGöteborg och Malmö. Tillverkar dextrin,\nflytande gummi, flytande lim och\nkalllim, limämnen, remvax, klister, valsmassa\nm. m. Varumärke: »Hernia».\n\nHuvudkontor: Norrköping. Telefon:\n24114 o. 24166. Postgiro: 11214. Avd.-",
    "structured": {
        "1": {
            "name": "Henrikssons Brandredskap",
            "location": "Stockholm",
            "business": "Brandredskap",
            "products": "Se Handels AB. Henrikssons Brandredskap, Stockholm.",
            "contact": {
                "telegraph": "Henrikssons, Örebro",
                "phone": [
                    "10672"
                ],
                "postgiro": "11649"
            },
            "financials": {
                "capital": "150,000 kr",
                "employees": {
                    "industriarb.": 10
                }
            },
            "foundation_year": 1905,
            "corporation_year": 1919,
            "board": [
                {
                    "name": "ing. Hugo Hennig",
                    "role": "ordf."
                },
                {
                    "name": "handl. Bror A. Lindgren",
                    "role": "member"
                },
                {
                    "name": "handl. Gustaf Lindgren",
                    "role": "member"
                }
            ],
            "director": "Hugo Hennig",
            "managing_director": "Hugo Hennig",
            "sales_manager": "ing. Kurt Hennig"
        },
        "2": {
            "name": "Henrikssons Tekn. Fabriks AB.",
            "location": "Örebro",
            "business": "Kem,-tekn. fabrik",
            "products": "Tillverkar tvål, såpa och parfymer, antiseptiska preparat, mejeripreparat, skur- och tvättmedel, skosmörja m. m.",
            "contact": {
                "telegraph": "Henrikssons, Örebro",
                "phone": [
                    "10672"
                ],
                "postgiro": "11649"
            },
            "financials": {
                "capital": "300,000 kr",
                "employees": {
                    "industriarb.": 70
                },
                "annual_production_value": "2,000,000 kr"
            },
            "foundation_year": 1907,
            "board": [
                {
                    "name": "Bengt Orrvik",
                    "role": "verkst. dir."
                }
            ]
        },
        "3": {
            "name": "Birger Henricsson",
            "location": "Hjo",
            "business": "Mek. verkstad",
            "products": "Tillverkar pakethållare för velocipeder samt möbelbeslag.",
            "contact": {
                "phone": [
                    "103"
                ],
                "postgiro": "92497"
            },
            "financials": {
                "employees": {
                    "industriarb.": 15
                }
            },
            "foundation_year": 1901
        },
        "4": {
            "name": "Olof Henrikssons Byggnadsvaror, AB.",
            "location": "Tenhult",
            "business": "Betowgvarufabrik",
            "products": "Tillverkar betong och mosaiktrappor och -plattor. Bolaget idkar jämväl handel med byggnadsmateriel.",
            "contact": {
                "telegraph": "Byggnadsvaror, Tenhult",
                "phone": [
                    "Tenhult 62",
                    "89",
                    "Jönköping 2922",
                    "3952"
                ],
                "postgiro": "136655"
            },
            "financials": {
                "capital": "225,000 kr",
                "employees": {
                    "industriarb.": 30
                },
                "annual_production_value": "350,000 kr"
            },
            "foundation_year": 1915
        },
        "5": {
            "name": "Herdins Färgeri & Kemiska Tvätt, Anders Herdin AB.",
            "location": "Falun",
            "business": "Färgeri & Kemiska Tvätt",
            "products": "Utför färgning, kem. tvätt och impregnering.",
            "contact": {
                "telegraph": "Aherdin, Falun",
                "phone": [
                    "2920"
                ],
                "postgiro": "170062"
            },
            "financials": {
                "capital": "100,000 kr",
                "employees": {
                    "industriarb.": 60
                }
            },
            "foundation_year": 1944,
            "managing_director": "disp. Anders Herdin"
        },
        "6": {
            "name": "A. W. Herdins Färgverk AB.",
            "location": "Falun",
            "business": "Färgfabrik och kem. tekn. fabrik",
            "products": "Tillverkar hemfärger, betsfärger, anilin-tryckfärger och malpreparat m. m.",
            "contact": {
                "telegraph": "Färgverket, Falun",
                "phone": [
                    "3351"
                ],
                "postgiro": "11020"
            },
            "financials": {
                "capital": "55,000 kr",
                "employees": {
                    "industriarb.": 40
                }
            },
            "foundation_year": 1750,
            "corporation_year": 1937,
            "board": [
                {
                    "name": "fabr. Sivert Herdin",
                    "role": "verkst. dir."
                },
                {
                    "name": "Olle Herdin",
                    "role": "v. verkst. dir."
                }
            ]
        },
        "7": {
            "name": "AB. C. M. Hermanson",
            "location": "Stockholm",
            "business": "Herrkonfektionsfabrik",
            "products": "Tillverkar kostymer, överrockar, blazers och sportkostymer.",
            "contact": {
                "office": "Hornsg. 54",
                "telegraph": "Femtiosex, Stockholm",
                "phone": [
                    "406020",
                    "433377"
                ],
                "postgiro": "150001"
            },
            "financials": {
                "capital": "250,500 kr",
                "employees": {
                    "industriarb.": 85
                }
            },
            "foundation_year": 1859,
            "corporation_year": 1918,
            "board": [
                {
                    "name": "dir. Gustaf Ohlin",
                    "role": "ordf."
                },
                {
                    "name": "herr Sven Janson",
                    "role": "member"
                },
                {
                    "name": "fru Ruth Sandström",
                    "role": "member"
                }
            ],
            "director": "Gustaf Ohlin"
        },
        "8": {
            "name": "AB. Th. Hermanssons Metallfabrik",
            "location": "Stockholm",
            "business": "Metallfabrik",
            "products": "Tillverkar automobilkylare, kylelement för explosionsmotorer, värmeelement m. m. samt butiksinredningar, skylt- och fasadanläggningar, båtbeslag; utför förnicklings- och förkromningsarbeten.",
            "contact": {
                "office": "Hagagatan 16",
                "phone": [
                    "332808",
                    "317275"
                ],
                "postgiro": "157534",
                "sales_offices": [
                    {
                        "location": "Göteborg",
                        "phone": "161437"
                    }
                ]
            },
            "financials": {
                "capital": "130,000 kr",
                "employees": {
                    "industriarb.": 40
                },
                "annual_production_value": "600,000 kr"
            },
            "foundation_year": 1910,
            "corporation_year": 1945,
            "board": [
                {
                    "name": "fabr. Thure Hermansson",
                    "role": "verkst. dir."
                }
            ]
        },
        "9": {
            "name": "Hernia, Limfirman AB.",
            "location": "Norrköping",
            "business": "Limfabrik",
            "products": "Tillverkar dextrin, flytande gummi, flytande lim och kalllim, limämnen, remvax, klister, valsmassa m. m.",
            "contact": {
                "phone": [
                    "24114",
                    "24166"
                ],
                "postgiro": "11214"
            },
            "financials": {
                "capital": "N/A",
                "employees": {
                    "N/A": 0
                }
            }
        }
    }
}