{
    "original": "jEngblad—Engström\n\nEngblads Tapetfabrik, Göteborg.\n\nTillverkar tapeter och bårder.\nVarumärke: »Lotura».\n\nKontor: Underåsbro; postadr.:\nGöteborg 5. Telegr.-adr.: Tapetblad, Göteborg.\nTelefon: 161314 o. 161317. Postgiro:\n40681.\n\nAntal industriarb.: 40. Tillv.-värde pr\når: 1,000,000 kr. — Firman etabl. 1929.\n\nÄgare o. chef: fabr. Einar Engblad.\n\nDisp.: Knut R. Pettersson.\n\nEngblom &amp; Co., Bröderna,\n\nKristinehamn.\n\nSe Bröderna Engblom &amp; Co.,\nKristinehamn.\n\n*Engdahls Möbelfabrik,\n\nÖrserumsbrunn.\n\nSe AB. Bröderna Engdahls\n-Möbelfabrik, örserumsbrunn.\n\nGunnar Engdahl, Sävsjö.\n\nSågverk, hyvleri^ snickeri- och\nbränn-torvfabriker i Sävsjö, torvströfabrik\n(Fagerdals Torvströfabrik) i\nLannaskede-brunn (båda i Jönköp. l.).\n\nTelefon: 109. -t— Antal industriarb.:\n75. Tillv.-värde pr år: 500,000 kr. —\nFirman etabl. 1922.\n\nChef: fabr. Gunnar Engdahl.\n\n’Engel-Fabri kerna AB., Motala.\n\nTillverkar ylletyger såsom kamgarn,\nkorderoj, paletå, kapptyger, filtar m. m.\n\nTelefon: »Engel-Fabrikerna». Postgiro:\n28366.\n\nAkt.-kap.: 500,000 kr. Antal\nindustriarb.: 300. Tillv.-värde pr år: 4,500,000 kr.\n\n# Firman etabl. 1870, bolag 1910,\nom-bildat 1930 under namn Asps Yllefabriks\nAB., nuv. namn 1945. Bolaget äger\nMotala Täckfabriks AB. och Östgöta\nMattfabriks AB., båda i Motala.\n\nStyrelse: dir. Gösta Engel, bankdir. G.\nGyllensvärd, bankdir. Sigurd Hellgrén.\n\nVerkst. dir.: Gösta Engel.\n\n*Engelsbergs Bruk, Ängelsberg.\n\nSe Avesta Jernverks AB., Avesta. .\n\n*AB. P. Enger, Åmål\n\nTillverkar skjortor, pyjamas,\nskyddskläder och klänningar samt\nplastickap-por. Varumärken: »Engers», »President»,\n\n9*\n\n»Paramount», »Pilot» o. »A-skjortan».\nBolaget driver även engroshandel med\nmanufakturvaror.\n\nTelefon: 11 o. 56. Postgiro: 8264.\nAkt.-kap.: 175,000 kr. Antal\nindustriarb.: 140. Tillv.-värde pr år: 1,800,000\nkr. — Firman etabl. 1897, bolag 1930.\nVerkst. dir.: Filip Enger.\nDisp.: Yngve Enger.\n\n*0lle Engkvist Byggnads AB.,\n\nStockholm.\n\nByggnadsentreprenörfirma för\nbostads-och affärshus, industribyggnader m. m.\n\nKontor: Gröndal, Sjöbjörnsv. 16.\nTelefon: 452840. Postgiro: 199434. —\nAkt.-kap.: 500,000 kr. Prod.-värde pr år:\n10,000,000 kr. — Firman etabl. år 1923,\nbolag 1945.\n\nStyrelse: grossh. Robert^ Ljunglöf\n(ordf.), dir. Ragnar Blomquist, byggm.\nOlle Engkvist, dir. Claes Wahlund, disp.\nKils Westerdahl.\n\nVerkst. dir.: Olle Engkvist.\nKamrer: Artur Pettersson.\nKonstruhtionsing.: civiling. K.-Ö.\nRosén.\n\nOfferting.: civiling. Georg Schackne. :\nArbetschefer: ing. Tore Larsson o.\nciviling. Gunnar Lindegren.\n\n*AB. Englund &amp; Kjelsson,\n\nÖstersund.\n\nSadelmakeri och karosserifabrik.\nTillverkar arbetsselar och sadelmakerier,\nlastbilshytter och lastflak samt sportartiklar.\nTelefon: 95 o. 196. Postgiro: 22980.\n\n—\tAkt.-kap.: 70,000 kr. Antal\nindustriarb.: 40. Tillv.-värde pr år: 750,000 kr.\n\n—\tFirman etabl. 1882, bolag 1922.\nStyrelse: dir. Gunnar Englund, fru\n\nSylva Englund, köpm. Gösta Lindevall.\nVerkst. dir.: Gunnar Englund.\n\nAB. Engshyttan, Nybro.\n\nGlasbruk. Tillverkar belysningsglas.\nTelefon: 410. Postgiro: 92355. —\nAkt.-kap.: 70,000 kr. Antal industriarb.: 50.\nTillv.-värde pr år: 400,000 kr. — Bolaget\ngrundat 19,34.\nDisp.: E. Harri.\n\nJ. L. Engström &amp; Söner\nFabriks-bolag, Hagalund.\n\nMek. verkstad i Hagalund (Sthlms l.).\nTillverkar järnsängar, sjukhusmöbler ss.\nförlossnings- och sjuksängar, undersök-",
    "structured": {
        "firms": [
            {
                "name": "Engblads Tapetfabrik",
                "location": "Göteborg",
                "business": "Tillverkar tapeter och bårder",
                "products": "Varumärke: »Lotura»",
                "contact": {
                    "office": "Underåsbro; postadr.: Göteborg 5",
                    "phone": [
                        "161314",
                        "161317"
                    ],
                    "postgiro": "40681",
                    "telegraph": "Tapetblad, Göteborg"
                },
                "financials": {
                    "capital": null,
                    "employees": {
                        "industriarb": 40
                    },
                    "annual_turnover": "1,000,000 kr",
                    "annual_production_value": null
                },
                "foundation_year": 1929,
                "owner": "fabr. Einar Engblad",
                "director": "Knut R. Pettersson"
            },
            {
                "name": "Gunnar Engdahl",
                "location": "Sävsjö",
                "business": "Sågverk, hyvleri^ snickeri- och bränn-torvfabriker",
                "contact": {
                    "phone": "109"
                },
                "financials": {
                    "capital": null,
                    "employees": {
                        "industriarb": 75
                    },
                    "annual_turnover": "500,000 kr",
                    "annual_production_value": null
                },
                "foundation_year": 1922,
                "owner": "fabr. Gunnar Engdahl",
                "director": null
            },
            {
                "name": "Engel-Fabri kerna AB.",
                "location": "Motala",
                "business": "Tillverkar ylletyger såsom kamgarn, korderoj, paletå, kapptyger, filtar m. m.",
                "contact": {
                    "phone": "»Engel-Fabrikerna»",
                    "postgiro": "28366"
                },
                "financials": {
                    "capital": "500,000 kr",
                    "employees": {
                        "industriarb": 300
                    },
                    "annual_turnover": "4,500,000 kr",
                    "annual_production_value": null
                },
                "foundation_year": 1870,
                "current_name_year": 1945,
                "owner": null,
                "director": "Gösta Engel"
            },
            {
                "name": "AB. P. Enger",
                "location": "Åmål",
                "business": "Tillverkar skjortor, pyjamas, skyddskläder och klänningar samt plastickap-por",
                "products": "Varumärken: »Engers», »President», »Paramount», »Pilot» o. »A-skjortan»",
                "contact": {
                    "phone": [
                        "11",
                        "56"
                    ],
                    "postgiro": "8264"
                },
                "financials": {
                    "capital": "175,000 kr",
                    "employees": {
                        "industriarb": 140
                    },
                    "annual_turnover": "1,800,000 kr",
                    "annual_production_value": null
                },
                "foundation_year": 1897,
                "current_name_year": 1945,
                "owner": null,
                "director": "Filip Enger"
            },
            {
                "name": "0lle Engkvist Byggnads AB.",
                "location": "Stockholm",
                "business": "Byggnadsentreprenörfirma för bostads-och affärshus, industribyggnader m. m.",
                "contact": {
                    "office": "Gröndal, Sjöbjörnsv. 16",
                    "phone": "452840",
                    "postgiro": "199434"
                },
                "financials": {
                    "capital": "500,000 kr",
                    "employees": null,
                    "annual_turnover": "10,000,000 kr",
                    "annual_production_value": null
                },
                "foundation_year": 1923,
                "current_name_year": 1945,
                "owner": null,
                "director": "Olle Engkvist"
            },
            {
                "name": "AB. Englund & Kjelsson",
                "location": "Östersund",
                "business": "Sadelmakeri och karosserifabrik",
                "products": "Tillverkar arbetsselar och sadelmakerier, lastbilshytter och lastflak samt sportartiklar",
                "contact": {
                    "phone": [
                        "95",
                        "196"
                    ],
                    "postgiro": "22980"
                },
                "financials": {
                    "capital": "70,000 kr",
                    "employees": {
                        "industriarb": 40
                    },
                    "annual_turnover": "750,000 kr",
                    "annual_production_value": null
                },
                "foundation_year": 1882,
                "current_name_year": 1945,
                "owner": null,
                "director": null
            },
            {
                "name": "AB. Engshyttan",
                "location": "Nybro",
                "business": "Glasbruk",
                "products": "Tillverkar belysningsglas",
                "contact": {
                    "phone": "410",
                    "postgiro": "92355"
                },
                "financials": {
                    "capital": "70,000 kr",
                    "employees": {
                        "industriarb": 50
                    },
                    "annual_turnover": "400,000 kr",
                    "annual_production_value": null
                },
                "foundation_year": null,
                "current_name_year": 1945,
                "owner": null,
                "director": null
            },
            {
                "name": "J. L. Engström & Söner Fabriks-bolag",
                "location": "Hagalund",
                "business": "Mek. verkstad i Hagalund (Sthlms l.). Tillverkar järnsängar, sjukhusmöbler ss. förlossnings- och sjuksängar, undersök-",
                "contact": {},
                "financials": {},
                "foundation_year": null,
                "current_name_year": null,
                "owner": null,
                "director": null
            }
        ]
    }
}