{
    "original": "Karlsson—Karlstad\n\n*Martin Karlssons Möbelfabrik,\n\nTibro.\n\nTillverkar matsalsmöbler och\nkompletteringsmöbler vid fabrik i Tibro (Skarab.\n10.\n\nTelefon: 271. Postgiro: 27621. —\nArb.-antal: 12. Tillv.-värde pr år: 205,000 kr.\n— Firman grundad 1929.\n\nÄgare o. chef: fabr. Martin Karlsson.\n\nN. Karlsson, Kopparslageri &amp;\nMetall-tryckeri, Ronneby.\n\nTillverkar ^ fristående vattenvärmare,\nkoppar- och järnkittlar.\n\nTelefon: 178. Postgiro: 10225. —\nAntal industriarb.: 20. — Firman etabl.\n1876.\n\nÄgare o. chefer: fabr. Nils Karlsson o.\nfabr. Allan Karlsson.\n\n^Karlstads Bryggeri AB., Karlstad.\n\nTillverkar malt, maltdrycker,\nmineralvatten och läskedrycker.\n\nTelefon: »Bryggeribolaget». Postgiro:\n71033. — Akt.-kap.: 350,000 kr. Antal\nindustriarb.: 26.\n\nBolaget grundat 1890. AB.\nWermlands-bryggerier driver i bolagets namn\nrörelsen enligt kommissionärsavtal.\n\nVerTcst. dir.: disp. Sven Jansson.\n\nKarlstads Cementvar ufabr i k,\n\nKarlstad.\n\nBetongvarufabriker i Hynboholm och\nSkåre (båda i Värml. l.). Tillverkar i\nHynboholm byggnadsblock (vibroblock)\nsamt i Skåre avloppsrör, kulvertar,\nträ-ullsplattor, gångbaneplattor, större\nrenings- och vattenbrunnar.\n\nKontor: Karlstad. Telefon: 16268.\nPostgiro: 263306. — Antal industriarb.: 20,\nvarav i Skåre 15. Tillv.-värde pr år:\n165,000 kr. — Firman etabl. 1943.\n\nÄgare o. chef: ing. Armand Olsson.\n\nKarlstads Dissousgas AB.,\n\nKarlstad.\n\nFramställer dissousgas.\n\nTelefon: 15435. Postgiro: 36145. —\nAkt.-kap.: 150,000 kr. Arb.-antal: 2.\nTillv.-värde pr år: 200,000 kr. — Bolaget\ngrundat 1928.\n\nStyrelse: dir. Gunnar Dalén, dir. Axel\nMellin, byggm. O. Wästlund.\n\nVerkst. dir.: O. Wästlund.\n\nKontorschef: Folke Nilson.\n\nAB. Karlstads Marmor industri,\n\nKarlstad.\n\nTillverkar diskbänkar, öppna spisar,\ntrappor, fönsterbänkar m. m. av marmor\neller kalksten.\n\nTelefon: 12361. Postgiro: 98863. —\nAkt.-kap.: 5,000 kr. Arb.-antal: 4.\nTillv.-värde pr år: 50,000 kr. — Bolaget\ngrundat 1928.\n\nVerkst. dir.: Elof Elinder.\n\n*AB. Karlstads Mekaniska Werkstad*\n\nKarlstad.\n\nMekaniska verkstäder med gjuteri och\nplåtslageri i Karlstad och i Kristinehamn.\nTillverkar maskiner för pappersbruk,\ncellulosafabriker, träsliperier och\nwallboard-fabriker samt vattenturbiner,\nregulatorer-och tubledningar av plåt ävensom\nfartygspropellrar med fasta och omställbara blad\n( » KaMeWa »-propellrar).\n\nHuvudkontor: Karlstad. Telegr.-adr.:\nVerkstaden, Karlstad. Telefon: »KMW».\nPostgiro: 80300.\n\nAkt.-kap.: 3,600,000 kr. Antal\nindustriarb.: 1,035, varav i Karlstad: 630.\nTillv.-värde pr år: 18,000,000 kr.\n\nBolaget grundat 1873. Verkstaden i\nKarlstad anlagd 1860, verkstaden i\nKristinehamn 1859.\n\nStyrelse: bankdir. Anton Dahlia\n(ordf.), dir. Vilhelm Björkman, dir.\nGunnar Brolin, dir. Rob. Fredrikson, dir.\nRaabe, civiling. Ivan Södersten.\n\nDirektör: Gunnar Brolin.\n\nVerkstadschef: E. Norbäck.\n\nKamrer: Gunnar Hanson.\n\n^Karlstads Spinneri- &amp; Väveri AB.,\n\nKarlstad.\n\nUllspinneri, färgeri, väveri och\nappre-turverk. Tillverkar gångmattor och\navpassade mattor, möbeltyger,\nbadkapps-tyger, hästfiltar och yllegarn. Varumärke:\n»KSW».\n\nTelegr.-adr.: Spinneri, Karlstad.\nTelefon: 15250. Postgiro: 30608. Repr. i\nStockholm: Henning Wijk, Kungsg. 51,\ntelefon: 111695.\n\nAkt.-kap.: 400,000 kr. Antal\nindustriarb.: 125. Tillv.-värde pr år: 2,000,000 kr..\n— Bolaget grundat 1897.\n\nStyrelse: dir. Sigurd Brag (ordf.), ing,\nÅke Brag, jur. kand. Otto Ågren.\n\nVerkst. dir. o. disp.: Sigurd Brag.\n\nAB. Karlstads Strå- &amp; Filthatt,\nfabrik, Karlstad.\n\nTillverkar strå- och filthattar samt\nsorghattar för damer. Firman bedriver",
    "structured": {
        "1": {
            "name": "Martin Karlssons Möbelfabrik",
            "location": "Tibro",
            "business": "Tillverkar matsalsmöbler och kompletteringsmöbler",
            "products": "Description of products manufactured or services offered.",
            "contact": {
                "office": "Fabrik i Tibro (Skarab. 10)",
                "phone": [
                    "271"
                ],
                "postgiro": "27621",
                "head_office": "",
                "telegraph": "",
                "factory_office": "",
                "factory_phone": ""
            },
            "financials": {
                "capital": "",
                "employees": {
                    "Arb.-antal": 12
                },
                "annual_turnover": "",
                "annual_production_value": "205,000 kr"
            },
            "foundation_year": 1929,
            "current_name_year": "",
            "predecessor": "",
            "original_name": "",
            "corporation_year": "",
            "board": [],
            "owners": [
                "Martin Karlsson"
            ],
            "director": "Martin Karlsson",
            "managing_director": "",
            "sales_manager": "",
            "manager": ""
        },
        "2": {
            "name": "N. Karlsson, Kopparslageri & Metall-tryckeri",
            "location": "Ronneby",
            "business": "Tillverkar fristående vattenvärmare, koppar- och järnkittlar",
            "contact": {
                "office": "",
                "phone": [
                    "178"
                ],
                "postgiro": "10225",
                "head_office": "",
                "telegraph": "",
                "factory_office": "",
                "factory_phone": ""
            },
            "financials": {
                "capital": "",
                "employees": {
                    "Antal industriarb": 20
                },
                "annual_turnover": "",
                "annual_production_value": ""
            },
            "foundation_year": 1876,
            "current_name_year": "",
            "predecessor": "",
            "original_name": "",
            "corporation_year": "",
            "board": [],
            "owners": [
                "Nils Karlsson",
                "Allan Karlsson"
            ],
            "director": "",
            "managing_director": "",
            "sales_manager": "",
            "manager": ""
        },
        "3": {
            "name": "Karlstads Bryggeri AB.",
            "location": "Karlstad",
            "business": "Tillverkar malt, maltdrycker, mineralvatten och läskedrycker",
            "contact": {
                "office": "",
                "phone": [
                    "Bryggeribolaget"
                ],
                "postgiro": "71033",
                "head_office": "",
                "telegraph": "",
                "factory_office": "",
                "factory_phone": ""
            },
            "financials": {
                "capital": "350,000 kr",
                "employees": {
                    "Antal industriarb": 26
                },
                "annual_turnover": "",
                "annual_production_value": ""
            },
            "foundation_year": 1890,
            "current_name_year": "",
            "predecessor": "",
            "original_name": "",
            "corporation_year": "",
            "board": [],
            "owners": [],
            "director": "",
            "managing_director": "",
            "sales_manager": "",
            "manager": "Sven Jansson"
        },
        "4": {
            "name": "Karlstads Cementvarufabrik",
            "location": "Karlstad",
            "business": "Betongvarufabriker",
            "products": "Byggnadsblock (vibroblock) i Hynboholm, avloppsrör, kulvertar, trä-ullsplattor, gångbaneplattor, större renings- och vattenbrunnar i Skåre",
            "contact": {
                "office": "Kontor: Karlstad",
                "phone": [
                    "16268"
                ],
                "postgiro": "263306",
                "head_office": "",
                "telegraph": "",
                "factory_office": "",
                "factory_phone": ""
            },
            "financials": {
                "capital": "",
                "employees": {
                    "Antal industriarb": 20
                },
                "annual_turnover": "",
                "annual_production_value": "165,000 kr"
            },
            "foundation_year": 1943,
            "current_name_year": "",
            "predecessor": "",
            "original_name": "",
            "corporation_year": "",
            "board": [],
            "owners": [
                "Ing. Armand Olsson"
            ],
            "director": "",
            "managing_director": "",
            "sales_manager": "",
            "manager": ""
        },
        "5": {
            "name": "Karlstads Dissousgas AB.",
            "location": "Karlstad",
            "business": "Framställer dissousgas",
            "contact": {
                "office": "",
                "phone": [
                    "15435"
                ],
                "postgiro": "36145",
                "head_office": "",
                "telegraph": "",
                "factory_office": "",
                "factory_phone": ""
            },
            "financials": {
                "capital": "150,000 kr",
                "employees": {
                    "Arb.-antal": 2
                },
                "annual_turnover": "",
                "annual_production_value": "200,000 kr"
            },
            "foundation_year": 1928,
            "current_name_year": "",
            "predecessor": "",
            "original_name": "",
            "corporation_year": "",
            "board": [],
            "owners": [],
            "director": "",
            "managing_director": "O. Wästlund",
            "sales_manager": "",
            "manager": "Folke Nilson"
        },
        "6": {
            "name": "AB. Karlstads Marmor industri",
            "location": "Karlstad",
            "business": "Tillverkar diskbänkar, öppna spisar, trappor, fönsterbänkar m. m. av marmor eller kalksten",
            "contact": {
                "office": "",
                "phone": [
                    "12361"
                ],
                "postgiro": "98863",
                "head_office": "",
                "telegraph": "",
                "factory_office": "",
                "factory_phone": ""
            },
            "financials": {
                "capital": "5,000 kr",
                "employees": {
                    "Arb.-antal": 4
                },
                "annual_turnover": "",
                "annual_production_value": "50,000 kr"
            },
            "foundation_year": 1928,
            "current_name_year": "",
            "predecessor": "",
            "original_name": "",
            "corporation_year": "",
            "board": [],
            "owners": [],
            "director": "",
            "managing_director": "",
            "sales_manager": "",
            "manager": ""
        },
        "7": {
            "name": "AB. Karlstads Mekaniska Werkstad",
            "location": "Karlstad",
            "business": "Mekaniska verkstäder med gjuteri och plåtslageri",
            "products": "Maskiner för pappersbruk, cellulosafabriker, träsliperier och wallboard-fabriker, vattenturbiner, regulatorer-och tubledningar av plåt, fartygspropellrar med fasta och omställbara blad ( » KaMeWa »-propellrar)",
            "contact": {
                "office": "Huvudkontor: Karlstad",
                "phone": [
                    "Verkstaden, Karlstad",
                    "KMW"
                ],
                "postgiro": "80300",
                "head_office": "",
                "telegraph": "",
                "factory_office": "",
                "factory_phone": ""
            },
            "financials": {
                "capital": "3,600,000 kr",
                "employees": {
                    "Antal industriarb": 1035
                },
                "annual_turnover": "",
                "annual_production_value": "18,000,000 kr"
            },
            "foundation_year": 1873,
            "current_name_year": "",
            "predecessor": "",
            "original_name": "",
            "corporation_year": "",
            "board": [],
            "owners": [],
            "director": "Gunnar Brolin",
            "managing_director": "",
            "sales_manager": "",
            "manager": ""
        },
        "8": {
            "name": "Karlstads Spinneri- & Väveri AB.",
            "location": "Karlstad",
            "business": "Ullspinneri, färgeri, väveri och appreturverk",
            "products": "Gångmattor, avpassade mattor, möbeltyger, badkappstyger, hästfiltar och yllegarn",
            "contact": {
                "office": "Telegr.-adr.: Spinneri, Karlstad",
                "phone": [
                    "15250"
                ],
                "postgiro": "30608",
                "head_office": "",
                "telegraph": "",
                "factory_office": "",
                "factory_phone": ""
            },
            "financials": {
                "capital": "400,000 kr",
                "employees": {
                    "Antal industriarb": 125
                },
                "annual_turnover": "",
                "annual_production_value": "2,000,000 kr"
            },
            "foundation_year": 1897,
            "current_name_year": "",
            "predecessor": "",
            "original_name": "",
            "corporation_year": "",
            "board": [],
            "owners": [],
            "director": "",
            "managing_director": "Sigurd Brag",
            "sales_manager": "",
            "manager": ""
        },
        "9": {
            "name": "AB. Karlstads Strå- & Filthattfabrik",
            "location": "Karlstad",
            "business": "Tillverkar strå- och filthattar samt sorghattar för damer",
            "contact": {
                "office": "",
                "phone": [],
                "postgiro": "",
                "head_office": "",
                "telegraph": "",
                "factory_office": "",
                "factory_phone": ""
            },
            "financials": {
                "capital": "",
                "employees": {},
                "annual_turnover": "",
                "annual_production_value": ""
            },
            "foundation_year": "",
            "current_name_year": "",
            "predecessor": "",
            "original_name": "",
            "corporation_year": "",
            "board": [],
            "owners": [],
            "director": "",
            "managing_director": "",
            "sales_manager": "",
            "manager": ""
        }
    }
}