{
    "original": "Skandinaviska\n\nVerkst. dir.: Wilhelm Österman.\n\nÖvering.: Ernst O. Edelmann.\n\nFörsäljn.-chef: kamrer Helge\nJohansson.\n\nKontorschef: fru E. Nilsson.\n\n\"Skandinaviska Jute-Spinneri- &amp;\nVäfveri AB., Oskarström.\n\nJutespinneri, väveri, blekeri, färgeri,\nappreturverk och säcksömnadsverkstäder\ni Oskarström (Hallands l.).\n\nTillverkar jutevaror, såsom säckar,\npackväv, pressduk etc. Ensainförsälj. av\njutevaror: Svenska Jutefabrikernas\nCentralkontor. Halmstad; telefon: 220 o. 765.\nRepr.: i Stockholm-. Svenska\nJutefabrikernas avd.-kontor, R. Hägertz,\nRege-ringsg. 39, telefon: 110433 o. 200475;\nMalmö: Sven Wallberg, Föreningsg. 55,\ntelefon: 26129.\n\nBolaget äger Oskarströms Linnefabrik,\nsom tillverkar linnevaror, såsom\nbuldansäckar, presenningsduk,\nväggbe-klädnads-, hängmatte- och\nbolstervars-väv, handduksväv och lakanslärft,\nborddukar och servietter, lingarn m. m.\nNederlag för linnevaror i Stockholm,\nRegeringsg. 39 (föreståndare: R. Hägertz,\ntelefon: 110433).\n\nTelegr.-adr.: Jutespinneriet,\nÖskarström. Telefon: 1. Postgiro: 15500.\n\nAkt.-kap.: 4,500,000 kr. Antal\nindustriarb.: 675.\n\nBolaget grundat 1889.\n\nStyrelse: dir. Carl August Wicander\n(ordf.), dir. Kjell Hägglöf, (v. ^ ordf.),\nciviling. Gösta Blum, dir. Eric Lindelöf,\nstadsfogde Th. Nordström, disp. Isak R.\nWallberg.\n\nVerkst. dir. o. disp.: Gösta Blum.\n\nKamrer: H. Ottmar.\n\nKassör: Magn. Nilsson.\n\nFörsäljn.-chef: A. Berndtson.\n\nInköpschef: Knut Bengtson.\n\n\"AB. Skandinaviska Korsettfabriken,\n\nOskarshamn.\n\nTillverkar korsetter, bysthållare och\ndithörande artiklar. Varumärke: »Fröja».\n\nTelegr.-adr.: Fröja, Oskarshamn.\nTelefon: 645 o. 945. Postgiro: 12793.\n\nAkt.-kap.: 120,000 kr. Antal\nindustriarb.: 125. Tillv.-värde pr år: 1,500,000 kr.\n— Firman etabl. 1923, bolag 1925.\n\nStyrelse: dir. Gert Sederholm, överste\nJ. M. Sederholm.\n\nVerkst. dir.: Gert Sederholm.\n\nKontorschef: fru M. LindholUi.\n\n31\n\nSkandinaviska Montanindustri AB.,\n\nHedemora.\n\nSe Skandinaviska Gruv AB.,\nHedemora.\n\n\"AB. Skandinaviska\nPelsvarufabri-ken, ivan Levy, Stockholm.\n\nTillverkar dampälsar, dräktgarneringar,\npälsgarnityrer, kragar, muffar, dam- och\nherrpälsmössor m. m.\n\nKontor: Norrlandsg. 15 A. Telegr.-adr.:\nPelsfabriken, Stockholm. Telefon: 231400.\nPostgiro: 3081.\n\nAkt.-kap.: 800,000 kr. Antal\nindustriarb.: 35. Tillv.-värde pr år: 860,000 kr.\n\n—\tFirman etabl. 1889, bolag 1922.\nStyrelse: fru S. Hanner, fru O. Hoff-\n\nstedt, fru B. Levy, adv. Leodor Levy,\ndir. Rolf Levy.\n\nVerkst. dir.: Rolf Levy.\n\n\"Skandinaviska Pipfabriken AB.,\n\nUddevalla.\n\nTillverkar rökpipor. Varunamn: »Skapi».\nTelegr.-adr.: Skapi, Uddevalla. Telefon:\n14320. Postgiro: 97680.\n\nAkt.-kap.: 300,000 kr. Antal\nindustriarb.: 75. Tillv.-värde pr år: 1,500,000 kr.\n\n—\tBolaget grundat 1936.\n\nStyrelse: adv. Gunnar Lewerth (ordf.),\ndir. Olof Jahn, bankdir. H. Lugner, dir.\nMax D. Sphwab.\n\nVerkst. dir.: Max D. Schwab.\n\n\"AB. Skandinaviska Remfabriken,\n\nGöteborg.\n\nTillverkar transport- och drivremmar\nav balata.\n\nKontor: Krokslätt, Göteborg.\nTelegr.-adr.: Skandrem, Göteborg. Telefon:\n171860 o. 271535. Postgiro: 41787.\n\nAkt.-kap.: 180,000 kr. Arb.-antal: 15.\nTillv.-värde pr år: 1,000,000 kr. —\nBolaget grundat 1906.\n\nStyrelse: övering. Knut V. Bildt, disp.\nCarl-Olof Ericsson, bankdir. Ebbe\nLundberg, adv. Torsten Setterberg, dir. Folke\nThulin.\n\nDisp.: Carl-Olof Ericsson.\n\n\"Skandinaviska Skorstensbyggnads\n\nAB., Stockholm.\n\nByggnadsentreprénörf irma för\nskorstensbyggnader och ångpanneinmurningar\nsamt murningar av industriugnar och\nsopförbränningsanläggningar.\n\nKontor: Hamngatan 16; postadr.:\n\nStockholm 7. Telegr.-adr.: Cementgjute-\n\n*",
    "structured": {
        "1": {
            "name": "Skandinaviska Jute-Spinneri- & Väfveri AB., Oskarström",
            "location": "Oskarström (Hallands l.)",
            "business": "Jutespinneri, väveri, blekeri, färgeri, appreturverk och säcksömnadsverkstäder",
            "products": "Tillverkar jutevaror, såsom säckar, packväv, pressduk etc.",
            "contact": {
                "office": "Oskarström",
                "phone": [
                    "220",
                    "765"
                ],
                "postgiro": "15500",
                "head_office": "Oskarström",
                "sales_offices": [
                    {
                        "location": "Stockholm",
                        "phone": "110433 o. 200475"
                    },
                    {
                        "location": "Malmö",
                        "phone": "26129"
                    }
                ],
                "telegraph": "Jutespinneriet, Öskarström",
                "factory_office": "",
                "factory_phone": ""
            },
            "financials": {
                "capital": "4,500,000 kr",
                "employees": {
                    "industriarb": 675
                },
                "annual_turnover": "",
                "annual_production_value": ""
            },
            "foundation_year": 1889,
            "board": [
                {
                    "name": "Carl August Wicander",
                    "role": "ordf."
                },
                {
                    "name": "Kjell Hägglöf",
                    "role": "v. ordf."
                },
                {
                    "name": "Gösta Blum",
                    "role": "civiling."
                },
                {
                    "name": "Eric Lindelöf",
                    "role": "dir."
                },
                {
                    "name": "Th. Nordström",
                    "role": "stadsfogde"
                },
                {
                    "name": "Isak R. Wallberg",
                    "role": "disp."
                }
            ],
            "director": "Wilhelm Österman",
            "managing_director": "Gösta Blum",
            "sales_manager": "kamrer Helge Johansson"
        },
        "2": {
            "name": "AB. Skandinaviska Korsettfabriken, Oskarshamn",
            "location": "Oskarshamn",
            "business": "Tillverkar korsetter, bysthållare och dithörande artiklar",
            "products": "Varumärke: »Fröja»",
            "contact": {
                "office": "Oskarshamn",
                "phone": [
                    "645",
                    "945"
                ],
                "postgiro": "12793",
                "head_office": "Oskarshamn",
                "sales_offices": [],
                "telegraph": "Fröja, Oskarshamn",
                "factory_office": "",
                "factory_phone": ""
            },
            "financials": {
                "capital": "120,000 kr",
                "employees": {
                    "industriarb": 125
                },
                "annual_turnover": "1,500,000 kr",
                "annual_production_value": ""
            },
            "foundation_year": 1923,
            "director": "Gert Sederholm",
            "managing_director": "Gert Sederholm",
            "sales_manager": "",
            "manager": ""
        },
        "3": {
            "name": "AB. Skandinaviska Pelsvarufabriken, ivan Levy, Stockholm",
            "location": "Stockholm",
            "business": "Tillverkar dampälsar, dräktgarneringar, pälsgarnityrer, kragar, muffar, dam- och herrpälsmössor m. m.",
            "products": "",
            "contact": {
                "office": "Norrlandsg. 15 A",
                "phone": [
                    "231400"
                ],
                "postgiro": "3081",
                "head_office": "Stockholm",
                "sales_offices": [],
                "telegraph": "Pelsfabriken, Stockholm",
                "factory_office": "",
                "factory_phone": ""
            },
            "financials": {
                "capital": "800,000 kr",
                "employees": {
                    "industriarb": 35
                },
                "annual_turnover": "860,000 kr",
                "annual_production_value": ""
            },
            "foundation_year": 1889,
            "director": "Rolf Levy",
            "managing_director": "Rolf Levy",
            "sales_manager": "",
            "manager": ""
        },
        "4": {
            "name": "Skandinaviska Pipfabriken AB., Uddevalla",
            "location": "Uddevalla",
            "business": "Tillverkar rökpipor",
            "products": "Varunamn: »Skapi»",
            "contact": {
                "office": "Uddevalla",
                "phone": [
                    "14320"
                ],
                "postgiro": "97680",
                "head_office": "Uddevalla",
                "sales_offices": [],
                "telegraph": "Skapi, Uddevalla",
                "factory_office": "",
                "factory_phone": ""
            },
            "financials": {
                "capital": "300,000 kr",
                "employees": {
                    "industriarb": 75
                },
                "annual_turnover": "1,500,000 kr",
                "annual_production_value": ""
            },
            "foundation_year": 1936,
            "director": "",
            "managing_director": "Max D. Schwab",
            "sales_manager": "",
            "manager": ""
        },
        "5": {
            "name": "AB. Skandinaviska Remfabriken, Göteborg",
            "location": "Göteborg",
            "business": "Tillverkar transport- och drivremmar av balata",
            "products": "",
            "contact": {
                "office": "Krokslätt, Göteborg",
                "phone": [
                    "171860",
                    "271535"
                ],
                "postgiro": "41787",
                "head_office": "Göteborg",
                "sales_offices": [],
                "telegraph": "Skandrem, Göteborg",
                "factory_office": "",
                "factory_phone": ""
            },
            "financials": {
                "capital": "180,000 kr",
                "employees": {
                    "industriarb": 15
                },
                "annual_turnover": "1,000,000 kr",
                "annual_production_value": ""
            },
            "foundation_year": 1906,
            "director": "",
            "managing_director": "",
            "sales_manager": "",
            "manager": ""
        },
        "6": {
            "name": "Skandinaviska Skorstensbyggnads AB., Stockholm",
            "location": "Stockholm",
            "business": "Byggnadsentreprénörf irma för skorstensbyggnader och ångpanneinmurningar samt murningar av industriugnar och sopförbränningsanläggningar",
            "products": "",
            "contact": {
                "office": "Hamngatan 16",
                "phone": [],
                "postgiro": "",
                "head_office": "Stockholm 7",
                "sales_offices": [],
                "telegraph": "Cementgjute-",
                "factory_office": "",
                "factory_phone": ""
            },
            "financials": {
                "capital": "",
                "employees": {},
                "annual_turnover": "",
                "annual_production_value": ""
            },
            "foundation_year": null,
            "director": "",
            "managing_director": "",
            "sales_manager": "",
            "manager": ""
        }
    }
}