{
    "original": "Frid—Fritsla\n\nAkt.-kap.: 163,500 kr. Antal\nindustriarb.: 30. Tillv.-värde pr år: 600,000 kr.\n— Fabriken, anlagd 1919, övertogs av\nnuv. ägare 1925.\n\nStyrelse: godsäg. Gust. Fimmerstad\n(ordf.), snickare Axel W. E. Andersson,\nciviling. Axel Björkman, ing. Swen\nLjungwall, ing. D. Tenning.\nDisp.: D. Tenning.\n(Jfr annons nr 54.)\n\n*Axel d. Hj. Frid, Möbelverkstad,\n\nStockholm.\nTillverkar möbler.\n\nKontor: Högbergsg. 48. Telefon:\n405909. Arb.-antal: 2. — Firman etabl.\n1916.\n\nÄgare o. chef: fabr. Axel J. Hj. Frid.\n\n* Fridafors Fabriks AB., Fridafors.\n\nPappfabrik med träsliperi och elektr.\nkraftstation vid Fridafors (Kronob. l.).\nTillverkar papp samt för eget behov mek.\nträmassa. Bolaget idkar jämväl\nskogshantering.\n\nTelegr.-adr.: Fridaf orsbolag,\nKarlshamn. Telefon: Ryd 9 o. Fridafors 40.\nPostgiro: 178100.\n\nFörsäljare: Gustaf N. Lundin,\nGöteborg, Kronhusg. 2 F, telefon: 116996;\nLevin &amp; Nyström, Göteborg, ö. Hamng.\n14, telefon: 116500; Björckander &amp; Co.\nAB., Malmö, Nordenskiöldsg. 7—9,\ntelefon: »Björckander &amp; Co.»; AB.\nSvanströms Pappersagentur, Stockholm 15,\ntelefon: 440035; Gunnar Bernhard,\nSundbyberg, telefon: Stockholm 283636.\n\nAgenter i utlandet: R. L. Lundgren\nLtd., 29, New Bridge Street, London,\nE. O. 4; George S. Russeli, 7, Exchequer\nChambers, Dublin C. L.; Aug. Caspers,\n26, Route Royale, Coq sur Mer, Belgien;\nKnud Lous, St. Kongensgade 110,\nKöpenhamn; Björckander &amp; Co. A/S, Vester\nFarimagsgade 35 A, Köpenhamn; H. L.\nSchuurmans-Agenturen, Rokin 69,\nAmsterdam; Maurice Barki, 9, rue Bergére,\nParis; Luis R. Rios, Virtudes 667,\nHavana, Cuba; Albert Floren, Commonwealth\nBuilding, 8—10 Adderley Str., Cape\nTown.\n\nAkt.-kap.: 1,737,500 kr. Antal\nindustriarb.: 220. Årstillv.: 10,000 ton ask- och\nkartongpapp. — Bolaget grundat 1892.\n\nStyrelse: adv. Rolf Nordenstedt (ordf.),\növerste Otto Broman, ryttm. Eugéne\nFlygare, dir. Einar Hansen, bankdir.\nIvar Åkerman.\n\nVerkst. dir.: Einar Hansen.\nDisp.: Sten Berger.\nKamrer: Henry J. Carlsson.\n\n*AB. Fridhems Tegelbruk,\n\nVänersborg.\n\nTillverkar murtegel, taktegel och\ndräneringsrör. Specialiteter: poröst\nmurtegel och månghåltegel.\n\nTelefon: 69. — Akt.-kap.: 85,000 kr.\nAntal industriarb.: 50. Årstillv.: 4 milj.\nst. tegelvaror. — Bolaget grundat 1914.\n\nStyrelse: dir. Einar Ström (ordf.), dir.\nAlvar Ström, dir. Hilding Ström, v.\nkonsul Ture Ström.\n\nVerkst. dir.: Hilding Ström.\n\nFridkulla Fabrikers AB.,\n\nGöteborg.\n\nStrumpfabrik vid Elisedal, Göteborg.\nTillverkar herr-, dam- och barnstrumpor\nav silke, ylle, bomull, ylle-flor m. m.\n\nTelegr.-adr.: Strumpfabriken,\nGöteborg. Telefon: 164110—11. Postgiro:\n43121. — Akt.-kap.: 750,000 kr. Antal\nindustriarb.: 230. — Firman etabl. 1932.\n\nStyrelse: dir. Gustaf Werner (ordf.),\ndir. Frans H. Nilsson, dir. Sven\nPettersson.\n\nVerkst. dir.: F. H. Nilsson.\n\nDisp.: L. O. Smedmark.\n\nFriseils Maskiner, Nacka.\n\nTillverkar snabbsvarvar vid fabrik i\nNacka (Stockholms l.).\n\nTelefon: 410425. Postgiro: 97483. —\nAntal industriarb.: 25. — Firman etabl.\n1906, ombildad under nuv. namn 1923.\n\nÄgare o. chef: ing. Hjalmar F. Friseli.\n\nFristads Snickerifabriks AB.,\n\nFristad.\n\nTillverkar byggnadssnickerier och\ninredningar m. m. samt utför\nbeställningssnickerier vid fabrik i Fristad (Älvsb. l.).\n\nTelefon: Borås 60017. Postgiro: 266538.\n\n—\tAkt.-kap.: 62,000 kr. Antal\nindustriarb.: 12. Tillv.-värde pr år: 250,000 kr.\n\n—\tFirman etabl. 1897, bolag 1905.\n\nDisp.: Albin Andersson.\n\nAB. Fritsla Cardinfabrik, Fritsla.\n\nGardinfabrik i Fritsla (Älvsb. l.).\nTillverkar allmoge- och marquisettegardiner\nsamt draperityger m. m.\n\nTelegr.-adr.: Garfab, Fritsla.\nTelefon: Kinna 70123. Postgiro: 93977. Repr.\ni Stockholm: Ejnar Hedin, Kungsg. 33,\ntelefon: 205888.\n\nAkt.-kap.: 100,000 kr. Antal\nindustriarb.: 35.\n\n165*",
    "structured": {
        "firms": [
            {
                "name": "Axel d. Hj. Frid, Möbelverkstad",
                "location": "Stockholm",
                "products": "Tillverkar möbler.",
                "contact": {
                    "office": "Högbergsg. 48",
                    "phone": [
                        "405909"
                    ],
                    "description": "Kontor: Högbergsg. 48. Telefon: 405909. Arb.-antal: 2.",
                    "head_office": "Stockholm",
                    "factory_office": null,
                    "factory_phone": null
                },
                "foundation_year": 1916,
                "owner": "Axel J. Hj. Frid"
            },
            {
                "name": "Fridafors Fabriks AB.",
                "location": "Fridafors",
                "products": "Tillverkar papp samt för eget behov mek. trämassa. Bolaget idkar jämväl skogshanterin",
                "contact": {
                    "telegraph": "Fridaforsbolag, Karlshamn",
                    "phone": [
                        "Ryd 9",
                        "Fridafors 40"
                    ],
                    "postgiro": "178100",
                    "sales_offices": [
                        {
                            "location": "Göteborg",
                            "phone": "116996"
                        },
                        {
                            "location": "Göteborg",
                            "phone": "116500"
                        },
                        {
                            "location": "Malmö",
                            "phone": "Björckander & Co."
                        },
                        {
                            "location": "Stockholm 15",
                            "phone": "440035"
                        },
                        {
                            "location": "Sundbyberg",
                            "phone": "Stockholm 283636"
                        }
                    ],
                    "description": "Telegr.-adr.: Fridaf orsbolag, Karlshamn. Telefon: Ryd 9 o. Fridafors 40. Postgiro: 178100."
                },
                "financials": {
                    "capital": "1,737,500 kr.",
                    "employees": {
                        "industriarb.": 220
                    },
                    "annual_turnover": "10,000 ton ask- och kartongpapp",
                    "annual_production_value": "Bolaget grundat 1892"
                },
                "board": [
                    {
                        "name": "adv. Rolf Nordenstedt",
                        "role": "ordf."
                    },
                    {
                        "name": "överste Otto Broman",
                        "role": null
                    },
                    {
                        "name": "ryttm. Eugéne Flygare",
                        "role": null
                    },
                    {
                        "name": "dir. Einar Hansen",
                        "role": null
                    }
                ],
                "owners": null,
                "director": null,
                "managing_director": "Einar Hansen",
                "sales_manager": null,
                "manager": null,
                "foundation_year": null,
                "corporation_year": 1892
            },
            {
                "name": "Fridkulla Fabrikers AB.",
                "location": "Göteborg",
                "products": "Tillverkar herr-, dam- och barnstrumpor av silke, ylle, bomull, ylle-flor m. m.",
                "contact": {
                    "telegraph": "Strumpfabriken, Göteborg",
                    "phone": [
                        "164110-11"
                    ],
                    "postgiro": "43121",
                    "description": "Telegr.-adr.: Strumpfabriken, Göteborg. Telefon: 164110-11. Postgiro: 43121."
                },
                "financials": {
                    "capital": "750,000 kr.",
                    "employees": {
                        "industriarb.": 230
                    },
                    "annual_turnover": null,
                    "annual_production_value": null
                },
                "board": [
                    {
                        "name": "dir. Gustaf Werner",
                        "role": "ordf."
                    },
                    {
                        "name": "dir. Frans H. Nilsson",
                        "role": null
                    },
                    {
                        "name": "dir. Sven Pettersson",
                        "role": null
                    }
                ],
                "owners": null,
                "director": null,
                "managing_director": "F. H. Nilsson",
                "sales_manager": null,
                "manager": null,
                "foundation_year": 1932,
                "corporation_year": null
            },
            {
                "name": "Friseils Maskiner",
                "location": "Nacka",
                "products": "Tillverkar snabbsvarvar vid fabrik i Nacka (Stockholms l.).",
                "contact": {
                    "phone": [
                        "410425"
                    ],
                    "postgiro": "97483",
                    "description": "Telefon: 410425. Postgiro: 97483."
                },
                "financials": {
                    "employees": {
                        "industriarb.": 25
                    }
                },
                "owner": "ing. Hjalmar F. Friseli"
            },
            {
                "name": "Fristads Snickerifabriks AB.",
                "location": "Fristad",
                "products": "Tillverkar byggnadssnickerier och inredningar m. m. samt utför beställningssnickerier vid fabrik i Fristad (Älvsb. l.).",
                "contact": {
                    "phone": [
                        "Borås 60017"
                    ],
                    "postgiro": "266538",
                    "description": "Telefon: Borås 60017. Postgiro: 266538."
                },
                "financials": {
                    "capital": "62,000 kr.",
                    "employees": {
                        "industriarb.": 12
                    },
                    "annual_turnover": "250,000 kr."
                },
                "board": [
                    {
                        "name": "Albin Andersson",
                        "role": null
                    }
                ],
                "owners": null,
                "director": null,
                "managing_director": null,
                "sales_manager": null,
                "manager": null,
                "foundation_year": 1905,
                "corporation_year": null
            },
            {
                "name": "AB. Fritsla Cardinfabrik",
                "location": "Fritsla",
                "products": "Tillverkar allmoge- och marquisettegardiner samt draperityger m. m.",
                "contact": {
                    "telegraph": "Garfab, Fritsla",
                    "phone": [
                        "Kinna 70123"
                    ],
                    "postgiro": "93977",
                    "description": "Telegr.-adr.: Garfab, Fritsla. Telefon: Kinna 70123. Postgiro: 93977."
                },
                "financials": {
                    "capital": "100,000 kr.",
                    "employees": {
                        "industriarb.": 35
                    }
                },
                "owner": "Ejnar Hedin"
            }
        ]
    }
}