{
    "original": "Rubens—Rulles\n\noch vävnader, operations- och\nhushållshandskar av gummi, dinappar, fingertutor\nsamt artiklar av plastie såsom regnkappor,\nregnhuvor, badmössor, babyartiklar m. m.\n\nTelegr.-adr.: Rubberfilm, Åmål.\nTelefon: 440. Postgiro: 83304.\n\nAkt.-kap.: 50,000 kr. Antal\nindustriarb.: 50. Tillv.-värde pr år: 1,200,000 kr.\n— Firman etabl. 1932.\n\nStyrelse: disp. Georg Levin (ordf.),\nfru G. Levin.\n\nDisp.: Georg Levin.\n\nFabrikschef: Sture Levin.\n\nRubens Yllefabrik, Ulricehamn.\n\nTillverkar herrvästar, slipovers,\ngensa-re m. m. vid trikåfabrik i Ulricehamn\n(Älvsb. l.).\n\nTelefon: 512. Postgiro: 93035. — Antal\nindustriarb.: 10. Tillv.-värde pr år:\n250,000 kr. — Firman etabl. 1934.\n\nÄgare o. chef: fabr. Ruben Larsson.\n\nWilh. Rubergs Fabriks AB.,\n\nLångebro.\n\nMek. verkstad, metall- och järngjuteri i\nImmeln samt syrgasfabrik i Långebro\n(båda i Kristianstads l.). Tillverkar\nmo-torbrandsprutor och brandpumpar,\nbilreservdelar och verktyg för bilverkstäder\nsamt syrgas och dissousgas.\n\nKontor: Långebro. Telefon:\nKristianstad 10174 o. 10178. Postgiro: 162649 o.\n\"288384. — Akt.-kap.: 30,000 kr. Antal\nindustriarb.: 20. — Bolaget grundat 1943.\n\nStyrelse o. verkst. dir.: ing. Wilh.\nRuberg.\n\nAB. Ruda Nya Glasindustri,\n\nRuda.\n\nGlasbruk i Ruda (Kalmar l.).\nTillverkar hushålls- och prydnadsglas.\n\nTelefon: 28. Postgiro: 99484.—\nAkt.-kap.: 24,200 kr. Antal industriarb.: 50.\n— Bolaget grundat 1934.\n\nChef: disp. Harry Johansson.\n\n\"Ruda Snickeri- &amp; Möbelfabrik,\nBröderna Andrée, Ruda.\n\nTillverkar stoppade möbler, stolar och\nfartygsinredningar samt sågade trävaror\nvid fabrik i Ruda (Kalmar l.).\nSpecialiteter: fåtöljer, sittsoffor o. kontorsstolar.\nFirman driver även handel med\nsvarvgods och träfiberplattor.\n\nTelefon: 4 o. 64. Postgiro: 23753. —\nAntal industriarb.: 20. Tillv.-värde pr år:\n\n200,000 kr. — Fabriken anlagd 1906, nuv.\nfirma etabl. 1933.\n\nÄgare o. chefer: fabr. Weine Andrée\no. fabr. Axel Andrée.\n\nRudberg &amp; Co., Fabriks AB7\n\nFalköping.\n\nSe Fabriks AB. Rudberg &amp; Co.,\nFalköping.\n\n\"AB. Rudelius &amp; Boklund, Lund.\n\nMek. verkstad, plåt- och kopp ar slageri.\nTillverkar mejerimaskiner och\nmejeri-apparater såsom pastorer, mjölkkylare,\nkärnältare, ysterimaskiner, pumpar,\nmjölktankar m. m. Utför arbeten av\naluminium och rostfritt stål.\n\nTelegr.-adr.: Rudebok, Lund. Telefon:\n»Separator». Postgiro: 98620.\n\nAkt.-kap.: 150,300 kr. Antal\nindustriarb.: 130. Tillv.-värde pr år: 3,000,000 kr.\n\n—\tFirman etabl. 1897, bolag 1911.\n\nStyrelse: herr S. G. Arph, dir. E.\n\nBrändström, dir. Folke Hellstedt, dir.\nViktor Henning, dir. Axel Wästfelt.\n\nVerkst. dir.: Viktor Henning.\n\n\"AB. P. Rudholms Konfektionsfabrik,\n\nBorås.\n\nTillverkar barn- och sportkläder.\nVarumärken: »Rudholms» o. »Pedon».\n\nTelegr.-adr.: Pedon, Borås. Telefon:\n15280. Postgiro: 130640.\n\nAkt.-kap.: 45,000 kr. Antal\nindustriarb.: 25. Tillv.-värde pr år: 500,000 kr.\n\n—\tFabriken anlagd 1932, bolag 1937.\n\nStyrelse: grossh. D. G. Rudholm.\n\nDisp.: P. Rudholm.\n\n\"AB. Rudin &amp; Comp. Läderfabrik,\n\nHallsberg.\n\nGarveri i Hallsberg (Örebro l.).\nTillverkar bottenläder.\n\nTelefon: 280 o. 353. — Akt.-kap.:\n250,000 kr. Antal industriarb.: 55.\nTillv.-värde pr år: 2,870,000 kr. — Bolaget\ngrundat 1930.\n\nStyrelse: dir. Gösta Åqvist, dir. Knut\nÅqvist, dir. Sven Åqvist.\n\nVerkst. dir.: Gösta Åqvist.\n\nAB. Rulles, Stockholm.\n\nEssensfabrik. Tillverkar såsom\nspecialitet likörextrakter, punsch-, cocktail-,\nsaft- och spirituosaextrakter,\nhushålls-aromer samt extrakter för restauranger\nm. m. Varumärke: »Rulles».\n\nKontor: Rörstrandsg. 37 A. Telegr.-",
    "structured": {
        "firmar": [
            {
                "name": "Rubens—Rulles och vävnader",
                "location": "Åmål",
                "business": "operations- och hushållshandskar av gummi, dinappar, fingertutor samt artiklar av plastie såsom regnkappor, regnhuvor, badmössor, babyartiklar m. m.",
                "contact": {
                    "telegraph": "Rubberfilm, Åmål",
                    "phone": [
                        "440"
                    ],
                    "postgiro": "83304"
                },
                "financials": {
                    "capital": "50,000 kr",
                    "employees": {
                        "industriarb.": 50
                    },
                    "annual_turnover": "1,200,000 kr"
                },
                "foundation_year": 1932,
                "board": [
                    {
                        "name": "disp. Georg Levin",
                        "role": "ordf."
                    },
                    {
                        "name": "fru G. Levin",
                        "role": null
                    }
                ],
                "director": "Georg Levin",
                "manager": "Sture Levin"
            },
            {
                "name": "Rubens Yllefabrik",
                "location": "Ulricehamn",
                "business": "Tillverkar herrvästar, slipovers, gensare m. m.",
                "contact": {
                    "phone": [
                        "512"
                    ],
                    "postgiro": "93035"
                },
                "financials": {
                    "employees": {
                        "industriarb.": 10
                    },
                    "annual_turnover": "250,000 kr"
                },
                "foundation_year": 1934,
                "owner": "fabr. Ruben Larsson"
            },
            {
                "name": "Wilh. Rubergs Fabriks AB.",
                "location": "Långebro",
                "business": "Mek. verkstad, metall- och järngjuteri i Immeln samt syrgasfabrik i Långebro (båda i Kristianstads l.). Tillverkar mo-torbrandsprutor och brandpumpar, bilreservdelar och verktyg för bilverkstäder samt syrgas och dissousgas.",
                "contact": {
                    "phone": [
                        "Kristianstad 10174",
                        "10178"
                    ],
                    "postgiro": "162649 o. 288384"
                },
                "financials": {
                    "capital": "30,000 kr",
                    "employees": {
                        "industriarb.": 20
                    }
                },
                "foundation_year": 1943,
                "director": "ing. Wilh. Ruberg"
            },
            {
                "name": "AB. Ruda Nya Glasindustri",
                "location": "Ruda",
                "business": "Tillverkar hushålls- och prydnadsglas",
                "contact": {
                    "phone": [
                        "28"
                    ],
                    "postgiro": "99484"
                },
                "financials": {
                    "capital": "24,200 kr",
                    "employees": {
                        "industriarb.": 50
                    }
                },
                "foundation_year": 1934,
                "manager": "disp. Harry Johansson"
            },
            {
                "name": "Ruda Snickeri- & Möbelfabrik, Bröderna Andrée",
                "location": "Ruda",
                "business": "Tillverkar stoppade möbler, stolar och fartygsinredningar samt sågade trävaror vid fabrik i Ruda (Kalmar l.). Specialiteter: fåtöljer, sittsoffor o. kontorsstolar.",
                "contact": {
                    "phone": [
                        "4",
                        "64"
                    ],
                    "postgiro": "23753"
                },
                "financials": {
                    "employees": {
                        "industriarb.": 20
                    },
                    "annual_turnover": "200,000 kr"
                },
                "foundation_year": "Fabriken anlagd 1906, nuv. firma etabl. 1933",
                "owners": [
                    "fabr. Weine Andrée",
                    "fabr. Axel Andrée"
                ]
            },
            {
                "name": "Rudberg & Co., Fabriks AB7",
                "location": "Falköping",
                "business": "Se Fabriks AB. Rudberg & Co., Falköping"
            },
            {
                "name": "AB. Rudelius & Boklund",
                "location": "Lund",
                "business": "Mek. verkstad, plåt- och kopp ar slageri. Tillverkar mejerimaskiner och mejeri-apparater såsom pastorer, mjölkkylare, kärnältare, ysterimaskiner, pumpar, mjölktankar m. m. Utför arbeten av aluminium och rostfritt stål.",
                "contact": {
                    "telegraph": "Rudebok, Lund",
                    "phone": [
                        "Separator"
                    ],
                    "postgiro": "98620"
                },
                "financials": {
                    "capital": "150,300 kr",
                    "employees": {
                        "industriarb.": 130
                    },
                    "annual_turnover": "3,000,000 kr"
                },
                "foundation_year": "Firman etabl. 1897, bolag 1911",
                "board": [
                    {
                        "name": "herr S. G. Arph",
                        "role": null
                    },
                    {
                        "name": "dir. E. Brändström",
                        "role": null
                    },
                    {
                        "name": "dir. Folke Hellstedt",
                        "role": null
                    },
                    {
                        "name": "dir. Viktor Henning",
                        "role": null
                    },
                    {
                        "name": "dir. Axel Wästfelt",
                        "role": null
                    }
                ],
                "director": "Viktor Henning"
            },
            {
                "name": "AB. P. Rudholms Konfektionsfabrik",
                "location": "Borås",
                "business": "Tillverkar barn- och sportkläder. Varumärken: »Rudholms» o. »Pedon».",
                "contact": {
                    "telegraph": "Pedon, Borås",
                    "phone": [
                        "15280"
                    ],
                    "postgiro": "130640"
                },
                "financials": {
                    "capital": "45,000 kr",
                    "employees": {
                        "industriarb.": 25
                    },
                    "annual_turnover": "500,000 kr"
                },
                "foundation_year": "Fabriken anlagd 1932, bolag 1937",
                "owner": "grossh. D. G. Rudholm",
                "director": "P. Rudholm"
            },
            {
                "name": "AB. Rudin & Comp. Läderfabrik",
                "location": "Hallsberg",
                "business": "Garveri i Hallsberg (Örebro l.). Tillverkar bottenläder.",
                "contact": {
                    "phone": [
                        "280",
                        "353"
                    ]
                },
                "financials": {
                    "capital": "250,000 kr",
                    "employees": {
                        "industriarb.": 55
                    },
                    "annual_turnover": "2,870,000 kr"
                },
                "foundation_year": 1930,
                "board": [
                    {
                        "name": "dir. Gösta Åqvist",
                        "role": null
                    },
                    {
                        "name": "dir. Knut Åqvist",
                        "role": null
                    },
                    {
                        "name": "dir. Sven Åqvist",
                        "role": null
                    }
                ],
                "director": "Gösta Åqvist"
            },
            {
                "name": "AB. Rulles",
                "location": "Stockholm",
                "business": "Essensfabrik. Tillverkar såsom specialitet likörextrakter, punsch-, cocktail-, saft- och spirituosaextrakter, hushålls-aromer samt extrakter för restauranger m. m. Varumärke: »Rulles».",
                "contact": {
                    "office": "Rörstrandsg. 37 A"
                }
            }
        ]
    }
}