{
    "original": "Heijl—Helle fors\n\nRutger Heijl AB., Stockholm.\n\nFarmaceutisk-kemisk fabrik vid\nTrångsund (Stockholm C). Tillverkar\nmedicinskt kol, kloramin m. m. samt disk- och\nrengöringsmedel, avfettningsmedel,\ntextilrengöringsmedel m. m. Varumärken:\n»Cleora», »Clipper» m. fl.\n\nPostadr.: Stockholm 20. Telegr.-adr.:\nHeijlab, Stockholm. Telefon:\nDrevviks-strand 150—153. Postgiro: 158648. —\nAkt.-kap.: 60,000 kr. Antal industriarb.:\n11. Tillv.-värde pr år: 300,000 kr. —\nBolaget grundat 1924.\n\nStyrelse o. verkst. dir.: Rutger C-son\nHeijl.\n\nKamrer: Bertil Kristensson.\n\nFörsäljn.-chef: Börje Altstad.\n\nAB. Hejarsmide, Enköping.\n\nSmidesverkstad. Utför som specialitet\nselsmide och hejade cykeldelar.\n\nTelefon: 370. Postgiro: 15060.\nEnsam-försälj. för cykeldelar: AB. Josef\nEriksson, Uppsala.\n\nAkt.-kap.: 100,000 kr. Antal\nindustriarb.: 32. Tillv.-värde pr år: 460,000 kr.\n— Firman etabl. 1920, bolag 1931.\n\nStyrelse; grossh. Erik Jonsson, dir. E.\nNissbeck, dir. E. J. P ålsson, fabr. Axel\nE. Söderberg.\n\nVerkst. dir.: E. Nissbeck.\n\nV ericstads chef: Ivan Söderberg.\n\n*Helios, Elektriska AB., Stockholm.\n\nSe Elektriska AB. Helios, Stockholm.\n\n’Hellos Kemisk-Tekniskä Fabriker\nAB., Stockholm.\n\nKem.-tekn. fabrik vid\nMidsommarkransen, Stockholm. Tillverkar tvättmedel,\nskur- och putspulver, bonvax,\nrengörings-och avfettningsmedel. Varumärken: »Vita\nTvättbjörn», »Standard», »Skur-Björn»,\n»Parkolin», »Persil», »Henko», »Per»,\n»Äta»., »P3» m. fl.\n\nKontor: Nybrokajen 7. Telegr.-adr.:\nHeliosbjörn, Stockholm. Telefon: 233980.\nPostgiro: 2137.\n\nAkt.-kap.: 1,500,000 kr. Antal\nindustriarb.: 115. — Firman etabl. 1902, bolag\n1931.\n\nStyrelse: dir. Thure Holmberg, adv.\nNils-Erik Lindblom, disp. Ivar Stille.\n\nVerkst. dir.: H. Koux.\n\nDisp.: Ivar Stille.\n\nFabrikschef: fil. dr Yngve Dalström.\n\n’AB. Helios Strumpfabriker,\n\nGöteborg.\n\nSe AB. Alingsås Trikåfabrik, Alingsås.\n\n’AB. C. V. Heljestrand, Eskilstuna.\n\nSmidesverkstad och stålvarufabrik.\nTillverkar rakknivar, rakhyvlar med\ntjocka blad, dam- och frisérsaxar,\npapperssaxar, korkskruvar samt kirurgiska\ninstrument.\n\nTelegr.-adr.: Heljestrand, Eskilstuna.\nTelefon: 30620 o. 34620. Postgiro: 10710.\n\nAkt.-kap.: 180,000 kr. Antal\nindustriarb.: 140. Tillv.-värde pr år: 1,500,000 kr.\n— Firman etabl. 1808, bolag 1907.\n\nStyrelse: f. kapten P. Bergsten, dir.\nRichard M. Kindal.\n\nVerkst. dir.: R. M. Kindal.\nDisp.: Gösta Lindblom.\n\n’Hellbergs Fabriks AB.,\n\nUlricehamn.\n\nTrikå- och herrkonfektionsfabrik.\nTillverkar herr- och barnkläder såsom\nkostymer, ulstrar, paletåer etc., arbetskläder\nsåsom overalls, byxor, blusar, skjortor\nm. m. samt trikåvaror såsom koftor,\nstrumpor, vantar, herrvästar, sweaters,\nslipovers o. d. Varumärken: »Hellbergs\nblåkläder», »Rutria», »Helltex» o.\n»Hell-rud».\n\nPost-, telegr.-adr. o. telefon: »Helltex»,\nUlricehamn. Postgiro: 8946. — Akt.-kap.:\n300,000 kr. Antal industriarb.: 85. —\nFirman etabl. 1915, bolag 1921, nuv. bolag\n1938.\n\nStyrelse: adv. E. Grenfors, grossh.\nJohn Hellberg, disp. Ernst H. Rudin.\n\nVerkst. dir.: John Hellberg.\n\nDisp.: E. H. Rudin.\n\n*J. A. Hellbergs Knivfabrik,\n\nEskilstuna.\n\nTillverkar rakknivar, jakt- och\nslidknivar samt hästsaxar.\n\nTelefon: 30646. Postgiro: 10797. —\nAntal industriarb.: 15. — Firman etabl.\n1891.\n\nÄgare o. chefer: fabr. Sven Hellberg o.\nkamrer Nils Hellberg.\n\n’Hellefors Bruks AB., Hällefors.\n\nBolaget äger Hellefors Bruk, Hällefors,\nSikfors Bruk, Sikfors, Bångbroverken,\nBångbro (samtl. i Örebro l.),\nFredriks-bergsverken, Fredriksberg (Kopparb. l.)\nsamt stållinefabrik i Kristinehamn\n(Värml. l.).\n\nHellefors Bruk, Hällefors. Järnbruk\nmed martin-, elektrostål- och\nvarmvalsverk, gjuteri, mek. verkstad, sågverk,\nhyvleri och lådfabrik samt snickerifabrik.\nTillverkar stål i sur eller basisk martin-",
    "structured": {
        "firms": [
            {
                "name": "Rutger Heijl AB",
                "location": "Stockholm",
                "business": "Farmaceutisk-kemisk fabrik",
                "products": "Tillverkar medicinskt kol, kloramin m.m. samt disk- och rengöringsmedel, avfettningsmedel, textilrengöringsmedel m.m. Varumärken: »Cleora», »Clipper» m.fl.",
                "contact": {
                    "office": "Trångsund (Stockholm C)",
                    "phone": [
                        "Drevviks-strand 150—153"
                    ],
                    "postgiro": "158648",
                    "head_office": "Stockholm 20",
                    "telegraph": "Heijlab, Stockholm",
                    "factory_office": "Factory office address.",
                    "factory_phone": "Factory phone number."
                },
                "financials": {
                    "capital": "60,000 kr",
                    "employees": {
                        "industriarb": 11
                    },
                    "annual_turnover": "300,000 kr",
                    "annual_production_value": "300,000 kr"
                },
                "foundation_year": 1924,
                "board": [
                    {
                        "name": "Rutger C-son Heijl",
                        "role": "Styrelse o. verkst. dir."
                    },
                    {
                        "name": "Bertil Kristensson",
                        "role": "Kamrer"
                    },
                    {
                        "name": "Börje Altstad",
                        "role": "Försäljn.-chef"
                    }
                ]
            },
            {
                "name": "AB. Hejarsmide",
                "location": "Enköping",
                "business": "Smidesverkstad",
                "products": "Utför som specialitet selsmide och heljade cykeldelar.",
                "contact": {
                    "office": "Office address.",
                    "phone": [
                        "370"
                    ],
                    "postgiro": "15060",
                    "sales_offices": [
                        {
                            "location": "AB. Josef Eriksson, Uppsala",
                            "phone": "Ensam-försälj. för cykeldelar"
                        }
                    ]
                },
                "financials": {
                    "capital": "100,000 kr",
                    "employees": {
                        "industriarb": 32
                    },
                    "annual_turnover": "460,000 kr"
                },
                "foundation_year": 1920,
                "corporation_year": 1931,
                "board": [
                    {
                        "name": "Erik Jonsson",
                        "role": "Styrelse"
                    },
                    {
                        "name": "E. Nissbeck",
                        "role": "dir."
                    },
                    {
                        "name": "E. J. P ålsson",
                        "role": "dir."
                    },
                    {
                        "name": "Axel E. Söderberg",
                        "role": "fabr."
                    }
                ]
            },
            {
                "name": "Hellos Kemisk-Tekniskä Fabriker AB.",
                "location": "Stockholm",
                "business": "Kemisk-tekn. fabrik",
                "products": "Tillverkar tvättmedel, skur- och putspulver, bonvax, rengörings-och avfettningsmedel. Varumärken: »Vita Tvättbjörn», »Standard», »Skur-Björn» m.fl.",
                "contact": {
                    "office": "Vid Midsommarkransen, Stockholm",
                    "phone": [
                        "233980"
                    ],
                    "postgiro": "2137"
                },
                "financials": {
                    "capital": "1,500,000 kr",
                    "employees": {
                        "industriarb": 115
                    },
                    "annual_production_value": "300,000 kr"
                },
                "foundation_year": 1902,
                "corporation_year": 1931,
                "board": [
                    {
                        "name": "Thure Holmberg",
                        "role": "dir."
                    },
                    {
                        "name": "Nils-Erik Lindblom",
                        "role": "adv."
                    },
                    {
                        "name": "Ivar Stille",
                        "role": "disp."
                    }
                ],
                "director": "H. Koux",
                "managing_director": "Yngve Dalström"
            },
            {
                "name": "AB. C. V. Heljestrand",
                "location": "Eskilstuna",
                "business": "Smidesverkstad och stålvarufabrik",
                "products": "Tillverkar rakknivar, rakhyvlar med tjocka blad, dam- och frisérsaxar, papperssaxar, korkskruvar samt kirurgiska instrument.",
                "contact": {
                    "telegraph": "Heljestrand, Eskilstuna",
                    "phone": [
                        "30620",
                        "34620"
                    ],
                    "postgiro": "10710"
                },
                "financials": {
                    "capital": "180,000 kr",
                    "employees": {
                        "industriarb": 140
                    },
                    "annual_turnover": "1,500,000 kr"
                },
                "foundation_year": 1808,
                "corporation_year": 1907,
                "board": [
                    {
                        "name": "P. Bergsten",
                        "role": "f. kapten"
                    },
                    {
                        "name": "Richard M. Kindal",
                        "role": "dir."
                    }
                ],
                "director": "R. M. Kindal",
                "managing_director": "R. M. Kindal",
                "sales_manager": "Gösta Lindblom"
            },
            {
                "name": "Hellbergs Fabriks AB",
                "location": "Ulricehamn",
                "business": "Trikå- och herrkonfektionsfabrik",
                "products": "Tillverkar herr- och barnkläder såsom kostymer, ulstrar, paletåer etc., arbetskläder såsom overalls, byxor, blusar, skjortor m.m. samt trikåvaror såsom koftor, strumpor, vantar, herrvästar, sweaters, slipovers o. d.",
                "contact": {
                    "office": "Trikå- och herrkonfektionsfabrik",
                    "phone": [
                        "Helltex, Ulricehamn"
                    ],
                    "postgiro": "8946"
                },
                "financials": {
                    "capital": "300,000 kr",
                    "employees": {
                        "industriarb": 85
                    }
                },
                "foundation_year": 1915,
                "corporation_year": 1938,
                "board": [
                    {
                        "name": "E. Grenfors",
                        "role": "adv."
                    },
                    {
                        "name": "John Hellberg",
                        "role": "grossh."
                    },
                    {
                        "name": "Ernst H. Rudin",
                        "role": "disp."
                    }
                ],
                "director": "John Hellberg",
                "managing_director": "John Hellberg",
                "sales_manager": "E. H. Rudin"
            },
            {
                "name": "J. A. Hellbergs Knivfabrik",
                "location": "Eskilstuna",
                "business": "Knivfabrik",
                "products": "Tillverkar rakknivar, jakt- och slidknivar samt hästsaxar.",
                "contact": {
                    "phone": [
                        "30646"
                    ],
                    "postgiro": "10797"
                },
                "employees": {
                    "industriarb": 15
                },
                "foundation_year": 1891,
                "owners": [
                    "fabr. Sven Hellberg",
                    "kamrer Nils Hellberg"
                ]
            },
            {
                "name": "Hellefors Bruks AB",
                "location": "Hällefors",
                "business": "Järnbruk, martin-, elektrostål- och varmvalsverk, gjuteri, mek. verkstad, sågverk, hyvleri och lådfabrik samt snickerifabrik.",
                "products": "Tillverkar stål i sur eller basisk martin-.",
                "corporation_year": 1907,
                "owners": [
                    "Hellefors Bruk, Hällefors",
                    "Sikfors Bruk, Sikfors",
                    "Bångbroverken, Bångbro",
                    "Fredriksbergsverken, Fredriksberg (Kopparb. l.)",
                    "stållinefabrik i Kristinehamn (Värml. l.)"
                ]
            }
        ]
    }
}