{
    "original": "Forsså—Fotoramar\n\n* Forsså Bruks AB., Näsviken.\n\nPapp- och kartongfabrik med träsliperi\nsamt sågverk och hvvleri vid Näsviken\n(Gävleb. l.). Tillverkar bokbinderipapp,\nask- och biljettkartong, middles, mek.\nträmassa samt sågade och hyvlade trävaror.\n\nTelegr.-adr.: Forssån, Näsviken.\nTelefon: 7. Postgiro: 8008. Ensamförsälj. av\npapp för Sverige: Edv. Schneidler AB.,\nStockholm, Malmskillnadsg. 54; telefon:\n232420.\n\nAkt.-kap.: 1,000,000 kr. Antal\nindustriarb.: 75. Årstillv.: 16,000 ton våt mek.\nträmassa, 10,000 ton kartong o. papp, 800\nstds sågade o. hyvlade trävaror. —\nBolaget grundat 1911.\n\nStyrelse: disp. Paul B. Burehardt,\nlandstingsm. L. J. Grönstedt, kamrer\nAnders Larsson, dir. Ernst Persson, major\nCarl Rhedin.\n\nVerkst. dir. o. disp.: P. B. Burehardt.\n\nFabrikschef: ing. A. R. Sundholm.\n\n*Forstners Paraplyfabriks AB.,\n\nStockholm.\n\nTillverkar paraplyer, parasoller och\npromenadkäppar.\n\nKontor: Mästersamuelsg. 61. Telefon:\n101142 o. 107270. Postgiro: 3122.\n\nAkt.-kap.: 20,000 kr. Antal\nindustriarb.: 31 samt 15 hemarbetare.\nTillv.-värde pr år: 1,100,000 kr. — Firman\netabl. 1853, bolag 1938.\n\nStyrelse o. verkst. direktörer: grossh.\nErik G. Lundquist o. disp. Börje\nLund-quist.\n\n*AB. Forsviks Bruk, Forsvik.\n\nMek. verkstad och gjuteri vid Forsvik\n(Skarab. l.).\n\nTillverkar gjutna rör och rördelar,\nlåg-tryckscentrifugalpumpar och\ndiafragmapumpar, brandposter, slussventiler,\nback-ventiler, bottenventiler, dilitationsmuffar,\nsugsilar. Bolaget idkar jämväl\nkvarn-rörelse.\n\nTelegr.-adr.: Forsviks, Forsvik.\nTelefon: 31. Postgiro: 80751. Ensamförsälj.\nför slussventiler: AB. Nordiska\nArmaturfabrikerna, Linköping; telefon:\n»Armaturbolaget».\n\nAkt.-kap.: 250,000 kr. Antal\nindustriarb.: 105. Tillv.-värde pr år: 1,200,000 kr.\n— Mek. verkstaden anlagd 1869, nuv.\nbolag grundat 1932.\n\nStyrelse: grossh. Axel Kindbom,\njäg-mäst. John Söderström, bruksäg. S. A.\nWiking.\n\nVerkst. dir.: A. Kindbom.\n\nDisp.: S. A. Wiking.\n\nKamrer: Eric Lindberg.\n\nDriftsing.: Lars Bergman.\n\n*Forsviks Skogar, Forsvik.\n\nTillverkar sågade och hyvlade trävaror,\nlaths, käppämnen m. m. samt träkol vid\nsågverk och hyvleri i Forsvik (Skarab.\n1.). Firman driver även skogs- och\nlantbruk.\n\nTelegr.-adr.: Forsskogar, Karlsborg*.\nTelefon: 51 o. 19. Postgiro: 28200.\n\nAntal industriarb.: 85. Årstillv.: l,50ö&lt;\nstds trävaror, 5,000 m3 träkol. — Firman\netabl. 1936.\n\nÄgare o. chef: disp. Sture W.\nJohansson.\n\nKamrer: Bertil W. Svahn.\n\n*Forså Pappersbruk, Kisa.\n\nSe AB. Långasjönäs Pappersbruk, Kisa..\n\nAB. Forsåkers Fabriker, Mölndal.\n\nBomullsspinneri och väveri. Tillverkar\ntrassel, skur-, disk-, puts- och\ndammhanddukar, vadd, bomullsgarn,\nbomullslinor, blånor, tjärdrev samt\npackningsgarn.\n\nTelegr.-adr.: Forsåkers, Mölndal.\nTelefon: Göteborg 272100. Postgiro: 45015.\nRepresentant: Olof Palmbäck,\nStockholm, Vasagatan 7, telefon: 208010.\n\nAkt.-kap.: 352,000 kr. Antal\nindustriarb.: 115. Tillv.-värde pr år: 2,000,000 kr.\n— Bolaget grundat 1880.\n\nStyrelse: disp. Carl Wictor Willumsen\n(ordf.), ing. Sten Haeger, dir.-ass.\nCarl-Björn Willumsen, ing. Mogens\nWillum-sen.\n\nVerkst. dir.: C. W. Willumsen.\n\nDir.-assist.: Carl-Björn Willumsen.\n\nInköps- o. försäljn.-chef: John Olsson,\n\n* Fosfatbolaget, Stockholm.\n\nSe Stockholms Superfosfat Fabriks\nAB., Stockholm.\n\nAB. Fotomekano, Stockholm.\n\nTillverkar fotografiska apparater samt\nmaskiner för fotografiska laboratorier*.\nVarumärken: »Fotomat», »Uniprint»*.\n»Unoscop» o. »Neoscop».\n\nKontor: Lästmakarg. 29. Telefon::\n113987.\n\nAkt.-kap.: 5,000 kr. Antal\nindustriarb.-25. Tillv.-värde pr år: 250,000 kr. —\nBolaget grundat 1940.\n\nVerkst. dir.: adv. Hakon Fallenius.\n\nAB. Fotoramar, Nyköping.\n\nTillverkar fotografi- och tavelramar.\n\nTelefon: 2466. Postgiro: 87392. —-\n\n»-x-",
    "structured": {
        "firms": [
            {
                "name": "Forsså Bruks AB",
                "location": "Näsviken",
                "business": "Papp- och kartongfabrik med träsliperi samt sågverk och hvvleri",
                "products": "Tillverkar bokbinderipapp, ask- och biljettkartong, middles, mek. trämassa samt sågade och hyvlade trävaror",
                "contact": {
                    "office": "Forssån, Näsviken",
                    "phone": [
                        "7"
                    ],
                    "postgiro": "8008",
                    "telegraph": "Forssån, Näsviken"
                },
                "financials": {
                    "capital": "1,000,000 kr",
                    "employees": {
                        "industriarb": 75
                    },
                    "annual_turnover": "16,000 ton våt mek. trämassa, 10,000 ton kartong o. papp, 800 stds sågade o. hyvlade trävaror"
                },
                "foundation_year": 1911,
                "board": [
                    {
                        "name": "Paul B. Burehardt",
                        "role": "disp."
                    },
                    {
                        "name": "L. J. Grönstedt",
                        "role": "landstingsm."
                    },
                    {
                        "name": "Anders Larsson",
                        "role": "kamrer"
                    },
                    {
                        "name": "Ernst Persson",
                        "role": "dir."
                    },
                    {
                        "name": "Carl Rhedin",
                        "role": "major"
                    }
                ],
                "director": "P. B. Burehardt",
                "factory_office": "Forssån, Näsviken"
            },
            {
                "name": "Forstners Paraplyfabriks AB",
                "location": "Stockholm",
                "business": "Tillverkar paraplyer, parasoller och promenadkäppar",
                "contact": {
                    "office": "Mästersamuelsg. 61",
                    "phone": [
                        "101142",
                        "107270"
                    ],
                    "postgiro": "3122"
                },
                "financials": {
                    "capital": "20,000 kr",
                    "employees": {
                        "industriarb": 31
                    },
                    "annual_turnover": "1,100,000 kr"
                },
                "foundation_year": 1853,
                "board": [
                    {
                        "name": "Erik G. Lundquist",
                        "role": "grossh."
                    },
                    {
                        "name": "Börje Lundquist",
                        "role": "disp."
                    }
                ]
            },
            {
                "name": "AB. Forsviks Bruk",
                "location": "Forsvik",
                "business": "Mek. verkstad och gjuteri",
                "products": "Tillverkar gjutna rör och rördelar, låg-tryckscentrifugalpumpar och diafragmapumpar, brandposter, slussventiler, back-ventiler, bottenventiler, dilitationsmuffar, sugsilar",
                "contact": {
                    "office": "Forsviks, Forsvik",
                    "phone": [
                        "31"
                    ],
                    "postgiro": "80751"
                },
                "financials": {
                    "capital": "250,000 kr",
                    "employees": {
                        "industriarb": 105
                    },
                    "annual_turnover": "1,200,000 kr"
                },
                "foundation_year": 1932,
                "board": [
                    {
                        "name": "Axel Kindbom",
                        "role": "grossh."
                    },
                    {
                        "name": "John Söderström",
                        "role": "jäg-mäst."
                    },
                    {
                        "name": "S. A. Wiking",
                        "role": "bruksäg."
                    }
                ],
                "director": "A. Kindbom"
            },
            {
                "name": "Forsviks Skogar",
                "location": "Forsvik",
                "business": "Tillverkar sågade och hyvlade trävaror, laths, käppämnen m. m. samt träkol",
                "contact": {
                    "office": "Forsskogar, Karlsborg",
                    "phone": [
                        "51",
                        "19"
                    ],
                    "postgiro": "28200"
                },
                "financials": {
                    "employees": {
                        "industriarb": 85
                    },
                    "annual_production_value": "l,50ö<stds trävaror, 5,000 m3 träkol"
                },
                "foundation_year": 1936,
                "owners": [
                    "disp. Sture W. Johansson"
                ],
                "manager": "Sture W. Johansson"
            },
            {
                "name": "AB. Forsåkers Fabriker",
                "location": "Mölndal",
                "business": "Bomullsspinneri och väveri",
                "products": "Tillverkar trassel, skur-, disk-, puts- och dammhanddukar, vadd, bomullsgarn, bomullslinor, blånor, tjärdrev samt packningsgarn",
                "contact": {
                    "office": "Forsåkers, Mölndal",
                    "phone": [
                        "Göteborg 272100"
                    ],
                    "postgiro": "45015"
                },
                "financials": {
                    "capital": "352,000 kr",
                    "employees": {
                        "industriarb": 115
                    },
                    "annual_production_value": "2,000,000 kr"
                },
                "foundation_year": 1880,
                "board": [
                    {
                        "name": "Carl Wictor Willumsen",
                        "role": "disp."
                    },
                    {
                        "name": "Sten Haeger",
                        "role": "ing."
                    },
                    {
                        "name": "Carl-Björn Willumsen",
                        "role": "dir.-ass."
                    },
                    {
                        "name": "Mogens Willum-sen",
                        "role": "ing."
                    }
                ],
                "director": "C. W. Willumsen",
                "managing_director": "C. W. Willumsen",
                "sales_manager": "John Olsson"
            },
            {
                "name": "AB. Fotomekano",
                "location": "Stockholm",
                "business": "Tillverkar fotografiska apparater samt maskiner för fotografiska laboratorier",
                "products": "Varumärken: »Fotomat», »Uniprint»*; »Unoscop» o. »Neoscop»",
                "contact": {
                    "office": "Lästmakarg. 29",
                    "phone": [
                        "113987"
                    ]
                },
                "financials": {
                    "capital": "5,000 kr",
                    "employees": {
                        "industriarb": 25
                    },
                    "annual_production_value": "250,000 kr"
                },
                "foundation_year": 1940,
                "director": "adv. Hakon Fallenius"
            },
            {
                "name": "AB. Fotoramar",
                "location": "Nyköping",
                "business": "Tillverkar fotografi- och tavelramar",
                "contact": {
                    "phone": [
                        "2466"
                    ],
                    "postgiro": "87392"
                }
            }
        ]
    }
}