{
    "original": "Try eke ri—Try ckrör\n\n\"Tryckeri AB. Aurora, Ystad.\n\nBok- och tidningstryckeri. Utgiver\ntidningen »Aurora» (daglig tidning för\nsydöstra Skåne) samt utför tidskrifter,\nbroschyrer, accidenstryck, affischer\nm. m.\n\nTelefon: »Aurora». Postgiro: 28433.\n\nAkt.-kap.: 83,510 kr. Antal\nindustriarb.: 15. Tillv.-värde pr år: 325,000 kr.\n\n—\tBolaget grundat 1899.\n\nStyrelse: byggm. Nils J. Persson\n(ordf.), rektor Holger Holmgren,\nom-budsm. Per Krantz, ekonomichef Josef\nOhlsson, kassör Axel Strand, red. Ludvig\nTörnqvist, vaktm. August Wiberg.\n\nVerkst. dir.: Josef Ohlsson.\n\n*Tryckeri AB. Framtiden i Malmö,\n\nMalmö.\n\nUtför tidnings-, tidskrifts- och\nboktryck, accidenstryck, reklamtryck m. m.\nBolaget utger tidningen »Arbetet».\n\nKontor: Bergsg. 20. Telefon:\n»Arbetet». Postgiro: 14065.\n\nAkt.-kap.: 500,000 kr. Arb.-antal (tekn.\navd.): 73. Tillv.-värde pr år: 2,500,000\nkr. — Bolaget grundat 1897.\n\nStyrelse: ombudsm. N. O. Persson\n(ordf.), förbundsordf. Otto Friman,\nchefred. Gösta Netzén, expeditör Per Larsson,\nkassör Axel Strand, expeditör Eric\nSvensson, red. A. Uhlén, dir. Helmer Wikström.\n\nVerkst. dir. - Helmer Wikström.\n\n*Tryckeri AB. Småland, Jönköping.\n\nTidnings- och boktryckeri. Tillverkar\ntidningar, böcker, broschyrer, affischer\nsamt accidenstryck. Varumärke: »Tabs».\n\nTelefon: 3930—35. Postgiro: 11566.\n\nAkt.-kap.: 248,200 kr. Antal\nindustriarb.: 49. Prod.-värde pr år: 1,060,000 kr.\n\n—\tBolaget, grundat 1902, utger tidningen\n»Smålands Folkblad».\n\nStyrelse: bruksarb. Arnold Bolin, dir.\nErnst Karlson, förman Carl Kvist,\nlinjeförman Johan Skoog, dir. Ragnar\nÅkerberg, kontorist Alvar österberg, typograf\nJohn östergren.\n\nVerkst. dir. o. ekonomichef: Ragnar\nÅkerberg.\n\nTryckeri AB. Svea, Stockholm.\n\nUtför illustrationstryck, kataloger och\naffärstryck\n\nKontor: Grevtureg. 11. Telefon: 670675.\nPostgiro: 50316.\n\nAkt.-kap.: 100,000 kr. Antal\nindustriarb.: 30. Tillv.-värde pr år: 650,000 kr.\n\nFirman etabl. 1900, nuv. bolag grundat\n\n1902. Bolaget äger AB. Skandinaviska\nBokb. och Kartongfabriken, Stockholm.\n\nStyrelse: dir. Ejnar Ohlsson (ordf.),\ndir. Josef Holmquist, disp. Tage\nHolmquist.\n\nVerkst. dir.: Ejnar Ohlsson.\n\nTryckeri AB. Sätherlund &amp; Krook,\n\nStockholm.\n\nUtför bok- och tidningstryck samt\nbok-binderiarbeten.\n\nKontor: Klarabergsg. 52. Telefon:\n108038—39. Postgiro: 198212.\n\nAkt.-kap.: 25,400 kr. Antal\nindustriarb.: 14. Tillv.-värde pr år: 190.000 kr.\n\nFirman etabl. 1915 under namn\nHedberg &amp; Krook, bolag 1916, nuv. namn\n1917.\n\nStyrelse: fru Waldy Sätherlund (ordf.),\nfaktor Eugen Krook, boktryckare Stig\nSätherlund.\n\nVerkst. dir.: Stig Sätherlund.\n\n*Tryckerl AB. Thule, Stockholm.\n\nBoktryckeri och bokbinderi. Utför\nboktryck, vetenskapliga arbeten, affärstryck,\ntidskrifter m. m.\n\nKontor: S:t Eriksg. 33. Telefon:\n520245. Postgiro: 52545.\n\nAkt.-kap.: 140,000 kr. Antal\nindustriarb.: 90. Tillv.-värde pr år: 1,000,000 kr.\n— Tryckeriet anlagt 1914, nuv. bolag\ngrundat 1926.\n\nStyrelse: dir. E. Frieberg (ordf.),\nkamrer Edvin Andersson, fru A. Frieberg,\ndisp. Nils Nordqvist.\n\nDisp.: Nils Nordqvist.\n\nAB. Tryckfärger, Stockholm.\n\nTillverkar tryckfärger samt stilmetall.\nBolaget driver även försäljning av\nmaskiner och förnödenheter för den grafiska\nindustrien.\n\nKontor: Drottningg. 10. Telegr.-adr.:\nAbetesto, Stockholm. Telefon: 233485.\nPostgiro: 50471.\n\nAkt.-kap.: 250,000 kr. Antal\nindustriarb.: 9. Tillv.-värde pr år: 700,000 kr. —\nBolaget grundat 1924.\n\nVerkst. dir.: civiling. Sten Thiel.\n\nDisp.: Pehr Griberg.\n\nFabrikschef: Karl Muller.\n\nAB. Tryckrör, Limhamn.\n\nBetongvarufabrik i Limhamn (Malmöh.\n1.). Tillverkar bonnarör avsedda för\nledningar med höga tryck (2—20 atö) och\ncentrifugalgjutna rör för\nlågtrycksledningar (0—2 atö).",
    "structured": {
        "1": {
            "name": "Tryckeri AB. Aurora",
            "location": "Ystad",
            "business": "Bok- och tidningstryckeri",
            "products": "Utgiver tidningen »Aurora» (daglig tidning för sydöstra Skåne) samt utför tidskrifter, broschyrer, accidenstryck, affischer m. m.",
            "contact": {
                "office": "Aurora",
                "phone": [
                    "Phone number not provided"
                ],
                "postgiro": "28433"
            },
            "financials": {
                "capital": "83,510 kr",
                "employees": {
                    "industriarb": 15
                },
                "annual_turnover": "325,000 kr",
                "annual_production_value": "Not provided"
            },
            "foundation_year": 1899,
            "board": [
                {
                    "name": "Nils J. Persson",
                    "role": "byggm."
                },
                {
                    "name": "Holger Holmgren",
                    "role": "rektor"
                },
                {
                    "name": "Per Krantz",
                    "role": "om-budsm."
                },
                {
                    "name": "Josef Ohlsson",
                    "role": "ekonomichef"
                },
                {
                    "name": "Axel Strand",
                    "role": "kassör"
                },
                {
                    "name": "Ludvig Törnqvist",
                    "role": "red."
                },
                {
                    "name": "August Wiberg",
                    "role": "vaktm."
                }
            ],
            "director": "Josef Ohlsson"
        },
        "2": {
            "name": "Tryckeri AB. Framtiden i Malmö",
            "location": "Malmö",
            "business": "Utför tidnings-, tidskrifts- och boktryck, accidenstryck, reklamtryck m. m. Bolaget utger tidningen »Arbetet».",
            "contact": {
                "office": "Arbetet",
                "phone": [
                    "Phone number not provided"
                ],
                "postgiro": "14065"
            },
            "financials": {
                "capital": "500,000 kr",
                "employees": {
                    "tekn. avd.": 73
                },
                "annual_turnover": "2,500,000 kr",
                "annual_production_value": "Not provided"
            },
            "foundation_year": 1897,
            "board": [
                {
                    "name": "N. O. Persson",
                    "role": "ombudsm."
                },
                {
                    "name": "Otto Friman",
                    "role": "förbundsordf."
                },
                {
                    "name": "Gösta Netzén",
                    "role": "chefred."
                },
                {
                    "name": "Per Larsson",
                    "role": "expeditör"
                },
                {
                    "name": "Axel Strand",
                    "role": "kassör"
                },
                {
                    "name": "Eric Svensson",
                    "role": "expeditör"
                },
                {
                    "name": "A. Uhlén",
                    "role": "red."
                },
                {
                    "name": "Helmer Wikström",
                    "role": "dir."
                }
            ],
            "director": "Helmer Wikström"
        },
        "3": {
            "name": "Tryckeri AB. Småland",
            "location": "Jönköping",
            "business": "Tidnings- och boktryckeri",
            "products": "Tillverkar tidningar, böcker, broschyrer, affischer samt accidenstryck. Varumärke: »Tabs».",
            "contact": {
                "office": "Not provided",
                "phone": [
                    "3930—35"
                ],
                "postgiro": "11566"
            },
            "financials": {
                "capital": "248,200 kr",
                "employees": {
                    "industriarb": 49
                },
                "annual_turnover": "1,060,000 kr",
                "annual_production_value": "Not provided"
            },
            "foundation_year": 1902,
            "board": [
                {
                    "name": "Arnold Bolin",
                    "role": "bruksarb."
                },
                {
                    "name": "Ernst Karlson",
                    "role": "dir."
                },
                {
                    "name": "Carl Kvist",
                    "role": "förman"
                },
                {
                    "name": "Johan Skoog",
                    "role": "linjeförman"
                },
                {
                    "name": "Ragnar Åkerberg",
                    "role": "dir."
                },
                {
                    "name": "Alvar österberg",
                    "role": "kontorist"
                },
                {
                    "name": "John östergren",
                    "role": "typograf"
                }
            ],
            "director": "Ragnar Åkerberg"
        },
        "4": {
            "name": "Tryckeri AB. Svea",
            "location": "Stockholm",
            "business": "Utför illustrationstryck, kataloger och affärstryck",
            "contact": {
                "office": "Not provided",
                "phone": [
                    "670675"
                ],
                "postgiro": "50316"
            },
            "financials": {
                "capital": "100,000 kr",
                "employees": {
                    "industriarb": 30
                },
                "annual_turnover": "650,000 kr",
                "annual_production_value": "Not provided"
            },
            "corporation_year": 1902,
            "board": [
                {
                    "name": "Ejnar Ohlsson",
                    "role": "dir."
                },
                {
                    "name": "Josef Holmquist",
                    "role": "dir."
                },
                {
                    "name": "Tage Holmquist",
                    "role": "disp."
                }
            ],
            "director": "Ejnar Ohlsson"
        },
        "5": {
            "name": "Tryckeri AB. Sätherlund & Krook",
            "location": "Stockholm",
            "business": "Utför bok- och tidningstryck samt bok-binderiarbeten",
            "contact": {
                "office": "Not provided",
                "phone": [
                    "108038—39"
                ],
                "postgiro": "198212"
            },
            "financials": {
                "capital": "25,400 kr",
                "employees": {
                    "industriarb": 14
                },
                "annual_turnover": "190,000 kr",
                "annual_production_value": "Not provided"
            },
            "corporation_year": 1917,
            "board": [
                {
                    "name": "Waldy Sätherlund",
                    "role": "fru"
                },
                {
                    "name": "Eugen Krook",
                    "role": "faktor"
                },
                {
                    "name": "Stig Sätherlund",
                    "role": "boktryckare"
                }
            ],
            "director": "Stig Sätherlund"
        },
        "6": {
            "name": "Tryckerl AB. Thule",
            "location": "Stockholm",
            "business": "Boktryckeri och bokbinderi. Utför boktryck, vetenskapliga arbeten, affärstryck, tidskrifter m. m.",
            "contact": {
                "office": "Not provided",
                "phone": [
                    "520245"
                ],
                "postgiro": "52545"
            },
            "financials": {
                "capital": "140,000 kr",
                "employees": {
                    "industriarb": 90
                },
                "annual_turnover": "1,000,000 kr",
                "annual_production_value": "Not provided"
            },
            "corporation_year": 1926,
            "board": [
                {
                    "name": "E. Frieberg",
                    "role": "dir."
                },
                {
                    "name": "Edvin Andersson",
                    "role": "kamrer"
                },
                {
                    "name": "A. Frieberg",
                    "role": "fru"
                },
                {
                    "name": "Nils Nordqvist",
                    "role": "disp."
                }
            ],
            "director": "Nils Nordqvist"
        },
        "7": {
            "name": "AB. Tryckfärger",
            "location": "Stockholm",
            "business": "Tillverkar tryckfärger samt stilmetall. Bolaget driver även försäljning av maskiner och förnödenheter för den grafiska industrion",
            "contact": {
                "office": "Abetesto",
                "phone": [
                    "233485"
                ],
                "postgiro": "50471"
            },
            "financials": {
                "capital": "250,000 kr",
                "employees": {
                    "industriarb": 9
                },
                "annual_turnover": "700,000 kr",
                "annual_production_value": "Not provided"
            },
            "corporation_year": 1924,
            "board": [
                {
                    "name": "Sten Thiel",
                    "role": "civiling."
                },
                {
                    "name": "Pehr Griberg",
                    "role": "disp."
                },
                {
                    "name": "Karl Muller",
                    "role": "Fabrikschef"
                }
            ]
        },
        "8": {
            "name": "AB. Tryckrör",
            "location": "Limhamn",
            "business": "Betongvarufabrik i Limhamn. Tillverkar bonnarör avsedda för ledningar med höga tryck (2—20 atö) och centrifugalgjutna rör för lågtrycksledningar (0—2 atö).",
            "contact": {
                "office": "Not provided",
                "phone": [
                    "Phone number not provided"
                ],
                "postgiro": "Not provided"
            }
        }
    }
}