{
    "original": "RegnkappfabriJcen—Reijmyre\n\n*AB. Regn kappf abr i ken i Stockholm,\n\nStockholm.\n\nTillverkar herr-, dam- oeh\nbarnregn-kappor, poplin-, bomulls- och\ngabardin-rockar samt sportjackor. Varumärken:\n»Libelle» o. »Trassy».\n\nKontor: Brännkyrkag. 165. Telefon:\n440515. Postgiro: 150224.\n\nAkt.-kap.: 40,000 kr. Antal\nindustriarb.: 175. Tillv.-värde pr år: 6,000,000 kr.\n\n—\tBolaget grundat 1936.\n\nStyrelse; adv. Mauritz Griinberger.\n\nFabrikschef: dir. Siegbert Kiewe.\n\n*Regnklädersfabrlken Vargen AB.,\n\nNorrköping.\n\nTillverkar regnkläder alla slag,\noljekläder, fiskarkläder, oljeduk, sjukhusduk,\ntrenchcoats och sportkläder samt\növerdragskläder (overalls). Varumärken:\n»Vargen» o. »Albatross».\n\nTelegr.-adr. o. telefon: Vargen,\nNorrköping. Postgiro: 11098.\n\nAkt.-kap.: 300,000 kr. Antal\nindustriarb.: 175. Tillv.-värde pr år: 4,000,000 kr.\n\n—\tBolaget grundat 1898.\n\nStyrelse: överdir. Ryno Lundqvist\n(ordf.), disp. Eric Alkner, kamrer Eric\nStenson, disp. Ragnar Öländer.\n\nVerkst. dir. o. disp.: Eric Alkner.\n\n* Regn konfektions AB., Stockholm.\n\nTillverkar regnkläder.\n\nKontor: Igeldammsg. 22. Telegr.-adr.:\nRegnkonfektion, Stockholm. Telefon:\n500960. Postgiro: 156927.\n\nAkt.-kap.: 80,000 kr. Antal\nindustriarb.: 75, Tillv.-värde pr år: 1,700,000 kr.\n\n—\tBolaget grundat 1939.\n\nStyrelse: dir. S. Gerov, dir. M. Kaplan.\n\nVerkst. dir.: S. Gerov.\n\n^Regulator AB. Armas, Stockholm.\n\nMek. verkstad. Tillverkar\ntryckregulatorer för ånga, vatten och gaser,\nångom-formare, elektr. regulatorer, regulatorer\nför hållandet av viss temperatur,\nfuktighet, nivå, koncentration, hastighet m. m.\nVarumärke: »Armas».\n\nKontor; Svedenborgsg. 7. Telefon:\n410178. Postgiro: 3277.\n\nAkt.-kap.: 180,000 kr. Antal\nindustriarb.: 18. Tillv.-värde pr år: 375,000 kr.\n\nFirman etabl. 1923.\n\nStyrelse: ing. A. M. Sjöö (ordf.), ing.\nPer Johansson, arkitekt Mårten Karlson.\n\nVerkst. dir.: A. M. Sjöö.\n\nFörsäljn.-chef: K. Edqvist.\n\nRegulator- &amp; Instrument AB.\nBillman, Stockholm.\n\nElektrömek. verkstad. Tillverkar\nautomatiska regulatorer för temperatur, tryck,\nnivå, fuktighet, gastryck m. m. för värme\noch ventilation, andra regulatorer för\nindustriella tillämpningar samt\nfotoelektriska regulatorer, magnetreläer,\nmotor-skydd, kontaktorer och kortslutna motorer\nför motorventiler.\n\nKontor: Lindhagensg. 126—128.\nTelegr.-adr.: Billcontrol, Stockholm. Telefon:\n520320. Postgiro: 54396. Avd.-kontor:\nGöteborg, Richertsg. 14, telefon: 160025:\nMalmö, S:t Johannesg. 2, telefon: 21422;\nKarlstad, telefon: 13576.\n\nAkt.-kap.: 200,000 kr. Antal\nindustriarb.: 95. Tillv.-värde pr år: 1,700,000 kr.\n\n—\tFirman etabl. 1932 under namn Stig\nK. M. Billman, nuv. namn och bolag 1945.\n\nStyrelse: civiling. Stig K, M. Billmah,\ndir. Gunnar Dalén, bankdir. Tor Stenberg.\n\nVerkst. dir.: Stig K. M. Billman.\n\nFörsäljn.-chef: civiling. Curt Haij.\n\nKonstruktions- o. driftschef: övering.\nTure Lindblad.\n\nAvd.-chefer: Göteborg: ing. Per\nGrau-ers; Malmö: dipl. ing. Kjell Rode;\nKarlstad: ing. Sigvard Reinholdsson.\n\nReijmyre Glasbruk AB.,\n\nRejmyra.\n\nGlasbruk vid Rejmyra lÖstergötl. l.).\nTillverkar hushållsglas, tekn. glas,\napoteksglas och prydnadsglas.\n\nTelegr.-adr.: Reijmyreglas, Norrköping.\nTelefon: Rejmyra 12 o. 36. Postgiro:\n131888.\n\nAkt.-kap.: 60,000 kr. Antal\nindustriarb.: 80. Tillv.-värde pr år: 500,000 kr.\n\nBruket anlagt 1808, nuv. bolag grundat\n1937.\n\nStyrelse: prof. Rolf Sievert (ordf.),\nfru II. Almqvist, kapten R. G:son\nSjöberg.\n\nDisp.: Einar Rosengren.\n\nAB. Reijmyre Lädervarufabrik,\n\nNorrköping.\n\nTillverkar ryggsäckar, remmar, väskor,\npackfickor m. m. samt plånböcker och\nportmonnäer.\n\nTelegr.-adr.: Rejsport, Norrköping.\nTelefon: 23141. Postgiro: 26232,\n\nAkt.-kap.: 43,000 kr. Antal\nindustriarb.: 20. Tillv.-värde pr år: 200,000 kr.\n\n—\tBolaget grundat 1933, ombildat 1938.\n\nVerkst. dir.: fabr. Nils Ringdahl.\n\n1*",
    "structured": {
        "firms": [
            {
                "name": "AB. Regn kappf abr i ken",
                "location": "Stockholm",
                "business": "Tillverkar herr-, dam- oeh barnregn-kappor, poplin-, bomulls- och gabardin-rockar samt sportjackor. Varumärken: »Libelle» o. »Trassy».",
                "contact": {
                    "office": "Brännkyrkag. 165",
                    "phone": [
                        "440515"
                    ],
                    "postgiro": "150224"
                },
                "financials": {
                    "capital": "40,000 kr",
                    "employees": {
                        "industriarb": 175
                    },
                    "annual_turnover": "6,000,000 kr",
                    "annual_production_value": "6,000,000 kr"
                },
                "foundation_year": 1936,
                "board": [
                    {
                        "name": "adv. Mauritz Griinberger",
                        "role": "Styrelse"
                    }
                ],
                "director": "dir. Siegbert Kiewe"
            },
            {
                "name": "Regnklädersfabrlken Vargen AB.",
                "location": "Norrköping",
                "business": "Tillverkar regnkläder alla slag, oljekläder, fiskarkläder, oljeduk, sjukhusduk, trenchcoats och sportkläder samt överdragskläder (overalls). Varumärken: »Vargen» o. »Albatross».",
                "contact": {
                    "telegraph": "Vargen, Norrköping",
                    "phone": [
                        "Vargen, Norrköping"
                    ],
                    "postgiro": "11098"
                },
                "financials": {
                    "capital": "300,000 kr",
                    "employees": {
                        "industriarb": 175
                    },
                    "annual_turnover": "4,000,000 kr",
                    "annual_production_value": "4,000,000 kr"
                },
                "foundation_year": 1898,
                "board": [
                    {
                        "name": "överdir. Ryno Lundqvist",
                        "role": "ordförande"
                    },
                    {
                        "name": "disp. Eric Alkner",
                        "role": "Styrelse"
                    },
                    {
                        "name": "kamrer Eric Stenson",
                        "role": "Styrelse"
                    },
                    {
                        "name": "disp. Ragnar Öländer",
                        "role": "Styrelse"
                    }
                ],
                "director": "Eric Alkner"
            },
            {
                "name": "Regn konfektions AB.",
                "location": "Stockholm",
                "business": "Tillverkar regnkläder.",
                "contact": {
                    "office": "Igeldammsg. 22",
                    "phone": [
                        "500960"
                    ],
                    "postgiro": "156927"
                },
                "financials": {
                    "capital": "80,000 kr",
                    "employees": {
                        "industriarb": 75
                    },
                    "annual_turnover": "1,700,000 kr",
                    "annual_production_value": "1,700,000 kr"
                },
                "foundation_year": 1939,
                "board": [
                    {
                        "name": "dir. S. Gerov",
                        "role": "Styrelse"
                    },
                    {
                        "name": "dir. M. Kaplan",
                        "role": "Styrelse"
                    }
                ],
                "director": "S. Gerov"
            },
            {
                "name": "Regulator AB. Armas",
                "location": "Stockholm",
                "business": "Mek. verkstad. Tillverkar tryckregulatorer för ånga, vatten och gaser, ångom-formare, elektr. regulatorer, regulatorer för hållandet av viss temperatur, fuktighet, nivå, koncentration, hastighet m. m. Varumärke: »Armas».",
                "contact": {
                    "office": "Svedenborgsg. 7",
                    "phone": [
                        "410178"
                    ],
                    "postgiro": "3277"
                },
                "financials": {
                    "capital": "180,000 kr",
                    "employees": {
                        "industriarb": 18
                    },
                    "annual_turnover": "375,000 kr",
                    "annual_production_value": "375,000 kr"
                },
                "corporation_year": 1923,
                "board": [
                    {
                        "name": "ing. A. M. Sjöö",
                        "role": "ordförande"
                    },
                    {
                        "name": "ing. Per Johansson",
                        "role": "Styrelse"
                    },
                    {
                        "name": "arkitekt Mårten Karlson",
                        "role": "Styrelse"
                    }
                ],
                "director": "A. M. Sjöö",
                "sales_manager": "K. Edqvist"
            },
            {
                "name": "Regulator- & Instrument AB. Billman",
                "location": "Stockholm",
                "business": "Elektrömek. verkstad. Tillverkar automatiska regulatorer för temperatur, tryck, nivå, fuktighet, gastryck m. m. för värme och ventilation, andra regulatorer för industriella tillämpningar samt fotoelektriska regulatorer, magnetreläer, motor-skydd, kontaktorer och kortslutna motorer för motorventiler.",
                "contact": {
                    "office": "Lindhagensg. 126—128",
                    "phone": [
                        "520320"
                    ],
                    "postgiro": "54396",
                    "sales_offices": [
                        {
                            "location": "Göteborg",
                            "phone": "160025"
                        },
                        {
                            "location": "Malmö",
                            "phone": "21422"
                        },
                        {
                            "location": "Karlstad",
                            "phone": "13576"
                        }
                    ]
                },
                "financials": {
                    "capital": "200,000 kr",
                    "employees": {
                        "industriarb": 95
                    },
                    "annual_turnover": "1,700,000 kr",
                    "annual_production_value": "1,700,000 kr"
                },
                "corporation_year": 1945,
                "board": [
                    {
                        "name": "civiling. Stig K, M. Billmah",
                        "role": "Styrelse"
                    },
                    {
                        "name": "dir. Gunnar Dalén",
                        "role": "Styrelse"
                    },
                    {
                        "name": "bankdir. Tor Stenberg",
                        "role": "Styrelse"
                    }
                ],
                "director": "Stig K. M. Billman",
                "sales_manager": "civiling. Curt Haij",
                "manager": "iviling. Curt Haij"
            },
            {
                "name": "Reijmyre Glasbruk AB.",
                "location": "Rejmyra",
                "business": "Glasbruk vid Rejmyra lÖstergötl. l.). Tillverkar hushållsglas, tekn. glas, apoteksglas och prydnadsglas.",
                "contact": {
                    "telegraph": "Reijmyreglas, Norrköping",
                    "phone": [
                        "Rejmyra 12 o. 36"
                    ],
                    "postgiro": "131888"
                },
                "financials": {
                    "capital": "60,000 kr",
                    "employees": {
                        "industriarb": 80
                    },
                    "annual_turnover": "500,000 kr",
                    "annual_production_value": "500,000 kr"
                },
                "foundation_year": 1937,
                "board": [
                    {
                        "name": "prof. Rolf Sievert",
                        "role": "ordförande"
                    },
                    {
                        "name": "fru II. Almqvist",
                        "role": "Styrelse"
                    },
                    {
                        "name": "kapten R. G:son Sjöberg",
                        "role": "Styrelse"
                    }
                ],
                "manager": "Einar Rosengren"
            },
            {
                "name": "AB. Reijmyre Lädervarufabrik",
                "location": "Norrköping",
                "business": "Tillverkar ryggsäckar, remmar, väskor, packfickor m. m. samt plånböcker och portmonnäer.",
                "contact": {
                    "telegraph": "Rejsport, Norrköping",
                    "phone": [
                        "23141"
                    ],
                    "postgiro": "26232"
                },
                "financials": {
                    "capital": "43,000 kr",
                    "employees": {
                        "industriarb": 20
                    },
                    "annual_turnover": "200,000 kr",
                    "annual_production_value": "200,000 kr"
                },
                "foundation_year": 1933,
                "current_name_year": 1938,
                "manager": "fabr. Nils Ringdahl"
            }
        ]
    }
}