{
    "original": "Skånska\n\nSkånska Bomullskrutfabriks AB.,\n\nLandskrona.\n\nKrutbruk, färg- och fernissfabrik samt\nkemisk-teknisk fabrik vid Dösjöbro\n(Malmöh. l.).\n\nTillverkar pressad trinitrotoluol och\nhexanitrodifenylamin (»Novit»),\nnitro-cellulosakrut för jaktgevär i blad- och\nkornform, knallsignaler för\nsignalstationer, kollodiumlösningar för tekn.\nändamål, etyleter (specialitet: pro narcosi),\nkopal- och oljefernissor, sprit- och\nzapon-lacker (»A. V. S.-lack»), emalj- och\nrostskyddsfärger, celluloidlack (»Normack»)\nför automobiler.\n\nTelegr.-adr.: Normal, Landskrona.\nTelefon: 19 o. 91. Postgiro: 82330. —\nAkt.-kap.: 500,000 kr. Tillv.-värde pr år:\n1,000,000 kr.\n\nBolaget, som grundades 1893, arbetar\nunder gemensam förvaltning med AB.\nSvenska Krutfaktorierna, Landskrona.\n\nStyrelse: dir. C. F. Tranchell (ordf.),\ndir. Harry Tranchell (v. ordf.), fil. dr\nA. Matteoschat, major B. Wessel, disp.\nG. A. Widström.\n\nVerkst. dir.: Harry Tranchell.\n\nDisp.: A. Matteoschat.\n\n*Skånska Cement AB-, Malmö.\n\nOementfabrik, kalkbrott och kalkbruk\ni Limhamn, tegelbruk i Lomma (båda i\nMalmöh. l.), cementfabrik, kalkstensbrott\noch stenhuggeri i Hellekis (Skarab. l.),\ncementfabrik i Köping.\n\nTillverkar cement, tegel, bränd kalk,\njordbrukskalk och kalksten; utför\ninrednings- och fasadarbeten i kalksten.\n\nHuvudkontor: Malmö. Telegr.-adr. o.\ntelefon: Cementbolaget, Malmö. Postgiro:\n24570. Tekniska Avdelningen: Stockholm,\nLövholmsbrinken 2; postadr.: Stockholm\n9, telefon: 452815.\n\nEnsamförsälj. för cement: Cementa,\nSvenska Cementförsäljnings AB., Malmö\n(se detta bolag); för kalk: Calcium,\nSvenska Kalkförsäljnings AB., Malmö, och\nMellersta Sveriges Kalkbruks Oentralför*\nening m. b. p. a., Falköping; för tegel:\nSkånska Tegelförsäljnings AB., Malmö:\nför kalksten: A/S Faellesagenturet for\nFaxe-Limhamn Kalkbrud, Köpenhamn.\n\nAkt.-kap.: 28,000,000 kr. Antal\nindustriarb.: 1,700. Tillv.-värde pr år:\n39,000,000 kr.\n\nBolaget grundat 1871.\n\nStyrelse: majoren greve W. A. H.\nHa-milton (ordf.), dir. Carl Joh. Malmros (v.\nordf.), disp. Nils Danielsen,\ngeneralkonsul G. M. I. Fagraeus, hovjägmäst. frih.\nWilh. Klingspor, generallöjtn. Bengt\n\nNordenskiöld, överstelöjtn. Carl O. A.\nNyström, dir. Ernst Wehtje.\nVerkst. dir.: Ernst Wehtje.\nVice verkst. dir.: Malte Ström.\növering.: Donovan Werner.\nChef kamrer: Einar Mellberg.\nKontorschef: kamrer Nils Lindh.\nOmbudsman: Sten Sandell.\nInköpschef: kamrer Harald Wijk.\nAvd.-chefer: vid Limhamn: disp.\nGunnar Laurell; vid Hellekis: disp. H.\nSebastian Tham; vid Köping: disp. O.\nRustan; vid Lomma: dir. Bertil\nKyl-berg.\n\n*AB. Skånska Gementgjuteriet,\n\nStockholm.\n\nEntreprenadfirma för hus- och\nfabriksbyggnader, för väg- och\nvattenbyggnadsarbeten samt för asfalt- och\nmarmorarbeten. Betongvarufabriker ^ Stockholm,\nMalmö, Norrköping, Jönköping,\nLinköping, Ettebro (Blekinge l.), Vassmolösa\n(Kalmar l.) och Sveden pr Gävle samt\nmarmorstenhuggerier i Stockholm och\nMalmö.\n\nTillverkar trappsteg, golv- och\nväggplattor av betong och mosaik, avloppsrör\noch kulvertar av betong, trappor och\nplattor av marmor och kalksten, fasadputs\n(porfyrit) samt betonghålsten.\n\nHuvudkontor: Stockholm. Postadr.:\nStockholm 7. Telegr.-adr.:\nCementgjute-riet, Stockholm. Telefon: »Skånska\nCe-mentgjuteriet». Postgiro: 128.\nAvd.-kontor: Malmö, Göteborg, Jönköping,\nKalmar, Karlskrona, Karlstad o. Norrköping.\n\nAkt.-kap.: 6,000,000 kr. Prod.-värde pr\når: 85,000,000 kr. — Bolaget grundat\n1887.\n\nStyrelse: f. generaldir. Gösta Malm\n(ordf.), dir. Agne Sandberg, dir. Sven\nSchwartz, dir. Sverre Sohlman, dir. Ernst\nWehtje.\n\nVerkst. dir.: Agne Sandberg.\n\növeringenjör: civiling. Tryggve\nHö-kerberg.\n\nOmbudsman: jur. kand. J.-O.\nBergen-feldt.\n\nDisp. i Malmö: civiling. Nils\nKjellström.\n\nAvd.-chefer: i Göteborg: civiling. L.\nRönnmark; i Jönköping: civiling.\nVilhelm Andrén; i Kalmar: civiling. Arne\nBjörneklint; i Karlskrona: civiling. Arne\nHillborg; i Karlstad: civiling. Thure\nMannerfelt; i Norrköping: civiling. Sven\nEwald.",
    "structured": {
        "firms": [
            {
                "name": "Skånska Bomullskrutfabriks AB",
                "location": "Landskrona",
                "business": "Krutbruk, färg- och fernissfabrik samt kemisk-teknisk fabrik",
                "products": "Tillverkar pressad trinitrotoluol och hexanitrodifenylamin (»Novit»), nitro-cellulosakrut för jaktgevär i blad- och kornform, knallsignaler för signalstationer, kollodiumlösningar för tekn. ändamål, etyleter (specialitet: pro narcosi), kopal- och oljefernissor, sprit- och zapon-lacker (»A. V. S.-lack»), emalj- och rostskyddsfärger, celluloidlack (»Normack») för automobiler",
                "contact": {
                    "office": "Dösjöbro, Malmöh. l.",
                    "phone": [
                        "19",
                        "91"
                    ],
                    "postgiro": "82330",
                    "head_office": "Landskrona",
                    "sales_offices": [],
                    "telegraph": "Normal, Landskrona",
                    "factory_office": "",
                    "factory_phone": ""
                },
                "financials": {
                    "capital": "500,000 kr",
                    "annual_turnover": "1,000,000 kr",
                    "annual_production_value": ""
                },
                "foundation_year": 1893,
                "predecessor": "",
                "corporation_year": 0,
                "board": [
                    {
                        "name": "C. F. Tranchell",
                        "role": "ordf."
                    },
                    {
                        "name": "Harry Tranchell",
                        "role": "v. ordf."
                    },
                    {
                        "name": "A. Matteoschat",
                        "role": ""
                    },
                    {
                        "name": "B. Wessel",
                        "role": "major"
                    },
                    {
                        "name": "G. A. Widström",
                        "role": "disp."
                    }
                ],
                "owners": [],
                "director": "",
                "managing_director": "Harry Tranchell",
                "sales_manager": "",
                "manager": ""
            },
            {
                "name": "Skånska Cement AB",
                "location": "Malmö",
                "business": "Oementfabrik, kalkbrott och kalkbruk",
                "products": "Tillverkar cement, tegel, bränd kalk, jordbrukskalk och kalksten; utför inrednings- och fasadarbeten i kalksten",
                "contact": {
                    "office": "Limhamn",
                    "phone": [],
                    "postgiro": "24570",
                    "head_office": "Malmö",
                    "sales_offices": [
                        {
                            "location": "Stockholm, Lövholmsbrinken 2",
                            "phone": "452815"
                        }
                    ],
                    "telegraph": "",
                    "factory_office": "Hellekis",
                    "factory_phone": ""
                },
                "financials": {
                    "capital": "28,000,000 kr",
                    "annual_turnover": "39,000,000 kr",
                    "annual_production_value": ""
                },
                "foundation_year": 1871,
                "predecessor": "",
                "corporation_year": 0,
                "board": [
                    {
                        "name": "greve W. A. H. Hamilton",
                        "role": "majoren (ordf.)"
                    },
                    {
                        "name": "Carl Joh. Malmros",
                        "role": "dir."
                    },
                    {
                        "name": "Nils Danielsen",
                        "role": "disp."
                    },
                    {
                        "name": "G. M. I. Fagraeus",
                        "role": "generalkonsul"
                    },
                    {
                        "name": "frih. Wilh. Klingspor",
                        "role": "hovjägmäst."
                    }
                ],
                "owners": [],
                "director": "",
                "managing_director": "Ernst Wehtje",
                "sales_manager": "",
                "manager": ""
            },
            {
                "name": "AB. Skånska Gementgjuteriet",
                "location": "Stockholm",
                "business": "Entreprenadfirma för hus- och fabriksbyggnader, för väg- och vattenbyggnadsarbeten samt för asfalt- och marmorarbeten",
                "products": "Tillverkar trappsteg, golv- och väggplattor av betong och mosaik, avloppsrör och kulvertar av betong, trappor och plattor av marmor och kalksten, fasadputs (porfyrit) samt betonghålsten",
                "contact": {
                    "office": "",
                    "phone": [],
                    "postgiro": "128",
                    "head_office": "Stockholm",
                    "sales_offices": [
                        {
                            "location": "Malmö",
                            "phone": ""
                        },
                        {
                            "location": "Göteborg",
                            "phone": ""
                        },
                        {
                            "location": "Jönköping",
                            "phone": ""
                        },
                        {
                            "location": "Kalmar",
                            "phone": ""
                        },
                        {
                            "location": "Karlskrona",
                            "phone": ""
                        },
                        {
                            "location": "Karlstad",
                            "phone": ""
                        },
                        {
                            "location": "Norrköping",
                            "phone": ""
                        }
                    ],
                    "telegraph": "Cementgjuteriet, Stockholm",
                    "factory_office": "",
                    "factory_phone": ""
                },
                "financials": {
                    "capital": "6,000,000 kr",
                    "annual_turnover": "85,000,000 kr",
                    "annual_production_value": ""
                },
                "foundation_year": 1887,
                "predecessor": "",
                "corporation_year": 0,
                "board": [
                    {
                        "name": "Gösta Malm",
                        "role": "f. generaldir. (ordf.)"
                    },
                    {
                        "name": "Agne Sandberg",
                        "role": "dir."
                    },
                    {
                        "name": "Sven Schwartz",
                        "role": "dir."
                    },
                    {
                        "name": "Sverre Sohlman",
                        "role": "dir."
                    }
                ],
                "owners": [],
                "director": "",
                "managing_director": "Agne Sandberg",
                "sales_manager": "",
                "manager": ""
            }
        ]
    }
}