{
    "original": "Håksberg—Häfla\n\n*Håksbergs Nya Cruf AB.,\n\nHåksberg.\n\nBryter och anrikar järnmalm vid\njärnmalmsgruvor och anrikningsverk i\nHåksberg (Kopparb. l.) samt i\nKarlvagns-och EskiIsbacksfälten i Norberg\n(Västmanl. l.).\n\nKontor: Håksberg. Telegr.-adr.:\nHaks-berggruva, Ludvika. Telefon: Ludvika\n818. Postgiro: 146394.\n\nAkt.-kap.: 3.000,000 kr. Antal\nindustriarb.: 200. — Bolaget, grundat 1913, har\növertagit den rörelse, som bedrivits av\nIckorrbottens Grufve AB. i likv. och Gruf\nAB. Stark i likv.\n\nStyrelse: dir. Hermann Hennemann\n(ordf.), disp. John A. Hedlund, adv. Nils\nHögberg.\n\nVerkst. dir.: H. Hennemann.\n\nDisp.: J. A. Hedlund.\n\nGruving.: B. G. Wickbom.\n\nKamrer: P. Henke.\n\nHållstedts AB., Grönskåra.\n\nTillverkar träleksaker och svarvade\nmassartiklar såsom handtag och bobiner\nvid träförädlingsfabrik i Grönskåra\n(Kalmar l.).\n\nTelefon: 23. Postgiro: 76890. —\nAkt.-kap.: 60,000 kr. Tillv.-värde pr år:\n200,000 kr. — Firman grundad 1930.\n\nStyrelse o. verkst. dir.: disp. A.\nHåll-stedt.\n\nHåll torps AB., Vinninga.\n\nTegelbruk, kvarn och stärkelsefabrik i\nHålltorp, Vinninga (Skarab. l.).\nTillverkar mur- och taktegel, dräneringsrör\nsamt potatismjöl. Bolaget driver även\njordbruk.\n\nTelefon: Lidköping 182. Postgiro:\n34612. — Akt.-kap.: 100,000 kr. Antal\nindustriarb. (tegelbruket): 40. Årstillv.:\n2,7 milj. st. tegelvaror. — Bolaget\ngrundat 1909.\n\nVerkst. dir.: godsäg. J. E. Synnergren.\n\n* Hånsfors Bruks AB., Töcksfors.\n\nSågverk med hvvleri och elektr.\nkraftstationer vid Töcksfors samt pappersbruk,\npappersförädlingsfabrik och elektr.\nkraftstation vid Hånsfors (båda i Värml. l.).\n\nTillverkar sågade och hyvlade trävaror,\nomslagspapper och påspapper,\npapperspåsar, pappersmanufaktur m. m. samt\ndistribuerar elektr. energi.\n\nHuvudkontor: Töcksfors. Telefon: 1,\n69 o. 76. Postgiro: 136115. Försäljn. av\npapper o. pappersprodukter: Thorsten\n\nBrunius &amp; Co. AB., Göteborg, V. Hamng.\n2. Telegr.-adr.: Brunius, Göteborg.\nTelefon: 135037 o. 117920. Nederlag för\nträvaror: Årjäng, telefon: 230.\n\nAkt.-kap.: 315,000 kr. Antal\nindustriarb.: 70. Årstillv.: 1,000 stds sågade och\nhyvlade trävaror, 3,000 ton papper och\npappersmanufaktur.\n\nBolaget grundat 1919 under namn\nSannes Söners AB., nuv. namn 1937.\n\nStyrelse: bankdir. Axel ^ Gustafsson\n(ordf.), dir. Gomer Brunius, ing. Sverker\nBrunius, dir. Eric Lindelöf.\n\nVerkst. dir. o. disp.: Sverker Brunius.\n\nKontorschef: Bengt Magnér.\n\n*Håstaholmens Snickerifabrik,\n\nHudiksvall.\n\nSe AB. Iggesunds Bruk, Iggesund.\nHädinge Torfströ AB., Örebro.\n\nTillverkar torvströ, torvmull och\ntorv-fiber från Stora Mosse yid fabrik i\nHädinge (Jönköp. l.).\n\nHuvudkontor: Örebro. Telefon: 21010.\nPostgiro: 99746. Fabrikskontor:\nHädinge. Telefon: Värnamo 16.\n\nAkt.-kap.: 180,000 kr. Antal\nindustriarb.: 60. Årstillv.: 110,000 st. balar\ntorvströ och torvmull. — Bolaget grundat\n1906.\n\nVerkst. dir.: disp. Johan Elion.\n\nFörvalt. i Hädinge: Einar Lindh.\n\n* Häfla Bruks AB., Hävla.\n\nJärnbruk med valsverk, hästskofabriker\nmed hästskobeslagsmédja samt\nsvetsningsverkstad, mek. verkstad och\nsmides-verkstad vid Hävla (Östergötl. l.).\n\nTillverkar värmeledningspannor och\nmed sådana kombinerade\nvarmvattenberedare, valsat hästskojärn och såsom\nspecialitet hästskor. Bolaget idkar jämväl\njordbruk och skogshantering samt\nkvarnrörelse.\n\nTelegr.-adr.: Häfla, Katrineholm.\nTelefon: Häfla 30, 31 o. 37. Postgiro: 93350.\n\nEnsamförsälj.: för hästskor: i\nStockholm: Rundquist &amp; Schultz AB.,\nSlussplan 9, telefon: »Rundquist &amp; Schultz»;\ni Göteborg: Gustaf Fagerberg AB.,\nKronhusg. 16, telefon: 170915; i\nKarlstad: Herman Geijer &amp; Co. AB.,\ntelefon: 15300, för värmepannor: i\nStockholm: Svenska Rörförsäljn. AB.,\nSlussplan 5, telefon: »Svenska\nRörförsäljningen» ; i Göteborg: Levin\nCarlsson, Olofs Wiksg. 1, telefon: 161653; för\nsödra Sverige: Bröderna Edstrand\nAB., Malmö, telefon: »Bröderna\nEd-strand».",
    "structured": {
        "firms": [
            {
                "name": "Håksbergs Nya Cruf AB.",
                "location": "Håksberg",
                "business": "Bryter och anrikar järnmalm",
                "contact": {
                    "office": "Håksberg",
                    "telegraph": "Haks-berggruva, Ludvika",
                    "phone": [
                        "Ludvika 818"
                    ],
                    "postgiro": "146394"
                },
                "financials": {
                    "capital": "3.000.000 kr",
                    "employees": {
                        "industriarb": 200
                    }
                },
                "foundation_year": 1913,
                "board": [
                    {
                        "name": "Hermann Hennemann",
                        "role": "ordf."
                    },
                    {
                        "name": "John A. Hedlund",
                        "role": "disp."
                    },
                    {
                        "name": "Nils Högberg",
                        "role": "adv."
                    }
                ],
                "director": "H. Hennemann",
                "managing_director": "H. Hennemann",
                "sales_manager": "J. A. Hedlund"
            },
            {
                "name": "Hållstedts AB.",
                "location": "Grönskåra",
                "business": "Tillverkar träleksaker och svarvade massartiklar",
                "contact": {
                    "office": "Grönskåra",
                    "phone": [
                        "23"
                    ],
                    "postgiro": "76890"
                },
                "financials": {
                    "capital": "60.000 kr",
                    "annual_production_value": "200.000 kr"
                },
                "foundation_year": 1930,
                "board": [
                    {
                        "name": "A. Håll-stedt",
                        "role": "disp."
                    }
                ]
            },
            {
                "name": "Hålltorps AB.",
                "location": "Vinninga",
                "business": "Tegelbruk, kvarn och stärkelsefabrik",
                "contact": {
                    "office": "Hålltorp, Vinninga",
                    "phone": [
                        "Lidköping 182"
                    ],
                    "postgiro": "34612"
                },
                "financials": {
                    "capital": "100.000 kr"
                },
                "foundation_year": 1909,
                "director": "J. E. Synnergren"
            },
            {
                "name": "Hånsfors Bruks AB.",
                "location": "Töcksfors",
                "business": "Sågverk med hvvleri och elektr. kraftstationer",
                "contact": {
                    "office": "Töcksfors",
                    "phone": [
                        "1",
                        "69",
                        "76"
                    ],
                    "postgiro": "136115"
                },
                "financials": {
                    "capital": "315.000 kr",
                    "employees": {
                        "industriarb": 70
                    },
                    "annual_production_value": "1.000 stds sågade och hyvlade trävaror, 3.000 ton papper och pappersmanufaktur"
                },
                "foundation_year": 1919,
                "current_name_year": 1937,
                "board": [
                    {
                        "name": "Axel ^ Gustafsson",
                        "role": "bankdir."
                    },
                    {
                        "name": "Gomer Brunius",
                        "role": "dir."
                    },
                    {
                        "name": "Sverker Brunius",
                        "role": "ing."
                    },
                    {
                        "name": "Eric Lindelöf",
                        "role": "dir."
                    }
                ],
                "manager": "Sverker Brunius"
            },
            {
                "name": "Hädinge Torfströ AB.",
                "location": "Örebro",
                "business": "Tillverkar torvströ, torvmull och torv-fiber",
                "contact": {
                    "office": "Örebro",
                    "phone": [
                        "21010"
                    ],
                    "postgiro": "99746",
                    "factory_office": "Hädinge",
                    "factory_phone": "Värnamo 16"
                },
                "financials": {
                    "capital": "180.000 kr",
                    "employees": {
                        "industriarb": 60
                    },
                    "annual_production_value": "110.000 st. balar torvströ och torvmull"
                },
                "foundation_year": 1906,
                "director": "disp. Johan Elion"
            },
            {
                "name": "Häfla Bruks AB.",
                "location": "Hävla",
                "business": "Järnbruk med valsverk, hästskofabriker med hästskobeslagsmédja",
                "contact": {
                    "office": "Hävla",
                    "telegraph": "Häfla, Katrineholm",
                    "phone": [
                        "Häfla 30",
                        "Häfla 31",
                        "Häfla 37"
                    ],
                    "postgiro": "93350"
                },
                "financials": {
                    "capital": "Not available"
                }
            }
        ]
    }
}