{
    "original": "E n g ström—Enkö pin g\n\nnings- och operationsbord ävensom\nsnabb-lyftblock.\n\nTelefon: Stockholm 272535. Postgiro:\n57087. — Antal industriarb.: 25.\nTillv.-värde pr år: 325,000 kr. — Firman etabl.\n1924.\n\nÄgare: smidesmäst. Ludvig Engström,\nfabr. Gösta Engström, fabr. Charles\nEngström, fabr. Arne Engström.\n\nR. Engströms Mek. Verkstad,\n\nKatrineholm.\n\nTillverkar automobil- och\nmotordetaljer, bussningar, pressade och svetsade\nplåtkonstruktioner, specialmaskiner och\n-verktyg m. m. samt utför finmekaniska\narbeten.\n\nTelefon: 1413 o. 1414. Postgiro: 72901.\n\n—\tAntal industriarb.: 50. Tillv.-värde pr\når: 600,000 kr. — Firman etabl. 1926 i\nLidköping, överflyttades till Katrineholm\n1939.\n\nÄgare o. chef: ing. Rudolf Engström.\n\nDriftsing.: civiling. Stellan Engström.\n\nEning &amp; Wentzel AB., Mjölby.\n\nKaramell- och kolafabrik. Tillverkar\nkola, dragéer och tabletter. Varumärke:\n»Mejod»-tabletten.\n\nTelefon: 701 o. 722. Postgiro: 134493.\n\nAkt.-kap.: 31,200 kr. Antal\nindustriarb.: 20. Tillv.-värde pr år: 600,000 kr.\n\n—\tFirman etabl. 1937, bolag 1939.\n\nStyrelse o. verTcst. dir.: fabr. Tore H.\n\nWentzel.\n\n^Enköpings Mössfabrik, Enköping.\n\nTillverkar herr-, dam- och barnmössor\nsamt pälsmössor och pälsbaretter.\nVarumärke: »Ena». Firman driver även\nen-grosförsäljning av herrhattar och\npälsskinn.\n\nTelefon: 33. Postgiro: 86450. Repr. i\nStockholm: Hans Kaiser,\nMalmskill-nadsg. 34 A, telefon: 103656. — Antal\nindustriarb.: 40. Tillv.-värde pr år:\n600,000 kr. — Firman grundad 1864.\n\nÄgare o. chef: jur. kand. Olof\nBark-feldt.\n\n*AB. Enköpings Verkstäder,\n\nEnköping.\n\nVerktygsverkstäder med hejarsmedja,\nfläktverkstäder och gjuteri i Enköping\nsamt installationsverkstäder i Stockholm\noch Hälsingborg.\n\nVerktygsverkstäderna tillverka under\nvarumärket »BAHCO»: skift- och skruv-\n\nnycklar, hylsnycklar, skruvmejslar,\nskruv-tvingar, ^ rörtänger, röravskärare,\nbultsaxar, bil- och cykelverktyg,\nträdgårdsverktyg m. m.\n\nTelefon: Enköping 33040. Försäljning\nuteslutande genom moderbolaget AB..\nB. A. Hjorth &amp; Co., Stockholm, Klara\nJST:aKyrkog. 31. Telefon: »Hjorth &amp; Co.».\n\nFläktverkstäderna tillverka under\nvarumärket »BAHCO»: fläktar för alla\nändamål samt aggregat och kompletta\nanläggningar för ventilation,\nluftkonditionering, uppvärmning, torkning,\nbefukt-ning, värmeåtervinning,\nmaterialtransport, luft- och rökgasrening samt\ndamm-avskiljning m. m.; standardapparater r\npropellerfläktar, bastuberedare,\nbyggtor-kar, luftförvärmare, dynamiska filter\nsåsom rökgasfilter och andra filter samt\nspecialaggregat för olika områden inom.\nventilationstekniken, ässjor,\nborrmaskiner, plåtsaxar m. m.\n\nTelefon: Enköping 33200. Försäljning:\nfläktkonstruktionerna offereras och\nsäljas av AB. Enköpings Verkstäder direkt;\nbastuberedare och byggtorkar, ässjor^,\nborrmaskiner och plåtsaxar genom\nmoderbolaget AB. B. A. Hjorth &amp; Co.,\nStockholm.\n\nGjuteriet i Enköping tillverkar\ntack-järnsgjutgods på direkt beställning.\n\nHuvudkontorets postadr.:\nEnköping-Telegr.-adr.: Bahcoverk, Enköping.\nPostgiro: 12757.\n\nAvdelningskontor i Stockholm för\nfläktar och ventilation, Sveavägen 48.\nTelefon: 231950. — Plåt- och\nfläktinstalla-tionsverkstaden å Lilla Essingen.\nPost.-adr.: Primus-området, Stockholm.\nTelefon: 510358 o. 513318.\n\nAvdelningskontor i Hälsingborg ^ för\nfläktar och ventilation med\ninstallations-verkstad: Hamntorget 3. Telefon: 11325.\n\nAkt.-kap.: 2,100,000 kr. Antal\nindustriarb.: 550. Tillv.-värde pr år: 10,000,000*\nkr.\n\nFöretaget, grundat 1886, ombildat till\nnuv. bolag 1914, är dotterbolag till AB.\nB. A. Hjorth «&amp; Co., Stockholm.\n\nStyrelse: generalkonsul Hugo Duhs\n(ordf.), dir. Arnold Hjorth (v. ordf.)„\nciviling. Hannes Brynge, notarie Tore\nDuhs, dir. A. Uggla.\n\nVerkst. dir.: Arnold Hjorth (Sthlm).\n\nV. verkst. dir.: Hugo Duhs (Sthlm).\n\nDir.: H. Brynge (Enköping).\n\nInköpschef: intendent E. Besander\n(Enköping).\n\nVerkstadschef vid\nverktygsverkstäderna: övering. G. Strand.",
    "structured": {
        "1": {
            "name": "R. Engströms Mek. Verkstad",
            "location": "Katrineholm",
            "business": "Tillverkar automobil- och motordetaljer, bussningar, pressade och svetsade plåtkonstruktioner, specialmaskiner och verktyg m. m. samt utför finmekaniska arbeten.",
            "contact": {
                "office": null,
                "phone": [
                    "1413",
                    "1414"
                ],
                "postgiro": "72901"
            },
            "financials": {
                "capital": null,
                "employees": {
                    "industriarb": 50
                },
                "annual_turnover": "600,000 kr",
                "annual_production_value": "600,000 kr"
            },
            "foundation_year": 1926,
            "owners": [
                "ing. Rudolf Engström"
            ]
        },
        "2": {
            "name": "Ening & Wentzel AB.",
            "location": "Mjölby",
            "business": "Karamell- och kolafabrik. Tillverkar kola, dragéer och tabletter. Varumärke: »Mejod»-tabletten.",
            "contact": {
                "office": null,
                "phone": [
                    "701",
                    "722"
                ],
                "postgiro": "134493"
            },
            "financials": {
                "capital": "31,200 kr",
                "employees": {
                    "industriarb": 20
                },
                "annual_turnover": "600,000 kr"
            },
            "foundation_year": 1937,
            "board": [
                {
                    "name": "fabr. Tore H. Wentzel",
                    "role": "Styrelse o. verTcst. dir."
                }
            ]
        },
        "3": {
            "name": "Enköpings Mössfabrik",
            "location": "Enköping",
            "business": "Tillverkar herr-, dam- och barnmössor samt pälsmössor och pälsbaretter. Varumärke: »Ena». Firman driver även en-grosförsäljning av herrhattar och pälsskinn.",
            "contact": {
                "office": null,
                "phone": [
                    "33"
                ],
                "postgiro": "86450",
                "sales_offices": [
                    {
                        "location": "Stockholm",
                        "phone": "103656"
                    }
                ]
            },
            "financials": {
                "capital": null,
                "employees": null,
                "annual_turnover": "600,000 kr"
            },
            "foundation_year": 1864,
            "owners": [
                "jur. kand. Olof Barkfeldt"
            ]
        },
        "4": {
            "name": "AB. Enköpings Verkstäder",
            "location": "Enköping",
            "business": "Verktygsverkstäder med hejarsmedja, fläktverkstäder och gjuteri i Enköping samt installationsverkstäder i Stockholm och Hälsingborg.",
            "products": "Verktygsverkstäderna tillverka under varumärket »BAHCO»: skift- och skruvnycklar, hylsnycklar, skruvmejslar, skruv-tvingar, rörtänger, röravskärare, bultsaxar, bil- och cykelverktyg, trädgårdsverktyg m. m.",
            "contact": {
                "office": null,
                "phone": [
                    "Enköping 33040"
                ]
            },
            "financials": {
                "capital": "2,100,000 kr",
                "employees": {
                    "industriarb": 550
                },
                "annual_turnover": "10,000,000 kr"
            },
            "foundation_year": 1886,
            "board": [
                {
                    "name": "generalkonsul Hugo Duhs",
                    "role": "Styrelse"
                },
                {
                    "name": "dir. Arnold Hjorth",
                    "role": "v. ordf."
                },
                {
                    "name": "civiling. Hannes Brynge",
                    "role": null
                },
                {
                    "name": "notarie Tore Duhs",
                    "role": null
                },
                {
                    "name": "dir. A. Uggla",
                    "role": null
                }
            ],
            "owner": "AB. B. A. Hjorth & Co."
        }
    }
}