{
    "original": "Linoljeslag erierna—Ljuder\n\nStyrelse: adv. Gösta Grönberg (ordf.),\ndir. Jan Kaars-Sypesteyn, disp. Albert\nMattson, dir. Carl Aug. Wicander, dir.\nCarl Gustaf Wicander, bankdir. dr C.\nZoelly.\n\nVerkst. dir.: Ernst Kaars-Sypesteyn.\n\nDisp. i Göteborg: Sven örtegren.\n\nChef för Försäljningscentralen i\nStockholm: dir. Thure Allgén.\n\nLinoljeslageriernas Försäljnings\n\nAB., Göteborg.\n\nBolaget handhar försäljningen inom\nlandet av de svenska linoljeslageriernas\nprodukter av linolja, linkakor, och\nlinkak-mjöl.\n\nHuvudkontor: Mölndal, Gamla Torget;\npostadr.: Göteborg 5. Telegr.-adr.:\nLinoljebolaget, Göteborg. Telefon: 272000.\nPostgiro: 12225. Filialkontor: Stockholm,\nHenriksdal; postadr.: Stockholm 2.\nTelefon: 437070—72. Postgiro: 50460.\n\nAkt.-kap.: 100,000 kr. Omsättn.-värde\når 1945: 22,000,000 kr. — Bolaget\ngrundat 1923.\n\nStyrelse: konsul Oscar Gullander\n(ordf.), konsul Edw. H. Thomée (v.\nordf.), dir. Hjalmar Carlborn, disp. A.\nChristoffersson, dir. H. E. Helmerson,\nadv. Erik Leman, dir. Rudolf Molin, disp.\nDavid Thorburn.\n\nVerkst. dir.: H. E. Helmerson.\n\nKontorschef: Ralph Fischer.\n\nDisp. i Stockholm: Helge Peterson.\n\n*AB. Otto Lion &amp; Co., Nordisk\nIndustri, Hälsingborg.\n\nSidenväveri för tillverkning av\nklänningstyger, foder- och satinvävnader;\nblomsterindustri för tillverkning av\nkrans- och dekorationsband, artificiella\nblommor och dekorationsföremål,\nblomsterkorgar, begravningsartiklar m. m.\n\nTelegr.-adr.: Lionco, Hälsingborg.\nTelefon: 20410. Postgiro: 5423.\n\nAkt.-kap.: 300,300 kr. Antal\nindustriarb.: 200. Tillv.-värde pr år: 4,000,000 kr.\n— Firman etabl. 1898, bolag 1932.\n\nStyrelse: dir. Carl Lööb (ordf.),\ndir.-assist. Lennart Lööb.\n\nVerkst. dir.: Carl Lööb.\n\nLars Lissman, Malungsfors.\n\nSkinnvarufabrik i Malungsfors\n(Kopparb. l.). Tillverkar\nskinnbeklädnadsar-tiklar såsom skinnkläder, pälsar, handskar\noch motormössor. .\n\nTelefon: 12. Postgiro: 13557. — Antal\nindustriarb.: 15. Tillv.-värde pr år:\n250,000 kr. — Firman etabl. 1925.\n\nÄgare o. chef: fabr. Lars Lissman.\n\n\"Lithografiska AB. Norrköping,\n\nNorrköping.\n\nLitografisk anstalt, bok- och\nståltryc-keri. Tillverkar kuvert, påsar,\nkontorsböcker, kartonger, blanketter, spelkort\nm. m.\n\nHuvudkontor: Norrköping.\nTelegr.-adr.: Lithografen, Norrköping. Telefon:\n»Lithografen». Postgiro: 5290.\nAvd.-kon-tor: i Stockholm, Drottningg. 18, telefon:\n230630; i Göteborg, Ingenjörsg. 1 B,\ntelefon: 131106; i Malmö, Mårtensg. 8,\ntelefon: 24831.\n\nBolaget, som grundades 1858, är\nanslutet till AB. Sveriges Litografiska\nTryckerier, Stockholm. (Se detta bolag.)\n\nStyrelse o. disp.: disp. C. O. Meurling.\n\nChefsassist.: civiling. Jarl-Erik\nOhlsson.\n\nFörsäljn.-chef: Karl Ekström.\n\nKontorschef: kamrer Nils O. Karlsson.\n\nOffertavd.: kamrer H. Widén.\n\nTekn. avd.: övering. K. Brunnander.\n\nAvd.-chefer: i Stockholm: kapten Elof\nAhlström; i Göteborg: A. Ringstrand; i\nMalmö: Thorsten Wahlberg.\n\n(Jfr annons nr 80.)\n\n\"Litografiska Tryckerier, AB.\nSveriges, Stockholm.\n\n^ Se AB. Sveriges Litografiska\nTryckerier, Stockholm.\n\nLitotryck, E. Sääw, Linköping.\n\nTillverkar etiketter, omslag, tårtpapper\nsamt affärstryck.\n\nTelefon: 22966. Postgiro: 82520. —\nAntal industriarb.: 10. Tillv.-värde pr\når: 140,000 kr. — Firman etabl. 1932.\n\nÄgare o. chef: fabr. Ejnar Sääw.\n\nAB. Livbåtsvarvet, Göteborg.\n\nB åt varv i Varberg och i Allmag,\nStill-ingsön (Göteb. o. Bohus l.). Tillverkar\nlivbåtar, motor- och segelbåtar.\nVarumärke: »Allmagsnipan».\n\nKontor: Göteborg, Kyrkog. 4. Telefon:\n118365. Postgiro: 42611. — Akt.-kap.:\n26,000 kr. Antal industriarb.: 26.\nTillv.-värde pr år: 140,000 kr. — Bolaget\ngrundat 1917.\n\nVerkst. dir.: John R. Wennerholm.\n\nLjuders Nickelsilverfabrik AB.,\n\nHovmantorp.\n\nLås- och metallvarufabrik samt\nmetallgjuteri i Hovmantorp (Kronob. l.).\nTillverkar lås, metallbeslag, gångjärn,\nuppstigningshandtag och näthyllor för\njärnvägsvagnar, för elektr. lokomotiv, för\n\n-K-",
    "structured": {
        "1": {
            "name": "Linoljeslageriernas Försäljnings AB.",
            "location": "Göteborg",
            "business": "Bolaget handhar försäljningen inom landet av de svenska linoljeslageriernas produkter av linolja, linkakor, och linkak-mjöl.",
            "contact": {
                "office": "Mölndal, Gamla Torget, Göteborg 5",
                "phone": [
                    "272000"
                ],
                "postgiro": "12225",
                "head_office": "Mölndal, Gamla Torget, Göteborg 5",
                "sales_offices": [
                    {
                        "location": "Stockholm, Henriksdal",
                        "phone": "437070–72",
                        "postgiro": "50460"
                    }
                ],
                "telegraph": "Linoljebolaget, Göteborg",
                "factory_office": "",
                "factory_phone": ""
            },
            "financials": {
                "capital": "100,000 kr",
                "annual_turnover": "22,000,000 kr",
                "annual_production_value": ""
            },
            "foundation_year": 1923,
            "board": [
                {
                    "name": "Oscar Gullander",
                    "role": "ordf."
                },
                {
                    "name": "Edw. H. Thomée",
                    "role": "v. ordf."
                }
            ]
        },
        "2": {
            "name": "AB. Otto Lion & Co.",
            "location": "Hälsingborg",
            "business": "Sidenväveri för tillverkning av klänningstyger, foder- och satinvävnader; blomsterindustri för tillverkning av krans- och dekorationsband, artificiella blommor och dekorationsföremål, blomsterkorgar, begravningsartiklar m. m.",
            "contact": {
                "office": "",
                "phone": [
                    "20410"
                ],
                "postgiro": "5423",
                "head_office": "",
                "sales_offices": [],
                "telegraph": "Lionco, Hälsingborg",
                "factory_office": "",
                "factory_phone": ""
            },
            "financials": {
                "capital": "300,300 kr",
                "annual_turnover": "4,000,000 kr",
                "annual_production_value": ""
            },
            "foundation_year": 1932,
            "board": [
                {
                    "name": "Carl Lööb",
                    "role": "ordf."
                },
                {
                    "name": "Lennart Lööb",
                    "role": "dir.-assist."
                }
            ]
        },
        "3": {
            "name": "Lars Lissman",
            "location": "Malungsfors",
            "business": "Skinnvarufabrik i Malungsfors (Kopparb. l.). Tillverkar skinnbeklädnadsar-tiklar såsom skinnkläder, pälsar, handskar och motormössor.",
            "contact": {
                "office": "",
                "phone": [
                    "12"
                ],
                "postgiro": "13557",
                "head_office": "",
                "sales_offices": [],
                "telegraph": "",
                "factory_office": "",
                "factory_phone": ""
            },
            "financials": {
                "capital": "",
                "annual_turnover": "250,000 kr",
                "annual_production_value": ""
            },
            "foundation_year": 1925,
            "board": []
        },
        "4": {
            "name": "AB. Lithografiska AB. Norrköping",
            "location": "Norrköping",
            "business": "Litografisk anstalt, bok- och ståltryc-keri. Tillverkar kuvert, påsar, kontorsböcker, kartonger, blanketter, spelkort m. m.",
            "contact": {
                "office": "Norrköping",
                "phone": [],
                "postgiro": "5290",
                "head_office": "Norrköping",
                "sales_offices": [
                    {
                        "location": "Stockholm, Drottningg. 18",
                        "phone": "230630"
                    },
                    {
                        "location": "Göteborg, Ingenjörsg. 1 B",
                        "phone": "131106"
                    },
                    {
                        "location": "Malmö, Mårtensg. 8",
                        "phone": "24831"
                    }
                ],
                "telegraph": "Lithografen, Norrköping",
                "factory_office": "",
                "factory_phone": ""
            },
            "financials": {
                "capital": "",
                "annual_turnover": "",
                "annual_production_value": ""
            },
            "foundation_year": 1858,
            "board": []
        },
        "5": {
            "name": "Litotryck, E. Sääw",
            "location": "Linköping",
            "business": "Tillverkar etiketter, omslag, tårtpapper samt affärstryck.",
            "contact": {
                "office": "",
                "phone": [
                    "22966"
                ],
                "postgiro": "82520",
                "head_office": "",
                "sales_offices": [],
                "telegraph": "",
                "factory_office": "",
                "factory_phone": ""
            },
            "financials": {
                "capital": "",
                "annual_turnover": "140,000 kr",
                "annual_production_value": ""
            },
            "foundation_year": 1932,
            "board": []
        },
        "6": {
            "name": "AB. Livbåtsvarvet",
            "location": "Göteborg",
            "business": "B åt varv i Varberg och i Allmag, Still-ingsön (Göteb. o. Bohus l.). Tillverkar livbåtar, motor- och segelbåtar.",
            "contact": {
                "office": "Göteborg, Kyrkog. 4",
                "phone": [
                    "118365"
                ],
                "postgiro": "42611",
                "head_office": "Göteborg, Kyrkog. 4",
                "sales_offices": [],
                "telegraph": "",
                "factory_office": "",
                "factory_phone": ""
            },
            "financials": {
                "capital": "26,000 kr",
                "annual_turnover": "140,000 kr",
                "annual_production_value": ""
            },
            "foundation_year": 1917,
            "board": []
        },
        "7": {
            "name": "Ljuders Nickelsilverfabrik AB.",
            "location": "Hovmantorp",
            "business": "Lås- och metallvarufabrik samt metallgjuteri i Hovmantorp (Kronob. l.). Tillverkar lås, metallbeslag, gångjärn, uppstigningshandtag och näthyllor för järnvägsvagnar, för elektr. lokomotiv, för",
            "contact": {
                "office": "",
                "phone": [],
                "postgiro": "",
                "head_office": "",
                "sales_offices": [],
                "telegraph": "",
                "factory_office": "",
                "factory_phone": ""
            },
            "financials": {
                "capital": "",
                "annual_turnover": "",
                "annual_production_value": ""
            },
            "foundation_year": "",
            "board": []
        }
    }
}