{
    "original": "C hristemson—C lase\n\nKontor: Kungsbroplan 1. Telegr.-adr.:\nAmanda, Stockholm. Telefon: 520135.\nPostgiro: 2780.\n\nAkt.-kap.: 600,000 kr. Antal\nindustriarb.: 200. Tillv.-värde pr år: 2,000,000 kr.\n— Firman etabl. 1885, bolagsform 1918.\n\nStyrelse: dir. Rudolf Christensen, herr\nVidar Christensen.\n\nVerkst. dir.: Rudolf Christensen.\n\nAB. Alfr. Christensson &amp; Co.,\n\nTorup.\n\nSågverk i Torup (Hallands l.).\nTillverkar sågade och hyvlade trävaror, spec.\nsparrar och bjälkar.\n\nTelegr.-adr.: Christenssons, Torup.\nTelefon: 11 o. 22. Postgiro: 37500. —\nAkt.-kap.: 180,000 kr. Antal industriarb.: 10.\nÅrstillv.: 2,000 stds trävaror. — Bolaget\ngrundat 1903.\n\nVerkst. dir.: Alfr. Christensson.\n\nDisp.: Erik Christner.\n\n*AB. Axel Christiernsson, Stockholm.\n\nOljekokeri, konsistensfettfabrik och\nke-misk-teknisk fabrik. Tillverkar\nkon-sistensfett, kullagerfett, smörjoljor för\nverkstadsindustri och motortrafik,\nmarinoljor samt rostskyddsmedel. Bolaget\ndriver jämväl engroshandel med\nsmörjoljor och maskinförnödenheter.\nVarumärken: »Frigus», »Alexol», »Acrisil»,\n»Cyklop», »Best Ox» o. »Panter».\n\nHuvudkontor: Stockholm, Vasag. 14.\nTelegr.-adr.: Christian, Stockholm.\nTelefon: »Christiernssons». Postgiro: 748.\nFilialkontor: Norrköping, Västra Nyg. 8.\n\nAkt.-kap.: 360,000 kr. Antal\nindustriarb.: 18. Tillv.-värde pr år: 1,500,000 kr.\n\nStyrelse: rådman Carl Gustav Nanne\n(ordf.), dir. Jean W. Fryckstedt, dir.\nAnders Nanne.\n\nVerkst. dir.: Anders Nanne.\n\nV. verkst. dir.: Jean W. Fryckstedt.\n\nChristoffercon, Bröderna, Vingåker.\n\nSe Bröderna Christofferson, Vingåker.\n\n*Chromgarverlet Klippan AB.,\n\nKlippan.\n\nSe AB. Klippans Läderfabrik,\nKlippan.\n\n*AB. Chromläderfabriken Elmo-Calf,\n\nSverdjunga.\n\nGarveri i Svenljunga (Älvsb. l.).\nTillverkar svart och kulört boxkalv samt\nsportläder. Varumärken: »Elmo-Calf» o.\n»Ätrakid».\n\nTelegr.-adr.: Elmocalf, Svenljunga.\nTelefon: 1132. — Akt.-kap.: 150,000 kr.\nAntal industriarb.: 45. Tillv.-värde pr år:\n1,300,000 kr. — Bolaget, grundat 1931,\näges av Kooperativa Förbundet.\n\nStyrelse: dir. Albin Johansson (ordf.)y\nfil. lic. Mauritz Bonow, dir. Hj.\nDeger-stedt, dir. Hugo Edstam, dir. G. Osvaldr\ndir. Ernst Persson.\n\nDisp.: V. Theander.\n\n*Cimbria, AB. Randfabriken,\n\nSimrishamn.\n\nSe AB. Randfabriken Cimbria,\nSimrishamn.\n\n*Cimbrishamns Tegelbruks AB.f\n\nSimrishamn.\n\nTillverkar mur-, fasad-, flam- och\ntaktegel, porös tegel jämte gul fasadtegel\nsamt dräneringsrör.\n\nTelegr.-adr.: Tegelbruket, Simrishamn.\nTelefon: 20. — Akt.-kap.: 100,000 kr.\nAntal industriarb.: 35. Årstillv.: 4 milj.\nst. tegelvaror. — Bolaget grundat 1899.\n\nStyrelse: dir. Gösta Ehrnberg (ordf.),\nlandsfiskal A. Ismark (v. ordf.), dir.\nAlex. Larsson, lantbr. M. Månsson, dir.\nN. Gottfrid Olson.\n\nVerkst. dir. o. disp.: Alex. Larsson.\n\nClaesson, AB. Bröderna, Kungälv.\n\nSe AB. Bröderna Claesson, Kungälv.\n\nAB. Claesons Hatt- &amp; Mössfabrik,\n\nGöteborg.\n\nTillverkar barn- och damhattar,\nsportmössor, skolmössor och uniformsmössor.\n\nKontor: N. Larmg. 5. Telegr.-adr.:\nMössclaeson, Göteborg. Telefon: 130100\no. 131690. Postgiro: 25462.\n\nAkt.-kap.: 5,000 kr. Antal industriarb.:\n30. Tillv.-värde pr år (egen tillverkning):\n400,000 kr. — Firman etabl. 1924, bolag\n1944.\n\nStyrelse: dir. Sven Carlson.\n\nVerkst. dir.: N. H. Boren.\n\n*C. A. Clase AB., Göteborg.\n\nTillverkar isoleringsmateriel samt\nutför isoleringsarbeten för ljud,^ värme och\nkyla. Varumärken: »Bitumastic»,\n»Paxti-le» o. »Perfocel»:\n\nKontor: Lilla torget 1. Telegr.-adr.:\nAlbion, Göteborg. Telefon: 139796.\nPostgiro: 40002.\n*",
    "structured": {
        "firms": [
            {
                "name": "C hristemson—C lase",
                "location": "Kungsbroplan 1, Amanda, Stockholm",
                "contact": {
                    "telegraph": "Amanda, Stockholm",
                    "phone": [
                        "520135"
                    ],
                    "postgiro": "2780"
                },
                "financials": {
                    "capital": "600,000 kr",
                    "employees": {
                        "industriarb": 200
                    },
                    "annual_turnover": "2,000,000 kr",
                    "annual_production_value": "2,000,000 kr"
                },
                "foundation_year": 1885,
                "corporation_year": 1918,
                "board": [
                    {
                        "name": "Rudolf Christensen",
                        "role": "dir."
                    },
                    {
                        "name": "Vidar Christensen",
                        "role": "herr"
                    }
                ],
                "director": "Rudolf Christensen"
            },
            {
                "name": "AB. Alfr. Christensson & Co.",
                "location": "Torup",
                "products": "Tillverkar sågade och hyvlade trävaror, spec. sparrar och bjälkar.",
                "contact": {
                    "telegraph": "Christenssons, Torup",
                    "phone": [
                        "11",
                        "22"
                    ],
                    "postgiro": "37500"
                },
                "financials": {
                    "capital": "180,000 kr",
                    "employees": {
                        "industriarb": 10
                    },
                    "annual_production_value": "2,000 stds trävaror"
                },
                "foundation_year": 1903,
                "board": [
                    {
                        "name": "Alfr. Christensson",
                        "role": "Verkst. dir."
                    }
                ],
                "director": "Alfr. Christensson"
            },
            {
                "name": "AB. Axel Christiernsson",
                "location": "Stockholm, Vasag. 14",
                "products": "Tillverkar konsistensfett, kullagerfett, smörjoljor för verkstadsindustri och motortrafik, marinoljor samt rostskyddsmedel.",
                "contact": {
                    "telegraph": "Christian, Stockholm",
                    "phone": [
                        "»Christiernssons»"
                    ],
                    "postgiro": "748"
                },
                "financials": {
                    "capital": "360,000 kr",
                    "employees": {
                        "industriarb": 18
                    },
                    "annual_turnover": "1,500,000 kr"
                },
                "board": [
                    {
                        "name": "Carl Gustav Nanne",
                        "role": "rådman"
                    },
                    {
                        "name": "Jean W. Fryckstedt",
                        "role": "dir."
                    },
                    {
                        "name": "Anders Nanne",
                        "role": "dir."
                    }
                ],
                "director": "Anders Nanne",
                "managing_director": "Jean W. Fryckstedt"
            }
        ]
    }
}