{
    "original": "Lindström—Linghed\n\nAkt.-kap.: 70,000 kr. Antal\nindustriarb.: 35. Tillv.-värde pr år: 450,000 kr.\n— Bolaget grundat 1893.\n\nStyrelse o. verkst. dir.: fru Sonja\nWallin.\n\nJohn Lindström9 Skruvfabrik,\n\nSträngnäs.\n\nPrecisionstillverkning av skruvar och\nmuttrar, koniska pinnar, facondelar av\nalla slag samt detaljer för radio- och\nelektr. industri.\n\nTelegr.-adr.: Skruvfabriken,\nSträngnäs. Telefon: 87 o. 187. Postgiro: 10115.\n— Arb.-antal: 10. Tillv.-värde pr år:\n200,000 kr. — Firman etabl. 1908.\n\nÄgare o. chef: ing. John Lindström.\n\n\"Waldemar Lindström AB.,\n\nStockholm.\n\nPälsberederi och färgeri i Gröndal,\nStockholm. Bereder och färgar pälsskinn.\n\nKontor: Sannadalsvägen 7—9, Gröndal.\nTelegr.-adr.: Beredfaerg, Stockholm.\nTelefon: 452595. Postgiro: 190171.\n\nAkt.-kap.: 150,000 kr. Antal\nindustriarb.: 62. — Bolaget grundat 1941 under\nnamn Lindström &amp; Lundberg AB., nuv.\nnamn 1946.\n\nStyrelse: konsul Gustav Algård (ordf.),\nherr Gösta Algård, dir. Wald. Lindström.\n\nVerkst. dir.: Wald. Lindström.\n\n\"AB. Emil Lindvall, Nybro.\n\nSvarveri och möbelfabrik. Tillverkar\nkompletteringsmöbler, svarvade\nmassartiklar av trä, gardinstänger och -ringar\nsamt rullgardiner.\n\nTelegr.-adr.: Bobiner, Nybro. Telefon:\n31 o. 313. Postgiro: 20544. — Akt.-kap.:\n60,000 kr. Arb.-antal: 60. — Bolaget\ngrundat 1920.\n\nStyrelse: fru Vivi Fylke, disp. G.\nGöransson, fabr. Arthur Thor.\n\nDisp.: G. Göransson.\n\n0. A. Lindvalls Repslagen,\n\nJättendal.\n\nTillverkar handspunnet tågvirke samt\nlinpackningar vid repslageri i Jättendal\n(Gävleb. l.).\n\nTelegr.-adr.: Linpackning, Jättendal.\nTelefon: 14. Postgiro: 84550. —\nTillv.-värde pr år: 100,000 kr. — Firman etabl.\n1894. -\n\nÄgare o. chef: fabr. O. A. Lindvall.\n\n\"Lindås Cjuteri &amp; Formfabriks AB.,\n\nLindas.\n\nMek. verkstad och gjuteri vid Lindås\n(Kalmar l.). Tillverkar bensin-,\nfotogen-och dieselmotorer för båtar och stationär\ndrift, värmeledningspumpar,\ncentrifugal-pumpar, formar och maskiner för\nsten-och glasindustrien. Specialiteter; motorer\noch centrifugalpumpar. Varumärken:\n»Karl-Erik» o. »Herkules».\n\nTelegr.-adr.: Stenbergs, Lindås.\nTelefon: Emmaboda 5 o. 51. Postgiro: 22494.\nRepresentanter i Stockholm: för motorer:\nAB. Lindåsdiesel, Drottningg. 80, telefon:\n100396; för pumpar: AB. Flygts Pumpar,\nKungsg. 38, telefon: 111540.\n\nAkt.-kap.: 160,000 kr. Antal\nindustriarb.: 85. Tillv.-värde pr år: 2,000,000 kr.\n— Bolaget grundat 1912.\n\nStyrelse: disp. Tage Stenberg (ordf.),\ning. Agne Stenberg, ing. Erik Stenberg.\n\nDisp.: Tage Stenberg.\n\nVerk stadsingenjör er: Agne Stenberg o.\nErik Stenberg.\n\n(Jfr annons nr 84.)\n\n\"AB. Lingbo Verkstäder, Lingbo.\n\nMek. verkstad och gjuteri i Lingbo\n(Gävleb. l.). Tillverkar maskiner för\nsågverk och cellulosaindustrien, grövre\nplåtslageriarbeten, järnkonstruktionerj\ntransportapparater, transportörkedjor,\nrundmaskiner, kuggväxlar, lager och\nlagerbockar, remskivor m. m. samt gjut gods\ni upp till 10,000 kg. styckevikt.\n\nTelefon: 4. Postgiro: 34055. —\nAkt.-kap.: 48,600 kr. Antal industriarb.: 30.\nTillv.-värde pr år: 550,000 kr.\n\nFirman etabl. 1909, bolag 1922 under\nnamn AB. Segerbloms Mek. Verkstad,\nombildat 1929.\n\nStyrelse: fabr. P. J. Wikholm (ordf.),\ning. Karl Andersson, bokhandl. J. E.\nBergman, verkm. Bertil Källberg, kamrer\nTh. Rosenius.\n\nVerkst. dir.: Karl Andersson.\n\n(Jfr annons nr 42.)\n\nLingheds Sågverks AB Linghed.\n\nSågverk, hyvleri, trähus- ocli\nsnickerifabrik i Linghed (Kopparb. l.).,\nTillverkar sågade och hyvlade trävaror,\nmonte-ringsfärdiga trähus samt\nbyggnadssnickerier. Varumärke: »Dala-hus». Bolaget\ndistribuerar även elkraft från egen\nkraftstation.\n\nTelefon: 18. Postgiro; 10407. Repr. i\nStockholm: Bröderna Nordqvist, Katarina\nBang. 20, telefon: 442201. — Akt.-kap.:\n19,500 kr. Antal industriarb.: 70. Tillv.-",
    "structured": {
        "1": {
            "name": "Lindström—Linghed",
            "location": "Linghed (Kopparb. l.)",
            "foundation_year": 1893,
            "financials": {
                "capital": "70,000 kr",
                "employees": {
                    "industriarb": 35
                },
                "annual_turnover": "450,000 kr"
            },
            "contact": {
                "telegraph": "Skruvfabriken, Strängnäs",
                "phone": [
                    "87",
                    "187"
                ],
                "postgiro": "10115"
            },
            "board": [
                {
                    "name": "fru Sonja Wallin",
                    "role": "Styrelse o. verkst. dir."
                }
            ],
            "description": "Precisionstillverkning av skruvar och muttrar, koniska pinnar, facondelar av alla slag samt detaljer för radio- och elektr. industri."
        },
        "2": {
            "name": "John Lindström Skruvfabrik",
            "location": "Strängnäs",
            "foundation_year": 1908,
            "financials": {
                "capital": "Information not available",
                "employees": {
                    "Arb.-antal": 10
                },
                "annual_turnover": "200,000 kr"
            },
            "contact": {
                "telegraph": "Skruvfabriken, Strängnäs",
                "phone": [
                    "87",
                    "187"
                ],
                "postgiro": "10115"
            },
            "owner": "ing. John Lindström",
            "description": "Precisionstillverkning av skruvar och muttrar, koniska pinnar, facondelar av alla slag samt detaljer för radio- och elektr. industri."
        },
        "3": {
            "name": "Waldemar Lindström AB.",
            "location": "Stockholm",
            "foundation_year": 1941,
            "current_name_year": 1946,
            "financials": {
                "capital": "150,000 kr",
                "employees": {
                    "industriarb": 62
                }
            },
            "contact": {
                "office": "Sannadalsvägen 7—9, Gröndal, Stockholm",
                "telegraph": "Beredfaerg, Stockholm",
                "phone": "452595",
                "postgiro": "190171"
            },
            "board": [
                {
                    "name": "konsul Gustav Algård",
                    "role": "ordf."
                },
                {
                    "name": "herr Gösta Algård",
                    "role": "Styrelse"
                },
                {
                    "name": "dir. Wald. Lindström",
                    "role": "Styrelse"
                }
            ],
            "description": "Pälsberederi och färgeri i Gröndal, Stockholm. Bereder och färgar pälsskinn."
        },
        "4": {
            "name": "AB. Emil Lindvall",
            "location": "Nybro",
            "foundation_year": 1920,
            "financials": {
                "capital": "60,000 kr",
                "employees": {
                    "Arb.-antal": 60
                }
            },
            "contact": {
                "office": "Information not available",
                "telegraph": "Bobiner, Nybro",
                "phone": [
                    "31",
                    "313"
                ],
                "postgiro": "20544"
            },
            "board": [
                {
                    "name": "fru Vivi Fylke",
                    "role": "Styrelse"
                },
                {
                    "name": "disp. G. Göransson",
                    "role": "Styrelse"
                },
                {
                    "name": "fabr. Arthur Thor",
                    "role": "Styrelse"
                }
            ],
            "owner": "ing. John Lindström",
            "description": "Svarveri och möbelfabrik. Tillverkar kompletteringsmöbler, svarvade massartiklar av trä, gardinstänger och -ringar samt rullgardiner."
        },
        "5": {
            "name": "O. A. Lindvalls Repslagen",
            "location": "Jättendal (Gävleb. l.)",
            "foundation_year": 1894,
            "financials": {
                "capital": "Information not available",
                "employees": {
                    "Arb.-antal": "Information not available"
                }
            },
            "contact": {
                "telegraph": "Linpackning, Jättendal",
                "phone": "14",
                "postgiro": "84550"
            },
            "owner": "fabr. O. A. Lindvall",
            "description": "Tillverkar handspunnet tågvirke samt linpackningar vid repslageri i Jättendal (Gävleb. l.)"
        },
        "6": {
            "name": "Lindås Gjuteri & Formfabriks AB.",
            "location": "Lindas (Kalmar l.)",
            "foundation_year": "Information not available",
            "financials": {
                "capital": "160,000 kr",
                "employees": {
                    "industriarb": 85
                },
                "annual_turnover": "2,000,000 kr"
            },
            "contact": {
                "telegraph": "Stenbergs, Lindås",
                "phone": [
                    "Emmaboda 5",
                    "51"
                ],
                "postgiro": "22494"
            },
            "board": [
                {
                    "name": "disp. Tage Stenberg",
                    "role": "ordf."
                },
                {
                    "name": "ing. Agne Stenberg",
                    "role": "Styrelse"
                },
                {
                    "name": "ing. Erik Stenberg",
                    "role": "Styrelse"
                }
            ],
            "description": "Mek. verkstad och gjuteri vid Lindås (Kalmar l.). Tillverkar bensin-, fotogen-och dieselmotorer för båtar och stationär drift, värmeledningspumpar, centrifugal-pumpar, formar och maskiner för sten-och glasindustrien."
        },
        "7": {
            "name": "AB. Lingbo Verkstäder",
            "location": "Lingbo (Gävleb. l.)",
            "foundation_year": "Information not available",
            "financials": {
                "capital": "48,600 kr",
                "employees": {
                    "industriarb": 30
                },
                "annual_turnover": "550,000 kr"
            },
            "contact": {
                "phone": "4",
                "postgiro": "34055"
            },
            "board": [
                {
                    "name": "fabr. P. J. Wikholm",
                    "role": "ordf."
                },
                {
                    "name": "ing. Karl Andersson",
                    "role": "Styrelse"
                },
                {
                    "name": "bokhandl. J. E. Bergman",
                    "role": "Styrelse"
                },
                {
                    "name": "verkm. Bertil Källberg",
                    "role": "Styrelse"
                },
                {
                    "name": "kamrer Th. Rosenius",
                    "role": "Styrelse"
                }
            ],
            "description": "Mek. verkstad och gjuteri i Lingbo (Gävleb. l.). Tillverkar maskiner för sågverk och cellulosaindustrien, grövre plåtslageriarbeten, järnkonstruktioner, transportapparater, transportörkedjor, rundmaskiner, kuggväxlar, lager och lagerbockar, remskivor m. m. samt gjutgods i upp till 10,000 kg. styckevikt."
        },
        "8": {
            "name": "Lingheds Sågverks AB",
            "location": "Linghed (Kopparb. l.)",
            "foundation_year": "Information not available",
            "financials": {
                "capital": "19,500 kr",
                "employees": {
                    "industriarb": 70
                }
            },
            "contact": {
                "phone": "18",
                "postgiro": "10407"
            },
            "description": "Sågverk, hyvleri, trähus- ocli snickerifabrik i Linghed (Kopparb. l.). Tillverkar sågade och hyvlade trävaror, monte-ringsfärdiga trähus samt byggnadssnickerier."
        }
    }
}