{
    "original": "Lindelöf—Lindgren\n\nAkt.-kap.: 450,000 kr. Antal\nindustriarb.: 175. — Fabriken anlagd 1877, bolag\n1902.\n\nStyrelse: herr Bengt Björk, ing.\nDavid Lindeli, herr Olof Lindell, civiling.\nRob. Lindell, bankdir. Sven Lindell.\n\nVerkst. dir.: Rob. Lindell.\n\növering.: O.-O. Lundquist.\n\nKamrer: Georg Frödin.\n\nRitkontorschef; K. O. Hilding.\n\n(Jfr annons nr 53.)\n\n\"J. M. Lindelöf Träförädlingsfabrik,\n\nLandskrona.\n\nTräförädlingsfabrik och kalkbruk i\nLandskrona. TiHverkar dörrar, fönster,\ninredningar, möbler, trädetaljer av bok,\nlådämnen och lådor samt bränd kalk.\n\nTelefon: 45. Postgiro: 135405. —\nAntal industriarb.: 33. Tillv.-värde pr år:\n490,000 kr. — Firman,# etabl. 1888, äger\nSaxtorps Murbruksfabriks AB.\n\nÄgare o. chef: Pål Berggren.\n\n\"Lindesbergs Gjuter i &amp; Mek.\nVerkstad AB., Lindesberg.\n\nTillverkar grövre och finare\nmaskin-gjutgods, motorgods, vatten- och\nluft-kylda cylindrar, hårdgjutgods,\nkokillhär-dat slitgods, vattenledningsgod?, rör och\nrördelar, gatu- och gårdsbrunnar.\n\nTelegr.-adr. o. telefon: »Gjuteriet»,\nLindesberg. Postgiro: 133419. —\nAkt.-kap.: 75,000 kr. Antal industriarb.: 100.\nTillv.-värde pr år: 1,000,000 kr. —\nFirman etabl. 1920, bolag 1943.\n\nStyrelse o. verkst. dir.: Berndt\nStig-bahr.\n\nAB. Lindesbergs Ängbryggeri,\n\nlÅndesberg.\n\nTillverkar fatsvagdricka vid bryggeri\ni Lindesberg (Örebro l.).\n\nTelefon: 24. Postgiro: 289109. —\nAkt.-kap.: 25,000 kr. Antal industriarb.: 8.\nTillv.-värde pr år: 50,000 kr. — Bolaget,\ngrundat 1945, äges av Eskilstuna\nBryggeri AB.\n\nStyrelse: disp. Gösta Sverdrup (ordf.),\ndir. Richard Hellgren, bankdir. Eric\nTöfte.\n\nVerkst. dir.: Gösta Sverdrup\n(Eskilstuna).\n\nLindesby Masugn, Järnboås.\n\nMasugn i Järnboås (Örebro l.).\nTillverkar martin-, aducerings-,\nlancashire-och gjuteritaekjärn.\n\nHuvudkontor: Stockholm, Birger\nJarlsg. 26, telefon: 232565. Avd.-kontor:\nJärnboås. Telefon: Järnboås 1. — Antal\nindustriarb.: 35. Tillv.-värde pr år:\n1,500,000 kr. — Masugnen anlagd 1861.\n\nÄgare: Lindesby Hyttebolag, Carl\nSet-terwall &amp; Co. AB. (Stockholm) o. disp.\nCarl F. Geijer.\n\nPlatschef: Carl F. Geijer.\n\nA. Lindgren &amp; Söner, Göteborg.\n\nBoktryckeri, bokbinderi, kartong- och\nkuvertfabrik samt affischeringsbyrå.\nVarumärke for självklistrande kuvert:\n»Alos».\n\nKontor: Rosenlundsplatsen 3.\nTelegr.-adr.: Trycket, Göteborg. Telefon: 170985.\nPostgiro: 25409. — Antal industriarb.:\n75. Tillv.-värde pr år: 1,000,000 kr. —\nFirman etabl. 1845.\n\nÄgare: fru M. Lindgren.\n\nDisponenter: Arne Svensson o. T.\nLessler.\n\n\"Algot Lindgren, Stockholm.\n\nByggnadsentreprenörfirma för\nbostads-och affärshus, industribyggnader samt\nför väg- och vattenbyggnadsarbeten.\n\nKontor: Sveavägen 33. Telefon: 115058\no. 208834. Postgiro: 55727.\n\nProd.-värde pr år: 2,000,000 kr. —\nFirman etabl. 1921.\n\nÄgare o. chefer: överstelöjtn. Algot\nLindgren o. kapten Ragnar Lindgren.\n\nArbetschef: Börje Hellstrand.\n\nBitr. ing.: Birger Hanström.\n\nKamrer: Edvard Ahlefors.\n\n\"Arvid Lindgren &amp; Co., Stockholm.\n\nSe Färg- &amp; Ferniss Fabriks AB.,\nArvid Lindgren &amp; Co., Stockholm.\n\n\"Cottfr. Lindgren, Uppsala.\n\nByggnadsentreprenörfirjna för\nbostads-och affärshus, industribyggnader m. m.\nsamt mek. verkstad i Uppsala och\nsnickerifabrik i Skyttorp (Uppsala l.).\n\nKontor: Uppsala. Telefon: 39645.\nPostgiro: 90701. Avd.-kontor: Västerås,\ntelefon: 35298; Gävle, telefon: 5982;\nKarlskoga, telefon: 31500; Kungsör, telefon:\n424. — Prod.-värde pr år: 12,000,000 kr.\n— Firman etabl. 1921.\n\nÄgare o. chef: byggm. Gottfrid\nLindgren.\n\nAvdelningschefer: Västerås: ing. Oscar\nRing; Gävle: verkm. Johan Ericson;\nKarlskoga: verkm. Gustaf Carlgren;\nKungsör: ing. Sten Meiton.",
    "structured": {
        "1": {
            "name": "J. M. Lindelöf Träförädlingsfabrik",
            "location": "Landskrona",
            "business": "Träförädlingsfabrik och kalkbruk",
            "products": "TiHverkar dörrar, fönster, inredningar, möbler, trädetaljer av bok, lådämnen och lådor samt bränd kalk.",
            "contact": {
                "office": "Telefon: 45",
                "postgiro": "135405"
            },
            "financials": {
                "capital": "450,000 kr",
                "employees": {
                    "industriarb": 33
                },
                "annual_production_value": "490,000 kr"
            },
            "foundation_year": 1888,
            "owners": [
                "Pål Berggren"
            ]
        },
        "2": {
            "name": "Lindesbergs Gjuteri & Mek. Verkstad AB",
            "location": "Lindesberg",
            "business": "Tillverkar grövre och finare maskin-gjutgods, motorgods, vatten- och luft-kylda cylindrar, hårdgjutgods, kokillhärdat slitgods, vattenledningsgod?, rör och rördelar, gatu- och gårdsbrunnar.",
            "contact": {
                "office": "Telegr.-adr. o. telefon: \"Gjuteriet\", Lindesberg",
                "postgiro": "133419"
            },
            "financials": {
                "capital": "75,000 kr",
                "employees": {
                    "industriarb": 100
                },
                "annual_production_value": "1,000,000 kr"
            },
            "foundation_year": 1920
        },
        "3": {
            "name": "AB. Lindesbergs Ängbryggeri",
            "location": "Lindesberg",
            "business": "Tillverkar fatsvagdricka vid bryggeri",
            "contact": {
                "office": "Telefon: 24",
                "postgiro": "289109"
            },
            "financials": {
                "capital": "25,000 kr",
                "employees": {
                    "industriarb": 8
                },
                "annual_production_value": "50,000 kr"
            },
            "foundation_year": 1945,
            "owners": [
                "Eskilstuna Bryggeri AB"
            ],
            "director": "Gösta Sverdrup",
            "manager": "Gösta Sverdrup"
        },
        "4": {
            "name": "Lindesby Masugn",
            "location": "Järnboås",
            "business": "Tillverkar martin-, aducerings-, lancashire-och gjuteritaekjärn.",
            "contact": {
                "head_office": "Huvudkontor: Stockholm, Birger Jarlsg. 26, telefon: 232565",
                "sales_offices": [
                    {
                        "location": "Järnboås",
                        "phone": "Järnboås 1"
                    }
                ]
            },
            "financials": {
                "annual_production_value": "1,500,000 kr"
            },
            "predecessor": "Lindesby Hyttebolag, Carl Setterwall & Co. AB. (Stockholm)"
        },
        "5": {
            "name": "A. Lindgren & Söner",
            "location": "Göteborg",
            "business": "Boktryckeri, bokbinderi, kartong- och kuvertfabrik samt affischeringsbyrå.",
            "contact": {
                "office": "Kontor: Rosenlundsplatsen 3. Telegr.-adr.: Trycket, Göteborg. Telefon: 170985",
                "postgiro": "25409"
            },
            "financials": {
                "annual_production_value": "1,000,000 kr"
            },
            "foundation_year": 1845,
            "owners": [
                "fru M. Lindgren"
            ],
            "director": "Arne Svensson",
            "manager": "T. Lessler"
        },
        "6": {
            "name": "Algot Lindgren",
            "location": "Stockholm",
            "business": "Byggnadsentreprenörfirma för bostads-och affärshus, industribyggnader samt för väg- och vattenbyggnadsarbeten.",
            "contact": {
                "office": "Kontor: Sveavägen 33. Telefon: 115058 o. 208834",
                "postgiro": "55727"
            },
            "financials": {
                "annual_production_value": "2,000,000 kr"
            },
            "foundation_year": 1921,
            "owners": [
                "överstelöjtn. Algot Lindgren",
                "kapten Ragnar Lindgren"
            ],
            "manager": "Börje Hellstrand"
        },
        "7": {
            "name": "Arvid Lindgren & Co.",
            "location": "Stockholm",
            "business": "Färg- & Ferniss Fabriks AB.",
            "foundation_year": 1921
        },
        "8": {
            "name": "Cottfr. Lindgren",
            "location": "Uppsala",
            "business": "Byggnadsentreprenörfirma för bostads-och affärshus, industribyggnader m. m. samt mek. verkstad i Uppsala och snickerifabrik i Skyttorp (Uppsala l.).",
            "contact": {
                "office": "Kontor: Uppsala. Telefon: 39645. Postgiro: 90701",
                "sales_offices": [
                    {
                        "location": "Västerås",
                        "phone": "35298"
                    },
                    {
                        "location": "Gävle",
                        "phone": "5982"
                    },
                    {
                        "location": "Karlskoga",
                        "phone": "31500"
                    },
                    {
                        "location": "Kungsör",
                        "phone": "424"
                    }
                ]
            },
            "financials": {
                "annual_production_value": "12,000,000 kr"
            },
            "foundation_year": 1921,
            "owners": [
                "byggm. Gottfrid Lindgren"
            ],
            "board": [
                {
                    "name": "Oscar Ring",
                    "role": "Avdelningschef, Västerås"
                },
                {
                    "name": "Johan Ericson",
                    "role": "Verkmästare, Gävle"
                },
                {
                    "name": "Gustaf Carlgren",
                    "role": "Verkmästare, Karlskoga"
                },
                {
                    "name": "Sten Meiton",
                    "role": "Ingenjör, Kungsör"
                }
            ]
        }
    }
}