{
    "original": "Thura b—T idan\n\nTelefon: »Thulin verken». Postgiro:\n32749.\n\nAkt.-kap.: 300,000 kr. Antal\nindustriarb.: 300.\n\nFirman etabl. 1915 under namn AB.\nEnoch Thulins Aeroplanfabrik, ombildad\nunder nuv. namn 1919.\n\nStyrelse: jur. dr Axel Roos (ordf.),\nkapten S. M. Eskilson, dir. Ernhold\nLundström, dir. Sven Malmberg.\n\nDir.: vakant.\n\nAB. Thurab, Värmlands Nysäter.\n\nResår- och sängfabrik i Värmlands\nNy-säter (Värml. l.). Tillverkar turistsängar\noch ottomaner, soffstommar i järn och\nträ, kedjebottnar med stål och träramar,\nresårmadrasser, kudd- och plymåkärnor\nsamt ståltransportband.\n\nKontor: Värmlands Nysäter.\nTelegr.-adr.: Thurab, Säffle. Telefon: Kohlsäter\n24 o. 34.\n\nAkt.-kap.: 45,000 kr. Antal\nindustriarb.: 50. Tillv.-värde pr år: 500,000 kr.\n— Bolaget grundat 1939.\n\nVerkst. dir.: Ernst Berg.\n\nAB. Olof Thylén &amp; Co., Göteborg.\n\nLädervarufabrik. Tillverkar som\nspecialitet damväskor.\n\nKontor: övra Spannmålsg. 6.\nTelegr.-adr.: Tylénco, Göteborg. Telefon: 113667.\nPostgiro: 12368.\n\nAkt.-kap.: 150,000’ kr. Antal\nindustriarb.: 60. Tillv.-värde pr år: 1,000,000 kr.\n— Firman etabl. 1932, bolag 1944.\n\nVerkst. direktörer: Olof Thylén o.\nJosef Thylén.\n\nThörner, Bröderna, Kumla.\n\nSe AB. Bröderna Thörner, Kumla.\n\n*Tia AB., Tandsbyn.\n\nSnickerifabrik i Tandsbyn (Jämtl. l.).\nTillverkar butiksinredningar och\ninredningsdetaljer såsom kasettdiskar,\nkassahurtsar, skyltmontrar m. m. samt\nfasad-bokstäver.\n\nTelefon: 26 o. 29. Postgiro: 274666.\n\n—\tAkt.-kap.: 125,000 kr. Antal\nindustriarb.: 28. Tillv.-värde pr år: 340,000 kr.\n\n—\tBolaget grundat 1943.\n\nStyrelse: folkskollärare Iwan Englund\n(ordf.), köpm. Ernst Emilsson, riksdagsm.\nNils Jönsson, sågverksäg. Petrus Näs,\nsmidesmäst. Alfr. Pettersson.\nVerkst. dir.: Walter Strömgren.\n\nö\n\n*C. Tibblin AB., Örebro.\n\nSkofabrik. Tillverkar ago-damskor ock\nrandsydda herrskor. Varumärken:\n»Drabant» o. »Tibblins».\n\nTelegr.-adr.: Tibblins, Örebro. Telefon:\n10737 o. 14637. Postgiro: 34344.\n\nAkt.-kap.: 200,000 kr. Antal\nindustriarb.: 25. Tillv.-värde pr år: 1,000,000 kr.\n\n—\tFirman etabl. 1929, bolag 1946.\nStyrelse: dir. Gr. Tibblin (ordf.), fru\n\nInga Tibblin.\n\nVerkst. dir.: G. Tibblin.\nKontorschef: John W. Carlson.\n\n*AB. Tidaholms Möbelfabrik,\n\nTidaholm.\n\nTillverkar som specialitet\nkompletteringsmöbler.\n\nTelefon: 22. Postgiro: 27304.\nAkt.-kap.: 45,000 kr. Antal\nindustriarb.: 30. Tillv.-värde pr år: 300,000 kr.\n\n—\tFabriken anlagd 1917, nuv. bolag\ngrundat 1938.\n\nStyrelse o. chefer: fabr. Erland\nThu-rén o. möbelarkitekt Fritjof Söderholm.\n\nAB. Tidaholms Träindustri,\n\nTidaholm.\n\nSågverk och hyvleri i Tidaholm\n(Skarab. l.). Tillverkar sågade och hyvlade\nträvaror. Bolaget driver även handel med\nbyggnadsmaterial.\n\nTelefon: 230 o. 250. Postgiro: 76424.\n\n—\tAkt.-kap.: 101,250 kr. Antal\nindustriarb.: 20. — Bolaget grundat 1922.\n\nDisp.: Karl Boström.\nFörsäljn.-chef: Bertil Boström.\n\n\"Tidaholms Tändsticksfabrik,\n\nTidaholm.\n\nSe Jönköpings och Vulcans\nTändsticksfabriks AB., Jönköping.\n\n*AB. Tidaholmsverken, Tidaholm.\n\nMek. verkstad för tillverkning av\nmaskinaggregat och seriedetaljer i\nautomatmaskiner.\n\nAkt.-kap.: 500,000 kr. Antal\nindustriarb.: 450. Ensamförsälj.: AB. Bofors,.\nBofors. — Bolaget, grundat 1935, är\ndotterbolag till AB. Bofors.\n\nStyrelse o. verkst. dir.: disp. Evert\nWijkander (Bofors).\n\nPlatschef: ing. Carl Holmqvist.\n\n*AB. Tidan, Mariestad.\n\nVulkanfiber- och vulkanfibervarufabrik.\nTillverkar vulkanfiber samt reseffekter*",
    "structured": {
        "1": {
            "name": "AB. Thura",
            "location": "Värmlands Nysäter",
            "business": "Resår- och sängfabrik",
            "products": "Tillverkar turistsängar och ottomaner, soffstommar i järn och trä, kedjebottnar med stål och träramar, resårmadrasser, kudd- och plymåkärnor samt ståltransportband.",
            "contact": {
                "office": "Värmlands Nysäter",
                "telegraph": "Thurab, Säffle",
                "phone": [
                    "Kohlsäter 24",
                    "Kohlsäter 34"
                ],
                "postgiro": "32749"
            },
            "financials": {
                "capital": "300,000 kr",
                "employees": {
                    "industriarb": 300
                },
                "foundation_year": 1915,
                "current_name_year": 1919
            },
            "board": [
                {
                    "name": "jur. dr Axel Roos",
                    "role": "ordf."
                },
                {
                    "name": "kapten S. M. Eskilson",
                    "role": ""
                },
                {
                    "name": "dir. Ernhold Lundström",
                    "role": ""
                },
                {
                    "name": "dir. Sven Malmberg",
                    "role": ""
                }
            ]
        },
        "2": {
            "name": "AB. Thurab",
            "location": "Värmlands Nysäter",
            "business": "Resår- och sängfabrik",
            "products": "Tillverkar turistsängar och ottomaner, soffstommar i järn och trä, kedjebottnar med stål och träramar, resårmadrasser, kudd- och plymåkärnor samt ståltransportband.",
            "contact": {
                "office": "Värmlands Nysäter",
                "telegraph": "Thurab, Säffle",
                "phone": [
                    "Kohlsäter 24",
                    "Kohlsäter 34"
                ],
                "postgiro": "32749"
            },
            "financials": {
                "capital": "45,000 kr",
                "employees": {
                    "industriarb": 50
                },
                "annual_turnover": "500,000 kr",
                "foundation_year": 1939
            },
            "director": "Ernst Berg"
        },
        "3": {
            "name": "AB. Olof Thylén & Co.",
            "location": "Göteborg",
            "business": "Lädervarufabrik",
            "products": "Tillverkar som specialitet damväskor.",
            "contact": {
                "office": "övra Spannmålsg. 6",
                "telegraph": "Tylénco, Göteborg",
                "phone": "113667",
                "postgiro": "12368"
            },
            "financials": {
                "capital": "150,000 kr",
                "employees": {
                    "industriarb": 60
                },
                "annual_turnover": "1,000,000 kr",
                "foundation_year": 1932,
                "corporation_year": 1944
            },
            "directors": [
                "Olof Thylén",
                "Josef Thylén"
            ]
        },
        "4": {
            "name": "Tia AB.",
            "location": "Tandsbyn",
            "business": "Snickerifabrik",
            "products": "Tillverkar butiksinredningar och inredningsdetaljer såsom kasettdiskar, kassahurtsar, skyltmontrar m. m. samt fasad-bokstäver.",
            "contact": {
                "office": "Tandsbyn",
                "phone": [
                    "26",
                    "29"
                ],
                "postgiro": "274666"
            },
            "financials": {
                "capital": "125,000 kr",
                "employees": {
                    "industriarb": 28
                },
                "annual_turnover": "340,000 kr",
                "corporation_year": 1943
            },
            "board": [
                {
                    "name": "folkskollärare Iwan Englund",
                    "role": "ordf."
                },
                {
                    "name": "köpm. Ernst Emilsson",
                    "role": ""
                },
                {
                    "name": "riksdagsm. Nils Jönsson",
                    "role": ""
                },
                {
                    "name": "sågverksäg. Petrus Näs",
                    "role": ""
                },
                {
                    "name": "smidesmäst. Alfr. Pettersson",
                    "role": ""
                }
            ],
            "director": "Walter Strömgren"
        },
        "5": {
            "name": "C. Tibblin AB.",
            "location": "Örebro",
            "business": "Skofabrik",
            "products": "Tillverkar ago-damskor ock randsydda herrskor. Varumärken: »Drabant» o. »Tibblins».",
            "contact": {
                "telegraph": "Tibblins, Örebro",
                "phone": [
                    "10737",
                    "14637"
                ],
                "postgiro": "34344"
            },
            "financials": {
                "capital": "200,000 kr",
                "employees": {
                    "industriarb": 25
                },
                "annual_turnover": "1,000,000 kr",
                "corporation_year": 1946
            },
            "board": [
                {
                    "name": "dir. Gr. Tibblin",
                    "role": "ordf."
                },
                {
                    "name": "fru Inga Tibblin",
                    "role": ""
                }
            ],
            "directors": {
                "G. Tibblin": "John W. Carlson"
            },
            "6": {
                "name": "AB. Tidaholms Möbelfabrik,",
                "location": "Tidaholm",
                "business": "Tillverkar som specialitet kompletteringsmöbler.",
                "contact": {
                    "office": "Tidaholm",
                    "phone": "22",
                    "postgiro": "27304"
                },
                "financials": {
                    "capital": "45,000 kr",
                    "employees": {
                        "industriarb": 30
                    },
                    "annual_turnover": "300,000 kr",
                    "corporation_year": 1938
                },
                "board": [
                    {
                        "name": "fabr. Erland Thurén",
                        "role": ""
                    },
                    {
                        "name": "möbelarkitekt Fritjof Söderholm",
                        "role": ""
                    }
                ]
            },
            "7": {
                "name": "AB. Tidaholms Träindustri,",
                "location": "Tidaholm",
                "business": "Sågverk och hyvleri",
                "products": "Tillverkar sågade och hyvlade trävaror. Bolaget driver även handel med byggnadsmaterial.",
                "contact": {
                    "office": "Tidaholm",
                    "phone": [
                        "230",
                        "250"
                    ],
                    "postgiro": "76424"
                },
                "financials": {
                    "capital": "101,250 kr",
                    "employees": {
                        "industriarb": 20
                    },
                    "corporation_year": 1922
                },
                "directors": [
                    "Karl Boström",
                    "Bertil Boström"
                ]
            },
            "8": {
                "name": "Tidaholms Tändsticksfabrik,",
                "location": "Tidaholm",
                "description": "Se Jönköpings och Vulcans Tändsticksfabriks AB., Jönköping."
            },
            "9": {
                "name": "AB. Tidaholmsverken,",
                "location": "Tidaholm",
                "business": "Mek. verkstad",
                "products": "Tillverkning av maskinaggregat och seriedetaljer i automatmaskiner.",
                "contact": {
                    "office": "Tidaholm"
                },
                "financials": {
                    "capital": "500,000 kr",
                    "employees": {
                        "industriarb": 450
                    }
                },
                "directors": [
                    "disp. Evert Wijkander (Bofors)"
                ],
                "managing_director": "ing. Carl Holmqvist"
            },
            "10": {
                "name": "AB. Tidan,",
                "location": "Mariestad",
                "business": "Vulkanfiber- och vulkanfibervarufabrik",
                "products": "Tillverkar vulkanfiber samt reseffekter.",
                "financials": {
                    "capital": "500,000 kr",
                    "employees": {
                        "industriarb": 450
                    }
                },
                "director": "disp. Evert Wijkander (Bofors)",
                "manager": "ing. Carl Holmqvist"
            }
        }
    }
}