{
    "original": "Marieholm—Mark\n\nTelegr.-adr.: International, Göteborg.\nTelefon: 171090. Postgiro: 43368.\nAvd.-kontor: Stockholm, Blasieholmsg. 3,\ntelefon: 112875; Malmö, St. Varvsg. 2,\ntelefon: 26735.\n\nAkt.-kap.: 50,000 kr. Antal\nindustriarb.: 30. Tillv.-värde pr år: 600,000 kr.\n\nBolaget grundat 1932. Färg AB.\nInternational, Göteborg, äger aktiemajoriteten\ni bolaget.\n\nStyrelse: generalkonsul Gunnar\nCarlsson (ordf.), dir. K. R. Bökman, grossh.\nVictor Janson.\n\nVerkst. dir.: Rob. Johansson.\n\nKamrer: M. Byttner.\n\n\"Marieholms Tegelbruks AB.,\n\nMarieholm.\n\nTillverkar rött fasadtegel, murtegel\nsamt dräneringsrör vid tegelbruk i\nMarieholm (Malmöh. l.).\n\nTelefon: 1. — Akt.-kap.: 50,200 kr.\nAntal industriarb.: 20. Årstillv.: 900,000\nst. tegelvaror. — Bolaget grundat 1916.\n\nStyrelse: civiling. Bonde Bondeson\n(ordf.), disp. Egon Persson (v. ordf.),\nlantbr. Eric Bondeson, köpm. Helge\nPersson, kamrer Sture Silve.\n\nVerkst. dir. o. disp.: Egon Persson.\n\n\"Marieholms Yllefabriks AB.,\n\nMarieholm.\n\nUllspinneri, ylleväveri, färgeri och\nberedningsverk i Marieholm (Malmöh. l.).\nTillverkar hel- och halvyllevävnader,\nkam-garn, filtar m. m.\n\nTelefon o. telegr.-adr.: Marifa,\nMarieholm. Postgiro: 8709. Repr. i Borås: R.\nUhlins Textilagentur, telefon: 11512.\n\nAkt.-kap.: 800,000 kr. Antal\nindustriarb.: 275. Tillv.-värde pr år: 5,000,000 kr.\n— Firman etabl. 1898, bolag 1919.\n\nStyrelse: dir. Thure Hallmark (ordf.),\ndir.-assist. Hans Hallmark, adv. Sigfrid\nLindström, adv. Gösta Wennerholm.\n\nVerkst. dir.; Thure Hallmark.\n\nKamrer: Sixten Wendestam.\n\nFörsäljn.-chef: kapten Olof Asplund.\n\nDriftsledare: Henry Sjölund.\n\nEkonomichef: Sigurd Sjölund.\n\n\"Mariestads Bryggeri AB.,\n\nMariestad.\n\nTillverkar malt samt malt- och\nläskedrycker vid bryggerier i Mariestad och\nMellerud (Älvsb. l.).\n\nTelegr.-adr.: Bryggeribolaget,\nMariestad. Telefon: 47. Postgiro: 27311.\nAvd.-kontor i Mellerud.\n\nAkt.-kap.: 420,000 kr. Antal\nindustriarb.: 30. Tillv.-värde pr år: 880,000 kr.\n— Bolaget grundat 1866.\n\nStyrelse: f. kapten C. G. Bendz (ordf.),\nfru N. Collin, kamrer W. Falk.\n\nVerkst. dir. o. disp.: C. G. Bendz.\n\nKamrer: W. Falk.\n\nBryggmästare: i Mariestad: Olof\nHelgeson; i Mellerud: E. W. Waenerlund.\n\n\"Mariestads Möbelfabrik, Mariestad.\n\nTillverkar möbler och inredningar för\nbank-, affärs- och samlingslokaler m. m.\n\nTelefon: 363. Postgiro: 36898. —\nAntal industriarb.: 18. Tillv.-värde pr år:\n125,000 kr. — Firman etabl. 1916.\n\nÄgare: fabr. Nathan Jonsson, fabr.\nIvar Karlsson o. fabr. Carl Björk.\nChef: Nathan Jonsson.\n\n\"AB. Mariestads Trikåfabrik,\n\nMariestad.\n\nTillverkar herr- och damunderkläder.\n\nTelefon: 169. Postgiro: 23774. —\nAkt.-kap.: 60,000 kr. Antal industriarb.: 15.\n— Bolaget grundat 1932.\n\nStyrelse o. disp.: Carl Johansson.\n\nKamrer: Harry Helsner.\n\nMarieströms Fabrik, Gnosjö.\n\nMetallfabrik i Gnosjö (Jönköp. L).\n\nTillverkar spik, klackspik, stift,\nkrampor, saxsprintar, mutterbrickor m. m.\n\nTelefon: 16. Postgiro: 28327. —\nArb.-antal: 10. — Firman etabl. 1928.\n\nÄgare o. chef: fabr. Rudolf Bauréus.\n\n\"AB. Marks Jacquardväveri,\n\nBjörketorp.\n\nVäveri i Björketorp (Älvsb. l.).\nTillverkar draperiväv och möbeltyger i\nkonst-silke och bomull, ottomanöverkast m. m.\n\nTelefon: Kinna 60008. Postgiro: 22655.\nFörsäljare: S. Leijon, Varberg, telefon:\n1121.\n\nAkt.-kap.: 220,000 kr. Antal\nindustriarb.: 55. Tillv.-värde pr år: 1,000,000 kr.\n— Bolaget grundat 1926.\n\nStyrelse: dir. Artur Persson (ordf.),\ndir. Anders Ekelund, dir. Rob. Svedman.\n\nVerkst. dir. o. disp.: Rob. Svedman.\n\n\"Marks Linnemanufaktur AB.,\n\nKungälv.\n\nSe Almedahl-Dalsjöfors AB., Göteborg.",
    "structured": {
        "1": {
            "name": "Marieholm—Mark",
            "location": "International, Göteborg",
            "contact": {
                "telegraph": "International, Göteborg",
                "phone": [
                    "171090"
                ],
                "postgiro": "43368",
                "sales_offices": [
                    {
                        "location": "Stockholm, Blasieholmsg. 3",
                        "phone": "112875"
                    },
                    {
                        "location": "Malmö, St. Varvsg. 2",
                        "phone": "26735"
                    }
                ]
            },
            "financials": {
                "capital": "50,000 kr",
                "employees": {
                    "industriarb": 30
                },
                "annual_production_value": "600,000 kr"
            },
            "foundation_year": 1932,
            "owners": [
                "Färg AB"
            ],
            "board": [
                {
                    "name": "generalkonsul Gunnar Carlsson",
                    "role": "ordf"
                },
                {
                    "name": "dir. K. R. Bökman",
                    "role": null
                },
                {
                    "name": "grossh. Victor Janson",
                    "role": null
                }
            ],
            "director": "Rob. Johansson"
        },
        "2": {
            "name": "Marieholms Tegelbruks AB",
            "location": "Marieholm",
            "contact": {
                "phone": [
                    "1"
                ],
                "postgiro": "43368"
            },
            "financials": {
                "capital": "50,200 kr",
                "employees": {
                    "industriarb": 20
                },
                "annual_production_value": "900,000 st. tegelvaror"
            },
            "foundation_year": 1916,
            "board": [
                {
                    "name": "civiling. Bonde Bondeson",
                    "role": "ordf"
                },
                {
                    "name": "disp. Egon Persson",
                    "role": "v. ordf."
                },
                {
                    "name": "lantbr. Eric Bondeson",
                    "role": null
                },
                {
                    "name": "köpm. Helge Persson",
                    "role": null
                },
                {
                    "name": "kamrer Sture Silve",
                    "role": null
                }
            ],
            "director": "Rob. Johansson"
        },
        "3": {
            "name": "Marieholms Yllefabriks AB",
            "location": "Marieholm",
            "contact": {
                "telegraph": "Marifa, Marieholm",
                "phone": [
                    "Marifa, Marieholm"
                ],
                "postgiro": "8709",
                "sales_offices": [
                    {
                        "location": "Borås",
                        "phone": "R. Uhlins Textilagentur, telefon: 11512"
                    }
                ]
            },
            "financials": {
                "capital": "800,000 kr",
                "employees": {
                    "industriarb": 275
                },
                "annual_production_value": "5,000,000 kr"
            },
            "foundation_year": 1898,
            "board": [
                {
                    "name": "dir. Thure Hallmark",
                    "role": "ordf"
                },
                {
                    "name": "dir.-assist. Hans Hallmark",
                    "role": null
                },
                {
                    "name": "adv. Sigfrid Lindström",
                    "role": null
                },
                {
                    "name": "adv. Gösta Wennerholm",
                    "role": null
                }
            ],
            "director": "Thure Hallmark"
        },
        "4": {
            "name": "Mariestads Bryggeri AB",
            "location": "Mariestad",
            "contact": {
                "telegraph": "Bryggeribolaget, Mariestad",
                "phone": [
                    "47"
                ],
                "postgiro": "27311"
            },
            "financials": {
                "capital": "420,000 kr",
                "employees": {
                    "industriarb": 30
                },
                "annual_production_value": "880,000 kr"
            },
            "foundation_year": 1866,
            "board": [
                {
                    "name": "f. kapten C. G. Bendz",
                    "role": "ordf"
                },
                {
                    "name": "fru N. Collin",
                    "role": null
                },
                {
                    "name": "kamrer W. Falk",
                    "role": null
                }
            ],
            "director": "C. G. Bendz"
        },
        "5": {
            "name": "Mariestads Möbelfabrik",
            "location": "Mariestad",
            "contact": {
                "phone": [
                    "363"
                ],
                "postgiro": "36898"
            },
            "financials": {
                "employees": {
                    "industriarb": 18
                },
                "annual_production_value": "125,000 kr"
            },
            "foundation_year": 1916
        },
        "6": {
            "name": "AB. Mariestads Trikåfabrik",
            "location": "Mariestad",
            "contact": {
                "phone": [
                    "169"
                ],
                "postgiro": "23774"
            },
            "financials": {
                "capital": "60,000 kr",
                "employees": {
                    "industriarb": 15
                }
            },
            "foundation_year": 1932
        },
        "7": {
            "name": "Marieströms Fabrik",
            "location": "Gnosjö",
            "contact": {
                "phone": [
                    "16"
                ],
                "postgiro": "28327"
            },
            "financials": {
                "employees": {
                    "antal": 10
                }
            },
            "foundation_year": 1928
        },
        "8": {
            "name": "AB. Marks Jacquardväveri",
            "location": "Björketorp",
            "contact": {
                "phone": [
                    "Kinna 60008"
                ],
                "postgiro": "22655",
                "sales_offices": [
                    {
                        "location": "Varberg",
                        "phone": "1121"
                    }
                ]
            },
            "financials": {
                "capital": "220,000 kr",
                "employees": {
                    "industriarb": 55
                },
                "annual_production_value": "1,000,000 kr"
            },
            "foundation_year": 1926,
            "board": [
                {
                    "name": "dir. Artur Persson",
                    "role": "ordf"
                },
                {
                    "name": "dir. Anders Ekelund",
                    "role": null
                },
                {
                    "name": "dir. Rob. Svedman",
                    "role": null
                }
            ],
            "director": "Rob. Svedman"
        },
        "9": {
            "name": "Marks Linnemanufaktur AB",
            "location": "Kungälv"
        }
    }
}