{
    "original": "Sniekerifq^r^en^Somme^\n\nSnickerifabriken ödmark &amp;\nNordgren, Borlänge.\n\nTillverkar trappor, köksinredningar.,\nbyggnadssnickerier och möbler.\n\nTelefon: Borlänge 10612. Postgiro;\n28715.\n\nAntal industriarb.: 12. Tillv.-värde pr\når: 110,000 kr. — Firman etabl. 1923.\nÄgare o. chef: fabr. Helmer ödmark.\n\n\"Sockerbolaget, Malmö.\nSe; Svenska Sockerfabriks AB., Malmö.\n\nSodafabrikernas Försäljnings AB.,\n\nGöteborg.\t’\n\nFörsäljer delägande och samarbetande\nfabrikers\" hélä tillverkning av\nkristall-soda.\n\nKontor: Thulehuset. Telegr.-adr.: Soda,\nGöteborg. Telefon: 136904. Postgiro:\n25536.\n\nAkt.-kap^: 117,600 kr. — Bolaget\ngrundat 1900.\n\nStyrelse:, dir. Otto Hill (ordf.), disp.\nAnders Christofferson, kapten P. Gustaf\nÅgren.\n\nVqrkst. dir.: Sven Thurén.\n\n\"Sofiehems träsliperi, TJmeå.\n\nSe AB. Umeå Trämassefabriker, Umeå.\n\n\"AB. Solberga Fabriker, Solberga.\n\nTillverkar likkistor och möbler vid\nsnickerifabrik i Solberga (Jönköp. l.).\n\nTelefon: 10. Postgiro: 81260. —\nAkt.-kap.: 32,000 kr. Arb.-antal: 10.\nTillv.-värde pr år: 120,000 kr. — Bolaget\ngrundat 1940.\n\nStyrelse: dir. Gunnar Leide (ordf.),\ndisp. Johan Bergström, verkm. Vilh.\nSvensson.\n\nDisp.: Johan Bergström.\n\n\"Solberga Mek. Werkstads A B.,\n\nSolberga.\n\nMek. verkstad vid Solberga (Jönköp.\n1.). Tillverkar verktygsmaskiner m. m.\n\nTelegr.-adr.: Verkstaden, Solberga.\nTelefon: 90. Postgiro: 27897.\n\nAkt.-kap.: 200,000 kr. Antal\nindustriarb.: 45. Tillv.-värde pr år: 600,000 kr.\n— Firman etabl. 1900, bolag 1915.\n\nStyrelse: disp. Nathan Widfeldt\n(ordf.), fabr. Eric Widfeldt.\n\nVerkst. dir. o. disp.: Nathan Widfeldt.\nKontorschef: Nils-Gustaf Widfeldt.\n\n*AB. Solfarin, Sölvesborg.\n\nGlykosfabrik. Tillverkar glykos,\nsago-och potatisgryn.\t7\n\nTelégr.-adr.:’! Solfarin, Sölvesborg:.\n.’Telef dn: 10ÖÖ8. Postgiro: 20954.\n\nAkt.-kap.: 225,000 kr. Antal\nindustriarb.: 15. Tillv.-värde pr år: 900,000 kr.\n\n—\tBolaget grundat 1904.\n\nS tyrelse: v. konsul Thure Carlssöh\n(ordf.), kapten Fritz Arne, dir. Hj.\nCarl-born, fröken Thyra Carlsson, handl. J.\nLjungh.\n\nVerTcst. dir.: Thure Carlsson.\nDisp.: Emil Eklund.\n\n\"Sollefteå Bryggeri AB;,\n\nSollefteå. ,\t:,. ;\n\nTillverkar malt- och läskedrycker.\nTelegr.-adr. o. telefon: Bryggeriet;\nSollefteå. Postgiro: 76450.\n\nAkt.-käp.: 150,000 kr. Antal\nindustriarb.: 25. Tillv.-värde pr år: 700,000 kr.\n\n—\tBryggeriet anlagt 1857, bolag 193?.\nStyrelse: försäljn.tchef Dayid Jansson,\n\nfru A.-L. Otterström, disp. S. Otterström.\nDisp.: S. Otterström.\n\nAB. Soilefteå Kalksandstegel,\n\nSollefteå.\t= &gt; :\n\nTillverkar kalksandstegel,\nméllianväggs-plattor och betongtegel. ,\n\nTelefon: 380. Postgiro: 84611: —\nAkt.-kap,: 50,000 kr. Arb.-antal: 12.— Bolaget\ngrundat 1908. ; :\n\nVerkst. dir.: Gustaf, Lunägren.\n\n\"AB. Sollefteå Syrgas verk, •\n\nSollefteå.\n\nFramställer syrgas och dissousgas vid\nfabriker i Sundsvall, Örnsköldsvik,\nSkel-leftehamm (Västerbott. L) och Luleå.\n\nKontor: Sollefteå. Telefon:, 358.\nPostgiro: 13492.\n\nAkt.-kap.: 990,000 kr. Antal\nindustriarb.: 14. Tillv.-värde pr år: 1,000,000 kr.\n— Bolaget grundat 1914. ] ; ! :\n\nStyrelse: sågverksäg. P. Sjödin (ordf.),\nkabinettskammarh. Rolf v. Heidenstam,\ning. Herbert Lindblad, dir. Axel Mellin,\nfil. lie. S. A. Webjörn.\n\nVerkst. dir.: August Bylund.\n\n\"Sollex, Rakbladsfabriken,\n\nJönköping.\n\nSe Rakbladsfabriken Sollex, Jönköping.\n\n\"Sömmens Lådfabrik, Sömmen.\n\nSe Nya AB. Sömmens Lådfabrik,\nSömmen.\n\n499*",
    "structured": {
        "1": {
            "name": "Snickerifabriken Ödmark & Nordgren",
            "location": "Borlänge",
            "business": "Tillverkar trappor, köksinredningar, byggnadssnickerier och möbler",
            "contact": {
                "phone": [
                    "10612"
                ],
                "postgiro": "28715"
            },
            "financials": {
                "employees": {
                    "industriarb": 12
                },
                "annual_production_value": "110,000 kr"
            },
            "foundation_year": 1923,
            "owners": [
                "fabr. Helmer Ödmark"
            ]
        },
        "2": {
            "name": "Sodafabrikernas Försäljnings AB",
            "location": "Göteborg",
            "business": "Försäljer delägande och samarbetande fabrikers hélä tillverkning av kristall-soda",
            "contact": {
                "sales_offices": [
                    {
                        "location": "Thulehuset",
                        "phone": "136904"
                    }
                ],
                "telegraph": "Soda, Göteborg",
                "postgiro": "25536"
            },
            "financials": {
                "capital": "117,600 kr"
            },
            "foundation_year": 1900,
            "board": [
                {
                    "name": "Otto Hill",
                    "role": "ordf."
                },
                {
                    "name": "Anders Christofferson",
                    "role": "disp."
                },
                {
                    "name": "P. Gustaf Ågren",
                    "role": "kapten"
                }
            ],
            "managing_director": "Sven Thurén"
        },
        "3": {
            "name": "AB. Solberga Fabriker",
            "location": "Solberga (Jönköp. l.)",
            "business": "Tillverkar likkistor och möbler vid snickerifabrik",
            "contact": {
                "phone": "10",
                "postgiro": "81260"
            },
            "financials": {
                "employees": {
                    "Arb.-antal": 10
                },
                "annual_production_value": "120,000 kr"
            },
            "foundation_year": 1940,
            "board": [
                {
                    "name": "Gunnar Leide",
                    "role": "ordf."
                },
                {
                    "name": "Johan Bergström",
                    "role": "disp."
                },
                {
                    "name": "Vilh. Svensson",
                    "role": "verkm."
                },
                {
                    "name": "Johan Bergström",
                    "role": "disp."
                }
            ]
        },
        "4": {
            "name": "Solberga Mek. Werkstads A B",
            "location": "Solberga (Jönköp. l.)",
            "business": "Tillverkar verktygsmaskiner m. m",
            "contact": {
                "telegraph": "Verkstaden, Solberga",
                "phone": "90",
                "postgiro": "27897"
            },
            "financials": {
                "capital": "200,000 kr",
                "employees": {
                    "industriarb": 45
                },
                "annual_production_value": "600,000 kr"
            },
            "foundation_year": 1900,
            "corporation_year": 1915,
            "board": [
                {
                    "name": "Nathan Widfeldt",
                    "role": "ordf."
                },
                {
                    "name": "Eric Widfeldt",
                    "role": "fabr."
                },
                {
                    "name": "Nathan Widfeldt",
                    "role": "verkst. dir."
                },
                {
                    "name": "Nils-Gustaf Widfeldt",
                    "role": "Kontorschef"
                }
            ]
        },
        "5": {
            "name": "AB. Solfarin",
            "location": "Sölvesborg",
            "business": "Glykosfabrik - Tillverkar glykos, sago-och potatisgryn",
            "contact": {
                "telegraph": "Solfarin, Sölvesborg",
                "phone": "10ÖÖ8",
                "postgiro": "20954"
            },
            "financials": {
                "capital": "225,000 kr",
                "employees": {
                    "industriarb": 15
                },
                "annual_production_value": "900,000 kr"
            },
            "foundation_year": 1904,
            "board": [
                {
                    "name": "Thure Carlssöh",
                    "role": "v. konsul"
                },
                {
                    "name": "Fritz Arne",
                    "role": "kapten"
                },
                {
                    "name": "Hj. Carl-born",
                    "role": "dir."
                },
                {
                    "name": "Thure Carlsson",
                    "role": "Verkst. dir."
                },
                {
                    "name": "Emil Eklund",
                    "role": "Disp."
                }
            ]
        },
        "6": {
            "name": "Sollefteå Bryggeri AB",
            "location": "Sollefteå",
            "business": "Tillverkar malt- och läskedrycker",
            "contact": {
                "phone": "Bryggeriet, Sollefteå",
                "postgiro": "76450"
            },
            "financials": {
                "capital": "150,000 kr",
                "employees": {
                    "industriarb": 25
                },
                "annual_production_value": "700,000 kr"
            },
            "corporation_year": 1937,
            "board": [
                {
                    "name": "Dayid Jansson",
                    "role": "försäljn.tchef"
                },
                {
                    "name": "A.-L. Otterström",
                    "role": "fru"
                },
                {
                    "name": "S. Otterström",
                    "role": "disp."
                }
            ]
        },
        "7": {
            "name": "AB. Sollefteå Kalksandstegel",
            "location": "Sollefteå",
            "business": "Tillverkar kalksandstegel, méllianväggs-plattor och betongtegel",
            "contact": {
                "phone": "380",
                "postgiro": "84611"
            },
            "financials": {
                "capital": "50,000 kr",
                "employees": {
                    "Arb.-antal": 12
                }
            },
            "foundation_year": 1908,
            "director": "Gustaf Lunägren"
        },
        "8": {
            "name": "AB. Sollefteå Syrgas verk",
            "location": "Sollefteå",
            "business": "Framställer syrgas och dissousgas vid fabriker i Sundsvall, Örnsköldsvik, Skelleftehamm (Västerbott. L) och Luleå",
            "contact": {
                "phone": "358",
                "postgiro": "13492"
            },
            "financials": {
                "capital": "990,000 kr",
                "employees": {
                    "industriarb": 14
                },
                "annual_production_value": "1,000,000 kr"
            },
            "foundation_year": 1914,
            "board": [
                {
                    "name": "P. Sjödin",
                    "role": "sågverksäg."
                },
                {
                    "name": "Rolf v. Heidenstam",
                    "role": "kabinettskammarh."
                },
                {
                    "name": "Herbert Lindblad",
                    "role": "ing."
                },
                {
                    "name": "Axel Mellin",
                    "role": "dir."
                },
                {
                    "name": "S. A. Webjörn",
                    "role": "fil. lie."
                }
            ],
            "managing_director": "August Bylund"
        }
    }
}