{
    "original": "Nordiska—Nordmaling\n\nping, telefon: 3301; Kalmar, telefon:\n1747; Västerås, telefon: 34900;\nNorrköping, telefon: 21808; Halmstad, telefon:\n4775 och Linköping, telefon: 28691.\nTelegr.-adr.: för Stockholm och Örebro:\nSyrgas verken; för Göteborg: Syrgas.\n\nAkt.-kap.: 2.000,000 kr. Antal\nindustriarb.: 73. — Bolaget grundat 1907.\n\nStyrelse: disp. Ejnar Rodling (ordf.),\nkabinettskammarh. Rolf v. Heidenstam,\ndir. Hans Rydin, dir. Nils Westberg.\n\nVerkst. dir.: Ernst Weland.\n\nTeknisk ledare: civiling. Åke Anderfelt.\n\nDriftsing.: Gösta Dahlström. ____\n\nDisp. i Göteborg: Arne Mellgren.\n\n(Jfr annons nr 33.)\n\nAB. Nordiska Tapetfabriken,\n\nArvika.\n\nTillverkar tapeter och bårder.\n\nTelegr.-adr.: Tapetfabriken, Arvika.\nTelefon: 108 o. 477. Postgiro: 37317.\n\nAkt.-kap.: 400,000 kr. Antal\nindustriarb.: 23. Tillv.-värde pr år: 400,000 kr.\n\n—\tBolaget grundat 1905.\n\nStyrelse: adv. H. Benndorf, herr J.\nEdenquist, dir. Robert J:son Lindh.\n\nVerkst. dir.: Robert J:son Lindh.\n\n*AB. Nordiska Tubfabriken,\n\nKungsör.\n\nTillverkar vid fabrik i Kungsör\n(Västmanl. l.) förpackningstuber av\naluminium, bly och tenn, tennpläterade tuber,\nkapslar, lackerade och tryckta tuber för\nkem. tekn. industrin, för färger m. m.\nsamt zaponerade tuber för\nkonservindustrin.\n\nTelegr.-adr. o. telefon: Tubfabriken,\nKungsör. Postgiro: 76670.\n\nAkt.-kap.: 137,500 kr. Antal\nindustriarb.: 47. Tillv.-värde pr år: 1,278,000 kr.\n\n—\tBolaget grundat 1917.\n\nStyrelse: disp. Berthold Orrvik (ordf.),\nfru M. Orrvik, verkstadschef Åke Orrvik.\n\nVerkst. dir. o. disp.: Berthold Orrvik.\n\n(Jfr annons nr 30.)\n\n*Nordiska Värme- &amp; Ventilations AB.,\n\nGöteborg.\n\nBolaget äger mek. verkstad, plåtslageri\noch svetsningsverkstad samt driver\nentreprenadverksamhet i värme- och\nsanitets-tekniska branschen.\n\nTillverkar badkaminer, svetsade\nvarmvattenpannor och cisterner m. m., utför\nkompletta gas-, vatten-, avlopps-, W. O.-,\nång-, värme- och ventilationsanläggningar,\nångköks-, tvätt-, tork-, desinfektions- och\nsteriliseringsanläggningar.\n\nHuvudkontor: Göteborg, 3:dje Långg.\n13; postadr.: Värmebolaget. Telegr.-adr.:\nVärmebolaget, Göteborg. Telefon: 171045.\nPostgiro: 42160. Filialer i Eskilstuna,\nHalmstad, Karlstad, Kristinehamn,\nKöping, Ljungby, Ludvika, Norrköping,\nSunne, Surahammar, Växjö, Västerås,\nFagersta-Västanfors och Uddevalla.\n\nAkt.-kap.: 900,000 kr. Antal\nindustriarb.: 350. Prod.-värde pr år: 8,000,000 kr.\n\n—\tBolaget grundat 1903.\n\nStyrelse: dir. C. Gunnar Laurenius\n(ordf.), ing. B. Gunnar Laurenius,\nciviling. Eric Levan.\n\nVerkst. dir.: O. G. Laurenius.\n\nV. verkst. dir.: Eric Levan.\n\növering.; Erik Gabrielsson.\n\n*AB. Nordiska Yllefabriken,\n\nNorrköping.\n\nUllspinneri, väveri, färgeri och\nappre-turverk. Tillverkar klädes- och\nkamgarns-tyger samt cheviot. Varumärken:\n»Kungs-cheviot» o. »NYF».\n\nTelegr.-adr.: Nordylle, Norrköping.\nTelefon: 23149 o. 22163. Postgiro: 11106.\n\nAkt.-kap.: 100,000 kr. Antal\nindustriarb.: 120. Tillv.-värde pr år: 1,700,000 kr.\n\n—\tFirman etabl. 1919, bolag 1938.\n\nStyrelse o. verkst. dir.: fabr. Christian\n\nSchnock.\n\n*d. F. Nordlöf, Lerum.\n\nSkofabrik i Lerum (Älvsb. l.).\nTillverkar herr- och damskodon. Specialitet:\nhandarbetade skor.\n\nTelegr.-adr.: Nordlöf s, Lerum. Telefon:\n333, 350 o. 992. Postgiro: 40826. —\nAntal industriarb.: 40. Tillv.-värde pr år:\n500,000 kr. — Firman etabl. 1875.\n\nÄgare o. chef: dir. Sam. Bjerkander.\n\n*Nordmalings Angsågs AB.,\n\nNordmaling.\n\nÅngsåg och wallboardfabrik vid\nRundvik, manufaktur- och kättingsmedja vid\nOlovsfors samt elektr. vattenkraftstation\nvid Leduåfors (samtl. i Västerb. l.).\n\nTillverkar sågade trävaror, wallboard\n(masonite) för isolerings-, byggnads- och\ninredningsändamål, kätting och\nflott-ningssmiden, redskap för\ntimmeravverkning samt distribuerar elektr. energi.\nBolaget idkar jämväl jordbruk,\nskogshantering och kvarnrörelse.\n\nHuvudkontor: Olovsfors Bruk,\nNordmaling. Telegr.-adr.: Ångsågsbolaget,\nNordmaling. Telefon: 26. Postgiro: 62486.\n\nEnsamförsälj. för trävaror och\nmasonite: P. Wikström J:or, Stockholm,\nStallg. 3, telefon: 109925 o. 101018.",
    "structured": {
        "1": {
            "name": "Nordiska",
            "location": "Nordmaling",
            "business": "Ping, telefon",
            "contact": {
                "telegraph": "Syrgas verken"
            },
            "financials": {
                "capital": "2.000.000 kr"
            },
            "foundation_year": 1907,
            "board": [
                {
                    "name": "Ejnar Rodling",
                    "role": "ordf."
                },
                {
                    "name": "Rolf v. Heidenstam",
                    "role": "kabinettskammarh."
                },
                {
                    "name": "Hans Rydin",
                    "role": "dir."
                },
                {
                    "name": "Nils Westberg",
                    "role": "dir."
                }
            ],
            "director": "Ernst Weland",
            "managing_director": "Ernst Weland",
            "sales_manager": "Gösta Dahlström"
        },
        "2": {
            "name": "AB. Nordiska Tapetfabriken",
            "location": "Arvika",
            "business": "Tillverkar tapeter och bårder",
            "contact": {
                "telegraph": "Tapetfabriken, Arvika",
                "phone": [
                    "108",
                    "477"
                ],
                "postgiro": "37317"
            },
            "financials": {
                "capital": "400.000 kr"
            },
            "foundation_year": 1905,
            "board": [
                {
                    "name": "H. Benndorf",
                    "role": "adv."
                },
                {
                    "name": "J. Edenquist",
                    "role": "herr"
                },
                {
                    "name": "Robert J:son Lindh",
                    "role": "dir."
                }
            ],
            "director": "Robert J:son Lindh",
            "managing_director": "Robert J:son Lindh"
        },
        "3": {
            "name": "*AB. Nordiska Tubfabriken",
            "location": "Kungsör",
            "business": "Tillverkar vid fabrik i Kungsör (Västmanl. l.) förpackningstuber av aluminium, bly och tenn, tennpläterade tuber, kapslar, lackerade och tryckta tuber för kem. tekn. industrin, för färger m. m. samt zaponerade tuber för konservindustrin",
            "contact": {
                "telegraph": "Tubfabriken, Kungsör",
                "phone": "Undisclosed",
                "postgiro": "76670"
            },
            "financials": {
                "capital": "137.500 kr"
            },
            "foundation_year": 1917,
            "board": [
                {
                    "name": "Berthold Orrvik",
                    "role": "disp."
                },
                {
                    "name": "M. Orrvik",
                    "role": "fru"
                },
                {
                    "name": "Åke Orrvik",
                    "role": "verkstadschef"
                }
            ],
            "director": "Berthold Orrvik",
            "managing_director": "Berthold Orrvik"
        },
        "4": {
            "name": "*Nordiska Värme- & Ventilations AB.",
            "location": "Göteborg",
            "business": "Bolaget äger mek. verkstad, plåtslageri och svetsningsverkstad samt driver entreprenadverksamhet i värme- och sanitetstekniska branschen",
            "contact": {
                "office": "3:dje Långg. 13",
                "telegraph": "Värmebolaget, Göteborg",
                "phone": "171045",
                "postgiro": "42160"
            },
            "financials": {
                "capital": "900.000 kr"
            },
            "foundation_year": 1903,
            "board": [
                {
                    "name": "C. Gunnar Laurenius",
                    "role": "dir."
                },
                {
                    "name": "B. Gunnar Laurenius",
                    "role": "ing."
                },
                {
                    "name": "Eric Levan",
                    "role": "civiling."
                }
            ],
            "director": "O. G. Laurenius",
            "managing_director": "O. G. Laurenius",
            "sales_manager": "Erik Gabrielsson"
        },
        "5": {
            "name": "*AB. Nordiska Yllefabriken",
            "location": "Norrköping",
            "business": "Ullspinneri, väveri, färgeri och appreturverk. Tillverkar klädes- och kamgarns-tyger samt cheviot. Varumärken: »Kungs-cheviot» o. »NYF»",
            "contact": {
                "telegraph": "Nordylle, Norrköping",
                "phone": [
                    "23149",
                    "22163"
                ],
                "postgiro": "11106"
            },
            "financials": {
                "capital": "100.000 kr"
            },
            "foundation_year": 1938,
            "director": "Christian Schnock",
            "managing_director": "Christian Schnock"
        },
        "6": {
            "name": "d. F. Nordlöf",
            "location": "Lerum",
            "business": "Skofabrik i Lerum (Älvsb. l.). Tillverkar herr- och damskodon. Specialitet: handarbetade skor",
            "contact": {
                "telegraph": "Nordlöf s, Lerum",
                "phone": [
                    "333",
                    "350",
                    "992"
                ],
                "postgiro": "40826"
            },
            "financials": {
                "capital": "Undisclosed"
            },
            "foundation_year": 1875,
            "director": "Sam. Bjerkander"
        },
        "7": {
            "name": "*Nordmalings Angsågs AB.",
            "location": "Nordmaling",
            "business": "Ångsåg och wallboardfabrik vid Rundvik, manufaktur- och kättingsmedja vid Olovsfors samt elektr. vattenkraftstation vid Leduåfors (samtl. i Västerb. l.). Tillverkar sågade trävaror, wallboard (masonite) för isolerings-, byggnads- och inredningsändamål, kätting och flottningsmiden, redskap för timmeravverkning samt distribuerar elektr. energi. Bolaget idkar jämväl jordbruk, skogshantering och kvarnrörelse",
            "contact": {
                "office": "Olovsfors Bruk",
                "telegraph": "Ångsågsbolaget, Nordmaling",
                "phone": "26",
                "postgiro": "62486"
            },
            "financials": {
                "capital": "Undisclosed"
            },
            "foundation_year": "Undisclosed",
            "director": "Undisclosed"
        }
    }
}