{
    "original": "Brandahl—Breitholtz\n\nVerkst. dir. o. disp.: Jonas Hult.\n\növering.: Uno Wiking-Johnsson.\n\nFörsäljn.-chef för järnavd.: intendent\nÅ. Wass.\n\nKamrer o. hontorschef: E. Willner.\n\nAvd.-chefer: för trävaruavd.: intendent\nC. Malmström; för skogsavd.: jägm. E.\nO. Edlund.\n\nGruving.: bergsing. Stellan Anestad.\n\nAB. Erik Brandahl &amp; Co., Mölndal.\n\nDamväskfabrik. Tillverkar damväskor.\n\nTelegr.-adr.: Brandahl, Mölndal.\nTelefon: Göteborg 272010. Postgiro: 42206.\n\n—\tAkt.-kap.: 60,000 kr. Antal\nindustriarb.: 110. Tillv.-värde pr år: 2,500,000 kr.\n\n—\tFirman etabl. 1924, bolag 1945.\n\nVerkst. dir.: Erik Brandahl.\n\n*\tBrandholmens Varv, Nyköping.\n\nSe Byggnads AB. Contractor,\nStockholm.\n\n*\tBrandredskapsaffären, E. Bergström\n\n&amp; Co., Stockholm.\n\nSe Allmänna Brandredskapsaffären\nAB., Stockholm.\n\n*Brandsmo Sågverk, Brandsmo.\n\nTillverkar sågade och hyvlade trävaror\nsamt lådor och lådämnen vid sågverk\nmed hyvleri i Brandsmo (Älvsb. l.),\nhopsättningsverkstad för lådor i\nHälsingborg (Hälsingborgs Emballagefabrik).\nSpecialitet: grönsakslådor.\n\nKontor: Brandsmo. Telefon:\nSven-ljunga 7211. Postgiro: 162637.\n\nAntal industriarb.: 15. Tillv.-värde pr\når: 200,000 kr. — Firman etabl. 1939\nunder namn Uddebo Träförädling, nuv.\nnamn 1944.\n\nÄgare o. chefer: fabr. Ernst Johansson\no. fabr. Arvid Jonasson.\n\n*\tBrandsnäs Såg och Tegelbruk,\n\nTranås.\n\nTillverkar sågade trävaror samt\nmur-och taktegel.\n\nKontor: Brandsnäs, Tranås. Telefon:\nTorpön 1. — Antal industriarb.: 20.\nTillv.-värde pr år: 125,000 kr. — Firman\netabl. 1879.\n\nÄgare o. chef: disp. Ernst Brandel.\n\n*\tBrandstad &amp; Monteen, Torshälla.\n\nSe Eminentverktyg, Brandstad &amp;\nMonteen, Torshälla.\n\nAB. Branteviks Gruvor, Stockholm.\n\nBryter flusspat vid fyndigheter i\nGladsax pr Järrestad och i Brantevik (båda i\nKristianst. l.).\n\nKontor: Stockholm, Kungsg. 28.\nTelefon: 230920. — Akt.-kap.: 5,000 kr.\nAntal industriarb.: 38. Prod.-värde pr år:\n150,000 kr. — Bolaget grundat 1941.\n\nChef: kamrer Carl W. Anderson.\n\nBrattefors Kalkbruks AB.,\n\nKinnemalma.\n\nKalkbruk vid Kinnemalma (Skarab.\n1.). Tillverkar kalk för industri- och\njordbruksändamål. Bolaget idkar\njämväl jordbruk.\n\nTelefon: Kinne-Kleva 58. Postgiro:\n8476. — Akt.-kap.: 50,000 kr. Antal\nindustriarb.: 15. Tillv.-värde pr år: 150,000\nkr. — Bolaget grundat 1918.\n\nStyrelse: dir. Knut Karlsson (ordf.),\nfru J. Beckman.\n\nFörvalt.: Eric Wermel.\n\nR. 0. Brauer &amp; Co., Kosta.\n\nSe Transjö Glasbruk, R. O. Brauer &amp;\nCo., Kosta.\n\nAB. Bredaryds Mek. Verkstad,\n\nBredaryd.\n\nMek. verkstad och snickerifabrik i Bre^\ndaryd (Jönköp. l.) samt mek. verkstad i\nVärnamo. Tillverkar lantbruksmaskiner\nsåsom tröskverk, halm- och bossfläktar,\ncirkelsågverk, klyvsågar för\nlådtillverk-ning, kapsågar, kantverk,\nvedklyvnings-maskiner, takspånshyvlar och spånfläktar\nsamt rattkälkar.\n\nTelefon: 2 o. 66. Postgiro: 162166.\n\nAkt.-kap.: 20,000 kr. Antal\nindustriarb.: 40. Tillv.-värde pr år: 550,000 kr.\n— Firman etabl. 1871 under namn Aug.\nLundeils Gjuteri &amp; Mek. Verkstad,\nom-bildad under nuv. namn 1933.\n\nStyrelse o. verkst. dir.: disp. Sten\nLundblad.\n\n* Bredsjö Bruk, Bredsjö.\n\nSe AB. Stjernfors-Ställdalen,\nStälldalen.\n\n^Breitholtz Tekn. Fabriks AB.,\n\nStockholm.\n\nTillverkar disk- och rengöringsmedel\nsamt putsmedel. Varumärken:\n»Eminent», »Eminé», »Tekå-zinkputs»,\n»Gloria-stålull», »Ultra-rapid» o. »Ultra-glans»,",
    "structured": {
        "firms": [
            {
                "name": "AB. Erik Brandahl & Co.",
                "location": "Mölndal",
                "business": "Damväskfabrik",
                "products": "Tillverkar damväskor",
                "contact": {
                    "office": "",
                    "phone": [
                        "Göteborg 272010"
                    ],
                    "postgiro": "42206",
                    "telegraph": "Brandahl, Mölndal"
                },
                "financials": {
                    "capital": "60,000 kr",
                    "employees": {
                        "industriarb": 110
                    },
                    "annual_turnover": "2,500,000 kr",
                    "annual_production_value": "2,500,000 kr"
                },
                "foundation_year": 1924,
                "corporation_year": 1945,
                "director": "Erik Brandahl"
            },
            {
                "name": "Brandsmo Sågverk",
                "location": "Brandsmo",
                "business": "Tillverkar sågade och hyvlade trävaror samt lådor och lådämnen",
                "products": "Specialitet: grönsakslådor",
                "contact": {
                    "office": "Brandsmo",
                    "phone": [
                        "Sven-ljunga 7211"
                    ],
                    "postgiro": "162637"
                },
                "financials": {
                    "employees": {
                        "industriarb": 15
                    },
                    "annual_turnover": "200,000 kr"
                },
                "foundation_year": 1939,
                "current_name_year": 1944,
                "owners": [
                    "fabr. Ernst Johansson",
                    "fabr. Arvid Jonasson"
                ]
            },
            {
                "name": "Brandsnäs Såg och Tegelbruk",
                "location": "Tranås",
                "business": "Tillverkar sågade trävaror samt mur-och taktegel",
                "contact": {
                    "office": "Brandsnäs, Tranås",
                    "phone": [
                        "Torpön 1"
                    ]
                },
                "financials": {
                    "employees": {
                        "industriarb": 20
                    },
                    "annual_turnover": "125,000 kr"
                },
                "foundation_year": 1879,
                "manager": "disp. Ernst Brandel"
            },
            {
                "name": "Brattefors Kalkbruks AB.",
                "location": "Kinnemalma",
                "business": "Tillverkar kalk för industri- och jordbruksändamål",
                "contact": {
                    "phone": [
                        "Kinne-Kleva 58"
                    ],
                    "postgiro": "8476"
                },
                "financials": {
                    "employees": {
                        "industriarb": 15
                    },
                    "annual_turnover": "150,000 kr"
                },
                "foundation_year": 1918,
                "owners": [
                    "dir. Knut Karlsson (ordf.)",
                    "fru J. Beckman"
                ],
                "manager": "Eric Wermel"
            },
            {
                "name": "AB. Bredaryds Mek. Verkstad",
                "location": "Bredaryd",
                "business": "Mek. verkstad och snickerifabrik",
                "products": "Tillverkar lantbruksmaskiner såsom tröskverk, halm- och bossfläktar",
                "contact": {
                    "phone": "2 o. 66",
                    "postgiro": "162166"
                },
                "financials": {
                    "capital": "20,000 kr",
                    "employees": {
                        "industriarb": 40
                    },
                    "annual_turnover": "550,000 kr"
                },
                "foundation_year": 1871,
                "current_name_year": 1933,
                "manager": "disp. Sten Lundblad"
            },
            {
                "name": "Breitholtz Tekn. Fabriks AB.",
                "location": "Stockholm",
                "business": "Tillverkar disk- och rengöringsmedel samt putsmedel",
                "products": "Varumärken: »Eminent», »Eminé», »Tekå-zinkputs», »Gloria-stålull», »Ultra-rapid» och »Ultra-glans»"
            }
        ]
    }
}