{
    "original": "Hakefjorden—-Hallarum\n\nHakefjordens Konservfabrik, Ivar\nOlausson &amp; Co., Klädesholmen.\n\nTillverkar sillkonserver, ansjovis m. m.\nvid fabrik å Klädesholmen (Göteb. o.\nBohus l.).\n\nTelegr.-adr.: Ivar, Klädesholmen.\nTelefon: 35 o. 55. Postgiro: 21361. — Antal\nindustriarb.: 25. — Firman etabl. 1923.\n\nÄgare o. chef: fabr. Ivar Olausson.\n\nAB. F. W. Haker &amp; Co., Skurup.\n\nGjuteri och mek. verkstad i Skurup\n(Malmöh. l.). Tillverkar som specialitet\nslåttermaskiner (märken: »Skurup» o.\n»Champion») samt cambridgevältar,\npo-tatisupptagare, gröpkvarnar, sädeskrossar\nm. m.\n\nTelegr.-adr.: Gjuteriet, Skurup.\nTelefon: »Hakers gjuteri». Repr. för\nslåttermaskiner i Sverige: Kooperativa\nFörbundet, Stockholm.\n\nAkt.-kap.: 500,000 kr. Antal\nindustriarb.; 115. Tillv.-värde pr år: 600,000 kr.\n— Firman etabl. 1892, bolag 1944.\n\nIndustrichef: ing. Sune Haker.\n\n*Halda AB., Svängsta.\n\nSpecialfabrik i Svängsta (Blekinge l.)\nför tillverkning av skrivmaskiner.\nVarumärke: »Halda».\n\nTelegr.-adr.: Halda, Karlshamn.\nTelefon: Karlshamn 400. Postgiro: 22475.\nEnsamförsäljare: för Sverige: AB.\nÅtvidabergs Industrier; för utlandet: AB.\nFacit (se dessa bolag).\n\nAkt.-kap.: 400,000 kr. Antal\nindustriarb.: 550. — Fabriken anlagd 1887, nuv.\nbolag stiftat 1927. Bolaget äges av AB.\nÅtvidabergs Industrier.\n\nStyrelse: disp. Elof Ericsson (ordf.),\ndir. R. Dencker, dir. Albert Engvall.\n\nPlatschef: ing. G. Freidenfelt.\n\nStf. platschef: civiling. John Vifot.\n\nVerkstads chef: ing. Arne O. Hermansen.\n\nKamrer: Karl-Gustav Johansson.\n\nInköpschef: Per Bergman.\n\n*Haldataxametern, Fabriks AB.,\n\nHalmstad.\n\nSe Verkstads AB. Haldex, Halmstad.\n*Haldens Färgeri AB., Fritsla.\n\nFärgeri, blekeri, appreturverk och\nfilmtryckeri i Fritsla (Älvsb. l.). Utför\nfärgning och brillantblekning av ullgarn,\nbomullsgarn och cellull i såväl hank som\nx-rullar samt färgning, tryckning\nblekning och appretering av gardiner,\ndrape-rier, möbeltyger och trikå.\n\nTelefon: Kinna 70062 o. 70110.\nPostgiro: 13468.\n\nAkt.-kap.: 400,000 kr. Antal\nindustriarb: 70. Prod.-värde pr år: 1,300,000 kr.\n\n—\tFirman etabl. på 1850-talet, bolag\n1946.\n\nStyrelse o. verkst. dir.; Holger\nÅkerlund.\n\nDisp.: Lennart Halden.\n\nDriftsingenjörer: Nils Frieberg, Jens\nE. Carlstedt o. Knut Ylander.\n\n* Hal la Textil AB., Överlida.\n\nGardinfabrik och färgeri i överlida\n(Älvsb. l.). Tillverkar som specialitet\ns. k. allmogegardiner.\n\nTelefon: 18. Postgiro: 13737. —\nAkt.-kap.: 130,000 kr. Antal industriarb.: 30.\nTillv.-värde pr år: 225,000 kr. — Firman\netabl. 1910, bolag 1921.\n\nStyrelse: disp. Fritz Sterner (ordf.),\nvävm. Bernhard Bengtsson, chefsassistent\nAlf Sterner.\n\nDisp.: Fritz Sterner.\n\nChefsassistent: Alf Sterner.\n\n*Hallabo Metallgjuteri, Gnosjö.\n\nMetallgjuteri och metallvarufabrik i\nGnosjö (Jönköp. l.). Tillverkar\nmetall-gjutgods, båtbeslag, skeppsklockor, elektr.\nmarinmateriel m. m.\n\nTelefon: 19. Postgiro: 6538. —\nArb.-antal: 11. Tillv.-värde pr år: 180,000 kr.\n\n—\tFirman etabl. 1907.\n\nÄgare: fabr. Algot Halidén o. fabr.\nOscar Uhnér.\n\nHallands läns linodlareförening\nu. p. a., Laholm.\n\nLinberedningsverk. Tillverkar lintåga\noch linblånor\n\nTelefon: 435. Postgiro: 173038.\nFör-säljn.-kontor: Riksförbundet Lin och\nHampa, Stockholm, Valhallavägen 132,\ntelefon: 602235.\n\nAndelskap.: 235,000 kr. Antal\nindustriarb.: 120. Tillv.-värde pr år: 2,500,000\nkr. — Föreningen bildad 1940.\n\nDisp.: Lars Ekberg.\n\nDriftsing.: Bernt Larson.\n\nHaliarums Tegelbruk,\n\nNättrabyhamn.\n\nTillverkar murtegel och dräneringsrör\nvid tegelbruk i Jämjöslätt (Blekinge l.).\nFirman driver även jordbruk.\n\nKontor: Nättrabyhamn. Telefon:\nNätt-raby 1 o. 211. Postgiro: 5476. — Antal",
    "structured": {
        "1": {
            "name": "Hakefjordens Konservfabrik, Ivar Olausson & Co.",
            "location": "Klädesholmen (Göteb. o. Bohus l.)",
            "business": "Tillverkar sillkonserver, ansjovis m. m. vid fabrik å Klädesholmen",
            "contact": {
                "telegraph": "Ivar, Klädesholmen",
                "phone": [
                    "35",
                    "55"
                ],
                "postgiro": "21361"
            },
            "financials": {
                "employees": {
                    "industriarb": 25
                },
                "foundation_year": 1923
            },
            "owners": [
                "Ivar Olausson"
            ]
        },
        "2": {
            "name": "AB. F. W. Haker & Co.",
            "location": "Skurup (Malmöh. l.)",
            "business": "Gjuteri och mek. verkstad",
            "products": "Tillverkar slåttermaskiner, cambridgevältar, po-tatisupptagare, gröpkvarnar, sädeskrossar m. m.",
            "contact": {
                "telegraph": "Gjuteriet, Skurup",
                "phone": "Hakers gjuteri",
                "sales_offices": [
                    {
                        "location": "Sverige",
                        "phone": "Kooperativa Förbundet, Stockholm"
                    }
                ],
                "postgiro": "Not available"
            },
            "financials": {
                "capital": "500,000 kr",
                "employees": {
                    "industriarb": 115
                },
                "annual_turnover": "600,000 kr",
                "corporation_year": 1944
            },
            "director": "Sune Haker"
        },
        "3": {
            "name": "Halda AB.",
            "location": "Svängsta (Blekinge l.)",
            "business": "Specialfabrik för tillverkning av skrivmaskiner",
            "products": "Varumärke: »Halda»",
            "contact": {
                "telegraph": "Halda, Karlshamn",
                "phone": "Karlshamn 400",
                "postgiro": "22475",
                "sales_offices": [
                    {
                        "location": "Sverige",
                        "phone": "AB. Åtvidabergs Industrier"
                    },
                    {
                        "location": "Utlandet",
                        "phone": "AB. Facit"
                    }
                ]
            },
            "financials": {
                "capital": "400,000 kr",
                "employees": {
                    "industriarb": 550
                },
                "corporation_year": 1927
            },
            "board": [
                {
                    "name": "Elof Ericsson",
                    "role": "ordf"
                },
                {
                    "name": "R. Dencker",
                    "role": "dir"
                },
                {
                    "name": "Albert Engvall",
                    "role": "dir"
                }
            ],
            "manager": "G. Freidenfelt"
        },
        "4": {
            "name": "Halendataxametern, Fabriks AB.",
            "location": "Halmstad",
            "contact": {
                "telegraph": "Not available",
                "phone": "Not available",
                "postgiro": "Not available"
            }
        },
        "5": {
            "name": "Haldens Färgeri AB.",
            "location": "Fritsla (Älvsb. l.)",
            "business": "Färgeri, blekeri, appreturverk och filmtryckeri",
            "products": "Utför färgning och brillantblekning av ullgarn, bomullsgarn och cellull i såväl hank som x-rullar samt färgning, tryckning blekning och appretering av gardiner, draperier, möbeltyger och trikå",
            "contact": {
                "phone": [
                    "Kinna 70062",
                    "70110"
                ],
                "postgiro": "13468"
            },
            "financials": {
                "capital": "400,000 kr",
                "employees": {
                    "industriarb": 70
                },
                "annual_turnover": "1,300,000 kr",
                "corporation_year": 1946
            },
            "board": [
                {
                    "name": "Holger Åkerlund",
                    "role": "styrelse o. verkst. dir"
                }
            ],
            "director": "Lennart Halden"
        },
        "6": {
            "name": "Halla Textil AB.",
            "location": "Överlida (Älvsb. l.)",
            "business": "Gardinfabrik och färgeri",
            "products": "Tillverkar s. k. allmogegardiner",
            "contact": {
                "phone": "18",
                "postgiro": "13737"
            },
            "financials": {
                "capital": "130,000 kr",
                "employees": {
                    "industriarb": 30
                },
                "annual_turnover": "225,000 kr",
                "corporation_year": 1921
            },
            "board": [
                {
                    "name": "Fritz Sterner",
                    "role": "disp and styrelse"
                },
                {
                    "name": "Bernhard Bengtsson",
                    "role": "vävm"
                },
                {
                    "name": "Alf Sterner",
                    "role": "chefsassistent"
                }
            ],
            "director": "Fritz Sterner"
        },
        "7": {
            "name": "Hallabo Metallgjuteri",
            "location": "Gnosjö (Jönköp. l.)",
            "business": "Metallgjuteri och metallvarufabrik",
            "products": "Tillverkar metallgjutgods, båtbeslag, skeppsklockor, elektr. marinmateriel m. m.",
            "contact": {
                "phone": "19",
                "postgiro": "6538"
            },
            "financials": {
                "employees": {
                    "antalarb": 11
                },
                "annual_production_value": "180,000 kr"
            },
            "owners": [
                "Algot Halidén",
                "Oscar Uhnér"
            ]
        },
        "8": {
            "name": "Hallands läns linodlareförening u. p. a.",
            "location": "Laholm",
            "business": "Linberedningsverk",
            "products": "Tillverkar lintåga och linblånor",
            "contact": {
                "phone": "435",
                "postgiro": "173038",
                "sales_offices": {
                    "location": "Stockholm",
                    "phone": "602235"
                }
            },
            "financials": {
                "capital": "235,000 kr",
                "employees": {
                    "industriarb": 120
                },
                "annual_turnover": "2,500,000 kr"
            },
            "board": [
                {
                    "name": "Lars Ekberg",
                    "role": "disp"
                }
            ],
            "director": "Bernt Larson"
        },
        "9": {
            "name": "Haliarums Tegelbruk",
            "location": "Nättrabyhamn (Jämjöslätt, Blekinge l.)",
            "business": "Tillverkar murtegel och dräneringsrör",
            "contact": {
                "office": "Nättrabyhamn",
                "phone": [
                    "Nätt-raby 1",
                    "211"
                ],
                "postgiro": "5476"
            }
        }
    }
}