{
    "original": "Ho hnens—Holmgruvan\n\n*Holmens Bruks och Fabriks AB.,\n\nNorrköping.\n\nPappersbruk, träsliperi,\nbomullsspinneri oeh -väveri i Norrköping,\npappersbruk, träsliperi och sulfitfabrik i\nHallstavik (Sthlms l.), sulfitfabrik i Loddby\n(Östergötl. l.).\n\n: Tillverkar tidningspapper, tändsticks-,\ntapet- och tryckpapper, sulfitcellulosa,\nträmassa samt vävnader och garn av\nbomull. Bolaget idkar jämväl jord- och\nskogsbruk samt sågverksrörelse.\n\nHuvudkontor: Norrköping.\nTelegr.-adr.: Holmens, Norrköping. Telefon:\n»Holmens Bruk». Postgiro: 22211.\nAvd.-kontor: Hallstavik och Loddby.\n\nAkt.-kap.: 34,560,000 kr. Antal\nindustriarb.: 3,000, varav vid textilavd. 1,700.\nÅrstillv.: 185,000 ton papper samt 1,400\nton bomullsgarn och 135,000 st.\nbomullsvävnader.\n\nFirman grundad 1854, nuv. bolag\nsamma år.\n\nStyrelse: bankdir. Ernst O:son\nHers-low (ordf.), bankir J. W. Fristedt, fil.\ndr Erik Kempe, disp. Chr. v. Sydow,\ngeneralkonsul Ragnar Söderberg.\n\nVerkst. dir.: Chr. v. Sydow.\n\nFörsäljn.-chef: dir. Sven Belfrage.\n\nChefshamrer: Axel Olsson.\n\nInköpschef: Einar Nilsson.\n\n*Holmens Mek. Verkstad, Torshälla.\nSe Nyby Bruks AB., Nybybruk.\n\n\"Holmens Möbelfabrik, Karl\nAndersson, Mjölby.\nTillverkar möbler.\n\nTelefon: 338. Postgiro: 71301. —\nArb.-antal: 3. — Firman etabl. 1919.\n\nÄgare o. chef: snickaremäst. Karl A.\nAndersson.\n\nHolmens Nya Verkstad,\n\nHärnösand.\n\nTillverkar maskiner för plywood- och\nwallboardfabriker samt\njärnkonstruktioner, utför fartygs- och motorreparationer\nsamt plåt- och smidesarbeten.\n\nTelefon: 2891. Postgiro: 28838. —\nAntal industriarb.: 30. Tillv.-värde pr år:\n200,000 kr. — Firman etabl. 1925.\n\nÄgare o. chef: fabr. A. Einar Nyman.\n\nDriftsing.: Olof Waessman.\n\n(Jfr annons nr 23.)\n\n*Holmérs Konfektionsfabrik, AB.,\n\nMjölby.\n\nTillverkar sportkläder, goss- och\nynglingakostymer, byxor, kjolar, jackor,\nbarnoveralls, blazer. Varumärke: »EH».\nTelefon: 721 o. 729. Postgiro: 90754.\n\n—\tAkt.-kap.: 200,000 kr. Antal\nindustriarb.: 75. Årstillv.: 70,000 st. styckeplagg.\n\n—\tFirman etabl. 1934, bolag 1945.\n\nStyrelse o. verkst. dir.: Edvin Holmér.\n\nHolmex, Konfektions AB.,\n\nTidaholm.\n\nSe Konfektions AB. Holmex,\nTidaholm.\n\nAB. Holmgrens Skofabrik,\n\nSkellefteå.\n\nTillverkar filt- och läderskodon vid\nfabrik i Skellefteå (Västerb. l.).\nVarumärken: »Pekka» o. »Medle-Pjäxan».\n\nTelefon: 11001. Postgiro: 65317. —\nAkt.-kap.: 37,000 kr. Antal industriarb.:\n18. Tillv.-värde pr år: 300.000 kr. —\nFirman etabl. 1897, bolag 1942.\n\nVerkst. dir.: Eric Palmheden.\n\n*Cunnar Holmgren,\nPapperspås-fabrik AB., Stockholm.\n\nTillverkar speeeri-, bageri-, frukt-,\nkaffe- och konfektpåsar samt\npergamyn-påsar.\n\nKontor: Agneg. 20—22. Telefon: 505577\no. 505560. Postgiro: 2624.\n\nAkt.-kap.: 150,000 kr. Antal\nindustriarb.: 15. Tillv.-värde pr år: 550,000 kr.\n— Firman etabl. 1926, bolag 1941.\n\nStyrelse: fabr. Gunnar Holmgren\n(ordf.), försäljn.-chef Lars-Åke Mörck,\nlöjtn. Sven-Gunnar Mörck.\n\nVerkst. dir.: vakant.\n\nKontorschef: Åke Rundqvist.\n\nAB. Holmgruvan, Bispberg.\n\nJärnmalmsgruvor i Långviks- och\nHolmgruvefälten m. fl. (Kopparb. l.).\nBryter manganhaltig järnmalm.\n\nKontor: Bispberg. Telefon: Säter 3. —\nAkt.-kap.: 250,000 kr. — Bolaget grundat\n1911. Driften f. n. nedlagd.\n\nStyrelse: dir. Nils Elf ström, dir. Erik\nG. Pehrsson, disp. Hj. Åselius.\n\nVerkst. dir.: Erik G. Pehrsson.\n\nPlatschef o. gruving.: bergsing. Gustaf\nLindroth.",
    "structured": {
        "1": {
            "name": "Holmens Bruks och Fabriks AB.",
            "location": "Norrköping",
            "business": "Pappersbruk, träsliperi, bomullsspinneri och väveri",
            "products": "Tidningspapper, tändsticks-, tapet- och tryckpapper, sulfitcellulosa, trämassa, samt vävnader och garn av bomull",
            "contact": {
                "office": "Norrköping",
                "phone": [
                    "Holmens Bruk"
                ],
                "postgiro": "22211",
                "head_office": "Norrköping",
                "sales_offices": [
                    {
                        "location": "Hallstavik",
                        "phone": ""
                    },
                    {
                        "location": "Loddby",
                        "phone": ""
                    }
                ],
                "telegraph": "Holmens, Norrköping"
            },
            "financials": {
                "capital": "34,560,000 kr",
                "employees": {
                    "industriarb": 3000,
                    "textilavd": 1700
                },
                "annual_turnover": "185,000 ton papper och 1,400 ton bomullsgarn och 135,000 st. bomullsvävnader"
            },
            "foundation_year": 1854,
            "current_name_year": 1854,
            "board": [
                {
                    "name": "Ernst O:son Hers-low",
                    "role": "bankdir."
                },
                {
                    "name": "J. W. Fristedt",
                    "role": "bankir"
                },
                {
                    "name": "Erik Kempe",
                    "role": "fil. dr"
                },
                {
                    "name": "Chr. v. Sydow",
                    "role": "disp."
                },
                {
                    "name": "Ragnar Söderberg",
                    "role": "generalkonsul"
                }
            ],
            "director": "Chr. v. Sydow",
            "sales_manager": "Sven Belfrage"
        },
        "2": {
            "name": "Holmens Möbelfabrik",
            "location": "Mjölby",
            "business": "Tillverkar möbler",
            "contact": {
                "phone": [
                    "338"
                ],
                "postgiro": "71301"
            },
            "foundation_year": 1919,
            "owner": "Karl A. Andersson"
        },
        "3": {
            "name": "Holmens Nya Verkstad",
            "location": "Härnösand",
            "business": "Tillverkar maskiner för plywood- och wallboardfabriker samt järnkonstruktioner, utför fartygs- och motorreparationer samt plåt- och smidesarbeten",
            "contact": {
                "phone": [
                    "2891"
                ],
                "postgiro": "28838"
            },
            "employees": 30,
            "annual_production_value": "200,000 kr",
            "foundation_year": 1925,
            "owner": "A. Einar Nyman"
        },
        "4": {
            "name": "Holmérs Konfektionsfabrik AB.",
            "location": "Mjölby",
            "business": "Tillverkar sportkläder, goss- och ynglingakostymer, byxor, kjolar, jackor, barnoveralls och blazer",
            "products": "Varumärke: EH",
            "contact": {
                "phone": [
                    "721",
                    "729"
                ],
                "postgiro": "90754"
            },
            "financials": {
                "capital": "200,000 kr",
                "employees": 75,
                "annual_production_value": "70,000 st. styckeplagg"
            },
            "foundation_year": 1934
        },
        "5": {
            "name": "Holmex, Konfektions AB.",
            "location": "Tidaholm",
            "business": "See Konfektions AB. Holmex, Tidaholm"
        },
        "6": {
            "name": "AB. Holmgrens Skofabrik",
            "location": "Skellefteå",
            "business": "Tillverkar filt- och läderskodon",
            "products": "Varumärken: Pekka och Medle-Pjäxan",
            "contact": {
                "phone": [
                    "11001"
                ],
                "postgiro": "65317"
            },
            "financials": {
                "capital": "37,000 kr",
                "employees": 18,
                "annual_production_value": "300,000 kr"
            },
            "foundation_year": 1897
        },
        "7": {
            "name": "Cunnar Holmgren, Papperspåsfabrik AB.",
            "location": "Stockholm",
            "business": "Tillverkar speceri-, bageri-, frukt-, kaffe- och konfektpåsar samt pergamyn-påsar",
            "contact": {
                "office": "Stockholm",
                "phone": [
                    "505577",
                    "505560"
                ],
                "postgiro": "2624"
            },
            "financials": {
                "capital": "150,000 kr",
                "employees": 15,
                "annual_production_value": "550,000 kr"
            },
            "foundation_year": 1926
        },
        "8": {
            "name": "AB. Holmgruvan",
            "location": "Bispberg",
            "business": "Järnmalmsgruvor i Långviks- och Holmgruvefälten m. fl.",
            "products": "Bryter manganhaltig järnmalm",
            "contact": {
                "office": "Bispberg",
                "phone": [
                    "Säter 3"
                ],
                "postgiro": "",
                "head_office": "Bispberg"
            },
            "financials": {
                "capital": "250,000 kr"
            },
            "foundation_year": 1911
        }
    }
}