{
    "original": "Nikame kaller—Nilsson\n\nKontor: Mårten Krakowg. 8.\nTelegr.-s&amp;dr.: Nihlmark, Göteborg. Telefon:\n»&gt;Nihlmarks Trä». Postgiro: 42700.\n\nAkt.-kap.: 500,000 kr. Antal\nindustriarb.: 40. — Bolaget grundat 1919.\n\nStyrelse: dir. Yngve Nihlmark (ordf.),\nciviling. Elof Frändberg, handl. Fritz\nKärrberg.\n\nVerkst. dir.: Yngve Nihlmark.\nKontorschef: C. O. Hallinger.\nFörsäljn.-chef: James Olofsson.\n\nAB. Ni kametal ler, Stockholm.\n\nMetallgjuteri. Tillverkar brons- och\n^itiagermetaller samt aluminium-,\nröd-gods- och mässingsgjutgods. Varumärke:\n»NIKA».\n\nKontor: Wollmar Yxkullsgatan 11—13.\nTelegr.-adr.: Nikametall, Stockholm.\nTelefon: 444635 o. 444637. Postgiro:\n4619. — Akt.-kap.: 50,000 kr. Arb.-antal:\n15. — Bolaget grundat 1927.\n\nStyrelse o. verkst. dir.: Nils Sievert.\n\n\"Nike, Domkraft AB., Eskilstuna.\nSe Domkraft AB. Nike, Eskilstuna.\n\n*Nilsson &amp; C:o, Textil AB.,\n\nSmålandsstenar.\n\nSe Textil AB. Nilsson &amp; C:o,\nSmålandsstenar.\n\nNilsson &amp; Söner, Stenhuggeri,\n\nVästervik.\n\nTillverkar gravvårdar,\nskulpturarbeten och granitplattor för beklädnad av\nfasader samt marmorarbeten.\n\nTelefon: 83. Postgiro: 33584. —\nAntal industriarb.: 20. Tillv.-värde pr år:\n4550,000 kr. — Firman etabl. 1921.\n\nChefer: fabr. K. Edvin Nilsson o.\nfabr. John A. Nilsson.\n\nNilssons Konfektionsfabrik,\n\nGullestorp.\n\nTillverkar herr- och gosskläder vid\nfabrik i Gullestorp (Älvsb. l.).\n\nKontor: Gullestorp. Telefon: Borås\n76019. Postgiro: 179127. — Antal\nindustriarb.: 40. Tillv.-värde pr år: 400,000\nikr. — Firman etabl. 1935.\n\nÄgare o. chef: fabr. Gösta Nilsson.\n\n* Nilssons Industrier, Bröderna,\n\nÅsljunga.\n\nSe Bröderna Nilssons Industrier,\nÅsljunga.\n\no\n\nC\n\n* Nilssons Möbelfabrik, Bröderna,\n\nMålilla station.\n\nSe Bröderna Nilssons Möbelfabrik,\nMålilla station.\n\n*AB. A. W. Nilsson &amp; Co., Sävsjö.\n\nTillverkar sandalsydda mans-, dam- och\nflickskodon samt sandaler vid fabrik i\nSävsjö (Jönköp. l.).\n\nTelefon: 169. Postgiro: 144584. —\nAkt.-kap.: 60,000 kr. Antal industriarb.:\n20. Tillv.-värde pr år: 200,000 kr. —\nBolaget grundat 1922.\n\nStyrelse: fabr. Axel W. Nilsson (ordf.),\nverkm. Oskar Nilsson, modellör Åke\nNilsson.\n\nVerkst. dir.: Axel W. Nilsson.\n\n*AB. A. W. Nilssons Fabriker,\n\nMalmö.\n\nBarnvagn- och stålmöbelfabrik.\nTillverkar barnvagnar, dockvagnar samt\nstålmöbler.\n\nKontor: Möllevångsg. 53. Telegr.-adr.:\nAwnilsson, Malmö. Telefon: 72200.\nPostgiro: 38576.\n\nAkt.-kap.: 559,000 kr. Antal\nindustriarb.-. 140. — Firman etabl. 1855, bolag\n1918.\n\nStyrelse: dir. Sven Malmberg, disp.\nErik Nilsson, fröken Maja Nilsson.\nVerkst. dir.: fröken Maja Nilsson.\nDisp.: Erik Nilsson.\n\nBror Nilssons Valsgravyranstalt,\n\nRydboholm.\n\nUtför gravering av valsar för\ntygtryckning samt för pappers-, tapet- och\nläderindustrier i Rydboholm (Älvsb. l.).\n\nTelegr.-adr.: Valsgravyr, Rydboholm.\nTelefon: Borås 90010. Postgiro: 88394.\n— Antal industriarb.: 40. — Firman\netabl. 1913.\n\nÄgare o. chef: fabr. Bror Nilsson.\n\n*Erik Nilssons Fabriks AB., Borås.\n\nTrikåfabrik. Tillverkar koftor,\njumpers, västar, slipovers m. m. av ylle.\n\nTelefon: 17535. Postgiro: 83555.\nRepr. i Stockholm: Edw. Derkert, Vasag.\n12, telefon: 101214.\n\nAkt.-kap.: 300,000 kr. Antal\nindustriarb.: 60, ävensom 100 hemarb.\nTillv.-värde pr år: 1,700,000 kr. — Firman\netabl. 1906, bolag 1928.\n\nStyrelse: disp. Bror H. Nilsson, disp.\nElis Nilsson, fröken Isa Nilsson.\n\nDisponenter: Bror H. Nilsson o. Elis\nNilsson.",
    "structured": {
        "firms": [
            {
                "name": "Nikame kaller—Nilsson",
                "location": "Mårten Krakowg. 8",
                "contact": {
                    "office": "Mårten Krakowg. 8",
                    "phone": [
                        "N/A"
                    ],
                    "postgiro": "42700",
                    "telegraph": "Nihlmark, Göteborg"
                },
                "financials": {
                    "capital": "500,000 kr",
                    "employees": {
                        "industriarb": 40
                    },
                    "foundation_year": 1919
                },
                "board": [
                    {
                        "name": "Yngve Nihlmark",
                        "role": "ordf."
                    },
                    {
                        "name": "Elof Frändberg",
                        "role": "civiling."
                    },
                    {
                        "name": "Fritz Kärrberg",
                        "role": "handl."
                    }
                ],
                "manager": "Yngve Nihlmark",
                "description": "Tillverkar brons- och mässingmetaller samt aluminium-, rödgods- och mässingsgjutgods."
            },
            {
                "name": "Ni kametal ler",
                "location": "Wollmar Yxkullsgatan 11—13",
                "contact": {
                    "office": "Wollmar Yxkullsgatan 11—13",
                    "phone": [
                        "444635",
                        "444637"
                    ],
                    "postgiro": "4619",
                    "telegraph": "Nikametall, Stockholm"
                },
                "financials": {
                    "capital": "50,000 kr",
                    "employees": {
                        "industriarb": 15
                    },
                    "foundation_year": 1927
                },
                "owners": [],
                "description": "Tillverkar brons- och mässingmetaller samt aluminium-, rödgods- och mässingsgjutgods."
            },
            {
                "name": "Nilsson & C:o, Textil AB.",
                "location": "Smålandsstenar",
                "description": "N/A"
            },
            {
                "name": "Nilsson & Söner, Stenhuggeri",
                "location": "Västervik",
                "contact": {
                    "phone": [
                        "83"
                    ],
                    "postgiro": "33584"
                },
                "financials": {
                    "employees": {
                        "industriarb": 20
                    },
                    "annual_production_value": "4550,000 kr"
                },
                "description": "Tillverkar gravvårdar, skulpturarbeten och granitplattor för beklädnad av fasader samt marmorarbeten."
            },
            {
                "name": "Nilssons Konfektionsfabrik",
                "location": "Gullestorp",
                "contact": {
                    "office": "Gullestorp",
                    "phone": [
                        "Borås 76019"
                    ],
                    "postgiro": "179127"
                },
                "financials": {
                    "employees": {
                        "industriarb": 40
                    },
                    "annual_production_value": "400,000 ikr"
                },
                "owner": "Gösta Nilsson",
                "description": "Tillverkar herr- och gosskläder vid fabrik i Gullestorp (Älvsb. l.)."
            },
            {
                "name": "Nilssons Möbelfabrik, Bröderna",
                "location": "Målilla station",
                "description": "N/A"
            },
            {
                "name": "AB. A. W. Nilsson & Co.",
                "location": "Sävsjö",
                "contact": {
                    "phone": [
                        "169"
                    ],
                    "postgiro": "144584"
                },
                "financials": {
                    "capital": "60,000 kr",
                    "employees": {
                        "industriarb": 20
                    },
                    "annual_production_value": "200,000 kr"
                },
                "owner": "fabr. Axel W. Nilsson",
                "description": "Tillverkar sandalsydda mans-, dam- och flickskodon samt sandaler vid fabrik i Sävsjö (Jönköp. l.)."
            },
            {
                "name": "AB. A. W. Nilssons Fabriker",
                "location": "Malmö",
                "contact": {
                    "office": "Möllevångsg. 53",
                    "phone": [
                        "72200"
                    ],
                    "postgiro": "38576"
                },
                "financials": {
                    "capital": "559,000 kr",
                    "employees": {
                        "industriarb": 140
                    }
                },
                "owners": [
                    "dir. Sven Malmberg",
                    "disp. Erik Nilsson",
                    "fröken Maja Nilsson"
                ],
                "manager": "fröken Maja Nilsson",
                "description": "Tillverkar barnvagnar, dockvagnar samt stålmöbler."
            },
            {
                "name": "Bror Nilssons Valsgravyranstalt",
                "location": "Rydboholm",
                "contact": {
                    "phone": [
                        "Borås 90010"
                    ],
                    "postgiro": "88394"
                },
                "financials": {
                    "employees": {
                        "industriarb": 40
                    }
                },
                "owner": "fabr. Bror Nilsson",
                "description": "Utför gravering av valsar för tygtryckning samt för pappers-, tapet- och läderindustrier i Rydboholm (Älvsb. l.)."
            },
            {
                "name": "Erik Nilssons Fabriks AB.",
                "location": "Borås",
                "contact": {
                    "phone": [
                        "17535"
                    ],
                    "postgiro": "83555"
                },
                "financials": {
                    "capital": "300,000 kr",
                    "employees": {
                        "industriarb": 60
                    }
                },
                "owner": "disp. Bror H. Nilsson, disp. Elis Nilsson, fröken Isa Nilsson",
                "description": "Tillverkar koftor, jumpers, västar, slipovers m. m. av ylle."
            }
        ]
    }
}