{
    "original": "Ignaberga—Industri\n\nhyvlade trävaror, 50,000 ton sulfit- och\nkonstsilkecellulosa, 35,000 ton\nsulfatcellulosa. . 30,000 ton våt, vit mek. trämassa,\n\n3,500,000 ltr sulfitsprit, 150,000 kg\nterpentin samt 6,000 ton järn och stål.\n\nBruket, grundat 1685, bolag 1876, äger\nStrömbacka Bruks AB. och Runemo\nSågverks AB.\n\nStyrelse: dir. Carl Trygger (ordf.),\nbankdir. H. Bexelius, dr Gunnar\nSundblad, generalkonsul Ragnar Söderberg.\n\nVerkst. dir. o. disp.: Gunnar\nSundblad.\n\nEkonomichef: Hans Westberg.\n\növeringenjörer: för\npappersmassefabrikerna: Gunnar Lindström; för\njärnverket: Nils Wahlberg.\n\nSåtj verks för v alt.: H. Palmborg.\n\nFörsäljn.-chef er: för trävaror: John\nJohansson; för pappersmassa samt järn o.\nstål: S. E. Norman.\n\nInköpschef: Einar Anderson.\n\nSkogschef: Rolf Ålund.\n\n*AB. Ignaberga Kalksten, Ignaberga.\n\nKalkbrott, kalkbruk,\nkalkgödningsfabri-ker och kalkstenshuggerier i Ignaberga\n(Kristianst. l.). Tillverkar murkalk,\njordbrukskalk, kalk för tekn. ändamål samt\nrå och huggen byggnadssten.\n\nTelegr.-adr.: Kalksten, Kristianstad.\nTelefon: Vinslöv 66 o. 132. Postgiro:\n30916.\n\nAkt.-kap.: 750,000 kr. Antal\nindustriarb.: 50. Tillv.-värde pr år: 500,000 kr.\n— Bolaget grundat 1914.\n\nStyrelse: frih. Carl Palmstierna\n(ordf.), arkitekt Leon Nilson, kamrer K.\nA. Sontag.\n\nVerkst. dir. o. disp.: Leon Nilson.\n\n*AB. liva, Huddinge.\n\nSe AB. Stockholms Strumpfabrik,\nHuddinge.\n\n* I lända Tegelbruk, Svartsjö.\n\nSe AB. Mälardalens Tegelbruk,\nStockholm.\n\n*AB. Imo-lndustri, Stockholm.\n\nMek. verkstad. Tillverkar pumpar,\nhydrauliska motorer och vattenmätare.\nVarumärke: »IMO».\n\nKontor: Lindhagensg. 132; postadr.:\nStockholm 30. Telegr.-adr.: Imoindustri,\nStockholm. Telefon: 520405. Postgiro:\n53845. Generalagenter för Sverige: AB.\nZander &amp; Ingeström, Stockholm, Fredsg.\n4, telefon: »Zander &amp; Ingeström».\n\nAkt.-kap.: 1,250,000 kr. Antal\nindustriarb.: 100. Tillv.-värde pr år: 2,000,000 kr.\n\n—\tFirman etabl. 1931.\n\nStyrelse: dir. Bengt Ingeström (ordf.),\nfrih. Gösta De Geer, dir. Hans Hylander,\nciviling. Carl Fr. Jacobsson, disp. Hans\nv. Kantzow, övering. Carl Montelius,\ngeneralkonsul Ragnar Söderberg.\n\nVerkst. dir.: Carl Fr. Jacobsson.\n\nEkonomidir.: frih. Gösta De Geer.\n\növering.: Carl Montelius.\n\nVerkstadschef: Torsten Montelius.\n\nKamrer: Gunnar Korsgren.\n\nIndustri AB., Elektriska, Stockholm.\n\nSe Elektriska Industri AB., Stockholm.\n\n\"Industri AB. Furuplywood,\n\nKristinehamn.\n\nTräförädlingsfabrik. Tillverkar\nkryss-faner (plywood) av furu och björk,\nlamellträ (blockboard) samt kombinationsskivan\n»Startex». Varumärken:\n»Stjärn-Ply-wood», »Stjärn-lamell» o. »Startex».\n\nTelegr.-adr. o. telefon: »Furuplywood»,\nKristinehamn. Postgiro: 81150.\n\nAkt.-kap.: 700,000 kr. Antal\nindustriarb.: 275. Årstillv.: 12,000 kbm plywood.\n\n—\tBolaget grundat 1927.\n\nStyrelse: disp. Lars Amundsen (ordf.),\nadv. Otto Lange, disp. Idor Raij.\n\nVerkst. dir.: Idor Raij.\n\nSkogschef: forstmäst. Ingmar\nHallström.\n\nIndustri AB. Halba, Stockholm.\n\nSe AB. Avant, Stockholm.\n\nIndustri AB. Kerba, Göteborg.\n\nDamkonfektionsfabrik. Tillverkar\nblusar, underkläder, klänningar, bysthållare\noch scarves\n\nKontor: S. Allég. 5. Telefon: 135686.\nPostgiro: 46924.\n\nAkt.-kap.: 50,000 kr. Antal\nindustriarb.: 80. Tillv.-värde pr år: 1,000,000 kr.\n\n—Bolaget grundat 1941.\n\nStyrelse o. verkst. dir.: Gösta Bjarne.\n\nIndustri AB. Kronan, Norrköping.\n\nKem.-tekn. fabriker i Norrköping och\ni Doverstorp (Östergötl. l.).^ Tillverkar\nsåpa, tvätt- och diskpulver, disktabletter,\nhandpasta, borroljeersättning, fernissa,\nbonvax, golvolja, vagnsmörja samt\nkali-rikt stenmjöl och rödfärg.\n\nTelegr.-adr.: Industrikronan,\nNorrköping. Telefon: 29685. Postgiro: 141030.\n\ni*",
    "structured": {
        "firms": [
            {
                "name": "AB. Ignaberga Kalksten, Ignaberga",
                "business": "Kalkbrott, kalkbruk, kalkgödningsfabriker och kalkstenshuggerier",
                "location": "Ignaberga, Kristianstad l.",
                "contact": {
                    "telegraph": "Kalksten, Kristianstad",
                    "phone": [
                        "Vinslöv 66",
                        "Vinslöv 132"
                    ],
                    "postgiro": "30916"
                },
                "financials": {
                    "capital": "750,000 kr",
                    "employees": 50,
                    "annual_turnover": "500,000 kr"
                },
                "foundation_year": 1914
            },
            {
                "name": "AB. Imo-Industri, Stockholm",
                "business": "Mek. verkstad. Tillverkar pumpar, hydrauliska motorer och vattenmätare. Varumärke: »IMO».",
                "location": "Stockholm",
                "contact": {
                    "office": "Lindhagensg. 132",
                    "telegraph": "Imoindustri, Stockholm",
                    "phone": "520405",
                    "postgiro": "53845"
                },
                "financials": {
                    "capital": "1,250,000 kr",
                    "employees": 100,
                    "annual_turnover": "2,000,000 kr"
                },
                "foundation_year": 1931
            },
            {
                "name": "Industri AB., Elektriska, Stockholm",
                "location": "Stockholm"
            },
            {
                "name": "Industri AB. Furuplywood, Kristinehamn",
                "business": "Träförädlingsfabrik. Tillverkar kryssfaner (plywood) av furu och björk, lamellträ (blockboard) samt kombinationsskivan »Startex». Varumärken: »Stjärn-Plywood», »Stjärn-lamell» o. »Startex».",
                "location": "Kristinehamn",
                "contact": {
                    "telegraph": "Furuplywood, Kristinehamn",
                    "phone": "Furuplywood",
                    "postgiro": "81150"
                },
                "financials": {
                    "capital": "700,000 kr",
                    "employees": 275
                },
                "foundation_year": 1927
            },
            {
                "name": "Industri AB. Halba, Stockholm",
                "location": "Stockholm"
            },
            {
                "name": "Industri AB. Kerba, Göteborg",
                "business": "Damkonfektionsfabrik. Tillverkar blusar, underkläder, klänningar, bysthållare och scarves",
                "location": "Göteborg",
                "contact": {
                    "office": "S. Allég. 5",
                    "phone": "135686",
                    "postgiro": "46924"
                },
                "financials": {
                    "capital": "50,000 kr",
                    "employees": 80,
                    "annual_turnover": "1,000,000 kr"
                },
                "foundation_year": 1941
            },
            {
                "name": "Industri AB. Kronan, Norrköping",
                "business": "Kem.-tekn. fabriker. Tillverkar såpa, tvätt- och diskpulver, disktabletter, handpasta, borroljeersättning, fernissa, bonvax, golvolja, vagnsmörja samt kalirikt stenmjöl och rödfärg.",
                "location": "Norrköping, Doverstorp (Östergötl. l.)",
                "contact": {
                    "telegraph": "Industrikronan, Norrköping",
                    "phone": "29685",
                    "postgiro": "141030"
                }
            }
        ]
    }
}