{
    "original": "Forss—Forssjö\n\nDriftsingenjörer: T. Apler, Frits\nIsaksson o. Oskar Wahlberg.\n\nFörsäljn.-chef er: för trävaror: intend.\nÅron Lindgren; för cellulosa: intend.\nUlf Hedberg.\n\nForss Mek. Verkstads AB.,\n\nVikingstad.\n\nTillverkar klöverfrönötare,\nspannmålsfläktar, spannmålselevatorer,\närtrens-ningsmaskiner samt utemjölkningsvagnar\nvid mek. verkstad och snickerifabrik i\nVikingstad (Östergötl. l.).\n\nTelefon: 38. Postgiro: 172245. -\nAkt.-kap.: 80,500 kr. Antal industriarb.: 10.\nTillv.-värde pr år: 150,000 kr. — Bolaget\ngrundat 1897.\n\nVerkst. dir.: David Andersson,\n(Linköping).\n\n*Forss &amp; Son AB., Stockholm.\n\nByggnadsentreprenörfirma för\nbostads-och affärshus, industribyggnader m. m.\n\nKontor: Riddarg. 46. Telefon: 610075.\nPostgiro: 150568. — Akt.-kap.: 205,200\nkr. — Firman etabl. 1920, bolag 1946.\n\nStyrelse: bankdir. John Bergström,\ning. Eric Forss, fru Maggie Forss.\n\nVerkst. dir.: Eric Forss.\n\nJ. A* Forss’ AB., Falköping.\n\nHattfabrik. Tillverkar herrhattar av\null och hår (märke: »Forss»-hatten) samt\nhalvfabrikat (stumpar) för damhattar.\n\nTelegr.-adr.: Forss, Falköping.\nTelefon: 37 o. 112. Postgiro: 22079. —\nAkt.-kap.: 666,000 kr. Antal industriarb.: 60.\n\n—\tFirman etabl. 1876.\n\nStyrelse: disp. Primus A. Forss (ordf.),\nfru E. Forss, disp. James A. P:son Forss,\nmed. dr Victor Kock, kapten B. T.\nRupert.\n\nVerkst. dir. o. disp.: P. A. Fors3.\nDisp.: J. A. P:son Forss.\nKontorschef: B. T. Rupert.\n\nAB. Forssa Läderfabrik,\n\nMadängsholm.\n\nTillverkar skofoderskinn m. m. vid\ngarveri i Madängsholm (Skarab. l.).\n\nKontor: Madängsholm. Telefon:\nTidaholm 59. Postgiro: 94202.\n\nAkt.-kap.: 50,000 kr. Antal\nindustriarb.: 25. Tillv.-värde pr år: 1,000,000 kr.\n\n—\tFirman etabl. 1880, bolag 1934.\nVerkst. dir. o. disp.: Ernst G. A. Brodin.\n\nii\n\n*AB. Forssa Tegelbruk, Borås.\n\nTegelbruk vid Forssa, Bollebygd (Älvsb.\n1.). Tillverkar murtegel, poröst tegel,\nporösa mellanväggsplattor,\nreveterings-tegel samt dräneringsrör.\n\nKontor: Borås; telefon: 10077.\nPostgiro: 99112.\n\nAkt.-kap.: 200,000 kr. Antal\nindustriarb.: 45. Årstillv.: 4 milj. st. tegelvaror.\n— Bolaget grundat 1917.\n\nStyrelse: bvggm. Oscar Ohlson (ordf.),\nv. konsul Knut A. Evers, disp. Nils\nFridén.\n\nVerkst. dir.: O. Ohlson.\n\nPlatschef: förv. Wilhelm Ohlin.\n\nForsse Träsliperl, Österforsa.\nSe Graninge verkens AB., Bollstabruk.\n\n*\tForssjö Bruk, Forssjöbruk.\n\nSågverk, hyvleri,\nvirkesimpregnerings-verk, murbruksfabrik, cementrörfabrik\noch elektricitetsverk vid Forssjö, elektr.\nvattenkraftverk vid Forssjö och\nErics-berg samt kalkbruk vid Lissnäs (samtl.\ni Södermanl. l.).\n\nTillverkar sågade och hyvlade\nträvaror, impregnerade stolpar, slip rar och\nannat virke samt cementrör, kalk och\nmurbruk; distribuerar elektr. energi.\nFirman driver även kvarnrörelse, jordbruk\noch skogshantering.\n\nTelegr.-adr.: Forssjöbruk, Katrineholm.\nTelefon: Forssjö 27 o. Katrineholm 1011.\nPostgiro: 75005.\n\nAntal industriarb.: 100. Årstillv.: 2,000\nstds trävaror och 10,000 ton kalk. —\nBruket anlagt på 1600-talet.\n\nÄgare: frih. Carl J. C:son Bonde.\n\nPlatschef: bruksförvalt. Axel Ekstrand.\n\nKontorschef: kassör Julius Larsson.\n\nShogschef: jägmäst. Carl Cedergren.\n\n*\tForssjö Nya Trävaru AB.,\n\nKatrineholm.\n\nSågverk, hyvleri och lådfabrik.\nTillverkar sågade och hyvlade trävaror,\nlåd-ämnen samt monteringsfärdiga trähus.\n\nTelegr.-adr.: Forssjö, Katrineholm.\nTelefon: »Träförädlingen». Postgiro: 87975;\n\nAkt.-kap.: 320,000 kr. Antal\nindustriarb.: 150. Tillv.-värde pr år: 1,500,000 kr.\n— Firman etabl. 1913.\n\nStyrelse: dir. A. Dahlander, fru G.\nDahlander, med. lic. Olarence Malmnäs,\narkitekt V. Malmnäs.\n\nVerkst. dir.: A. Dahlander.\n\n",
    "structured": {
        "1": {
            "name": "Forss Mek. Verkstads AB",
            "location": "Vikingstad",
            "business": "Tillverkning av klöverfrönötare, spannmålsfläktar, spannmålselevatorer, ärtrens-ningsmaskiner samt utemjölkningsvagnar",
            "contact": {
                "office": "Vikingstad (Östergötl. l.)",
                "phone": [
                    "38"
                ],
                "postgiro": "172245",
                "telegraph": "",
                "factory_office": "",
                "factory_phone": ""
            },
            "financials": {
                "capital": "80,500 kr",
                "employees": {
                    "industriarb": 10
                },
                "annual_turnover": "150,000 kr",
                "annual_production_value": "150,000 kr"
            },
            "foundation_year": 1897
        },
        "2": {
            "name": "Forss & Son AB",
            "location": "Stockholm",
            "business": "Byggnadsentreprenörfirma för bostads-och affärshus, industribyggnader m. m.",
            "contact": {
                "office": "Riddarg. 46",
                "phone": [
                    "610075"
                ],
                "postgiro": "150568",
                "telegraph": "",
                "head_office": ""
            },
            "financials": {
                "capital": "205,200 kr"
            },
            "foundation_year": 1920,
            "corporation_year": 1946,
            "board": [
                {
                    "name": "John Bergström",
                    "role": "bankdir."
                },
                {
                    "name": "Eric Forss",
                    "role": "ing."
                },
                {
                    "name": "Maggie Forss",
                    "role": "fru"
                }
            ],
            "director": "Eric Forss"
        },
        "3": {
            "name": "J. A* Forss’ AB",
            "location": "Falköping",
            "business": "Tillverkar herrhattar av ull och hår (märke: »Forss»-hatten) samt halvfabrikat (stumpar) för damhattar.",
            "contact": {
                "office": "Falköping",
                "phone": [
                    "37",
                    "112"
                ],
                "postgiro": "22079",
                "telegraph": "Forss",
                "head_office": ""
            },
            "financials": {
                "capital": "666,000 kr",
                "employees": {
                    "industriarb": 60
                }
            },
            "foundation_year": 1876,
            "board": [
                {
                    "name": "Primus A. Forss",
                    "role": "disp."
                },
                {
                    "name": "E. Forss",
                    "role": "fru"
                },
                {
                    "name": "James A. P:son Forss",
                    "role": "disp."
                },
                {
                    "name": "Victor Kock",
                    "role": "med. dr"
                },
                {
                    "name": "B. T. Rupert",
                    "role": "kapten"
                }
            ],
            "director": "P. A. Fors3",
            "sales_manager": "J. A. P:son Forss",
            "manager": "B. T. Rupert"
        },
        "4": {
            "name": "AB. Forssa Läderfabrik",
            "location": "Madängsholm",
            "business": "Tillverkar skofoderskinn m. m.",
            "contact": {
                "office": "Madängsholm",
                "phone": [
                    "Tidaholm 59"
                ],
                "postgiro": "94202",
                "telegraph": "",
                "head_office": ""
            },
            "financials": {
                "capital": "50,000 kr",
                "employees": {
                    "industriarb": 25
                },
                "annual_production_value": "1,000,000 kr"
            },
            "foundation_year": 1880,
            "corporation_year": 1934,
            "director": "Ernst G. A. Brodin"
        },
        "5": {
            "name": "AB. Forssa Tegelbruk",
            "location": "Borås",
            "business": "Tillverkar murtegel, poröst tegel, porösa mellanväggsplattor, reveterings-tegel samt dräneringsrör.",
            "contact": {
                "office": "Borås",
                "phone": [
                    "10077"
                ],
                "postgiro": "99112",
                "telegraph": "",
                "head_office": ""
            },
            "financials": {
                "capital": "200,000 kr",
                "employees": {
                    "industriarb": 45
                },
                "annual_production_value": "4 milj. st. tegelvaror"
            },
            "foundation_year": 1917,
            "board": [
                {
                    "name": "Oscar Ohlson",
                    "role": "bvggm."
                },
                {
                    "name": "Knut A. Evers",
                    "role": "v. konsul"
                },
                {
                    "name": "Nils Fridén",
                    "role": "disp."
                }
            ],
            "director": "O. Ohlson",
            "sales_manager": "Wilhelm Ohlin"
        },
        "6": {
            "name": "Forssjö Bruk",
            "location": "Forssjöbruk",
            "business": "Sågverk, hyvleri, virkesimpregnerings-verk, murbruksfabrik, cementrörfabrik och elektricitetsverk",
            "products": "Tillverkar sågade och hyvlade trävaror, impregnerade stolpar, slip rar och annat virke samt cementrör, kalk och murbruk; distribuerar elektr. energi",
            "contact": {
                "office": "Forssjö, Katrineholm",
                "phone": [
                    "Forssjö 27",
                    "Katrineholm 1011"
                ],
                "postgiro": "75005",
                "telegraph": "Forssjöbruk",
                "head_office": ""
            },
            "financials": {
                "employees": {
                    "industriarb": 100
                },
                "annual_turnover": "2,000 stds trävaror och 10,000 ton kalk"
            },
            "owner": "frih. Carl J. C:son Bonde",
            "manager": "Axel Ekstrand",
            "sales_manager": "Julius Larsson",
            "director": "Carl Cedergren"
        },
        "7": {
            "name": "Forssjö Nya Trävaru AB",
            "location": "Katrineholm",
            "business": "Sågverk, hyvleri och lådfabrik",
            "products": "Tillverkar sågade och hyvlade trävaror, låd-ämnen samt monteringsfärdiga trähus",
            "contact": {
                "office": "Katrineholm",
                "phone": [
                    "Träförädlingen"
                ],
                "postgiro": "87975",
                "telegraph": "Forssjö",
                "head_office": ""
            },
            "financials": {
                "capital": "320,000 kr",
                "employees": {
                    "industriarb": 150
                },
                "annual_production_value": "1,500,000 kr"
            },
            "foundation_year": 1913,
            "board": [
                {
                    "name": "A. Dahlander",
                    "role": "dir."
                },
                {
                    "name": "G. Dahlander",
                    "role": "fru"
                },
                {
                    "name": "Olarence Malmnäs",
                    "role": "med. lic."
                },
                {
                    "name": "V. Malmnäs",
                    "role": "arkitekt"
                }
            ],
            "director": "A. Dahlander"
        }
    }
}