{
    "original": "Eriksson\n\nStyrelse: övering. Arvid Stenberg,\nciviling. Ivar Stenberg.\n\nVerkst. dir.: Arvid Stenberg.\nDisp.: Ivar Stenberg.\nKamrer: Ivar Holm.\n(Jfr annons nr 47.)\n\n*Bror Eriksson, Byggnadsfirman,\n\nVisby.\n\nSe Byggnads AB. Bror Eriksson, Visby.\n\nBäcke Nils &amp; Erik Erikssons Eftr.,\n\nMalung.\n\nSkinnvarufabrik i Malung (Kopparb.\n1.). Tillverkar handskar, skinnkläder\nsamt motorekiperingsartiklar av skinn.\n\nTelegr.-adr.: Bäckebröder, Malung.\nTelefon: 41. Postgiro: 32899. — Antal\nindustriarb.: 25. Tillv.-värde pr år:\n350,000 kr. —Firman etabl. 1895.\n\nÄgare o. chefer: fabr. Bäcke Henry\nNilsson o. fabr. Bäcke Valfrid Nilsson.\n\nAB. C. O. Ericson &amp; Co., Malung.\n\nTillverkar handskar och skinnkläder vid\nfabriker i Malung (Kopparb. l.) och i\nMotala (Östergötl. l.).\n\nTelegr.-adr. o. telefon: »Ceo», Malung.\nPostgiro: 173217. — Akt.-kap.: 100,000\nkr. Antal industriarb.: 75. Tillv.-värde\npr år: 900,000 kr. — Firman etabl. 1911,\nbolag 1941.\n\nVerkst. dir.: fabr. ö. Oscar Ericson.\n\n*AB. C. Th. Ericson, Borlänge.\n\nMöss- och pälsvarufabrik i Borlänge\n(Kopparb. l.). Tillverkar mössor och\ntyghattar samt pälsvaror; specialitet:\nsportmössor.\n\nTelegr.-adr.: Hattimport, Borlänge.\nTelefon: »Cetehå». Postgiro: 21213. Repr.\ni Stockholm: AB. Per Sundström &amp; Co.,\nKungsg. 55, telefon: 118150. —\nAkt.-kap.: 500,000 kr. Antal industriarb.: 170.\n\n—\tFirman etabl. 1885, bolag 1921.\nStyrelse o. verkst. dir.: Nils G. Ericson.\nDisp.: Gustav Ericson.\nKontorschef: R. Svanström.\n\nE. Ericssons Kokkärlsfabrik AB.,\n\nHov sta.\n\nMetallfabrik i Hovsta (Örebro l.).\nTillverkar kokkärl och emballage samt\nlampskärmar (reflektorer) av aluminium.\nTelefon: Örebro 60041. Postgiro: 94805.\n\n—\tAkt.-kap.: 50,000 kr. Antal\nindustriarb.: 20. Tillv.-värde pr år: 500,000 kr.\n\n—\tFirman etabl. 1920, bolag 1946.\nVerkst. dir.: ing. Em. Ericsson.\n\n*Erlk Eriksson Junior\nVerktygsmaskiner, Torshälla.\n\nTillverkar verktygsmaskiner såsom\nsnabbsvarvar, vertikalborrmaskiner,\nplan-slipmaskiner, planfräsmaskiner, tryck*\noch metallsvarvar, pressar,\nspecialmaskiner samt maskinparallellskruvstycken.\n\nPost- o. båtadr.: Torshälla. Godsadr.:\nNybybruk. Telefon: Eskilstuna 55037 o.\n55136. Postgiro: 36463. — Antal\nindustriarb.: 65. Tillv.-värde pr år: 700,000\nkr. —Firman etabl. 1916.\n\nÄgare o. chef: civiling. Karl Erik\nEriksson.\n\nAB. Filip Eriksson, Norrköping.\n\nKlädesfabrik. Tillverkar vattolin och\ntagelduk.\n\nTelegr.-adr.: Filips, Norrköping.\nTelefon: 23360. Postgiro: 272308. —\nAkt.-kap.: 50,000 kr. Antal industriarb.: 30.\nTillv.-värde pr år: 1,000,000 kr. —\nFirman etabl. 1910, bolag 1929^\nVerkst. dir.: Carl Erik Eriksson.\n\n*AB. Gustaf Erikssons Metallfabrik,\n\nEskilstuna.\n\nSe AB. Gense, Eskilstuna.\n\nH. P. Erikssons Skinnvaru AB.,\n\nMalung.\n\nPäls- och skinnvarufabrik i Malung\n(Kopparb. l.). Tillverkar skinntröjor och\nvästar, damjackor, bilkläder, handskar,\nmilitär-, promenad- och dampälsar m. m.\n\nTelefon: 144 o. 145. Postgiro: 73193.\nAvd.-kontor: Stockholm, Regeringsg. 17,\ntelefon: 107779. — Akt.-kap.: 60,000 kr.\nAntal industriarb.: 40. — Firman etabl.\n1931.\n\nStyrelse o. chefer: fabr. Helmer\nJonsson (ordf.), fabr. Erik Persson\n(Stockholm) o. fabr. Erik G. Matsson.\n\n*AB. John Erikson &amp; Co., Borås.\n\nSyfabrik. Tillverkar pyjamas och\nskjortor. Varumärken: »Monitor», »Musketör»\no. »Jercoline».\n\nTelegr.-adr.: Jerco, Borås. Telefon:\n10237 o. 15022. Postgiro: 99799. —\nAkt.-kap.: 60,000 kr. Tillv.-värde pr år:\n1,600,000 kr. — Firman etabl. 1936.\nStyrelse o. disp.: John Erikson.\n\n*AB. Josef Eriksson, Uppsala.\n\nVelocipedfabrik. Tillverkar velocipeder\noch velocipeddelar. Varumärken: »Fram»\no. »Dixi».\n\n133*",
    "structured": {
        "firms": [
            {
                "name": "Bror Eriksson, Byggnadsfirman",
                "location": "Visby",
                "products": "Tillverkar handskar, skinnkläder samt motorekiperingsartiklar av skinn.",
                "contact": {
                    "telegraph": "Bäckebröder, Malung",
                    "phone": [
                        "41"
                    ],
                    "postgiro": "32899"
                },
                "financials": {
                    "employees": {
                        "industriarb": 25
                    },
                    "annual_turnover": "350,000 kr",
                    "annual_production_value": "350,000 kr"
                },
                "foundation_year": 1895,
                "owners": [
                    "fabr. Bäcke Henry Nilsson",
                    "fabr. Bäcke Valfrid Nilsson"
                ]
            },
            {
                "name": "AB. C. O. Ericson & Co.",
                "location": "Malung",
                "products": "Tillverkar handskar och skinnkläder vid fabriker i Malung och i Motala.",
                "contact": {
                    "telegraph": "Ceo, Malung",
                    "phone": [
                        "Ceo"
                    ],
                    "postgiro": "173217"
                },
                "financials": {
                    "employees": {
                        "industriarb": 75
                    },
                    "annual_turnover": "900,000 kr"
                },
                "foundation_year": 1911,
                "corporation_year": 1941,
                "board": [
                    {
                        "name": "Nils G. Ericson",
                        "role": "Verkst. dir."
                    },
                    {
                        "name": "Gustav Ericson",
                        "role": "Disp."
                    },
                    {
                        "name": "R. Svanström",
                        "role": "Kontorschef"
                    }
                ]
            },
            {
                "name": "AB. C. Th. Ericson",
                "location": "Borlänge",
                "products": "Tillverkar mössor, tyghattar samt pälsvaror; specialitet: sportmössor.",
                "contact": {
                    "telegraph": "Hattimport, Borlänge",
                    "phone": [
                        "Cetehå"
                    ],
                    "postgiro": "21213",
                    "factory_phone": "500,000 kr"
                },
                "financials": {
                    "capital": "500,000 kr",
                    "employees": {
                        "industriarb": 170
                    }
                },
                "foundation_year": 1885,
                "corporation_year": 1921,
                "director": "Nils G. Ericson",
                "board": [
                    {
                        "name": "Nils G. Ericson",
                        "role": "Verkst. dir."
                    },
                    {
                        "name": "Gustav Ericson",
                        "role": "Disp."
                    },
                    {
                        "name": "R. Svanström",
                        "role": "Kontorschef"
                    }
                ]
            },
            {
                "name": "E. Ericssons Kokkärlsfabrik AB.",
                "location": "Hovsta",
                "products": "Tillverkar kokkärl, emballage samt lampskärmar (reflektorer) av aluminium.",
                "contact": {
                    "phone": [
                        "Örebro 60041"
                    ],
                    "postgiro": "94805"
                },
                "financials": {
                    "capital": "50,000 kr",
                    "employees": {
                        "industriarb": 20
                    },
                    "annual_production_value": "500,000 kr"
                },
                "foundation_year": 1920,
                "corporation_year": 1946,
                "director": "ing. Em. Ericsson"
            },
            {
                "name": "Erlk Eriksson Junior Verktygsmaskiner",
                "location": "Torshälla",
                "products": "Tillverkar verktygsmaskiner såsom snabbsvarvar, vertikalborrmaskiner, plan-slipmaskiner, planfräsmaskiner, tryck- och metallsvarvar, pressar, specialmaskiner samt maskinparallellskruvstycken.",
                "contact": {
                    "postgiro": "36463"
                },
                "financials": {
                    "employees": {
                        "industriarb": 65
                    },
                    "annual_turnover": "700,000 kr"
                },
                "foundation_year": 1916,
                "manager": "civiling. Karl Erik Eriksson"
            },
            {
                "name": "AB. Filip Eriksson",
                "location": "Norrköping",
                "products": "Tillverkar vattolin och tagelduk.",
                "contact": {
                    "telegraph": "Filips, Norrköping",
                    "phone": [
                        "23360"
                    ],
                    "postgiro": "272308"
                },
                "financials": {
                    "capital": "50,000 kr",
                    "employees": {
                        "industriarb": 30
                    },
                    "annual_turnover": "1,000,000 kr"
                },
                "foundation_year": 1910,
                "corporation_year": 1929,
                "director": "Carl Erik Eriksson"
            },
            {
                "name": "H. P. Erikssons Skinnvaru AB.",
                "location": "Malung",
                "products": "Tillverkar skinntröjor, västar, damjackor, bilkläder, handskar, militär-, promenad- och dampälsar m. m.",
                "contact": {
                    "phone": [
                        "144",
                        "145"
                    ],
                    "postgiro": "73193"
                },
                "financials": {
                    "capital": "60,000 kr",
                    "employees": {
                        "industriarb": 40
                    }
                },
                "foundation_year": 1931,
                "owners": [
                    "fabr. Helmer Jonsson (ordf.)",
                    "fabr. Erik Persson (Stockholm)",
                    "fabr. Erik G. Matsson"
                ]
            },
            {
                "name": "AB. John Erikson & Co.",
                "location": "Borås",
                "products": "Tillverkar pyjamas och skjortor. Varumärken: Monitor, Musketör, Jercoline.",
                "contact": {
                    "telegraph": "Jerco, Borås",
                    "phone": [
                        "10237",
                        "15022"
                    ],
                    "postgiro": "99799"
                },
                "financials": {
                    "capital": "60,000 kr",
                    "annual_turnover": "1,600,000 kr"
                },
                "foundation_year": 1936,
                "director": "John Erikson"
            },
            {
                "name": "AB. Josef Eriksson",
                "location": "Uppsala",
                "products": "Tillverkar velocipeder och velocipeddelar. Varumärken: Fram, Dixi.",
                "contact": {
                    "phone": [
                        "133*"
                    ],
                    "postgiro": "133*"
                },
                "financials": {
                    "capital": "133*"
                },
                "foundation_year": 133
            }
        ]
    }
}