{
    "original": "Klosterbryggeriet—Knutsson\n\nStyrelse: disp. Sture Engström (ordf.),\nmajor Eric Engström, fru Greta Hy din,\nfru E. Yogel.\n\nVerkst. dir.: Sture Engström.\n(Jfr annons nr 92.)\n\n*AB. Klosterbryggeriet, Ystad.\n\nTillverkar malt, maltdrycker och\nläskedrycker.\n\nTelegr.-adr.: Klosterbryggeriet, Ystad.\nTelefon: 11 o. 444. Postgiro: 92318.\n\nAkt.-kap.: 400,000 kr. Antal\nindustriarb.: 25. Tillv.-värde pr år: 497,000 kr.\n\n—\tBryggeriet anlagt 1844.\n\nStyrelse: dir. L. W. Malmquist (ordf;),\ndisp. Carl-Gerhard Borgenstierna, dir.\nErik Malmquist.\n\nDisp.: Carl-Gerhard Borgenstierna.\nKamrer: H. Hennigor.\n\n*Th. Max Klusendick\nMetallvaru-fabrik, Alingsås.\nSe Tekaverken AB., Alingsås.\n\n*AB. Kläderfabriken, Nässjö.\n\nKonfektionsfabrik. Tillverkar\nherrkläder. Varumärke: »Rang».\n\nTelegr.-adr. o. telefon: Kläderfabriken,\nNässjö. Postgiro: 85777.\n\nAkt.-kap.: 900,000 kr. Antal\nindustriarb.: 420. Tillv.-värde pr år: 5,500,000 kr.\n\n—\tFirman etabl. 1909, nuv. bolagsform\n1920.\n\nStyrelse: civiling. Sten Westerberg\n(ordf.), ing. Wilhelm Johansson, dir.\nJonas Ljungqvist, dir. Oscar W.\nWestman.\n\nVerkst. dir.: Oscar W. Westman.\nKamrer: A. Herentz.\n\n* Kläderfabriken Stockholm,\n\nStockholm.\n\nTillverkar högtidskläder, herrkostymer,\npaletåer, ulstrar och trenchcoats samt\ndamdräkter, kappor och ulstrar.\nVarumärke: »Nordmandia».\n\nKontor: Norra Smedjeg. 28. Telefon:\n114487. Postgiro: 1733. — Antal\nindustriarb.: 22. Tillv.-värde pr år: 300,000\nkr. — Firman etabl. 1922 under namn\nNordiska Herrkonfektionen, nuv. namn\n1933.\n\nÄgare o. disp.: Rob. Apéria.\n\n*Knappindustri, Svensk, Strängnäs.\n\nSe AB. Svensk Knappindustri,\nSträngnäs.\n\n^Knislinge Skofabriks AB.,\n\nKnislinge.\n\nTillverkar skodon vid fabrik i\nKnislinge (Kristianst. l.). Varunamn:\n»Lejonskor».\n\nTelegr.-adr.: Skofabriken, Knislinge.\nTelefon: 31 o. 92. Postgiro: 23787.\nKontor i Stockholm: Drottningg. 73 A,\ntelefon: 219260.\n\nAkt.-kap.: 1,250,000 kr. Antal\nindustriarb.: 175. Tillv.-värde pr år: 2,500,000 kr.\n\n—\tBolaget grundat 1898.\n\nStyrelse: dir. Gust. Enocson, f.\nlands-hövd. Johan Nilsson, godsäg. Sam B.\nNorup, fru Eva Olsson, ing. Åke Sigfrid,\ngrossh. N. E. Stigner.\n\nVerkst. dir.: Gust. Enocson.\nDisp.: Johan W. Åkesson.\nKontorschef: J. Fägerstam.\n\n*AB. Knislinge Strumpfabrik,\n\nKnislinge.\n\nTillverkar damstrumpor vid fabrik i\nKnislinge (Kristianst. l.).\n\nTelefon: 125. Postgiro: 70272.\nFör-säljn.-kontor: Stockholm, Kungsg. 66.\nTelefon: 113670.\n\nAkt.-kap.: 300,000 kr. Antal\nindustriarb.: 100. Tillv.-värde pr år: 1,200,000 kr.\n\n—\tFirman etabl. 1930.\n\nStyrelse: dir. Gust. Enocson (ordf.),\nlantbr. Assar Erlansson (v. ordf.), disp.\nJoel Ekelund, dir. Joel Lindblom, disp.\nJohan W. Åkesson.\n\nVerkst. dir.: Joel Lindblom.\nDisp.: Joel Ekelund.\n\nKnutsilplåtar, N M. Malm,\n\nGrästorp.\n\nTillverkar knutsilar, knutsilcylindrar,\nknutsilplåtar för såväl plana som\nroterande silar, siebrar, presscylindrar samt\nmetallgjutgods vid mek. verkstad i\nGrästorp (Skarab. l.).\n\nTelefon: 106. Postgiro: 94633.\nRepresentant i Stockholm: AB. Lorentzen &amp;\nWettres Maskinaffär, Drottningg. 49,\ntelefon: 230625.\n\nArb.-antal: 8. Tillv.-värde pr år: 75,000\nkr. — Firman etabl. 1924.\n\nÄgare o. chef: fabr. N. M. Malm.\n\n*AB. Knutsson &amp; Berggren,\n\nJ önköping.\n\nByggnadsentreprenörfirma.\nTelefon: 925. Postgiro: 76403. —\nAkt.-kap.: 150,000 kr. Prod.-värde pr år:\n2,000,000 kr. — Firman etabl. 1907, bolag\n1945.",
    "structured": {
        "1": {
            "name": "Klosterbryggeriet—Knutsson",
            "location": "Ystad",
            "business": "Tillverkar malt, maltdrycker och läskedrycker.",
            "contact": {
                "telegraph": "Klosterbryggeriet, Ystad",
                "phone": [
                    "11",
                    "444"
                ],
                "postgiro": "92318"
            },
            "financials": {
                "capital": "400,000 kr",
                "employees": {
                    "industriarb": 25
                },
                "annual_turnover": "497,000 kr",
                "annual_production_value": "497,000 kr"
            },
            "foundation_year": 1844
        },
        "2": {
            "name": "Kläderfabriken, Nässjö",
            "location": "Nässjö",
            "business": "Konfektionsfabrik. Tillverkar herrkläder. Varumärke: Rang.",
            "contact": {
                "telegraph": "Kläderfabriken, Nässjö",
                "phone": "Kläderfabriken, Nässjö",
                "postgiro": "85777"
            },
            "financials": {
                "capital": "900,000 kr",
                "employees": {
                    "industriarb": 420
                },
                "annual_turnover": "5,500,000 kr",
                "annual_production_value": "5,500,000 kr"
            },
            "foundation_year": 1909,
            "corporation_year": 1920
        },
        "3": {
            "name": "Kläderfabriken Stockholm",
            "location": "Stockholm",
            "business": "Tillverkar högtidskläder, herrkostymer, paletåer, ulstrar och trenchcoats samt damdräkter, kappor och ulstrar. Varumärke: Nordmandia.",
            "contact": {
                "office": "Norra Smedjeg. 28",
                "phone": "114487",
                "postgiro": "1733"
            },
            "financials": {
                "employees": {
                    "industriarb": 22
                },
                "annual_turnover": "300,000 kr"
            },
            "current_name_year": 1933
        },
        "4": {
            "name": "Knislinge Skofabriks AB.",
            "location": "Knislinge",
            "business": "Tillverkar skodon vid fabrik i Knislinge. Varunamn: Lejonskor.",
            "contact": {
                "telegraph": "Skofabriken, Knislinge",
                "phone": [
                    "31",
                    "92"
                ],
                "postgiro": "23787"
            },
            "financials": {
                "capital": "1,250,000 kr",
                "employees": {
                    "industriarb": 175
                },
                "annual_turnover": "2,500,000 kr"
            },
            "foundation_year": 1898
        },
        "5": {
            "name": "Knislinge Strumpfabrik",
            "location": "Knislinge",
            "business": "Tillverkar damstrumpor vid fabrik i Knislinge (Kristianst. l.).",
            "contact": {
                "phone": "125",
                "postgiro": "70272"
            },
            "financials": {
                "capital": "300,000 kr",
                "employees": {
                    "industriarb": 100
                },
                "annual_turnover": "1,200,000 kr"
            },
            "foundation_year": 1930
        },
        "6": {
            "name": "Knutsilplåtar, N M. Malm",
            "location": "Grästorp",
            "business": "Tillverkar knutsilar, knutsilcylindrar, knutsilplåtar för såväl plana som roterande silar, siebrar, presscylindrar samt metallgjutgods vid mek. verkstad i Grästorp (Skarab. l.).",
            "contact": {
                "phone": "106",
                "postgiro": "94633"
            },
            "financials": {
                "employees": {
                    "Arb.-antal": 8
                },
                "annual_production_value": "75,000 kr"
            },
            "foundation_year": 1924
        },
        "7": {
            "name": "AB. Knutsson & Berggren",
            "location": "Jönköping",
            "business": "Byggnadsentreprenörfirma.",
            "contact": {
                "phone": "925",
                "postgiro": "76403"
            },
            "financials": {
                "capital": "150,000 kr",
                "annual_turnover": "2,000,000 kr"
            },
            "foundation_year": 1907,
            "corporation_year": 1945
        }
    }
}