{
    "original": "Tidan—Timmergata\n\nkugghjul, fabriks vagnar, lådor av olika\nslag, spinnkannor, packningar,\nfriktionsskivor in. m. av vulkanfiber. Varumärke:\n\n»Unica».\n\nTelegr.-adr. o. telefon: Unica,\nMariestad. Postgiro: 30636.\n\nAkt.-kap.: 600,000 kr. Antal\nindustriarb.: 350. Tillv.-värde pr år: 5,000,000 kr.\n\nBolaget, grundat 1898, äges av\nKatrine-fors AB.\n\nStyrelse: dir. Axel Brandin (ordf.),\ndir. Richard Hedlund, dir. Sten\nSundgren.\n\nVerkst. dir.: Richard Hedlund.\n\nBitr. dir.: Carl Oldby.\n\növering.: Bengt Forssell.\n\n(Jfr annons nr 38.)\n\nTidans Ullspinneri, F. o. S. Kämpe,\n\nUttervad.\n\nTillverkar ullgarner, filtar samt flock\noch vadd vid ullspinneri och väveri i\nUllervad (Skarab. l.).\n\nTelefon: 6. Postgiro: 70914. — Antal\nindustriarb.: 15. Tillv.-värde pr år:\n350,000 kr. — Firman etabl. 1891.\n\nÄgare o. chefer: fabr. Folke Kämpe o.\ning. Stig Kämpe.\n\n♦Tidans Yllefabrik, Tidan.\n\nSe Svenska Yllekoncernen, AB., Tidan.\n\n*J. H. Tidbeck AB., Stockholm.\n\nMetallduksväveri och\nmetalltrådvaru-fabrik. Tillverkar vävd och flätad\ntrådduk, rabitz och monjérduk, skyddsgaller\nför hissar, stängselnät, pressade\ntrådgaller, perforerade plåtar, transportband\nsamt alla slags metalltrådsarbeten.\n\nKontor: Malmgårdsv. 32. Telegr.-adr.:\nMetalltråd, Stockholm. Telefon: 433238,\n433251 o. 437223. Postgiro: 3174.\n\nAkt.-kap.: 450,000 kr. Antal\nindustriarb.: 50. Tillv.-värde pr år: 950,000 kr.\n— Firman etabl. 1840, bolag 1940.\n\nStyrelse: fabr. Herman Tidbeck (ordf.),\ndir.-assist. Gösta Tidbeck, disp. Sture\nTidbeck.\n\nVerkst. dir.: Herman Tidbeck.\n\nB. Tielman, Linköping.\n\nSe Bohus Varv, Knut Tiderman, Bohus.\n\nB. Tielman, Linköping.\n\nPappersindustri. Tillverkar\npappersbägare, tallrikar, -fat, kartonger,\npappersformar, tårt- och fatpapper, tårtbrickor,\nserviettväskor samt filtrerpapper.\n\nTelegr.-adr.: Betielman, Linköping.\nTelefon: 29730. Postgiro: 72702.\n\nAntal industriarb.: 20. Tillv.-värde pr\når: 700,000 kr. — Firman etabl. 1931.\n\nÄgare o. chef: dir. Bertil Tielman.\n\n*AB. Tika, Stockholm.\n\nTillverkar farmaceutiska ^ preparat vid\nfabrik i Hässleholm (Kristianst. l.).\nVarumärken: »Tika» o. »Rila».\n\nKontor: Flemingg. 75. Telegr.-adr.:\nTika, Stockholm. Telefon: 520330.\nPostgiro: 25309.\n\nAkt.-kap.: 233,000 kr. — Firman etabl.\n1926, bolag 1927.\n\nStyrelse: dir. Tore Grönwall (ordf.),\ndir. Gösta Lagergren, adv. Wilhelm\nMoberg.\n\nVerkst. dir.: Gösta Lagergren.\n\n*Tillberga Gjuter i, Johansson &amp; Co.,\n\nVästerås.\n\nTackjärnsgjuteri i Tillberga (Västmanl.\n1.). Tillverkar maskingjutgods.\nSpecialitet: grövre handformat gods.\n\nKontor: Västerås. Telefon: 30225.\nPostgiro: 75384. — Antal industriarb.: 50.\nÅrsprod.: 1,500 ton gjutgods. — Gjuteriet\nanlagt 1907.\n\nChef: ing. David Sjölander.\n\nTimander, Bröderna, Lastad.\n\nSe Bröderna Timander, Låstad.\n\n*Timber Trading Co. AB., Göteborg.\n\nSågverk och hyvleri. Tillverkar sågade\noch hyvlade trävaror. Bolaget driver även\nhandel med byggnadsmateriel.\n\nKontor: Linnég. 72—74. Telegr.-adr.:\nWoodgoods, Göteborg. Telefon: 174665.\nPostgiro: 41811.\n\nAkt.-kap.: 225,000 kr. Antal\nindustriarb.: 27. — Bolaget grundat 1926.\n\nStyrelse: dir. Ernst Falksten (ordf.),\ndir. Alfred Olsson.\n\nVerkst. dir.: E. Falksten.\n\nKontorschef: John H. Raftell.\n\n*Timmergata Tegelbruk,\n\nNorrköping.\n\nTillverkar murtegel vid tegelbruk i\nTimmergata, Krokek (Östergötl. l.).\n\nKontor, ägare o. ensamförsälj.: AB. P.\nJanson &amp; Co., Norrköping. Telegr.-adr.:\nJansons, Norrköping. Telefon: »P.\nJansons». Postgiro: 28334.\n\n■k",
    "structured": {
        "1": {
            "name": "Tidan—Timmergata",
            "location": "Mariestad",
            "business": "Tillverkning av kugghjul, fabrikvagnar, olika typer av lådor, spinnkannor, packningar och friktionsskivor av vulkanfiber.",
            "products": "Varumärke: »Unica».",
            "contact": {
                "office": "Unica, Mariestad",
                "phone": [
                    "Telefon: 30636"
                ],
                "postgiro": "30636",
                "head_office": "Unica, Mariestad",
                "telegraph": "Unica, Mariestad",
                "factory_office": "Unica, Mariestad",
                "factory_phone": "Unica, Mariestad"
            },
            "financials": {
                "capital": "600,000 kr",
                "employees": {
                    "industriarb": 350
                },
                "annual_turnover": "5,000,000 kr",
                "annual_production_value": "5,000,000 kr"
            },
            "foundation_year": 1898,
            "owners": [
                "Katrinefors AB"
            ],
            "board": [
                {
                    "name": "Axel Brandin",
                    "role": "ordf."
                },
                {
                    "name": "Richard Hedlund",
                    "role": "dir."
                },
                {
                    "name": "Sten Sundgren",
                    "role": "dir."
                }
            ],
            "director": "Richard Hedlund",
            "managing_director": "Richard Hedlund"
        },
        "2": {
            "name": "Tidans Ullspinneri, F. o. S. Kämpe",
            "location": "Uttervad",
            "business": "Tillverkning av ullgarner, filtar samt flock och vadd vid ullspinneri och väveri.",
            "contact": {
                "phone": [
                    "Telefon: 6"
                ],
                "postgiro": "70914"
            },
            "financials": {
                "employees": {
                    "industriarb": 15
                },
                "annual_turnover": "350,000 kr",
                "annual_production_value": "350,000 kr"
            },
            "foundation_year": 1891,
            "owners": [
                "Folke Kämpe",
                "Stig Kämpe"
            ]
        },
        "3": {
            "name": "J. H. Tidbeck AB., Stockholm",
            "business": "Tillverkning av metallduksväv och metalltrådvaror som vävda och flätade tråddukar, rabitz och monjérduk, skyddsgaller för hissar, stängselnät, pressade trådgaller, perforerade plåtar, transportband samt andra metalltrådsarbeten.",
            "contact": {
                "office": "Malmgårdsv. 32, Stockholm",
                "phone": [
                    "Telefon: 433238",
                    "Telefon: 433251",
                    "Telefon: 437223"
                ],
                "postgiro": "3174"
            },
            "financials": {
                "capital": "450,000 kr",
                "employees": {
                    "industriarb": 50
                },
                "annual_turnover": "950,000 kr"
            },
            "corporation_year": 1940,
            "board": [
                {
                    "name": "Herman Tidbeck",
                    "role": "ordf."
                },
                {
                    "name": "Gösta Tidbeck",
                    "role": "dir.-assist."
                },
                {
                    "name": "Sture Tidbeck",
                    "role": "disp."
                }
            ],
            "director": "Herman Tidbeck"
        },
        "4": {
            "name": "B. Tielman, Linköping",
            "business": "Tillverkning av pappersbägare, tallrikar, fat, kartonger, pappersformar, tårt- och fatpapper, tårtbrickor, serviettväskor samt filtrerpapper.",
            "contact": {
                "office": "Betielman, Linköping",
                "phone": [
                    "Telefon: 29730"
                ],
                "postgiro": "72702"
            },
            "financials": {
                "employees": {
                    "industriarb": 20
                },
                "annual_turnover": "700,000 kr"
            },
            "foundation_year": 1931,
            "director": "Bertil Tielman"
        },
        "5": {
            "name": "AB. Tika, Stockholm",
            "business": "Tillverkning av farmaceutiska preparat vid fabrik i Hässleholm (Kristianst. l.).",
            "products": "Varumärken: »Tika» o. »Rila».",
            "contact": {
                "office": "Flemingg. 75, Stockholm",
                "phone": [
                    "Telefon: 520330"
                ],
                "postgiro": "25309"
            },
            "financials": {
                "capital": "233,000 kr"
            },
            "corporation_year": 1927,
            "board": [
                {
                    "name": "Tore Grönwall",
                    "role": "ordf."
                },
                {
                    "name": "Gösta Lagergren",
                    "role": "dir."
                },
                {
                    "name": "Wilhelm Moberg",
                    "role": "adv."
                }
            ],
            "director": "Gösta Lagergren"
        },
        "6": {
            "name": "Tillberga Gjuter i, Johansson & Co.",
            "location": "Västerås",
            "business": "Tackjärnsgjuteri i Tillberga (Västmanl. l.). Tillverkar maskingjutgods. Specialitet: grövre handformat gods.",
            "contact": {
                "office": "Tillberga, Västerås",
                "phone": [
                    "Telefon: 30225"
                ],
                "postgiro": "75384"
            },
            "financials": {
                "employees": {
                    "industriarb": 50
                },
                "annual_production_value": "1,500 ton gjutgods"
            },
            "director": "David Sjölander"
        },
        "7": {
            "name": "Timander, Bröderna, Lastad"
        },
        "8": {
            "name": "Timber Trading Co. AB., Göteborg",
            "business": "Sågverk och hyvleri. Tillverkar sågade och hyvlade trävaror. Bolaget driver även handel med byggnadsmateriel.",
            "contact": {
                "office": "Linnég. 72—74, Göteborg",
                "phone": [
                    "Telefon: 174665"
                ],
                "postgiro": "41811"
            },
            "financials": {
                "capital": "225,000 kr",
                "employees": {
                    "industriarb": 27
                }
            },
            "corporation_year": 1926,
            "board": [
                {
                    "name": "Ernst Falksten",
                    "role": "ordf."
                },
                {
                    "name": "Alfred Olsson",
                    "role": "dir."
                }
            ],
            "director": "E. Falksten",
            "manager": "John H. Raftell"
        },
        "9": {
            "name": "Timmergata Tegelbruk, Norrköping",
            "business": "Tillverkning av murtegel vid tegelbruk i Timmergata, Krokek (Östergötl. l.).",
            "contact": {
                "office": "AB. P. Janson & Co., Norrköping",
                "phone": [
                    "Telefon: »P. Jansons»"
                ],
                "postgiro": "28334"
            }
        }
    }
}