{
    "original": "Hilloverken—Hjo\n\nAB. Hilloverken, Värnamo.\n\nMek. verkstäder i Hillerstorp och\nVärnamo (båda i Jönköp. l.). Tillverkar som\nspecialitet hänglås.\n\nKontor: Värnamo. Telefon: 11295—96.\nPostgiro: 71236. — Akt.-kap.: 50,000 kr.\nAntal industriarb.: 25. — Bolaget\ngrundat 1946.\n\nVerkst. dir.: Olof Backnäs.\n\n\"Hillringsbergs Bruk, Olava.\n\nSe Billeruds AB., Säffle.\n\n\"AB. Hisingstads Snickerifabrik,\n\nGöteborg.\n\nTillverkar möbler, båt-, bank- och\naffärsinredningar, fotografikameror i trä\nsamt trätryckvalsar m. m. vid\nmöbelfabrik i Partille (Göteb. o. Bohus l.).\n\nKontor: Kungsg. 7 A. Telefon: 136598.\nPostgiro: 48872. — Akt.-kap.: 44,300 kr.\nAntal industriarb.: 13. — Bolaget\ngrundat 1905.\n\nStyrelse: fabr. Ernst F. Granath (ordf.),\nverkm. Erik Granath, verkm. Gustav\nGranath, köpman Sture Granath.\n\nVerkst. dir.: Ernst F. Granath.\n\n\"Hissmofors AB., Krokom.\n\nSulfitfabrik, sulfitspritfabrik, sågverk\noch elektr. vattenkraftstation vid\nHiss-mofors, Krokom (Jämtl. l.). Tillverkar\nsulfitcellulosa, sulfitsprit samt sågade och\nhyvlade trävaror samt distribuerar elektr.\nenergi.\t’\n\nTelegr.-adr.: Hissmofors, Krokom.\nTelefon: 61. Postgiro: 9977.\n\nAkt.-kap.: 4,290,000 kr. Antal\nindustriarb.: 235. Årstillv.: 24,000 ton\nsulfitcellulosa, 4,000 stds sågade o. hyvlade\nträvaror. — Bolaget grundat 1894.\n\nStyrelse: dir. P. G. Palmquist (ordf.),\ndir. Carl Sundelin (v. ordf.), ing. S.\nNo-bell, övering. J. Strindlund, dir. Sjune\nSvensson.\n\nVerkst. dir. o. disp.: Sjune Svensson.\n\nKamrer: K. A. Kilander.\n\n\"Oskar Hjalmarsson, Möbelfabrik,\n\nSiringe.\n\nSe AB. Karl Andersson &amp; Söner,\nHuskvarna.\n\nHjeltevads Nya Träförädlings AB.,\n\nHjältevad.\n\nSnickerifabrik, sågverk och hyvleri i\nHjältevad (Jönköp. l.). Tillverkar\nbyggnadssnickerier, sågade och hyvlade träva-\n\nror; utför dörrar och fönster av svensk\nstandardtyp. Bolaget idkar jämväl\njord-och skogsbruk.\n\nTelegr.-adr.: Träförädlingen,\nHjältevad. Telefon: 1. Postgiro: 91811.\n\nAkt.-kap.: 125,000 kr. Antal\nindustriarb.: 46. Årstillv.: 2,100 stds sågade o.\n800 stds hyvlade trävaror. — Bolaget\ngrundat 1906.\n\nStyrelse: disp. C. Christog Carlsson\n(ordf.), förvalt. Carl-Åke Carlsson,\nhem-mansäg. Karl August Johansson, fru M.\nLeisner, fru A.-G. Lundell.\n\nDisp.: C. O. Carlsson.\n\nKontorschef: F. Zackrisson.\n\n\"Hjerpens Sulfitfabrik, Järpen.\n\nSe AB. Tegefors Verk, Järpen.\n\n*Hjo Bryggeri, Hjo.\n\nSkattepliktigt bryggeri med\nvattenfabrik. Tillverkar malt- och läskedrycker.\n\nTelefon: 80. — Antal industriarb.: 18.\nTillv.-värde pr år: 425,000 kr. —\nBryggeriet anlagt 1875, nuv. firma etabl. 1908.\n\nÄgare o. chef: dir. Per A. Forssell.\n\n\"Hjo Mek. Verkstad &amp; Elektricitets,\nverk, K. o. W. Smedberg, Hjo.\n\nTillverkar radiatorer, transportabla\nlyftanordningar,\nplåtbearbetningsmaski-ner, branddörrar, stålmellanväggar och\nstålfönster; framställer syrgas och\ndistribuerar elektr. energi.\n\nTelefon: »Hjo mekaniska». Postgiro:\n33229. Antal industriarb.: 145. — Firman\netabl. 1889.\n\nDisp.: Åke Lindholm.\n\nChefsassist.: Bo Lindholm.\n\nVerkstadschef: ing. Gösta Ågren.\n\nHjo Snickerifabrik AB., Hjo.\n\nTillverkar sågade och hyvlade trävaror.\nFirman driver även handel med\nbygg-nadsmateriel.\n\nTelefon: 600—03. Postgiro: 37358. —\nAkt.-kap.: 150,000 kr. Antal industriarb.:\n25. — Firman etabl. 1906, bolag 1946.\n\nVerkst. dir.: Gustaf Törling.\n\n*AB. Hjo Söm- &amp; Broddfabrik,\n\nHjo.\n\nSmides- och mek. verkstad. Tillverkar\nbyggnadsbeslag och pressartiklar.\nSpecialiteter: skåpreglar och lådhandtag\n(märke: »Hio»), skyddsglasögon,\nskärpspännen, trycklås, portmonnäbyglar m. m.",
    "structured": {
        "1": {
            "name": "Hilloverken—Hjo",
            "location": "AB. Hilloverken, Värnamo.",
            "business": "Mek. verkstäder i Hillerstorp och Värnamo (båda i Jönköp. l.). Tillverkar som specialitet hänglås.",
            "contact": {
                "office": "Värnamo",
                "phone": [
                    "11295",
                    "96"
                ],
                "postgiro": "71236"
            },
            "financials": {
                "capital": "50,000 kr",
                "employees": {
                    "industriarb": 25
                }
            },
            "foundation_year": 1946,
            "director": "Olof Backnäs"
        },
        "2": {
            "name": "AB. Hisingstads Snickerifabrik",
            "location": "Göteborg",
            "business": "Tillverkar möbler, båt-, bank- och affärsinredningar, fotografikameror i trä samt trätryckvalsar m. m. vid möbelfabrik i Partille (Göteb. o. Bohus l.).",
            "contact": {
                "office": "Kungsg. 7 A",
                "phone": "136598",
                "postgiro": "48872"
            },
            "financials": {
                "capital": "44,300 kr",
                "employees": {
                    "industriarb": 13
                }
            },
            "foundation_year": 1905,
            "board": [
                {
                    "name": "fabr. Ernst F. Granath",
                    "role": "ordf."
                },
                {
                    "name": "verkm. Erik Granath",
                    "role": ""
                },
                {
                    "name": "verkm. Gustav Granath",
                    "role": ""
                },
                {
                    "name": "köpman Sture Granath",
                    "role": ""
                }
            ],
            "director": "Ernst F. Granath"
        },
        "3": {
            "name": "Hissmofors AB.",
            "location": "Krokom",
            "business": "Sulfitfabrik, sulfitspritfabrik, sågverk och elektr. vattenkraftstation vid Hiss-mofors, Krokom (Jämtl. l.). Tillverkar sulfitcellulosa, sulfitsprit samt sågade och hyvlade trävaror samt distribuerar elektr. energi.",
            "contact": {
                "telegraph": "Hissmofors, Krokom",
                "phone": "61",
                "postgiro": "9977"
            },
            "financials": {
                "capital": "4,290,000 kr",
                "employees": {
                    "industriarb": 235
                },
                "annual_turnover": "24,000 ton sulfitcellulosa, 4,000 stds sågade o. hyvlade trävaror"
            },
            "foundation_year": 1894,
            "board": [
                {
                    "name": "dir. P. G. Palmquist",
                    "role": "ordf."
                },
                {
                    "name": "dir. Carl Sundelin",
                    "role": "v. ordf."
                },
                {
                    "name": "ing. S. No-bell",
                    "role": ""
                },
                {
                    "name": "övering. J. Strindlund",
                    "role": ""
                },
                {
                    "name": "dir. Sjune Svensson",
                    "role": ""
                }
            ],
            "director": "Sjune Svensson",
            "manager": "K. A. Kilander"
        },
        "4": {
            "name": "Hjeltevads Nya Träförädlings AB.",
            "location": "Hjältevad",
            "business": "Snickerifabrik, sågverk och hyvleri i Hjältevad (Jönköp. l.). Tillverkar byggnadssnickerier, sågade och hyvlade trävaror; utför dörrar och fönster av svensk standardtyp. Bolaget idkar jämväl jord-och skogsbruk.",
            "contact": {
                "telegraph": "Träförädlingen, Hjältevad",
                "phone": "1",
                "postgiro": "91811"
            },
            "financials": {
                "capital": "125,000 kr",
                "employees": {
                    "industriarb": 46
                },
                "annual_production_value": "2,100 stds sågade o. 800 stds hyvlade trävaror"
            },
            "foundation_year": 1906,
            "board": [
                {
                    "name": "disp. C. Christog Carlsson",
                    "role": "ordf."
                },
                {
                    "name": "förvalt. Carl-Åke Carlsson",
                    "role": ""
                },
                {
                    "name": "hemmansäg. Karl August Johansson",
                    "role": ""
                },
                {
                    "name": "fru M. Leisner",
                    "role": ""
                },
                {
                    "name": "fru A.-G. Lundell",
                    "role": ""
                }
            ],
            "director": "C. O. Carlsson",
            "manager": "F. Zackrisson"
        },
        "5": {
            "name": "Hjo Bryggeri",
            "location": "Hjo",
            "business": "Skattepliktigt bryggeri med vattenfabrik. Tillverkar malt- och läskedrycker.",
            "contact": {
                "phone": "80"
            },
            "financials": {
                "employees": {
                    "industriarb": 18
                },
                "annual_turnover": "425,000 kr"
            },
            "foundation_year": 1908,
            "director": "dir. Per A. Forssell"
        },
        "6": {
            "name": "Hjo Mek. Verkstad & Elektricitetsverk, K. o. W. Smedberg",
            "location": "Hjo",
            "business": "Tillverkar radiatorer, transportabla lyftanordningar, plåtbearbetningsmaski-ner, branddörrar, stålmellanväggar och stålfönster; framställer syrgas och distribuerar elektr. energi.",
            "contact": {
                "telegraph": "Hjo mekaniska",
                "postgiro": "33229"
            },
            "financials": {
                "employees": {
                    "industriarb": 145
                }
            },
            "foundation_year": 1889,
            "director": "Åke Lindholm",
            "manager": "Bo Lindholm",
            "sales_manager": "ing. Gösta Ågren"
        },
        "7": {
            "name": "Hjo Snickerifabrik AB.",
            "location": "Hjo",
            "business": "Tillverkar sågade och hyvlade trävaror. Firman driver även handel med bygg-nadsmateriel.",
            "contact": {
                "phone": [
                    "600",
                    "03"
                ],
                "postgiro": "37358"
            },
            "financials": {
                "capital": "150,000 kr",
                "employees": {
                    "industriarb": 25
                }
            },
            "foundation_year": 1946,
            "director": "Gustaf Törling"
        },
        "8": {
            "name": "AB. Hjo Söm- & Broddfabrik",
            "location": "Hjo",
            "business": "Smides- och mek. verkstad. Tillverkar byggnadsbeslag och pressartiklar. Specialiteter: skåpreglar och lådhandtag (märke: »Hio»), skyddsglasögon, skärpspännen, trycklås, portmonnäbyglar m. m."
        }
    }
}