{
    "original": "Mark—Marstrand\n\n*AB. Marks Skofabrik, Örebro.\n\nTillverkar finare skodon. Varumärke:\n»Marks».\n\nEnsamförsälj.: AB. A. P. Hallqvist,\nÖrebro. Telefon: 10582. Postgiro: 20794.\n\nAkt.-kap.: 426,000 kr. Antal\nindustriarb.: 100. Tillv.-värde pr år: 1,500,000 kr.\n\n—\tBolaget grundat 1897.\n\nStyrelse: grossh. A. P. Hallqvist\n(ordf.), köpman David Hallqvist, disp.\nÅke Hallqvist.\n\nVerJcst. dir.: A. P. Hallqvist.\n\nDisp.: Åke Hallqvist.\n\n*AB. Marks Tegelbruk, Örebro.\n\nTillverkar mur- och taktegel samt\ndräneringsrör.\n\nTelefon: 10601. Postgiro: 161045. —\nAkt.-kap.: 190,00 kr. Antal industriarb.:\n40. Tillv.-värde pr år: 495,000 kr. —\nBolaget grundat 1902.\n\nVerJcst. dir.: Arvid Adamson.\n\nTegelmästare: Erik J. Larsson.\n\n*Marks Textilfabrik, Kinna.\n\nMek. jacquardväveri vid Häggåstrand,\nKinna (Älvsb. l.). Tillverkar borddukar,\nottomantäcken, sängöverkast, draperi-,\nmöbel- och allmogetyger m. m.\n\nTelegr.-adr.: Textil, Kinna. Telefon:\n10735, 10077 o. 10125. Postgiro: 31793.\n\nAntal industriarb.: 65. Tiljv.-värde pr\når: 1,200,000 kr. — Firman etabl. 1908.\n\nÄgare: fabr. Carl Ad. Carlson o. Gust.\nArv. Gadhs sterbhus.\n\nChef: Carl Ad. Carlson.\n\n* Markström &amp; Co. AB., Smålands\n\nFarstorp.\n\nTillverkar sittmöbler och bord vid\nfabrik i Smålands Farstorp (Jönköp. l.).\n\nTelefon: 4. Postgiro: 72767. —\nAkt.-kap.: 70,000 kr. Antal industriarb.: 36.\n\n—\tFirman etabl. 1899, bolag 1936.\n\nStyrelse: fabr. Harald Dahlberg, fabr.\n\nSven Dahlberg.\n\nVerJcst. dir.: disp. Ernst Dahlberg.\n\n*Marma—Långrörs AB., Söderhamn.\n\nSulfatfabrik, biproduktsfabrik och\nsågverk i Marmaverken, brädgård och hyvleri\ni Söderhamn, sulfitfabrik och\nsulfitspritfabrik i Vallvik, sågverk och träsliperi i\nLottefors (samtl. i Gävleb. l.).\n\nTillverkar oblekt sulfat- och\nsulfitcellulosa, torr mekanisk massa, sågade och\nhyvlade trävaror, kemiska produkter\nsåsom terpentin, flotationsoljor, tallolja,\nharts och beck, kraftlim för wallboardtill-\n\nverkning samt sulfitsprit. Bolaget idkar\njämväl jordbruk och skogshantering.\n\nHuvudkontor: Söderhamn. Telegr.-adr.:\nMarmabolag, Söderhamn. Telefon:\n»Mar-ma-Långrör», Söderhamn. Postgiro:\n144062. Skogskontor: Ljusdal.\n\nAkt.-kap.: 4,200,000 kr. Antal\nindustriarb.: 700. Kapacitet: 70,000 ton\nsulfatcellulosa, 50,000 ton sulfitcellulosa, 16,000\nton torrberäknad mek. massa, 15,000 stds\nträvaror, 4 milj. ltr sulfitsprit.\n\nBolaget grundades år 1907. Till bolaget\näro anslutna: Marma Sågverks AB.\n(grundat 1854), Marma Sulfatfabriks AB.\n(f. d. Marma-Långrörs AB., grundat\n1896), samt Adolf Ungers Industri AB.,\n(grundat 1899).\n\nStyrelser handl. Hj. Wijk (ordf.),\nbankir Tage Cervin (v. ordf.), kapten\nBjörn Barkman, bankdir. P. Brundell,\nfrih. Wilh. Klingspor, dir. Ludvig\nLund-quist, adv. Hugo Stenbeck.\n\nVerkst. dir.: Ludvig Lundquist.\n\nFörsäljn.-dir.: Hugo Roland.\n\nTeJcn. dir.: Gustaf Lindoff.\n\nSkogschef: Göran Unger.\n\nPlatschefer: vid sulfatfabriken:\növer-ing. B. Ullstrand; vid sulfitfabriken:\nciviling. M. A. Norell; vid träsliperiet:\nslipm. E. Flodström; vid Marma sågverk\no. brädgård: förv. G. Moritz.\n\n(Jfr annons nr 54.)\n\n*\tMarma Sågverks AB., Söderhamn.\n\nSe Marma-Långrörs AB., Söderhamn.\n\n*\tMarmorbruks AB., Kolmården.\n\nSe Nya Marmorbruks AB., Kolmården.\n\nMarmorförädlings AB., Malmö.\n\nTillverkar marmor-, kalkstens- och\nskifferarbeten vid fabrik i Malmö samt\ncement- och mosaikvaror vid fabrik i\nStävie (Malmöh. l.).\n\nKontor: Spång. 91. Telegr.-adr.:\nMarmorförädling, Malmö. Telefon: 21131 o.\n21257. Postgiro: 37804.\n\nAkt.-kap.: 100,000 kr. Antal\nindustriarb.: 63, varav i Malmö 8. — Bolaget\ngrundat 1919.\n\nVerkst. dir.: N. G. Nihlén.\n\n*AB. Marstrands Mek. Verkstad,\n\nMarstrand.\n\nSkeppsvarv med slipar, grovplåtslageri,\nsågverk och snickeri. Utför ny- och\nombyggnader av fartyg samt tillverkar\nlivbåtar av stål och livflottar, maskindelar,\ncisterner, svetsade behållare m. m.",
    "structured": {
        "firms": [
            {
                "name": "AB. Marks Skofabrik",
                "location": "Örebro",
                "business": "Tillverkar finare skodon",
                "products": "Varumärke: »Marks»",
                "contact": {
                    "office": "AB. A. P. Hallqvist",
                    "phone": [
                        "10582"
                    ],
                    "postgiro": "20794"
                },
                "financials": {
                    "capital": "426,000 kr",
                    "employees": {
                        "industriarb": 100
                    },
                    "annual_turnover": "1,500,000 kr"
                },
                "foundation_year": 1897,
                "board": [
                    {
                        "name": "grossh. A. P. Hallqvist",
                        "role": "ordf."
                    },
                    {
                        "name": "köpman David Hallqvist",
                        "role": "disp."
                    },
                    {
                        "name": "Åke Hallqvist",
                        "role": "disp."
                    }
                ],
                "director": "A. P. Hallqvist"
            },
            {
                "name": "AB. Marks Tegelbruk",
                "location": "Örebro",
                "business": "Tillverkar mur- och taktegel samt dräneringsrör",
                "contact": {
                    "phone": [
                        "10601"
                    ],
                    "postgiro": "161045"
                },
                "financials": {
                    "capital": "190,00 kr",
                    "employees": {
                        "industriarb": 40
                    },
                    "annual_turnover": "495,000 kr"
                },
                "foundation_year": 1902,
                "director": "Arvid Adamson",
                "manager": "Erik J. Larsson"
            },
            {
                "name": "Marks Textilfabrik",
                "location": "Kinna",
                "business": "Mek. jacquardväveri",
                "products": "Tillverkar borddukar, ottomantäcken, sängöverkast, draperi-, möbel- och allmogetyger m. m",
                "contact": {
                    "telegraph": "Textil, Kinna",
                    "phone": [
                        "10735",
                        "10077",
                        "10125"
                    ],
                    "postgiro": "31793"
                },
                "financials": {
                    "employees": {
                        "industriarb": 65
                    },
                    "annual_turnover": "1,200,000 kr"
                },
                "foundation_year": 1908,
                "owners": [
                    "fabr. Carl Ad. Carlson",
                    "Gust. Arv. Gadhs sterbhus"
                ],
                "director": "Carl Ad. Carlson"
            },
            {
                "name": "Markström & Co. AB.",
                "location": "Smålands Farstorp",
                "business": "Tillverkar sittmöbler och bord",
                "contact": {
                    "phone": [
                        "4"
                    ],
                    "postgiro": "72767"
                },
                "financials": {
                    "capital": "70,000 kr",
                    "employees": {
                        "industriarb": 36
                    }
                },
                "foundation_year": 1899,
                "corporation_year": 1936,
                "board": [
                    {
                        "name": "fabr. Harald Dahlberg",
                        "role": null
                    },
                    {
                        "name": "fabr. Sven Dahlberg",
                        "role": null
                    }
                ],
                "director": "disp. Ernst Dahlberg"
            },
            {
                "name": "Marma—Långrörs AB.",
                "location": "Söderhamn",
                "business": "Sulfatfabrik, biproduktsfabrik och sågverk",
                "products": "Tillverkar oblekt sulfat- och sulfitcellulosa, torr mekanisk massa, sågade och hyvlade trävaror, kemiska produkter samt jordbruk och skogshantering",
                "contact": {
                    "office": "Söderhamn",
                    "phone": [
                        "Mar-ma-Långrör"
                    ],
                    "postgiro": "144062",
                    "factory_office": "Lottefors"
                },
                "financials": {
                    "capital": "4,200,000 kr",
                    "employees": {
                        "industriarb": 700
                    },
                    "annual_turnover": "N/A",
                    "annual_production_value": "70,000 ton sulfatcellulosa, 50,000 ton sulfitcellulosa, 16,000 ton torrberäknad mek. massa, 15,000 stds trävaror, 4 milj. ltr sulfitsprit"
                },
                "foundation_year": 1907,
                "original_name": "Marma Sågverks AB.; Marmorbruks AB.",
                "owners": [
                    "Marma Sågverks AB.",
                    "Marma Sulfatfabriks AB.",
                    "Adolf Ungers Industri AB."
                ],
                "director": "Ludvig Lundquist",
                "sales_manager": "Hugo Roland",
                "manager": "Göran Unger"
            },
            {
                "name": "Marmorförädlings AB.",
                "location": "Malmö",
                "business": "Tillverkar marmor-, kalkstens- och skifferarbeten samt cement- och mosaikvaror",
                "contact": {
                    "office": "Spång. 91",
                    "phone": [
                        "21131",
                        "21257"
                    ],
                    "postgiro": "37804"
                },
                "financials": {
                    "capital": "100,000 kr",
                    "employees": {
                        "industriarb": 63
                    },
                    "annual_turnover": "N/A"
                },
                "foundation_year": 1919,
                "director": "N. G. Nihlén"
            },
            {
                "name": "AB. Marstrands Mek. Verkstad",
                "location": "Marstrand",
                "business": "Skeppsvarv med slipar, grovplåtslageri, sågverk och snickeri",
                "products": "Livbåtar av stål och livflottar, maskindelar, cisterner, svetsade behållare m. m",
                "contact": {
                    "phone": [
                        "Mar-ma-Långrör"
                    ],
                    "postgiro": "N/A"
                }
            }
        ]
    }
}