{
    "original": "Ing enj ö rsfirman—Instrum e nt\n\nKontor: Luntmakarg. 14. Telefon:\n112480. Postgiro: 2359.\n\nAkt.-kap.: 50,000 kr. Antal\nindustriarb.: 20. — Bolaget, grundat 1928,\ntillhör Asea-koncernen.\n\nStyrelse o. verkst. dir.: Hugo Edström.\n\nAB. Ingenjörsfirman Alb. J.\nWahlbeck, Halmstad.\n\nMaskinfabrik (»Maskinfabriken Waco»).\nTillverkar som specialitet\nsnickerimaskiner. Varumärke: »Waco».\n\nTelegr.-adr.: Waco. Telefon: 952 o.\n2152. Postgiro: 93626. — Akt.-kap.:\n150,000 kr. Antal industriarb.: 60.\nTillv.-värde pr år: 800,000 kr. — Firman etabl.\n1918, bolag 1946.\n\nDisp.: Carl-Eric Wahlbeck.\n\n\"Ingenjörsfirman Yentilator, S.\nRomedahl, Stockholm.\n\nMek. verkstad. Tillverkar fläktar,\nven-tilationsmateriel, plåttrummor och\nkompletta ventilationsanläggningar.\nVarumärke: »Vento».\n\nKontor: Västbergavägen. Telefon:\n452830. Postgiro: 53070. — Antal\nindustriarb.: 56. Tillv.-värde pr år: 1,300,000\nkr. — Firman etabl. 1931.\n\nÄgare o. chef: civiling. Sven Romedahl.\n\n\"Ingenjörstekniska Byrån AB.,\n\nStockholm.\n\nTillverkar regenereringsmedel för\nmetallsmältor (»Renovalit») samt bedriver\nkonstruktionsverksamhet.\n\nKontor: Blasieholmstorg 11 C.\nTelegr.-adr.: Polytecnos, Stockholm. Telefon:\n104550. Postgiro: 2850. — Akt.-kap.:\n5,000 kr. Omsättnings värde pr år: 120,000\nkr. — Bolaget grundat 1926.\n\nStyrelse o. verkst. dir.: civiling. Karl\nWessblad.\n\n\"Inlands AB., Lilla Edet.\n\nPapp- och kartongfabrik, pappersbruk\nsamt träsliperi vid Lilla Edet (Göteb. o.\nBohus l.). Tillverkar kartong och papper,\nsåsom trämassepapp. bokbindarpapp.\nchro-moersatzkartong, duplex- och\ntriplexkar-tong, middles, M. G.-sulfit,\nomslagspapper, kvistpapper samt trämassa för eget\nbehov.\n\nHuvudkontor: Lilla Edet. Telegr.-adr.:\nInlandmills, Lilla Edet. Telefon: 26, 200\no. 272. Postgiro: 163464.\n\nFörsäljning: för inlandet: Grubbens &amp;\nCo. AB., Ferkensgränd 1 o. 3, Stockholm,\ntelefon: »Grubbens»; exportförsäljn.\ndirekt från bruket.\n\nAgenter i utlandet:\n\nStorbritannien o. Eiré: Messrs. A. H.\nMason &amp; Co. Ltd., 22/3 Laurence\nPount-ney Lane, London E C 4; Holland: Mr. J.\nHinnen, Parklaan 3, Hilversum; Belgien:\nMessrs. Le Duplex S. P. R. L., 37, Rue\nAug. Denie, Brussels; Argentina: Messrs.\nIMPEX S. A., Balcarce 749, Buenos\nAires.\n\nAkt.-kap.: 1,100,000 kr. Antal\nindustriarb.: 180. Årstillv.: 12,000 ton kartong\noch papper. — Fabriken anlagd 1894,\nnuv. bolag grundat 1913.\n\nStyrelse: dir. Folke L. Lindqvist\n(ordf.), disp. O. Gunnar Haeger, adv.\nAxel T. Nilsson.\n\nVerkst. dir. o. disp.: C. Gunnar Haeger.\nKontorschef: I. Stenwall.\n\n\"Insjöns Sågverks AB., Insjön.\n\nSågverk, hyvleri, snickerifabrik samt\nkolugnar vid Insjön (Kopparb. l.).\nTillverkar sågade och hyvlade trävaror,\nmonteringsfärdiga trähus, fönster och dörrar\nsamt träkol och trätjära.\n\nTelegr.-adr.: Sågverket, Insjön.\nTelefon: 40220—23. Postgiro: 143800.\nEnsamförsälj. av trähus: AB. Svenska\nTrähus, Stockholm, Birger Jarlsg. 27,\ntelefon: »Svenska Trähus».\n\nAkt.-kap.: 1,100,000 kr. Antal\nindustriarb.: 275. Årstillv.: 6.000 stds sågade o.\nhyvlade trävaror, 12,000 läster träkol,\n250 ton trätjära. — Bolaget grundat 1912.\n\nStyrelse: hovrättsassessor Å. Thorell\n(ordf.), disp. August Andersson, disp.\nJohan Danielsson, disp.-assistent Rolf v.\nHeidenstam, dir. K. I. Hising, prof.\nOskar Lindberg, disp. Axel Wiklund.\n\nVerkst. dir.: K. I. Hising.\n\nDisp. o. platschef: August Andersson.\n\nKamrer: E. A. Engelcrona.\n\nFörsäljn.-chef: E. Waldrén.\n\n\"Instrument AB. J. A. Palm,\n\nStockholm.\n\nFinmekanisk verkstad i Storängen\n(Sthlms l.). Tillverkar ingenjörs- och\nkontorsutensilier såsom ritinstrument,\nstålmåttband, pennformeringsmaskiner,\nböjlig metallslang samt pressade och\nsvarvade massartiklar. Varumärke:\n»Instrument-Palm».\n\nHuvudkontor: Stockholm, Välling. 12.\nTelefon: 235995. Postgiro: 195945.\n\nAkt.-kap.: 25,000 kr. Antal\nindustriarb.: 35. Tillv.-värde pr år: 500,000 kr.\n\n— Firman etabl. 1919, bolag 1943.\n*",
    "structured": {
        "firms": [
            {
                "name": "Ingenjörsfirman—Instrum e nt",
                "location": "Luntmakarg. 14",
                "business": "Ingenjörsfirman",
                "contact": {
                    "office": "Luntmakarg. 14",
                    "phone": [
                        "112480"
                    ],
                    "postgiro": "2359"
                },
                "financials": {
                    "capital": "50,000 kr",
                    "employees": {
                        "industriarb": 20
                    }
                },
                "foundation_year": 1928,
                "board": [
                    {
                        "name": "Hugo Edström",
                        "role": "Styrelse o. verkst. dir."
                    }
                ]
            },
            {
                "name": "Ingenjörsfirman Alb. J. Wahlbeck",
                "location": "Halmstad",
                "business": "Maskinfabrik",
                "products": "Tillverkar som specialitet snickerimaskiner. Varumärke: »Waco».",
                "contact": {
                    "office": "Halmstad",
                    "phone": [
                        "952",
                        "2152"
                    ],
                    "postgiro": "93626"
                },
                "financials": {
                    "capital": "150,000 kr",
                    "employees": {
                        "industriarb": 60
                    },
                    "annual_production_value": "800,000 kr"
                },
                "foundation_year": 1918,
                "current_name_year": 1946,
                "director": "Carl-Eric Wahlbeck"
            },
            {
                "name": "Ingenjörsfirman Yentilator",
                "location": "Stockholm",
                "business": "Mek. verkstad",
                "products": "Tillverkar fläktar, ventilationsmateriel, plåttrummor och kompletta ventilationsanläggningar. Varumärke: »Vento».",
                "contact": {
                    "office": "Västbergavägen",
                    "phone": [
                        "452830"
                    ],
                    "postgiro": "53070"
                },
                "financials": {
                    "employees": {
                        "industriarb": 56
                    },
                    "annual_production_value": "1,300,000 kr"
                },
                "foundation_year": 1931,
                "owner": "civiling. Sven Romedahl"
            },
            {
                "name": "Ingenjörstekniska Byrån AB.",
                "location": "Stockholm",
                "business": "Tillverkar regenereringsmedel för metallsmältor samt bedriver konstruktionsverksamhet."
            },
            "contact",
            {
                "office": "Blasieholmstorg 11 C",
                "phone": [
                    "104550"
                ],
                "postgiro": "2850"
            },
            "financials",
            {
                "capital": "5,000 kr",
                "annual_turnover": "120,000 kr"
            },
            "foundation_year",
            1926,
            "board",
            [
                {
                    "name": "civiling. Karl Wessblad",
                    "role": "Styrelse o. verkst. dir."
                }
            ],
            "owners",
            [
                ""
            ],
            "director",
            "civiling. Karl Wessblad",
            "manager",
            "civiling. Karl Wessblad",
            "sales_manager",
            "civiling. Karl Wessblad",
            "managing_director",
            "civiling. Karl Wessblad",
            {
                "name": "Inlands AB.",
                "location": "Lilla Edet",
                "business": "Papp- och kartongfabrik, pappersbruk samt träsliperi.",
                "products": "Tillverkar kartong och papper, såsom trämassepapp. bokbindarpapp. etc.",
                "contact": {
                    "office": "Lilla Edet",
                    "phone": [
                        "26",
                        "200",
                        "272"
                    ],
                    "postgiro": "163464"
                },
                "financials": {
                    "capital": "1,100,000 kr",
                    "employees": {
                        "industriarb": 180
                    },
                    "annual_turnover": "12,000 ton kartong och papper"
                },
                "foundation_year": 1913,
                "board": [
                    {
                        "name": "dir. Folke L. Lindqvist",
                        "role": "Styrelse"
                    },
                    {
                        "name": "disp. O. Gunnar Haeger",
                        "role": "disp."
                    },
                    {
                        "name": "adv. Axel T. Nilsson",
                        "role": "adv."
                    }
                ]
            },
            {
                "name": "Insjöns Sågverks AB.",
                "location": "Insjön",
                "business": "Sågverk, hyvleri, snickerifabrik samt kolugnar",
                "products": "Tillverkar sågade och hyvlade trävaror, monteringsfärdiga trähus, fönster och dörrar samt träkol och trätjära.",
                "contact": {
                    "office": "Insjön",
                    "phone": [
                        "40220-23"
                    ],
                    "postgiro": "143800"
                },
                "financials": {
                    "capital": "1,100,000 kr",
                    "employees": {
                        "industriarb": 275
                    },
                    "annual_production_value": {
                        "sågade o. hyvlade trävaror": "6,000 stds",
                        "träkol": "12,000 läster",
                        "trätjära": "250 ton"
                    }
                },
                "foundation_year": 1912,
                "board": [
                    {
                        "name": "hovrättsassessor Å. Thorell",
                        "role": "Styrelse"
                    },
                    {
                        "name": "disp. August Andersson",
                        "role": "disp."
                    },
                    {
                        "name": "disp. Johan Danielsson",
                        "role": "disp."
                    },
                    {
                        "name": "disp.-assistent Rolf v. Heidenstam",
                        "role": "disp.-assistent"
                    },
                    {
                        "name": "dir. K. I. Hising",
                        "role": "dir."
                    },
                    {
                        "name": "prof. Oskar Lindberg",
                        "role": "prof."
                    }
                ]
            },
            {
                "name": "Instrument AB. J. A. Palm",
                "location": "Stockholm",
                "business": "Finmekanisk verkstad",
                "products": "Tillverkar ingenjörs- och kontorsutensilier såsom ritinstrument, stålmåttband, pennformeringsmaskiner, böjlig metallslang samt pressade och svarvade massartiklar.",
                "contact": {
                    "office": "Stockholm, Välling. 12",
                    "phone": [
                        "235995"
                    ],
                    "postgiro": "195945"
                },
                "financials": {
                    "capital": "25,000 kr",
                    "employees": {
                        "industriarb": 35
                    },
                    "annual_production_value": "500,000 kr"
                },
                "foundation_year": 1919,
                "current_name_year": 1943
            }
        ]
    }
}