{
    "original": "Bitumuls—Bjärnum\n\n*AB. Bitumuls, Göteborg.\n\nSe AB. Geveko, Göteborg.\n\n*AB. Bjelkes, Karlskoga.\n\nSnickerifabrik. Tillverkar inredningar\nocli grövre snickerier samt lådor. Bolaget\ndriver även handel med byggnadsmateriel\noch trävaror.\n\nTelefon: 32565. Postgiro: 81490. —\nAkt.-kap.: 35,000 kr. Antal industriarb.:\n50. Tillv.-värde pr år: 1,500,000 kr. —\nFirman etabl. 1923, bolag 1935.\n\nStyrelse: fabr. Ragnar E. Jansson\n(ordf.), fabr. Johan T. Jansson.\n\nVerkst. dir.: Ragnar E. Jansson.\n\nBjerkås AB., Göteborg.\n\nArmaturfabrik. Tillverkar\nbelysningsarmatur och konstsmide.\n\nKontor: Nils Ericsonsg. A 3. Telefon:\n154124. Postgiro: 40407. — Akt.-kap.:\n15,000 kr. Antal industriarb.: 40.\nTillv.-värde pr år: 600,000 kr. — Bolaget\ngrundat 1927.\n\nVerkst. dir.: Olof Gertorp.\n\nDriftsing.: Sture Lantz.\n\n* B jur hagens Fabrikers AB., Malmö.\n\nKabelfabrik. Tillverkar vulkaniserade\nstarkströmsledningar.\n\nKontor: Agneslundsvägen 8.\nTelegr.-adr.: Kabelfabriken, Malmö. Telefon:\n72165. Postgiro: 39069.\n\nAkt.-kap.: 200,000 kr. Antal\nindustriarb.: 100. — Firman etabl. 1924.\n\nStyrelse: dir. Georg Olsson (ordf.), dir.\nEric Carlson, dir. Hugo Edström.\n\nVerkst. dir.: Eric Carlson.\n\nAB. Bjurstorps Marmorverk,\n\nVästervik.\n\nMarmorbearbetning i Bjurstorp,\nKatrineholm (Södermanl. l.), marmorbrott\ni Vånga socken, (ös t er gö ti. l.) samt\ngra-nitstenhuggeri i Västervik. Tillverkar\nbyggnadsmarmor, möbelmarmor samt\ngravvårdar.\n\nHuvudkontor: Västervik. Telefon: 83.\nPostgiro: 272320. Repr. i Stockholm: T.\nMarschall, Skåneg. 44, telefon: 428098.\n\nAkt.-kap.: 50,000 kr. Antal\nindustriarb.: 35, varav i Västervik 20.\nTillv.-värde pr år: 425,000 kr. — Firman etabl.\n1944.\n\nVerkst. dir.: fabr. Edvin Nilsson.\n\nBjursås Kvarn- &amp; Såg AB.,\n\nIngels.\n\nSågverk och hyvlerier i Bjursås och\nBorn, Ingels (båda i Kopparb. l.).\nTillverkar sågade och hyvlade trävaror,\nlistverk samt träkol. Bolaget driver jämväl\nkvarnrörelse.\n\nHuvudkontor: Born, Ingels.\nTelegr.-adr.: Kvarnsågen, Rättvik. Telefon:\nIngels 13. Postgiro: 14376. Avd.-kontor:\nBjursås. Telefon: Bjursås 13. Postgiro:\n81485. — Akt.-kap.: 137,300 kr. Antal\nindustriarb.: 65. Tillv.-värde pr år: 900,000\nkr. — Bolaget grundat 1917.\n\nVerkst. dir. o. disp.: Erik Sjögren\n(Rättvik).\n\nFörvaltare: Anders Sjögren.\n\n* Bjursås Skomakeriförening, Bjursås.\n\nTillverkar pjäxor, arbetsskor,\nvandrar-skor och sandaler vid fabrik i Bjursås\n(Kopparb. l.).\n\nTelefon: 14. Postgiro: 24802. —\nAn-delskap.: 85,000 kr. Antal industriarb.:\n33. Tillv.-värde pr år: 650,000 kr. —\nFöreningen bildad år 1921.\n\nFöreståndare: fabr. Johan Hag.\n\nAB. Bjäre Industrier, Karpalund.\n\nTillverkar fruktkonserver, fruktmos\noch marmelad vid fabrik i Karpalund\n(Kristianst. l.).\n\nTelefon: 14490—91. Postgiro: 12621.\nEnsamförsälj.: Margarinbolaget AB.,\nStockholm, Vasag. 16, telefon: 230960.\n\nAkt.-kap.: 100,000 kr. Antal\nindustriarb.: 20. — Firman etabl. 1918, nuv.\nbolag 1942.\n\nVerkst. dir.: civiling. Gunnar Nilsson.\n\nAB. Bjärnums Möbelfabriker,\n\nBjärnum.\n\nTillverkar möbler vid fabrik i\nBjärnum (Kristianst. l.).\n\nTelefon: 15. Postgiro: 23550. —\nAkt.-kap.: 73,700 kr. Antal industriarb.: 70.\nTillv.-värde pr år: 550,000 kr. — Firman\netabl. 1919, nuv. namn 1929.\n\nStyrelse o. disp.: William Cederholm.\n\nBjärnums Redskapsfabrik,\n\nBjärnum.\n\nMek. verkstad och skaftfabrik i\nBjärnum (Kristianst. l.). Tillverkar skyfflar\nmed smidda beslag, spadar, bethackor,\npotatiskvarnar samt yx- och andra skaft.\n\nTelefon: 75 o. 116. Postgiro: 29554. —\nArb.-antal: 10. Tillv.-värde pr år: 100,000\nkr. — Firman etabl. 1880.\n\nÄgare o. chef: fabr. Oscar Findahl.",
    "structured": {
        "1": {
            "name": "AB. Bitumuls",
            "location": "Bjärnum",
            "business": "Asfaltprodukter",
            "products": "Tillverkar inredningar och grövre snickerier samt lådor.",
            "contact": {
                "office": "Göteborg",
                "phone": [
                    "32565"
                ],
                "postgiro": "81490",
                "head_office": "",
                "telegraph": "",
                "factory_office": "",
                "factory_phone": ""
            },
            "financials": {
                "capital": "35,000 kr",
                "employees": {
                    "Antal industriarb.": 50
                },
                "annual_turnover": "1,500,000 kr",
                "annual_production_value": "1,500,000 kr"
            },
            "foundation_year": 1923,
            "corporation_year": 1935,
            "board": [
                {
                    "name": "fabr. Ragnar E. Jansson",
                    "role": "ordf."
                },
                {
                    "name": "fabr. Johan T. Jansson",
                    "role": ""
                }
            ],
            "director": "Ragnar E. Jansson",
            "managing_director": "",
            "sales_manager": "",
            "manager": ""
        },
        "2": {
            "name": "Bjelkes",
            "location": "Karlskoga",
            "business": "Snickare och byggarbeten",
            "products": "Tillverkar inredningar och grövre snickerier samt lådor. Driver även handel med byggnadsmateriel och trävaror.",
            "contact": {
                "office": "",
                "phone": [],
                "postgiro": "",
                "head_office": "",
                "telegraph": "",
                "factory_office": "",
                "factory_phone": ""
            },
            "financials": {
                "capital": "35,000 kr",
                "employees": {
                    "Antal industriarb.": 50
                },
                "annual_turnover": "1,500,000 kr",
                "annual_production_value": "1,500,000 kr"
            },
            "foundation_year": 1923,
            "corporation_year": 1935,
            "board": [
                {
                    "name": "fabr. Ragnar E. Jansson",
                    "role": "ordf."
                },
                {
                    "name": "fabr. Johan T. Jansson",
                    "role": ""
                }
            ],
            "director": "Ragnar E. Jansson",
            "managing_director": "",
            "sales_manager": "",
            "manager": ""
        },
        "3": {
            "name": "Bjerkås AB.",
            "location": "Göteborg",
            "business": "Armaturfabrik",
            "products": "Tillverkar belysningsarmatur och konstsmide.",
            "contact": {
                "office": "Nils Ericsonsg. A 3",
                "phone": [
                    "154124"
                ],
                "postgiro": "40407",
                "head_office": "",
                "telegraph": "",
                "factory_office": "",
                "factory_phone": ""
            },
            "financials": {
                "capital": "15,000 kr",
                "employees": {
                    "Antal industriarb.": 40
                },
                "annual_turnover": "600,000 kr",
                "annual_production_value": "600,000 kr"
            },
            "foundation_year": 1927,
            "corporation_year": null,
            "board": [],
            "director": "Olof Gertorp",
            "managing_director": "",
            "sales_manager": "",
            "manager": "Sture Lantz"
        },
        "4": {
            "name": "Bjurhagens Fabrikers AB.",
            "location": "Malmö",
            "business": "Kabelfabrik",
            "products": "Tillverkar vulkaniserade starkströmsledningar.",
            "contact": {
                "office": "Agneslundsvägen 8",
                "phone": [
                    "72165"
                ],
                "postgiro": "39069",
                "head_office": "",
                "telegraph": "Kabelfabriken, Malmö",
                "factory_office": "",
                "factory_phone": ""
            },
            "financials": {
                "capital": "200,000 kr",
                "employees": {
                    "Antal industriarb.": 100
                },
                "annual_turnover": "",
                "annual_production_value": ""
            },
            "foundation_year": 1924,
            "corporation_year": null,
            "board": [],
            "director": "Eric Carlson",
            "managing_director": "",
            "sales_manager": "",
            "manager": ""
        },
        "5": {
            "name": "AB. Bjurstorps Marmorverk",
            "location": "Västervik",
            "business": "Marmorbearbetning",
            "products": "Marmorbearbetning i Bjurstorp, Katrineholm, marmorbrott i Vånga socken samt granitstenhuggeri i Västervik.",
            "contact": {
                "office": "",
                "phone": [
                    "83"
                ],
                "postgiro": "272320",
                "head_office": "",
                "telegraph": "",
                "factory_office": "",
                "factory_phone": ""
            },
            "financials": {
                "capital": "50,000 kr",
                "employees": {
                    "Antal industriarb.": 35
                },
                "annual_turnover": "425,000 kr",
                "annual_production_value": "425,000 kr"
            },
            "foundation_year": 1944,
            "corporation_year": null,
            "board": [],
            "director": "fabr. Edvin Nilsson",
            "managing_director": "",
            "sales_manager": "",
            "manager": ""
        },
        "6": {
            "name": "Bjursås Kvarn- & Såg AB.",
            "location": "Ingels",
            "business": "Sågverk och hyvleri",
            "products": "Tillverkar sågade och hyvlade trävaror, listverk samt träkol.",
            "contact": {
                "office": "Born, Ingels",
                "phone": [
                    "Ingels 13",
                    "Bjursås 13"
                ],
                "postgiro": "14376 (Born), 81485 (Bjursås)",
                "head_office": "",
                "telegraph": "Kvarnsågen, Rättvik",
                "factory_office": "",
                "factory_phone": ""
            },
            "financials": {
                "capital": "137,300 kr",
                "employees": {
                    "Antal industriarb.": 65
                },
                "annual_turnover": "900,000 kr",
                "annual_production_value": "900,000 kr"
            },
            "foundation_year": 1917,
            "corporation_year": null,
            "board": [],
            "director": "Erik Sjögren",
            "managing_director": "Anders Sjögren",
            "sales_manager": "",
            "manager": ""
        },
        "7": {
            "name": "Bjursås Skomakeriförening",
            "location": "Bjursås",
            "business": "Tillverkning av skor och fotbeklädnader",
            "products": "Tillverkar pjäxor, arbetsskor, vandrarskor och sandaler.",
            "contact": {
                "office": "",
                "phone": [
                    "14"
                ],
                "postgiro": "24802",
                "head_office": "",
                "telegraph": "",
                "factory_office": "",
                "factory_phone": ""
            },
            "financials": {
                "capital": "85,000 kr",
                "employees": {
                    "Antal industriarb.": 33
                },
                "annual_turnover": "650,000 kr",
                "annual_production_value": "650,000 kr"
            },
            "foundation_year": 1921,
            "corporation_year": null,
            "board": [],
            "director": "",
            "managing_director": "",
            "sales_manager": "",
            "manager": "fabr. Johan Hag"
        },
        "8": {
            "name": "AB. Bjäre Industrier",
            "location": "Karpalund",
            "business": "Livsmedelsindustri",
            "products": "Tillverkar fruktkonserver, fruktmos och marmelad.",
            "contact": {
                "office": "Karpalund (Kristianst. l.)",
                "phone": [
                    "14490—91"
                ],
                "postgiro": "12621",
                "head_office": "",
                "telegraph": "",
                "factory_office": "",
                "factory_phone": ""
            },
            "financials": {
                "capital": "100,000 kr",
                "employees": {
                    "Antal industriarb.": 20
                },
                "annual_turnover": "",
                "annual_production_value": ""
            },
            "foundation_year": 1918,
            "corporation_year": 1942,
            "board": [],
            "director": "civiling. Gunnar Nilsson",
            "managing_director": "",
            "sales_manager": "",
            "manager": ""
        },
        "9": {
            "name": "AB. Bjärnums Möbelfabriker",
            "location": "Bjärnum",
            "business": "Möbeltillverkning",
            "products": "Tillverkar möbler.",
            "contact": {
                "office": "",
                "phone": [
                    "15"
                ],
                "postgiro": "23550",
                "head_office": "",
                "telegraph": "",
                "factory_office": "",
                "factory_phone": ""
            },
            "financials": {
                "capital": "73,700 kr",
                "employees": {
                    "Antal industriarb.": 70
                },
                "annual_turnover": "550,000 kr",
                "annual_production_value": "550,000 kr"
            },
            "foundation_year": 1919,
            "corporation_year": 1929,
            "board": [],
            "director": "",
            "managing_director": "",
            "sales_manager": "",
            "manager": "William Cederholm"
        },
        "10": {
            "name": "Bjärnums Redskapsfabrik",
            "location": "Bjärnum",
            "business": "Mekanisk verkstad",
            "products": "Tillverkar skyfflar med smidda beslag, spadar, bethackor, potatiskvarnar samt yx- och andra skaft.",
            "contact": {
                "office": "Bjärnum (Kristianst. l.)",
                "phone": [
                    "75",
                    "116"
                ],
                "postgiro": "29554",
                "head_office": "",
                "telegraph": "",
                "factory_office": "",
                "factory_phone": ""
            },
            "financials": {
                "capital": "",
                "employees": {
                    "Arb.-antal": 10
                },
                "annual_turnover": "100,000 kr",
                "annual_production_value": "100,000 kr"
            },
            "foundation_year": 1880,
            "corporation_year": null,
            "board": [],
            "director": "fabr. Oscar Findahl",
            "managing_director": "",
            "sales_manager": "",
            "manager": ""
        }
    }
}