{
    "original": "Nordiska\n\n\"Nordiska Maskinfilt AB., Halmstad.\n\nMaskinfiltfabrik med ullspinneri,\nylle-väveri, appreturverk och färgeri.\nTillverkar vävd och stampad maskinfilt för\npappers- och cellulosaindustrin och andra\ntekniska ändamål samt filt för sko- och\nbeklädnadsindustrin.\n\nTelegr.-adr. o. telefon: Nordiskafilt,\nHalmstad. Postgiro: 20577.\n\nAkt.-kap.: 1,500,000 kr. Antal\nindustriarb.: 375. Tillv.-värde pr år: 6,000,000 kr.\n\n—\tBolaget grundat 1904.\n\nStyrelse: dir. Carl Jönsson (ordf.),\nkonsul Gottfrid Westerberg, löjtn.\nGunnar O. Westerberg.\n\nVerkst. dir.: Gottfrid Westerberg.\n\nKamrer: B. W. Jönsson.\n\n\"AB. Nordiska Metallduksväveriet,\n\nUppsala.\n\nTillverkar viror och dukar för\npappers-, cellulosa- och trämasseindustrierna.\n\nTelegr.-adr.: Viror, Uppsala. Telefon:\n30803 o. 30895. Postgiro: 25150.\n\nRepresentant för Sverige: AB.\nöfver-gård &amp; Co., Stockholm, Hovslagarg. 3,\ntelefon: 105919.\n\nAkt.-kap.: 500,000 kr. Antal\nindustriarb.: 90. Tillv.-värde pr år: 2,000,000 kr.\n\n—\tBolaget grundat 1924.\n\nStyrelse: grossh. H. Isselhorst (ordf.),\nv. auditör Harald Håkansson, disp. Carl\nKehrer.\n\nDisp.: C. Kehrer.\n\nKamrer: Sten Janemark.\n\nFörsäljn.-chef: Alvar Hellgren.\n\nAB. Nordiska Måttstockfabriken,\n\nFristad.\n\nSe Nya AB. Nordiska\nMåttstockfabriken, Fristad.\n\nAB. Nordiska Möbelfabrikerna,\n\nÖdeshög.\n\nMöbelfabrik i Backasand, ödeshög\n(Östergötl. l.). Tillverkar kontors- och\nbostadsmöbler.\n\nTelegr.-adr. o. telefon: Nordiska,\nödeshög. Postgiro: 70209. — Akt.-kap.: 79,100\nkr. Antal industriarb.: 85. Tillv.-värde\npr år: 1,000,000 kr.\n\nBolaget grundat 1918.\n\nDisp.: H. Rask-Andersen.\n\n\"Nordiska Pianofabriken, Vetlanda.\n\nTillverkar pianon. Specialitet:\nLill-pianon.\n\nTelefon: 342. Postgiro: 74903. —\nAntal industriarb.: 15. Tillv.-värde pr år:\n150,000 kr. — Firman etabl. 1922 i\nStockholm, överflyttades 1926 till Vetlanda.\n\nÄgare o. chef: fabr. Emanuel Lager.\n\nNordiska Neonfabriken, Göteborg.\n\nSe A. Edwin Andrén &amp; Co., Göteborg.\n\nNordiska Plywoodfabriken,\n\nHassela.\n\nTillverkar fanér, plywood och\nlamellplattor vid fabrik i Hassela (Gävleb. l.).\n\nTelefon: 60. Postgiro: 288044. — Antal\nindustriarb.: 50. Tillv.-värde pr år:\n1,000,000 kr.\n\nFirman etabl. 1945.\n\nDisp.: H. Rask-Andersen.\n\n\"Nordiska Slangfabriken, AB.\nSpiralslang, Stockholm.\n\nMetallslangfabrik i Hägersten,\nStockholm. Tillverkar böjliga metallslangar.\nSpecialitet: dammsugareslang.\nVarumärke: »Nordslang».\n\nPostadr.: Stockholm 9. Telegr.-adr.:\nNordslang, Stockholm. Telefon: 452665.\nPostgiro: 53835. — Akt.-kap.: 62,500 kr.\nAntal industriarb.: 20. — Bolaget\ngrundat 1924.\n\nStyrelse: f. d. bruksdisp. Olof Hjorth\n(ordf.), dir. Stig Hjorth, dir. Ivar Kull.\n\nVerkst. dir.: Stig Hjorth.\n\nAB. Nordiska Stansknivfabriken &amp;\nMek. Verkstad, Örebro.\n\nTillverkar stansknivar, byggnadssmiden\nm. m.\n\nPostadr.: postfack 3020, Örebro 3.\nTelegr.-adr.: Nordstans, Örebro. Telefon:\n14759. Postgiro: 71097.\n\nAkt.-kap.: 22,500 kr. Antal\nindustriarb.: 20. Tillv.-värde pr år: 200,000 kr.\n— Firman etabl. 1929, bolag 1938.\n\nVerkst. dir.: Jakob E. Ekelund.\n\n\"Nordiska Syrgasverken AB.,\n\nStockholm.\n\nGasfabriker i Örebro, Göteborg, Motala,\nHedemora, Trollhättan, Jönköping,\nKalmar, Västerås, Norrköping, Halmstad och\nLinköping. Framställer syrgas, vätgas,\nkvävgas samt komprimerad luft.\n\nHuvudkontor: Stockholm, Kungsg. 13.\nTelefon: 201188, 201233. Postgiro: 825.\nFabrikskontor: örebo, telefon: 11218—\n19; Göteborg, telefon: 223891 o. 223991;\nMotala, telefon: 85; Hedemora, telefon:\n575; Trollhättan, telefon: 10008; Jönkö-\n\nr*",
    "structured": {
        "1": {
            "name": "Nordiska Maskinfilt AB",
            "location": "Halmstad",
            "business": "Maskinfiltfabrik med ullspinneri, ylle-väveri, appreturverk och färgeri.",
            "products": "Tillverkar vävd och stampad maskinfilt för pappers- och cellulosaindustrin och andra tekniska ändamål samt filt för sko- och beklädndasindustrin.",
            "contact": {
                "office": "Nordiska Maskinfilt AB, Halmstad",
                "phone": [
                    "Nordiska Maskinfilt, Halmstad"
                ],
                "postgiro": "20577"
            },
            "financials": {
                "capital": "1,500,000 kr",
                "employees": {
                    "industriarb": 375
                },
                "annual_turnover": "6,000,000 kr",
                "annual_production_value": "6,000,000 kr"
            },
            "foundation_year": 1904,
            "board": [
                {
                    "name": "Carl Jönsson",
                    "role": "ordf."
                },
                {
                    "name": "Gottfrid Westerberg",
                    "role": "konsul"
                },
                {
                    "name": "Gunnar O. Westerberg",
                    "role": "löjtn"
                }
            ],
            "manager": "Gottfrid Westerberg"
        },
        "2": {
            "name": "AB. Nordiska Metallduksväveriet",
            "location": "Uppsala",
            "products": "Tillverkar viror och dukar för pappers-, cellulosa- och trämasseindustrierna.",
            "contact": {
                "office": "Viror, Uppsala",
                "phone": [
                    "30803",
                    "30895"
                ],
                "postgiro": "25150",
                "sales_offices": {
                    "location": "Stockholm, Hovslagarg. 3",
                    "phone": "105919"
                }
            },
            "financials": {
                "capital": "500,000 kr",
                "employees": {
                    "industriarb": 90
                },
                "annual_turnover": "2,000,000 kr",
                "annual_production_value": "2,000,000 kr"
            },
            "foundation_year": 1924,
            "board": [
                {
                    "name": "H. Isselhorst",
                    "role": "ordf."
                },
                {
                    "name": "Harald Håkansson",
                    "role": "v. auditör"
                },
                {
                    "name": "Carl Kehrer",
                    "role": "disp."
                }
            ],
            "manager": "C. Kehrer"
        },
        "3": {
            "name": "AB. Nordiska Måttstockfabriken",
            "location": "Fristad",
            "original_name": "Nya AB. Nordiska Måttstockfabriken",
            "foundation_year": 1918,
            "manager": "H. Rask-Andersen"
        },
        "4": {
            "name": "AB. Nordiska Möbelfabrikerna",
            "location": "Ödeshög",
            "products": "Tillverkar kontors- och bostadsmöbler.",
            "contact": {
                "office": "Nordiska, Ödeshög",
                "phone": [
                    "Ödeshög"
                ],
                "postgiro": "70209"
            },
            "financials": {
                "capital": "79,100 kr",
                "employees": {
                    "industriarb": 85
                },
                "annual_turnover": "1,000,000 kr",
                "annual_production_value": "1,000,000 kr"
            },
            "foundation_year": 1918,
            "manager": "H. Rask-Andersen"
        },
        "5": {
            "name": "Nordiska Pianofabriken",
            "location": "Vetlanda",
            "products": "Tillverkar pianon. Specialitet: Lill-pianon.",
            "contact": {
                "phone": [
                    "342"
                ],
                "postgiro": "74903"
            },
            "financials": {
                "employees": {
                    "industriarb": 15
                },
                "annual_turnover": "150,000 kr"
            },
            "foundation_year": 1922,
            "current_name_year": 1926,
            "owner": "fabr. Emanuel Lager"
        },
        "6": {
            "name": "Nordiska Neonfabriken",
            "location": "Göteborg",
            "contact": {
                "office": "A. Edwin Andrén & Co., Göteborg",
                "phone": [
                    "Göteborg"
                ],
                "postgiro": "Unknown"
            }
        },
        "7": {
            "name": "Nordiska Plywoodfabriken",
            "location": "Hassela",
            "products": "Tillverkar fanér, plywood och lamellplattor vid fabrik i Hassela (Gävleb. l.).",
            "contact": {
                "phone": [
                    "60"
                ],
                "postgiro": "288044"
            },
            "financials": {
                "employees": {
                    "industriarb": 50
                },
                "annual_turnover": "1,000,000 kr"
            },
            "foundation_year": 1945,
            "manager": "H. Rask-Andersen"
        },
        "8": {
            "name": "Nordiska Slangfabriken, AB. Spiralslang",
            "location": "Stockholm",
            "products": "Tillverkar böjliga metallslangar. Specialitet: dammsugareslang. Varumärke: »Nordslang».",
            "contact": {
                "office": "Nordstans, Örebro",
                "phone": [
                    "452665"
                ],
                "postgiro": "53835"
            },
            "financials": {
                "capital": "62,500 kr",
                "employees": {
                    "industriarb": 20
                }
            },
            "foundation_year": 1924,
            "board": [
                {
                    "name": "Olof Hjorth",
                    "role": "ordf."
                },
                {
                    "name": "Stig Hjorth",
                    "role": "dir."
                },
                {
                    "name": "Ivar Kull",
                    "role": "dir."
                }
            ],
            "manager": "Stig Hjorth"
        },
        "9": {
            "name": "Nordiska Stansknivfabriken & Mek. Verkstad",
            "location": "Örebro",
            "products": "Tillverkar stansknivar, byggnadssmiden m. m.",
            "contact": {
                "office": "Postfack 3020, Örebro 3",
                "phone": [
                    "14759"
                ],
                "postgiro": "71097"
            },
            "financials": {
                "capital": "22,500 kr",
                "employees": {
                    "industriarb": 20
                },
                "annual_turnover": "200,000 kr"
            },
            "foundation_year": 1929
        },
        "10": {
            "name": "Nordiska Syrgasverken AB.",
            "location": "Stockholm",
            "products": "Framställer syrgas, vätgas, kvävgas samt komprimerad luft.",
            "contact": {
                "office": "Stockholm, Kungsg. 13",
                "phone": [
                    "201188",
                    "201233"
                ],
                "postgiro": "825",
                "sales_offices": {
                    "Örebro": "11218—19",
                    "Göteborg": "223891 o. 223991",
                    "Motala": "85",
                    "Hedemora": "575",
                    "Trollhättan": "10008"
                }
            }
        }
    }
}