{
    "original": "Andersson\n\ntal industriarb.: 20. Tillv.-värde pr år:\n550,000 kr. — Firman etabl. 1938.\n\nÄgare o. chef: fabr. E. Einar\nAndersson.\n\nEmil Anderssons Nysilverfabrik\nEftr., Bröderna Andersson,\n\nBarikeryd.\n\nNysilverfabrik i Bankeryd (Jönköp. l.).\nTillverkar kuvertnysilver.\n\nTelefon: Jönköping 1764. Postgiro:\n71413. — Firman etabl. 1928.\n\nÄgare o. chefer: fabr. Gustav\nAndersson o. fabr. Åke Andersson.\n\n\"Erik Andersson, Byggmästare,\n\nLinköping.\n\nSe Byggnadsfirman Erik Andersson\nAB., Linköping.\n\n\"AB. Eric Andersson &amp; Co.\nSkofabriker, Hallsberg.\n\nSkofabriker i Hallsberg (Örebro l.).\nTillverkar randsydda och ago-skodon,\npjäxor och sportskodon. Varumärken:\n»Birgittaskon», »Glaciär», »Hector» o.\n»Senorita».\n\nTelefon: 208 o. 448. Postgiro: 141336.\nEnsamförsälj.: Handelsbolaget Karl\nTheorell, Mjölby; telefon: 17.\n\nAkt.-kap.: 25,000 kr. Antal\nindustriarb.: 90. Tillv.-värde pr år: 900,000 kr. —\nBolaget grundat 1938.\n\nStyrelse: dir. Gustaf A. Carlsson\n(ordf.), grossh. Rudolf Carlsson, disp.\nElis Nylin.\n\nVerJcst. dir.: Gustaf Carlsson.\nDisp.: E. Nylin.\n\nErik Anderssons Tröskmaskin-\n\nfabrik, Kristinehamn.\n\nTillverkar tröskverk samt agn- och\nboss-ifläktar. Varumärken: »Wega» o. »Vega\nPatent». Firman driver även försäljning\nav lantbruksmaskiner och redskap samt\nmaski nf örnödenheter.\n\nTelefon: 10333 o. 11062. Postgiro:\n:28602. — Antal industriarb.: 30.\nTillv.-värde pr år: 360,000 kr. — Firman etabl.\n1902.\n\nÄgare o. chef: fabr. Erik Andersson.\n\nInköps- o. försäljn.-chef: John Eric\nAndersson.\n\n2\n\nErnst Andersson Handskfabrik AB.,\n\nHälsingborg.\n\nTillverkar gants de Suéde, glacé- och\nnappahandskar, renhuds- och\nsämsk-skinnshandskar samt foderhandskar.\n\nTelefon: 11833. Postgiro: 9816,\n-Akt.-kap.: 75,000 kr. Antal industriarb.: 40.\nTillv.-värde pr år: 150,000 kr. — Firman\netabl. 1906, bolag 1945.\n\nVerJcst. dir.: fabr. Algot Andersson.\n\nFabian Andersson, Sävsjö-hus,\n\nSävsjö.\n\nSe Sävsjö-hus, Fabian Andersson,\nSävsjö.\n\nFingal Anderssons\nTräförädlings-fabrik, Gnosjö.\n\nSe Gnosjö Trämanufaktur, Gnosjö.\n\nAB. Cerh. Andersson,\nCalvanise-ringsfabrik &amp; Pressverk, Lyckeby.\n\nGalvaniseringsfabrik och pressverk i\nLyckeby (Blekinge l.).\nSpecialtillverkning av galvaniserade hinkar, baljor,\nskopor, konserveringsapparater, sopkärl,\navfallsbehållare, såpkärl, asfalterade\nlatrinkärl m. m.\n\nTelegr.-adr.: Galvanfabriken, Lyckeby.\nTelefon: Lyckeby 49. Postgiro: 72930.\n\nRepresentanter: i Stockholm:\nStockholms Järnvaru Bolag, Hudiksvallsg. 8,\ntelefon: 234240, och Rundquist &amp; Schultz\nAB., Slussplan 9, telefon: »Rundquist &amp;\nSchultz»; i Göteborg: Axel H. Ågren,\nKungsg. 4, telefon: 172060; i Malmö:\nRosengren &amp; Riis AB., telefon: 71130 o.\nEdw. H. Thomée AB., telefon: »Thomées\nJärn»\n\nAkt.-kap.: 337,500 kr. Antal\nindustriarb.: 35. Tillv.-värde pr år: 880,000 kr.\n— Firman etabl. 1918.\n\nStyrelse: godsäg. Karl Olsson (ordf.),\ngodsäg. Theodor Anderson, notarie Curt\nArnewi, nämndem. Olof Håkansson,\ngodsäg. Oskar Persson.\n\nVerJcst. dir. o. disp.: Knut V.\nBrent-ner.\n\n*AB. Herbert Anderssons\nMöbelverkstäder, Gärsnäs.\n\nMöbelfabrik och sågverk i Gärsnäs\n(Kristianst. l.). Tillverkar möbler och\nsågade trävaror såsom bräder och plank\nsamt lövträämnen. Varumärke: »Gärsnäs\nmöbler».\n\nTelefon: 13. Postgiro: 146863.",
    "structured": {
        "firms": [
            {
                "name": "Emil Anderssons Nysilverfabrik Eftr.",
                "location": "Bankeryd (Jönköp. l.)",
                "business": "Nysilverfabrik",
                "products": "Kuvertnysilver",
                "contact": {
                    "office": "Bröderna Andersson, Bankeryd, Jönköping",
                    "phone": [
                        "Jönköping 1764"
                    ],
                    "postgiro": "71413",
                    "head_office": "Bröderna Andersson, Bankeryd, Jönköping",
                    "factory_office": "Not available",
                    "factory_phone": "Not available"
                },
                "financials": {
                    "capital": "Not available",
                    "employees": {
                        "manufacturing": 20
                    },
                    "annual_turnover": "550,000 kr"
                },
                "foundation_year": 1928,
                "current_name_year": "Not applicable",
                "predecessor": "Not applicable",
                "original_name": "Not applicable",
                "corporation_year": "Not applicable",
                "board": [],
                "owners": [
                    "fabr. E. Einar Andersson"
                ],
                "director": "Not available",
                "managing_director": "Not available",
                "sales_manager": "Not available",
                "manager": "Not available"
            },
            {
                "name": "AB. Eric Andersson & Co. Skofabriker",
                "location": "Hallsberg (Örebro l.)",
                "business": "Skofabriker",
                "products": "Randsydda and ago-skodon, pjäxor, sportskodon",
                "contact": {
                    "office": "Hallsberg, Örebro",
                    "phone": [
                        "208",
                        "448"
                    ],
                    "postgiro": "141336",
                    "head_office": "Hallsberg, Örebro",
                    "factory_office": "Not available",
                    "factory_phone": "Not available"
                },
                "financials": {
                    "capital": "25,000 kr",
                    "employees": {
                        "manufacturing": 90
                    },
                    "annual_turnover": "900,000 kr"
                },
                "foundation_year": 1938,
                "current_name_year": "Not applicable",
                "predecessor": "Not applicable",
                "original_name": "Not applicable",
                "corporation_year": "Not applicable",
                "board": [
                    {
                        "name": "dir. Gustaf A. Carlsson",
                        "role": "ordf."
                    },
                    {
                        "name": "grossh. Rudolf Carlsson",
                        "role": "Not available"
                    },
                    {
                        "name": "disp. Elis Nylin",
                        "role": "Not available"
                    }
                ],
                "owners": [
                    "fabr. Gustav Andersson",
                    "fabr. Åke Andersson"
                ],
                "director": "Not available",
                "managing_director": "Gustaf Carlsson",
                "sales_manager": "Not available",
                "manager": "E. Nylin"
            },
            {
                "name": "Erik Andersson, Byggmästare",
                "location": "Linköping",
                "business": "Byggnadsfirman",
                "products": "Not available",
                "contact": {
                    "office": "Linköping",
                    "phone": [
                        "Not available"
                    ],
                    "postgiro": "Not available",
                    "head_office": "Not available",
                    "factory_office": "Not available",
                    "factory_phone": "Not available"
                },
                "financials": {
                    "capital": "Not available",
                    "employees": {
                        "manufacturing": 20
                    },
                    "annual_turnover": "Not available"
                },
                "foundation_year": "Not available",
                "current_name_year": "Not applicable",
                "predecessor": "Not applicable",
                "original_name": "Not applicable",
                "corporation_year": "Not applicable",
                "board": [],
                "owners": [
                    "Erik Andersson"
                ],
                "director": "Not available",
                "managing_director": "Not available",
                "sales_manager": "Not available",
                "manager": "Not available"
            },
            {
                "name": "Erik Anderssons Tröskmaskinfabrik",
                "location": "Kristinehamn",
                "business": "Tröskverk, agn- och bosfläktar, lantbruksmaskiner",
                "products": "Varumärken: 'Wega', 'Vega Patent'",
                "contact": {
                    "office": "Kristinehamn",
                    "phone": [
                        "10333",
                        "11062"
                    ],
                    "postgiro": "28602",
                    "head_office": "Kristinehamn",
                    "factory_office": "Not available",
                    "factory_phone": "Not available"
                },
                "financials": {
                    "capital": "Not available",
                    "employees": {
                        "manufacturing": 30
                    },
                    "annual_turnover": "360,000 kr"
                },
                "foundation_year": 1902,
                "current_name_year": "Not applicable",
                "predecessor": "Not applicable",
                "original_name": "Not applicable",
                "corporation_year": "Not applicable",
                "board": [],
                "owners": [
                    "fabr. Erik Andersson"
                ],
                "director": "Not available",
                "managing_director": "Not available",
                "sales_manager": "Not available",
                "manager": "John Eric Andersson"
            },
            {
                "name": "Ernst Andersson Handskfabrik AB.",
                "location": "Hälsingborg",
                "business": "Handskfabrik",
                "products": "Gants de Suéde, glacé- and nappahandskar, renhuds- and sämsk-skinnshandskar, foderhandskar",
                "contact": {
                    "office": "Hälsingborg",
                    "phone": [
                        "11833"
                    ],
                    "postgiro": "9816",
                    "head_office": "Hälsingborg",
                    "factory_office": "Not available",
                    "factory_phone": "Not available"
                },
                "financials": {
                    "capital": "75,000 kr",
                    "employees": {
                        "manufacturing": 40
                    },
                    "annual_turnover": "150,000 kr"
                },
                "foundation_year": 1906,
                "current_name_year": 1945,
                "predecessor": "Not applicable",
                "original_name": "Not applicable",
                "corporation_year": "Not applicable",
                "board": [],
                "owners": [
                    "fabr. Algot Andersson"
                ],
                "director": "Not available",
                "managing_director": "Not available",
                "sales_manager": "Not available",
                "manager": "Not available"
            },
            {
                "name": "AB. Cerh. Andersson",
                "location": "Lyckeby (Blekinge l.)",
                "business": "Galvaniseringsfabrik & Pressverk",
                "products": "Galvaniserade hinkar, skopor, konserveringsapparater, sopkärl, avfallsbehållare",
                "contact": {
                    "office": "Lyckeby, Blekinge",
                    "phone": [
                        "Lyckeby 49"
                    ],
                    "postgiro": "72930",
                    "head_office": "Lyckeby, Blekinge",
                    "factory_office": "Not available",
                    "factory_phone": "Not available"
                },
                "financials": {
                    "capital": "337,500 kr",
                    "employees": {
                        "manufacturing": 35
                    },
                    "annual_turnover": "880,000 kr"
                },
                "foundation_year": 1918,
                "current_name_year": "Not applicable",
                "predecessor": "Not applicable",
                "original_name": "Not applicable",
                "corporation_year": "Not applicable",
                "board": [
                    {
                        "name": "godsäg. Karl Olsson",
                        "role": "ordf."
                    },
                    {
                        "name": "godsäg. Theodor Anderson",
                        "role": "Not available"
                    },
                    {
                        "name": "notarie Curt Arnewi",
                        "role": "Not available"
                    },
                    {
                        "name": "nämn- dem. Olof Håkansson",
                        "role": "Not available"
                    },
                    {
                        "name": "godsäg. Oskar Persson",
                        "role": "Not available"
                    }
                ],
                "owners": [
                    "Familjen Andersson"
                ],
                "director": "Knut V. Brentner",
                "managing_director": "Knut V. Brentner",
                "sales_manager": "Not available",
                "manager": "Not available"
            },
            {
                "name": "AB. Herbert Anderssons Möbelverkstäder",
                "location": "Gärsnäs (Kristianst. l.)",
                "business": "Möbel- & Sågverk",
                "products": "Möbler, bräder, plank, lövträämnen",
                "contact": {
                    "office": "Gärsnäs, Kristianstad",
                    "phone": [
                        "13"
                    ],
                    "postgiro": "146863",
                    "head_office": "Gärsnäs, Kristianstad",
                    "factory_office": "Not available",
                    "factory_phone": "Not available"
                },
                "financials": {
                    "capital": "Not available",
                    "employees": {
                        "manufacturing": "Not available"
                    },
                    "annual_turnover": "Not available"
                },
                "foundation_year": "Not available",
                "current_name_year": "Not applicable",
                "predecessor": "Not applicable",
                "original_name": "Not applicable",
                "corporation_year": "Not applicable",
                "board": [],
                "owners": [
                    "Familjen Andersson"
                ],
                "director": "Not available",
                "managing_director": "Not available",
                "sales_manager": "Not available",
                "manager": "Not available"
            }
        ]
    }
}