{
    "original": "Dorthé-—Drufvefors\n\nStyrelse: adv. Folke Sjögren (ordf.),\nprof. Arvid Hedvall, disp. Nils Rudell,\ndir. Adolf Svensson.\n\nVerkst. dir.: Adolf Svensson.\n\nFabrihschef: fil. dr Nils Pihlblad.\n\nLaboratoriechef: fil. lie. Hugo\nAndersson.\n\nFörsäljn.-chef: Gunnar Berglund.\n\nDorthés Konservfabrik,\n\nFjällbacJca.\n\nTillverkar ansjovis, sillkonserver och\nkaviar vid fabrik i Fjällbacka (Göteb. o.\nBohus l.).\n\nTelefon: 23 o. 128. Postgiro: 74634. —\nAntal industriarb.: 20. Tillv.-värde pr år:\n150,000 kr. — Firman etabl. 1922.\n\nÄgare o. chef: fabr. Ivar Dorthé.\n\n*\tDrabant, Konfektions AB.,\n\nAlingsås.\n\nSe Konfektions AB. Drabant, Alingsås.\n\n*\tDragéfabriken, Carl Klein, Gävle.\n\nKonfektyrfabrik. Tillverkar dragéer.\n\nTelefon: 4384. Postgiro: 140718. —\nArb.-antal: 5. — Firman etabl. 1938.\n\nÄgare o. chef: fabr. Carl Klein.\n\n*Drags AB., Norrköping.\n\nKamgarns- och streichgarnsspinneri,\nväveri, appreturverk och färgeri.\nTillverkar helylletyger.\n\nHuvudkontor: Norrköping.\nTelegr.-adr.: Dragsbolaget, Norrköping. Telefon:\n»Drags Bolag». Postgiro: 8441.\nAvd.-kon-tor: Stockholm, Regeringsg. 19—21,\ntelefon: 115592; Göteborg, O. Hamng. 15,\ntelefon: 136282; ombud i Malmö: F.\nOdenrick. Exercisg. 2 B, telefon: 27538.\n\nAkt.-kap.: 1,800,000 kr. Antal\nindustriarb.: 300. Tillv.-värde pr år: 4,300,000\nkr. — Fabriken anlagd 1642, nuv. bolag\ngrundat 1854.\n\nStyrelse: överdir. Ryno Lundquist\n(ordf.), disp. Evert Björkne, konsul Eric\nEnhörning, disp. Ragnar Öländer.\n\nVerkst. dir.: Evert Björkne.\n\nFabrihschef: ing. Hermann Derkum.\n\nAvd.-föreståndare: i Stockholm: Elis\nSöderman; i Göteborg: Ebbe B. Johnson.\nRepr. i Malmö: F. Odenrick.\n\nDragspelsfabriken Skandia, V. B i se,\n\nGöteborg.\n\nTillverkar dragspel. Varumärke:\n»Skandia».\n\nKontor: ö. Hamng. 50 A. Telefon:\n133488. Postgiro: 42753. Repr.: Skandia\nMusik AB., Örebro, telefon: 16385.\n\nAntal industriarb.: 7. Tillv.-värde pr\når: 50,000 kr. — Firman etabl. 1931.\n\nÄgare o. chef: fabr. Victor Dise.\n\n*AB. Dress, Göteborg.\n\nKonfektionsfabrik. Tillverkar herr- och\ngosskläder samt damkappor och\ndamdräkter. Varumärke: »Dress».\n\nKontor: Gamlestadsv. 1 A.\nTelegr.-adr.: Dress, Göteborg. Telefon: 192500.\nPostgiro: 41200.\n\nAntal industriarb.: 200. Tillv.-värde pr\når: 3,000,000 kr. — Firman grundad 1916\nunder namn Nya AB. Herr- &amp;\nGossklä-derfabriken.\n\nStyrelse: dir. Thorbjörn Holm (ordf.),\ndir. Fredrik Holm, dir. Henning C.\nSet-tergren, dir. Oscar Stenberg.\n\nVerkst. dir.: O. Stenberg.\n\n*Drev &amp; Trassel, Fabriks AB.,\n\nGöteborg.\n\nSe Fabriks AB. Drev &amp; Trassel,\nGöteborg.\n\nDrott, Vaddfabriken, Nässjö.\n\nSe Vaddfabriken Drott, Nässjö.\n\nH. I. Drucker &amp; Son AB., Malmö.\n\nPälsvarufabrik. Tillverkar dampälsar,\nkragar och muffar samt pälsmössor.\n\nKontor: S. Förstadsg. 18. Telegr.-adr.:\nDrucker, Malmö. Telefon: 15055 o. 26905.\n\nAkt.-kap.: 300,000 kr. Antal\nindustriarb.: 40. — Firman etabl. 1847, bolag\n1941.\n\nVerkst. dir.: A. Goldschmidt.\n\n* Drufvefors Väfveri AB., Borås.\n\nBomullsväveri och ylleväveri samt\nfärgeri och blekeri. Tillverkar kulörta\nbomulls- och konstsilkevävnader samt\nyllevävnader.\n\nTelegr.-adr.: Drufvefors, Borås.\nTelefon: 17175 o. »Drufvefors väveri».\nPostgiro: 140130.\n\nAkt.-kap.: 1,537,900 kr. Antal\nindustriarb.: 250. Tillv.-värde pr år: 6,500,000 kr.\n— Bolaget grundat 1871.\n\nStyrelse: bankdir. Bertil Odelfelt\n(ordf.), ryttmäst. H. v. Bornstedt, prof.\nGerhard Forssell, dir. Hj. Grahl, ing. A.\nG. Snickars.\n\nVerkst. dir.: H. v. Bornstedt.\n\n110*",
    "structured": {
        "1": {
            "name": "Dorthé-—Drufvefors",
            "location": "FjällbacJca",
            "business": "Tillverkar ansjovis, sillkonserver och kaviar",
            "products": "vid fabrik i Fjällbacka (Göteb. o. Bohus l.)",
            "contact": {
                "phone": [
                    "23",
                    "128"
                ],
                "postgiro": "74634"
            },
            "financials": {
                "capital": "",
                "employees": {
                    "industriarb": 20
                },
                "annual_turnover": "150,000 kr",
                "annual_production_value": "150,000 kr"
            },
            "foundation_year": 1922,
            "owner": "fabr. Ivar Dorthé"
        },
        "2": {
            "name": "Drabant, Konfektions AB.",
            "location": "Alingsås",
            "business": "Se Konfektions AB. Drabant, Alingsås."
        },
        "3": {
            "name": "Dragéfabriken, Carl Klein",
            "location": "Gävle",
            "business": "Tillverkar dragéer",
            "contact": {
                "phone": "4384",
                "postgiro": "140718"
            },
            "financials": {
                "employees": {
                    "industriarb": 5
                },
                "annual_turnover": "",
                "annual_production_value": ""
            },
            "foundation_year": 1938,
            "owner": "fabr. Carl Klein"
        },
        "4": {
            "name": "Drags AB.",
            "location": "Norrköping",
            "business": "Kamgarns- och streichgarnsspinneri, väveri, appreturverk och färgeri. Tillverkar hel ylteyger.",
            "contact": {
                "head_office": "Norrköping",
                "sales_offices": [
                    {
                        "location": "Stockholm",
                        "phone": "115592"
                    },
                    {
                        "location": "Göteborg",
                        "phone": "136282"
                    },
                    {
                        "location": "Malmö",
                        "phone": "27538"
                    }
                ],
                "telegraph": "Dragsbolaget, Norrköping",
                "postgiro": "8441",
                "factory_phone": "Drags Bolag",
                "factory_office": "Dragsbolaget, Norrköping"
            },
            "financials": {
                "capital": "1,800,000 kr",
                "employees": {
                    "industriarb": 300
                },
                "annual_turnover": "4,300,000 kr",
                "annual_production_value": "4,300,000 kr"
            },
            "foundation_year": 1854,
            "board": [
                {
                    "name": "Ryno Lundquist",
                    "role": "ordf."
                },
                {
                    "name": "Evert Björkne",
                    "role": "disp."
                },
                {
                    "name": "Eric Enhörning",
                    "role": "konsul"
                }
            ]
        },
        "5": {
            "name": "Dragspelsfabriken Skandia, V. B i se",
            "location": "Göteborg",
            "business": "Tillverkar dragspel",
            "products": "Varumärke: »Skandia»",
            "contact": {
                "phone": "133488",
                "postgiro": "42753"
            },
            "financials": {
                "employees": {
                    "industriarb": 7
                },
                "annual_turnover": "50,000 kr",
                "annual_production_value": "50,000 kr"
            },
            "foundation_year": 1931,
            "owner": "fabr. Victor Dise"
        },
        "6": {
            "name": "AB. Dress",
            "location": "Göteborg",
            "business": "Tillverkar herr- och gosskläder samt damkappor och damdräkter",
            "products": "Varumärke: »Dress»",
            "contact": {
                "office": "Gamlestadsv. 1 A",
                "postgiro": "41200"
            },
            "financials": {
                "employees": {
                    "industriarb": 200
                },
                "annual_turnover": "3,000,000 kr",
                "annual_production_value": "3,000,000 kr"
            },
            "foundation_year": 1916,
            "board": [
                {
                    "name": "Thorbjörn Holm",
                    "role": "ordf."
                },
                {
                    "name": "Fredrik Holm",
                    "role": "dir."
                },
                {
                    "name": "Henning C. Settergren",
                    "role": "dir."
                }
            ],
            "owner": ""
        },
        "7": {
            "name": "Drev &amp; Trassel, Fabriks AB.",
            "location": "Göteborg",
            "business": "Se Fabriks AB. Drev &amp; Trassel, Göteborg."
        },
        "8": {
            "name": "Drott, Vaddfabriken",
            "location": "Nässjö",
            "business": "Se Vaddfabriken Drott, Nässjö."
        },
        "9": {
            "name": "H. I. Drucker &amp; Son AB.",
            "location": "Malmö",
            "business": "Tillverkar dampälsar, kragar och muffar samt pälsmössor",
            "contact": {
                "office": "S. Förstadsg. 18",
                "telegraph": "Drucker, Malmö",
                "phone": [
                    "15055",
                    "26905"
                ]
            },
            "financials": {
                "capital": "300,000 kr",
                "employees": {
                    "industriarb": 40
                },
                "annual_turnover": "",
                "annual_production_value": ""
            },
            "foundation_year": 1941,
            "owner": ""
        },
        "10": {
            "name": "Drufvefors Väfveri AB.",
            "location": "Borås",
            "business": "Bomullsväveri och ylleväveri samt färgeri och blekeri. Tillverkar kulörta bomulls- och konstsilkevävnader samt yllevävnader",
            "contact": {
                "telegraph": "Drufvefors, Borås",
                "phone": "17175",
                "postgiro": "140130"
            },
            "financials": {
                "capital": "1,537,900 kr",
                "employees": {
                    "industriarb": 250
                },
                "annual_turnover": "6,500,000 kr",
                "annual_production_value": "6,500,000 kr"
            },
            "foundation_year": 1871,
            "board": [
                {
                    "name": "Bertil Odelfelt",
                    "role": "bankdir."
                },
                {
                    "name": "H. v. Bornstedt",
                    "role": "ordf."
                },
                {
                    "name": "Gerhard Forssell",
                    "role": "prof."
                }
            ],
            "owner": ""
        }
    }
}