{
    "original": "Dockans—Dordi\n\nPostadr.: Kallinge station.\nTelegr.-adr.: Djupafors, Ronneby. Telefon:\n»Djupafors bruk». Postgiro: 72456.\n\nAkt.-kap.: 4,000,000 kr. Antal\nindustriarb.: 125. Årstillv.: 10,000 ton papp o.\nkartong. — Bolaget, grundat 1868, äges\nav Sydsvenska Kraft AB.\n\nStyrelse: dir. Emil Olsson (ordf.),\nriks-dagsm. Edvin Berling (v. ordf.),\nriks-dagsm. Olof Andersson, dir. Jonte\nHult-krantz, lokförare F. Hägertz, expeditör\nPer Larsson, civiling. Carl-Axel Nilsson,\nlektor Sven Olsson, riksdagsm. Wald.\nOlsson, ombudsm. Nils O. Persson,\nom-budsm. Harald Sclioug.\n\nDisp.: G. C. Hansen.\n\nDriftsing.: B. Gullberg.\n\nKamrer: Nils Johnsson.\n\nDockans Fabriks AB.,\n\nSöderköping.\n\nMek. verkstad, förnicklings- och\nsnickerifabrik. Tillverkar som specialitet\nbarnvagnar samt utför pressarbeten.\n\nFabrikskontor: Söderköping. Telefon:\n435. Affärskontor: Norrköping, Borgsg.\n5, telefon: 20297. Postgiro: 131783.\n\nAkt.-kap.: 30,000 kr. Antal\nindustriarb.: 35. Tillv.-värde pr år: 300,000 kr.\n— Bolaget grundat 1936.\n\nStyrelse o. verkst. dir:: Erik\nWäs-ström (Norrköping).\n\n* Domkraft AB, Nike, Eskilstuna.\n\nMek. verkstad och aduceringsgjuteri.\nTillverkar mekaniska och hydrauliska\nlyftaggregat, spec. automobildomkrafter\noch hydrauliska frisörstolar samt\nadu-ceringsgods såväl obearbetat som\nfärdigbearbetat. Varumärke: »Nike».\n\nTelegr.-adr.: Nikedomkraft, Eskilstuna.\nTelefon: 32439, 34469, 35669 o. 30811.\nPostgiro: 85282.\n\nAkt.-kap.: 550,000 kr. Antal\nindustriarb.: 105. — Fabriken anlagd 1926, bolag\n1937. Bolaget tillhör Kooperativa\nFörbundet.\n\nStyrelse: dir. Albin Johansson (ordf.),\nfil. lic. Mauritz Bonow, dir. Hj.\nDeger-stedt, dir. Hugo Eclstam, dir. G. Osvalcl,\ndir. Ernst Persson.\n\nDisp.: fabr. Herbert Landin.\n\n*Domnarfvets Jernverk, Domnarvet.\n\nJärn- och stålverk med elektr. och\nbläs-termasugnar, elektr. stålugnar, elektr.\nlegeringsugnar, stålgjuteri, valsverk, mek.\nverkstad, plåtslageriverkstad,\nmanufaktursmedja, elektrodfabrik, tegelbruk m. m.\ni Borlänge.\n\nTillverkar stångjärn, fason järn, balkar,\nräls, plåt, fartygsplåt, band järn, val st råd,\nledningstråd, svetsningstråd,\nsvetselektroder, rälsspik, vägtrummor, stålgjutgods\nsamt thomasfosfat och syrgas.\n\nTelegr.-adr.: J ernverket, Domnarvet.\nTelefon: »Domnarfvets Jernverk»,\nBorlänge. — Antal industriarb.: 2,700.\nÅrstillv.: 200,000 ton järnvaror.\n\nJärnverket, som anlades 1873—78, äges\nav Stora Kopparbergs Bergslags AB. (se\ndetta bolag).\n\nVerkschef: dir. Sixten Wohlfahrt.\n\nÖvering.: Sven v. Hofsten.\n\nFörsäljn.-chef: intendent Bror Hanson.\n\nDomsands Verkstads AB., Bankeryd.\n\nTillverkar pressade massartiklar för\nradio- o. elarmatur, penselringar m. m.,\nhel- och halvautomatiska pressverktyg,\nslidmatningar för excenterpressar,\nspecialmaskiner m. m. vid mek. verkstad i\nBankeryd (Jönköp. l.).\n\nTelefon: 194. Postgiro: 173799. ■ —\nAkt.-kap.: 25,000 kr. Antal industriarb.:\n35. Tillv.-värde pr år: 425,000 kr. —\nFirman etabl. 1941.\n\nVerkst. dir.: fabr. Eskil H. Bengtson.\n\nKamrer: Peter Räf.\n\n* Domsjö Ångsåg o. Sulfitfabrik,\n\nDomsjöverken.\n\nSe Mo och Domsjö AB., Stockholm o.\nHärnösand.\n\n*Dorclt, Bäcksin &amp; Co:s AB.,\n\nGöteborg.\n\nFärg-, ferniss- och kem.-tekn. fabrik\n\nvid Agnesberg (Älvsb. l.).\n\nTillverkar lack-, olje-, sprit- och\ncellulosafärger, synt. klarlacker och\nlackfärger, fernissor alla slag, cellulosalacker,\nklorkautschukfärger, rostskydds- och\nmaskinfärger, torkmedel, ugnslacker,\nputs-och polérmedel, kem. tekn. artiklar m. m.\nVarumärken: Ariman, Diabol, Chinalack,\nD. B. C., Dorsin, Metrol, Faktor,\nHerku-les, Solitaire, Spar-Var, 2350, Nepi Matt,\nNeptulin, Neptun, Nicol, Synpal,\nVieto-rit m. fl.\n\nHuvudkontor: Göteborg, N. Hamng. 24.\nTelegr.-adr.: Dorch, Göteborg. Télefon:\n»Dorch Bäcksin». Postgiro: 44000.\nAvd.-kontor: Stockholm, Brunkebergsg. 3,\ntelefon: 102456; Malmö: Hermansg. 7,\ntelefon: 18770.\n\nAkt.-kap.: 1,250,000 kr. Antal\nindustriarb.: 125. — Firman etabl. 1889, bolag\n1897.\n\n",
    "structured": {
        "firms": [
            {
                "name": "Dockans Fabriks AB",
                "location": "Söderköping",
                "business": "Mekanisk verkstad, förnicklings- och snickerifabrik",
                "contact": {
                    "office": "Söderköping",
                    "phone": "435",
                    "postgiro": "131783"
                },
                "financials": {
                    "capital": "30,000 kr",
                    "employees": {
                        "industriarb": 35
                    },
                    "annual_production_value": "300,000 kr"
                },
                "foundation_year": 1936,
                "board": [
                    {
                        "name": "Erik Wäström",
                        "role": "Verkställande direktör (Norrköping)"
                    }
                ]
            },
            {
                "name": "Domkraft AB",
                "location": "Nike, Eskilstuna",
                "business": "Mekanisk verkstad och aduceringsgjuteri",
                "contact": {
                    "office": "Eskilstuna",
                    "phone": "32439, 34469, 35669, 30811",
                    "postgiro": "85282",
                    "telegraph": "Nikedomkraft, Eskilstuna"
                },
                "financials": {
                    "capital": "550,000 kr",
                    "employees": {
                        "industriarb": 105
                    }
                },
                "foundation_year": 1937,
                "board": [
                    {
                        "name": "Albin Johansson",
                        "role": "Ordförande"
                    },
                    {
                        "name": "Mauritz Bonow",
                        "role": "Filosofie licentiat"
                    },
                    {
                        "name": "Hj. Degerstedt",
                        "role": "Direktör"
                    },
                    {
                        "name": "Hugo Eclstam",
                        "role": "Direktör"
                    },
                    {
                        "name": "G. Osvalcl",
                        "role": "Direktör"
                    },
                    {
                        "name": "Ernst Persson",
                        "role": "Direktör"
                    }
                ],
                "director": "Herbert Landin"
            },
            {
                "name": "Domnarfvets Jernverk",
                "location": "Domnarvet",
                "business": "Järn- och stålverk",
                "contact": {
                    "office": "Borlänge",
                    "phone": "Domnarfvets Jernverk, Borlänge",
                    "telegraph": "Jernverket, Domnarvet"
                },
                "financials": {
                    "employees": {
                        "industriarb": 2700
                    },
                    "annual_production_value": "200,000 ton järnvaror"
                },
                "board": [
                    {
                        "name": "Sixten Wohlfahrt",
                        "role": "Verkschef"
                    },
                    {
                        "name": "Sven v. Hofsten",
                        "role": "Övering. (överingenjör)"
                    },
                    {
                        "name": "Bror Hanson",
                        "role": "Försäljningschef"
                    }
                ]
            },
            {
                "name": "Domsands Verkstads AB",
                "location": "Bankeryd",
                "business": "Tillverkning av pressade massartiklar för radio- o. elarmatur, penselringar m. m.",
                "contact": {
                    "office": "Bankeryd",
                    "phone": "194",
                    "postgiro": "173799"
                },
                "financials": {
                    "capital": "25,000 kr",
                    "employees": {
                        "industriarb": 35
                    },
                    "annual_production_value": "425,000 kr"
                },
                "foundation_year": 1941,
                "board": [
                    {
                        "name": "Eskil H. Bengtson",
                        "role": "Verkställande direktör"
                    },
                    {
                        "name": "Peter Räf",
                        "role": "Kamrer"
                    }
                ]
            },
            {
                "name": "Dorclt, Bäcksin & Co:s AB.",
                "location": "Göteborg",
                "business": "Färg-, ferniss- och kem.-tekn. fabrik vid Agnesberg (Älvsb. l.)",
                "contact": {
                    "office": "Göteborg",
                    "phone": "N. Hamng. 24",
                    "postgiro": "44000",
                    "sales_offices": [
                        {
                            "location": "Stockholm",
                            "phone": "Brunkebergsg. 3, 102456"
                        },
                        {
                            "location": "Malmö",
                            "phone": "Hermansg. 7, 18770"
                        }
                    ]
                },
                "financials": {
                    "capital": "1,250,000 kr",
                    "employees": {
                        "industriarb": 125
                    }
                },
                "foundation_year": 1889
            }
        ]
    }
}