{
    "original": "Lange—Larsson\n\nJanson, dir. Carl Joh. Malmros, dir. Axel\nWahlsteen.\n\nVerkst. dir.: Arvid Janson.\n\növeringenjörer: David Gustavsson o.\nWilh, Buchegger.\n\nFörsäljn.-chef: Åke Andreasson.\n\nKamrer: Stig Nordström.\n\nV erhstadschef: Edvin Söhr.\n\nL. J. Lange, AB., Göteborg.\n\nOptisk industri och finmekanisk\nverkstad. Tillverkar glasögon, termometrar,\nglasapparater m. m. Varumärken: »Elila»\no. »Optal».\n\nKontor: Värmlandsg. 16.\nTelegr.-adr.: Glasögonlange, Göteborg. Telefon:\n140760—62. Postgiro: 12040.\n\nAkt.-kap.: 200,000 kr. Arb.-antal: 12.\nTillv.-värde pr år: 165,000 kr. — Firman\netabl. 1881, bolag 1923.\n\nStyrelse o. verkst. dir.: Hugo Schramm.\n\nAB. Lanna Stenhuggeri,\n\nLannabruh.\n\nStenhuggeri vid Lanna, Lannabruk\n(Örebro l.), marmorbrott vid Näs,\nGropp-torp (Södermanl. l.). Bryter och förädlar\nsvensk kalksten och marmor till\nbyggnadsarbeten såsom trappor, golv,\nfönsterbänkar, väggbeklädnader och öppna\nspisar; tillverkar elektr. plattor, gravvårdar,\nmöbelmarmor samt levererar råsten till\nträdgårdsanläggningar och murverk.\n\nKontor: Lannabruk. Telefon:\nHidinge-bro 6. Godsadr.: Hidingebro. Postgiro:\n75453. — Akt.-kap.: 47,000 kr. Antal\nindustriarb.: 48. Tillv.-värde pr år: 350,000\nkr. — Firman etabl. 1895, bolag 1925.\n\nStyrelse o. verkst. dir.: Eric G.\nSöderberg. ^\n\nDriftsing.: Alf Ljunggren.\n\nJoh. K. Lannmark, Mek. Verkstad,\n\nStockholm.\n\nTillverkar transportanordningar,\nbagerimaskiner samt utför modell- och\nexperimentmaskiner.\n\nKontor: Bondeg. 17. Telefon: 415666.\nPostgiro: 150861. — Arb.-antal: 14.\nTillv.-värde pr år: 140,000 kr. — Firman\netabl. 1904.\n\nÄgare o. chef: ing. Gunnar Lannmark.\n\nLantmännens Byggnads AB., iAind.\n\nEntreprenörfirma för bostads- och\nlantmannabyggnader.\n\nKontor: Lund. Telefon: 16884. -\nAkt.-kap.: 100,000 kr. — Bolaget, grundat\n1945, är dotterbolag till Skogsägarnas\nIndustri AB., Växjö (se detta bolag).\n\nVerkst. dir.: Gösta Edström.\n\n\"AB. T. H. Lapidus, Borås.\n\nDamkonfektionsfabrik i Borås,\ntrikå-fabrik i Olsfors, Hultafors (Älvsb. l.).\nTillverkar trikåvaror i bomull, ylle, silke\noch charmeuse samt dam- och\nfliek-klänningar. Varumärken: »Soltrikå» o.\n»Svikt».\n\nTelegr.-adr.: Fabriken, Borås. Telefon:\nBorås 10112, 13112 o. 11931, Hultafors\n95013 o. 95028. Postgiro: 20612. Repr. i\nStockholm: Per Jute, St. Ny g. 40,\ntelefon: 107847.\n\nAkt.-kap.: 442,000 kr. Antal\nindustriarb.: i Borås 42, i Olsfors 107.\nTillv.-värde pr år: 2,150,000 kr. — Firman\netabl. 1880, bolag 1924.\n\nStyrelse: grossh. Jacob Lapidus\n(ordf.), grossh. Gottlieb Lapidus, fru S.\nLapidus.\n\nVerkst. dir.: Jacob Lapidus.\n\nLarsbo Kalk AB.,\n\nGuldsmedshyttan.\n\nKalkstens- och dolomitbrott samt\nkalkbruk vid Larsbo, Guldsmedhyttan\n(Örebro l.). Bryter kalksten och dolomit samt\nframställer bränd kalk för byggnads- och\njordbruksändamål. Bolaget idkar även\njordbruk och skogshantering.\n\nHuvudkontor: Bofors. Fabrikskontor:\nGuldsmedshyttan. Telefon:\nGuldsmedshyttan 20. Postgiro: 71138.\n\nAkt.-kap.: 250,000 kr. Antal\nindustriarb.: 50. Tillv.-värde pr år: 600,000 kr.\n\n—\tBolaget, grundat 1899, är dotterbolag\ntill AB. Bofors.\n\nStyrelse: dir. Evert Wijkander (ordf.),\ndisp. Helmer Nordqvist.\n\nDisp.: Helmer Nordqvist.\n\nFörvalt. i Larsbo: Helge Jansson.\n\n* Larsbo-N or ns AB., Vikmanshyttan.\n\nSe Wikmanshytte Bruks AB.,\nVikmanshyttan.\n\n*0. Larsens Modellsnickeri, Malmö.\n\nTillverkar gjutmodeller och alla slags\ntekniska träarbeten.\n\nKontor: V. Långg. 5. Telefon: 21332.\nPostgiro: 39311. — Antal industriarb.: 7.\n\n—\tFirman etabl. 1932.\n\nÄgare o. chef: fabr. Oscar Larsen.\n\n\"Larsson &amp; Johansson, Kumla.\n\nSkofabrik i Kumla (Örebro l.).\nTillverkar dam- och barnskodon. Varumärke:\n»Roxy».",
    "structured": {
        "1": {
            "name": "L. J. Lange, AB.",
            "location": "Göteborg",
            "business": "Optisk industri och finmekanisk verkstad",
            "products": "Tillverkar glasögon, termometrar, glasapparater m. m. Varumärken: »Elila» o. »Optal».",
            "contact": {
                "office": "Värmlandsg. 16",
                "phone": [
                    "140760-62"
                ],
                "postgiro": "12040",
                "telegraph": "Glasögonlange, Göteborg"
            },
            "financials": {
                "capital": "200,000 kr",
                "employees": {
                    "Arbetsgivare": 12
                },
                "annual_turnover": "165,000 kr",
                "annual_production_value": "165,000 kr"
            },
            "foundation_year": 1881,
            "corporation_year": 1923,
            "board": [
                {
                    "name": "Hugo Schramm",
                    "role": "Styrelse o. verkst. dir."
                }
            ]
        },
        "2": {
            "name": "AB. Lanna Stenhuggeri",
            "location": "Lannabruh",
            "business": "Stenhuggeri",
            "products": "Bryter och förädlar svensk kalksten och marmor till byggnadsarbeten såsom trappor, golv, fönsterbänkar, väggbeklädnader och öppna spisar; tillverkar elektr. plattor, gravvårdar, möbelmarmor samt levererar råsten till trädgårdsanläggningar och murverk.",
            "contact": {
                "office": "Lannabruk",
                "phone": [
                    "Hidingebro 6"
                ],
                "postgiro": "75453"
            },
            "financials": {
                "capital": "47,000 kr",
                "employees": {
                    "industriarb": 48
                },
                "annual_production_value": "350,000 kr"
            },
            "foundation_year": 1895,
            "corporation_year": 1925,
            "board": [
                {
                    "name": "Eric G. Söderberg",
                    "role": "Styrelse o. verkst. dir."
                }
            ]
        },
        "3": {
            "name": "Joh. K. Lannmark, Mek. Verkstad",
            "location": "Stockholm",
            "business": "Tillverkar transportanordningar, bagerimaskiner samt utför modell- och experimentmaskiner",
            "contact": {
                "office": "Bondeg. 17",
                "phone": [
                    "415666"
                ],
                "postgiro": "150861"
            },
            "financials": {
                "employees": {
                    "Arb.-antal": 14
                },
                "annual_production_value": "140,000 kr"
            },
            "foundation_year": 1904,
            "manager": "Gunnar Lannmark"
        },
        "4": {
            "name": "Lantmännens Byggnads AB.",
            "location": "Malmö",
            "business": "Entreprenörfirma för bostads- och lantmannabyggnader",
            "contact": {
                "office": "Lund"
            },
            "financials": {
                "capital": "100,000 kr"
            },
            "director": "Gösta Edström"
        },
        "5": {
            "name": "AB. T. H. Lapidus",
            "location": "Borås",
            "business": "Damkonfektionsfabrik",
            "products": "Tillverkar trikåvaror i bomull, ylle, silke och charmeuse samt dam- och fliek-klänningar. Varumärken: »Soltrikå» o. »Svikt».",
            "contact": {
                "telegraph": "Fabriken, Borås",
                "phone": [
                    "Borås 10112",
                    "13112",
                    "11931",
                    "Hultafors 95013",
                    "95028"
                ],
                "postgiro": "20612"
            },
            "financials": {
                "capital": "442,000 kr",
                "employees": {
                    "industriarb.": "i Borås 42, i Olsfors 107"
                },
                "annual_production_value": "2,150,000 kr"
            },
            "foundation_year": 1880,
            "corporation_year": 1924,
            "board": [
                {
                    "name": "Jacob Lapidus",
                    "role": "Styrelse"
                },
                {
                    "name": "Gottlieb Lapidus",
                    "role": "Styrelse"
                },
                {
                    "name": "fru S. Lapidus",
                    "role": "Styrelse"
                }
            ],
            "director": "Jacob Lapidus"
        },
        "6": {
            "name": "Larsbo Kalk AB.",
            "location": "Guldsmedshyttan",
            "business": "Kalkstens- och dolomitbrott samt kalkbruk",
            "products": "Bryter kalksten och dolomit samt framställer bränd kalk för byggnads- och jordbruksändamål. Bolaget idkar även jordbruk och skogshantering.",
            "contact": {
                "office": "Bofors",
                "factory_office": "Guldsmedshyttan",
                "phone": [
                    "Guldsmedshyttan 20"
                ],
                "postgiro": "71138"
            },
            "financials": {
                "capital": "250,000 kr",
                "employees": {
                    "industriarb": 50
                },
                "annual_production_value": "600,000 kr"
            },
            "foundation_year": 1899,
            "board": [
                {
                    "name": "dir. Evert Wijkander",
                    "role": "Styrelse"
                }
            ],
            "director": "Disp. Helmer Nordqvist"
        },
        "7": {
            "name": "O. Larsens Modellsnickeri",
            "location": "Malmö",
            "business": "Tillverkar gjutmodeller och alla slags tekniska träarbeten",
            "contact": {
                "office": "V. Långg. 5",
                "phone": [
                    "21332"
                ],
                "postgiro": "39311"
            },
            "financials": {
                "employees": {
                    "industriarb.": 7
                }
            },
            "foundation_year": 1932,
            "owner": "fabr. Oscar Larsen"
        },
        "8": {
            "name": "Larsson & Johansson",
            "location": "Kumla",
            "business": "Skofabrik",
            "products": "Tillverkar dam- och barnskodon. Varumärke: »Roxy».",
            "financials": {
                "employees": {
                    "industriarb.": "N/A"
                }
            },
            "foundation_year": "N/A"
        }
    }
}