{
    "original": "A llmänna—A lltryck\n\nKontor: Schéeleg. 28. Telegr.-adr.:\nIdeal, Stockholm. Telefon: 532258—59\nö. 516551. Postgiro: 109.\n\nAkt.-kap.: 100,000 kr. Antal\nindustri-arb.: 25. Tillv.-värde pr år: 400,000 kr.\n— Firman, etabl. 1896, bolag 1940, äger\nWattholma Bruks AB., Stockholm (se\ndetta företag).\n\nStyrelse: ing. Edwin Bergström (ordf.),\nciviling. Erik Bergström, civiling. Knut\nBergström.\n\nVerkst. dir.; Edwin Bergström.\n\nDriftsing.: Erik Bergström.\n\n*Allmänna Svenska Elektriska AB.\n(ASEA), Väst eras.\n\nElektriska och elektromekaniska\nverkstäder i Västerås, Ludvika och Stockholm.\n\nTillverkar elektr. generatorer,\ntransformatorer, motorer, omformare och\nlikrik-tare, starkströmsapparater, reläer och\nspänningsregulatorer, ställverk, gruvspel,\ntraverser, kranar, hissar, spel och telfrar,\nlokomotiv, motorvagnar, släpvagnar och\ntrådbussar, precisionskuggväxlar,\nkugg-växelmotorer oeli koniska kugghjul, ugnar\nför metallurgiska och keramiska\nändamål, borrmaskiner, verktygsmotorer,\noljerenings- och oljeprovningsapparater,\nvarmluftsapparater, isolermateriel samt\nhalvfabrikat för elektr. industrien. Utför\nelektr. järnvägs-, spårvägs-, hiss-, kran-,\nkraftöverförings- och\nbelysningsanläggningar.\n\nBolaget säljer förutom egna\ntillverkningar artiklar tillverkade vid\ndotterbolag såsom elektr. truckar,\nstarkströms-kondensatorer, armatur, elektr. spisar,\nkok- och värmeapparater, elektr.\ninstalla-tionsmateriel samt tillverkningar av\nfrämmande fabrikat såsom radiomateriel,\nglödlampor m. m.\n\nHuvudkontor: Västerås. Telegr.-adr.\no. telefon: Asea. Postgiro: 14000.\n\nFilialkontor: Västerås (telegr.-adr.:\nBergslagsfilial); Stockholm, Klarabergsg.\n21 (telegr.-adr. o. telefon: Asea);\nGöteborg, ö. Hamng. 29; Malmö, Skomakareg.\n6; Norrköping, Drottningg. 39;\nJönköping, Karlstad, Sundsvall, Umeå o.\nÖstersund. Avdelningskontor: Ludvika, Luleå\noch Sollefteå. Avdelning för\ninstalla-tionsmateriel: Stockholm, Rosenlundsg.\n31 (telegr.-adr.: Allsvenska; telefon:\n»Asea-Söder»).\n\nAsea är huvudintressent i:\n\nSurahammars Bruks AB., Surahammar,\n\nAB. Liljeholmens Kabelfabrik, Sthlm,\n\nElektriska AB. Helios, Stockholm,\n\nCebe AB., Svalöv,\n\nLuth &amp; Roséns Elektr. AB., Eskilstuna.\n\nSvenska Turbinfabriks AB.\nLjungström, Finspång,\n\nAB. Svenska Fläktfabriken, Stockholm,\nAB. Skandinaviska Elektricitetsverk,\nStockholm,\nAB. Asea Svetsmaskiner, Stockholm,\nSvenska Elektrobil AB., Stockholm,\nAB. Aseka, Västerås,\nAB. Electro-Invest, Stockholm.\nAkt.-kap.: 90,000,000 kr. Antal\nanställda: 13,714. Bolaget grundat 1883.\n\nStyrelse: dir. J. S. Edström (ordf.),\nkommerserådet Axel F. Enström (v.\nordf.), dir. Thorsten Ericson, dir. Ruben\nRausing, generalkonsul Ragnar\nSöderberg, bankclir. Marcus Wallenberg.\nVerkst. dir.: Thorsten Ericson.\nVerkst. dir:s assistent: dir. Fritz\nLillie-ereutz.\n\nKonsult, tehnish dir.: dr Ragnar\nLiljeblad.\n\nChef för försäljn.- o. anläggningsavd.:\ndir. Y. övergaard.\n\nChef för konstruktions- o.\nanläggningsavd.: dir. Karl E. Eriksson.\n\nChef för procluktionsavd.: dir. O.\nHell-man.\n\nChef för gjuterierna i Västerås:\nbergs-ing. Yngve Granström.\n\nChef för Ludvikatillv. o. assistent åt\nproduktionschefen: övering. Sven Erik\nEriksson.\n\nChef för Stockholmstillverkningen:\növering. Jan Smith.\n\nChef för filialerna: civiling. Olof\nörn-gård.\n\nEkonomidir.: Arnold Landin.\nChef för sekretariatet: civiling. Ralf\nThorburn.\n\nKontrollchef: kamrer John Agnevall.\nInköpschef: civiling. John Lundgren.\nChef för Avd. för installationsmateriel:\ndir. Hugo Edström.\n\n(Jfr annons före Firmarégistret.)\n\n*Allmänna Telefon AB. L. M.\nEricsson, Stockholm.\n\nSe Telefon AB. L. M. Ericsson,\nStockholm.\n\nAB. Allrings Snickerier, Vetlanda.\n\nTillverkar byggnadssnickerier.\nTelefon: »Åsedahus». Postgiro: 280700.\nAkt.-kap.: 50,000 kr. Antal\nindustri-arb.: 50. Tillv.-värde pr år: 600,000 kr.\n\n—\tFirman etabl. 1944.\n\nVerkst. dir. o. disp.: Eric Allring.\nKamrer: Tage Alfredsson.\n\n*Alltryck AB., Ystad.\n\nUtför bok- och aecidenstryck.\n\nTelefon: 14 o. 1402. Postgiro: 134447.\n\n—\tAkt.-kap.: 100,000 kr. Antal industri-",
    "structured": {
        "name": "Allmänna—Alltryck",
        "location": "Stockholm",
        "business": "Publishing and Printing",
        "contact": {
            "office": "Schéeleg. 28",
            "phone": [
                "532258",
                "532259",
                "516551"
            ],
            "postgiro": "109",
            "head_office": "Stockholm",
            "sales_offices": [
                {
                    "location": "Västerås",
                    "phone": "Asea"
                },
                {
                    "location": "Ludvika",
                    "phone": "Asea"
                },
                {
                    "location": "Stockholm",
                    "phone": "Asea"
                },
                {
                    "location": "Göteborg",
                    "phone": "Asea"
                },
                {
                    "location": "Malmö",
                    "phone": "Asea"
                },
                {
                    "location": "Norrköping",
                    "phone": "Asea"
                },
                {
                    "location": "Jönköping"
                },
                {
                    "location": "Karlstad"
                },
                {
                    "location": "Sundsvall"
                },
                {
                    "location": "Umeå"
                },
                {
                    "location": "Östersund"
                }
            ],
            "telegraph": "Ideal, Stockholm"
        },
        "financials": {
            "capital": "100,000 kr",
            "employees": {
                "industrial": 25
            },
            "annual_turnover": "400,000 kr",
            "annual_production_value": "400,000 kr"
        },
        "foundation_year": 1896,
        "corporation_year": 1940,
        "board": [
            {
                "name": "ing. Edwin Bergström",
                "role": "Chairman"
            },
            {
                "name": "civiling. Erik Bergström",
                "role": "Director"
            },
            {
                "name": "civiling. Knut Bergström",
                "role": "Director"
            }
        ]
    }
}