{
    "original": "Kihlgren—Kinna\n\nTelegr.-adr.: Kihlbergs, Hjo. Telefon:\n8 o. 15. Postgiro: 5422. — Antal\nindustriarb.: 45. Tillv.-värde pr år: 660,000 kr.\n— Firman etabl. omkr. år 1860.\n\nÄgare: Handelsbolaget Josef Kihlberg.\n\nDir.: Sven Kihlberg.\n\nKihlgrens Elektrotekniska Byrå,\n\nStockholm.\n\nTillverkar elektr. trappautomater,\nlysande elektr. tryck-knappar,\nsignallamp-hållare samt specialströmbrytare.\nVarumärke: »Vidi».\n\nKontor: S:t Eriksg. 103. Telefon:\n305655 o. 305666. Postgiro: 3048. —\nAntal industriarb.: 8. Tillv.-värde pr år:\n150,000 kr. —Firman etabl. 1917.\n\nÄgare o. chef: Emil W. Kihlgren.\n\nAdolf Kihlströms Manometerfabrik\nEftr., Stockholm.\n\nInstrumentfabrik och mek. verkstad.\nTillverkar manometrar, vacuummetrar,\nmanovacuummetrar, mängdmätare för\ngas, vatten och ånga,\nkvicksilvertermometrar, tensionstermometrar,\nbimetallter-mometrar, termostater och\ninstrumenttavlor.\n\nKontor: Bryggarg. 6 B. Telegr.-adr.:\nTermomano, Stockholm. Telefon: 105339\no. 201182. Postgiro: 156040.\n\nAntal industriarb.: 45. — Firman\netabl. 1876.\n\nÄgare o. chef: ing. Gösta Eriksson.\n\nFörsäljn.-chef: ing. Ivar Möllby.\n\n\"Emil Kihlströms Tryckeri AB.,\n\nStockholm.\n\n^ Utför tidskrift-, katalog-, bok- och\nac-cidenstryck.\n\nKontor: Mästersamuelsg. 22. Telefon:\n102510 o. 103015. Postgiro: 51409.\n\nAkt.-kap.: 90,000 kr. Antal\nindustriarb.: 30. — Firman etabl. 1919 under\nnamn Nya Tryckeribolaget, nuv. namn\n1931.\n\nStyrelse: adv. Knut Strömberg.\n\nVerkst. dir.: vakant.\n\n*Kiholms Tegelbruk, Södertälje.\n\nSe AB. Mälardalens Tegelbruk,\nStockholm.\n\n*Kiirunavaara Malmfält, Kiruna.\n\nSe Luossavaara-Kiirunavaara AB.,\nStockholm.\n\n\"Kiléns Fabriks AB., Ulricehamn.\n\nTrikåfabrik. Tillverkar pullovers,\nstrumpor, jumpers, koftor m. m. av ylle.\n\nTelefon: 430. Postgiro: 83549. —\nAkt.-kap.: 90,000 kr. Antal industriarb.: 25\nsamt 10 hemarbetare. Tillv.-värde pr år:\n500,000 kr. — Firman etabl. 1924, bolag\n1932.\n\nStyrelse o. verkst. dir.: fabr. Olof Kilen.\n\n\"Kilshammars Gjuter i, Kristinehamn.\n\nSe AB. Falköpings Mek. Verkstad,\nFalköping.\n\nKilsmo Sågverk, Kilsmo.\n\nSe Brevens Bruk, Carl Gripenstedt,\nKilsmo.\n\n\"Kilström &amp; Mannerborn, Säffle.\n\nSe Älfängens Tegelbruk, Kilström &amp;\nMannerborn, Säffle.\n\n\"Kilsunds AB., Borås.\n\nYlle- och sidenväverier, färgeri, blekeri\noch appreturverk. Tillverkar ylle- och\nkonstsidenvävnader.\n\nTelegr.-adr. o. telefon: Kilsunds,\nBorås. Postgiro: 8834.\n\nAkt.-kap.: 5,000,000 kr. Antal\nindustriarb.: 465. Tillv.-värde pr år: 10,000,000\nkr.\n\nBolaget, grundat 1896, har i sig\nupptagit Manufaktur AB. Svea, bildat 1902,\nsamt äger AB. Borås Klädningstygsfabrik\noch AB. Merinos, Borås.\n\nStyrelse: dir. Carl Eiserman (ordf.)r\ning. Nils Hörstadius (v. ordf.), dir.\nArthur Anderson, dir. C. E. Edlund.\nVerkst. dir.: Arthur Anderson.\növering.: E. J. Wijkman.\n\nKinds Yllefabriks AB.,\n\nUlricehamn.\n\nTrikåfabrik vid Lindstorp, Ulricehamn.\nTillverkar baddräkter, koftor, jumpers,\nherrvästar, slipovers, babykläder,\nstrumpor, sockor, vantar m. m.\n\nTelefon: ölsremma 51 o. 53. Postgiro:\n94746. — Akt.-kap.: 100,000 kr. Antal\nindustriarb.: 35. — Firman etabl. 1934.\nVerkst. dir.: fabr. Henning F. Orre.\n\nKinna Bryggeri AB., Kinna.\n\nTillverkar maltdrycker vid bryggeri i\nKinna (Älvsb. l.).\n\nTelefon: 10246. Postgiro: 77420. —\nAkt.-kap.: 164,500 kr. Antal industriarb.:\n10. Omsättn.-värde pr år: 500,000 kr. —",
    "structured": {
        "1": {
            "name": "Kihlgren—Kinna",
            "location": "Hjo",
            "business": "Industriarbete",
            "products": "Ingen information tillgänglig",
            "contact": {
                "office": "Ingen information tillgänglig",
                "phone": [
                    "8",
                    "15"
                ],
                "postgiro": "5422",
                "head_office": "Ingen information tillgänglig",
                "telegraph": "Kihlbergs, Hjo",
                "factory_office": "Ingen information tillgänglig",
                "factory_phone": "Ingen information tillgänglig"
            },
            "financials": {
                "capital": "Ingen information tillgänglig",
                "employees": {
                    "industriarb": 45
                },
                "annual_turnover": "660,000 kr",
                "annual_production_value": "Ingen information tillgänglig"
            },
            "foundation_year": 1860,
            "owners": [
                "Handelsbolaget Josef Kihlberg"
            ],
            "director": "Sven Kihlberg"
        },
        "2": {
            "name": "Kihlgrens Elektrotekniska Byrå",
            "location": "Stockholm",
            "business": "Tillverkning av elektriska produkter",
            "products": "Tillverkar elektr. trappautomater, lysande elektr. tryck-knappar, signallamp-hållare samt specialströmbrytare. Varumärke: »Vidi»",
            "contact": {
                "office": "S:t Eriksg. 103",
                "phone": [
                    "305655",
                    "305666"
                ],
                "postgiro": "3048"
            },
            "financials": {
                "employees": {
                    "industriarb": 8
                },
                "annual_turnover": "150,000 kr",
                "capital": "Ingen information tillgänglig",
                "annual_production_value": "Ingen information tillgänglig"
            },
            "foundation_year": 1917,
            "owners": [
                "Emil W. Kihlgren"
            ],
            "manager": "Emil W. Kihlgren"
        },
        "3": {
            "name": "Adolf Kihlströms Manometerfabrik Eftr.",
            "location": "Stockholm",
            "business": "Tillverkning av instrument och mekaniska produkter",
            "products": "Tillverkar manometrar, vacuummetrar, manovacuummetrar, mängdmätare för gas, vatten och ånga, kvicksilvertermometrar, tensionstermometrar, bimetalltermometrar, termostater och instrumenttavlor",
            "contact": {
                "office": "Bryggarg. 6 B",
                "phone": [
                    "105339",
                    "201182"
                ],
                "postgiro": "156040"
            },
            "financials": {
                "employees": {
                    "industriarb": 45
                },
                "annual_turnover": "Ingen information tillgänglig",
                "capital": "Ingen information tillgänglig",
                "annual_production_value": "Ingen information tillgänglig"
            },
            "foundation_year": 1876,
            "owners": [
                "Ing. Gösta Eriksson"
            ],
            "director": "Ing. Gösta Eriksson",
            "sales_manager": "Ing. Ivar Möllby"
        },
        "4": {
            "name": "Emil Kihlströms Tryckeri AB.",
            "location": "Stockholm",
            "business": "Tidskrift-, katalog-, bok- och accidenstryck",
            "products": "Ingen information tillgänglig",
            "contact": {
                "office": "Mästersamuelsg. 22",
                "phone": [
                    "102510",
                    "103015"
                ],
                "postgiro": "51409"
            },
            "financials": {
                "capital": "90,000 kr",
                "employees": {
                    "industriarb": 30
                },
                "annual_turnover": "Ingen information tillgänglig",
                "annual_production_value": "Ingen information tillgänglig"
            },
            "foundation_year": 1919,
            "current_name_year": 1931,
            "board": [
                {
                    "name": "adv. Knut Strömberg",
                    "role": "Ingen information tillgänglig"
                }
            ]
        },
        "5": {
            "name": "Kiléns Fabriks AB.",
            "location": "Ulricehamn",
            "business": "Trikåfabrik",
            "products": "Tillverkar pullovers, strumpor, jumpers, koftor m. m. av ylle",
            "contact": {
                "phone": [
                    "430"
                ],
                "postgiro": "83549"
            },
            "financials": {
                "capital": "90,000 kr",
                "annual_production_value": "500,000 kr",
                "employees": {
                    "industriarb": 25,
                    "hemarbetare": 10
                },
                "annual_turnover": "Ingen information tillgänglig"
            },
            "foundation_year": 1924,
            "corporation_year": 1932,
            "owners": [
                "Fabr. Olof Kilen"
            ]
        },
        "6": {
            "name": "Kilåker AB.",
            "location": "Stockholm",
            "business": "Transport och spedition",
            "products": "Ingen information tillgänglig",
            "contact": {
                "office": "Karlav. 75",
                "phone": [
                    "411896"
                ]
            },
            "financials": {
                "capital": "10,000 kr",
                "employees": {
                    "industriarb": 3
                },
                "annual_turnover": "40,000 kr",
                "annual_production_value": "Ingen information tillgänglig"
            },
            "foundation_year": 1938,
            "current_name_year": 1938,
            "owners": [
                "Bertil Grosk"
            ]
        },
        "7": {
            "name": "Kil's Tryckeri AB.",
            "location": "Norrköping",
            "business": "Tidskrifts-, katalog- och boktryck",
            "products": "Ingen information tillgänglig",
            "contact": {
                "office": "St)’rmg. 63",
                "phone": [
                    "105539"
                ]
            },
            "financials": {
                "capital": "50,000 kr",
                "employees": {
                    "industriarb": 15
                },
                "annual_turnover": "70,000 kr",
                "annual_production_value": "Ingen information tillgänglig"
            },
            "foundation_year": 1913,
            "corporation_year": 1933,
            "owners": [
                "Fabr. J. A. Kihlberg"
            ]
        }
    }
}