{
    "original": "Westberg—V esterås\n\nTelefon: »Wesströms verktyg».\nPostgiro: 10432.\n\nAkt.-kap.: 436,800 kr. Antal\nindustriarb.: 100. Tillv.-värde pr år: 1,500,000 kr.\n\n—\tFirman etabl. 1898, bolag 1910.\n\nStyrelse: dir. Edvin Jansson, major\n\nE. L. Stackeli, ing. Einar Wiberg.\n\nVerkst. dir.: Edvin Jansson.\n\n*AB. Westbergs Möbler, Tranås.\n\nTillverkar möbler samt konditori-,\nkafé- och restauranginredningar.\n\nTelefon: 2418. Postgiro: 11702.\nRepresentanter: för Stockholm: Gerhard Utter,\nBeckholmen, telefon: 628481; för\nlandsorten: Aron Ode, Tranås, telefon: 2035.\n\nAkt.-kap.: 125,000 kr. Antal\nindustriarb.: 45. Tillv.-värde pr år: 750,000 kr.\n\n—\tFirman etabl. 1922, bolag 1937.\n\nStyrelse o. verkst. dir.: Tage\nWestberg.\n\nCharles Westerberg &amp; Co. AB.,\n\nNyköping.\n\nElektromek. verkstad. Tillverkar\ngjut-järnskapslad elektr. materiel såsom\nmotorkontakter, motorskydd, säkringslådor,\nknivströmbrytare, flottör- och\ntryckströmbrytare, högspänningsmateriel för\ninomhusmontage, rörsäkringar,\nfrånskil-jare och genomföringar, polomkopplare,\nomkastare samt startapparater för elektr.\nmotorer (stjärntriangelkopplare).\n\nAkt.-kap.: 150,000 kr. Telefon: 2900.\nPostgiro: 77697. — Antal industriarb.:\n85. Tillv.-värde pr år: 2,000,000 kr. —\nFirman etabl. 1919, bolag 1942.\n\nStyrelse: fabr. Erik G. Olsson, fabr.\nCharles Westerberg, ing. Folke\nWesterberg.\n\nVerkst. dir.: Ch. Westerberg.\n\nErnst Westerbergs Boktryckeri AB.,\n\nStockholm.\n\nTrycker tidningar, tidskrifter och\nböcker samt utför accidenstryck.\n\nKontor: Klarabergsg. 50. Telefon:\n105035, 105093 o. 204948. Postgiro: 1484.\n\n—\tAkt.-kap.: 75,000 kr. Antal\nindustriarb.: 37. — Firman etabl. 1897, bolag\n1916.\n\nVerkst. dir.: missionssekr. K. A. Moden.\n\nTekn. chef: disp. Josef Lönn.\n\n*AB. Westerdahi &amp; Karsten,\n\nStockholm.\n\nBageri. Tillverkar mjukt vetebröd,\nrågbröd, finare bakverk. Specialitet:\n»Kars-tens skorpor». Bolaget driver jämväl\ndetaljhandel.\n\n6:\n\nKontor: Mästersamuelsg. 56 B.\nTelefon: »Karstens bröd». Postgiro: 458.\n\nAkt.-kap.: 300,000 kr. Antal\nindustriarb.: 55. Tillv.-värde pr år: 2,500,000 kr.\n\n—\tFirman grundad 1820, bolag 1896.\nStyrelse: dir. E. A. Westerdahi (ordf.),\n\ndisp. O. Dandanell, kassör Albin Larsson.\nVerkst. dir.: E. A. Westerdahi.\nTekn. chef: C. Dandanell.\n\n*lsaac Westergren &amp; C:o AB.,\n\nGävle.\n\nKem.-tekn. fabrik (Gefle Såpfabrik).\nTillverkar såpa, toalett-, textil-,\ntvätt-och skurtvål, tvålflingor, tvålpulver,\ngly-cerin, soda, tvättpulver, lutpulver och\nskurpulver samt eau de cologne,\nparfymer och hårvatten.\n\nTelegr.-adr.: Westergrens, Gävle.\nTelefon: 601. Postgiro: 8522.\n\nAkt.-kap.: 250,000 kr. Antal\nindustriarb.: 25. Tillv.-värde pr år: 1,100,000 kr.\n\n—\tFirman etabl. 1872, bolag 1933.\nStyrelse: bankdir. Thure Bergman\n\n(ordf.), dir. Y. Liden, köpman Fridolf\nMeurling.\n\nVerkst. dir.: Y. Liden.\n\n*Alb. Westerholm, Norrköping.\n\nSe AB. Norrköpings Tricotfabrik, Alb.\nWesterholm, Norrköping.\n\nWesterlunds Karamellfabrik,\n\nHärnösand.\n\nTillverkar karameller och\njulgranskonfekt.\n\nTelefon: 2720. Postgiro: 74656. —\nArb-antal: 7. Tillv.-värde pr år: 110,000\nkr. — Firman etabl. 1927.\n\nÄgare o. chef: grossh. Bernhard F.\nBergmän.\n\nAB. Westerstrand &amp; Söner,\nUrfabrik, T öreboda.\n\nTillverkar väggurverk, tornurverk,\nfasadur, urverk för registreringsändamål,\nsignalur, indikatorklockor, kugghjul och\nautomatsvarvade detaljer för räkneverk,\nurverk och instrument vid fabrik i\nTöre-boda (Skarab. l.).\n\nTelefon: 69. Postgiro: 133507. —\nAkt.-kap.: 50,000 kr. Antal industriarb.: 220.\n\n—\tFirman etabl. 1906, bolag 1944.\nVerkst. dir.: fabr. Yngve Westerstrand.\nDriftsing.: James Westerstrand.\n\nVestervik, se Västervrk.\nVesterås, se Västerås.",
    "structured": {
        "1": {
            "name": "Westberg—V esterås",
            "location": "Västerås",
            "financials": {
                "capital": "436,800 kr",
                "employees": {
                    "industriarb": 100
                },
                "annual_turnover": "1,500,000 kr",
                "foundation_year": 1898,
                "corporation_year": 1910
            }
        },
        "2": {
            "name": "AB. Westbergs Möbler",
            "location": "Tranås",
            "products": "Tillverkar möbler samt konditori-, kafé- och restauranginredningar.",
            "financials": {
                "capital": "125,000 kr",
                "employees": {
                    "industriarb": 45
                },
                "annual_turnover": "750,000 kr",
                "foundation_year": 1922,
                "corporation_year": 1937
            }
        },
        "3": {
            "name": "Charles Westerberg & Co. AB.",
            "location": "Nyköping",
            "products": "Elektromek. verkstad. Tillverkar gjut-järnskapslad elektr. materiel.",
            "financials": {
                "capital": "150,000 kr",
                "employees": {
                    "industriarb": 85
                },
                "annual_turnover": "2,000,000 kr",
                "foundation_year": 1919,
                "corporation_year": 1942
            }
        },
        "4": {
            "name": "Ernst Westerbergs Boktryckeri AB.",
            "location": "Stockholm",
            "products": "Trycker tidningar, tidskrifter och böcker samt utför accidenstryck.",
            "financials": {
                "capital": "75,000 kr",
                "employees": {
                    "industriarb": 37
                },
                "foundation_year": 1897,
                "corporation_year": 1916
            }
        },
        "5": {
            "name": "AB. Westerdahi & Karsten",
            "location": "Stockholm",
            "products": "Bageri. Tillverkar mjukt vetebröd, rågbröd, finare bakverk.",
            "financials": {
                "capital": "300,000 kr",
                "employees": {
                    "industriarb": 55
                },
                "annual_turnover": "2,500,000 kr",
                "foundation_year": 1820,
                "corporation_year": 1896
            }
        },
        "6": {
            "name": "lsaac Westergren & C:o AB.",
            "location": "Gävle",
            "products": "Kem.-tekn. fabrik (Gefle Såpfabrik). Tillverkar såpa, toalett-, textil-, tvätt-och skurtvål, tvålflingor, tvålpulver, gly-cerin, soda, tvättpulver, lutpulver och skurpulver samt eau de cologne, parfymer och hårvatten.",
            "financials": {
                "capital": "250,000 kr",
                "employees": {
                    "industriarb": 25
                },
                "annual_turnover": "1,100,000 kr",
                "foundation_year": 1872,
                "corporation_year": 1933
            }
        },
        "7": {
            "name": "Alb. Westerholm",
            "location": "Norrköping"
        },
        "8": {
            "name": "Westerlunds Karamellfabrik",
            "location": "Härnösand",
            "products": "Tillverkar karameller och julgranskonfekt.",
            "financials": {
                "employees": {
                    "arb-antal": 7
                },
                "annual_turnover": "110,000 kr",
                "foundation_year": 1927
            }
        },
        "9": {
            "name": "AB. Westerstrand & Söner",
            "location": "Töreboda",
            "products": "Tillverkar väggurverk, tornurverk, fasadur, urverk för registreringsändamål, signalur, indikatorklockor, kugghjul och automatsvarvade detaljer för räkneverk, urverk och instrument vid fabrik i Töre-boda (Skarab. l.).",
            "financials": {
                "capital": "50,000 kr",
                "employees": {
                    "industriarb": 220
                },
                "corporation_year": 1944
            }
        }
    }
}