{
    "original": "Bröderna\n\nAB. Bröderna Hammarstedt, Växjö.\n\nMek. verkstad. Tillverkar dental- och\nkirurgiska möbler och apparater,\npressverktyg och pressade artiklar samt elektr.\nvärmeapparater.\n\nTelefon: 2408. Postgiro: 279789. —\nAkt.-kap.: 21,300 kr. Antal industriarb.:\n15. — Firman etabl. 1899, bolag 1944.\n\nStyrelse o. verkst. dir.: fabr. Carl\nHammarstedt.\n\nBröderna Hanssons Handskfabriks\nAB., Malung.\n\nTillverkar handskar, speciellt\narbets-och sporthandskar vid fabrik i Malung\n(Kopparb. l.).\nTelefon: 130 o. 430. Postgiro: 130178.\n\n—\tAkt.-kap.: 60,000 kr. Antal\nindustriarb.: 35. Tillv.-värde pr år: 450,000 kr.\n\n—\tFirman etabl. 1932, bolag 1941.\nChefer: fabr. Gunnar Hansson o. fabr.\n\nErik Hansson.\n\n*AB. Bröderna Hedlund, Stockholm.\n\nMek. verkstad. Tillverkar\nbrobyggnader, järnkonstruktioner, grovplåtsarbeten\noch grövre smiden m. m.\n\nKontor: Hammarbyvägen 40; postadr.:\nStockholm 20. Telegr.-adr.: Fackverk,\nStockholm. Telefon: 440890. Postgiro:\n3555.\n\nAkt.-kap.: 900,000 kr. Antal\nindustriarb.: 328. Tillv.-värde pr år: 7,000,000\nkr. — Bolaget grundat 1911.\n\nStyrelse: dir. Petrus E. Hedlund\n(ordf.), ing. Olof Hedlund, ing. Sven\nHedlund.\n\nVerkst. dir.: P. E. Hedlund.\nOffertavd.: ing. Mauritz Engström.\n\nBröderna Holm AB., Bansta.\n\nKorgmöbelfabrik och mek. verkstad i\nRansta (Västmanl. l.). Tillverkar\nkorgmöbler, sportfiskredskap, tévagnshjul,\nskåpreglar m. m. Bolaget driver även\nengroshandel i trävaror.\n\nTelegr.-adr.: Korgholm, Ransta.\nTelefon: »Bröderna Holm». Postgiro: 76625.\n\nAkt.-kap.: 125,000 kr. Antal\nindustriarb.: 40. Tillv.-värde pr år: 800,000 kr.\n\n—\tFirman etabl. 1931, bolag 1943.\nDisp.: Einar Holm.\n\nKamrer: Gösta Elmerudh.\n\nBröderna Hulln AB., Vegby.\n\nTrikåfabrik i Vegby (Älvsb. l.).\nTillverkar jumpers, koftor, västar samt\ndam-och barnunderkläder.\n\nTelefon: 3. Postgiro: 85645. Repr. i\nStockholm: Paul Björklund, John Bergs\npl. 1, telefon: 513810. — Akt.-kap.:\n50,000 kr. Antal industriarb.: 50. —\nFirman etabl. 1914, bolag 1934.\n\nDisp.: Arthur V. Svedberg.\n\nBröderna Höglunds Verkstäder AB.,\n\nIlsbo.\n\nMek. verkstad med sågverk i Ilsbo\n(Gävleb. l.). Tillverkar hydrauliska\n3-vägs tippar för lastbilar samt\nlastbilsflak.\n\nTelefon: 19. Postgiro: 6929.\n\nAkt.-kap.: 12,000 kr. Antal\nindustriarb.: 20. Tillv.-värde pr år: 125,000 kr.\n— Firman etabl. 1919, bolag 1939.\n\nVerkst. direktörer: Fredrik Höglund\no. J. Gunnar Höglund.\n\n*\tBröderna Ivarsson AB., Osby.\n\nSnickerifabriker i Osby (Kristianst. l.).\nTillverkar träleksaker, barnvagnar samt\nträdgårds- och kompletteringsmöbler.\nVarumärke: »Brio». Bolaget driver även\nengroshandel med husgeråd, glas och\nporslin, textilvaror, leksaker m. m.\n\nTelefon: »Bröderna Ivarsson».\nPostgiro: 6075.\n\nAkt.-kap.: 1,200,000 kr. Antal\nanställda: 300, varav 55 industriarb. —\nFirman etabl. 1884, bolag 1937.\n\nStyrelse o. verkst. direktörer: dir.\nAnton Ivarsson o. dir Emil Ivarsson.\n\n*\tBröderna Johansson &amp; Co.,\n\nSmålandsstenar.\n\nTillverkar turistsängar vid fabrik i\nSmålandsstenar (Jönköp. l.). Varumärke:\n»Tor».\n\nTelefon: 46. Postgiro: 30545. — Antal\nindustriarb.: 12. Tillv.-värde pr år:\n200,000 kr. — Firman etabl. 1917.\n\nÄgare: fru Alma Benjaminson, fabr.\nIngmar Benjaminson, fabr. Runo\nBenjaminson o. fabr. Thure Billvén.\n\nDriftschef: Ingmar Benjaminson.\n\nAB. Bröderna Johanssons\nMöbelindustri, Landsbro.\n\nMöbelfabrik i Landsbro (Jönköp. l.).\nTillverkar bord såsom specialitet.\n\nTelefon: 4. Postgiro: 77959. —-\nAkt.-kap.: 70,000 kr. Antal industriarb.: 30.\nTillv.-värde pr år: 400,000 kr. — Firman\netabl. 1928, bolag 1944.\n\nDisp.: Karl Johansson.",
    "structured": {
        "firms": [
            {
                "name": "AB. Bröderna Hammarstedt",
                "location": "Växjö",
                "business": "Mek. verkstad",
                "products": "Tillverkar dental- och kirurgiska möbler och apparater, pressverktyg och pressade artiklar samt elektr. värmeapparater.",
                "contact": {
                    "office": "Not available",
                    "phone": [
                        "2408"
                    ],
                    "postgiro": "279789",
                    "head_office": "Not available",
                    "sales_offices": [],
                    "telegraph": "Not available",
                    "factory_office": "Not available",
                    "factory_phone": "Not available"
                },
                "financials": {
                    "capital": "21,300 kr",
                    "employees": {
                        "industriarb": 15
                    },
                    "annual_turnover": "Not available",
                    "annual_production_value": "Not available"
                },
                "foundation_year": 1899,
                "corporation_year": 1944,
                "board": [
                    {
                        "name": "fabr. Carl Hammarstedt",
                        "role": "Styrelse o. verkst. dir."
                    }
                ],
                "owners": [],
                "director": "Not available",
                "managing_director": "Not available",
                "sales_manager": "Not available",
                "manager": "Not available"
            },
            {
                "name": "Bröderna Hanssons Handskfabriks AB.",
                "location": "Malung",
                "business": "Tillverkar handskar, speciellt arbets-och sporthandskar",
                "products": "Not available",
                "contact": {
                    "office": "Not available",
                    "phone": [
                        "130",
                        "430"
                    ],
                    "postgiro": "130178",
                    "head_office": "Not available",
                    "sales_offices": [],
                    "telegraph": "Not available",
                    "factory_office": "Not available",
                    "factory_phone": "Not available"
                },
                "financials": {
                    "capital": "60,000 kr",
                    "employees": {
                        "industriarb": 35
                    },
                    "annual_turnover": "Not available",
                    "annual_production_value": "450,000 kr"
                },
                "foundation_year": 1932,
                "corporation_year": 1941,
                "board": [
                    {
                        "name": "fabr. Gunnar Hansson",
                        "role": "Chefer"
                    },
                    {
                        "name": "fabr. Erik Hansson",
                        "role": "Chefer"
                    }
                ],
                "owners": [],
                "director": "Not available",
                "managing_director": "Not available",
                "sales_manager": "Not available",
                "manager": "Not available"
            },
            {
                "name": "AB. Bröderna Hedlund",
                "location": "Stockholm",
                "business": "Mek. verkstad",
                "products": "Not available",
                "contact": {
                    "office": "Hammarbyvägen 40",
                    "phone": [
                        "440890"
                    ],
                    "postgiro": "3555",
                    "head_office": "Stockholm 20",
                    "sales_offices": [],
                    "telegraph": "Fackverk, Stockholm",
                    "factory_office": "Not available",
                    "factory_phone": "Not available"
                },
                "financials": {
                    "capital": "900,000 kr",
                    "employees": {
                        "industriarb": 328
                    },
                    "annual_turnover": "Not available",
                    "annual_production_value": "7,000,000 kr"
                },
                "foundation_year": 1911,
                "corporation_year": "Not available",
                "board": [
                    {
                        "name": "dir. Petrus E. Hedlund",
                        "role": "Styrelse"
                    },
                    {
                        "name": "ing. Olof Hedlund",
                        "role": "Styrelse"
                    },
                    {
                        "name": "ing. Sven Hedlund",
                        "role": "Styrelse"
                    }
                ],
                "owners": [],
                "director": "P. E. Hedlund",
                "managing_director": "Not available",
                "sales_manager": "Not available",
                "manager": "Not available"
            },
            {
                "name": "Bröderna Holm AB.",
                "location": "Bansta",
                "business": "Korgmöbelfabrik och mek. verkstad",
                "products": "Tillverkar korgmöbler, sportfiskredskap, tévagnshjul, skåpreglar m. m. Bolaget driver även engroshandel i trävaror.",
                "contact": {
                    "office": "Not available",
                    "phone": [
                        "Bröderna Holm"
                    ],
                    "postgiro": "76625",
                    "head_office": "Not available",
                    "sales_offices": [],
                    "telegraph": "Korgholm, Ransta",
                    "factory_office": "Not available",
                    "factory_phone": "Not available"
                },
                "financials": {
                    "capital": "125,000 kr",
                    "employees": {
                        "industriarb": 40
                    },
                    "annual_turnover": "Not available",
                    "annual_production_value": "800,000 kr"
                },
                "foundation_year": 1931,
                "corporation_year": 1943,
                "board": [
                    {
                        "name": "Einar Holm",
                        "role": "Disp."
                    }
                ],
                "owners": [],
                "director": "Not available",
                "managing_director": "Not available",
                "sales_manager": "Not available",
                "manager": "Not available"
            },
            {
                "name": "Bröderna Hulln AB.",
                "location": "Vegby",
                "business": "Trikåfabrik",
                "products": "Tillverkar jumpers, koftor, västar samt dam-och barnunderkläder.",
                "contact": {
                    "office": "Not available",
                    "phone": [
                        "3"
                    ],
                    "postgiro": "85645",
                    "head_office": "Not available",
                    "sales_offices": [
                        {
                            "location": "Stockholm",
                            "phone": "513810"
                        }
                    ],
                    "telegraph": "Not available",
                    "factory_office": "Not available",
                    "factory_phone": "Not available"
                },
                "financials": {
                    "capital": "50,000 kr",
                    "employees": {
                        "industriarb": 50
                    },
                    "annual_turnover": "Not available",
                    "annual_production_value": "Not available"
                },
                "foundation_year": 1914,
                "corporation_year": 1934,
                "board": [
                    {
                        "name": "Arthur V. Svedberg",
                        "role": "Disp."
                    }
                ],
                "owners": [],
                "director": "Not available",
                "managing_director": "Not available",
                "sales_manager": "Not available",
                "manager": "Not available"
            },
            {
                "name": "Bröderna Höglunds Verkstäder AB.",
                "location": "Ilsbo",
                "business": "Mek. verkstad med sågverk",
                "products": "Tillverkar hydrauliska 3-vägs tippar för lastbilar samt lastbilsflak.",
                "contact": {
                    "office": "Not available",
                    "phone": [
                        "19"
                    ],
                    "postgiro": "6929",
                    "head_office": "Not available",
                    "sales_offices": [],
                    "telegraph": "Not available",
                    "factory_office": "Not available",
                    "factory_phone": "Not available"
                },
                "financials": {
                    "capital": "12,000 kr",
                    "employees": {
                        "industriarb": 20
                    },
                    "annual_turnover": "Not available",
                    "annual_production_value": "125,000 kr"
                },
                "foundation_year": 1919,
                "corporation_year": 1939,
                "board": [
                    {
                        "name": "Fredrik Höglund",
                        "role": "Verkst. direktörer"
                    },
                    {
                        "name": "J. Gunnar Höglund",
                        "role": "Verkst. direktörer"
                    }
                ],
                "owners": [],
                "director": "Not available",
                "managing_director": "Not available",
                "sales_manager": "Not available",
                "manager": "Not available"
            },
            {
                "name": "AB. Bröderna Ivarsson",
                "location": "Osby",
                "business": "Snickerifabriker",
                "products": "Tillverkar träleksaker, barnvagnar samt trädgårds- och kompletteringsmöbler. Varumärke: »Brio».",
                "contact": {
                    "office": "Not available",
                    "phone": [
                        "Bröderna Ivarsson"
                    ],
                    "postgiro": "6075",
                    "head_office": "Not available",
                    "sales_offices": [],
                    "telegraph": "Not available",
                    "factory_office": "Not available",
                    "factory_phone": "Not available"
                },
                "financials": {
                    "capital": "1,200,000 kr",
                    "employees": {
                        "industriarb": 300
                    },
                    "annual_turnover": "Not available",
                    "annual_production_value": "Not available"
                },
                "foundation_year": 1884,
                "corporation_year": 1937,
                "board": [
                    {
                        "name": "dir. Anton Ivarsson",
                        "role": "Styrelse o. verkst. direktörer"
                    },
                    {
                        "name": "dir Emil Ivarsson",
                        "role": "Styrelse o. verkst. direktörer"
                    }
                ],
                "owners": [],
                "director": "Not available",
                "managing_director": "Not available",
                "sales_manager": "Not available",
                "manager": "Not available"
            },
            {
                "name": "AB. Bröderna Johansson & Co.",
                "location": "Smålandsstenar",
                "business": "Tillverkar turistsängar",
                "products": "Not available",
                "contact": {
                    "office": "Not available",
                    "phone": [
                        "46"
                    ],
                    "postgiro": "30545",
                    "head_office": "Not available",
                    "sales_offices": [],
                    "telegraph": "Not available",
                    "factory_office": "Not available",
                    "factory_phone": "Not available"
                },
                "financials": {
                    "capital": "Not available",
                    "employees": {
                        "industriarb": 12
                    },
                    "annual_turnover": "Not available",
                    "annual_production_value": "200,000 kr"
                },
                "foundation_year": 1917,
                "corporation_year": "Not available",
                "board": [
                    {
                        "name": "fru Alma Benjaminson",
                        "role": "Ägare"
                    },
                    {
                        "name": "fabr. Ingmar Benjaminson",
                        "role": "Ägare"
                    },
                    {
                        "name": "fabr. Runo Benjaminson",
                        "role": "Ägare"
                    },
                    {
                        "name": "fabr. Thure Billvén",
                        "role": "Ägare"
                    }
                ],
                "owners": [],
                "director": "Not available",
                "managing_director": "Not available",
                "sales_manager": "Ingmar Benjaminson",
                "manager": "Not available"
            },
            {
                "name": "AB. Bröderna Johanssons Möbelindustri",
                "location": "Landsbro",
                "business": "Möbelfabrik",
                "products": "Tillverkar bord såsom specialitet.",
                "contact": {
                    "office": "Not available",
                    "phone": [
                        "4"
                    ],
                    "postgiro": "77959",
                    "head_office": "Not available",
                    "sales_offices": [],
                    "telegraph": "Not available",
                    "factory_office": "Not available",
                    "factory_phone": "Not available"
                },
                "financials": {
                    "capital": "70,000 kr",
                    "employees": {
                        "industriarb": 30
                    },
                    "annual_turnover": "Not available",
                    "annual_production_value": "400,000 kr"
                },
                "foundation_year": 1928,
                "corporation_year": 1944,
                "board": [
                    {
                        "name": "Karl Johansson",
                        "role": "Disp."
                    }
                ],
                "owners": [],
                "director": "Not available",
                "managing_director": "Not available",
                "sales_manager": "Not available",
                "manager": "Not available"
            }
        ]
    }
}