{
    "original": "Kemifa—Kemiska\n\n\"AB. Kemifa, Partille.\n\nKemisk fabrik. Tillverkar\nenzymprodukter, såsom pyrmedel och tvättmedel,\nsulf.-oljor, fetter för läder-, textil- och\npappersindustrierna, klister,\nappreturme-&lt;del för textilindustrien,\nneutraliserings-och avkalkningsmedel för läderindustrien,\ndegras, garvämnen m. m. Varumärken:\n»Tanopyr», »Tanovan», »Cellydress»,\n»Cellycol», »Solvozym» o. »Silkodress».\n\nTelefon: 409. Postgiro: 41277.\n\nAkt.-kap.: 50,000 kr. Tillv.-värde pr år:\n700,000 kr. — Bolaget grundat 1939.\n\nStyrelse o. verkst. dir.: kapten Georg\nÖsterdahl.\n\nKemist: dr Kurt Schuller.\n\nKamrer: Erik Martinson.\n\n\"Kemigrafiska AB. i Malmö, Malmö.\n\nKemigrafisk anstalt, gravyranstalt och\nkautschukstämpelfabrik. Utför klichéer,\nteckningar, retusch och metallgravyr,\netsade och tryckta maskinskyltar av\nmetall samt tillverkar kautschukstämplar.\n\nKontor: St. Ny g. 55. Telegr.-adr.:\nKe-inigrafen, Malmö. Telefon: 21894 o.\n23163. Postgiro: 38449.\n\nAkt.-kap.: 23,850 kr. Antal\nindustriarb.: 17. — Bolaget grundat 1909.\n\nStyrelse o. verkst. dir.: Anders S.\nMånsson.\n\nAB. Kemikalia, Malmö.\n\nKemisk teknisk fabrik. Tillverkar\nostlöpe, ost- och smörfärger samt\nrengöringsmedel för mejerier.\n\nKontor: Generalsg. 1. Telegr.-adr.:\nKemikalia, Malmö. Telefon: 25695.\nPostgiro: 38089. Repr. i Stockholm: Svenska\nMejeriernas Riksförening, Vasag. 16;\ntelefon: »Mejeriernas Riksförening».\n\nAkt.-kap.: 50,000 kr. Arb.-antal: 6.\nTillv.-värde pr år: 500,000 kr. — Bolaget,\ngrundat 1913, äges av Svenska\nMejeriernas Riksförening.\n\nDisp.: Albin Fosse.\n\n\"AB. för Kemisk och Elektrokemisk\nProduktion, Avesta.\n\nElektrokemisk fabrik i Trollhättan.\nTillverkar vit och röd fosfor, fosforsyra,\nfosformetaller m. m. samt kiselkarbid.\n\nHuvudkontor: Månsbo, Avesta.\nTelegr.-adr.: Phosphorus, Avesta. Telefon:\n»Månsbo», Avesta. Postgiro: 267784.\nFabrikskontor: Trollhättan. Telegr.-adr.:\nPhosphorus, Trollhättan. Telefon:\nTrollhättan 295.\n\nAkt.-kap.: 150,000 kr. Antal\nindustriarb.: 40. Tillv.-värde pr år: 1,000,000 kr.\n\nBolaget, som grundades 1915, äges av\nAB. Förenade Svenska\nTändsticksfabriker, Jönköping.\n\nStyrelse: ing. E. Lustig (ordf.), dir.\nArndt Kristiansson, dir. Sten Sundgren.\n\nVerkst. dir.: E. Lustig.\n\nKontorschef: Albert Wallin.\n\n*Kemiska Fabriks AB. i Malmö,\n\nMalmö.\n\nTillverkar metallsalter och kemiska\npreparat såsom kromsalter, koppar- och\nkvicksilversalter, kobolt, nickel- och\nbly-salter. Varumärke: »Kemfa».\n\nKontor: Kopparbergsg. 23. Telegr.-adr.:\nKemfa, Malmö. Postgiro: 148244.\nTelefon: 24795 o. 24895. Representanter:\nFranzén &amp; Fried AB., Stockholm,\nSkeppsbron 16, telefon: 205892; Detlow B.\nv. Braun, Göteborg, Skeppsbron 4,\ntelefon: 111959.\n\nAkt.-kap.: 25,000 kr. Antal\nindustriarb.: 10. Tillv.-värde pr år: 500,000 kr.\n\n—\tFirman etabl. 1940, bolag 1945.\n\nStyrelse: dir. Kjell Knutson (ordf.),\n\ndisp. Nils Adolf Knutson.\n\nVerkst. dir.: K. Knutson.\n\nDisp.: N. A. Knutson.\n\nKem. Tekn. Fabriken Triangeln AB.,\n\nMalmö.\n\nTillverkar kosmetiska artiklar såsom\nhårmedel, puder, smink, ^ alunpreparat\nm. m. Varumärken: »Ellonin», »Trident»,\n»Triosap» o. »Carmia».\n\nKontor: Industrig. 14—18. Telefon:\n22503 o. 25935. Postgiro: 24513.\n\nAkt.-kap.: 40,000 kr. Antal\nindustriarb.: 30. Tillv.-värde pr år: 450,000 kr.\n\n—\tFirman etabl. 1928, bolag 1937.\n\nVerkst. dir.: ing. Gunnar Mårtenson.\n\nKamrer: Erik Mårtenson.\n\nAB. Kem. Tekn. Clasfabriken,\n\nNybro.\n\nTillverkar burkar, flaskor samt\npressglas.\n\nTelefon: 757. Postgiro: 94986. —\nAkt.-kap.: 12,200 kr. Antal industriarb.: 35.\nTillv.-värde pr år: 200,000 kr. — Bolaget\ngrundat 1935.\n\nVerkst. dir. o. disp.: disp. Arthur\nMell-ström.\n\n*Kemiska Fabriken D:r Ernst\nHar-beck AB., Partille.\n\nKemisk fabrik och mek. verkstad i\nPartille (Göteb. o. Bohus l.). Tillverkar\ngal-vaniska bad, kemikalier och preparat för",
    "structured": {
        "firms": [
            {
                "name": "AB. Kemifa",
                "location": "Partille",
                "business": "Kemisk fabrik",
                "products": "enzymprodukter, såsom pyrmedel och tvättmedel, sulf.-oljor, fetter för läder-, textil- och pappersindustrierna, klister, appreturmedel för textilindustrien, neutraliserings-och avkalkningsmedel för läderindustrien, degras, garvämnen m. m.",
                "contact": {
                    "office": "Telefon: 409",
                    "phone": [
                        "409"
                    ],
                    "postgiro": "41277"
                },
                "financials": {
                    "capital": "50,000 kr",
                    "annual_turnover": "700,000 kr"
                },
                "foundation_year": 1939,
                "board": [
                    {
                        "name": "kapten Georg Österdahl",
                        "role": "Styrelse o. verkst. dir."
                    },
                    {
                        "name": "dr Kurt Schuller",
                        "role": "Kemist"
                    },
                    {
                        "name": "Erik Martinson",
                        "role": "Kamrer"
                    }
                ]
            },
            {
                "name": "Kemigrafiska AB",
                "location": "Malmö",
                "business": "Kemigrafisk anstalt, gravyranstalt och kautschukstämpelfabrik",
                "products": "klichéer, teckningar, retusch och metallgravyr, etsade och tryckta maskinskyltar av metall samt tillverkar kautschukstämplar.",
                "contact": {
                    "office": "Kontor: St. Ny g. 55",
                    "phone": [
                        "21894",
                        "23163"
                    ],
                    "postgiro": "38449"
                },
                "financials": {
                    "capital": "23,850 kr"
                },
                "foundation_year": 1909,
                "board": [
                    {
                        "name": "Anders S. Månsson",
                        "role": "Styrelse o. verkst. dir."
                    }
                ]
            },
            {
                "name": "AB. Kemikalia",
                "location": "Malmö",
                "business": "Kemisk teknisk fabrik",
                "products": "ostlöpe, ost- och smörfärger samt rengöringsmedel för mejerier.",
                "contact": {
                    "office": "Kontor: Generalsg. 1",
                    "phone": [
                        "25695"
                    ],
                    "postgiro": "38089"
                },
                "financials": {
                    "capital": "50,000 kr",
                    "annual_turnover": "500,000 kr"
                },
                "foundation_year": 1913,
                "owners": [
                    "Svenska Mejeriernas Riksförening"
                ],
                "board": [
                    {
                        "name": "Albin Fosse",
                        "role": "Disp."
                    }
                ]
            },
            {
                "name": "AB. för Kemisk och Elektrokemisk Produktion",
                "location": "Avesta",
                "business": "Elektrokemisk fabrik",
                "products": "vit och röd fosfor, fosforsyra, fosformetaller m. m. samt kiselkarbid.",
                "contact": {
                    "office": "Huvudkontor: Månsbo, Avesta",
                    "phone": [
                        "Trollhättan 295"
                    ],
                    "postgiro": "267784"
                },
                "financials": {
                    "capital": "150,000 kr",
                    "annual_turnover": "1,000,000 kr"
                },
                "foundation_year": 1915,
                "owners": [
                    "AB. Förenade Svenska Tändsticksfabriker, Jönköping"
                ],
                "board": [
                    {
                        "name": "ing. E. Lustig",
                        "role": "Styrelse"
                    },
                    {
                        "name": "dir. Arndt Kristiansson",
                        "role": "Styrelse"
                    },
                    {
                        "name": "dir. Sten Sundgren",
                        "role": "Styrelse"
                    },
                    {
                        "name": "E. Lustig",
                        "role": "Verkst. dir."
                    },
                    "director"
                ],
                "manager": "Albert Wallin"
            },
            {
                "name": "Kemiska Fabriks AB.",
                "location": "Malmö",
                "business": "Tillverkar metallsalter och kemiska preparat",
                "products": "kromsalter, koppar- och kvicksilversalter, kobolt, nickel- och bly-salter.",
                "contact": {
                    "office": "Kontor: Kopparbergsg. 23",
                    "phone": [
                        "24795",
                        "24895"
                    ],
                    "postgiro": "148244"
                },
                "financials": {
                    "capital": "25,000 kr",
                    "annual_turnover": "500,000 kr"
                },
                "foundation_year": 1940,
                "board": [
                    {
                        "name": "dir. Kjell Knutson",
                        "role": "Styrelse"
                    },
                    {
                        "name": "disp. Nils Adolf Knutson",
                        "role": "Disp."
                    }
                ]
            },
            {
                "name": "Kem. Tekn. Fabriken Triangeln AB.",
                "location": "Malmö",
                "business": "Tillverkar kosmetiska artiklar",
                "products": "hårmedel, puder, smink, alunpreparat m. m.",
                "contact": {
                    "office": "Kontor: Industrig. 14—18",
                    "phone": [
                        "22503",
                        "25935"
                    ],
                    "postgiro": "24513"
                },
                "financials": {
                    "capital": "40,000 kr",
                    "annual_turnover": "450,000 kr"
                },
                "foundation_year": 1928,
                "board": [
                    {
                        "name": "ing. Gunnar Mårtenson",
                        "role": "Verkst. dir."
                    },
                    {
                        "name": "Erik Mårtenson",
                        "role": "Kamrer"
                    }
                ]
            },
            {
                "name": "AB. Kem. Tekn. Clasfabriken",
                "location": "Nybro",
                "business": "Tillverkar burkar, flaskor samt pressglas",
                "contact": {
                    "phone": [
                        "757"
                    ],
                    "postgiro": "94986"
                },
                "financials": {
                    "capital": "12,200 kr",
                    "annual_turnover": "200,000 kr"
                },
                "foundation_year": 1935,
                "board": [
                    {
                        "name": "disp. Arthur Mell-ström",
                        "role": "Verkst. dir. o. disp."
                    }
                ]
            },
            {
                "name": "Kemiska Fabriken D:r Ernst Harbeck AB.",
                "location": "Partille",
                "business": "Kemisk fabrik och mek. verkstad",
                "products": "galvaniska bad, kemikalier och preparat",
                "contact": {
                    "phone": [
                        "Göteb. o. Bohus l."
                    ],
                    "postgiro": "Unknown"
                },
                "financials": {
                    "capital": "Unknown",
                    "annual_turnover": "Unknown"
                },
                "foundation_year": "Unknown",
                "board": [
                    {
                        "name": "Unknown",
                        "role": "Unknown"
                    }
                ]
            }
        ]
    }
}