{
    "original": "25. Tillv.-värde pr år: 200,000 kr. —\nBolaget grundat 1934.\n\nVerkst. dir.: disp. Oscar Dahlgren.\n\n*Åmåls Nya Bryggeri AB., Åmål.\n\nTillverkar malt och maltdrycker,\nmineralvatten och läskedrycker.\n\nTelefon: 34. Postgiro: 13086.\n\nAkt.-kap.: 150,000 kr. Antal\nindustriarb.: 25. Tillv.-värde pr år: 900,000 kr.\n\nBolaget, grundat 1915, äges av AB.\nSveabryggerier, Filipstad.\n\nStyrelse: disp. Nils G. Arvedson\n(ordf.), dir. A. Bäcklund, disp. Sven\nJansson, disp. John Löfgren, disp.\nGunnar Nilsson.\n\nVerkst. dir.: John Löfgren.\n\nDisp. o. bryggmäst.: Gunnar Nilsson.\n\nAB. Åmåls Sportindustri, Åmål.\n\nVäskfabrik. Tillverkar väskor av tyg,\nläder och plastic.\n\nTelefon-. 625 o. 733. Postgiro: 280344.\n\n—\tAkt.-kap.: 150,000 kr. Antal\nindustriarb.: 36. Tillv.-värde pr år: 400,000 kr.\n\n—\tBolaget, grundat 1943, äger Åmåls\nVärv.\n\nVerkst. dir.: Gösta Nordström.\n\nÅmåls Sågverks AB., <i>Åmål</i>.\n\nTrähusfabrik och sågverk. Tillverkar\nmonteringsfärdiga hus. Varumärke:\n»Åsa».\n\nTelegr.-adr. o. telefon: Åsabolaget,\nÅmål.\n\nFörsäljningskontor: i Stockholm,\nKungsgat. 54, telefon: 105398 o. 104695; i\nGöteborg, Kungsg. 34, telefon: 112495; i\nMalmö, Herbert Björling AB., Kalendeg.\n17, telefon: 71600.\n\nAkt.-kap.: 200,000 kr. Antal\nindustriarb.: 300. Tillv.-värde pr år: 5,000,000\nkr. — Firman etabl. 1924.\n\nStyrelse: godsäg. Karl Nordström\n(ordf.), fru Greta Nordström, disp. Ivar\nNordström.\n\nVerkst. dir. o. disp.: Ivar Nordström.\n\nKamrer: Bror Larvall.\n\n*Ångbryggeri AB. i Gävle, Gävle.\n\nSe AB. Gefle Förenade Bryggerier,\nGävle.\n\n\"Ångbryggeri AB. i Själevad,\n\nSjälevad.\n\nBryggerier i Själevad (Västernorrl. l.)\noch Åsele (Västerbottens l.). Tillverkar\nmalt- och läskedrycker.\n\nTelegr.-adr.: Ångbryggeriet, Örnskölds-\n\nvik. Telefon: Örnsköldsvik 2111.\nPostgiro: 62565.\n\nAkt.-kap.: 312,000 kr. Antal\nindustriarb.: 20. Tillv.-värde pr år: 510,000 kr.\n\nFirman etabl. 1888, bolag 1893^ under\nnamn örnsköldsviks Ångbryggeri AB.,*\nnuv. bolag 1921.\n\nStyrelse: disp. E. N. Hörnblad (ordf.),\nbankdir. Torsten Hedén, f. d. rådm. Oarl\nKusoffsky.\n\nDisp.: E. N. Hörnblad.\n\nBryggmäst.: Egon Andersson.\n\n\"Ångbryggeriet Skruf, Skruv.\n\nSkattepliktigt bryggeri i Skruv\n(Kronob. l.). Tillverkar malt- och\nläske-drvcker.\n\nTelefon: 24. Postgiro: 174322. —\nArb.-antal: 7. — Firman etabl. 1939.\n\nÄgare: köpman Alfr. Larsson, fröken.\nM. Larsson, bokh. Gunnar Larsson.\n\nChef: fröken M. Larsson.\n\n\"Ångbryggeri AB. Svea, Filipstad.\n\nSe AB. Sveabryggerier, Filipstad.\n\n\"Ångbåts AB. Kalmarsund, Kalmar,\n\nSe Kalmar Varv, Kalmar.\n\nÅnghärdad Casbetong AB.,\n\nBorensberg.\n\nLättbetongfabrik i Borensberg\n(Östergötl. l.). Tillverkar kalk- och\nlättbetong-(»Ytong»).\n\nTelefon: 94. Postgiro: 94592.\nEnsamförsälj. i Stockholm: Yxhults\nFörsäljnings AB., Lagerlöfsg. 4, telefon: 520915.\n\nAkt.-kap.: 300,000 kr. Antal\nindustriarb.: 90. Prod.-värde pr år: 1,800,000 kr.\n— Bolaget grundat 1935.\n\nDriftschef: disp. Svante Kjellgren.\n\nAB. Ångsågen, Skruv.\n\nSågverk och hyvleri i Skruv,\ntaksticks-hyvleri i Älmeboda (båda i Kronob. l.).\nTillverkar sågade och hyvlade trävaror\nsamt takstickor.\n\nKontor: Skruv. Telefon: 9. Postgiro:\n99758. — Akt.-kap.: 100,000 kr. Antal\nindustriarb.: 31, varav i Skruv 20.\n\nTillv.-värde pr år: 1,000,000 kr.\nÅrstillv.: 1,200 stds trävaror. — Bolaget\ngrundat 1907.\n\nDisp.: Gunnar Fransén.\n\n*Årnäs Bruk, Österäng.\n\nGlasbruk i Årnäs, österäng (Skarab. l.)-.\nTillverkar buteljer och fönsterglas.\n",
    "structured": {
        "1": {
            "name": "Åmåls Nya Bryggeri AB.",
            "location": "Åmål",
            "business": "Tillverkar malt och maltdrycker, mineralvatten och läskedrycker",
            "products": null,
            "contact": {
                "office": null,
                "phone": [
                    "34"
                ],
                "postgiro": "13086",
                "head_office": null,
                "sales_offices": null,
                "telegraph": null,
                "factory_office": null,
                "factory_phone": null
            },
            "financials": {
                "capital": "150,000 kr",
                "employees": {
                    "industriarb": 25
                },
                "annual_turnover": "900,000 kr",
                "annual_production_value": null
            },
            "foundation_year": 1934,
            "current_name_year": null,
            "predecessor": null,
            "original_name": null,
            "corporation_year": null,
            "board": [
                {
                    "name": "disp. Oscar Dahlgren",
                    "role": null
                }
            ],
            "owners": [
                "AB. Sveabryggerier, Filipstad"
            ],
            "director": null,
            "managing_director": "disp. Oscar Dahlgren",
            "sales_manager": null,
            "manager": null
        },
        "2": {
            "name": "AB. Åmåls Sportindustri",
            "location": "Åmål",
            "business": "Väskfabrik. Tillverkar väskor av tyg, läder och plastic",
            "products": null,
            "contact": {
                "office": null,
                "phone": [
                    "625",
                    "733"
                ],
                "postgiro": "280344",
                "head_office": null,
                "sales_offices": null,
                "telegraph": null,
                "factory_office": null,
                "factory_phone": null
            },
            "financials": {
                "capital": "150,000 kr",
                "employees": {
                    "industriarb": 36
                },
                "annual_turnover": "400,000 kr",
                "annual_production_value": null
            },
            "foundation_year": 1943,
            "current_name_year": null,
            "predecessor": "Äger Åmåls Värv",
            "original_name": null,
            "corporation_year": null,
            "board": [],
            "owners": [],
            "director": null,
            "managing_director": "Verkst. dir.: Gösta Nordström",
            "sales_manager": null,
            "manager": null
        },
        "3": {
            "name": "Åmåls Sågverks AB.",
            "location": "Åmål",
            "business": "Trähusfabrik och sågverk. Tillverkar monteringsfärdiga hus.",
            "products": "Varumärke: »Åsa»",
            "contact": {
                "office": null,
                "phone": [
                    "Åsabolaget, Åmål"
                ],
                "postgiro": null,
                "head_office": null,
                "sales_offices": [
                    {
                        "location": "Stockholm",
                        "phone": "105398 o. 104695"
                    },
                    {
                        "location": "Göteborg",
                        "phone": "112495"
                    },
                    {
                        "location": "Malmö",
                        "phone": "71600"
                    }
                ],
                "telegraph": null,
                "factory_office": null,
                "factory_phone": null
            },
            "financials": {
                "capital": "200,000 kr",
                "employees": {
                    "industriarb": 300
                },
                "annual_turnover": "5,000,000 kr",
                "annual_production_value": null
            },
            "foundation_year": 1924,
            "current_name_year": null,
            "predecessor": null,
            "original_name": null,
            "corporation_year": null,
            "board": [
                {
                    "name": "godsäg. Karl Nordström",
                    "role": "ordf."
                },
                {
                    "name": "fru Greta Nordström",
                    "role": null
                },
                {
                    "name": "disp. Ivar Nordström",
                    "role": null
                }
            ],
            "owners": [],
            "director": null,
            "managing_director": "Verkst. dir. o. disp.: Ivar Nordström",
            "sales_manager": null,
            "manager": "Kamrer: Bror Larvall"
        }
    }
}