{
    "original": "Billerud—Billesholm\n\ntelefon: Billerud, Säffle. Postgiro: 36262.\nSpeditionskontor: Göteborg, Pusterviksg.\nil. Telegr.-adr.: Billerud, Göteborg.\nTelefon: 135108 o. 135118.\n\nAgenter i utlandet: för cellulosa:\n\nAr g en tina: Sparr-Hofstedt &amp; Cia, Av.\nL. N. Alem 428, Buenos Aires.\n\nBelgien; för viskoscellulosa och blekt\npapperssulfit: Continental Cellulose S.\nA., 222 a, Rue Royale, Bruxelles; för\nstarksulfit och kraftmassa: Gross &amp;\nIr-gens S. A., 2, Longue rue de 1’Hopital,\nAntwerpen.\n\nFrankrike: Nordling, Macé &amp; Cie, Rue\ndo la Pépiniere, Paris 11.\n\nItalien: Ditta G. E. Hess, Casella\nPos-tale 317, Turin.\n\nJapan: Gordon &amp; Gotch Ltd., 75—79,\nFarringdon Street, London E. C. 4.\n\nNederländerna: för pappersmassa: J.\nHinnen, Parklaan 3, Hilversum.\n\nStorbritannien: Billerud Sales Co.\nLtd., Blackfriars House, New Bridge\nStreet, London E. C. 4.\n\nTurkiet: F. Z. Birkan, Ataturk\nBulvan 144, Ankara.\n\nU. S. A.: Elof Hansson Inc., 10, East\n40th Street, New York 16, N. Y.\n\nför papper:\n\nArgentina: Sparr-IIofstedt &amp; Cia (se\novan).\n\nAustralien; Haege Ltd., Coventry\nHouse, South Place, London E. C. 2;\nGordon &amp; Gotch Ltd., 75—79, Farringdon\nStreet, London E. C. 4; Edwards Dunlop\n\nCo. Ltd., 46—47, Chancerv Lane,\nLondon W. C. 2.\n\nBelgien: Win. Utné, 21, Chaussee de\nCharleroi, Bruxelles.\n\nBritt. Sydafrika: W. 11. Smith &amp; Co.\n(Pt-y.) Ltd., P. O. Box 979, Cape Town.\n\nDanmark: H. II. Andersen &amp; Co. A/S,\nVestre Boulevard 40, Köpenhamn V; F.\nS t arnpe, Höj b j er g.\n\nFrankrike: Sven H. Sjöholm, 21, Rue\nCasimir-Péricr, Paris VII: e.\n\nItalien: Lodovico Ferrari, Via Regina\nKlena 10, Bolzano.\n\nNederländerna: J. Hinnen (se ovan).\n\nStorbritannien: Billerud Sales Co.\nLtd., (se ovan).\n\nAkt.-kap.: 31,020,000 kr. Antal\nindustriarb.: 1,850.\n\nArstillverkning: 90.000 ton torr, blekt\nsulfitcellulosa för pappers- eller\nkonst-silketillverkning, 25,000 ton (torrtänkt)\nvåt, stark sulfitmassa, 45.000 ton\n(torr-tänkt) stark sulfatmassa, 60,000 ton\npapper, 40 milj. st. papperssäckar, 15—20,000\n\nstds sågade trävaror, 8,000 stds lådbräder,\n9,500,000 liter 95 %-ig sprit samt 1,000\nton sulfatharts.\n\nBolaget grundat 1883, nuvarande\nbolagsordning antagen 1915 (med senare\nändringar). Bolaget har i sig upptagit\nSlottsbrons Sulfit AB., Stömne Bruks AB.,\nAB. Stömne Sulfatfabrik, Hillringsbergs\nAB., Nors Jernbruks AB., AB.\nRämen-Liljendahl, Jössefors AB., Sälboda AB.,\nCharlottenbergs AB., Gustaf Hallgrens\nTrävaru AB. och Kyrkebyns Sulfit AB.\nsamt äger Borgviks AB., AB. Nyhammars\nSkogar, AB. Ludvika Skogar, AB.\nLudvika Ångsåg, A/S Lier, Varald &amp; Bogen,\nAB. Glafva Skogar, Glafva Glasbruks\nAB. och AB. Hvitsands Elektricitetsverk.\n\nStyrelse: skeppsred. And. R. Smith\n(ordf.), disp. Chr. Storjohann (v. ordf.),\ndir. II. Dyster-Aas, landshövd. Bo\nHammarskjöld, adv. L. Killander, skeppsred.\nA. F. Klaveness, godsäg. G. Liedberg.\n\nVerkst. dir.: Chr. Storjohann.\n\nFörste vice verkst. dir.: H. Dyster-Aas.\n\nAndre vice verkst. dir.: E. A.\nVerm-crantz.\n\nSkogschef: Gösta Ekman.\n\növeringenjörer: B. Pedersen, E.\nDah-lén o. A. Malmgren.\n\nFörsäljningschefer: för cellulosa o.\npapper: E. A. Vermcrantz; för trävaror:\nH. Linderren.\n\nInköpschef: Karl Axel Bergstedt.\n\nEkonomichef: O. Rynell.\n\nOmbudsm.: S. Drakenberg.\n\nBillesholms Glasulls AB.,\n\nBillesholm.\n\nGlasullsfabrik vid Billesholm\n(Malmöh. l.). Tillverkar isoleringsmaterial av\nglasull. Varumärke: »Glasullit».\n\nTelegr.-adr.: Glasullsbolaget,\nBillesholm. Telefon: »Glasullsbolaget».\nPostgiro: 84350.\n\nRepr. för norra, mellersta och västra\nSverige: AB. Gerber &amp; Iiesslow,\nStockholm, Birger Jarlsg. 6, telefon: 679040;\nGöteborg: N. Larmg. 11—13, telefon:\n115251.\n\nAkt.-kap.: 1,000,000 kr. Antal\nindustri-arb.: 200.\n\nBolaget grundat 1933.\n\nStyrelse: dir. Ragnar Blomquist\n(ordf.), dir. P. Eg. Gummeson, frih.\nCarl Hermelin, dir. M. Schwartz.\n\nVerkst. dir.: P. Eg. Gummeson.\n\nDisp.: frih. Carl Hermelin.\n\n*",
    "structured": {
        "firms": [
            {
                "name": "Billerud",
                "location": "Billesholm",
                "business": "Massa- och pappersproduktion",
                "contact": {
                    "telegraph": "Billerud, Göteborg",
                    "phone": [
                        "135108",
                        "135118"
                    ]
                },
                "financials": {
                    "capital": "31,020,000 kr",
                    "employees": {
                        "industriarb": 1850
                    }
                },
                "foundation_year": 1883,
                "original_name": "Billerud Sales Co. Ltd."
            },
            {
                "name": "Billesholms Glasulls AB.",
                "location": "Billesholm",
                "business": "Tillverkning av isoleringsmaterial av glasull",
                "contact": {
                    "telegraph": "Glasullsbolaget, Billesholm",
                    "phone": [
                        "Glasullsbolaget"
                    ],
                    "postgiro": "84350"
                },
                "financials": {
                    "capital": "1,000,000 kr",
                    "employees": {
                        "industriarb": 200
                    }
                },
                "foundation_year": 1933
            }
        ]
    }
}