{
    "original": "Hörmun—I dun\n\nOttilia Hörman, Konservfabrik,\n\nLysekil.\n\nTillverkar sillkonserver och ansjovis.\nVarumärken för ansjovis: »Nornan»,\n»Delfin» o. »Fenix».\n\nTelefon: 73. Postgiro: 22198.\nRepresentanter: O.-G. Hallonqvist, Stockholm,\nFurusundsg. 8; Emil W. Engleson, Malmö,\nRegementsg. 66 A.\n\nArb.-antal: 11. Tillv.-värde pr år:\n150,000 kr. — Firman etabl. 1897.\n\nÄgare o. chef: fabr. Allan Forsström.\n\n\"Hörnefors Sulfitfabrik, Hörneå.\n\nSe Mo och Domsjö AB., Stockholm o.\nHärnösand.\n\n\"Hörnsjöfors Bruk, Västerfämebo.\nSe AB. Svenska Metallverken, Västerås.\n\n\"Hörstedts Kritbruk, Kvamby.\n\nSe AB. Kritbruksbolaget i Malmö,\nKvarnby.\n\ni\n\n* utmärker till Sveriges Industriförbund anslutna företag.\n\n\"Ickorrbottens Crufve AB.,\n\nHåksberg.\n\nSe Håksbergs Nya Gruf AB.,\nHåks-berg.\n\n\"Icopal &amp; Takpixfabriken, Malmö.\n\nSe AB. Svenska Icopal &amp;\nTakpixfabriken, Malmö.\n\nIdeal, Linnefabriken, Göteborg.\n\nSe Linnefabriken Ideal, Göteborg.\n\n\"Idealhus, AB. Svenska, Hultsfred.\n\nSe AB. Svenska Idealhus, Hultsfred.\n\nAB. Ideals Motorfabrik,\n\nGöteborg.\n\nMotorfabrik och fartygsslip vid\nKlippans varv, Göteborg. Tillverkar\nstationära och marina råoljemotorer (märke:\n»Ideal») samt utför reparationer av\nmotorer och fartyg.\n\nTelegr.-adr.: Motorideal, Göteborg.\nTelefon: 144956 o. 144792. Postgiro: 40385.\n\nAkt.-kap.: 25,000 kr. Antal\nindustriarb.: 30. Prod.-värde pr år: 225,000 kr.\n— Bolaget grundat 1926.\n\nVerkst. dir.: Knut Jonsson.\n\n\"AB. Idealmöbler, Nässjö.\nTillverkar möbler.\n\nTelefon: 994. Postgiro: 134431. —\nAkt.-kap.: 20,000 kr. Antal industriarb.:\n\n15. Tillv.-värde pr år: 200,000 kr. —\nBolaget grundat 1937.\n\nStyrelse o. chefer: disp. Bertil Edfeldt\n(ordf.), fabr. Anders Edfeldt.\n\n\"Idkerbergets Gruf AB., IdJcerberget.\n\nJärnmalmsgruvor i Idkerberget\n(Kopparb. l.). Bryter järnmalm.\n\nTelegr.-adr,: Dalamalm, Falun.\nTelefon: Borlänge 39041. Postgiro: 94350.\n\nAkt.-kap.: 500,000 kr. Antal\nindustriarb.: 280. Prod.-värde pr år: 2,000,000 kr.\n— Bolaget, grundat 1921, äges av\nStäll-bergs Gruf ve AB.\n\nStyrelse: hovstallmäst. frih. G. A.\nKlingspor (ordf.), kabinettskammarh.\nRobert v. Horn, disp. J. Kempe, kammarh.\nfrih. B. Klingspor, hovjägmäst. frih. W.\nKlingspor, adv. Hugo Stenbeck.\n\nVerkst. dir.: disp. B. Stein.\n\nPlatschef: gruving. Yngve Henricsson.\n\nKamrer: G. Norrbohm.\n\n\"Iduns Tryckeri AB., Stockholm.\n\nUtför bok-, offset- och djuptryck,\nkemigrafiska arbeten samt tillverkar såsom\nspecialitet kort- och vertikalsystem.\n\nKontor: Vasag. 16—18. Telegr.-adr.:\nIduntryckeriet, Stockholm. Telefon:\n»Iduns tryckeri». Postgiro: 3014.\n\nBolaget, grundat 1892, är anslutet till\nAB. Sveriges Litografiska Tryckerier,\nStockholm. (Se detta bolag.)\n\nStyrelse o. verkst. dir.: disp. Gösta\nSmith.\n\nBeställning sk ont or et: faktor Fritz Ek.\n\n247*",
    "structured": {
        "1": {
            "name": "Hörmun—I dun",
            "location": "Lysekil",
            "business": "Konservfabrik",
            "products": "Tillverkar sillkonserver och ansjovis. Varumärken för ansjovis: »Nornan», »Delfin» o. »Fenix».",
            "contact": {
                "office": "Not available",
                "phone": [
                    "73"
                ],
                "postgiro": "22198"
            },
            "financials": {
                "capital": "Not available",
                "employees": {
                    "Arb.-antal": 11
                },
                "annual_turnover": "Not available",
                "annual_production_value": "150,000 kr"
            },
            "foundation_year": 1897,
            "current_name_year": "Not available",
            "director": "Allan Forsström"
        },
        "2": {
            "name": "AB. Idealmöbler",
            "location": "Nässjö",
            "business": "Tillverkar möbler",
            "contact": {
                "phone": [
                    "994"
                ],
                "postgiro": "134431"
            },
            "financials": {
                "capital": "20,000 kr",
                "employees": {
                    "Antal industriarb.": 15
                },
                "annual_turnover": "Not available",
                "annual_production_value": "200,000 kr"
            },
            "foundation_year": 1937,
            "current_name_year": "Not available",
            "board": [
                {
                    "name": "Bertil Edfeldt",
                    "role": "disp."
                },
                {
                    "name": "Anders Edfeldt",
                    "role": "fabr."
                }
            ]
        },
        "3": {
            "name": "AB. Ideas Motorfabrik",
            "location": "Göteborg",
            "business": "Motorfabrik och fartygsslip",
            "products": "Tillverkar stationära och marina råoljemotorer (märke: »Ideal») samt utför reparationer av motorer och fartyg.",
            "contact": {
                "office": "Not available",
                "phone": [
                    "144956",
                    "144792"
                ],
                "postgiro": "40385"
            },
            "financials": {
                "capital": "25,000 kr",
                "employees": {
                    "Antal industriarb.": 30
                },
                "annual_turnover": "Not available",
                "annual_production_value": "225,000 kr"
            },
            "foundation_year": 1926,
            "current_name_year": "Not available",
            "director": "Knut Jonsson"
        },
        "4": {
            "name": "Idkerbergets Gruf AB.",
            "location": "Idkerberget",
            "business": "Järnmalmsgruvor",
            "products": "Bryter järnmalm.",
            "contact": {
                "phone": [
                    "Borlänge 39041"
                ],
                "postgiro": "94350"
            },
            "financials": {
                "capital": "500,000 kr",
                "employees": {
                    "Antal industriarb.": 280
                },
                "annual_turnover": "Not available",
                "annual_production_value": "2,000,000 kr"
            },
            "foundation_year": 1921,
            "current_name_year": "Not available",
            "owners": [
                "Ställbergs Grufve AB"
            ],
            "board": [
                {
                    "name": "G. A. Klingspor",
                    "role": "hovstallmäst."
                },
                {
                    "name": "Robert v. Horn",
                    "role": "kabinettskammarh."
                },
                {
                    "name": "J. Kempe",
                    "role": "disp."
                },
                {
                    "name": "B. Klingspor",
                    "role": "kammarh."
                },
                {
                    "name": "W. Klingspor",
                    "role": "hovjägmäst."
                },
                {
                    "name": "Hugo Stenbeck",
                    "role": "adv."
                }
            ],
            "director": "disp. B. Stein",
            "manager": "G. Norrbohm"
        },
        "5": {
            "name": "AB. Iduns Tryckeri",
            "location": "Stockholm",
            "business": "Utför bok-, offset- och djuptryck",
            "products": "Kemigrafiska arbeten samt tillverkar såsom specialitet kort- och vertikalsystem.",
            "contact": {
                "office": "Vasag. 16—18",
                "telegraph": "Iduntryckeriet, Stockholm",
                "phone": "Not available",
                "postgiro": "3014"
            },
            "foundation_year": 1892,
            "current_name_year": "Not available",
            "board": [
                {
                    "name": "Gösta Smith",
                    "role": "disp."
                }
            ],
            "manager": "faktor Fritz Ek"
        }
    }
}