{
    "original": "Byxfabriken—Bäckhammar\n\n*AB. Byxfabriken Kirudd,\n\nVänersborg.\n\nSe AB. Svenkonfektion, Vänersborg.\nBång, se Bong.\n\n*Bångbroverken, Bångbro.\n\nSe Hellefors Bruks AB., Hällefors.\n\nBårebo Metallvarufabrlk AB.,\n\nGnosjö.\n\nMetallvarufabrik i Gnosjö (Jönköp. l.).\nTillverkar möbel- och byggnadsbeslag,\ndraghandtag, klädkrok, rakhyvlar,\ngångjärn m. m.\n\nTelegr.-adr. o. telefon: Bårebo, Gnosjö.\nPostgiro: 30005. — Akt.-kap.: 300,000 kr.\nAntal industriarb.: 35. Tillv.-värde pr år:\n400,000 kr. — Firman etabl. 1883, bolag\n1946.\n\nVerkst. dir.: David Bauréus.\n\n*\tB ål sta Snickeri &amp; Möbelfabrik, Hj.\nHolmquist, Stockholm.\n\nTillverkar butiksinredningar vid fabrik\ni Bålsta (Uppsala l.). Specialiteter:\nfärghandels- och konditoriinredningar.\n\nKontor o. ensamförsälj.: Prydnobolaget\nHj. Holmquist, Stockholm. Tuleg. 35.\nTelegr.-adr.: Prydno, Stockholm.\nTelefon: 318216 o. 318242. Postgiro: 57629.\nRepr. för västra Sverige: Stig Lindberg,\nGöteborg, Kungsg. 10 B, telefon: 131617.\n\nAntal industriarb.: 11. Tillv.-värde pr\når: 125,000 kr. — Firman etabl. 1944.\n\nÄgare: fabr. Hj. Holmquist.\n\nFabriks för est.: Hugo Sehlberg.\n\n*\tB ås t ad s Kalkindustri AB., Målen.\n\nKalkbruk i Målen (Kristianst. l.) och\nö, Karup (Hallands l.). Tillverkar bränd\nkalk i pulverform, stampad kalk samt\ngödningskalk.\n\nGodsadr.: Båstad. Telefon: Båstad 443.\nPostgiro: 145610.\n\nAkt.-kap.: 309,000 kr. Antal\nindustriarb.: 60. Tillv.-värde pr år: 800,000 kr.\n— Bolaget grundat 1907.\n\nStyrelse: dir. Ernst Wehtje (ordf.),\nfrih. Arvid De Geer, dir. Bertil Ewe,\narkitekt Leon Nilson, dir. Malte Ström,\növering. Donovan Werner.\n\nDisp.: Åke Dahlgren.\n\nBåtbyggeribolaget Andersson &amp;\nSundberg, Söderköping.\n\nTillverkar motorbåtar,\nutombordsmotor-båtar, roddbåtar samt livbåtar.\n\nTelefon: 67. Antal industriarb.: 25.\n— Firman etabl. 1929.\n\nÄgare o. chefer: fabr. Helmer\nAndersson o. fabr. Uno Sundberg.\n\n*Båtskärsnäs Sågverk, Båtskärsnäs.\n\nSe ÅB. Statens Skogsindustrier,\nStockholm.\n\nBäckebo Industri AB.,\n\nffisingsbacka.\n\nBenextraktionsverk i Hisingsbacka\n(Göteb. o. Bohus l.). Tillverkar benfett,\nhorn-mjöl och härdffryn.\n\nTelefon: Göteborg 224040. Postgiro:\n32953. — Akt.-kap.: 1,150,000 kr. Antal\nindustriarb.: 20. — Bolaget grundat 1916.\n\nStyrelse: godsäg. Anders Bergengren\n(ordf.), dir. Gösta Du Rietz, civiling.\nGustaf Eckerbom, civiling. Sune Lindahl,\ndisp. Ivar Nilsson, bankombudsman Eric\nPaulson.\n\nVerkst. dir.: Gustaf Eckerbom.\n\nDisp.: E. SÖnne.\n\n*Bäckebo Ångsåg, Tallåsen.\n\nSe AB. Jon Jonsson &amp; Co., Ljusdal.\n\n*Bäckefors Armaturfabrik, Bäckefors.\n\nSe AB. Kjells Armaturfabrik,\nBacke-fors.\n\nBäckerefjordens Konservfabrik,\nBernh. Andreasson &amp; Söner,\n\nKlädesholmen.\n\nTillverkar sillkonserver, ansjovis och\nkaviar vid fabrik i Klädesholmen (Göteb.\no. Bohus l.).\n\nTelefon: 12. Postgiro: 131622. —\nAntal industriarb.: 10. Tillv.-värde pr år:\n90,000 kr. — Firman etabl. 1900.\n\nÄgare o. chef: fabr. Knut Andreasson.\n\nFörsäljn.-chef: köpman Evald\nAndreasson.\n\n*Bäckhammars Bruk, AB.,\n\nBjörneborg.\n\nPappersbruk med sulfatfabrik och\ntakpappfabrik vid Bäckhammar, Björneborg\n(Värml. l.). Tillverkar omslags-, spinn-,\npås- och toalettpapper, takpapp och\nför-hydningspapp samt sulfatcellulosa för\neget behov.\n\nTelegr.-adr.: Bäckhammarsbruk,\nKristinehamn. Telefon: Kristinehamn\n29010-11-12-14. Postgiro: 91169.",
    "structured": {
        "1": {
            "name": "Byxfabriken—Bäckhammar AB. Byxfabriken Kirudd",
            "location": "Vänersborg",
            "contact": {
                "office": "Kirudd, Vänersborg",
                "telegraph": "Bäckhammar, Bäckhammar"
            },
            "financials": {
                "capital": "300,000 kr",
                "employees": {
                    "Antal industriarb.": 35
                },
                "annual_turnover": "400,000 kr",
                "annual_production_value": "400,000 kr"
            },
            "foundation_year": 1883
        },
        "2": {
            "name": "Bårebo Metallvarufabrlk AB.",
            "location": "Gnosjö",
            "products": "Tillverkar möbel- och byggnadsbeslag, draghandtag, klädkrok, rakhyvlar, gångjärn m. m.",
            "contact": {
                "office": "Bårebo, Gnosjö",
                "telegraph": "Bårebo, Gnosjö",
                "postgiro": "30005"
            },
            "financials": {
                "capital": "300,000 kr",
                "employees": {
                    "Antal industriarb.": 35
                },
                "annual_turnover": "400,000 kr",
                "annual_production_value": "400,000 kr"
            },
            "foundation_year": 1883,
            "corporation_year": 1946
        },
        "3": {
            "name": "Bålsta Snickeri & Möbelfabrik",
            "location": "Stockholm",
            "products": "Tillverkar butiksinredningar vid fabrik i Bålsta (Uppsala l.). Specialiteter: färghandels- och konditoriinredningar.",
            "contact": {
                "office": "Prydnobolaget Hj. Holmquist, Stockholm",
                "telegraph": "Prydno, Stockholm",
                "phone": [
                    "318216",
                    "318242"
                ]
            },
            "owners": [
                "fabr. Hj. Holmquist"
            ],
            "financials": {
                "capital": "N/A",
                "employees": {
                    "Antal industriarb.": 11
                },
                "annual_turnover": "125,000 kr"
            },
            "foundation_year": 1944
        },
        "4": {
            "name": "Båstad s Kalkindustri AB.",
            "location": "Målen (Kristianst. l.) and ö, Karup (Hallands l.)",
            "products": "Tillverkar bränd kalk i pulverform, stampad kalk samt gödningskalk.",
            "contact": {
                "phone": "Båstad 443"
            },
            "financials": {
                "capital": "309,000 kr",
                "employees": {
                    "Antal industriarb.": 60
                },
                "annual_turnover": "800,000 kr"
            },
            "foundation_year": 1907
        },
        "5": {
            "name": "Båtbyggeribolaget Andersson & Sundberg",
            "location": "Söderköping",
            "products": "Tillverkar motorbåtar, utombordsmotor-båtar, roddbåtar samt livbåtar.",
            "contact": {
                "phone": "67"
            },
            "financials": {
                "capital": "N/A",
                "employees": {
                    "Antal industriarb.": 25
                }
            },
            "foundation_year": 1929
        },
        "6": {
            "name": "Bäckebo Industri AB.",
            "location": "Hisingsbacka",
            "products": "Benextraktionsverk i Hisingsbacka (Göteb. o. Bohus l.). Tillverkar benfett, horn-mjöl och härdffryn.",
            "contact": {
                "phone": "Göteborg 224040",
                "postgiro": "32953"
            },
            "financials": {
                "capital": "1,150,000 kr",
                "employees": {
                    "Antal industriarb.": 20
                }
            },
            "foundation_year": 1916
        },
        "7": {
            "name": "Bäckerefjordens Konservfabrik, Bernh. Andreasson & Söner",
            "location": "Klädesholmen (Göteb. o. Bohus l.)",
            "products": "Tillverkar sillkonserver, ansjovis och kaviar vid fabrik i Klädesholmen (Göteb. o. Bohus l.).",
            "contact": {
                "phone": "12",
                "postgiro": "131622"
            },
            "owners": [
                "fabr. Knut Andreasson"
            ],
            "financials": {
                "capital": "N/A",
                "employees": {
                    "Antal industriarb.": 10
                },
                "annual_turnover": "90,000 kr"
            },
            "foundation_year": 1900
        },
        "8": {
            "name": "Bäckhammars Bruk, AB.",
            "location": "Björneborg (Värml. l.)",
            "products": "Tillverkar omslags-, spinn-, pås- och toalettpapper, takpapp och förhydningspapp samt sulfatcellulosa för eget behov.",
            "contact": {
                "telegraph": "Bäckhammarsbruk, Kristinehamn",
                "phone": "Kristinehamn 29010-11-12-14",
                "postgiro": "91169"
            },
            "financials": {
                "capital": "N/A",
                "employees": {
                    "Antal industriarb.": 60
                }
            }
        }
    }
}