{
    "original": "E. W. T —Fabriken\n\nStyrelse: bankdir. Rich. Julin (ordf.),\ndir. Alb. M. Elfström, dir. Börje\nGabrielsson, grossh. E. Kistner.\n\nVerkst. dir.: Wictor Weide.\n\nAB. E.W.T.-Glas, Emmaboda.\n\nTillverkar plana och kupiga\nfotografi-glas, urglas, belysningsarmatur,\nsand-blästrat och lackerat glas samt utför\nslip-ningar av planglas vid\nglasförädlingsfa-brik i Emmaboda (Kalmar l.).\n\nTelefon: 238. Postgiro: 293491.\n—-Akt.-kap.: 15,000 kr. Antal industriarb.:\n15. Tillv.-värde pr år: 150,000 kr. —\nBolaget grundat 1946.\n\nChef: kamrer Knut Engström.\n\nExcelsior, AB., Kartongfabriken,\n\nGöteborg.\n\nSe Kartongfabriken Excelsior AB.,\nGöteborg.\n\n*Exoverken AB., Kalmar.\n\nMek. verkstad. Tillverkar\nvärmeledningspannor, varmvattenberedare,\npumpar, bryggeriapparater samt\nplåtbock-ningsmaskiner.\n\nTelefon: 485. — Akt.-kap.: 100,000\nkr. Antal industriarb.: 40. Tillv.-värde pr\når: 1,000,000 kr. — Bolaget grundat 1939.\n\nStyrelse: ing. Harry Hill, kamrer\nSigge Hill.\n\nVerkst. dir.: ing. Harry Hill.\n\n*AB. Exportlist, Nyköping.\n\nGuldlistfabrik. Tillverkar ram- och\ntapetlister samt speglar, fotografiramar,\ngardinbrädor (märke: »Ota») m. m.\n\nTelegr.-adr.: Exportlist, Nyköping.\nTelefon: 1400, 109 o. 453. Postgiro: 23223.\n\n—\tAkt.-kap.: 72,000 kr. Antal\nindustriarb.: 100. Tillv.-värde pr år: 1,300,000 kr.\n-— Bolaget grundat 1915.\n\nStyrelse: bankdir. P. I. Widebeck\n(ordf.), disp. Knut Irving, fru S. Irving.\nVerkst. dir.: Knut Irving.\n\n*AB. Express-Dynamit, Grängesberg.\n\nSprängämnes-teknisk fabrik vid\nGrängesberg (Kopparb. l.). Tillverkar dynamit\noch andra nitroglycerinhaltiga\nsprängämnen.\n\nTelefon: »Förvaltningen» o. 84. —\nAkt.-kap.: 1,500,000 kr. Antal\nindustriarb.: 80. Tillv.-värde pr år: 2,500,000 kr.\n\n—\tBolaget grundat 1889.\n\nStyrelse: dir. Martin Waldenström\n(ordf.), disp. Carl G. Granström, dir.\nHugo Gårde.\n\nVerkst. dir.: Carl G. Granström.\nFabriks för est.: P. G. Wallerius.\n\n*Extractionsverken AB., Agnesberg.\n\nKraftfoderfabrik och extr aktions verk\nvid Agnesberg (Älvsb. l.). Tillverkar\nfiskmjöl, sillmjöl, svin- och hönsfoder,\nextraherad fiskolja, torskleverolja,\nsillolja, lim, fisk- och sillguano m. m.\n\nTelegr.-adr.: Extractor, Göteborg.\nTelefon: Göteborg 174064. Postgiro: 22124.\n\nAkt.-kap.: 51,000 kr. Antal\nindustriarb.: 15. Tillv.-värde pr år: 500,000 kr.\n\n—\tBolaget grundat 1924.\n\nStyrelse: fil. dr Philip Lindstedt\n(ordf.), ing. G. Hanse.\n\nVerkst. dir.: Philip Lindstedt.\nDisp.: G. Hanse.\n\n* utmärker till Sveriges Industriförbund anslutna företag.\n\nAB. Fabriken Carl, Malmö.\n\nKem.-teknisk fabrik. Tillverkar tvål,\nparfymer, puderkräm, kem,-tekn.\npreparat m. m. Varunamn: »Abeca», »Vidi»,\n»Kosmata», »Hygienol», »Tabu»,\n»Jap-rose».\n\nKontor: Nobelvägen 129. Telegr.-adr.:\nAbecatvål, Malmö. Telefon: 20445.\nPostgiro: 39280. Nederlag: Stockholm,\nNärkesgatan 1, telefon: 410083; Göteborg:\nMellang. 2 A, telefon: 111943.\n\nAkt.-kap.: 10,000 kr. Antal industri-\n\narb.: 15. Tillv.-värde pr år: 400,000 kr. —\nBolaget grundat 1904.\n\nStyrelse: konsul Gustaf Wingårdh\n(ordf.), disp. Anders Ohristofferson.\n\nDisp.: Anders Chri stoff er son.\n\n* Fabriken Hammare, AB.,\n\nEskilstuna.\n\nManufaktursmidesfabrik. Tillverkar\nhammare, hovslageriverktyg m. m.\nVarumärke: Tors hammare.\n\n141*",
    "structured": {
        "0": {
            "name": "E. W. T —Fabriken",
            "location": "Emmaboda",
            "business": "Glasfabrik",
            "products": "Tillverkar plana och kupiga fotografi-glas, urglas, belysningsarmatur, sand-blästrat och lackerat glas samt utför slipningar av planglas.",
            "contact": {
                "office": "Okänt",
                "phone": [
                    "238"
                ],
                "postgiro": "293491"
            },
            "financials": {
                "capital": "15,000 kr",
                "employees": {
                    "industriarb.": 15
                },
                "annual_turnover": "150,000 kr",
                "annual_production_value": "150,000 kr"
            },
            "foundation_year": 1946,
            "board": [
                {
                    "name": "bankdir. Rich. Julin",
                    "role": "ordf."
                },
                {
                    "name": "dir. Alb. M. Elfström",
                    "role": "dir."
                },
                {
                    "name": "dir. Börje Gabrielsson",
                    "role": "dir."
                }
            ],
            "manager": "Wictor Weide"
        },
        "1": {
            "name": "Exoverken AB.",
            "location": "Kalmar",
            "business": "Mekanisk verkstad",
            "products": "Tillverkar värmeledningspannor, varmvattenberedare, pumpar, bryggeriapparater samt plåtbockningsmaskiner.",
            "contact": {
                "phone": [
                    "485"
                ]
            },
            "financials": {
                "capital": "100,000 kr",
                "employees": {
                    "industriarb.": 40
                },
                "annual_turnover": "1,000,000 kr",
                "annual_production_value": "1,000,000 kr"
            },
            "foundation_year": 1939,
            "board": [
                {
                    "name": "ing. Harry Hill",
                    "role": "styrelse"
                }
            ],
            "manager": "ing. Harry Hill"
        },
        "2": {
            "name": "AB. Exportlist",
            "location": "Nyköping",
            "business": "Guldlistfabrik",
            "products": "Tillverkar ram- och tapetlister samt speglar, fotografiramar, gardinbrädor m. m.",
            "contact": {
                "telegraph": "Exportlist, Nyköping",
                "phone": [
                    "1400",
                    "109",
                    "453"
                ],
                "postgiro": "23223"
            },
            "financials": {
                "capital": "72,000 kr",
                "employees": {
                    "industriarb.": 100
                },
                "annual_turnover": "1,300,000 kr",
                "annual_production_value": "1,300,000 kr"
            },
            "foundation_year": 1915,
            "board": [
                {
                    "name": "bankdir. P. I. Widebeck",
                    "role": "ordf."
                },
                {
                    "name": "disp. Knut Irving",
                    "role": "disp."
                },
                {
                    "name": "fru S. Irving",
                    "role": "styrelse"
                }
            ],
            "manager": "Knut Irving"
        },
        "3": {
            "name": "AB. Express-Dynamit",
            "location": "Grängesberg",
            "business": "Sprängämnes-teknisk fabrik",
            "products": "Tillverkar dynamit och andra nitroglycerinhaltiga sprängämnen.",
            "contact": {
                "telegraph": "Förvaltningen",
                "phone": [
                    "84"
                ]
            },
            "financials": {
                "capital": "1,500,000 kr",
                "employees": {
                    "industriarb.": 80
                },
                "annual_turnover": "2,500,000 kr",
                "annual_production_value": "2,500,000 kr"
            },
            "foundation_year": 1889,
            "board": [
                {
                    "name": "dir. Martin Waldenström",
                    "role": "ordf."
                },
                {
                    "name": "disp. Carl G. Granström",
                    "role": "disp."
                },
                {
                    "name": "dir. Hugo Gårde",
                    "role": "dir."
                }
            ],
            "manager": "Carl G. Granström"
        },
        "4": {
            "name": "Extractionsverken AB.",
            "location": "Agnesberg",
            "business": "Kraftfoderfabrik och extraktionsverk",
            "products": "Tillverkar fiskmjöl, sillmjöl, svin- och hönsfoder, extraherad fiskolja, torskleverolja, sillolja, lim, fisk- och sillguano m. m.",
            "contact": {
                "telegraph": "Extractor, Göteborg",
                "phone": [
                    "Göteborg 174064"
                ],
                "postgiro": "22124"
            },
            "financials": {
                "capital": "51,000 kr",
                "employees": {
                    "industriarb.": 15
                },
                "annual_turnover": "500,000 kr",
                "annual_production_value": "500,000 kr"
            },
            "foundation_year": 1924,
            "board": [
                {
                    "name": "fil. dr Philip Lindstedt",
                    "role": "ordf."
                },
                {
                    "name": "ing. G. Hanse",
                    "role": "styrelse"
                }
            ],
            "manager": "Philip Lindstedt"
        },
        "5": {
            "name": "AB. Fabriken Carl",
            "location": "Malmö",
            "business": "Kem-teknisk fabrik",
            "products": "Tillverkar tvål, parfymer, puderkräm, kem-teknisk preparat m. m.",
            "contact": {
                "office": "Nobelvägen 129",
                "telegraph": "Abecatvål, Malmö",
                "phone": [
                    "20445"
                ],
                "postgiro": "39280",
                "nederlag": {
                    "Stockholm": "Närkesgatan 1, telefon: 410083",
                    "Göteborg": "Mellang. 2 A, telefon: 111943"
                }
            },
            "financials": {
                "capital": "10,000 kr",
                "employees": {
                    "industriarb.": 15
                },
                "annual_turnover": "400,000 kr",
                "annual_production_value": "400,000 kr"
            },
            "foundation_year": 1904,
            "board": [
                {
                    "name": "konsul Gustaf Wingårdh",
                    "role": "ordf."
                },
                {
                    "name": "disp. Anders Ohristofferson",
                    "role": "styrelse"
                }
            ],
            "manager": "Anders Christofferson"
        },
        "6": {
            "name": "Fabriken Hammare AB.",
            "location": "Eskilstuna",
            "business": "Manufaktursmidesfabrik",
            "products": "Tillverkar hammare, hovslageriverktyg m. m.",
            "contact": {
                "office": "Okänt"
            },
            "financials": {
                "capital": "Okänt",
                "employees": {
                    "industriarb.": "Okänt"
                },
                "annual_turnover": "Okänt",
                "annual_production_value": "Okänt"
            },
            "foundation_year": "Okänt",
            "board": [
                {
                    "name": "Okänt",
                    "role": "Okänt"
                }
            ],
            "manager": "Okänt"
        }
    }
}