{
    "original": "A Im eäahl—Almqvist\n\narb.: 10. Tillv.-värde pr år: 70,000 kr.\n-— Bolaget grundat 1937.\n\nStyrelse: dir. Anders österlin- (ordf.),\nkamrer Emil Ståhl, disp. Sture österlin.\n\nVerkst. dir.: Sture österlin.\n\nTrycheriförest.: Hilmer Hallgren.\n\n*Almedahl—Dalsjöfors AB.,\n\nGöteborg.\n\nLinneväven, bomullsväven, färgeri och\n\ntryckeri samt fabrik för\nbomullskonfektion vid Almedal i Göteborg, linspinneri,\nväveri och blekeri i Dalsjöfors (Älvsb. l.).\n\nTillverkar linne- och bomullsvävnader,\nalla slag av lingarner samt dam- och\nflickkonfektion.\n\nHuvudkontor o. verkst. direktörens\nkontor: Göteborg, postadr.: Göteborg 5,\ntelegr.-adr.: Almedahls, Göteborg,\ntelefon: 187180; postgiro: 12120. Kontor:\nDalsjöfors, postadr.: Dalsjöfors,\ntelegr.-adr.: Björnlinne, Borås, telefon: Borås\n70150, postgiro: 26835. Avd.-kontor:\nStockholm, Drottningg. 31, telegr.-adr.:\nAlmedahls, Stockholm, telefon: 108579,\npostgiro: 2402.\n\nAkt.-kap.: 8,124,000 kr. Antal\nindustriarb.: 850. Tillv.-värde pr är: 12,000,000\nkr.\n\nBolaget, som bildades 1920 och i sig\nupptagit f. d. Marks Linnemanufaktur\nAB., Kungsäter, utgör en\nsammanslutning av Almedahls Fabriks AB., grundat\n1856, och Dalsjöfors Väveri AB., grundat\n1897. Bolaget är huvudintressent i\nHolma-Helsinglands Linspinneri &amp;\nVäf-veri AB., Iläggådalens Mek.\nLinneväf-veriers AB., Kinna, och i Ahlafors nya\nSpinneri AB.\n\nStyrelse; dir. A. Lem an (ordf.), dir.\nErik Kullgren, tekn. dr Gunnar\nSundblad, major Herman Sundelin, ing. M,\nWenander, bankdir. Stig ödmark.\n\nVerkst. dir.: Herman Sundelin.\n\növering.: Thor Svenzon.\n\nKontorschef: Tor Norlén.\n\nFörsäljn.-chef: Nils Gunnart.\n\nPlatschef i Dalsjöfors: Bertil\nGabrielsson.\n\n* Almgrens Konfektions AB.,\n\nStockholm.\n\nTillverkar klänningar och blusar.\n\nKontor: Kornhamnstorg 6.\nTelegr.-adr.: Almgrens, Stockholm. Telefon:\n235035. Postgiro: 199860.\n\nAkt.-kap.: 60,000 kr. Antal\nindustriarb.: 35. — Bolaget grundat 1945.\n\nStyrelse o.-verkst. dir.: Hans\nBratt-berg.\n\nAB. Almgrens Kravattfabrlk,\n\nStockholm.\n\nTillverkar kravatter och kragskyddare.\n\nKontor: Kornhamnstorg 6. Telegr.-adr.:\nAlmgrens, Stockholm. Telefon: 235035.\nPostgiro: 199855.\n\nAkt.-kap.: 60,000 kr. Antal\nindustriarb.: 21. — Bolaget grundat 1945.\n\nStyrelse o. verkst. dir.: Henrik\nBrattberg.\n\n*Almnäs Sågverk, Hjo.\n\nSe Ohs Bruk, AB., Osbruk.\n\nC. B. Almquists AB., Göteborg.\n\nFörgylleri, glasmästeri, glassliperi,\nram- och skyltfabrik.\n\nTillverkar speglar och blyfönster,\nventilglas för fartyg, ramar, skyltar m. m.\nsamt utför foliering och slipning av glas.\n\nKontor: Drottningg. 15. Telefon: 130485\no. 131928. Postgiro: 42475. — Akt.-kap.:\n75,000 kr. Antal industriarb.: 8.\nTillv.-värde pr år: 100,000 kr. — Firman etabl.\n1822, bolag 1898.\n\nVerkst. dir.: Ernst F. Larson.\n\nAB. Almquist &amp; Cöster, Hälsingborg.\n\nVykorts- och klichéfabrik. Tillverkar\nfotografiska vykort samt klichéer.\n\nTelegr.-adr.: Rotation, Hälsingborg.\n\nTelefon: 20895. — Akt.-kap.: 130,000 kr.\nAntal industriarb.: 68. Tillv.-värde pr år:\n1,270,000 kr. — Firman etabl. 1920, bolag\n1927.\n\nStyrelse: dir. Salfon Almquist, disp.\nYngve Almquist, dir. Rudolf Cöster.\nVerkst. dir.: Salfon Almquist.\n\nV. verkst. dir.: R. Cöster.\n\nFörest, för klichéanstalten: Yngve\nAlmquist.\n\n*AB. Almqvist &amp; Johanson, Örebro.\n\nSkofabrik. Tillverkar randsydda\nherrskodon. Varumärke: »Regent».\n\nTelefon: 1JL074. Postgiro: 20800* —\nAkt.-kap.: 450,000 kr. Antal industriarb.:\n65. Tillv.-värde pr år: 1,400,000 kr. —\nFirman etabl. 1899, bolag 1913.\n\nStyrelse: dir. Jacob Johanson (ordf.),\nlandsfiskal John Ignell, fastighetsäg.\nErik Johanson, förman Erik Johanson,\nkassör Herman Lindberg.\n\nVerkst. dir.: Jacob Johanson.\nKassör: Herman Lindberg.",
    "structured": {
        "SwedishFirms1947": [
            {
                "name": "Almedahl—Dalsjöfors AB.",
                "location": "Göteborg",
                "business": "Linen and cotton weaving, dyeing, and printing",
                "products": "Linen and cotton fabrics, linens, and women's and girl's clothing",
                "contact": {
                    "office": "Göteborg, postadr.: Göteborg 5",
                    "phone": [
                        "187180"
                    ],
                    "postgiro": "12120",
                    "head_office": "Göteborg, postadr.: Göteborg 5",
                    "sales_offices": [
                        {
                            "location": "Dalsjöfors",
                            "phone": "Borås 70150"
                        },
                        {
                            "location": "Stockholm, Drottningg. 31",
                            "phone": "108579"
                        }
                    ],
                    "telegraph": "Almedahls, Göteborg",
                    "factory_office": "Dalsjöfors, postadr.: Dalsjöfors",
                    "factory_phone": "Borås 70150"
                },
                "financials": {
                    "capital": "8,124,000 kr",
                    "employees": {
                        "industrial_workers": 850
                    },
                    "annual_turnover": "12,000,000 kr",
                    "annual_production_value": "70,000 kr"
                },
                "foundation_year": 1920,
                "predecessor": "Marks Linnemanufaktur AB., Kungsäter",
                "corporation_year": 1856,
                "board": [
                    {
                        "name": "A. Lem an",
                        "role": "Chairman"
                    },
                    {
                        "name": "Erik Kullgren",
                        "role": "Director"
                    },
                    {
                        "name": "Gunnar Sundblad",
                        "role": "Technical Director"
                    },
                    {
                        "name": "Stig ödmark",
                        "role": "Bank Director"
                    }
                ],
                "brands": [
                    "Almedahls",
                    "Dalsjöfors"
                ]
            },
            {
                "name": "Almgrens Konfektions AB.",
                "location": "Stockholm",
                "business": "Manufacturing of dresses and blouses",
                "contact": {
                    "office": "Kornhamnstorg 6",
                    "phone": [
                        "235035"
                    ],
                    "postgiro": "199860"
                },
                "financials": {
                    "capital": "60,000 kr",
                    "employees": {
                        "industrial_workers": 35
                    }
                },
                "foundation_year": 1945,
                "director": "Hans Bratt-berg"
            },
            {
                "name": "Almgrens Kravattfabrik",
                "location": "Stockholm",
                "business": "Manufacturing of ties and collars",
                "contact": {
                    "office": "Kornhamnstorg 6",
                    "phone": [
                        "235035"
                    ],
                    "postgiro": "199855"
                },
                "financials": {
                    "capital": "60,000 kr",
                    "employees": {
                        "industrial_workers": 21
                    }
                },
                "foundation_year": 1945,
                "director": "Henrik Brattberg"
            },
            {
                "name": "C. B. Almquists AB.",
                "location": "Göteborg",
                "business": "Gilding, glassworks, glass grinding, and frame and sign factory",
                "products": "Mirrors, lead windows, valve glass for ships, frames, and signs",
                "contact": {
                    "office": "Drottningg. 15",
                    "phone": [
                        "130485",
                        "131928"
                    ],
                    "postgiro": "42475"
                },
                "financials": {
                    "capital": "75,000 kr",
                    "employees": {
                        "industrial_workers": 8
                    },
                    "annual_turnover": "100,000 kr"
                },
                "foundation_year": 1822,
                "corporation_year": 1898,
                "director": "Ernst F. Larson"
            },
            {
                "name": "AB. Almquist & Cöster",
                "location": "Hälsingborg",
                "business": "Postcard and cliché factory",
                "products": "Photographic postcards and clichés",
                "contact": {
                    "phone": "20895"
                },
                "financials": {
                    "capital": "130,000 kr",
                    "employees": {
                        "industrial_workers": 68
                    },
                    "annual_turnover": "1,270,000 kr"
                },
                "foundation_year": 1920,
                "corporation_year": 1927,
                "board": [
                    {
                        "name": "Salfon Almquist",
                        "role": "Director"
                    },
                    {
                        "name": "Yngve Almquist",
                        "role": "Deputy Director"
                    },
                    {
                        "name": "Rudolf Cöster",
                        "role": "Director"
                    }
                ]
            },
            {
                "name": "AB. Almqvist & Johanson",
                "location": "Örebro",
                "business": "Shoe factory",
                "products": "Welted men's shoes (brand: Regent)",
                "contact": {
                    "phone": "11L074",
                    "postgiro": "20800"
                },
                "financials": {
                    "capital": "450,000 kr",
                    "employees": {
                        "industrial_workers": 65
                    },
                    "annual_turnover": "1,400,000 kr"
                },
                "foundation_year": 1899,
                "corporation_year": 1913,
                "board": [
                    {
                        "name": "Jacob Johanson",
                        "role": "Chairman"
                    },
                    {
                        "name": "John Ignell",
                        "role": "District Attorney"
                    },
                    {
                        "name": "Erik Johanson",
                        "role": "Property Owner"
                    },
                    {
                        "name": "Herman Lindberg",
                        "role": "Treasurer"
                    }
                ]
            }
        ]
    }
}