{
    "original": "A ndersson—Andrén\n\nWalfrid Anderssons Mek. Verkstad,\n\nTollarp.\n\nTillverkar tältspisar, vedspisar,\nmaskiner för sättning och upptagning av\npotatis, termometeranordningar för\npotatis-stukor (märke: »Tollarp»),\njärnkonstruktioner m. m. vid mek. verkstad i Tollarp\n(Kristianst. l.).\n\nTelefon:: 75. Postgiro: 27857. — Antal\nindustriarb.: 60. Tillv.-värde pr år:\n300,000 kr. — Firman etabl. 1924.\n\nÄgare o. chef: fabr. Walfrid\nAndersson.\n\n*Walfrid Anderssons Sadelmakeri\n\nAB., Uppsala.\n\nTillverkar sadelmakeriartiklar.\nSpecialitet: cykelsådW.\n\nTelefon: 30641. — Akt.-kap.: 50,000\nkr. Antal industriarb.: 20. Tillv.-värde pr\når: 400,000 kr. — Firman etabl. 1889,\nbolag 1930.\n\nStyrelse o. chefer: fabr. Algot\nKarlberg o. fabr. E. Norlund.\n\n* Verner Andersson AB.,\nByggnads-, firman, Västerås.\n\nSe Byggnadsfirman Verner Andersson\nAB., Västerås.\n\nVilh. Andersons Metallfabrik AB.,\n\nStockholm.\n\nTillverkar belysningsarmatur (spec.\nkristallkronor), bank- och bu\ntiksinredningar, skyltställ samt fasadarbeten av\nmetall.\n\nKontor: Åsög. 113—119. Telefon:\n428065. Postgiro: 3539.\n\nAkt.-kap.: 50,000 kr. Antal\nindustriarb.: 12. Tillv.-värde pr år: 85,000 kr. —\nFirman etabl. 1913, bolag 1939.\n\nStyrelse o. verkst. dir.: disp. Sven E.\nV. Anderson.\n\n*AB. Åbjörn Anderson, Svedala.\n\nMek. verkstad och gjuteri i Svedala\n(Malmöh. l.). Tillverkar maskiner för\ntegel- och torvindustri, för\nvägbyggnads-arbeten m. m., stenkrossar, kol-, koks- och\nandra krossmaskiner, torktrumlor,\nbland-fciingsmaskiner, transportapparater,\ntack-järnsgjutgods i vikter upp till 18 å 20\nton, kokillgods, stålgjutgods i vikter upp\ntill 3 ton, hög- och lågprocentigt\nmanganstål m. fl. legerade stål samt göt av\nönskad analys.\n\nTelegrf-adr. o. telefon: Gjuteriet,\nSvedala. Postgiro: 23240. Avd.-kontor:\nStockholm: Svedala-Verken,\nFridhems-plan 29, telefon: 512485 o. 5124-95;\nGöteborg: Svedala-Verken, N. Hamng. 36,\ntelefon: 112634—35.\n\nAkt.-kap.: 1,600,000 kr. Antal\nindustriarb.: 550. Tillv.-värde pr år: 6,110,000 kr.\n\n—\tFirman etabl. 1882, bolag 1892, nuv.\nbolagsordning antagen 1916.\n\nStyrelse: f. d. undervisningsrådet Nils\nFredriksson (ordf.), dir. Herman Å.\nÅbjörnsson (v. ordf.), övering. Herman\nHärstedt, ing. Krister Johnsson,\nbok-handl. A. Ottoson.\n\nVerkst. dir.: H. Å. Åbjörnsson.\n\nDir.-assistent: civiling. Edvin Dalin,\n\növering.: Herman Härstedt.\n\nOjuterichef: bergsing. Åke Adolfsson.\n\nVerkstadschef: ing. Elis Sandberg.\n\nInhöpschef: Lars Billing.\n\nKontorschef: Janne Persson.\n\nAvd.-chef er: i Stockholm: civiling.\nKossuth Falk; i Göteborg: ing. Eric\nNyström.\n\n(Jfr annons nr 6.)\n\nAnderstorps Armaturfabrik,\n\nAnderstorp.\n\nTillverkar elektr. armatur såsom\nkapslad armatur, tonp- och vägginföringar,\njärnarmar, nollskenor, kabelskor m. m.;\nutför pressning av massartiklar i järn\noch metall vid manufakturverk i\nAnderstorp (Jönköp. l.).\n\nPostadr.: Box 50, Anderstorp. Telefon:\n71. Postgiro: 85060. — Antal\nindustriarb.: 12. Tillv.-värde pr år: 300,000 kr.\n\n—\tFirman etabl. 1927.\n\nÄgare o. chef: fabr. Robert Henjeby.\n\nAB. Anderstorps Träindustri,\n\nAnderstorp.\n\nSnickerifabrik i Anderstorp (Jönköp.\n1.). Tillverkar turistsängar och ottomaner.\n\nTelefon: 114 o. 66. Postgiro: 22577.\n\n—\tAntal industriarb.: 45. Tillv.-värde pr\når: 875,000 kr. — Bolaget grundat 1926.\n\nVerkst. dir.: Malkolm Sjödahl.\n\n*AB. Bernh. Andréns Läderfabrik,\n\nTrelleborg.\n\nGarveri. Tillverkar bindsulläder,\nkrom-garvat handskläder, kolädercruponger,\nplattläder, reseffektläder, smorläder,\ntof-felläder m. m.\n\nTelegr.-adr.: Andrén, Trelleborg.\nTelefon: 81 o. 263. Postgiro: 33420. —",
    "structured": {
        "firm1": {
            "name": "Walfrid Anderssons Mek. Verkstad",
            "location": "Tollarp",
            "business": "Manufacturing",
            "products": "Tent stoves, wood stoves, potato handling and harvesting machines, thermometer devices for potatoes, iron constructions, etc.",
            "contact": {
                "office": "Tollarp, Kristianst. l.",
                "phone": [
                    "75"
                ],
                "postgiro": "27857",
                "head_office": "Tollarp, Kristianst. l.",
                "sales_offices": [],
                "telegraph": "",
                "factory_office": "",
                "factory_phone": ""
            },
            "financials": {
                "capital": "",
                "employees": {
                    "industriarb": 60
                },
                "annual_turnover": "300,000 kr"
            },
            "foundation_year": 1924,
            "current_name_year": null,
            "predecessor": "",
            "original_name": "",
            "corporation_year": null,
            "board": [],
            "owners": [],
            "director": "Walfrid Andersson",
            "managing_director": "",
            "sales_manager": "",
            "manager": "Walfrid Andersson"
        },
        "firm2": {
            "name": "Walfrid Anderssons Sadelmakeri AB.",
            "location": "Uppsala",
            "business": "Manufacturing",
            "products": "Saddlery articles, specialized in bicycle saddles.",
            "contact": {
                "office": "Uppsala",
                "phone": [
                    "30641"
                ],
                "postgiro": "",
                "head_office": "Uppsala",
                "sales_offices": [],
                "telegraph": "",
                "factory_office": "",
                "factory_phone": ""
            },
            "financials": {
                "capital": "50,000 kr",
                "employees": {
                    "industriarb": 20
                },
                "annual_turnover": "400,000 kr"
            },
            "foundation_year": 1889,
            "current_name_year": 1930,
            "predecessor": "",
            "original_name": "",
            "corporation_year": null,
            "board": [],
            "owners": [],
            "director": "",
            "managing_director": "",
            "sales_manager": "",
            "manager": ""
        },
        "firm3": {
            "name": "Vilh. Andersons Metallfabrik AB.",
            "location": "Stockholm",
            "business": "Manufacturing",
            "products": "Lighting fixtures (especially crystal chandeliers), bank and shop fittings, sign holders, and facade works made of metal.",
            "contact": {
                "office": "Åsög. 113—119, Stockholm",
                "phone": [
                    "428065"
                ],
                "postgiro": "3539",
                "head_office": "Stockholm",
                "sales_offices": [],
                "telegraph": "",
                "factory_office": "",
                "factory_phone": ""
            },
            "financials": {
                "capital": "50,000 kr",
                "employees": {
                    "industriarb": 12
                },
                "annual_turnover": "85,000 kr"
            },
            "foundation_year": 1913,
            "current_name_year": 1939,
            "predecessor": "",
            "original_name": "",
            "corporation_year": null,
            "board": [],
            "owners": [],
            "director": "",
            "managing_director": "Sven E. V. Anderson",
            "sales_manager": "",
            "manager": ""
        },
        "firm4": {
            "name": "AB. Åbjörn Anderson",
            "location": "Svedala",
            "business": "Manufacturing",
            "products": "Machinery for the brick and peat industry, road construction equipment, crushers, mixing machines, transport devices, cast iron and steel castings, etc.",
            "contact": {
                "office": "Svedala, Malmöh. l.",
                "phone": [],
                "postgiro": "23240",
                "head_office": "Svedala, Malmöh. l.",
                "sales_offices": [
                    {
                        "location": "Stockholm",
                        "phone": "512485 o. 5124-95"
                    },
                    {
                        "location": "Göteborg",
                        "phone": "112634—35"
                    }
                ],
                "telegraph": "Gjuteriet, Svedala",
                "factory_office": "",
                "factory_phone": ""
            },
            "financials": {
                "capital": "1,600,000 kr",
                "employees": {
                    "industriarb": 550
                },
                "annual_turnover": "6,110,000 kr"
            },
            "foundation_year": 1882,
            "current_name_year": 1916,
            "predecessor": "",
            "original_name": "",
            "corporation_year": 1892,
            "board": [
                {
                    "name": "Nils Fredriksson",
                    "role": "Chairman"
                },
                {
                    "name": "Herman Å. Åbjörnsson",
                    "role": "Vice Chairman"
                },
                {
                    "name": "Herman Härstedt",
                    "role": "Member"
                },
                {
                    "name": "Krister Johnsson",
                    "role": "Member"
                },
                {
                    "name": "A. Ottoson",
                    "role": "Member"
                }
            ],
            "owners": [],
            "director": "",
            "managing_director": "H. Å. Åbjörnsson",
            "sales_manager": "",
            "manager": "H. Å. Åbjörnsson"
        },
        "firm5": {
            "name": "Anderstorps Armaturfabrik",
            "location": "Anderstorp",
            "business": "Manufacturing",
            "products": "Electrical fixtures such as enclosed fixtures, wall and ceiling brackets, iron arms, zero rails, cable shoes, etc.",
            "contact": {
                "office": "Anderstorp, Jönköp. l.",
                "phone": [
                    "71"
                ],
                "postgiro": "85060",
                "head_office": "Anderstorp, Jönköp. l.",
                "sales_offices": [],
                "telegraph": "Box 50, Anderstorp",
                "factory_office": "",
                "factory_phone": ""
            },
            "financials": {
                "capital": "",
                "employees": {
                    "industriarb": 12
                },
                "annual_turnover": "300,000 kr"
            },
            "foundation_year": 1927,
            "current_name_year": null,
            "predecessor": "",
            "original_name": "",
            "corporation_year": null,
            "board": [],
            "owners": [],
            "director": "",
            "managing_director": "",
            "sales_manager": "",
            "manager": "Robert Henjeby"
        },
        "firm6": {
            "name": "AB. Anderstorps Träindustri",
            "location": "Anderstorp",
            "business": "Manufacturing",
            "products": "Tourist beds and ottomans.",
            "contact": {
                "office": "Anderstorp, Jönköp. l.",
                "phone": [
                    "114",
                    "66"
                ],
                "postgiro": "22577",
                "head_office": "Anderstorp, Jönköp. l.",
                "sales_offices": [],
                "telegraph": "",
                "factory_office": "",
                "factory_phone": ""
            },
            "financials": {
                "capital": "",
                "employees": {
                    "industriarb": 45
                },
                "annual_turnover": "875,000 kr"
            },
            "foundation_year": null,
            "current_name_year": null,
            "predecessor": "",
            "original_name": "",
            "corporation_year": null,
            "board": [],
            "owners": [],
            "director": "",
            "managing_director": "",
            "sales_manager": "",
            "manager": "Malkolm Sjödahl"
        },
        "firm7": {
            "name": "AB. Bernh. Andréns Läderfabrik",
            "location": "Trelleborg",
            "business": "Manufacturing",
            "products": "Tanned leather, chrome-tanned gloves, coal leather coupons, flat leather, travel leather, suede leather, etc.",
            "contact": {
                "office": "Trelleborg",
                "phone": [
                    "81",
                    "263"
                ],
                "postgiro": "33420",
                "head_office": "Trelleborg",
                "sales_offices": [],
                "telegraph": "Andrén, Trelleborg",
                "factory_office": "",
                "factory_phone": ""
            },
            "financials": {
                "capital": "",
                "employees": {
                    "industriarb": 0
                },
                "annual_turnover": ""
            },
            "foundation_year": null,
            "current_name_year": null,
            "predecessor": "",
            "original_name": "",
            "corporation_year": null,
            "board": [],
            "owners": [],
            "director": "",
            "managing_director": "",
            "sales_manager": "",
            "manager": ""
        }
    }
}