{
    "original": "Ward—Wasa\n\n*Wards Möbelfabrik, Anton Ward,\n\nTibro.\n\nTillverkar biblioteksbord, soff- och\nmatbord, höj- och sänkbara bord,\npelar-bord, rökbord, radiobord m. fl. vid\nfabrik i Tibro (Skarab. l.).\n\nTelefon: 117. Postgiro: 26957. — Antal\nindustriarb.: 14. Tillv.-värde pr år:\n200,000 kr. — Firman etabl. 1916.\n\nÄgare o. chef: fabr. Anton Ward.\n\n*Vargen AB., Regnklädersfabriken,\n\nNorrköping.\n\nSe Regnklädersfabriken Vargen AB.,\nNorrköping.\n\n*AB. Yargläderfabriken, Uddevalla.\n\nTillverkar sulläder. Specialitet:\nkromsulläder. Varumärke: »Vargläder».\n\nTelefon: 11291. Postgiro: 279828.\n\nAkt.-kap.: 50,000 kr. Antal\nindustriarb.: 10. Tillv.-värde pr år: 500,000 kr.\n— Firman etabl. 1917, bolag 1945 under\nnamn Gust. Perssons Läder fabriks AB.,\nnuv. namn 1946.\n\nStyrelse: ing. Stellan Ljungberg\n(ordf.), dir. Karl Ljungberg.\n\nVerkst. dir.: Stellan Ljungberg.\n\n*Wargöns AB., Vargön.\n\nPappersbruk med träsliperi och\nsulfitfabrik, elektr. smältverk,\nelektrodmasse-fabrik och karbidfabrik i Vargön (Älvsb.\nL), elektr. smältverk i Porjus och\nTrollhättan (AB. Porjus Järnverk och AB.\nTrollhättans Elektr. Masugn),\nmangangruvor vid Böhlet, Karlsborg (Skarab. l.),\ni Spexerydsfältet, Tenhult (Jönköp. l.)\noch i Kesebol, Tösse (Älvsb. l.) samt\nkvartsbrott å olika platser i Dalsland,\nVästergötland och Norrland.\n\nTillverkar tidningspapper,\nomslagspapper, pås- och tapetpapper,\nsulfitspinn-papper, ind. sulfitlut, torr och flytande;\nframställer elektrodmassa, karbid, krom-,\nmangan- och kisellegeringar samt bryter\nmanganmalm och kvarts. Bolaget\ntillverkar för eget behov mek. trämassa och\nsulfitcellulosa samt driver jordbruk.\n\nHuvudkontor: Vargön. Telegr.-adr.:\nWargön, Vänersborg. Telefon: »Wargöns\nAktiebolag», Vänersborg. Postgiro: 7773.\nRepresentant för papper: Björckander &amp;\nCo. AB., Göteborg, Mårten Krakowsg. 7,\ntelefon: 170150.\n\nAkt.-kap.: 6,000,000 kr. Antal\nindustriarb.: 1,000. Tillv.-värde pr år: 20,000,000\nkr.\n\nStyrelse: disp. Thorsten Wigelius (ordf.),\nbankdir. P. Brundell (v. ordf.), disp.\n\nHelmer de Verdier, bankdir. Erik Lundh,\ndisp. F. G. Samuelsson.\n\nVerkst. dir. o. disp.: Helmer de\nVerdier.\n\nKamrer: E. W. Bernell.\n\nKassör: K.-G. Johansson.\n\nChef f. bokföring: Arvid E. Petersson.\n\nInköpschef: G. J. Särner.\n\nFörsäljn.-chef: U. Levan.\n\nDriftsingenjörer: för pappersbruket:\nA. G. Benton; för smältverken: i Vargön:\nJ. Harlitz; i Porjus: G. O. Meurell; i\nTrollhättan: Ossian Jonson.\n\nMetallurg: bergsing. G. Stig.\n\n*Varia, AB. Möbelfabriken, Flen.\n\nSe AB. Möbelfabriken Varia, Flen.\n\n*Wasabryggeriet, Borlänge.\n\nSe AB. Sveabryggerier, Filipstad.\n\nWasa-Bryggeriet, Örebro.\n\nTillverkar måltidsdricka, lagrat\nsvag-dricka, mineralvatten och läskedrycker.\n\nTelefon: 10205. Postgiro: 134586. —\nAntal industriarb.: 15. — Bryggeriet\nanlagt på 1880-talet.\n\nFirmainnehavare o. chef: disp. Eric\nG. Karlsson.\n\n*AB. Vasalampan, Stockholm.\n\nTillverkar elektr. glödlampor.\nVarumärke: »Vasa».\n\nKontor: Katarina Bangata 26.\nTelegr.-adr. : Vasalampan, Stockholm. Telefod .\n440510. Postgiro: 1781.\n\nAkt.-kap.: 76,000 kr. Antal\nindustriarb.: 40. Tillv.-värde pr år: 850,000 kr.\n— Bolaget grundat 1925.\n\nStyrelse: dir. Yngve Jansén (ordf.),\ndisp. Gunnar Norberg, ing. Gösta Widén.\n\nVerkst. dir.: Yngve Jansén.\n\nDisp.; Gunnar Norberg.\n\nDriftsing.: Gösta Widén.\n\nKamrer: Th. Fredlund.\n\n*AB. Wasa Spisbrödsfabrik,\n\nFilipstad.\n\nTillverkar spis- och knäckebröd. ^\n\nTelegr.-adr. o. telefon: Wasafabriken,\nFilipstad. Postgiro: 6882. Avd.-kontor:\nUlvsunda, Stockholm, telefon:\n»Wasabrödfabriker». Försäljn.-central o.\nexportkontor: Stockholm, Högbergsg. 62,\ntelefon: 412815.\n\nAkt.-kap.: 3,000,000 kr. Antal\nindustriarb.: 800. Tillv.-värde pr år: 23,000,000\nkr. Tillv.-kapacitet pr år: 35 milj. kg\nbröd.",
    "structured": {
        "1": {
            "name": "Wards Möbelfabrik",
            "location": "Tibro",
            "business": "Tillverkar biblioteksbord, soff- och matbord, höj- och sänkbara bord, pelar-bord, rökbord, radiobord m. fl.",
            "contact": {
                "office": "Tibro",
                "phone": [
                    "117"
                ],
                "postgiro": "26957",
                "factory_office": "Tibro"
            },
            "financials": {
                "capital": "ej tillgänglig",
                "employees": {
                    "antal_industriarb": 14
                },
                "annual_turnover": "200,000 kr",
                "annual_production_value": "ej tillgänglig"
            },
            "foundation_year": 1916,
            "manager": "fabr. Anton Ward"
        },
        "2": {
            "name": "Vargen AB., Regnklädersfabriken",
            "location": "Norrköping",
            "business": "Se Regnklädersfabriken Vargen AB., Norrköping."
        },
        "3": {
            "name": "AB. Yargläderfabriken",
            "location": "Uddevalla",
            "business": "Tillverkar sulläder. Specialitet: kromsulläder."
        },
        "4": {
            "name": "Wargöns AB.",
            "location": "Vargön",
            "business": "Pappersbruk med träsliperi och sulfitfabrik, elektr. smältverk, elektrodmasse-fabrik och karbidfabrik i Vargön."
        },
        "5": {
            "name": "Varia, AB. Möbelfabriken",
            "location": "Flen",
            "business": "Se AB. Möbelfabriken Varia, Flen."
        },
        "6": {
            "name": "Wasabryggeriet",
            "location": "Borlänge",
            "business": "Se AB. Sveabryggerier, Filipstad."
        },
        "7": {
            "name": "Wasa-Bryggeriet",
            "location": "Örebro",
            "business": "Tillverkar måltidsdricka, lagrat svag-dricka, mineralvatten och läskedrycker."
        },
        "8": {
            "name": "AB. Vasalampan",
            "location": "Stockholm",
            "business": "Tillverkar elektr. glödlampor."
        },
        "9": {
            "name": "AB. Wasa Spisbrödsfabrik",
            "location": "Filipstad",
            "business": "Tillverkar spis- och knäckebröd."
        }
    }
}