{
    "original": "Järnforsen—Jönhöping\n\nAB. Järnforsens Möbelfabrik,\n\nJärnforsen.\n\nTillverkar kontorsmöbler vid fabrik i\nJärnforsen (Kalmar l.).\n\nTelefon: 2. Postgiro: 23468.\nEnsamförsälj.: Maskinaffären Carl Lamm AB.,\nStockholm, Kungsg. 29, telefon: 232640.\n\nAkt.-kap.: 40,000 kr. Antal\nindustriarb.: 21. Tillv.-värde pr år: 200,000 kr.\n\n—\tBolaget grundat 1909. Maskinaffären\nCarl Lamm AB. är huvudintressent i\nbolaget.\n\nDisp.: Ernst T. Johansson.\n\n*AB. Järnförädling, Hälleforsnäs.\n\nAduceringsgjuteri, manufakturverk,\nmek. verkstad och galvaniseringsverk i\nHälleforsnäs (Södermanl. l.). Tillverkar\naducerat gjutgods, aducerade rördelar,\nbåtsmide m. m.\n\nTelegr.-adr.: Malleable, Flen. Telefon:\nHälleforsnäs 1. Postgiro: 8282. —\nAkt.-kap.: 4,000,000 kr. Antal industriarb.:\n600.\n\nVerket anlagt 1659 under namn\nHelle-fors Styckebruk. Bolaget grundat 1918\nefter övertagande av AB. Svenska\nAdu-ceringsverken, som började sin\nverksamhet 1906.\n\nStyrelse: dir. J. S. Edström (ordf.),\ndir. Sixten V. Nilsson, kapten Sten\nRud-berg, dir. C. A. Wicander.\n\nVerkst. dir.: Sten Rudberg.\n\nDir.-assist.: civiling. Hans Rudberg.\n\nKontorschef: kamrer Nils östling.\n\nFörsäljn.-chef er: för aducergods: ing.\nP. Wm Nelson; för rördelar: dir.\nWilhelm v. Redlich.\n\nVerkstadsing.: Gerh. Dahlström.\n\nGjuteriing.: C. G. Sporrong.\n\n*Järnhs Elektriska AB-, Stockholm.\n\nElektromek. verkstad i Hagalund,\nSolna. Tillverkar röntgen- och\nelektro-medi-cinska apparater jämte tillbehör.\n\nKontor: Hagalund, Solna; postadr.:\nBox 21060, Stockholm 21. Telegr.-adr.:\nElektrojärnh, Stockholm. Telefon:\nStockholm 272630. Postgiro: 3207.\n\nAkt.-kap.: 400,000 kr. Antal\nindustriarb.: 140. Tillv.-värde pr år: 1,800^000 kr.\n\n—\tFirman etabl. 1890, bolag 1917.\n\nStyrelse: ing. Bror Edv. Järnh (ordf.),\n\ndipl.-ing. Bertil Edv. Järnh.\n\nVerkst. dir.: Bertil Edv. Järnh.\n\n*Järnmanufaktur AB., Eskilstuna.\n\nSe Eskilstuna Jernmanuf åktur AB.,\nEskilstuna.\n\nAB. Järnmontering, Malmö.\n\nGrovplåtslageri och mek. verkstad.\nTillverkar stålkonstruktioner för hus-,\nindustri-, väg- och vattenbyggnader,\nplåtarbeten, cisterner och tryckkärl samt kittfria\nglastak. Utför formsättning för\nbetongbjälklag med patentform.\n\nKontor: Magasinsg. Telefon: 72140.\nPostgiro: 39225 — Akt.-kap.: 100,000 kr.\nAntal industriarb.: 125, formarb. 30.\nTillv.-värde pr år: 2,000,000 kr. —\nBolaget grundat 1938.\n\nChef: civiling. Ruben J:son Pontén.\n\n(Jfr annons nr 27.)\n\n*\tJärnvägsverkstäderna, Linköping.\n\nSe AB. Svenska Järnvägs verkstäderna,\nLinköping.\n\nAB. Järpens Tapetfabrik, Örebro.\n\nTillverkar limfärgstapeter.\n\nTelegr.-adr.: Wallpaper, Örebro.\nTelefon: 10931. Postgiro: 22093. —\nAkt.-kap.: 78,080 kr. Antal industriarb.: 15.\n\nFirman etabl. 1907 i Stockholm under\nnamn AB. Hassett* ombildat 1925 i\nJär-pen under nuv. namn; 1927 flyttades\nverksamheten till Örebro.\n\nStyrelse o. verkst. dir.: Axel Fromeli.\n\n*\tJästfabriks AB., Svenska,\n\nStockholm.\n\nSe Svenska Jästfabriks AB., Stockholm.\n\n*Jönells AB., Borås.\n\nDamkonfektionsfabrik. Tillverkar\nklänningar, blusar och kjolar.\n\nTelefon: 14795. Postgiro: 94218.\n\nAkt.-kap.: 45,000 kr. Antal\nindustriarb.: 21 (ävensom 30 hemarbetare).\nTillv.-värde pr år: 300,000 kr. — Firman etabl.\n1935, bolag 1938.\n\nVerkst. dir.: disp. Carl G. Jönell.\n\nJönköpings Borstfabrik, Jönköping.\n\nTillverkar industriborstar såsom\ncirku-lärborstar av ståltråd och av fiber,\ntub-rensare, handstålborstar, maskinborstar,\ncykelborstar av tagel och ståltråd,\nrör-borstar, borstar för bilmotorer,\nbiltvätt-ningsborstar, golvdammborstar m. m.\n\nTelefon: 5103. Postgiro: 171574. Repr.\ni Stockholm: C. G. Collin, Rindög. 40;\ntelefon: 671556. — Antal industriarb.: 4.\nTillv.-värde pr år: 60,000 kr. — Firman\netabl. 1941.\n\nÄgare o. chef: fabr. Oscar Johansson.\n\n*",
    "structured": {
        "1": {
            "name": "AB. Järnforsens Möbelfabrik",
            "location": "Järnforsen",
            "business": "Tillverkar kontorsmöbler",
            "contact": {
                "office": "Järnforsen",
                "phone": [
                    "2"
                ],
                "postgiro": "23468",
                "sales_offices": [
                    {
                        "location": "Stockholm",
                        "phone": "232640"
                    }
                ]
            },
            "financials": {
                "capital": "40,000 kr",
                "employees": {
                    "industriarb": 21
                },
                "annual_turnover": "200,000 kr"
            },
            "foundation_year": 1909,
            "predecessor": "Maskinaffären Carl Lamm AB"
        },
        "2": {
            "name": "AB. Järnförädling",
            "location": "Hälleforsnäs",
            "business": "Aduceringsgjuteri, manufakturverk, mek. verkstad och galvaniseringsverk",
            "contact": {
                "telegraph": "Malleable, Flen",
                "phone": "Hälleforsnäs 1",
                "postgiro": "8282"
            },
            "financials": {
                "capital": "4,000,000 kr",
                "employees": {
                    "industriarb": 600
                }
            },
            "foundation_year": 1918,
            "original_name": "Helle-fors Styckebruk",
            "board": [
                {
                    "name": "dir. J. S. Edström",
                    "role": "ordf."
                },
                {
                    "name": "dir. Sixten V. Nilsson",
                    "role": ""
                },
                {
                    "name": "kapten Sten Rudberg",
                    "role": ""
                },
                {
                    "name": "dir. C. A. Wicander",
                    "role": ""
                }
            ],
            "director": "Sten Rudberg",
            "managing_director": "Sten Rudberg",
            "sales_manager": "N/A"
        },
        "3": {
            "name": "Järnhs Elektriska AB",
            "location": "Stockholm",
            "business": "Elektromek. verkstad",
            "contact": {
                "office": "Hagalund, Solna",
                "phone": "Stockholm 272630",
                "postgiro": "3207"
            },
            "financials": {
                "capital": "400,000 kr",
                "employees": {
                    "industriarb": 140
                },
                "annual_turnover": "1,800,000 kr"
            },
            "foundation_year": 1890,
            "corporation_year": 1917,
            "board": [
                {
                    "name": "ing. Bror Edv. Järnh",
                    "role": "ordf."
                },
                {
                    "name": "dipl.-ing. Bertil Edv. Järnh",
                    "role": ""
                }
            ],
            "director": "Bertil Edv. Järnh",
            "managing_director": "Bertil Edv. Järnh"
        },
        "4": {
            "name": "AB. Järnmontering",
            "location": "Malmö",
            "business": "Grovplåtslageri och mek. verkstad",
            "contact": {
                "office": "Magasinsg.",
                "phone": "72140",
                "postgiro": "39225"
            },
            "financials": {
                "capital": "100,000 kr",
                "employees": {
                    "industriarb": 125,
                    "formarb": 30
                },
                "annual_turnover": "2,000,000 kr"
            },
            "foundation_year": 1938,
            "manager": "Ruben J:son Pontén"
        },
        "5": {
            "name": "Järnvägsverkstäderna",
            "location": "Linköping",
            "business": "Se AB. Svenska Järnvägs verkstäderna",
            "description": "Gjuteriing.: N/A"
        },
        "6": {
            "name": "AB. Järpens Tapetfabrik",
            "location": "Örebro",
            "business": "Tillverkar limfärgstapeter"
        },
        "7": {
            "name": "Jästfabriks AB., Svenska",
            "location": "Stockholm",
            "business": "Se Svenska Jästfabriks AB."
        },
        "8": {
            "name": "Jönells AB.",
            "location": "Borås",
            "business": "Damkonfektionsfabrik",
            "contact": {
                "phone": "14795",
                "postgiro": "94218"
            },
            "financials": {
                "capital": "45,000 kr",
                "employees": {
                    "industriarb": 21,
                    "hemarbetare": 30
                },
                "annual_turnover": "300,000 kr"
            },
            "foundation_year": 1935,
            "manager": "Carl G. Jönell"
        },
        "9": {
            "name": "Jönköpings Borstfabrik",
            "location": "Jönköping",
            "business": "Tillverkar industriborstar"
        }
    }
}