{
    "original": "Öland—Örebro\n\nAB. Ölands Maltfabrik,\n\nBorgholm.\n\nTillverkar malt. Bolaget driver även\nhandel med spannmål, fodervaror,\ngödningsämnen och utsäde.\n\nTelegr.-adr.: Maltfabriken, Borgholm.\nTelefon: 31 o. 78. Postgiro: 73895.\n\nAkt.-kap.: 65,900 kr. Arb.-antal: 8.\nTillv.-värde pr år: 180,000 kr. — Bolaget\ngrundat 1927.\n\nVerkst. dir.: Rudolf Ohlsson.\n\nKamrer: Sven Ohlsson.\n\nÖlands-Sandviks Bruks AB.,\n\nPersnäs.\n\nKalkstensbrott och stenhuggeri i\nPersnäs (Kalmar l.). Tillverkar arbeten i\nbyggnadskalksten, råskivor,\nträdgårdskalksten m. m.\n\nHuvudkontor: Holmquist k Co. AB.,\nStockholm, Kungsg. 14. Telegr.-adr.:\nAx-ragn, Stockholm. Telefon: 233830.\nPostgiro: 58913. Brukskontor: Persnäs,\ntelefon: 12 o. 112, telegr.-adr.: Stenbild,\nPersnäs.\n\nAkt.-kap.: 150,000 kr. Antal\nindustriarb.: 100. Tillv.-värde pr år: 1,000,000 kr.\n\n—\tFirman etabl. 1910 under namn\nSandviks Sten- o. Bildhuggeri, bolag 1942\nunder nuv. namn.\n\nVerkst. dir.: Axel Holmquist (Sthlm).\n\nPlatschef: disp. Erik Persson.\n\nÖlandssten, Industri AB., Kalmar.\n\nSe Industri AB. ölandssten, Kalmar.\n\n\"AB. Önos Fruktindustri, Tollarp.\n\nTillverkar fruktkonserver, marmelad,\nsylt, gelé, äpplemos, saft, fruktextrakter,\nessenser och bageriartiklar vid fabrik i\nTollarp (Kristianst. l.).\n\nTelefon: »önos». Postgiro: 15027.\n\nAkt.-kap.: 76,600 kr. Antal\nindustriarb.: 70. Tillv.-värde pr år: 2,000,000 kr.\n\n—\tFirman etabl. 1903.\n\nStyrelse: adv. J. Listander (ordf.),\ndir. Hj. Svensson, kapten Dettmar\nWol-lin, fru Olga Wollin, fru Sonja Wollin.\n\nVerkst. dir.: fru Olga Wollin.\n\nDisp. o. v. verkst. dir.: Dettmar Wollin.\n\nAB. Örbyhus Lantbruksmaskiner,\n\nStockholm.\n\nTillverkar tröskverk, gödselspridare,\npotatiskrossare, höpressar m. m. vid fabrik\ni örbyhus (Uppsala l.). Varumärken:\n»Velo» o. »örby».\n\nHuvudkontor i Stockholm: AB. Slöörs\nMaskin- k Redskapsaffär, Nybrogatan\n\n23. Telegr.-adr.: Maskinslöör, Stockholm..\nTelefon: 679240. Postgiro: 282678.\n\nAkt.-kap.: 75,000 kr. Antal\nindustriarb.: 30. Tillv.-värde pr år: 500,000 kr..\n\n—\tBolaget grundat 1944.\nVerkst. dir.: Gösta Törnblom.\nDisp. i örbyhus: Yngve Erhardt.\n\nAB. Örbyhus Syfabrik, Örbyhus.\n\nSyfabriker i örbyhus och Tierp (båda\ni Uppsala l.). Tillverkar herr- och\ngosskläder, damkappor och dräkter samt\nskid-dräkter. Varumärken: »SABÖ» o.\n»ÖR-SY».\n\nTelegr.-adr.: Syfabriken, örbyhus.\nTelefon: 45 o. 145. Postgiro: 8662. —\nAkt.-kap.: 300,000 kr. Antal industriarb.: 155\n(exkl. hemarbetare).\n\nBolaget grundat 1920 under namn\nManufaktur &amp; Syfabriks AB., nuv. namn\n1939.\n\nStyrelse: fabr. G. E. Tunelius (ordf.),,\ndisp. And. Dahl, gårdsäg. P. A. Tunell.\nDisp.: And. Dahl.\n\n\"AB. Örebro Bleckemballagefabrik,\n\nÖrebro.\n\nBleckemballagefabrik, blecktryckeri och\nmek. verkstad.\n\nTillverkar blankt och dekorerat\nbleckemballage såsom helpressade askar,\nburkar, patentburkar för färger, läcker,\nfernissor o. d., buteljlackburkar, helpressade\ntorrspritburkar, oljekanistrar, skrin för\nkaffe och kakor, reklamskyltar m. m.\n\nTelegr.-adr.: Karla, Örebro. Telefon:\n10451 o. 12451. Postgiro: 14352.\n\nAkt.-kap.: 300,000 kr. Antal\nindustriarb.: 128. Tillv.-värde pr år: 2,100,000 kr.\n\n—\tFabriken anlagd 1898, bolag 1942.\nStyrelse: fru Matilda Jansson, fru T.\n\nS. Marcus, disp. Bertil Palmgren.\n\nVerkst. dir. o. disp.: Bertil Palmgren.\n\n\"Örebro Bryggeri AB., Örebro.\n\nTillverkar malt, maltdrycker samt\nkol-syrade vatten och läskedrycker.\n\nTelegr.-adr.: Bryggeribolaget, Örebro.\nTelefon: 10138, 13058 o. 12058. Postgiro:\n91630.\n\nAkt.-kap.: 500,000 kr. Antal\nindustriarb.: 30. Tillv.-värde pr år: 900,000 kr..\n\n—\tFirman etabl. 1796, bolag 1902.\nStyrelse: fröken A. Cederberg, disp.\nErland Skantze, adv. Per Westling.\n\nVerkst. dir.: Erland Skantze.\n\nÖrebro Elektriska AB., Örebro.\n\nElektr. vattenkraftstationer vid\nBrattforsen och Skråmforsen inom Karlskoga»",
    "structured": {
        "firms": [
            {
                "name": "Ölands Maltfabrik, AB",
                "location": "Borgholm",
                "business": "Tillverkar malt. Bolaget driver även handel med spannmål, fodervaror, gödningsämnen och utsäde.",
                "contact": {
                    "telegraph": "Maltfabriken, Borgholm",
                    "phone": [
                        "31",
                        "78"
                    ],
                    "postgiro": "73895"
                },
                "financials": {
                    "capital": "65,900 kr",
                    "employees": {
                        "total": 8
                    },
                    "annual_turnover": "180,000 kr",
                    "annual_production_value": "180,000 kr"
                },
                "foundation_year": 1927,
                "director": "Rudolf Ohlsson",
                "manager": "Sven Ohlsson"
            },
            {
                "name": "Ölands-Sandviks Bruks AB",
                "location": "Persnäs",
                "business": "Kalkstensbrott och stenhuggeri i Persnäs (Kalmar l.). Tillverkar arbeten i byggnadskalksten, råskivor, trädgårdskalksten m. m.",
                "contact": {
                    "head_office": "Holmquist k Co. AB., Stockholm, Kungsg. 14",
                    "phone": "233830",
                    "postgiro": "58913",
                    "sales_offices": [
                        {
                            "location": "Persnäs",
                            "phone": "12 o. 112"
                        }
                    ]
                },
                "financials": {
                    "capital": "150,000 kr",
                    "employees": {
                        "total": 100
                    },
                    "annual_turnover": "1,000,000 kr",
                    "annual_production_value": "1,000,000 kr"
                },
                "foundation_year": 1910,
                "director": "Axel Holmquist",
                "manager": "disp. Erik Persson"
            },
            {
                "name": "AB. Önos Fruktindustri",
                "location": "Tollarp",
                "business": "Tillverkar fruktkonserver, marmelad, sylt, gelé, äpplemos, saft, fruktextrakter, essenser och bageriartiklar vid fabrik i Tollarp (Kristianst. l.)",
                "contact": {
                    "telegraph": "»önos»",
                    "postgiro": "15027"
                },
                "financials": {
                    "capital": "76,600 kr",
                    "employees": {
                        "total": 70
                    },
                    "annual_turnover": "2,000,000 kr",
                    "annual_production_value": "2,000,000 kr"
                },
                "foundation_year": 1903,
                "board": [
                    {
                        "name": "adv. J. Listander",
                        "role": "ordf."
                    },
                    {
                        "name": "dir. Hj. Svensson",
                        "role": ""
                    },
                    {
                        "name": "kapten Dettmar Wollin",
                        "role": ""
                    },
                    {
                        "name": "fru Olga Wollin",
                        "role": ""
                    },
                    {
                        "name": "fru Sonja Wollin",
                        "role": ""
                    }
                ],
                "director": "fru Olga Wollin",
                "manager": "Dettmar Wollin"
            },
            {
                "name": "AB. Örbyhus Lantbruksmaskiner",
                "location": "Stockholm",
                "business": "Tillverkar tröskverk, gödselspridare, potatiskrossare, höpressar m. m. vid fabrik i örbyhus (Uppsala l.)",
                "contact": {
                    "office": "AB. Slöörs Maskin- k Redskapsaffär, Nybrogatan 23",
                    "phone": "679240",
                    "postgiro": "282678"
                },
                "financials": {
                    "capital": "75,000 kr",
                    "employees": {
                        "total": 30
                    },
                    "annual_turnover": "500,000 kr",
                    "annual_production_value": "500,000 kr"
                },
                "foundation_year": 1944,
                "director": "Gösta Törnblom",
                "manager": "Yngve Erhardt"
            },
            {
                "name": "AB. Örbyhus Syfabrik",
                "location": "Örbyhus",
                "business": "Tillverkar herr- och gosskläder, damkappor och dräkter samt skid-dräkter",
                "contact": {
                    "telegraph": "Syfabriken, örbyhus",
                    "phone": [
                        "45",
                        "145"
                    ],
                    "postgiro": "8662"
                },
                "financials": {
                    "capital": "300,000 kr",
                    "employees": {
                        "total": 155
                    },
                    "annual_production_value": "N/A"
                },
                "foundation_year": 1920,
                "director": "fabr. G. E. Tunelius",
                "manager": "And. Dahl"
            },
            {
                "name": "AB. Örebro Bleckemballagefabrik",
                "location": "Örebro",
                "business": "Tillverkar blankt och dekorerat bleckemballage såsom helpressade askar, burkar, patentburkar för färger, läcker, fernissor o. d., buteljlackburkar, helpressade torrspritburkar, oljekanistrar, skrin för kaffe och kakor, reklamskyltar m. m.",
                "contact": {
                    "telegraph": "Karla, Örebro",
                    "phone": [
                        "10451",
                        "12451"
                    ],
                    "postgiro": "14352"
                },
                "financials": {
                    "capital": "300,000 kr",
                    "employees": {
                        "total": 128
                    },
                    "annual_turnover": "2,100,000 kr",
                    "annual_production_value": "2,100,000 kr"
                },
                "foundation_year": 1942,
                "director": "Bertil Palmgren",
                "manager": "Bertil Palmgren"
            },
            {
                "name": "Örebro Bryggeri AB",
                "location": "Örebro",
                "business": "Tillverkar malt, maltdrycker samt kolsyrade vatten och läskedrycker",
                "contact": {
                    "telegraph": "Bryggeribolaget, Örebro",
                    "phone": [
                        "10138",
                        "13058",
                        "12058"
                    ],
                    "postgiro": "91630"
                },
                "financials": {
                    "capital": "500,000 kr",
                    "employees": {
                        "total": 30
                    },
                    "annual_turnover": "900,000 kr",
                    "annual_production_value": "900,000 kr"
                },
                "foundation_year": 1902,
                "director": "Erland Skantze"
            },
            {
                "name": "Örebro Elektriska AB",
                "location": "Örebro",
                "business": "Elektr. vattenkraftstationer vid Brattforsen och Skråmforsen inom Karlskoga.",
                "contact": {
                    "telegraph": "N/A",
                    "phone": "N/A",
                    "postgiro": "N/A"
                },
                "financials": {
                    "capital": "N/A",
                    "employees": "N/A",
                    "annual_turnover": "N/A",
                    "annual_production_value": "N/A"
                },
                "foundation_year": "N/A"
            }
        ]
    }
}