{
    "original": "Trikå—Tryckeri\n\nAB. Trikå- &amp; Syfabriken Standard,\n\nBorås.\n\nSe Bertil Petzén AB., Borås.\n\nTrikåindustri W. A. Fält AB.,\n\nFritsla.\n\nTillverkar dam-, herr- och\nbarnunderkläder vid trikåfabrik i Fritsla (Älvsb. l.).\n\nTelefon: 70061. — Akt.-kap.: 100,000\nkr. Antal industriarb.: 25. Tillv.-värde\npr år: 400,000 kr. — Firman etabl. 1917\nunder namn Fritsla Nya Yllefabrik, nuv.\nnamn 1944.\n\nVerkst. dir.: fabr. W. A. Fält.\n\nTrio AB., Armaturfabriken,\n\nMidsommarkransen.\n\nSe Armaturfabriken Trio AB.,\nMidsommarkransen.\n\nAB. Trio-Sport, Kungälv.\n\nTillverkar sportartiklar såsom tält,\nsov-och ryggsäckar, sportväskor,\nshoppingväskor, packfickor, fot- och handbollar,\nbandybollar, skidstavar och -bindningar,\nhängmattor, kartfodral,\nsadelmakeriar-tiklar m. m.\n\nTelegr.-adr.: Triosport, Kungälv.\nTelefon: 325 o. 335. Postgiro: 144256.\nRepr. i Stockholm: Sportagenturen,\nTek-nologg. 5, telefon: 326257.\n\nAkt.-kap.: 30.000 kr. Antal\nindustriarb.: 100. Tillv.-värde pr år: 1,300,000 kr.\n— Bolaget grundat 1939.\n\nVerkst. &lt;},ir.: Eric Carlson.\n\nFörsäljn.-chef: O. J. Reis.\n\nAB. Tripasin, Malmö.\n\nTillverkar animaliska konsttarmar för\nkorvberedning. Varumärke: »Naturin».\n\nKontor: Industrig. 19. Telefon: 17630\no. 17650. Postgiro: 148152. Ensamförsälj.:\nAB. Schaub &amp; Co., Stockholm, Göteborg\no. Malmö.\n\nAkt.-kap.: 600,000 kr. Antal\nindustriarb.: 150. — Bolaget grundat 1937,\nfabrikationen börjad 1939.\n\nStyrelse: dir. K. Leube, dir. J. Schytt,\ndir. Hugo Thaning.\n\nVerkst. dir.: K. Leube.\n\nDisp.: H. Coles Frederiksen.\n\n*AB. Triplexfabriken, Enköping.\n\nMek. verkstad i Fanna, Enköping.\nTillverkar ställbar belysningsarmatur samt\ndörrknäppen och dörrlås; utför\nkallpressning och svetsning av tunnplåtsdetaljer.\nVarunamn: »Triplex», »3 Ex» o. »Trix».\n\nTelefon: 284. Postgiro: 36343.\nEnsamförsäljare för Triplex-pendlar: Asea,\nStockholm, Rosenlundsg. 31.\n\nAkt.-kap.: 140,200 kr. Antal\nindustriarb.: 20. Tillv.-värde pr år: 200,000 kr.\n\n—\tFirman etabl. 1919, bolag 1935.\nStyrelse: dir. H. Brynge, fröken J.\n\nBrynge, fru Ingrid Hammar.\nVerkst. dir.: H. Brynge.\nDisp.: Gustaf Kareli.\n\nTrollebo Yllefabrik, Eerrljunga.\n\nSpinneri, väveri och vaddfabrik i\nHerr-ljunga (Älvsb. l.). Tillverkar stickgarner,\nfiltar, möbeltyger, vadd och flock.\n\nTelefon: Hudene 16. Postgiro: 133447.\n\n—\tAntal industriarb.: 15. — Firman\netabl. 1887.\n\nÄgare o. chef: textiling. Bo Kämpe.\n\nAB. Trollhättans Bomullsväverl,\n\nTrollhättan.\n\nBomullsväven och färgeri. Tillverkar\nrutiga och randiga bomullstyger samt\nflaneller.\n\nTelefon: 10131 o. 10541. Postgiro:\n270096. — Akt.-kap.: 100,000 kr. Antal\nindustriarb.: 60. Tillv.-värde pr år:\n700,000 kr. — Firman etabl. 1920, bolag\n1923.\n\nVerkst. dir.: vakant.\n\n’Trollhättans Kloratfabrik,\n\nTrollhättan.\n\nSe Stockholms Superfosfat Fabriks\nAB., Stockholm.\n\nTrollhättans Läskedrycksfabrik &amp;\nSvagdrycksbryggeri, Trollhättan.\n\nTillverkar måltidsdricka, läskedrycker\noch mineralvatten.\n\nTelefon: 10346. Postgiro: 83978. —\nAntal industriarb.: 11. Tillv.-värde pr år:\n150,000 kr. — Firman etabl. 1922.\n\nÄgare o. chef: fabr. Henry Comstedt.\n\n’Tryckeri AB. C. A. Andersson &amp; Co»,\n\nMalmö.\n\nBoktryckeri.\n\nKontor: Hjulhamnsg. 5. Telefon:\n76220 o. 15002. Postgiro: 39241. —\nAkt.-kap.: 80,000 kr. Antal industriarb.: 20.\n\n—\tFirman grundad 1869, bolag 1939.\nStyrelse: disp. H.-O. Karlinder, fru E.\n\nNordmark.\n\nDisp.: H.-O. Karlinder.",
    "structured": {
        "1": {
            "name": "AB. Trikå- & Syfabriken Standard",
            "location": "Borås",
            "business": "Tillverkar dam-, herr- och barnunderkläder vid trikåfabrik i Fritsla (Älvsb. l.)",
            "contact": {
                "phone": [
                    "70061"
                ]
            },
            "financials": {
                "capital": "100,000 kr",
                "employees": {
                    "Antal industriarb.": 25
                },
                "annual_production_value": "400,000 kr"
            },
            "foundation_year": 1917,
            "current_name_year": 1944,
            "director": "fabr. W. A. Fält"
        },
        "2": {
            "name": "Trio AB., Armaturfabriken",
            "location": "Midsommarkransen",
            "business": "Se Armaturfabriken Trio AB., Midsommarkransen"
        },
        "3": {
            "name": "AB. Trio-Sport",
            "location": "Kungälv",
            "business": "Tillverkar sportartiklar såsom tält, sov-och ryggsäckar, sportväskor, shoppingväskor, packfickor, fot- och handbollar, bandybollar, skidstavar och -bindningar, hängmattor, kartfodral, sadelmakeriar-tiklar m. m."
        },
        "4": {
            "name": "AB. Tripasin",
            "location": "Malmö",
            "business": "Tillverkar animaliska konsttarmar för korvberedning. Varumärke: »Naturin»"
        },
        "5": {
            "name": "AB. Triplexfabriken",
            "location": "Enköping",
            "business": "Tillverkar ställbar belysningsarmatur samt dörrknäppen och dörrlås; utför kallpressning och svetsning av tunnplåtsdetaljer. Varunamn: »Triplex», »3 Ex» o. »Trix»"
        },
        "6": {
            "name": "Trollebo Yllefabrik",
            "location": "Herrljunga",
            "business": "Spinneri, väveri och vaddfabrik i Herr-ljunga (Älvsb. l.). Tillverkar stickgarner, filtar, möbeltyger, vadd och flock"
        },
        "7": {
            "name": "AB. Trollhättans Bomullsväverl",
            "location": "Trollhättan",
            "business": "Bomullsväven och färgeri. Tillverkar rutiga och randiga bomullstyger samt flaneller"
        },
        "8": {
            "name": "Trollhättans Läskedrycksfabrik & Svagdrycksbryggeri",
            "location": "Trollhättan",
            "business": "Tillverkar måltidsdricka, läskedrycker och mineralvatten"
        },
        "9": {
            "name": "Tryckeri AB. C. A. Andersson & Co»",
            "location": "Malmö",
            "business": "Boktryckeri"
        }
    }
}