{
    "original": "A Imqvist—A Ipha\n\n*AlmqMjst &amp; Wiksells Boktryckeri\nAB., Uppsala.\n\nBoktryckeri» ...litografi.sk anstalt,\nbok-binderi samt bokhandelsdistribution.\nUtför boktryck, spec. praktverk och\nvetenskapliga arbeten. Bolaget arrenderar\nKungl. Vetenskapsakademiens\nuteslutande privilegium å utgivandet av\nalmanackor och kalendarier för Sverige.\n\nHuvudkontor: Uppsala. Telegr.-adr.:\nCalender, Uppsala. Avd.-kontor:\nStockholm, Gamla Brog. 26. Telefoner:\n»Almqvist &amp; Wiksell», Uppsala o. Stockholm.\n— Akt.-kap.: 3,500,000 kr. ’Antå!\nindustriarb.: 429.\n\nFirman etabl. 1839, bolag och nuv.\nnamn 1888. Bolaget äger Ivar\nHaegg-ströms Boktryckeri &amp; Bokförlags AB.,\nStockholm, samt Hugo Gebers Förlag\nAB., Stockholm.\n\nStyrelse: ^ prof% Thore Engströmer\n(ordf.), f. riksbibliotekarien Isak Collijn\n(v. ordf.), disp. Göran Z. Haeggström,\nprof. Henning Pleijel, dir. H. W.\nSöderman.\n\nVerkst. dir.: Göran Z. Haeggström.\n\nKamrerare: S. B. Wiksell o. G. F. Ca-\n\n* Almunge Snickerifabrik, Almunge.\n\nTillverkar byggnadssnickerier vid\nfabrik i Almunge (Sthliös l.).\n\nTelefon: 31. — Antal industriarb.: 8.\nTillv.-värde pr år: 100,000 kr. — Firman\netabl. 1920.\n\nÄgare o. chef: fabr. Anselm Andersson.\n\nAlmviks Såg &amp; Tegelbruk, Almvih.\n\nSågverk, hyvleri, skaftfabrik och\ntegelbruk i Blekhem, Almvik (Kalmar l.).\nTillverkar sågade och hyvlade trävaror,\nverktygsskaft, mur- och taktegel samt\ndräneringsrör. Firman driver jämväl\njordbruk och skogshantering.\n\nTelefon: 11 o. 3. Postgiro: 75036. —\nAntal industriarb.: 35. Tillv.-värde pr år:\n100,000 kr.\n\nÄgare: frih. Johan A. Nordenfalk.\n\nFörvaltare: Karl E. Petersson.\n\nTegelmäst.: Joh. Johansson.\n\nAlnarps Redskapsverkstad, Gustaf\nBjörklund &amp; Son, Åharp.\n\nTillverkar lantbruksmaskiner,\ntipp-vagnar, cykel ställ, domkrafter, hej\nar-smidda kedjor och kedjehjul, kugghjul,\nskruvhakar m. m. vid mek. verkstad i\n\nÅkarp (Malin öL. i.).\n\nTelefon: 25. Postgiro: 142549.\nEnsam-försälj. för cykelställ och domkrafter:\nAB. Wilh. Sonesson &amp; Co., Malmön\nösterg. 35, telefon: »Sonesson &amp; Co.».\n\nAntal industriarb.: 20. Tillv.-värde pr\når: 300,000 kr. — Firman etabl. 1896.\n\nÄgare o. chef: civiling. Georg\nBjörklund.\n\nAlnö Tegelbruk AB., Alnö.\n\nTillverkar vanligt murtegel,\nlättmurtegel och högporöst murtegel vid\ntegelbruk i Stornäset, Alnö (Västernorrl. l.).\n\nKontor: Lervik, Alnö. Telefon:\nSundsvall 68200. Postgiro: 162967.\n\nAkt.-kap.: 80,000 kr. Antal\nindustriarb.: 35. Årstillv.: 2,5 milj. st. murtegel.\n— Bolaget grundat 1939.\n\nVerkst. dir.: grossh. C. O. Dahlström,\n\n*Aloxldverken AB., Svenska,\n\nStockholm.\n\nSe Svenska Aloxidverken AB.,\nStockholm.\n\nAlp AB., Mek. Verkstaden,\n\nSkillingaryd.\n\nSe Mek. Verkstaden Alp AB..,\nSkillingaryd.\n\n*AB. Alpha, Sundbyberg.\n\nMek. verkstad och bakelitfabrik i\nSundbyberg, bakelitfabrik i Uddevalla.\nTillverkar materialprovningsmaskiner,^\nkonden-satorer, ytskiktsmotstånd, elektrisk\ninstal-lationsmateriel samt pressade\nbakelitartiklar för radioapparater och telefoner\nm. m.\n\nTelegr.-adr.: Aktiealpha, Sundbyberg.\nTelefon: Stockholm 28260Ö o. Uddevalla\n11414. Postgiro: 3344.\n\nAkt.-kap.: 800,000 kr. Antal\nindustriarb.: 800. Tillv.-värde pr år: 9,000,000 kr.\n— Bolaget, grundat 1888, äges av Telefon\nAB. L. M. Ericsson.\n\nStyrelse: dir. Helge Ericson (ordf.)*\ndir. H. Berlin, dir. Hemming\nJohansson, dir. Gösta Klemming, dir. Georg\nOlsson.\n\nVerkst. dir.: H. Berlin.\n\nKamrer: S. Rossel.\n\nVerkstadschefer: i Sundbyberg:\nS-Ewerlöf, V. Juhlin o. Carl-Axel Sellberg;\ni Uddevalla: Ewert Karlson.\n\nFörsäljn.-chefer: Karl Nilson o. G.\nThorén.\n\n12*",
    "structured": {
        "firms": [
            {
                "name": "AlmqMjst & Wiksells Boktryckeri AB.",
                "location": "Stockholm",
                "business": "Boktryckeri, litografi, bok-binderi, bokhandelsdistribution",
                "products": "Boktryck, praktverk, vetenskapliga arbeten, almanackor, kalendarier",
                "contact": {
                    "office": "Uppsala",
                    "phone": [
                        "Almqvist & Wiksell, Uppsala",
                        "Almqvist & Wiksell, Stockholm"
                    ],
                    "postgiro": "Calender, Uppsala",
                    "head_office": "Uppsala",
                    "sales_offices": [
                        {
                            "location": "Stockholm",
                            "phone": "Gamla Brog. 26"
                        }
                    ],
                    "telegraph": "Calender, Uppsala",
                    "factory_office": "Ivar Haegg-ströms Boktryckeri & Bokförlags AB., Stockholm",
                    "factory_phone": "Not available"
                },
                "financials": {
                    "capital": "3,500,000 kr",
                    "employees": {
                        "industriarb": 429
                    },
                    "annual_turnover": "Not available",
                    "annual_production_value": "Not available"
                },
                "foundation_year": 1839,
                "current_name_year": 1888,
                "predecessor": "Not available",
                "original_name": "Not available",
                "corporation_year": "Not applicable",
                "board": [
                    {
                        "name": "prof% Thore Engströmer",
                        "role": "ordf."
                    },
                    {
                        "name": "Isak Collijn",
                        "role": "v. ordf."
                    },
                    {
                        "name": "Göran Z. Haeggström",
                        "role": "disp."
                    },
                    {
                        "name": "Henning Pleijel",
                        "role": "prof."
                    },
                    {
                        "name": "H. W. Söderman",
                        "role": "dir."
                    }
                ],
                "owners": [
                    "AB. L. M. Ericsson"
                ],
                "director": "Göran Z. Haeggström",
                "managing_director": "Not available",
                "sales_manager": "Not available",
                "brands": [
                    "Not available"
                ],
                "manager": "Not available",
                "reference": "Not available"
            },
            {
                "name": "Almunge Snickerifabrik",
                "location": "Almunge",
                "business": "Byggnadssnickerier",
                "products": "Not available",
                "contact": {
                    "office": "Almunge",
                    "phone": [
                        "31"
                    ],
                    "postgiro": "Not available",
                    "head_office": "Not available",
                    "sales_offices": [],
                    "telegraph": "Not available",
                    "factory_office": "Not available",
                    "factory_phone": "Not available"
                },
                "financials": {
                    "capital": "Not available",
                    "employees": {
                        "industriarb": 8
                    },
                    "annual_turnover": "Not available",
                    "annual_production_value": "100,000 kr"
                },
                "foundation_year": 1920,
                "current_name_year": "Not applicable",
                "predecessor": "Not available",
                "original_name": "Not available",
                "corporation_year": "Not applicable",
                "board": [],
                "owners": [
                    "Not available"
                ],
                "director": "Anselm Andersson",
                "managing_director": "Not available",
                "sales_manager": "Not available",
                "brands": [
                    "Not available"
                ],
                "manager": "Not available",
                "reference": "Not available"
            },
            {
                "name": "Almviks Såg & Tegelbruk",
                "location": "Almvih",
                "business": "Sågverk, hyvleri, skaftfabrik, tegelbruk, jordbruk, skogshantering",
                "products": "Sågade trävaror, hyvlade trävaror, verktygsskaft, murtegel, taktegel, dräneringsrör",
                "contact": {
                    "office": "Blekhem, Almvik",
                    "phone": [
                        "11",
                        "3"
                    ],
                    "postgiro": "75036",
                    "head_office": "Not available",
                    "sales_offices": [],
                    "telegraph": "Not available",
                    "factory_office": "Not available",
                    "factory_phone": "Not available"
                },
                "financials": {
                    "capital": "Not available",
                    "employees": {
                        "industriarb": 35
                    },
                    "annual_turnover": "Not available",
                    "annual_production_value": "100,000 kr"
                },
                "foundation_year": "Not available",
                "current_name_year": "Not applicable",
                "predecessor": "Not available",
                "original_name": "Not available",
                "corporation_year": "Not applicable",
                "board": [],
                "owners": [
                    "frih. Johan A. Nordenfalk"
                ],
                "director": "Not available",
                "managing_director": "Karl E. Petersson",
                "sales_manager": "Not available",
                "brands": [
                    "Not available"
                ],
                "manager": "Not available",
                "reference": "Not available"
            },
            {
                "name": "Alnarps Redskapsverkstad, Gustaf Björklund & Son",
                "location": "Åharp",
                "business": "Tillverkar lantbruksmaskiner, tipp-vagnar, cykel ställ, domkrafter, hejar-smidda kedjor, kedjehjul, kugghjul, skruvhakar",
                "products": "Not available",
                "contact": {
                    "office": "Åkarp",
                    "phone": [
                        "25"
                    ],
                    "postgiro": "142549",
                    "head_office": "Not available",
                    "sales_offices": [],
                    "telegraph": "Not available",
                    "factory_office": "Not available",
                    "factory_phone": "Not available"
                },
                "financials": {
                    "capital": "Not available",
                    "employees": {
                        "industriarb": 20
                    },
                    "annual_turnover": "Not available",
                    "annual_production_value": "300,000 kr"
                },
                "foundation_year": 1896,
                "current_name_year": "Not applicable",
                "predecessor": "Not available",
                "original_name": "Not available",
                "corporation_year": "Not applicable",
                "board": [],
                "owners": [
                    "Not available"
                ],
                "director": "civiling. Georg Björklund",
                "managing_director": "Not available",
                "sales_manager": "Not available",
                "brands": [
                    "Not available"
                ],
                "manager": "Not available",
                "reference": "Not available"
            },
            {
                "name": "Alnö Tegelbruk AB.",
                "location": "Alnö",
                "business": "Tillverkar vanligt murtegel, lättmurtegel, högporöst murtegel",
                "products": "Not available",
                "contact": {
                    "office": "Stornäset, Alnö",
                    "phone": [
                        "Sundsvall 68200"
                    ],
                    "postgiro": "162967",
                    "head_office": "Not available",
                    "sales_offices": [],
                    "telegraph": "Not available",
                    "factory_office": "Not available",
                    "factory_phone": "Not available"
                },
                "financials": {
                    "capital": "80,000 kr",
                    "employees": {
                        "industriarb": 35
                    },
                    "annual_turnover": "Not available",
                    "annual_production_value": "2,5 milj. st. murtegel"
                },
                "foundation_year": 1939,
                "current_name_year": "Not applicable",
                "predecessor": "Not available",
                "original_name": "Not available",
                "corporation_year": "Not applicable",
                "board": [],
                "owners": [
                    "Not available"
                ],
                "director": "grossh. C. O. Dahlström",
                "managing_director": "Not available",
                "sales_manager": "Not available",
                "brands": [
                    "Not available"
                ],
                "manager": "Not available",
                "reference": "Not available"
            },
            {
                "name": "AB. Alpha",
                "location": "Sundbyberg",
                "business": "Mek. verkstad, bakelitfabrik",
                "products": "Materialprovningsmaskiner, kondensatorer, ytskiktsmotstånd, elektrisk installationsmateriel, pressade bakelitartiklar",
                "contact": {
                    "office": "Sundbyberg, Uddevalla",
                    "phone": [
                        "Stockholm 28260",
                        "Uddevalla 11414"
                    ],
                    "postgiro": "3344",
                    "head_office": "Not available",
                    "sales_offices": [],
                    "telegraph": "Aktiealpha, Sundbyberg",
                    "factory_office": "Not available",
                    "factory_phone": "Not available"
                },
                "financials": {
                    "capital": "800,000 kr",
                    "employees": {
                        "industriarb": 800
                    },
                    "annual_turnover": "9,000,000 kr",
                    "annual_production_value": "Not available"
                },
                "foundation_year": 1888,
                "current_name_year": "Not applicable",
                "predecessor": "Not available",
                "original_name": "Not available",
                "corporation_year": "Not applicable",
                "board": [
                    {
                        "name": "dir. Helge Ericson",
                        "role": "ordf."
                    },
                    {
                        "name": "H. Berlin",
                        "role": "dir."
                    },
                    {
                        "name": "Hemming Johansson",
                        "role": "dir."
                    },
                    {
                        "name": "Gösta Klemming",
                        "role": "dir."
                    },
                    {
                        "name": "Georg Olsson",
                        "role": "dir."
                    }
                ],
                "owners": [
                    "Telefon AB. L. M. Ericsson"
                ],
                "director": "Not available",
                "managing_director": "H. Berlin",
                "sales_manager": "Karl Nilson, G. Thorén",
                "brands": [
                    "Not available"
                ],
                "manager": "Not available",
                "reference": "Not available"
            }
        ]
    }
}