{
    "original": "Svenska\n\nAB. Svenska Salpeterverken,\n\nKöping.\n\nFabrik för tillverkning av\nkvävegödselmedel (kalkammonsalpeter), salpetersyra,\nammoniak, ammoniumnitrat och andra\nammoniakprodukter.\n\nTelegr.-adr.: Koab, Köping. Telefon:\n»Salpeterverken». Postgiro: 280970.\n\nAkt.-kap.: 5,000,000 kr. Arb.-antal: 200.\nTillv.-värde pr år: 8,000,000 kr. —\nBolaget, grundat 1943, äges av Kooperativa\nFörbundet, Stockholm.\n\nStyrelse: dir. Albin Johansson (ordf.),\nfil. lic. Mauritz Bonow, dir. Hj.\nDeger-stedt, dir. Hugo Edstam, dir. G. Osvald,\ndir. Ernst Persson.\n\nVerkst. dir. o. disp: civiling. Hilding\nHåkanson.\n\növering.: civiling. Pål Pålsson.\n\nKamrer: Kaleb Back.\n\nLaboratoriechef: dr J. Kuusk.\n\n\"AB. Svenska Siden väveriet,\n\nHälsingborg.\n\nTillverkar sidentyger.\n\nTelegr.-adr.: Svesiko, Hälsingborg.\nTelefon: 17929. Postgiro: 135780.\n\nAkt.-kap.: 100,000 kr. Antal\nindustriarb. : 60. — Bolaget grundat 1937.\n\nStyrelse: f. d. assessor Henry\nLjunggren (ordf.), adv. Bengt Linders, dir. Carl\nJ. Michaelsen.\n\nDisp.: Walter Michaelsen.\n\nSvenska Silikategelfabriken, Sven\nSetterberg, Göteborg.\n\nKvartsbrott och tegelfabrik vid\nAnnenäset, Köpmannebro (Älvsb. l.).\n\nBryter kvarts och kvartsit samt\nframställer krossad kvarts och kvartsit för\njärnbruk, för blästringsändamål, som\nfiltersand, till putsmedel m. fl. ändamål;\ntillverkar silikategel, kupolugnstegel,\nångpannetegel och annat specialtegel,\nkupolugns- och stampmassa (märke: »Svea»),\neldfast cement (märke: »Silicit»),\nsilika-paint för stålgjuterier, råvattenglas m. m.\n\nHuvudkontor o. försäljn.: Göteborg,\nStora Badhusg. 20. Telegr.-adr.: Silika,\nGöteborg. Telefon: 132953 o. 132956.\nFabrikskontor: Köpmannebro. Telefon:\nKöpmannebro 5.\n\nAntal industriarb.: 85. Tillv.-värde pr\når: 1,000,000 kr. — Firman etabl. 1902.\n\nÄgare o. chef: disp. Sven Setterberg.\n\nDriftsing.: Oleg Backlund.\n\nKontorschef: fru H. Silfverstolpe.\n\nSvenska Skaftfabriken,\n\nSöderhamn.\n\nSnickerifabrik. Tillverkar skaft samt\nandra svarvade massartiklar.\n\nTelegr.-adr.: Skaftfabriken, Söderhamn.\nTelefon: 2345. Postgiro: 34567. —\nArb.-antal: 11. Tillv.-värde pr år: 90,000 kr.\n— Fabriken anlagd 1907.\n\nÄgare: fabr. Ernst Erikson.\n\nFabriks förest.: verkmäst. Emil\nNilsson.\n\n\"Svenska Skandex AB., Stockholm.\n\nStålmanufakturfabrik i Ulvsunda\n(Stockholm). Tillverkar kortregisterskåp,\nbrandisolerade dokumentskåp,\nbokföringssystem och övrig kontorsteknisk\nutrustning. Varumärke: »Skandex».\n\nKontor: Stockholm, Nybrokajen 3.\nTelegr.-adr.: Skandex, Stockholm. Telefon:\n230895. Postgiro: 3121.\n\nAkt.-kap.: 200,000 kr. Antal\nindustriarb.: 165. — Bolaget grundat 1932.\n\nStyrelse: dir. Gustaf B. Söderlund\n(ordf.), dir. Algot Hanson, bankdir. G.\nG. Rissler, kapten Bengt Söderlund,\nbergsing. Finn Söderlund, ing. Stig\nSöderlund.\n\nVerkst. dir.: Gustaf B. Söderlund.\n\nFörsäljn.-chef: Bengt Söderlund.\n\nExportchef: Algot Hanson.\n\n\"Svenska Skifferolje AB., Örebro.\n\nSkifferoljeverk i Kvarntorp (Örebro\n1.) samt i Kinne-Kleva (Skarab. l.).\nTillverkar brännolja, bensin och fotogen,\nskifferasfalt, svavel, ammoniumsulfat,\nkalk m. m.\n\nKontor: Örebro, Drottningg. 3.\nTele-gr.-adr.: Sveskiab, Örebro. Telefon:\n19195. Postgiro: 159662.\n\nAkt.-kap.: 20,000,000 kr. Antal\nindustriarb.: 1,000.\n\nBolaget grundat 1941. Svenska staten\näger aktiemajoriteten i bolaget.\n\nStyrelse: marinöverdir. J. H.\nQvist-gaard (ordf.), förbundssekr. Gunnar\nMohlne (v. ordf.), riksdagsm. ^ E. R.\nBrandt, dir. Claes Gejrot, övering. E.\nSchön, dir. Torsten Åqvist.\n\nVerkst. dir.: Claes Gejrot.\n\nIntendent o. försäljn.-dir.: Hans\nWi-borgh.\n\nKamrer: Henry Steijer.\n\nPlaneringschef: civiling. Nils\nBergen-stråhle.\n\növering.: civiling. Arvid Johansson.\n\nLaboratoriechef: prof. Edmund\nSchjån-berg.\n\nInköpschef: Inge Svenson.",
    "structured": {
        "1": {
            "name": "AB. Svenska Salpeterverken",
            "location": "Köping",
            "business": "Fabrik för tillverkning av kvävegödselmedel (kalkammonsalpeter), salpetersyra, ammoniak, ammoniumnitrat och andra ammoniakprodukter",
            "contact": {
                "telegraph": "Koab, Köping",
                "phone": [
                    "»Salpeterverken»"
                ],
                "postgiro": "280970"
            },
            "financials": {
                "capital": "5,000,000 kr",
                "employees": {
                    "arb.-antal": 200
                },
                "annual_production_value": "8,000,000 kr"
            },
            "foundation_year": 1943,
            "owners": [
                "Kooperativa Förbundet, Stockholm"
            ],
            "board": [
                {
                    "name": "dir. Albin Johansson",
                    "role": "ordf."
                },
                {
                    "name": "fil. lic. Mauritz Bonow",
                    "role": null
                },
                {
                    "name": "dir. Hj. Deger-stedt",
                    "role": null
                },
                {
                    "name": "dir. Hugo Edstam",
                    "role": null
                },
                {
                    "name": "dir. G. Osvald",
                    "role": null
                },
                {
                    "name": "dir. Ernst Persson",
                    "role": null
                }
            ],
            "director": "civiling. Hilding Håkanson",
            "managing_director": "civiling. Pål Pålsson",
            "manager": "Kaleb Back",
            "laboratory_manager": "dr J. Kuusk"
        },
        "2": {
            "name": "AB. Svenska Siden väveriet",
            "location": "Hälsingborg",
            "business": "Tillverkar sidentyger",
            "contact": {
                "telegraph": "Svesiko, Hälsingborg",
                "phone": [
                    "17929"
                ],
                "postgiro": "135780"
            },
            "financials": {
                "capital": "100,000 kr",
                "employees": {
                    "industriarb.": 60
                }
            },
            "foundation_year": 1937,
            "board": [
                {
                    "name": "f. d. assessor Henry Ljunggren",
                    "role": "ordf."
                },
                {
                    "name": "adv. Bengt Linders",
                    "role": null
                },
                {
                    "name": "dir. Carl J. Michaelsen",
                    "role": null
                }
            ],
            "manager": "Walter Michaelsen"
        },
        "3": {
            "name": "Svenska Silikategelfabriken",
            "manager": "Sven Setterberg",
            "location": "Göteborg",
            "business": "Kvartsbrott och tegelfabrik",
            "contact": {
                "head_office": "Stora Badhusg. 20, Göteborg",
                "sales_offices": [
                    {
                        "location": "Göteborg",
                        "phone": "132953"
                    },
                    {
                        "location": "Köpmannebro",
                        "phone": "Köpmannebro 5"
                    }
                ]
            },
            "financials": {
                "employees": {
                    "industriarb.": 85
                },
                "annual_production_value": "1,000,000 kr"
            },
            "foundation_year": 1902,
            "owners": [
                "Sven Setterberg"
            ],
            "managerial_staff": {
                "driftsing.": "Oleg Backlund",
                "kontorschef": "fru H. Silfverstolpe"
            }
        },
        "4": {
            "name": "Svenska Skaftfabriken",
            "location": "Söderhamn",
            "business": "Snickerifabrik",
            "contact": {
                "telegraph": "Skaftfabriken, Söderhamn",
                "phone": [
                    "2345"
                ],
                "postgiro": "34567"
            },
            "financials": {
                "employees": {
                    "arb.-antal": 11
                },
                "annual_production_value": "90,000 kr"
            },
            "foundation_year": 1907,
            "owners": [
                "fabr. Ernst Erikson"
            ],
            "managerial_staff": {
                "verkmäst.": "Emil Nilsson"
            }
        },
        "5": {
            "name": "Svenska Skandex AB.",
            "location": "Stockholm",
            "business": "Stålmanufakturfabrik",
            "contact": {
                "location": "Stockholm, Nybrokajen 3",
                "telegraph": "Skandex, Stockholm",
                "phone": [
                    "230895"
                ],
                "postgiro": "3121"
            },
            "financials": {
                "capital": "200,000 kr",
                "employees": {
                    "industriarb.": 165
                }
            },
            "foundation_year": 1932,
            "board": [
                {
                    "name": "dir. Gustaf B. Söderlund",
                    "role": "ordf."
                },
                {
                    "name": "dir. Algot Hanson",
                    "role": null
                },
                {
                    "name": "bankdir. G. G. Rissler",
                    "role": null
                },
                {
                    "name": "kapten Bengt Söderlund",
                    "role": null
                },
                {
                    "name": "bergsing. Finn Söderlund",
                    "role": null
                },
                {
                    "name": "ing. Stig Söderlund",
                    "role": null
                }
            ],
            "managerial_staff": {
                "verkst. dir.": "Gustaf B. Söderlund",
                "försäljn.-chef": "Bengt Söderlund",
                "exportchef": "Algot Hanson"
            }
        },
        "6": {
            "name": "Svenska Skifferolje AB.",
            "location": "Örebro",
            "business": "Skifferoljeverk",
            "contact": {
                "location": "Örebro, Drottningg. 3",
                "telegraph": "Sveskiab, Örebro",
                "phone": [
                    "19195"
                ],
                "postgiro": "159662"
            },
            "financials": {
                "capital": "20,000,000 kr",
                "employees": {
                    "industriarb.": 1,
                    "bord members": [
                        165
                    ]
                }
            },
            "foundation_year": 1941,
            "owners": [
                "Svenska staten"
            ],
            "board": [
                {
                    "name": "marinöverdir. J. H. Qvistgaard",
                    "role": "ordf."
                },
                {
                    "name": "förbundssekr. Gunnar Mohlne",
                    "role": "v. ordf."
                },
                {
                    "name": "riksdagsm. ^ E. R. Brandt",
                    "role": null
                },
                {
                    "name": "dir. Claes Gejrot",
                    "role": null
                },
                {
                    "name": "övering. E. Schön",
                    "role": null
                },
                {
                    "name": "dir. Torsten Åqvist",
                    "role": null
                }
            ],
            "managerial_staff": {
                "verkst. dir.": "Claes Gejrot",
                "intendent o. försäljn.-dir.": "Hans Wiborgh",
                "kamrer": "Henry Steijer",
                "planeringschef": "civiling. Nils Bergenstråhle",
                "övering.": "civiling. Arvid Johansson",
                "laboratoriechef": "prof. Edmund Schjånberg",
                "inköpschef": "Inge Svenson"
            }
        }
    }
}