{
    "original": "Blomberg—Blomster måla\n\nJohn Blomberg &amp; Co. AB.,\n\nStockholm.\n\nPåsfabrik med tryckeri. Tillverkar\npapperspåsar samt s. k. dräktpåsar\n(märke: »Altifin»). Firman driver även\nengroshandel med papper.\n\nKontor: Torsg. 10. Telegr.-adr.:\nJohnblombergs, Stockholm. Telefon: 233795.\nPostgiro: 1434. — Akt.-kap.: 300,000\nkr. Antal industriarb.: 35. Tillv.-värde\npr år: 700,000 kr. — Firman etabl. 1868,\nbolag 1909.\n\nStyrelse: kabinettskammarh. Eric A.\nHallin (ordf.), fröken M. Molin, dir.\nConrad Neiglick.\n\nVerkst. dir.: C. Neiglick.\nV. verkst. direktörer: B. Deland o.\nSven Neiglick.\n\n*Erik Blomgren, Gnosjö.\n\nTillverkar klädhängare vid\nsnickerifabrik i Gnosjö (Jönköp. l.).\n\nTelefon: Maråsby 16. Postgiro: 76785.\n— Antal industriarb.: 11. Tillv.-värde pr\når: 100,000 kr. — Firman etabl. 1929.\nÄgare o. chef: fabr. Erik Blomgren.\n\n*Blomqvists Verkstads AB.,\n\nSödertälje.\n\nTillverkar blandningsmaskiner (»Beve»,\n»Svenske» o. SV) för kök, bagerier och\nkonditorier samt bänksvarvar och mindre\nrevolversvarvar.\n\nTelegr.-adr.: Beve, Södertälje. Telefon:\n30301 o. 30497. Postgiro: 161780.\nFörsälj.: i Stockholm: AB. Schaub &amp; Co.,\nMaskinavd., Enskede, Stockholm 20,\ntelefon: 492525 o. Julius Sjögren\nSpecialmaskiner AB., Drottningg. 100, telefon:\n208028; Malmö: Georg Hy len AB.,\nStormg. 9 b, telefon: 71630.\n\nAkt.-kap.: 50,000 kr. Antal\nindustriarb.: 35. Tillv.-värde pr år: 600,000 kr.\n— Bolaget grundat 1926.\n\nStyrelse, verkst. dir. o. verkstadschef:\nAxel Aastrup.\n\nArtur Blomkvist Metallfabrik,\n\nEskilstuna.\n\nTillverkar elektr. belysningsarmatur,\noljekranar samt järnmanufaktur.\n\nTelefon: 31549. Postgiro: 72331. —\nArb.-antal: 12. Tillv.-värde pr år: 150,000\nkr. — Firman etabl. 1921.\n\nÄgare o. chef: fabr. Artur Blomkvist.\n\nC. C. Blomqvist, Eskilstuna.\n\nKnivfabrik. Tillverkar slidknivar,\nkorkskruvar, rostfria skalknivar och\npo-tatisskalare.\n\nTelefon: 31134. — Arb.-antal: 6.\nTillv.-värde pr år: 50,000 kr. — Firman\netabl. 1915.\n\nÄgare: fru Alma Blomqvist.\n\nDriftschefer: fabr. Thore Blomqvist o.\nfabr. Elmer Blomqvist.\n\n*AB. J. E. Blomqvist, Uppsala.\n\nMöbelverkstäder i Storvreta (Uppsala\n1.). Tillverkar möbler och inredningar.\n\nKontor: Uppsala. Telefon: 30779.\nPostgiro: 5360. — Akt.-kap.: 65,000 kr. Antal\nindustriarb.: 40. Tillv.-värde pr år:\n525,000 kr. — Bolaget grundat 1912.\n\nStyrelse: dir. Petrus Blomqvist (ordf.),\ndisp. Jabez Blomqvist.\n\nVerkst. dir.: Petrus Blomqvist.\n\nVerkstadschef: Jabez Blomqvist.\n\n*AB. Sterner Blomquist, Malmö.\n\nMek. verkstad. Utför renoveringar av\nautomobil- och flygmotorer; tillverkar\nbilreservdelar, verktyg och slipmaskiner\nför motorarbeten samt\nvattendynamomet-rar för provning av motorer.\n\nKontor: ö. Förstadsg. 9—11.\nTelegr.-adr.: Motorsterner, Malmö. Telefon:\n»Sterner Blomquist». Postgiro: 38321.\n\nAkt.-kap.: 120,000 kr. Antal\nindustriarb.: 150. Tillv.-värde pr år: 2,000,000 kr.\n— Firman etabl. 1927, bolag 1928.\n\nStyrelse: ing. Sterner Blomquist\n(ordf.), chefsassistent Gunnar\nMalmström.\n\nVerkst. dir.: Sterner Blomquist.\n\nChefsassistent: Gunnar Malmström.\n\nVerkstads chef: Karl Holmström.\n\nBlomsterfabriks AB., Malmö.\n\nTillverkar konstgjorda blommor.\n\nKontor: Drottningg. 38. Telegr.-adr.:\nBlomsterbolaget, Malmö. Telefon: 20167.\nPostgiro: 37715. — Akt.-kap.: 48,000 kr.\nAntal industriarb.: 50. — Bolaget\ngrundat 1902.\n\nStyrelse: adv. Rolf Nordenstedt (ordf.),\nadv. Gunnar Behm, dir. H. G. Raaschou.\n\nDisp.: fröken E. Palmgren.\n\n*AB. Blomstermåla Möbelfabrik,\n\nBlomstermåla.\n\nTillverkar matsals-, sovrums- och\nherr-rumsmöbler samt inredningar vid fabrik\ni Blomstermåla (Kalmar l.).",
    "structured": {
        "1": {
            "name": "John Blomberg & Co. AB.",
            "location": "Stockholm",
            "business": "Påsfabrik med tryckeri. Tillverkar papperspåsar samt s. k. dräktpåsar (märke: »Altifin»). Firman driver även engroshandel med papper.",
            "contact": {
                "office": "Torsg. 10",
                "phone": [
                    "233795"
                ],
                "postgiro": "1434",
                "telegraph": "Johnblombergs, Stockholm"
            },
            "financials": {
                "capital": "300,000 kr",
                "employees": {
                    "industriarb": 35
                },
                "annual_turnover": "700,000 kr",
                "annual_production_value": "700,000 kr"
            },
            "foundation_year": 1868,
            "corporation_year": 1909,
            "board": [
                {
                    "name": "kabinettskammarh. Eric A. Hallin",
                    "role": "ordf."
                },
                {
                    "name": "fröken M. Molin",
                    "role": ""
                },
                {
                    "name": "dir. Conrad Neiglick",
                    "role": ""
                }
            ],
            "director": "C. Neiglick",
            "managing_director": "C. Neiglick",
            "sales_manager": "",
            "manager": ""
        },
        "2": {
            "name": "Erik Blomgren",
            "location": "Gnosjö",
            "business": "Tillverkar klädhängare vid snickerifabrik i Gnosjö (Jönköp. l.)",
            "contact": {
                "office": "",
                "phone": [
                    "Maråsby 16"
                ],
                "postgiro": "76785"
            },
            "financials": {
                "employees": {
                    "industriarb": 11
                },
                "annual_production_value": "100,000 kr"
            },
            "foundation_year": 1929,
            "director": "",
            "managing_director": "",
            "sales_manager": "",
            "manager": "Erik Blomgren"
        },
        "3": {
            "name": "Blomqvists Verkstads AB.",
            "location": "Södertälje",
            "business": "Tillverkar blandningsmaskiner (»Beve», »Svenske» o. SV) för kök, bagerier och konditorier samt bänksvarvar och mindre revolversvarvar",
            "contact": {
                "office": "",
                "phone": [
                    "30301",
                    "30497"
                ],
                "postgiro": "161780"
            },
            "financials": {
                "capital": "50,000 kr",
                "employees": {
                    "industriarb": 35
                },
                "annual_turnover": "600,000 kr",
                "corporation_year": 1926
            },
            "director": "",
            "managing_director": "Axel Aastrup",
            "sales_manager": "",
            "manager": "Axel Aastrup"
        },
        "4": {
            "name": "Artur Blomkvist Metallfabrik",
            "location": "Eskilstuna",
            "business": "Tillverkar elektr. belysningsarmatur, oljekranar samt järnmanufaktur",
            "contact": {
                "office": "",
                "phone": [
                    "31549"
                ],
                "postgiro": "72331"
            },
            "financials": {
                "employees": {
                    "antal": 12
                },
                "annual_production_value": "150,000 kr"
            },
            "foundation_year": 1921,
            "director": "",
            "managing_director": "",
            "sales_manager": "",
            "manager": "Artur Blomkvist"
        },
        "5": {
            "name": "C. C. Blomqvist",
            "location": "Eskilstuna",
            "business": "Knivfabrik. Tillverkar slidknivar, korkskruvar, rostfria skalknivar och po-tatisskalare",
            "contact": {
                "office": "",
                "phone": [
                    "31134"
                ]
            },
            "financials": {
                "employees": {
                    "antal": 6
                },
                "annual_production_value": "50,000 kr"
            },
            "foundation_year": 1915,
            "director": "",
            "managing_director": "",
            "sales_manager": "",
            "manager": "fru Alma Blomqvist"
        },
        "6": {
            "name": "AB. J. E. Blomqvist",
            "location": "Uppsala",
            "business": "Möbelverkstäder i Storvreta (Uppsala 1.). Tillverkar möbler och inredningar",
            "contact": {
                "office": "",
                "phone": [
                    "30779"
                ],
                "postgiro": "5360"
            },
            "financials": {
                "capital": "65,000 kr",
                "employees": {
                    "antal": 40
                },
                "annual_production_value": "525,000 kr"
            },
            "corporation_year": 1912,
            "board": [
                {
                    "name": "dir. Petrus Blomqvist",
                    "role": "ordf."
                },
                {
                    "name": "disp. Jabez Blomqvist",
                    "role": ""
                }
            ],
            "director": "Petrus Blomqvist",
            "managing_director": "Petrus Blomqvist",
            "sales_manager": "",
            "manager": "Jabez Blomqvist"
        },
        "7": {
            "name": "AB. Sterner Blomquist",
            "location": "Malmö",
            "business": "Mek. verkstad. Utför renoveringar av automobil- och flygmotorer; tillverkar bilreservdelar, verktyg och slipmaskiner för motorarbeten samt vattendynamomet-rar för provning av motorer",
            "contact": {
                "office": "ö. Förstadsg. 9—11",
                "phone": [
                    ""
                ],
                "postgiro": "38321"
            },
            "financials": {
                "capital": "120,000 kr",
                "employees": {
                    "antal": 150
                },
                "annual_production_value": "2,000,000 kr"
            },
            "corporation_year": 1928,
            "board": [
                {
                    "name": "ing. Sterner Blomquist",
                    "role": "ordf."
                },
                {
                    "name": "chefsassistent Gunnar Malmström",
                    "role": ""
                }
            ],
            "director": "Sterner Blomquist",
            "managing_director": "Sterner Blomquist",
            "sales_manager": "",
            "manager": "Karl Holmström"
        },
        "8": {
            "name": "Blomsterfabriks AB.",
            "location": "Malmö",
            "business": "Tillverkar konstgjorda blommor",
            "contact": {
                "office": "Drottningg. 38",
                "phone": [
                    "20167"
                ],
                "postgiro": "37715"
            },
            "financials": {
                "capital": "48,000 kr",
                "employees": {
                    "antal": 50
                }
            },
            "foundation_year": 1902,
            "board": [
                {
                    "name": "adv. Rolf Nordenstedt",
                    "role": "ordf."
                },
                {
                    "name": "adv. Gunnar Behm",
                    "role": ""
                },
                {
                    "name": "dir. H. G. Raaschou",
                    "role": ""
                },
                {
                    "name": "fröken E. Palmgren",
                    "role": "Disp."
                }
            ],
            "director": "",
            "managing_director": "",
            "sales_manager": "",
            "manager": ""
        },
        "9": {
            "name": "AB. Blomstermåla Möbelfabrik",
            "location": "Blomstermåla",
            "business": "Tillverkar matsals-, sovrums- och herr-rumsmöbler samt inredningar vid fabrik i Blomstermåla (Kalmar l.)",
            "contact": {
                "office": "",
                "phone": [
                    ""
                ],
                "postgiro": ""
            },
            "financials": {
                "capital": "N/A",
                "employees": {
                    "antal": 0
                }
            },
            "foundation_year": "N/A",
            "director": "",
            "managing_director": "",
            "sales_manager": "",
            "manager": "fabr. Erik Blomgren"
        }
    }
}