{
    "original": "A pote karne—A rabin\n\nApotekarnas Kemiska Laboratorium\n\nAB., Stockholm.\n\nKem.-tekn. fabrik. Tillverkar fria\nläkemedel, förbandsartiklar, kosmetiska\npreparat, pastiller m. m. Varumärken:\n»Akla», »Kim» o. »Askamin».\n\nKontor: Norrtullsg. 41—43.\nTelegr.-adr.: Apotekskemi, Stockholm. Telefon:\n232380. Postgiro: 1670.\n\nAkt.-kap.: 300,000 kr. Antal\nindustriarb.: 80. Tillv.-värde pr år: 750,000 kr.\n— Firman etabl. 1926, ombildad 1928.\n\nStyrelse: dir. E. öhman (ordf.), apot.\nI. G:son Blomqvist, dir. Bertil H.\nLarsson.\n\nVerkst. dir,: B. H. Larsson.\n\nKamrer: Gunnar Wanger.\n\n\"Apotekarnes Mineralvattens AB.y\n\nStockholm.\n\nTillverkar mineralvatten, läskedrycker\noch medicinska vatten. Varumärke:\n»AMA».\n\nKontor: Norra Stationsg. 69.\nTelegr.-adr.: Mineralvatten, Stockholm. Telefon:\n»Apotekarnes vatten». Postgiro: 1949.\n\nAkt.-kap.: 5,000,000 kr. Antal\nindustriarb.: 285. Prod.-värde pr år: 9,000,000 kr.\n\nBolaget grundat 1874. AB. Stockholms\nBryggerier är huvudintressent i bolaget.\n\nStyrelse: dir. Sven Schwartz (ordf.),\ndir. Harald Engström, dir. Ivan\nNordgren.\n\nVerkst. dir.: Ivan Nordgren.\n\nDir.-assist.: jur. kand. E. G. Jonsell.\n\nÖvering.: civiling. Rolf Steenhoff.\n\nApoteksvarucentralen Vitrum,\nApotekare AB., Stockholm.\n\nLäkemedelsfabrik och förbandsfabrik.\nFirman driver dessutom engroshandel\nmed läkemedel, sjukvårdsartiklar och\nlaboratorieutensilier.\n\nKontor: Torsg. 4. Telegr.-adr.: Vitrum,\nStockholm. Telefon:\n»Apoteksvarucentralen». Postgiro: 1151.\n\nAkt.-kap.: 2,268,000 kr. Antal\nindustriarb.: 105. — Firman etabl. 1877 under\nnamn Nordstjärnans Droghandel, nuv.\nnamn o. bolag 1930.\n\nStyrelse: apot. Harald Ringberg\n(ordf.), apot. Erik Berlin, dir. Bertil\nBjurling, apot. Gösta Bjurling, apot.\nGottfrid Winberg.\n\nVerkst. dir.: Bertil Bjurling.\n\nDriftschef: Gösta Bjurling.\n\nInlcöpschef: Eric Runert.\n\nFörsäljn.-chef: Josef Magnuson.\n\nAppelbergs Boktryckeri AB.,\n\nU ppsala.\n\nUtför boktryck, akademiska\navhandlingar och tidskrifter m. m. ävensom\nreklam- och accidenstryck samt\nombesörjer distribution av trycksaker.\n\nTelefon: 31016 o. 33300. Postgiro:\n26060. — Akt.-kap.: 250,000 kr. Antal\nindustriarb.: 25. Tillv.-värde pr år:\n350,000 kr. — Firman etabl. 1903, bolag\n1916.\n\nVerkst. dir.: A. Lunden.\n\nAppelgrens Borstfabrik, Stockholm.\n\nTillverkar kvastar, levanger, hårborstar\nm. m. Specialitet: maskinborstar och\nborstrullar.\n\nKontor: S:t Paulsg. 33 B. Telefon:\n434720. — Antal industriarb.: 5.\nTillv.-värde pr år: 60,000 kr. — Firman etabl.\n1888.\n\nÄgare o. chef: fru Thyra Appelgren.\n\nAB. Appells Smides- &amp; Mek.\n\nVerkstad, Falun.\n\nTillverkar smidesarbeten,\ngrovplåtsar-beten samt järnkonstruktioner.\n\nTelefon: 1691. Postgiro: 171407. —\nAkt.-kap.: 20,000 kr. Antal industriarb.:\n30. Tillv.-värde pr år: 350,000 kr. —\nFirman etabl. 1906, bolag 1941.\nVerkst. dir.: fabr. Erik Appell.\n\n\"Appeltofftska Bryggeri AB.,\n\nHalmstad.\n\nTillverkar malt samt malt- och\nläskedrycker.\n\nTelefon: 317 o. 3317. Postgiro: 98290.\n\n—\tAkt.-kap.: 765,000 kr. Antal\nindustriarb.: 25. Tillv.-värde pr år: 1,000,000 kr.\n\n—\tBolaget grundat 1861.\n\nStyrelse: jur. dr K. Hillgård (ordf.),\ndir. A. Krönlein, grossh. E. Thestrup.\nVerkst. dir.: A. Krönlein.\n\nArabin AB., Hälsingborg.\n\nKem.-tekn. fabrik. Tillverkar lim och\nklister. Varumärken: »Arabin», »Sikatit»,\n»Vexamyl» o. »Silkigum».\n\nTelegr.-adr.: Arabin, Hälsingborg.\nTelefon: 16454. Postgiro: 140064. —\nAkt.-kap.: 75,000 kr. Antal industriarb.: 16.\nTillv.-värde pr år: 800,000 kr. —\nBolaget grundat 1938.\n\nVerkst. dir.: A. Julius Junger.\n\nDriftsing.: Robert Ebel.",
    "structured": {
        "1": {
            "name": "Apotekarnas Kemiska Laboratorium AB",
            "location": "Stockholm",
            "business": "Kem.-tekn. fabrik",
            "products": "Tillverkar fria läkemedel, förbandsartiklar, kosmetiska preparat, pastiller m.m.",
            "contact": {
                "office": "Norrtullsg. 41-43",
                "phone": [
                    "232380"
                ],
                "postgiro": "1670",
                "telegraph": "Apotekskemi, Stockholm"
            },
            "financials": {
                "capital": "300,000 kr",
                "employees": {
                    "industriarb": 80
                },
                "annual_turnover": "750,000 kr"
            },
            "foundation_year": 1926,
            "current_name_year": 1928,
            "board": [
                {
                    "name": "E. Öhman",
                    "role": "dir."
                },
                {
                    "name": "I. G:son Blomqvist",
                    "role": "apot."
                },
                {
                    "name": "Bertil H. Larsson",
                    "role": "dir."
                }
            ]
        },
        "2": {
            "name": "Apotekarnes Mineralvattens AB",
            "location": "Stockholm",
            "business": "Tillverkar mineralvatten, läskedrycker och medicinska vatten",
            "products": "Varumärke: »AMA»",
            "contact": {
                "office": "Norra Stationsg. 69",
                "phone": [
                    "Apotekarnes vatten"
                ],
                "postgiro": "1949",
                "telegraph": "Mineralvatten, Stockholm"
            },
            "financials": {
                "capital": "5,000,000 kr",
                "employees": {
                    "industriarb": 285
                },
                "annual_turnover": "9,000,000 kr"
            },
            "foundation_year": 1874,
            "board": [
                {
                    "name": "Sven Schwartz",
                    "role": "dir."
                },
                {
                    "name": "Harald Engström",
                    "role": "dir."
                },
                {
                    "name": "Ivan Nordgren",
                    "role": "dir."
                }
            ]
        },
        "3": {
            "name": "Apoteksvarucentralen Vitrum, Apotekare AB",
            "location": "Stockholm",
            "business": "Läkemedelsfabrik och förbandsfabrik",
            "contact": {
                "office": "Torsg. 4",
                "phone": [
                    "Apoteksvarucentralen"
                ],
                "postgiro": "1151",
                "telegraph": "Vitrum, Stockholm"
            },
            "financials": {
                "capital": "2,268,000 kr",
                "employees": {
                    "industriarb": 105
                }
            },
            "foundation_year": 1877,
            "current_name_year": 1930,
            "board": [
                {
                    "name": "Harald Ringberg",
                    "role": "apot."
                },
                {
                    "name": "Erik Berlin",
                    "role": "apot."
                },
                {
                    "name": "Bertil Bjurling",
                    "role": "dir."
                },
                {
                    "name": "Gösta Bjurling",
                    "role": "apot."
                },
                {
                    "name": "Gottfrid Winberg",
                    "role": "apot."
                }
            ]
        },
        "4": {
            "name": "Appelbergs Boktryckeri AB",
            "location": "Uppsala",
            "business": "Utför boktryck, akademiska avhandlingar och tidskrifter m.m.",
            "contact": {
                "phone": [
                    "31016",
                    "33300"
                ],
                "postgiro": "26060"
            },
            "financials": {
                "capital": "250,000 kr",
                "employees": {
                    "industriarb": 25
                },
                "annual_turnover": "350,000 kr"
            },
            "foundation_year": 1903,
            "corporation_year": 1916
        },
        "5": {
            "name": "Appelgrens Borstfabrik",
            "location": "Stockholm",
            "business": "Tillverkar kvastar, levanger, hårborstar m.m.",
            "products": "Specialitet: maskinborstar och borstrullar",
            "contact": {
                "office": "S:t Paulsg. 33 B",
                "phone": [
                    "434720"
                ]
            },
            "employees": {
                "industriarb": 5
            },
            "foundation_year": 1888
        },
        "6": {
            "name": "AB. Appells Smides- & Mek. Verkstad",
            "location": "Falun",
            "business": "Tillverkar smidesarbeten, grovplåtsar-beten samt järnkonstruktioner",
            "contact": {
                "phone": [
                    "1691"
                ],
                "postgiro": "171407"
            },
            "financials": {
                "capital": "20,000 kr",
                "employees": {
                    "industriarb": 30
                },
                "annual_turnover": "350,000 kr"
            },
            "foundation_year": 1906,
            "corporation_year": 1941
        },
        "7": {
            "name": "Appeltofftska Bryggeri AB",
            "location": "Halmstad",
            "business": "Tillverkar malt samt malt- och läskedrycker",
            "contact": {
                "phone": [
                    "317",
                    "3317"
                ],
                "postgiro": "98290"
            },
            "financials": {
                "capital": "765,000 kr",
                "employees": {
                    "industriarb": 25
                },
                "annual_turnover": "1,000,000 kr"
            },
            "foundation_year": 1861,
            "board": [
                {
                    "name": "K. Hillgård",
                    "role": "jur. dr"
                },
                {
                    "name": "A. Krönlein",
                    "role": "dir."
                },
                {
                    "name": "E. Thestrup",
                    "role": "grossh."
                }
            ]
        },
        "8": {
            "name": "Arabin AB",
            "location": "Hälsingborg",
            "business": "Kem.-tekn. fabrik",
            "products": "Tillverkar lim och klister",
            "contact": {
                "telegraph": "Arabin, Hälsingborg",
                "phone": [
                    "16454"
                ],
                "postgiro": "140064"
            },
            "financials": {
                "capital": "75,000 kr",
                "employees": {
                    "industriarb": 16
                },
                "annual_turnover": "800,000 kr"
            },
            "foundation_year": 1938,
            "board": [
                {
                    "name": "A. Julius Junger",
                    "role": "Verkst. dir."
                }
            ]
        }
    }
}