{
    "original": "Standard—Staten\n\nPostadr.: Strängnäs. Telegr.-adr.:\nStal-farinda, S tallarholmen, Telefon:\n»Industribolaget», Stallarholmen. Postgiro:\n2308.\n\nAkt.-kap.: 45,000 kr. Antal\nindustriarb.: 30. Tillv.-värde pr år: 400,000 kr.\n— Firman etabl. 1908, ombildad 1934.\n\nStyrelse o. disp.: Gunnar Wahlgren.\n\n*Standard, Chokladfabriken,\n\nDandéryd.\n\nSö Ohokladfabriken Standard,\nDandéryd.\n\nStandard, Färg- &amp; Ferniss Fabriks\n\nAB., Trelleborg.\n\nSe Färg- &amp; Ferniss Fabriks AB.\nStandard, Trelleborg.\n\n\"Standard, AB. Skofabriken, Lund.\n\nSe AB. Skofabriken Standard, Lund.\n\nAB. Standardhjul, Norrköping.\n\nVagnfabrik. Tillverkar hästvagnar samt\nhjul med kullagernav och gummidäck.\n\nTelefon: 23881. Postgiro: 176524. —\nAkt.-kap.: 40,000 kr. Antal industriarb.:\n8. Tillv.-värde pr år: 250,000 kr. —\nBolaget grundat 1940.\n\nDisp.: Owe Nilsson.\n\nAB. Standardhus, Hultsfred.\n\nTillverkar monteringsfärdiga trähus\nvid snickerifabrik i Hultsfred\n(Kalmar l.).\n\nHuvudkontor: Hultsfred. Telegr.-adr.:\no. telefon: Standardhus, Hultsfred.\nAvd.-kontor i Stockholm, Stureplan 19.\nTelefon: 211470.\n\nAkt.-kap.: 100,000 kr. Tillv.-värde pr\når : 10,000,000 kr.\n\nFirman, etabl. 1927, ombildad 1935, är\ndotterbolag till Hultsfreds Träförädlings\nAB.\n\nVerkst. dir.: Gösta Edström (Växjö).\n\nPlatschef: disp. Torsten Wahlquist.\n\nAB. Standard Radiofabrik,\n\nTJlv sunda.\n\nTillverkar maskiner och apparater för\nTadiotelefoni och telegrafi, elektronrör,\nlikriktare m. m. vid fabrik i Ulvsunda,\nStockholm.\n\nKontor: Johannesfredsv. 9—11,\nUlv-sunda. Telegr.-adr.: Stanelco, Stockholm.\nTelefon: Stockholm 252610. Postgiro:\n156723.\n\nAkt.-kap.: 1,000,000 kr. Antal\nindustriarb.: 250. Tillv.-värde pr år: 3,000,000 kr.\n\n—\tBolaget grundat 1938. /\n\nStyrelse: f. d. generaldir. greve Adolf\nHamilton (ordf.), dir. Jens Bache-Wiig,\nciviling. Per Erikson, dir. Paul Hallgren,\nkapten Bertil af Klercker, dir. Pér-Olov\nÅhlén.\n\nVerkst. dir.: Per-Olov Åhlén.\nKamrer: Hans Dahl.\n\nStår, Kartongfabriken, Habo.\nSe Kartongfabriken Star, Habo.\n\n\"Starbo Bruksägares AB., Starbo.\nSe Avesta Jernverks AB., Avesta.\n\nAB. Starfors Säteri, Heby.\n\nTegelbruk och bränntorvfabrik i Heby\n(Västmanl. l.). Tillverkar taktegel och\ndräneringsrör samt bränntorv.\nVarumärke: »Starfors Heby Tegel».\n\nTelefon: » S t arf orstegel». Postgiro :\n144565. Repr.: Söderberg &amp; Haak AB.,\nStockholm, Göteborg o. Malmö.\n\nAkt.-kap.: 200,000 kr. Antal\nindustriarb.: 65. Årstillv.: 3,5 milj. st. tegelvaror.\n\n—\tTegelbruket anlagt 1905.\nDisp.: fil. lic. Bengt Hahr.\nFörvalt.: Filip Magnusson.\n\n\"Stark, Cruf AB., i Likv., Håksberg.\n\nSe Håksbergs Nya Gruv AB.,\nHåksberg.\n\n\"AB. Statens Skogsindustrier,\n\nStockholm.\n\nSågverk vid Sandvik pr Seskarö och\nvid Båtskärsnäs, sågverk, hyvleri och\nträhusfabrik vid Karlsborg pr\nKarlsborgs-verken, sågverk, hyvleri och trähusfabrik\nvid Lövholmen pr Piteå, sulfatfabrik med\nbiproduktsverk vid Karlsborg och\nträkemiska fabriker i Piteå (samtl. i Norrb. l.),\nlegosågning vid Sandviks sågverk pr\nHolmsund (Västerb. l.),\n\nsågverk, hyvleri, trähusfabrik,\nsnickerifabrik och träullsfabrik i Horndal,\nååg-verk och hyvleri vid Saxviken pr Mora\n(båda i Kopparb. l.),\n\nsågverk, hyvleri, lådfabrik,\nträhusfabrik och träkemiska fabriker i\nSkinn-skatteberg (Västmanl. l.),\n\nsågverk, hyvleri och trähusfabrik i\nValåsen (Örebro l.),\n\nsågverk i Kungsskogen pr ölme (Värml.\n]-)&gt;\n\nsågverk och hyvleri i Sjöbacka pr\nMas-pelösa (Östergötl. l.),\n\n503*",
    "structured": {
        "1": {
            "name": "Standard—Staten",
            "location": "Strängnäs",
            "contact": {
                "office": "Stallarholmen",
                "phone": [
                    "Telefon: Industribolaget, Stallarholmen"
                ],
                "postgiro": "2308",
                "telegraph": "Stal-farinda"
            },
            "financials": {
                "capital": "45,000 kr",
                "employees": {
                    "industriarb": 30
                },
                "annual_turnover": "400,000 kr",
                "annual_production_value": "400,000 kr"
            },
            "foundation_year": 1908,
            "corporation_year": 1934,
            "board": [
                {
                    "name": "Gunnar Wahlgren",
                    "role": "Styrelse o. disp."
                }
            ]
        },
        "2": {
            "name": "Standard, Chokladfabriken",
            "location": "Dandéryd",
            "products": "Chokladfabrik"
        },
        "3": {
            "name": "Standard, Färg- & Ferniss Fabriks AB.",
            "location": "Trelleborg",
            "products": "Färg- & Ferniss Fabriks"
        },
        "4": {
            "name": "Standard, AB. Skofabriken",
            "location": "Lund",
            "products": "Skofabrik"
        },
        "5": {
            "name": "AB. Standardhjul",
            "location": "Norrköping",
            "business": "Vagnfabrik",
            "products": "Hästvagnar, hjul med kullagernav och gummidäck",
            "contact": {
                "phone": "23881",
                "postgiro": "176524"
            },
            "financials": {
                "capital": "40,000 kr",
                "employees": {
                    "industriarb": 8
                },
                "annual_turnover": "250,000 kr",
                "annual_production_value": "250,000 kr"
            },
            "foundation_year": 1940,
            "board": [
                {
                    "name": "Owe Nilsson",
                    "role": "Disp."
                }
            ]
        },
        "6": {
            "name": "AB. Standardhus",
            "location": "Hultsfred",
            "business": "Trähus",
            "contact": {
                "office": "Hultsfred",
                "phone": "Telefon: Standardhus, Hultsfred"
            },
            "financials": {
                "capital": "100,000 kr",
                "annual_production_value": "10,000,000 kr"
            },
            "foundation_year": 1927,
            "corporation_year": 1935
        },
        "7": {
            "name": "AB. Standard Radiofabrik",
            "location": "Ulv sunda",
            "business": "Maskiner och apparater",
            "products": "Maskiner och apparater för radiotelefoni och telegrafi, elektronrör, likriktare m. m.",
            "contact": {
                "office": "Ulv-sunda",
                "phone": "Stockholm 252610",
                "postgiro": "156723"
            },
            "financials": {
                "capital": "1,000,000 kr",
                "employees": {
                    "industriarb": 250
                },
                "annual_turnover": "3,000,000 kr"
            },
            "foundation_year": 1938,
            "board": [
                {
                    "name": "greve Adolf Hamilton",
                    "role": "Ordf."
                },
                {
                    "name": "Jens Bache-Wiig",
                    "role": "Dir."
                },
                {
                    "name": "Per Erikson",
                    "role": "Civiling."
                },
                {
                    "name": "Paul Hallgren",
                    "role": "Dir."
                },
                {
                    "name": "Bertil af Klercker",
                    "role": "Kapten"
                },
                {
                    "name": "Pér-Olov Åhlén",
                    "role": "Dir."
                }
            ]
        },
        "8": {
            "name": "Står, Kartongfabriken",
            "location": "Habo",
            "products": "Kartongfabrik"
        },
        "9": {
            "name": "Starbo Bruksägares AB.",
            "location": "Starbo"
        },
        "10": {
            "name": "AB. Starfors Säteri",
            "location": "Heby",
            "business": "Tegelbruk och bränntorvfabrik",
            "products": "Taktegel, dräneringsrör, bränntorv",
            "contact": {
                "phone": "Starf orstegel",
                "postgiro": "144565"
            },
            "financials": {
                "capital": "200,000 kr",
                "employees": {
                    "industriarb": 65
                },
                "annual_production_value": "3,500,000 kr"
            }
        },
        "11": {
            "name": "Stark, Cruf AB.",
            "location": "Håksberg"
        },
        "12": {
            "name": "AB. Statens Skogsindustrier",
            "location": "Stockholm",
            "business": "Sågverk, hyvleri och trähusfabrik"
        }
    }
}