{
    "original": "Hasselblad—Haux\n\nningar samt plomber. Firman driver även\ngrosshandelsrörelse med kvarnutensilier.\n\nKontor: Stockholm, Vasag. 26.\nTelegr.-adr.: Harmsen, Stockholm. Telefon:\n101404—05. Postgiro: 194400.\n\nAkt.-kap.: 75,000 kr. Antal\nindustriarb.: 20. Tillv.-värde pr år: 500,000 kr.\n\n—\tFirman etabl. 1875, bolag 1911.\n\nDisp.: Erik Wintermark.\n\nAB. D. Hasselblads Charkuteri,\n\nGöteborg.\n\nTillverkar charkuterivaror och\nköttkonserver.\n\nKontor: L:a Katrinelund, Göteborg.\nTelefon: 161051. Postgiro: 42410.\n\nAkt.-kap.: 75,600 kr. Antal\nindustriarb.: 125. Tillv.-värde pr år: 2,500,000 kr.\n\n—\tBolaget grundat 1913.\n\nStyrelse: fru E. Hasselblad (ordf.),\ndisp. C. D. Hasselblad, dir. O. A.\nSwedberg.\n\nVerkst. dir.: fru E. Hasselblad.\n\n\"AB. F. W. Hasselblad &amp; Co.,\n\nGöteborg.\n\nHattfabrik, kravattfabrik och\nkonfektionsfabrik. Tillverkar dam- och\nbarnhattar, halsdukar och kravatter,\ndamunderkläder, skjortor, förkläden,\nbarn-och ^damkragar. Varunamn: »Juno»,\n»Sylfid», »Radiantine» o. »Hasco».\n\nBolaget driver även engrosrörelse i\nkortvaror, manufaktur- och tricotvaror,\nporslins-och glasvaror.\n\nHuvudkontor: ö. Hamng. 3.\nTelegr.-adr. o. telefon: Hasselblads, Göteborg.\nPostgiro: 40724. Avd.-kontor: i\nStockholm, Nybrokajen 5, telefon: 104323;\ni Malmö, Skomakareg. 2, telefon: 26934.\n\nAkt.-kap.: 5,650,000 kr. Antal\nindustriarb.: 110. — Firman, etabl. 1841, bolag\n1919, äger Rob. Skarstedt AB. (se detta\nbolag).\n\nStyrelse: dir. Victor Hasselblad (ordf.),\nbankdir. Orvar Hansson, adv. Emil\nHeijne.\n\nVerkst. dir.: Gunnar Bergenstråhle.\n\n\"Hasselfors Bruks AB., Hasselfors.\n\nSågverk, hyvleri, lådfabrik,\nimpregne-ringsverk och elektr. kraftstation vid\nHasselfors, järnverk med masugn,\nlan-cashiresmedja m. m. vid Svartå,\ntorv-fabriker vid Porla och Stockås (samtl. i\nÖrebro l.).\n\nTillverkar tackjärn, smältstycken,\nråstänger, sågade och hyvlade trävaror,\nlåd-bräder, impregnerade stolpar och sågat\n\nvirke samt torvströ. Bolaget driver\njämväl jordbruk, skogshantering och\nkvarnrörelse.\n\nHuvudkontor: Hasselfors. Telefon:\nHasselfors 1, 21—23 o. 32. Postgiro:\n92220. Avd.-kontor: Svartå.\n\nAkt.-kap.: 4,500,000 kr. Antal\nindustriarb.: 170. Tillv.-värde pr år: 6,000,000 kr.\nÅrstillv.: 3,000 stds sågade och 1,000 stds\nhyvlade trävaror, 10,000 ton tackjärn.\n— Bolaget grundades 1874.\n\nStyrelse: frih. 1. Lagerfelt (ordf.),\ngeneralmajoren frih. Axel Lagerfelt, disp.\nW. Risberg, greve Shering Wachtmeister,\ngreve Nils Wachtmeister.\n\nDisp.: W. Risberg.\n\nDisp.-assist.: bergsing. Bo Risberg.\n\nSågverhsförvalt.: J. Ljungström.\n\nShogsförvalt.: jägm. P. Silfversparre.\n\nDriftsing. i Svartå: ing, Folke\nHallgren.\n\nInhöpschef: kamrer Carl Winroth.\n\n\"Hasselgrens Verkstäder, Stockholm.\n\nKoppar-, bleck- och plåtslageri,\nsmides- och svetsningsverkstad. Tillverkar\ngrövre och finare smiden, kabelrännor,\nkabelkrökar, belysningsreflektorer ^ för\ntennisanläggningar, fönsterinfattningar\nav metall, metalldörrar, pressade\nrörvinklar, plåtslageriarbeten,\ngrovplåtsar-beten, cykelställ för S. J., gjuterideglar\nav plåt m. m.\n\nKontor: Blekingeg. 51. Telefon:\n403476. Postgiro: 156484. —Arb.-antal:\n8. Tillv.-värde pr år: 60,000 kr. —\nFirman etabl. 1875.\n\nÄgare o. chef: fabr. Sigfrid Hasselgren.\n\nHasslaröd Kiselgurfabrik, Osby.\n\nKiselgurfabrik i Osby (Kristianst. l.).\nTillverkar kalcinerad kiselgur,\nisoleringsmassa, isoleringsplattor och\nisoleringstegel (»diatomit»), filtrercylindrar\nm. m.\n\nTelegr.-adr.: Kiselgur, Osby. Telefon:\n71. Postgiro: 30801. — Antal\nindustriarb.: 15. — Firman etabl. 1911.\n\nÄgare o. chef: ing. G. Smith-Petersen.\n\nHattfabrikerna, Förenade, Malmö.\n\nSe AB. Sveriges Förenade\nHattfabriker, Malmö.\n\n\"C. A. Haux Trikåfabriks Nya AB.,\n\nUlricehamn.\n\nTillverkar trikåunderkläder m. m.\n\nTelegr.-adr.: Haux, Ulricehamn.\nTelefon: 145. Postgiro: 73777. Repr. i",
    "structured": {
        "firms": [
            {
                "name": "Hasselblad—Hauxningar samt plomber",
                "location": "Stockholm",
                "business": "Grosshandel med kvarnutensilier",
                "contact": {
                    "office": "Vasag. 26",
                    "phone": [
                        "101404",
                        "101405"
                    ],
                    "postgiro": "194400",
                    "telegraph": "Harmsen, Stockholm"
                },
                "financials": {
                    "capital": "75,000 kr",
                    "employees": {
                        "industriarb": 20
                    },
                    "annual_turnover": "500,000 kr",
                    "annual_production_value": "500,000 kr"
                },
                "foundation_year": 1875,
                "corporation_year": 1911,
                "board": [
                    {
                        "name": "Erik Wintermark",
                        "role": "Disp."
                    }
                ],
                "director": "Erik Wintermark"
            },
            {
                "name": "AB. D. Hasselblads Charkuteri",
                "location": "Göteborg",
                "business": "Tillverkar charkuterivaror och köttkonserver",
                "contact": {
                    "office": "L:a Katrinelund, Göteborg",
                    "phone": "161051",
                    "postgiro": "42410"
                },
                "financials": {
                    "capital": "75,600 kr",
                    "employees": {
                        "industriarb": 125
                    },
                    "annual_turnover": "2,500,000 kr"
                },
                "foundation_year": 1913,
                "board": [
                    {
                        "name": "fru E. Hasselblad",
                        "role": "ordf."
                    },
                    {
                        "name": "C. D. Hasselblad",
                        "role": "disp."
                    },
                    {
                        "name": "O. A. Swedberg",
                        "role": "dir."
                    }
                ],
                "director": "fru E. Hasselblad",
                "managing_director": "fru E. Hasselblad"
            },
            {
                "name": "AB. F. W. Hasselblad & Co.",
                "location": "Göteborg",
                "business": "Hattfabrik, kravattfabrik och konfektionsfabrik. Tillverkar dam- och barnhattar, halsdukar och kravatter, damunderkläder, skjortor, förkläden, barn-och damkragar",
                "contact": {
                    "head_office": "ö. Hamng. 3",
                    "phone": "Hasselblads, Göteborg",
                    "postgiro": "40724",
                    "sales_offices": [
                        {
                            "location": "Stockholm",
                            "phone": "104323"
                        },
                        {
                            "location": "Malmö",
                            "phone": "26934"
                        }
                    ]
                },
                "financials": {
                    "capital": "5,650,000 kr",
                    "employees": {
                        "industriarb": 110
                    }
                },
                "foundation_year": 1841,
                "corporation_year": 1919,
                "board": [
                    {
                        "name": "Victor Hasselblad",
                        "role": "ordf."
                    },
                    {
                        "name": "Orvar Hansson",
                        "role": "bankdir."
                    },
                    {
                        "name": "Emil Heijne",
                        "role": "adv."
                    }
                ],
                "director": "Gunnar Bergenstråhle"
            },
            {
                "name": "Hasselfors Bruks AB.",
                "location": "Hasselfors",
                "business": "Sågverk, hyvleri, lådfabrik, impregneringsverk och elektr. kraftstation",
                "contact": {
                    "head_office": "Hasselfors",
                    "phone": "Hasselfors 1, 21—23 o. 32",
                    "postgiro": "92220",
                    "sales_offices": [
                        {
                            "location": "Svartå"
                        }
                    ]
                },
                "financials": {
                    "capital": "4,500,000 kr",
                    "employees": {
                        "industriarb": 170
                    },
                    "annual_turnover": "6,000,000 kr",
                    "annual_production_value": "6,000,000 kr"
                },
                "foundation_year": 1874,
                "board": [
                    {
                        "name": "frih. I. Lagerfelt",
                        "role": "ordf."
                    },
                    {
                        "name": "genmalmajoren frih. Axel Lagerfelt"
                    },
                    {
                        "name": "W. Risberg",
                        "role": "disp."
                    },
                    {
                        "name": "greve Shering Wachtmeister"
                    },
                    {
                        "name": "greve Nils Wachtmeister"
                    }
                ],
                "director": "W. Risberg"
            },
            {
                "name": "Hasslaröd Kiselgurfabrik",
                "location": "Osby",
                "business": "Tillverkar kalcinerad kiselgur, isoleringsmassa, isoleringsplattor och isoleringstegel (»diatomit»), filtrercylindrar",
                "contact": {
                    "telegraph": "Kiselgur, Osby",
                    "phone": "71",
                    "postgiro": "30801"
                },
                "employees": {
                    "industriarb": 15
                },
                "foundation_year": 1911,
                "director": "ing. G. Smith-Petersen"
            },
            {
                "name": "Hattfabrikerna, Förenade",
                "location": "Malmö",
                "business": "Se AB. Sveriges Förenade Hattfabriker, Malmö"
            },
            {
                "name": "C. A. Haux Trikåfabriks Nya AB.",
                "location": "Ulricehamn",
                "business": "Tillverkar trikåunderkläder",
                "contact": {
                    "office": "Ulricehamn",
                    "phone": "145",
                    "postgiro": "73777"
                }
            }
        ]
    }
}