{
    "original": "Fischer—-Fjettman\n\nAkt.-kap.: 200,000 kr. Antal\nindustriarb.: 40. Tillv.-värde pr år: 600,000 kr.\n— Firman etabl. 1893, bolag 1929.\n\nStyrelse: fabr. J. Waldemar Fintling\n(ordf.), ing. Erik Fintling, lokmäst. E.\nJ. Forsling.\n\nVerkst. dir.: J. Waldemar Fintling.\nDriftsing.: Erik Fintling.\n\n*AB. Elis Fischer, Stockholm.\n\nKonfektionsfabrik. Tillverkar\ndamkappor, dräkter och backfischkappor.\n\nKontor: L:a Nyg. 13. Telegr.-adr.:\nKappfischer, Stockholm. Telefon: 232595.\nPostgiro: 53450.\n\nAkt.-kap.: 450,000 kr. Antal\nindustriarb.: 132. — Firman etabl. 1905.\n\nStyrelse: dir. Erik W. Paues (ordf.),\ndir. Algot Larson, dir. Thure Öberg, dir.\nArvid Ohlin, herr Erik öhlin.\nVerkst. dir.: Algot Larson.\n\n\"Fiskeby Fabriks AB.y Norrköping.\n\nPappersbruk med träsliperi och\nsulfitfabriker i Fiskeby och Skärblacka,\nsulfitspritfabrik vid Skärblacka, pappersbruk\nmed papperssäckfabrik och sulfatfabrik i\nLjusfors, pappfabrik i Fiskeby, tegelbruk\ni Finspång, sågverk i Yxviken,\nsnickerifabrik i Butbro, impregneringsanläggning\ni Lotorp (samtl. i Östergötl. l.).\n\nTillverkar omslagspapper, påspapper,\nsmörpapper och kraftpapper, kraftliners\n(för wellpapp) m. m., sulfitsprit, klistrad\noch oklistrad kartong, sågade och hyvlade\nträvaror, byggnadssnickerier samt\nsulfat-och sulfitcellulosa och mek. trämassa för\neget behov. Bolaget idkar jämväl\njordbruk och skogshantering samt har egna\nelektriska kraftstationer.\n\nHuvudkontor o. försäljn.-kontor:\nNorrköping. Telefon: »Fiskebybolag»,\nNorrköping. Postgiro: 11105.\n\nAkt.-kap.: 15,000,000 kr. Antal\nindustriarb.: 1,050. Årstillv.: 45,000 ton\npapper, 5,000 ton papp, 5,000 stds sågade och\nhyvlade trävaror. — Bolaget, grundat\n1871, äges av Kooperativa Förbundet.\n\nStyrelse: dir. Albin Johansson (ordf.),\nfil. lic. Mauritz Bonow, dir. Hj.\nDeger-stedt, dir. Hugo Edstam, dir. G. Osvald,\ndir. Ernst Persson.\n\nVerkst. dir. o. disp.: Vilhelm\nKugel-berg.\n\nFörsäljn.-dir.: Eskil Hedgårdh.\n\nInköpschef: Emil Nilsson.\n\növering.: Ivar Humble.\n\nFiskredskapsindustrif Johansson &amp;\n\nCo., Onosjö.\n\nJärn- och metallmanufakturverk i\nGnosjö (Jönköp. l.). Tillverkar fiskredskap\nsåsom drag, spinnspön, wobblers och\nspin-nare samt tvålaskar, tobaksaskar,\ncykellås, sulskydd för skidskor, sandspadar för\nbarn, mattsopare m. m.\n\nTelefon: 136. Postgiro: 134529. —\nAntal industriarb.: 30. Tillv.-värde pr år:\n380,000 kr. — Firman etabl. 1937.\n\nChefer: fabr. Bertil Johansson o. fabr.\nEmil Hageberg.\n\nAB. Fisksätra Motor bitsvarv,\n\nSaltsjöbaden.\n\nUtför nybyggnader av båtar upp till\n70 ton, motorrenoveringar samt mek.\nverkstadsarbeten och finsnickerier i\nFisksätra, Saltsjöbaden (Sthlms l.).\n\nTelefon: Stockholm 170423 o. 170817.\nPostgiro: 131646.\n\nAkt.-kap.: 20,000 kr. Antal\nindustriarb.: 35. Tillv.-värde pr år: 400,000 kr.\n\n—\tVarvsrörelsen började 1919 under\nnamn Larssons Båtvarv, nuv. namn och\nbolag 1927.\n\nVerkst. dir.: F. Axel Larsson.\n\nDriftsing.: Torild Larsson.\n\n\"Fittja Tegelbruk, Fittja,\n\nSe AB. Mälardalens Tegelbruk,\nStockholm.\n\nAB. Fixfabriken, Göteborg.\n\nMetallvarufabrik. Tillverkar\nespagno-letter och byggnadsbeslag; utför\nautomat-svarvning och pressgjutning. Varumärke:\n»Fix».\n\nKontor: Maj viken, Kusttorget.\nTelegr.-adr.: Fixfabriken, Göteborg. Telefon:\n148659. Postgiro: 40166.\n\nAkt.-kap.: 300,000 kr. Antal\nindustriarb.: 100. Tillv.-värde pr år: 1,000,000 kr.\n\n—\tFirman etabl. 1925, bolag 1929 under\nnamn AB. Espagnolettfabriken Fix, nuv.\nnamn 1939.\n\nVerkst. dir.: ing. S. Walter Bengtsson.\n\nVerkstads chef: ing. Gunnar Olsson.\n\nFörsäljn.-chef: Kurt Sernheden.\n\n\"Fjellmans Mek. Verkstads AB.,\n\nMariestad.\n\nTillverkar spån- och\nvedeldningspannor, fanérpressar, värmebord och\nlim-kokare för snickeri- och möbelfabriker\nm. m.\n\n154*",
    "structured": {
        "1": {
            "name": "Fischer—-Fjettman",
            "location": "Stockholm",
            "business": "Konfektionsfabrik",
            "products": "Tillverkar damkappor, dräkter och backfischkappor",
            "contact": {
                "office": "L:a Nyg. 13",
                "telegraph": "Kappfischer, Stockholm",
                "phone": [
                    "232595"
                ],
                "postgiro": "53450"
            },
            "financials": {
                "capital": "200,000 kr",
                "employees": {
                    "industriarb": 40
                },
                "annual_turnover": "600,000 kr"
            },
            "foundation_year": 1893,
            "corporation_year": 1929,
            "board": [
                {
                    "name": "J. Waldemar Fintling",
                    "role": "fabr."
                },
                {
                    "name": "Erik Fintling",
                    "role": "ing."
                },
                {
                    "name": "E. J. Forsling",
                    "role": "lokmäst."
                }
            ],
            "director": "J. Waldemar Fintling",
            "managing_director": "Erik Fintling"
        },
        "2": {
            "name": "AB. Elis Fischer",
            "location": "Stockholm",
            "business": "Not available",
            "contact": {
                "office": "L:a Nyg. 13",
                "telegraph": "Kappfischer, Stockholm",
                "phone": [
                    "232595"
                ],
                "postgiro": "53450"
            },
            "financials": {
                "capital": "450,000 kr",
                "employees": {
                    "industriarb": 132
                }
            },
            "foundation_year": 1905
        },
        "3": {
            "name": "Fiskeby Fabriks AB.y",
            "location": "Norrköping",
            "business": "Pappersbruk med träsliperi och sulfitfabriker",
            "products": "Tillverkar omslagspapper, påspapper, smörpapper och kraftpapper, sulfitsprit, klistrad och oklistrad kartong, sågade och hyvlade trävaror, byggnadssnickerier samt sulfat-och sulfitcellulosa och mek. trämassa för eget behov",
            "contact": {
                "office": "Norrköping",
                "phone": [
                    "Fiskebybolag, Norrköping"
                ],
                "postgiro": "11105"
            },
            "financials": {
                "capital": "15,000,000 kr",
                "employees": {
                    "industriarb": 1,
                    "Årstillv": 45,
                    "Antal": 1,
                    "050 ton papper": 5,
                    "000 ton papp": 5
                }
            },
            "foundation_year": 1871
        },
        "4": {
            "name": "Fiskredskapsindustrif Johansson & Co.",
            "location": "Onosjö",
            "business": "Järn- och metallmanufakturverk",
            "products": "Tillverkar fiskredskap såsom drag, spinnspön, wobblers och spinnare samt tvålaskar, tobaksaskar, cykellås, sulskydd för skidskor, sandspadar för barn, mattsopare m. m.",
            "contact": {
                "phone": [
                    "136"
                ],
                "postgiro": "134529"
            },
            "financials": {
                "employees": {
                    "industriarb": 30
                }
            },
            "foundation_year": 1937
        },
        "5": {
            "name": "AB. Fisksätra Motor bitsvarv",
            "location": "Saltsjöbaden",
            "business": "Utför nybyggnader av båtar upp till 70 ton, motorrenoveringar samt mek. verkstadsarbeten och finsnickerier",
            "contact": {
                "office": "Fisksätra, Saltsjöbaden",
                "phone": [
                    "Stockholm 170423",
                    "170817"
                ],
                "postgiro": "131646"
            },
            "financials": {
                "capital": "20,000 kr",
                "employees": {
                    "industriarb": 35
                }
            },
            "corporation_year": 1927,
            "director": "F. Axel Larsson",
            "managing_director": "Torild Larsson"
        },
        "6": {
            "name": "Fittja Tegelbruk",
            "location": "Fittja",
            "business": "See AB. Mälardalens Tegelbruk, Stockholm"
        },
        "7": {
            "name": "AB. Fixfabriken",
            "location": "Göteborg",
            "business": "Metallvarufabrik",
            "products": "Tillverkar espagnoletter och byggnadsbeslag; utför automat-svarvning och pressgjutning",
            "contact": {
                "office": "Majviken, Kusttorget",
                "telegraph": "Fixfabriken, Göteborg",
                "phone": [
                    "148659"
                ],
                "postgiro": "40166"
            },
            "financials": {
                "capital": "300,000 kr",
                "employees": {
                    "industriarb": 100
                }
            },
            "corporation_year": 1929,
            "director": "ing. S. Walter Bengtsson",
            "manager": "Kurt Sernheden"
        },
        "8": {
            "name": "Fjellmans Mek. Verkstads AB.",
            "location": "Mariestad",
            "business": "Tillverkar spån- och vedeldningspannor, fanérpressar, värmebord och lim-kokare för snickeri- och möbelfabriker m. m."
        }
    }
}