{
    "original": "Vebe—Vegeå\n\nKontor: Porslinsfabriken, Kvilleg. 9 B.\nTelegr.-adr.: Wazoverken, Göteborg.\nTelefon: 225041—42. Postgiro: 48459.\n\nAkt.-kap.: 50,000 kr. Antal\nindustriarb.: 38. Tillv.-värde pr år: 800,000 kr..\n— Bolaget grundat 1943.\n\nVerkst. dir.: disp. Oscar Wallmark.\n\nDriftsing.: Sigurd Bröhne.\n\nAB. Vebe-Betong, Björköby.\n\nBetongvarufabrik i Björköby\n(Jönköp. l.).\n\nTillverkar muff- och vägrör, kulvertar,\nbyggnadssten, sanitetsbrunnar, urnor\nm. m.\n\nTelefon: 3. Postgiro: 10831. —\nAkt.-kap.: 62,000 kr. Antal industriarb.: 15.\nTillv.-värde pr år: 180,000 kr. — Firman\netabl. 1921, bolag 1945.\n\nVerkst. dir.: ing. Yilh. Bäckman.\n\n\"Weberöds Nya Tegelbruks AB.,\n\nVeberöd.\n\nTegelbruk vid Veberöd (Malmöh. l.).\nTillverkar tak- och fasadtegel,\ndräneringsrör m. m.\n\nTelefon: 8 o. 9. — Akt.-kap.: 270,000\nkr. Antal industriarb.: 132. Årstillv.: 12\nmilj. tegelvaror. — Bolaget grundat 1913.\n\nStyrelse: v. konsul A. Hyberg, bankdir.\nAxel Jonason, fröken R. Persson, grossh.\nRudolf Petersen, kapten K. v. Schinkel.\n\nVerkst. dir.: Axel Jonason.\n\nDisp.: Oskar Persson.\n\n*Weco, AB. Linnefabriken,\n\nÄngelholm.\n\nSe AB. Linnefabriken Weco,\nÄngelholm.\n\n*Wedaverken, Södertälje.\n\nSe AB. W. Dan Bergman, Södertälje.\n\n*Wedevågs Bruks AB., Vedevåg.\n\nJärnmanufakturverk med mek.\nverkstad, verktygsfabrik, färg- och\nferniss-fabrik, sågverk och skaftfabrik vid\nVedevåg (Örebro l.).\n\nTillverkar handredskap såsom spadar,\nskyfflar, grepar och högafflar m. m.,\nsvartsmiden, redskapsskaft; spiralborrar\noch brotschar av snabbstål, borrchuckar;\nfärger, fernissor och läcker. Vid bruket\ndrives jämväl jordbruk och\nskogshantering.\n\nTelegr.-adr.: Wedevågbruk, Lindesberg.\nTelefon: Lindesberg 26100—05.\nPostgiro: 10061. Kontor: Stockholm, V.\n\nTrädgårdsg. 17, telefon: 234630. Lager:\nStockholm, Inedalsg. 13 B, telefon:\n515016; Göteborg: Vasaplatsen 8, telefon:\n119770.\n\nAkt.-kap.: 1,500,000 kr. Antal\nindustriarb.: 300. Tillv.-värde pr år: 6,000,000 kr.\n\n—\tBruket anlagt före år 1539, nuv.\nbolag grundat 1922.\n\nStyrelse: dir. Helge Norlander (ordf.),\ndir. Lars V. Blume, kapten S.-E.\nCorne-lius, dir. Harry Lindqvist, dir. C.\nMatt-hiesen, disp. Gösta Norlander, övering.\nPatrik Rydbeck, dir. Gunnar Wallgren.\n\nVerkst. dir.: Gösta Norlander.\n\nV. verkst. dir.: Hans Hulthén.\n\n*Wedholms AB., Nyköping.\n\nPress- och förtenningsverk, plåtslageri\nsamt mek. verkstad i Nyköping,\nverkstäder i Lund och Vara (Skarab. l.).\n\nTillverkar transportflaskor, kärl,\ntankar och behållare av järn och rostfritt\nmaterial för mejerier, mejerimaskiner\nsåsom kärnor, plattapparater,\nmaskinostkar m. m.; utför pressade och svetsade\narbeten.\n\nHuvudkontor: Nyköping. Telegr.-adr.:\nWedholms, Nyköping. Telefon:\n»Wed-holmsbolag». Postgiro: 72320.\nAvd.-kontor: Malmö, österg. 11, telefon: 13672.\n\nAkt.-kap.: 1,000,000 kr. Antal\nindustriarb.: 220. Tillv.-värde pr år: 5,000,000 kr.\n\n—\tFabriken anlagd 1879, bolag 1904.\n\nStyrelse: godsäg. S. B. Norup (ordf.),\n\ndir. V. Aaröe, godsäg. Knut Lindström,\ngodsäg. N. H. Sahlström, dir. Gösta\nWin-berg.\n\nVerkst. dir.: Gösta Ekwall.\n\nFörsäljn.-chef: A. Omnell.\n\nKamrer: Stig Kördel.\n\n*Vegeå Tegelbruk, H. Axelson,\n\nSe Möbelfabriks AB. Vega, Vag:geryd.\n\n*Vega, Träförädlingsfabriken, Borås.\n\nSe Träförädlingsfabriken Vega, Borås.\n\n\"Vegeå Tegelbruk, H. Axelson,\n\nMalmö.\n\nTillverkar mur- och taktegel samt\ndräneringsrör vid tegelbruk i Vegeholm\n(Malmöh. l.). Varumärke: »VG».\n\nFörsäljn.-kontor: Malmö, Jörgen\nKocksg. 4, telefon: 10414. Brukskontor:\nVegeholm, telefon: Ängelholm 22. —\nAntal industriarb.: 30. Årstillv.: 2,5 milj.\nst. tegelvaror. — Firman etabl. 1926.\n\nÄgare o. chef: dir. Harald Axelson.",
    "structured": {
        "1": {
            "name": "Vebe",
            "location": "Porslinsfabriken, Kvilleg. 9 B.",
            "business": "Porslinsfabrik",
            "contact": {
                "office": "Porslinsfabriken, Kvilleg. 9 B.",
                "phone": [
                    "225041",
                    "225042"
                ],
                "postgiro": "48459",
                "telegraph": "Wazoverken, Göteborg"
            },
            "financials": {
                "capital": "50,000 kr",
                "employees": {
                    "industriarb": 38
                },
                "annual_turnover": "800,000 kr",
                "annual_production_value": "800,000 kr"
            },
            "foundation_year": 1943,
            "director": "Oscar Wallmark",
            "managing_director": "Oscar Wallmark",
            "required": [
                "name",
                "location",
                "business"
            ]
        },
        "2": {
            "name": "Vebe-Betong",
            "location": "Björköby",
            "business": "Betongvarufabrik",
            "products": "Tillverkar muff- och vägrör, kulvertar, byggnadssten, sanitetsbrunnar, urnor m. m.",
            "contact": {
                "phone": [
                    "3"
                ],
                "postgiro": "10831"
            },
            "financials": {
                "capital": "62,000 kr",
                "employees": {
                    "industriarb": 15
                },
                "annual_turnover": "180,000 kr",
                "annual_production_value": "180,000 kr"
            },
            "foundation_year": 1921,
            "current_name_year": 1945,
            "director": "ing. Yilh. Bäckman",
            "required": [
                "name",
                "location",
                "business"
            ]
        },
        "3": {
            "name": "Weberöds Nya Tegelbruks AB",
            "location": "Veberöd",
            "business": "Tegelbruk",
            "products": "Tillverkar tak- och fasadtegel, dräneringsrör m. m.",
            "contact": {
                "phone": [
                    "8",
                    "9"
                ],
                "postgiro": "N/A"
            },
            "financials": {
                "capital": "270,000 kr",
                "employees": {
                    "industriarb": 132
                },
                "annual_production_value": "12 milj. tegelvaror"
            },
            "foundation_year": 1913,
            "board": [
                {
                    "name": "v. konsul A. Hyberg",
                    "role": "ordf."
                },
                {
                    "name": "bankdir. Axel Jonason",
                    "role": "N/A"
                },
                {
                    "name": "fröken R. Persson",
                    "role": "N/A"
                },
                {
                    "name": "grossh. Rudolf Petersen",
                    "role": "N/A"
                },
                {
                    "name": "kapten K. v. Schinkel",
                    "role": "N/A"
                }
            ],
            "director": "Axel Jonason",
            "managing_director": "Axel Jonason",
            "required": [
                "name",
                "location",
                "business"
            ]
        },
        "4": {
            "name": "Wedevågs Bruks AB",
            "location": "Vedevåg",
            "business": "Järnmanufakturverk",
            "products": "Tillverkar handredskap såsom spadar, skyfflar, grepar och högafflar m. m., svartsmiden, redskapsskaft; spiralborrar och brotschar av snabbstål, borrchuckar; färger, fernissor och läcker.",
            "contact": {
                "office": "Trädgårdsg. 17",
                "phone": [
                    "234630"
                ],
                "postgiro": "10061",
                "sales_offices": [
                    {
                        "location": "Stockholm",
                        "phone": "234630"
                    },
                    {
                        "location": "Göteborg",
                        "phone": "119770"
                    }
                ],
                "telegraph": "Wedevågbruk, Lindesberg"
            },
            "financials": {
                "capital": "1,500,000 kr",
                "employees": {
                    "industriarb": 300
                },
                "annual_turnover": "6,000,000 kr",
                "annual_production_value": "6,000,000 kr"
            },
            "foundation_year": "före år 1539",
            "corporation_year": 1922,
            "board": [
                {
                    "name": "dir. Helge Norlander",
                    "role": "ordf."
                },
                {
                    "name": "dir. Lars V. Blume",
                    "role": "N/A"
                },
                {
                    "name": "kapten S.-E. Cornelius",
                    "role": "N/A"
                },
                {
                    "name": "dir. Harry Lindqvist",
                    "role": "N/A"
                },
                {
                    "name": "dir. C. Matthewisen",
                    "role": "N/A"
                },
                {
                    "name": "disp. Gösta Norlander",
                    "role": "N/A"
                },
                {
                    "name": "övering. Patrik Rydbeck",
                    "role": "N/A"
                },
                {
                    "name": "dir. Gunnar Wallgren",
                    "role": "N/A"
                }
            ],
            "director": "Gösta Norlander",
            "managing_director": "Gösta Norlander",
            "required": [
                "name",
                "location",
                "business"
            ]
        },
        "5": {
            "name": "Wedholms AB",
            "location": "Nyköping",
            "business": "Press- och förtenningsverk, plåtslageri samt mek. verkstad",
            "products": "Tillverkar transportflaskor, kärl, tankar och behållare av järn och rostfritt material för mejerier, mejerimaskiner såsom kärnor, plattapparater, maskinostkar m. m.; utför pressade och svetsade arbeten.",
            "contact": {
                "telegraph": "Wedholms, Nyköping",
                "phone": "N/A",
                "postgiro": "72320",
                "sales_offices": [
                    {
                        "location": "Malmö",
                        "phone": "13672"
                    }
                ]
            },
            "financials": {
                "capital": "1,000,000 kr",
                "employees": {
                    "industriarb": 220
                },
                "annual_turnover": "5,000,000 kr",
                "annual_production_value": "5,000,000 kr"
            },
            "foundation_year": 1879,
            "corporation_year": 1904,
            "board": [
                {
                    "name": "godsäg. S. B. Norup",
                    "role": "ordf."
                },
                {
                    "name": "dir. V. Aaröe",
                    "role": "N/A"
                },
                {
                    "name": "godsäg. Knut Lindström",
                    "role": "N/A"
                },
                {
                    "name": "godsäg. N. H. Sahlström",
                    "role": "N/A"
                },
                {
                    "name": "dir. Gösta Winberg",
                    "role": "N/A"
                }
            ],
            "director": "Gösta Ekwall",
            "managing_director": "Gösta Ekwall",
            "required": [
                "name",
                "location",
                "business"
            ]
        },
        "6": {
            "name": "Vegeå Tegelbruk",
            "location": "Malmö",
            "business": "Tegelbruk",
            "products": "Tillverkar mur- och taktegel samt dräneringsrör vid tegelbruk i Vegeholm (Malmöh. l.). Varumärke: »VG».",
            "contact": {
                "office": "Försäljn.-kontor: Malmö, Jörgen Kocksg. 4",
                "phone": [
                    "10414"
                ],
                "factory_office": "Brukskontor: Vegeholm, telefon: Ängelholm 22",
                "postgiro": "N/A",
                "sales_offices": []
            },
            "financials": {
                "employees": {
                    "industriarb": 30
                }
            },
            "foundation_year": 1926,
            "board": [],
            "director": "dir. Harald Axelson",
            "managing_director": "dir. Harald Axelson",
            "required": [
                "name",
                "location",
                "business"
            ]
        }
    }
}