{
    "original": "Hernö—Hestra\n\nkontor: Sundbyberg, telefon: 283351;\nGöteborg, St. Pedersg. 4 B, telefon: 155010;\nMalmö, Ahlmansg. 7, telefon: 14062.\nRepresentanter: AB. Rabe &amp; Co., Borås;\nHugo Matselius, Örebro.\n\nAkt.-kap.: 300,000 kr. Antal\nindustriarb.: 35. Tillv.-värde pr år: 2,800,000 kr.\n\n—\tFirman etabl. 1920.\n\nStyrelse: disp. Oskar Hofverberg,\ndriftsing. Egon Liden, kontorschef S. I.\nMarcus.\n\nVerkst. dir,: O. Hofverberg.\nKontorschef: S. I, Marcus.\n\n*\tHernö Bryggeri AB., Härnösand.\n\nTillverkar malt- och läskedrycker samt\nmalt jämväl för avsalu. Ensamförsälj. i\nHärnösand för D. Carnegie &amp; Co:s\nporter.\n\nHuvudkontor: Härnösand. Telefon: 55.\nPostgiro: 28837. Avd.-kontor i Kramfors.\n\nAkt.-kap.: 445,500 kr. Antal\nindustriarb.: 26. Tillv.-värde pr år: 950,000 kr.\n\n—\tBolaget grundat 1888.\n\nStyrelse: grossh. Erik Lundquist,\nkonsul Herman Ramström, disp. L. Valentin.\nDisp.: L. Valentin.\nKamrer: A. Häggqvist.\nBryggmäst.: A. Hauke.\n\nHernösand, se Härnösand.\n\n*AB. Herrijunga Möbelfabrik,\n\nHerrljunga.\n\nTillverkar soff- och fåtöljstommar vid\nfabrik i Herrljunga (Älvsb. l.).\n\nTelefon: 81 o. 481. Postgiro: 72950.\n-Akt.-kap.: 225,000 kr. Antal\nindustriarb.: 45. Tillv.-värde pr år: 550,000 kr.\n\n—\tFirman etabl. 1910, bolag 1945.\nStyrelse: dir. Harald Johanson, fabr.\n\nSven A. Pettersson, fabr. Eric Stjerna.\nVerkst. dir.: Harald Johanson.\n\n*\tHerrängs Cruf AB., Herräng.\n\nJärnmalmsgruvor i Herrängsfältet,\njärnverk med anriknings- och\nsintrings-verk samt masugnar vid Herräng (Sthlms\n1.). Bryter och anrikar järnmalm,\ntillverkar sinter och tackjärn.\n\nTelegr.-adr.: Pigiron, Norrtälje.\nTelefon: 1. Postgiro: 75522.\n\nAkt.-kap.: 1,500,000 kr. Antal\nindustriarb.: 275. Tillv.-värde pr år: 4,000,000 kr.\n\n—\tBolaget grundat 1889. ^\n\nStyrelse: bruksdisp. Wiking Johnsson\n(ordf.), bruksdisp. N. Arvid Ericsson,\nbruksdisp. E. Hedendahl, bankdir.\nHenrik Skoog.\n\nVerkst. dir.: E. Hedendahl.\n\nJohn L. Hertzman, Stockholm.\n\nLädervarufabrik. Tillverkar damväskor.\n\nKontor: Gävleg. 12 B. Telefon: 332640.\nPostgiro: 81305. — Antal industriarb.:\n35. Tillv.-värde pr år: 500,000 kr. —\nFirman grundad 1887.\n\nÄgare: John L. Hertzmans sterbhus.\n\nChef: fru Karin Hertzman.\n\n*AB. P. Herzog &amp; Söner, Stockholm.\n\nBokbinderi och kontorsbokfabrik med\nbok- och litografiskt tryckeri. Tillverkar\nalbum, kontorsböcker och psalmböcker\nsamt utför parti- och\nprivatbokbindnings-arbeten, kartuppfodringar, boktryck och\nlitografiska tryckalster. Generalagent för\nSverige för Acme horisontalkortsystem\nsamt för Stoffel-Plomber.\n\nKontor: Vasag. 16. Telegr.-adr.:\nHerzog, Stockholm. Telefon: »Herzogs».\nPostgiro: 465.\n\nFirman etabl. 1862. Bolaget är\nanslutet till AB. Sveriges Litografi ska\nTryckerier, Stockholm (se detta bolag).\n\nStyrelse o. disp.: Gustaf Dahlbäck.\n\nAssistenter: kamrer Rudolf Ehrlund o.\nbokhandl. Carl G. Wiberg.\n\n(Jfr annons nr 44.)\n\n*Hesselman Motor Corporation AB.,\n\nStockholm.\n\nMek. verkstäder vid Henriksdal\n(Sthlms l.) och Hammarby\nindustriområde, Stockholm.\n\nExploaterar patent enligt ing. K. J.\nE. Hesselmans uppfinningar: tillverkar\nbränsleinsprutningspumpar, elektrisk\nutrustning för motorer samt tändstift.\n\nKontor: Henriksdal. Postadr.:\nStockholm 4. Telegr.-adr.: Lowpressure,\nStockholm. Telefon: 440760 o. 440310.\nPostgiro: 77571.\n\nAkt.-kap.: 2,250,000 kr. Antal\nindustriarb.: 500. — Bolaget grundat 1931.\n\nStyrelse: civiling. Birger Dahlerus\n(ordf.), dir. J. Anér, överstelöjtn. Edvard\nDahlerus, rådman M. Hammar, civiling.\nMartin Johansson.\n\nVerkst. dir.: vakant.\n\nHestra Industri AB., Hestra.\n\nKonfektionsfabrik i Hestra (Jönköp.\n1.). Tillverkar sydda och stickade varor\nsåsom arbetskläder, byxor, blusar,\nskjortor, sporttröjor, slipovers, strumpor m. m.\nVarumärke: »Hiab».\n\nTelefon: 12. Postgiro: 22768. —\nAkt.-kap.: 90,000 kr. Antal industriarb.: 25.\nTillv.-värde pr år: 300,000 kr. — Firman\netabl. 1919, bolag 1925.\n\nStyrelse o. verkst. dir.: fabr. Algot\nEberstål.\n\n222*",
    "structured": {
        "1": {
            "name": "Hernö",
            "location": "Sundbyberg",
            "business": "Sprit- och läskedrycksfabrik",
            "contact": {
                "office": "Sundbyberg",
                "phone": [
                    "283351"
                ]
            },
            "financials": {
                "capital": "300,000 kr",
                "employees": {
                    "industriarb": 35
                },
                "annual_turnover": "2,800,000 kr"
            },
            "foundation_year": 1920,
            "board": [
                {
                    "name": "Oskar Hofverberg",
                    "role": "disp."
                },
                {
                    "name": "Egon Liden",
                    "role": "driftsing."
                },
                {
                    "name": "S. I. Marcus",
                    "role": "kontorschef"
                }
            ],
            "director": "O. Hofverberg",
            "managing_director": "O. Hofverberg",
            "sales_manager": "S. I. Marcus"
        },
        "2": {
            "name": "Hernö Bryggeri AB.",
            "location": "Härnösand",
            "business": "Malt- och läskedrycksfabrik",
            "contact": {
                "office": "Härnösand",
                "phone": "55",
                "postgiro": "28837"
            },
            "financials": {
                "capital": "445,500 kr",
                "employees": {
                    "industriarb": 26
                },
                "annual_turnover": "950,000 kr"
            },
            "foundation_year": 1888,
            "board": [
                {
                    "name": "Erik Lundquist",
                    "role": "grossh."
                },
                {
                    "name": "Herman Ramström",
                    "role": "konsul"
                },
                {
                    "name": "L. Valentin",
                    "role": "disp."
                }
            ],
            "director": "L. Valentin"
        },
        "3": {
            "name": "AB. Herrijunga Möbelfabrik",
            "location": "Herrljunga",
            "business": "Möbelfabrik",
            "contact": {
                "office": "Herrljunga",
                "phone": [
                    "81",
                    "481"
                ],
                "postgiro": "72950"
            },
            "financials": {
                "capital": "225,000 kr",
                "employees": {
                    "industriarb": 45
                },
                "annual_turnover": "550,000 kr"
            },
            "foundation_year": 1910,
            "corporation_year": 1945,
            "board": [
                {
                    "name": "Harald Johanson",
                    "role": "dir."
                },
                {
                    "name": "Sven A. Pettersson",
                    "role": "fabr."
                },
                {
                    "name": "Eric Stjerna",
                    "role": "fabr."
                }
            ],
            "director": "Harald Johanson"
        },
        "4": {
            "name": "Herrängs Cruf AB.",
            "location": "Herräng",
            "business": "Järnmalmsgruvor och järnverk",
            "contact": {
                "telegraph": "Pigiron, Norrtälje",
                "phone": "1",
                "postgiro": "75522"
            },
            "financials": {
                "capital": "1,500,000 kr",
                "employees": {
                    "industriarb": 275
                },
                "annual_turnover": "4,000,000 kr"
            },
            "foundation_year": 1889,
            "board": [
                {
                    "name": "Wiking Johnsson",
                    "role": "bruksdisp."
                },
                {
                    "name": "N. Arvid Ericsson",
                    "role": "bruksdisp."
                },
                {
                    "name": "E. Hedendahl",
                    "role": "bruksdisp."
                },
                {
                    "name": "Henrik Skoog",
                    "role": "bankdir."
                }
            ],
            "director": "E. Hedendahl"
        },
        "5": {
            "name": "John L. Hertzman",
            "location": "Stockholm",
            "business": "Lädervarufabrik",
            "contact": {
                "office": "Gävleg. 12 B",
                "phone": [
                    "332640"
                ],
                "postgiro": "81305"
            },
            "financials": {
                "employees": {
                    "industriarb": 35
                },
                "annual_turnover": "500,000 kr"
            },
            "foundation_year": 1887,
            "owners": [
                "John L. Hertzmans sterbhus"
            ],
            "sales_manager": "fru Karin Hertzman"
        },
        "6": {
            "name": "AB. P. Herzog & Söner",
            "location": "Stockholm",
            "business": "Bokbinderi och kontorsbokfabrik",
            "contact": {
                "office": "Vasag. 16",
                "phone": [
                    "»Herzogs»"
                ],
                "postgiro": "465"
            },
            "foundation_year": 1862,
            "board": [
                {
                    "name": "Gustaf Dahlbäck"
                }
            ]
        },
        "7": {
            "name": "Hesselman Motor Corporation AB.",
            "location": "Stockholm",
            "business": "Mek. verkstäder",
            "contact": {
                "office": "Henriksdal",
                "postgiro": "77571",
                "phone": [
                    "440760",
                    "440310"
                ]
            },
            "financials": {
                "capital": "2,250,000 kr",
                "employees": {
                    "industriarb": 500
                }
            },
            "foundation_year": 1931,
            "board": [
                {
                    "name": "civiling. Birger Dahlerus",
                    "role": "ordf."
                },
                {
                    "name": "dir. J. Anér"
                },
                {
                    "name": "överstelöjtn. Edvard Dahlerus"
                },
                {
                    "name": "rådman M. Hammar"
                },
                {
                    "name": "civiling. Martin Johansson"
                }
            ]
        },
        "8": {
            "name": "Hestra Industri AB.",
            "location": "Hestra",
            "business": "Konfektionsfabrik",
            "contact": {
                "office": "Hestra",
                "phone": [
                    "12"
                ],
                "postgiro": "22768"
            },
            "financials": {
                "capital": "90,000 kr",
                "employees": {
                    "industriarb": 25
                },
                "annual_turnover": "300,000 kr"
            },
            "foundation_year": 1919,
            "corporation_year": 1925,
            "director": "fabr. Algot Eberstål",
            "managing_director": "fabr. Algot Eberstål"
        }
    }
}