{
    "original": "Stockho Im—Stokke bye\n\n(båda i Västernorrl. l.) samt i Trollhättan.\n\nTillverkar gödningsämnen, karbid,\nklo-rater, perklorater, överklorsyra,\nkväveprodukter, legeringar, konsthartser och\ndiverse kemikalier. Bryter kalksten vid\nFurillen (Gotl. l.) o. Mattmar (Jämtl. l.).\n\nKontor: Stockholm, Sturegatan 26.\nPost- o. telegr.-adr.: Fosfatbolaget,\nStockholm. Telefon: Fosfat. Postgiro: 92.\n\nAkt.-kap.: 15,000,000 kr. Antal\nindustriarb.: 1,750. Tillv.-värde pr år:\n35,000,000 kr.\n\nBolaget grundat 1871.\n\nStyrelse: fil. dr Harald Nordensop\n(ordf.), kabinettskammarh. Rolf v.\nHei-denstam, grossh. Robert Ljunglöf, dr\nSigurd Nauckhoff, f. d. landshövd. Joh.\nNilsson, disp. Ejnar Rödling, civiling.\nHans Rydin.\n\nVerkst. dir.: Hans Rydin.\n\nDriftschefer: i Ljungaverk: disp.\nGustav Carlsson; i Stockviks verken: disp. Bj.\nColbj örasen; i Trollhättan: disp. Thore\nRosendahl.\n\n*AB. Stockholms Tekniska\nPappersfabrik, Stockholm.\n\nKem.-tekn. fabrik för pappersförädling.\nTillverkar blåkopierings-,\nvitkopierings-och sepiakopieringspapper samt\nljus-känslig väv.\n\nKontor: Valhallavägen 140.\nTelegr.-adr.: Esstepa, Stockholm. Telefon: 622867.\nPostgiro: 52589.\n\nAkt.-kap.: 90,300 kr. Arb.-antal: 5.\nTillv.-värde pr år: 110,000 kr. — Firman\netabl. 1910, bolag 1929.\n\nStyrelse: verkm. Fritz Johansson,\nkommendörkapt. Gösta\nSjöberg-Silfver-ling.\n\nVerkst. dir.: Gösta Sjöberg-Silfverling.\n\nStockholms Transport- och\nBogserings AB., Stockholm.\n\nSkeppsvarv och mek. verkstad vid\nHög-marsö, Furusund (Sthlms l.).\n\nUtför nybyggnader och reparationer av\nfartyg^ upp till 600 ton dw. Utför jämväl\nbogseringar och pråmtransporter samt\ntimmerbogseringar ävensom\nbärgnings-och dykeri arbeten.\n\nKontor: Stadsgården 20; postadr.:\nStockholm 15. Telegr.-adr.:\nTransportbolag, Stockholm. Telefon:\n»Transportbolaget». Postgiro: 3140.\n\nAkt.-kap.: 800,000 kr. Antal varvsarb.:\n50.\n\nBolaget grundat 1870, ombildat 1924.\n\nStyrelse: dir. Nils Wahlberg (ordf.),\nkapten Erik Appelqvist, skeppsklarerare\nBörje Tägtmeijer.\n\nVerkst. dir.: Erik Appelqvist.\n\n*AB. Stockholms Vaddfabrik,\n\nLiljeholmen.\n\nVaddfabrik å Liljeholmen, Stockholm.\nTillverkar vadd och sängkläder.\nVarunamn: »Systern».\n\nTelefon: 451985—87. Postgiro: 8806.\nAkt.-kap.: 350,000 kr. Antal\nindustriarb.: 65. Tillv.-värde pr år: 1,000,000 kr.\n\nBolaget, grundat 1901, äger AB. Nya\nVaddfabriken, Liljeholmen.\n\nStyrelse: dir. Ernst Rudels (ordf.), dir.\nTorsten Brodin, överdir. Ryno Lundqvist.\nVerkst. dir.: Torsten Brodin.\nKontorschef: Ernst Söderberg.\n\n*AB. F. Stocklassas Borst- &amp;\nPenselfabrik, Stockholm.\n\nTillverkar borstar och penslar.\nKontor: Nytorgsg. 17. Telegr.-adr.:\nStocklassas, Stockholm. Telefon: 434817.\nPostgiro: 916.\n\nAkt.-kap.: 90,000 kr. Antal\nindustriarb.: 20. Tillv.-värde pr år: 300,000 kr.\n— Firman etabl. 1856.\n\nStyrelse: adv. Fredrik Blomdahl,\nkamrer Martin öhman, dir. Ture öhman.\nVerkst. dir. o. fabrikschef: Ture öhman.\n\n\"Stockviks Fabriker, Stockviksverken.\n\nSe Stockholms Superfosfat Fabriks\nAB., Stockholm.\n\n*AB. Stohne-Verken, Stockholm,\n\nElektromek. verkstad. Tillverkar\napparater, instrumenteringar,\nmanöverutrustningar, specialmotstånd och reläer; utför\nomlindningar samt reparationer av elektr.\nmotorer, transformatorer m. m.\n\nKontor: Lindhagensg. 128; postadr.:\nStockholm 30. Telegr.-adr.:\nElektro-stohne, Stockholm. Telefon: 520060.\nPostgiro: 199193.\n\nAkt.-kap.: 50,000 kr. Antal\nindustriarb.: 68. Tillv.-värde pr år: 800,000 kr. —\nFirman etabl. 1944 under namn Sandblom\n&amp; Stohne Verkstads AB., nuv. namn 1946.\n\nStyrelse o. verkst. dir.: ing. Bertil\nStohne.\n\nKamrer: Karl Ahnmarker.\nDriftsing.: Ansgar Hansen.\n\nP. 0. Stokkebyes Kvarn AB.,\n\nGöteborg.\n\nKvarnar samt oljeslageri och\nfoder-blandningsfabrik vid Agnesberg (Älvsb.\n1.). Tillverkar ångpreparerade havregryn,\nhavremjöl, havremust, krossgryn,\nvetemjöl, vetekli, risflingor, havrefodérmjol,\nkraftfoderblandningar, linolja och linfrö-\n\n648*",
    "structured": {
        "1": {
            "name": "Fosfatbolaget",
            "location": "Stockholm",
            "business": "Tillverkning av gödningsämnen, karbid, klorater, perklorater, överklorsyra, kväveprodukter, legeringar, konsthartser och diverse kemikalier.",
            "contact": {
                "office": "Sturegatan 26",
                "phone": [
                    "Fosfat"
                ],
                "postgiro": "92"
            },
            "financials": {
                "capital": "15,000,000 kr",
                "employees": {
                    "industriarb.": 1750
                },
                "annual_turnover": "35,000,000 kr",
                "annual_production_value": "35,000,000 kr"
            },
            "foundation_year": 1871,
            "board": [
                {
                    "name": "fil. dr Harald Nordensop",
                    "role": "ordf."
                },
                {
                    "name": "kabinettskammarh. Rolf v. Heidenstam",
                    "role": ""
                },
                {
                    "name": "grossh. Robert Ljunglöf",
                    "role": ""
                },
                {
                    "name": "dr Sigurd Nauckhoff",
                    "role": ""
                },
                {
                    "name": "f. d. landshövd. Joh. Nilsson",
                    "role": ""
                },
                {
                    "name": "disp. Ejnar Rödling",
                    "role": ""
                },
                {
                    "name": "civiling. Hans Rydin",
                    "role": ""
                }
            ],
            "director": "Hans Rydin",
            "sales_manager": "Hans Rydin",
            "manager": "Hans Rydin"
        },
        "2": {
            "name": "AB. Stockholms Tekniska Pappersfabrik",
            "location": "Stockholm",
            "business": "Kemisk-teknisk fabrik för pappersförädling. Tillverkning av blåkopierings-, vitkopierings- och sepiakopieringspapper samt ljuskänslig väv.",
            "contact": {
                "office": "Valhallavägen 140",
                "telegraph": "Esstepa",
                "phone": "622867",
                "postgiro": "52589"
            },
            "financials": {
                "capital": "90,300 kr",
                "employees": {
                    "Arb.-antal": 5
                },
                "annual_turnover": "110,000 kr"
            },
            "foundation_year": 1910,
            "current_name_year": 1929,
            "board": [
                {
                    "name": "verkm. Fritz Johansson",
                    "role": ""
                },
                {
                    "name": "kommendörkapt. Gösta Sjöberg-Silfverling",
                    "role": ""
                }
            ],
            "director": "Gösta Sjöberg-Silfverling"
        },
        "3": {
            "name": "Stockholms Transport- och Bogserings AB.",
            "location": "Stockholm",
            "business": "Skeppsvarv och mek. verkstad. Utför nybyggnader och reparationer av fartyg upp till 600 ton dw. Utför jämväl bogseringar och pråmtransporter samt timmerbogseringar ävensom bärgnings- och dykeri arbeten.",
            "contact": {
                "office": "Stadsgården 20",
                "phone": "Transportbolaget",
                "postgiro": "3140"
            },
            "financials": {
                "capital": "800,000 kr",
                "employees": {
                    "Antal varvsarb.": 50
                }
            },
            "foundation_year": 1870,
            "current_name_year": 1924,
            "board": [
                {
                    "name": "dir. Nils Wahlberg",
                    "role": "ordf."
                },
                {
                    "name": "kapten Erik Appelqvist",
                    "role": ""
                },
                {
                    "name": "skeppsklarerare Börje Tägtmeijer",
                    "role": ""
                }
            ],
            "director": "Erik Appelqvist"
        },
        "4": {
            "name": "AB. Stockholms Vaddfabrik",
            "location": "Liljeholmen",
            "business": "Tillverkning av vadd och sängkläder.",
            "products": "Varunamn: »Systern»",
            "contact": {
                "phone": [
                    "451985—87"
                ],
                "postgiro": "8806"
            },
            "financials": {
                "capital": "350,000 kr",
                "employees": {
                    "industriarb.": 65
                },
                "annual_turnover": "1,000,000 kr"
            },
            "foundation_year": 1901,
            "board": [
                {
                    "name": "dir. Ernst Rudels",
                    "role": "ordf."
                },
                {
                    "name": "dir. Torsten Brodin",
                    "role": ""
                },
                {
                    "name": "överdir. Ryno Lundqvist",
                    "role": ""
                }
            ],
            "director": "Torsten Brodin",
            "manager": "Ernst Söderberg"
        },
        "5": {
            "name": "AB. F. Stocklassas Borst- & Penselfabrik",
            "location": "Stockholm",
            "business": "Tillverkning av borstar och penslar.",
            "contact": {
                "office": "Nytorgsg. 17",
                "telegraph": "Stocklassas",
                "phone": "434817",
                "postgiro": "916"
            },
            "financials": {
                "capital": "90,000 kr",
                "employees": {
                    "industriarb.": 20
                },
                "annual_turnover": "300,000 kr"
            },
            "foundation_year": 1856,
            "director": "Ture öhman"
        },
        "6": {
            "name": "AB. Stohne-Verken",
            "location": "Stockholm",
            "business": "Elektromek. verkstad. Tillverkning av apparater, instrumenteringar, manöverutrustningar, specialmotstånd och reläer; utför omlindningar samt reparationer av elektr. motorer, transformatorer m. m.",
            "contact": {
                "office": "Lindhagensg. 128",
                "telegraph": "Elektro-stohne",
                "phone": "520060",
                "postgiro": "199193"
            },
            "financials": {
                "capital": "50,000 kr",
                "employees": {
                    "industriarb.": 68
                },
                "annual_turnover": "800,000 kr"
            },
            "foundation_year": 1944,
            "current_name_year": 1946,
            "director": "ing. Bertil Stohne"
        },
        "7": {
            "name": "P. 0. Stokkebyes Kvarn AB.",
            "location": "Göteborg",
            "business": "Tillverkning av ångpreparerade havregryn, havremjöl, havremust, krossgryn, vetemjöl, vetekli, risflingor, havrefodérmjol, kraftfoderblandningar, linolja och linfrö"
        }
    }
}