{
    "original": "Svenska\n\nHuvudkontor: Göteborg, S. Hamng. 25.\nTelegr.-adr.: Swedjoin, Göteborg.\nTelefon: 138160. Postgiro: 47283.\n\nAkt.-kap.: 150,000 kr. Antal\nindustriarb.: 75. Tillv.-värde pr år: 1,000,000 kr.\n— Firman etabl. 1941.\n\nVerkst. dir.: Carl A. Schröder.\nDisp.; Carl Skoglund.\n\nSvenska Sniljegarnsfabriken,\n\nKinna.\n\nSpinneri i Kinna (Älvsb. l.). Tillverkar\nsniljegarn.\n\nTelegr.-adr.: Snilje, Kinna. Telefon:\n10353. Postgiro: 89980. — Arb.-antal: 11.\nTillv.-värde pr år: 125.000 kr. — Firman\netabl. 1934.\n\nÄgare o. chef: fabr. Arne Gadh.\n\n*Svenska Sockerfabriks AB.,\n\nMalmö.\n\nSockerraffinaderier i Arlöv (Malmöh.\n1.). Göteborg. Landskrona, Lidköping o.\nStockholm, råsockerbruk i Arlöv,\nHass-larp, Hälsingborg, Hököpinge,\nJord-berga, Kävlinge, Köpingebro, Skivarp,\nStaffanstorp, Svedala, Säbyholm,\nTrelleborg och örtofta (samtl. i Malmöh. l.),\nKarpalund (Kristianst. l.), Roma (Gotl.\n1.), Mörbyiånga (Kalmar l.) samt i\nLidköping, Linköping och Karlshamn,\nsaftstationer i Ängelholm, Gärsnäs (Kristianst.\n1.) och Teckomatorp (Malmöh. l.).\n\nTillverkar: vid raffinaderierna:\nraffinerat socker, sirap och melass; vid\nrå-sockerbruken: råsocker, betfor, betmassa\noch melass.\n\nHuvudkontor: Malmö, Fersens väg 9.\nTelegr.-adr. o. telefon: Sockerbolaget,\nMalmö. Avd.-kontor vid samtliga fabriker.\n\nAkt.-kap.: 81,000,000 kr. Arb.-antal\nunder full drift: c:a 7,300. — Bolaget\ngrundat 1907.\n\nStyrelse: f. d. landshövd. Johan\nNilsson (ordf.), f. d. häradshövd. K.\nDahlberg, bankdir. Ernst C:son Herslow, dir.\nHakon Leffler, dir. N. W. Lundblad, dir.\nCarl Joh. Malmros, dir. H. Ståhlbrandt,\ndir. C. F. Tranchell, bankdir. Ivar\nÅkerman.\n\nDirektion: ordf.: C. F. Tranchell;\nverkst. dir.: N. W. Lundblad; övering.: T.\nWintzell; försäljningschef: Gustaf T.\nRooth.\n\nDir.-assist, o. styrelsens sekreterare:\nCurt Malmberg.\n\nOmbudsman: Albert Dufberg.\n\nInköpschef: ing. Erik Wollert.\n\nChefkamrer: Carl Lindström.\n\nFabrikschefer:\nvid raffinaderiet och råsockerbruket i\nArlöv: disp. H. Matton;\n\nvid raffinaderiet i Göteborg: disp^\n\nA.\tLaudon;\n\nvid råsockerbruket i Hasslarp:\ndisp. I. Elmer;\n\nvid råsockerbruket i Hälsingborg:\ndisp. Sigurd Ekman;\n\nvid råsockerbruket i Hököpinge:\ndisp. R. Harksen;\n\nvid råsockerbruket i Jordberga:\ndisp. J. Herslow;\n\nvid råsockerbruket i Karlshamn:\ndisp. C. L. Junker;\n\nvid råsockerbruket i Karpalund:\ndisp. J. Wrangel v. Brehmer ;\n\nvid råsockerbruket i Kävlinge:\ndisp. J. Winslow;\n\nvid råsockerbruket i Köpingebro:\ndisp. T. Lindman;\n\nvid raffinaderiet i Landskrona:\ndisp. Bo Höglund;\n\nvid raffinaderiet o. råsockerbruket i\nLidköping: disp. C. Höweler;\n\nvid råsockerbruket i Linköping:\ndisp. E. Lindefelt;\n\n#vid råsockerbruket i Mörbyiånga:\ndisp. L. Lindblad;\n\nvid råsockerbruket i Roma: disp.\n\nB.\tDieden;\n\nvid råsockerbruket i Skivarp: disp.\nA. Fritsch;\n\nvid råsockerbruket i\nStaffanstorp: disp. U. Lundell;\n\nvid raffinaderiet i Stockholm:\ndisp. L. Christensson;\n\nvid råsockerbruket i Svedala: disp.\nG. Schröder;\n\n^ vid råsockerbruket i Säbyholm:\ndisp. Gskar Magnusson;\n\nvid råsockerbruket i Trelleborg:\ndisp. C.-A. Nilsson;\n\nvid råsockerbruket i örtofta: disp.\nT. Ulfheden.\n\n*AB. Svenska Spiralfabriken,\n\nStockholm.\n\nMek. verkstad med galv. tekn. avdelning.\nTillverkar spiral-, platt- och\nfasonfjädrar av alla slag och dimensioner,\nsmörjbara bärfjädrar för järnvägs- och\nspårvagnar, ventilfjädrar,\nstartmotor-fjädrar, böjliga axlar, dörr- och\nportstäng-are, velocipedsadelfjädrar, låsfjädrar,\ndy-namometrar, fjädervågar,\nremsyningsspi-raler, magsonder för nötkreatur,\nmutterbrickor, kloakrensare, muskelstärkare,\nhästskyddare, fjädersortiment samt\nmetallslangar m. m. utför förnickling,\nför-kromning, fosfatisering, glansförzinkning\noch försilvring. Varumärke: »Asspi».",
    "structured": {
        "1": {
            "name": "Svenska",
            "location": "Göteborg",
            "business": "Swedish firm",
            "contact": {
                "office": "S. Hamng. 25",
                "telegraph": "Swedjoin, Göteborg",
                "phone": [
                    "138160"
                ],
                "postgiro": "47283"
            },
            "financials": {
                "capital": "150,000 kr",
                "employees": {
                    "industriarb": 75
                },
                "annual_turnover": "1,000,000 kr",
                "annual_production_value": "1,000,000 kr"
            },
            "foundation_year": 1941,
            "director": "Carl A. Schröder",
            "board": [
                {
                    "name": "Carl A. Schröder",
                    "role": "Verkst. dir."
                },
                {
                    "name": "Carl Skoglund",
                    "role": "Disp."
                }
            ]
        },
        "2": {
            "name": "Svenska Sniljegarnsfabriken",
            "location": "Kinna",
            "business": "Spinneri",
            "products": "Tillverkar sniljegarn",
            "contact": {
                "office": "Älvsb. l.",
                "telegraph": "Snilje, Kinna",
                "phone": "10353",
                "postgiro": "89980"
            },
            "financials": {
                "employees": {
                    "Arb.-antal": 11
                },
                "annual_production_value": "125,000 kr"
            },
            "foundation_year": 1934,
            "owners": [
                "fabr. Arne Gadh"
            ]
        },
        "3": {
            "name": "Svenska Sockerfabriks AB.",
            "location": "Malmö",
            "business": "Sockerraffinaderier",
            "products": "Tillverkar raffinerat socker, sirap och melass; råsocker, betfor, betmassa och melass.",
            "contact": {
                "office": "Fersens väg 9",
                "telegraph": "Sockerbolaget, Malmö"
            },
            "financials": {
                "capital": "81,000,000 kr",
                "board": [
                    {
                        "name": "Johan Nilsson",
                        "role": "Ordf."
                    },
                    {
                        "name": "K. Dahlberg",
                        "role": "Häradshövd."
                    },
                    {
                        "name": "Ernst C:son Herslow",
                        "role": "Bankdir."
                    },
                    {
                        "name": "Hakon Leffler",
                        "role": "Dir."
                    },
                    {
                        "name": "N. W. Lundblad",
                        "role": "Dir."
                    },
                    {
                        "name": "Carl Joh. Malmros",
                        "role": "Dir."
                    },
                    {
                        "name": "H. Ståhlbrandt",
                        "role": "Dir."
                    },
                    {
                        "name": "C. F. Tranchell",
                        "role": "Dir."
                    },
                    {
                        "name": "Ivar Åkerman",
                        "role": "Bankdir."
                    }
                ],
                "director": "C. F. Tranchell",
                "managing_director": "N. W. Lundblad",
                "sales_manager": "Gustaf T. Rooth"
            },
            "foundation_year": 1907
        },
        "4": {
            "name": "AB. Svenska Spiralfabriken",
            "location": "Stockholm",
            "business": "Mek. verkstad",
            "products": "Tillverkar spiral-, platt- och fasonfjädrar, smörjbara bärfjädrar, ventilfjädrar, startmotor-fjädrar, böjliga axlar, dörr- och portstängare, velocipedsadelfjädrar, låsfjädrar, m.m.",
            "contact": {
                "office": "Med galv. tekn. avdelning"
            },
            "financials": {
                "products": "Utför förnickling, för-kromning, fosfatisering, glansförzinkning och försilvring",
                "capital": "N/A",
                "board": [
                    {
                        "name": "N/A",
                        "role": "N/A"
                    }
                ],
                "director": "N/A"
            }
        }
    }
}