{
    "original": "Kopiering—Korkbetong!\n\nAkt.-kap.: 100,000 kr. Antal\nindustriarb.: 30. Tillv.-värde pr år: 500,000 kr.\n\n—\tFirman etabl. 1909.\n\nStyrelse: dir. Werner Lundström\n(ordf.), dir. Gustaf A. Carlsson.\n\nVerkst. dir.: W. Lundström.\n\n\"Kopierings AB., Svenska, Stockholm.\n\nSe Svenska Kopierings AB., Stockholm.\n\n\"Kopparbergs &amp; Hofors Sågverks AB.,\n\nOckelbo.\n\nSe Kopparfors AB., Ockelbo.\n\n\"Kopparbergs Bryggeri AB.,\n\nKopparberg.\n\nTillverkar pilsner, svagdricka,\nmineralvatten och läskedrycker vid bryggeri i\nKopparberg (Örebro l.).\n\nTelefon: Kopparberg 44. Postgiro:\n295723. — Akt.-kap.: 150,000 kr.\nArb.-antal: 14. — Firman etabl. 1885, bolag\n1946.\n\nStyrelse o. verkst. dir.: Yngve Lindvall.\n\nAB. Kopparbergs Spisbrödsfabrik,\n\nKopparberg.\n\nSpisbrödsfabrik i Kopparbergs köping\n(Örebro l.). Tillverkar knäcke- och\nspisbröd. Yarunamn: »Kopparbergsbröd».\n\nTelefon: 183 o. 170. Postgiro: 13641.\n\n—\tAkt.-kap.: 200,000 kr. Antal\nindustriarb.: 45. Tillv.-värde pr år: 600,000 kr.\n\n—\tBolaget grundat 1918.\n\nStyrelse: disp. Karl Andersson (ordf.),\nadv. G. B. Ihrman, dir. Claes Jansson.\n\nVerkst. dir.: Claes Jansson.\n\n\"Kopparfors AB., Ockelbo.\n\nSågverk och hyvleri samt sulfatfabrik\nvid Norrsundet, järnverk vid Jädraås\n(båda i Gävleb. l.), lådfabrik vid Näs,\nKorsnäs (Kopparb. l.).\n\nTillverkar sågade och hyvlade trävaror,\nlådor samt sulfatcellulosa. Bolaget idkar\njämväl skogshantering.\n\nHuvudkontor: Wij Bruk, Ockelbo.\nTelegr.-adr.: Kopparfors, Gävle. Telefon:\n»Kopparfors», Ockelbo. Postgiro: 9999.\n\nAkt.-kap.: 20,000,000 kr. Antal\nindustriarb.: 690. Årstillv.: 18,000 stds\nsågade o. hyvlade trävaror, 42,000 ton torr,\nstark sulfatcellulosa och blekt massa.\n\nBolaget, som grundades 1854 under\nnamn Kopparbergs &amp; Hofors Sågverks\nAB., namnförändring 1937, äger Storviks\nSulfit AB.\n\nStyrelse: envoyé Axel Wallenberg\n\n(ordf.), jägm. Lars H. Carlsson, disp.\nSig-björn Holgersson, bankdir. Bertil\nWallenberg, bankdir. Jacob Wallenberg.\n\nVerkst. dir. o. disp.: S. Holgersson.\n\nFörsäljn.-chef: M. Wallerström.\n\nKamrer: Folke Nordenfors.\n\nShogschef: jägm. Gösta Wiman.\n\nSågverhsförvalt.: vid Norrsundet: H.\nFreudenthal; vid Näs: kontorschef John\nLindqvist.\n\növering. vid Norrsundets sultfatfabrik:\nC. F. Palm.\n\n\"Koppoms Pappersfabriks AB.,\n\nGöteborg.\n\nPappersbruk med sulfitfabrik och\nträ-sliperi i Koppom (Värml. l.). Tillverkar\nomslagspapper, såväl rent sulfitpapper\nsom slipblandade pappersslag, affisch-,\nbutelj- och silkespapper samt mek.\nträmassa.\n\nHuvudkontor: Göteborg, St. Badhusg.\n7. Telegr.-adr.: Koppom, Göteborg.\nFabrikskontor: Koppom. Telefon:\nSkönne-rud 16 o. 45. Postgiro: 45256. Försäljare:\nAB. Hedström &amp; Co., Göteborg, St.\nBad-husg. 7. Telefon: 139204.\n\nAkt.-kap.: 1,050,000 kr. Antal\nindustriarb.: 70. Årstillv.: 5,000 ton papper,\n2,000 ton mek. trämassa. — Bolaget\ngrundat 1889.\n\nStyrelse: adv. Folke Jörgensen (ordf.),\ndir. Otto Bengtson, grossh. Olof\nGill-holm, adv. Elias S. Markfelt.\n\nVerkst. dir.: Otto Bengtson.\n\n\"AB. Kores, Stockholm.\n\n^ Kem.-tekn. fabrik. Tillverkar färgband\ntill skriv- och räknemaskiner, karbon- och\nkalkérpapper samt stenciler och\nduplice-ringsfärg. Yarumärken: »Kores»,\n»Carbo-plan», »Copynet» o. »Typo».\n\nKontor: Nybrokajen 3. Telegr.-adr.:\nKorescarbo, Stockholm. Telefon: 234495.\nPostgiro: 51277.\n\nAkt.-kap.: 30,000 kr. Antal\nindustriarb.: 20. — Firman etabl. 1934.\n\nStyrelse o. verkst. dir.: Theodor\nHar-ting.\n\nFörsäljn.-chef: Börje Engkvist.\n\nDriftsing.: Tord Engberg.\n\nAB. Korkbetong, TJmeå.\n\nBetongvarufabrik i Böleå, Teg\ni(Väster-bott. l.). Tillverkar isoleringsmateriel\nsåsom korkbetongplattor och träullsplattor,\nmellanväggsplattor, skalsandbetong i block\noch plattor, hålsten samt\nventilationstrummor.",
    "structured": {
        "1": {
            "name": "Kopiering—Korkbetong",
            "location": "Stockholm",
            "business": "Betongvarufabrik",
            "products": "Isoleringsmateriel såsom korkbetongplattor och träullsplattor, mellanväggsplattor, skalsandbetong i block och plattor, hålsten samt ventilationstrummor",
            "contact": {
                "office": "Böleå, Teg, Umeå",
                "phone": [],
                "postgiro": null
            },
            "financials": {
                "capital": "100,000 kr",
                "employees": {
                    "industriarb": 30
                },
                "annual_turnover": "500,000 kr",
                "annual_production_value": null
            },
            "foundation_year": 1909,
            "board": [
                {
                    "name": "Werner Lundström",
                    "role": "dir."
                },
                {
                    "name": "Gustaf A. Carlsson",
                    "role": "dir."
                }
            ],
            "director": "W. Lundström",
            "managing_director": null,
            "sales_manager": null,
            "manager": null
        },
        "2": {
            "name": "Kopparbergs Bryggeri AB.",
            "location": "Kopparberg",
            "business": "Bryggeri",
            "products": "Pilsner, svagdricka, mineralvatten och läskedrycker",
            "contact": {
                "office": "Kopparberg (Örebro l.)",
                "phone": [
                    "Kopparberg 44"
                ],
                "postgiro": "295723"
            },
            "financials": {
                "capital": "150,000 kr",
                "employees": {
                    "industriarb": 14
                },
                "annual_turnover": null,
                "annual_production_value": "600,000 kr"
            },
            "foundation_year": 1885,
            "board": [
                {
                    "name": "Yngve Lindvall",
                    "role": "Styrelse o. verkst."
                }
            ],
            "director": null,
            "managing_director": null,
            "sales_manager": null,
            "manager": null
        },
        "3": {
            "name": "Kopparbergs Spisbrödsfabrik AB.",
            "location": "Kopparberg",
            "business": "Spisbrödsfabrik",
            "products": "Knäcke- och spisbröd",
            "contact": {
                "office": "Kopparberg (Örebro l.)",
                "phone": [
                    "183",
                    "170"
                ],
                "postgiro": "13641"
            },
            "financials": {
                "capital": "200,000 kr",
                "employees": {
                    "industriarb": 45
                },
                "annual_turnover": "600,000 kr",
                "annual_production_value": null
            },
            "foundation_year": 1918,
            "board": [
                {
                    "name": "Karl Andersson",
                    "role": "disponent"
                },
                {
                    "name": "G. B. Ihrman",
                    "role": "adv."
                },
                {
                    "name": "Claes Jansson",
                    "role": "dir."
                }
            ],
            "director": null,
            "managing_director": null,
            "sales_manager": null,
            "manager": null
        },
        "4": {
            "name": "Kopparfors AB.",
            "location": "Ockelbo",
            "business": "Sågverk, hyvleri, sulfatfabrik, lådfabrik och skogshantering",
            "products": "Sågade och hyvlade trävaror, lådor samt sulfatcellulosa",
            "contact": {
                "office": "Wij Bruk, Ockelbo",
                "phone": [
                    "Kopparfors",
                    "Ockelbo"
                ],
                "postgiro": "9999"
            },
            "financials": {
                "capital": "20,000,000 kr",
                "employees": {
                    "industriarb": 690
                },
                "annual_turnover": null,
                "annual_production_value": "18,000 stds sågade o. hyvlade trävaror, 42,000 ton torr, stark sulfatcellulosa och blekt massa"
            },
            "foundation_year": 1918,
            "board": [
                {
                    "name": "Axel Wallenberg",
                    "role": "envoyé"
                },
                {
                    "name": "Lars H. Carlsson",
                    "role": "jägm."
                },
                {
                    "name": "Sigbjörn Holgersson",
                    "role": "disponent"
                },
                {
                    "name": "Bertil Wallenberg",
                    "role": "bankdir."
                },
                {
                    "name": "Jacob Wallenberg",
                    "role": "bankdir."
                }
            ],
            "director": null,
            "managing_director": "S. Holgersson",
            "sales_manager": "M. Wallerström",
            "manager": null
        },
        "5": {
            "name": "Koppoms Pappersfabriks AB.",
            "location": "Göteborg",
            "business": "Pappersbruk med sulfitfabrik och trä-sliperi",
            "products": "Omslagspapper, rent sulfitpapper, slipblandade pappersslag, affisch-, butelj- och silkespapper samt mek. trämassa",
            "contact": {
                "office": "Göteborg, St. Badhusg. 7",
                "phone": [
                    "Skönnerud 16",
                    "45"
                ],
                "postgiro": "45256"
            },
            "financials": {
                "capital": "1,050,000 kr",
                "employees": {
                    "industriarb": 70
                },
                "annual_turnover": null,
                "annual_production_value": "5,000 ton papper, 2,000 ton mek. trämassa"
            },
            "foundation_year": 1889,
            "board": [
                {
                    "name": "Folke Jörgensen",
                    "role": "adv."
                },
                {
                    "name": "Otto Bengtson",
                    "role": "dir."
                },
                {
                    "name": "Olof Gillholm",
                    "role": "grossh."
                },
                {
                    "name": "Elias S. Markfelt",
                    "role": "adv."
                }
            ],
            "director": null,
            "managing_director": "Otto Bengtson",
            "sales_manager": null,
            "manager": null
        },
        "6": {
            "name": "AB. Kores",
            "location": "Stockholm",
            "business": "Kem.-tekn. fabrik",
            "products": "Färgband till skriv- och räknemaskiner, karbon- och kalkérpapper samt stenciler och duplice-ringsfärg",
            "contact": {
                "office": "Nybrokajen 3",
                "phone": [
                    "234495"
                ],
                "postgiro": "51277"
            },
            "financials": {
                "capital": "30,000 kr",
                "employees": {
                    "industriarb": 20
                },
                "annual_turnover": null,
                "annual_production_value": null
            },
            "foundation_year": 1934,
            "board": [
                {
                    "name": "Theodor Harting",
                    "role": "Styrelse o. verkst."
                }
            ],
            "director": null,
            "managing_director": null,
            "sales_manager": "Börje Engkvist",
            "manager": "Tord Engberg"
        }
    }
}