{
    "original": "Tynell—Tärnan\n\nSven Sjöstedt &amp; Co., Torsg. 8. Telefon:\n111959 o. 214266. Postgiro: 191720.\n\nAkt.-kap.: 15,000 kr. Arb.-antal: 8.\nTillv.-värde pr år: 200,000 kr. —\nBolaget grundat 1941.\n\nStyrelse: dir. Sven Sjöstedt (ordf.),\nkamrer Gösta Bergh.\n\nVerkst. dir.: Sven Sjöstedt.\n\n*N. &amp; A. Tynell, Malmö.\n\nMöbelfabrik. Tillverkar möbler och\ninredningar.\n\nKontor: Bergsg. 13. Telefon: 23049.\nPostgiro: 38607. — Arb.-antal: 5. —\nFirman etabl. 1906.\n\nÄgare o. chef: snickarmäst. Anders\nTynell.\n\nDriftschef: fabr. Ernst Tynell.\n*AB. Typochroma, Stockholm.\n\nTryckfärgsfabrik. Tillverkar svarta och\nkulörta tryckfärger, valsmassa samt\ngrafiska fernissor.\n\nHuvudkontor: Stockholm, Bondeg. 18 o.\n22. Telefon: 403088 o. 433682. Postgiro:\n1398. Avd.-kontor och lager i Göteborg\noch Malmö.\n\nAkt.-kap.: 400,000 kr. Arb.-antal: 10.\nTillv.-värde pr år: 300,000 kr. — Firman\netabl. 1896, bolag 1931.\n\nStyrelse: fru Eli Hanner, herr Holger\nHanner, disp. Nils Westerdahl.\n\nVerkst. dir.: vakant.\n\nKontorschef: Rob. Hanner.\n\nAB. Tyringe Möbelfabrik,\n\nTyringe.\n\nTillverkar finare möbler vid fabrik i\nTyringe (Kristianst. l.). Specialiteter:\nmatsalsmöbler i ek och björk samt möbler\ni renässansstilar.\n\nTelefon: 58. Postgiro: 9386. —\nAkt.-kap.: 110,000 kr. Antal industriarb.: 25.\nTillv.-värde pr år: 130,000 kr. — Firman\netabl. 1922, bolag 1938.\n\nStyrelse o. disponenter: fabr. Edvin\nAndersson, fabr. Fride Olsson, fabr.\nHil-bert Olsson.\n\nAB. Tyringe Stanskniv- &amp;\nPress-verktygsfabrik, Tyringe.\n\nTillverkar stansknivar för sko-,\ngummi-oeh lädervaruindustrin, kuvert- och\netikettstansar samt pressverktyg vid mek.\nverkstad i Tyringe (Kristianst. l.).\nVarumärke: TSF.\n\nTelegr.-adr.: Tyringestans, Tyringe.\nTelefon: 11. Postgiro: 23554. — Akt.-kap.:\n\n731*\n\n100,000 kr. Antal industriarb.: 20.\nTillv.-värde pr år: 175,000 kr. —- Firman etabL\n1912, bolag 1923.\n\nVerkst. dir.: Ivar Nyberg.\nKontorschef: Aug. Dahlén.\n\n\"Täckfabriken A. J. Ängel AB«,\n\nHälsingborg.\n\nTillverkar som specialitet sticktäcken\nsamt duntäcken, madrasser, sovsäckar\nm. m.\n\nTelefon: 12885. Postgiro: 95544.\nAkt.-kap.: 90,000 kr. Antal\nindustriarb.: 12. Tillv.-värde pr år: 300,000 kr.\n\n—\tFirman etabl. 1898, bolag 1933.\nStyrelse: dir. Gunnar Ängel (ordf.),\n\nf. kassörska Mia Ahlander, fru Edit\nÄngel, fru Karin Ängel, ing. Thure\nÄngel.\n\nVerkst. dir.: Gunnar Ängel.\n\"AB. Täckindustri, Flen.\n\nTillverkar vadd, stickade täcken,\nmadrasser och kuddar vid fabrik i Flen\n(Södermanl. l.). Varumärke: »Jon Blund».\nTelefon: 267. Postgiro: 8919.\nAkt.-kap.: 75,000 kr. Antal\nindustriarb.: 28. Tillv.-värde pr år: 750,000 kr.\n\n—\tFirman etabl. 1923, bolag 1932.\nStyrelse o. verkst. dir.: Fred. Ronn-\n\ngaard.\n\n\"Tändsticksbolaget, Jönköping.\nSe Svenska Tändsticks AB., Jönköping-\n\nTändsticksfabriker, AB. Förenade\nSvenska, Jönköping.\n\nSe AB. Förenade Svenska\nTändsticksfabriker, Jönköping.\n\n\"AB. Tärna, Göteborg.\n\nStrumpfabrik. Tillverkar herrstrumpor.\nVarumärke: »Tell».\n\nKontor: Haga Nygata 25. Telefon:\n111534. Postgiro: 43816. Repr. i\nStockholm: Joel Lindblom &amp; Co. AB., Kungsg.\n66, telefon: 113470.\n\nAkt.-kap.: 30,000 kr. Antal\nindustriarb.: 20. — Bolaget grundat 1932.\n\nStyrelse: dir. Joel Lindblom (ordf.),\ning. Folke Ternell.\n\nVerkst. dir.: Folke Ternell.\n\n\"Tärnan, Skofabriks AB., Örebro.\nSe Skofabriks AB. Tärnan, Örebro.",
    "structured": {
        "1": {
            "name": "Sven Sjöstedt & Co.",
            "location": "Torsg. 8",
            "business": "Okänd",
            "contact": {
                "office": "Torsg. 8",
                "phone": [
                    "111959",
                    "214266"
                ],
                "postgiro": "191720"
            },
            "financials": {
                "capital": "15,000 kr",
                "employees": {
                    "Arb.-antal": 8
                },
                "annual_production_value": "200,000 kr"
            },
            "foundation_year": 1941,
            "board": [
                {
                    "name": "Sven Sjöstedt",
                    "role": "ordf."
                },
                {
                    "name": "Gösta Bergh",
                    "role": "kamrer"
                }
            ],
            "director": "Sven Sjöstedt"
        },
        "2": {
            "name": "N. & A. Tynell",
            "location": "Malmö",
            "business": "Möbelfabrik",
            "products": "Tillverkar möbler och inredningar",
            "contact": {
                "office": "Bergsg. 13",
                "phone": [
                    "23049"
                ],
                "postgiro": "38607"
            },
            "financials": {
                "employees": {
                    "Arb.-antal": 5
                }
            },
            "foundation_year": 1906,
            "owners": [
                "Anders Tynell"
            ],
            "director": "Anders Tynell",
            "sales_manager": "Ernst Tynell"
        },
        "3": {
            "name": "AB. Typochroma",
            "location": "Stockholm",
            "business": "Tryckfärgsfabrik",
            "products": "Tillverkar svarta och kulörta tryckfärger, valsmassa samt grafiska fernissor",
            "contact": {
                "office": "Stockholm, Bondeg. 18 o. 22",
                "phone": [
                    "403088",
                    "433682"
                ],
                "postgiro": "1398",
                "sales_offices": [
                    {
                        "location": "Göteborg",
                        "phone": "Okänd"
                    },
                    {
                        "location": "Malmö",
                        "phone": "Okänd"
                    }
                ]
            },
            "financials": {
                "capital": "400,000 kr",
                "employees": {
                    "Arb.-antal": 10
                },
                "annual_turnover": "Okänd",
                "annual_production_value": "300,000 kr"
            },
            "foundation_year": 1896,
            "corporation_year": 1931,
            "board": [
                {
                    "name": "fru Eli Hanner",
                    "role": "Okänd"
                },
                {
                    "name": "herr Holger Hanner",
                    "role": "Okänd"
                },
                {
                    "name": "disp. Nils Westerdahl",
                    "role": "Okänd"
                }
            ],
            "manager": "Rob. Hanner"
        },
        "4": {
            "name": "AB. Tyringe Möbelfabrik",
            "location": "Tyringe",
            "business": "Möbelfabrik",
            "products": "Tillverkar finare möbler",
            "contact": {
                "phone": [
                    "58"
                ],
                "postgiro": "9386"
            },
            "financials": {
                "capital": "110,000 kr",
                "employees": {
                    "antal industriarb.": 25
                },
                "annual_production_value": "130,000 kr"
            },
            "foundation_year": 1922,
            "corporation_year": 1938,
            "board": [
                {
                    "name": "fabr. Edvin Andersson",
                    "role": "Okänd"
                },
                {
                    "name": "fabr. Fride Olsson",
                    "role": "Okänd"
                },
                {
                    "name": "fabr. Hil-bert Olsson",
                    "role": "Okänd"
                }
            ]
        },
        "5": {
            "name": "AB. Tyringe Stanskniv- & Press-verktygsfabrik",
            "location": "Tyringe",
            "business": "Tillverkar stansknivar för sko-, gummi-oeh lädervaruindustrin, kuvert- och etikettstansar samt pressverktyg",
            "products": "Varumärke: TSF",
            "contact": {
                "telegraph": "Tyringestans",
                "phone": [
                    "11"
                ],
                "postgiro": "23554"
            },
            "financials": {
                "capital": "100,000 kr",
                "employees": {
                    "Antal industriarb.": 20
                },
                "annual_production_value": "175,000 kr"
            },
            "foundation_year": 1912,
            "corporation_year": 1923,
            "director": "Ivar Nyberg",
            "manager": "Aug. Dahlén"
        },
        "6": {
            "name": "Täckfabriken A. J. Ängel AB",
            "location": "Hälsingborg",
            "business": "Tillverkar sticktäcken samt duntäcken, madrasser, sovsäckar m. m.",
            "contact": {
                "phone": [
                    "12885"
                ],
                "postgiro": "95544"
            },
            "financials": {
                "capital": "90,000 kr",
                "employees": {
                    "Antal industriarb.": 12
                },
                "annual_production_value": "300,000 kr"
            },
            "foundation_year": 1898,
            "corporation_year": 1933,
            "board": [
                {
                    "name": "dir. Gunnar Ängel",
                    "role": "ordf."
                },
                {
                    "name": "f. kassörska Mia Ahlander",
                    "role": "Okänd"
                },
                {
                    "name": "fru Edit Ängel",
                    "role": "Okänd"
                },
                {
                    "name": "fru Karin Ängel",
                    "role": "Okänd"
                },
                {
                    "name": "ing. Thure Ängel",
                    "role": "Okänd"
                }
            ],
            "director": "Gunnar Ängel"
        },
        "7": {
            "name": "AB. Täckindustri",
            "location": "Flen",
            "business": "Tillverkar vadd, stickade täcken, madrasser och kuddar",
            "products": "Varumärke: »Jon Blund»",
            "contact": {
                "phone": [
                    "267"
                ],
                "postgiro": "8919"
            },
            "financials": {
                "capital": "75,000 kr",
                "employees": {
                    "Antal industriarb.": 28
                },
                "annual_production_value": "750,000 kr"
            },
            "foundation_year": 1923,
            "corporation_year": 1932,
            "director": "Fred. Ronn-gaard"
        },
        "8": {
            "name": "AB. Tärna",
            "location": "Göteborg",
            "business": "Strumpfabrik",
            "products": "Tillverkar herrstrumpor",
            "contact": {
                "office": "Haga Nygata 25",
                "phone": [
                    "111534"
                ],
                "postgiro": "43816",
                "sales_offices": [
                    {
                        "location": "Stockholm",
                        "phone": [
                            "113470"
                        ]
                    }
                ]
            },
            "financials": {
                "capital": "30,000 kr",
                "employees": {
                    "Antal industriarb.": 20
                }
            },
            "foundation_year": 1932,
            "board": [
                {
                    "name": "dir. Joel Lindblom",
                    "role": "ordf."
                },
                {
                    "name": "ing. Folke Ternell",
                    "role": "Okänd"
                }
            ],
            "director": "Folke Ternell"
        }
    }
}