{
    "original": "S chéel—Schull ström\n\n41066; Malmö, telefon: 71355, postgiro:\n37682. Telegr.-adr.: Tripas, Stockholm,\nGöteborg o. Malmö.\n\nAkt.-kap.: 1,500,000 kr. Antal\nindustriarb.: Stockholm 100, Göteborg 150 o.\nMalmö 50. — Firman etabl. 1907.\n\nDirektörer: Stockholm: H. Thaning;\nGöteborg: J. Schytt; Malmö: K. Leube.\n\n*Schéels Fabriker, AB., Göteborg.\n\nKem.-tekn. fabrik. Tillverkar såpa,\ntvål och kem.-tekn. preparat.\n\nHuvudkontor: Göteborg. Telegr.-adr.:\nSchéels, Göteborg. Telefon: 135396.\nPostgiro: 42434. Avd.-kontor: Stockholm,\nDrottningg. 50—52, telefon: 118070;\nMalmö, Gråbrödersg. 6, telefon: 28396.\n\nAkt.-kap.: 120,000 kr. Antal\nindustriarb.: 15. — Bolaget grundat 1916.\n\nStyrelse: adv. Torsten Setterberg.\n\n\"J. Scheja, Stockholm.\n\nTillverkar förhydningsmassa\n(»Scheja-massa») till golvbeläggning och\nväggbeklädnad.\n\nKontor: Kungsg. 29. Telegr.-adr.:\nScheja. Stockholm. Telefon: 114082 o.\n211016. Postgiro: 59395. — Antal\nindustriarb.: 8. —- Firman etabl. 1899.\n\nÄgare o. chef ring. Oscar Scheja.\n\n\"C. E. Scheutz’ Son, Tranås.\n\nLäderfabrik. Tillverkar helt koläder och\nkruponger. Varumärke: »Solidsulläder».\n\nTelefon: 2038. — Antal industriarb.:\n20. — Firman etabl. 1870.\n\nÄgare o. chef: ing. Sven Segerdahl.\n\nProkurist: Ernst Folin.\n\n\"AB. K. A. Schilds Sågbladsfabrik,\n\nEnköping.\n\nTillverkar metallsågblad,\nmetallfräs-klingor och slitsfräsar.\n\nTelegr.-adr.: Schild, Enköping.\nTelefon: 128. Postgiro: 30388.\n\nAkt.-kap.: 100,000 kr. Antal\nindustriarb.: 30. Tillv.-värde pr år: 500,000 kr.\n— Firman etabl. 1909, bolag 1922.\n\nStyrelse: köpman Uno Hultgren\n(ordf.), fabr. Carl A. Johansson, fabr. K.\nAlbin Schild.\n\nVerkst. dir.: K. A. Schild.\n\n\"Henning Schlasberg &amp; Co. AB.,\n\nLandskrona.\n\nKonfektionsfabrik. Tillverkar herr-,\ndam- och gosskonfektion. Varumärke:\n»Lejon-Märket».\n\nTelegr.-adr. o. telefon: Schlasbergs,\nLandskrona. Postgiro: 93500.\nRepresentanter: i Stockholm: Harald Goldstein,\nKungsg. 16—18, telefon: 212908; i\nGöteborg: A. Savosnick, Surbrunnsg. 6,\ntelefon: 121010.\n\nAkt.-kap.: 800,000 kr. Antal\nindustriarb.: 350. Tillv.-värde pr år: 4,000,000 kr.\n\n—\tFirman etabl. 1896, bolag 1936.\nStyrelse: adv. Alf Lindahl (ordf.), adv.\n\nSigfrid Lindström, dir. Mauritz Nidén,\ndisp. Harald Schlasberg.\n\n\"Jul. Schlichtings Eftr., Nils Halden,\n\nFritsla.\n\nSe Nils Haldens Färgeri, Fritsla.\n\nSchmidts Boktryckeri AB.,\n\nHälsingborg.\n\nBoktryckeri och bokbinderi. Utför\nbok-och affärstryck, kataloger, reklamtryck\nm. m.\n\nTelefon: 20345. Postgiro: 14301. —\nAkt.-kap.: 100,000 kr. Antal industriarb.:\n60. Tillv.-värde pr år: 450,000 kr. —\nFirman etabl. 1880, bolag 1918.\n\nStyrelse: ing. O. Winkler (ordf.), disp.\nE. Grefors, avd.-chef Carl Kristensson.\nVerkst. dir.: O. Winkler.\nDisp.: E. Grefors.\n\n\"AB. Schreuder &amp; Olsson,\n\nStockholm.\n\nTenngjuteri, metallvaruf abrik samt\nmek. verkstad. Tillverkar gjutna\nkonstindustriella tennsaker, stänkkork,\napoteksutensilier, leksaker m. m. av tenn.\n\nKontor: Huvudstavägen 51. Telefon:\n531249 o. 507782. Postgiro: 1393.\n\nAkt.-kap.: 200,000 kr. Arb.-antal: 10.\nTillv.-värde pr år: 150,000 kr. — Firman\netabl. 1896, bolag 1923.\n\nStyrelse: fru Edit Engström, typograf\nErik Schreuder, fröken Greta Schreuder.\n\nFirmateclcnare: Edit Engström o. Greta\nSchreuder.\n\n\"Schullström &amp; Sjöströms Fabriks\n\nAB., Högsjö.\n\nUllspinneri och ylleväveri i Högsjö\n(Södermanl. l.). Tillverkar maskinfilt.\n\nTelegr.-adr.: Schullsjö, Katrineholm.\nTelefon: Högsjö 45066. Postgiro: 22173.\n\nAkt.-kap.: 2,700,000 kr. Antal\nindustriarb.: 300. Tillv.-värde pr år: 3,500,000 kr.\n\n—\tFirman grundad 1862, bolag 1888.\nStyrelse: kammarh. Fredrik v.\nMecklenburg, disp. Alf Schullström, ing.\nWilhelm Schullström.\n\nVerkst. dir.: Wilhelm Schullström.\nDisp.: Alf Schullström.\n\n■x-",
    "structured": {
        "1": {
            "name": "Scheel-Schullström",
            "location": "Malmö",
            "contact": {
                "office": "41066; Malmö",
                "phone": [
                    "71355"
                ],
                "postgiro": "37682",
                "telegraph": "Tripas, Stockholm, Göteborg o. Malmö"
            },
            "financials": {
                "capital": "1,500,000 kr",
                "employees": {
                    "Stockholm": 100,
                    "Göteborg": 150,
                    "Malmö": 50
                }
            },
            "foundation_year": 1907,
            "board": [
                {
                    "name": "H. Thaning",
                    "role": "Director"
                },
                {
                    "name": "J. Schytt",
                    "role": "Director"
                },
                {
                    "name": "K. Leube",
                    "role": "Director"
                }
            ]
        },
        "2": {
            "name": "Schéels Fabriker, AB.",
            "location": "Göteborg",
            "business": "Kem.-tekn. fabrik",
            "products": "Tillverkar såpa, tvål och kem.-tekn. preparat",
            "contact": {
                "office": "Göteborg",
                "phone": [
                    "135396"
                ],
                "postgiro": "42434",
                "sales_offices": [
                    {
                        "location": "Stockholm",
                        "phone": "118070"
                    },
                    {
                        "location": "Malmö",
                        "phone": "28396"
                    }
                ]
            },
            "financials": {
                "capital": "120,000 kr",
                "employees": 15
            },
            "foundation_year": 1916,
            "board": [
                {
                    "name": "Torsten Setterberg",
                    "role": "Board Member"
                }
            ]
        },
        "3": {
            "name": "J. Scheja",
            "location": "Stockholm",
            "business": "Tillverkar förhydningsmassa (»Scheja-massa») till golvbeläggning och väggbeklädnad",
            "contact": {
                "office": "Kungsg. 29",
                "phone": [
                    "114082",
                    "211016"
                ],
                "postgiro": "59395"
            },
            "financials": {
                "employees": 8
            },
            "foundation_year": 1899,
            "owners": [
                "Oscar Scheja"
            ],
            "director": "Oscar Scheja"
        },
        "4": {
            "name": "C. E. Scheutz’ Son",
            "location": "Tranås",
            "business": "Läderfabrik",
            "products": "Tillverkar helt koläder och kruponger. Varumärke: »Solidsulläder»",
            "contact": {
                "phone": [
                    "2038"
                ]
            },
            "financials": {
                "employees": 20
            },
            "foundation_year": 1870,
            "owners": [
                "Sven Segerdahl"
            ],
            "manager": "Sven Segerdahl",
            "sales_manager": "Ernst Folin"
        },
        "5": {
            "name": "AB. K. A. Schilds Sågbladsfabrik",
            "location": "Enköping",
            "business": "Tillverkar metallsågblad, metallfräs-klingor och slitsfräsar",
            "contact": {
                "office": "Enköping",
                "phone": "128",
                "postgiro": "30388"
            },
            "financials": {
                "capital": "100,000 kr",
                "employees": 30,
                "annual_production_value": "500,000 kr"
            },
            "foundation_year": 1909,
            "board": [
                {
                    "name": "Uno Hultgren",
                    "role": "Chairman"
                },
                {
                    "name": "Carl A. Johansson",
                    "role": "Director"
                },
                {
                    "name": "K. Albin Schild",
                    "role": "Director"
                }
            ],
            "director": "K. A. Schild"
        },
        "6": {
            "name": "Henning Schlasberg & Co. AB.",
            "location": "Landskrona",
            "business": "Konfektionsfabrik",
            "products": "Tillverkar herr-, dam- och gosskonfektion. Varumärke: »Lejon-Märket»",
            "contact": {
                "office": "Landskrona",
                "phone": "Schlasbergs",
                "postgiro": "93500",
                "sales_offices": [
                    {
                        "location": "Stockholm",
                        "phone": "212908"
                    },
                    {
                        "location": "Göteborg",
                        "phone": "121010"
                    }
                ]
            },
            "financials": {
                "capital": "800,000 kr",
                "employees": 350,
                "annual_production_value": "4,000,000 kr"
            },
            "foundation_year": 1896,
            "board": [
                {
                    "name": "Alf Lindahl",
                    "role": "Chairman"
                },
                {
                    "name": "Sigfrid Lindström",
                    "role": "Board Member"
                },
                {
                    "name": "Mauritz Nidén",
                    "role": "Director"
                },
                {
                    "name": "Harald Schlasberg",
                    "role": "Manager"
                }
            ]
        }
    }
}