{
    "original": "Elit—Elner\n\nTelefon: 20003 o. 20011. Postgiro:\n26585. — Antal industriarb.: 20.\nTillv.-värde pr år: 300,000 kr. — Firman etabl.\n1890.\n\nChefer: dir. Filip Eliasson o. dir.\nGunnar Eliasson.\n\n*Elit, Chokladfabriken, Solna.\n\nSe Chokladfabriken Elit, Gösta Westin,\nSolna.\n\n*AB. Elit-Sko, Halmstad.\n\nTillverkar damskodon.\nTelefon: 1030. Postgiro: 160418.\nAkt.-kap.: 30,000 kr. Antal\nindustriarb.: 38. — Bolaget grundat 1939.\n\nStyrelse: fabr. John F. Palmqvist\n(ordf.), fabr. Arvid Lundström, fabr.\nGösta Måshammar.\n\nVerkst. dir.: John F. Palmqvist.\n\n*Elit, Trikåfabriken, Borås.\nSe AB. Trikåfabriken Elit, Borås.\n\n*Elko Konfektions AB., Stockholm.\n\nTillverkar damunderkläder i charmeuse\noch siden samt damklänningar och -blusar.\nVarumärke: »ELKO».\n\nKontor: Bryggarg. 18. Telefon: 212567,\n204066 o. 102360. Postgiro: 24696.\n\nAkt.-kap.: 45,000 kr. Antal\nindustriarb.: 50. Tillv.-värde pr år: 600,000 kr.\n— Firman etabl. 1922, nuv. namn 1931.\nStyrelse o. verkst. dir.: Hedvig Inf eld.\n\nElias, Fabriks AB., Stockholm.\nSe Fabriks AB. Elias, Stockholm.\n\n*Otto Ellerström, Malmö.\n\nByggnadsentreprenörfirma för bostads-\n\noch affärshus, industribyggnader,\nång-skorstenar samt för inmurningar av\nångpannor.\n\nKontor: Jörgen Ankersg. 20. Telefon:\n28130 o. 12492. — Antal industriarb.:\n60. — Firman etabl. 1923.\n\nÄgare o. chef: byggm. Otto Ellerström.\n\nEliess Maskinfabrik AB., Göteborg.\n\nTillverkar iläggningsapparater för\ntryckpressar. Varumärke: »Elless».\n\nKontor: Köpmansg. 36—38.\nTelegr.-adr.: Elless, Göteborg. Telefon: 136988 o.\n137914. Postgiro: 12479.\n\nAkt.-kap.: 20,000 kr. Antal\nindustriarb.: 30. — Firman etabl. 1901, bolag\n\n1926 under namn AB. Westerlin &amp; Co.*\nnuv. namn 1944.\n\nVerkst. dir.: disp. August Sandberg.\n\nDriftschef: ing. Yngve Danielson.\n\nKamrer: Eric Schortz.\n\n*AB. Bror Eiliot, Stockholm.\n\nDamkonfektionsfabrik. Tillverkar\ndamklänningar. Bolaget driver även\nengros-handel med manufakturvaror.\n\nKontor: Sveavägen 34. Telegr.-adr.:\nBrelliot, Stockholm. Telefon: 232070.\nPostgiro: 1774.\n\nAkt.-kap.: 200,000 kr. Antal\nindustriarb.: 20. — Firman etabl. 1921, bolag\n1932.\n\nStyrelse: dir. Bror Elliot (ordf.), disp»\nArne Elliot.\n\nVerkst. dir.: Bror Elliot.\n\nDisp.: Arne Elliot.\n\nEllkå, Furstenberg &amp; Söner,\nKommanditbolaget, Kalmar.\n\nSe Kommanditbolaget Ellkå,\nFurstenberg &amp; Söner, Kalmar.\n\nElme Glasbruk, Borgarp &amp; Co.,\n\nÄlmhult.\n\nGlasbruk o. torvmosse (Gemöns\nBränntorvmosse) vid Älmhult (Kronob. l.).\nTillverkar hushållsglas, konservglas,\nmedicinglas och kem, tekn. glas samt\nbränntorv. Specialiteter: pressglas och\ngraverat konstglas. Varumärke: »Elme».\n\nKontor: Älmhult. Telegr.-adr.: Elme,\nÄlmhult. Telefon: 4 o. 120. Postgiro:\n142110.\n\nAntal industriarb.: vid glasbruket 70,\nvid torvmossen 120. Tillv.-värde pr år:\nför glasbruket: 500,000 kr., för\ntorvmossen: 250,000 kr. — Firman grundad 1918.\n\nÄgare: bruksäg. Fredrik Svensson,\nbruksäg. Leonard Borgarp o. bruksäg.\nFilip Aste.\n\nKamrer: Paul K. Jonsson.\n\n*Elmo-Calf, AB. Chromläderfabriken,\n\nSvenljunga.\n\nSe AB. Chromläderfabriken Elmo-Calf,\nSvenljunga.\n\nNils Elner &amp; Co., Arkelstorp.\n\nSe Kommanditbolaget Lövträ, Nils\nElner &amp; Co., Arkelstorp.",
    "structured": {
        "1": {
            "name": "Elit—Elner",
            "location": "Solna",
            "business": "Chokladfabrik",
            "contact": {
                "phone": [
                    "20003",
                    "20011"
                ],
                "postgiro": "26585"
            },
            "financials": {
                "employees": {
                    "industriarb": 20
                },
                "annual_production_value": "300,000 kr"
            },
            "foundation_year": 1890,
            "board": [
                {
                    "name": "Filip Eliasson",
                    "role": "dir."
                },
                {
                    "name": "Gunnar Eliasson",
                    "role": "dir."
                }
            ]
        },
        "2": {
            "name": "AB. Elit-Sko",
            "location": "Halmstad",
            "business": "Tillverkar damskodon",
            "contact": {
                "phone": "1030",
                "postgiro": "160418"
            },
            "financials": {
                "capital": "30,000 kr",
                "employees": {
                    "industriarb": 38
                }
            },
            "foundation_year": 1939,
            "board": [
                {
                    "name": "John F. Palmqvist",
                    "role": "fabr."
                },
                {
                    "name": "Arvid Lundström",
                    "role": "fabr."
                },
                {
                    "name": "Gösta Måshammar",
                    "role": "fabr."
                },
                {
                    "name": "John F. Palmqvist",
                    "role": "verkst. dir."
                }
            ]
        },
        "3": {
            "name": "Elko Konfektions AB.",
            "location": "Stockholm",
            "business": "Tillverkar damunderkläder i charmeuse och siden samt damklänningar och -blusar.",
            "contact": {
                "office": "Bryggarg. 18",
                "phone": [
                    "212567",
                    "204066",
                    "102360"
                ],
                "postgiro": "24696"
            },
            "financials": {
                "capital": "45,000 kr",
                "employees": {
                    "industriarb": 50
                },
                "annual_turnover": "600,000 kr"
            },
            "foundation_year": 1922,
            "current_name_year": 1931,
            "board": [
                {
                    "name": "Hedvig Inf eld",
                    "role": "verkst. dir."
                }
            ]
        },
        "4": {
            "name": "Otto Ellerström",
            "location": "Malmö",
            "business": "Byggnadsentreprenörfirma för bostads-och affärshus, industribyggnader, ång-skorstenar samt för inmurningar av ångpannor.",
            "contact": {
                "office": "Jörgen Ankersg. 20",
                "phone": [
                    "28130",
                    "12492"
                ]
            },
            "financials": {
                "employees": {
                    "industriarb": 60
                }
            },
            "foundation_year": 1923,
            "owner": "byggm. Otto Ellerström"
        },
        "5": {
            "name": "Eliess Maskinfabrik AB.",
            "location": "Göteborg",
            "business": "Tillverkar iläggningsapparater för tryckpressar",
            "contact": {
                "office": "Köpmansg. 36—38",
                "phone": [
                    "136988",
                    "137914"
                ],
                "postgiro": "12479"
            },
            "financials": {
                "capital": "20,000 kr",
                "employees": {
                    "industriarb": 30
                }
            },
            "foundation_year": 1901,
            "corporation_year": 1926,
            "current_name_year": 1944,
            "board": [
                {
                    "name": "disp. August Sandberg",
                    "role": "verkst. dir."
                },
                {
                    "name": "ing. Yngve Danielson",
                    "role": "driftschef"
                },
                {
                    "name": "Eric Schortz",
                    "role": "Kamrerer"
                }
            ]
        },
        "6": {
            "name": "AB. Bror Eiliot",
            "location": "Stockholm",
            "business": "Damkonfektionsfabrik",
            "contact": {
                "office": "Sveavägen 34",
                "phone": "232070",
                "postgiro": "1774"
            },
            "financials": {
                "capital": "200,000 kr",
                "employees": {
                    "industriarb": 20
                }
            },
            "foundation_year": 1921,
            "corporation_year": 1932,
            "board": [
                {
                    "name": "dir. Bror Elliot",
                    "role": "ordf."
                },
                {
                    "name": "disp» Arne Elliot",
                    "role": "Disp."
                },
                {
                    "name": "Bror Elliot",
                    "role": "Verkst. dir."
                },
                {
                    "name": "Arne Elliot",
                    "role": "Disp."
                }
            ]
        },
        "7": {
            "name": "Elme Glasbruk, Borgarp & Co.",
            "location": "Älmhult",
            "business": "Glasbruk o. torvmosse",
            "contact": {
                "office": "Älmhult",
                "phone": [
                    "4",
                    "120"
                ],
                "postgiro": "142110"
            },
            "financials": {
                "employees": {
                    "glasbruket": 70,
                    "torvmossen": 120
                },
                "annual_production_value": "500,000 kr (glasbruket), 250,000 kr (torvmossen)"
            },
            "foundation_year": 1918,
            "owners": [
                "bruksäg. Fredrik Svensson",
                "bruksäg. Leonard Borgarp",
                "bruksäg. Filip Aste"
            ],
            "board": [
                {
                    "name": "Paul K. Jonsson",
                    "role": "Kamrerer"
                }
            ]
        }
    }
}