{
    "original": "Sundsvall—S undsvik\n\nStyrelse: dir. Torsten Hérnod (ordf.),\ndisp. Rye Engström, dir. Gust. Göranson,\ndir. K. Erik Nyberg.\n\nVerkst. dir.: Gust. Göranson.\n\nDisp.: Rye Engström.\n\nÖvering. för cellulosafabriker o.\npappersbruk: C. Gunnar Ahlzén.\n\nChef för kraftverk: civiling. H. Nylén.\n\nChef för sågverk o. träförädling: disp.\nA. Mörch.\n\nChef för skogar o. virkesanskaffning:\ndisp. G. Wärn.\n\nInköpschef för material: kamrer C.\nBorgh.\n\nFörsäkringar: kamrer Björn Blomberg.\n\nFörsäljn.-chef er: för trävaror: E.\nFryk-borg; för papper: O. From.\n\n’Sundsvalls Bryggeri AB.,\n\nSundsvall.\n\nTillverkar malt och maltdrycker,\nmineralvatten och läskedrycker.\n\nTelefon: »Sundsvalls Bryggeri».\nPostgiro: 134386. — Akt.-kap.: 900,000 kr.\nAntal industriarb.: 34. — Bolaget\ngrundat 1858, ombildat 1930.\n\nStyrelse: hovrättsrådet B. Thuresson\n(ordf.), disp. B. Nygren (v. ordf.), fru\nH. Johansson, fru H. österman.\n\nVerkst. dir. o. disp.: B. Nygren.\n\nBryggm.: Olle Wijkström.\n\n’Sundsvalls Cellulosa AB., Sundsvall.\n\nSe Essviks AB., Sundsvall.\n\nAB. Sundsvalls Elektriska\nSpisbrödsfabrik, Sundsvall.\n\nKvarn och spisbrödsfabrik. Tillverkar\nmjöl och gryn, fodermedel samt\ndelikatess-, spis- och knäckebröd.\n\nTelefon: 2212 o. 3439. Postgiro: 75888.\n-— Akt.-kap.: 50,000 kr. Antal\nindustriarb.: 14. Tillv.-värde pr år: 500,000 kr.\n— Bolaget grundat 1934.\n\nVerkst. dir. o. disp.: ing. Gustaf\nBrattström.\n\n’AB. Sundsvalls Förenade\nVerkstäder, Sundsvall.\n\nGjuteri och mek. verkstad. Tillverkar\n\nhydrauliska pressar, hydrauliska\npresspumpar och ackumulatorer samt\nhydrauliska manöver- och avstängningsventiler;\nfilter av alla slag; excenter- och\nknäleds-pressar för den keramiska industrien,\nmaskiner och apparater för träsliperier\noch cellulosafabriker, tablettmaskiner\n•samt tackjärnsgjutgods i styckevikter upp\ntill 15 ton.\n\nTelegr.-adr.: Verkstäderna, Sundsvall.\nTelefon: 55740. Postgiro: 24174.\n\nAkt.-kap.: 630,000 kr. Antal\nindustriarb.: 110. Tillv.-värde pr år: 2,000,000 kr.\n— Bolaget grundat 1905.\n\nStyrelse: bankdir. Erik Berggren\n(ordf.), ing. Erik Berg, bankdir. Ivar\nWallmark, bankdir. Ando Wikström.\n\nDisp.: Erik Berg.\n\nChefsassist.: civiling. Anders\nBjörkman.\n\nKamrer: Sven Almroth.\n\nRitkontor sch ef: Birger Welander.\n\nSundsvalls Perspektivfönster AB.,\n\nStockholm.\n\nBolaget försäljer perspektivfönster,\ndörrar, panel m. m., tillverkade vid\nKubikenborgs Snickerifabrik, Svartviks AB.,\nSundsvall.\n\nKontor: Stockholm, Stureplan 13.\nTelegr.-adr.: Perspektiv, Stockholm.\nTelefon: Cellulosabolaget. Postgiro: 57574.\n\nAkt.-kap.: 100,000 kr. — Bolaget,\ngrundat 1941, är anslutet till Svenska\nCellulosa AB., Stockholm.\n\nStyrelse: dir. Gust. Göranson (ordf.),\ndisp. Rye Engström, disp. Arne Mörch,\ndir. K. Erik Nyberg, byggm. Eric S.\nPersson.\n\nVerkst. dir.: Bengt Falk.\n\nKamrer: Anders Berg.\n\n’Sundsviks Bruk AB., Sundsvik.\n\nSågverk, hyvleri och tegelbruk vid\nSundsvik (Sthlms l.). Tillverkar sågade\noch hyvlade trävaror samt murtegel.\nBolaget driver även jordbruk och\nskogshantering.\n\nTelefon: Turinge 6, 14 o. 55. Postgiro:\n276252\n\nAkt.-kap.: 100,000 kr. Antal\nindustriarb.: 90. Årstillv.: 2,000 stds trävaror, 6\nmilj. st. tegel. — Nuv. firma etabl. 1944.\n\nStyrelse: civiling. Boris Hagelin\n(ordf.), civiling. Wilhelm Qvarnström.\n\nDisp.: Sven Svensson.\n\nKamrer: Hjalmar Björklund.\n\n’Sundsviks Såg &amp; Hyvleri, Ingvald\nÖvergaard, Sunne.\n\nSågverk och hyvleri i Sunne (Värml.\n1.). Tillverkar sågade och hyvlade\nträvaror samt lister. Firman driver även\nhandel med byggnadsmateriel.\n\nTelegr.-adr.: övergaard, Sunne.\nTelefon: 306. Postgiro: 11293.\n\nAntal industriarb.: 25. Årstillv.: 1,500\nstds trävaror. — Bruket anlagt 1885, nuv.",
    "structured": {
        "firms": [
            {
                "name": "Sundsvalls Bryggeri AB.",
                "location": "Sundsvall",
                "products": "Tillverkar malt och maltdrycker, mineralvatten och läskedrycker.",
                "contact": {
                    "phone": [
                        "\"Sundsvalls Bryggeri\""
                    ],
                    "postgiro": "134386"
                },
                "financials": {
                    "capital": "900,000 kr",
                    "employees": {
                        "industriarb": 34
                    },
                    "foundation_year": 1858,
                    "current_name_year": 1930
                },
                "board": [
                    {
                        "name": "hovrättsrådet B. Thuresson",
                        "role": "ordf."
                    },
                    {
                        "name": "disp. B. Nygren",
                        "role": "v. ordf."
                    },
                    {
                        "name": "fru H. Johansson",
                        "role": null
                    },
                    {
                        "name": "fru H. österman",
                        "role": null
                    }
                ],
                "managing_director": "B. Nygren",
                "sales_manager": "Olle Wijkström"
            },
            {
                "name": "Sundsvalls Cellulosa AB.",
                "location": "Sundsvall"
            },
            {
                "name": "AB. Sundsvalls Elektriska Spisbrödsfabrik",
                "location": "Sundsvall",
                "products": "Tillverkar mjöl och gryn, fodermedel samt delikatess-, spis- och knäckebröd.",
                "contact": {
                    "phone": [
                        "2212",
                        "3439"
                    ],
                    "postgiro": "75888"
                },
                "financials": {
                    "capital": "50,000 kr",
                    "employees": {
                        "industriarb": 14
                    },
                    "annual_turnover": "500,000 kr",
                    "foundation_year": 1934
                },
                "managing_director": "ing. Gustaf Brattström"
            },
            {
                "name": "AB. Sundsvalls Förenade Verkstäder",
                "location": "Sundsvall",
                "financials": {
                    "capital": "630,000 kr",
                    "employees": {
                        "industriarb": 110
                    },
                    "annual_turnover": "2,000,000 kr",
                    "foundation_year": 1905
                }
            },
            {
                "name": "Sundsvalls Perspektivfönster AB.",
                "location": "Stockholm",
                "products": "Försäljer perspektivfönster, dörrar, panel m. m., tillverkade vid Kubikenborgs Snickerifabrik, Svartviks AB., Sundsvall.",
                "contact": {
                    "phone": [
                        "Cellulosabolaget"
                    ],
                    "postgiro": "57574"
                },
                "financials": {
                    "capital": "100,000 kr",
                    "foundation_year": 1941
                },
                "board": [
                    {
                        "name": "dir. Gust. Göranson",
                        "role": "ordf."
                    },
                    {
                        "name": "disp. Rye Engström",
                        "role": null
                    },
                    {
                        "name": "disp. Arne Mörch",
                        "role": null
                    },
                    {
                        "name": "dir. K. Erik Nyberg",
                        "role": null
                    },
                    {
                        "name": "byggm. Eric S. Persson",
                        "role": null
                    }
                ],
                "managing_director": "Bengt Falk"
            },
            {
                "name": "Sundsviks Bruk AB.",
                "location": "Sundsvik (Sthlms l.)",
                "products": "Tillverkar sågade och hyvlade trävaror samt murtegel."
            },
            {
                "name": "Sundsviks Såg & Hyvleri, Ingvald Övergaard",
                "location": "Sunne",
                "products": "Tillverkar sågade och hyvlade trävaror samt lister."
            }
        ]
    }
}