{
    "original": "Svenska\n\nvid fabrik i Stockholm (Firma\nDrangel-konfektion).\n\nKontor: Valhallav. 10. Telegr.-adr.:\nKapok, Stockholm. Telefon: 328077.\nPostgiro: 53170.\n\nAkt.-kap.: 75,000 kr. Antal\nindustriarb.: 50. — Firman etabl. 1930, bolag\n1940.\n\nStyrelse: disp. Hugo Bergqvist, adv.\nO.-G. Hedström, kamrer Erik Holmberg.\n\nVerkst. dir.: Hugo Bergqvist.\n\nKamrer: Erik Holmberg.\n\n*AB. Svenska Kappfabriken,\n\nM almö.\n\nTillverkar damkappor och dräkter.\n\nKontor- Södra Promenaden 51.\nTelegr.-adr.: Kappfabriken. Malmö. Telefon:\n26535 o. 23535. Postgiro: 148940.\n\nAkt.-kap.: 312,500 kr. Antal\nindustriarb.: 70. Tillv.-värde pr år: 1,000,000 kr.\n— Firman etabl. 1907, bolag 1911.\n\nStyrelse: fru F. Hartz, grossh. Hektor\nKiaer, polismästare Y, Schaar.\n\nVerkst. dir.: fru F. Hartz.\n\nKontorschef: Alfred Nilsson.\n\n\"AB. Svenska Kapsyifabriken,\n\nStockholm.\n\nTillverkar kapsyler för flaskor och\nburkar, skruvlock. aluminiumhylsor,\naluminium-, bly- och tenn tuber m. fl.\nmetallartiklar.\n\nKontor: Tjärhovsg. 44. Telegr.-adr.:\nKapsyl, Stockholm. Telefon: 414322,\n418838 o. 433387. Postgiro: 3771.\n\nAkt.-kap.: 300,000 kr. Antal\nindustriarb.: 40. — Bolaget grundat 1888.\n\nStyrelse: f. d. taxeringskom. Sven\nEkman, disp. Folke Gill.\n\nVerkst. dir.: Folke Gill.\n\n\"Svenska Karosseri Verkstäderna\nAB., Katrineholm.\n\n^ Karos^erifabrik. Tillverkar karosserier\nför omnibusar.\n\nTelegr.-adr.: Karossen, Katrineholm.\nTelefon: 825, 826 o. 836. Postgiro: 8516.\n\nAkt.-kap.: 150,000 kr. Antal\nindustriarb.: 200. Tillv.-värde pr år: 2,000,000 kr.\n— Bolaget grundat 1927.\n\nStyrelse: disp. Alfred Jönsson, adv.\nVilh. Moberg.\n\nDisp.: Alfred Jönsson.\nFörsäljn.-chef: Nils Manning.\nInköpschef: Einar Jonsson.\n\nSvenska Kassaskåpsfabriken,\n\nStockholm.\n\nTillverkar kassaskåp, valvdörrar,\nbranddörrar m. m.\n\nKontor: Hornsg. 35. Telefon: 436654\no. 437604. Postgiro: 54538. — Antal\nindustriarb.: 18. Tillv.-värde pr år: 300,000\nkr. — Firman etabl. 1895.\n\nÄgare o. chef: ing. K. R. Berglund.\nKamrer: Nils Berglund.\n\n\"Svenska Kolsyrefabriken,\n\nStockholm.\n\nSe De Förenade Kolsyrefabrikernas\nAB., Stockholm.\n\nSvenska Konfektionsfabriken, Carl\nHögström AB-, Göteborg.\n\nTillverkar damunderkläder såsom\nnattlinnen och pyjamas.\n\nKontor: Järntorgsg. 12—14. Telefon:\n115270. Postgiro: 40459. — Akt.-kap.:\n40,000 kr. Antal industriarb.: 25. —\nFirman etabl. 1919, bolag 1941.\nVerkst. dir.: Carl Högström.\n\n\"AB. Svenska Konstgödnings- &amp;\nSvavelsyrefabrikerna, Malmö.\n\nSe AB. Förenade Superfosfatfabriker,\nHälsingborg.\n\nAB. Svenska Konservfabriken\nClobus, Stockholm.\n\nTillverkar tomatprodukter, frukt- och\ngrönsakskonserver, marmelader, bageriar-*\ntiklar m. m. vid fabrik i Hälsingborg.\nVarumärke: »Globus».\n\nHuvudkontor o. ensamförsälj.: AB.\nBanan-Kompaniet, Stockholm,\nFrihamnen, telegr.-adr. o. telefon: Bananer,\nStockholm, med avd.-kontor i Göteborg,\nMalmö o. Hälsingborg.\n\nAkt.-kap.: 5,000 kr. Antal\nindustriarb.: 60. — Bolaget grundat 1945.\n\nStyrelse: dir. Carl Matthiessen (ordf.),\ndir. Ernst Holmström, skeppsredare Sven\nG. Salén.\n\nDisp.: Erik Nilsson.\n\n\"Svenska Kopierings AB.,\n\nStockholm.\n\nt Mek. verkstad. Tillverkar stycklist- och\nljuskopieringsmaskiner, båglampor för\nkopierings- och fotoändamål samt\nframkall-ningsmaskiner. Varumärke: »S. K. A.».\nFirman driver även engroshandel med rit-",
    "structured": {
        "1": {
            "name": "AB. Svenska Drangel-konfektion",
            "location": "Stockholm",
            "business": "Tillverkar damkappor och dräkter",
            "contact": {
                "office": "Valhallav. 10",
                "phone": [
                    "328077"
                ],
                "postgiro": "53170",
                "telegraph": "Kapok, Stockholm"
            },
            "financials": {
                "capital": "75,000 kr",
                "employees": {
                    "industriarb": 50
                },
                "foundation_year": 1930,
                "corporation_year": 1940
            },
            "board": [
                {
                    "name": "Hugo Bergqvist",
                    "role": "disp."
                },
                {
                    "name": "O.-G. Hedström",
                    "role": "adv."
                },
                {
                    "name": "Erik Holmberg",
                    "role": "kamrer"
                }
            ],
            "director": "Hugo Bergqvist",
            "kamrer": "Erik Holmberg"
        },
        "2": {
            "name": "AB. Svenska Kappfabriken",
            "location": "Malmö",
            "business": "Tillverkar damkappor och dräkter",
            "contact": {
                "office": "Södra Promenaden 51",
                "phone": [
                    "26535",
                    "23535"
                ],
                "postgiro": "148940",
                "telegraph": "Kappfabriken, Malmö"
            },
            "financials": {
                "capital": "312,500 kr",
                "employees": {
                    "industriarb": 70
                },
                "annual_production_value": "1,000,000 kr",
                "foundation_year": 1907,
                "corporation_year": 1911
            },
            "board": [
                {
                    "name": "fru F. Hartz",
                    "role": null
                },
                {
                    "name": "grossh. Hektor Kiaer",
                    "role": null
                },
                {
                    "name": "polismästare Y, Schaar",
                    "role": null
                }
            ],
            "director": "fru F. Hartz",
            "kontorschef": "Alfred Nilsson"
        },
        "3": {
            "name": "AB. Svenska Kapsyifabriken",
            "location": "Stockholm",
            "business": "Tillverkar kapsyler för flaskor och burkar, skruvlock. aluminiumhylsor, aluminium-, bly- och tenn tuber m. fl. metallartiklar",
            "contact": {
                "office": "Tjärhovsg. 44",
                "phone": [
                    "414322",
                    "418838",
                    "433387"
                ],
                "postgiro": "3771",
                "telegraph": "Kapsyl, Stockholm"
            },
            "financials": {
                "capital": "300,000 kr",
                "employees": {
                    "industriarb": 40
                },
                "corporation_year": 1888
            },
            "board": [
                {
                    "name": "f. d. taxeringskom. Sven Ekman",
                    "role": "disp."
                },
                {
                    "name": "disp. Folke Gill",
                    "role": null
                }
            ],
            "director": "Folke Gill"
        },
        "4": {
            "name": "Svenska Karosseri Verkstäderna AB.",
            "location": "Katrineholm",
            "business": "Karosserifabrik. Tillverkar karosserier för omnibusar",
            "contact": {
                "telegraph": "Karossen, Katrineholm",
                "phone": [
                    "825",
                    "826",
                    "836"
                ],
                "postgiro": "8516"
            },
            "financials": {
                "capital": "150,000 kr",
                "employees": {
                    "industriarb": 200
                },
                "annual_production_value": "2,000,000 kr",
                "corporation_year": 1927
            },
            "board": [
                {
                    "name": "disp. Alfred Jönsson",
                    "role": null
                },
                {
                    "name": "adv. Vilh. Moberg",
                    "role": null
                }
            ],
            "disp": "Alfred Jönsson",
            "försäljn.-chef": "Nils Manning",
            "inköpschef": "Einar Jonsson"
        },
        "5": {
            "name": "Svenska Kassaskåpsfabriken",
            "location": "Stockholm",
            "business": "Tillverkar kassaskåp, valvdörrar, branddörrar m. m",
            "contact": {
                "office": "Hornsg. 35",
                "phone": [
                    "436654",
                    "437604"
                ],
                "postgiro": "54538"
            },
            "financials": {
                "employees": {
                    "industriarb": 18
                },
                "annual_production_value": "300,000 kr"
            },
            "owners": [
                "ing. K. R. Berglund"
            ],
            "chef": "K. R. Berglund",
            "kamrer": "Nils Berglund"
        },
        "6": {
            "name": "Svenska Konfektionsfabriken, Carl Högström AB",
            "location": "Göteborg",
            "business": "Tillverkar damunderkläder såsom nattlinnen och pyjamas",
            "contact": {
                "office": "Järntorgsg. 12—14",
                "phone": [
                    "115270"
                ],
                "postgiro": "40459"
            },
            "financials": {
                "capital": "40,000 kr",
                "employees": {
                    "industriarb": 25
                },
                "corporation_year": 1941
            },
            "director": "Carl Högström"
        },
        "7": {
            "name": "AB. Svenska Konservfabriken Clobus",
            "location": "Stockholm",
            "business": "Tillverkar tomatprodukter, frukt- och grönsakskonserver, marmelader, bageriar-tiklar m. m. vid fabrik i Hälsingborg",
            "contact": {
                "main_office": "Frihamnen, Stockholm",
                "phone": [
                    "Bananer"
                ],
                "postgiro": "40459"
            },
            "financials": {
                "capital": "5,000 kr",
                "employees": {
                    "industriarb": 60
                },
                "corporation_year": 1945
            },
            "board": [
                {
                    "name": "dir. Carl Matthiessen",
                    "role": "ordf."
                },
                {
                    "name": "dir. Ernst Holmström",
                    "role": null
                },
                {
                    "name": "skeppsredare Sven G. Salén",
                    "role": null
                }
            ],
            "disp": "Erik Nilsson"
        },
        "8": {
            "name": "Svenska Kopierings AB.",
            "location": "Stockholm",
            "business": "Mek. verkstad. Tillverkar stycklist- och ljuskopieringsmaskiner, båglampor för kopierings- och fotoändamål samt framkall-ningsmaskiner",
            "contact": {
                "phone": [
                    "S.K.A."
                ],
                "telegraph": null
            }
        }
    }
}