{
    "original": "Wahlén— V al b o\n\nAB. Wahlén &amp; Block,\n\nStockholm.\n\nOljeraffinaderi och kem.-tekn. fabrik i\nVärtan, Stockholm^ Tillverkar smörjmedel\nsåsom automobiloljor, maskin- och\nspecialoljor, konsistensfett m. m.,\ntransformatoroljor samt puts- och slipmedel.\nBolaget driver såsom huvudrörelse\nengroshandel med smörjoljor, transformatoroljor\noch maskinförnödenheter.\n\nHuvudkontor: Stora Ny g. 7.\nTelegr.-adr.: Wabo, Stockholm. Telefon: »Wahlén\n&amp; Block». Postgiro: 859. Avd.-kontor: i\nMalmö, Norra Vallg. 20, telefon: 16958\no. 28358; i Göteborg, L. Bommens Ö. Kaj,\ntelefon: 153432—33; i Kalmar, telefon:\n53; i Sundsvall, telefon: 56809.\n\nAkt.-kap.: 1,200,000 kr. Antal\nindustriarb.: 30. — Firman etabl. 1886, bolag\n1903.\n\nStyrelse: dir. K. Heinecke (ordf.), dir.\nEmil Edman, bankdir. Helmer Lindh.\n\nVerkst. dir.: Emil Edman.\n\nVice dir.: Einar G:son Dal.\n\nDriftsing.: Bertil Knutson.\n\n*AB. K. F. Wahlgren, Borås.\n\nSkofabrik. Tillverkar skodon.\nVarumärke: »W-sko».\n\nTelefon: 17650. — Akt.-kap.: 10,000 kr.\nAntal industriarb.: 40. — Nuv. bolag\ngrundat 1946.\n\nStyrelse: fru Ellen Ljungberg (ordf.),\nmed. lic. Gunnar Wihman, disp. Tore\nWihman.\n\nDisp.: Tore Wihman.\n\nErik Wahlqvist AB., Skebokvarn.\n\nSnickerifabrik i Skebokvarn\n(Södermanl. l.). Tillverkar byggnadssnickerier\noch inredningar samt bowlingbanor.\n\nTelefon: 46. Postgiro: 97114. —\nAkt.-kap.: 16,000 kr. Antal industriarb.: 20.\nTillv.-värde pr år: 200,000 kr. — Firman\netabl. 1914, bolag 1933.\n\nDisp.: Erik Wahlqvist.\n\n*Wahlqvistska Klädesfabriken C. A.\nSvahn, Svängsta.\n\nKlädesfabrik vid Marieberg, Svängsta\n(Blekinge l.). Tillverkar uniformskläde\noch andra yllevävnader, filtar m. m.\nFirman äger jämväl kraftstation vid\nMör-rums ström och distribuerar elektr. energi.\n\nTelegr.-adr.: Klädesfabriken, Svängsta.\nTelefon: Karlshamn 3. Postgiro: 22437.\n\nAntal industriarb.: 200. Tillv.-värde\npr år: 2,000,000 kr. — Firman etabl.\n1824.\n\nÄgare o. chef: kammarh. Nils\nSwart-ling.\n\nAB. L. E. Wahlström, Earlstad.\n\nTillverkar begravningsartiklar,\nkonstgjorda blommor, kransstommar (märke:\n»Ideal») m. m. samt blomstergödning\n(märke: »Flower-Food»).\n\nTelefon: 10124 o. 10594. Postgiro:\n8493.\n\nAkt.-kap.: 135,000 kr. Antal\nindustriarb.: 30. Tillv.-värde pr år: 550,000 kr.\n\n—\tFirman etabl. 1904, bolag 1927.\n\nVerkst. dir. o. disp.: Knut Wahlström.\n\n*AB. Waidele, Göteborg.\n\nMusikinstrumentfabrik. Tillverkar\nlu-tor, gitarrer och andra stränginstrument.\nBolaget driver även engros- och\ndetaljhandel inom musikinstrument-, radio- och\ncykelbranschen. Varumärken: »Crafton»,\n»Tone-Craft», »Jenny Lind» o.\n»El-gramm».\n\nKontor: Fredsg. 3. Telegr.-adr.:\nWaidele, Göteborg. Telefon: 170030.\nPostgiro: 12487.\n\nAkt.-kap.: 180,000 kr. Antal\nindustriarb.: 39. — Firman etabl. 1880, bolag\n1924.\n\nStyrelse: dir. Heimer Waidele (ordf.),\ndir. Arne Waidele, änkefru A. Waidele.\n\nVerkst. dir.: Heimer Waidele.\n\nFabrikschef: Max Wilfer.\n\nKontorschef: Leif Norlander.\n\n*Waksala Nya Tegelbruk, Lundqvist\n&amp; Johansson, Stockholm.\n\nTegelbruk i Uppsala. Tillverkar\nmur-och taktegel, radialtegel samt\ndräneringsrör.\n\nKontor: Stockholm, Dalag. 56 B.\nTelefon: 323807 o. 335631. Postgiro: 53360.\n\nAvd.-kontor: Uppsala, telefon: 30179.\n\nAntal industriarb.: 30. Årstillv.: 2,3\nmilj. tegel var or. — Tegelbruket anlagt\n1880, nuv. firma etabl. 1912.\n\nÄgare: disp. E. W. Lundqvists sterbhus\no. ing. Oscar Johansson.\n\n* Valbo Verkstads AB.,\n\nNorra Valbo.\n\nKarosseriverkstäder i Norra Valbo\n(Gävleb. l.). Tillverkar skåp- och\nlastvagnskarosser, begravningskarosser m. m.\n\nTelefon: Valbo 87 o. 245. Postgiro:\n36912.\n\nAkt.-kap.: 38,000 kr. Antal\nindustriarb.: 40. Tillv.-värde pr år: 500,000 kr.\n\n—\tVerkstaden anlagd 1919, nuv. bolag\ngrundat 1929.\n\nStyrelse: kamrer Allert Holmgren,\ning. G. Ålenius, fru Maja Ålenius.\n\nVerkst. dir.: G. Ålenius.\n\nKamrer: Allert Holmgren.",
    "structured": {
        "1": {
            "name": "AB. Wahlén—V al b o",
            "location": "Stockholm",
            "business": "Oljeraffinaderi och kem.-tekn. fabrik",
            "products": "Tillverkar smörjmedel såsom automobiloljor, maskin- och specialoljor, konsistensfett m. m., transformatoroljor samt puts- och slipmedel. Bolaget driver såsom huvudrörelse engroshandel med smörjoljor, transformatoroljor och maskinförnödenheter.",
            "contact": {
                "office": "Stora Ny g. 7",
                "telegraph": "Wabo, Stockholm",
                "phone": [
                    "‘Wahlén & Block’"
                ],
                "postgiro": "859",
                "sales_offices": [
                    {
                        "location": "Malmö",
                        "phone": "16958, 28358"
                    },
                    {
                        "location": "Göteborg",
                        "phone": "153432-33"
                    },
                    {
                        "location": "Kalmar",
                        "phone": "53"
                    },
                    {
                        "location": "Sundsvall",
                        "phone": "56809"
                    }
                ]
            },
            "financials": {
                "capital": "1,200,000 kr",
                "employees": {
                    "industriarb": 30
                },
                "annual_turnover": "NotAvailable",
                "annual_production_value": "NotAvailable"
            },
            "foundation_year": 1886,
            "corporation_year": 1903,
            "board": [
                {
                    "name": "K. Heinecke",
                    "role": "ordf."
                },
                {
                    "name": "Emil Edman",
                    "role": "dir."
                },
                {
                    "name": "Helmer Lindh",
                    "role": "bankdir."
                }
            ]
        },
        "2": {
            "name": "AB. K. F. Wahlgren",
            "location": "Borås",
            "business": "Skofabrik",
            "products": "Tillverkar skodon",
            "contact": {
                "phone": [
                    "17650"
                ]
            },
            "financials": {
                "capital": "10,000 kr",
                "employees": {
                    "industriarb": 40
                }
            },
            "foundation_year": 1946,
            "board": [
                {
                    "name": "fru Ellen Ljungberg",
                    "role": "ordf."
                },
                {
                    "name": "med. lic. Gunnar Wihman",
                    "role": "NotAvailable"
                },
                {
                    "name": "disp. Tore Wihman",
                    "role": "NotAvailable"
                }
            ]
        },
        "3": {
            "name": "Erik Wahlqvist AB.",
            "location": "Skebokvarn",
            "business": "Snickerifabrik",
            "products": "Tillverkar byggnadssnickerier och inredningar samt bowlingbanor",
            "contact": {
                "phone": [
                    "46"
                ],
                "postgiro": "97114"
            },
            "financials": {
                "capital": "16,000 kr",
                "employees": {
                    "industriarb": 20
                },
                "annual_turnover": "NotAvailable",
                "annual_production_value": "200,000 kr"
            },
            "foundation_year": 1914,
            "corporation_year": 1933,
            "board": [
                {
                    "name": "Erik Wahlqvist",
                    "role": "disp."
                }
            ]
        },
        "4": {
            "name": "Wahlqvistska Klädesfabriken C. A.Svahn",
            "location": "Svängsta",
            "business": "Klädesfabrik",
            "products": "Tillverkar uniformskläde och andra yllevävnader, filtar m. m. Firman äger jämväl kraftstation vid Mör-rums ström och distribuerar elektr. energi",
            "contact": {
                "telegraph": "Klädesfabriken, Svängsta",
                "phone": [
                    "Karlshamn 3"
                ],
                "postgiro": "22437"
            },
            "financials": {
                "employees": {
                    "industriarb": 200
                },
                "annual_turnover": "2,000,000 kr",
                "annual_production_value": "NotAvailable"
            },
            "foundation_year": 1824,
            "board": [
                {
                    "name": "kammarh. Nils Swartling",
                    "role": "ägare o. chef"
                }
            ]
        },
        "5": {
            "name": "L. E. Wahlström",
            "location": "Earlstad",
            "business": "Tillverkar begravningsartiklar, konstgjorda blommor, kransstommar",
            "products": "Märke: »Ideal», blomstergödning (märke: »Flower-Food»)",
            "contact": {
                "office": "NotAvailable"
            },
            "financials": {
                "capital": "135,000 kr",
                "employees": {
                    "industriarb": 30
                },
                "annual_turnover": "NotAvailable",
                "annual_production_value": "550,000 kr"
            },
            "foundation_year": 1904,
            "corporation_year": 1927,
            "board": [
                {
                    "name": "Knut Wahlström",
                    "role": "Verkst. dir. o. disp."
                }
            ]
        },
        "6": {
            "name": "AB. Waidele",
            "location": "Göteborg",
            "business": "Musikinstrumentfabrik",
            "products": "Tillverkar lu-tor, gitarrer och andra stränginstrument. Bolaget driver även engros- och detaljhandel inom musikinstrument-, radio- och cykelbranschen",
            "contact": {
                "factory_office": "NotAvailable",
                "factory_phone": "NotAvailable"
            },
            "financials": {
                "capital": "180,000 kr",
                "employees": {
                    "industriarb": 39
                },
                "annual_turnover": "NotAvailable",
                "annual_production_value": "NotAvailable"
            },
            "foundation_year": 1880,
            "corporation_year": 1924,
            "board": [
                {
                    "name": "Heimer Waidele",
                    "role": "ordf."
                },
                {
                    "name": "Arne Waidele",
                    "role": "dir."
                },
                {
                    "name": "änkefru A. Waidele",
                    "role": "NotAvailable"
                }
            ]
        },
        "7": {
            "name": "Waksala Nya Tegelbruk, Lundqvist & Johansson",
            "location": "Stockholm",
            "business": "Tegelbruk",
            "products": "Tillverkar mur-och taktegel, radialtegel samt dräneringsrör",
            "contact": {
                "office": "Dalag. 56 B",
                "telegraph": "NotAvailable",
                "phone": [
                    "323807, 335631"
                ],
                "postgiro": "53360",
                "sales_offices": [
                    {
                        "location": "Uppsala",
                        "phone": "30179"
                    }
                ]
            },
            "financials": {
                "employees": {
                    "industriarb": 30
                },
                "annual_turnover": "NotAvailable",
                "annual_production_value": "2.3 milj. tegel var or."
            },
            "foundation_year": 1912,
            "board": [
                {
                    "name": "Oscar Johansson",
                    "role": "ing."
                }
            ]
        },
        "8": {
            "name": "Valbo Verkstads AB.",
            "location": "Norra Valbo",
            "business": "Karosseriverkstäder",
            "products": "Tillverkar skåp- och lastvagnskarosser, begravningskarosser",
            "contact": {
                "phone": [
                    "Valbo 87, 245"
                ],
                "postgiro": "36912"
            },
            "financials": {
                "capital": "38,000 kr",
                "employees": {
                    "industriarb": 40
                },
                "annual_turnover": "NotAvailable",
                "annual_production_value": "500,000 kr"
            },
            "foundation_year": 1919,
            "corporation_year": 1929,
            "board": [
                {
                    "name": "Allert Holmgren",
                    "role": "kamrer"
                },
                {
                    "name": "G. Ålenius",
                    "role": "NotAvailable"
                },
                {
                    "name": "Maja Ålenius",
                    "role": "fru"
                }
            ]
        }
    }
}