{
    "original": "S öderling—Södervärn\n\nTelegr.-adr.: Sverk, Söderhamn.\nTelefon: »Söderhamns verkstäder». Postgiro:\n174200.\n\nAkt.-kap.: 300,000 kr. Antal\nindustriarb.: 200. Tillv.-värde pr år: 3,000,000 kr.\n\nVerkstaden anlagd 1864, bolaget bildat\n1941 efter övertagandet av AB. Svenska\nMaskinverkens, Södertälje,\nverkstadsrörelse i Söderhamn.\n\nStyrelse: dir. Mauritz Carlson (ordf.),\n&lt;iir. Gunnar L. Jacobsson, dir. Sven\nOt-t er beck.\n\nVerkst. dir.: Lars Dalman.\n\nKamrer: Axel Bendrik.\n\nVerkstadschef: Runo Lundbergh.\n\nInköpschef: Hilmer Burman.\n\nAB. C. F. Söderlings Fabriker,\n\nLomma.\n\nPolerskivfabrik i Lomma (Malmöh. l.).\nTillverkar sydda och limmade lappskivor\n{sliposkivor) samt sydda och osydda\njglänsskivor. Firman driver även handel\nmed slipmateriel samt med slip- och poler-\n\nniärSkmcr\n\nTelefon: Malmö 462019 o. 462003.\nPostgiro: 32567. Repr. i Göteborg: Axel F.\nJohansson, Kvarngärdesg. 3 A, telefon:\n184833.\n\nAkt.-kap.: 50,000 kr. Antal\nindustriarb.: 24. Tillv.-värde pr år: 210,000 kr.\n— Firman etabl. 1908, bolag 1946.\n\nVerkst. dir.; Hans F. Söderling.\n\nKamrer: Stewart Bahrman.\n\nSöderlund &amp; Lindström, Gävle.\n\nMek. verkstad. Tillverkar reservdelar\n€ör bil- och motorcykelmotorer samt utför\nmotorrenoveringar, finmekaniska arbeten\nsamt metallisering.\n\nTelefon: 7320. Postgiro: 26181. —\nAntal industriarb.: 55. Tillv.-värde pr år:\nS00,000 kr. — Firman etabl. 1919.\n\nÄgare o. chef: fabr. J. Alfr. Söderlund.\n\nKamrer: Swen A. Sundberg.\n\n*AB. Södermalms Nya\nSnickerifabrik, EnsJcede.\n\nTillverkar byggnadssnickerier såsom\ndörrar och fönster, köksskåp, paneler och\nlistverk samt inredningar för butiker\n^standarddisken »Service»). Specialiteter:\ntrappor och ledstänger.\n\nKontor: Huddingevägen 111, Enskede\n(Stockholm). Telefon: 496295 o. 496395,\nPostgiro: 51519.\n\nAkt.-kap.: 10,000 kr. Arb.-antal: 15.\n—- Firman etabl. 1929, bolag 1935. ^\n\nStyrelse o. verkst. dir.: disp. Bertil\nSa-tomonson.\n\n*W. Söderströms Cjuteri &amp; Mek.\nVerkstads AB., Norrköping.\n\nMek. verkstad, gjuteri och\ngrovplåtslageri. Tillverkar ångpannor,\njärnkonstruktioner, svetsade och nitade plåtarbeten,\ntransmissioner, gjutgods m. m. samt utför\nreparationer. Varumärke: »WESAB».\n\nTelegr.-adr.: Wesab, Norrköping.\nTelefon: 23060 o. 20306. Postgiro: 11035.\n\nAkt.-kap.: 330,000 kr. Antal\nindustriarb.: 55. Tillv.-värde pr år: 750,000 kr.\n— Firman etabl. 1868, bolag 1902.\n\nStyrelse: ing. Gustav Söderström\n(ordf.), gjutm. Hugo Söderström, kassör\nIvar Söderström.\n\nDisp.: Gustav Söderström.\n\n(Jfr annons nr 83.)\n\n*Södertelje Bryggeri AB.,\n\nSödertälje.\n\nTillverkar malt- och läskedrycker.\n\nTelefon: »Bryggeribolaget». Postgiro:\n134692. Bolaget har upplag i Mariefred\noch Trosa.\n\nAkt.-kap.: 400,000 kr. Antal\nindustriarb.: 65. Tillv.-värde pr år: 1,500,000 kr.\n\nBolaget grundades 1896. AB.\nStockholms Bryggerier är huvudintressent i\nbolaget.\n\nStyrelse: dir. Sven Schwartz (ordf.),\ndir. Harald Engström, disp. Sten\nSimonsson.\n\nVerkst. dir.: Sten Simonsson.\n\nAB. Södertälje Metallförädling,\n\nSödertälje.\n\nElektriskt smältverk för mässing.\nFramställer stångmaterial av\ncentrifuge-rad mässing.\n\nTelegr.-adr.: Metallförädling,\nSödertälje. Telefon: 33201 o. 33202. Postgiro:\n174899.\n\nAkt.-kap.: 500,000 kr. Antal\nindustriarb.: 60. — Bolaget grundat 1941.\n\nStyrelse: dir. L. Bamberger (ordf.),\nadv. S. Lindskog, civiling. Sixten Nilsson,\nbergsing. P. Odelberg.\n\nVerkst. dir.: L. Bamberger.\n\nTehn. chef: civiling. Sixten Nilsson.\n\nDriftsing.; Gunnar Westman.\n\nKamrer: R. Lorin.\n\nFörsäljn.-chef: Thure Johanson.\n\n\"Södervärns Tricotfabrik AB.,\n\nMalmö.\n\nTillverkar silkestrikåunderkläder och\nstrumpor. Varumärke: »Tallen».\n\nKontor: Industrig. Telefon: 21657.\nPostgiro: 24542. Repr. i Stockholm: Si-",
    "structured": {
        "1": {
            "name": "Söderlings Fabriker",
            "location": "Söderhamn",
            "business": "Verkstad och tillverkning",
            "contact": {
                "office": "Sverk, Söderhamn",
                "postgiro": "174200"
            },
            "financials": {
                "capital": "300,000 kr",
                "employees": {
                    "industriarb.": 200
                },
                "annual_turnover": "3,000,000 kr",
                "annual_production_value": "3,000,000 kr"
            },
            "foundation_year": 1864,
            "corporation_year": 1941,
            "board": [
                {
                    "name": "Mauritz Carlson",
                    "role": "ordf."
                },
                {
                    "name": "Gunnar L. Jacobsson",
                    "role": "dir."
                },
                {
                    "name": "Sven Otterbeck",
                    "role": "dir."
                }
            ],
            "director": "Lars Dalman",
            "manager": "Runo Lundbergh",
            "sales_manager": "Hilmer Burman"
        },
        "2": {
            "name": "C. F. Söderlings Fabriker",
            "location": "Lomma",
            "business": "Polerskivfabrik och handel",
            "contact": {
                "phone": [
                    "Malmö 462019",
                    "Malmö 462003"
                ],
                "postgiro": "32567",
                "sales_offices": [
                    {
                        "location": "Göteborg",
                        "phone": "184833"
                    }
                ]
            },
            "financials": {
                "capital": "50,000 kr",
                "employees": {
                    "industriarb.": 24
                },
                "annual_turnover": "210,000 kr"
            },
            "foundation_year": 1908
        },
        "3": {
            "name": "Söderlund & Lindström",
            "location": "Gävle",
            "business": "Mekanisk verkstad",
            "contact": {
                "phone": "7320",
                "postgiro": "26181"
            },
            "financials": {
                "employees": {
                    "industriarb.": 55
                },
                "annual_turnover": "800,000 kr"
            },
            "foundation_year": 1919,
            "owners": [
                "J. Alfr. Söderlund"
            ],
            "manager": "J. Alfr. Söderlund",
            "sales_manager": "Swen A. Sundberg"
        },
        "4": {
            "name": "Södermalms Nya Snickerifabrik",
            "location": "Enskede",
            "business": "Tillverkning av snickerier och inredningar",
            "contact": {
                "office": "Huddingevägen 111, Enskede (Stockholm)",
                "phone": [
                    "496295",
                    "496395"
                ],
                "postgiro": "51519"
            },
            "financials": {
                "capital": "10,000 kr",
                "employees": {
                    "arb.-antal": 15
                }
            },
            "foundation_year": 1929,
            "board": [
                {
                    "name": "Bertil Satomonson",
                    "role": "disp."
                }
            ]
        },
        "5": {
            "name": "W. Söderströms Gjuteri & Mek. Verkstads AB",
            "location": "Norrköping",
            "business": "Mekanisk verkstad, gjuteri och plåtslageri",
            "contact": {
                "office": "Wesab, Norrköping",
                "phone": [
                    "23060",
                    "20306"
                ],
                "postgiro": "11035"
            },
            "financials": {
                "capital": "330,000 kr",
                "employees": {
                    "industriarb.": 55
                },
                "annual_turnover": "750,000 kr"
            },
            "foundation_year": 1868
        },
        "6": {
            "name": "Södertelje Bryggeri AB",
            "location": "Södertälje",
            "business": "Tillverkning av malt- och läskedrycker",
            "contact": {
                "phone": "Bryggeribolaget",
                "postgiro": "134692"
            },
            "financials": {
                "capital": "400,000 kr",
                "employees": {
                    "industriarb.": 65
                },
                "annual_turnover": "1,500,000 kr"
            },
            "foundation_year": 1896
        },
        "7": {
            "name": "Södertälje Metallförädling",
            "business": "Elektriskt smältverk för mässing",
            "location": "Södertälje",
            "contact": {
                "office": "Metallförädling, Södertälje",
                "phone": [
                    "33201",
                    "33202"
                ],
                "postgiro": "174899"
            },
            "financials": {
                "capital": "500,000 kr",
                "employees": {
                    "industriarb.": 60
                }
            },
            "foundation_year": 1941,
            "board": [
                {
                    "name": "L. Bamberger",
                    "role": "ordf."
                },
                {
                    "name": "S. Lindskog",
                    "role": "adv."
                },
                {
                    "name": "Sixten Nilsson",
                    "role": "civiling."
                }
            ],
            "director": "L. Bamberger",
            "manager": "Gunnar Westman"
        },
        "8": {
            "name": "Södervärns Tricotfabrik AB",
            "location": "Malmö",
            "business": "Tillverkning av silkestrikåunderkläder och strumpor",
            "contact": {
                "office": "Industrig.",
                "phone": "21657",
                "postgiro": "24542",
                "sales_offices": [
                    {
                        "location": "Stockholm",
                        "phone": "Unknown"
                    }
                ]
            }
        }
    }
}