{
    "original": "Å tvidaberg•—Ä l fången\n\nVerkst. dir.: Elof Ericsson.\nFörsäljn.-dir.: R. Dencker.\nTehn. dir.: Albert Engvall.\nInköpschef: Gunnar Collin.\n(Jfr annons före Personregistret.)\n\nÅtvidabergs Kvarn AB.,\n\nÅtvidaberg.\n\nTillverkar mjöl och korngryn vid kvarn\ni Åtvidaberg (Östergötl. l.).\n\nTelefon: 46 o. 216. Postgiro: 86600.\nAkt.-kap.: 150,000 kr. Arb.-antal: 8.\nProd.-värde pr år: 500,000 kr. — Bolaget\ngrundat 1905.\n\nStyrelse: godsförvalt. Å. Joachimsson,\n(ordf.), disp. John Johnsson, bankdir. G.\nLjungmark.\n\nDisp.: John Johnsson.\nKamrer: Gustaf Ekström.\n\nÅtvidabergs Spårväxlar &amp;\nSignal-fabriks AB. (Åssa), Stockholm.\n\nMek. verkstad i Åtvidaberg (Östergötl.\n1.). Tillverkar spårväxlar, vändskivor,\nsignalmaterial för järnvägar,\nplåtbyggnader, smörj apparater samt\nbränslepumpar och automatiska elektr.\noljekontroller för explosionsmotorer.\n\nHuvudkontor: Stockholm, Nybrog. 7.\nTelegr.-adr.: Signalroth, Stockholm.\nTelefon: 617956—57. Postgiro: 3997.\nFabrikskontor: Åtvidaberg. Telegr.-adr.:\nÅs-sa, Åtvidaberg. Telefon: 404 o. 405.\n\nAkt.-kap.: 600,000 kr. Antal\nindustriarb.: 120. Tillv.-värde pr år: 2,000,000 kr.\n— Firman etabl. 1912, bolag 1923.\n\nStyrelse: hovauditör Birger # Barre\n(ordf.), övering. W. Jiillig, dipl.-ing. R.\nVogelgesang.\n\nVerkst. dir.: R. Vogelgesang (Sthlm).\n\nVerkstads chef: W. Jiillig.\n\n\n\n* utmärker till Sveriges Industriförbund anslutna företag.\n\n’Ådelmetall AB., Malmö.\n\nAffineri, legerings- och krätzanstalt.\nUtvinner ädla metaller ur avfall samt\nframställer legeringar för juvelerare,\nden-taländamål samt för tekniskt bruk.\n\nKontor: Citadellskajen 23; postadr.:\nBox 1, Malmö. Telegr.-adr.: Ädelmetall,\nMalmö. Telefon: 28346. Postgiro: 37677.\n\nAkt.-kap.: 100,000 kr. Antal\nindustriarb.: 10. Prod.-värde pr år: 4,500,000 kr.\n— Bolaget grundat 1918.\n\nStyrelse: jur. dr Axel Roos (ordf.),\nfru Gerhild Nyström, dipl.-ing. G. I.\nRoman, dir. Carl S. Roos.\n\nVerkst. dir.: G. I. Roman.\n\nKontorschef: Rud. Rohlsson.\n\nAB. Åggemballage, Alvesta.\n\nTillverkar äggemballage av trä och\npapp vid fabrik i Alvesta (Kronob. l.).\n\nTelefon: 25. Postgiro: 92949. —\nAkt.-kap.: 50,000 kr. Antal industriarb.: 10.\nTillv.-värde pr år: 100,000 kr. —\nBolaget grundat 1937.\n\nVerkst. dir. o. disp.: Nils G. Berg.\n\n’Aggfors AB., Mörsil.\n\nTräsliperi vid Äggfors, Mörsil (Jämtl.\n1.). Tillverkar mek. trämassa.\n\nTelegr.-adr.: Äggfors, Mörsil. Telefon:\n20. Postgiro: 179065.\n\nAkt.-kap.: 2,700,000 kr. Antal\nindustriarb.: 100. Årskapacitet: 60,000 ton våt vit\nträmassa. — Bolaget grundat 1887.\n\nStyrelse: disp. N. B. Börresen, ing. Alf\nPrydz, disp. Tor Prydz, adv. Sune Wetter.\n\nDisp.: Tor Prydz.\n\nKontorschef: Hilding Ericsson.\n\n’Alfkarleö Bruk, Älvkarleö.\n\nStålmanufakturverk vid Älvkarleö\n(Uppsala l.). Tillverkar alla slags\nfjädrar samt annan hejad och smidd\nstålmanufaktur.\n\nTelegr.-adr.: Bruket, Älvkarleby.\nTelefon: 16 o. 34. — Antal industriarb.: 75.\n\nBruket, som anlades 1659—1662, äges\nav Stora Kopparbergs Bergslags AB.,\nFalun. (Se detta bolag.)\n\nPlatschef: ing. N. G. Fredriksson.\n\nKassör o. bokförare: Edvard Edvinger.\n\n’Älfängens Tegelbruk, Kilström &amp;\nMannerborn, Säffle.\n\nTillverkar murtegel och dräneringsrör\nvid tegelbruk i Säffle (Värml. l.).\n\nTelefon: 191. Postgiro: 172454. —\nAntal industriarb.: 26. Tillv.-värde pr år:\n\n645*",
    "structured": {
        "1": {
            "name": "Åtvidabergs Kvarn AB.",
            "location": "Åtvidaberg",
            "business": "Tillverkar mjöl och korngryn vid kvarn i Åtvidaberg (Östergötl. l.).",
            "contact": {
                "phone": [
                    "46",
                    "216"
                ],
                "postgiro": "86600"
            },
            "financials": {
                "capital": "150,000 kr",
                "employees": {
                    "Arb.-antal": 8
                },
                "annual_production_value": "500,000 kr"
            },
            "foundation_year": 1905,
            "board": [
                {
                    "name": "godsförvalt. Å. Joachimsson",
                    "role": "ordf."
                },
                {
                    "name": "disp. John Johnsson",
                    "role": "disp."
                },
                {
                    "name": "bankdir. G. Ljungmark",
                    "role": "bankdir."
                }
            ]
        },
        "2": {
            "name": "Åtvidabergs Spårväxlar & Signal-fabriks AB. (Åssa)",
            "location": "Stockholm",
            "business": "Tillverkar spårväxlar, vändskivor, signalmaterial för järnvägar, plåtbyggnader, smörj apparater samt bränslepumpar och automatiska elektr. oljekontroller för explosionsmotorer.",
            "contact": {
                "phone": "617956—57",
                "postgiro": "3997",
                "sales_offices": [
                    {
                        "location": "Stockholm",
                        "phone": "617956—57"
                    },
                    {
                        "location": "Åtvidaberg",
                        "phone": "404 o. 405"
                    }
                ]
            },
            "financials": {
                "capital": "600,000 kr",
                "employees": {
                    "Antal industriarb.": 120
                },
                "annual_production_value": "2,000,000 kr"
            },
            "foundation_year": 1912,
            "board": [
                {
                    "name": "hovauditör Birger # Barre",
                    "role": "ordf."
                },
                {
                    "name": "övering. W. Jiillig",
                    "role": "övering."
                },
                {
                    "name": "dipl.-ing. R. Vogelgesang",
                    "role": "dipl.-ing."
                }
            ]
        },
        "3": {
            "name": "Ådelmetall AB.",
            "location": "Malmö",
            "business": "Affineri, legerings- och krätzanstalt. Utvinner ädla metaller ur avfall samt framställer legeringar för juvelerare, dentaländamål samt för tekniskt bruk.",
            "contact": {
                "phone": "28346",
                "postgiro": "37677"
            },
            "financials": {
                "capital": "100,000 kr",
                "employees": {
                    "Antal industriarb.": 10
                },
                "annual_production_value": "4,500,000 kr"
            },
            "foundation_year": 1918,
            "board": [
                {
                    "name": "jur. dr Axel Roos",
                    "role": "ordf."
                },
                {
                    "name": "fru Gerhild Nyström",
                    "role": "fru"
                },
                {
                    "name": "dipl.-ing. G. I. Roman",
                    "role": "dipl.-ing."
                }
            ]
        },
        "4": {
            "name": "Åggemballage AB.",
            "location": "Alvesta",
            "business": "Tillverkar äggemballage av trä och papp vid fabrik i Alvesta (Kronob. l.).",
            "contact": {
                "phone": "25",
                "postgiro": "92949"
            },
            "financials": {
                "capital": "50,000 kr",
                "employees": {
                    "Antal industriarb.": 10
                },
                "annual_production_value": "100,000 kr"
            },
            "foundation_year": 1937,
            "director": "Nils G. Berg"
        },
        "5": {
            "name": "Aggfors AB.",
            "location": "Mörsil",
            "business": "Träsliperi vid Äggfors, Mörsil (Jämtl. l.). Tillverkar mek. trämassa.",
            "contact": {
                "phone": "20",
                "postgiro": "179065"
            },
            "financials": {
                "capital": "2,700,000 kr",
                "employees": {
                    "Antal industriarb.": 100
                },
                "annual_production_value": "60,000 ton våt vit trämassa"
            },
            "foundation_year": 1887,
            "board": [
                {
                    "name": "disp. N. B. Börresen",
                    "role": "disp."
                },
                {
                    "name": "ing. Alf Prydz",
                    "role": "ing."
                },
                {
                    "name": "disp. Tor Prydz",
                    "role": "disp."
                }
            ]
        },
        "6": {
            "name": "Alfkarleö Bruk",
            "location": "Älvkarleö",
            "business": "Stålmanufakturverk vid Älvkarleö (Uppsala l.). Tillverkar alla slags fjädrar samt annan hejad och smidd stålmanufaktur.",
            "contact": {
                "phone": [
                    "16",
                    "34"
                ]
            },
            "employees": {
                "Antal industriarb.": 75
            }
        },
        "7": {
            "name": "Älfängens Tegelbruk, Kilström & Mannerborn",
            "location": "Säffle",
            "business": "Tillverkar murtegel och dräneringsrör vid tegelbruk i Säffle (Värml. l.).",
            "contact": {
                "phone": "191",
                "postgiro": "172454"
            },
            "employees": {
                "Antal industriarb.": 26
            },
            "annual_production_value": "645*"
        }
    }
}