{
    "original": "Andersson\n\n* A. C. Anderssons Snickerifabrik,\n\nValåse n.\n\nTillverkar darrar och fönster,\nköksinredningar, trappor, luckor och lådor vid\nsnickerifabrik i Valåsen (Örebro L).\n\nTelefon:; Karlskoga 28170: Postgiro:\n139541. — Antal industriarb.: 2.\nTillv.-värde pr år: 30,000 kr. — Firman etabl.\n\n192..8- . * „.\n\nÄgare o. chef: fabr. Änders G.\nAndersson.\n\n*A. H. Andersson &amp; C:o. AB.,\n\nLjung.\n\nArmaturfabrik och metallgjuteri i\nLjung (Älvsb. l.). Tillverkar gjutgods i\nsåväl tung- som lättmetall, lagermetaller *\noch syrafast gjutgods samt varmpressade\ndetaljer av mässing cxÄ aluiömium.\nSpecialitet: radiatorarmatur. -, -:\n\nTelegr.-adr. o. telefon: Ljungarmatur,\nLjung. Postgiro: 79600.\n\nAkt.-kap.: 150,000 kr. Antal\nindustriarb.: 120. Tillv.-värde pr år: 2,000,000 kr.\n\n—\tfirman etabl. 1875, bolag 1943. : :\n\nStyrelse: adv. G. Sundberg (ordf.), dir.\n\nG. Berntson, dir. Wilhelm Carlsson, herr\nO. E. Plomgren.\n\nVerkst. dir.: Göte Berntson.\n\nVerkstadschef: ing. R. Kordell.\n\n*AB. Carl Anderson, Motala.\n\nMöss- och pälsvarufabrik. Tillverkar\nmössor, dam- och barnhattar, pälsmössor,\npälsbaretter, pälskappor m. m. samt\nplyschkappor. Firman’ driver även\nen-groshandel med skinn; mösstillbehör,\nfilthattar, baskers m. m.\n\nTelegr.-adr.: Gam, Motala. Telefon: 6\no. 230. Postgiro: 28359.\n\nAkt-.-kap.: 150.000 kr. Antal\nindustriarb. : 87. Tillv.-väråe pr år:\tkr.\n\n—\tFirman etabl. 1872, bolag 1917,\nom-bildat 1930 och 1934.\n\nStyrelse: dir. Torgil Nilson (ordf.),\nadv. Arnold Andersson, bankdir. A. S.\nRingberg.\n\nVerkst. dir.: Torgil ifilsbn.\n\nCarl Anderssons Åkdonsfabrik,\n\nMora.\n\nTillverkar knivar samt arbetsåkdon vid\nfabrik i Mora (Kopparb. l.).\n\nTelefon: 42. Postgiro: 30026. — Antal\nindustriarb.: 25. — Firman etabl. 1890.\n\nÄgare: Carl Anderssons sterbhus.\n\nChef: Erik V. Andersson.\n\nC. A. AnderssonsMöbelfåbrik, *\n\nHogstad.\n\nTillverkar kompletteringsmöblér vid\nfabrik i Hogstad (österg-ötl. l.).\n\nTelefon: 58.–Antal industriarb.: 12.\n\nTillv.-värde pr år: 80,000 kr. — Firman\netabl. 1915.\n\nÄgare o. chef: fabr. C. Albert\nAndersson.\n\n*C. A, Andersson &amp; Co., Tryckeri\nAB., Malmö.\n\nSe Tryckeri AB. 0. A. Andersson å\nCo., Malmö.\n\nC. V. Anderssons Aluminium- &amp;\nMetallgjuteri AB., Södertälje.\n\nTillverkar gjutgods av\naluminiuml$ge-ringår och silumin.\n\nTelefon: 32186. Postgiro: 77863. —\nAkt.-kap,: 30,000 kr. Antal industriarb.:\n12. Tillv.-värde pr år: 200,000 kr. —\nFirman etabl. 1928, bolag 1945.\n\nVerkst. dir,: gjutmäst. Valfrid\nAndersson.\n\nAvd.-chef: gjutmäst. Evert Andersson.\n* David Andersson, Örkelljunga.\n\nSågverk och snickerifabrik i\nörkelljunga (Kristianst. l.). Tillverkar sågade\noch hyvlade trävaror samt\nbyggnadssnickerier.\n\nTelegr.-adr.: Dea, örkelljunga.\nTelefon: »Davidanders». Postgiro: 27557.\n\nAntal industriarb.: 15. Årstillv.: 1,500\nstds trävaror. — Firman, etabl. 1911,\näger Malmö Trävaru AB.\n\nÄgare o. chef: disp. Anders Davidson.\n\nKamrer: Frithiof Flodén.\n\nEdvin Anderssons Mössfabrik,\n\nHässleholm.\n\nTillverkar alla slag av mössor vid\nfabrik i Hässleholm (Kristianst. l.).\nFirman driver även engroshandel med\nherr-hattar\n\nTelefon: 778. Postgiro: 134161. —\nAntal industriarb.: 20. Tillv.-värde pr år:\n100,000 kr. — Firman etabl. 1902.\n\nÄgare o. chef: fabr. Edvin Andersson.\n\nEinar Anderssons Mek. Verkstad,\n\nÖrnsköldsvik.\n\nTillverkar hydrauliska biltippar och\nbillastkranar (märke: »ETE»).\n\nTelefon: 1380. Postgirq: 63672. — An-",
    "structured": {
        "1": {
            "name": "A. C. Anderssons Snickerifabrik",
            "location": "Valåse",
            "business": "Manufacturing of doors, windows, kitchen fittings, stairs, and drawers",
            "products": "Doors, windows, kitchen fittings, stairs, drawers",
            "contact": {
                "office": "Valåsen (Örebro L)",
                "phone": [
                    "Karlskoga 28170"
                ],
                "postgiro": "139541",
                "head_office": "Valåsen",
                "telegraph": "",
                "factory_office": "",
                "factory_phone": ""
            },
            "financials": {
                "capital": "",
                "employees": {
                    "industrial": 2
                },
                "annual_turnover": "30,000 kr"
            },
            "foundation_year": 1928,
            "current_name_year": null,
            "predecessor": null,
            "original_name": null,
            "corporation_year": null,
            "board": [],
            "owners": [],
            "director": "Anders G. Andersson",
            "managing_director": "",
            "sales_manager": "",
            "manager": "Anders G. Andersson"
        },
        "2": {
            "name": "A. H. Andersson & C:o. AB.",
            "location": "Ljung",
            "business": "Manufacturing of castings in heavy and light metals and brass and aluminum castings",
            "products": "Castings in heavy and light metals, brass and aluminum, radiator fittings",
            "contact": {
                "office": "Ljung (Älvsb. l.)",
                "phone": [
                    "Ljungarmatur"
                ],
                "postgiro": "79600",
                "head_office": "",
                "telegraph": "Ljungarmatur",
                "factory_office": "",
                "factory_phone": ""
            },
            "financials": {
                "capital": "150,000 kr",
                "employees": {
                    "industrial": 120
                },
                "annual_turnover": "2,000,000 kr"
            },
            "foundation_year": 1875,
            "current_name_year": 1943,
            "predecessor": null,
            "original_name": null,
            "corporation_year": null,
            "board": [
                {
                    "name": "adv. G. Sundberg",
                    "role": "ordf."
                },
                {
                    "name": "dir. G. Berntson",
                    "role": ""
                },
                {
                    "name": "dir. Wilhelm Carlsson",
                    "role": ""
                },
                {
                    "name": "herr O. E. Plomgren",
                    "role": ""
                }
            ],
            "owners": [],
            "director": "",
            "managing_director": "Göte Berntson",
            "sales_manager": "",
            "manager": ""
        },
        "3": {
            "name": "AB. Carl Anderson",
            "location": "Motala",
            "business": "Manufacturing of hats, fur products, and wholesale trading of skins and fur accessories",
            "products": "Hats, fur hats, fur caps, fur coats, fur accessories, skins",
            "contact": {
                "office": "Motala",
                "phone": [
                    "6",
                    "230"
                ],
                "postgiro": "28359",
                "head_office": "",
                "telegraph": "Gam",
                "factory_office": "",
                "factory_phone": ""
            },
            "financials": {
                "capital": "150,000 kr",
                "employees": {
                    "industrial": 87
                },
                "annual_turnover": "kr"
            },
            "foundation_year": 1872,
            "current_name_year": 1934,
            "predecessor": null,
            "original_name": null,
            "corporation_year": null,
            "board": [
                {
                    "name": "dir. Torgil Nilson",
                    "role": "ordf."
                },
                {
                    "name": "adv. Arnold Andersson",
                    "role": ""
                },
                {
                    "name": "bankdir. A. S. Ringberg",
                    "role": ""
                }
            ],
            "owners": [],
            "director": "",
            "managing_director": "Torgil ifilsbn",
            "sales_manager": "",
            "manager": ""
        },
        "4": {
            "name": "Carl Anderssons Åkdonsfabrik",
            "location": "Mora",
            "business": "Manufacturing of knives and work implements",
            "products": "Knives, work implements",
            "contact": {
                "office": "Mora (Kopparb. l.)",
                "phone": [
                    "42"
                ],
                "postgiro": "30026",
                "head_office": "",
                "telegraph": "",
                "factory_office": "",
                "factory_phone": ""
            },
            "financials": {
                "capital": "",
                "employees": {
                    "industrial": 25
                },
                "annual_turnover": "kr"
            },
            "foundation_year": 1890,
            "current_name_year": null,
            "predecessor": null,
            "original_name": null,
            "corporation_year": null,
            "board": [],
            "owners": [],
            "director": "",
            "managing_director": "",
            "sales_manager": "",
            "manager": "Erik V. Andersson"
        },
        "5": {
            "name": "C. A. Anderssons Möbelfåbrik",
            "location": "Hogstad",
            "business": "Manufacturing of complementary furniture",
            "products": "Complementary furniture",
            "contact": {
                "office": "Hogstad (österg-ötl. l.)",
                "phone": [
                    "58"
                ],
                "postgiro": "",
                "head_office": "",
                "telegraph": "",
                "factory_office": "",
                "factory_phone": ""
            },
            "financials": {
                "capital": "",
                "employees": {
                    "industrial": 12
                },
                "annual_turnover": "80,000 kr"
            },
            "foundation_year": 1915,
            "current_name_year": null,
            "predecessor": null,
            "original_name": null,
            "corporation_year": null,
            "board": [],
            "owners": [],
            "director": "",
            "managing_director": "",
            "sales_manager": "",
            "manager": "C. Albert Andersson"
        },
        "6": {
            "name": "C. V. Anderssons Aluminium- & Metallgjuteri AB.",
            "location": "Södertälje",
            "business": "Manufacturing of aluminum castings, steel, and silumin",
            "products": "Aluminium castings, steel, silumin",
            "contact": {
                "office": "Södertälje",
                "phone": [
                    "32186"
                ],
                "postgiro": "77863",
                "head_office": "",
                "telegraph": "",
                "factory_office": "",
                "factory_phone": ""
            },
            "financials": {
                "capital": "30,000 kr",
                "employees": {
                    "industrial": 12
                },
                "annual_turnover": "200,000 kr"
            },
            "foundation_year": 1928,
            "current_name_year": 1945,
            "predecessor": null,
            "original_name": null,
            "corporation_year": null,
            "board": [],
            "owners": [],
            "director": "",
            "managing_director": "",
            "sales_manager": "",
            "manager": ""
        },
        "7": {
            "name": "David Andersson",
            "location": "Örkelljunga",
            "business": "Sawmill and carpentry factory",
            "products": "Sawed and planed timber, carpentry",
            "contact": {
                "office": "Örkelljunga (Kristianst. l.)",
                "phone": [
                    "Davidanders"
                ],
                "postgiro": "27557",
                "head_office": "",
                "telegraph": "Dea",
                "factory_office": "",
                "factory_phone": ""
            },
            "financials": {
                "capital": "",
                "employees": {
                    "industrial": 15
                },
                "annual_turnover": "1,500 stds trävaror"
            },
            "foundation_year": 1911,
            "current_name_year": null,
            "predecessor": "Malmö Trävaru AB",
            "original_name": null,
            "corporation_year": null,
            "board": [],
            "owners": [],
            "director": "",
            "managing_director": "",
            "sales_manager": "",
            "manager": "Anders Davidson"
        },
        "8": {
            "name": "Edvin Anderssons Mössfabrik",
            "location": "Hässleholm",
            "business": "Manufacturing of all types of hats and wholesale of men's hats",
            "products": "All types of hats, men's hats",
            "contact": {
                "office": "Hässleholm (Kristianst. l.)",
                "phone": [
                    "778"
                ],
                "postgiro": "134161",
                "head_office": "",
                "telegraph": "",
                "factory_office": "",
                "factory_phone": ""
            },
            "financials": {
                "capital": "",
                "employees": {
                    "industrial": 20
                },
                "annual_turnover": "100,000 kr"
            },
            "foundation_year": 1902,
            "current_name_year": null,
            "predecessor": null,
            "original_name": null,
            "corporation_year": null,
            "board": [],
            "owners": [],
            "director": "",
            "managing_director": "",
            "sales_manager": "",
            "manager": "Edvin Andersson"
        },
        "9": {
            "name": "Einar Anderssons Mek. Verkstad",
            "location": "Örnsköldsvik",
            "business": "Manufacturing of hydraulic truck tipper and crane (brand: ETE)",
            "products": "Hydraulic truck tipper, truck crane (brand: ETE)",
            "contact": {
                "office": "Örnsköldsvik",
                "phone": [
                    "1380"
                ],
                "postgiro": "63672",
                "head_office": "",
                "telegraph": "",
                "factory_office": "",
                "factory_phone": ""
            },
            "financials": {
                "capital": "",
                "employees": {},
                "annual_turnover": ""
            },
            "foundation_year": null,
            "current_name_year": null,
            "predecessor": null,
            "original_name": null,
            "corporation_year": null,
            "board": [],
            "owners": [],
            "director": "",
            "managing_director": "",
            "sales_manager": "",
            "manager": ""
        }
    }
}