{
    "original": "Johansfors—Johansson\n\nTelegr.-adr.: Bryggeriet, Johannisberg.\nTelefon: »Bryggeriet». Postgiro: 283830.\n\n—\tAkt.-kap.: 60,0000 kr. Arb.-antal: 7.\nTillv.-värde pr år: 250,000 kr. — Bolaget\ngrundat 1906.\n\nStyrelse: disp. Richard Wallerstedt\n(ordf.), bryggmäst. Carl-Erik Flygt, fru\nI. Wilson.\n\nDisp.: Rune Wilson.\n\n\"AB. Johansfors Glasbruk, Broakulla.\n\nGlasbruk med sliperi, gravör- och\nets-verkstäder samt glasmåleri i Johansfors,\nBroakulla (Kronob. l.). Tillverkar\nkristall-, hushålls- och prydnadsglas.\n\nTelegr.-adr.: Johansfors, Karlskrona.\nTelefon: Broakulla 47. Postgiro: 87800.\n\nAkt.-kap.: 120,000 kr. Antal\nindustriarb.: 140. Tillv.-värde pr år: 950,000 kr.\n\n—\tFirman grundad 1891, bolag 1913.\nStyrelse: dir. Johan E. Rundqvist\n\n(ordf.), fru Inga Lövgren, fru Emy\nSchmidt, kantor Sixten Wennerstrand.\nVerkst. dir.: J. E. Rundqvist.\n\n\"Johansson &amp; Co-, Bröderna,\n\nSmålandsstenar.\n\nSe Bröderna Johansson &amp; Co.,\nSmålandsstenar.\n\n\"AB. Johansson &amp; Ljunggren, Nässjö.\n\nMöbelfabrik och tapetserareverkstad.\nTillverkar fåtöljer och stommar därtill.\nTelefon: 819 o. 564. Postgiro: 141266.\n\n—\tAkt.-kap.: 50,000 kr. Antal\nindustriarb.: 80. Tillv.-värde pr år: 950,000 kr.\n\n—\tFirman etabl. 1932, bolag 1944.\nStyrelse o. verkst. dir.: fabr. Valter\n\nLjunggren.\n\n\"Johansson &amp; Söner, Falkenberg.\n\nSe Skofabriken Johansson &amp; Söner,\nFalkenberg.\n\nJohanssons Möbelindustri, Landsbro.\n\nSe Bröderna Johanssons Möbelindustri,\nLandsbro.\n\nJohanssons Skofabrik, Bröderna,\n\njKumla.\n\nSe Bröderna Johanssons Skofabrik,\nKumla.\n\n\"Johanssons Snickerifabrik,\nBröderna, Osby.\n\nSe Bröderna Johanssons Snickerifabrik,\nOsby.\n\n\"Johanssons Stol- &amp; Möbelfabrik,\nAB. Bröderna, Virserum.\n\nSe AB. Bröderna Johanssons Stol- &amp;\nMöbelfabrik, Virserum.\n\n\"AB. A. Johanssons Radiofabrik,\n\nSundbyberg.\n\nTillverkar vridkondensatorer,\nomkopplare, strömbrytare för radioapparater,\npotentiometrar och trimmerkondensatorer.\n\nTelegr.-adr.: Johnrad, Stockholm.\nTelefon: 280440. Postgiro: 51479.\n\nAkt.-kap.: 60,000 kr. Antal\nindustriarb.: 90. Tillv.-värde pr år: 700,000 kr.\n— Firman etabl. 1923, bolag 1932.\n\nStyrelse o. verkst. dir.: Amandus\nJohansson.\n\n\"Algot Johansson AB., Borås.\n\nKonfektionsfabrik. Tillverkar\nsport-och fritidskläder, arbets- och skyddskläder\nsamt barnkläder. Varunamn: »Algots».\n\nTelegr.-adr. o. telefon: »Algots», Borås.\nPostgiro: 10438.\n\nAkt.-kap.: 4,000,000 kr. Antal\nindustriarb..- 800. Tillv.-värde pr år: 20,000,000\nkr. — Firman etabl. 1907, bolag 1937.\n\nStyrelse: dir. Algot Johansson (ordf.),\nkamrer Arne M. Johansson, godsäg. Elis\nJohansson, disp. Göte Johansson, disp.\nÅke Johansson.\n\nVerkst. dir.: Algot Johansson.\n\nAB. Axel Johanssons Mek. Verkstad,\n\nVästerås.\n\nMek. verkstad i Västerås samt\ntackjärnsgjuter i i Tillberga (Västmanl. l.).\nUtför elektr. svetsninsr. samt tillverkar\ngrövre maskingods, snöslungor och\nbock–maskiner\n\nTelefon: 30225. Postgiro: 70268. —\nAkt.-kap.: 40,000 kr. Antal industriarb.:\n25. Tillv.-värde pr år: 350,000 kr. —\nFirman etabl. 1898, bolag 1937.\n\nVerkst. dir.: ing* David Sjölander.\n\n\"AB. Axel Johanssons\nMöbleringsaffär, Falun.\n\nSnickerifabrik. Tillverkar möbler samt\nbutiks- och bankinredningar. Bolaget\ndriver jämväl detaljhandel med möbler och\ngardiner m. m.\n\nTelefon: 207, 2007 o. 3008. Postgiro:\n21191.\n\nAkt.-kap.: 76,000 kr. Antal industri-",
    "structured": {
        "1": {
            "name": "Johansfors",
            "location": "Johannisberg",
            "contact": {
                "telegraph": "Bryggeriet, Johannisberg",
                "phone": [
                    "Bryggeriet"
                ],
                "postgiro": "283830"
            },
            "financials": {
                "capital": "60,0000 kr",
                "employees": {
                    "total": 7
                },
                "annual_turnover": "250,000 kr"
            },
            "foundation_year": 1906,
            "board": [
                {
                    "name": "Richard Wallerstedt",
                    "role": "disp."
                },
                {
                    "name": "Carl-Erik Flygt",
                    "role": "bryggmäst."
                },
                {
                    "name": "fru I. Wilson"
                }
            ]
        },
        "2": {
            "name": "AB. Johansfors Glasbruk",
            "location": "Broakulla",
            "products": "kristall-, hushålls- och prydnadsglas",
            "contact": {
                "telegraph": "Johansfors, Karlskrona",
                "phone": "Broakulla 47",
                "postgiro": "87800"
            },
            "financials": {
                "capital": "120,000 kr",
                "employees": {
                    "total": 140
                },
                "annual_turnover": "950,000 kr"
            },
            "foundation_year": 1891,
            "corporation_year": 1913,
            "board": [
                {
                    "name": "Johan E. Rundqvist",
                    "role": "dir."
                },
                {
                    "name": "fru Inga Lövgren"
                },
                {
                    "name": "fru Emy Schmidt"
                },
                {
                    "name": "kantor Sixten Wennerstrand"
                }
            ],
            "director": "J. E. Rundqvist"
        },
        "3": {
            "name": "AB. Johansson & Ljunggren",
            "location": "Nässjö",
            "business": "Möbelfabrik och tapetserareverkstad",
            "products": "fåtöljer och stommar därtill",
            "contact": {
                "phone": [
                    "819",
                    "564"
                ],
                "postgiro": "141266"
            },
            "financials": {
                "capital": "50,000 kr",
                "employees": {
                    "total": 80
                },
                "annual_turnover": "950,000 kr"
            },
            "foundation_year": 1932,
            "corporation_year": 1944,
            "managing_director": "fabr. Valter Ljunggren"
        },
        "4": {
            "name": "AB. A. Johanssons Radiofabrik",
            "location": "Sundbyberg",
            "products": "vridkondensatorer, omkopplare, strömbrytare för radioapparater, potentiometrar och trimmerkondensatorer",
            "contact": {
                "telegraph": "Johnrad, Stockholm",
                "phone": "280440",
                "postgiro": "51479"
            },
            "financials": {
                "capital": "60,000 kr",
                "employees": {
                    "total": 90
                },
                "annual_turnover": "700,000 kr"
            },
            "foundation_year": 1923,
            "corporation_year": 1932,
            "director": "Amandus Johansson"
        },
        "5": {
            "name": "Algot Johansson AB.",
            "location": "Borås",
            "business": "Konfektionsfabrik",
            "products": "sport-och fritidskläder, arbets- och skyddskläder samt barnkläder",
            "contact": {
                "telegraph": "Algots, Borås",
                "phone": "Algots",
                "postgiro": "10438"
            },
            "financials": {
                "capital": "4,000,000 kr",
                "employees": {
                    "total": 800
                },
                "annual_turnover": "20,000,000 kr"
            },
            "foundation_year": 1907,
            "corporation_year": 1937,
            "board": [
                {
                    "name": "Algot Johansson",
                    "role": "dir."
                },
                {
                    "name": "kamrer Arne M. Johansson"
                },
                {
                    "name": "godsäg. Elis Johansson"
                },
                {
                    "name": "disp. Göte Johansson"
                },
                {
                    "name": "disp. Åke Johansson"
                }
            ],
            "managing_director": "Algot Johansson"
        },
        "6": {
            "name": "AB. Axel Johanssons Mek. Verkstad",
            "location": "Västerås",
            "business": "Mek. verkstad",
            "products": "elektr. svetsninsr., grövre maskingods, snöslungor och bock–maskiner",
            "contact": {
                "phone": "30225",
                "postgiro": "70268"
            },
            "financials": {
                "capital": "40,000 kr",
                "employees": {
                    "total": 25
                },
                "annual_turnover": "350,000 kr"
            },
            "foundation_year": 1898,
            "corporation_year": 1937,
            "director": "ing* David Sjölander"
        },
        "7": {
            "name": "AB. Axel Johanssons Möbleringsaffär",
            "location": "Falun",
            "business": "Snickerifabrik",
            "products": "möbler, butiks- och bankinredningar",
            "contact": {
                "phone": [
                    "207",
                    "2007",
                    "3008"
                ],
                "postgiro": "21191"
            },
            "financials": {
                "capital": "76,000 kr"
            }
        }
    }
}