{
    "original": "J ohansson\n\nTelefon: 389, 1772 o. 907. Postgiro:\n26525..— Akt.-kap.: 150,000 kr. Antal\nindustriarb.: 68. — Firman, etabl. 1847,\nbolag 1908, äger Ronneby-Postens\nTryckeri AB.\n\nStyrelse: dir. Folke E. Bengtsson\n(ordf.), boktr. Sven Ivar Bengtsson (v.\nordf.), fröken B. Johansson.\n\nVerkst. dir.: Folke E. Bengtsson.\n\nTrycheriförest.: S. I. Bengtsson.\n\nKontorschef: fröken G. Karlsson.\n\nE. M. Johansson &amp; Co., Tranemo.\n\nTrikåfabrik i Tranemo (Älvsb. l.).\nTillverkar stickade yllevaror.\n\nKontor: Tranemo. Telefon: Svenljunga\n70083. Postgiro^ 8241.\n\nAntal industriarb.: 9 samt 30\nhemarbetare. Tillv.-värde pr år: 200,000 kr.\n— Firman etabl. 1922.\n\nÄgare o. chefer: disp. Enoch M.\nJohansson o. lagerchef Ernst Tranefors.\n\nGust. Johansson, Moholm.\n\nSe Gust. Fimmerstad, Moholm.\n\n* Gustaf Johanssons Möbelfabrik,\n\nSkillingaryd.\n\nTillverkar möbler vid, fabrik i\nSkillingaryd (Jönköp. l.). Specialitet:\nSängkammarmöbler.\n\nTelefon: 2. Postgiro: 176011. —-\nArb.-antal: 8. Tillv.-värde pr år: 40,000 kr. —\nFirman etabl. 1908.\n\nÄgare o. chef: Gustaf Johansson.\n\n*H. Johanssons Möbel verkstäder,\n\nVislanda.\n\nTillverkar möbler samt träarmatur vid\nfabrik i Vislanda (Kronob. l.).\n\nTelefon: 139. Postgiro: 168095. —\nAntal industriarb.: 12. Tillv.-värde pr år:\n90,000 kr. — Firman etabl. 1939.\n\nÄgare o. chef: fabr. Harry Johansson.\n\nHj. Johanssons Barncykelfabrik,\n\nAnderstorp.\n\nMek. verkstad i Anderstorp (Jönköp. l.).\nTillverkar barncyklar samt svetsade och\npressade massartiklar av plåt.\n\nTelefon: 28. Postgiro: 163395. — Antal\nindustriarb.: 16. — Firman etabl. 1914.\n\nÄgare o. chef: fabr. Hjalmar Johansson.\n\nAB. I. A. Johansson, Flisby.\n\nTillverkar trätofflor, trätoffelbottnar\nsamt träbottensandaler vid fabrik i Flisby\n(Jönköp. l.).\n\nTelefon: 1. Postgiro: 5405. —\nAkt.-kap.: 86,000 kr. Antal industriarb.: 18.\nTillv.-värde pr år: 300,000 kr. — Firman\netabl. 1879, bolag 1932.\nDisp.: Efr. Odengren.\n\n*J. Johanssons Träförädlingsfabrik,\n\nÅstorp.\n\nSe Ji-Te AB., Åstorp.\n\n*Leonard Johanssons Fabriks AB.,\n\nEskilstuna.\n\nJärnmanufakturfabrik. Tillverkar\nma-manufaktursmide såsom sågbågar\n(bågså-gar), elektriska strykjärn,\nspiraldörr-stängare, spisringsställ, lieringar och\npressade velocipeddelar; utför slipning,\nförnickling och förkromning.\n\nTelegr.-adr.: Leonard jo. Eskilstuna.\nTelefon: 30480 o. 34480. Postgiro: 10787.\n\n—\tAkt.-kap.: 50,000 kr. Tillv.-värde pr\når: 300,000 kr. — Firman etabl. 1892,\nbolag 1908.\n\nStyrelse: disp. Nils L. Johansson\n(ordf.), kontorschef Sven Eriksson, ing.\nOlov Johansson.\n\nVerkst. dir. o. disp.: Nils L. Johansson.\n\n*N. J. Johanssons Eftr. AB.,\n\nAplared.\n\nKonfektionsfabrik i Aplared (Älvsb. l.).\nTillverkar arbetskläder och sportkläder.\nSpecialiteter: overalls och skyddskläder.\nVarumärke: »Joflo».\n\nTelegr.-adr.: Joflo, Borås. Telefon:\nBorås 80001, 80002. Postgiro: 33040.\n\nAkt.-kap.: 175,000 kr. Antal\nindustriarb.: 90. Tillv.-värde pr år: 2,400,000 kr.\n\n—\tFirman etabl. 1875, bolag 1919.\nStyrelse: disp. John^ N. Johanson\n\n(ordf.), kontorschef Daniel J:son Apler,\ndisp. O. Flodin.\n\nDisponenter: John N. Johanson o. O.\nFlodin.\n\nOskar Johansons Slakteri AB.,\n\nNorrköping.\n\nCharkuteri- och konservfabrik.\nTillverkar charkuterivaror och konserver.\nVarumärke: »O. J:s».\n\nTelegr.-adr.: Ojohansons, Norrköping.\nTelefon: »Oskar Johansons». Postgiro:\n10024. — Akt.-kap.: 250,000 kr. Antal\nindustriarb.: 50. — Firman etabl. 1857,\nbolag 1914.\n\nStyrelse o. chefer: disp. Axel\nJohansson, fabr. Erik W. Johanson, dir. James\n\nJohanson.\n**",
    "structured": {
        "firms": [
            {
                "name": "E. M. Johansson & Co.",
                "location": "Tranemo",
                "business": "Trikåfabrik",
                "products": "Tillverkar stickade yllevaror.",
                "contact": {
                    "office": "Tranemo",
                    "phone": [
                        "70083"
                    ],
                    "postgiro": "8241"
                },
                "financials": {
                    "capital": "150,000 kr",
                    "employees": {
                        "industriarb": 9,
                        "hemarbetare": 30
                    },
                    "annual_production_value": "200,000 kr"
                },
                "foundation_year": 1922,
                "owners": [
                    "Enoch M. Johansson",
                    "Ernst Tranefors"
                ]
            },
            {
                "name": "Gustaf Johanssons Möbelfabrik",
                "location": "Skillingaryd",
                "business": "Tillverkar möbler",
                "products": "Specialitet: Sängkammarmöbler.",
                "contact": {
                    "office": "Skillingaryd",
                    "phone": [
                        "2"
                    ],
                    "postgiro": "176011"
                },
                "financials": {
                    "annual_production_value": "40,000 kr"
                },
                "foundation_year": 1908,
                "manager": "Gustaf Johansson"
            },
            {
                "name": "H. Johanssons Möbel verkstäder",
                "location": "Vislanda",
                "business": "Tillverkar möbler",
                "products": "Samt träarmatur",
                "contact": {
                    "office": "Vislanda",
                    "phone": [
                        "139"
                    ],
                    "postgiro": "168095"
                },
                "financials": {
                    "annual_production_value": "90,000 kr"
                },
                "foundation_year": 1939,
                "manager": "Harry Johansson"
            },
            {
                "name": "Hj. Johanssons Barncykelfabrik",
                "location": "Anderstorp",
                "business": "Mek. verkstad",
                "products": "Tillverkar barncyklar samt svetsade och pressade massartiklar av plåt.",
                "contact": {
                    "office": "Anderstorp",
                    "phone": [
                        "28"
                    ],
                    "postgiro": "163395"
                },
                "financials": {
                    "annual_production_value": "Not available"
                },
                "foundation_year": 1914,
                "manager": "Hjalmar Johansson"
            },
            {
                "name": "AB. I. A. Johansson",
                "location": "Flisby",
                "business": "Tillverkar trätofflor",
                "products": "Trätoffelbottnar samt träbottensandaler.",
                "contact": {
                    "office": "Flisby",
                    "phone": [
                        "1"
                    ],
                    "postgiro": "5405"
                },
                "financials": {
                    "capital": "86,000 kr",
                    "employees": {
                        "industriarb": 18
                    },
                    "annual_production_value": "300,000 kr"
                },
                "foundation_year": 1879,
                "directors": [
                    "Efr. Odengren"
                ]
            },
            {
                "name": "Leonard Johanssons Fabriks AB.",
                "location": "Eskilstuna",
                "business": "Järnmanufakturfabrik",
                "products": "Tillverkar ma-manufaktursmide såsom sågbågar, elektriska strykjärn, spiraldörrstängare, spisringsställ, lieringar och pressade velocipeddelar; utför slipning, förnickling och förkromning.",
                "contact": {
                    "telegraph": "Leonard jo. Eskilstuna",
                    "phone": [
                        "30480",
                        "34480"
                    ],
                    "postgiro": "10787"
                },
                "financials": {
                    "capital": "50,000 kr",
                    "annual_production_value": "300,000 kr"
                },
                "foundation_year": 1892,
                "owner": "Nils L. Johansson",
                "directors": [
                    {
                        "name": "Nils L. Johansson",
                        "role": "Verkst. dir. o. disp."
                    }
                ]
            },
            {
                "name": "N. J. Johanssons Eftr. AB.",
                "location": "Aplared",
                "business": "Konfektionsfabrik",
                "products": "Tillverkar arbetskläder och sportkläder. Specialiteter: overalls och skyddskläder. Varumärke: Joflo.",
                "contact": {
                    "telegraph": "Joflo, Borås",
                    "phone": [
                        "80001",
                        "80002"
                    ],
                    "postgiro": "33040"
                },
                "financials": {
                    "capital": "175,000 kr",
                    "employees": {
                        "industriarb": 90
                    },
                    "annual_production_value": "2,400,000 kr"
                },
                "foundation_year": 1875,
                "owner": "John N. Johanson",
                "directors": [
                    "John N. Johanson",
                    "O. Flodin"
                ]
            },
            {
                "name": "Oskar Johansons Slakteri AB.",
                "location": "Norrköping",
                "business": "Charkuteri- och konservfabrik",
                "products": "Tillverkar charkuterivaror och konserver. Varumärke: O. J:s.",
                "contact": {
                    "telegraph": "Ojohansons, Norrköping",
                    "phone": [
                        "Oskar Johansons"
                    ],
                    "postgiro": "10024"
                },
                "financials": {
                    "capital": "250,000 kr",
                    "employees": {
                        "industriarb": 50
                    },
                    "annual_production_value": "Not available"
                },
                "foundation_year": 1857,
                "directors": [
                    "Axel Johansson",
                    "Erik W. Johanson",
                    "James Johanson"
                ]
            }
        ]
    }
}