{
    "original": "Eskilstuna\n\nEskilstuna Armatur &amp; Metall, W.\nStåhlberg, Eskilstuna.\n\nGjuteri och mek. verkstad i Eskilstuna\n(Södermanl. l.). Tillverkar\nbelysningsarmatur såsom golvstakar, taklampor,\nbor4§lampor, lampskärmar och\nlampskärmsställningar m. m. samt borrsväpgar\noch lättmetallartiklar såsom vattenpass\nm. m.\n\nTelefon: 37190. Postgiro: 291549. —\nAntal industriarb.: 120. Tillv.-värde pr\når: 1,500,000 kr. — Firman etabl. 1946.\n\nÄgare o. chef: dir. White Ståhlberg.\n\n\"Eskilstuna Borr- och Verktygs AB.,\n\nEskilstuna.\n\nMek. verkstad. Tillverkar verktyg för\nmetallbearbetning såsom spiralborrar,\nbrotschar, fräsar m. m. Varumärke:\n»B &amp; V».\n\nTelegr.-adr.: Borrverktyg, Eskilstuna.\nTelefon: 37440. Postgiro: 30064. —\nAkt.-kap.: 700,000 kr. Antal industriarb.: 150.\nTillv.-värde pr. år: 2,000,000 kr, &gt;\n\nFirman bildad 1924 genom\nsammanslutning av Munktells verktygsavd. och\nAB. Eskilstuna Verktygsfabrik, grundad\n1917.\n\nStyrelse: kapten Peter Schollin-Borg\n(ordf.), dir. E. Benson, löjtn. A.\nGyllen-berg, disp. Arvid H. Nilsson, med. lic.\nI. Ryott-Iohnson, bergsing. Allan\nSchollin-Borg, civiling. Gunnar Schollin-Borg,\nstiftsjägm. E. Wesström, kapten Jan-Erik\nÅlund.\n\nVerkst. dir.: A. Schollin-Borg.\n\n\"Eskilstuna Bryggeri AB.,\n\nEskilstuna.\n\nTillverkar malt- och läskedrycker.\n\nTelegr.-adr. o. telefon: Bryggeribolaget,\nEskilstuna. Postgiro: 140170.\n\nAkt.-kap.: 1,512,000 kr. Antal\nindustriarb.: 80. — Tillv.-värde pr år: 2,500,000\nkr. — Bolaget grundat 1875.\n\nStyrelse: disp. Gösta SverdruT) (ordf),\ndisp. Tage Bendz, dir. Rudolf DomellÖf,\nbergsing. Rich. Hellgren, bankdir. Eric\nTofte.\n\nVerkst. dir. o. disp.: Gösta Sverdrup.\n\"Eskilstuna Fabriks AB., Eskilstuna.\n\nMek. verkstad. Tillverkar svarta och\nblanka bultartiklar av alla slag,\ntransmissionskedjor såsom rull-, galls- och\nsmörjkedjor m. m., »Fenesträ»\nStålfönster, dörrar, mellanväggar m. m., fasader,\nfönster och dörrar m. m. av anodiserat\naluminium.\n\nTelegr.-adr.: Fabriksbolaget,\nEskilstuna. Telefon: 37410. Postgiro: 7770.\n\nEnsamförsäljare för Sverige: av\nbultartiklar: Söderberg &amp; Haatk AB.,\nStockholm, Drottningg. 2, telefon: »Söderberg\n&amp; Haak»; av kedjor: Tornborg &amp;\nLundberg AB., Årstadalshamnen,\nLiljeholmen, Stockholm 9, telefon: »Tornborg &amp;\nLundberg».\n\nAkt.-kap.: 1,000,000 kr. Antal\nindustriarb.: 150. Tillv.-värde pr år: 2,750,000 kr.\n— Bolaget grundat 1908.\n\nStyrelse: dir. Bengt Ingeström (ordf.),\ndisp. Hans v. Kantzow, disp. Gust.\nKihl-gren, generalkonsul Ragnar Söderberg.\n\nVerkst. dir. o. disp.: Gust. Kihlgren.\n\nKontorschef : Knut Dahlin.\n\nFörsäljn.-chef: R. Scharf.\n\n\"Eskilstuna Cjuteri AB., Eskilstuna.\n\nTillverkar gjutgods upp till 3 tons vikt.\n\nTelefon: 31049. Postgiro: 10792. —\nAkt.-kap.: 150,000 kr. Antal industriarb.:\n20. Tillv.-värde pr år: 230,000 kr. —\nFirman etabl. 1911.\n\nStyrelse: fabr. Hugo Andersson (ordf.),\ngjutmäst. Elon Andersson, ing. Sven\nRåby.\n\nVerkst. dir.: Hugo Andersson.\n\n\"Eskilstuna Jernmanufaktur AB.,\n\nEskilstuna.\n\nJärn- och, stålmanufakturfabrik,\ntack-järnsgjuteri samt elektr.\nvattenkraftstation vid Tunafors (Södermanl. l.).\n\nTillverkar hushållsknivar och\nhushållsgafflar, slaktknivar, kockknivar,\nyrkesknivar, rakhyvelbladet »Anchor», saxar,\nhydrauliska dörrstängaren »Anchor»,\nautomatiska branddörrstängare,\nfingjut-gods, Snickeriverktyg, spärrskruvmejslar,\nskruvnycklar samt skridskor. Varumärke:\nankare med »E» och krona.\n\nHuvudkontor: Eskilstuna. Telegr.-adr.\no. telefon: »Jernbolaget», Eskilstuna.\nPostgiro: 10716. Avd.-kontor o, lager:\nStockholm, Klara N. Kyrkog. 17,\ntelefon: 232440; Göteborg: ö. Hamng. .13,\ntelefon: 114214—16; Malmö: Rosengren\n&amp; Riis AB., Söderg, 24, telefon: 71130.\n\nAkt.-kap.: 2,000,000 kr. Antal\nindustriarb.: 700. Tillv.-värde pr år: 4,720,000 kr.\n\nBolaget, grundat 1868, har i sig\nupptagit B. &amp; O. Libergs Fabriks AB.\n\nStyrelse: överste Ch. Holmgren (ordf.),\nbankdir. L. O. Hessner, dir. Erik\nNygren, järnhandl. Nils Ohlsson, dir. Arvid\nReuterskiöld.\n\nVerkst. dir.: Arvid Reuterskiöld.\n\növering.: Tage Follin.",
    "structured": {
        "1": {
            "name": "Eskilstuna Armatur & Metall, W. Ståhlberg",
            "location": "Eskilstuna",
            "business": "Gjuteri och mek. verkstad",
            "products": "Tillverkar belysningsarmatur såsom golvstakar, taklampor, borrlampor, lampskärmar och lampskärmsställningar m. m. samt borrsväpgar och lättmetallartiklar såsom vattenpass m. m.",
            "contact": {
                "office": "Ståhlberg, Eskilstuna",
                "phone": [
                    "37190"
                ],
                "postgiro": "291549",
                "head_office": "Eskilstuna",
                "telegraph": "Not available",
                "factory_office": "Not available",
                "factory_phone": "Not available"
            },
            "financials": {
                "capital": "Not available",
                "employees": {
                    "industriarb": 120
                },
                "annual_turnover": "1,500,000 kr",
                "annual_production_value": "Not available"
            },
            "foundation_year": 1946,
            "current_name_year": "Not available",
            "predecessor": "Not available",
            "original_name": "Not available",
            "corporation_year": "Not available",
            "board": [
                {
                    "name": "dir. White Ståhlberg",
                    "role": "Ägare o. chef"
                }
            ],
            "owners": "Not available",
            "director": "Not available",
            "managing_director": "Not available",
            "sales_manager": "Not available",
            "manager": "Not available"
        },
        "2": {
            "name": "Eskilstuna Borr- och Verktygs AB.",
            "location": "Eskilstuna",
            "business": "Mek. verkstad",
            "products": "Tillverkar verktyg för metallbearbetning",
            "contact": {
                "office": "Eskilstuna",
                "phone": [
                    "37440"
                ],
                "postgiro": "30064",
                "head_office": "Not available",
                "telegraph": "Borrverktyg, Eskilstuna",
                "factory_office": "Not available",
                "factory_phone": "Not available"
            },
            "financials": {
                "capital": "700,000 kr",
                "employees": {
                    "industriarb": 150
                },
                "annual_turnover": "2,000,000 kr",
                "annual_production_value": "Not available"
            },
            "foundation_year": 1924,
            "current_name_year": "Not available",
            "predecessor": "Munktells verktygsavd. and AB. Eskilstuna Verktygsfabrik",
            "original_name": "Not available",
            "corporation_year": "Not available",
            "board": [
                {
                    "name": "kapten Peter Schollin-Borg",
                    "role": "ordf."
                },
                {
                    "name": "dir. E. Benson",
                    "role": "Not available"
                },
                {
                    "name": "löjtn. A. Gyllen-berg",
                    "role": "Not available"
                },
                {
                    "name": "disp. Arvid H. Nilsson",
                    "role": "Not available"
                },
                {
                    "name": "med. lic. I. Ryott-Iohnson",
                    "role": "Not available"
                },
                {
                    "name": "bergings. Allan Schollin-Borg",
                    "role": "Not available"
                },
                {
                    "name": "civiling. Gunnar Schollin-Borg",
                    "role": "Not available"
                },
                {
                    "name": "stiftsjägm. E. Wesström",
                    "role": "Not available"
                },
                {
                    "name": "kapten Jan-Erik Ålund",
                    "role": "Not available"
                }
            ],
            "owners": "Not available",
            "director": "A. Schollin-Borg",
            "managing_director": "Not available",
            "sales_manager": "Not available",
            "manager": "Not available"
        },
        "3": {
            "name": "Eskilstuna Bryggeri AB.",
            "location": "Eskilstuna",
            "business": "Tillverkar malt- och läskedrycker",
            "products": "Not available",
            "contact": {
                "office": "Eskilstuna",
                "phone": [
                    "Not available"
                ],
                "postgiro": "140170",
                "head_office": "Not available",
                "telegraph": "Not available",
                "factory_office": "Not available",
                "factory_phone": "Not available"
            },
            "financials": {
                "capital": "1,512,000 kr",
                "employees": {
                    "industriarb": 80
                },
                "annual_turnover": "2,500,000 kr",
                "annual_production_value": "Not available"
            },
            "foundation_year": 1875,
            "current_name_year": "Not available",
            "predecessor": "Not available",
            "original_name": "Not available",
            "corporation_year": "Not available",
            "board": [
                {
                    "name": "disp. Gösta Sverdrup",
                    "role": "ordf"
                },
                {
                    "name": "disp. Tage Bendz",
                    "role": "Not available"
                },
                {
                    "name": "dir. Rudolf DomellÖf",
                    "role": "Not available"
                },
                {
                    "name": "bergsing. Rich. Hellgren",
                    "role": "Not available"
                },
                {
                    "name": "bankdir. Eric Tofte",
                    "role": "Not available"
                }
            ],
            "owners": "Not available",
            "director": "Gösta Sverdrup",
            "managing_director": "Gösta Sverdrup",
            "sales_manager": "Not available",
            "manager": "Not available"
        },
        "4": {
            "name": "Eskilstuna Fabriks AB.",
            "location": "Eskilstuna",
            "business": "Mek. verkstad",
            "products": "Tillverkar svarta och blanka bultartiklar av alla slag, transmissionskedjor såsom rull-, galls- och smörjkedjor m. m., »Fenesträ» Stålfönster, dörrar, mellanväggar m. m., fasader, fönster och dörrar m. m. av anodiserat aluminium.",
            "contact": {
                "office": "Eskilstuna",
                "phone": [
                    "37410"
                ],
                "postgiro": "7770",
                "head_office": "Eskilstuna",
                "telegraph": "Fabriksbolaget, Eskilstuna",
                "factory_office": "Not available",
                "factory_phone": "Not available"
            },
            "financials": {
                "capital": "1,000,000 kr",
                "employees": {
                    "industriarb": 150
                },
                "annual_turnover": "2,750,000 kr",
                "annual_production_value": "Not available"
            },
            "foundation_year": 1908,
            "current_name_year": "Not available",
            "predecessor": "Not available",
            "original_name": "Not available",
            "corporation_year": "Not available",
            "board": [
                {
                    "name": "dir. Bengt Ingeström",
                    "role": "ordf."
                },
                {
                    "name": "disp. Hans v. Kantzow",
                    "role": "Not available"
                },
                {
                    "name": "disp. Gust. Kihl-gren",
                    "role": "Not available"
                },
                {
                    "name": "generalkonsul Ragnar Söderberg",
                    "role": "Not available"
                }
            ],
            "owners": "Not available",
            "director": "Gust. Kihlgren",
            "managing_director": "Gust. Kihlgren",
            "sales_manager": "R. Scharf",
            "manager": "Knut Dahlin"
        },
        "5": {
            "name": "Eskilstuna Gjuteri AB.",
            "location": "Eskilstuna",
            "business": "Tillverkar gjutgods upp till 3 tons vikt",
            "products": "Not available",
            "contact": {
                "office": "Eskilstuna",
                "phone": [
                    "31049"
                ],
                "postgiro": "10792",
                "head_office": "Not available",
                "telegraph": "Not available",
                "factory_office": "Not available",
                "factory_phone": "Not available"
            },
            "financials": {
                "capital": "150,000 kr",
                "employees": {
                    "industriarb": 20
                },
                "annual_turnover": "230,000 kr",
                "annual_production_value": "Not available"
            },
            "foundation_year": 1911,
            "current_name_year": "Not available",
            "predecessor": "Not available",
            "original_name": "Not available",
            "corporation_year": "Not available",
            "board": [
                {
                    "name": "fabr. Hugo Andersson",
                    "role": "ordf."
                },
                {
                    "name": "gjutmäst. Elon Andersson",
                    "role": "Not available"
                },
                {
                    "name": "ing. Sven Råby",
                    "role": "Not available"
                }
            ],
            "owners": "Not available",
            "director": "Hugo Andersson",
            "managing_director": "Hugo Andersson",
            "sales_manager": "Not available",
            "manager": "Not available"
        },
        "6": {
            "name": "Eskilstuna Jernmanufaktur AB.",
            "location": "Eskilstuna",
            "business": "Järn- och, stålmanufakturfabrik",
            "products": "Not available",
            "contact": {
                "office": "Eskilstuna",
                "phone": [
                    "Not available"
                ],
                "postgiro": "10716",
                "head_office": "Eskilstuna",
                "telegraph": "Jernbolaget, Eskilstuna",
                "factory_office": "Not available",
                "factory_phone": "Not available"
            },
            "financials": {
                "capital": "2,000,000 kr",
                "employees": {
                    "industriarb": 700
                },
                "annual_turnover": "4,720,000 kr",
                "annual_production_value": "Not available"
            },
            "foundation_year": 1868,
            "current_name_year": "Not available",
            "predecessor": "B. & O. Libergs Fabriks AB",
            "original_name": "Not available",
            "corporation_year": "Not available",
            "board": [
                {
                    "name": "överste Ch. Holmgren",
                    "role": "ordf."
                },
                {
                    "name": "bankdir. L. O. Hessner",
                    "role": "Not available"
                },
                {
                    "name": "dir. Erik Nygren",
                    "role": "Not available"
                },
                {
                    "name": "järnhandl. Nils Ohlsson",
                    "role": "Not available"
                },
                {
                    "name": "dir. Arvid Reuterskiöld",
                    "role": "Not available"
                }
            ],
            "owners": "Not available",
            "director": "Arvid Reuterskiöld",
            "managing_director": "Not available",
            "sales_manager": "Not available",
            "manager": "Tage Follin"
        }
    }
}