{
    "original": "Elf ström—Eliasson\n\n*AB. Allon Elf ströms Trlkåfabrik,\n\nGävle.\n\nTillverkar trikåvaror i Lahmans,\nchar-meuse oeh interlock samt kragskyddare.\nSpecialitet: arbetstrikå. Varumärke:\n»Elfströms trikå».\n\nTelefon: 5696. Postgiro: 278398. —\nAkt.-kap.: 25,000 kr. Antal industriarb.:\n20. Tillv.-värde pr år: 200,000 kr. —\nFabriken anlagd 1930, bolaget grundat 1945.\n\nStyrelse, verkst. dir. o. disp.: fabr.\nAllon Elfström.\n\nAB. Elfvings Skofabrik,\n\nÖrnsköldsvik.\n\nTillverkar sportskodon och pjäxor,\nrandsydda skodon samt arbets- och\nsporthandskar. Varumärke: »Elfvings».\n\nTelefon: 2346 o. 1286. Postgiro: 62777.\nRepr. i Stockholm: Erik Burman,\nTrie-waldsgränd 1, telefon: 213188.\n\nAkt.-kap.: 50,300 kr. Antal\nindustriarb.: 30. Tillv.-värde pr år: 350,000 kr.\n— Firman etabl. 1904 i Anundsjö,\növerflyttades till Örnsköldsvik 1916, bolag\n1935.\n\nVerkst. dir.: John-Erik Elfving.\n\nAB. Elga, Stockholm.\n\nMek. verkstad. Tillverkar gasmätare och\nutför pressningsarbeten.\n\nKontor: Kronobergsg. 21. Telegr.-adr.:\nNordgas, Stockholm. Telefon: 520365.\nPostgiro: 157987.\n\nAkt.-kap.: 300,000 kr. Antal\nindustriarb.: 75. — Bolaget grundat 1930 under\nnamn AB. Nordgas, nuv. namn 1940.\n\nVerkst. dir.: E. Scherrer.\n\n*AB. Elge-Verken (Linköpings\nGjuteri &amp; Mek. Verkstad), Linköping.\n\nMek. verkstad och gjuteri. Tillverkar\ncentrifugal- och friktionskopplingar,\nfrik-tionsremskivor, kabelmuffar, kabelskåp,\nkabelmassa, bil- och traktorkolvar,\ntack-järnsgjutgods m. m. Varumärken: »Elge»\no. »St.artex».\n\nTelegr.-adr.: Elgeverken, Linköping.\nTelefon; 20204 o. 21454. Postgiro: 6065.\nLager: i Stockholm: Luntmakare. 42,\ntelefon: 106693; i Göteborg: Götabergsg.\n28, telefon: 183861.\n\nAkt.-kap.: 324,000 kr. Antal\nindustriarb.: 49. — Företaget grundades 1878,\nbolag 1909.\n\nStyrelse: adv. Gösta Grönberg (ordf.),\nadv. Hans Berggren, civiling. Nils\nEdholm, civiling. F. E. Weyde.\n\nVerkst. dir.: F. E. Weyde.\n\nElghammars Väveri, Skillingaryd.\n\nTillverkar mattor och möbeltyger vid\nväveri i Skillingaryd (Jönköp. l.).\n\nTelefon: 244 o. 273. — Arb.-antal: 10.\nTillv.-värde pr år: 300,000 kr. — Firman\netabl. 1922.\n\nÄgare o. chef: fabr. Gustaf\nElge-hammar.\n\n* Janne Elgqvist AB., Nybro.\n\nBleck var ufabrik. Tillverkar blankt och\ndekorerat emballage, ficklampsfodral och\nhandlyktor samt massartiklar av\nbleckplåt.\n\nTelefon: 10 o. 660. Postgiro: 20546.\nRepr. i Stockholm: AB. Olof Johnsson,\nGarvareg. 15, telefon: 520335.\n\nAkt.-kap.: 251,000 kr. Antal\nindustriarb.: 85. — Firman etabl. 1867, bolag\n1921.\n\nStyrelse: disp. Birger Ljungdahl,\növer-ing. Arvid B. Stenberg, civiling. Ivar\nStenberg.\n\nVerkst. dir.: Arvid B. Stenberg.\n\nDisp.: B. Ljungdahl.\n\nDriftsing.: Martin Ågren.\n\nKamrer: Martin Sandholm.\n\n*J. Owe Elgström, Ingenjörsfirman,\n\nHärnösand.\n\nSe Ingenjörsfirman J. Owe Elgström,\nHärnösand.\n\n*And. Eliassons Läderindustri AB.,\n\nM alung.\n\nTillverkar smor- och pjäxläder,\nboxsidor, kromsport- och »grönlandsläder»,\nsandalläder, koläder m. m. vid garveri i\nGrönland, Malung (Kopparb. l.).\n\nTelegr.-adr. o. telefon:\n»Eliassonslä-der», Malung. Postgiro: 74909.\n\nAkt.-kap.: 900,000 kr. Antal\nindustriarb.: 85. — Firman etabl. 1888, bolag\n1898.\n\nStyrelse: dir. And. Eliasson (ordf.),\ndir. Rob. Eliasson, lagerchef Gustaf Adolf\nEriksson.\n\nVerkst. dir.: Rob. Eliasson.\n\nEdv. Eliasson, Bollebygd.\n\nMadrass- och rullgardinsfabrik i\nBollebygd (Älvsb. l.). Tillverkar rullgardiner\nav väv och papper, madrasser samt\nvil-stolar av markisväv. Firman driver även\nengroshandel med korgvaror, slöjd- och\nbosättningsartiklar.",
    "structured": {
        "1": {
            "name": "Allon Elf ströms Trlkåfabrik, AB",
            "location": "Gävle",
            "business": "Tillverkar trikåvaror i Lahmans, char-meuse oeh interlock samt kragskyddare.",
            "products": "Specialitet: arbetstrikå. Varumärke: »Elfströms trikå».",
            "contact": {
                "office": "",
                "phone": [
                    "5696"
                ],
                "postgiro": "278398",
                "head_office": "",
                "sales_offices": [],
                "telegraph": "",
                "factory_office": "",
                "factory_phone": ""
            },
            "financials": {
                "capital": "25,000 kr",
                "employees": {
                    "industriarb": 20
                },
                "annual_turnover": "200,000 kr",
                "annual_production_value": "200,000 kr"
            },
            "foundation_year": 1930,
            "current_name_year": 1945
        },
        "2": {
            "name": "Elfvings Skofabrik, AB",
            "location": "Örnsköldsvik",
            "business": "Tillverkar sportskodon och pjäxor, randsydda skodon samt arbets- och sporthandskar.",
            "products": "Varumärke: »Elfvings».",
            "contact": {
                "office": "",
                "phone": [
                    "2346",
                    "1286"
                ],
                "postgiro": "62777",
                "head_office": "",
                "sales_offices": [
                    {
                        "location": "Stockholm",
                        "phone": "213188"
                    }
                ],
                "telegraph": "",
                "factory_office": "",
                "factory_phone": ""
            },
            "financials": {
                "capital": "50,300 kr",
                "employees": {
                    "industriarb": 30
                },
                "annual_turnover": "350,000 kr",
                "annual_production_value": "350,000 kr"
            },
            "foundation_year": 1904,
            "corporation_year": 1935
        },
        "3": {
            "name": "AB. Elga",
            "location": "Stockholm",
            "business": "Mek. verkstad. Tillverkar gasmätare och utför pressningsarbeten.",
            "contact": {
                "office": "Kronobergsg. 21",
                "phone": [
                    "520365"
                ],
                "postgiro": "157987",
                "head_office": "",
                "sales_offices": [],
                "telegraph": "Nordgas, Stockholm",
                "factory_office": "",
                "factory_phone": ""
            },
            "financials": {
                "capital": "300,000 kr",
                "employees": {
                    "industriarb": 75
                },
                "annual_turnover": "",
                "annual_production_value": ""
            },
            "foundation_year": 1930,
            "current_name_year": 1940
        },
        "4": {
            "name": "AB. Elge-Verken (Linköpings Gjuteri & Mek. Verkstad)",
            "location": "Linköping",
            "business": "Mek. verkstad och gjuteri. Tillverkar centrifugal- och friktionskopplingar, friktionsremskivor, kabelmuffar, kabelskåp, kabelmassa, bil- och traktorkolvar, tack-järnsgjutgods m. m.",
            "products": "Varumärken: »Elge» o. »St.artex».",
            "contact": {
                "office": "",
                "phone": [
                    "20204",
                    "21454"
                ],
                "postgiro": "6065",
                "head_office": "",
                "sales_offices": [],
                "telegraph": "Elgeverken, Linköping",
                "factory_office": "",
                "factory_phone": ""
            },
            "financials": {
                "capital": "324,000 kr",
                "employees": {
                    "industriarb": 49
                },
                "annual_turnover": "",
                "annual_production_value": ""
            },
            "foundation_year": 1878,
            "corporation_year": 1909
        },
        "5": {
            "name": "Elghammars Väveri",
            "location": "Skillingaryd",
            "business": "Tillverkar mattor och möbeltyger vid väveri i Skillingaryd (Jönköp. l.).",
            "contact": {
                "office": "",
                "phone": [
                    "244",
                    "273"
                ],
                "postgiro": "",
                "head_office": "",
                "sales_offices": [],
                "telegraph": "",
                "factory_office": "",
                "factory_phone": ""
            },
            "financials": {
                "employees": {
                    "antal": 10
                },
                "annual_turnover": "300,000 kr"
            },
            "foundation_year": 1922,
            "owners": [
                "fabr. Gustaf Elgehammar"
            ]
        },
        "6": {
            "name": "Janne Elgqvist AB.",
            "location": "Nybro",
            "business": "Bleck var ufabrik. Tillverkar blankt och dekorerat emballage, ficklampsfodral och handlyktor samt massartiklar av bleckplåt.",
            "contact": {
                "office": "",
                "phone": [
                    "10",
                    "660"
                ],
                "postgiro": "20546",
                "head_office": "",
                "sales_offices": [
                    {
                        "location": "Stockholm",
                        "phone": "520335"
                    }
                ],
                "telegraph": "",
                "factory_office": "",
                "factory_phone": ""
            },
            "financials": {
                "capital": "251,000 kr",
                "employees": {
                    "antal": 85
                }
            },
            "foundation_year": 1867,
            "corporation_year": 1921
        },
        "7": {
            "name": "And. Eliassons Läderindustri AB.",
            "location": "Malung",
            "business": "Tillverkar smor- och pjäxläder, boxsidor, kromsport- och »grönlandsläder», sandalläder, koläder m. m. vid garveri i Grönland, Malung (Kopparb. l.).",
            "contact": {
                "office": "",
                "phone": [],
                "postgiro": "74909",
                "head_office": "",
                "sales_offices": [],
                "telegraph": "Eliassonslä-der, Malung",
                "factory_office": "",
                "factory_phone": ""
            },
            "financials": {
                "capital": "900,000 kr",
                "employees": {
                    "antal": 85
                }
            },
            "foundation_year": 1888,
            "corporation_year": 1898
        },
        "8": {
            "name": "Edv. Eliasson",
            "location": "Bollebygd",
            "business": "Madrass- och rullgardinsfabrik i Bollebygd (Älvsb. l.). Tillverkar rullgardiner av väv och papper, madrasser samt vil-stolar av markisväv. Firman driver även engroshandel med korgvaror, slöjd- och bosättningsartiklar.",
            "contact": {
                "office": "",
                "phone": [],
                "postgiro": "",
                "head_office": "",
                "sales_offices": [],
                "telegraph": "",
                "factory_office": "",
                "factory_phone": ""
            }
        }
    }
}