{
    "original": "CTC—Dahlgren\n\n*AB. CTC, Göteborg.\n\nTillverkar varmvattenberedare och\nvärmeledningspannor samt utrustningar för\nvärme- och sanitetsanläggningar vid\nmek. verkstäder i Ljungby (Kronob. l.),\nmek. verkstad i Lerum (Älvsb. l.), samt\nmonteringsverkstad i Göteborg.\n\nHuvudkontor: Göteborg, Stora\nBad-husg. 20. Telegr.-adr.: Cetec, Göteborg.\nTelefon: 172630. Postgiro: 25596.\nAvd.-kontor: Stockholm, Nybrokajen 7.\nTelefon: 232320. Verkstadskontor: Ljungby,\ntelefon: 311 o. 418.\n\nAkt.-kap.: 500,000 kr. Antal\nindustriarb.: 400. Tillv.-värde pr år: 12,000,000\nkr. — Bolaget grundat 1923.\n\nStyrelse: disp. Franz Hartmann, dir.\nEric Höglund, adv. Karl Westin.\n\nV erkst. dir.: Eric Höglund.\n\nVerkstadschef: civiling. Olof Danielson\n(Ljungby).\n\nChef för Sthlmskontoret: ing. Gösta\nMagnusson.\n\n*AB. Cykelfabriken Monark,\n\nVarberg.\n\nTillverkar velocipeder och motorcyklar.\nVarumärken: »Monark», »Erlan»,\n»Nornan», »Scout» o. »Pilot».\n\nHuvudkontor: Varberg. Telegr.-adr.:\nMonark, Varberg. Telefon: »Monark\nvelocipeder». Postgiro: 31586. Avd.-kontor:\nStockholm, Birger Jarlsg. 34, telefon:\n234005; Göteborg: St. Nyg. 33, telefon:\n133520, 133302 o. 131840; Malmö, österg.\n14, telefon: 26511 o. 17633; m. fl. orter.\n\nAkt.-kap.: 2,000,000 kr. Antal\nindustriarb.: 500. (Hela antalet anställda inom\nkoncernen: 2,300.)\n\nFabriken grundad 1908 undér i^amn\nSvenska Cykelfabriken Monark, nuv.\nbolag: 1939. Bolaget äger AB. Värnamo\nGummifabrik, AB. Tobo Bruk och\nLandskrona Tricotfabrik.\n\nStyrelse o. verkst. dir.: disp. Tage\nWar-born.\n\n* utmärker till Sveriges Industriförbund anslutna företag.\n\nAB. Dago, Falun.\n\nBryter dolomit vid fyndigheter i\nMårds-hyttan, Guldsmedshyttan (Örebro l.).\n\nKontor: Falun. Telegr.-adr. o. telefon:\nBergslaget, Falun. — Akt.-kap.: 100,000\nkr. Arb.-antal: 5. Prod.-värde pr år:\n100 000 kr. — Bolaget grundat 1918.\n\nStyrelse: dir. Erik G. Pehrsson (ordf.),\ndir. Karl Rutberg, disp. Rutger\nWijkan-der.\n\nVerkst. dir.: Karl Rutberg.\n\nJ. Dahl &amp; Son AB. Mek. Verkstad,\n\nStockholm.\n\nTillverkar specialmaskiner för bok- och\ntidningstryckerier, bokbinderier,\nkarton-nagefabriker, tapetfabriker och\npåsfabri-ker.\n\nKontor: Adolf Fred rikstorg 5. Telefon:\n418080 o. 418680. Postgiro: 58797. —\nAkt.-kap.: 150.000 kr. Antal industriarb.:\n40. Tillv.-värde pr år: 520,000 kr. —\nFirman etabl. 1932, bolag 1942.\n\nVerkst. dir.: Julius Dahl.\n\n*Pehr Aug. Dahl AB., Norrköping.\n\nYllefabrik med spinneri och väveri.\nTillverkar paletå- och sporttyger samt\nvattolin och tagelvävnader.\n\nTelefon: 20488. — Akt.-kap.: 50,000\nkr. Antal industriarb.: 25. Tillv.-värde pr\når: 350,000 kr. — Firman etabl. 1883,\nbolag 1938.\n\nStyrelse o. verkst. dir.: fabr. Ragnar\nDahl.\n\n*J. Dahlander &amp; Co:s Fabriks AB.,\n\nGöteborg.\n\nTapet-, markis- och metallvarufabrik i\nörgryte, Göteborg. Tillverkar tapeter,\nbårder, markiser, rullgardiner,\npresenningar, flaggor, tält m. m.; utför\naffärs-fasader i metall och rostfritt stål samt\nbranddörrar och dörrar till\nluftskyddsrum.\n\nKontor: Mölndalsvägen; postadr.:\nGöteborg 5. Telegr.-adr.: Dahlander.\nGöteborg. Telefon: »Dahlanders fabriker».\nPostgiro: 40792.\n\nAkt.-kap.: 200,000 kr. Antal\nindustriarb.: 96. — Firman etabl. 1850, bolag\n1908.\n\nStyrelse: disp. Gunnar Jonson, disp.\nLars H. Jonson, fru Lisa Jonson.\n\nDisp.: L. H. Jonson.\n\n’C. Dahlgren &amp; Co., Malmö.\n\nSe Guldvaru AB. G. Dahlgren &amp; Co.,\nMalmö.\n\n102*",
    "structured": {
        "1": {
            "name": "CTC—Dahlgren*AB",
            "location": "Göteborg",
            "business": "Tillverkar varmvattenberedare och värmeledningspannor samt utrustningar för värme- och sanitetsanläggningar vid mek. verkstäder i Ljungby (Kronob. l.), mek. verkstad i Lerum (Älvsb. l.), samt monteringsverkstad i Göteborg.",
            "contact": {
                "office": "Stora Bad-husg. 20, Göteborg",
                "phone": [
                    "172630"
                ],
                "postgiro": "25596",
                "sales_offices": [
                    {
                        "location": "Stockholm",
                        "phone": "232320"
                    },
                    {
                        "location": "Ljungby",
                        "phone": "311 o. 418"
                    }
                ],
                "telegraph": "Cetec, Göteborg"
            },
            "financials": {
                "capital": "500,000 kr",
                "employees": {
                    "industriarb": 400
                },
                "annual_turnover": "12,000,000 kr"
            },
            "foundation_year": 1923,
            "board": [
                {
                    "name": "Franz Hartmann",
                    "role": "disp."
                },
                {
                    "name": "Eric Höglund",
                    "role": "dir."
                },
                {
                    "name": "Karl Westin",
                    "role": "adv."
                }
            ],
            "director": "Eric Höglund"
        },
        "2": {
            "name": "AB. Cykelfabriken Monark",
            "location": "Varberg",
            "business": "Tillverkar velocipeder och motorcyklar. Varumärken: »Monark», »Erlan», »Nornan», »Scout» o. »Pilot».",
            "contact": {
                "office": "Varberg",
                "phone": [
                    "Monark velocipeder"
                ],
                "postgiro": "31586",
                "sales_offices": [
                    {
                        "location": "Stockholm",
                        "phone": "234005"
                    },
                    {
                        "location": "Göteborg",
                        "phone": "133520, 133302 o. 131840"
                    },
                    {
                        "location": "Malmö",
                        "phone": "26511 o. 17633"
                    }
                ],
                "telegraph": "Monark, Varberg"
            },
            "financials": {
                "capital": "2,000,000 kr",
                "employees": {
                    "industriarb": 500
                }
            },
            "foundation_year": 1908,
            "board": [
                {
                    "name": "Tage War-born",
                    "role": "disp."
                }
            ]
        },
        "3": {
            "name": "AB. Dago",
            "location": "Falun",
            "business": "Bryter dolomit vid fyndigheter i Mårds-hyttan, Guldsmedshyttan (Örebro l.).",
            "contact": {
                "office": "Falun",
                "phone": [
                    "Bergslaget, Falun"
                ],
                "postgiro": "Bergslaget, Falun"
            },
            "financials": {
                "capital": "100,000 kr",
                "employees": {
                    "arb": 5
                },
                "annual_turnover": "100,000 kr"
            },
            "foundation_year": 1918,
            "board": [
                {
                    "name": "Erik G. Pehrsson",
                    "role": "dir."
                },
                {
                    "name": "Karl Rutberg",
                    "role": "dir."
                },
                {
                    "name": "Rutger Wijkan-der",
                    "role": "disp."
                }
            ],
            "director": "Karl Rutberg"
        },
        "4": {
            "name": "J. Dahl & Son AB. Mek. Verkstad",
            "location": "Stockholm",
            "business": "Tillverkar specialmaskiner för bok- och tidningstryckerier, bokbinderier, kartonnagefabriker, tapetfabriker och påsfabri-ker.",
            "contact": {
                "office": "Adolf Fredrikstorg 5, Stockholm",
                "phone": [
                    "418080 o. 418680"
                ],
                "postgiro": "58797"
            },
            "financials": {
                "capital": "150,000 kr",
                "employees": {
                    "industriarb": 40
                },
                "annual_turnover": "520,000 kr"
            },
            "foundation_year": 1932,
            "board": [
                {
                    "name": "Julius Dahl",
                    "role": "Verkst. dir."
                }
            ]
        },
        "5": {
            "name": "Pehr Aug. Dahl AB.",
            "location": "Norrköping",
            "business": "Yllefabrik med spinneri och väveri. Tillverkar paletå- och sporttyger samt vattolin och tagelvävnader.",
            "contact": {
                "phone": [
                    "20488"
                ],
                "postgiro": "50,000 kr"
            },
            "financials": {
                "capital": "50,000 kr",
                "employees": {
                    "industriarb": 25
                },
                "annual_turnover": "350,000 kr"
            },
            "foundation_year": 1883,
            "board": [
                {
                    "name": "Ragnar Dahl",
                    "role": "fabr."
                }
            ]
        },
        "6": {
            "name": "J. Dahlander & Co:s Fabriks AB.",
            "location": "Göteborg",
            "business": "Tapet-, markis- och metallvarufabrik i örgryte, Göteborg. Tillverkar tapeter, bårder, markiser, rullgardiner, presenningar, flaggor, tält m. m.; utför affärs-fasader i metall och rostfritt stål samt branddörrar och dörrar till luftskyddsrum.",
            "contact": {
                "office": "Mölndalsvägen, Göteborg",
                "phone": [
                    "Dahlanders fabriker"
                ],
                "postgiro": "40792"
            },
            "financials": {
                "capital": "200,000 kr",
                "employees": {
                    "industriarb": 96
                }
            },
            "foundation_year": 1850,
            "board": [
                {
                    "name": "Gunnar Jonson",
                    "role": "disp."
                },
                {
                    "name": "Lars H. Jonson",
                    "role": "disp."
                },
                {
                    "name": "Lisa Jonson",
                    "role": "fru"
                }
            ],
            "manager": "L. H. Jonson"
        }
    }
}