{
    "original": "Ljungby—Ljungdell\n\nLjungby Konfektions Industri,\n\nLjungby.\n\n, Tillverkar skjortor, byxor och\narbetskläder. Varumärke: »Elki».\n\nTelefon: 175. Postgiro: 77377. —\nAntal industriarb.: 80. Tillv.-värde pr år:\n585,000 kr. — Firman etabl. 1928.\n\nÄgare o. chef: Manfred Svensson.\n\n*AB. Ljungby Möbelindustri,\n\nLjungby.\n\nTillverkar butiksinredningar vid fabrik\ni Ljungby (Kronob. l.).\n\nTelefon: 334. Postgiro: 22408.\nEnsamförsälj..- AB. Köpmannatjänst, Västerås,\ntelefon: »Köpmannatjänst».\n\nAkt.-kap.: 22,000 kr. Antal\nindustriarb.: 20. Tillv.-värde pr år: 250,000 kr.\n— Bolaget grundat 1931.\n\nStyrelse: köpm. Edvin Tranberg\n(ordf.), dir. Herman Green, dir. Harald\nMörck.\n\nVerJcst. dir.: Harald Mörck (Västerås).\n\nLjungby Snickerifabrik, Andersson\n&amp; Son, Ljungby.\n\nTillverkar lamelldörrar.\n\nTelefon: 201. Postgiro: 174129. —\nAntal industriarb.: 40. Tillv.-värde pr år:\n600,000 kr. — Firman etabl. 1919.\n\nÄgare o. chef: fabr. F. E. Alf fram.\n\n*AB. Ljungby Stålgjuteri, Ljungby.\n\nElektr. stålgjuteri i Ljungby (Kronob.\n1.). Tillverkar smärre och medelgrovt\nstålgjutgods på beställning samt\nsten-krossplattor av högprocentigt manganstål.\n\nTelegr.-adr.: Stålgjuteriet, Ljungby.\nTelefon: 8. o. 108. Postgiro: 24016. —\nAkt.-kap.: 300,000 kr. Antal industriarb.:\n45. Tillv.-värde pr år: 630,000 kr. —\nBolaget grundat 1913.\n\nStyrelse: adv. Per Yngström (ordf.),\ning. Herman Andersson, fru N.\nHartman, byråsekr. Nils Yngström, civiling.\nPer Yngström.\n\nVerJcst. dir. o. disp.: Herman\nAndersson.\n\nLjungby Trikåindustri, D. Nyqvist,\n\nLjungby.\n\nTillverkar herr-, dam- och\nbarnunder-kläder\n\nTelefon: 324. Postgiro: 131570. —\nTillv.-värde pr år: 290,000 kr. — Firman\netabl. 1936.\n\nÄgare o. chef: fabr. David Nyqvist.\n\nAB. Ljungby Velociped- och\nFör-nicklingsfabrik, Ljungby.\n\nTillverkar vid fabrik i Ljungby\n(Kronob. l.) velocipeddelar såsom styrstänger,\npedaler, sadelstolpar, skärmstag m. m.\n\nTelefon: 143. Postgiro: 98400.. —\nAkt.-kap.: 50,000 kr. Antal industriarb.: 70.\nTillv.-värde pr år: 700,000 kr. — Firman\netabl. 1918, bolag 1945.\n\nVerJcst. direktörer: Egon Sjöberg o.\nTorsten Weidrup.\n\n*C. Ljungdahls Handels &amp; Fabriks\nAB., Lerum.\n\n^ Färg-, ferniss- och kem.-teknisk fabrik\nvid Lerum (Älvsb. l.). Tillverkar\ngrund-ningsfärger (»Ljunga-grund»), oljefärger,\nmatta lackfärger (»Täckofiat»),\nbindemedel för färger (»Impentol»),\nemulsionsfärger (»Impento»), emaljoljefärger\n(»Ankarfärg»), emaljfärger (»Täcktolin»),\nnitrocellulosalacker (»Nitrosa»),\nmaskinfärger, spackelfärg, patenterade\nspackel-färgspreparat (»Spackolin»),\nskeppsbot-tenfärger (»Ankaret»), dubbelkokt\nlinolja, limfärgspreparat, fennissor m. m.\n\nInköps- och försäljningskontor:\nGöteborg, S:t Eriksg. 4. Telegr.-adr.:\nSpackolin, Göteborg. Telefon: Göteborg 174760.\nPostgiro: 40110.\n\nAkt.-kap.: 165,000 kr. Antal\nindustriarb.: 26. Tillv.-värde pr år: 2,400,000 kr.\n— Bolaget grundat 1917.\n\nStyrelse: ing. Oscar Ljungdahl, dir.\nGunnar Ringström, disp. Torsten\nRingström.\n\nVerkst. dir.: Gunnar Ringström.\n\n*AB. Sture Ljungdahl &amp; Co., Nybro.\n\nKuvertfabrik och boktryckeri i Nybro\n(Kalmar l.). Tillverkar kuvert av alla\nslag. Firman driver även engroshandel\nmed pappersvaror.\n\nTelegr.-adr.: Ljungdahls, Nybro.\nTelefon: »Ljungdahls fabriker». Postgiro:\n9477. Avd.-kontor: Stockholm,\nWahren-dorffsg. 1, telefon: 114613; Göteborg:\nDrottningg. 11, telefon: 134585; Malmö,\nJöns Filsg. 2, telefon: 72160.\n\nAkt.-kap.: 1,200,000 kr. Antal\nindustriarb.: 225. — Firman etabl. 1915.\n\nStyrelse: kontorschef Anders\nLjungdahl (ordf.), kontorist Evald Ljungdahl,\nfabrikschef Ivar Ljungdahl, dir. Sture\nLjungdahl, kamrer A. W. Öländer.\nVerkst. dir.: Sture Ljungdahl.\nV. verkst. dir.: A. W. Öländer.\n\nLjungdell, AB. Bröderna, Malmö.\n\nSe AB. Bröderna Ljungdell, Malmö.",
    "structured": {
        "1": {
            "name": "Ljungby Konfektions Industri",
            "location": "Ljungby",
            "business": "Tillverkning av skjortor, byxor och arbetskläder",
            "products": "Varumärke: »Elki»",
            "contact": {
                "office": "Telefon: 175, Postgiro: 77377",
                "employees": {
                    "industriarb": 80
                }
            },
            "financials": {
                "capital": "Ej tillgängligt",
                "employees": {
                    "Ej tillgängligt": "Ej tillgängligt"
                },
                "annual_turnover": "585,000 kr",
                "annual_production_value": "Ej tillgängligt"
            },
            "foundation_year": 1928,
            "director": "Manfred Svensson"
        },
        "2": {
            "name": "AB. Ljungby Möbelindustri",
            "location": "Ljungby",
            "business": "Tillverkning av butiksinredningar",
            "contact": {
                "office": "Telefon: 334, Postgiro: 22408"
            },
            "financials": {
                "capital": "22,000 kr",
                "employees": {
                    "industriarb": 20
                },
                "annual_turnover": "250,000 kr",
                "annual_production_value": "Ej tillgängligt"
            },
            "foundation_year": 1931,
            "board": [
                {
                    "name": "köpm. Edvin Tranberg",
                    "role": "ordf."
                },
                {
                    "name": "dir. Herman Green",
                    "role": "Ej tillgängligt"
                },
                {
                    "name": "dir. Harald Mörck",
                    "role": "Ej tillgängligt"
                }
            ],
            "sales_manager": "Harald Mörck",
            "manager": "Ej tillgängligt"
        },
        "3": {
            "name": "Ljungby Snickerifabrik, Andersson & Son",
            "location": "Ljungby",
            "business": "Tillverkning av lamelldörrar",
            "contact": {
                "office": "Telefon: 201, Postgiro: 174129",
                "employees": {
                    "industriarb": 40
                }
            },
            "financials": {
                "capital": "Ej tillgängligt",
                "employees": {
                    "Ej tillgängligt": "Ej tillgängligt"
                },
                "annual_turnover": "Ej tillgängligt",
                "annual_production_value": "600,000 kr"
            },
            "foundation_year": 1919,
            "director": "fabr. F. E. Alf fram"
        },
        "4": {
            "name": "AB. Ljungby Stålgjuteri",
            "location": "Ljungby",
            "business": "Tillverkning av smärre och medelgrovt stålgjutgods samt sten-krossplattor av högprocentigt manganstål",
            "contact": {
                "office": "Telegr.-adr.: Stålgjuteriet, Ljungby, Telefon: 8. o. 108, Postgiro: 24016",
                "employees": {
                    "industriarb": 45
                }
            },
            "financials": {
                "capital": "300,000 kr",
                "employees": {
                    "Ej tillgängligt": "Ej tillgängligt"
                },
                "annual_turnover": "630,000 kr",
                "annual_production_value": "Ej tillgängligt"
            },
            "foundation_year": 1913,
            "board": [
                {
                    "name": "adv. Per Yngström",
                    "role": "ordf."
                },
                {
                    "name": "ing. Herman Andersson",
                    "role": "Ej tillgängligt"
                },
                {
                    "name": "fru N. Hartman",
                    "role": "Ej tillgängligt"
                },
                {
                    "name": "byråsekr. Nils Yngström",
                    "role": "Ej tillgängligt"
                },
                {
                    "name": "civiling. Per Yngström",
                    "role": "Ej tillgängligt"
                }
            ],
            "director": "Herman Andersson"
        },
        "5": {
            "name": "Ljungby Trikåindustri, D. Nyqvist",
            "location": "Ljungby",
            "business": "Tillverkning av herr-, dam- och barnunderkläder",
            "contact": {
                "office": "Telefon: 324, Postgiro: 131570",
                "employees": {
                    "Ej tillgängligt": "Ej tillgängligt"
                }
            },
            "financials": {
                "capital": "Ej tillgängligt",
                "employees": {
                    "Ej tillgängligt": "Ej tillgängligt"
                },
                "annual_turnover": "290,000 kr",
                "annual_production_value": "Ej tillgängligt"
            },
            "foundation_year": 1936,
            "director": "fabr. David Nyqvist"
        },
        "6": {
            "name": "AB. Ljungby Velociped- och Förnicklingsfabrik",
            "location": "Ljungby",
            "business": "Tillverkning av velocipeddelar såsom styrstänger, pedaler, sadelstolpar, skärmstag m. m",
            "contact": {
                "office": "Telefon: 143, Postgiro: 98400..",
                "employees": {
                    "industriarb": 70
                }
            },
            "financials": {
                "capital": "50,000 kr",
                "employees": {
                    "Ej tillgängligt": "Ej tillgängligt"
                },
                "annual_turnover": "700,000 kr",
                "annual_production_value": "Ej tillgängligt"
            },
            "foundation_year": 1918,
            "managing_director": "Egon Sjöberg o. Torsten Weidrup"
        },
        "7": {
            "name": "C. Ljungdahls Handels & Fabriks AB.",
            "location": "Lerum",
            "business": "Färg-, ferniss- och kem.-teknisk fabrik",
            "contact": {
                "office": "Inköps- och försäljningskontor: Göteborg, S:t Eriksg. 4",
                "phone": {
                    "Göteborg": "174760"
                },
                "employees": {
                    "industriarb": 26
                }
            },
            "financials": {
                "capital": "165,000 kr",
                "employees": {
                    "Ej tillgängligt": "Ej tillgängligt"
                },
                "annual_turnover": "2,400,000 kr",
                "annual_production_value": "Ej tillgängligt"
            },
            "foundation_year": 1917,
            "board": [
                {
                    "name": "ing. Oscar Ljungdahl",
                    "role": "Ej tillgängligt"
                },
                {
                    "name": "dir. Gunnar Ringström",
                    "role": "Ej tillgängligt"
                },
                {
                    "name": "disp. Torsten Ringström",
                    "role": "Ej tillgängligt"
                }
            ],
            "director": "Gunnar Ringström"
        },
        "8": {
            "name": "AB. Sture Ljungdahl & Co.",
            "location": "Nybro",
            "business": "Kuvertfabrik och boktryckeri",
            "contact": {
                "office": "Telegr.-adr.: Ljungdahls, Nybro, Telefon: »Ljungdahls fabriker», Postgiro: 9477",
                "phone": {
                    "Stockholm": "114613",
                    "Göteborg": "134585",
                    "Malmö": "72160"
                },
                "employees": {
                    "industriarb": 225
                }
            },
            "financials": {
                "capital": "1,200,000 kr",
                "employees": {
                    "Ej tillgängligt": "Ej tillgängligt"
                }
            },
            "foundation_year": 1915,
            "board": [
                {
                    "name": "kontorschef Anders Ljungdahl",
                    "role": "ordf."
                },
                {
                    "name": "kontorist Evald Ljungdahl",
                    "role": "Ej tillgängligt"
                },
                {
                    "name": "fabrikschef Ivar Ljungdahl",
                    "role": "Ej tillgängligt"
                },
                {
                    "name": "dir. Sture Ljungdahl",
                    "role": "Ej tillgängligt"
                },
                {
                    "name": "kamrer A. W. Öländer",
                    "role": "Ej tillgängligt"
                }
            ],
            "director": "Sture Ljungdahl",
            "manager": "A. W. Öländer"
        },
        "9": {
            "name": "AB. Bröderna Ljungdell",
            "location": "Malmö",
            "director": "Ej tillgängligt",
            "manager": "Ej tillgängligt"
        }
    }
}