{
    "original": "S venska—Svenskt\n\nAB. Svenska Velocipedfabriken,\n\nStockholm.\n\nTillverkar velocipeder. Varumärken:\nUnion, Herkules, Svea, Trygg, Viking o.\nThor.\n\nKontor: Bellmansg. 2. Telegr.-adr.:\nSnabb, Stockholm. Telefon: 437065—66.\nPostgiro: 637.\n\nAkt.-kap.: 100,000 kr. Antal\nindustriarb.: 25. Tillv.-värde pr år: 500,000 kr.\n— Bolaget grundat 1922.\n\nDir.: Rolf Gille.\n\n\"Svenska Väg AB., Stockholm.\n\nByggnadsentreprenörfirma för\nindustribyggnader, gator, vägar, vatten och\navlopp, vattenarbeten såsom kajer,\nkraftverk m. m. samt asfaltfabrik. Tillverkar\ngatu- och vägbeläggningsämnen samt ss.\nspecialitet slungade betongrör.\nVarumärke for asfaltbeläggning: »Amiesite».\n\nHuvudkontor: Stockholm, Kaptensg. 6.\nTelegr.-adr.: Viaco, Stockholm. Telefon:\n679110. Postgiro: 52333. Avd.-kontor:\n^Göteborg, Packhusplatsen 2, telefon:\n110452.\n\nAkt.-kap.: 1,000,000 kr. Prod.-värde år\n1945: 9,000,000 kr. — Bolaget grundat\n1930, ombildat 1933.\n\nStyrelse: dir. Tore Grönwall (ordf.),\ndir. Vilhelm Björkman, major Sven V.\nErikson, bankdir. Richard Julin, dir.\nAlexius Kleist.\n\nVerkst. dir.: Sven V. Erikson.\n\nKamrer: Nils G. Alin.\n\nArbetschefer: för byggnadsavd.:\nkapten Nils O. Lidin; för vägavd.: ing. John\nSvedberg.\n\nPlatschef i Göteborg: civiling. Bertil\n^yllenberg.\n\n\"Svenska Värme-Elektr. AB.,\n\nUlvsunda.\n\nElektromek. verkstad. Tillverkar\nvat-tenvärmare, varmbord, värmeskåp,\nkylskåp och kyldiskar, spec. s. k.\nsjälvserveringsdiskar för restauranger samt för\npersonallunchrum och sjukhus, rostfria\nkantiner, behållare, arbetsbord och\nför-varingstankar. Varumärke: »Svea».\n\nTelegr.-adr.: Elektrosvea, Stockholm.\nTelefon: Stockholm 281255 o. 281010.\nPostgiro: 52282.\n\nAkt.-kap.: 50,000 kr. Arb.-antal: 20.\nTillv.-värde pr år: 400,000 kr.\n\nBolaget grundat 1930.\n\nStyrelse: dir. Gunnar Blomstrand\n(ordf.), dir. Gunnar Arnbrink,\n\nVerkst. dir.: G. Blomstrand.\n\nDir.: G. Arnbrink.\n\n\"Svenska Yllekoncernen, AB., Tidan.\n\nUllspinneri, ylleväveri, färgeri och\nberedningsverk vid Tidan (Skarab. l.).\nTillverkar ullgarner, yllevävnader och filtar\nm. m.\n\nHuvudkontor: Borås. Telegr.-adr.^ o.\ntelefon: Yllekoncernen, Borås. Postgiro:\n6901. Fabriks- o. direktörskontor: Tidan.\nTelegr.-adr.: Yllekoncernen, Tidan\nTelefon: Tidan 11.\n\nAkt.-kap.: 2,265,800 kr. Antal\nindustriarb.: 170. Tillv.-värde pr år: 4,500,000 kr.\n\nBolaget grundades 1911 under namn av\nWestergötlands Yllefabriks AB., ombildat\n1930. Svenska Yllekoncernen AB. är\nhuvudintressent i följande företag: Borås\nYllefabriks AB., Borås, AB. Fors\nUllspinneri, Nyköping, Stigens AB., Stigen, och\nFors och Sahlströmska Fabrikerna AB.,\nNyköping.\n\nStyrelse: disp. C. G. Lundberg, (ordf.),\nkontorschef O. Byrgård, bankdir. E.\nLö-wenhard, dir. Gösta Åhlén.\n\nVerkst. dir.: C. G. Lundberg (Tidan).\n\nKontorschef: O. Byrgård (Borås).\n\nFabrikschef i Tidan: Einar Lundberg.\n\nInköpschef: Nils V. Svenson (Borås).\n\n\"AB. Svenskt Konstsilke, Borås.\n\nKonstsilkefabrik. Tillverkar konstsilke\noch cellull.\n\nTelegr.-adr. o. telefon: Konstsilke,\nBorås. Postgiro: 14941.\n\nAkt.-kap.: 2,400,000 kr. Antal\nindustriarb.: 750. Tillv.-värde pr år: 15,000,000\nkr. — Bolaget grundat 1918.\n\nStyrelse: bankdir. Helmer Stén (ordf.),\növerste E. v. Goumoéns.\n\nVerkst. dir.: civiling. N. W.\nHörsta-dius.\n\nFabrikschef: civiling. Artur J.\nEriksson.\n\nKamrer: E. Grosskopf.\n\nFörsäljn.-chef: F. Suter.\n\n\"AB. Svenskt Kontrollregister,\n\nStockholm.\n\nTillverkar kassakontrollapparater.\nVarumärke: »Hugin».\n\nKontor: Magnus Ladulåsg. 11.\nTelegr.-adr.: Svenskregister, Stockholm. Telefon:\n440230.\n\nAkt.-kap.: 250,000 kr. Antal\nindustriarb.: 90. Tillv.-värde pr år: 2,000,000 kr.\n\nBolaget, grundat 1937, äges av\nKooperativa Förbundet.\n\nStyrelse: dir. Albin Johansson.\n\nChef: Tord Dahlberg.",
    "structured": {
        "1": {
            "name": "AB. Svenska Velocipedfabriken",
            "location": "Stockholm",
            "business": "Tillverkar velocipeder",
            "products": "Varumärken: Union, Herkules, Svea, Trygg, Viking och Thor",
            "contact": {
                "office": "Bellmansg. 2",
                "phone": [
                    "437065",
                    "437066"
                ],
                "postgiro": "637",
                "telegraph": "Snabb, Stockholm"
            },
            "financials": {
                "capital": "100,000 kr",
                "employees": {
                    "industriarb": 25
                },
                "annual_turnover": "500,000 kr",
                "annual_production_value": "500,000 kr"
            },
            "foundation_year": 1922,
            "director": "Rolf Gille"
        },
        "2": {
            "name": "Svenska Väg AB.",
            "location": "Stockholm",
            "business": "Byggnadsentreprenörfirma för industribyggnader, gator, vägar, vatten och avlopp, vattenarbeten såsom kajer, kraftverk m.m. samt asfaltfabrik",
            "products": "Tillverkar gatu- och vägbeläggningsämnen samt specialitet slungade betongrör. Varumärke for asfaltbeläggning: »Amiesite»",
            "contact": {
                "office": "Kaptensg. 6",
                "phone": "679110",
                "postgiro": "52333",
                "sales_offices": [
                    {
                        "location": "Göteborg",
                        "phone": "110452"
                    }
                ],
                "telegraph": "Viacö, Stockholm"
            },
            "financials": {
                "capital": "1,000,000 kr",
                "annual_production_value": "9,000,000 kr"
            },
            "foundation_year": 1930,
            "board": [
                {
                    "name": "Tore Grönwall",
                    "role": "ordf."
                },
                {
                    "name": "Vilhelm Björkman",
                    "role": ""
                },
                {
                    "name": "Sven V. Erikson",
                    "role": "major"
                },
                {
                    "name": "Richard Julin",
                    "role": "bankdir."
                },
                {
                    "name": "Alexius Kleist",
                    "role": "dir."
                }
            ],
            "director": "Sven V. Erikson",
            "manager": "civiling. Bertil ^yllenberg"
        },
        "3": {
            "name": "Svenska Värme-Elektr. AB.",
            "location": "Ulvsunda",
            "business": "Elektromek. verkstad",
            "products": "Tillverkar vat-tenvärmare, varmbord, värmeskåp, kylskåp och kyldiskar, spec. s. k. självserveringsdiskar för restauranger samt för personallunchrum och sjukhus, rostfria kantiner, behållare, arbetsbord och för-varingstankar. Varumärke: »Svea»",
            "contact": {
                "telegraph": "Elektrosvea, Stockholm",
                "phone": [
                    "281255",
                    "281010"
                ],
                "postgiro": "52282"
            },
            "financials": {
                "capital": "50,000 kr",
                "annual_turnover": "400,000 kr"
            },
            "foundation_year": 1930,
            "board": [
                {
                    "name": "Gunnar Blomstrand",
                    "role": "ordf."
                },
                {
                    "name": "Gunnar Arnbrink",
                    "role": ""
                }
            ],
            "director": "G. Blomstrand",
            "sales_manager": "G. Arnbrink"
        },
        "4": {
            "name": "Svenska Yllekoncernen, AB.",
            "location": "Tidan",
            "business": "Ullspinneri, ylleväveri, färgeri och beredningsverk",
            "products": "Tillverkar ullgarner, yllevävnader och filtar m.m.",
            "contact": {
                "office": "Borås",
                "phone": "Yllekoncernen, Borås",
                "postgiro": "6901",
                "sales_offices": [
                    {
                        "location": "Tidan",
                        "phone": "Tidan 11"
                    }
                ]
            },
            "financials": {
                "capital": "2,265,800 kr",
                "employees": {
                    "industriarb": 170
                },
                "annual_turnover": "4,500,000 kr"
            },
            "foundation_year": 1911
        },
        "5": {
            "name": "AB. Svenskt Konstsilke",
            "location": "Borås",
            "business": "Konstsilkefabrik",
            "contact": {
                "phone": "Konstsilke, Borås",
                "postgiro": "14941"
            },
            "financials": {
                "capital": "2,400,000 kr",
                "employees": {
                    "industriarb": 750
                },
                "annual_turnover": "15,000,000 kr"
            },
            "foundation_year": 1918
        },
        "6": {
            "name": "AB. Svenskt Kontrollregister",
            "location": "Stockholm",
            "business": "Tillverkar kassakontrollapparater",
            "products": "Varumärke: »Hugin»",
            "contact": {
                "office": "Magnus Ladulåsg. 11",
                "phone": "440230",
                "postgiro": "250,000 kr"
            },
            "financials": {
                "capital": "250,000 kr",
                "employees": {
                    "industriarb": 90
                },
                "annual_turnover": "2,000,000 kr"
            },
            "foundation_year": 1937
        }
    }
}