{
    "original": "Osmund—Ousby\n\nStyrelse: dir. H. Wellner (ordf.),\nbankdir. G. Didner, bankdir. F. Sandelin.\n\nVerkst. dir.: H. Wellner.\n\nDriftsing.: civiling. Sverre Jenssen.\n\n\"Osmund, Fabriks AB., TJppsala.\n\nSe Fabriks AB. Osmund, Uppsala.\n\n\"AB. Osram-Elektraverken,\n\nStockholm.\n\nGlödlampfabrik. Tillverkar\nmetalltrådslampor av märket »Osram».\n\nKontor: Ringvägen 98; postadr.:\nStockholm 20. Telegr.-adr. o. telefon: Osram,\nStockholm. Postgiro: 727.\n\nAkt.-kap.: 2,750,000 kr. Antal\nindustriarb.: 300.\n\nBolaget, grundat 1917 under namn AB.\nElektraverken, fusionerades 1930 med\nOsram AB. och ändrade därvid namnet\ntill AB. Osram-Elektraverken.\n\nBolaget står vid kalenderns tryckning\nunder administration.\n\nStyrelse: generaldir. W. Borgquist\n(ordf.), dir. Jerker Henke, adv. Linus\nLindberg, prof. Edy Veländer.\n\nVerkst. dir.: Jerker Henke.\n\nV. verkst. dir.: Fredrik Schéle.\n\nAdministratör: adv. Otto Lagerström.\n\n(Jfr annons nr 66.)\n\n\"AB. Hans Österman, Stockholm.\n\nBilreparations- och serviceverkstäder.\n\nUtför bilreparationer och monteringar\nav bilar. Firman driver såsom\nhuvud-rörelse försäljning av automobiler och\ngummiringar.\n\nKontor o. utställning: Birger Jarlsg.\n18; postadr.: Stockholm 7. Telegr.-adr.:\nBilosterman, Stockholm. Telefon: »Hans\nÖsterman». Postgiro: 767.\n\nAkt.-kap.: 1,500,000 kr. — Firman\netabl. 1908, bolag 1915.\n\nStyrelse: bankdir. Rich. Julin (ordf.),\nbyggm. Olle Engkvist, adv. Gösta\nGrönberg, ing. Lennart Österman.\n\nVerkst. dir.: Lennart Österman.\n\nKamrer: Einar Helenius.\n\nFörsäljn.: disp. K.-H. Björngård.\n\nServicechef: ing. Sten Walles.\n\nVerkstadschefer: Gösta Andersson,\nTage Berglund o. ing. Thorvald Hedin.\n\n\"John Österman, Eiektr. AB.,\n\nStockholm.\n\nSe Elektriska AB. John Österman,\nStockholm.\n\n\"Ostvik-Sniokerifaforik, Ostvik.\n\nTillverkar fönster och dörrar samt\nbostads- och butiksinredningar vid fabrik\ni Ostvik (Västerbott. l.).\n\nTelefon: 29. Postgiro: 65672. —\nArb.-antal: 12. Tillv.-värde pr år: 70,000 kr.\n— Fabriken anlagd 1928.\n\nÄgare o. chef: fabr. E. Manfred\nLindgren.\n\nAB. Carl Ottossons Remfabrik,\n\nAnderstorp.\n\nTillverkar livremmar och bälten,\nsportartiklar, ryggsäckar, shoppingväskor,\nres-effekter m. m. vid fabrik i Anderstorp\n(Jönköp. l.). Varumärke: »Carlo»,.\n\nTelegr.-adr.: Carlo, Anderstorp.\nTelefon: »Carlobolaget». Postgiro: 28814.\n\nAkt.-kap.: 100,000 kr. Antal\nindustriarb.: 50. Tillv.-värde pr år: 2,000,000 kr.\n— Firman grundad 1921, bolag 1945.\n\nVerkst. dir.: Holge Ottosson.\n\nAB. Karl G. Ottosson, Falköping.\n\nTrikåfabrik. Tillverkar koftor,\njumpers, blusar, klänningar, baddräkter,\nbadbyxor, scarves, babyartiklar m. m.\n\nTelegr.-adr. o. telefon: Ottossons,\nFalköping. Postgiro: 76520. — Akt.-kap.:\n650,000 kr. Antal industriarb.: 300.\nTillv.-värde pr år: 5,000,000 kr. — Firman\netabl. 1924, bolag 1940.\n\nVerkst. dir.: Karl G. Ottosson.\n\nE. S. Ouchterlony &amp; Comp.,\n\nTrångsviken.\n\nSågverk och hyvleri i Trångsviken\n(Jämtl. l.). Tillverkar sågade och\nhyvlade trävaror.\n\nTelegr.-adr.: Ouchterlony, Trångsviken.\nTelefon: 10. — Antal industriarb.: 40.\nÅrstillv.: 3,500 stds trävaror. — Firman\netabl. 1907.\n\nÄgare o. chef: ing. E. S. Ouchterlony.\n\nOusby Kimröks Fabriks AB.,\n\nOsby.\n\nKimröksfabrik vid Skansen, Osby\n(Kristianst. l.). Tillverkar kimrök.\n\nTelegr.-adr.: Kimrök, Osby. Telefon:\n17. Postgiro: 85300. — Akt.-kap.: 79,000\nkr. Arb.-antal: 10. Tillv.-värde pr år:\n100,000 kr. — Bolaget grundat 1887.\nVerkst. dir. o. disp.: Joh. Ekman.\nKamrer: Ernst Rooth.\n\n431*",
    "structured": {
        "1": {
            "name": "AB. Osram-Elektraverken",
            "location": "Stockholm",
            "business": "Glödlampfabrik. Tillverkar metalltrådslampor av märket »Osram».",
            "contact": {
                "office": "Ringvägen 98",
                "phone": [
                    "Osram, Stockholm"
                ],
                "postgiro": "727"
            },
            "financials": {
                "capital": "2,750,000 kr",
                "employees": {
                    "industriarb.": 300
                }
            },
            "foundation_year": 1917,
            "corporation_year": 1930,
            "board": [
                {
                    "name": "W. Borgquist",
                    "role": "generaldirektör"
                },
                {
                    "name": "Jerker Henke",
                    "role": "direktör"
                },
                {
                    "name": "Linus Lindberg",
                    "role": "advokat"
                },
                {
                    "name": "Edy Veländer",
                    "role": "professor"
                }
            ]
        },
        "2": {
            "name": "AB. Hans Österman",
            "location": "Stockholm",
            "business": "Bilreparations- och serviceverkstäder. Utför bilreparationer och monteringar av bilar. Firman driver försäljning av automobiler och gummiringar.",
            "contact": {
                "office": "Birger Jarlsg. 18",
                "phone": [
                    "Hans Österman"
                ],
                "postgiro": "767"
            },
            "financials": {
                "capital": "1,500,000 kr"
            },
            "foundation_year": 1908,
            "corporation_year": 1915,
            "board": [
                {
                    "name": "Rich. Julin",
                    "role": "bankdirektör"
                },
                {
                    "name": "Olle Engkvist",
                    "role": "byggmästare"
                },
                {
                    "name": "Gösta Grönberg",
                    "role": "advokat"
                },
                {
                    "name": "Lennart Österman",
                    "role": "ingenjör"
                }
            ],
            "director": "Lennart Österman",
            "sales_manager": "K.-H. Björngård"
        },
        "3": {
            "name": "John Österman, Elektr. AB.",
            "location": "Stockholm"
        },
        "4": {
            "name": "Ostvik-Snickerifabrik",
            "location": "Ostvik",
            "products": "Tillverkar fönster och dörrar samt bostads- och butiksinredningar.",
            "contact": {
                "phone": "29",
                "postgiro": "65672"
            },
            "financials": {
                "employees": 12,
                "annual_production_value": "70,000 kr"
            },
            "foundation_year": 1928
        },
        "5": {
            "name": "AB. Carl Ottossons Remfabrik",
            "location": "Anderstorp",
            "products": "Tillverkar livremmar och bälten, sportartiklar, ryggsäckar, shoppingväskor, res-effekter m. m.",
            "contact": {
                "telegraph": "Carlo, Anderstorp",
                "phone": "Carlobolaget",
                "postgiro": "28814"
            },
            "financials": {
                "capital": "100,000 kr",
                "employees": 50,
                "annual_production_value": "2,000,000 kr"
            },
            "foundation_year": 1921,
            "corporation_year": 1945,
            "director": "Holge Ottosson"
        },
        "6": {
            "name": "AB. Karl G. Ottosson",
            "location": "Falköping",
            "business": "Trikåfabrik. Tillverkar koftor, jumpers, blusar, klänningar, baddräkter, badbyxor, scarves, babyartiklar m. m.",
            "contact": {
                "phone": "Ottossons, Falköping",
                "postgiro": "76520"
            },
            "financials": {
                "capital": "650,000 kr",
                "employees": 300,
                "annual_production_value": "5,000,000 kr"
            },
            "foundation_year": 1924,
            "corporation_year": 1940,
            "director": "Karl G. Ottosson"
        },
        "7": {
            "name": "E. S. Ouchterlony & Comp.",
            "location": "Trångsviken",
            "products": "Tillverkar sågade och hyvlade trävaror.",
            "contact": {
                "phone": "10"
            },
            "financials": {
                "employees": 40,
                "annual_production_value": "3,500 stds trävaror"
            },
            "foundation_year": 1907,
            "director": "E. S. Ouchterlony"
        },
        "8": {
            "name": "Ousby Kimröks Fabriks AB.",
            "location": "Osby",
            "business": "Kimröksfabrik. Tillverkar kimrök.",
            "contact": {
                "phone": "17",
                "postgiro": "85300"
            },
            "financials": {
                "capital": "79,000 kr",
                "employees": 10,
                "annual_production_value": "100,000 kr"
            },
            "foundation_year": 1887,
            "director": "Joh. Ekman",
            "sales_manager": "Ernst Rooth"
        }
    }
}