{
    "original": "Falkenberg—Falu\n\noch skolor; utför dörrar och fönster av\nsvensk standardtyp.\n\nTelegr.-adr.: Snickerifabrik,\nFalkenberg. Telefon: 308. Postgiro: 86695.\n\nAkt.-kap.: 50,000 kr. Antal\nindustriarb.: 15. — Firman etabl. 1918,\nombilda-des till bolag 1924.\n\nStyrelse: byggm. Janne Andersson\n(ordf.), disp. Otto J. Johansson, disp. O.\nTheodor Larsson, modellsnickare Alfr. G.\nSvensson, trädgårdsm. Anders M. J.\nSvensson.\n\nDisponenter: för snickerifabriken: O.\nJ. Johansson; för möbelfabriken: O. T.\nLarsson.\n\n* Falkenbergs Tegelbruks AB.,\n\nFalkenberg.\n\nTillverkar murtegel, lättegel, håltegel,\nmellanväggsplattor, tak- och\nreveterings-tegel samt dräneringsrör.\n\nTelegr.-adr.: Tegelbruket, Falkenberg.\nTelefon: 48 o. 748.\n\nAkt.-kap.: 150.000 kr. Årstillv.: 5 milj.\nst. tegel varor. — Tegelbruket anlagt\n1904, bolaget grundat 1914.\n\nStyrelse: lantbr. Sven-Ivar\nChristians-son, dir. Erik Lindvall, disp. Tore\nLindvall.\n\nDisp.: Tore Lindvall.\n\n*AB. Falköpings Mek. Verkstad,\n\nFalköping.\n\nMek. verkstad i Falköping, samt\ntackjärnsgjuter i (»Kilshammars Gjuteri») i\nKristinehamn.\n\nTillverkar verktygsmaskiner såsom\nsvarvar, borrmaskiner,\navskämingsma-skiner m. m.\n\nKontor: Falköping. Telegr.-adr.:\nMek-verkstaden, Falköping. Telefon: 29 o. 426.\nPostgiro: 6406. — Akt.-kap.: 150,000 kr.\nAntal industriarb.: 40, varav i Falköping\n30. — Firman etabl. 1880, bolag 1922.\n\niStyrelse: fabr. Sven Frisk (ordf.), fabr.\nFrans Engstrand, disp. Ingvar Frisk.\n\nVerkst. dir.: Sven Frisk.\n\n^Falköpings Textilfabriks AB.,\n\nFalköping.\n\nTrikåfabrik. Tillverkar jumpers,\njackor, västar samt badartiklar m. m.\n\nTelefon: 354. Postgiro: 83540. —\nAkt.-kap.: 45,000 kr. — Bolaget grundat 1927.\n\nStyrelse: disp. Sven Gustavson (ordf.),\nfru E. J. Brandt, herr Johan Gustafsson.\n\nVerkst. dir. o. disp.: Sven Gustavson.\n\n*AB. G. I. Fall, Eskilstuna.\n\nSmidesverkstad och stålvarufabrik.\nTillverkar borrar för träbearbetning samt\nskruvmejslar. Varumärke: C. I. F.\nSwe-den.\n\nTelefon: 30583, 36583 o. 35783.\nPostgiro: 10784. — Akt.-kap.: 100,000 kr.\nAntal industriarb.: 70. Tillv.-värde pr år:\n900,000 kr. — Firman etabl. 1894-, bolag\n1928.\n\nStyrelse: fabr. Erik Fall, fabr. Carl\nFall, ing. Gösta Fall.\n\nVerkst. dir.: Gösta Fall.\n\nKontorschef: Isidor Fall.\n\nC. M. Fall &amp; Son, Eskilstuna.\n\nVerktygsfabrik. Tillverkar\nsnickeriverktyg såsom vinklar, cirklar samt\nträborrar m. m.\n\nTelefon: 30688. Postgiro: 10788. —\nAntal industriarb.: 12. Tillv.-.värde’pr år:\n122,000 kr. — Firman etabl. 1883.\n\nÄgare o. chef: fabr. Wilhelm Fall.\n\nFalu Industri AB-, Korsnäs.\n\nManufakturverk och mek. verkstad i\nKorsnäs (Kopparb. l.). Tillverkar\nträdgårds- och skogsredskap, murareverktyg,\nskäror, oljecisterner och oljeeldade ugnar,\ntransportvagnar m. m. Bolaget levererar\näven färdigkokad Falu rödfärg.\n\nTelegr.-adr.: industribol, Korsnäs.\nTelefon: 34 o. 63. Postgiro: 85099.\n\nAkt.-kap.: 30,000 kr. Antal\nindustriarb.: 25. Tillv.-värde pr år: 200,000 kr. —\nBolaget grundat 1933.\n\nVerkst. dir.: civiling. Gösta Bjurner.\n\n*Falu Kopparverk, Falun,\n\nFalu gruva med anrikningsverk,\nrödfärgsverk, talkkvarn, kopparhytta,\nkemiska fabriker samt mek. verkstad och\ngjuteri i Falun.\n\nBryter svavelkis, zink-, bly- och\nkopparmalmer samt talk; tillverkar zink-,\nbly- och kopparsliger, koppar- och\njärn-vitrio!, svavelsyra, vanadinsyra,\netylace-tat, rödfärg (»Falu rödfärg»), ättiksyra\nsamt ättiksyreanhydrid.\n\nTelefon: 391. — Försäljningen sker\ngenom Stora Kopparbergs Bergslags AB.,\nFalun, som äger verket (se detta bolag).\nTelefon: »Bergslaget», Falun.\n\nAntal industriarb.: 450. — Falu gruva\nbörjade bearbetas på 1200-talet.\n\nPlatschef: övering. Folke Lagergren.\n\nFörsäljn.-chef: intendent Bo Stenberg.",
    "structured": {
        "firms": [
            {
                "name": "Falkenbergs Tegelbruks AB.",
                "location": "Falkenberg",
                "description": "Tillverkar murtegel, lättegel, håltegel, mellanväggsplattor, tak- och reveterings-tegel samt dräneringsrör.",
                "telegraph": "Tegelbruket, Falkenberg",
                "phone": [
                    "48",
                    "748"
                ],
                "postgiro": "86695",
                "financials": {
                    "capital": "150,000 kr",
                    "annual_turnover": "5 milj. st. tegel varor"
                },
                "foundation_year": 1914,
                "board": [
                    {
                        "name": "Sven-Ivar Christians-son",
                        "role": "lantbr."
                    },
                    {
                        "name": "Erik Lindvall",
                        "role": "dir."
                    },
                    {
                        "name": "Tore Lindvall",
                        "role": "disp."
                    }
                ],
                "director": "Tore Lindvall"
            },
            {
                "name": "AB. Falköpings Mek. Verkstad",
                "location": "Falköping",
                "description": "Mek. verkstad i Falköping, samt tackjärnsgjuter i (»Kilshammars Gjuteri») i Kristinehamn. Tillverkar verktygsmaskiner såsom svarvar, borrmaskiner, avskämingsma-skiner m. m.",
                "telegraph": "Mek-verkstaden, Falköping",
                "phone": [
                    "29",
                    "426"
                ],
                "postgiro": "6406",
                "financials": {
                    "capital": "150,000 kr"
                },
                "foundation_year": 1922,
                "board": [
                    {
                        "name": "Sven Frisk",
                        "role": "fabr."
                    },
                    {
                        "name": "Frans Engstrand",
                        "role": "fabr."
                    },
                    {
                        "name": "Ingvar Frisk",
                        "role": "disp."
                    }
                ],
                "director": "Sven Frisk"
            },
            {
                "name": "Falköpings Textilfabriks AB.",
                "location": "Falköping",
                "description": "Trikåfabrik. Tillverkar jumpers, jackor, västar samt badartiklar m. m.",
                "phone": [
                    "354"
                ],
                "postgiro": "83540",
                "financials": {
                    "capital": "45,000 kr"
                },
                "foundation_year": 1927,
                "board": [
                    {
                        "name": "Sven Gustavson",
                        "role": "disp."
                    },
                    {
                        "name": "E. J. Brandt",
                        "role": "fru"
                    },
                    {
                        "name": "Johan Gustafsson",
                        "role": "herr"
                    }
                ],
                "director": "Sven Gustavson"
            },
            {
                "name": "AB. G. I. Fall",
                "location": "Eskilstuna",
                "description": "Smidesverkstad och stålvarufabrik. Tillverkar borrar för träbearbetning samt skruvmejslar.",
                "contact": {
                    "phone": "30583, 36583 o. 35783",
                    "postgiro": "10784"
                },
                "financials": {
                    "capital": "100,000 kr"
                },
                "foundation_year": 1928,
                "board": [
                    {
                        "name": "Erik Fall",
                        "role": "fabr."
                    },
                    {
                        "name": "Carl Fall",
                        "role": "fabr."
                    },
                    {
                        "name": "Gösta Fall",
                        "role": "ing."
                    }
                ],
                "director": "Gösta Fall",
                "manager": "Isidor Fall"
            },
            {
                "name": "C. M. Fall & Son",
                "location": "Eskilstuna",
                "description": "Verktygsfabrik. Tillverkar snickeriverktyg såsom vinklar, cirklar samt träborrar m. m.",
                "phone": [
                    "30688"
                ],
                "postgiro": "10788",
                "financials": {
                    "annual_production_value": "122,000 kr"
                },
                "foundation_year": 1883,
                "manager": "Wilhelm Fall"
            },
            {
                "name": "Falu Industri AB-",
                "location": "Korsnäs",
                "description": "Manufakturverk och mek. verkstad i Korsnäs (Kopparb. l.). Tillverkar trädgårds- och skogsredskap, murareverktyg, skäror, oljecisterner och oljeeldade ugnar, transportvagnar m. m. Bolaget levererar även färdigkokad Falu rödfärg.",
                "telegraph": "industribol, Korsnäs",
                "phone": [
                    "34",
                    "63"
                ],
                "postgiro": "85099",
                "financials": {
                    "capital": "30,000 kr",
                    "annual_production_value": "200,000 kr"
                },
                "foundation_year": 1933,
                "director": "Gösta Bjurner"
            },
            {
                "name": "Falu Kopparverk",
                "location": "Falun",
                "description": "Falu gruva med anrikningsverk, rödfärgsverk, talkkvarn, kopparhytta, kemiska fabriker samt mek. verkstad och gjuteri i Falun. Bryter svavelkis, zink-, bly- och kopparmalmer samt talk; tillverkar zink-, bly- och kopparsliger, koppar- och järn-vitrio!, svavelsyra, vanadinsyra, etylacetat, rödfärg (»Falu rödfärg»), ättiksyra samt ättiksyreanhydrid.",
                "phone": [
                    "391"
                ],
                "financials": {
                    "employees": {
                        "industriarbetare": 450
                    }
                },
                "original_name": "Falu gruva",
                "corporation_year": 1928,
                "director": "Folke Lagergren",
                "sales_manager": "Bo Stenberg"
            }
        ]
    }
}