{
    "original": "Magnusson—Malmberg\n\n\"A. Magnussons Orgelbyggeri,\n\nGöteborg.\n\nTillverkar piporglar för kyrkor och\nkonsertsalar.\n\nKontor: Dämmevägen 19. Telefon:\n151279. Postgiro: 40803.. — Arb.-antal:\n\n14.\tTillv.-värde pr år: 150,000 kr. —\nFirman etabl. 1888,\n\nÄgare o. chef: civiling. Anders\nMagnusson.\n\nArv. H. Magnusson, Flen.\n\nSvarveri i Flen (Södermanl. l.).\nTillverkar svarvade massartiklar och kanoter.\n\nTelefon: 126. — Antal industriarb.:\n\n15.\tTillv.-värde pr år: 90,000 kr. —\nFirman etabl. 1921.\n\nÄgare o. chef: svarvare Arv. H.\nMagnusson.\n\n*AB. Carl M. Magnussons\nChoklad-&amp; Konfektfabrik, Malmö.\n\nTi] Iverkar kakao, choklad, konfekt och\nkarameller. Varumärke: »Magno».\n\nKontor: Fosievägen. Telegr.-adr.:\nMagnocarl, Malmö. Telefon: 23833 o.\n24800. Postgiro: 38057.\n\nAkt.-kap.: 200,000 kr. Antal\nindustriarb.: 60. Tillv.-värde pr år: 1,000,000 kr.\n— Firman etabl. 1911, bolag 1927.\n\nStyrelse: herr Carl Magnusson, fru\nGreta Magnusson.\n\nVerkst. dir.: fru Greta Magnusson.\n\n\"Fr. Magnussons Möbelfabrik AB.,\n\nBor.\n\nMöbelfabrik, sågverk och elektr.\nvattenkraftverk vid Värmeshult, Bor (Jönköp.\n1.). Tillverkar möbler samt distribuerar\nelektr. energi. Bolaget driver även kvarn\nsamt jordbruk och skogshantering.\n\nKontor: Värmeshult; postadr.: Bor.\nTelefon; Värnamo 53012. Postgiro: 9418.\n\nAkt.-kap.: 432,000 kr. Antal\nindustriarb.: 10. — Firman etabl. 1900, bolag\n1934.\n\nStyrelse: fru S. Magnusson (ordf.),\ndisp. Bernhard Magnusson, kamrer\nMagnus Magnusson.\n\nVerkst. dir.: Bernhard Magnusson.\n\nAB. Maj or nas Ångbageri,\n\nGöteborg.\n\nTillverkar bröd, konditorivaror och\nknäckebröd.\n\nKontor: Allmänna Vägen 40; postadr.:\nGöteborg 4. Telegr.-adr.: Majbageri,\nGöteborg. Telefon: »Pååls bröd». Postgiro:\n42543.\n\nAkt.-kap.: 501,500 kr. Antal\nindustriarb.: 180. Tillv.-värde pr år: 5,000,000 kr.\n— Firman etabl. 1883 av O. E.\nSegerdahl, bolag 1906.\n\nStyrelse: dir. Frans Påhlsson.\n\nVerkst. dir.: Albert Påhlsson.\n\nDisp.: Lars Påhlsson.\n\nMakadam- &amp; Murbruksfabriken\n\nSvanevik, Åsumtorp.\n\nFramställer makadam samt mur-,\nputsbruk och fin-putsbruk vid fabrik i\nSvanevik, Åsumtorp (Kristianst. l.).\n\nTelefon: Kristianstad 10671. Postgiro:\n97486. — Antal industriarb.: 18.\nProd.-värde pr år: 225,000 kr. — Firman etabl.\n1920.\n\nÄgare o. chef: dir. Torsten Nilsson.\n\nMakaronibolaget, Svenska\nMaka-ronifabrikers Försäljnings AB.,\n\nGöteborg.\n\nBolaget är försäljningsorganisation för\nNorrköpings Makaronifabriks AB:s\ntillverkning av makaroner, spaghetti och\nvermiceller. Varumärken: »Munk» o.\n»Drott».\n\nKontor: Lilla Bommenstorg 2.\nTelegr.-adr.: Makaronibolaget, Göteborg. Telefon:\n135847. Postgiro: 12021.\n\nAkt.-kap.: 30,000 kr. — Bolaget\ngrundat 1923.\n\nVerkst. dir.: Alarik Arthur (Åby).\n\n\"Malcus, Halmstad.\n\nSe AB. Malcus Holmquist, Halmstad.\n\n\"AB. Elof Malmberg, Gävle.\n\nFabrik för sport- och läderartiklar.\nTillverkar flaggor, hängmattor, tält,\nträdgårdsparaplyer, markiser, ryggsäckar,\nskidbindslen samt utrustning för\nskidåkning, ishockey- och bandysport,\nfotbollsartiklar, kartfodral, hästutrustnings-,\ntravsports-, hundutrustnings-, jakt-,\nskytte-, militär- och scoutartiklar,\nbagagesäckar, packfickor samt\nsadelmakeriar-tiklar för järnvägar.\n\nInreg. varunamn: The King, Tirfing,\nGoal, Iron. Heja, Pysen, Mascot, Hobby,\nKompis, Blixt, Måsen, Final, Buster,\nCyklon, Yrhättan, Campus o. Träff.\n\nTelefon: 1637, 2207, 3973 o. 4712.\nPostgiro: 22217. — Akt.-kap.: 120,000 kr.\nAntal industriarb.: 125. Tillv.-värde pr\når: 1,200,000 kr. — Firman etabl. 1905,\nbolag 1913.",
    "structured": {
        "1": {
            "name": "A. Magnussons Orgelbyggeri",
            "location": "Göteborg",
            "business": "Tillverkar piporglar för kyrkor och konsertsalar",
            "contact": {
                "office": "Dämmevägen 19",
                "phone": [
                    "151279"
                ],
                "postgiro": "40803",
                "factory_office": "Svarveri i Flen",
                "factory_phone": "126"
            },
            "financials": {
                "capital": "N/A",
                "employees": {
                    "Arb.-antal": 14
                },
                "annual_turnover": "150,000 kr",
                "annual_production_value": "N/A"
            },
            "foundation_year": 1888,
            "current_name_year": "N/A",
            "predecessor": "N/A",
            "original_name": "N/A",
            "corporation_year": "N/A",
            "owners": [
                "civiling. Anders Magnusson"
            ],
            "director": "civiling. Anders Magnusson",
            "manager": "N/A"
        },
        "2": {
            "name": "Arv. H. Magnusson",
            "location": "Flen",
            "business": "Tillverkar svarvade massartiklar och kanoter",
            "contact": {
                "office": "N/A",
                "phone": [
                    "126"
                ],
                "postgiro": "N/A",
                "factory_office": "N/A",
                "factory_phone": "N/A"
            },
            "financials": {
                "capital": "N/A",
                "employees": {
                    "Antal industriarb.": 15
                },
                "annual_turnover": "90,000 kr",
                "annual_production_value": "N/A"
            },
            "foundation_year": 1921,
            "current_name_year": "N/A",
            "predecessor": "N/A",
            "original_name": "N/A",
            "corporation_year": "N/A",
            "owners": [
                "svarvare Arv. H. Magnusson"
            ],
            "director": "svarvare Arv. H. Magnusson",
            "manager": "N/A"
        },
        "3": {
            "name": "AB. Carl M. Magnussons Choklad-& Konfektfabrik",
            "location": "Malmö",
            "business": "Tillverkar kakao, choklad, konfekt och karameller",
            "contact": {
                "office": "Fosievägen",
                "phone": [
                    "23833",
                    "24800"
                ],
                "postgiro": "38057",
                "sales_offices": [
                    {
                        "location": "N/A",
                        "phone": "N/A"
                    }
                ],
                "factory_office": "N/A",
                "factory_phone": "N/A",
                "telegraph": "Magnocarl, Malmö"
            },
            "financials": {
                "capital": "200,000 kr",
                "employees": "N/A",
                "annual_turnover": "1,000,000 kr",
                "annual_production_value": "N/A"
            },
            "foundation_year": 1911,
            "current_name_year": 1927,
            "predecessor": "N/A",
            "original_name": "N/A",
            "corporation_year": "N/A",
            "owners": [
                "herr Carl Magnusson",
                "fru Greta Magnusson"
            ],
            "director": "fru Greta Magnusson",
            "manager": "N/A"
        },
        "4": {
            "name": "Fr. Magnussons Möbelfabrik AB.",
            "location": "Bor",
            "business": "Möbelfabrik, sågverk och elektr. vattenkraftverk vid Värmeshult",
            "contact": {
                "office": "Värmeshult",
                "phone": [
                    "Värnamo 53012"
                ],
                "postgiro": "9418",
                "sales_offices": [
                    {
                        "location": "N/A",
                        "phone": "N/A"
                    }
                ],
                "factory_office": "N/A",
                "factory_phone": "N/A",
                "telegraph": "N/A"
            },
            "financials": {
                "capital": "432,000 kr",
                "employees": "N/A",
                "annual_turnover": "N/A",
                "annual_production_value": "N/A"
            },
            "foundation_year": 1900,
            "current_name_year": 1934,
            "predecessor": "N/A",
            "original_name": "N/A",
            "corporation_year": "N/A",
            "owners": [
                "fru S. Magnusson"
            ],
            "director": "N/A",
            "manager": "Bernhard Magnusson"
        },
        "5": {
            "name": "AB. Major Nas Ångbageri",
            "location": "Göteborg",
            "business": "Tillverkar bröd, konditorivaror och knäckebröd",
            "contact": {
                "office": "Allmänna Vägen 40",
                "phone": [
                    "N/A"
                ],
                "postgiro": "42543",
                "sales_offices": [
                    {
                        "location": "N/A",
                        "phone": "N/A"
                    }
                ],
                "factory_office": "N/A",
                "factory_phone": "N/A",
                "telegraph": "Majbageri, Göteborg"
            },
            "financials": {
                "capital": "501,500 kr",
                "employees": "N/A",
                "annual_turnover": "5,000,000 kr",
                "annual_production_value": "N/A"
            },
            "foundation_year": 1883,
            "current_name_year": 1906,
            "predecessor": "N/A",
            "original_name": "N/A",
            "corporation_year": "N/A",
            "owners": [
                "O. E. Segerdahl"
            ],
            "director": "N/A",
            "manager": "Albert Påhlsson"
        },
        "6": {
            "name": "Makadam- & Murbruksfabriken Svanevik",
            "location": "Åsumtorp",
            "business": "Framställer makadam samt mur-, putsbruk och fin-putsbruk",
            "contact": {
                "office": "Svanevik, Åsumtorp",
                "phone": [
                    "Kristianstad 10671"
                ],
                "postgiro": "97486",
                "sales_offices": [
                    {
                        "location": "N/A",
                        "phone": "N/A"
                    }
                ],
                "factory_office": "N/A",
                "factory_phone": "N/A",
                "telegraph": "N/A"
            },
            "financials": {
                "capital": "N/A",
                "employees": {
                    "Antal industriarb.": 18
                },
                "annual_turnover": "225,000 kr",
                "annual_production_value": "N/A"
            },
            "foundation_year": 1920,
            "current_name_year": "N/A",
            "predecessor": "N/A",
            "original_name": "N/A",
            "corporation_year": "N/A",
            "owners": [
                "dir. Torsten Nilsson"
            ],
            "director": "N/A",
            "manager": "N/A"
        },
        "7": {
            "name": "Makaronibolaget, Svenska Maka-ronifabrikers Försäljnings AB.",
            "location": "Göteborg",
            "business": "Bolaget är försäljningsorganisation för Norrköpings Makaronifabriks AB:s tillverkning av makaroner, spaghetti och vermiceller",
            "contact": {
                "office": "Lilla Bommenstorg 2",
                "phone": [
                    "135847"
                ],
                "postgiro": "12021",
                "sales_offices": [
                    {
                        "location": "N/A",
                        "phone": "N/A"
                    }
                ],
                "factory_office": "N/A",
                "factory_phone": "N/A",
                "telegraph": "Makaronibolaget, Göteborg"
            },
            "financials": {
                "capital": "30,000 kr",
                "employees": "N/A",
                "annual_turnover": "N/A",
                "annual_production_value": "N/A"
            },
            "foundation_year": "N/A",
            "current_name_year": "N/A",
            "predecessor": "N/A",
            "original_name": "N/A",
            "corporation_year": "N/A",
            "owners": [
                "N/A"
            ],
            "director": "N/A",
            "manager": "Alarik Arthur (Åby)"
        },
        "8": {
            "name": "AB. Elof Malmberg",
            "location": "Gävle",
            "business": "Fabrik för sport- och läderartiklar. Tillverkar flaggor, hängmattor, tält, trädgårdsparaplyer, markiser, ryggsäckar, skidbindslen samt utrustning för skidåkning, ishockey- och bandysport, fotbollsartiklar, kartfodral, hästutrustnings-, travsports-, hundutrustnings-, jakt-, skytte-, militär-, och scoutartiklar, bagagesäckar, packfickor samt sadelmakeriartiklar för järnvägar. Inreg. varunamn: The King, Tirfing, Goal, Iron, Heja, Pysen, Mascot, Hobby, Kompis, Blixt, Måsen, Final, Buster, Cyklon, Yrhättan, Campus och Träff",
            "contact": {
                "office": "N/A",
                "phone": [
                    "1637",
                    "2207",
                    "3973",
                    "4712"
                ],
                "postgiro": "22217",
                "factory_office": "N/A",
                "factory_phone": "N/A",
                "telegraph": "N/A"
            },
            "financials": {
                "capital": "120,000 kr",
                "employees": "N/A",
                "annual_turnover": "1,200,000 kr",
                "annual_production_value": "N/A"
            },
            "foundation_year": 1905,
            "current_name_year": 1913,
            "predecessor": "N/A",
            "original_name": "N/A",
            "corporation_year": "N/A",
            "owners": [
                "N/A"
            ],
            "director": "N/A",
            "manager": "N/A"
        }
    }
}