{
    "original": "Nittsjö—Norberg\n\nAB. Nittsjö Sten kärlsfabrik,\n\nRättvik.\n\nKeramikfabrik i Rättvik (Kopparb. l.).\nTillverkar keramik, blomkrukor ock\nhus-gerådskärl.\n\nTelefon: 80 o. 380. Postgiro: 70938. —\nAkt.-kap.: 110,000 kr. Antal industriarb.:\n60. — Fabriken grundlagd 1847, bolag\n1917.\n\nStyrelse: kyrkvärd S. Anders\nAndersson, disp. S. Anders Hansson, disp. Åke\nLöfgren.\n\nDisp.: Åke Löfgren.\n\nAB. Njurunda Industrier, Njurunda.\n\nSe Nya AB. Njurunda Industrier,\nNjurunda.\n\n*Nohab Flygmotorfabriker AB.,\n\nTrollhättan.\n\nSe Svenska Flygmotor AB.,\nTrollhättan.\n\n*AB. Nol-Tingstad, Mariestad.\n\nFörsäljningsbolag för vissa av\nKatrine-forsbolagens tillverkningar bl. a.\nhårdpapp, konstläderpapp, läderit och noloid\n(pegamoid).\n\nHuvud- o. försäljn.-kontor: Mariestad.\nTelegr.-adr. o. telefon: Nolfiber,\nMariestad. Postgiro: 40634.\n\nAkt.-kap.: 900,000 kr. — Bolaget,\ngrundat 1915 under namn AB.\nKonstläder-fabriken, ombildat 1922, äges av\nKatrine-fors AB.\n\nStyrelse: disp. Richard Hedlund\n(ordf.), ing. Paul Gibson, dir. Carl\nOldby.\n\nVerkst. dir.: Richard Hedlund.\n\nBitr. dir.: Carl Oldby.\n\nFörsäljn.-chef: intend. Sven Runnquist.\n\n*AB. Nomy, TJlvsunda.\n\nSe Ulvsunda Verkstäder AB., Ulvsunda.\n\n*Nora Bryggeri AB., Nora.\n\nTillverkar malt- och läskedrycker.\n\nTelefon: 32. Postgiro: 28330. —\nAkt.-kap.: 50,000 kr. Arb.-antal: 8.\nTillv.-värde pr år: 250,000 kr. — Bolaget\ngrundat 1912.\n\nStyrelse: bryggm. Bengt Hallander\n(ordf.), disp. Harald Hallander, fru M.\nHallander.\n\nVerkst. dir. o. disp.: Harald Hallander.\n\nAB. Nora Gjuteri &amp; Mek. Verkstad,\n\nNora.\n\nTillverkar gjutgods och utför mek.\nverkstadsarbeten.\n\nTelefon: 30. Postgiro: 93456. —\nAkt.-kap.: 75,000 kr. Antal industriarb.: 20.\nTillv.-värde pr år: 300,000 kr. — Firman\netabl. 1896, bolag 1920.\nDisp.: Erik W. Järnerot.\n\nNora Möbelfabrik, Nora.\n\nTillverkar rökbord och\nkompletteringsmöbler.\n\nTelefon: 374. — Antal industriarb.: 12.\nTillv.-värde pr år: 100,000 kr. — Firman\netabl. 1917.\n\nÄgare: fru Elisabet Löfgren.\n\nDisp.: Bertil Löfgren.\n\n*Nora Tegelbruk, Svartsjö.\n\nSe AB. Mälardalens Tegelbruk,\nStockholm.\n\n*AB. Nora Tändrörsfabrik,\n\nGrängesberg.\n\nTillverkar stubintråd vid fabrik i Nora.\nHuvudkontor: Grängesberg (Kopparb.\n1.). Telefon: »Förvaltningen»,\nGrängesberg. Postgiro: 71374. Ensamförsälj.: AB.\nExpressdynamit, Grängesberg samt\nNi-troglycerin AB., Gyttorp o. Stockholm.\n\nAkt.-kap.: 280,000 kr. Antal\nindustriarb.: 70. Tillv.-värde pr år: 1,200,000 kr.\n— Bolaget grundat 1899.\n\nStyrelse: disp. O. G. Granström, disp.\nErik Malm, fil. dr Sigurd Nauckhoff.\nVerkst. dir.: C. G. Granström.\nFabriksförest.: ing. Birger Nauckhoff.\n\n*C. Aug. Norberg, Motala.\n\nManufakturverk. Tillverkar spadar,\nskyfflar, grepar och högafflar, skaft samt\neldningsredskap.\n\nTelegr.-adr.: Bergspade, Motala.\nTelefon: 397. Postgiro: 31467. — Antal\nindustriarb.: 26. Tillv.-värde pr år: 700,000\nkr. — Firman etabl. 1890.\n\nÄgare o. chefer: fabr. Eric Norberg o.\nfabr. Olof Norberg.\n\n* Norbergs Gruf AB., Kärrgruvan.\n\nSe Norbergs Grufförvaltning,\nKärrgruvan.\n\n394*",
    "structured": {
        "1": {
            "name": "AB. Nittsjö Sten kärlsfabrik",
            "location": "Rättvik",
            "business": "Keramikfabrik i Rättvik (Kopparb. l.)",
            "products": "Tillverkar keramik, blomkrukor ock hus-gerådskärl",
            "contact": {
                "office": "Telefon: 80 o. 380",
                "phone": [
                    "80",
                    "380"
                ],
                "postgiro": "70938",
                "head_office": "N/A",
                "sales_offices": [],
                "telegraph": "N/A",
                "factory_office": "N/A",
                "factory_phone": "N/A"
            },
            "financials": {
                "capital": "110,000 kr",
                "employees": {
                    "industriarb": 60
                },
                "annual_turnover": "N/A",
                "annual_production_value": "N/A"
            },
            "foundation_year": 1847,
            "current_name_year": 1917,
            "predecessor": "N/A",
            "original_name": "N/A",
            "corporation_year": "N/A",
            "board": [
                {
                    "name": "S. Anders Andersson",
                    "role": "kyrkvärd"
                },
                {
                    "name": "S. Anders Hansson",
                    "role": "disp."
                },
                {
                    "name": "Åke Löfgren",
                    "role": "disp."
                }
            ],
            "owners": [],
            "director": "Åke Löfgren",
            "managing_director": "N/A",
            "sales_manager": "N/A",
            "manager": "N/A"
        },
        "2": {
            "name": "AB. Njurunda Industrier",
            "location": "Njurunda",
            "business": "N/A"
        },
        "3": {
            "name": "AB. Nol-Tingstad",
            "location": "Mariestad",
            "business": "Försäljningsbolag för vissa av Katrine-forsbolagens tillverkningar bl.a. hårdpapp, konstläderpapp, läderit och noloid (pegamoid)",
            "contact": {
                "office": "Huvud- o. försäljn.-kontor: Mariestad",
                "phone": "N/A",
                "postgiro": "40634",
                "head_office": "N/A",
                "sales_offices": [],
                "telegraph": "Nolfiber, Mariestad",
                "factory_office": "N/A",
                "factory_phone": "N/A"
            },
            "financials": {
                "capital": "900,000 kr",
                "employees": {},
                "annual_turnover": "N/A",
                "annual_production_value": "N/A"
            },
            "foundation_year": 1915,
            "current_name_year": 1922,
            "predecessor": "N/A",
            "original_name": "AB. Konstläder-fabriken",
            "corporation_year": "N/A",
            "board": [
                {
                    "name": "Richard Hedlund",
                    "role": "disp."
                },
                {
                    "name": "Paul Gibson",
                    "role": "ing."
                },
                {
                    "name": "Carl Oldby",
                    "role": "dir."
                }
            ],
            "owners": [],
            "director": "Richard Hedlund",
            "managing_director": "Carl Oldby",
            "sales_manager": "Sven Runnquist",
            "manager": "N/A"
        },
        "4": {
            "name": "AB. Nora Bryggeri",
            "location": "Nora",
            "business": "Tillverkar malt- och läskedrycker"
        },
        "5": {
            "name": "AB. Nora Gjuteri & Mek. Verkstad",
            "location": "Nora",
            "business": "Tillverkar gjutgods och utför mek. verkstadsarbeten",
            "contact": {
                "office": "Telefon: 30",
                "phone": [
                    "30"
                ],
                "postgiro": "93456",
                "head_office": "N/A",
                "sales_offices": [],
                "telegraph": "N/A",
                "factory_office": "N/A",
                "factory_phone": "N/A"
            },
            "financials": {
                "capital": "75,000 kr",
                "employees": {
                    "industriarb": 20
                },
                "annual_turnover": "N/A",
                "annual_production_value": "N/A"
            },
            "foundation_year": 1896,
            "current_name_year": 1920,
            "predecessor": "N/A",
            "original_name": "N/A",
            "corporation_year": "N/A",
            "board": [
                {
                    "name": "Erik W. Järnerot",
                    "role": "disp."
                }
            ],
            "owners": [],
            "director": "N/A",
            "managing_director": "N/A",
            "sales_manager": "N/A",
            "manager": "N/A"
        },
        "6": {
            "name": "Nora Möbelfabrik",
            "location": "Nora",
            "business": "Tillverkar rökbord och kompletteringsmöbler",
            "contact": {
                "office": "Telefon: 374",
                "phone": [
                    "374"
                ],
                "postgiro": "N/A",
                "head_office": "N/A",
                "sales_offices": [],
                "telegraph": "N/A",
                "factory_office": "N/A",
                "factory_phone": "N/A"
            },
            "financials": {
                "capital": "N/A",
                "employees": {
                    "industriarb": 12
                },
                "annual_turnover": "N/A",
                "annual_production_value": "N/A"
            },
            "foundation_year": 1917,
            "current_name_year": "N/A",
            "predecessor": "N/A",
            "original_name": "N/A",
            "corporation_year": "N/A",
            "board": [],
            "owners": [
                "fru Elisabet Löfgren"
            ],
            "director": "N/A",
            "managing_director": "N/A",
            "sales_manager": "N/A",
            "manager": "N/A"
        },
        "7": {
            "name": "AB. Nora Tändrörsfabrik",
            "location": "Grängesberg",
            "business": "Tillverkar stubintråd vid fabrik i Nora",
            "contact": {
                "office": "Huvudkontor: Grängesberg (Kopparb. l.)",
                "phone": [
                    "N/A"
                ],
                "postgiro": "71374",
                "head_office": "N/A",
                "sales_offices": [],
                "telegraph": "N/A",
                "factory_office": "N/A",
                "factory_phone": "N/A"
            },
            "financials": {
                "capital": "280,000 kr",
                "employees": {
                    "industriarb": 70
                },
                "annual_turnover": "N/A",
                "annual_production_value": "1,200,000 kr"
            },
            "foundation_year": 1899,
            "current_name_year": "N/A",
            "predecessor": "N/A",
            "original_name": "N/A",
            "corporation_year": "N/A",
            "board": [
                {
                    "name": "O. G. Granström",
                    "role": "disp."
                },
                {
                    "name": "Erik Malm",
                    "role": "disp."
                },
                {
                    "name": "Sigurd Nauckhoff",
                    "role": "fil. dr"
                }
            ],
            "owners": [],
            "director": "C. G. Granström",
            "managing_director": "Birger Nauckhoff",
            "sales_manager": "N/A",
            "manager": "N/A"
        },
        "8": {
            "name": "C. Aug. Norberg",
            "location": "Motala",
            "business": "Manufakturverk. Tillverkar spadar, skyfflar, grepar och högafflar, skaft samt eldningsredskap"
        }
    }
}