{
    "original": "D egerhamn—D elihon\n\nPostadr.: Degerfors. Telegr.-adr.:\nJärnverket, Degerfors. Telefon: »Degerfors\njärnverk», Karlskoga. Postgiro: 72400.\n\nAkt.-kap.: 9,000,000 kr. Antal\nindustriarb.: 2,000. Tillv.-värde pr år: 28,000,000\nkr. ;-i!\n\nBolagets namn var från 1870\nDegerfors AB., namnet förändrades 1886 till\nStrömsnäs Jernverks AB., nuv. namn\n1939. Huvudintressent i bolaget är\nUddeholms AB.\n\nStyrelse: bankir Tage Cervin (ordf.),\ndir. Ragnar Blomqvist, disp. Bengt\nCarleson, dir. Mauritz Carlson, disp. Nils\nDanielsen, bankdir. Erland Geijer.\n\nVerkst. dir. o. disp.: Bengt Carleson.\n\növering.: Erik Hermanson.\n\nIntendent: John H. Hallström.\n\nSekreterare: Tor W. Jansson.\n\nInköpschef: Eric A. Larsson.\n\nKamrer: G. H. Frisk.\n\nAvd.-chefer vid tekn. avd.:\nför pressverk o. verkst.: Edv. Eriksson;\nför hyttor o. martinverk: Bo Tiger-\n\nsehiöld;\n\nför valsverken: Martin Haglund;\nför ritkontor: A. B. Adelrot.\nför laboratorium: Gösta Sehlberg.\n\n(Jfr annons nr 62.)\n\n*Degerhamns Cementfabrik,\n\nDegerhamn.\n\nSe Ölands Cement AB., Degerhamn.\n\n*Deje Sulfatfabrik och Pappersbruk,\n\nDeje.\n\nSe AB. Mölnbacka-Trysil, Forshaga.\n\n*Dejefors Kraft- &amp; Fabriks AB.,\n\nDejeforsbruk.\n\nSe AB. Mölnbacka-Trysil, Forshaga.\n\n*Delary Sulfatfabrik, Delary.\n\nSe Strömsnäs Bruks AB.,\nStrömsnäs-bruk.\n\n*AB. de Lavals Angturbin,\n\nStockholm.\n\nMek. verkstad och gjuteri vid\nSaltsjö-Järla (Sthlms l.). Tillverkar ångturbiner.\nelektr. generatorer och motorer,\n»ZETA»-centrifuaral pumpar. fläktar,\nkompressorer, »TMO»-skruvpumpar, kondensorer,\nroterande luftpumpar samt\n»LAVAL»-råoljemotorer.\n\nHuvudkontor: Saltsjö-Järla; postadr.:\nBox 15025, Stockholm 15. Telegr.-adr.:\nLavalturbo, Stockholm. Telefon: »De La-\n\nvals Ångturbin». Postgiro: 51548. Repr.\ni Stockholm: AB. Zander &amp; Ingeström,\nFredsg. 4.\n\nA gent er i utlandet:\n\nDanmark: Ingeniörsfirman Larsen &amp;\nSelding, Köpenhamn, Norre Voldg. 2;\nKoefoed Meyer, Ingeniorförretning,\nKöpenhamn, Frederiksg. 11;\n\nFinland: Industria Osakeyhtiö,\nHelsingfors, Södra Esplanadg. 14;\n\nNorge: Maskin Aktieselskapet Zeta,\nOslo, Drammensveien 26; De Lavals\nÅngturbin, Norsk Aksjeselskap, Oslo,\nPrin-sensg. 2;\n\nBelgien: Agence Generale, Turbines å\nVapeur Laval, Bryssel, 29, rue de\n1’In-dustrie;\n\nSpanien: S. A. E. Turbinas, Bombas y\nMotores de Laval, Madrid, Apartado 910;\n\nHolland: Koopman &amp; Co., Amsterdam,\nGebouw »Atlanta», Stadhouderskade 6;\n\nEngland: Bolling &amp; Lowe, Ltd.,\nLondon, 2, Laurence Pountney Hill;\n\nFrankrike: Etablissements Alba, Paris,\n7, Rue du Bois;\n\nGrekland: Michel D. Chryssafidis,\nPiraeus, 30 a Akti Possidonos;\n\nKina: H. J. Moysey &amp; Co., Ltd.,\nShanghai, 3/170 Route Ghisi.\n\nAkt.-kap.: 4,800,000 kr. Antal\nindustriarb.: 450. Tillv.-värde pr år: 5,000,000\nkr. — Bolaget grundat 1893.\n\nStyrelse: dir. Erik J. Bengtson (ordf.),\ngrossh. Robert Ljunglöf (v. ordf.), dir.\nGunnar Dalen, frih. Louis de Geer, ing.\nVilhelm Nordström, adv. Hugo Stenbeck.\n\nVerkst. dir.: Vilhelm Nordström.\n\nKamrer: Axel Järbin.\n\nVerkstadsing.: Hans Ström.\n\nInköpschef: Gunnar Kry.\n\nOscar Delavaux, Smålands Anneberg.\n\nSmides- och mek. verkstad i Smålands\nAnneberg (Jönköp. l.). Tillverkar\nkallsågar, borr- och slipmaskiner,\nbetonghål-stensmaskiner samt piskställ.\n\nTelefon: 50. Postgiro: 98672. — Antal\nindustriarb.: 12. Tillv.-värde pr år:\n110,000 kr. — Firman etabl. 1936.\n\nÄgare o. chef: fabr. Oscar Delavaux.\n\nAB. Delikon, Norrköping.\n\nKonservfabrik. Tillverkar konserverade\nfrukter, bär, svamp och rödbetor, senap,\nsoja m. m., sylter, fruktmos, marmelad,\nsaft m. m. Varumärken: »Tre F»,\n»Träff» o. »Lukullus».",
    "structured": {
        "firms": [
            {
                "name": "Degerhamn—D elihon",
                "location": "Degerfors",
                "business": "Järnverk",
                "contact": {
                    "telegraph": "Järnverket, Degerfors",
                    "postgiro": "72400"
                },
                "financials": {
                    "capital": "9,000,000 kr",
                    "employees": {
                        "industriarb": 2000
                    },
                    "annual_turnover": "28,000,000 kr",
                    "annual_production_value": "28,000,000 kr"
                },
                "foundation_year": 1870,
                "current_name_year": 1939,
                "predecessor": "Degerfors AB",
                "corporation_year": 1886,
                "board": [
                    {
                        "name": "Tage Cervin",
                        "role": "bankir (ordf.)"
                    },
                    {
                        "name": "Ragnar Blomqvist",
                        "role": "dir."
                    },
                    {
                        "name": "Bengt Carleson",
                        "role": "disp."
                    },
                    {
                        "name": "Mauritz Carlson",
                        "role": "dir."
                    },
                    {
                        "name": "Nils Danielsen",
                        "role": "disp."
                    },
                    {
                        "name": "Erland Geijer",
                        "role": "bankdir."
                    }
                ],
                "owners": [
                    "Uddeholms AB"
                ],
                "director": "Bengt Carleson",
                "managing_director": "Erik Hermanson",
                "sales_manager": "John H. Hallström",
                "manager": "Tor W. Jansson"
            },
            {
                "name": "AB. de Lavals Angturbin",
                "location": "Stockholm",
                "business": "Mek. verkstad och gjuteri",
                "contact": {
                    "head_office": "Saltsjö-Järla",
                    "postgiro": "51548",
                    "sales_offices": [
                        {
                            "location": "Stockholm",
                            "phone": "AB. Zander & Ingeström, Fredsg. 4"
                        }
                    ]
                },
                "financials": {
                    "capital": "4,800,000 kr",
                    "employees": {
                        "industriarb": 450
                    },
                    "annual_turnover": "5,000,000 kr",
                    "corporation_year": 1893
                },
                "board": [
                    {
                        "name": "Erik J. Bengtson",
                        "role": "dir. (ordf.)"
                    },
                    {
                        "name": "Robert Ljunglöf",
                        "role": "grossh. (v. ordf.)"
                    },
                    {
                        "name": "Gunnar Dalen",
                        "role": "dir."
                    },
                    {
                        "name": "Louis de Geer",
                        "role": "frih."
                    },
                    {
                        "name": "Vilhelm Nordström",
                        "role": "ing."
                    },
                    {
                        "name": "Hugo Stenbeck",
                        "role": "adv."
                    }
                ],
                "director": "Vilhelm Nordström",
                "manager": "Axel Järbin",
                "sales_manager": "Gunnar Kry",
                "factory_office": "Smålands Anneberg (Jönköp. l.)",
                "factory_phone": "50",
                "owners": [
                    "Oscar Delavaux"
                ]
            },
            {
                "name": "AB. Delikon",
                "location": "Norrköping",
                "business": "Konservfabrik",
                "products": "Konserverade frukter, bär, svamp, rödbetor, senap, soja, sylter, fruktmos, marmelad, saft",
                "contact": {
                    "postgiro": "N/A"
                },
                "description": "Varumärken: Tre F, Träff, Lukullus",
                "factory_office": "N/A",
                "factory_phone": "N/A"
            }
        ]
    }
}