{
    "original": "Sune x—Surahammar\n\n£irma etabl. 1923. Firman äger\nMolanders Trävaruaffär, Kil.\n\nÄgare o. disp.: Ingvald övergaard.\nFörsäljare: Gudbrand övergaard.\n\n\"Sunex Säkerhetsglas AB., Stockholm.\n\nGlasförädlingsfabrik och\nspecialglassli-peri. Tillverkar splitterfritt glas för\nbilar, bussar, elektr. lok, flygplan, fartyg\netc. samt varierande lamellkonstruktioner\nför andra ändamål. Varumärke: »Sunex».\nBolaget driver även försäljning av härdat\nsäkerhetsglas (»Restex»).\n\nKontor: Drottningg. 17. Telegr.-adr.:\nSunexglas, Stockholm. Telefon: 201201 o.\n201231. Postgiro: 54404.\n\nAkt.-kap.: 59,500 kr. Arb.-antal: 8.\nTillv.-värde pr år: 100,000 kr. — Bolaget\ngrundat 1932.\n\nStyrelse: f. d. taxeringskommissarie\nSven Ekman, ing. Sten Lindvall.\n\nVerkst. dir.: vakant.\n\nVerkstads- o. försäljn.-chef: Eric Berg.\n\n\"AB. Sunlight, Stockholm.\n\nKemisk-teknisk fabrik i Nyköping.\nTillverkar tvål, tvättpulver, skurpulver,\nsåpa och glycerin. Varumärken: »Radion»,\n»Omo», »Sunlight», »Lux», »Vim»,\n»Ge-fion» m. fl.\n\nHuvudkontor: Stockholm, Sveavägen\n25—27. Telegr.-adr.: Sunlight,\nStockholm. Telefon: 234065. Postgiro: 9113.\nAvd.-kontor: Göteborg, Göteborgs\nLagerhus. Telefon: 136914; Malmö, Neptunig.\n15. Telefon: 77044.\n\nAkt.-kap.: 1,510,000 kr. Antal\nindustriarb.: 225. — Bolaget grundat 1911.\n\nStyrelse: adv. C.-L. Schönmeyr (ordf.),\ndir. R. C. Elliott, adv. Torsten E.\nSvensson.\n\nVerkst. dir.: R. C. Elliott.\n\nFÖrsäljn.-chef: E. Selinder\".\n\nFabrikschef: civiling. Gunnar Lamby.\n\nAB. Sunmos Konfektionsindustri,\n\nEksjö.\n\nTillverkar kostymer och ulstrar.\nTelefon: 1120. Postgiro: 70099. —\nAkt.-kap.: 38,000 kr. Antal industriarb.:\n32. Tillv.-värde pr år: 300,000 kr. —\nBolaget grundat 1939.\n\nVerkst. dir.: disp. Folke Sunmo.\n\n\"Sunnanå Ångsåg, Mellerud.\nSe Bark &amp; Warburgs AB., Göteborg.\n\n\"Sunne Mek. Verkstad, Sunne.\n\nTillverkar verktygsmaskiner samt\nmaskiner för sågverksindustrien vid mek.\nverkstad i Sunne (Värml. l.).\n\nTelefon: 66. Postgiro: 94889. —\nAntal industriarb.: 25. — Verkstaden\nanlagd 1902, nuv. firma etabl. 1937.\nÄgare o. chef: ing. Carl-Axel Olson.\n\n*Superfosfatfabriker, AB. Förenade,\n\nHälsingborg.\n\nSe AB. Förenade Superfosfatfabriker,\nHälsingborg.\n\n\"Superfosfat Fabriks AB., Stockholm.\n\nSe Stockholms Superfosfat Fabriks\nAB., Stockholm.\n\nSuperfosfat-Försäljnings AB.,\nSvenska, Hälsingborg.\n\nSe Svenska Superfosfat-Försäljnings\nAB., Hälsingborg.\n\n\"AB. Superior, Stockholm.\n\nTillverkar sotningsapparater,\nborrmaskiner, pressar, skevspindlar,\nshuntventi-ler samt dragregulatorer; utför allmänna\nverkstadsarbeten samt exploaterar patent.\n\nKontor: Nybrokajen 7. Telegr.-adr.:\nUtilis, Stockholm. Telefon: 107048,107053\no. 107056. Postgiro: 1835. — Akt.-kap.:\n496,000 kr. Antal industriarb.: 30.\nTillv.-värde pr år: 800,000 kr. — Firman etabl.\n1923.\n\nStyrelse: adv. Bengt af Klintberg\n(ordf.), dir. A. H. Carell, dir. Th. Grill,\ning. Thure Höglund.\n\nVerkst. dir.: T. Höglund.\n\n\"Surahammars Bruks AB.,\n\nSurahammar.\n\nJärnverk med elektrostål-, martin- och\nvalsverk, ånghammare- och\npressmides-verkstäder, plåtpressnings- och\nsvetsningsverk, mek. verkstäder samt stål- och\ntack-järnsgjuteri vid Surahammar, masugnar,\nsintringsverk, gjuteri och mek. verkstad\nvid Spännarhyttan, järngruvor i Norberg,\nelektr. vattenkraftstationer vid Nordansjö,\nSurahammar, Ålsätra, Hallstahammar,\nSörstafors och Västerkvarn, sågverk vid\nNordansjö (Norberg) och Surahammar,\nsamt jordbruk och skogsbruk vid\nSurahammar, Lisjö, Svanå och Gäsjö (samtl.\ni Västmanl. l.).\n\nBolaget bryter och anrikar järnmalm,\ntillverkar tackjärn, göt av elektro- och\nmartinstål, grov-, medium- och tunnplåt,\nsågblads- och elektroplåt, smiden, stål- och\n\n523*",
    "structured": {
        "1": {
            "name": "Sunex Säkerhetsglas AB.",
            "location": "Stockholm",
            "business": "Glasförädlingsfabrik",
            "products": "Tillverkar splitterfritt glas för bilar, bussar, elektr. lok, flygplan, fartyg etc. samt varierande lamellkonstruktioner för andra ändamål. Varumärke: »Sunex». Bolaget driver även försäljning av härdat säkerhetsglas (»Restex»).",
            "contact": {
                "office": "Drottningg. 17",
                "phone": [
                    "201201",
                    "201231"
                ],
                "postgiro": "54404",
                "telegraph": "Sunexglas",
                "head_office": "Stockholm"
            },
            "financials": {
                "capital": "59,500 kr",
                "employees": {
                    "Arbetsplatser": 8
                },
                "annual_turnover": "N/A",
                "annual_production_value": "100,000 kr"
            },
            "foundation_year": 1932
        },
        "2": {
            "name": "AB. Sunlight",
            "location": "Stockholm",
            "business": "Kemisk-teknisk fabrik",
            "products": "Tillverkar tvål, tvättpulver, skurpulver, såpa och glycerin. Varumärken: »Radion», »Omo», »Sunlight», »Lux», »Vim», »Ge-fion» m. fl.",
            "contact": {
                "office": "Sveavägen 25—27",
                "phone": [
                    "234065"
                ],
                "postgiro": "9113"
            },
            "financials": {
                "capital": "1,510,000 kr",
                "employees": {
                    "Antal industriarb.": 225
                },
                "annual_turnover": "N/A",
                "annual_production_value": "N/A"
            },
            "foundation_year": 1911
        },
        "3": {
            "name": "AB. Sunmos Konfektionsindustri",
            "location": "Eksjö",
            "business": "Klädesindustri",
            "contact": {
                "phone": [
                    "1120"
                ],
                "postgiro": "70099"
            },
            "financials": {
                "capital": "38,000 kr",
                "employees": {
                    "Antal industriarb.": 32
                },
                "annual_turnover": "N/A",
                "annual_production_value": "300,000 kr"
            },
            "foundation_year": 1939
        },
        "4": {
            "name": "Sunne Mek. Verkstad",
            "location": "Sunne",
            "business": "Tillverkar verktygsmaskiner samt maskiner för sågverksindustrien",
            "contact": {
                "phone": [
                    "66"
                ],
                "postgiro": "94889"
            },
            "financials": {
                "employees": {
                    "Antal industriarb.": 25
                },
                "annual_production_value": "N/A"
            },
            "foundation_year": 1937
        },
        "5": {
            "name": "AB. Superior",
            "location": "Stockholm",
            "business": "Tillverkar sotningsapparater, borrmaskiner, pressar, skevspindlar, shuntventiler samt dragregulatorer; utför allmänna verkstadsarbeten samt exploaterar patent.",
            "contact": {
                "office": "Nybrokajen 7",
                "phone": [
                    "107048",
                    "107053",
                    "107056"
                ],
                "postgiro": "1835"
            },
            "financials": {
                "capital": "496,000 kr",
                "employees": {
                    "Antal industriarb.": 30
                },
                "annual_production_value": "800,000 kr"
            },
            "foundation_year": 1923
        },
        "6": {
            "name": "Surahammars Bruks AB.",
            "location": "Surahammar",
            "business": "Järnverk",
            "contact": {
                "phone": [
                    "N/A"
                ]
            },
            "financials": {
                "employees": {
                    "Arbetsplatser": "N/A"
                }
            }
        }
    }
}