{
    "original": "Karsten—Kassabio ek\n\n\"Karstens Bageri, Stockholm.\n\nSe AB. Westerdahl &amp; Karsten,\nStockholm.\n\n\"AB. Karta &amp; Oaxens Kalkbruk,\n\nStockholm.\n\nKalkstensbrott och kalkbruk. Bolaget\nbryter kalksten å ön Oaxen i\nSödertälje-viken (Södermanl. l.) och vid Bläse (Gotl.\n1.) samt driver å dessa platser fabrikation\nav kalk för jordbruks-, byggnads- och\ntekniska ändamål; försäljer cement,\nmur-och putsbruk, sand, grus, singel,\nmakadam, eldfast tegel och lera. Bolaget\nåtager sig transporter medelst pråmar i\nMälaren och Östersjön.\n\nHuvudkontor: Stockholm, Norr\nMälarstrand 22. Telegr.-adr.: Oaxen, Stockholm.\nTelefon: »Karta-Oaxen». Postgiro: 968.\nAvd.-kontor: Bläse och Oaxen.\n\nAkt.-kap.: 1,000,000 kr. Antal\nindustriarb.: 225. — Firman etabl. 1816, bolag\n1896, ombildat 1921.\n\nStyrelse: generalkonsul G. M. I.\nFa-grseus (ordf.), dir. Malte Ström, dir.\nErnst Wehtje.\n\nVerkst. dir.: Albert Rothstein.\n\nKamrerare: Johan Nilsson o. Arthur\nBoréus.\n\nAB. Kartografiska Institutet,\n\nStockholm.\n\nRedaktion och ritning av kartor,\ngrafiska framställningar m. m.; utför arbeten\ni offset, boktryck och ljustryck.\n\nKontor: Vasag. 16. Telegr.-adr.:\nCentraltryck, Stockholm. Telefon: »Esselte».\nPostgiro: 35.\n\nBolaget, som grundades 1922, är\nanslutet till AB. Sveriges Litografiska\nTryckerier, Stockholm. (Se detta bolag.)\n\nStyrelse o. verkst. dir.: ryttm. Åke G.\nWickman.\n\nKartredaktör: Magnus Lundqvist.\n\nKartong AB., Nya, Stockholm.\n\nSe Nya Kartong AB., Stockholm.\n\nAB. Kartonger &amp; Tryck,\n\nStockholm.\n\nKartongfabrik. Tillverkar askar och\nkartonger.\n\nKontor: Lindhagensg. 57—59. Telefon:\n534549 o. 502380. Postgiro: 56682.\n\nAkt.-kap.: 30,000 kr. Antal\nindustriarb.: 30. Tillv.-värde pr år: 325,000 kr.\n— Firman etabl. 1933, bolag 1934.\n\nStyrelse o. chefer: dir. Herman\nStenberg, dir. Erik Sundblom.\n\nKartongfabriken Excelsior AB.,\n\nGöteborg.\n\nTillverkar kartonger, kapslar och runda\naskar.\n\nKontor: Sävenäs. Telefon: Göteborg\n262060. Postgiro: 40085. —- Akt.-kap.:\n75,000 kr. Antal industriarb.: 75.\nTillv.-värde pr år: 850,000 kr. — Firman etabl.\n1897, bolag 1912.\n\nStyrelse o. verkst. dir.: fabr. Arthur\nJohansson.\n\nKartongfabriken Star, Habo.\n\nTillverkar cylindriskt pappemballage\nvid fabrik i Habo (Skarab. l.).\n\nTelefon: 60. Postgiro: 144760. —\nAntal industriarb.: 20. Tillv.-värde pr år:\n400,000 kr. — Firman etabl. 1931.\n\nÄgare o. chef: fabr. C. A. Dagman.\n\nKartongindustrin, Hansson &amp;\nAndersson AB., Malmö.\n\nTillverkar kartonger, spec. bakelse-,\ntårt-, bär- och skokartonger.\n\nKontor: Industrigatan. Telefon: 18752\no. 23252. Postgiro: 37606.\n\nAkt.-kap.: 45,000 kr. Antal\nindustriarb.: 40. Tillv.-värde pr år: 350,000 kr.\n— Firman etabl. 1932, bolag 1934.\n\nStyrelse o. verkst. direktörer: fabr.\nHerbert Hansson o. fabr. Gottfrid\nAndersson.\n\nAB. Kartonnage, Gävle.\n\nTillverkar förpackningskartonger.\n\nTelefon: 3128. Postgiro: 263670. —\nAkt.-kap.: 30,000 kr. Antal industriarb.:\n25. Tillv.-värde pr år: 250,000 kr.\n\nBolaget grundat 1918. F. Ahlgrens\nTekn. Fabrik AB. är huvudintressent i\nbolaget.\n\nVerkst. dir.: Adolf F. Ahlgren.\n\nVice verkst. dir.; Bengt Ahlgren.\n\nDisp.: Gust. Melin.\n\nAB. Kassablock, 1 sidor Svahn\nPappersindustri, Hälsingborg.\n\nTryckeri för tillverkning av\ngenom-skriftsblanketter såsom kassablock,\nfölje-och fraktsedlar, fakturor, adresslappar,\nbiljetter, motböcker samt boktryck.\n\nTelefon: 10260 o. 14407. Postgiro:\n36453. __ Akt.-kap.: 10,000 kr. Antal\nindustriarb.: 45. — Firman etabl. 1929,\nbolag 1942.\n\nStyrelse o. verkst. dir.: ryttm. Åke G.\nWickman (Sthlm).\n\nFörs t %;-chef: G. Trobäcker.\n\nPlatsonef: Nils Karlsson.\n",
    "structured": {
        "1": {
            "name": "AB. Karta & Oaxens Kalkbruk",
            "location": "Stockholm",
            "business": "Kalkstensbrott och kalkbruk",
            "products": "Bolaget bryter kalksten å ön Oaxen i Södertälje-viken (Södermanl. l.) och vid Bläse (Gotl. 1.) samt driver å dessa platser fabrikation av kalk för jordbruks-, byggnads- och tekniska ändamål; försäljer cement, mur-och putsbruk, sand, grus, singel, makadam, eldfast tegel och lera. Bolaget åtager sig transporter medelst pråmar i Mälaren och Östersjön.",
            "contact": {
                "office": "Stockholm, Norr Mälarstrand 22",
                "phone": [
                    "Karta-Oaxen"
                ],
                "postgiro": "968",
                "head_office": "Stockholm, Norr Mälarstrand 22",
                "sales_offices": [
                    {
                        "location": "Bläse",
                        "phone": "unspecified"
                    },
                    {
                        "location": "Oaxen",
                        "phone": "unspecified"
                    }
                ]
            },
            "financials": {
                "capital": "1,000,000 kr",
                "employees": {
                    "industriarb": 225
                },
                "annual_turnover": "unspecified",
                "annual_production_value": "unspecified"
            },
            "foundation_year": 1816,
            "corporation_year": 1896,
            "board": [
                {
                    "name": "generalkonsul G. M. I. Fagréus",
                    "role": "ordf."
                },
                {
                    "name": "dir. Malte Ström",
                    "role": "unspecified"
                },
                {
                    "name": "dir. Ernst Wehtje",
                    "role": "unspecified"
                }
            ]
        },
        "2": {
            "name": "AB. Kartografiska Institutet",
            "location": "Stockholm",
            "business": "Redaktion och ritning av kartor, grafiska framställningar m. m.; utför arbeten i offset, boktryck och ljustryck",
            "contact": {
                "office": "Vasag. 16",
                "phone": [
                    "Esselte"
                ],
                "postgiro": "35"
            },
            "description": "Bolaget, som grundades 1922, är anslutet till AB. Sveriges Litografiska Tryckerier, Stockholm. (Se detta bolag.)",
            "board": [
                {
                    "name": "ryttm. Åke G. Wickman",
                    "role": "unspecified"
                }
            ]
        },
        "3": {
            "name": "Kartong AB., Nya",
            "location": "Stockholm",
            "business": "unspecified",
            "contact": {
                "office": "Lindhagensg. 57—59",
                "phone": [
                    "534549",
                    "502380"
                ],
                "postgiro": "56682"
            },
            "financials": {
                "capital": "30,000 kr",
                "employees": {
                    "industriarb": 30
                },
                "annual_turnover": "325,000 kr",
                "annual_production_value": "unspecified"
            },
            "foundation_year": 1933
        },
        "4": {
            "name": "Kartongfabriken Excelsior AB., Göteborg",
            "location": "Göteborg",
            "business": "Tillverkar kartonger, kapslar och runda askar",
            "contact": {
                "office": "Sävenäs",
                "phone": [
                    "Göteborg 262060"
                ],
                "postgiro": "40085"
            },
            "financials": {
                "capital": "75,000 kr",
                "employees": {
                    "industriarb": 75
                },
                "annual_turnover": "850,000 kr",
                "annual_production_value": "unspecified"
            },
            "foundation_year": 1897,
            "corporation_year": 1912
        },
        "5": {
            "name": "Kartongfabriken Star, Habo",
            "location": "Habo",
            "business": "Tillverkar cylindriskt pappemballage vid fabrik i Habo (Skarab. l.)",
            "contact": {
                "phone": [
                    "60"
                ],
                "postgiro": "144760"
            },
            "financials": {
                "employees": {
                    "industriarb": 20
                },
                "annual_turnover": "400,000 kr",
                "annual_production_value": "unspecified"
            },
            "foundation_year": 1931
        },
        "6": {
            "name": "Kartongindustrin, Hansson & Andersson AB., Malmö",
            "location": "Malmö",
            "business": "Tillverkar kartonger, spec. bakelse-, tårt-, bär- och skokartonger",
            "contact": {
                "office": "Industrigatan",
                "phone": [
                    "18752",
                    "23252"
                ],
                "postgiro": "37606"
            },
            "financials": {
                "capital": "45,000 kr",
                "employees": {
                    "industriarb": 40
                },
                "annual_turnover": "350,000 kr",
                "annual_production_value": "unspecified"
            },
            "foundation_year": 1932,
            "corporation_year": 1934
        },
        "7": {
            "name": "AB. Kartonnage, Gävle",
            "location": "Gävle",
            "business": "Tillverkar förpackningskartonger",
            "contact": {
                "phone": [
                    "3128"
                ],
                "postgiro": "263670"
            },
            "financials": {
                "capital": "30,000 kr",
                "employees": {
                    "industriarb": 25
                },
                "annual_turnover": "250,000 kr",
                "annual_production_value": "unspecified"
            }
        },
        "8": {
            "name": "AB. Kassablock, 1 sidor Svahn Pappersindustri, Hälsingborg",
            "location": "Hälsingborg",
            "business": "Tryckeri för tillverkning av genomskriftsblanketter såsom kassablock, följe-och fraktsedlar, fakturor, adresslappar, biljetter, motböcker samt boktryck",
            "contact": {
                "phone": [
                    "10260",
                    "14407"
                ],
                "postgiro": "36453"
            },
            "financials": {
                "capital": "10,000 kr",
                "employees": {
                    "industriarb": 45
                }
            }
        }
    }
}