{
    "original": "H Vetlanda—Hyltén\n\n\"AB. Hvetlanda Stol- &amp; Möbelfabrik,\n\nVetlanda.\n\nTillverkar radiolådor och -skåp.\n\nTelegr.-adr.: Möbelfabriken, Vetlanda.\nTelefon: 20. Postgiro: 26001.\n\nAkt.-kap.: 35,000 kr. Antal\nindustriarb.: 35. — Firman etabl. 1897, bolag\n1936.\n\nStyrelse: dir. Eric Johanson, fröken\nRuth Johanson, dir. Silas Johanson.\n\nVerkst. direktörer: Eric Johanson o.\nSilas Johanson.\n\n\"Hvetlanda Tändsticksfabriker,\n\nVetlanda.\n\nSe Jönköpings och Vulcans\nTändsticksfabriks AB., Jönköping.\n\n\"Hvetlanda Ullspinneri AB.,\n\nVetlanda.\n\nSe Vetlanda Ullspinneri AB., Vetlanda.\n\n\"Hvilans Mek. Verkstads AB.,\n\nKristianstad.\n\nMek. verkstad, gjuteri och plåtslageri.\nTillverkar kranar och lyftanordningar,\nhissar, svetsade och nitade plåtarbeten\nsamt järnkonstruktioner, ångpannor,\nmaskiner för sprit- och stärkelsefabriker\nävensom transportvagnar,\ngranskningsmaskiner för tyger m. m. för ylleindustri.\n\nKontor: Hvilan, Kristianstad.\nTelegr.-adr.: II vi lans Gjuteri, Kristianstad.\nTelefon: 10029, 10429 o. 10939. Postgiro:\n24066.\n\nAkt.-kap.: 394,500 kr. Antal\nindustriarb.: 115. Tillv.-värde pr år: 1,700,000 kr.\n— Bolaget grundat 1899.\n\nStyrelse: disp. P. Hroar de la Oour\n(ordf.), jur. kand. Lennart de la Cour,\nlandstingsm. Nils Jönsson, dir. Alb.\nLarsson, dir. Joh. Persson.\n\nVerkst. dir.: Alb. Larsson.\n\nKamrer: C. Malmqvist.\n\n(Jfr annons nr 82.)\n\nHydrauliska Industri AB.,\n\nHudiksvall.\n\nMek. verkstad. Tillverkar hydrauliska\nmaskiner och verktyg såsom pressar,\ngarage- och pelardomkrafter, bil- och\nsläpvagnstippar, lastkranar för\nautomo-biler, bockningsapparater, hjulavdragare\nm. m. Varumärke: »H. I. A. B.».\n\nTelefon: 1500. Postgiro: 277680. —\nAkt.-kap.: 50,000 kr. Antal industriarb.:\n45. Tillv.-värde pr år: 600,000 kr. —\nBolaget grundat 1944.\n\nDisp.: Carl Johan Börjesson.\n\nDriftsing.; Gunnar Lundeli.\n\n*Hylin &amp; Co. Fabriks AB.,\n\nStockholm.\n\nKem.-tekn. fabrik. Tillverkar tvål, såpa,\ntvätt- och skurmedel, parfymer,\nkosmetiska och antiseptiska artiklar m. m.\nVarunamn: »Rakin», »Avena», »Novosin»,\n»Barbol».\n\nKontor: östgötag. 52. Telegr.-adr.:\nHy-lins, Stockholm. Telefon: 440260.\nPostgiro: 2664.\n\nAkt.-kap.: 750,000 kr. Antal\nindustriarb.: 40. Tillv.-värde pr år: 1,500,000 kr.\n\nFirman etabl. 1857, bolag 1891.\nSyster-firmor till bolaget äro: AB. Grumme &amp;\nSon och Albin Lenhardtsons\nStomatol-fabrik.\n\nStyrelse: ing. C. Ed. Grumme (ordf.),\nkontorschef Curt Aspegrén, ing.\nFerdinand Grumme.\n\nVerkst. dir.: C. Ed. Grumme.\n\nKontorschef: Curt Aspegrén.\n\n\"Hyllingeverken, Hyllinge.\n\nSe Höganas-Billesholms AB., Höganäs.\n\n\"Hylte Bruks ABHyltebruk.\n\nPappersbruk med sulfitfabrik vid\nHyl-tebruk (Jönköp. l.). Tillverkar\nsulfitcellulosa för eget behov, sulfitsprit,\nomslagspapper samt pås- och smörpapper.\n\nTelegr.-adr.: Hylte, Halmstad. Telefon:\nHyltebruk 22.\n\nAkt.-kap.: 5,000,000 kr. Antal\nindustriarb.: 425. Årstillv.: 21,000 ton papper,\n1,2 milj. 1. sulfitsprit. — Bolaget,\ngrundat 1908, äger Rydö Bruks &amp; Fabriks AB.\n\nStyrelse: bankdir. Rich. Julin (ordf.),\ndisp. Ivar Bjerström, disp. Sigbjörn\nHolgersson, disp. Sten E. Holgersson, dir.\nJohn Lindström.\n\nVerkst. dir. o. disp.: Sten E.\nHolgersson.\n\növering.: Sigir. Lindsjö.\n\nFörsäljn.-chef: Albert österberg.\n\nSkogschef: J. M. Nerfeldt.\n\nKamrer: Yngve Teurneau.\n\nInköpschef: Thorvald Svensson.\n\n&lt;1. E. Hylténs Metallvarufabrik,\n\nGnosjö.\n\nMetallvarufabrik i Gnosjö (Jönköp. l.).\nTillverkar rörledningsarmatur,\nbrandarmatur, båtbeslag m. m.\n\nTelegr.-adr.: Hyltén, Gnosjö. Telefon:\n7. Postgiro: 266382. — Antal\nindustriarb.: 25. Tillv.-värde pr år: 336,000 kr.\n— Firman etabl. 1874.\n\nÄgare: J. E. Hylténs sterbhus.\n\nDriftsing.: John Hyltén.\n\nKontorschef: Paul Hyltén.",
    "structured": {
        "firms": [
            {
                "name": "AB. Hvetlanda Stol- & Möbelfabrik",
                "location": "Vetlanda",
                "business": "Tillverkar radiolådor och -skåp",
                "contact": {
                    "telegraph": "Möbelfabriken, Vetlanda",
                    "phone": [
                        "20"
                    ],
                    "postgiro": "26001"
                },
                "financials": {
                    "capital": "35,000 kr",
                    "employees": {
                        "industriarb": 35
                    },
                    "annual_production_value": "N/A"
                },
                "foundation_year": 1897,
                "corporation_year": 1936,
                "board": [
                    {
                        "name": "Eric Johanson",
                        "role": "dir."
                    },
                    {
                        "name": "Ruth Johanson",
                        "role": "fröken"
                    },
                    {
                        "name": "Silas Johanson",
                        "role": "dir."
                    }
                ],
                "managing_director": "Eric Johanson",
                "sales_manager": "Silas Johanson"
            },
            {
                "name": "Hvilans Mek. Verkstads AB.",
                "location": "Kristianstad",
                "business": "Mek. verkstad, gjuteri och plåtslageri. Tillverkar kranar och lyftanordningar, hissar, svetsade och nitade plåtarbeten samt järnkonstruktioner, ångpannor, maskiner för sprit- och stärkelsefabriker ävensom transportvagnar, granskningsmaskiner för tyger m. m. för ylleindustri.",
                "contact": {
                    "office": "Hvilan, Kristianstad",
                    "telegraph": "II vi lans Gjuteri, Kristianstad",
                    "phone": [
                        "10029",
                        "10429",
                        "10939"
                    ],
                    "postgiro": "24066"
                },
                "financials": {
                    "capital": "394,500 kr",
                    "employees": {
                        "industriarb": 115
                    },
                    "annual_turnover": "N/A",
                    "annual_production_value": "1,700,000 kr"
                },
                "foundation_year": 1899,
                "board": [
                    {
                        "name": "P. Hroar de la Oour",
                        "role": "disp."
                    },
                    {
                        "name": "Lennart de la Cour",
                        "role": "jur. kand."
                    },
                    {
                        "name": "Nils Jönsson",
                        "role": "landstingsm."
                    },
                    {
                        "name": "Alb. Larsson",
                        "role": "dir."
                    },
                    {
                        "name": "Joh. Persson",
                        "role": "dir."
                    }
                ],
                "director": "Alb. Larsson",
                "manager": "C. Malmqvist"
            },
            {
                "name": "Hydrauliska Industri AB.",
                "location": "Hudiksvall",
                "business": "Mek. verkstad. Tillverkar hydrauliska maskiner och verktyg såsom pressar, garage- och pelardomkrafter, bil- och släpvagnstippar, lastkranar för automo-biler, bockningsapparater, hjulavdragare m. m.",
                "contact": {
                    "phone": [
                        "1500"
                    ],
                    "postgiro": "277680"
                },
                "financials": {
                    "capital": "50,000 kr",
                    "employees": {
                        "industriarb": 45
                    },
                    "annual_turnover": "N/A",
                    "annual_production_value": "600,000 kr"
                },
                "foundation_year": 1944,
                "director": "Carl Johan Börjesson",
                "sales_manager": "Gunnar Lundeli"
            },
            {
                "name": "Hylin & Co. Fabriks AB.",
                "location": "Stockholm",
                "business": "Kem.-tekn. fabrik. Tillverkar tvål, såpa, tvätt- och skurmedel, parfymer, kosmetiska och antiseptiska artiklar m. m.",
                "contact": {
                    "office": "östgötag. 52",
                    "telegraph": "Hy-lins, Stockholm",
                    "phone": [
                        "440260"
                    ],
                    "postgiro": "2664"
                },
                "financials": {
                    "capital": "750,000 kr",
                    "employees": {
                        "industriarb": 40
                    },
                    "annual_turnover": "N/A",
                    "annual_production_value": "1,500,000 kr"
                },
                "foundation_year": 1857,
                "corporation_year": 1891,
                "board": [
                    {
                        "name": "ing. C. Ed. Grumme",
                        "role": "ordf."
                    },
                    {
                        "name": "Curt Aspegrén",
                        "role": "kontorschef"
                    },
                    {
                        "name": "Ferdinand Grumme",
                        "role": "ing."
                    }
                ],
                "director": "C. Ed. Grumme",
                "manager": "Curt Aspegrén"
            },
            {
                "name": "Hylte Bruks AB",
                "location": "Hyltebruk",
                "business": "Pappersbruk med sulfitfabrik vid Hyl-tebruk (Jönköp. l.). Tillverkar sulfitcellulosa för eget behov, sulfitsprit, omslagspapper samt pås- och smörpapper.",
                "contact": {
                    "telegraph": "Hylte, Halmstad",
                    "phone": [
                        "Hyltebruk 22"
                    ]
                },
                "financials": {
                    "capital": "5,000,000 kr",
                    "employees": {
                        "industriarb": 425
                    },
                    "annual_turnover": "N/A",
                    "annual_production_value": "N/A"
                },
                "foundation_year": 1908,
                "board": [
                    {
                        "name": "bankdir. Rich. Julin",
                        "role": "ordf."
                    },
                    {
                        "name": "Ivar Bjerström",
                        "role": "disp."
                    },
                    {
                        "name": "Sigbjörn Holgersson",
                        "role": "disp."
                    },
                    {
                        "name": "Sten E. Holgersson",
                        "role": "disp."
                    },
                    {
                        "name": "John Lindström",
                        "role": "dir."
                    }
                ],
                "director": "Sten E. Holgersson",
                "sales_manager": "Sigir. Lindsjö"
            },
            {
                "name": "J. E. Hylténs Metallvarufabrik",
                "location": "Gnosjö",
                "business": "Metallvarufabrik i Gnosjö (Jönköp. l.). Tillverkar rörledningsarmatur, brandarmatur, båtbeslag m. m.",
                "contact": {
                    "telegraph": "Hyltén, Gnosjö",
                    "phone": [
                        "7"
                    ],
                    "postgiro": "266382"
                },
                "financials": {
                    "capital": "N/A",
                    "employees": {
                        "industriarb": 25
                    },
                    "annual_turnover": "N/A",
                    "annual_production_value": "336,000 kr"
                },
                "foundation_year": 1874,
                "owner": "J. E. Hylténs sterbhus",
                "director": "John Hyltén",
                "manager": "Paul Hyltén"
            }
        ]
    }
}