{
    "original": "J onsson\n\n\"Jonsson, Sternhagen &amp; Co. AB.,\n\nGöteborg.\n\nTrävarufirma. Exporterar laths.\nBolaget driver även speditions- och\nskeppskla-reringsrörelse, försäkringsagentur samt\nagenturverksamhet i byggnadsbranschen.\n\nKontor: Broströmia, Packhusplatsen 6.\nTelegr.-adr.: Sternhagen, Göteborg.\nTelefon: 134390. Postgiro: 40337. —\nAkt.-kap.: 250,000 kr. — Firman etabl. 1872,\nbolag 1939.\n\nStyrelse: kammarh. G. A. Bratt (ordf.),\ngeneralkonsul Folke Jonsson, dir. Gunnar\nRodin.\n\nVerkst. dir.: Folke Jonsson.\n\n\"Jonssons Fabriker, N. Osk. Jonsson,\n\nMalung.\n\nSe Jofa, Jonssons Fabriker AB.,\nMalung.\n\nAB. Johnssons Korkfabrik,\n\nMalmö.\n\nTillverkar butelj kork, kapsyler och\nkorksmul. Bolaget driver även försäljning\nav korkisolering och korkparkett.\n\nKontor: Rönneholmsvägen. Telefon:\n23272 o. 28047. Postgiro: 14135. —\nAkt.-kap.: 140,000 kr. Antal industriarb.: 20.\nTillv.-värde pr år: 300,000 kr. — Firman\netabl. 1879, bolag 1936.\n\nDisp.: Bengt Malmström.\n\nAB. Johnson Metall, Örebro.\n\nMetallgjuteri, mek. verkstad och\nmodellverkstad. Utför gjutningar av\ntung-och lättmetaller. Specialitet:\nfärdigbearbetade bussningar.\n\nTelegr.-adr.: Johnsonmetall, Örebro.\nTelefon: 19750. — Akt.-kap.: 30,000 kr.\nAntal industriarb.: 106. — Firman etabl.\n1940, bolag 1944.\n\nVerkst. dir.: K. Åke Johnson.\n\n\"Johnsons Pappersindustri AB.,\n\nHälsingborg.\n\nBoktryckeri, litografisk anstalt och\nbokbinderi samt pås- och kartongfabrik.\nTillverkar påsar, kartonger för emballage,\nkuvert- och kontorsböcker samt utför bok-,\noffset- och litografiskt tryck.\n\nTelegr.-adr.: Pappersindustri,\nHälsingborg. Telefon: »Johnsons\nPappersindustri». Postgiro: 6274.\n\nBolaget, grundat 1897, är anslutet till\nAB. Sveriges Litografiska Tryckerier,\nStockholm (se detta bolag).\n\nStyrelse o. verkst. dir.: disp. Hj.\nMagnuson.\n\nKontorschef: fröken T. Larsson.\n\n\"A. Johnson &amp; Co., Oljeraffinaderiet,\n\nNynäshamn.\n\nPetroleumraffinaderi i Nynäshamn\n(Sthlms l.). Tillverkar bil- och\nflygbensin, fotogen, white spirit, solarolja,\ndieseloljor, transformatorolja, smörjoljor,\npannbrännoljor, asfalt samt organiska\nkemikalier.\n\nTelegr.-adr.: Raffinaderiet,\nNynäshamn. Telefon: Nynäshamn 2510.\nHuvudkontor: A. Johnson &amp; Co., Stureplan 3,\nStockholm. Telegr.-adr.: Johnsons,\nStockholm. Telefon: »Johnsons».\nFörsäljn.-kontor: AB. Nynäs-Petroleum,\nJakobs-bergsg. 2, Stockholm. Telefon: 235440.\n\nAntal industriarb.: 350. —\nRaffinaderiet anlagt 1928 och 1939—41.\n\nPlatschef: disp. Per H. W. Ågren.\n\n\"Alfr. Jonsson Fabriks AB.,\n\nLidköping.\n\nMek. verkstad och sågbladsfabrik.\nTillverkar bågfils- och maskinsågblad för\nmetall (märken: »Solo» o.\n»Solo-Wol-fram»), bandsågblad för trä samt\nslip-och polermaskiner.\n\nTelefon: 20224. Postgiro: 88464. —\nAkt.-kap.: 40,500 kr. Antal industriarb.:\n15. Tillv.-värde pr år: 260,000 kr. —\nBolaget grundat 1941.\n\nStyrelse: fabr. Arvid Jonsson, fabr.\nEinar Jonsson, fabr. Emil Jonsson.\n\nVerkst. dir.: Arvid Jonsson.\n\n\"Axel Jonssons Svarveri, Vetlanda.\n\nTillverkar pelarbord och barnstolar.\nTelefon: 307. Postgiro: 144494. —\nAntal industriarb.: 25. — Firman etabl.\n1914.\n\nÄgare o. chefer: fabr. Axel Jonsson o.\nfabr. Folke Jonsson.\n\n\"C. A. Jonssons Skofabrik AB.,\n\nKumla.\n\nSkofabrik i Kumla (Örebro l.).\nTillverkar randsydda, durksydda, pliggade och\nsandalsydda skodon. Varumärken:\n»Ex-cellent», »S:t Moritz», »Grandezza» o.\n»Gulliver».\n\nTelefon: 70910. Postgiro: 28309. —\nAkt.-kap.: 500,000 kr. Antal\nindustriarb.: 130. Tillv.-värde pr år: 2,500,000\nkr. — Firman etabl. 1913, bolag 1934.\n\nStyrelse: fabr. Carl A. Jonsson, disp.\nC. Lennart Jonsson, fru Hulda Jonsson.\n\nVerkst. dir.: Carl A. Jonsson.\n\n265*",
    "structured": {
        "0": {
            "name": "Jonsson, Sternhagen & Co. AB.",
            "location": "Göteborg",
            "business": "Trävarufirma",
            "products": "Exporterar laths. Bolaget driver även speditions- och skeppskla-reringsrörelse, försäkringsagentur samt agenturverksamhet i byggnadsbranschen.",
            "contact": {
                "office": "Broströmia, Packhusplatsen 6",
                "phone": [
                    "134390"
                ],
                "postgiro": "40337",
                "telegraph": "Sternhagen, Göteborg"
            },
            "financials": {
                "capital": "250,000 kr",
                "foundation_year": 1872,
                "corporation_year": 1939
            },
            "board": [
                {
                    "name": "kammarh. G. A. Bratt",
                    "role": "(ordf.)"
                },
                {
                    "name": "generalkonsul Folke Jonsson",
                    "role": ""
                },
                {
                    "name": "dir. Gunnar Rodin",
                    "role": ""
                }
            ],
            "director": "Folke Jonsson"
        },
        "1": {
            "name": "AB. Johnssons Korkfabrik",
            "location": "Malmö",
            "business": "Tillverkar butelj kork, kapsyler och korksmul",
            "products": "Bolaget driver även försäljning av korkisolering och korkparkett.",
            "contact": {
                "office": "Rönneholmsvägen",
                "phone": [
                    "23272",
                    "28047"
                ],
                "postgiro": "14135"
            },
            "financials": {
                "capital": "140,000 kr",
                "employees": {
                    "industriarb.": 20
                },
                "annual_turnover": "300,000 kr",
                "annual_production_value": "300,000 kr"
            },
            "corporation_year": 1936,
            "director": "Bengt Malmström"
        },
        "2": {
            "name": "AB. Johnson Metall",
            "location": "Örebro",
            "business": "Metallgjuteri, mek. verkstad och modellverkstad",
            "products": "Utför gjutningar av tung-och lättmetaller. Specialitet: färdigbearbetade bussningar.",
            "contact": {
                "telegraph": "Johnsonmetall, Örebro",
                "phone": "19750"
            },
            "financials": {
                "capital": "30,000 kr",
                "employees": {
                    "industriarb.": 106
                }
            },
            "corporation_year": 1944,
            "director": "K. Åke Johnson"
        },
        "3": {
            "name": "Johnsons Pappersindustri AB.",
            "location": "Hälsingborg",
            "business": "Boktryckeri, litografisk anstalt och bokbinderi samt pås- och kartongfabrik",
            "products": "Tillverkar påsar, kartonger för emballage, kuvert- och kontorsböcker samt utför bok-, offset- och litografiskt tryck.",
            "contact": {
                "telegraph": "Pappersindustri, Hälsingborg",
                "phone": "»Johnsons Pappersindustri»",
                "postgiro": "6274"
            },
            "corporation_year": 1897,
            "director": "disp. Hj. Magnuson",
            "manager": "fröken T. Larsson"
        },
        "4": {
            "name": "A. Johnson &amp; Co., Oljeraffinaderiet",
            "location": "Nynäshamn",
            "business": "Petroleumraffinaderi i Nynäshamn (Sthlms l.)",
            "products": "Tillverkar bil- och flygbensin, fotogen, white spirit, solarolja, dieseloljor, transformatorolja, smörjoljor, pannbrännoljor, asfalt samt organiska kemikalier.",
            "contact": {
                "telegraph": "Raffinaderiet, Nynäshamn",
                "phone": "Nynäshamn 2510",
                "sales_offices": [
                    {
                        "location": "A. Johnson &amp; Co., Stureplan 3, Stockholm",
                        "phone": "»Johnsons»"
                    },
                    {
                        "location": "AB. Nynäs-Petroleum, Jakobs-bergsg. 2, Stockholm",
                        "phone": "235440"
                    }
                ],
                "financials": {
                    "employees": {
                        "industriarb.": 350
                    }
                },
                "corporation_year": 1928,
                "manager": "disp. Per H. W. Ågren"
            },
            "5": {
                "name": "Alfr. Jonsson Fabriks AB.",
                "location": "Lidköping",
                "business": "Mek. verkstad och sågbladsfabrik",
                "products": "Tillverkar bågfils- och maskinsågblad för metall (märken: »Solo» o. »Solo-Wol-fram»), bandsågblad för trä samt slip-och polermaskiner.",
                "contact": {
                    "phone": "20224",
                    "postgiro": "88464"
                },
                "financials": {
                    "capital": "40,500 kr",
                    "employees": {
                        "industriarb.": 15
                    },
                    "annual_production_value": "260,000 kr"
                },
                "corporation_year": 1941,
                "board": [
                    {
                        "name": "fabr. Arvid Jonsson",
                        "role": ""
                    },
                    {
                        "name": "fabr. Einar Jonsson",
                        "role": ""
                    },
                    {
                        "name": "fabr. Emil Jonsson",
                        "role": ""
                    }
                ],
                "director": "Arvid Jonsson"
            },
            "6": {
                "name": "Axel Jonssons Svarveri",
                "location": "Vetlanda",
                "business": "Tillverkar pelarbord och barnstolar",
                "contact": {
                    "phone": "307",
                    "postgiro": "144494"
                },
                "financials": {
                    "employees": {
                        "industriarb.": 25
                    }
                },
                "corporation_year": 1914,
                "owners": [
                    "fabr. Axel Jonsson",
                    "fabr. Folke Jonsson"
                ]
            },
            "7": {
                "name": "C. A. Jonssons Skofabrik AB.",
                "location": "Kumla",
                "business": "Skofabrik i Kumla (Örebro l.)",
                "products": "Tillverkar randsydda, durksydda, pliggade och sandalsydda skodon. Varumärken: »Ex-cellent», »S:t Moritz», »Grandezza» o. »Gulliver».",
                "contact": {
                    "phone": "70910",
                    "postgiro": "28309"
                },
                "financials": {
                    "capital": "500,000 kr",
                    "employees": {
                        "industriarb.": 130
                    },
                    "annual_production_value": "2,500,000 kr"
                },
                "corporation_year": 1934,
                "board": [
                    {
                        "name": "fabr. Carl A. Jonsson",
                        "role": ""
                    },
                    {
                        "name": "disp. C. Lennart Jonsson",
                        "role": ""
                    },
                    {
                        "name": "fru Hulda Jonsson",
                        "role": ""
                    }
                ],
                "director": "Carl A. Jonsson"
            }
        }
    }
}