{
    "original": "Lejonet—Lenna\n\n* Lejonets Fabriker AB., Stockholm.\n\nLivsmedelsfabrik och kemisk-teknisk\nfabrik. Tillverkar wafers samt hudkräm,\npuder, hårvatten m. m. Varumärke:\n»Lejonet».\n\nKontor o. ensamförsäljn.: Elis\nPihl-kvist &amp; Co. AB., Bredgränd 1. Telefon:\n230120. Postgiro: 3708.\n\nAkt.-kap.: 25,000 kr. Antal\nindustriarb.: 15. Tillv.-värde pr år (egen\ntillverkning): 400,000 kr. — Firman etabl.\n1898 såsom kafferosteri, nuv. bolag 1930.\n\nStyrelse: polisint. Alvar Zetterquist\n(ordf.), dir. Georg Hurtig, fru Mary\nPihlkvist-Liljeson.\n\nVerkst. dir.: Georg Hurtig.\n\nKamrer: Frank Weslien.\n\nDriftsing.; Harry S. Jansson.\n\nLeksaksfabriken Norco,\n\nStockholm.\n\nFabrik i Norrköping för tillverkning\nav stoppade djur och dockor.\n\nKontor: Stockholm, Upplandsg. 19 A.\nTelefon: 308499. Postgiro: 58256. —\n\nAntal industriarb.: 33. Tillv.-värde pr år:\n310,000 kr. — Firman etabl. 1935.\n\nÄgare: fil. dr A. Magasanik.\n\nFabriks förest.: Kurt Westerberg.\n\nLeksaksfabriken, Svenska,\n\nHälsingborg.\n\nSe Svenska Leksaksfabriken,\nHälsingborg.\n\nAB. Leksandsbröd, Häradsbygden.\n\nSpisbrödsfabrik och handelskvarn i\nHäradsbygden (Kopparb. l.).\n\nTillverkar spis- och knäckebröd samt\nrågmjöl för eget behov. Varumärken:\n»Leksandsbröd» och »Ruth-röd».\n\nTelefon: 17 o. 87. Postgiro: 85925. —\nAkt.-kap.: 67,000 kr. Antal industriarb.:\n18. Tillv.-värde pr år: 350,000 kr. —\nBolaget grundat 1929.\n\nVerkst. dir.: fabr. Martin Joon.\n\nAB. Lemunda Sandstensbrott,\n\nMotala.\n\nSandstensbrott vid Lemunda, Motala.\nTillverkar slipstenar och raffinörstenar;\nbryter byggnadssten och kvartssandsten\nför ugnar och till beredning av formsand\noch kupolugnsmassa m. m., levererar\nkvartssand för stålgjutning, blästring,\nslipning, glas ti 11 verkning samt kärnsand,\nformsand och kupolugnsmassa. Bolaget\ndriver jämväl rederirörelse.\n\nTelegr.-adr.: Lemundabolaget, Motala.\nTelefon: 86. — Akt.-kap.: 270,000 kr.\nAntal industriarb.: 60. — Bolaget\ngrundat 1899.\n\nStyrelse: folkskollärare Åke G.\nOlofsson (ordf.), köpman H. Almborg,\ngods-äg. Arvid Olofsson.\n\nDisp.: ing. E. V. Abenius.\n\n* Albin Lenhardtsons Stomatolfabrik,\n\nStockholm.\n\nSe AB. Grumme &amp; Son, Stockholm.\n\nLenhovda Radiatorfabriks AB.,\n\nLenhovda.\n\nTillverkar värmeiedningsradiatorer av\nplåt vid mek. verkstad i Lenhovda\n(Kronob. l.).\n\nTelegr.-adr.: Radiatorer, Lenhovda,\nVäxjö. Telefon: SS. Postgiro: 131650. —\nAkt.-kap.: 60,000 kr. Antal industriarb.:\n30. — Bolaget grundat 1936.\n\nDisp.: Yngve Johansson.\n\n*AB. Lenhovdaverken, Lenhovda.\n\nSnickeri- och trähusfabrik i Lenhovda\n(Kronob. l.). Tillverkar\nmonteringsfärdiga trähus, snickerier samt lådor.\n\nHuvudkontor: Lenhovda. Telegr.-adr.:\nHovdaverk, Lenhovda. Telefon: 161—63.\nPostgiro: 11461. Försäljn.-kontor:\nStockholm, Radmansg. 72, telefon: 300704;\nNorrköping, Generalsg. 1, telefon: 21664\no. 21864.\n\nAkt.-kap.: 190,000 kr. Antal\nindustriarb.: 210. Tillv.-värde pr år: 4,000,000\nkr. — Bolaget grundat 1944 efter\növertagandet av fd. Lenhovda Träförädlings\nAB. och AB. Lenhovda Snickerifabrik.\n\nStyrelse: grossh. Artur Alexandersson\n(ordf.), disp. Eric Jakobsson,\nbyggnads-ing. Henry Johansson, disp. Oscar\nTörn-qvist, kamrer Gustaf Widerström.\n\nVerkst. dir.: Artur Alexandersson.\n\n*Lenna Bruks AB., Länna.\n\nSågverk, hyvleri och snickerifabrik vid\nLänna (Sthlms l.). Tillverkar sågade och\nhyvlade trävaror, byggnadssnickerier samt\nmonteringsfärdiga trähus. Bolaget driver\näven jordbruk och skogshantering.\n\nHuvudkontor: Länna. Telefon: Länna\n57. Postgiro: 134335. Ensamförsälj. för\nmonteringsfärdiga trähus; AB. Svenska\nTrähus, Stockholm, Birger Jarlsg. 27,\ntelefon: »Svenska Trähus».\n\nAkt.-kap.: 2,100,000 kr. Antal\nindustriarb.: 175. — Bolaget grundat 1912.\n\no o O\n-K-uZo",
    "structured": {
        "1": {
            "name": "Lejonets Fabriker AB.",
            "location": "Stockholm",
            "business": "Livsmedelsfabrik och kemisk-teknisk fabrik",
            "products": "Tillverkar wafers samt hudkräm, puder, hårvatten m. m.",
            "contact": {
                "office": "Elis Pihlkvist & Co. AB., Bredgränd 1.",
                "phone": [
                    "230120"
                ],
                "postgiro": "3708"
            },
            "financials": {
                "capital": "25,000 kr",
                "employees": {
                    "industriarb": 15
                },
                "annual_turnover": "400,000 kr",
                "annual_production_value": "400,000 kr"
            },
            "foundation_year": 1898,
            "board": [
                {
                    "name": "polisint. Alvar Zetterquist",
                    "role": "ordf."
                },
                {
                    "name": "dir. Georg Hurtig",
                    "role": ""
                },
                {
                    "name": "fru Mary Pihlkvist-Liljeson",
                    "role": ""
                }
            ]
        },
        "2": {
            "name": "Leksaksfabriken Norco",
            "location": "Stockholm",
            "products": "Tillverkning av stoppade djur och dockor",
            "contact": {
                "office": "Upplandsg. 19 A",
                "phone": [
                    "308499"
                ],
                "postgiro": "58256"
            },
            "financials": {
                "employees": {
                    "industriarb": 33
                },
                "annual_turnover": "310,000 kr"
            },
            "foundation_year": 1935,
            "owners": [
                "fil. dr A. Magasanik"
            ],
            "manager": "Kurt Westerberg"
        },
        "3": {
            "name": "AB. Leksandsbröd",
            "location": "Häradsbygden",
            "business": "Spisbrödsfabrik och handelskvarn",
            "products": "Tillverkar spis- och knäckebröd samt rågmjöl för eget behov",
            "contact": {
                "phone": [
                    "17",
                    "87"
                ],
                "postgiro": "85925"
            },
            "financials": {
                "capital": "67,000 kr",
                "employees": {
                    "industriarb": 18
                },
                "annual_turnover": "350,000 kr"
            },
            "foundation_year": 1929,
            "director": "fabr. Martin Joon"
        },
        "4": {
            "name": "AB. Lemunda Sandstensbrott",
            "location": "Motala",
            "business": "Sandstensbrott",
            "products": "Tillverkar slipstenar och raffinörstenar; bryter byggnadssten och kvartssandsten för ugnar och till beredning av formsand och kupolugnsmassa m. m., levererar kvartssand för stålgjutning, blästring, slipning, glastillverkning samt kärnsand, formsand och kupolugnsmassa",
            "contact": {
                "telegraph": "Lemundabolaget, Motala",
                "phone": [
                    "86"
                ],
                "financials": {
                    "capital": "270,000 kr",
                    "employees": {
                        "industriarb": 60
                    }
                },
                "foundation_year": 1899,
                "board": [
                    {
                        "name": "folkskollärare Åke G. Olofsson",
                        "role": "ordf."
                    },
                    {
                        "name": "köpman H. Almborg",
                        "role": ""
                    },
                    {
                        "name": "gods-äg. Arvid Olofsson",
                        "role": ""
                    },
                    {
                        "name": "ing. E. V. Abenius",
                        "role": "Disp."
                    }
                ]
            },
            "5": {
                "name": "Lenhovda Radiatorfabriks AB.",
                "location": "Lenhovda",
                "business": "Tillverkar värmeledningsradiatorer av plåt",
                "products": "Vid mek. verkstad i Lenhovda (Kronob. l.)",
                "contact": {
                    "telegraph": "Radiatorer, Lenhovda, Växjö",
                    "phone": [
                        "SS"
                    ],
                    "postgiro": "131650"
                },
                "financials": {
                    "capital": "60,000 kr",
                    "employees": {
                        "industriarb": 30
                    }
                },
                "foundation_year": 1936,
                "director": "Yngve Johansson"
            },
            "6": {
                "name": "AB. Lenhovdaverken",
                "location": "Lenhovda",
                "business": "Snickeri- och trähusfabrik",
                "products": "Tillverkar monteringsfärdiga trähus, snickerier samt lådor",
                "contact": {
                    "phone": [
                        "161-63"
                    ],
                    "postgiro": "11461",
                    "sales_offices": [
                        {
                            "location": "Stockholm",
                            "phone": "300704"
                        },
                        {
                            "location": "Norrköping",
                            "phone": "21664 o. 21864"
                        }
                    ]
                },
                "financials": {
                    "capital": "190,000 kr",
                    "employees": {
                        "industriarb": 210
                    },
                    "annual_turnover": "4,000,000 kr"
                },
                "foundation_year": 1944,
                "board": [
                    {
                        "name": "grossh. Artur Alexandersson",
                        "role": "ordf."
                    },
                    {
                        "name": "disp. Eric Jakobsson",
                        "role": ""
                    },
                    {
                        "name": "byggnads-ing. Henry Johansson",
                        "role": ""
                    },
                    {
                        "name": "disp. Oscar Törn-qvist",
                        "role": ""
                    },
                    {
                        "name": "kamrer Gustaf Widerström",
                        "role": ""
                    },
                    "manager: Artur Alexandersson"
                ],
                "7": {
                    "name": "Lenna Bruks AB.",
                    "location": "Länna",
                    "business": "Sågverk, hyvleri och snickerifabrik",
                    "products": "Tillverkar sågade och hyvlade trävaror, byggnadssnickerier samt monteringsfärdiga trähus",
                    "contact": {
                        "phone": [
                            "Länna 57"
                        ],
                        "postgiro": "134335"
                    },
                    "financials": {
                        "capital": "2,100,000 kr",
                        "employees": {
                            "industriarb": 175
                        }
                    },
                    "foundation_year": 1912
                }
            }
        }
    }
}