{
    "original": "Bonnier—Borg\n\nTelegr.-adr.: Bong, Ystad. Telefon: 8\no. 9. Postgiro: 23181. Representanter:\nPatrik Petersson, Stockholm, Hornsg.\n51, telefon: 438760; Ossian Carlson &amp; Co\nAB., Göteborg, N. Gubberog. 11, telefon:\n154415; för Skåne: John Johnson,\nHälsingborg, Drottningg. 15, telefon: 14545.\n\nAkt.-kap.: 300,600 kr. Antal\nindustriarb.: 65. Tillv.-värde pr år: 1,400,000 kr.\n\n—\tFirman etabl. 1890, bolag 1930.\n\nStyrelse; fabr. Gustaf Bong,\nkontorschef Ludvig Bong, bankdir. Axel\nJonason, lantbr. Johan L. Larsson.\n\nDisp.: Fredrik Bong.\n\nKontorschef: Ludvig Bong.\n\n*AIbert Bonniers Förlag AB.,\n\nStockholm.\n\nBokförlag, boktryckeri, bokbinder i,\noffset samt klichéanstalt.\n\nKontor: Sveavägen 56. Telegr.-adr. o.\ntelefon: Bonniers, Stockholm.\n\nAkt.-kap.: 2,100,000 kr. Antal\nindustriarb.: 545. — Bokförlagsrörelsen etabl.\n1837.\n\nStyrelse: bokförl. Tor Bonnier (ordf.),\nherr Gerard Bonnier, bokförl. Kaj\nBonnier, adv. Ivar Philipson.\n\nTekn. chef: disp. Lars Gustaf Brolin.\n\nBore, Konservfabriken, Lyse.\n\nSe Konservfabriken Bore, Lyse.\n\nBore, Skjortfabriken, AB.,\n\nTrollhättan.\n\nSe Skjortfabriken Bore AB.,\nTrollhättan.\n\nBoréns AB., Borås.\n\nMetallvarufabrik. Tillverkar elektr.\nbelysningsarmatur. Varumärken: »BABO»\no. »Hellas».\n\nTelefon: 17900. Postgiro: 34110. —\nAkt.-kap.: 50,000 kr. Antal industriarb.:\n63. Tillv.-värde pr år: 600,000 kr. —\nFirman etabl. 1924.\n\nDisp.: Karl Boren.\n\n*Borens Trikåfabrik AB., Motala.\n\nTillverkar herr-, dam- och barnartiklar\ni trikå. Specialitet: konstsilke-,\nimitat-och lahmannsartiklar i underkläder.\n\nTelefon: 450 o. 879. Postgiro: 177317.\n\n—\tAkt.-kap.: 90,000 kr. Antal\nindustriarb.: 125. — Tillv.-värde pr år: 1,800,000\nkr. — Firman etabl. 1916, bolag 1936.\n\nStyrelse o. verkst. dir.: fabr. Ivar\nEricson.\n\nBorensbergs Glasbruks Arrenda-\n\ntorer, Borensberg.\n\nTillverkar buteljer vid glasbruk i\nBorensberg (Östergötl. l.).\n\nTelefon: 19. Postgiro: 87788.\n\nAndelskap.: 300,000 kr. Antal\nindustriarb.: 33. Tillv.-värde pr år: 365,000\nkr. — Bolaget grundat 1932.\n\nDisp.: Hjalmar Råsberg.\n\nAB. Borensbergs Mek. Verkstad,\n\nMotala.\n\nSe Verkstads AB. Lindqvist, Motala.\n\nBorgs Fabriks AB., Norrköping.\n\nSpinneri i Kneippbaden, Norrköping.\nTillverkar vigogne- och yllegarner samt\nutför löngodsarbeten.\n\nTelefon: Norrköping 20385. Postgiro:\n71501. — Akt.-kap.: 100,000 kr. Antal\nindustriarb.: 22. Tillv.-värde pr år:\n225,000 kr. — Bolaget grundat 1904.\n\nStyrelse: ing. Sven-Erik Ronnerström\n(ordf.), fru D. Ronnerström, fru Gunvor\nRonnerström.\n\nVerkst. dir. o. disp.: Sven-Erik\nRonnerström.\n\n*AB. Borgs Snickerifabrik,\n\nNorrköping.\n\nTillverkar fönster, dörrar, trappor och\nköksinredningar.\n\nKontor: Torsgatan 1; postadr.:\nNorrköping 5. Telefon: 25202. Postgiro:\n161047.\n\nAkt.-kap.: 40,000 kr. Antal\nindustriarb.: 20. Tillv.-värde pr år: 250,000 kr.\n— Firman etabl. 1926, bolag 1939.\n\nStyrelse: disp. Ivar Karlsson (ordf.),\nverkm. Waldemar Karlsson.\n\nDisp.: Ivar Karlsson.\n\n*A. J. Borgs Väfveri AB., Kinnahult.\n\nJacquardväveri i örby s:n (Älvsb. l.).\nTillverkar möbeltyger, ottoman- och\nsängöverkast, badväv, gardin- och\ndraperityger, allmogevävnader m. m.\n\nPostadr.: Kinnahult. Telegr.-adr.: Borg,\nKinna. Telefon: Kinna »Borgs väveri»\no. 10670. Postgiro: 10636. Repr. för\nStockholm: Gösta Fredberg, Regeringsg.\n56, telefon: 200678.\n\nAkt.-kap.: 800,000 kr. Antal\nindustriarb.: 166. — Firman etabl. 1893, bolag\n1917.\n\nStyrelse: dir. Carl Gustaf Borg (ordf.),\ning. Bror Erik Borg (v. ordf.), disp. Tage\nBorg.\n\nVerkst. dir.: Carl Gustaf Borg.\n\nDisp.: Tage Borg.",
    "structured": {
        "1": {
            "name": "Bong, Ystad",
            "location": "Ystad",
            "business": "Telegraftjänster",
            "contact": {
                "telegraph": "Bong, Ystad",
                "postgiro": "23181",
                "sales_offices": [
                    {
                        "location": "Stockholm",
                        "phone": "438760"
                    },
                    {
                        "location": "Göteborg",
                        "phone": "154415"
                    },
                    {
                        "location": "Hälsingborg",
                        "phone": "14545"
                    }
                ]
            },
            "financials": {
                "capital": "300 600 kr",
                "employees": {
                    "industriarb": 65
                },
                "annual_turnover": "Information saknas",
                "annual_production_value": "1 400 000 kr"
            },
            "foundation_year": 1890,
            "corporation_year": 1930,
            "board": [
                {
                    "name": "Gustaf Bong",
                    "role": "Fabrikör"
                },
                {
                    "name": "Ludvig Bong",
                    "role": "Kontorschef"
                },
                {
                    "name": "Axel Jonason",
                    "role": "Bankdirektör"
                },
                {
                    "name": "Johan L. Larsson",
                    "role": "Lantbrukare"
                }
            ],
            "director": "Fredrik Bong",
            "managing_director": "Ludvig Bong"
        },
        "2": {
            "name": "Albert Bonniers Förlag AB.",
            "location": "Stockholm",
            "business": "Bokförlag, boktryckeri, bokbinderi, offset samt klichéanstalt",
            "contact": {
                "office": "Sveavägen 56",
                "telegraph": "Bonniers, Stockholm",
                "phone": [
                    "Information saknas"
                ],
                "postgiro": "23181"
            },
            "financials": {
                "capital": "2 100 000 kr",
                "employees": {
                    "industriarb": 545
                },
                "annual_turnover": "Information saknas",
                "annual_production_value": "Information saknas"
            },
            "foundation_year": "1837",
            "board": [
                {
                    "name": "Tor Bonnier",
                    "role": "Bokförläggare (ordförande)"
                },
                {
                    "name": "Gerard Bonnier",
                    "role": "Herr"
                },
                {
                    "name": "Kaj Bonnier",
                    "role": "Bokförläggare"
                },
                {
                    "name": "Ivar Philipson",
                    "role": "Advokat"
                }
            ],
            "director": "Information saknas"
        },
        "3": {
            "name": "Boréns AB.",
            "location": "Borås",
            "business": "Metallvarufabrik. Tillverkar elektr. belysningsarmatur. Varumärken: »BABO» o. »Hellas»",
            "contact": {
                "phone": [
                    "17900"
                ],
                "postgiro": "34110"
            },
            "financials": {
                "capital": "50 000 kr",
                "employees": {
                    "industriarb": 63
                },
                "annual_turnover": "Information saknas",
                "annual_production_value": "600 000 kr"
            },
            "foundation_year": 1924,
            "board": [
                {
                    "name": "Karl Boren",
                    "role": "Direktör"
                }
            ],
            "director": "Karl Boren"
        },
        "4": {
            "name": "Borens Trikåfabrik AB.",
            "location": "Motala",
            "business": "Tillverkar herr-, dam- och barnartiklar i trikå. Specialitet: konstsilke-, imitat-och lahmannsartiklar i underkläder",
            "contact": {
                "phone": [
                    "450",
                    "879"
                ],
                "postgiro": "177317"
            },
            "financials": {
                "capital": "90 000 kr",
                "employees": {
                    "industriarb": 125
                },
                "annual_turnover": "Information saknas",
                "annual_production_value": "1 800 000 kr"
            },
            "foundation_year": "1916",
            "corporation_year": 1936,
            "director": "Ivar Ericson"
        },
        "5": {
            "name": "Borensbergs Glasbruks Arrendatorer",
            "location": "Borensberg",
            "business": "Tillverkar buteljer vid glasbruk i Borensberg (Östergötl. l.)",
            "contact": {
                "phone": [
                    "19"
                ],
                "postgiro": "87788"
            },
            "financials": {
                "capital": "300 000 kr",
                "employees": {
                    "industriarb": 33
                },
                "annual_turnover": "Information saknas",
                "annual_production_value": "365 000 kr"
            },
            "corporation_year": 1932,
            "director": "Hjalmar Råsberg"
        },
        "6": {
            "name": "AB. Borensbergs Mek. Verkstad",
            "location": "Motala",
            "business": "Information saknas",
            "contact": {
                "phone": [
                    "Information saknas"
                ],
                "postgiro": "Information saknas"
            }
        },
        "7": {
            "name": "Borgs Fabriks AB.",
            "location": "Norrköping",
            "business": "Spinneri i Kneippbaden, Norrköping. Tillverkar vigogne- och yllegarner samt utför löngodsarbeten",
            "contact": {
                "phone": [
                    "Norrköping 20385"
                ],
                "postgiro": "71501"
            },
            "financials": {
                "capital": "100 000 kr",
                "employees": {
                    "industriarb": 22
                },
                "annual_turnover": "Information saknas",
                "annual_production_value": "225 000 kr"
            },
            "corporation_year": 1904,
            "board": [
                {
                    "name": "Sven-Erik Ronnerström",
                    "role": "Ingenjör (ordförande)"
                },
                {
                    "name": "D. Ronnerström",
                    "role": "Fru"
                },
                {
                    "name": "Gunvor Ronnerström",
                    "role": "Fru"
                }
            ],
            "director": "Sven-Erik Ronnerström"
        },
        "8": {
            "name": "AB. Borgs Snickerifabrik",
            "location": "Norrköping",
            "business": "Tillverkar fönster, dörrar, trappor och köksinredningar",
            "contact": {
                "office": "Torsgatan 1",
                "postgiro": "161047"
            },
            "financials": {
                "capital": "40 000 kr",
                "employees": {
                    "industriarb": 20
                },
                "annual_turnover": "Information saknas",
                "annual_production_value": "250 000 kr"
            },
            "foundation_year": 1926,
            "corporation_year": 1939,
            "board": [
                {
                    "name": "Ivar Karlsson",
                    "role": "Direktör (ordförande)"
                },
                {
                    "name": "Waldemar Karlsson",
                    "role": "Verkställande direktör"
                }
            ],
            "director": "Ivar Karlsson"
        },
        "9": {
            "name": "A. J. Borgs Väfveri AB.",
            "location": "Kinnahult",
            "business": "Jacquardväveri i örby s:n (Älvsb. l.). Tillverkar möbeltyger, ottoman- och sängöverkast, badväv, gardin- och draperityger, allmogevävnader m. m",
            "contact": {
                "location": "Kinnahult",
                "telegraph": "Borg, Kinna",
                "phone": [
                    "Kinna »Borgs väveri» o.",
                    "10670"
                ],
                "postgiro": "10636"
            },
            "financials": {
                "capital": "800 000 kr",
                "employees": {
                    "industriarb": 166
                },
                "annual_turnover": "Information saknas",
                "annual_production_value": "Information saknas"
            },
            "foundation_year": 1893,
            "corporation_year": 1917,
            "board": [
                {
                    "name": "Carl Gustaf Borg",
                    "role": "Direktör (ordförande)"
                },
                {
                    "name": "Bror Erik Borg",
                    "role": "Ingenjör (vice ordförande)"
                },
                {
                    "name": "Tage Borg",
                    "role": "Direktör"
                }
            ],
            "director": "Carl Gustaf Borg"
        }
    }
}