{
    "original": "Kemiska—Kihlberg\n\ngalvaniseringsändamål samt utför\nfullständiga inredningar för\ngalvaniserings-verkstäder.\n\nTelegr.-adr.: Galvanosalt, Partille.\nTelefon: 18 o. 219. Postgiro: 11519.\n\nAkt.-kap.: 75,000 kr. Antal\nindustriarb.: 36. Tillv.-värde pr år: 1,200,000 kr.\n\n—\tFirman etabl. 1909, bolag 1930.\n\nStyrelse: kommendörkapten Erik Sund-\n\nblad (ordf.), dr Ernst Harbeck, civiling.\nErik Sundberg.\n\nVerkst. dir.: Erik Sundberg.\n\nDriftsing.: civiling. Gunvald Jonsson.\n\nKamrer: Rickard Magnusson.\n\n*AB. Kemiska Fabriken Monopol,\n\nBorås.\n\nTillverkar hjälpprodukter för\ntextilindustri och garverier såsom\nricinolje-och fettalkoholsulfonat, tvål, såpa,\nappre-turmedel, sulfonerad tran,\ntätningsme-del för cement och murbruk (»Poresit»)\nm. m.\n\nTelegr.-adr.: Monopol, Borås. Telefon:\n10678 o. 14301. Postgiro: 33935. —\nAkt.-kap.: 225,000 kr. Arb.-antal: 10. —\nFabriken grundad 1903.\n\nStyrelse: v. konsul K. A. Evers (ordf.),\ndir. Josef Lerjefors, kand. Erik Törnell.\n\nVerkst. dir. o. disp.: Josef Lerjefors.\n\nDriftsing.: Bror Hansson.\n\nAB. Kemiska Fabriken Norden,\n\nGöteborg.\n\nFärg- och fernissfabrik i Älvängen\n(Älvsb. l.). Tillverkar spec.\nskeppsbotten-färger och rostskyddsfärger samt färger\nmot kemiska angrepp. Varumärken:\n»Ekorren» o. »Nordolinolja».\n\nKontor: Packhusplatsen 2; postadr.:\nGöteborg. Telegr.-adr.: Bunnfärg,\nGöteborg. Telefon: 113530. Postgiro: 46386.\n\nAkt.-kap.: 120,000 kr. Antal\nindustriarb.: 10. Tillv.-värde pr år: 750,000 kr.\n\n—\tFirman etabl. 1938, bolag 1942.\n\nDisp.: Bertil Damm.\n\nDriftsing.: civiling. Sven Kristensson.\n\n*Kemiska Industrier, AB.\nCentral-bolaget för, Stockholm.\n\nSe Centralbolaget för Kemiska\nIndustrier AB., Stockholm.\n\nKerba, Industri AB., Göteborg.\n\nSe Industri AB. Kerba, Göteborg.\n\nKerema, Konfektions AB., Borås.\n\nSe Konfektions AB., Kerema, Borås.\n\n*AB. Keros, Stockholm.\n\nGlödnätsfabrik i Södertälje. Tillverkar\nglödnät för gas, fotogen, bensin, acetylen,\nsprit m. m. Varunamn: »Keros».\nFörsäljer glödljuslampor och -lyktor av\nfrämmande fabrikat.\n\nKontor: Stockholm, Sveavägen 33.\nTelegr.-adr.: Keros, Stockholm. Telefon:\n105394. Fabrikskontor: Södertälje,\ntelefon: 30432 o. 30932. Postgiro: 26054.\n\nAkt.-kap.: 300,000 kr. Antal\nindustriarb.: 35 ävensom 50 hemarb. — Bolaget\ngrundat 1901.\n\nStyrelse: dir. Nils Westberg (ordf.),\ndir. Gunnar Dalén, fil. dr Birger\nLindgren.\n\nDisp.: J. Erh. Ericson (Södertälje).\n\n*\tKexfabriken, Kungälv.\n\nSe Göteborgs Kexfabriks AB., Kungälv.\n\n*\tKexfabriken, Stockholm.\n\nSe AB. Stockholms Kexfabrik,\nStockholm.\n\n*Kexfabriken, Örebro.\n\nSe AB. Örebro Kexfabrik, Örebro.\n\n*Kifa, Stockholm.\n\nSe Kirurgiska Instrument Fabriks AB.\nKifa, Stockholm.\n\nAB. Kigus Instrumentfabrik,\n\nHuvudsta, Solna.\n\nTillverkar tandläkarutensilier vid\ninstrumentfabrik i Huvudsta (Stockh. l.).\nVarumärke: »Kigus».\n\nTelegr.-adr.: Kigus, Stockholm.\nTelefon: Stockholm 271752. Postgiro: 193635.\n\nAkt.-kap.: 72,000 kr. Antal\nindustriarb.: 18. Tillv.-värde pr år: 300,000 kr.\n— Bolaget grundat 1943.\n\nVerkst. dir.: tandläkare Karl Diamant.\n\n* Josef Kihlberg, II jo.\n\nSmidesverkstäder, gjuteri och mek.\nverkstad. Tillverkar vagns- och\nautomo-bilfjädrar, kapsågar (märke: »Göta»),,\nhäftklammer, häfthammare och\nhäft-apparater (märke: »Ortona») samt\nsmi-den och pressade artiklar. Firman driver\näven engrosr och minuthandel med\njärnvaror samt engroshandel med skriv- och\nräknemaskiner.",
    "structured": {
        "1": {
            "name": "AB. Kemiska Fabriken Monopol",
            "location": "Borås",
            "business": "Tillverkar hjälpprodukter för textilindustri och garverier såsom ricinolje-och fettalkoholsulfonat, tvål, såpa, appreturmedel, sulfonerad tran, tätningsmedel för cement och murbruk (»Poresit») m. m.",
            "contact": {
                "office": "Monopol, Borås",
                "phone": [
                    "10678",
                    "14301"
                ],
                "postgiro": "33935"
            },
            "financials": {
                "capital": "225,000 kr",
                "employees": {
                    "arb.antal": 10
                },
                "annual_turnover": "N/A",
                "annual_production_value": "N/A"
            },
            "foundation_year": 1903,
            "board": [
                {
                    "name": "v. konsul K. A. Evers",
                    "role": "ordf."
                },
                {
                    "name": "dir. Josef Lerjefors",
                    "role": "N/A"
                },
                {
                    "name": "kand. Erik Törnell",
                    "role": "N/A"
                }
            ],
            "director": "Josef Lerjefors"
        },
        "2": {
            "name": "AB. Kemiska Fabriken Norden",
            "location": "Göteborg",
            "business": "Färg- och fernissfabrik i Älvängen (Älvsb. l.). Tillverkar spec. skeppsbotten-färger och rostskyddsfärger samt färger mot kemiska angrepp. Varumärken: »Ekorren» o. »Nordolinolja».",
            "contact": {
                "office": "Göteborg",
                "phone": [
                    "113530"
                ],
                "postgiro": "46386"
            },
            "financials": {
                "capital": "120,000 kr",
                "employees": {
                    "arb.antal": 10
                },
                "annual_turnover": "750,000 kr",
                "annual_production_value": "N/A"
            },
            "foundation_year": 1938,
            "board": [
                {
                    "name": "N/A",
                    "role": "ordf."
                }
            ],
            "director": "N/A"
        },
        "3": {
            "name": "AB. Keros",
            "location": "Stockholm",
            "business": "Glödnätsfabrik i Södertälje. Tillverkar glödnät för gas, fotogen, bensin, acetylen, sprit m. m. Varunamn: »Keros». Försäljer glödljuslampor och -lyktor av främmande fabrikat.",
            "contact": {
                "office": "Stockholm, Sveavägen 33",
                "phone": [
                    "105394"
                ],
                "postgiro": "26054"
            },
            "financials": {
                "capital": "300,000 kr",
                "employees": {
                    "industriarb.": 35,
                    "hemarb.": 50
                },
                "annual_turnover": "N/A",
                "annual_production_value": "N/A"
            },
            "foundation_year": 1901,
            "board": [
                {
                    "name": "dir. Nils Westberg",
                    "role": "ordf."
                },
                {
                    "name": "dir. Gunnar Dalén",
                    "role": "N/A"
                },
                {
                    "name": "fil. dr Birger Lindgren",
                    "role": "N/A"
                }
            ],
            "director": "N/A"
        },
        "4": {
            "name": "AB. Kigus Instrumentfabrik",
            "location": "Huvudsta, Solna",
            "business": "Tillverkar tandläkarutensilier vid instrumentfabrik i Huvudsta (Stockh. l.). Varumärke: »Kigus».",
            "contact": {
                "office": "Kigus, Stockholm",
                "phone": [
                    "271752"
                ],
                "postgiro": "193635"
            },
            "financials": {
                "capital": "72,000 kr",
                "employees": {
                    "arb.antal": 18
                },
                "annual_turnover": "300,000 kr",
                "annual_production_value": "N/A"
            },
            "foundation_year": 1943,
            "board": [],
            "director": "tandläkare Karl Diamant"
        },
        "5": {
            "name": "Josef Kihlberg, II jo",
            "location": "N/A",
            "business": "Smidesverkstäder, gjuteri och mek. verkstad. Tillverkar vagns- och automobilfjädrar, kapsågar (märke: »Göta»), häftklammer, häfthammare och häftapparater (märke: »Ortona») samt smiden och pressade artiklar. Firman driver även engroshandel med järnvaror samt engroshandel med skriv- och räknemaskiner.",
            "financials": {
                "capital": "N/A",
                "employees": {
                    "N/A": "N/A"
                },
                "annual_turnover": "1,200,000 kr",
                "annual_production_value": "N/A"
            },
            "foundation_year": 1909,
            "board": [
                {
                    "name": "kommendörkapten Erik Sundblad",
                    "role": "ordf."
                },
                {
                    "name": "dr Ernst Harbeck",
                    "role": "N/A"
                },
                {
                    "name": "civiling. Erik Sundberg",
                    "role": "N/A"
                }
            ],
            "director": "Erik Sundberg"
        }
    }
}