{
    "original": "Stathmos—Stekens\n\nsågverk, hyvleri och\nträdestillations-verk i Grankullaviken pr Boda ■ och pr\nByxelkrok på Öland (Kalmar l.).\n\nTillverkar sågade och hyvlade trävaror,\nlådor, träull, monteringsfärdiga trähus,\nsulfatcellulosa, terpentin och\nhartsoljeprodukter, såpa och tvål, träkemiska\ndestillationsprodukter, träkol, trätjära,\nlösningsmedel, metylalkohol,\nättiksyreprodukter m. m.\n\nKontor: Stockholm, Drottningg. 48.\nTelegr.-adr.: Forestry, Stockholm.\nTelefon: »Skogsindustri». Postgiro: 179243.\n\nAkt.-kap.: 22,000,000 kr. Sammanlagt\nantal industriarb.: 2,041. — Bolaget\ngrundat 1941.\n\nStyrelse: generaldir. Bo v.\nStocken-ström (ordf.), f. d. justitierådet Rudolf\nEklund, överdir. E. Hedulff, dir. Knut\nO. Norlin, bruksdisp. Carl Sundberg.\nVerkst. dir.: Knut O. Norlin.\nKamrer: Enoch Rönnquist.\nChef för de tekn. avdelningarna:\nciviling. G. V. Silmark.\n\nFörsäljn.-chef er: Thure A. Nilsson, B.\nM. Odenman, Gunnar Englund o. W.\nöhrn.\n\nInköpschef: ing. Yngve Sellmann.\nByggnadschef: civiling. B. Sjöstedt,\nPlatschefer:\nSandviks sågverk: insp. A. Lindahl;\nBåtskärsnäs sågverk: förvalt. John Th.\nNyman.\n\nKarlsborgs verken: plats- o. driftschef för\nsulfatfabriken: civiling. Rutger\nMar-tin-Löf; förvalt. för sågverket: H.\nHackzell;\n\nLövholmens sågverk o. Sandviks legosåg-\n\nning: disp. C.-H. Hallgren;\nPiteå träkemiska fabriker: dispciviling.\n\nJohn Eliasson;\nHorndals sågverk: jägmäst. W.\nLejd-ström ;\n\nSaxvikens sågverk: förvalt. S. Linder;\nSkinnskattebergsverken: disp. Fritz\nMalmström;\n\nValåsens sågverk: förvalt. K. E.\nRingdahl;\tj\nSjöbacka sågverk: jägmäst. A.\nChatillon-Winbergh;\n\nGrankullavikens sågverk: förvalt. H.\nÅsberg;\n\nKungsskogens sågverk: jägmäst. B.\nBlohm.\n\n*AB. Stathmos, Eskilstuna.\n\nMek. verkstad i Eskilstuna. Tillverkar\nvågar av alla slag, såväl i standard- som\nspecialutförande.\n\nHuvudkontor: Eskilstuna. Telefon:\n»Stathmos». Postgiro: 31189.\nTelegr.-adr.: Stathmos, Eskilstuna. Utställning o.\n\nuthyrning av vågar: Stockholm, Birger\nJarlsg. 11, telefon: 102070.\n\nAkt.-kap.: 100,000 kr. Antal\nindustriarb.: 125.\n\nFirman, etabl. 1898 i Stockholm, nuv.\nbolag, grundat 1940, tillhör Kooperativa\nFörbundet.\n\nStyrelse: dir. Albin Johansson (ordf.),\nfil. lic. Mauritz Bonow, dir. Hj.\nDeger-stedt, dir. Hugo Edstam, dir. Eric\nOlsson, dir. G. Osvald, dir. Ernst Persson.\n\nDisp.: Holger Malm.\n\nFörsäljn.-chef: civiling. Egon\nNordström.\n\nInköpschef: Erik Utterström.\n\n*AB. Sem L. Stawe, Karlstad.\n\nTrikåfabrik. Tillverkar stickade varor\nsåsom koftor, jumpers, baddräkter,\nslipovers, herrvästar, barnkläder,\nsportartiklar samt äkta kamelhårsartiklar.\n\nTelegr.-adr.: Stawe, Karlstad. Telefon:\n10740, 11840 o. 13740. Postgiro: 13155.\nFörsäljn.-kontor: Stockholm, Sveavägen\n25—27, telefon: 100399.\n\nAkt.-kap.: 75,000 kr. Antal\nindustriarb.: 150. — Firman etabl. 1888, bolag\n1933.\n\nStyrelse o. verkst. dir.: disp. Tor Stawe.\n\nKontorschef: Eric Nilsson.\n\nStavsborgs AB., Stockholm.\n\nTillverkar betongvaror samt\nkrom-mönjepigment m. m. vid\nbetongvaru-fabrik och pulvriseringsverk i Stavsborg,\nSvartsjö (Sthlms l.).\n\nKontor: Stockholm, Lövholmsbrinken\n2; postadr.: Stockholm 9. Telefon:\n459850. Postgiro: 57790.\n\nAkt.-kap.: 400,000 kr. Antal\nindustriarb.: 50. Tillv.-värde pr år: 1,000,000 kr.\n— Bolaget grundat 1930 under namn AB.\nBetongklinker, nuv. namn 1943.\n\nStyrelse: dir. Ernst Wehtje (ordf.),\ndir. Malte Ström, disp. H. Seb. Tham.\n\nVerkst. dir.: disp. Ivar Strömberg.\n\n(Jfr annons efter Alphabetical List of\nGoods.)\n\n*Stekens Tegelbruk, E. Nymansson,\n\nAgnesberg.\n\nTegelbruk i Agnesberg (Älvsb. l.).\nTillverkar murtegel och dräneringsrör.\n\nTelefon: Göteborg 174017. Postgiro:\n42910. Försäljn.-kontor: Göteborg,\nKyr-kog. 4. Telefon: 131378.\n\nAntal industriarb.: 35. Årstillv.: 3,5\nmilj. st. tegelvaror. — Firman etabl.\n1898.\n\nÄgare: E. Nymanssons sterbhus.\n\nDisp.: Ragnar Nymansson.\n\n504*",
    "structured": {
        "1": {
            "name": "AB. Stathmos",
            "location": "Grankullaviken pr Boda ■ och pr Byxelkrok på Öland (Kalmar l.)",
            "business": "sågverk, hyvleri och trädestillations-verk",
            "products": "sågade och hyvlade trävaror, lådor, träull, monteringsfärdiga trähus, sulfatcellulosa, terpentin, hartsoljeprodukter, såpa, tvål, träkemiska destillationsprodukter, träkol, trätjära, lösningsmedel, metylalkohol, ättiksyreprodukter m.m.",
            "contact": {
                "office": "Stockholm, Drottningg. 48",
                "telegraph": "Forestry, Stockholm",
                "phone": [
                    "Skogsindustri"
                ],
                "postgiro": "179243"
            },
            "financials": {
                "capital": "22,000,000 kr",
                "employees": {
                    "industriarb": 2041
                },
                "foundation_year": 1941
            },
            "board": [
                {
                    "name": "Bo v. Stocken-ström",
                    "role": "generaldirektör (ordf.)"
                },
                {
                    "name": "Rudolf Eklund",
                    "role": "f.d. justitieråd"
                },
                {
                    "name": "E. Hedulff",
                    "role": "överdirektör"
                },
                {
                    "name": "Knut O. Norlin",
                    "role": "direktör"
                },
                {
                    "name": "Carl Sundberg",
                    "role": "bruksdisponent"
                }
            ],
            "director": "Knut O. Norlin",
            "sales_manager": "Thure A. Nilsson"
        },
        "2": {
            "name": "AB. Stathmos",
            "location": "Eskilstuna",
            "business": "Mek. verkstad",
            "products": "Vågar av alla slag, såväl i standard- som specialutförande",
            "contact": {
                "office": "Eskilstuna",
                "telegraph": "Stathmos, Eskilstuna",
                "phone": [
                    "Stathmos"
                ],
                "postgiro": "31189"
            },
            "financials": {
                "capital": "100,000 kr",
                "employees": 125,
                "foundation_year": 1940
            },
            "board": [
                {
                    "name": "Albin Johansson",
                    "role": "direktör (ordf.)"
                },
                {
                    "name": "Mauritz Bonow",
                    "role": "fil. lic."
                },
                {
                    "name": "Hj. Deger-stedt",
                    "role": "direktör"
                },
                {
                    "name": "Hugo Edstam",
                    "role": "direktör"
                },
                {
                    "name": "Eric Olsson",
                    "role": "direktör"
                },
                {
                    "name": "G. Osvald",
                    "role": "direktör"
                },
                {
                    "name": "Ernst Persson",
                    "role": "direktör"
                }
            ],
            "director": "Holger Malm",
            "sales_manager": "civiling. Egon Nordström"
        },
        "3": {
            "name": "AB. Sem L. Stawe",
            "location": "Karlstad",
            "business": "Trikåfabrik",
            "products": "Stickade varor såsom koftor, jumpers, baddräkter, slipovers, herrvästar, barnkläder, sportartiklar samt äkta kamelhårsartiklar",
            "contact": {
                "telegraph": "Stawe, Karlstad",
                "phone": [
                    "10740",
                    "11840",
                    "13740"
                ],
                "postgiro": "13155",
                "sales_office": [
                    {
                        "location": "Stockholm",
                        "phone": "100399"
                    }
                ]
            },
            "financials": {
                "capital": "75,000 kr",
                "employees": 150,
                "foundation_year": 1933
            },
            "board": [
                {
                    "name": "Tor Stawe",
                    "role": "disp."
                }
            ]
        },
        "4": {
            "name": "Stavsborgs AB.",
            "location": "Stockholm",
            "business": "Tillverkar betongvaror samt krommönjepigment m.m.",
            "products": "Murtegel, dräneringsrör",
            "contact": {
                "office": "Stockholm, Lövholmsbrinken 2",
                "postgiro": "57790",
                "phone": [
                    "459850"
                ]
            },
            "financials": {
                "capital": "400,000 kr",
                "employees": 50,
                "annual_production_value": "1,000,000 kr",
                "corporation_year": 1930
            },
            "board": [
                {
                    "name": "Ernst Wehtje",
                    "role": "direktör (ordf.)"
                },
                {
                    "name": "Malte Ström",
                    "role": "direktör"
                },
                {
                    "name": "H. Seb. Tham",
                    "role": "disp."
                }
            ],
            "director": "Ivar Strömberg"
        },
        "5": {
            "name": "Stekens Tegelbruk, E. Nymansson",
            "location": "Agnesberg (Älvsb. l.)",
            "business": "Tegelbruk",
            "products": "Murtegel, dräneringsrör",
            "contact": {
                "phone": [
                    "Göteborg 174017"
                ],
                "postgiro": "42910",
                "sales_office": [
                    {
                        "location": "Göteborg",
                        "phone": "131378"
                    }
                ]
            },
            "financials": {
                "employees": 35,
                "annual_production_value": "3,5 milj. st. tegelvaror",
                "foundation_year": 1898
            },
            "owners": [
                "E. Nymanssons sterbhus"
            ],
            "director": "disp. Ragnar Nymansson"
        }
    }
}