{
    "original": "Smålaiidsstenar—Snickerifabriken\n\nStyrelse: fabr. Ä. L. Tidstrand (ordf.),\ning. Gunnar Tidstrand, disp. Henry\nTidstrand, dir. Ragnar Tidstrand, disp.\nSven Tidstrand.\n\nVerkst. dir.: A. L. Tidstrand.\n\nDisp.: Henry Tidstrand.\n\nKamrer: John Möllgård.\n\nÄB. Smålandsstenars Mek. Verkstad,\n\nSmalandsstenar.\n\nTillverkar maskiner för massartiklar av\ntråd och band såsom spikmaskiner,\nexcen-terpressar, trådriktmaskiner,\nfjädermaskiner, kedjemaskiner, nitpressar m. fl. vid\nmek. verkstad i Smålandsstenar\n(Jönköp. l.).\n\nTelefon: 55 o. 59. Postgiro: 22598. -—\nAkt.-kap.: 52,000 kr. Antal industriarb.:\n35. Tillv.-värde pr år: 350,000 kr. —\nBolaget grundat 1922.\n\nDisp.: Ture Peterson.\n\n\"AB. Smålandsstenars Trikåfabrik,\n\nSmålandsstenar.\n\nTrikåfabrik i Smålandsstenar (Jönköp.\n1.). Tillverkar herr- och damtrikåvaror.\n\nTelefon: 90. Postgiro: 95205.\n\nAkt.-kap.: 55,000 kr. Antal\nindustriarb.: 18. Tillv.-värde pr år: 400,000 kr.\n— Bolaget grundat 1934.\n\nStyrelse: dir. Fritz Nilsson (ordf.),\ngrossh. Artur Anderson (v. ordf.), köpm.\nSven Anderson, köpm. Karl-Otto Nilsson,\ndisp. Enock Peterson.\n\nVerkst. dir.: Fritz Nilsson.\n\n\"AB. Smålandsstenars Ångsåg &amp;\nSnickerifabrik, Smålandssténar.\n\nSågverk, hyvleri och snickerifabrik vid\nSmålandsstenar (Jönköp. l.). Tillverkar\nsågade ^ och hyvlade trävaror,\nbyggnadssnickerier och inredningar, listverk,\ntrappor, träullsplattor, monteringsfärdiga\nträhus m. m.\n\nTelegr.-adr.: Trä, Smålandsstenar.\nTelefon: 3, 150 o. 225. Postgiro: 22590.\nRepresentant i Göteborg: AB. Götene\nTräindustri, ö. Hamng. 50 b, telefon:\n138325—26.\n\nAkt.-kap.: 224,000 kr. Antal\nindustriarb.: 90. Årstillv.: 1,500 stds sågade och\nhyvlade trävaror. Tillv.-värde pr år:\n1,800,000 kr.\n\nFirman etabl. 1895, bolag 1921.\n\nStyrelse: dir. Arthur Storck (ordf.),\ndir. Fritz Nilsson, disp. Eric Storck.\n\nVerkst. dir.: Eric Storck.\n\nInsp.: Rolf Peterson.\n\n\"Smärgelskiffabriken, Svenska,\n\nHöganäs.\n\nSe AB. Svenska Smergelskiffabriken*\nHöganäs.\n\nAB. Smögens Konservfabrik,\nBröderna Ivarsson, Smögen.\n\nTillverkar ansjovis och sillkonserver\nsamt steriliserade varor av makrill,\nsardiner, herring, räkor och havskräftor\nvid fabrik i Smögen (Göteb. o. Bohus l.).\nVarumärken: »Kräftan», »Fregatt-ans\njo-vis» o. »Furste-sill».\n\nTelefon: 30. Postgiro: 93666. —\nAkt.-kap.: 75,000 kr. Antal industriarb.: 25.\nTillv.-värde pr år: 500,000 kr. — Firman\netabl. 1924, bolag 1943.\n\nChefer: fabr. Ivar Ivarsson o. fabr.\nLars Ivarsson.\n\n\"Snickeribolaget Hägerlöf &amp; Co.,\n\nVårgårda.\n\nTillverkar byggnadssnickerier och\ninredningar m. m. vid snickerifabrik i\nVårgårda (Älvsb. l.).\n\nTelefon: 128. Postgiro: 95795. — Antal\nindustriarb.: 16. Tillv.-värde pr år:\n220.000 kr. — Firman etabl, 1935.\n\nÄgare o. chefer: fabr. Åke Hägerlöf o.\nfabr. Josef Carlsson.\n\n\"AB. Snickeri &amp; Träförädlingen,\n\nVetlanda.\n\nSågverk, hyvleri och snickerifabrik.\nTillverkar byggnadssnickerier, köks- och\naffärsinredningar samt sågade och hy\nv-lade trävaror\n\nTelefon: 225. Postgiro: 87549. —\nAkt.-kap.: 60,000 kr. Antal industriarb.: 15.\nTillv.-värde pr år: 300,000 kr. — Bolaget\ngrundat 1928.\n\nStyrelse: disp. Emil Gustafsson (ordf.),\nfru A. Gustavsson, fröken I. Gustavsson.\n\nDisp.: Emil Gustafsson.\n\n\"Snickerifabriken Kondoren,\n\nNorrköping.\n\nTillverkar byggnadssnickerier och\nskolbänkar, kyrk- och bankinredningar samt\nutför dörrar och fönster av svensk\nstandardtyp. Filman driver jämväl\nsågverksrörelse och trävaruaffär.\n\nTelefon: 20082 o. 20932. Postgiro:\n29450.\n\nAntal industriarb.: 20. Tillv.-värde pr\når: 300,000 kr. — Fabriken grundlagd\n1862.\n\nÄgare: Gustaf Nordenström &amp; Co.\n\nChef: disp. Gustaf Nordenström.",
    "structured": {
        "1": {
            "name": "AB. Smålaiidsstenar—Snickerifabriken",
            "location": "Smålandsstenar",
            "business": "Tillverkar maskiner för massartiklar av tråd och band såsom spikmaskiner, excen-terpressar, trådriktmaskiner, fjädermaskiner, kedjemaskiner, nitpressar m. fl.",
            "contact": {
                "office": "Smålandsstenar (Jönköp. l.)",
                "phone": [
                    "55",
                    "59"
                ],
                "postgiro": "22598",
                "telegraph": "N/A"
            },
            "financials": {
                "capital": "52,000 kr",
                "employees": {
                    "industriarb": 35
                },
                "annual_turnover": "350,000 kr",
                "annual_production_value": "N/A"
            },
            "foundation_year": 1922
        },
        "2": {
            "name": "AB. Smålandsstenars Trikåfabrik",
            "location": "Smålandsstenar",
            "business": "Trikåfabrik i Smålandsstenar (Jönköp. 1.). Tillverkar herr- och damtrikåvaror.",
            "contact": {
                "office": "Smålandsstenar (Jönköp. l.)",
                "phone": [
                    "90"
                ],
                "postgiro": "95205",
                "telegraph": "N/A"
            },
            "financials": {
                "capital": "55,000 kr",
                "employees": {
                    "industriarb": 18
                },
                "annual_turnover": "400,000 kr",
                "annual_production_value": "N/A"
            },
            "foundation_year": 1934
        },
        "3": {
            "name": "AB. Smålandsstenars Ångsåg & Snickerifabrik",
            "location": "Smålandsstenar",
            "business": "Sågverk, hyvleri och snickerifabrik. Tillverkar sågade och hyvlade trävaror, byggnadssnickerier och inredningar, listverk, trappor, träullsplattor, monteringsfärdiga trähus m. m.",
            "contact": {
                "office": "Smålandsstenar (Jönköp. l.)",
                "phone": [
                    "3",
                    "150",
                    "225"
                ],
                "postgiro": "22590",
                "telegraph": "Trä, Smålandsstenar"
            },
            "financials": {
                "capital": "224,000 kr",
                "employees": {
                    "industriarb": 90
                },
                "annual_turnover": "1,800,000 kr",
                "annual_production_value": "N/A"
            },
            "foundation_year": 1921
        },
        "4": {
            "name": "AB. Smögens Konservfabrik, Bröderna Ivarsson",
            "location": "Smögen",
            "business": "Tillverkar ansjovis och sillkonserver samt steriliserade varor av makrill, sardiner, herring, räkor och havskräftor vid fabrik i Smögen (Göteb. o. Bohus l.).",
            "contact": {
                "office": "Smögen (Göteb. o. Bohus l.)",
                "phone": [
                    "30"
                ],
                "postgiro": "93666",
                "telegraph": "N/A"
            },
            "financials": {
                "capital": "75,000 kr",
                "employees": {
                    "industriarb": 25
                },
                "annual_turnover": "500,000 kr",
                "annual_production_value": "N/A"
            },
            "foundation_year": 1943
        },
        "5": {
            "name": "AB. Snickeribolaget Hägerlöf & Co.",
            "location": "Vårgårda",
            "business": "Tillverkar byggnadssnickerier och inredningar m. m. vid snickerifabrik i Vårgårda (Älvsb. l.)",
            "contact": {
                "office": "Vårgårda (Älvsb. l.)",
                "phone": [
                    "128"
                ],
                "postgiro": "95795",
                "telegraph": "N/A"
            },
            "financials": {
                "capital": "N/A",
                "employees": {
                    "industriarb": 16
                },
                "annual_turnover": "220,000 kr",
                "annual_production_value": "N/A"
            },
            "foundation_year": 1935
        },
        "6": {
            "name": "AB. Snickeri & Träförädlingen",
            "location": "Vetlanda",
            "business": "Sågverk, hyvleri och snickerifabrik. Tillverkar byggnadssnickerier, köks- och affärsinredningar samt sågade och hy v-lade trävaror",
            "contact": {
                "office": "Vetlanda",
                "phone": [
                    "225"
                ],
                "postgiro": "87549",
                "telegraph": "N/A"
            },
            "financials": {
                "capital": "60,000 kr",
                "employees": {
                    "industriarb": 15
                },
                "annual_turnover": "300,000 kr",
                "annual_production_value": "N/A"
            },
            "foundation_year": 1928
        },
        "7": {
            "name": "Snickerifabriken Kondoren",
            "location": "Norrköping",
            "business": "Tillverkar byggnadssnickerier och skolbänkar, kyrk- och bankinredningar samt utför dörrar och fönster av svensk standardtyp.",
            "contact": {
                "office": "Norrköping",
                "phone": [
                    "20082",
                    "20932"
                ],
                "postgiro": "29450",
                "telegraph": "N/A"
            },
            "financials": {
                "capital": "N/A",
                "employees": {
                    "industriarb": 20
                },
                "annual_turnover": "300,000 kr",
                "annual_production_value": "N/A"
            },
            "foundation_year": 1862
        }
    }
}