{
    "original": "Petit—Pettersson\n\nPetit, AB. Klichéanstalten,\n\nGöteborg.\n\nSe AB. Klichéanstalten Petit,\nGöteborg.\n\n\"K. Petrelius Smides- o. Mek. Verk-\n\nstad, Stockholm.\n\nTillverkar byggnads-, konst- och\norna-mentsmiden samt vändkors och\nspärr-grindar.\n\nKontor: Hantverkarg. 38. Telefon:\n533252. Postgiro: 2658.\n\nArb.-antal: 12. Tillv.-värde pr år:\n150,000 kr. — Firman etabl. 1911.\n\nÄgare o. chef: fabr. Knut Petrelius.\n\n(Jfr annons nr 100.)\n\nPetterson, Peterson.\n\nPeterson &amp; Co., Ulricehamn.\n\nKonfektionsfabrik. Tillverkar herr- och\ngosskonfektion samt sport- och\narbetskläder. Varumärke: »Peters». Firman driver\näven engroshandel med trikåvaror, filtar\nm. m.\n\nTelefon: 326. Postgiro: 22005.\n\nTillv.-värde pr år: 1,350,000 kr. —\nFirman etabl. 1921.\n\nÄgare o. chef: grossh. Peter Tellow.\n\nPettersson, Engström &amp; Co.,\n\nNorrköping.\n\nMek. verkstad med smedja,\ngrovplåtslageri och maskinverkstad. Tillverkar\ncisterner, järnkonstruktioner,\ngrovplåts-arbeten och grovsmiden; utför\nfartygsreparationer, maskinarbeten samt gas- o.\nelektrisk svetsning.\n\nTelegr.-adr.: Peco, Norrköping.\nTelefon: 21976. Postgiro: 90310. — Antal\nindustriarb.: 25. Tillv.-värde pr år: 225,000\nkr. — Firman etabl. 1909.\n\nÄgare o. chef: fabr. Henning S. Pers-\n\nPettersson &amp; Perssons Möbelfabriks\n\nAB., Bjärnum.\n\nTillverkar lackerade möbler, spec.\nsängkammarmöbler vid fabrik i Bjärnum\n(Kristianst. l.).\n\nTelefon: 11. Postgiro: 72081. —\nAkt.-kap.: 90,000 kr. Antal industriarb.: 45.\nTillv.-värde pr år: 350,000 kr. — Firman\netabl. 1895, bolag 1928.\n\nDisp.: Hartvig Persson.\n\n\"Peterssons Snickerifabrik,\nBröderna, Skillingaryd.\n\nSe Bröderna Peterssons Snickerifabrik,\nSkillingaryd.\n\n\"AB. Pettersson &amp; Tisell,\n\nKinnahult.\n\nJacquardväveri och trikåfabrik i\nEke-bo, Kinnahult (Älvsb. l.). Tillverkar\nkragskyddare, schalar och huvuddukar\ni ylle, bomull och siden samt jumpers&gt;\nkoftor, mössor och herrvästar i trikå.\n\nTelefon: Kinna 10012 o. 10062.\nPostgiro: 84600. Representant för Sverige:\nJoel Lindblom &amp; Co. AB., Stockholm,\nKungsg. 66, telefon: 113670.\n\nAkt.-kap.: 225,000 kr. Antal\nindustriarb.: 75 (ävensom 50 hemarbetare).\nTillv.-värde pr år: 1,500,000 kr. — Firman\netabl. 1885, bolag 1928.\n\nStyrelse: med. dr F. Tisell (ordf.),\növering. V. Christiansen, dir. Asbjörn\nJonassen.\n\nVerkst. dir.: Asbjörn Jonassen.\n\nArvid Petersson, Stockaryd.\n\nTillverkar sågade och hyvlade trävaror,\nläkt och ribb, hyvlade takstickor samt\nsågad takspån vid sågverk och hyvleri i\nStockaryd (Jönköp. l.).\n\nTelefon: 30. — Arb.-antal: 12. —\nFirman etabl. 1920.\n\nÄgare o. chef: trävaruhandl. Arvid\nPetersson.\n\nAB. C. A. Petterson, Norrköping.\n\nHerrkonfektionsfabrik. Tillverkar\nherrkläder. Varumärke: »Elit».\n\nKontor: N. Kungsg. 9. Telegr.-adr.:\nCap, Norrköping. Telefon: 21761.\nPostgiro: 6319.\n\nAkt.-kap.: 139,025 kr. Antal\nindustriarb.: 150. Tillv.-värde pr år: 1,300,000 kr.\n\nFirman etabl. 1897, bolag 1906.\n\nStyrelse: dir. Gunnar W. Anderson\n(ordf.), ing. Ernst P:son Caap, dir. Carl\nP:son Cahp.\n\nVerkst. dir.: Carl P:son Cahp.\n\n\"AB. C. E. Petterssons\nTräförädlings-fabrik,’ Valdemarsvik.\n\nSågverk, hyvleri och kolugnar vid\nGrän-näset invid Valdemarsvik samt sågverk\nvid Fåfalla och Skedshult (båda i\nKalmar l.). Tillverkar sågade och hyvlade\nträvaror samt pappersved och träkol.\nBolaget idkar jämväl skogsbruk samt handel\nmed trävaror, träfiberplattor och plywood\n\n439*",
    "structured": {
        "1": {
            "name": "K. Petrelius Smides- o. Mek. Verkstad",
            "location": "Stockholm",
            "business": "Tillverkar byggnads-, konst- och ornamentsmiden samt vändkors och spärr-grindar",
            "contact": {
                "office": "Hantverkarg. 38",
                "phone": [
                    "533252"
                ],
                "postgiro": "2658"
            },
            "financials": {
                "capital": "N/A",
                "employees": {
                    "Arbetsantal": 12
                },
                "annual_turnover": "150,000 kr",
                "annual_production_value": "N/A"
            },
            "foundation_year": 1911,
            "owner": "fabr. Knut Petrelius"
        },
        "2": {
            "name": "Peterson & Co.",
            "location": "Ulricehamn",
            "business": "Konfektionsfabrik. Tillverkar herr- och gosskonfektion samt sport- och arbetskläder",
            "contact": {
                "phone": [
                    "326"
                ],
                "postgiro": "22005"
            },
            "financials": {
                "capital": "N/A",
                "employees": "N/A",
                "annual_turnover": "1,350,000 kr",
                "annual_production_value": "N/A"
            },
            "foundation_year": 1921,
            "owner": "grossh. Peter Tellow"
        },
        "3": {
            "name": "Pettersson, Engström & Co.",
            "location": "Norrköping",
            "business": "Mek. verkstad med smedja, grovplåtslageri och maskinverkstad. Tillverkar cisterner, järnkonstruktioner, grovplåts-arbeten och grovsmiden; utför fartygsreparationer, maskinarbeten samt gas- o. elektrisk svetsning",
            "contact": {
                "telegraph": "Peco, Norrköping",
                "phone": "21976",
                "postgiro": "90310"
            },
            "financials": {
                "capital": "N/A",
                "employees": {
                    "Antal industriarb": 25
                },
                "annual_turnover": "225,000 kr",
                "annual_production_value": "N/A"
            },
            "foundation_year": 1909,
            "owner": "fabr. Henning S. Pers"
        },
        "4": {
            "name": "Pettersson & Perssons Möbelfabriks AB.",
            "location": "Bjärnum",
            "business": "Tillverkar lackerade möbler, spec. sängkammarmöbler vid fabrik i Bjärnum (Kristianst. l.)",
            "contact": {
                "phone": "11",
                "postgiro": "72081"
            },
            "financials": {
                "capital": "90,000 kr",
                "employees": {
                    "Antal industriarb": 45
                },
                "annual_turnover": "350,000 kr",
                "annual_production_value": "N/A"
            },
            "foundation_year": 1895,
            "corporation_year": 1928,
            "owner": "Hartvig Persson"
        },
        "5": {
            "name": "AB. Pettersson & Tisell",
            "location": "Kinnahult",
            "business": "Jacquardväveri och trikåfabrik i Eke-bo, Kinnahult (Älvsb. l.). Tillverkar krag-skyddare, schalar och huvuddukar i ylle, bomull och siden samt jumpers, koftor, mössor och herrvästar i trikå",
            "contact": {
                "phone": "Kinna 10012 o. 10062",
                "postgiro": "84600"
            },
            "financials": {
                "capital": "225,000 kr",
                "employees": {
                    "Antal industriarb": 75
                },
                "annual_turnover": "1,500,000 kr",
                "annual_production_value": "N/A"
            },
            "foundation_year": 1885,
            "corporation_year": 1928,
            "board": [
                {
                    "name": "med. dr F. Tisell",
                    "role": "ordf."
                },
                {
                    "name": "övering. V. Christiansen",
                    "role": "N/A"
                },
                {
                    "name": "dir. Asbjörn Jonassen",
                    "role": "N/A"
                }
            ],
            "director": "Asbjörn Jonassen"
        },
        "6": {
            "name": "Arvid Petersson",
            "location": "Stockaryd",
            "business": "Tillverkar sågade och hyvlade trävaror, läkt och ribb, hyvlade takstickor samt sågad takspån vid sågverk och hyvleri i Stockaryd (Jönköp. l.)",
            "contact": {
                "phone": "30"
            },
            "financials": {
                "capital": "N/A",
                "employees": {
                    "Arb.-antal": 12
                },
                "annual_turnover": "N/A",
                "annual_production_value": "N/A"
            },
            "foundation_year": 1920,
            "owner": "trävaruhandl. Arvid Petersson"
        },
        "7": {
            "name": "AB. C. A. Petterson",
            "location": "Norrköping",
            "business": "Herrkonfektionsfabrik. Tillverkar herrkläder",
            "contact": {
                "office": "N. Kungsg. 9",
                "phone": [
                    "21761"
                ],
                "postgiro": "6319"
            },
            "financials": {
                "capital": "139,025 kr",
                "employees": {
                    "Antal industriarb": 150
                },
                "annual_turnover": "1,300,000 kr",
                "annual_production_value": "N/A"
            },
            "foundation_year": 1906,
            "board": [
                {
                    "name": "dir. Gunnar W. Anderson",
                    "role": "ordf."
                },
                {
                    "name": "ing. Ernst P:son Caap",
                    "role": "N/A"
                },
                {
                    "name": "dir. Carl P:son Cahp",
                    "role": "N/A"
                }
            ],
            "director": "Carl P:son Cahp"
        },
        "8": {
            "name": "AB. C. E. Petterssons Träförädlings-fabrik",
            "location": "Valdemarsvik",
            "business": "Sågverk, hyvleri och kolugnar vid Grännäset invid Valdemarsvik samt sågverk vid Fåfalla och Skedshult (båda i Kalmar l.). Tillverkar sågade och hyvlade trävaror samt pappersved och träkol. Bolaget idkar jämväl skogsbruk samt handel med trävaror, träfiberplattor och plywood",
            "contact": {
                "phone": "N/A"
            },
            "financials": {
                "capital": "N/A",
                "employees": "N/A",
                "annual_turnover": "N/A",
                "annual_production_value": "N/A"
            },
            "predecessor": "N/A",
            "foundation_year": "N/A",
            "corporation_year": "N/A",
            "owners": "N/A",
            "director": "N/A",
            "managing_director": "N/A",
            "sales_manager": "N/A",
            "manager": "N/A"
        }
    }
}