{
    "original": "Tärnsjö—Töreboda\n\nTärnsjö Ånggarveri AB., Tärnsjö.\n\nGarveri, sadelmakeri och t2$t of felfabrik\ni Tärnsjö (Västmanl. l.). Tillverkar\nplattläder, sy- och rålädersremmar, arbetsselar\noch andra sadelmakeriarbeten,\narbetshandskar samt trätofflor.\n\nTelefon: 27. Postgiro: 22138.\n\nAkt.-kap.: 100,000 kr. Antal\nindustriarb.: 60. Tillv.-värde pr år: 1,100,000 kr.\n— Firman etabl. 1873, bolag 1935.\n\nStyrelse: dir. Julius Åström (ordf.),\nverkm. Gösta Åström, disp. Torsten\nÅström.\n\nVerkst. dir.: Julius Åström.\n\nDisp.: Torsten Åström.\n\nTöcksfors Sågverk,\n\nTöcksfors.\n\nSe Hånsfors Bruks AB., Göteborg.\n\n*AB. Tölö Fabriker, Kungsbacka.\n\nFabrik för tillverkning av tak- och\nunderlagspapp, förhydnings- och\ntrossbottenpapp, isoleringspapp m. m. samt fabrik\nför tillverkning av träullsplattor.\nVarumärken: »Wasapapp», »Kungspapp»,\n»Ajekopapp» o. »Ajekoplattan».\n\nHuvudkontor: Kungsbacka.\nTelegr.-adr.: Tölöfabrik, Kungsbacka. Telefon:\n170. Försäljn.-kontor o. lager: AB. John\nEkelund &amp; Co., Göteborg, Lilla\nKlädpres-sareg. 5, telefon: 114378; Stockholm,\nSveavägen 147, telefon: 335588.\n\nAkt.-kap.: 150,000 kr. Arb.-antal: 8. —\nBolaget grundat 1920.\n\nStyrelse: grossh. John A. Ekelund,\ngrossh. G. V. Rundström, disp. Gustaf M.\nWadstein.\n\nVerkst. dir. o. disp.: Gustaf M.\nWadstein.\n\nTönnångers Trävaru AB.,\n\nHolmsveden.\n\nSågverk och hyvleri vid Holmsveden\n(Gävleb. l.). Tillverkar sågade och\nhyvlade trävaror. Bolaget driver jämväl\njordbruk och skogshantering.\n\nTelegr.-adr.: Trävarubolaget,\nHolmsveden. Telefon: 10. Postgiro: 21336.\n\nAkt.-kap.: 300,000 kr. Antal\nindustriarb.: 35. Årstillv.: 500 stds sågade o.\n1,500 stds hyvlade trävaror. — Bolaget\ngrundat 1919.\n\nStyrelse: sågverksäg. K.-E. Westholm\n(ordf.), ing. Torsten Nordgren,\nlantmätare Herman Schönning.\n\nDisp.: K.-E. Westholm.\n\nKassör: K. A. Gullbrand.\n\n*AB. Tönseth &amp; Co., Stockholm.\n\nMotor-mek. verkstad. Tillverkar\nmotorkolvar av gjutjärn och lättmetall,\nlagerskålar av blybrons och vitmetall,\nkolvtappar, ventiler och andra reservdelar för\nbil- och flygmotorer; utför översyn och\nrenovering av bil- och flygmotorer.\nVarumärken: »Ateko» o. »Lo-Ex». Bolaget\ndriver även engrosförsäljning av\nmotorreservdelar.\n\nKontor: Ulvsundav. 132. Telegr.-adr.:\nTonsetco, Stockholm. Telefon: »Tönseth\n&amp; Comp». Postgiro: 1911.\n\nAkt.-kap.: 250,000 kr. Antal\nindustriarb.: 300. Tillv.-värde pr år: 5.000,000 kr.\n\nFirman etabl. 1921, nuv. bolag 1928.\n\nStyrelse: bankdir. H. Hagenius (ordf.),\nkonsul Joh. Sande J:or, dir. Ivar\nYng-ström.\n\nVerkst. dir.: Ivar Yngström.\n\nFörsäljningschef: ing. Gunnar\nTönseth.\n\nV erk stads chef: ing. Helge Edam.\n\nInköpschef: Gunnar Holm.\n\nTöreboda Cjuteri &amp; Mek. Verkstads\nAB., Töreboda.\n\nGjuteri och mek. verkstad i Töreboda\n(Skarab. l.). Tillverkar armatur för\ngas-och vattenledningsverk.\n\nTelefon: 10. Postgiro: 137670. —\nAkt.-kap.: 75,000 kr. Antal industriarb.: 40.\nTillv.-värde pr år: 380,000 kr. — Bolaget\ngrundat 1918.\n\nStyrelse o. verkst. dir.: ing. Sven Wall.\n\nTöreboda Keramikfabrik, B.\nJohansson, Töreboda.\n\nTillverkar keramik vid fabrik i\nTöreboda (Skarab. l.). Specialiteter:\nhushålls-och prydnadskeramik (s. k. konstkeramik).\n\nTelefon: 163. Postgiro: 174570. —\nArb.-antal: 7. Tillv.-värde pr år: 100,000 kr. —\nFirman etabl. 1941.\n\nÄgare o. chef: fabr. Birger Johansson.\n\n*AB. Töreboda Tegelbruk,\n\nVärnamo.\n\nTillverkar mur-, fasad- och\nreveterings-tegel, taktegel samt dräneringsrör vid\ntegelbruk i Töreboda (Skarab. l.).\nSpecialitet: månghåltegel.\n\nKontor: Värnamo. Telefon: 10098 o.\n10638. Postgiro: 281262.\n\nAkt.-kap.: 15,000 kr. Antal\nindustriarb.: 35. Årstillv.: 10 milj. st. tegelvaror.\n— Bolaget grundat 1927.\n\nVerkst. dir. o. disp.: Gunnar Thilén.\n\nKamrer: Lage Thilén.",
    "structured": {
        "1": {
            "name": "Tärnsjö Ånggarveri AB.",
            "location": "Tärnsjö",
            "business": "Garveri, sadelmakeri och tillverkning av felfabrik",
            "products": "Tillverkar plattläder, sy- och rålädersremmar, arbetsselar och andra sadelmakeriarbeten, arbetshandskar samt trätofflor.",
            "contact": {
                "office": "Tärnsjö",
                "phone": [
                    "27"
                ],
                "postgiro": "22138"
            },
            "financials": {
                "capital": "100,000 kr",
                "employees": {
                    "industriarb": 60
                },
                "annual_turnover": "1,100,000 kr",
                "annual_production_value": "1,100,000 kr"
            },
            "foundation_year": 1873,
            "corporation_year": 1935,
            "board": [
                {
                    "name": "Julius Åström",
                    "role": "dir. (ordf.)"
                },
                {
                    "name": "Gösta Åström",
                    "role": "verkm."
                },
                {
                    "name": "Torsten Åström",
                    "role": "disp."
                }
            ],
            "director": "Julius Åström",
            "managing_director": "Julius Åström",
            "sales_manager": "Torsten Åström"
        },
        "2": {
            "name": "AB. Tölö Fabriker",
            "location": "Kungsbacka",
            "business": "Fabrik för tillverkning av tak- och underlagspapp, förhydnings- och trossbottenpapp, isoleringspapp m. m. samt fabrik för tillverkning av träullsplattor",
            "products": "Varumärken: »Wasapapp», »Kungspapp», »Ajekopapp» o. »Ajekoplattan».",
            "contact": {
                "office": "Kungsbacka",
                "phone": [
                    "170"
                ],
                "telegraph": "Tölöfabrik, Kungsbacka"
            },
            "financials": {
                "capital": "150,000 kr",
                "employees": {
                    "industriarb": 8
                },
                "corporation_year": 1920
            },
            "board": [
                {
                    "name": "John A. Ekelund",
                    "role": "grossh."
                },
                {
                    "name": "G. V. Rundström",
                    "role": "grossh."
                },
                {
                    "name": "Gustaf M. Wadstein",
                    "role": "disp."
                }
            ],
            "director": "Gustaf M. Wadstein",
            "managing_director": "Gustaf M. Wadstein"
        },
        "3": {
            "name": "Tönnångers Trävaru AB.",
            "location": "Holmsveden",
            "business": "Sågverk och hyvleri",
            "products": "Tillverkar sågade och hyvlade trävaror. Driver även jordbruk och skogshantering.",
            "contact": {
                "office": "Holmsveden",
                "phone": [
                    "10"
                ],
                "postgiro": "21336"
            },
            "financials": {
                "capital": "300,000 kr",
                "employees": {
                    "industriarb": 35
                },
                "annual_production_value": "500 stds sågade o. 1,500 stds hyvlade trävaror"
            },
            "foundation_year": 1919,
            "board": [
                {
                    "name": "K.-E. Westholm",
                    "role": "sågverksäg."
                },
                {
                    "name": "Torsten Nordgren",
                    "role": "ing."
                },
                {
                    "name": "Herman Schönning",
                    "role": "lantmätare"
                }
            ],
            "director": "K.-E. Westholm"
        },
        "4": {
            "name": "AB. Tönseth & Co.",
            "location": "Stockholm",
            "business": "Motor-mek. verkstad",
            "products": "Tillverkar motorkolvar av gjutjärn och lättmetall, lagerskålar av blybrons och vitmetall, kolvtappar, ventiler och andra reservdelar för bil- och flygmotorer; utför översyn och renovering av bil- och flygmotorer. Varumärken: »Ateko» o. »Lo-Ex».",
            "contact": {
                "office": "Ulvsundav. 132",
                "phone": [
                    "Tönseth & Comp"
                ],
                "postgiro": "1911"
            },
            "financials": {
                "capital": "250,000 kr",
                "employees": {
                    "industriarb": 300
                },
                "annual_turnover": "5,000,000 kr"
            },
            "foundation_year": 1921,
            "corporation_year": 1928,
            "board": [
                {
                    "name": "H. Hagenius",
                    "role": "bankdir. (ordf.)"
                },
                {
                    "name": "Joh. Sande J:or",
                    "role": "konsul"
                },
                {
                    "name": "Ivar Yngström",
                    "role": "dir."
                }
            ],
            "director": "Ivar Yngström",
            "manager": "Gunnar Holm"
        },
        "5": {
            "name": "Töreboda Cjuteri & Mek. Verkstads AB.",
            "location": "Töreboda",
            "business": "Gjuteri och mek. verkstad",
            "products": "Tillverkar armatur för gas-och vattenledningsverk.",
            "contact": {
                "office": "Töreboda",
                "phone": [
                    "10"
                ],
                "postgiro": "137670"
            },
            "financials": {
                "capital": "75,000 kr",
                "employees": {
                    "industriarb": 40
                },
                "annual_production_value": "380,000 kr"
            },
            "foundation_year": 1918,
            "director": "Sven Wall"
        },
        "6": {
            "name": "Töreboda Keramikfabrik, B. Johansson",
            "location": "Töreboda",
            "business": "Tillverkning av keramik",
            "products": "Specialiteter: hushålls-och prydnadskeramik (s. k. konstkeramik).",
            "contact": {
                "office": "Töreboda",
                "phone": [
                    "163"
                ],
                "postgiro": "174570"
            },
            "financials": {
                "employees": {
                    "industriarb": 7
                },
                "annual_production_value": "100,000 kr"
            },
            "foundation_year": 1941,
            "manager": "Birger Johansson"
        },
        "7": {
            "name": "AB. Töreboda Tegelbruk",
            "location": "Värnamo",
            "business": "Tillverkning av mur-, fasad- och reveterings-tegel, taktegel samt dräneringsrör",
            "products": "Specialitet: månghåltegel.",
            "contact": {
                "office": "Värnamo",
                "phone": [
                    "10098",
                    "10638"
                ],
                "postgiro": "281262"
            },
            "financials": {
                "capital": "15,000 kr",
                "employees": {
                    "industriarb": 35
                },
                "annual_production_value": "10 milj. st. tegelvaror"
            },
            "corporation_year": 1927,
            "board": [
                {
                    "name": "Gunnar Thilén",
                    "role": "verkst. dir. o. disp."
                },
                {
                    "name": "Lage Thilén",
                    "role": "Kamrer"
                }
            ]
        }
    }
}