{
    "original": "Hestra—Hillerstorp\n\n* Hest ra Träindustriförening u. p. a.,\n\nHestra.\n\nTillverkar trädgårdsmöbler av ekgrenar\nsamt räfsor, högaffelskaft, fasonerade\nkrattskaft och markiser m. m. vid fabrik\ni Hestra (Jönköp. l.).\n\nTelefon: 35. Postgiro: 98731. —\nInsats-kap.: 25,000 kr. Antal industriarb.: 10.\nTillv.-värde pr år: 120,000 kr. —\nFöreningen bildad 1935.\n\nStyrelse o. firmaledare: fabr. Martin\nMagnusson (ordf.), fabr. Lage Berndtson,\nfru Kerstin Berndtson.\n\nHettemarks Konfektions AB.,\n\nGripenberg.\n\nTillverkar damkappor vid fabrik i\nGripenberg (Jönköp. l.). Varumärke:\n»Hettemarks».\n\nTelefon: »Hettemarks». Postgiro:\n277000. — Akt.-kap.: 50,000 kr. Antal\nindustriarb.: 30. Tillv.-värde pr år: 350,000\nkr. — Bolaget grundat 1945.\n\nVerkst. dir.: Sven Hettemark.\n\n*AB. A. Heyrnan, Vårgårda.\n\nGrynverk och kvarn samt tegelbruk i\nVårgårda (Älvsb. l.).\n\nTillverkar ångpreparerade havregryn\n(»Vårgårda Havregryn» o. »Vårgårda\n\nHavrenötter»), rostat ris och vete\n(»Rostat Vårgårda Ris» o. »Rostat Vårgårda\nVete»), havre-, vete- och rågmjöl,\nkorngryn, kornmjöl och kornflingor, kli,\nfodermjöl, hundmjöl samt murtegel, taktegel\noch dräneringsrör. Bolaget idkar jämväl\njordbruk och sågverksrörelse.\n\nTelefon: 2 o. 138. Postgiro: 22690. —\nAkt.-kap.: 600,000 kr. Antal industriarb.:\n70. — Bolaget grundat 1900.\n\nStyrelse: adv. Fred. Holmgren (ordf.),\ning. Uffe Gowers-Lund, disp. Ivan\nHeyrnan, fru S. Heyman, major G. Hjort.\n\nVerkst. dir.: Ivan Heyman.\n\nKontorschef: Carl Nilsson.\n\nHidinge Kaikverk AB.,\n\nHällekis.\n\nCementfabrik i Lanna, Hidingebro\n(Örebro l.). Tillverkar cement.\n\nHuvudkontor: Hällekis. telefon:\nHällekis 17. Fabrikskontor: Hidingebro;\ntelefon: Örebro 10911 o. Hidingebro 21.\nEn-samförsälj.: Cementa, Svenska\nCement-försäljn. AB., Malmö, telefon: 71050.\n\nAkt.-kap.: 25,000 kr. Antal\nindustriarb.: 64. Tillv.-värde pr år: 1,200,000 kr.\n\nBolaget, grundat 1934, äges av Cementa,\nSvenska Cementförsäljnings AB., Malmö.\n\nStyrelse: dir. Ernst Wehtje (ordf.),\ndir. Albin Persson, dir. Malte Ström.\n\nDisp.: bergsing. Henry Rudberg.\n\nDriftsing.: Molle Nilsson.\n\n*Hidingsta Tegelbruks AB.,\n\nSkäller sta.\n\nTegelbruk i Hidingsta (Örebro l.).\nTillverkar mur- och taktegel, nocktegel,\nmellanväggsplattor samt dräneringsrör.\n\nKontor: Sköllersta. Telefon: Sköllersta\n11. Postgiro: 145990.\n\nAkt.-kap.: 150,000 kr. Antal\nindustriarb.: 35. Årstillv.: 2 milj. st. tegelvaror.\n\n—\tBolaget grundat 1898.\n\nStyrelse: godsäg. E. M. Ribbing (ordf.),\ndisp. O. Gunnar Bengtsson, major A.\nCoyet.\n\nVerkst. dir.: O. G. Bengtsson.\n\n*AB. Hildesborgs Tegelbruk,\n\nLandskrona.\n\nTegelbruk vid Hildesborg (Malmöh. l.).\nTillverkar murtegel och dräneringsrör.\n\nEnsamförsälj. o. kontor: Frans\nTörn-qvist, Landskrona. Telegr.-adr.:\nTörn-qvist, Landskrona. Telefon: 85.\nPostgiro: 84328.\n\nAkt.-kap.: 25,000 kr. Antal\nindustriarb.: 40. Årstillv.: 3 milj. st. tegelvaror.\n\n—\tBolaget grundat 1923.\n\nVerkst. dir.: v. konsul Frans\nTörn-qvist.\n\nAB. Hillerstorps Metallverk,\n\nHillerstorp.\n\nTillverkar fönsterbeslag såsom\nfönsterlås, fönstervred, koppelhakar och\nstorm-haspar, skruvöglor, märlor, stjärnstift\nsamt klädkrokar, cykellås, frisörgarnityr\nm. m. vid metallfabrik i Hillerstorp\n(Jönköp. l.).\n\nTelefon: 57. Postgiro: 8487. —\nAkt.-kap.: 121,500 kr. Antal industriarb.: 35.\nTillv.-värde pr år: 500,000 kr. — Bolaget\ngrundat 1941.\n\nVerkst. dir.: fabr. Carl Törefors.\n\nH i I lerstor ps Stängseldu ksf abri k,\n\nHillerstorp.\n\nTillverkar trådarbeten såsom pappers-,\npotatis- och grönsakskorgar m. m. samt\ndörrmattor och stängselnät vid fabrik i\nHillerstorp (Jönköp. l.).\n\nTelefon: 15. Postgiro: 274959. — Antal\nindustriarb.: 8. Tillv.-värde pr år: 160,000\nkr. — Firman etabl. 1930.\n\nÄgare o. chef: fabr. Nils Heijel.",
    "structured": {
        "1": {
            "name": "Hest ra Träindustriförening u. p. a.",
            "location": "Hestra (Jönköp. l.)",
            "business": "Tillverkar trädgårdsmöbler av ekgrenar samt räfsor, högaffelskaft, fasonerade krattskaft och markiser m. m.",
            "contact": {
                "office": "Hestra",
                "phone": [
                    "35"
                ],
                "postgiro": "98731",
                "factory_office": "Hestra",
                "factory_phone": "35"
            },
            "financials": {
                "capital": "25,000 kr",
                "employees": {
                    "industriarb": 10
                },
                "annual_turnover": "120,000 kr",
                "annual_production_value": "120,000 kr"
            },
            "foundation_year": 1935,
            "board": [
                {
                    "name": "fabr. Martin Magnusson",
                    "role": "ordf."
                },
                {
                    "name": "fabr. Lage Berndtson"
                },
                {
                    "name": "fru Kerstin Berndtson"
                }
            ]
        },
        "2": {
            "name": "Hettemarks Konfektions AB.",
            "location": "Gripenberg (Jönköp. l.)",
            "business": "Tillverkar damkappor",
            "products": "Varumärke: »Hettemarks».",
            "contact": {
                "office": "Gripenberg",
                "phone": [
                    "Hettemarks"
                ],
                "postgiro": "277000"
            },
            "financials": {
                "capital": "50,000 kr",
                "employees": {
                    "industriarb": 30
                },
                "annual_turnover": "350,000 kr"
            },
            "foundation_year": 1945,
            "director": "Sven Hettemark"
        },
        "3": {
            "name": "AB. A. Heyrnan",
            "location": "Vårgårda (Älvsb. l.)",
            "business": "Grynverk och kvarn samt tegelbruk",
            "products": "Tillverkar ångpreparerade havregryn, rostat ris och vete, havre-, vete- och rågmjöl, korngryn, kornmjöl och kornflingor, kli, fodermjöl, hundmjöl samt murtegel, taktegel och dräneringsrör.",
            "contact": {
                "office": "Vårgårda",
                "phone": [
                    "2",
                    "138"
                ],
                "postgiro": "22690"
            },
            "financials": {
                "capital": "600,000 kr",
                "employees": {
                    "industriarb": 70
                }
            },
            "foundation_year": 1900,
            "board": [
                {
                    "name": "adv. Fred. Holmgren",
                    "role": "ordf."
                },
                {
                    "name": "ing. Uffe Gowers-Lund"
                },
                {
                    "name": "disp. Ivan Heyrnan"
                },
                {
                    "name": "fru S. Heyman"
                },
                {
                    "name": "major G. Hjort"
                }
            ],
            "director": "Ivan Heyman",
            "manager": "Carl Nilsson"
        },
        "4": {
            "name": "Hidinge Kaikverk AB.",
            "location": "Hällekis, Lanna, Hidingebro (Örebro l.)",
            "business": "Cementfabrik",
            "contact": {
                "office": "Hällekis",
                "phone": [
                    "17"
                ],
                "sales_offices": [
                    {
                        "location": "Hidingebro",
                        "phone": "Örebro 10911 o. Hidingebro 21"
                    }
                ]
            },
            "financials": {
                "capital": "25,000 kr",
                "employees": {
                    "industriarb": 64
                },
                "annual_turnover": "1,200,000 kr"
            },
            "foundation_year": 1934,
            "board": [
                {
                    "name": "dir. Ernst Wehtje",
                    "role": "ordf."
                },
                {
                    "name": "dir. Albin Persson"
                },
                {
                    "name": "dir. Malte Ström"
                }
            ],
            "director": "bergsing. Henry Rudberg",
            "manager": "Molle Nilsson"
        },
        "5": {
            "name": "Hidingsta Tegelbruks AB.",
            "location": "Hidingsta (Örebro l.)",
            "business": "Tegelbruk",
            "contact": {
                "office": "Sköllersta",
                "phone": [
                    "Sköllersta 11"
                ],
                "postgiro": "145990"
            },
            "financials": {
                "capital": "150,000 kr",
                "employees": {
                    "industriarb": 35
                }
            },
            "foundation_year": 1898,
            "board": [
                {
                    "name": "godsäg. E. M. Ribbing",
                    "role": "ordf."
                },
                {
                    "name": "disp. O. Gunnar Bengtsson"
                },
                {
                    "name": "major A. Coyet"
                }
            ],
            "director": "O. G. Bengtsson"
        },
        "6": {
            "name": "AB. Hildesborgs Tegelbruk",
            "location": "Hildesborg (Malmöh. l.)",
            "business": "Tegelbruk",
            "contact": {
                "office": "Frans Törn-qvist, Landskrona",
                "phone": [
                    "85"
                ],
                "postgiro": "84328"
            },
            "financials": {
                "capital": "25,000 kr",
                "employees": {
                    "industriarb": 40
                }
            },
            "foundation_year": 1923,
            "director": "v. konsul Frans Törn-qvist"
        },
        "7": {
            "name": "AB. Hillerstorps Metallverk",
            "location": "Hillerstorp (Jönköp. l.)",
            "business": "Tillverkar fönsterbeslag såsom fönsterlås, fönstervred, koppelhakar och storm-haspar, skruvöglor, märlor, stjärnstift samt klädkrokar, cykellås, frisörgarnityr m. m.",
            "contact": {
                "office": "Hillerstorp",
                "phone": [
                    "57"
                ],
                "postgiro": "8487"
            },
            "financials": {
                "capital": "121,500 kr",
                "employees": {
                    "industriarb": 35
                },
                "annual_turnover": "500,000 kr"
            },
            "foundation_year": 1941,
            "director": "fabr. Carl Törefors"
        },
        "8": {
            "name": "Hillerstorps Stängseldu ksf abri k",
            "location": "Hillerstorp (Jönköp. l.)",
            "business": "Tillverkar trådarbeten såsom pappers-, potatis- och grönsakskorgar m. m. samt dörrmattor och stängselnät",
            "contact": {
                "office": "Hillerstorp",
                "phone": [
                    "15"
                ],
                "postgiro": "274959"
            },
            "financials": {
                "employees": {
                    "industriarb": 8
                },
                "annual_production_value": "160,000 kr"
            },
            "foundation_year": 1930,
            "director": "fabr. Nils Heijel"
        }
    }
}