{
    "original": "A Ung sås—A llmänna\n\nStyrelse: adv. Bertil Davidson, fru Eva\nDavidson, ing. Torsten Davidson,\nbankdir. Erik D. Norrman.\n\nVerkst. dir.: Torsten Davidson.\n\n\"Alingsås Snickerifabriks AB-,\n\nAlingsås.\n\nSågverk och snickerifabrik*\n\nTillverkar sågade och hyvlade trävaror\nsamt ’byggnadssnickerier. Firman\ndriver även handel med byggnadsmaterial.\n\nTelegr.-adr.: Ångsågen, Alingsås.,\nTelefon: 50 o. 1250. Postgiro: 164004. —\nAkt.-kap.: 80,000 kr. Antal industriarb.:\n41. Tillv.-värde pr år: 800,000 kr. —\nBolaget grundat 1892.\n\nStyrelse: verkm. Anders Sjögren\n(ordf.), virkesmätare Ivar Bengtsson,\ndisp. Sigfr. Johansson* bankdir. Arne\nJosefson, ikeriäg. Hjalmar Sjögren.\n\nDisp.: Sigfr. Johansson.\n\n*AB. Alingsås Trikåfabrik, Alingsås.\n\nTillverkar herrstrumpor,\nsportstrumpor m. m.\n\nTelefon: 1417. Postgiro: 46051.\n\nAkt.-kap.: 30,000 kr. Antal\nindustriarb.: 30. Tillv.-värde pr år: 300,000 kr.\n— Bolaget grundat 1939 i Göteborg\nunder namn AB. Helios Strumpfabriker,\növerflyttades 1943 till Alingsås under\nnuv. namn.\n\nStyrelse o. verkst. dir.: köpm. Holger\nLittorin.\n\n*AB. Alka Aluminiumkapslar,\n\nLinköping.\n\nMek. verkstad. Tillverkar\nflasktillslut-ningsmaskiner samt flaskförslutningar\nsåsom patentkork och aluminmmkapslar.\n\nDriften vid bolagets verkstad har under\nkalenderns tryckning övertagits av AB.\nWicander$ Korkfabriker, Stockholm (se\ndetta bolag).\n\nTelegr.-adr.: Alkamaskin, Linköping.\nTelefon: 20808, 23878 o. 24310. Postgiro:\n85370.\n\nDirektörer: G. Rooth o. Felix\nBerglund.\n\nAB. Alkafol, Stocholm.\n\nTillverkar konsthartsfolier vid fabrik\ni Västberga, Stockholm. Varumärke:\n» Alkafol».\n\nKontor: Västberga; postadr.:\nStockholm 9. Telefon: 453400. Postgiro:\n251274. Ensamförsälj. för Sverige: AB.\nJ. E. Francke, Stockholm, Drottningg.\n73 G, telefon: 118638. — Akt.-kap.:\n5,000 kr. — Bolaget grundat 1945.\n\nStyrelse o. verkst. dir.: dir. Hugo\nEdström.\t,\n\nAB. Allkartong, Stockholm.\n\nTillverkar kartonger, pappformar: och\nrunda pappburkar.\n\nKontor: Arbetar g* 33 A. Telefon:\n520055. postgiro: 154950.\n\nAkt.-kap.: 45,000 kr. Antal\nindustriarb.: 70. Tillv.-värde pr år: 700,000 kr.\n— Firman etabl. 1912 under namn Pa-N\npetypi, nuv. namn och bolag 1938.\n\nVerkst. dir.: Sten F. Lindblom.\n\nV. verkst. dir.: Thor Wahlberg.\n\nAllkonfektion AB., Borås. .\n\nTillverkar dam-, barn- och\nherxspoxt-kläder, byxor, trenchcoats, ulsfrar öch\nkostymer. Varumärke: »Allko».\n\nTelegr.-adr.: Allkonfektion, Borås. Te^\nlefon: 15001 o. 12001. Postgiro: 71347.\n\nAkt.-kap.: 150,000 kr. Antal\nindustriarb.: 50 samt 120 hemarbetare. Tillv.-\n\nvärde pr år: 800,000 kr.–Firman etabl.\n\n1928 under namn Trikå AB., Ramnås,\nnuv. namn 1934.\n\nVerkst. dir.: Sven O. Jacobson.\n\n*AllmänG0 AB., Borås.\n\nTrikå- och konfektionsfabrik.\nTillverkar herrtrikåvaror, arbetskläder och\nherrkostymer, klänningar samt täcken och\ntäpisserivaror. Bolaget driver såsom\nhu-vudrörelse engroshandel med\nmanufakturvaror och korta varor.\n\nTelegr.-adr. o. telefon: Allmänco,\nBorås. Postgiro: 6464.\n\nAkt.-kap.: 600,000 kr. Antal\nindustriarb.: 200. — Bolaget grundat 1933.\n\nStyrelse o. chefer: dir. Erik Pedersen,\ndisp. Hans Pedersen o. disp. Hilding\nPedersen.\n\n* Allmänna Betongbyggnadsbyrån,\n\nStockholm.\n\nKonstruktions- och entreprenadf irmä\nför industri- och gruvanläggningar,\nbro-och vattenbyggnader.\n\nKontor: Stureg. 10. Telefon: 603988.\nPostgiro: 154311. —- Prod.-värde pr år:\n1,000,000 kr. — Firman etabl. 1925.\n\nÄgare o. chef: civiling. Nils Ranow.\n\n*Allmänna Brandredskapsaffären\nAB., Stockholm.\n\nMek. verkstad. Tillverkar armatur,\nbrandredskap, mek. stegar, pumpar,\nskum-släckningsaggregat, slangklämmor m. m.\nVarumärken: »Aba», »Ideal»,\n»Protek-tor» ot~*Isku».. ...",
    "structured": {
        "swedish_firms": [
            {
                "name": "Alingsås Snickerifabriks AB",
                "location": "Alingsås",
                "business": "Sågverk och snickerifabrik",
                "products": "Tillverkar sågade och hyvlade trävaror samt byggnadssnickerier. Driver handel med byggnadsmaterial.",
                "contact": {
                    "office": "Ångsågen, Alingsås",
                    "phone": [
                        "50",
                        "1250"
                    ],
                    "postgiro": "164004"
                },
                "financials": {
                    "capital": "80,000 kr",
                    "employees": {
                        "industrial_workers": 41
                    },
                    "annual_turnover": "800,000 kr",
                    "annual_production_value": "800,000 kr"
                },
                "foundation_year": 1892
            },
            {
                "name": "AB. Alingsås Trikåfabrik",
                "location": "Alingsås",
                "business": "Tillverkar herrstrumpor, sportstrumpor m. m.",
                "contact": {
                    "phone": "1417",
                    "postgiro": "46051"
                },
                "financials": {
                    "capital": "30,000 kr",
                    "employees": {
                        "industrial_workers": 30
                    },
                    "annual_turnover": "300,000 kr"
                },
                "foundation_year": 1939,
                "current_name_year": 1943,
                "predecessor": "AB. Helios Strumpfabriker",
                "original_name": "AB. Helios Strumpfabriker"
            },
            {
                "name": "AB. Alka Aluminiumkapslar",
                "location": "Linköping",
                "business": "Mek. verkstad. Tillverkar flasktillslutningsmaskiner samt flaskförslutningar såsom patentkork och aluminmmkapslar.",
                "contact": {
                    "office": "Alkamaskin, Linköping",
                    "phone": [
                        "20808",
                        "23878",
                        "24310"
                    ],
                    "postgiro": "85370"
                },
                "financials": {},
                "foundation_year": null
            },
            {
                "name": "AB. Alkafol",
                "location": "Stocholm",
                "business": "Tillverkar konsthartsfolier",
                "contact": {
                    "office": "Västberga",
                    "phone": "453400",
                    "postgiro": "251274"
                },
                "financials": {
                    "capital": "5,000 kr"
                },
                "foundation_year": 1945
            },
            {
                "name": "AB. Allkartong",
                "location": "Stockholm",
                "business": "Tillverkar kartonger, pappformar, och runda pappburkar.",
                "contact": {
                    "office": "Arbetarg* 33 A",
                    "phone": "520055",
                    "postgiro": "154950"
                },
                "financials": {
                    "capital": "45,000 kr",
                    "employees": {
                        "industrial_workers": 70
                    },
                    "annual_turnover": "700,000 kr"
                },
                "foundation_year": 1912,
                "current_name_year": 1938,
                "original_name": "Pa-N petypi"
            },
            {
                "name": "Allkonfektion AB.",
                "location": "Borås",
                "business": "Tillverkar dam-, barn- och herxspoxtkläder, byxor, trenchcoats, ulsfrar öch kostymer.",
                "contact": {
                    "office": "Allkonfektion, Borås",
                    "phone": [
                        "15001",
                        "12001"
                    ],
                    "postgiro": "71347"
                },
                "financials": {
                    "capital": "150,000 kr",
                    "employees": {
                        "industrial_workers": 50,
                        "home_workers": 120
                    },
                    "annual_turnover": "800,000 kr"
                },
                "foundation_year": 1928,
                "current_name_year": 1934,
                "original_name": "Trikå AB., Ramnås"
            },
            {
                "name": "AllmänG0 AB.",
                "location": "Borås",
                "business": "Trikå- och konfektionsfabrik. Tillverkar herrtrikåvaror, arbetskläder och herrkostymer, klänningar samt täcken och täpisserivaror.",
                "contact": {
                    "office": "Allmänco, Borås",
                    "phone": "Allmänco",
                    "postgiro": "6464"
                },
                "financials": {
                    "capital": "600,000 kr",
                    "employees": {
                        "industrial_workers": 200
                    }
                },
                "foundation_year": 1933
            },
            {
                "name": "Allmänna Betongbyggnadsbyrån",
                "location": "Stockholm",
                "business": "Konstruktions- och entreprenadf irmäför industri- och gruvanläggningar, bro-och vattenbyggnader.",
                "contact": {
                    "office": "Stureg. 10",
                    "phone": "603988",
                    "postgiro": "154311"
                },
                "financials": {},
                "foundation_year": 1925
            },
            {
                "name": "Allmänna Brandredskapsaffären AB.",
                "location": "Stockholm",
                "business": "Mek. verkstad. Tillverkar armatur, brandredskap, mek. stegar, pumpar, skumsläckningsaggregat, slangklämmor m. m.",
                "contact": {
                    "phone": "Allmänna Brandredskapsaffären AB., Stockholm",
                    "postgiro": "Allmänna Brandredskapsaffären AB."
                },
                "financials": {},
                "foundation_year": null
            }
        ]
    }
}