{
    "original": "Möller—Mölnlyche\n\nJ. P. Möllers Handskfabrik,\n\nLund.\n\nTillverkar autohandskar,\nfoderhandskar, nappa-, mocka- och suéde-handskar,\nrenhudshandskar m. m. Firmamärke:\n»Hästen».\n\nTelegr.-adr.: Handskmöller, Lund.\nTelefon: 10020 o. 13620. Postgiro: 75770.\n— Antal industriarb.: 91. — Firman\netabl. 1854.\n\nÄgare o. chef: kapten J. P. Möller.\n*AB. Mölnbacka-Trysil, Forshaga.\n\nPappersbruk med sulfitfabrik vid\nForshaga, pappersbruk och sulfatfabrik vid\nDeje, sågverk, hyvleri och snickerifabrik\nvid Dejefors, tegelbruk i östanås (samtl.\ni Värml. l.), sågverk vid Nora.\n\nTillverkar kraftpapper,\nkraftspinnpap-per, kraftsäckpapper, kraftkräppapper,\nvattentätt kraftpapper, impregnerat\nkraftpapper, kraftpapperssäckar, blekt\nsulfitcellulosa för konstsilke- och\npapperstillverkning, terpentin, hartsolja, metanol,\nsulfitsprit, foderjäst, finkelolja, terpineol,\nsågade och hyvlade trävaror, dörrar och\nfönster, taktegel och byggnadsplattor\n(märke: »Kraftelit»).\n\nBolaget, som äger elektr. kraftstationer\nvid Dejefors, Frykfors, Mölnbacka,\nForshaga, Edsvalla m. fl. platser, idkar\njämväl jordbruk, skogshantering och\nkvarnrörelse. Från kraftstationerna levereras\nenergi även till ett flertal andra större\nindustrier och samhällen.\n\nHuvudkontor (varigenom samtliga\ninköp och försäljningar ske): Forshaga.\nTelegr.-adr.: Mölnbacka, Karlstad.\nTelefon: »Mölnbacka-Trysil», Forshaga.\nPostgiro: 80494.\n\nRepresentanter för Sverige: Otto\nJacobson AB., Stockholm, Svartmang. 16,\ntelefon: 101298; E. Th. Sundin,\nGöteborg, Ö. Hamng. .15, telefon: 131904; J.\nHeligrens Eftr., Sundsvall, telefon: 3410.\n\nAkt.-kap.: 13,889,000 kr. Antal\nindustriarb.: 1,400. Årstillv.: 32,000 ton blekt\nsulfitcellulosa, 40,000 ton sulfatcellulosa\n(för eget behov), 38,000 ton kraftpapper\no. kraftpapperssäckar, 3,000 stds\nträvaror, 3 milj. ltr sulfitsprit, 300 ton\nterpentin^ 200 ton metanol samt 900 ton\nhartsolja.\n\nBolaget, som grundades 1873, äger\nForshaga Sulfit AB., Forshaga, Dejefors\nKraft- &amp; Fabriks AB., Dejeforsbruk,\nFrykfors AB., Frykfors samt\nHammarby-Yxe AB., Nora (vilkas anläggningar och\ntillverkningar här ovan sammanförts\nmed moderbolagets).\n\nStyrelse: f. d. landshövd. A. Unger\n\n(ordf.), dir. Fr. Cappelen, generaldir.\nA. Meidell, disp. J. T. Rådberg.\n\nVerkst. dir.: Fr. Cappelen.\n\nV. verkst. dir.: överste Nils Petersen.\n\nDriftsingenjörer: i Forshaga: för\nsulfitfabriken: Th. E. Oisen, för\npappersbruket: B. Gregertsen; i Deje: för\nsulfatfabriken o. pappersbruket: Henry\nWahlberg; för kraftstationerna: H.\nörtendahl.\n\nBruksförvalt. i Dejefors: Gustaf Alm.\n\nAB. Mölndals Murbruksfabrik,\n\nMölndal.\n\nTillverkar mur- och putskalk samt\nbetongvaror såsom rör, brunnsringar,\nkul-vertar m. m.\n\nTelefon: 270292 o. 270702. Postgiro:\n42315. — Akt.-kap.: 32,000 kr. Antal\nindustriarb.: 15. Tillv.-värde pr år:\n300,000 kr. — Firman etabl. 1922, bolag\n1936.\n\nChef: fabr. Joh. N. Johansson.\n\n*Mölnlycke Väfveri AB., Göteborg.\n\nBomullsspinneri, vigognespinneri,\nsytrådsfabrik, bomulls- och silkeväverier,\ntrikåfabrik samt täck- och madrassfabrik\ni Krokslätt, väverier, blekeri, färgeri,\ntryckeri, appreturverk, vaddfabrik,\nförbandsavdelning och vaxduksfabrik i\nMöln-lycke (båda i Göteb. o. Bohus l.).\n\nTillverkar oblekta, blekta och färgade\nbomullsgarner samt tryckta, färgade och\nkulörta bomulls- och konstsilkevävnader,\nsytråd, förbandsgas, sanitetsbindor,\nelastiska biudor, kem. ren bomull, herr- och\ndamtrikå, vaxduk, täcken och madrasser\nm. m.\n\nTelegr.-adr.: Textil, Göteborg. Telefon:\n»Mölnlycke Väveri» o. 171860. Postgiro:\n41125.\n\nAkt.-kap.: 6,000,000 kr. Antal\nindustriarb.: 2,330. Tillv.-värde pr år: 45,000,000\nkr.\n\nBolaget grundades 1907 och\nsamman-slogs med Claes Johansson &amp; Co:s\nVäfveri AB. 1930; sistnämnda bolag\ngrundades 1893.\n\nStyrelse: bankdir. Ebbe Lundberg\n(ordf.), övering. Knut Bildt, ing. Erik\nMagnus, ad v. Torsten Setterberg, dir.\nFolke G. Thulin.\n\nVerkst. dir.: Folke G. Thulin.\n\növering.: Sverker Ljungren.\n\nKamrer: Einar Collin.\n\nFörsäljn.-chef: Bertil Johnson.",
    "structured": {
        "1": {
            "namn": "Möller—Mölnlycke",
            "plats": "Lund",
            "affärsverksamhet": "Tillverkning av handskar",
            "produkter": "Autohandskar, foderhandskar, nappa-, mocka- och suéde-handskar, renhudshandskar",
            "kontakt": {
                "kontorsadress": "J. P. Möllers Handskfabrik, Lund",
                "telefon": [
                    "10020",
                    "13620"
                ],
                "postgiro": "75770",
                "telegrafiadress": "Handskmöller, Lund"
            },
            "finansiell information": {
                "anställda": {
                    "industriarbete": 91
                },
                "grundades": 1854,
                "ägare och chef": "kapten J. P. Möller"
            }
        },
        "2": {
            "namn": "AB. Mölnbacka-Trysil, Forshaga",
            "affärsverksamhet": "Pappersbruk, sulfatfabrik, sågverk, hyvleri, snickerifabrik, tegelbruk, kraftpapperstillverkning, kraftspinnpapperstillverkning, kraftsäckpapperstillverkning, vattentät kraftpapperstillverkning, impregnerat kraftpapperstillverkning, kraftpapperssäckstillverkning, blekt sulfitcellulosa för konstsilke- och papperstillverkning, terpentin, hartsolja, metanol, sulfitsprit, foderjäst, finkelolja, terpineol, sågade och hyvlade trävaror, dörrar, fönster, taktegel, byggnadsplattor",
            "kontakt": {
                "huvudkontor": "Forshaga",
                "telefon": [
                    "Mölnbacka-Trysil, Forshaga"
                ],
                "postgiro": "80494"
            },
            "finansiell information": {
                "aktiekapital": "13,889,000 kr",
                "anställda": {
                    "industriarbete": 1400
                },
                "årstillverkning": {
                    "blekt sulfitcellulosa": "32,000 ton",
                    "sulfatcellulosa": "40,000 ton",
                    "kraftpapper och kraftpapperssäckar": "38,000 ton",
                    "trävaror": "3,000 stds",
                    "sulfitsprit": "3 milj. ltr",
                    "terpentin": "300 ton",
                    "metanol": "200 ton",
                    "hartsolja": "900 ton"
                },
                "grundades": 1873
            }
        },
        "3": {
            "namn": "AB. Mölndals Murbruksfabrik, Mölndal",
            "affärsverksamhet": "Tillverkning av mur- och putskalk samt betongvaror",
            "kontakt": {
                "telefon": [
                    "270292",
                    "270702"
                ],
                "postgiro": "42315"
            },
            "finansiell information": {
                "aktiekapital": "32,000 kr",
                "anställda": {
                    "industriarbete": 15
                },
                "årstillverkning": "300,000 kr",
                "grundades": 1922,
                "bolaget": 1936
            },
            "chef": "fabr. Joh. N. Johansson"
        },
        "4": {
            "namn": "Mölnlycke Väfveri AB., Göteborg",
            "affärsverksamhet": "Bomullsspinneri, vigognespinneri, sytrådsfabrik, bomulls- och silkeväverier, trikåfabrik, täck- och madrassfabrik, blekeri, färgeri, tryckeri",
            "produkter": "Oblekta, blekta och färgade bomullsgarner, tryckta, färgade och kulörta bomulls- och konstsilkevävnader, sytråd, förbandsgas, sanitetsbindor, elastiska biudor, kem. ren bomull, herr- och damtrikå, vaxduk, täcken och madrasser",
            "kontakt": {
                "telefon": [
                    "Mölnlycke Väveri"
                ]
            },
            "finansiell information": {
                "aktiekapital": "6,000,000 kr",
                "anställda": {
                    "industriarbete": 2330
                },
                "årstillverkning": "45,000,000 kr",
                "grundades": 1907
            },
            "styrelse": [
                {
                    "namn": "bankdir. Ebbe Lundberg",
                    "roll": "ordf."
                },
                {
                    "namn": "övering. Knut Bildt",
                    "roll": ""
                },
                {
                    "namn": "ing. Erik Magnus",
                    "roll": ""
                },
                {
                    "namn": "ad v. Torsten Setterberg",
                    "roll": "dir."
                }
            ],
            "verkst. dir.": "Folke G. Thulin"
        }
    }
}