{
    "original": "Pettersson\n\nTelefon: 64, 227 o. 278, } Postgiro:\n21300.\t^\n\nAkt.-kap.: 150,000 kr. Antal\nindustriarb.: 30. Tillv.-värde pr år: 900,000 kr.\n— Bolaget grundat 1916.\n\nStyrelse o. verkst. dir.: S. Ählman.\n\nInköps- o. försäljn,-chef: Carl Ählp&amp;an.\n\n\"Erik Pettersons Stilgjuteri Eftr.,\n\nStockholm:\n\nTillverkar boktrycksstilar, lågmaterial\noch mässingslinjer.\n\nKontor: G:la Brog. 36. Telegr.-adr,:\nTypus, Stockholm. Telefon: 105227.\nPostgiro: 50893.\n\nAntal industriarb.: 10. Tillv.rvärde pr\når: 90,000 kr. — Firman etabl. 1889.\n\nÄgare: fabr. E. Menckel.\n\nE. Petterssons Träullsfabrik,\n\nVästanhede.\n\nTillverkar träull, sågade trävaror och\nlister vid fabrik i Västanhede\n(Kopparb. l.).\n\nTelefon: 39. Postgiro: 9370. — Antal\nindustriarb.: 30. — Firman etabl, 1894.\n\nÄgare o. chef: fabr. Edvard Pettersson.\n\n*F. 0. Peterson &amp; Söner, Göteborg.\n\nByggnadsentreprenörfirma för\naffärshus, industribyggnader, bostadshus m. m.\n\nKontor: Kyrkog. 10. Telegr.-adr.:\nFo-pos, Göteborg. Telefon: 131114, 138452 o.\n138453. Postgiro: 47174.\n\nFirman etabl. 1870.\n\nÄgare o. chefer: arkitekt Sven Steen\no. arkitekt Jan Steen.\n\nKontorschef: Hilding Forsberg.\n\n\"Gunnar Petersson, Gullebo Snickeri.\n\nfabrik, Rottne.\n\nSe Gullebo Snickerifabrik, Gunnar\nPetersson, Rottne.\n\n\"Halvdan Petterssons Möbelsnickeri,\n\nTibro.\n\nTillverkar enrumsmöbler vid fabrik i\nTibro (Skarab. l.).\n\nTelefon: 100. Postgiro: 26977. —\nArb.-antal: 10. Tillv.-värde pr år: 105,000\nkr. — Firman etabl. 1915.\n\nÄgare o. chef: fabr. Halvdan\nPettersson.\n\nJohn Pettersons Eftr., Juvelerare\n\nAB ^Stockholm.\n\nSe Juvelerare AB. John Pettersons\nEftr., Stockholm.\n\n\"AB. J. A. Petterson &amp; Co.,\n\nMålsryd.\n\nHerrkonfektionsfabrik i Målsryd\n(Älvsborgs l.). Tillverkar herrkläder.\n\nTelegr.-adr.: Pettersönerna, Målsryd.\nTelefon: Borås 49080—81—82. Postgiro:\n7$ 167. -\n\nAkt.-kap.: 800,000 kr. Antal\nindustriarb.: 190 samt 60 hemarbetare.\nTillv.-värde pr år: 2,600,000 kr. — Firman\netabl. 1863, bolag 1910.\n\nStyrelse: dir. Elis Aronsson (ordf.),\ning. Per Martin, disp. Hjalmar Tholén.\n\nVerkst. dir.: Elis Aronsson.\n\nJ. E. Petterssons Järnförädling,\n\nHillerstorp.\n\nTillverkar vid fabrik i Hillerstorp\n(Jönköp. l.) kallvalsat band järn, skruv-\n\nkrok, klädkrok, masonitépik m. m.\n\nTelefon: 37. Postgiro: 37375. — Antal\nindustriarb.: 10. Tillv.-värde pr år:\n250,000 kr. — Firman etabl. 1921.\n\nÄgare o. chefer: fabr. J. Emil\nPettersson o. Erland Törefors.\n\nProkurist: Erland Törefors.\n\n\"AB. J. C. Peterssons Möbel- &amp;\nTräindustri, Vaggeryd.\n\nSnickerifabrik i Vaggeryd (Jönköp. l.).\nTillverkar möbler och inredningar.\n\nTelefon: 31. Postgiro: 23503.\n\nAkt.-kap.: 125,000 kr. Antal\nindustriarb.: 59. Tillv.-värde pr år: 600,000 kr.\n— Firman etabl. 1904, bolag 1922.\n\nStyrelse: fabr. J. Gustaf Petersson\n(ordf.), kamrer Olof Bigner, fru Maja\nGustavsson.\n\nVerkst. dir.: J. G. Petersson.\n\n\"AB. K. J. Pettersson &amp; Söner,\n\nStorvreta.\n\nMöbelfabrik i Storvreta (Uppsala l.).\nTillverkar bäddsoffor och dyschateller.\n\nTelefon: 14. Postgiro: 94428. —\nAkt.-kap.: 40,000 kr. Antal industriarb.: 25.\nTillv.-värde pr år: 310,000 kr. — Firman\netabl. 1934, bolag 1938.\n\nStyrelse: disp. Gösta A. Pettersson\n(ordf.), fabr. Karl Julius Pettersson.\n\nDisp.: G. A. Pettersson.\n\nVerkstadschef: Karl-Erik Pettersson.\n\nLevi Peterson Industri AB.,\n\nAnderstorp.\n\nMek. verkstad i Anderstorp (JonkÖp.\n1.). Tillverkar lås och beslag för\nres-effekter, dubbelnit, knappar samt mandel-",
    "structured": {
        "1": {
            "name": "Erik Pettersons Stilgjuteri Eftr.",
            "location": "Stockholm",
            "business": "Tillverkar boktrycksstilar, lågmaterial och mässingslinjer.",
            "contact": {
                "office": "G:la Brog. 36",
                "phone": [
                    "105227"
                ],
                "postgiro": "50893"
            },
            "financials": {
                "capital": "150,000 kr",
                "employees": {
                    "industriarb": 30
                },
                "annual_turnover": "900,000 kr"
            },
            "foundation_year": 1916,
            "board": [
                {
                    "name": "S. Ählman",
                    "role": "Styrelse o. verkst. dir."
                }
            ],
            "director": "S. Ählman"
        },
        "2": {
            "name": "E. Petterssons Träullsfabrik",
            "location": "Västanhede",
            "business": "Tillverkar träull, sågade trävaror och lister vid fabrik i Västanhede (Kopparb. l.).",
            "contact": {
                "phone": [
                    "39"
                ],
                "postgiro": "9370"
            },
            "financials": {
                "employees": {
                    "industriarb": 30
                }
            },
            "foundation_year": 1894,
            "owner": "fabr. Edvard Pettersson",
            "director": "fabr. Edvard Pettersson"
        },
        "3": {
            "name": "F. 0. Peterson & Söner",
            "location": "Göteborg",
            "business": "Byggnadsentreprenörfirma för affärshus, industribyggnader, bostadshus m.m.",
            "contact": {
                "office": "Kyrkog. 10",
                "phone": [
                    "131114",
                    "138452",
                    "138453"
                ],
                "postgiro": "47174"
            },
            "foundation_year": 1870,
            "owners": [
                "arkitekt Sven Steen",
                "arkitekt Jan Steen"
            ],
            "manager": "Hilding Forsberg"
        },
        "4": {
            "name": "Gunnar Petersson, Gullebo Snickeri",
            "location": "Rottne",
            "business": "Se Gullebo Snickerifabrik, Gunnar Petersson, Rottne."
        },
        "5": {
            "name": "Halvdan Petterssons Möbelsnickeri",
            "location": "Tibro",
            "business": "Tillverkar enrumsmöbler vid fabrik i Tibro (Skarab. l.).",
            "contact": {
                "phone": [
                    "100"
                ],
                "postgiro": "26977"
            },
            "financials": {
                "employees": {
                    "arb.-antal": 10
                },
                "annual_production_value": "105,000 kr"
            },
            "foundation_year": 1915,
            "owner": "fabr. Halvdan Pettersson",
            "director": "fabr. Halvdan Pettersson"
        },
        "6": {
            "name": "John Pettersons Eftr., Juvelerare AB",
            "location": "Stockholm",
            "business": "Se Juvelerare AB. John Pettersons Eftr., Stockholm."
        },
        "7": {
            "name": "AB. J. A. Petterson & Co.",
            "location": "Målsryd",
            "business": "Herrkonfektionsfabrik i Målsryd (Älvsborgs l.). Tillverkar herrkläder.",
            "contact": {
                "phone": [
                    "49080",
                    "81",
                    "82"
                ],
                "postgiro": "7167"
            },
            "financials": {
                "capital": "800,000 kr",
                "employees": {
                    "industriarb": 190,
                    "hemarbetare": 60
                },
                "annual_turnover": "2,600,000 kr"
            },
            "foundation_year": 1863,
            "corporation_year": 1910,
            "board": [
                {
                    "name": "Elis Aronsson",
                    "role": "ordf."
                },
                {
                    "name": "Per Martin",
                    "role": "ing."
                },
                {
                    "name": "Hjalmar Tholén",
                    "role": "disp."
                }
            ],
            "director": "Elis Aronsson",
            "manager": "Elis Aronsson"
        },
        "8": {
            "name": "J. E. Petterssons Järnförädling",
            "location": "Hillerstorp",
            "business": "Tillverkar vid fabrik i Hillerstorp (Jönköp. l.) kallvalsat band järn, skruvkrok, klädkrok, masonitépik m.m.",
            "contact": {
                "phone": [
                    "37"
                ],
                "postgiro": "37375"
            },
            "financials": {
                "employees": {
                    "industriarb": 10
                },
                "annual_turnover": "250,000 kr"
            },
            "foundation_year": 1921,
            "owners": [
                "fabr. J. Emil Pettersson",
                "Erland Törefors"
            ],
            "director": "fabr. J. Emil Pettersson",
            "manager": "Erland Törefors"
        },
        "9": {
            "name": "AB. J. C. Peterssons Möbel- & Träindustri",
            "location": "Vaggeryd",
            "business": "Snickerifabrik i Vaggeryd (Jönköp. l.). Tillverkar möbler och inredningar.",
            "contact": {
                "phone": [
                    "31"
                ],
                "postgiro": "23503"
            },
            "financials": {
                "capital": "125,000 kr",
                "employees": {
                    "industriarb": 59
                },
                "annual_turnover": "600,000 kr"
            },
            "foundation_year": 1904,
            "corporation_year": 1922,
            "board": [
                {
                    "name": "J. Gustaf Petersson",
                    "role": "ordf."
                },
                {
                    "name": "Olof Bigner",
                    "role": "kamrer"
                }
            ],
            "director": "J. G. Petersson"
        },
        "10": {
            "name": "AB. K. J. Pettersson & Söner",
            "location": "Storvreta",
            "business": "Möbelfabrik i Storvreta (Uppsala l.). Tillverkar bäddsoffor och dyschateller.",
            "contact": {
                "phone": [
                    "14"
                ],
                "postgiro": "94428"
            },
            "financials": {
                "capital": "40,000 kr",
                "employees": {
                    "industriarb": 25
                },
                "annual_turnover": "310,000 kr"
            },
            "foundation_year": 1934,
            "corporation_year": 1938,
            "board": [
                {
                    "name": "Gösta A. Pettersson",
                    "role": "ordf."
                },
                {
                    "name": "Karl Julius Pettersson",
                    "role": "fabr."
                }
            ],
            "director": "G. A. Pettersson",
            "manager": "Karl-Erik Pettersson"
        }
    }
}