{
    "original": "Richardson—Ringarum\n\nAkt.-kap.: 75,000 kr. Antal\nindustriarb.: 90. Tillv.-värde pr år: 1,500,000 kr.\n\n—\tFirman etabl. 1925, bolag 1933.\nStyrelse: dir. Erling Richard (ordf.),\n\nfru A. Richard.\n\nVerkst. dir.: Erling Richard.\nDisp.: fru A. Richard.\nKamrer: K. Wennerholm.\n\n\"AB. Janne Richardson,\n\nHalmstad.\n\nLäder- och skofabrik i Halmstad samt\nbilreparationsverkstäder i Halmstad och\nFalkenberg. Tillverkar läder, skodon samt\nskinn- och filttofflor; utför reparationer\nav automobiler m. m.\n\nTelegr.-adr.: Richardi, Halmstad.\nTelefon: »Janne Richardson». Postgiro:\n30540.\n\nAkt.-kap.: 510,000 kr. Antal\nindustriarb.: 180. — Firman etabl. 1898, bolag\n1909.\n\nStyrelse: fabr. Janne Richardson\n(ordf.), fröken M. Hallen.\n\nVerkst. dir.: Janne Richardson.\n\n\"Richters Bryggeri, Malmö.\n\nSe AB. Malmö Förenade Bryggerier,\nMalmö.\n\nAB. Gusti Richter, Lysekil.\n\nKonservfabrik. Tillverkar ansjovis-,\nsill- och fiskkonserver. Varunamn:\n»Tärnan», »Yggdrasil», »överstesill»,\n»Mälar-drottning», »L’loyd», »Herrgårdssill»,\n»Nubbesill» o. »Yachtsill» m. fl.\n\nTelegr.-adr.: Richter, Lysekil. Telefon:\n12. Postgiro: 20825.\n\nAkt.-kap.: 225,000 kr. Antal\nindustriarb.: 75. Tillv.-värde pr år: 1,000,000 kr.\n\n—\tFirman etabl: 1889, bolag 1916.\nStyrelse: kanslirådet C. Wilh. Hagman\n\n(ordf.), kapten Hans Granfelt, v. konsul\nJames öhrnberg.\n\nVerkst. dir. o. disp.: James Öhrnberg.\n\nAB. Richters Fabriker, Malmö.\n\nTillverkar dam- Och herrparaplyer.\nKontor: IJngelbrektsg. 14. Telegr.-adr.:\nKäpprichter, Malmö. Telefon: 20762 o.\n20765. Postgiro: 38095.\n\nAkt.-kap.: 100,000 kr. Antal\nindustriarb.: 20. — Firman etabl. 1879, bolag\n1909.\n\nStyrelse o. verkst. dir.: Carl Herman\nRichter.\n\n\"Riddarhyt^é AB., Riddarhyttan.\n\nBergverk! med järn- och koppargruvor\nsamt anriknings- och sintringsverk vid\n\nRiddarhytte malmfält, järnbruk med\nmasugn vid Lienshyttan, sågverk, hyvleri och\nträförädlingsverk vid Riddarhyttan samt\nsmältsmedja med råskenevalsverk och\nsågverk vid Gisslarbo (samti. i Västmanl. l.).\n\nBryter och anrikar järn- och\nkopparmalm; tillverkar sinter, tackjärn, råskenor\nsamt sågade och hyvlade trävaror.\nBolaget idkar jämväl jordbruk och\nskogshantering samt äger elektr.\nvattenkraftstationer vid Riddarhyttan, Gisslarbp,\nUttersberg och Skinnskatteberg.\n\nTelegr.-adr.: Riddarbruk, Köping.\nTelefon: Skinnskatteberg 13001-—05.\nPostgiro: 9727.\n\nAkt.-kap.: 6,000,000 kr. Antal\nindustriarb.: 500. Produktionsvärde pr år:\n8,000,000 kr.\n\nBolaget grundat 1877.\n\nStyrelse: bankdir. Gustaf Söderlund\n(ordf.), dir. Mauritz Carlson, bankdir.\nErik Lundh, disp. Thorsten Wigelius, dir.\nKarl K:son Wistrand, disp. O.\nÅkerström.\n\nVerkst. dir.: O. Åkerström.\n\nKamrer o. försäljn.-chef: C.-R.\nÅhr-man.\n\nGruving.: Erik Fredriksson.\n\nHytting.: B. Enström.\n\nPlatschef i Gisslarbo: ing. C.-G.\nNorrbohm.\n\n(Jfr annons nr 51.)\n\n\"Rimbo Tegelbruk, Rimbo.\n\nSe AB. Mälardalens Tegelbruk,\nStockholm.\n\nAB. Rimforsa Möbelfabrik,\n\nRim forsa.\n\nTillverkar björkmöbler vid fabrik i\nRimforsa (Östergötl. l.).\n\nTelefon: 51. Postgiro: 9222. —\nAkt.-kap.: 39,700 kr. Antal industriarb.: 25.\nTillv.-värde pr år: 301,000 kr. — Firman\netabl. 1919, bolag 1927.\n\nDisp.: Simon Andersson.\n\nAB. Rinaldos Kartongfabrik,\n\nKumla.\n\nTillverkar kartonger vid fabrik i\nKumla (Örebro l.).\n\nTelefon: 70082 o. 71111. Postgiro:\n30347. — Akt.-kap.: 75,000 kr. Antal\nindustriarb.: 20. Tillv.-värde pr år: 1,000,000\nkr. — Firman etabl. 1915, bolag 1942.\n\nVerkst. dir.: fabr. Gösta Rinaldo.\n\n\"Ringarums Tegelbruk, Ringar am.\n\nTillverkar mur-, tak- och\nreveterings-tegel, skorstenstegel samt dräneringsrör\nvid tegelbruk i Ringarum (Östergötl. l.).",
    "structured": {
        "1": {
            "name": "AB. Janne Richardson",
            "location": "Halmstad",
            "business": "Läder- och skofabrik",
            "products": "Tillverkar läder, skodon samt skinn- och filttofflor; utför reparationer av automobiler m. m.",
            "contact": {
                "office": "Halmstad",
                "phone": [
                    "Janne Richardson"
                ],
                "postgiro": "30540",
                "telegraph": "Richardi, Halmstad"
            },
            "financials": {
                "capital": "510,000 kr",
                "employees": {
                    "industriarb": 180
                },
                "annual_turnover": "1,500,000 kr"
            },
            "foundation_year": 1925,
            "corporation_year": 1933,
            "board": [
                {
                    "name": "Janne Richardson",
                    "role": "ordf."
                },
                {
                    "name": "fröken M. Hallen"
                }
            ],
            "director": "Erling Richard",
            "managing_director": "Erling Richard",
            "sales_manager": "fru A. Richard"
        },
        "2": {
            "name": "AB. Gusti Richter",
            "location": "Lysekil",
            "business": "Konservfabrik",
            "products": "Tillverkar ansjovis-, sill- och fiskkonserver. Varunamn: »Tärnan», »Yggdrasil», »överstesill», »Mälar-drottning», »L’loyd», »Herrgårdssill», »Nubbesill» o. »Yachtsill» m. fl.",
            "contact": {
                "office": "Lysekil",
                "phone": [
                    "12"
                ],
                "postgiro": "20825",
                "telegraph": "Richter, Lysekil"
            },
            "financials": {
                "capital": "225,000 kr",
                "employees": {
                    "industriarb": 75
                },
                "annual_turnover": "1,000,000 kr"
            },
            "foundation_year": 1889,
            "corporation_year": 1916,
            "board": [
                {
                    "name": "kanslirådet C. Wilh. Hagman",
                    "role": "ordf."
                },
                {
                    "name": "kapten Hans Granfelt"
                },
                {
                    "name": "v. konsul James öhrnberg"
                }
            ],
            "director": "James Öhrnberg",
            "managing_director": "James Öhrnberg"
        },
        "3": {
            "name": "AB. Richters Fabriker",
            "location": "Malmö",
            "business": "Tillverkar dam- Och herrparaplyer",
            "contact": {
                "office": "Malmö",
                "phone": [
                    "20762",
                    "20765"
                ],
                "postgiro": "38095",
                "telegraph": "Käpprichter, Malmö"
            },
            "financials": {
                "capital": "100,000 kr",
                "employees": {
                    "industriarb": 20
                }
            },
            "foundation_year": 1879,
            "corporation_year": 1909,
            "board": [
                {
                    "name": "Carl Herman Richter"
                }
            ],
            "director": "Carl Herman Richter",
            "managing_director": "Carl Herman Richter"
        },
        "4": {
            "name": "Riddarhyt^é AB.",
            "location": "Riddarhyttan",
            "business": "Bergverk",
            "products": "Bryter och anrikar järn- och kopparmalm; tillverkar sinter, tackjärn, råskenor samt sågade och hyvlade trävaror.",
            "contact": {
                "office": "Riddarhyttan",
                "phone": [
                    "Skinnskatteberg 13001-—05"
                ],
                "postgiro": "9727",
                "telegraph": "Riddarbruk, Köping"
            },
            "financials": {
                "capital": "6,000,000 kr",
                "employees": {
                    "industriarb": 500
                },
                "annual_turnover": "8,000,000 kr"
            },
            "foundation_year": 1877,
            "board": [
                {
                    "name": "bankdir. Gustaf Söderlund",
                    "role": "ordf."
                },
                {
                    "name": "dir. Mauritz Carlson"
                },
                {
                    "name": "bankdir. Erik Lundh"
                },
                {
                    "name": "disp. Thorsten Wigelius"
                },
                {
                    "name": "dir. Karl K:son Wistrand"
                },
                {
                    "name": "disp. O. Åkerström"
                }
            ],
            "director": "O. Åkerström",
            "sales_manager": "Erik Fredriksson",
            "manager": "B. Enström"
        },
        "5": {
            "name": "AB. Rimforsa Möbelfabrik",
            "location": "Rimforsa",
            "business": "Tillverkar björkmöbler"
        },
        "6": {
            "name": "AB. Rinaldos Kartongfabrik",
            "location": "Kumla",
            "business": "Tillverkar kartonger",
            "contact": {
                "phone": [
                    "70082",
                    "71111"
                ],
                "postgiro": "30347"
            },
            "financials": {
                "capital": "75,000 kr",
                "employees": {
                    "industriarb": 20
                },
                "annual_turnover": "1,000,000 kr"
            },
            "foundation_year": 1915,
            "corporation_year": 1942,
            "director": "Gösta Rinaldo"
        },
        "7": {
            "name": "Ringarums Tegelbruk",
            "location": "Ringarum",
            "business": "Tillverkar mur-, tak- och reveterings-tegel, skorstenstegel samt dräneringsrör",
            "contact": {
                "office": "Ringarum"
            }
        }
    }
}