{
    "original": "M osjön—Motala\n\nAkt.-kap.: 1,699,500 kr. Antal\nindustriarb.: 200. Tillv.-värde pr år: 4,500,000 kr.\n\n—\tBolaget grundat 1895.\n\nStyrelse: f. d. bankdir. Gust. Ekman\n(ordf.), bergsing^ Gustaf Ekman, disp.\nPer G. Ekman, dir. Assar Grönwall, dir.\nSven Lind.\nDisp. o. verkst. dir.: Per G. Ekman.\nAvd.-chefer: för verkstäder: civiling.\nErik Sandberg, ing. Sverre Larsen; för\nritkontor: civiling. C. G. Smitterberg; för\nförsäljning: för gruvmaskiner: civiling.\nA. Kjelgaard; för järnverksmaskiner:\nbergsing. Erik Norlindh; för\njärnmanu-fakturmaskiner: ing. B. Yngve Bengtson;\nför inköp: ing. Agnar Nauclér; för kassa\n\n0.\tbokf.: kamrer Holger Eriksson.\n\nMosjöns Sågverks AB., Vallerås.\n\nSågverk i Malung, Vallerås (Kopparb.\n\n1.).\tTillverkar sågade och hyvlade\nträvaror.\n\nTelefon: Vallerås 21. Postgiro: 37163.\n\n—\tAkt.-kap.: 187,500 kr. Antal\nindustriarb.: 26. Tillv.-värde pr år: 500,000 kr.\n\n—\tBolaget grundat 1917.\n\nVerkst. dir. o. disp.: Bengt Hansson.\n\n\"Mossgruvornas Cruv AB.,\n\nHögforsbruh.\n\nJärnmalmsgruvor i Skött- och\nMoss-gruvefälten med anrikningsverk (båda i\nÖrebro l.). Bryter och anrikar järnmalm.\n\nTelefon: Högforsbruk 40. Akt.-kap.:\n50,000 kr. Antal industriarb.: 70.\nProd.-värde pr år: 300,000 kr. — Bolaget\ngrundat 1921.\n\nStyrelse: dir. Joel Larsson (ordf.),\növering. Ivar Bohm, bergsing. Halvar\nLöwenhielm.\n\nVerkst. dir.: Halvar Löwenhielm\n(Ho-fors).\n\nGruving.: P. Vilhelm Villner.\n\n\"AB. Mosås Tegelbruk, Fjugesta.\n\nTillverkar murtegel, tak- och nocktegel,\nmellanväggsplattor samt dräneringsrör\nvid tegelbruk i Mosås (Örebro l.).\n\nKontor: Fjugesta. Telefon: Fjugesta 7.\nPostgiro: 98972.\n\nAkt.-kap.: 40,000 kr. Antal\nindustriarb.: 25. Årstillv.: 2 milj. st. tegel varor.\n\n—\tTegelbruket anlagt 1906, bolag 1935.\nVerkst. dir. o. disp.: E. P. Wahlberg.\n\n\"AB. Motala Bryggerier, Motala.\n\nTillverkar maltdrycker, läskedrycker\nsamt vichy- och sodavatten.\n\nTelegr.-adr.: Bryggeribolaget, Motala.\nTelefon: »Bryggeribolaget». Postgiro:\n10833. Nederlag i Linköping, Skänninge\noch Vadstena.\n\nAkt.-kap.: 450,000 kr. Antal\nindustriarb.: 25. — Bolaget grundat 1893,\nom-bildat 1910.\n\nStyrelse: bankdir. H. Sunnerstedt\n(ordf.), dir. Hjalmar Hensmar, dir.\nBirger Paulson.\n\nVerkst. dir.: Birger Paulson.\n\nDisp.: J. F. Spendrup.\n\n\"Motala Hästskofabrik, Motala.\n\nSe AB. Finspongs Hästskor, Stockholm.\n\nMotala Kartongfabrik, Motala.\n\nTillverkar såsom specialitet kartonger\nför juvelerare.\n\nTelefon: 604. Postgiro: 21022. —\nAntal industriarb.: 16. Tillv.-värde pr år:\n60,000 kr. — Firman etabl. 1920.\n\nÄgare o. chef: fabr. Eric Forssell.\n\nMotala Plastic, Berglund &amp;\nBergstedt, Motala.\n\nKonsthartsfabrik i Motala (Östergötl. l.).\nTillverkar pressade detaljer till elektr. och\nmek. verkstadsindustrin, hushållsartiklar,\nfläsk- och burktillslutningar i bakelit och\nannan konstharts samt bijouterivaror\nm. m. i s. k. ädelharts; utför fräsning av\nkugghjul av laminerade\nkonsthartspro-dukter m. m.\n\nTelefon: 1660. Postgiro: 327041. —\nAntal industriarb.: 12. Tillv.-värde pr\når: 150,000 kr. — Firman etabl. 1946.\n\nÄgare o. chefer: med. dr Arne\nBerglund o. ing. Bertil Bergstedt.\n\nTillv.- o. försäljn.-chef: Bertil\nBergstedt.\n\n\"Motala Ström, Kvarn AB., Motala.\n\nSe Kvarn AB. Motala Ström, Motala.\n\n\"Motala Tekn. Fabrik, Motala.\n\nSe A. E. Fernstedt &amp; Co., Motala.\n\n\"AB. Motala Trikåfabrik, Motala.\n\nTillverkar dam- och herrunderkläder i\ntrikå.\n\nTelegr.-adr. o. telefon: »Trickson»,\nMotala. Postgiro: 32083.\n\nAkt.-kap.: 380,000 kr. Antal\nindustriarb.: 120. Tillv.-värde pr år: 1,200,000 kr.\n— Firman etabl. 1899, bolag 1938.",
    "structured": {
        "firms": [
            {
                "name": "Mosjön—Motala",
                "financials": {
                    "capital": "1,699,500 kr",
                    "employees": {
                        "industriarb": 200
                    },
                    "annual_turnover": "4,500,000 kr",
                    "annual_production_value": "4,500,000 kr"
                },
                "foundation_year": 1895,
                "board": [
                    {
                        "name": "Gust. Ekman",
                        "role": "f. d. bankdir. (ordf.)"
                    },
                    {
                        "name": "Gustaf Ekman",
                        "role": "bergsing^"
                    },
                    {
                        "name": "Per G. Ekman",
                        "role": "disp."
                    },
                    {
                        "name": "Assar Grönwall",
                        "role": "dir."
                    },
                    {
                        "name": "Sven Lind",
                        "role": "dir."
                    }
                ],
                "director": "Per G. Ekman",
                "manager": "Per G. Ekman"
            },
            {
                "name": "Mosjöns Sågverks AB., Vallerås",
                "financials": {
                    "capital": "187,500 kr",
                    "employees": {
                        "industriarb": 26
                    },
                    "annual_turnover": "500,000 kr",
                    "annual_production_value": "500,000 kr"
                },
                "foundation_year": 1917,
                "director": "Bengt Hansson",
                "manager": "Bengt Hansson"
            },
            {
                "name": "Mossgruvornas Cruv AB., Högforsbruh",
                "financials": {
                    "capital": "50,000 kr",
                    "employees": {
                        "industriarb": 70
                    },
                    "annual_turnover": "300,000 kr",
                    "annual_production_value": "300,000 kr"
                },
                "foundation_year": 1921,
                "board": [
                    {
                        "name": "Joel Larsson",
                        "role": "dir. (ordf.)"
                    },
                    {
                        "name": "Ivar Bohm",
                        "role": "övering."
                    },
                    {
                        "name": "Halvar Löwenhielm",
                        "role": "bergsing."
                    },
                    {
                        "name": "P. Vilhelm Villner",
                        "role": "Gruving."
                    }
                ],
                "director": "Halvar Löwenhielm",
                "manager": "Halvar Löwenhielm"
            },
            {
                "name": "AB. Mosås Tegelbruk, Fjugesta",
                "financials": {
                    "capital": "40,000 kr",
                    "employees": {
                        "industriarb": 25
                    }
                },
                "foundation_year": 1935,
                "director": "E. P. Wahlberg",
                "manager": "E. P. Wahlberg"
            },
            {
                "name": "AB. Motala Bryggerier, Motala",
                "financials": {
                    "capital": "450,000 kr",
                    "employees": {
                        "industriarb": 25
                    }
                },
                "foundation_year": 1910,
                "board": [
                    {
                        "name": "H. Sunnerstedt",
                        "role": "bankdir. (ordf.)"
                    },
                    {
                        "name": "Hjalmar Hensmar",
                        "role": "dir."
                    },
                    {
                        "name": "Birger Paulson",
                        "role": "dir."
                    }
                ],
                "director": "Birger Paulson",
                "manager": "Birger Paulson",
                "sales_manager": "J. F. Spendrup"
            },
            {
                "name": "Motala Kartongfabrik, Motala",
                "financials": {
                    "employees": {
                        "industriarb": 16
                    },
                    "annual_production_value": "60,000 kr"
                },
                "foundation_year": 1920,
                "manager": "Eric Forssell"
            },
            {
                "name": "Motala Plastic, Berglund & Bergstedt, Motala",
                "financials": {
                    "employees": {
                        "industriarb": 12
                    },
                    "annual_production_value": "150,000 kr"
                },
                "foundation_year": 1946,
                "owners": [
                    "med. dr Arne Berglund",
                    "ing. Bertil Bergstedt"
                ],
                "director": "med. dr Arne Berglund",
                "manager": "med. dr Arne Berglund",
                "sales_manager": "Bertil Bergstedt"
            },
            {
                "name": "AB. Motala Trikåfabrik, Motala",
                "financials": {
                    "capital": "380,000 kr",
                    "employees": {
                        "industriarb": 120
                    },
                    "annual_turnover": "1,200,000 kr"
                },
                "foundation_year": 1938,
                "director": "N/A",
                "manager": "N/A"
            }
        ]
    }
}