{
    "original": "Tranås\n\nAkt.-kap.: 72,200 kr. Antal\nindustriarb.: 40. Tillv.-värde pr år: 1,500,000 kr.\n\n—\tBolaget grundat 1940.\nDisp.: Gustaf Wejnarth.\nFabrihschef er: Karl V. Andersson o.\n\nOlof E. Larsson.\n\n*Tranås Bryggeri AB., Tranås.\n\nTillverkar maltdrycker och\nläskedryc-ker.\n\nTelefon: 4135. Postgiro: 22736. —\nAkt.-kap.: 150,000 kr. Antal industriarb.: 16.\n\n—\tBolaget grundat 1903.\n\nStyrelse: disp. Ernst Brandel, disp.\nFelix Brandel, stationsskrivare Göran\nUhr-feldt.\n\nVerkst. dir.: Ernst Brandel.\nDisp.: Felix Brandel.\n\n*Tranås Culdlistfabrik, Svensson &amp;\nHellberg, Tranås.\n\nTillverkar ramlister och fotografiramar.\nTelegr.-adr.: Tranåslist, Tranås.\nTelefon: 2053. Postgiro: 70107. — Antal\nindustriarb.: 30. — Firman etabl. 1920.\n\nÄgare o. chefer: fabr. Carl H. Svensson\no. fabr. Erik Hellberg.\n\nTranås Kartongfabrik, Tranås.\n\nTillverkar industriförpackningar,\nkonfektionskartonger, konditorikartonger,\nbärkartonger, kranskartonger, papprullar,\nsamlingspärmar, bakstöd för fotoramar\nm. m.\n\nTelegr.-adr.: Kartongfabriken, Tranås.\nTelefon: 2196 o. 2212. Postgiro: 83000.\n\n—\tAntal industriarb.: 30. — Firman\netabl. 1914.\n\nÄgare o. chef: fabr. Sven Johansson.\n\n*AB. Tranås Kontorsmöbler,\n\nTranås.\n\nTillverkar kontorsmöbler.\nTelegr.-adr.: Kontorsmöbler, Tranås.\nTelefon: 2003 o. 2833. Postgiro: 11701.\n\nAkt.-kap.: 400,000 kr. Antal\nindustriarb.: 60. Tillv.-värde pr år: 700,000 kr.\n\n—\tBolaget grundat 1908, ombildat 1917,\nnuv. namn 1937.\n\nStyrelse: bankdir. G. Brunkman (ordf.),\ndir. Ragnar Berg, adv. C. O. Frunck,\ndisp. Nils J. Nilsson, dir. S. Wennberg.\nVerkst. dir.: Nils J. Nilsson.\n\n*Tranås Möbelfabriks AB.,\n\nTranås.\n\nTillverkar bostadsmöbler såsom\nsovrums- och kompletteringsmöbler.\nTelefon: 2023. Postgiro: 29710.\n\nAkt.-kap.: 130,000 kr. Antal\nindustriarb.: 45. Tillv.-värde pr år: 580,000 kr.\n\n—\tBolaget grundat 1897.\n\nStyrelse: grossh. D. Sterne (ordf.),\ning. Stig Carlsson, nämndeman Ernst\nGöransson, disp. Emanuel Uppman, fabr.\nWilhelm Wigén.\n\nDisp.: Emanuel Uppman.\n\nAB. Tranåspäls, Ringqvist &amp; Co.,\n\nTranas.\n\nTillverkar dam- och barnpälsar, jackor,\ncapes, colliers m. m. vid fabrik i Tranås\n(Jönköp. l.).\n\nTelefon: 2678. Postgiro: 34741.\nAvd.-kontor: Stockholm. Arbetareg. 34,\ntelefon: 526008.\n\nAkt.-kap.: 60,000 kr. Antal\nindustriarb.: 20. Tillv.-värde pr år: 300,000 kr.\n\n—\tFirman etabl. 1942, bolag 1945.\nVerkst. dir.: Anselm Ringqvist.\n\nTranås Pälsvarukompani AB.,\n\nTranås.\n\nTillverkar pälsvaror och tygkappor för\ndamer.\n\nTelefon: 2104 o. 4060. Postgiro: 32858.\n\n—\tAkt.-kap.: 36,000 kr. Antal\nindustriarb.: 49. Tillv.-värde pr år: 700,000 kr.\n\n—\tBolaget grundat 1942.\n\nVerkst. dir. o. disp.: Josef Anderson.\n\n*AB. Tranås Skinnberederi, Tranås.\n\nBeredning och färgning av pälsskinn.\nTelegr.-adr.: Berederiet, Tranås.\nTelefon: 2830 o. 2230. Postgiro: 11666.\n\nAkt.-kap.: 50,000 kr. Antal\nindustriarb.: 150. Tillv.-värde pr år: 2,000,000 kr.\n\n—\tFirman etabl. 1917.\n\nStyrelse o. disp : David Johansson.\nKamrer: Harry Carlsson.\n\n*Tranås Snickerifabrik AB.,\n\nTranås.\n\nTillverkar skolmöbler.\nTelefon: 2163. Postgiro: 11703. —\nAkt.-kap.: 62,500 kr. Antal industriarb.: 40.\nTillv.-värde pr år: 400,000 kr. —\nFirman etabl. 1896, bolag 1933.\n\nStyrelse: disp. Efr. Samuelsson (ordf.),\nfru T. Bengtsson, ing. Olof Samuelsson.\nVerkst. dir.: Efr. Samuelsson.\n\nAB. Tranås Vagnfabrik, Tranås.\n\nTillverkar omnibus-, skåpvagns- och\nlastbilskarosserier m. m.\n\nTelegr.-adr.: Vagnfabriken, Tranås.\nTelefon: 2089. Postgiro: 29446. — Akt.-",
    "structured": {
        "1": {
            "name": "Tranås Bryggeri AB",
            "location": "Tranås",
            "business": "Tillverkar maltdrycker och läskedrycker",
            "contact": {
                "phone": [
                    "4135"
                ],
                "postgiro": "22736"
            },
            "financials": {
                "capital": "150,000 kr",
                "employees": {
                    "industriarb": 16
                },
                "annual_production_value": "1,500,000 kr"
            },
            "foundation_year": 1903
        },
        "2": {
            "name": "Tranås Culdlistfabrik, Svensson & Hellberg",
            "location": "Tranås",
            "business": "Tillverkar ramlister och fotografiramar",
            "contact": {
                "telegraph": "Tranåslist, Tranås",
                "phone": "2053",
                "postgiro": "70107"
            },
            "financials": {
                "employees": {
                    "industriarb": 30
                }
            },
            "foundation_year": 1920
        },
        "3": {
            "name": "Tranås Kartongfabrik",
            "location": "Tranås",
            "contact": {
                "telegraph": "Kartongfabriken, Tranås",
                "phone": [
                    "2196",
                    "2212"
                ],
                "postgiro": "83000"
            },
            "financials": {
                "employees": {
                    "industriarb": 30
                }
            },
            "foundation_year": 1914
        },
        "4": {
            "name": "AB. Tranås Kontorsmöbler",
            "location": "Tranås",
            "business": "Tillverkar kontorsmöbler",
            "contact": {
                "telegraph": "Kontorsmöbler, Tranås",
                "phone": [
                    "2003",
                    "2833"
                ],
                "postgiro": "11701"
            },
            "financials": {
                "capital": "400,000 kr",
                "employees": {
                    "industriarb": 60
                },
                "annual_production_value": "700,000 kr"
            },
            "foundation_year": 1908,
            "corporation_year": 1937
        },
        "5": {
            "name": "Tranås Möbelfabriks AB",
            "location": "Tranås",
            "business": "Tillverkar bostadsmöbler såsom sovrums- och kompletteringsmöbler",
            "contact": {
                "phone": "2023",
                "postgiro": "29710"
            },
            "financials": {
                "capital": "130,000 kr",
                "employees": {
                    "industriarb": 45
                },
                "annual_production_value": "580,000 kr"
            },
            "foundation_year": 1897
        },
        "6": {
            "name": "AB. Tranåspäls, Ringqvist & Co.",
            "location": "Tranas",
            "business": "Tillverkar dam- och barnpälsar, jackor, capes, colliers m.m.",
            "contact": {
                "phone": "2678",
                "postgiro": "34741"
            },
            "financials": {
                "capital": "60,000 kr",
                "employees": {
                    "industriarb": 20
                },
                "annual_production_value": "300,000 kr"
            },
            "foundation_year": 1945
        },
        "7": {
            "name": "Tranås Pälsvarukompani AB",
            "location": "Tranås",
            "business": "Tillverkar pälsvaror och tygkappor för damer",
            "contact": {
                "phone": [
                    "2104",
                    "4060"
                ],
                "postgiro": "32858"
            },
            "financials": {
                "capital": "36,000 kr",
                "employees": {
                    "industriarb": 49
                },
                "annual_production_value": "700,000 kr"
            },
            "foundation_year": 1942
        },
        "8": {
            "name": "AB. Tranås Skinnberederi",
            "location": "Tranås",
            "business": "Beredning och färgning av pälsskinn",
            "contact": {
                "telegraph": "Berederiet, Tranås",
                "phone": [
                    "2830",
                    "2230"
                ],
                "postgiro": "11666"
            },
            "financials": {
                "capital": "50,000 kr",
                "employees": {
                    "industriarb": 150
                },
                "annual_production_value": "2,000,000 kr"
            },
            "foundation_year": 1917
        },
        "9": {
            "name": "Tranås Snickerifabrik AB",
            "location": "Tranås",
            "business": "Tillverkar skolmöbler",
            "contact": {
                "phone": "2163",
                "postgiro": "11703"
            },
            "financials": {
                "capital": "62,500 kr",
                "employees": {
                    "industriarb": 40
                },
                "annual_production_value": "400,000 kr"
            },
            "foundation_year": 1933
        },
        "10": {
            "name": "AB. Tranås Vagnfabrik",
            "location": "Tranås",
            "business": "Tillverkar omnibus-, skåpvagns- och lastbilskarosserier m.m.",
            "contact": {
                "telegraph": "Vagnfabriken, Tranås",
                "phone": "2089",
                "postgiro": "29446"
            }
        }
    }
}