{
    "original": "Arki—Armerad\n\nkonfektions-, konditori- och\nbagerikartonger. Varumärke: »Aristo».\n\nTelefon: 278. Postgiro: 25880. —\nAkt.-kap.: 70,000 kr. Antal industriarb.: 55.\nTillv.-värde pr år: 900,000 kr. —\nBolaget grundat 1921.\n\nDisp.: Gustaf Gustafson.\n\nAB. Arki, Stockholm.\n\nIsoleringsmaterialfabrik å Torö (Sthlms\n1.). Tillverkar isoleringsmattor och -rör\nför byggnadsindustrien samt mattor och\nplattor för akustiska ändamål.\nVarunamn: »Arki».\n\nKontor: Stockholm, östermalmstorg 5.\nPostadr.: Stockholm 7. Telegr.-adr.: Arki,\nStockholm. Telefon: 670680. Postgiro:\n879.\n\nAkt.-kap.: 100,000 kr. Antal\nindustriarb.: 25. Tillv.-värde pr år: 800,000 kr.\n\n—\tBolaget grundat 1915, ombildat 1933.\n\nVerkst. dir.: Gustaf A. Ericsson.\n\n*\tArmas, Regulator AB., Stockholm.\n\nSe Regulator AB. Armas, Stockholm.\n\n*AB. Armator, Stockholm.\n\nEntreprenadfirma för bostads- och\nfabriksbyggnader, betongarbeten,\nsprängningsarbeten och grundläggningar m. m.\n\nKontor: Birger Jarlsg. 37.\nTelegr.-adr.: Abarmator, Stockholm. Telefon:\n231890. Postgiro: 52213.\n\nAkt.-kap.: 200,000 kr. Prod.-värde pr\når: 5,000,000 kr. — Bolaget grundat 1922.\n\nStyrelse o. verkst. dir.: ing. Gunnar\nörn.\n\n*AB. Armaturfabriken Svea,\n\nKungsör.\n\nTillverkar armatur för vatten, ånga,\ngas och värme vid fabrik i Kungsör\n(Västmanl. l.).\n\nTelefon: 75. Repr. i Stockholm: A. T.\nBång, Braheg. 25, telefon: 600053.\n\nAkt.-kap.: 208,000 kr. Antal\nindustriarb.: 110. Tillv.-värde pr år: 1,000,000 kr.\n\n—\tBolaget grundat 1917.\n\nStyrelse: dir. A. T. Bång (ordf.), fabr.\nErik A. Hoving, ing. T. E. Hoving.\n\nVerkst. dir.: Erik A. Hoving.\n\n*\tArmaturfabriken Svecia AB.,\n\nNorrtälje.\n\nTillverkar ång-, vatten- och\nvärmeledningsarmatur, syrafast armatur av metall\noch stållegeringar för cellulosa-,\nträmasse-och pappersfabriker, knutsilsplåtar m. m.\n\nTelefon: 376. Postgiro: 72522. -\nAkt.-kap.: 105,000 kr. Tillv.-värde pr år:\n700,000 kr. — Bolaget grundat 1919\nunder namn Nordsvenska Ventil &amp; Armatur\nAB., ombildat med nuv. namn 1924.\n\nStyrelse: disp. Birger Welin (ordf.),\nkassör Harry Andreasson, fröken Birgit\nWelin.\n\nVerkst. dir.: Birger Welin.\n\nArmaturfabriken Trio AB.,\n\nMidsommarkransen.\n\nArmaturfabrik i Midsommarkransen,\nStockholm.\n\nTillverkar armatur samt svarvade och\npressade massartiklar av metall, ventiler\noch beslag till gasmasker, flottörkranar\nm. m. Specialiteter: återsugnings- och\növerströmningsskydd för\nvattenledningsarmatur och sanitära apparater samt\nvat-tenblandare med dylika^ skydd.^\n\nKontor: Västberga industriområde 1,\nMidsommarkransen. Telefon: 451508—\n09. Postgiro: 154659.\n\nAkt.-kap.: 100,200 kr. Antal\nindustriarb.: 45. Tillv.-värde pr år: 1,000,000 kr.\n— Firman etabl. 1938.\n\nStyrelse: övering. Olof Lund (ordf.),\ning. Olof Lundberg, dir. Bror Sjögren.\n\nVerkst. dir.: Olof Lundberg.\n\n* Armaturfabrikerna, AB. Nordiska,\n\nLinköping.\n\nSe AB. Nordiska Armaturfabrikerna,\nLinköping.\n\n*AB. Armerad Betong, Malmö.\n\nUtför affärs- och fabriksbyggnader,\nkraftverks- och hamnbyggnader samt\nbro-och vägbyggnader.\n\nHuvudkontor: Malmö, österg. 19.\nTelegr.-adr. o. telefon: Armeradbetong, Malmö.\nPostgiro: 37820. Avd.-kontor: Stockholm,\nStureplan 19, telefon: 214414; Göteborg,\nN. Hamng. 18, telefon: 135321;\nNorrköping, telefon: 24749; Örebro, telefon:\n15004; Skövde, telefon: 1555.\n\nAkt.-kap.: 2 600,000 kr. Prod.-värde\npr år: 30,000,000 kr. — Firman etabl.\n1916.\n\nStyrelse: f. d. landssekreterare IIj. P.\nKjäll (ordf.), övering. David Andersson,\nciviling. Bo Ekelund, dir. Harald G.\nEvers, övering. Hj. Jepsson.\n\nVerkst. dir.: H. G. Evers.\n\nÖvering.: Hj. Jepsson.\n\nKamrer: A. Mårde.",
    "structured": {
        "1": {
            "name": "Arki—Armerad",
            "location": "Stockholm",
            "business": "konfektions-, konditori- och bagerikartonger",
            "contact": {
                "office": "Stockholm, östermalmstorg 5",
                "phone": [
                    "670680"
                ],
                "postgiro": "25880",
                "telegraph": "Arki, Stockholm"
            },
            "financials": {
                "capital": "70,000 kr",
                "employees": {
                    "industrial": 55
                },
                "annual_turnover": "900,000 kr"
            },
            "foundation_year": 1921,
            "director": "Gustaf Gustafson"
        },
        "2": {
            "name": "Arki",
            "location": "Stockholm",
            "business": "Isoleringsmaterialfabrik",
            "products": "isoleringsmattor, -rör, mattor, plattor för akustiska ändamål",
            "contact": {
                "office": "Stockholm, östermalmstorg 5",
                "phone": [
                    "670680"
                ],
                "postgiro": "879",
                "telegraph": "Arki, Stockholm"
            },
            "financials": {
                "capital": "100,000 kr",
                "employees": {
                    "industrial": 25
                },
                "annual_turnover": "800,000 kr"
            },
            "foundation_year": 1915,
            "current_name_year": 1933,
            "managing_director": "Gustaf A. Ericsson"
        },
        "3": {
            "name": "Armator",
            "location": "Stockholm",
            "business": "Entreprenadfirma",
            "products": "bostads- och fabriksbyggnader, betongarbeten, sprängningsarbeten, grundläggningar m. m.",
            "contact": {
                "office": "Birger Jarlsg. 37",
                "phone": [
                    "231890"
                ],
                "postgiro": "52213",
                "telegraph": "Abarmator, Stockholm"
            },
            "financials": {
                "capital": "200,000 kr",
                "annual_turnover": "5,000,000 kr"
            },
            "foundation_year": 1922,
            "board": [
                {
                    "name": "ing. Gunnar örn",
                    "role": "Styrelse o. verkst. dir."
                }
            ]
        },
        "4": {
            "name": "Armaturfabriken Svea",
            "location": "Kungsör",
            "business": "Tillverkar armatur för vatten, ånga, gas och värme",
            "contact": {
                "phone": [
                    "75"
                ]
            },
            "financials": {
                "capital": "208,000 kr",
                "employees": {
                    "industrial": 110
                },
                "annual_turnover": "1,000,000 kr"
            },
            "foundation_year": 1917,
            "board": [
                {
                    "name": "dir. A. T. Bång",
                    "role": "Styrelse"
                },
                {
                    "name": "fabr. Erik A. Hoving",
                    "role": "Styrelse"
                },
                {
                    "name": "ing. T. E. Hoving",
                    "role": "Styrelse"
                }
            ],
            "managing_director": "Erik A. Hoving"
        },
        "5": {
            "name": "Armaturfabriken Svecia AB.",
            "location": "Norrtälje",
            "business": "Tillverkar ång-, vatten- och värmeledningsarmatur, syrafast armatur av metall och stållegeringar",
            "products": "cellulosa-, trämasse-och pappersfabriker, knutsilsplåtar m. m.",
            "contact": {
                "phone": [
                    "376"
                ],
                "postgiro": "72522"
            },
            "financials": {
                "capital": "105,000 kr",
                "annual_turnover": "700,000 kr"
            },
            "foundation_year": 1919,
            "original_name": "Nordsvenska Ventil & Armatur AB.",
            "current_name_year": 1924,
            "board": [
                {
                    "name": "disp. Birger Welin",
                    "role": "Styrelse (ordf.)"
                },
                {
                    "name": "kassör Harry Andreasson",
                    "role": "Styrelse"
                },
                {
                    "name": "fröken Birgit Welin",
                    "role": "Styrelse"
                }
            ],
            "managing_director": "Birger Welin"
        },
        "6": {
            "name": "Armaturfabrikerna, AB. Nordiska",
            "location": "Linköping",
            "business": "Tillverkar armatur",
            "contact": {
                "phone": [
                    "75"
                ]
            },
            "foundation_year": 1917
        },
        "7": {
            "name": "Armerad Betong",
            "location": "Malmö",
            "business": "Utför affärs- och fabriksbyggnader, kraftverks- och hamnbyggnader samt bro-och vägbyggnader",
            "contact": {
                "office": "Malmö, österg. 19",
                "phone": [
                    "214414",
                    "135321",
                    "24749",
                    "15004",
                    "1555"
                ],
                "postgiro": "37820"
            },
            "financials": {
                "capital": "2,600,000 kr",
                "annual_turnover": "30,000,000 kr"
            },
            "foundation_year": 1916,
            "board": [
                {
                    "name": "f. d. landssekreterare IIj. P. Kjäll",
                    "role": "Styrelse (ordf.)"
                },
                {
                    "name": "övering. David Andersson",
                    "role": "Styrelse"
                },
                {
                    "name": "civiling. Bo Ekelund",
                    "role": "Styrelse"
                },
                {
                    "name": "dir. Harald G. Evers",
                    "role": "Styrelse"
                }
            ],
            "managing_director": "H. G. Evers",
            "owner": "Hj. P. Kjäll"
        }
    }
}