{
    "original": "Andersson\n\nAkt.-kap.: 200,000 kr. Antal\nindustriarb.: 61. Tillv.-värde pr år: 950,000 kr.\n\n—\tFirman etabl. 1893, bolag 1945.\n\n^ Styrelse: fabr. Herbert Andersson,\ndisp. Elias Bengtsson, kamrer Arne\nLiliengren.\n\nVerkst. dir.: Herbert Andersson.\n\n*Josef Anderson &amp; Co-, Kumla.\n\nTillverkar randsydda, ago och\nsandal-sydda dam- och barnskodon.\n\nTelefon: 70114. Postgiro: 84883. —\nAntal industriarb.: 20. Tillv.-värde pr\når: 200,000 kr. — Firman etabl. 1919.\n\nÄgare o. chefer: fabr. Josef A.\nAnderson o. fabr. Carl James.\n\n*Joh. D. Andersson AB., Malmö.\n\nKem.-teknisk fabrik. Tillverkar tvål\noch tvättmedel, eau de Cologne och\nparfymer, kosmetiska medel, polermedel,\nlack m. m. Varumärken: Baltia,\nOava-lier, Joda, Luna, Nirvana, Petral,\nSolvargen, Sonor o. Suzon.\n\nKontor: Rönneholmsvägen 43 A.\nTelegr.-adr.: Joda, Malmö. Telefon: 21570.\nPostgiro: 14049. Repr. i Stockholm: P.\nNorrbo, Kungsholms Hamnplan 3,\ntelefon: 533223.\n\nAkt.-kap.: 50,000 kr. Antal\nindustriarb.: 20. Tillv.-värde pr år: 600,000 kr.\n\n—\tFirman etabl. 1859.\n\nStyrelse: fru E. Andersson (ordf.), adv.\nS. Malmquist, ing. E. G. Warnholtz,\nkapten H, Warnholtz.\n\nDisp.: E. G. Warnholtz.\n\n*Jörgen Anderssons Snickeri &amp;\nMöbelverkstad, Djursholm.\n\nTillverkar möbler och inredningar.\nTelefon: Stockholm 551743. Postgiro:\n28558. — Antal industriarb.: 5.\nTillv.-värde pr år: 60,000 kr. — Firman etabl.\n1923.\n\nÄgare o. chef: snickaremäst. N. Jörgen\nAndersson.\n\n*J. R. Andersson &amp; Co. AB.\n(Rostfria Andersson), Sundbyberg.\n\nBleck- och plåtslageri. Tillverkar\nrostfria diskbord och andra artiklar såsom\nkärl, behållare, förvaringstankar m. m.\nför livsmedels- och kem.-tekn. industrien\nsåväl i rostfritt material som vanlig plåt,\ndörrar, fönsteranordningar, hissfronter\nm. m. såväl i rostfritt utförande som i\nmetall samt arkivbokhyllor, ritningsskåp,\narbetsbord, verktygsskåp m. m.\nVarumärke: »Rostfria Andersson».\n\nTelefon: »Rostfria Andersson»,\nStockholm. Postgiro: 52313.\n\nAkt.-kap.: 700 000 kr. Antal\nindustriarb.: 90. Tillv.-värde pr år: 2,900,000 kr..\n— Bolaget grundat 1934.\n\nStyrelsedir. G. Raabe (ordf.), dir.\nVilhelm Björkman, ing. S. Rydberg.\n\nVerkst. dir.: S. Rydberg.\n\n*Karl Andersson, Holmens\nMöbelfabrik, Mjölby.\n\nSe Holmens Möbelfabrik, Karl\nAndersson, Mjölby.\n\nKarl Andersson, Möbelfabrik,\n\nÖrebro.\n\nTillverkar kompletteringsmöbler.\n\nTelefon: 11182. Postgiro: 161501. —\nArb.-antal: 5. Tillv.-värde pr år: 30,000\nkr. — Firman etabl. 1909.\n\nÄgare o. chef: fabr. Roland Anderson-\n\n*AB. Karl Andersson &amp; Söner\nMöbelfabrik, Huskvarna.\n\nTillverkar furumöbler för sportstugor\nsamt radiomöbler vid fabriker i Siringe\noch Huskvarna (båda i Jönköp. l.).\n\nFörsäljn.-kontor: Huskvarna. Telefon:\n1330—31. Postgiro: 77665. — Akt.-kap.:\n64,000 kr. Antal industriarb.: 50.\nTillv.-värde pr år: 800,000 kr. — Firman, etabL\n1898, bolag 1944, har i sig upptagit f. d„\nOskar Hjalmarsson, Möbelfabrik, Siringe.\n\nStyrelse: fabr. Yngve Malm vall (ordf.)^\nverkm. Börje Malmvall, verkm. Göran\nMalmvall, fabr. Lennart Malmvall.\n\nVerkst. dir.: Yngve Malmvall.\n\n*Konrad Andersson AB., Kumla.\n\nTillverkar vändsydda och\nagotillver-kade damskodon vid skofabrik i Kumla\n(Örebro l.). Varumärke: »Ingrid».\n\nTelefon: 70120. Postgiro: 30348. —\nAkt.-kao.: 31,000 kr. Antal industriarb.:\n30. Tillv.-värde pr år: 300,000 kr. —\nBolaget grundat 1933.\n\nStyrelse: fabr. Gösta Andersson, fabr.\nJohn Andersson, fabr. Rudolf Andersson.\n\nVerkst. dir.: John Andersson.\n\n*AB. Ludvig Anderson, Kinna.\n\nSpinneri, väveri och färgeri (Kasthalls\nMattfabrik) i Kinna (Älvsb. l.).\nTillverkar avpassade mattor i ylle och i jute^\ngångmattor i ylle. bomull och jute samt\nhästtäcken och nöthårsgarn. Varumärke:\n» Kasthallsmattor ».\n\n18*",
    "structured": {
        "1": {
            "name": "Josef Anderson & Co-",
            "location": "Kumla",
            "business": "Manufacturing of randsydda, ago, and sandal-sydda dam- and barnskodon",
            "contact": {
                "office": "Kumla",
                "phone": [
                    "70114"
                ],
                "postgiro": "84883"
            },
            "financials": {
                "capital": "200,000 kr",
                "employees": {
                    "industriarb": 20
                },
                "annual_turnover": "200,000 kr"
            },
            "foundation_year": 1919,
            "board": [
                {
                    "name": "fabr. Josef A. Anderson",
                    "role": "owner"
                },
                {
                    "name": "fabr. Carl James",
                    "role": "owner"
                }
            ],
            "director": "Herbert Andersson"
        },
        "2": {
            "name": "Joh. D. Andersson AB.",
            "location": "Malmö",
            "business": "Manufacturing of soap, detergents, eau de cologne, perfumes, cosmetic products, polishing agents, varnish, etc.",
            "contact": {
                "office": "Rönneholmsvägen 43 A, Malmö",
                "phone": "21570",
                "postgiro": "14049",
                "sales_offices": [
                    {
                        "location": "Stockholm",
                        "phone": "533223"
                    }
                ],
                "telegraph": "Joda, Malmö"
            },
            "financials": {
                "capital": "50,000 kr",
                "employees": {
                    "industriarb": 20
                },
                "annual_turnover": "600,000 kr"
            },
            "foundation_year": 1859,
            "board": [
                {
                    "name": "fru E. Andersson",
                    "role": "chairman"
                },
                {
                    "name": "adv. S. Malmquist",
                    "role": "board member"
                },
                {
                    "name": "ing. E. G. Warnholtz",
                    "role": "board member"
                },
                {
                    "name": "kapten H, Warnholtz",
                    "role": "board member"
                }
            ],
            "director": "E. G. Warnholtz"
        },
        "3": {
            "name": "Jörgen Anderssons Snickeri & Möbelverkstad",
            "location": "Djursholm",
            "business": "Manufacturing of furniture and interior furnishings",
            "contact": {
                "office": "Djursholm",
                "phone": "Stockholm 551743",
                "postgiro": "28558"
            },
            "financials": {
                "employees": {
                    "industriarb": 5
                },
                "annual_turnover": "60,000 kr"
            },
            "foundation_year": 1923,
            "owner": "snickaremäst. N. Jörgen Andersson"
        },
        "4": {
            "name": "J. R. Andersson & Co. AB. (Rostfria Andersson)",
            "location": "Sundbyberg",
            "business": "Manufacturing of stainless steel sinks, containers, storage tanks, metal doors, window fixtures, elevator fronts, archive shelving, drafting cabinets, workbenches, tool cabinets, etc.",
            "contact": {
                "office": "Sundbyberg",
                "phone": "Rostfria Andersson, Stockholm",
                "postgiro": "52313"
            },
            "financials": {
                "capital": "700,000 kr",
                "employees": {
                    "industriarb": 90
                },
                "annual_turnover": "2,900,000 kr"
            },
            "corporation_year": 1934,
            "board": [
                {
                    "name": "G. Raabe",
                    "role": "chairman"
                },
                {
                    "name": "Vilhelm Björkman",
                    "role": "board member"
                },
                {
                    "name": "S. Rydberg",
                    "role": "board member"
                }
            ],
            "director": "S. Rydberg"
        },
        "5": {
            "name": "Karl Andersson, Möbelfabrik",
            "location": "Örebro",
            "business": "Manufacturing of supplementary furniture",
            "contact": {
                "office": "Örebro",
                "phone": "11182",
                "postgiro": "161501"
            },
            "financials": {
                "employees": {
                    "antal": 5
                },
                "annual_turnover": "30,000 kr"
            },
            "foundation_year": 1909,
            "owner": "fabr. Roland Anderson"
        },
        "6": {
            "name": "AB. Karl Andersson & Söner Möbelfabrik",
            "location": "Huskvarna",
            "business": "Manufacturing of pine furniture for holiday cottages and radio furniture",
            "contact": {
                "office": "Huskvarna",
                "phone": "1330—31",
                "postgiro": "77665"
            },
            "financials": {
                "capital": "64,000 kr",
                "employees": {
                    "industriarb": 50
                },
                "annual_turnover": "800,000 kr"
            },
            "foundation_year": 1898,
            "corporation_year": 1944,
            "predecessor": "Oskar Hjalmarsson, Möbelfabrik, Siringe",
            "board": [
                {
                    "name": "fabr. Yngve Malmvall",
                    "role": "chairman"
                },
                {
                    "name": "verkm. Börje Malmvall",
                    "role": "board member"
                },
                {
                    "name": "verkm. Göran Malmvall",
                    "role": "board member"
                },
                {
                    "name": "fabr. Lennart Malmvall",
                    "role": "board member"
                }
            ],
            "director": "Yngve Malmvall"
        },
        "7": {
            "name": "Konrad Andersson AB.",
            "location": "Kumla",
            "business": "Manufacturing of vändsydda and ago-made women's shoes",
            "contact": {
                "office": "Kumla",
                "phone": "70120",
                "postgiro": "30348"
            },
            "financials": {
                "capital": "31,000 kr",
                "employees": {
                    "industriarb": 30
                },
                "annual_turnover": "300,000 kr"
            },
            "corporation_year": 1933,
            "board": [
                {
                    "name": "fabr. Gösta Andersson",
                    "role": "board member"
                },
                {
                    "name": "fabr. John Andersson",
                    "role": "board member"
                },
                {
                    "name": "fabr. Rudolf Andersson",
                    "role": "board member"
                }
            ],
            "director": "John Andersson"
        },
        "8": {
            "name": "AB. Ludvig Anderson",
            "location": "Kinna",
            "business": "Spinning, weaving, and dyeing (Kasthalls Mattfabrik)",
            "contact": {
                "office": "Kinna",
                "phone": "",
                "postgiro": ""
            },
            "products": "Customized wool and jute rugs, hallway rugs in wool, cotton, and jute, horse blankets, and cow hair yarn",
            "foundation_year": "",
            "description": "The firm's information is incomplete",
            "board": [],
            "manager": ""
        }
    }
}