{
    "original": "Hässleholm—Höganäs\n\nTelegr.-adr.: Kapsylfabriken,\nHässleholm. Telefon: 98. Postgiro: 162396.\n\nAkt.-kap.: 53,500 kr. — Bolaget\ngrundat 1914.\n\nStyrelse: fru A. Rehfeld. fröken A.-L.\nWaldau, disp. Carl Rehfeld.\n\nVerkst. dir.: fru A. Rehfeld.\n\n*AB. Hässleholms Tegelbruk,\n\nMalmö.\n\nTillverkar röd fasadtegel, flamtegel och\nlättegel vid tegelbruk i Hässleholm.\n\nKontor: Malmö, Baltzarsg. 25. Telefon:\n25234. Postgiro: 147634.\n\nAkt.-kap.: 50,000 kr. Antal\nindustriarb.: 15. Årstillv.: 1,5 milj. st.\ntegelvaror. — Bolaget grundat 1939.\n\nStyrelse o. verkst. dir.: disp. Sam\nNilsson.\n\nAB. Hässleholms Verkstäder,\n\nHässleholm.\n\nMek. verkstad och gjuteri. Tillverkar\njärnkonstruktioner, plåtarbeten,\ngjut-gods, järnvägsmaterial, järnvägsvagnar,\ntransportanordningar, maskiner för\nsockerbruk, kemiska industrier, garverier,\nbagerier, stenhuggerier m. fl.\n\nTelegr.-adr.: Verkstäderna, Hässleholm.\nTelefon: 15, 16 o. 23. Postgiro: 23142.\n\nAkt.-kap.: 203.200 kr. Antal\nindustriarb.: 250. Tillv.-värde pr år: 2,300,000 kr.\n— Firman etabl. 1889. bolag 1915.\n\nStyrelse: adv. J. Listander (ordf.), ing.\nNils Weibull (v. ordf.), byggm. Olof\nPersson, bergsing. T. An. Tesch.\n\nVerkst. dir.: Nils Weibull.\n\nDisp.: Oscar Hedblad.\n\n*Hästbo Tegelbruk AB., Hästbo.\n\nSågverk, hyvieri och tegelbruk i\nHäst-bo (Gävleb. l.). Tillverkar sågade och\nhyvlade trävaror, taktegel samt\ndräneringsrör.\n\nTelefon: 6. Postgiro: 37419. —\nAkt.-kap.: 180,500 kr. Antal industriarb.: 35.\nÅrstillv.: 1,5 milj. st. tegelvaror, 500 stds\nträvaror. — Bolaget grundat 1929.\n\nStyrelse: v. konsul Robert Carrick\n(ordf.), hemmansäg. Axel Jönsson, köpm.\nP. J. Norbäck, hemmansäg. L. Nordgren,\nkamrer Torsten Stålberg.\n\nVerkst. styrelseled.: Robert Carrick.\n\nKamrer: Torsten Stålberg.\n\nAB. Hästholmsvarvet, Lidingö.\n\nBåtvarv vid Gåshaga å Lidingö. Utför\nny- och ombyggnader, vinterförvaring och\nutrustning av motor- och segelbåtar.\n\nPostadr.: Lidingö 3. Telegr.-adr.:\nHästholmsvarvet, Lidingö. Telefon: Stockholm\n656043. — Akt.-kap.: 300,000 kr.\nArb.-antal: 20. — Bolaget grundat 1906.\n\nStyrelse: adv. Anders Lind, ing. Knud\nH. Reimers.\n\nVerkst. dir.: kapten Stig Wilton.\n\n*AB. Höganäsarbeten, Stockholm.\n\nEntreprenörfirma för syrafasta och\neldfasta murningar, plattsättning och\nakustikförbättring, huvudsakligen med\nprodukter från Höganäs-Billesholms AB.,\nHöganäs.\n\nKontor: Malmtorgsgatan 6.\nTelegr.-adr. : Höganäsarbeten, Stockholm.\nTelefon: 232100. Postgiro: 159170.\n\nAkt.-kap.: 90,000 kr. Antal\nindustriarb.: 30. Prod.-värde pr år: 900,000 kr.\n— Firman etabl. 1910 under namn AB.\nSyrefast Murning, nuv. namn 1942.\n\nStyrelse: dir. P. Eg. Gummeson (ordf.),\ndir. Mårten Schwartz, övering. V. Terling,\nprof. Gunnar Wallquist.\n\nVerkst. dir.: V. Terling.\n\nArbetschef: civiling. Malcolm\nBrodd-ner.\n\n*Höganäs-Billesholms AB., Höganäs.\n\nStenkolsgruvor vid Höganäs,\nBilles-holm, Bjuv, Skromberga (pr Ekeby),\nGunnarstorp (samtl. i Malmöh. l.), och\nNyvång (Kristianst. l.).\n\nFabriker i Höganäs, Bjuv, Skromberga,\nHyllinge (Kristianst. l.) och Trollhättan\nför tillverkning av eldfast tegel,\njärnsvamp, golvklinker, glaserade väggplattor,\nglaserade lerrör, murtegel, syrafast\nstengods, lerkärl, kemiska produkter ur\nsten-kolstjära samt kiselkarbid och\nelektro-korund. Bolaget äger elektr. kraftcentral\nvid Nyvång samt idkar även jordbruk.\n\nHuvudkontor och försäljningskontor:\nHöganäs. Telegr.-adr. o. telefon:\nHöga-näsbolaget, Hösranäs. Postgiro: 8565.\n\nAkt.-kap.: 30,000,000 kr. Arb.-antal:\n3,100. Årsprod.: gruvprodukter: 669,500\nton; keramiska produkter: 166,000 ton;\nmetallurgiska produkter: 22,000 ton;\nkemiska produkter: 2,050 ton; el. energi:\n9,3 mill. kWh.\n\nBolaget, grundat 1903, äger Billesholms\nGlasulls AB., Billesholm, Handöls Nya\nTälj stens och Vattenkrafts AB.,\nStockholm, och AB. Slipmaterial-Naxos,\nVästervik.\n\nStyrelse: dir. Carl Johan Malmros\n(ordf.), bankdir. Allan Alexanderson, dir.\nRagnar Blomquist, bankir Tage Cervin,\ning. Fritz Egnell, bergsing. P. Eg.\nGummeson, godsäg. Rudolf Tornérhielm.\n\nVerkst. dir.: P. Eg. Gummeson.",
    "structured": {
        "1": {
            "name": "Kapsylfabriken",
            "location": "Hässleholm",
            "business": "Tillverkning av kapsyler",
            "contact": {
                "telegraph": "Kapsylfabriken, Hässleholm",
                "phone": [
                    "98"
                ],
                "postgiro": "162396"
            },
            "financials": {
                "capital": "53,500 kr",
                "foundation_year": 1914
            },
            "board": [
                {
                    "name": "fru A. Rehfeld",
                    "role": "Styrelseledamot"
                },
                {
                    "name": "fröken A.-L. Waldau",
                    "role": "Styrelseledamot"
                },
                {
                    "name": "disp. Carl Rehfeld",
                    "role": "Styrelseledamot"
                }
            ],
            "director": "fru A. Rehfeld"
        },
        "2": {
            "name": "AB. Hässleholms Tegelbruk",
            "location": "Malmö",
            "business": "Tegeltillverkning",
            "products": "Röd fasadtegel, flamtegel och lättegel",
            "contact": {
                "office": "Baltzarsg. 25, Malmö",
                "phone": [
                    "25234"
                ],
                "postgiro": "147634"
            },
            "financials": {
                "capital": "50,000 kr",
                "employees": {
                    "industriarb": 15
                },
                "annual_turnover": "1,500,000 st. tegelvaror",
                "foundation_year": 1939
            },
            "board": [
                {
                    "name": "disp. Sam Nilsson",
                    "role": "Styrelseledamot"
                }
            ]
        },
        "3": {
            "name": "AB. Hässleholms Verkstäder",
            "location": "Hässleholm",
            "business": "Mekanisk verkstad och gjuteri",
            "products": "Järnkonstruktioner, plåtarbeten, gjutgods, järnvägsmaterial, järnvägsvagnar, transportanordningar",
            "contact": {
                "office": "Verkstäderna, Hässleholm",
                "phone": [
                    "15",
                    "16",
                    "23"
                ],
                "postgiro": "23142"
            },
            "financials": {
                "capital": "203,200 kr",
                "employees": {
                    "industriarb": 250
                },
                "annual_production_value": "2,300,000 kr",
                "foundation_year": 1889,
                "corporation_year": 1915
            },
            "board": [
                {
                    "name": "adv. J. Listander",
                    "role": "Ordförande"
                },
                {
                    "name": "ing. Nils Weibull",
                    "role": "Vice ordförande"
                },
                {
                    "name": "byggm. Olof Persson",
                    "role": "Styrelseledamot"
                }
            ],
            "director": "Nils Weibull",
            "sales_manager": "disp. Oscar Hedblad"
        },
        "4": {
            "name": "AB. Hästbo Tegelbruk",
            "location": "Hästbo",
            "business": "Sågverk, hyvleri och tegeltillverkning",
            "products": "Sågade och hyvlade trävaror, taktegel samt dräneringsrör",
            "contact": {
                "phone": [
                    "6"
                ],
                "postgiro": "37419"
            },
            "financials": {
                "capital": "180,500 kr",
                "employees": {
                    "industriarb": 35
                },
                "annual_turnover": "1,500,000 st. tegelvaror, 500 stds trävaror",
                "foundation_year": 1929
            },
            "board": [
                {
                    "name": "v. konsul Robert Carrick",
                    "role": "Ordförande"
                },
                {
                    "name": "hemmansäg. Axel Jönsson",
                    "role": "Styrelseledamot"
                },
                {
                    "name": "köpm. P. J. Norbäck",
                    "role": "Styrelseledamot"
                }
            ],
            "director": "Verkställande styrelseledamot: Robert Carrick",
            "manager": "Kamrer: Torsten Stålberg"
        },
        "5": {
            "name": "AB. Hästholmsvarvet",
            "location": "Lidingö",
            "business": "Båtvarv",
            "products": "Ny- och ombyggnader, vinterförvaring och utrustning av motor- och segelbåtar",
            "contact": {
                "office": "Gåshaga, Lidingö",
                "phone": [
                    "Stockholm 656043"
                ],
                "postgiro": "300,000 kr"
            },
            "financials": {
                "capital": "300,000 kr",
                "employees": {
                    "arb-antal": 20
                },
                "foundation_year": 1906
            },
            "board": [
                {
                    "name": "adv. Anders Lind",
                    "role": "Styrelseledamot"
                },
                {
                    "name": "ing. Knud H. Reimers",
                    "role": "Styrelseledamot"
                }
            ],
            "director": "Verkställande direktör: kapten Stig Wilton"
        },
        "6": {
            "name": "AB. Höganäsarbeten",
            "location": "Stockholm",
            "business": "Entreprenörfirma",
            "products": "Syrafasta och eldfasta murningar, plattsättning och akustikförbättring",
            "contact": {
                "office": "Malmtorgsgatan 6, Stockholm",
                "phone": [
                    "232100"
                ],
                "postgiro": "159170"
            },
            "financials": {
                "capital": "90,000 kr",
                "employees": {
                    "industriarb": 30
                },
                "annual_turnover": "900,000 kr",
                "current_name_year": 1942
            },
            "board": [
                {
                    "name": "dir. P. Eg. Gummeson",
                    "role": "Ordförande"
                },
                {
                    "name": "dir. Mårten Schwartz",
                    "role": "Styrelseledamot"
                }
            ],
            "director": "Verkställande direktör: V. Terling",
            "sales_manager": "Arbetschef: civiling. Malcolm Broddner"
        },
        "7": {
            "name": "AB. Höganäs-Billesholms AB.",
            "location": "Höganäs",
            "business": "Tillverkning av gruvprodukter och keramiska produkter",
            "products": "Eldfast tegel, järnsvamp, golvklinker, glaserade väggplattor, glaserade lerrör, murtegel, syrafast stengods, lerkärl, kemiska produkter ur stenkolstjära samt kiselkarbid och elektrokorund",
            "contact": {
                "office": "Höganäs",
                "phone": [
                    "Höganäsbolaget, Höganäs"
                ],
                "postgiro": "8565"
            },
            "financials": {
                "capital": "30,000,000 kr",
                "employees": {
                    "arb-antal": 3,
                    "ärstprod": {
                        "gruvprodukter": "669,500 ton",
                        "keramiska produkter": "166,000 ton",
                        "metallurgiska produkter": "22,000 ton",
                        "kemiska produkter": "2,050 ton",
                        "el. energi": "9,3 mill. kWh"
                    }
                },
                "foundation_year": 1903
            },
            "board": [
                {
                    "name": "dir. Carl Johan Malmros",
                    "role": "Ordförande"
                },
                {
                    "name": "bankdir. Allan Alexanderson",
                    "role": "Styrelseledamot"
                }
            ],
            "director": "Verkställande direktör: P. Eg. Gummeson"
        }
    }
}