{
    "original": "Ingelsten—Ingeniörsfirman\n\nStyrelse: disp. Richard Hedlund\n(ordf.), ing. P. Gibson, dir. Carl Oldby.\n\nVerkst. dir.: R. Hedlund.\n\nBitr. dir.: Carl Oldby.\n\nFörsäljn.-chef: intend. Sven\nRunn-quist.\n\nFabrikschef: övering. Harry Sjögren.\n\nIngelsten &amp; Co., Anderstorp.\n\nPlåtmanufakturverk i Anderstorp\n(Jönköp. l.). Tillverkar frisyrartiklar såsom\npapiljotter, vågklämmor och clips,\nfärg-bandsspolar till skrivmaskiner,\nplanschetter, bysthållarekrok samt fotohörn.\n\nTelefon: 121. Postgiro: 133617. —\nAntal industriarb.: 10. Tillv.-värde pr år:\n200,000 kr. — Firman etabl. 1937.\n\nÄgare o. chefer: fabr. Ivar Ingelsten o.\nfabr. Harry Moden.\n\nIngenjörsfirma Sven Carlson AB.,\n\nFalun.\n\nMek. verkstad. Konstruerar och\ntillverkar transportanordningar såsom\nsläpskra-peanläggningar, automatiska hund- och\nspelbanor, skopelevatorer, rem-,\nkätting-och skraptransportörer, linbanor,\nfriktionsspel, släpskrapspel, släpskrapor,\nlinblock samt sorterverk och lastfickor.\n\nTelefon: 739. — Akt.-kap.: 50,500 kr.\nAntal industriarb.: 24. Tillv.-värde pr år:\n500,000 kr. — Firman etabl. 1909, bolag\n1937.\n\nVerkst. dir.: ing. Sven Carlson.\n\nKamrer: Gerh. Lindberg.\n\nIngenjörsfirman Certus AB.,\n\nBorås.\n\nTillverkar som specialitet\npressmaskiner för konfektionsindustrien vid mek.\nverkstad i Bollebygd (Älvsb. l.).\n\nKontor: Borås. Telegr.-adr.: Sutrec,\nBorås. Telefon: 20258 o. 20278. Postgiro:\n54984. — Akt.-kap.: 51,000 kr.\nArb.-an-tal: 15. — Firman etabl. 1925, bolag\n1945.\n\nVerkst. dir.: ing. Bertil Udden.\n\n^Ingenjörsfirma J. Owe Elgström,\n\nHärnösand.\n\nByggnadsentreprenörfirma för\nbostads-och affärshus, industribyggnader samt för\nväg- och vattenbyggnadsarbeten.\n\nTelefon: 1479 o. 1889. Postgiro: 73873.\n— Årsomsättning: 2,000,000 kr. —\nFirman etabl. 1927.\n\nÄgare o. chef: ing. J\". Owe Elgström.\n\nKamrer: Henning östholm.\n\n2 i\n\n*\tIngenjörsfirman Friberg &amp; Co. AB.,\n\nGöteborg.\n\nTillverkar elektr. värmeapparater för\nindustrien såsom lackerings- och\nkärntorkugnar, värmeskåp, värmepatroner, genom\nströmnings-, varmvatten- och ångpannor,\nkok- och smältgrytor, limpannor,\nvärme-bord, träböjningsmallar och\nvulkanise-ringsplattor samt\nelvärme-specialapparater och utrustningar. Varumärke:\n»Fri-co».\n\nKontor: Elisedal 7. Telefon: 167432 o.\n163441. Postgiro: 43139. — Akt-kap.:\n30,000 kr. Antal industriarb.: 26.\nTillv.-värde pr år: 500,000 kr. — Firman etabl.\n1932.\n\nStyrelse o. verkst. direktörer: ing. Dan\nEggertz o. ing. Chr. Christensson.\n\n*\tIngenjörsfirman Hagelin &amp; Larsson,\n\nGöteborg.\n\nByggnadsentreprenörfirma för väg- och\nvattenbyggnadsarbeten samt\nhusbyggnads-arbeten.\n\nKontor; N. Larmg. 11—13. Telefon:\n175302. Postgiro: 45868. — Antal\nindustriarb.: 100. —- Firman etabl. 1936.\n\nÄgare o. chefer: civiling. Yngve\nHagelin o. civiling. Anders Larsson.\n\n*\tIngenjörsfirma Ragnar Larson &amp;\nCo., AB., Sundsvall.\n\nByggnadsentreprenörfirma för\nbostads-och affärshus, industribyggnader samt\nför väg- och vattenbyggnadsarbeten.\n\nTelefon: 2909 o. 2990. Postgiro: 136519.\n— Akt.-kap.: 55,000 kr. Prod.-värde pr\når: 1,500,000 kr. — Firman etabl. 1927.\n\nStyrelse o. verkst. dir.: major Ragnar\nC. Larson.\n\nDisp.: Edvard Dahlström.\n\n*\tIngenjörsfirman Sandblom &amp;\nStohne AB., Stockholm.\n\nSe AB. Stohne-Verken, Stockholm.\n\n*\tIngenjörsfirman Georg Schönander,\n\nStockholm.\n\nSe Georg Schönander, Stockholm.\n\n*AB. Ingeniörsfirman Teknik,\n\nStockholm.\n\nFabrik för tillverkning av neonrör\noch kvicksilverånglampor för belysning\noch reklamändamål samt för fotografiskt\nbruk, kvicksilverströmbrytare m. m.",
    "structured": {
        "1": {
            "name": "Ingelsten—Ingeniörsfirman",
            "location": "Anderstorp",
            "business": "Plåtmanufakturverk",
            "products": "Tillverkar frisyrartiklar såsom papiljotter, vågklämmor och clips, färg-bandsspolar till skrivmaskiner, planschetter, bysthållarekrok samt fotohörn",
            "contact": {
                "office": "Anderstorp",
                "phone": [
                    "121"
                ],
                "postgiro": "133617"
            },
            "financials": {
                "capital": "Not available",
                "employees": {
                    "industriarb": 10
                },
                "annual_turnover": "200,000 kr",
                "annual_production_value": "Not available"
            },
            "foundation_year": 1937,
            "owners": [
                "fabr. Ivar Ingelsten",
                "fabr. Harry Moden"
            ],
            "director": "Not available",
            "managing_director": "R. Hedlund",
            "sales_manager": "intend. Sven Runn-quist",
            "manager": "Carl Oldby"
        },
        "2": {
            "name": "Ingenjörsfirma Sven Carlson AB.",
            "location": "Falun",
            "business": "Mek. Verkstad",
            "products": "Konstruerar och tillverkar transportanordningar såsom släpskra-peanläggningar, automatiska hund- och spelbanor, skopelevatorer, rem-, kätting- och skraptransportörer, linbanor, friktionsspel, släpskrapspel, släpskrapor, linblock samt sorterverk och lastfickor",
            "contact": {
                "office": "Falun",
                "phone": [
                    "739"
                ],
                "postgiro": "Not available"
            },
            "financials": {
                "capital": "50,500 kr",
                "employees": {
                    "industriarb": 24
                },
                "annual_turnover": "500,000 kr",
                "annual_production_value": "Not available"
            },
            "foundation_year": 1909,
            "corporation_year": 1937,
            "director": "ing. Sven Carlson",
            "managing_director": "Not available",
            "sales_manager": "Not available",
            "manager": "Not available"
        },
        "3": {
            "name": "Ingenjörsfirman Certus AB.",
            "location": "Borås",
            "business": "Pressmaskiner",
            "products": "Tillverkar som specialitet pressmaskiner för konfektionsindustrien",
            "contact": {
                "office": "Borås",
                "phone": [
                    "20258",
                    "20278"
                ],
                "postgiro": "54984"
            },
            "financials": {
                "capital": "51,000 kr",
                "employees": {
                    "arban": 15
                },
                "annual_turnover": "Not available",
                "annual_production_value": "Not available"
            },
            "foundation_year": 1925,
            "corporation_year": 1945,
            "director": "ing. Bertil Udden",
            "managing_director": "Not available",
            "sales_manager": "Not available",
            "manager": "Not available"
        },
        "4": {
            "name": "Ingenjörsfirma J. Owe Elgström",
            "location": "Härnösand",
            "business": "Byggnadsentreprenörfirma",
            "products": "Byggnadsentreprenörfirma för bostads-och affärshus, industribyggnader samt för väg- och vattenbyggnadsarbeten",
            "contact": {
                "office": "Härnösand",
                "phone": [
                    "1479",
                    "1889"
                ],
                "postgiro": "73873"
            },
            "financials": {
                "capital": "Not available",
                "employees": {
                    "industriarb": "Not available",
                    "arbarb": "Not available"
                },
                "annual_turnover": "2,000,000 kr",
                "annual_production_value": "Not available"
            },
            "foundation_year": 1927,
            "corporation_year": "Not available",
            "director": "ing. J\". Owe Elgström",
            "managing_director": "Not available",
            "sales_manager": "Not available",
            "manager": "Not available"
        },
        "5": {
            "name": "Ingenjörsfirman Friberg & Co. AB.",
            "location": "Göteborg",
            "business": "Tillverkar elektr. värmeapparater",
            "products": "Tillverkar elektr. värmeapparater för industrin",
            "contact": {
                "office": "Elisedal 7",
                "phone": [
                    "167432",
                    "163441"
                ],
                "postgiro": "43139"
            },
            "financials": {
                "capital": "30,000 kr",
                "employees": {
                    "industriarb": 26
                },
                "annual_turnover": "500,000 kr",
                "annual_production_value": "Not available"
            },
            "foundation_year": 1932,
            "corporation_year": "Not available",
            "director": "Not available",
            "managing_director": "ing. Dan Eggertz",
            "sales_manager": "Not available",
            "manager": "ing. Chr. Christensson"
        },
        "6": {
            "name": "Ingenjörsfirman Hagelin & Larsson",
            "location": "Göteborg",
            "business": "Byggnadsentreprenörfirma",
            "products": "Byggnadsentreprenörfirma för väg- och vattenbyggnadsarbeten samt husbyggnadsarbeten",
            "contact": {
                "office": "N. Larmg. 11—13",
                "phone": [
                    "175302"
                ],
                "postgiro": "45868"
            },
            "financials": {
                "capital": "Not available",
                "employees": {
                    "industriarb": 100
                },
                "annual_turnover": "Not available",
                "annual_production_value": "Not available"
            },
            "foundation_year": 1936,
            "corporation_year": "Not available",
            "director": "Not available",
            "managing_director": "Not available",
            "sales_manager": "Not available",
            "manager": "civiling. Anders Larsson"
        },
        "7": {
            "name": "Ingenjörsfirma Ragnar Larson & Co., AB.",
            "location": "Sundsvall",
            "business": "Byggnadsentreprenörfirma",
            "products": "Byggnadsentreprenörfirma för bostads-och affärshus, industribyggnader samt för väg- och vattenbyggnadsarbeten",
            "contact": {
                "office": "Sundsvall",
                "phone": [
                    "2909",
                    "2990"
                ],
                "postgiro": "136519"
            },
            "financials": {
                "capital": "55,000 kr",
                "employees": {
                    "arbarb": "Not available"
                },
                "annual_turnover": "Not available",
                "annual_production_value": "1,500,000 kr"
            },
            "foundation_year": 1927,
            "corporation_year": "Not available",
            "director": "major Ragnar C. Larson",
            "managing_director": "Not available",
            "sales_manager": "Not available",
            "manager": "Not available"
        }
    }
}