{
    "original": "Ekström—Elektrisk\n\nTelefon: 791 o. 1010. Postgiro: 36386.\n\nAkt.-kap.: 70,000 kr. Antal\nindustriarb.: 35. Tillv.-värde pr år: 300,000 kr.\n— Firman etabl. 1928, bolag 1943.\n\nVerkst. direktörer: Nils Blohm o.\nDaniel Ekström.\n\nAB. A. Ekströms Velocipedfabrik,\n\nHallsberg.\n\nTillverkar cykelramar, hopsätter och\nförsäljer cyklar samt utför\ncykelreparationer vid fabrik i Hallsberg (Örebro l.).\nVarumärke: »Ridax».\n\nTelefon: 46. Postgiro: 28301. —\nAkt.-kap.: 60,000 kr. Antal industriarb.: 10.\nTillv.-värde pr år: 200,000 kr. — Firman\netabl. 1910, bolag 1916.\n\nChef: Karl Karlsson.\n\n’AB. C. Ekström &amp; Compss\nPianofabrik, Malmö.\n\nTillverkar flyglar och pianinon.\n\nKontor: österg. 22. Telefon: 20230. —\nAkt.-kap.: 150,000 kr. Antal industriarb.:\n20. — Firman etabl. 1836, bolag 1907.\n\nStyrelse o. verkst. dir.: Gustaf\nHult-gren.\n\nTékn. chef: Axel Hultgren.\n\n’Ekströms Kem. Tekn. AB., Örebro.\n\nTillverkar bakpulver, vanillinsoeker,\nsoja och såspulver, nyponmust samt\nhushållsessenser. Specialitet: Ekströms\nbakpulver o. vanillinsoeker.\n\nTelegr.-adr.: Ketefa, Örebro. Telefon:\n19145. Postgiro: 20764.\n\nAkt.-kap.: 66,600 kr. Antal\nindustriarb.: 50. — Firman etabl. 1855, bolag\n1930 under namn AB. Örebro Kem. Tekn.\nFabrik, nuv. namn 1943.\n\nStyrelse: dir. Alf Bergå, ing. Håkan\nBergå, fru Anna Svensson.\n\nVerkst. dir. o. reklamchef: Alf Bergå.\n\nDriftsing. o. inköpschef: Håkan Bergå.\n\nK. A. Ekström &amp; Son,\n\nKristianstad.\n\nKopparslageri och mek. verkstad.\nTillverkar kok- och destillationsapparater,\nbryggeripannor, apparater för kemisk\nindustri, kopparrörledningar och plåtrör\nför pappersbruk.\n\nTelegr.-adr.: Ekströmarna,\nKristianstad. Telefon: 10259 o. 12359. Postgiro:\n30262. — Ensamförsälj. till bryggerier:\nOhr. Berner, Göteborg, telefon: 171010.\n\nAntal industriarb.: 47. Tillv.-värde pr\når: 700,000 kr. — Firman etabl. 1896.\n\nÄgare o. chef: fabr. K. Gunnar\nEkström.\n\n(Jfr annons nr 99.)\n\nEki, Fabriks AB., Markaryd.\n\nSe Fabriks AB. Ekå, Markaryd.\n\n’Eländers Boktryckeri AB., Göteborg.\n\nBoktryckeri, bokbinderi, klichéanstalt\noch stilgjuteri. Utför tryckning av\nkataloger, tidningar, vetenskapliga arbeten\noch accidensarbeten.\n\nKontor: Norra Allég. 2. Telegr.-adr.:\nPrinter, Göteborg. Telefon: 170170.\nPostgiro: 40654.\n\nAkt.-kap.: 200,000 kr. Antal\nindustriarb.: 80. Tillv.-värde pr år: 1,000,000 kr.\n\n—\tBolaget grundat 1908.\n\nStyrelse: bankdir. Axel G. Dahlander\n(ordf.), dir. Douglas Eländer, adv. Ivar\nGlimstedt.\n\nVerkst. dir.: Douglas Eländer.\n\n’AB. Electro-lnvest, Stockholm.-\n\nBolaget medverkar vid grundläggning\neller utvidgning samt administrering av\nföretag för alstring eller användning av\nelektrisk energi.\n\nKontor: Klarabergsg. 21. Telegr.-adr.:\nElectroinvest, Stockholm. Telefon: 101166\no. 114033. — Akt.-kap.: 12,000,000 kr. —\nBolaget, grundat 1929, äges av Asea och\nAB. Investor.\n\nStyrelse: dir. J. S. Edström (ordf.),\ndir. R. Oalissendorff, dir. Thorsten\nEricson, civiling. F. G. Liljenroth, frih.\nFritz Lilliecreutz, bankdir. Marcus\nWal-lenberg.\n\nVerkst. dir.: Lars Magnus Ericsson.\n\n’Elektraverken, Stockholm.\n\nSe AB. Osram-Elektraverken,\nStockholm.\n\nAB. Elektrisk Malmletning,\n\nStockholm.\n\nUtför geologiska och geofysiska\nberggrundsundersökningar för efterletning av\nmalmfyndigheter, salt- och\noljefyndighe-ter m. m. Tillverkar apparater för\njord-magnetiska och geoelektriska\nundersökningar, för tyngdkraftsmätningar samt\nför seismiska undersökningar.\n\nKontor: Kungsg. 44. Telegr.-adr.:\nProspecting, Stockholm. Telefon: 233380.\n\n—\tAkt.-kap.: 270,000 kr. — Bolaget,\ngrundat 1923, äges av Svenska\nDiamant-bergborrnings AB., Stockholm.\n\nStyrelse: bergsing. Helmer Hedström,\nciviling. F. G. Liljenroth, dir. B.\nWad-sted.\n\nVerkst. dir.: B. Wadsted.\n\nTekn. chef: Helmer Hedström.\n\nKamrer: Stig Tilländer.\n\n(Jfr annons efter Firmaregistret.)",
    "structured": {
        "firms": [
            {
                "name": "AB. A. Ekströms Velocipedfabrik",
                "location": "Hallsberg",
                "business": "Tillverkar cykelramar, hopsätter och försäljer cyklar samt utför cykelreparationer vid fabrik i Hallsberg (Örebro l.)",
                "financials": {
                    "capital": "70,000 kr",
                    "employees": {
                        "industriarb": 35
                    },
                    "annual_turnover": "300,000 kr",
                    "annual_production_value": "300,000 kr"
                },
                "foundation_year": 1928,
                "corporation_year": 1943,
                "board": [
                    {
                        "name": "Nils Blohm",
                        "role": "Verkst. direktör"
                    },
                    {
                        "name": "Daniel Ekström",
                        "role": ""
                    }
                ]
            },
            {
                "name": "AB. C. Ekström & Compss Pianofabrik",
                "location": "Malmö",
                "business": "Tillverkar flyglar och pianinon",
                "financials": {
                    "capital": "150,000 kr",
                    "employees": {
                        "industriarb": 20
                    }
                },
                "foundation_year": 1836,
                "corporation_year": 1907,
                "board": [
                    {
                        "name": "Gustaf Hultgren",
                        "role": "Styrelse o. verkst. dir."
                    },
                    {
                        "name": "Axel Hultgren",
                        "role": "Tékn. chef"
                    }
                ]
            },
            {
                "name": "Ekströms Kem. Tekn. AB.",
                "location": "Örebro",
                "business": "Tillverkar bakpulver, vanillinsoeker, soja och såspulver, nyponmust samt hushållsessenser",
                "financials": {
                    "capital": "66,600 kr",
                    "employees": {
                        "industriarb": 50
                    }
                },
                "foundation_year": 1855,
                "corporation_year": 1930,
                "board": [
                    {
                        "name": "Alf Bergå",
                        "role": "Styrelse"
                    },
                    {
                        "name": "Håkan Bergå",
                        "role": "Verkst. dir. o. reklamchef"
                    },
                    {
                        "name": "Anna Svensson",
                        "role": ""
                    }
                ]
            },
            {
                "name": "K. A. Ekström & Son",
                "location": "Kristianstad",
                "business": "Kopparslageri och mek. verkstad. Tillverkar kok- och destillationsapparater, bryggeripannor, apparater för kemisk industri, kopparrörledningar och plåtrör för pappersbruk",
                "financials": {
                    "employees": {
                        "industriarb": 47
                    },
                    "annual_turnover": "700,000 kr"
                },
                "foundation_year": 1896,
                "owner": "fabr. K. Gunnar Ekström"
            },
            {
                "name": "Eländers Boktryckeri AB.",
                "location": "Göteborg",
                "business": "Boktryckeri, bokbinderi, klichéanstalt och stilgjuteri. Utför tryckning av kataloger, tidningar, vetenskapliga arbeten och accidensarbeten",
                "financials": {
                    "capital": "200,000 kr",
                    "employees": {
                        "industriarb": 80
                    },
                    "annual_turnover": "1,000,000 kr"
                },
                "foundation_year": 1908,
                "board": [
                    {
                        "name": "Axel G. Dahlander",
                        "role": "Styrelse"
                    },
                    {
                        "name": "Douglas Eländer",
                        "role": "Verkst. dir."
                    },
                    {
                        "name": "Ivar Glimstedt",
                        "role": ""
                    }
                ]
            },
            {
                "name": "AB. Electro-lnvest",
                "location": "Stockholm",
                "business": "Bolaget medverkar vid grundläggning eller utvidgning samt administrering av företag för alstring eller användning av elektrisk energi",
                "financials": {
                    "capital": "12,000,000 kr"
                },
                "foundation_year": 1929,
                "board": [
                    {
                        "name": "J. S. Edström",
                        "role": "Styrelse"
                    },
                    {
                        "name": "R. Oalissendorff",
                        "role": ""
                    },
                    {
                        "name": "Thorsten Ericson",
                        "role": ""
                    },
                    {
                        "name": "F. G. Liljenroth",
                        "role": ""
                    },
                    {
                        "name": "Fritz Lilliecreutz",
                        "role": ""
                    },
                    {
                        "name": "Marcus Wal-lenberg",
                        "role": ""
                    },
                    {
                        "name": "Lars Magnus Ericsson",
                        "role": "Verkst. dir."
                    }
                ]
            },
            {
                "name": "AB. Elektrisk Malmletning",
                "location": "Stockholm",
                "business": "Utför geologiska och geofysiska berggrundsundersökningar för efterletning av malmfyndigheter, salt- och oljefyndighe-ter m. m. Tillverkar apparater för jord-magnetiska och geoelektriska undersökningar, för tyngdkraftsmätningar samt för seismiska undersökningar",
                "financials": {
                    "capital": "270,000 kr"
                },
                "foundation_year": 1923,
                "board": [
                    {
                        "name": "Helmer Hedström",
                        "role": "Styrelse"
                    },
                    {
                        "name": "F. G. Liljenroth",
                        "role": ""
                    },
                    {
                        "name": "B. Wadsted",
                        "role": "Verkst. dir."
                    }
                ],
                "manager": "Stig Tilländer"
            }
        ]
    }
}