{
    "original": "Matfors—Mattsson\n\n\"Matfors Yllefabriks AB., Matfors.\n\nUllspinneri, ylleväveri, färgeri,\nappre-turverk samt vadd- och täckfabrik i\nMatfors (Västernorrl. l.). Tillverkar\nullgarner, klännings- och kostymtyger av\nhel-och halvylle, filtar m. m. samt täcken\noch vadd.\n\nTelegr.-adr.: Matforsfabriken, Matfors.\nTelefon: »Yllefabriken». Postgiro: 102B6.\nRepr. i Stockholm: Elis Ekeberg,\nNorr-tullsg. 24, telefon: 802400.\n\nAkt.-kap.: 225,000 kr. Antal\nindustriarb.: 110. Tillv.-värde pr år: 2,000,000 kr.\n— Bolaget grundat 1897.\n\nStyrelse: dir. Mauritz Hägglund (ordf.),\ndisp. Henning Hägglund, dir. Sam Say.\n\nVerkst. dir.: M. Hägglund.\n\nDisp.: civiling. Börje Hägglund.\n\n\"Mathiassons Kritbruk, Kvarnby.\n\nSe AB. Kritbruksbolaget i Malmö,\nKvarnby.\n\n\"Matsilver AB., Sundbyberg.\n\nNysilverfabrik. Tillverkar\nkuvertartiklar i silver, nysilverråvara och rostfritt\nstål, nysilvervaror, tennvaror samt silver-,\nnysilver- och tennplåt.\n\nTelegr.-adr.: Matsilver, Sundbyberg.\nTelefon: Stockholm 281472. Postgiro:\n1472. — Akt.-kap.: 150,000 kr. Antal\nindustriarb.: 100. — Bolaget grundat 1917.\n\nStyrelse: disp. Olle Hultquist, löjtn. A.\nM. Myrtin, fabr. C. V. Stjernqvist.\n\nVerkst. dir.: Olle Hultquist.\n\nMattfabriken, Gust. Johansson,\n\nHabo.\n\nTillverkar ylle-, jute- och\nbomullsmattor, trasmattor samt allmogegardiner vid\nfabrik i Habo (Skarab. l.).\n\nTelefon: 28. Postgiro: 14779. — Antal\nindustriarb.: 15 samt 50 hemarbetare.\nTillv.-värde pr år: 110,000 kr. — Firman\netabl. 1926.\n\nÄgare o. chef: fabr. Gustaf Johansson.\n\nN. Mattisson, Glasindustri AB.,\n\nBroby.\n\nUtför böjning och slipning av glas för\nfotografiramar, pendyler och\ncykellyktor, backspeglar samt glas för\nbelysningsarmatur m. m. vid fabrik i Broby\n(Kristianst. l.).\n\nTelefon: 210. Postgiro: 174255. —\nAkt.-kap.: 42,300 kr. Antal industriarb.:\n\n28. Tillv.-värde pr år: 160,000 kr. —\nFirman etabl. 1920, nuv. namn 1941.\n\nStyrelsens ordf.: köpman Fridolf\nNilsson.\n\nDriftschef: Nils Mattisson.\n\n\"L. A. Mattons Läderfabriks AB.,\n\nGävle.\n\nTillverkar bottenläder.\n\nTelegr.-adr.: Matton, Gävle. Telefonr\n38. Postgiro: 80038.\n\nAkt.-kap.: 1,400,000 kr. Antal\nindustriarb.: 98. — Firman etabl. 1852, ombildad\ntill bolag 1930.\n\nStyrelse: borgm. Nils Berlin (ordf.)*\nfabr. Emil A. Matton, ing. Lars Matton.\n\nVerkst. dir.: Emil A. Matton.\n\nFabrihschef: Lars Matton.\n\nFörsäljn.-chef: John Rosell.\n\n\"And. Mattsons Mek. Verkstads AB^\n\nMora.\n\nMek. verkstad och gjuteri. Tillverkar\nsågverksmaskiner, brädgårdsvagnar,\ntorkhusvagnar, vagnstraverser, vändskivor,»\ntransportörer, spel, transmissioner,\nkugghjulspumpar, brunns- och gårdspumpar,,\nskogsredskap såsom tillväxtborrar,\ntum-klovar och stämpelyxor, jord- och\ntorv-borrar samt spolmaskiner för\nvävnads-slöjd m. m.\n\nTelefon: 6 o. 161. Postgiro: 14720.\n\nAkt.-kap.: 157,500 kr. Antal\nindustriarb.: 32. Tillv.-värde pr år: 550,000 kr..\n— Firman etabl. 1875, bolag 1910.\n\nStyrelse: dir. Alling Andersén (ordf.),,\nrektor Johan Pehrson, järnhandl. Enocb\nRingnér.\n\nVerkst. dir.: vakant.\n\n\"Ernst Mattssons Snörmakeri &amp;\nBandfabriks AB., Stockholm.\n\nTillverkar snörmakerier för möbler^\ngardiner, armatur, bilar, bussar och\njärnvägsvagnar ävensom drag-, persienne- och\nmarkissnören, packnings- och\nkondensor-snören samt fönsterpackning.\n\nKontor: Arbetarg. 33 A. Telefon:\n532096. Postgiro: 3921.\nUtställningslokal: Kungsg. 19. — Akt.-kap.: 150,000\nkr. Antal industriarb.: 20. Tillv.-värde pr\når: 300,000 kr. — Affären grundad 1833,,\nbolag 1923.\n\nStyrelse: fru Anna Mattsson (ordf.),,\ndir. Erik Larsson, disp. Gösta Mattsson\n\nVerkst. dir.: Gösta Mattsson.\n\n370*",
    "structured": {
        "1": {
            "name": "Matfors Yllefabriks AB",
            "location": "Matfors",
            "business": "Ullspinneri, ylleväveri, färgeri, appre-turverk samt vadd- och täckfabrik",
            "products": "Tillverkar ullgarner, klännings- och kostymtyger av hel-och halvylle, filtar m. m. samt täcken och vadd",
            "contact": {
                "office": "Matforsfabriken, Matfors",
                "phone": [
                    "Yllefabriken"
                ],
                "postgiro": "102B6",
                "head_office": "",
                "sales_offices": [
                    {
                        "location": "Stockholm",
                        "phone": "802400"
                    }
                ],
                "telegraph": "",
                "factory_office": "",
                "factory_phone": ""
            },
            "financials": {
                "capital": "225,000 kr",
                "employees": {
                    "industriarb": 110
                },
                "annual_turnover": "2,000,000 kr",
                "annual_production_value": "2,000,000 kr"
            },
            "foundation_year": 1897,
            "board": [
                {
                    "name": "Mauritz Hägglund",
                    "role": "ordf."
                },
                {
                    "name": "Henning Hägglund",
                    "role": "disp."
                },
                {
                    "name": "Sam Say",
                    "role": "dir."
                }
            ],
            "owner": "",
            "director": "",
            "managing_director": "M. Hägglund",
            "sales_manager": "",
            "manager": ""
        },
        "2": {
            "name": "Mathiassons Kritbruk",
            "location": "Kvarnby",
            "business": ""
        },
        "3": {
            "name": "Matsilver AB",
            "location": "Sundbyberg",
            "business": "Nysilverfabrik",
            "products": "Tillverkar kuvertartiklar i silver, nysilverråvara och rostfritt stål, nysilvervaror, tennvaror samt silver-, nysilver- och tennplåt",
            "contact": {
                "office": "Matsilver, Sundbyberg",
                "phone": [
                    "Stockholm 281472"
                ],
                "postgiro": "1472",
                "head_office": "",
                "sales_offices": [],
                "telegraph": "",
                "factory_office": "",
                "factory_phone": ""
            },
            "financials": {
                "capital": "150,000 kr",
                "employees": {
                    "industriarb": 100
                },
                "annual_turnover": "",
                "annual_production_value": ""
            },
            "foundation_year": 1917,
            "board": [
                {
                    "name": "Olle Hultquist",
                    "role": "disp."
                },
                {
                    "name": "A. M. Myrtin",
                    "role": "löjtn."
                },
                {
                    "name": "C. V. Stjernqvist",
                    "role": "fabr."
                }
            ],
            "owner": "",
            "director": "",
            "managing_director": "Olle Hultquist",
            "sales_manager": "",
            "manager": ""
        },
        "4": {
            "name": "Mattfabriken, Gust. Johansson",
            "location": "Habo",
            "business": "Tillverkar ylle-, jute- och bomullsmattor, trasmattor samt allmogegardiner",
            "products": "",
            "contact": {
                "office": "",
                "phone": [
                    "28"
                ],
                "postgiro": "14779",
                "head_office": "",
                "sales_offices": [],
                "telegraph": "",
                "factory_office": "",
                "factory_phone": ""
            },
            "financials": {
                "capital": "",
                "employees": "",
                "annual_turnover": "110,000 kr",
                "annual_production_value": "110,000 kr"
            },
            "foundation_year": 1926,
            "board": [],
            "owner": "fabr. Gustaf Johansson",
            "director": "",
            "managing_director": "",
            "sales_manager": "",
            "manager": ""
        },
        "5": {
            "name": "N. Mattisson, Glasindustri AB.",
            "location": "Broby",
            "business": "Utför böjning och slipning av glas för fotografiramar, pendyler och cykellyktor, backspeglar samt glas för belysningsarmatur",
            "products": "",
            "contact": {
                "office": "",
                "phone": [
                    "210"
                ],
                "postgiro": "174255",
                "head_office": "",
                "sales_offices": [],
                "telegraph": "",
                "factory_office": "",
                "factory_phone": ""
            },
            "financials": {
                "capital": "42,300 kr",
                "employees": {
                    "industriarb": 28
                },
                "annual_turnover": "160,000 kr",
                "annual_production_value": "160,000 kr"
            },
            "foundation_year": 1920,
            "board": [
                {
                    "name": "Fridolf Nilsson",
                    "role": "ordf."
                }
            ],
            "owner": "",
            "director": "",
            "managing_director": "Nils Mattisson",
            "sales_manager": "",
            "manager": ""
        },
        "6": {
            "name": "L. A. Mattons Läderfabriks AB",
            "location": "Gävle",
            "business": "Tillverkar bottenläder",
            "products": "",
            "contact": {
                "office": "Matton, Gävle",
                "phone": [
                    "38"
                ],
                "postgiro": "80038",
                "head_office": "",
                "sales_offices": [],
                "telegraph": "",
                "factory_office": "",
                "factory_phone": ""
            },
            "financials": {
                "capital": "1,400,000 kr",
                "employees": {
                    "industriarb": 98
                },
                "annual_turnover": "",
                "annual_production_value": ""
            },
            "foundation_year": 1852,
            "board": [
                {
                    "name": "Nils Berlin",
                    "role": "borgm."
                },
                {
                    "name": "Emil A. Matton",
                    "role": "fabr."
                },
                {
                    "name": "Lars Matton",
                    "role": "ing."
                }
            ],
            "owner": "",
            "director": "",
            "managing_director": "Emil A. Matton",
            "sales_manager": "John Rosell",
            "manager": "Lars Matton"
        },
        "7": {
            "name": "And. Mattsons Mek. Verkstads AB",
            "location": "Mora",
            "business": "Mek. verkstad och gjuteri",
            "products": "Tillverkar sågverksmaskiner, brädgårdsvagnar, torkhusvagnar, vagnstraverser, vändskivor, transportörer, spel, transmissioner, kugghjulspumpar, brunns- och gårdspumpar,skogsredskap såsom tillväxtborrar, tumklovar och stämpelyxor, jord- och torv-borrar samt spolmaskiner för vävnads-slöjd",
            "contact": {
                "office": "",
                "phone": [
                    "6",
                    "161"
                ],
                "postgiro": "14720",
                "head_office": "",
                "sales_offices": [],
                "telegraph": "",
                "factory_office": "",
                "factory_phone": ""
            },
            "financials": {
                "capital": "157,500 kr",
                "employees": {
                    "industriarb": 32
                },
                "annual_turnover": "550,000 kr",
                "annual_production_value": "550,000 kr"
            },
            "foundation_year": 1875,
            "board": [
                {
                    "name": "Alling Andersén",
                    "role": "dir."
                },
                {
                    "name": "Johan Pehrson",
                    "role": "rektor"
                },
                {
                    "name": "Enocb Ringnér",
                    "role": "järnhandl."
                }
            ],
            "owner": "",
            "director": "",
            "managing_director": "",
            "sales_manager": "",
            "manager": ""
        },
        "8": {
            "name": "Ernst Mattssons Snörmakeri & Bandfabriks AB",
            "location": "Stockholm",
            "business": "Tillverkar snörmakerier för möbler, gardiner, armatur, bilar, bussar och järnvägsvagnar ävensom drag-, persienne- och markissnören, packnings- och kondensor-snören samt fönsterpackning",
            "products": "",
            "contact": {
                "office": "Arbetarg. 33 A",
                "phone": [
                    "532096"
                ],
                "postgiro": "3921",
                "head_office": "Kungsg. 19",
                "sales_offices": [],
                "telegraph": "",
                "factory_office": "",
                "factory_phone": ""
            },
            "financials": {
                "capital": "150,000 kr",
                "employees": {
                    "industriarb": 20
                },
                "annual_turnover": "300,000 kr",
                "annual_production_value": "300,000 kr"
            },
            "foundation_year": 1833,
            "board": [
                {
                    "name": "Anna Mattsson",
                    "role": "fru"
                },
                {
                    "name": "Erik Larsson",
                    "role": "dir."
                },
                {
                    "name": "Gösta Mattsson",
                    "role": "disp."
                }
            ],
            "owner": "",
            "director": "",
            "managing_director": "Gösta Mattsson",
            "sales_manager": "",
            "manager": ""
        }
    }
}