{
    "original": "Mackmeter—Magnusson\n\nAB. Mackmeter,\nMidsommarkransen.\n\nMek. verkstad i Midsommarkransen,\nStockholm. Tillverkar\nbensinlagrings-anläggningar samt mätare för bensin och\noljor. Varumärke: »Mack».\n\nTelegr.-adr.: Mack, Stockholm. Telefon:\n450830 o. 451110. Postgiro: 2531.\n\nAkt.-kap.: 90,000 kr. Antal\nindustriarb.: 15. Tillv.-värde pr år: 300,000 kr.\n— Firman grundad 1916, nuv. bolag\n1922.\n\nVerkst. dir.: fru H. Älvring.\n\nKamrer: Vilgodt Lindberg.\n\n*Mackmyra Sulfit AB., Mackmyra.\n\nSulfit- och sulfitspritfabrik samt\nsågverk vid Mackmyra (Gävleb. l.).\nTillverkar sulfitcellulosa, sulfitsprit och sågade\nträvaror. Bolaget idkar jämväl jordbruk\noch skogshantering.\n\nTelegr.-adr.: Mackmyrasulf it, Gävle.\nTelefon: Valbo 15. Postgiro: 24854.\n\nAkt.-kap.: 2,050,000 kr. Antal\nindustriarb.: 190. Årstillv.: 30,000 ton\nsulfitcellulosa, 1 milj. 1. sulfitsprit, 500 stds sågade\nträvaror. — Bolaget grundat 1890.\n\nStyrelse: ’godsäg. Erik Edström (ordf.),\ndisp. Gunnar Hornborg, övering. J.\nStrindlund, dir. Sjune Svensson.\n\nDisp.: Gunnar Hornborg.\n\nKontorschef: Alvar Svahn.\n\nDriftsing.: U. J. Strindlund.\n\nSkogsförvalt.: jägm. Cl. Löfgren.\n\n*AB. Madrasser, Karlstad.\n\nTillverkar madrasser, resårplymåer och\nryggkuddar.\n\nTelefon: 13656. Postgiro: 99869.\nRepresentanter: för Stockholm: Seth E.\nLindblad, Ulvsundavägen 8, telefon: 256415;\nför övriga Sverige: Bengt Westholm,\nLinköping, telefon: 27995.\n\nAkt.-kap.: 15,0.00 kr. Arb.-antal: 15.\nTillv.-värde pr år: 400,000 kr. —\nBolaget grundat 1936.\n\nStyrelse, verkst. dir. o. disp.: Bertil\nKolthoff.\n\nMadrass-Fabriken Dux AB.,\n\nMalmö.\n\nTillverkar spiralmadrasser, kuddar,\nfåtöljer, ottomaner, soffor, sängar m. m.\nVarumärke: »Dux».\n\nKontor: Celsiusg. 41. Telegr.-adr.:\nDux-madrass, Malmö. Telefon: »Ljungs\nindustrier». Postgiro: 14098. Utställningar: i\nStockholm, Vasag. 9, telefon: 107508; i\n\nGöteborg: ö. Larmg. 9—11, telefon:\n119334; i Malmö, Adelg. 2, telefon;\n26690.\n\nAkt.-kap.: 225,000 kr. Antal\nindustriarb.: 225. — Bolaget grundat 1926.\n\nStyrelse: fabr. A. Efraim Ljung\n(ordf.), fabr. Martin B. Andersson, dis£.\nEric Ljung.\n\nVerkst. dir.: A. E. Ljung.\n\nDisp.: Eric Ljung.\n\n*Magni AB., Borås.\n\nKonfektionsfabrik. Tillverkar herr- och\ngosskläder.\n\nTelefon: 17305. Postgiro: 20614. —\nAkt.-kap.: 300,000 kr. Antal industriarb.:\n300. Tillv.-värde pr år: 5,100,000 kr.\n\nFirman etabl. 1913, bolag 1914 under\nnamn AB. Borås Konfektionsfabrik, nuv.\nnamn 1939.\n\nStyrelse: ing. Stig Magni (ordf.), disp.\nGösta Magni, fru W. Magni.\n\nVerkst. dir.: Gösta Magni.\n\nMagnussons Lädervaru AB-,\n\nKlippan.\n\nSe AB. Bröderna Ottosson &amp; Co.\nLä-dervarufabrik, Klippan.\n\n*AB. Magnussons Mek. Verkstad,\n\nStockholm.\n\nTillverkar ringboksmekanismer ocb\nandra detaljer för lösbladspärmar.\n\nKontor: Regeringsg. 109.\nTelegr.-adr.: Permmekanik, Stockholm. Telefon:\n210938 o. 104054. Postgiro: 50675.\n\nAgenter: för samtliga länder utom\nNorge; AB. Galco. Stockholm, Gävleg.\n12 A; för Norge: Vilh. Sten Edwardsen\nA/S, Oslo, Huitfeldtsg. 3.\n\nAkt.-kap.: 75,000 kr. Antal\nindustriarb.: 30. Tillv.-värde pr år: 300,000 kr.\n— Firman etabl. 1895, bolag 1937.\n\nStyrelse: dir. Konrad Andersson (ordf.),\nbergsing. Sven Strömgren, kamrer\nThorsten Wiberg.\n\nVerkst. dir.: Sven Strömgren.\n\nV. verkst. dir.: Thorsten Wiberg.\n\n*AB. Magnusson &amp; Ohlssons\nMöbelfabrik, Malmhäck.\n\nTillverkar kompletteringsmöbler vid\nfabrik i Malmbäck (Jönköp. l.).\n\nTelefon: 53. Postgiro: 90124. —\nAkt.-kap.: 13,000 kr. Arb.-antal: 10.\nTillv.-värde pr år: 110,000 kr. — Firman etabl.\n1934, bolag 1935.\n\nStyrelse: fabr. Lage Åberg (ordf.),\nåkare Ernst Andersson, fru Astrid Åberg.\n\nVerkst. dir.: Lage Åberg.\n\n355*",
    "structured": {
        "1": {
            "name": "AB. Mackmeter, Midsommarkransen",
            "location": "Midsommarkransen, Stockholm",
            "business": "Tillverkning av bensinlagrings-anläggningar samt mätare för bensin och oljor",
            "products": "Varumärke: »Mack»",
            "contact": {
                "office": "Mek. verkstad i Midsommarkransen, Stockholm",
                "phone": [
                    "450830",
                    "451110"
                ],
                "postgiro": "2531",
                "telegraph": "Mack, Stockholm"
            },
            "financials": {
                "capital": "90,000 kr",
                "employees": {
                    "industriarb.": 15
                },
                "annual_turnover": "300,000 kr",
                "annual_production_value": "300,000 kr"
            },
            "foundation_year": 1916,
            "corporation_year": 1922,
            "board": [
                {
                    "name": "fru H. Älvring",
                    "role": "Verkst. dir."
                },
                {
                    "name": "Vilgodt Lindberg",
                    "role": "Kamrer"
                }
            ]
        },
        "2": {
            "name": "Mackmyra Sulfit AB., Mackmyra",
            "location": "Mackmyra (Gävleb. l.)",
            "business": "Tillverkning av sulfitcellulosa, sulfitsprit och sågade trävaror, jordbruk och skogshantering",
            "contact": {
                "phone": "Valbo 15",
                "postgiro": "24854",
                "telegraph": "Mackmyrasulf it, Gävle"
            },
            "financials": {
                "capital": "2,050,000 kr",
                "employees": {
                    "industriarb.": 190
                },
                "annual_turnover": "30,000 ton sulfitcellulosa, 1 milj. 1. sulfitsprit, 500 stds sågade trävaror"
            },
            "foundation_year": 1890,
            "board": [
                {
                    "name": "godsäg. Erik Edström",
                    "role": "Styrelse: ordf."
                },
                {
                    "name": "disp. Gunnar Hornborg",
                    "role": "Disp."
                },
                {
                    "name": "övering. J. Strindlund",
                    "role": "Övering."
                },
                {
                    "name": "dir. Sjune Svensson",
                    "role": "Dir."
                },
                {
                    "name": "Gunnar Hornborg",
                    "role": "Styrelse: disp."
                },
                {
                    "name": "Alvar Svahn",
                    "role": "Kontorschef"
                },
                {
                    "name": "U. J. Strindlund",
                    "role": "Driftsing."
                },
                {
                    "name": "jägm. Cl. Löfgren",
                    "role": "Skogsförvalt."
                }
            ]
        },
        "3": {
            "name": "AB. Madrasser, Karlstad",
            "location": "Karlstad",
            "business": "Tillverkning av madrasser, resårplymåer och ryggkuddar",
            "contact": {
                "phone": "13656",
                "postgiro": "99869",
                "representatives": [
                    {
                        "location": "Stockholm",
                        "name": "Seth E. Lindblad",
                        "phone": "256415"
                    },
                    {
                        "location": "övriga Sverige",
                        "name": "Bengt Westholm",
                        "phone": "27995"
                    }
                ]
            },
            "financials": {
                "capital": "15,0.00 kr",
                "employees": {
                    "Arb.-antal": 15
                },
                "annual_turnover": "400,000 kr"
            },
            "foundation_year": 1936,
            "board": [
                {
                    "name": "Bertil Kolthoff",
                    "role": "Styrelse, verkst. dir. o. disp."
                }
            ]
        },
        "4": {
            "name": "Madrass-Fabriken Dux AB., Malmö",
            "location": "Malmö",
            "business": "Tillverkning av spiralmadrasser, kuddar, fåtöljer, ottomaner, soffor, sängar m. m.",
            "products": "Varumärke: »Dux»",
            "contact": {
                "office": "Celsiusg. 41",
                "phone": [
                    "Ljungs industri",
                    "107508"
                ],
                "postgiro": "14098",
                "exhibitions": [
                    {
                        "location": "Stockholm",
                        "phone": "107508"
                    },
                    {
                        "location": "Göteborg",
                        "phone": "119334"
                    },
                    {
                        "location": "Malmö",
                        "phone": "26690"
                    }
                ]
            },
            "financials": {
                "capital": "225,000 kr",
                "employees": {
                    "industriarb.": 225
                }
            },
            "foundation_year": 1926,
            "board": [
                {
                    "name": "fabr. A. Efraim Ljung",
                    "role": "Styrelse: ordf."
                },
                {
                    "name": "fabr. Martin B. Andersson",
                    "role": "Styrelse: disp."
                },
                {
                    "name": "dis¥. Eric Ljung",
                    "role": "Disp."
                }
            ]
        },
        "5": {
            "name": "Magni AB., Borås",
            "location": "Borås",
            "business": "Tillverkning av herr- och gosskläder",
            "contact": {
                "phone": "17305",
                "postgiro": "20614"
            },
            "financials": {
                "capital": "300,000 kr",
                "employees": {
                    "industriarb.": 300
                },
                "annual_turnover": "5,100,000 kr"
            },
            "foundation_year": 1913,
            "corporation_year": 1914,
            "current_name_year": 1939,
            "board": [
                {
                    "name": "ing. Stig Magni",
                    "role": "Styrelse: ordf."
                },
                {
                    "name": "disp. Gösta Magni",
                    "role": "Styrelse: disp."
                },
                {
                    "name": "fru W. Magni",
                    "role": "Styrelse"
                }
            ],
            "director": "Gösta Magni"
        },
        "6": {
            "name": "Magnussons Lädervaru AB-, Klippan",
            "location": "Klippan",
            "description": "Se AB. Bröderna Ottosson &amp; Co. Lä-dervarufabrik, Klippan"
        },
        "7": {
            "name": "AB. Magnussons Mek. Verkstad, Stockholm",
            "location": "Stockholm",
            "business": "Tillverkning av ringboksmekanismer ocb andra detaljer för lösbladspärmar",
            "contact": {
                "office": "Regeringsg. 109",
                "phone": [
                    "210938",
                    "104054"
                ],
                "postgiro": "50675",
                "agents": [
                    {
                        "country": "samtliga länder utom Norge",
                        "name": "AB. Galco. Stockholm",
                        "location": "Gävleg. 12 A"
                    },
                    {
                        "country": "Norge",
                        "name": "Vilh. Sten Edwardsen A/S, Oslo",
                        "location": "Huitfeldtsg. 3"
                    }
                ]
            },
            "financials": {
                "capital": "75,000 kr",
                "employees": {
                    "industriarb.": 30
                },
                "annual_turnover": "300,000 kr"
            },
            "foundation_year": 1895,
            "corporation_year": 1937,
            "board": [
                {
                    "name": "dir. Konrad Andersson",
                    "role": "Styrelse: ordf."
                },
                {
                    "name": "bergsing. Sven Strömgren",
                    "role": "Styrelse"
                },
                {
                    "name": "kamrer Thorsten Wiberg",
                    "role": "V. verkst. dir."
                }
            ],
            "director": "Sven Strömgren",
            "managing_director": "Thorsten Wiberg"
        },
        "8": {
            "name": "AB. Magnusson &amp; Ohlssons Möbelfabrik, Malmhäck",
            "location": "Malmbäck (Jönköp. l.)",
            "business": "Tillverkning av kompletteringsmöbler",
            "contact": {
                "phone": "53",
                "postgiro": "90124"
            },
            "financials": {
                "capital": "13,000 kr",
                "employees": {
                    "Arb.-antal": 10
                },
                "annual_turnover": "110,000 kr"
            },
            "foundation_year": 1934,
            "corporation_year": 1935,
            "board": [
                {
                    "name": "fabr. Lage Åberg",
                    "role": "Styrelse: ordf."
                },
                {
                    "name": "åkare Ernst Andersson",
                    "role": "Styrelse"
                },
                {
                    "name": "fru Astrid Åberg",
                    "role": "Styrelse"
                },
                {
                    "name": "Lage Åberg",
                    "role": "Verkst. dir."
                }
            ]
        }
    }
}