{
    "original": "Örebro—öresundsvarvet\n\nStyrelse: dir. Gösta Åqvist (ordf.),\ndisp. Harald Magnusson, disp. Sven\nÅqvist.\n\nDisp.: Harald Magnusson.\n\n*AB. Örebro Skobandfabrik, Örebro.\n\nTillverkar skoband och kängsnören.\n\nTelefon: 11573. Postgiro: 34243. —\nAkt.-kap.: 100,000 kr. Antal industriarb.:\n25. Tillv.-värde pr år: 400,000 kr. —\nFabriken anlagd 1901, bolag 1941.\n\nStyrelse o. verkst. dir.: Edv. Sandberg.\n\n*AB. Örebro Skofabrik, Örebro.\n\nTillverkar randsydda och genomsydda\nskodon samt agoskodon. Varunamn: för\ndamskor »Maritza»; för herrskor »Astor»;\nför pjäxor »Matsbo».\n\nTelegr.-adr.: Palmborg, Örebro.\nTelefon: 10555, 14555 o. 10559 (avd. Svea:\n10969). Postgiro: 71378.\n\nAkt.-kap.: 400,000 kr. Antal\nindustriarb.: 135. Tillv.-värde pr år: 2,500,000 kr.\n\nFirman, etabl. 1894, bolag 1929, har i\nsig upptagit f. d. AB. Skofabriken Svea.\n\nStyrelse: disp. Axel F. Bengtsson\n&lt;ordf.), fru A. Palmborg, dir. Bertil\nPalmborg, disp. Erik Palmborg, grossh.\nNils Palmborg.\n\nVerkst. dir.: Bertil Palmborg.\n\nDisponenter: Erik Palmborg o. Axel F.\n.Bengtsson.\n\nKassör: K. A. Nehrman.\n\n’Örebro Snickeri &amp; Trävaru AB.,\n\nÖrebro.\n\nTillverkar byggnadssnickerier,\nbutiks-och köksinredningar, Pivå-helljusfönster\noch Kährs lamelldörrar. Firman driver\näven handel med byggnadsmateriel.\n\nTelefon: 10296, 12596 o. 12562.\nPostgiro: 86008.\n\nAkt.-kap.: 225,000 kr. Antal\nindustriarb.: 50. Tillv.-värde pr år: 1,600,000 kr.\n— Firman etabl. 1876, bolag 1932.\n\nStyrelse: kabinettskammarh. frih. Hugo\nHamilton, kamrer Thor Palm, dir. Carl\nSvanström.\n\nVerkst. dir.; Carl Svanström.\n\nÖrebro Sportindustri, Örebro.\n\nSkofabrik i Örebro. Tillverkar\nidrotts-skodon, skidkängor och sandaler.\n\nTelefon: 13574. Postgiro: 77450. —\nTillv.-värde pr år: 500,000 kr. — Firman\netabl. 1921.\n\nÄgare o. chef: fabr. Paul Gustavsson.\n\n65\n\nAB. Örebro Strå- &amp; Filthattfabrik,\n\nÖrebro.\n\nTillverkar dam- och barnhattar.\n\nTelegr.-adr.: örebrohattar, Örebro.\nTelefon: 11030, 16920 o. 12630. Postgiro:\n28372. — Akt.-kap.: 80,000 kr. — Firman\ngrundad 1904, bolag 1923.\n\nVerkst. dir.: Karl Nyman.\n\n\"AB. Örebro Vadd- &amp; Yllefabrik,\n\nÖrebro.\n\nTillverkar schoddyvadd, bomullsvadd,\nlimvadd, förbands- och frisörvadd,\nsani-tetsbindor, isoleringsvadd, fönstervadd\nm. m. samt madrasser och kuddar vid\nfabrik i Sörby, Örebro.\n\nTelegr.-adr.: Yaddfabriken, Örebro.\nTelefon: 24010. Postgiro: 73141. Repr. i\nStockholm: C. Nordström, Agentur,\nSlät-baksv. 3, Enskede; telefon: 484573.\n\nAkt.-kap.: 120,300 kr. Antal\nindustriarb.: 30. Tillv.-värde pr år: 900,000 kr.\n— Firman etabl. 1916, bolag 1946.\n\nStyrelse o. verkst. dir.: Gösta Kardell.\n\n\"Öregrunds Slip &amp; Warfs AB.,\n\nÖregrund.\n\nSkeppsvarv med slip och mek. verkstad.\nUtför klassificerings- och\nreparationsarbeten av ång- och segelfartyg och pråmar\nsamt nybyggnader i mindre skala,\nävensom elektr. svetsning.\n\nTelegr.-adr.: Slipbolaget, Öregrund.\nTelefon: 15. Postgiro: 89902.\n\nAkt.-kap.: 187,500 kr. Antal\nindustriarb.: 45. Omsättningsvärde pr år: 350,000\nkr. — Bolaget grundat 1910.\n\nStyrelse: sjökapten August Svanström\n(ordf.), köpm. O. F. Leufstadius, ing.\nAlaric Nilsson.\n\nVerkst. dir.: Alaric Nilsson.\n\n\"Öresundsvarvet AB.,\n\nLandskrona.\n\nSkeppsvarv med dockor. Bygger\nstålfartyg och reparerar alla slags fartyg.\n\nTelegr.-adr. o. telefon: öresundsvarvet,\nLandskrona. Postgiro: 73722.\n\nAkt.-kap.: 2,000,000 kr. Antal\nindustriarb.: 1,000. Prod.-värde pr år: 20,000,000\nkr. — Bolaget grundat 1924.\n\nStyrelse: bankdir. Algot Riider (ordf.),\nskeppsred. J. E. Gorthon, dir. Hugo\nHey-man, dir. Karl Erik Jacobson, dir.\nHilding Nielsen, dir. C. A. Ridell, disp.\nGustaf Widström.\n\nVerkst. dir.: Hilding Nielsen.\n\nL*",
    "structured": {
        "1": {
            "name": "AB. Örebro Skobandfabrik",
            "location": "Örebro",
            "business": "Tillverkar skoband och kängsnören.",
            "contact": {
                "phone": [
                    "11573"
                ],
                "postgiro": "34243"
            },
            "financials": {
                "capital": "100,000 kr",
                "employees": {
                    "industriarb": 25
                },
                "annual_turnover": "400,000 kr",
                "annual_production_value": "400,000 kr"
            },
            "foundation_year": 1941
        },
        "2": {
            "name": "AB. Örebro Skofabrik",
            "location": "Örebro",
            "business": "Tillverkar randsydda och genomsydda skodon samt agoskodon.",
            "products": "Varunamn: för damskor »Maritza»; för herrskor »Astor»; för pjäxor »Matsbo».",
            "contact": {
                "telegraph": "Palmborg, Örebro",
                "phone": [
                    "10555",
                    "14555",
                    "10559 (avd. Svea: 10969)"
                ],
                "postgiro": "71378"
            },
            "financials": {
                "capital": "400,000 kr",
                "employees": {
                    "industriarb": 135
                },
                "annual_turnover": "2,500,000 kr",
                "annual_production_value": "2,500,000 kr"
            },
            "foundation_year": 1929,
            "predecessor": "f.d. AB. Skofabriken Svea"
        },
        "3": {
            "name": "AB. Örebro Snickeri & Trävaru AB.",
            "location": "Örebro",
            "business": "Tillverkar byggnadssnickerier, butiks-och köksinredningar, Pivå-helljusfönster och Kährs lamelldörrar. Driver även handel med byggnadsmateriel.",
            "contact": {
                "phone": [
                    "10296",
                    "12596",
                    "12562"
                ],
                "postgiro": "86008"
            },
            "financials": {
                "capital": "225,000 kr",
                "employees": {
                    "industriarb": 50
                },
                "annual_turnover": "1,600,000 kr",
                "annual_production_value": "1,600,000 kr"
            },
            "foundation_year": 1932
        },
        "4": {
            "name": "Örebro Sportindustri",
            "location": "Örebro",
            "business": "Tillverkar idrottsskodon, skidkängor och sandaler.",
            "contact": {
                "phone": [
                    "13574"
                ],
                "postgiro": "77450"
            },
            "financials": {
                "annual_turnover": "500,000 kr"
            },
            "foundation_year": 1921
        },
        "5": {
            "name": "AB. Örebro Strå- & Filthattfabrik",
            "location": "Örebro",
            "business": "Tillverkar dam- och barnhattar.",
            "contact": {
                "telegraph": "örebrohattar, Örebro",
                "phone": [
                    "11030",
                    "16920",
                    "12630"
                ],
                "postgiro": "28372"
            },
            "financials": {
                "capital": "80,000 kr"
            },
            "foundation_year": 1923
        },
        "6": {
            "name": "AB. Örebro Vadd- & Yllefabrik",
            "location": "Örebro",
            "business": "Tillverkar schoddyvadd, bomullsvadd, limvadd, förbands- och frisörvadd, sanitetsbindor, isoleringsvadd, fönstervadd m.m. samt madrasser och kuddar vid fabrik i Sörby, Örebro.",
            "contact": {
                "telegraph": "Yaddfabriken, Örebro",
                "phone": [
                    "24010"
                ],
                "postgiro": "73141"
            },
            "financials": {
                "capital": "120,300 kr",
                "employees": {
                    "industriarb": 30
                },
                "annual_turnover": "900,000 kr"
            },
            "foundation_year": 1946
        },
        "7": {
            "name": "Öregrunds Slip & Warfs AB.",
            "location": "Öregrund",
            "business": "Skeppsvarv med slip och mek. verkstad. Utför klassificerings- och reparationsarbeten av ång- och segelfartyg och pråmar samt nybyggnader i mindre skala, även elektr. svetsning.",
            "contact": {
                "telegraph": "Slipbolaget, Öregrund",
                "phone": [
                    "15"
                ],
                "postgiro": "89902"
            },
            "financials": {
                "capital": "187,500 kr",
                "employees": {
                    "industriarb": 45
                },
                "annual_turnover": "350,000 kr"
            },
            "foundation_year": 1910
        },
        "8": {
            "name": "Öresundsvarvet AB.",
            "location": "Landskrona",
            "business": "Skeppsvarv med dockor. Bygger stålfartyg och reparerar alla slags fartyg.",
            "contact": {
                "telegraph": "öresundsvarvet, Landskrona",
                "phone": [],
                "postgiro": "73722"
            },
            "financials": {
                "capital": "2,000,000 kr",
                "employees": {
                    "industriarb": 1000
                },
                "annual_turnover": "20,000,000 kr"
            },
            "foundation_year": 1924
        }
    }
}