{
    "original": "Nya—Nybro\n\n(ordf.), dir. Gustaf Änder, red. Erik\nBergström, tryckeförest. Viktor\nMagnusson, tandläkare Claes Stråhle.\n\nVerkst. dir.: Gustaf Änder.\n\nDir.-assist.: Einar Änder.\n\nTrycheriförest.: V. Magnusson.\n\n\"Nya AB. Visby Bryggeri, Visby.\n\nTillverkar maltdrycker, vichyvatten\noch läskedrycker.\n\nTelefon: »Visby bryggeri». Postgiro:\n189036. — Akt.-kap.: 1,080,000 kr. Antal\nindustriarb.: 20. Tillv.-värde pr år:\n1,200,000 kr. — Bolaget grundat 1910,\nombildat 1936.\n\nStyrelse: konsul C. E. Ekman (ordf.),\nbankdir. Henric Wiman (v. ordf.), dir.\nArendt de Jounge, disp. Kjell Wiman,\nbankdir. Malte Wiman.\n\nVerkst. dir.: Henric Wiman.\n\nDisp.: Kjell Wiman.\n\nNya AB. Östanåsågen, Ovanåker.\n\nSågverk och hyvleri i östanå, Ovanåker\n{Gävleb. l.). Tillverkar sågade och\nhyvlade trävaror, lister samt träkol.\n\nTelegr.-adr.: Ovanåkersvirke,\nOvanåker. Telefon: 34052. Postgiro: 277190.\n\nAkt.-kap.: 155,000 kr. Antal\nindustriarb.: 35. Årstillv.: 1,600 stds trävaror,\n800 läster träkol. — Nuv. bolag grundat\n1923.\n\nDisp.: Per Arvid Ericksson.\n\n*Nybble Klädesfabrik, Norrköping.\n\nSpinneri och färgeri. Tillverkar\nsvensk-ullgarner, yllegarner samt madrasser,\nkuddar, filtar, vadd och\nstoppningsmaterial; utför löngodsarbeten.\n\nTelefon: 30925 o. 31829. Postgiro:\n83578. — Antal industriarb.: 15. —\nFirman etabl. 1881 i Söderköping, flyttades\ntill Norrköping 1947.\n\nÄgare: fabr. Arvid Månssons sterbhus.\n\nChef: fabr, Bertil Monson.\n\n\"Nybergs Cruv AB.,\n\nSmedjebacken.\n\nSe Avesta Jernverks AB., Avesta.\n\"Nyboholms AB., Göteborg.\n\nPappersbruk med träsliperi, pappfabrik\n(Qvills Bruk), såg, bobinfabrik\n(Kvills-fors Bobinfabrik) vid Nyboholm\n(Kalmar l.) pr Kvillsfors. Tillverkar\nsilkesul-fit M. G., Cap- och silveromslagspapper,\ntoalettpapper, kräppat papper,\nbokbindar-papp och filtrerpapper m. m., våt\nslipmassa samt sågade trävaror och jutebobi-\n\nner. Bolaget driver även jordbruk och\nskogshantering samt distribuerar elkraft.\n\nHuvudkontor och ensamförsälj,:\nThorsten Brunius &amp; Co. AB., Göteborg, V.\nHamng. 2. Telegr.-adr,: Brunius,\nGöteborg. Telefon: 135037 o. 117920.\nPostgiro: 40748. Brukskontor: Kvillsfors.\nTelefon: 9 o. 15.\n\nAkt.-kap.: 300,000 kr. Antal\nindustriarb.: 75. Årstillv.: 2,500 ton papper o.\n100 ton papp m. m., 2,000 ton våt vit\neller brun slipmassa. — Bolaget grundat\n1901.\n\nStyrelse: ryttm. Gomer Brunius (ordf.),\ndisp. Sverker Brunius, dir. Eric\nLinde-löf.\n\nVerkst. dir. o. disp.: Gomer Brunius.\n\nFabrihschef: ing. Sten Fallenius.\n\nNyboholms Mek. Yerkstad, Skara.,\n\nTillverkar turbinf läktar, halm- och\nbossfläktar m. m. vid mek. verkstad i\nSkara.\n\nTelefon: 796. Postgiro: 141009. —-\nAntal industriarb.: 10. Tillv.-värde pr år:\n125,000 kr. — Fabriken grundad 1938.\n\nÄgare o. chefer: fabr. Nils Gustavsson\no. fabr. Einar Gustavsson.\n\n\"AB. Nyborgs Yllefabrik,\n\nNorrköping.\n\nUllspinneri, ylleväveri, appreturverk\noch färgeri. Tillverkar yllevävnader i\nfinare kvaliteter. Bolaget driver även\nengroshandel med fodervaror och\nskrädderiartiklar.\n\nTelegr.-adr.: Nyborgsylle, Norrköping.\nTelefon: »Nyborgs Yllefabrik». Postgiro:\n27242.\n\nAkt.-kap.: 1,350,000 kr. Antal\nindustriarb.: 330. Tillv.-värde pr år: 8,800,000 kr.\n\n—\tBolaget grundat 1905.\n\nStyrelse: disp. Fr. Nyborg (ordf.),\nkamrer J. Busch, ing. Sten Nyborg,\n\nVerkst. dir.: Fr. Nyborg.\n\nFabrihschef: Sten Nyborg.\n\nFörsäljn.-chef: J. Busch.\n\n\"Nybro Möbeibolag, Jonsson &amp; Son,\n\nNybro.\n\nTillverkar kompletteringsmöbler såsom\nhöj- och sänkbara bord, sekretärer,\nfåtöljbord, byråar, bokhyllor och skrivbord\nsamt dyschateller vid fabrik i Nybro\n(Kalmar l.).\n\nTelefon: 62 o. 500. Postgiro: 164239.\n\n—\tAntal industriarb.: 48. Tillv.-värde\npr år: 800,000 kr. — Firman etabl. 1935\nunder namn Eric Jonsson, Persmåla, nuv.\nnamn 1941.\n\nÄgare o. chefer: fabr. Eric Jonsson o.\nfabr. Lennart Jonsson.\n\n",
    "structured": {
        "1": {
            "name": "Nya AB. Visby Bryggeri",
            "location": "Visby",
            "business": "Tillverkar maltdrycker, vichyvatten och läskedrycker.",
            "contact": {
                "phone": [
                    "Visby bryggeri"
                ],
                "postgiro": "189036"
            },
            "financials": {
                "capital": "1,080,000 kr",
                "employees": {
                    "industriarb": 20
                },
                "annual_turnover": "1,200,000 kr"
            },
            "foundation_year": 1910,
            "corporation_year": 1936,
            "board": [
                {
                    "name": "konsul C. E. Ekman",
                    "role": "ordf."
                },
                {
                    "name": "bankdir. Henric Wiman",
                    "role": "v. ordf."
                },
                {
                    "name": "dir. Arendt de Jounge",
                    "role": "disp."
                },
                {
                    "name": "disp. Kjell Wiman",
                    "role": "bankdir."
                },
                {
                    "name": "bankdir. Malte Wiman",
                    "role": "disp."
                }
            ]
        },
        "2": {
            "name": "Nya AB. Östanåsågen",
            "location": "Ovanåker",
            "business": "Sågverk och hyvleri",
            "contact": {
                "telegraph": "Ovanåkersvirke, Ovanåker",
                "phone": "34052",
                "postgiro": "277190"
            },
            "financials": {
                "capital": "155,000 kr",
                "employees": {
                    "industriarb": 35
                },
                "annual_production_value": "1,600 stds trävaror, 800 läster träkol"
            },
            "foundation_year": 1923
        },
        "3": {
            "name": "Nybble Klädesfabrik",
            "location": "Norrköping",
            "business": "Spinneri och färgeri",
            "contact": {
                "phone": [
                    "30925",
                    "31829"
                ],
                "postgiro": "83578"
            },
            "financials": {
                "employees": {
                    "industriarb": 15
                }
            },
            "original_name": "fabr. Arvid Månssons sterbhus",
            "manager": "fabr, Bertil Monson"
        },
        "4": {
            "name": "Nybergs Cruv AB.",
            "location": "Smedjebacken"
        },
        "5": {
            "name": "Nyboholms AB.",
            "location": "Göteborg",
            "business": "Pappersbruk med träsliperi, pappfabrik",
            "contact": {
                "phone": "135037 o. 117920",
                "postgiro": "40748"
            },
            "financials": {
                "capital": "300,000 kr",
                "employees": {
                    "industriarb": 75
                },
                "annual_production_value": "2,500 ton papper o. 100 ton papp m. m., 2,000 ton våt vit eller brun slipmassa"
            },
            "foundation_year": 1901,
            "board": [
                {
                    "name": "ryttm. Gomer Brunius",
                    "role": "ordf."
                },
                {
                    "name": "disp. Sverker Brunius",
                    "role": "disp."
                },
                {
                    "name": "dir. Eric Lindelöf",
                    "role": "disp."
                }
            ]
        },
        "6": {
            "name": "Nyboholms Mek. Yerkstad",
            "location": "Skara",
            "business": "Tillverkar turbinf läktar, halm- och bossfläktar",
            "contact": {
                "phone": "796",
                "postgiro": "141009"
            },
            "financials": {
                "employees": {
                    "industriarb": 10
                },
                "annual_production_value": "125,000 kr"
            },
            "foundation_year": 1938
        },
        "7": {
            "name": "AB. Nyborgs Yllefabrik",
            "location": "Norrköping",
            "business": "Ullspinneri, ylleväveri, appreturverk och färgeri",
            "contact": {
                "phone": "Nyborgs Yllefabrik",
                "postgiro": "27242"
            },
            "financials": {
                "capital": "1,350,000 kr",
                "employees": {
                    "industriarb": 330
                },
                "annual_turnover": "8,800,000 kr"
            },
            "foundation_year": 1905,
            "board": [
                {
                    "name": "disp. Fr. Nyborg",
                    "role": "ordf."
                },
                {
                    "name": "kamrer J. Busch",
                    "role": "disp."
                },
                {
                    "name": "ing. Sten Nyborg",
                    "role": "verkst. dir."
                }
            ],
            "director": "Fr. Nyborg",
            "manager": "J. Busch"
        },
        "8": {
            "name": "Nybro Möbeibolag, Jonsson & Son",
            "location": "Nybro",
            "business": "Tillverkar kompletteringsmöbler",
            "contact": {
                "phone": [
                    "62",
                    "500"
                ],
                "postgiro": "164239"
            },
            "financials": {
                "employees": {
                    "industriarb": 48
                },
                "annual_production_value": "800,000 kr"
            },
            "original_name": "Eric Jonsson, Persmåla",
            "manager": "fabr. Lennart Jonsson"
        }
    }
}