{
    "original": "N. R. Rosenbergs Verkstäder,\n\nHässleholm.\n\nTillverkar byggnadssmiden, plåt- och\nbalkkonstruktioner samt smides- och\nhovbeslag vid mek. verkstad i Hässleholm\n(Kristianst. l.).\n\nTelefon: 148. Postgiro: 131293. —\nAntal industriarb.: 11. Tillv.-värde pr år:\n186,000 kr. — Firman etabl. 1940.\n\nÄgare o. chef: riksdagsman N. R.\nRosenberg.\n\nAB. Rosenblads Patenter,\n\n<i>Stockholm</i>.\n\nIngenjörsfirma med mek. verkstad i\nUlvsunda (Stockholm). Tillverkar\nvärmeväxlare (»Spiralförvärmaren») samt\napparatur för\nvärmeåtervinningsanläggningar, kondenseringsanläggningar,\nindunstnings- och torkanläggningar, ångboxar\noch kondensatsystem.\n\nKontor: Kommendörsg. 16.\nTelegr.-adr.: Calorspiral, Stockholm. Telefon:\n670670. Postgiro: 85299.\n\nAkt.-kap.: 84,000 kr, Autäl\nindustriarb.: 40. — Bolaget grundat 1933.\n\nStyrelse: marining. Carl Asker (ordf.),\nfrih. Carl Rosenblad, civiling. Curt\nRosenblad.\n\nVerkst. dir.: Curt Rosenblad.\n\n* Rosendahls Fabriker AB.,\n\nFilipstad.\n\nKem.-tekn. fabrik. Tillverkar\ncarbon-papper, kalkérpapper, färgband, stenciler,\nskrivbläck, tekniska och andra\nkontors-artiklar m. m. Varunamn: »Durit»,\n»Monument», »Prefecto», »Lifetime»,\n»Skantic», »Everest» m. fl.\n\nTelegr.-adr.: Rosendahls, Filipstad.\nTelefon: »Rosendahls Fabriker».\nPostgiro: 23838.\n\nAkt.-kap.: 350,000 kr. Antal\nindustriarb.: 75. Tillv.-värde pr år: 2,500,000 kr.\n— Firman etabl. 1922, bolag 1930.\n\nStyrelse: dir. Per Wenander (ordf.),\nkamrer Bertil Bremberg, kamrer Yngve\nWenander.\n\nVerkst. dir.: Per Wenander.\n\n(Jfr annons nr 53.)\n\n*AB. Rosenfors Bruk, Rosenfors.\n\nMek. verkstad och gjuteri vid\nRosenfors (Kalmar l.). Tillverkar\nverktygsmaskiner såsom fräsmaskiner,\nsnabbsvarvar och borrmaskiner jämte tillbehör.\nBolaget har eget vattenkraftverk och\ndriver jämväl jordbruk.\n\nTelegr.-adr.: Bruket, Rosenfors.\nTelefon: Målilla 171, 172 o. 173. Postgiro:\n8992.\n\nAkt.-kap.: 100,000 kr. Antal\nindustriarb.: 175. Tillv.-värde pr år: 2,100,000 kr.\n— Bruket anlagt 1802.\n\nStyrelse: bankdir. E. Beskow (ordf.),\nbankdir. G. Gyllensvärd, disp. Jonas\nHult, disp. Hj. Svenfelt, disp. L.\nTorstenson.\n\nDisp.: L. Torstenson.\n\nPlatschef: övering. Eric Hammarström.\n\nKamrer: Gösta Bohman.\n\nFörsäljn.-chef: Gerdt Falkheden.\n\n*AB. Rosenforsmöbler, Rosenfors.\n\nTillverkar matsalsmöbler i björk vid\nfabrik i Rosenfors (Kalmar l.).\n\nTelefon: 9. Postgiro: 99371. —\nAkt.-kap.: 20,700 kr. Arb.-antal: 10.\nTillv.-värde pr år: 80,000 kr. — Bolaget\ngrundat 1934.\n\nStyrelse o. verkst. dir.: Walter Carlberg.\n\n* Rosenfors Snickeri- &amp; Möbelfabrik,\n\nRosenfors.\n\nSe AB. Lundens Möbler, Rosenfors.\n\n*F. A. Rosengrens Kassaskåpsfabriks\nAB., <i>Göteborg</i>.\n\nMek. verkstad och specialfabrik för\nstålinredningar, stålmöbler och\nbyggnadsartiklar i Backa (Göteb. o. Bohus l.).\n\nTillverkningen omfattar:\n\n<i>bankinredningar</i> såsom depositionsfack,\ndepositionsfackskåp, postfack,\nkassavalvs-dörrar, dokumentlådor, lås och\nlåspatroner, bord för banker;\n\n<i>kontorsmöbler</i> såsom kassaskåp (även\ninmurningsskåp), förvaringsskåp (även\nbrandsäkra), ritningsskåp, bord,\narkiv- och bibliotekshyllor, kontorshyllor,\nkassaskrin, vertikalskåp (även brandsäkra),\nkortkrubbor;\n\n<i>industriinredningar</i> såsom hyllställningar,-\n]lingar,+} klädskåp, transportlådor,\narbetsbänkar, -bockar och -lådor, verktygsskåp,\nförmansbord;\n\n<i>artiklar för byggnadsindustrin</i> såsom\narkivdörrar, branddörrar (även\nskjutbara), andra ståldörrar, hissdörrar,\nstålkarmar, hörnskydd, plåtväggar o.\nhörnskydd.\n\nPostadr.: Göteborg 8. Telegr.-adr.:\nEarosengrens, Göteborg. Telefon: 222180.\nPostgiro: 12075. Avd.-kontor: Stockholm,\nFredsg. 12, telefon: 232180; Malmö,\nAdelg. 5, telefon: 70900; Norrköping,\ntelefon: 24686.\n\nAkt.-kap.: 2,000,000 kr. Antal\nindustriarb.: 450. Tillv.-värde pr år: 8,000,000 kr.\n",
    "structured": {
        "1": {
            "name": "N. R. Rosenbergs Verkstäder",
            "location": "Hässleholm",
            "business": "Byggnadssmiden, plåt- och balkkonstruktioner samt smides- och hovbeslag",
            "contact": {
                "office": "Hässleholm (Kristianst. l.)",
                "phone": [
                    "148"
                ],
                "postgiro": "131293"
            },
            "financials": {
                "employees": {
                    "industriarb": 11
                },
                "capital": "N/A",
                "annual_turnover": "186,000 kr",
                "annual_production_value": "N/A"
            },
            "foundation_year": 1940,
            "owners": [
                "riksdagsman N. R. Rosenberg"
            ],
            "director": "N/A",
            "managing_director": "N/A",
            "sales_manager": "N/A",
            "manager": "N/A"
        },
        "2": {
            "name": "AB. Rosenblads Patenter",
            "location": "Stockholm",
            "business": "Ingenjörsfirma med mek. verkstad",
            "products": "Värmeväxlare (»Spiralförvärmaren») samt apparatur för värmeåtervinningsanläggningar, kondenseringsanläggningar, indunstnings- och torkanläggningar, ångboxar och kondensatsystem.",
            "contact": {
                "office": "Ulvsunda (Stockholm)",
                "phone": [
                    "670670"
                ],
                "postgiro": "85299"
            },
            "financials": {
                "employees": {
                    "industriarb": 40
                },
                "capital": "84,000 kr",
                "annual_turnover": "N/A",
                "annual_production_value": "N/A"
            },
            "foundation_year": 1933,
            "board": [
                {
                    "name": "marining. Carl Asker",
                    "role": "ordf."
                },
                {
                    "name": "frih. Carl Rosenblad",
                    "role": "N/A"
                },
                {
                    "name": "civiling. Curt Rosenblad",
                    "role": "N/A"
                }
            ],
            "director": "Curt Rosenblad",
            "managing_director": "N/A",
            "manager": "N/A"
        },
        "3": {
            "name": "Rosendahls Fabriker AB.",
            "location": "Filipstad",
            "business": "Kem.-tekn. fabrik",
            "products": "Carbon-papper, kalkérpapper, färgband, stenciler, skrivbläck, tekniska och andra kontors-artiklar m. m.",
            "contact": {
                "office": "Rosenfors (Kalmar l.)",
                "phone": [
                    "Filipstad",
                    "Rosendahls Fabriker"
                ],
                "postgiro": "23838"
            },
            "financials": {
                "employees": {
                    "industriarb": 75
                },
                "capital": "350,000 kr",
                "annual_turnover": "2,500,000 kr",
                "annual_production_value": "N/A"
            },
            "foundation_year": 1922,
            "board": [
                {
                    "name": "dir. Per Wenander",
                    "role": "ordf."
                },
                {
                    "name": "kamrer Bertil Bremberg",
                    "role": "N/A"
                },
                {
                    "name": "kamrer Yngve Wenander",
                    "role": "N/A"
                }
            ],
            "director": "Per Wenander",
            "managing_director": "N/A",
            "manager": "N/A"
        },
        "4": {
            "name": "AB. Rosenfors Bruk",
            "location": "Rosenfors",
            "business": "Mek. verkstad och gjuteri",
            "products": "Verktygsmaskiner såsom fräsmaskiner, snabbsvarvar och borrmaskiner jämte tillbehör. Bolaget har eget vattenkraftverk och driver jämväl jordbruk.",
            "contact": {
                "office": "Rosenfors (Kalmar l.)",
                "phone": [
                    "Målilla 171",
                    "172",
                    "173"
                ],
                "postgiro": "8992"
            },
            "financials": {
                "employees": {
                    "industriarb": 175
                },
                "capital": "100,000 kr",
                "annual_turnover": "2,100,000 kr",
                "annual_production_value": "N/A"
            },
            "foundation_year": 1802,
            "board": [
                {
                    "name": "bankdir. E. Beskow",
                    "role": "ordf."
                },
                {
                    "name": "bankdir. G. Gyllensvärd",
                    "role": "N/A"
                },
                {
                    "name": "disp. Jonas Hult",
                    "role": "N/A"
                },
                {
                    "name": "disp. Hj. Svenfelt",
                    "role": "N/A"
                },
                {
                    "name": "disp. L. Torstenson",
                    "role": "N/A"
                }
            ],
            "director": "L. Torstenson",
            "manager": "N/A"
        },
        "5": {
            "name": "AB. Rosenforsmöbler",
            "location": "Rosenfors",
            "business": "Tillverkar matsalsmöbler i björk",
            "contact": {
                "office": "Rosenfors (Kalmar l.)",
                "phone": [
                    "9"
                ],
                "postgiro": "99371"
            },
            "financials": {
                "capital": "20,700 kr",
                "employees": {
                    "antal": 10
                },
                "annual_turnover": "80,000 kr",
                "annual_production_value": "N/A"
            },
            "foundation_year": 1934,
            "board": [],
            "director": "N/A",
            "managing_director": "Walter Carlberg",
            "sales_manager": "N/A",
            "manager": "N/A"
        },
        "6": {
            "name": "F. A. Rosengrens Kassaskåpsfabriks AB.",
            "location": "Göteborg",
            "business": "Mek. verkstad och specialfabrik för stålinredningar, stålmöbler och byggnadsartiklar"
        }
    }
}