{
    "original": "Fritsla—Franke l\n\nFirman etabl. 1931, bolag 1934 under\nnamn AB. Marboväveriet, nuv. namn\n1941.\n\nVerkst. dir. o. disp.: Knud Voss.\n*Fritsla Konfektionsfabrik, Fritsla.\n\nKonfektionsfabrik i Fritsla (Älvsb. L).\nTillverkar herr- och gosskläder samt\ndam-och flickkappor. Varumärke: »Atlas».\n\nTelefon: 70058. Postgiro: 10207. —\nAntal industriarb.: 97. Tillv.-värde pr år:\n1,025,000 kr. — Firman etabl. 1905 under\nnamn AB. Fritsla Syfabrik, nuv. namn\n1943.\n\nÄgare o. dis v.: Uno Thorson.\nAB. Fritsla Linneväveri, Fritsla.\n\nTillverkar gardiner, skj orttyger,\nlinnevaror m. in. vid väveri i Fritsla\n(Älvsb. l.).\n\nTelefon: 70104. Postgiro: 87420. —\nAkt.-kap.: 10,000 kr. Antal industriarb.:\n20. Tillv.-värde pr år: 300,000 kr. —\nBolaget grundat 1931.\n\nVerkst. dir.: fabr. Eskil Johansson.\n\n*\tFritsla Mek. Väfveri &amp; Spinnerier,\n\nFritsla.\n\nSe L. J. Wingqvist, Fritsla Mek.\nVäfveri &amp; Spinnerier, Fritsla.\n\n*\tFritsla Trikåstickeri, Johanson\n\n&amp; Co., Fritsla.\n\nTillverkar herr- och gossunderkläder i\nlahmansstickning vid fabrik i Fritsla\n(Älvsb. l.). Varumärke: »Åve».\n\nTelefon: Kinna 70121. Postgiro: 81984.\n— Antal industriarb.: 20. Tillv.-värde pr\når: 250,000 kr. — Firman etabl. 1931.\n\nÄgare o. chefer: fabr. Åke Johanson o.\nfabr. Wilh. Johansson.\n\n♦Fritsla Yllefabrik, Fritsla.\n\nSe AB. Sveriges Förenade\nTrikåfabri-ker, Borås.\n\nErik Frosts Knivfabrik, Mora.\n\nSmidesfabrik i Mora (Kopparb. l.).\nTillverkar tälj- och slidknivar, hushålls-,\nsport- och yrkesknivar.\n\nEnsamförsälj.: Böblmark &amp; Co., Mora.\nTelefon: 88, 388 o. 788. Postgiro: 6341.\n\nAntal industriarb.: 50. Tillv.-värde pr\når: 400,000 kr. — Firman etabl. 1891.\nÄgare: Erik Frosts sterbhus.\nChef: fabr. Karl Frost.\n\n\"AB. Fruetus Fabriker, Ulvsunda.\n\nFabrik för närings- och aromatiska\nprodukter i Ulvsunda, Stockholm.\nTillverkar saftkoncentrat, fruktextrakter och\nessenser för läskedrycksfabriker (märke:\n»Pommac» m. fl.) och för saft- och\nkaramellindustrien samt torkade nypon.\n\nKontor: Ulvsundavägen 108; postadr.:\nUlvsunda. Telegr.-adr.: Fructarom,\nStockholm. Telefon: 252630. Postgiro: 1441.\n\nAkt.-kap.: 410,000 kr. Antal\nindustriarb.: 25. — Firman etabl. 1919, bolag\n1930.\n\nStyrelse: adv. O. M. Fallenius, disp.\nFrithiof Lindahl, dir. Knut Mattsson,\nadv. Thorsten Persson.\n\nVerkst. dir.: Knut Mattsson.\nDisp.: Frithiof Lindahl.\nV. verkst. dir.: Einar Nordlundh.\n\n\"Frykfors AB., Dejeforsbruk.\nSe AB. Mölnbacka-Trysil, Forshaga.\n\n\"Frånö Sulfatfabrik, Frånö.\nSe Kramfors AB., Kramfors.\n\n\"Dan. Frändberg, Göteborg.\n\nByggnadsentreprenörfirma för\nbostads-och affärshus, industribyggnader m. m.\n\nKontor: Kyrkog. 4. Telefon: 113980,\n138751 o. 134033. Postgiro: 41006. —\nProd.-värde pr år: 1,500,000 kr. —\nFirman etabl. 1916.\n\nÄgare o. chef: ing. Dan. Frändberg.\nByråingenjör: Sixten Norrby.\n\n\"Erik I. Frändbergs Snickeri- &amp;\nKarosseriverkstad, Västerås.\n\nTillverkar karosserier till butikvagns-,\nskåpvagns- och ambulansbilar, lastflak\nför automobiler samt transportabla\nfisk-torgståndsvagnar.\n\nTelefon: 31238. Postgiro: 33916. —\nArb.-antal: 5. Tillv.-värde pr år: 80,000\nkr. — Firman etabl. 1922.\n\nÄgare o. chef: snickarmäst. Erik I.\nFrändberg.\n\nAB. Fränkel &amp; Elsner, Göteborg.\n\nMadrass- och resårfabrik. Tillverkar\nmadrasser, plymåer samt resårer.\nVarumärke: »Eisa». Bolaget driver såsom\nhuvudrörelse engroshandel med möbeltyger,\nmattor och stoppningsmaterialier.\n\nKontor: Andra Långg. 9. Telegr.-adr.:\nEisner, Göteborg. Telefon: 170545.\nPostgiro: 40599.",
    "structured": {
        "1": {
            "name": "Fritsla Konfektionsfabrik, Fritsla",
            "location": "Fritsla (Älvsb. L)",
            "business": "Konfektionsfabrik",
            "products": "Tillverkar herr- och gosskläder samt dam-och flickkappor. Varumärke: »Atlas».",
            "contact": {
                "phone": [
                    "70058"
                ],
                "postgiro": "10207"
            },
            "financials": {
                "employees": {
                    "industriarb": 97
                },
                "annual_turnover": "1,025,000 kr"
            },
            "foundation_year": 1905,
            "current_name_year": 1943
        },
        "2": {
            "name": "AB. Fritsla Linneväveri, Fritsla",
            "location": "Fritsla (Älvsb. l.)",
            "business": "Tillverkar gardiner, skj orttyger, linnevaror m. in. vid väveri",
            "contact": {
                "phone": [
                    "70104"
                ],
                "postgiro": "87420"
            },
            "financials": {
                "capital": "10,000 kr",
                "employees": {
                    "industriarb": 20
                },
                "annual_production_value": "300,000 kr"
            },
            "corporation_year": 1931
        },
        "3": {
            "name": "Fritsla Trikåstickeri, Johanson & Co., Fritsla",
            "location": "Fritsla (Älvsb. l.)",
            "business": "Tillverkar herr- och gossunderkläder i lahmansstickning vid fabrik",
            "products": "Varumärke: »Åve».",
            "contact": {
                "phone": "Kinna 70121",
                "postgiro": "81984"
            },
            "financials": {
                "employees": {
                    "industriarb": 20
                },
                "annual_production_value": "250,000 kr"
            },
            "owners": [
                "fabr. Åke Johanson",
                "fabr. Wilh. Johansson"
            ],
            "foundation_year": 1931
        },
        "4": {
            "name": "Erik Frosts Knivfabrik, Mora",
            "location": "Mora (Kopparb. l.)",
            "business": "Smidesfabrik",
            "products": "Tillverkar tälj- och slidknivar, hushålls-, sport- och yrkesknivar.",
            "contact": {
                "phone": [
                    "88",
                    "388",
                    "788"
                ],
                "postgiro": "6341"
            },
            "financials": {
                "employees": 50,
                "annual_production_value": "400,000 kr"
            },
            "foundation_year": 1891
        },
        "5": {
            "name": "AB. Fruetus Fabriker, Ulvsunda",
            "location": "Ulvsunda, Stockholm",
            "business": "Fabrik för närings- och aromatiska produkter",
            "products": "Tillverkar saftkoncentrat, fruktextrakter och essenser för läskedrycksfabriker (märke: »Pommac» m. fl.) och för saft- och karamellindustrien samt torkade nypon.",
            "contact": {
                "office": "Ulvsundavägen 108",
                "telegraph": "Fructarom, Stockholm",
                "phone": "252630",
                "postgiro": "1441"
            },
            "financials": {
                "capital": "410,000 kr",
                "employees": 25
            },
            "foundation_year": 1919,
            "corporation_year": 1930
        },
        "6": {
            "name": "Dan. Frändberg, Göteborg",
            "location": "Göteborg",
            "business": "Byggnadsentreprenörfirma",
            "products": "Byggnadsentreprenörfirma för bostads-och affärshus, industribyggnader m. m.",
            "contact": {
                "office": "Kyrkog. 4",
                "phone": [
                    "113980",
                    "138751",
                    "134033"
                ],
                "postgiro": "41006"
            },
            "financials": {
                "annual_turnover": "1,500,000 kr"
            },
            "foundation_year": 1916
        },
        "7": {
            "name": "Erik I. Frändbergs Snickeri- & Karosseriverkstad, Västerås",
            "location": "Västerås",
            "business": "Tillverkar karosserier till butikvagns-, skåpvagns- och ambulansbilar, lastflak för automobiler samt transportabla fisk- torgståndsvagnar.",
            "contact": {
                "phone": "31238",
                "postgiro": "33916"
            },
            "financials": {
                "employees": 5,
                "annual_production_value": "80,000 kr"
            },
            "foundation_year": 1922
        },
        "8": {
            "name": "AB. Fränkel & Elsner, Göteborg",
            "location": "Göteborg",
            "business": "Madrass- och resårfabrik",
            "products": "Tillverkar madrasser, plymåer samt resårer. Varumärke: »Eisa». Bolaget driver såsom huvudrörelse engroshandel med möbeltyger, mattor och stoppningsmaterialier.",
            "contact": {
                "office": "Andra Långg. 9",
                "telegraph": "Eisner, Göteborg",
                "phone": "170545",
                "postgiro": "40599"
            }
        }
    }
}