{
    "original": "Knutson—Ko chum\n\nStyrelse: byggm. Anders Knutsson\n(ordf.), kamrer Olof Andersson, ing. Ola\nKnutsson.\n\nVerkst. dir.: Anders Knutsson.\n\nArbetschef: Ola Knutsson.\n\nKamrer: Olof Andersson.\n\nKnutsons Marmeladfabriks AB.,\n\nVarberg.\n\nTillverkar marmelader, safter, sylter\nsamt konfityrer.\n\nTelefon: 456. Postgiro: 14843. —\nAkt.-kap.: 120,000 kr. Antal industriarb.: 15.\n\n—\tFirman etabl. 1892, bolag 1910.\n\nStyrelse: fröken H. Håkansson, köpm.\n\nJ. Håkansson, fröken S. Peterson.\n\nVerkst. dir.: vakant.\n\n\"Kocks Snickerifabriker AB.,\n\nMalmö.\n\nMöbelfabrik i Trelleborg. Tillverkar\nrestaurantmöbler, inredningar för teatrar\noch biografer, skolmöbler samt\nrumsmöbler. Specialitet: möbler av böjt trä.\n\nKontor: Malmö, Celsiusg. 41. Telefon:\n»Ljungs Industrier». Fabrikskontor:\nTrelleborg. Telefon: 486.\n\nAkt.-kap.: 100,000 kr. Antal\nindustriarb.: 60. Tillv.-värde pr år: 500,000 kr.\n\n—\tFirman etabl. 1917, bolag 1945.\n\nStyrelse: fabr. A. Efraim Ljung, disp.\n\nA. Eric Ljung, disp. S. Löfgren.\n\nVerkst. dir.: A. Eric Ljung.\n\n\"Kockums Emaljerverk, Ronneby.\n\nSe Kockums Jernverks AB., Kallinge.\n\n\"Kockums Jernverks AB., Kallinge.\n\nJärnverk med martinugnar, elektr.\nugnar, valsverk, galvaniserings- och\nemal-jeringsverk, gjuteri och mek. verkstad i\nKallinge (Blekinge l.) samt stans- och\nemaljeringsverk i Ronneby.\n\nTillverkar i Kallinge: martingöt,\nelek-trostålgöt, stålgjutgods, svart och galva\nniserad järnplåt, dynamoplåt och träns\nformatorplåt, svart och emaljerat\nhushålls- och sanitetsgjutgods,\nmaskinmang-lar. lyktstolpar, spiraltrappor,\nvärmeledningspannor (märke: »Rego»), gasspisar,\nelektriska spisar, vedspisar (vanliga\nspisar, V-KOCK-spisar), restaurangspisar\nm. m. samt utför förnickling,\nförkrom-ning och plåtpressning.\n\nTillverkar i Ronneby emaljerade kärl\n(varumärke: »K. E. R.») av plåt för\nhushålls- och sjukhusändamål samt utför\nplåtpressning och emaljering.\n\nBolaget, som har egna elektr.\nvattenkraftstationer i Kallinge, Ronneby och\nKarlsnäs, idkar jämväl jordbruk,\nskogshantering, kvarn- och sågverksrörelse.\n\nStyrelsens säte: Malmö, Regementsg.\n12. Telefon: 21240. Verkst. direktörs- och\nfabrikskontor i Kallinge, fabrikskontor i\nRonneby. Telegr.-adr.: Jernverket,\nKallinge. Försäljningskontor: Kallinge,\ntelefon: »Jernverket», postgiro: 9408;\nRonneby, telefon: 13, postgiro: 20900;\nStockholm, Kungsholmstorg 8, telefon:\n520360; Göteborg: Kungsportsavenyen\n11—13, telefon: 131789; Malmö,\nRegementsg. 12, telefon: 25524.\n\nAkt.-kap.: 4,000,000 kr. Antal\nindustriarb.: 1,700. Tillv.-värde pr år: 19,000,000\nkr. — Bolaget grundat 1875.\n\nStyrelse: bankdir. Åke Belfrage (ordf.),\ndir. Erik Kockum, dir.^ Frans Kockum,\ning. Gunnar Kockum, disp. Uno O.\nLarson, kapten J. H. Zethraeus.\n\nVerkst. dir.: Erik Kockum.\n\nDisp. i Kallinge: Uno O. Larson.\n\növeringenjörer: i Kallinge: T. Collén;\ni Ronneby: F. Gieseke.\n\nAvd.-chefer: i Kallinge: för kontoret o.\ninköp: kamrer Olof Ohlsson; för\nför-säljn.-avd.: Agnar Ohlsson; för\nplåtverken: ing. C. F. Fernegård; för\nmartinverket o. stålgjuteriet: bergsing. Olov\nEdström; för verkstaden och gjuteriet: ing.\nH. Ousbäck, R. Skarin o. O. Ordqvist;\nför ritkontoret: ing. S. Hartelius; för\nemaljverket: ing. Birger Olovson; för\narbetsstudieavd.: ing. N. Dageby; i\nRonneby: för försäljn.-avd.: Henning\nOhlsson; för emaljeringen: A. Arnevall; för\nstansverket: ing. Erik Säming; kamrer:\nC. Thorsell.\n\n\"Kockums Mekaniska Verkstads AB.,\n\nM almö.\n\nSkeppsvarv, mekanisk verkstad,\ngjuteri, manufaktur smed ja och vaggonfabrik.\n\nTillverkar krigsfartyg av alla slag,\nhandelsfartyg upp till 25,000 ton,\ndieselmotorer enligt Kockum-M. A. !N\".-system\nresp. Kockum—Frichssystem,\njärnvägsvagnar, motorlokomotiv, motorvagnar,\nbroar, lyftkranar, ångpannor och\nångmaskiner hejar- och ånghammarsmiden\nsamt »Tyfon»-signalapparater m. m.\n\nKontor: Stora Varvsg., Västra\nHamnsidan. Telegr.-adr. o. telefon:\nKockumsverkstad, Malmö. Postgiro: 38200.\n\nAkt.-kap.: 7,500,000 kr. Antal\nindustriarb.: 3,500 . Tillv.-värde pr år: 60,000,000\nkr. — Firman etabl. 1840, bolag 1866.\n\nStyrelse: bankdir. Ernst ö:son Herslow\n(ordf.), dir. Erik Kockum (v. ordf.), dir.",
    "structured": {
        "1": {
            "name": "Knutsons Marmeladfabriks AB.",
            "location": "Varberg",
            "business": "Tillverkar marmelader, safter, sylter samt konfityrer",
            "contact": {
                "phone": [
                    "456"
                ],
                "postgiro": "14843"
            },
            "financials": {
                "capital": "120,000 kr",
                "employees": {
                    "industriarb": 15
                }
            },
            "foundation_year": 1892,
            "corporation_year": 1910,
            "board": [
                {
                    "name": "fröken H. Håkansson",
                    "role": "köpm."
                },
                {
                    "name": "J. Håkansson",
                    "role": ""
                },
                {
                    "name": "fröken S. Peterson",
                    "role": ""
                }
            ],
            "director": "Anders Knutsson",
            "managing_director": "Anders Knutsson",
            "sales_manager": "Ola Knutsson"
        },
        "2": {
            "name": "Kocks Snickerifabriker AB.",
            "location": "Malmö",
            "business": "Möbelfabrik i Trelleborg. Tillverkar restaurantmöbler, inredningar för teatrar och biografer, skolmöbler samt rumsmöbler. Specialitet: möbler av böjt trä.",
            "contact": {
                "office": "Celsiusg. 41",
                "phone": [
                    "Ljungs Industrier"
                ]
            },
            "financials": {
                "capital": "100,000 kr",
                "employees": {
                    "industriarb": 60
                },
                "annual_production_value": "500,000 kr"
            },
            "foundation_year": 1917,
            "corporation_year": 1945,
            "board": [
                {
                    "name": "fabr. A. Efraim Ljung",
                    "role": ""
                },
                {
                    "name": "disp. A. Eric Ljung",
                    "role": ""
                },
                {
                    "name": "disp. S. Löfgren",
                    "role": ""
                }
            ],
            "director": "vakant"
        },
        "3": {
            "name": "Kockums Jernverks AB.",
            "location": "Kallinge",
            "business": "Järnverk med martinugnar, elektr. ugnar, valsverk, galvaniserings- och emal-jeringsverk, gjuteri och mek. verkstad",
            "products": "Tillverkar i Kallinge: martingöt, elek-trostålgöt, stålgjutgods, svart och galvaniserad järnplåt, dynamoplåt och träns formatorplåt, svart och emaljerat hushålls- och sanitetsgjutgods, maskinmang-lar. lyktstolpar, spiraltrappor, värmeledningspannor (märke: »Rego»), gasspisar, elektriska spisar, vedspisar (vanliga spisar, V-KOCK-spisar), restaurangspisar m. m. samt utför förnickling, förkrom-ning och plåtpressning.",
            "contact": {
                "office": "Malmö, Regementsg. 12",
                "phone": [
                    "21240"
                ],
                "sales_offices": [
                    {
                        "location": "Kallinge",
                        "phone": "»Jernverket»"
                    },
                    {
                        "location": "Ronneby",
                        "phone": "13"
                    },
                    {
                        "location": "Stockholm",
                        "phone": "520360"
                    },
                    {
                        "location": "Göteborg",
                        "phone": "131789"
                    },
                    {
                        "location": "Malmö",
                        "phone": "25524"
                    }
                ],
                "telegraph": "Jernverket, Kallinge"
            },
            "financials": {
                "capital": "4,000,000 kr",
                "employees": {
                    "industriarb": 1,
                    "'700": 19,
                    "'000,000 kr": 1,
                    "'900,000": 1
                }
            },
            "foundation_year": 1875,
            "board": [
                {
                    "name": "bankdir. Åke Belfrage",
                    "role": "ordf."
                },
                {
                    "name": "dir. Erik Kockum",
                    "role": "v. ordf."
                },
                {
                    "name": "dir.^ Frans Kockum",
                    "role": ""
                },
                {
                    "name": "ing. Gunnar Kockum",
                    "role": ""
                },
                {
                    "name": "disp. Uno O. Larson",
                    "role": ""
                },
                {
                    "name": "kapten J. H. Zethraeus",
                    "role": ""
                }
            ],
            "director": "Erik Kockum",
            "managing_director": "Erik Kockum"
        },
        "4": {
            "name": "Kockums Mekaniska Verkstads AB.",
            "location": "Malmö",
            "business": "Skeppsvarv, mekanisk verkstad, gjuteri, manufaktursmedja och vaggonfabrik",
            "products": "Tillverkar krigsfartyg av alla slag, handelsfartyg upp till 25,000 ton, dieselmotorer enligt Kockum-M. A. !N-.system resp. Kockum—Frichssystem, järnvägsvagnar, motorlokomotiv, motorvagnar, broar, lyftkranar, ångpannor och ångmaskiner hejar- och ånghammarsmiden samt »Tyfon»-signalapparater m. m.",
            "contact": {
                "office": "Stora Varvsg., Västra Hamnsidan",
                "phone": "Kockumsverkstad, Malmö",
                "postgiro": "38200"
            },
            "financials": {
                "capital": "7,500,000 kr",
                "employees": {
                    "industriarb": 3,
                    "'500": 60,
                    "'000,000 kr": 60,
                    "'000,000": 1
                }
            },
            "foundation_year": 1840,
            "corporation_year": 1866,
            "board": [
                {
                    "name": "bankdir. Ernst ö:son Herslow",
                    "role": "ordf."
                },
                {
                    "name": "dir. Erik Kockum",
                    "role": "v. ordf."
                }
            ],
            "director": "Erik Kockum"
        }
    }
}