{
    "original": "Norrlandslin—Norrte l je\n\nNorrlandslin u. p. a., Föreningen,\n\nMellansel.\n\nSe Föreningen Norrlandslin n. p. a.,\nMellansel.\n\n*AB. Norr/andsmöbler, Umeå.\n\nMöbel- och snickerifabrik i Norrfors\noch i Umeå (båda i Västerbott. l.).\n\n^ Tillverkar möbler, inredningar för\nbutiker, skolor, kaféer m. m. samt\nmonteringsfärdiga stugor.\n\nKontor: Umeå. Telefon: 438. Postgiro:\n64960.\n\nAkt.-kap.: 120,000 kr. Antal\nindustriarb.: 60. — Firman etabl. 1920 under\nnamn Norrfors Snickerifabrik, nuv.\nbolag 1945.\n\nStyrelse: verkm. William Persson, dir.\nA. Eberhard Rönnberg, verkm. Sixten\nSundström, fabr. Bo Wretling.\n\nVerkst. dir.: A. E. Rönnberg.\n\nNorrlands Vaddfabrik, Järbo.\n\nTillverkar täckvadd, limvadd,\ntät-ningslister, fönstervadd, frisörbomull\nsamt isoleringsvadd vid fabrik i Järbo\n(Gävleb. l.).\n\nTelefon: 19. Postgiro: 80088. Repr.:\nByggnadsmaterialaffären Göta AB.,\nStockholm, Järnvägsg. 16 o. Göteborg,\nKungsg. 34. — Arb.-antal: 6.\nTillv.-värde pr år: 100,000 kr. — Firman etabl.\n1902.\n\nÄgare o. chef: fabr. August Berggren.\n\nKontorschef: Rune Berggren.\n\n*AB. Norrländska Tråddrageriet,\n\nHudiksvall.\n\nTillverkar svart glödgad, hårddragen\noch glödgad förzinkad järntråd.\nVarumärke: »Tawi».\n\nTelegr.-adr.: Tråddrageriet,\nHudiksvall. Telefon: 916 o. 917. Postgiro: 47448.\nEnsamförsälj.^ Kjellberg &amp; Hedberg AB.,\nStockholm, Birger Jarlsg. 16; telefon:\n612162.\n\nAkt.-kap.: 25,000 kr. Arb.-antal: 12.\nTillv.-värde pr år: 1,000,000 kr. —\nFirman etabl. 1919, bolag 1942.\n\nStyrelse: disp. Rudolf SunstrÖm\n(ordf.), kanslisekr. Allan Tigerschiöld,\ndir. Folke Wilhelmson.\n\nDisp.: Marthel Byquist.\n\nAB. Norrmalms Gjuter! &amp; Mek.\nVerkstad, Borås.\n\nTillverkar maskiner och reservdelar\nför textilindustrien såsom elektriskt\ndrivna bomställ, syn- och tvistmaskiner,\n\nfärgerivagnar med hissanordning samt\nsom specialitet fjäderhammare (märke:\n»ABNO»).\n\nTelefon: 10393. Postgiro: 28577. —\nAkt.-kap.: 62,500 kr. Antal industriarb.;\n18. Tillv.-värde pr år: 280,000 kr. —\nFirman etabl. 1901, bolag 1918.\n\n’ Disp.: ing. Nils Bonander.\n\nNorrmalms Karosseri AB.,\n\nStockholm.\n\nSe Karosseri AB. Norrmalm,\nStockholm.\n\nNorrmalms Livsmedels AB.,\n\nStockholm.\n\nCharkuteri- och konservfabrik.\nTillverkar charkuterivaror samt köttkonserver.\nBolaget, som även idkar restaurant-,\nba-geri-, konditori- och partirörelse, driver\ndetaljhandel genom fjorton egna\nminutaffärer i Stockholm.\n\nKontor: Karlbergsvägen 77—81.\nTelegr.-adr.: Norrmalmbolaget, Stockholm..\nTelefon: »Norrmalms Livsmedel».\nPostgiro: 460.\n\nAkt.-kap.: 2,000,000 kr. Antal\nindustriarb.: 125.\n\nBolaget grundat 1895 under namn\nSlakteri AB. Norrmalm,\nnamnfÖrändring-1928.\n\nStyrelse: civiling. Gösta Olin (ordf.),\ndisp. Ernfrid Johansson, disp. Oskar\nOlin.\n\nVerkst. direktörer: Gösta Olin o. Oskar\nOlin.\n\n\"Norrsundets Ångsåg o. Sulfatfabrik,\n\nNorrsundet.\n\nSe Kopparfors AB., Ockelbo.\n\n\"AB. Norrtelje Förenade Verkstäder*\n\nNorrtälje.\n\nTillverkar snabbsvarvar samt\nmaskin-gradsaxar för elektr. drift med upp till\n2,5 m. skärlängd.\n\nTelegr.-adr.: Verkstäderna, Norrtälje.\nTelefon: 75. Postgiro: 96120. —\nAkt.-kap.: 100,000 kr. Antal industriarb.: 15.\nTillv.-värde pr år: 200,000 kr. — Firman\netabl. 1900, bolag 1942.\n\nStyrelse o. verkst. dir.: ing. Ragnar\nHolmén.\n\n\"Norrtelje Cjuteri, Greisz &amp; Söner,\n\nNorrtälje.\n\nGjuteri och mek. verkstad. Tillverkar\nhögeldhärdigt kromstål, gjutgods och\n\ni*",
    "structured": {
        "1": {
            "name": "AB. Norrlands möbler",
            "location": "Umeå",
            "business": "Möbel- och snickerifabrik",
            "products": "Tillverkar möbler, inredningar för butiker, skolor, kaféer m.m. samt monteringsfärdiga stugor.",
            "contact": {
                "office": "Umeå",
                "phone": [
                    "438"
                ],
                "postgiro": "64960"
            },
            "financials": {
                "capital": "120,000 kr",
                "employees": {
                    "industriarb": 60
                },
                "annual_turnover": "Not provided",
                "annual_production_value": "Not provided"
            },
            "foundation_year": 1920,
            "current_name_year": 1945,
            "board": [
                {
                    "name": "William Persson",
                    "role": "verkm."
                },
                {
                    "name": "A. Eberhard Rönnberg",
                    "role": "dir."
                },
                {
                    "name": "Sixten Sundström",
                    "role": "verkm."
                },
                {
                    "name": "Bo Wretling",
                    "role": "fabr."
                }
            ]
        },
        "2": {
            "name": "Norrlands Vaddfabrik",
            "location": "Järbo",
            "business": "Tillverkar täckvadd, limvadd, tät-ningslister, fönstervadd, frisörbomull samt isoleringsvadd",
            "contact": {
                "phone": [
                    "19"
                ],
                "postgiro": "80088",
                "sales_offices": [
                    {
                        "location": "Stockholm",
                        "phone": "Not provided"
                    },
                    {
                        "location": "Göteborg",
                        "phone": "Not provided"
                    }
                ]
            },
            "financials": {
                "annual_production_value": "100,000 kr"
            },
            "foundation_year": 1902,
            "director": "Not provided",
            "owners": [
                "fabr. August Berggren"
            ],
            "manager": "Rune Berggren"
        },
        "3": {
            "name": "AB. Norrländska Tråddrageriet",
            "location": "Hudiksvall",
            "business": "Tillverkar svart glödgad, hårddragen och glödgad förzinkad järntråd",
            "contact": {
                "telegraph": "Tråddrageriet, Hudiksvall",
                "phone": [
                    "916",
                    "917"
                ],
                "postgiro": "47448"
            },
            "financials": {
                "capital": "25,000 kr",
                "employees": {
                    "Arb.-antal": 12
                },
                "annual_turnover": "1,000,000 kr",
                "annual_production_value": "Not provided"
            },
            "foundation_year": 1919,
            "board": [
                {
                    "name": "Rudolf SunstrÖm",
                    "role": "disp."
                },
                {
                    "name": "Allan Tigerschiöld",
                    "role": "kanslisekr."
                },
                {
                    "name": "Folke Wilhelmson",
                    "role": "dir."
                },
                {
                    "name": "Marthel Byquist",
                    "role": "Disp."
                }
            ]
        },
        "4": {
            "name": "AB. Norrmalms Gjuter! & Mek. Verkstad",
            "location": "Borås",
            "business": "Tillverkar maskiner och reservdelar för textilindustrien",
            "products": "Elektriskt drivna bomställ, syn- och tvistmaskiner, färgerivagnar med hissanordning samt fjäderhammare (märke: »ABNO»)",
            "contact": {
                "phone": [
                    "10393"
                ],
                "postgiro": "28577"
            },
            "financials": {
                "capital": "62,500 kr",
                "employees": {
                    "industriarb": 18
                },
                "annual_turnover": "Not provided",
                "annual_production_value": "280,000 kr"
            },
            "foundation_year": 1901,
            "board": [
                {
                    "name": "Nils Bonander",
                    "role": "Disp."
                }
            ]
        },
        "5": {
            "name": "Norrmalms Karosseri AB.",
            "location": "Stockholm",
            "business": "Not provided"
        },
        "6": {
            "name": "Norrmalms Livsmedels AB.",
            "location": "Stockholm",
            "business": "Charkuteri- och konservfabrik",
            "products": "Tillverkar charkuterivaror samt köttkonserver, idkar även restaurant-, bageri-, konditori- och partirörelse, driver detaljhandel genom fjorton egna minutaffärer i Stockholm.",
            "contact": {
                "office": "Karlbergsvägen 77—81",
                "telegraph": "Norrmalmbolaget, Stockholm",
                "phone": [
                    "Not provided"
                ],
                "postgiro": "460"
            },
            "financials": {
                "capital": "2,000,000 kr",
                "employees": {
                    "industriarb": 125
                },
                "annual_turnover": "Not provided",
                "annual_production_value": "Not provided"
            },
            "foundation_year": 1895,
            "current_name_year": 1928,
            "board": [
                {
                    "name": "Gösta Olin",
                    "role": "civiling."
                },
                {
                    "name": "Ernfrid Johansson",
                    "role": "disp."
                },
                {
                    "name": "Oskar Olin",
                    "role": "disp."
                }
            ],
            "director": "Gösta Olin",
            "manager": "Oskar Olin"
        },
        "7": {
            "name": "Norrsundets Ångsåg o. Sulfatfabrik",
            "location": "Norrsundet",
            "business": "Se Kopparfors AB., Ockelbo."
        },
        "8": {
            "name": "AB. Norrtelje Förenade Verkstäder",
            "location": "Norrtälje",
            "business": "Tillverkar snabbsvarvar samt maskin-gradsaxar för elektr. drift med upp till 2,5 m. skärlängd",
            "contact": {
                "telegraph": "Verkstäderna, Norrtälje",
                "phone": [
                    "75"
                ],
                "postgiro": "96120"
            },
            "financials": {
                "capital": "100,000 kr",
                "employees": {
                    "industriarb": 15
                },
                "annual_turnover": "Not provided",
                "annual_production_value": "200,000 kr"
            },
            "foundation_year": 1900,
            "board": [
                {
                    "name": "Ragnar Holmén",
                    "role": "Verkst. dir."
                }
            ]
        },
        "9": {
            "name": "Norrtelje Gjuteri, Greisz & Söner",
            "location": "Norrtälje",
            "business": "Gjuteri och mek. verkstad",
            "products": "Tillverkar högeldhärdigt kromstål, gjutgods"
        }
    }
}