{
    "original": "Skånska\n\nAB. Skånska Dagbladet, Malmö.\n\nTidnings- och boktryckeri.\n\nHuvudkontor: österg. 11. Telegr.-adr.:\nDagbladet, Malmö. Telefon: »Skånska\nDagbladet». Postgiro: 24540.\n\nAkt.-kap.: 1,800,000 kr. Antal\nindustriarb.: 247. — Bolaget grundat 1899.\n\nVerkst. dir.: Carl Fr. Ljunggren.\n\nKamrer: Bengt Persson.\n\nT ryckeri förest.: Karl Lundstedt.\n\nSkånska Granit AB., 7iro?;?/.\n\nStenbrott i Boalt, Kräbbleboda,\nAxeltorp pr Hjärsås, Romeröd pr Glimåkra\noch Sibbhult (samtl. i Kristianst. l.).\nBryter och bearbetar svart och ljus granit till\ngravvårdar, monument och\nbyggnadsarbeten.\n\nKontor: Broby. Telegr.-adr.: Granit.\nBroby. Telefon: 1. Postgiro: 75780.\n\nAkt.-kap.: 150,000 kr. Antal\nindustriarb.: 70. — Bolaget grundat 1920,\nom-bildat 1926.\n\nStyrelse: åh. Ragnar Kindgren,\nbankdir. Erik Norrman, dir. Artur Persson.\n\nVerkst. dir.: vakant.\n\n\"Skånska Jutefabriks AB.,\n\nHälsingborg.\n\nSpinneri och väveri. Tillverkar\nvävnader, garn och säckar av jute och\npappersgarn (även pappersfodrade och\nasfalterade).\n\nTelegr.-adr.: Jutebolaget, Hälsingborg.\nTelefon: 10487, 12987 o. 19687. Postgiro:\n13907. Ensamförsalj.: Svenska\nJutefabrikernas Centralkontor, Halmstad, telefon:\n220 o. 765. Repr. i Stockholm: Svenska\nJutefabrikernas avd.-kontor, R. Hägertz\no. Sven Wallberg, Regeringsg. 39, telefon:\n110433 o. 200475.\n\nAkt.-kap.: 1,350,000 kr. Antal\nindustriarb.: 300. Tillv.-värde pr år: 3,600,000 kr.\n— Bolaget grundat 1896.\n\nStyrelse: disp. Henry Dunker (ordf.),\ndir. O. A. Wicander (v. ordf.), civiling.\nGösta Blum, dir. Kjell Hägglöf, dir. Hj.\nLeijon.\n\nDisp.: Hj. Leijon.\n\nDriftsing.: R. Melén.\n\n\"Skånska Kolbrytningsbolaget,\n\nHöganäs.\n\nSe Höganäs-Billesholms AB., Höganäs.\n\n\"AB. Skånska Konfektionsfabriken,\n\nMalmö.\n\nTillverkar damkappor, dräkter, jiggers\noch blazers.\n\nKontor: Maltgatarx 5. Telegr.-adr.:\nSkånekonfektion, Malmö. Telefon: 71690.\nPostgiro: 149528.\n\nAkt.-kap.: 80,000 kr. Antal\nindustriarb.: 65. Tillv.-värde pr år: 800,000 kr.\n\n—\tBolaget grundat 1925.\n\nStyrelse: adv. Tore Lindeli, dir. Harry\nMalmqvist.\n\nVerkst. dir.: Harry Malmqvist.\n\n\"Skånska Litografiska AB., Malmö.\n\nLitografisk anstalt, offsettryckeri,\nboktryckeri, kontorsbok- och kartongfabrik.\nTillverkar kontorsböcker, kuvert,\nkartonger m. m. samt utför litografiskt,\nbok-och duplikattryck.\n\nKontor: Engelbrektsg. 2. Telegr.-adr.:\nLitografiska, Malmö. Telefon: 71105.\nPostgiro: 38067.\n\nBolaget är anslutet till AB. Sveriges\nLitografiska Tryckerier, Stockholm. (Se\ndetta bolag.) ’\n\nStyrelse o. disp.: G. Trotzig.\n\nAB. Skånska Makadamfabriken,\n\nÅstorp.\n\nStenkrossanläggning i Åstorp\n(Kristianst. l.) samt siloanläggning i\nHälsingborg. Tillverkar makadam och filler.\n\nTelefon: 449. Postgfrö: 84050. —\nAkt.-kap.: 375,000 kr. Antal industriarb.: 50.\n\n—\tFirman etabl. 1903, bolag 1925.\nVerkst. dir.: F. R. Assarson.\nDisp.: Lennart Nyström.\n\n\"Skånska Marmor AB., Landskrona.\n\nBearbetar in- och utländsk marmor\nsamt kalksten för byggnads-, butiks- och\nmöbeländamål, instrumenttavlor m. m.\njämte granit för gravvårds- och\nbygg-nädsändamål.\n\nTelegr.-adr.: Marmorbolaget,\nLandskrona. Telefon: 695. Postgiro: 6816.\nAkt.-kap.: 100,000 kr. Arb.-antal: 10.\n\n—\tBolaget grundat 1897.\n\nStyrelse: major Bror Jepsson (ordf.),\ndir. Helge Helmers, fru L. Helmers.\nVerkst. dir.: Helge Helmers.\n\n\"AB. Skånska Spisbrödsfabriken,\n\nKristianstad.\n\nTillverkar spis-, knäcke- och\ndelikatess-bröd.\n\nTelegr.-adr.: Brödfabriken,\nKristianstad. Telefon: 10026,10507 o. 10660.\nPostgiro: 6855. Avd.-kontor: Malmö,\nVästkustvägen, telefon: 25667, 27665 o. 20293.\n\nAkt.-kap.: 200,000 kr. Antal\nindustriarb.: 125. Tillv.-värde pr år: 2,000,000 kr.\n\n•x-",
    "structured": {
        "1": {
            "name": "AB. Skånska Dagbladet",
            "location": "Malmö",
            "business": "Tidnings- och boktryckeri",
            "contact": {
                "office": "österg. 11",
                "phone": [
                    "Skånska Dagbladet"
                ],
                "postgiro": "24540",
                "telegraph": "Dagbladet, Malmö"
            },
            "financials": {
                "capital": "1,800,000 kr",
                "employees": {
                    "industriarb": 247
                }
            },
            "foundation_year": 1899,
            "board": [
                {
                    "name": "Carl Fr. Ljunggren",
                    "role": "Verkst. dir."
                },
                {
                    "name": "Bengt Persson",
                    "role": "Kamrer"
                },
                {
                    "name": "Karl Lundstedt",
                    "role": "T ryckeri förest."
                }
            ],
            "director": "Carl Fr. Ljunggren"
        },
        "2": {
            "name": "Skånska Granit AB.",
            "business": "Bryter och bearbetar svart och ljus granit till gravvårdar, monument och byggnadsarbeten",
            "location": "Broby",
            "contact": {
                "office": "Broby",
                "phone": [
                    "1"
                ],
                "postgiro": "75780",
                "telegraph": "Granit. Broby"
            },
            "financials": {
                "capital": "150,000 kr",
                "employees": {
                    "industriarb": 70
                }
            },
            "foundation_year": 1920,
            "board": [
                {
                    "name": "Ragnar Kindgren",
                    "role": "åh."
                },
                {
                    "name": "Erik Norrman",
                    "role": "bankdir."
                },
                {
                    "name": "Artur Persson",
                    "role": "dir."
                }
            ]
        },
        "3": {
            "name": "Skånska Jutefabriks AB.",
            "business": "Spinneri och väveri. Tillverkar vävnader, garn och säckar av jute och pappersgarn (även pappersfodrade och asfalterade)",
            "location": "Hälsingborg",
            "contact": {
                "office": "Jutebolaget, Hälsingborg",
                "phone": [
                    "10487",
                    "12987",
                    "19687"
                ],
                "postgiro": "13907",
                "sales_offices": [
                    {
                        "location": "Svenska Jutefabrikernas Centralkontor, Halmstad",
                        "phone": "220 o. 765"
                    },
                    {
                        "location": "Svenska Jutefabrikernas avd.-kontor, R. Hägertz o. Sven Wallberg, Regeringsg. 39, Stockholm",
                        "phone": "110433 o. 200475"
                    }
                ]
            },
            "financials": {
                "capital": "1,350,000 kr",
                "employees": {
                    "industriarb": 300
                },
                "annual_turnover": "3,600,000 kr"
            },
            "foundation_year": 1896,
            "board": [
                {
                    "name": "Henry Dunker",
                    "role": "disp."
                },
                {
                    "name": "O. A. Wicander",
                    "role": "dir."
                },
                {
                    "name": "Gösta Blum",
                    "role": "civiling."
                },
                {
                    "name": "Kjell Hägglöf",
                    "role": "dir."
                },
                {
                    "name": "Hj. Leijon",
                    "role": "disp."
                }
            ],
            "director": "Hj. Leijon",
            "sales_manager": "R. Melén"
        },
        "4": {
            "name": "Skånska Konfektionsfabriken",
            "business": "Tillverkar damkappor, dräkter, jiggers och blazers",
            "location": "Malmö",
            "contact": {
                "office": "Maltgatarx 5",
                "phone": [
                    "71690"
                ],
                "postgiro": "149528",
                "telegraph": "Skånekonfektion, Malmö"
            },
            "financials": {
                "capital": "80,000 kr",
                "employees": {
                    "industriarb": 65
                },
                "annual_production_value": "800,000 kr"
            },
            "foundation_year": 1925,
            "board": [
                {
                    "name": "Tore Lindeli",
                    "role": "adv."
                },
                {
                    "name": "Harry Malmqvist",
                    "role": "dir."
                }
            ],
            "director": "Harry Malmqvist"
        },
        "5": {
            "name": "Skånska Litografiska AB.",
            "business": "Litografisk anstalt, offsettryckeri, boktryckeri, kontorsbok- och kartongfabrik. Tillverkar kontorsböcker, kuvert, kartonger m. m. samt utför litografiskt, bok- och duplikattryck",
            "location": "Malmö",
            "contact": {
                "office": "Engelbrektsg. 2",
                "phone": [
                    "71105"
                ],
                "postgiro": "38067",
                "telegraph": "Litografiska, Malmö"
            },
            "financials": {
                "annual_production_value": "Se AB. Sveriges Litografiska Tryckerier, Stockholm (Se detta bolag)"
            },
            "board": [
                {
                    "name": "G. Trotzig"
                }
            ]
        },
        "6": {
            "name": "Skånska Makadamfabriken",
            "location": "Åstorp",
            "business": "Tillverkar makadam och filler",
            "contact": {
                "phone": [
                    "449"
                ],
                "postgiro": "84050"
            },
            "financials": {
                "capital": "375,000 kr",
                "employees": {
                    "industriarb": 50
                }
            }
        },
        "7": {
            "name": "Skånska Marmor AB.",
            "location": "Landskrona",
            "business": "Bearbetar in- och utländsk marmor samt kalksten för byggnads-, butiks- och möbeländamål, instrumenttavlor m. m. jämte granit för gravvårds- och byggnadsändamål",
            "contact": {
                "phone": [
                    "695"
                ],
                "postgiro": "6816"
            },
            "financials": {
                "capital": "100,000 kr",
                "employees": {
                    "arb": 10
                }
            },
            "foundation_year": 1897,
            "board": [
                {
                    "name": "major Bror Jepsson"
                },
                {
                    "name": "Helge Helmers",
                    "role": "dir."
                },
                {
                    "name": "L. Helmers",
                    "role": "fru"
                }
            ],
            "director": "Helge Helmers"
        },
        "8": {
            "name": "Skånska Spisbrödsfabriken",
            "location": "Kristianstad",
            "business": "Tillverkar spis-, knäcke- och delikatess-bröd",
            "contact": {
                "office": "Brödfabriken, Kristianstad",
                "phone": [
                    "10026",
                    "10507",
                    "10660"
                ],
                "postgiro": "6855",
                "sales_offices": [
                    {
                        "location": "Malmö",
                        "phone": "25667, 27665 o. 20293"
                    }
                ]
            },
            "financials": {
                "capital": "200,000 kr",
                "employees": {
                    "industriarb": 125
                },
                "annual_production_value": "2,000,000 kr"
            }
        }
    }
}