{
    "original": "Isa—Isoflex\n\nIsa Makaronifabriks AB., Gävle.\n\nTillverkar makaroner. Varumärke:\n»Isa Makaroner».\n\nTelefon: 3525. Postgiro: 79631. —\nAkt.-kap.: 50,000 kr. Antal industriarb.:\n6. Tillv.-värde pr år: 180,000 kr. —\nBolaget, grundat 1932, är dotterbolag till\nIsaac Westergren &amp; Co. AB., Gävle.\n\nStyrelse: dir. Yngve Lidén (ordf.),\nköpm. Fridolf Meurling.\n\nVerkst. dir.: Y. Lidén.\n\nFabrikschef: Bertil Jönsson.\n\nAB. Isacsons Emballagefabrik,\n\nGöteborg.\n\nTillverkar pappemballage och\nkartonger vid wellpapp- och kartonagefabrik\ni Brännögård (Hallands l.).\n\nHuvudkontor: Göteborg, Post g. 3 B.\nTelefon: 117598. Fabrikskontor:\nBrännögård; telefon: Kinnared 40. Postgiro:\n99391.\n\nAkt.-kap.: 250,000 kr. Antal\nindustriarb.: 110. Tillv.-värde pr år: 3,000,000 kr.\n\n—\tBolaget grundat 1934.\n\nStyrelse o. direktion: Folke Isacson o.\nWigge Isacson.\n\nAB. C. C. Isaksson &amp; Co., Ilabo.\n\nJärn- och metallvarufabrik i Habo\n(Skarab. l.). Tillverkar massartiklar i\njärn och metall, speciellt byggnadssmiden.\n\nTelefon: 78 o. 98. Postgiro: 29037. —\nAkt.-kap.: 100,400 kr. Antal industriarb.:\n60. Tillv.-värde pr år: 1,300,000 kr. —\nFirman etabl. 1921, bolag 1944.\n\nVerkst. dir.: fabr. C. G. Isaksson.\n\nFabrikschef: Sture Isaksson.\n\nFörsäljn.-chef: Åke Isaksson.\n\nKamrer: A. Wiebert.\n\n(Jfr annons nr 91.)\n\n*AB, J. Isaksson &amp; Co.,\nKassaskåpsfabrik, Stockholm.\n\nKassaskåpsfabrik i Ulvsunda\n(Stockholm). Tillverkar kassaskåp,\npansardörrar. kassavalvs-, arkiv-, kylrums- och\nbranddörrar, gasskyddsdörrar,\ninredningar för kassavalv, arkiv och bibliotek,\ndokumentskåp, klädskåp, stålmöbler,\ndörr-och fönsterkarmar, nyckellås, vertikalfack\noch kortregisterskåp, kassakistor och skrin,\npostboxar m. m.\n\nKontor: Ulvsunda. Telegr.-adr.:\nIsakssonfabrik, Stockholm. Telefon: 256480 o.\n256500. Postgiro: 3965.\n\nAkt.-kap.: 185,000 kr. Antal\nindustriarb.: 55. Tillv.-värde pr år: 900,000 kr.\n\n—\tFabriken etabl. 1867, bolag 1925.\n\nStyrelse: fabr. Albin Isaksson, disp.\nGunnar Klingvall.\n\nVerkst. dir.: Albin Isaksson.\nKamrer: Hilmer Berghagen.\n\nOscar Isacsons Boktryckeri AB.,\n\nGöteborg.\n\nUtför boktryck, affärs- och\nreklam-tryck, teckningar och klichéer, litografi,\noffsettryck samt bokbindning.\n\nKontor: Postg. 3 B. Telefon: 110433,\n117598 o. 117502. Postgiro: 12106. —\nAkt.-kap.: 200,000 kr. Antal\nindustriarb.: 95. Tillv.-värde pr år: 900,000 kr.\n\n—\tFirman etabl. 1903, bolag 1929.\nStyrelse o. direktion: Folke Isacson o.\n\nWigge Isacson.\n\nIsacsönerna, Fabriks AB.,\n\nMalmbäck.\n\nSe Fabriks AB. Isacsönerna,\nMalmbäck.\n\nA. Isberg &amp; Son, Norrköping.\n\nKontorsbokfabrik och bokbinderi.\nTillverkar kontorsböcker, hängmappar,\nlösblad ssystem, ringböcker, kart- och\ncellu-loidfodral samt kortsystem. Varumärken:\n»Ais» o. »Multi-Rand».\n\nTelegr.-adr.: Isbergetson, Norrköping.\nTelefon: 29090. Postgiro: 22288. —\nAntal industriarb.: 60. Tillv.-värde pr år:\n800,000 kr. — Firman etabl. 1892.\n\nÄgare o. chef: bokbindarmäst. Nils\nIsberg.\n\nAB. Isocorpa, Hälsingborg.\n\nTillverkar träullsplattor för isolering\nmot värme, kyla och ljud vid fabriker i\nHälsingborg och i Örebro. Varumärke:\n»Ecolith».\n\nKontor o. ensamförsälj.: Evers &amp; Co.\nAB., Hälsingborg, telefon: »Evers &amp; Co.»\n\n—\tAkt.-kap.: 50,000 kr. Antal\nindustriarb.: 40. Tillv.-värde pr år: 700,000 kr.\n\n—\tBolaget grundat 1944.\nDisp.: Karl Killgren.\n\nAB» Isoflex, Stockholm.\n\nTillverkar isoleringsplattor för kyla\noch värme samt fönsterisolering.\n\nTelegr.-adr.: Isoflex, Stockholm.\nKontor: Magnus Ladulåsg. 11. Telefon:\n400150 o. 435521. Postgiro: 156685.\n\nAkt.-kap.: 100,000 kr. Antal\nindustriarb.: 25. Tillv.-värde pr år: 500,000 kr.\n\n—\tBolaget, grundat 1936, äges av\nKooperativa Förbundet. ^\n\nStyrelse: dir. Albin Johansson.\nChef: Thore M. Elfving.",
    "structured": {
        "1": {
            "name": "Isa Makaronifabriks AB",
            "location": "Gävle",
            "business": "Tillverkar makaroner",
            "products": "Varumärke: Isa Makaroner",
            "contact": {
                "office": "Gävle",
                "phone": [
                    "3525"
                ],
                "postgiro": "79631"
            },
            "financials": {
                "capital": "50,000 kr",
                "employees": {
                    "industriarb": 6
                },
                "annual_turnover": "180,000 kr"
            },
            "foundation_year": 1932,
            "predecessor": "Isaac Westergren & Co. AB",
            "board": [
                {
                    "name": "Yngve Lidén",
                    "role": "ordf."
                },
                {
                    "name": "Fridolf Meurling",
                    "role": "köpm."
                }
            ],
            "director": "Y. Lidén",
            "managing_director": "Y. Lidén",
            "sales_manager": "Bertil Jönsson"
        },
        "2": {
            "name": "AB Isacsons Emballagefabrik",
            "location": "Göteborg",
            "business": "Tillverkar pappemballage och kartonger",
            "contact": {
                "office": "Göteborg",
                "phone": [
                    "117598"
                ],
                "postgiro": "99391",
                "sales_offices": [
                    {
                        "location": "Brännögård",
                        "phone": "Kinnared 40"
                    }
                ]
            },
            "financials": {
                "capital": "250,000 kr",
                "employees": {
                    "industriarb": 110
                },
                "annual_turnover": "3,000,000 kr"
            },
            "foundation_year": 1934,
            "board": [
                {
                    "name": "Folke Isacson",
                    "role": "Styrelse o. direktion"
                },
                {
                    "name": "Wigge Isacson",
                    "role": "Styrelse o. direktion"
                }
            ]
        },
        "3": {
            "name": "AB C. C. Isaksson & Co.",
            "location": "Ilabo",
            "business": "Järn- och metallvarufabrik",
            "contact": {
                "office": "Habo (Skarab. l.)",
                "phone": [
                    "78",
                    "98"
                ],
                "postgiro": "29037"
            },
            "financials": {
                "capital": "100,400 kr",
                "employees": {
                    "industriarb": 60
                },
                "annual_turnover": "1,300,000 kr"
            },
            "foundation_year": 1921,
            "corporation_year": 1944,
            "director": "C. G. Isaksson",
            "sales_manager": "Åke Isaksson",
            "manager": "A. Wiebert"
        },
        "4": {
            "name": "AB J. Isaksson & Co.",
            "location": "Stockholm",
            "business": "Kassaskåpsfabrik",
            "contact": {
                "office": "Ulvsunda (Stockholm)",
                "phone": [
                    "256480",
                    "256500"
                ],
                "postgiro": "3965"
            },
            "financials": {
                "capital": "185,000 kr",
                "employees": {
                    "industriarb": 55
                },
                "annual_turnover": "900,000 kr"
            },
            "foundation_year": 1867,
            "corporation_year": 1925,
            "board": [
                {
                    "name": "Albin Isaksson",
                    "role": "Styrelse"
                },
                {
                    "name": "Gunnar Klingvall",
                    "role": "disp."
                }
            ],
            "director": "Albin Isaksson",
            "manager": "Hilmer Berghagen"
        },
        "5": {
            "name": "Oscar Isacsons Boktryckeri AB",
            "location": "Göteborg",
            "business": "Utför boktryck, affärs- och reklam-tryck",
            "contact": {
                "office": "Göteborg",
                "phone": [
                    "110433",
                    "117598",
                    "117502"
                ],
                "postgiro": "12106"
            },
            "financials": {
                "capital": "200,000 kr",
                "employees": {
                    "industriarb": 95
                },
                "annual_turnover": "900,000 kr"
            },
            "foundation_year": 1903,
            "corporation_year": 1929,
            "board": [
                {
                    "name": "Folke Isacson",
                    "role": "Styrelse"
                },
                {
                    "name": "Wigge Isacson",
                    "role": "Styrelse"
                }
            ]
        },
        "6": {
            "name": "A. Isberg & Son",
            "location": "Norrköping",
            "business": "Kontorsbokfabrik och bokbinderi",
            "contact": {
                "office": "Norrköping",
                "phone": [
                    "29090"
                ],
                "postgiro": "22288"
            },
            "financials": {
                "employees": {
                    "industriarb": 60
                },
                "annual_turnover": "800,000 kr"
            },
            "foundation_year": 1892,
            "director": "Nils Isberg"
        },
        "7": {
            "name": "AB Isocorpa",
            "location": "Hälsingborg",
            "business": "Tillverkar träullsplattor för isolering mot värme, kyla och ljud",
            "contact": {
                "office": "Hälsingborg"
            },
            "financials": {
                "capital": "50,000 kr",
                "employees": {
                    "industriarb": 40
                },
                "annual_turnover": "700,000 kr"
            },
            "foundation_year": 1944,
            "director": "Karl Killgren"
        },
        "8": {
            "name": "AB Isoflex",
            "location": "Stockholm",
            "business": "Tillverkar isoleringsplattor för kyla och värme samt fönsterisolering",
            "contact": {
                "office": "Magnus Ladulåsg. 11",
                "phone": [
                    "400150",
                    "435521"
                ],
                "postgiro": "156685"
            },
            "financials": {
                "capital": "100,000 kr",
                "employees": {
                    "industriarb": 25
                },
                "annual_turnover": "500,000 kr"
            },
            "foundation_year": 1936,
            "owners": [
                "Kooperativa Förbundet"
            ],
            "board": [
                {
                    "name": "Albin Johansson",
                    "role": "Styrelse"
                }
            ],
            "manager": "Thore M. Elfving"
        }
    }
}