{
    "original": "Kraft-—Kramfors\n\nStyrelse: dir. Gustaf Th. Karlson\n(ordf.), dir. Gustaf Kähr, dir. Eric Åfors.\n\nVerkst. dir.: Eric Åfors (Emmaboda).\n\nPlatschef: civiling. Lennart Rosén.\n\nKamrer: Folke Rosengren,\n\n\"Kraft AB. Gullspång-Munkfors,\n\nMariestad.\n\nElektr. vattenkraftstationer vid\nGull-spång (Skarab. l.) och vid Åtorp (f. d.\nMunkfors) (Örebro l.) jämte vattenfall\nvid År ås i Gullspångs älven och vid\nMo-holm/i Tidan samt anläggningar för\ndistribution av elektr. kraft inom\nSkaraborgs, Värmlands och Örebro län.\n\nTelefon: 220, 221 o. 331. Postgiro:\n29300.\n\nAkt.-kap.: 10,055,000 kr. Distrib.-värde\npr år: 4,700,000 kr.\n\nBolaget, som grundades 1906, äger\nÖrebro Elektr. ABV, Örebro, och Gullspångs\nElektrokemiska AB., Gullspång.\n\nStyrelse: disp. John Hedin (ordf.),\nköpm. E. W. Bergwik, disp. Tore Hedin,\ndisp. Richard Hedlund, kammarh. Erland\nv. Hofsten, frih. Wilh. Klingspor,\nriks-dagsm. Folke Kyling, f. kapten C.\nSandels, disp. H. Seb. Tham.\n\nVerkst. dir.: Tore Hedin.\n\nDisp.: Gösta Grenstadius.\n\nAB. Kraftbox, Näsviken.\n\nKartongfabrik vid Näs viken (Gävleb. l.).\nTillverkar pappkartonger för\nytterem-ballage.\n\nTelefon: 7. Postgiro: 83796. —\nAkt.-kap.: 80,400 kr. Antal industriarb.: 45.\n— Bolaget grundat 1925.\n\nStyrelse: disp. P. B. Burchardt,\nhemmansäg. Anders Larsson, dir. Verner\nPehrzon.\n\nDriftsing.: Lars Bovin.\n\n*AB. Kraftemballage, Stockholm,\n\nWellpapp- och kartongfabrik samt mek.\nverkstad i Norrköping. Tillverkar\nwellpapp, wellpappkartonger och\nwellpapp-emballage, kartonger av solid board samt\nmaskiner för wellpappfabriker.\n\nHuvudkontor: Stockholm,\nBlasieholms-torg 11. Telegr.-adr.: Kraftemballage,\nStockholm. Telefon: 107247 o. 115505.\nPostgiro: 52616. Fabrikskontor:\nNorrköping, telefon: 23888 o. 26388.\n\nRepresentanter: i Göteborg: Nordström\n&amp; Tinggren, S. Larmg. 4, telefon:\n»Nordström o, Tinggren»; i Malmö: AB.\nEkenberg &amp; Huldberg, telefon: »Ekenberg o.\nHuldberg».\n\n20\n\nAkt.-kap.; 225,000 kr. Antal\nindustriarb.: 125. Tillv.-värde pr år; 4,700,000 kr.\n-— Bolaget grundat 1930.\n\nStyrelse: civiling. Karl A. Wessblad\n(ordf.), civiling. Alvar Lenning, disp.\nSigurd Lind, civiling. Harry Nyström,\ndisp. Erik Sundén.\n\nVerkst. dir.: Erik Sundén.\n\nKrag- och Skjortfabriken, Svenska,\n\nLinköping.\n\nSe Svenska Krag- och Skjortfabriken,\nLinköping.\n\nAnders Krahner Industrifirma,\n\nSkillingaryd.\n\nMöbelfabrik i Skillingaryd (Jönköp. l.).\nTillverkar arbetsstolar för industrier och\nkontor.\n\nTelefon: 213 o. 20. Postgiro: 91665. —\nAntal industriarb.: 18. — Firman, etabl.\n1934, äger Småländska Industriprodukter\nAB., Skillingaryd.\n\nÄgare o. clief: dir. Anders Krahner.\n\n’\"Kramfors AB., Kramfors.\n\nSågverk med hyvleri, sulfit- och\nsulfitspritfabrik, fiberplattfabrik och\nträhus-fabrik i Kramfors, sulfatfabrik i Frånö\n(samtl. i Västernorrl. l.).\n\nTillverkar sågade och hyvlade trävaror,\nmonteringsfärdiga trähus, sulfit- och\nsulfatcellulosa, fiberplattor, sulfitsprit,\nflytande harts och terpentin. Bolaget idkar\njämväl skogsbruk.\n\nHuvudkontor: Kramfors. Telegr.-adr.:\nKramforsco, Kramfors. Telefon: 2000.\nPostgiro: 5110.\n\nFörsäljn.-kontor: för trävaror:\nKramfors; för fiberplattor (Kramforsplattan):\nKramfors med serviskontor i Stockholm,\nV. Trädgårdsg. 15.\n\nEnsamförsälj.: för cellulosa: Svenska\nCellulosa AB., Stockholm, V. Trädgårdsg.\n15, telefon: »Cellulosabolaget»; för\nträhus: AB. Svenska Trähus, Stockholm,\nBirger Jarlsg. 27, telefon: »Svenska\nTrähus».\n\nAkt.-kap.: 25,000,000 kr. Antal\nindustriarb.: 1,800. Årskapacitet: 20,000 stds\nsågade o. hyvlade trävaror, 72,000 ton\nsulfitcellulosa, 30,000 ton sulfatcellulosa,\n5,500,000 1. sulfitsprit, 1,200 ton flytande\nharts, 250 ton terpentin, 600 st. hus,\n30,000 m3 porösa samt 20,000 ton hårda\nfiberplattor.\n\nBolaget grundat 1886. Aktiemajoriteten\ni bolaget innehaves av Svenska Cellulosa\nAB.",
    "structured": {
        "firms": [
            {
                "name": "Kraft AB",
                "location": "Gullspång-Munkfors, Mariestad",
                "business": "Elektr. vattenkraftstationer",
                "products": "Elektr. vattenkraftstationer vid Gull-spång (Skarab. l.) och vid Åtorp (f. d. Munkfors) (Örebro l.) jämte vattenfall vid År ås i Gullspångs älven och vid Mo-holm/i Tidan samt anläggningar för distribution av elektr. kraft inom Skaraborgs, Värmlands och Örebro län.",
                "contact": {
                    "office": "Gullspång-Munkfors, Mariestad",
                    "phone": [
                        "220",
                        "221",
                        "331"
                    ],
                    "postgiro": "29300"
                },
                "financials": {
                    "capital": "10,055,000 kr",
                    "annual_turnover": "4,700,000 kr"
                },
                "foundation_year": 1906,
                "owners": [
                    "Örebro Elektr. ABV",
                    "Gullspångs Elektrokemiska AB"
                ],
                "board": [
                    {
                        "name": "John Hedin",
                        "role": "disp."
                    },
                    {
                        "name": "E. W. Bergwik",
                        "role": "köpm."
                    },
                    {
                        "name": "Tore Hedin",
                        "role": "disp."
                    },
                    {
                        "name": "Richard Hedlund",
                        "role": "disp."
                    },
                    {
                        "name": "Erland v. Hofsten",
                        "role": "kammarh."
                    },
                    {
                        "name": "Wilh. Klingspor",
                        "role": "frih."
                    },
                    {
                        "name": "Folke Kyling",
                        "role": "riksdagsm."
                    },
                    {
                        "name": "C. Sandels",
                        "role": "f. kapten"
                    },
                    {
                        "name": "H. Seb. Tham",
                        "role": "disp."
                    }
                ],
                "director": "Eric Åfors",
                "managing_director": "Tore Hedin",
                "sales_manager": "Gösta Grenstadius"
            },
            {
                "name": "Kraftbox AB",
                "location": "Näsviken",
                "business": "Kartongfabrik",
                "products": "Tillverkar pappkartonger för ytterem-ballage.",
                "contact": {
                    "office": "Näsviken",
                    "phone": [
                        "7"
                    ],
                    "postgiro": "83796"
                },
                "financials": {
                    "capital": "80,400 kr"
                },
                "board": [
                    {
                        "name": "P. B. Burchardt",
                        "role": "disp."
                    },
                    {
                        "name": "Anders Larsson",
                        "role": "hemmansäg."
                    },
                    {
                        "name": "Verner Pehrzon",
                        "role": "dir."
                    }
                ],
                "manager": "Lars Bovin"
            },
            {
                "name": "Kraftemballage AB",
                "location": "Stockholm, Norrköping",
                "business": "Wellpapp- och kartongfabrik samt mek. verkstad",
                "products": "Tillverkar wellpapp, wellpappkartonger och wellpapp-emballage, kartonger av solid board samt maskiner för wellpappfabriker.",
                "contact": {
                    "office": "Stockholm, Blasieholmstorg 11",
                    "phone": [
                        "107247",
                        "115505"
                    ],
                    "postgiro": "52616",
                    "factory_office": "Norrköping",
                    "factory_phone": "23888"
                },
                "financials": {
                    "capital": "225,000 kr"
                },
                "board": [
                    {
                        "name": "Karl A. Wessblad",
                        "role": "civiling."
                    },
                    {
                        "name": "Alvar Lenning",
                        "role": "civiling."
                    },
                    {
                        "name": "Sigurd Lind",
                        "role": "disp."
                    },
                    {
                        "name": "Harry Nyström",
                        "role": "civiling."
                    },
                    {
                        "name": "Erik Sundén",
                        "role": "disp."
                    }
                ],
                "managing_director": "Erik Sundén"
            },
            {
                "name": "Anders Krahner Industrifirma",
                "location": "Skillingaryd",
                "business": "Möbelfabrik",
                "products": "Tillverkar arbetsstolar för industrier och kontor.",
                "contact": {
                    "office": "Skillingaryd",
                    "phone": [
                        "213",
                        "20"
                    ],
                    "postgiro": "91665"
                },
                "owner": "Anders Krahner"
            },
            {
                "name": "Kramfors AB",
                "location": "Kramfors",
                "business": "Sågverk med hyvleri, sulfit- och sulfitspritfabrik, fiberplattfabrik och trähus-fabrik",
                "products": "Tillverkar sågade och hyvlade trävaror, monteringsfärdiga trähus, sulfit- och sulfatcellulosa, fiberplattor, sulfitsprit, flytande harts och terpentin. Bolaget idkar jämväl skogsbruk.",
                "contact": {
                    "office": "Kramfors",
                    "phone": [
                        "2000"
                    ],
                    "postgiro": "5110",
                    "sales_offices": [
                        {
                            "location": "Kramfors",
                            "phone": "2000"
                        },
                        {
                            "location": "Stockholm",
                            "phone": "V. Trädgårdsg. 15"
                        }
                    ]
                },
                "financials": {
                    "capital": "25,000,000 kr"
                },
                "owners": [
                    "Svenska Cellulosa AB"
                ]
            }
        ]
    }
}