{
    "original": "Hoffman—Holma\n\nAkt.-kap.: 152,700 kr. Antal\nindustriarb.: 15. — Firman etabl. 1913, bolag\n1934.\n\nVerkst. dir.: fru Elma Hoffman.\n\nV. verkst. dir.: disp. Bo Hoffman.\n\nDisp.: Nils R:son Hoffman.\n\nAug. Hoffmans Pianofabriks AB.,\n\n- Stockholm.\n\nTillverkar pianinon.\n\nKontor: Malmskillnadsg. 46.\nTelegr.-adr.: Pianohoffman, Stockholm. Telefon:\n201606. Postgiro: 50006.\n\nAkt.-kap.: 250,000 kr. Antal\nindustriarb.: 20. Tillv.-värde pr år: 200,000 kr.\n— Firman etabl. 1832, bolag 1923.\n\nStyrelse: bankdir. Rich. Julin (ordf.),\nmusikhandl. Emil Carelius, fru B.\nMöller-Skoglund, kapten Edv. Schneidler, dir.\nAlbrekt Werner.\n\nVerkst. dir.: fru B. Möller-Skoglund.\n\n\"Einar Hoffmans Stolfabrik, Tibro.\n\nTillverkar stolar i olika stilar och\nträslag vid fabrik i Tibro (Skarab. l.).\n\nTelefon: 177. Postgiro: 15086. —\nArb.-antal: 10. Tillv.-värde pr år: 125,000 kr.\n— Firman etabl. 1920.\n\nÄgare o. chef: snickarna Einar\nHoffman.\n\n*Hj. Hofgrens AB., Örebro.\n\nTillverkar fiskredskap såsom revar och\nlinor. Varumärken: »Big Pike»,\n»Alaska» o. »Hofgrens».\n\nTelefon: »Lindmark &amp; Nilsson».\nPostgiro: 14292. — Akt.-kap.: 30,000 kr.\nArb.-antal: 10. — Bolaget grundat 1939.\n\nStyrelse: dir. Ivar Lindmark (ordf.),\nfabr. Artur Hofgren, dir. Birger\nLindmark.\n\nVerkst. dir.: Birger Lindmark.\n\n\"Hofors Bruk, Hofors.\n\nSe AB. Svenska Kullagerfabriken,\nHo-fors Bruk, Hofors.\n\nHofvids Trävaru AB., Sundsvall.\n\nSe Ankarsviks Ångsågs AB.,\nSundsvall.\n\nHofving &amp; Myrberg, Grafiska AB.,\n\nStockholm.\n\nSe Grafiska AB. Hofving &amp; Myrberg,\nStockholm.\n\n\"Hohults Snickerifabrik,\n\nHohultslätt.\n\nSnickeri och träförädlingsfabrik i\nHohultslätt (Kronob. l.). Tillverkar sågade\noch hyvlade trävaror samt tvättbräden\nsåväl helt av trä som med zinkplåt.\n\nTelegr.-adr.: Hohult, Kalmar. Telefon:\n3 o. 84. Postgiro: 82580. — Antal\nindustriarb.: 25. Tillv.-värde pr år: 460,000\nkr. — Firman grundad 1898.\n\nÄgare o. chef: disp. Simeon Weidow.\n\n\"Hohult-Spexeryds Mangangruvor,\n\nTenhult.\n\nSe Wargöns AB., Vargön.\n\nAB. Hohultslätts Spegelindustri,\n\nHohultslätt.\n\nTillverkar speglar och\nkompletteringsmöbler vid fabrik i Hohultslätt\n(Kronob. l.).\n\nTelefon: 45. Postgiro: 99494. —\nAkt.-kap.: 48,200 kr. Antal industriarb.: 45.\n— Bolaget grundat 1936.\n\nDisp.: Eric Wall.\n\nAB. Hollner &amp; Hultquist,\n\nStallarholmen.\n\nKartongfabrik och tryckeri i\nStallarholmen (Södermanl. l.). Tillverkar\nkartonger, kapslar samt spel och pussel m. m.\n\nTelefon: 19. Postgiro: 98486. —\nAkt.-kap.: 25,400 kr. Antal industriarb.: 30.\nTillv.-värde pr år: 350,000 kr. — Firman\netabl. 1935, bolag 1944.\n\nVerkst. dir.: fabr. William Hollner.\n\nHolm AB., Bröderna, Ransta.\n\nSe Bröderna Holm AB., Ransta.\n\nHolm &amp; Hoppe, Stockholm.\n\nSe Mepe, Holm &amp; Hoppe, Stockholm.\n\n*Holma-Helsinglands Linspinneri- &amp;\n\nVäfveri AB., Sörforsa och\n\nMadängsholm.\n\nLinspinneri och blekeri i Sörforsa\n(Gävleb. l.), samt linneväven och blekeri\ni Holma, Madängsholm (Skarab. l.).\n\nTillverkar i Sörforsa: lin- och\ntovgarner, fiskredskapsgarn, lintråd,\nknyppelgarner, sadelmakeri- och skogarn,\nseaminggarn, skotråd, nåtlingstråd,\njac-quardsnören, handhäfttråd, metrevar,\ndraglinor och simpelkort; i Holma:",
    "structured": {
        "1": {
            "name": "Aug. Hoffmans Pianofabriks AB.",
            "location": "Stockholm",
            "business": "Tillverkar pianinon",
            "contact": {
                "office": "Malmskillnadsg. 46",
                "phone": [
                    "201606"
                ],
                "postgiro": "50006",
                "telegraph": "Pianohoffman, Stockholm"
            },
            "financials": {
                "capital": "250,000 kr",
                "annual_production_value": "200,000 kr"
            },
            "foundation_year": 1832,
            "corporation_year": 1923,
            "director": "fru Elma Hoffman",
            "owners": [
                "Nils R:son Hoffman",
                "disp. Bo Hoffman"
            ]
        },
        "2": {
            "name": "Einar Hoffmans Stolfabrik",
            "location": "Tibro",
            "business": "Tillverkar stolar i olika stilar och träslag",
            "contact": {
                "phone": [
                    "177"
                ],
                "postgiro": "15086"
            },
            "financials": {
                "employees": {
                    "Arb.-antal": 10
                },
                "annual_production_value": "125,000 kr"
            },
            "foundation_year": 1920,
            "director": "snickarna Einar Hoffman"
        },
        "3": {
            "name": "Hj. Hofgrens AB.",
            "location": "Örebro",
            "business": "Tillverkar fiskredskap såsom revar och linor",
            "contact": {
                "phone": "Lindmark & Nilsson",
                "postgiro": "14292"
            },
            "financials": {
                "capital": "30,000 kr",
                "employees": {
                    "Arb.-antal": 10
                }
            },
            "foundation_year": 1939
        },
        "4": {
            "name": "Hofors Bruk",
            "location": "Hofors",
            "description": "Se AB. Svenska Kullagerfabriken, Hofors Bruk, Hofors"
        },
        "5": {
            "name": "Hofvids Trävaru AB.",
            "location": "Sundsvall",
            "description": "Se Ankarsviks Ångsågs AB., Sundsvall"
        },
        "6": {
            "name": "Hofving & Myrberg, Grafiska AB.",
            "location": "Stockholm",
            "description": "Se Grafiska AB. Hofving & Myrberg, Stockholm"
        },
        "7": {
            "name": "Hohults Snickerifabrik",
            "location": "Hohultslätt",
            "business": "Snickeri och träförädlingsfabrik",
            "contact": {
                "telegraph": "Hohult, Kalmar",
                "phone": [
                    "3",
                    "84"
                ],
                "postgiro": "82580"
            },
            "financials": {
                "employees": {
                    "Antal industriarb.": 25
                },
                "annual_production_value": "460,000 kr"
            },
            "foundation_year": 1898,
            "director": "disp. Simeon Weidow"
        },
        "8": {
            "name": "Hohult-Spexeryds Mangangruvor",
            "location": "Tenhult",
            "description": "Se Wargöns AB., Vargön"
        },
        "9": {
            "name": "AB. Hohultslätts Spegelindustri",
            "location": "Hohultslätt",
            "business": "Tillverkar speglar och kompletteringsmöbler",
            "contact": {
                "phone": "45",
                "postgiro": "99494"
            },
            "financials": {
                "capital": "48,200 kr",
                "employees": {
                    "Antal industriarb.": 45
                }
            },
            "foundation_year": 1936
        },
        "10": {
            "name": "AB. Hollner & Hultquist",
            "location": "Stallarholmen",
            "business": "Kartongfabrik och tryckeri",
            "contact": {
                "phone": "19",
                "postgiro": "98486"
            },
            "financials": {
                "capital": "25,400 kr",
                "employees": {
                    "Antal industriarb.": 30
                },
                "annual_production_value": "350,000 kr"
            },
            "foundation_year": 1935,
            "corporation_year": 1944,
            "director": "fabr. William Hollner"
        },
        "11": {
            "name": "Holm AB., Bröderna",
            "location": "Ransta",
            "description": "Se Bröderna Holm AB., Ransta"
        },
        "12": {
            "name": "Holm & Hoppe",
            "location": "Stockholm",
            "description": "Se Mepe, Holm & Hoppe, Stockholm"
        },
        "13": {
            "name": "Holma-Helsinglands Linspinneri- & Väfveri AB.",
            "location": "Sörforsa och Madängsholm",
            "business": "Linspinneri och blekeri",
            "financials": {
                "capital": "unknown"
            },
            "foundation_year": "unknown"
        }
    }
}