{
    "original": "Avos—Badkläder\n\n*Avos, Örebro.\n\nSe AB. Växlar och Signaler, Örebro.\n\n*Axonit AB., Stockholm.\n\nBryter och förädlar kiselgur för\nfiltrerings-, värmeisolerings- och\nabsorptions-ändamål vid fabrik i Ekträsk (Västerb.l.).\n\nKontor: Stockholm, Grevtureg. 14.\nTelefon: 671867. Postgiro: 150922. —\nAkt.-kap.: 90,000 kr. Arb.-antal: 20. —\nBolaget grundat 1941.\n\nStyrelse: övering. Magnus\nTiger-schiöld (ordf.), ing. Axel Ohlsson, disp.\nSeb. Tham.\n\nVerkst. dir. o. disp.: Axel Ohlsson.\n\n*AB. Axvalls Ångbryggeri, Axvall.\n\nTillverkar malt, maltdrycker och\nläskedrycker vid bryggeri i Axvall\n(Skarab. l.).\n\nTelefon: 8 o. 9. — Akt.-kap.: 300,000\nkr. Antal industriarb.: 20. Tillv.-värde pr\når: 400,000 kr. — Firman etabl. 1880,\nbolag 1933.\n\nStyrelse: civiling. G. Henry Andersson\n(ordf.), distriktsveterinär Einar A.\nAndersson, banktjänsteman Ragnar L.\nAndersson.\n\nVerkst. dir.: G. Henry Andersson.\n\nB\n\n* utmärker till Sveriges Industriförbund anslutna företag.\n\n* Backa-Hosjö AB., Sparreholm.\n\nSågverk, hyvleri och snickerifabrik i\nSparreholm, sågverk, hyvleri och\ntegelbruk i Vrena (båda i Södermanl. l.).\n\nTillverkar sågade och hyvlade trävaror,\ntak- och murtegel, tegelrör, dörrar och\nandra byggnadssnickerier. Bolaget idkar\njämväl jord- och skogsbruk.\n\nKontor: Sparreholm. Telegr.-adr.:\nBac-kahosjö, Flen. Telefon: Sparreholm 4.\nPostgiro: 29224.\n\nAkt.-kap.: 2,925,000 kr. Antal\nindustriarb.: 170. Årstillv.: 4,000 stds sågade och\n4,000 stds hyvlade trävaror, 4,5 milj. st.\ntegelvaror.\n\nBolaget, grundat 1897, äges av\nHolmens Bruks &amp; Fabriks AB., Norrköping.\n\nStyrelse: disp. Chr. v. Sydow (ordf.),\nkamrer Axel Olsson, jägmäst. Å. Norlén.\n\nVerkst. dir.: Chr. v. Sydow.\n\nPlatschef: disp. V. Hell.\n\nKamrer: O. Breij.\n\n*AB. Backe Trävaruindustrier,\n\nStockholm.\n\nSågverk, hyvleri och snickerifabrik i\nBacke (Västernorrl. l.). Tillverkar sågade\noch hyvlade trävaror, byggnadssnickerier,\nformplattor och lådämnen.\n\nKontor: Stockholm, Norrmalmstorg\n2 A. Telegr.-adr.: Anifab, Stockholm.\nTelefon: 118181 o. 207781. Postgiro: 56413.\n\nAkt.-kap.: 70,000 kr. Antal\nindustriarb.: 25. Tillv.-värde pr år: 250,000 kr.\n— Firman etabl. 1930, bolag 1946.\n\nStyrelse: dir. Oscar Ny len (ordf.), ing.\nBengt Norlander, köpm. Bernhard E.\nNorlander, disp. Harry Suneson.\n\nVerkst. dir.; Oscar Ny len.\n\nFörsäljn.-chef: Harry Suneson.\n\nDriftsing.: Bengt Norlander.\n\n*Jacob Bagges Söner, Stockholm.\n\nSe Stockholms Kartong- o.\nLitografiska AB., Stockholm.\n\n* Backa Såg- och Tegelverks AB.,\n\nKorsnäs.\n\nSågverk, hyvleri och tegelbruk vid\nBacka och Staberg, Korsnäs (Kopparb. l.).\nTillverkar sågade och hyvlade trävaror,\nstav, lådämnen samt dräneringsrör och\nmurtegel. Bolaget idkar jämväl\nskogs-och jordbruk.\n\nKontor: Korsnäs. Telegr.-adr.: Backa,\nFalun. Telefon: Falun 1522. Postgiro:\n26421.\n\nAkt.-kap.: 101,100 kr. Antal\nindustriarb.: 105. Årstillv.: 2,500 stds sågade och\n1,000 stds hyvlade trävaror, 3 milj.\nmurtegel. — Bolaget grundat 1919.\n\nStyrelse: disp. G. Otto Halle (ordf.),\ndisp. Hilmer Annerman, kamrer E. W.\nBley.\n\nVerkst. dir.: G. O. Halle.\n\nKontors- o. försäljn.-chef: E. W. Bley.\n\n*AB. Badkläders Industri, Malmö.\n\nKonfektionsfabrik. Tillverkar\nbadkappor, baddräkter och badbyxor, badmössor,\nstranddräkter samt sportbyxor.\n\n32*",
    "structured": {
        "Avos—Badkläder": {
            "name": "Avos—Badkläder",
            "location": "Örebro",
            "contact": {
                "office": "Örebro",
                "phone": [
                    "671867"
                ],
                "postgiro": "150922",
                "head_office": "Örebro"
            },
            "financials": {
                "capital": "90,000 kr",
                "employees": {
                    "total": 20
                },
                "annual_turnover": "Not available"
            },
            "foundation_year": 1941
        },
        "Axonit AB.": {
            "name": "Axonit AB.",
            "location": "Stockholm",
            "business": "Bryter och förädlar kiselgur",
            "products": "Filtrerings-, värmeisolerings- och absorptions-ändamål",
            "contact": {
                "office": "Stockholm, Grevtureg. 14",
                "phone": [
                    "671867"
                ],
                "postgiro": "150922"
            },
            "financials": {
                "capital": "90,000 kr",
                "employees": {
                    "total": 20
                },
                "annual_turnover": "Not available"
            },
            "foundation_year": 1941
        },
        "AB. Axvalls Ångbryggeri": {
            "name": "AB. Axvalls Ångbryggeri",
            "location": "Axvall",
            "business": "Tillverkar malt, maltdrycker och läskedrycker",
            "products": "Malt, maltdrycker, läskedrycker",
            "contact": {
                "phone": [
                    "8",
                    "9"
                ],
                "head_office": "Axvall"
            },
            "financials": {
                "capital": "300,000 kr",
                "employees": {
                    "total": 20
                },
                "annual_turnover": "400,000 kr"
            },
            "foundation_year": 1880,
            "predecessor": "Not available",
            "corporation_year": 1933
        },
        "Backa-Hosjö AB.": {
            "name": "Backa-Hosjö AB.",
            "location": "Sparreholm",
            "business": "Sågverk, hyvleri och snickerifabrik",
            "products": "Trävaror, tak- och murtegel, tegelrör, dörrar, jord- och skogsbruk",
            "contact": {
                "office": "Sparreholm",
                "phone": [
                    "Sparreholm 4"
                ],
                "postgiro": "29224",
                "telegraph": "Bac-kahosjö, Flen"
            },
            "financials": {
                "capital": "2,925,000 kr",
                "employees": {
                    "total": 170
                },
                "annual_turnover": "Not available"
            },
            "foundation_year": 1897
        },
        "AB. Backe Trävaruindustrier": {
            "name": "AB. Backe Trävaruindustrier",
            "location": "Stockholm",
            "business": "Sågverk, hyvleri och snickerifabrik",
            "products": "Trävaror, byggnadssnickerier, formplattor, lådämnen",
            "contact": {
                "office": "Stockholm, Norrmalmstorg 2 A",
                "phone": [
                    "118181",
                    "207781"
                ],
                "postgiro": "56413"
            },
            "financials": {
                "capital": "70,000 kr",
                "employees": {
                    "total": 25
                },
                "annual_turnover": "250,000 kr"
            },
            "foundation_year": 1930,
            "corporation_year": 1946
        },
        "Backa Såg- och Tegelverks AB.": {
            "name": "Backa Såg- och Tegelverks AB.",
            "location": "Korsnäs",
            "business": "Sågverk, hyvleri och tegelbruk",
            "products": "Trävaror, murtegel, skogs-och jordbruk",
            "contact": {
                "office": "Korsnäs",
                "phone": [
                    "Falun 1522"
                ],
                "postgiro": "26421"
            },
            "financials": {
                "capital": "101,100 kr",
                "employees": {
                    "total": 105
                },
                "annual_turnover": "Not available"
            },
            "foundation_year": 1919
        },
        "AB. Badkläders Industri": {
            "name": "AB. Badkläders Industri",
            "location": "Malmö",
            "business": "Konfektionsfabrik",
            "products": "Badkappor, baddräkter, badbyxor, badmössor, stranddräkter, sportbyxor",
            "financials": {
                "capital": "Not available",
                "employees": {
                    "total": "Not available"
                },
                "annual_turnover": "Not available"
            }
        }
    }
}