{
    "original": "j/Viskan—Wollrath\n\n*Wiskans AB-, Viskan.\n\nSågverk, hyvleri och snickerifabrik vid\nViskan (Västernorrl. l.). Tillverkar\nsågade och hyvlade trävaror samt\nbyggnadssnickerier.\n\nTelegr.-adr.: Wiskansbolag, Sundsvall.\nTelefon: Viskan 5 o. 55. Postgiro: 77393.\n\nAkt.-kap.: 330,000 kr. Antal\nindustriarb.: 55. Tillv.-värde pr år: 850,000 kr.\nÅrstillv.: 3,000 stds sågade o. 2,000 stds\nhyvlade trävaror. — Bolaget grundat\n1897.\n\nStyrelse: dir. Gust. Göranson (ordf.),\ndisp. Sanfred Blomberg, dir. J. W. R.\nLilliestråle.\n\nVerkst. dir.: S. Blomberg.\n\n*Vithala Bryggeri, Vetlanda.\n\nSe Nässjö Bryggeri AB., Nässjö.\n\n*AB. Vitin, Stockholm.\n\nKem.-tekn. fabrik. Tillverkar\nfettemulsion samt glassmassa. Varumärken:\n»Vitin», »Ettan», »Flodin» o. »Kajsa\nWarg».\n\nKontor: Katrinebergsv. 8—10; postadr.:\nStockholm 9. Telefon: 451934 o. 451254.\nPostgiro: 54597.\n\nAkt.-kap.: 85,000 kr. Arb.-antal: 10.\n— Bolaget grundat 1928.\n\nStyrelse: ing. August Kleine (ordf.),\nförsäljn.-chef Eduard Kleine,\nkontorschef Milena Kleine, ing. Erik Öström.\n\nVerkst. dir.: August Kleine.\n\nDriftsing.: E. Öström.\n\nFörsäljn.-chef: E. Kleine.\n\nM. L. Wittboldt, Göteborg.\n\nSågverk och lådfabrik i Göteborg.\nTillverkar sågat virke, gruvvirke och lådor.\nFirman driver även export av spiror,\nslanor, sågade och hyvlade trävaror, åror\nm. m.\n\nKontor: »Holmia», Lilla Bommens\ntorg 2. Telegr.-adr.: Wittboldt, Göteborg.\nTelefon: 135227 o. 139977. Postgiro:\n45473.\n\nAntal industriarb.: 125. Årstillv.:\n10,000 stds trävaror. — Firman etabl.\n1908.\n\nÄgare o. chef: kapten D. Wittboldt.\n\n*Vittinge Tegelbruks AB.,\n\nVittinge.\n\nTillverkar taktegel och ^ dräneringsrör\nvid tegelbruk i ösby, Vittinge\n(Västmanl. l.).\n\nTelegr.-adr.: Vi 11 ingetegel, Vittinge.\nTelefon: 10. Postgiro: 71855.\n\nAkt.-kap.: 120,000 kr. Antal\nindustriarb.: 30. Årstillv.: 3,50 milj. st.\ntegelvaror. — Tegelbruket anlagt 1917.\n\nVerkst. dir.: Karl Erik Wall.\n\n*AB, Vitvaruindustri, Borås.\n\nTillverkar klänningar, blusar, kjolar,\npyjamas, förkläden, nattskjortor,\nskyddsrockar, silkesunderkläder m. m.\nVarumärken: »Abeve» o. »Korall».\n\nTelegr.-adr.: Vitvaruindustri, Borås.\nTelefon: »Abeve». Postgiro: 20613.\n\nAkt.-kap.: 250,000 kr. Antal\nindustriarb.: 240. — Firman etabl. 1914, bolag\n1918.\n\nStyrelse: dir. E. Hjalmar Johannesson\n(ordf.), disp. Åke Johannesson, grossh.\nEric Wall.\n\nVerkst. dir.: E. Hj. Johannesson.\n\nWojidkow &amp; Co. AB., Malmö.\n\nMetallvarufabrik, metallgjuteri,\nför-kromnings- och förnicklingsverkstad,\nvarmgalvaniseringsverk samt plåtslageri.\nUtför metallarbeten såsom fartygs- och\njärnvägsdetaljer, fönster och\nfönsterventiler för fartyg och järnvägar,\nskjutfönster (märke: »Futurum») för\nhusbyggnader, rostfria plåtarbeten såsom\ndiskbänkar m. m.; utför förkromning av\nstörre detaljer.\n\nTelegr.-adr.: Wojidkowco, Malmö.\nTelefon: Malmö 71475. Postgiro: 24408.\n\nAkt.-kap.: 60,000 kr. Antal\nindustriarb.: 50. Tillv.-värde pr år: 750,000 kr.\n— Firman etabl. 1888, bolag 1933.\n\nVerkst. dir.: civiling. F. Peterzén.\n\nAB. Yolanit, Kristinehamn.\n\nMetallgjuteri. Tillverkar lagerbrons,\n\nmaskinbrons, rödgods, lättmetall och\nbabbit. Varumärke: »Volanit».\n\nTelefon: 11781. Postgiro: 150715. —\nAkt.-kap.: 47,500 kr. Antal industriarb.:\n20. Tillv.-värde pr år: 450,000 kr.\n\nBolaget grundat 1936 under namn AB\nAll-Gos, nuv. namn 1938.\n\nChef: ing. Erik Eriksson.\n\n\"0. J. Wollraths Snickerifabrik,\n\nStockholm.\n\nTillverkar möbler, byggnadssnickerier\noch inredningar.\n\nKontor: Styrmansg. 23. Telefon:\n613663. Postgiro: 52387. — Arb.-antal:\n10. — Firman etabl. 1912.\n\nÄgare o. chef: snickarmäst. Olof J.\nWollrath.",
    "structured": {
        "1": {
            "name": "Wiskans AB",
            "location": "Viskan, Västernorrland",
            "business": "Sågverk, hyvleri och snickerifabrik",
            "products": "Tillverkar sågade och hyvlade trävaror samt byggnadssnickerier.",
            "contact": {
                "office": "Viskan (Västernorrland)",
                "phone": [
                    "Viskan 5",
                    "Viskan 55"
                ],
                "postgiro": "77393",
                "telegraph": "Wiskansbolag, Sundsvall"
            },
            "financials": {
                "capital": "330,000 kr",
                "employees": {
                    "industriarb": 55
                },
                "annual_turnover": "850,000 kr",
                "annual_production_value": "3,000 stds sågade, 2,000 stds hyvlade trävaror"
            },
            "foundation_year": 1897,
            "board": [
                {
                    "name": "Gust. Göranson",
                    "role": "ordf."
                },
                {
                    "name": "Sanfred Blomberg",
                    "role": "disp."
                },
                {
                    "name": "J. W. R. Lilliestråle",
                    "role": "dir."
                }
            ]
        },
        "2": {
            "name": "AB. Vitin",
            "location": "Stockholm",
            "business": "Kem.-tekn. fabrik",
            "products": "Tillverkar fettemulsion samt glassmassa.",
            "contact": {
                "office": "Katrinebergsv. 8—10",
                "phone": [
                    "451934",
                    "451254"
                ],
                "postgiro": "54597"
            },
            "financials": {
                "capital": "85,000 kr",
                "employees": {
                    "industriarb": 10
                }
            },
            "foundation_year": 1928,
            "board": [
                {
                    "name": "August Kleine",
                    "role": "ordf."
                },
                {
                    "name": "Eduard Kleine",
                    "role": "försäljn.-chef"
                },
                {
                    "name": "Milena Kleine",
                    "role": "kontorschef"
                },
                {
                    "name": "Erik Öström",
                    "role": "ing."
                }
            ]
        },
        "3": {
            "name": "M. L. Wittboldt",
            "location": "Göteborg",
            "business": "Sågverk och lådfabrik",
            "products": "Tillverkar sågat virke, gruvvirke, lådor, spiror, slanor, m.m.",
            "contact": {
                "office": "Lilla Bommens torg 2",
                "telegraph": "Wittboldt, Göteborg",
                "phone": [
                    "135227",
                    "139977"
                ],
                "postgiro": "45473"
            },
            "financials": {
                "employees": {
                    "industriarb": 125
                },
                "annual_production_value": "10,000 stds trävaror"
            },
            "board": [],
            "director": "kapten D. Wittboldt"
        },
        "4": {
            "name": "Vittinge Tegelbruks AB.",
            "location": "Vittinge",
            "business": "Tillverkar taktegel och dräneringsrör",
            "contact": {
                "office": "ösby, Vittinge",
                "telegraph": "Vi11ingetegel, Vittinge",
                "phone": "10",
                "postgiro": "71855"
            },
            "financials": {
                "capital": "120,000 kr",
                "employees": {
                    "industriarb": 30
                },
                "annual_production_value": "3,50 milj. st. tegelvaror"
            },
            "board": [],
            "director": "Karl Erik Wall"
        },
        "5": {
            "name": "AB, Vitvaruindustri",
            "location": "Borås",
            "business": "Tillverkar klänningar, blusar, kjolar, pyjamas, m.m.",
            "products": "Varumärken: »Abeve» o. »Korall»",
            "contact": {
                "phone": "»Abeve»",
                "postgiro": "20613"
            },
            "financials": {
                "capital": "250,000 kr",
                "employees": {
                    "industriarb": 240
                }
            },
            "board": [
                {
                    "name": "E. Hjalmar Johannesson",
                    "role": "ordf."
                },
                {
                    "name": "Åke Johannesson",
                    "role": "disp."
                },
                {
                    "name": "Eric Wall",
                    "role": "grossh."
                }
            ],
            "director": "E. Hj. Johannesson"
        },
        "6": {
            "name": "Wojidkow & Co. AB.",
            "location": "Malmö",
            "business": "Metallvarufabrik, metallgjuteri, m.m.",
            "products": "Utför metallarbeten såsom fartygs- och järnvägsdetaljer, fönster och fönsterventiler, m.m.",
            "contact": {
                "phone": "Malmö 71475",
                "postgiro": "24408"
            },
            "financials": {
                "capital": "60,000 kr",
                "employees": {
                    "industriarb": 50
                },
                "annual_production_value": "750,000 kr"
            },
            "board": [],
            "director": "civiling. F. Peterzén"
        },
        "7": {
            "name": "AB. Yolanit",
            "location": "Kristinehamn",
            "business": "Metallgjuteri",
            "products": "Tillverkar lagerbrons, maskinbrons, rödgods, lättmetall och babbit.",
            "contact": {
                "phone": "11781",
                "postgiro": "150715"
            },
            "financials": {
                "capital": "47,500 kr",
                "employees": {
                    "industriarb": 20
                },
                "annual_production_value": "450,000 kr"
            },
            "director": "ing. Erik Eriksson"
        },
        "8": {
            "name": "O. J. Wollraths Snickerifabrik",
            "location": "Stockholm",
            "business": "Tillverkar möbler, byggnadssnickerier och inredningar",
            "contact": {
                "office": "Styrmansg. 23",
                "phone": "613663",
                "postgiro": "52387"
            },
            "financials": {
                "employees": {
                    "industriarb": 10
                }
            },
            "director": "snickarmäst. Olof J. Wollrath"
        }
    }
}