{
    "original": "Fågel fors—Färg\n\nTelefon: Eriksdal 55 o. Sjöbo 242.\nPostgiro: 157681.\n\nAkt.-kap.: 325,000 kr. Antal\nindustriarb.: 75. Årsprod.: 40,000 ton. — Bolaget\ngrundat 1938.\n\nStyrelse: civiling. F. G. Liljenroth\n(ordf.), dir. B. Wadsted, dir. S.\nWohl-fahrt, ing. P. Wretlind.\nDisp.: R. Sökjer-Petersen.\nKamrer: S. Hemne.\n\n* Fågelfors Bruk, Fågelfors.\nSe AB. Fogelfors Bruk, Fågelfors.\n\n*AB. Fåglaviks Glasbruk,\n\nGöteborg.\n\nGlasbruk vid Fåglavik (Älvsb. l.).\nTillverkar medicinskt och laboratorieglas.\n\nHuvudkontor: Göteborg, V. Hamng. 2.\nTelegr.-adr.: Fåglaviksglas, Göteborg.\nTelefon: 137824. Postgiro: 40718.\nFabrikskontor: Fåglavik. Telefon: Fåglavik\n25\n\nAkt.-kap.: 300,000 kr. Antal\nindustriarb.: 120. Tillv.-värde pr år: 1,000,000 kr.\n— Glasbruket anlagt 1874, bolag 1891.\n\nStyrelse: konteramiral Erik\nAnderberg, dir. Yngve W. Anderberg, adv. E.\nS. Markfelt.\n\nVerkst. dir.: Y. W. Anderberg.\nFörvalt.: Wilgott Håkanson.\n\n*AB. Färe Armaturfabrik, SibbhuM.\n\nArmaturfabrik och metallgjuteri i\nSibbhult (Kristianst. l.).\n\nTillverkar armatur för vatten, ånga,\ngas och syror, sanitetsarmatur,\nmetall-gjutgods i aluminium, fosforbrons,\nröd-metall, mässing, syrafast metall m. fl.\nlegeringar, pumpar för olika ändamål,\ngjutmodeller samt noxiventiler.\n\nTelegr.-adr.: Armatur, Sibbhult.\nTelefon: »Färearmatur». Postgiro: 9413.\n\nAkt.-kap.: 400,000 kr. Antal\nindustriarb.: 400. — Bolaget grundat 1922.\n\nStyrelse: disp. Bror Färe (ordf.),\nbankdir. G. Aspegren, fru L. Färe.\nVerkst. dir.: Bror Färe.\nKontorschef: Harry G. Nilson.\nRitkontorschef: Gösta Johnsson.\nVerkstadschef: K. Jensen.\nFörsäljn.-chefer: för armaturavd.: Nils\nPersson; för pumpavd.: Evert Johansson.\nInköpschef: S. Rosvall.\n\nAB. Färgfabriken Skandia,\n\nStockholm.\n\nTillverkar tryckfärger; specialitet\ntid-nings- och tidskriftsfärger.\n\nKontor: Hammarby fabriksväg,\npost-adr.: Stockholm 20. Telefon: 440210.\nPostgiro: 4539. — Akt.-kap.: 100,000 kr.\nArb.-antal: 5. — Firman etabl. 1913.\n\nVerkst. dir.: civiling. C.-H. Jacobson.\n\n*Färg AB. International, Göteborg.\n\nFabrik å Marieholm, Göteborg.\nTillverkar skeppsbottenfärger, fartygs- och\nrostskyddsfärger, färger och fernissor\nm. m. för industri- och hantverk.\n\nVarunamn: Blyoline, Blyonal,\nBlyo-de-Luxe, Boottop, Cemenlac, Corroline,\nDanboline, Fabi-Rexol, Galvex, Glypto,\nInterline, International, Lagolack,\nLago-line, Lagomatt, National, Odieo, Pintoff,\nPlate Primer, Remuverine, Silverette,\nSnögubben, Spectroline, Stivaline,\nSun-light-Enamel, Tanctectol, Terpoline,\nBrandoline, Pyroline,\nKlorkautschuk-Al-kaline, Interpinol.\n\nTelegr.-adr.: International, Göteborg.\nTelefon: »Färgbolaget International».\nPostgiro: 40585. Avd.-kontor: Stockholm,\nBlasieholmsg. 3, telefon: 112875; Malmö,\nSt. Varvsg. 2, telefon: 26735.\n\nAkt.-kap.: 500,000 kr. Antal\nindustriarb.: 50. Tillv.-värde pr år: 3,900,000 kr.\n\n—\tBolaget grundat 1913 under namn\nHolzapfels Svenska Färg AB.,\nnamnförändring 1919. Bolaget är huvuddelägare\ni Marieholms Nya Industri AB.\n\nStyrelse: generalkonsul Gunnar\nCarlsson (ordf.), konsul Tor E. J:son\nBroström, dir. K. R. Bökman, dir. Em.\nHögberg, dir. C. R. Petrie.\n\nVerkst. dir.: Rob. Johansson.\n\nKamrer: M. Byttner.\n\n*Färg- &amp; Ferniss Fabriks AB., Arvid\nLindgren &amp; Co., Stockholm.\n\nFärg- och fernissfabrik i Märsta\n(Sthlms l.). Tillverkar lack-, olje-,\nsyntetiska, emulsions- och cellulosafärger,\nfernissor, bottenfärger,\nfärgborttagnings-medel, industrilaeker och -färger.\n\nSpecialiteter: syntetisk emalj\n(»Synt-em») samt cellulosapreparater för\nträindustrien (»Decornit») och för\nbilmålning (»Auto-Luxe-Coat»), »Alecto»\noch »Sim» linoleumfernissa och\ngolv-lackfärg, »Decorin» emaljfärg, »Deeörol»\nfernissor (snabbtorkande), emulsionsfärg\n»Pastella», samt »Decorex»\nklorkaut-schu klack (mot starka kemiska\npåverkningar).\n\nKontor: Grevg. 5. Telegr.-adr.: Alco,\nStockholm. Telefon: 670765. Postgiro:\n716.\n\nAkt.-kap.: 400,000 kr. Antal\nindustriarb.: 50. Tillv.-värde pr år: 5,000,000 kr.\n\n—\tBolaget grundat 1923.",
    "structured": {
        "1": {
            "name": "Fågel Fors—Färg",
            "location": "Eriksdal 55 o. Sjöbo 242",
            "business": "Bolaget grundat 1938",
            "contact": {
                "office": "Fågel Fors, Fågel Fors",
                "phone": [
                    "137824"
                ],
                "postgiro": "40718",
                "telegraph": "Fåglaviksglas, Göteborg"
            },
            "financials": {
                "capital": "325,000 kr",
                "employees": {
                    "industriarb": 75
                },
                "annual_turnover": "N/A",
                "annual_production_value": "40,000 ton"
            },
            "foundation_year": 1938,
            "board": [
                {
                    "name": "civiling. F. G. Liljenroth",
                    "role": "ordf."
                },
                {
                    "name": "dir. B. Wadsted",
                    "role": "N/A"
                },
                {
                    "name": "dir. S. Wohl-fahrt",
                    "role": "N/A"
                },
                {
                    "name": "ing. P. Wretlind",
                    "role": "N/A"
                }
            ]
        },
        "2": {
            "name": "Fåglaviks Glasbruk",
            "location": "Fåglavik",
            "business": "Glasbruket anlagt 1874, bolag 1891",
            "contact": {
                "office": "Göteborg, V. Hamng. 2",
                "phone": [
                    "137824"
                ],
                "postgiro": "40718"
            },
            "financials": {
                "capital": "300,000 kr",
                "employees": {
                    "industriarb": 120
                },
                "annual_turnover": "N/A",
                "annual_production_value": "1,000,000 kr"
            },
            "foundation_year": 1891,
            "board": [
                {
                    "name": "konteramiral Erik Anderberg",
                    "role": "N/A"
                },
                {
                    "name": "dir. Yngve W. Anderberg",
                    "role": "N/A"
                },
                {
                    "name": "adv. E.S. Markfelt",
                    "role": "N/A"
                }
            ],
            "director": "Y. W. Anderberg"
        },
        "3": {
            "name": "Färe Armaturfabrik",
            "location": "Sibbhult",
            "business": "Tillverkar armatur för vatten, ånga, gas och syror",
            "contact": {
                "office": "Sibbhult",
                "phone": [
                    "Färearmatur"
                ],
                "postgiro": "9413",
                "telegraph": "Armatur, Sibbhult"
            },
            "financials": {
                "capital": "400,000 kr",
                "employees": {
                    "industriarb": 400
                }
            },
            "foundation_year": 1922,
            "board": [
                {
                    "name": "disp. Bror Färe",
                    "role": "ordf."
                },
                {
                    "name": "bankdir. G. Aspegren",
                    "role": "N/A"
                },
                {
                    "name": "fru L. Färe",
                    "role": "N/A"
                }
            ],
            "director": "Bror Färe",
            "manager": "S. Rosvall"
        },
        "4": {
            "name": "Färgfabriken Skandia",
            "location": "Stockholm",
            "business": "Tillverkar tryckfärger; specialitet tidnings- och tidskriftsfärger",
            "contact": {
                "office": "Hammarby fabriksväg",
                "phone": [
                    "440210"
                ],
                "postgiro": "4539"
            },
            "financials": {
                "capital": "100,000 kr",
                "employees": {
                    "arb-antal": 5
                }
            },
            "foundation_year": 1913,
            "director": "civiling. C.-H. Jacobson"
        },
        "5": {
            "name": "Färg AB. International",
            "location": "Göteborg",
            "business": "Bolaget grundat 1913 under namn Holzapfels Svenska Färg AB, namnförändring 1919",
            "contact": {
                "office": "Marieholm, Göteborg",
                "phone": [
                    "Färgbolaget International"
                ],
                "postgiro": "40585"
            },
            "financials": {
                "capital": "500,000 kr",
                "employees": {
                    "industriarb": 50
                },
                "annual_production_value": "3,900,000 kr"
            },
            "foundation_year": 1913,
            "board": [
                {
                    "name": "generalkonsul Gunnar Carlsson",
                    "role": "ordf."
                },
                {
                    "name": "konsul Tor E. J:son Broström",
                    "role": "N/A "
                }
            ],
            "director": "Rob. Johansson",
            "manager": "M. Byttner"
        },
        "6": {
            "name": "Färg- & Ferniss Fabriks AB. Arvid Lindgren & Co.",
            "location": "Stockholm",
            "business": "Bolaget grundat 1923",
            "contact": {
                "office": "Grevg. 5",
                "telegraph": "Alco, Stockholm",
                "phone": [
                    "670765"
                ],
                "postgiro": "716"
            },
            "financials": {
                "capital": "400,000 kr",
                "employees": {
                    "industriarb": 50
                },
                "annual_production_value": "5,000,000 kr"
            }
        }
    }
}