{
    "original": "8 trumpfabrik—8 tr omber g\n\n’Strumpfabriks AB. Sphinx,\n\nMjölby.\n\nSe AB. Norrköpings Tricotfabrik, Alb.\nWesterholm, Norrköping.\n\nAB. Strå Kalkbruk, Stockholm.\n\nKalkbruk vid Sala, Dyltabruk (Örebro\n1.) och Åsestugan (Jämtl. L), Borghamn\noch Lenbergsvik (båda i Östergötl. l.),\nHögdalsås och Innansjön (båda i\nVästerb. l.) samt kalkbrott vid Fårösund\n(Gotl. l.).\n\nBryter kalksten och dolomit samt\ntillverkar bränd kalk för industri-,\nbyggnads- och jordbruksändamål ävensom\nbränd dolomit för martinugnar. Bolaget\nidkar jämväl jordbruk.\n\nKontor: Stockholm, Jakobsbergsg. 2.\nTelegr.-adr.: Stråkalk, Stockholm.\nTelefon: »Strå Kalkbruk». Postgiro: 22200.\n\nAkt.-kap.: 2,000,000 kr. Antal\nindustriarb.: 500. — Bolaget grundat 1929.\n\nStyrelse: dir. Vilhelm Björkman\n(ordf.), dir. Josef Gendt, dir. G. Raabe.\n\nVerkst. dir. o. disp.: Josef Gendt.\n\nVice verkst. dir.: Elis Bergström.\n\n’Strängnäs Bryggeri AB.,\n\nSträngnäs.\n\nTillverkar maltdrycker och kolsyrade\ndrycker.\n\nTelefon: 44. Postgiro: 143131. —\nAkt.-kap.: 250,000 kr. Antal industriarb.: 19.\nTillv.-värde pr år: 450,000 kr. — Firman\netabl. 1907.\n\nStyrelse: disp. Gösta Sverdrup (ordf.),\ndisp. Hugo Carlberg, disp. Alvar Törnell.\n\nVerkst. dir.: Gösta Sverdrup\n(Eskilstuna).\n\nDisp. o. bryggm.: A. Törnell.\n\n\"Strängnäs Elektr. Valskvarn,\n\nSträngnäs.\n\nTillverkar mjöl, korngryn, kli och\ngröpe. Varumärke: »Polstjärnan».\n\nTelefon: 502 o. 506. Postgiro: 31973.\n— Antal industriarb.: 8. Prod.-värde pr\når: 700,000 kr. — Firman etabl. 1914.\n\nÄgare o. chef: kvarnägare Gustav\nSvenson.\n\n*C. C. Ströms AB., Kumla.\n\nTillverkar skodon vid fabrik i Kumla\n(Örebro l.). Varumärken: »CGS», »Igloo»,\n»Cortina», »Högfjäll», »Scout» o.\n»Hubert».\n\nTelegr.-adr.: Ström, Kumla. Telefon:\nÖrebro 70920. Postgiro: 6469.\n\nAkt.-kap.: 800,000 kr. Antal\nindustriarb.: 145. Tillv.-värde pr år: 2,500,000 kr.\n\n—\tFirman etabl. 1888, bolag 1930.\n\nStyrelse: dir. Arvid Lindfelt, disp. Carl\n\nEinar Ström, dir. Simon Ström.\n\nVerkst. dir.: Simon Ström.\n\nDisp.: Carl Einar Ström.\n\n*AB. Gust. Ström &amp; Co., Snickeri- och\nTrappfabrik, Vansbro.\n\nTillverkar byggnadssnickerier,\ninredningar och trappor vid fabrik i Vansbro\n(Kopparb. l.).\n\nTelefon: 105. Postgiro: 163717. —\nAkt.-kap.: 120,200 kr. Antal industriarb.: 25.\nTillv.-värde pr år: 200,000 kr. — Firman\netabl. 1925, bolag 1943.\n\nStyrelse o. verkst. dir.: Gustav Ström.\n\n*Ströms Bruks AB., Strömsbruk.\n\nSulfitfabrik och sulfitspritfabrik vid\nStrömsbruk samt sågverk vid Stocka\n(båda i Gävleb. l.). Tillverkar\nsulfitcellulosa, sulfitsprit och sågade trävaror.\nBolaget idkar jämväl skogshantering och\njordbruk.\n\nHuvudkontor: Strömsbruk.\nTelegr.-adr.: Strömsbruk, Hudiksvall. Telefon:\nStrömsbruk 7. Postgiro: 26800.\nSågverkskontor: Stocka. Skogskontor: Ljusne.\n\nAkt.-kap.: 12,000,000 kr. Antal\nindustriarb.: 450. Årstillv.: 38,000 ton\nviscos-massa o. blekt papperssulfit, 4 milj. ltr\nsulfitsprit, 10,000 stds sågade trävaror.\n\nBolaget, grundat 1873, äger\nLjusne-Woxna AB.\n\nStyrelse: vice amiral Fabian Tamm\n(ordf.), disp. Fabian Lundquist, dir. C.\nJ. Robbert, disp. C. G. Rothelius.\n\nDisp. o. verkst. dir.: Fabian Lundquist.\n\nEkonomichef: Nils Enocsson.\n\nFörsäljn.-chef: Einar Oléhn.\n\növering.: Gert Schiller.\n\n*Strömbacka Bruk, Strömbacka.\n\nSe AB. Iggesunds Bruk, Iggesund.\n\n*AB. H. Strömberg, Virserum.\n\nTillverkar stoppade möbler vid fabrik i\nVirserum (Kalmar l.).\n\nTelefon: 75 o. 200. Postgiro: 92400.\n\n—\tAkt.-kap.: 88,000 kr. Tillv.-värde pr\når: 550,000 kr. — Firman etabl. 1909,\nbolag 1938.\n\nChefer: disp. Harry Strömberg, kassör\nOlof Strömberg o. verkm. Lage\nStrömberg.",
    "structured": {
        "1": {
            "name": "AB. Strå Kalkbruk",
            "location": "Stockholm",
            "business": "Bryter kalksten och dolomit samt tillverkar bränd kalk för industri-, byggnads- och jordbruksändamål ävensom bränd dolomit för martinugnar. Bolaget idkar jämväl jordbruk.",
            "products": "Kalksten, dolomit, bränd kalk, bränd dolomit",
            "contact": {
                "office": "Jakobsbergsg. 2, Stockholm",
                "phone": [
                    "Strå Kalkbruk"
                ],
                "postgiro": "22200",
                "telegraph": "Stråkalk, Stockholm"
            },
            "financials": {
                "capital": "2,000,000 kr",
                "employees": {
                    "industriarb": 500
                },
                "annual_turnover": "Not available",
                "annual_production_value": "Not available"
            },
            "foundation_year": 1929,
            "board": [
                {
                    "name": "Vilhelm Björkman",
                    "role": "Ordinary Director"
                },
                {
                    "name": "Josef Gendt",
                    "role": "Director"
                },
                {
                    "name": "G. Raabe",
                    "role": "Director"
                }
            ]
        },
        "2": {
            "name": "Strängnäs Bryggeri AB.",
            "location": "Strängnäs",
            "business": "Tillverkar maltdrycker och kolsyrade drycker.",
            "contact": {
                "phone": "44",
                "postgiro": "143131"
            },
            "financials": {
                "capital": "250,000 kr",
                "employees": {
                    "industriarb": 19
                },
                "annual_turnover": "450,000 kr",
                "annual_production_value": "Not available"
            },
            "foundation_year": 1907,
            "board": [
                {
                    "name": "Gösta Sverdrup",
                    "role": "Chairman"
                },
                {
                    "name": "Hugo Carlberg",
                    "role": "Director"
                },
                {
                    "name": "Alvar Törnell",
                    "role": "Director"
                }
            ],
            "manager": "Gösta Sverdrup"
        },
        "3": {
            "name": "Strängnäs Elektr. Valskvarn",
            "location": "Strängnäs",
            "business": "Tillverkar mjöl, korngryn, kli och gröpe.",
            "products": "Mjöl, korngryn, kli, gröpe",
            "contact": {
                "phone": [
                    "502",
                    "506"
                ],
                "postgiro": "31973"
            },
            "financials": {
                "employees": {
                    "industriarb": 8
                },
                "annual_production_value": "700,000 kr"
            },
            "foundation_year": 1914,
            "owner": "Gustav Svenson"
        },
        "4": {
            "name": "C. C. Ströms AB.",
            "location": "Kumla",
            "business": "Tillverkar skodon vid fabrik i Kumla (Örebro l.).",
            "products": "Skodon",
            "contact": {
                "phone": "Örebro 70920",
                "postgiro": "6469"
            },
            "financials": {
                "capital": "800,000 kr",
                "employees": {
                    "industriarb": 145
                },
                "annual_turnover": "Not available",
                "annual_production_value": "2,500,000 kr"
            },
            "foundation_year": 1888,
            "corporation_year": 1930,
            "board": [
                {
                    "name": "Arvid Lindfelt",
                    "role": "Director"
                },
                {
                    "name": "Carl Einar Ström",
                    "role": "Manager"
                },
                {
                    "name": "Simon Ström",
                    "role": "Director"
                }
            ]
        },
        "5": {
            "name": "AB. Gust. Ström & Co.",
            "location": "Vansbro",
            "business": "Tillverkar byggnadssnickerier, inredningar och trappor vid fabrik i Vansbro (Kopparb. l.).",
            "products": "Byggnadssnickerier, inredningar, trappor",
            "contact": {
                "phone": "105",
                "postgiro": "163717"
            },
            "financials": {
                "capital": "120,200 kr",
                "employees": {
                    "industriarb": 25
                },
                "annual_production_value": "200,000 kr"
            },
            "foundation_year": 1925,
            "corporation_year": 1943,
            "owner": "Gustav Ström"
        },
        "6": {
            "name": "Ströms Bruks AB.",
            "location": "Strömsbruk",
            "business": "Tillverkar sulfitcellulosa, sulfitsprit och sågade trävaror. Bolaget idkar jämväl skogshantering och jordbruk.",
            "products": "Sulfitcellulosa, sulfitsprit, sågade trävaror",
            "contact": {
                "office": "Strömsbruk",
                "phone": "Strömsbruk 7",
                "postgiro": "26800",
                "sales_offices": [
                    {
                        "location": "Stocka",
                        "phone": "Not available"
                    },
                    {
                        "location": "Ljusne",
                        "phone": "Not available"
                    }
                ]
            },
            "financials": {
                "capital": "12,000,000 kr",
                "employees": {
                    "industriarb": 450
                },
                "annual_production_value": "Not available"
            },
            "foundation_year": 1873,
            "board": [
                {
                    "name": "Fabian Tamm",
                    "role": "Chairman"
                },
                {
                    "name": "Fabian Lundquist",
                    "role": "Director"
                },
                {
                    "name": "C. J. Robbert",
                    "role": "Director"
                },
                {
                    "name": "C. G. Rothelius",
                    "role": "Director"
                }
            ],
            "director": "Fabian Lundquist",
            "sales_manager": "Einar Oléhn"
        },
        "7": {
            "name": "Strömbacka Bruk",
            "location": "Strömbacka",
            "business": "Se AB. Iggesunds Bruk, Iggesund."
        },
        "8": {
            "name": "AB. H. Strömberg",
            "location": "Virserum",
            "business": "Tillverkar stoppade möbler vid fabrik i Virserum (Kalmar l.).",
            "products": "Stoppade möbler",
            "contact": {
                "phone": [
                    "75",
                    "200"
                ],
                "postgiro": "92400"
            },
            "financials": {
                "capital": "88,000 kr",
                "annual_production_value": "550,000 kr"
            },
            "foundation_year": 1909,
            "corporation_year": 1938,
            "director": "Harry Strömberg"
        }
    }
}