{
    "original": "Glemensnäs—G ondor verken\n\nFirman driver även engroshandel med\nisoleringsmateriel av främmande fabrikat\nsamt representerar vissa utländska\nmaskinfirmor för utrustnings- och\nhjälpmaskiner för fartyg.\n\nAkt.-kap.: 125,000 kr. Antal\nindustriarb.: 20. — Firman etabl. 1909, bolag\n1928.\n\nStyrelse o. verkst. dir.: Viking Clase.\n\nFörsäljn.-chef: ing. Carl-Otto Witte.\n\nClemensnäs Träsliperi, Klemensnäs.\n\nSe AB. Scharins Söner, Klemensnäs.\n\n*AB. Cleo, Ballingslöv.\n\nTillverkar rakblad vid fabrik i\nBallingslöv (Kristianst. l.). Varumärke: »Cleo».\n\nTelegr.-adr,: Cleo, Ballingslöv.\nTelefon: 73. Postgiro: 94398.\n\nAkt.-kap.: 22,000 kr. Antal\nindustriarb.: 9. Tillv.-värde pr år: 200,000 kr.\n\n—\tBolaget grundat 1934.\n\nVerkst. dir.: Nils E. Axelsson.\n\n*AB. cioetta, Ljungsbro.\n\nSe Svenska Chokladfabriks AB.,\nLjungsbro.\n\nAB. Cohn &amp; Lindblom, Göteborg.\n\nMössfabrik. Tillverkar skol- och\nuniformsmössor, sportmössor, spec.\nskidmös-sor, läder- och skinnmössor samt tyg- och\nläderhattar. Firman driver även\nengroshandel med herrhattar, pälsvaror samt\nmösskokarder.\n\nKontor: Kastellg. 1. Telegr.-adr.:\nCohn-blom, Göteborg. Telefon: 138091.\nPostgiro: 12158. Repr. i Stockholm: Rolf\nLilljekvist, Malmskillnadsg. 29, telefon:\n201338.\n\nAkt.-kap.: 60,000 kr. Antal\nindustriarb.: 60. Tillv.-värde pr år: 650,000 kr.\n\n—\tFirman etabl. 1901, bolag 1912.\n\nVerkst. dir.: Georg Nyman\n\nColgafabriken AB., Stockholm.\n\nKem. teknisk fabrik. Tillverkar\ntoaletttvål, raktvål, tvålflingor, skur- och\ntvätttvål, tråddragningspulver,\nhandrengöringsmedel, tvätt-v disk- och skurpulver.\nVarumärken: »Putsväck» o. »Colga».\n\nKontor: Huddingevägen 109; postadr.:\nStockholm 20. Telegr.-adr.: Putsväck,\nStockholm. Telefon: 492555. Postgiro:\n1801.\n\nAkt.-kap.: 40,000 kr. Antal\nindustriarb.: 30. Tillv.-värde pr år: 1,300,000 kr.\n\n—\tFirman grundad 1926\", bolag 1941.\n\nStyrelse: dir. A. Wober (ordf.), fru I.\n\nWober, ing. J. II. Åderman\n\nVerkst. dir.: A. Wober.\n\n*Golgate-Palmolive-Peet AB.,\n\nStockholm.\n\nTillverkar vid kem.-tekn. fabrik\ntoalett-tvål och toalettpreparat. Varumärken:\n»Colgate» o. »Palmolive».\n\nKontor: N. Stationsg. 79—81.\nTelegr.-adr.: Palmolive, Stockholm. Telefon:\n233610. Postgiro: 50285. Lager:\nÖstgö-tag. 50.\n\nAkt.-kap.: 500,000 kr. — Bolaget\ngrundat 1928.\n\nStyrelse: adv. Axel T. Nilsson, dir. W.\nL. Sims, dir. H. örtengren.\n\nVerkst. dir.: H. örtengren.\n\nKamrer: C. G. Griiting.\n\nIng.: R. E. Janerud.\n\n*AB. Collan-Olje-Fabriken, T. Oisen,\n\nStockholm.\n\nSe T. Oisens Fabriks AB., Stockholm.\n\n*AB. Gunnar Collijn, Stockholm.\n\nKonfektionsfabrik. Tillverkar\nherrkläder, damkappor och sportdräkter.\nVarumärke för herrkläder: »Collijns».\n\nKontor: Krukmakarg. 19.\nTélegr.-adr.: Collinbolag, Stockholm. Telefon:\n»Gunnar Collijn». Postgiro: 1761.\n\nAkt.-kap.: 600,000 kr. Antal\nindustriarb.: 500. Tillv.-värde pr år: 7,300,000\nkr. — Firman etabl. 1913.\n\nStyrelse: dir. Erik W. Paues (ordf.),\ninköpschef Gustav Morén, dir. Th. Öberg,\ndir. Arvid öhlin, herr Erik öhlin.\n\nVerkst. dir.: Arvid Öhlin.\n\n*CoIlins Tekn. Industri, Göteborg.\n\nFärg- och fernissfabrik. Tillverkar\nslamfärger, träkonserveringsfärger,\nlinoljefärger, emulsionsfärger, fernissor,\ncel-lulosalacker samt el. isolatianslacker.\n\nKontor: Tuvevägen; postadr.:\nGöteborg 8. Telegr.-adr.: Cotein, Göteborg.\nTelefon: 222040. Postgiro: 25421.\n\nAntal industriarb.;; 20. Tillv.-värde pr\når: 1,600,000 kr. — Firman etabl. 1917.\n\nÄgare o. chef: dir. Sven A. Höglund.\n\nFäbrihschef: ing. Sven Ahlström.\n\n*Condorverken AB., Göteborg.\n\nFärg- och fernissfabrik. Tillverkar olje-,\nlack-, sprit-, cellulosa- och syntetiska\nfärger och fernissor för alla ändamål,\nfärgborttagningsmedel, bonvax,\nugns-svärta m. m. Varumärken: »Triangeln»",
    "structured": {
        "1": {
            "name": "Glemensnäs—G ondor verken",
            "location": "Klemensnäs",
            "business": "Isoleringsmateriel och maskinhandel för fartyg",
            "contact": {
                "telegraph": "Cleo, Ballingslöv",
                "phone": [
                    "73"
                ],
                "postgiro": "94398"
            },
            "financials": {
                "capital": "125,000 kr",
                "employees": {
                    "industriarb": 20
                },
                "foundation_year": 1909,
                "corporation_year": 1928
            },
            "board": [
                {
                    "name": "Viking Clase",
                    "role": "Styrelse o. verkst. dir."
                },
                {
                    "name": "ing. Carl-Otto Witte",
                    "role": "Försäljn.-chef"
                }
            ]
        },
        "2": {
            "name": "AB. Cleo",
            "location": "Ballingslöv (Kristianst. l.)",
            "business": "Tillverkning av rakblad",
            "contact": {
                "telegraph": "Cleo, Ballingslöv",
                "phone": [
                    "73"
                ],
                "postgiro": "94398"
            },
            "financials": {
                "capital": "22,000 kr",
                "employees": {
                    "industriarb": 9
                },
                "annual_production_value": "200,000 kr",
                "foundation_year": 1934
            },
            "director": "Nils E. Axelsson"
        },
        "3": {
            "name": "AB. Cohn & Lindblom",
            "location": "Göteborg",
            "business": "Tillverkning av mössor och engroshandel med hattar och pälsvaror",
            "contact": {
                "office": "Kastellg. 1",
                "telegraph": "Cohn-blom, Göteborg",
                "phone": "138091",
                "postgiro": "12158",
                "sales_offices": [
                    {
                        "location": "Stockholm",
                        "phone": "201338"
                    }
                ]
            },
            "financials": {
                "capital": "60,000 kr",
                "employees": {
                    "industriarb": 60
                },
                "annual_production_value": "650,000 kr",
                "foundation_year": 1901,
                "corporation_year": 1912
            },
            "director": "Georg Nyman"
        },
        "4": {
            "name": "Colgafabriken AB.",
            "location": "Stockholm",
            "business": "Tillverkning av kemikalieprodukter såsom tvål och rengöringsmedel",
            "contact": {
                "office": "Huddingevägen 109",
                "telegraph": "Putsväck, Stockholm",
                "phone": "492555",
                "postgiro": "1801"
            },
            "financials": {
                "capital": "40,000 kr",
                "employees": {
                    "industriarb": 30
                },
                "annual_production_value": "1,300,000 kr",
                "foundation_year": 1926,
                "corporation_year": 1941
            },
            "board": [
                {
                    "name": "A. Wober",
                    "role": "Styrelse o. verkst. dir."
                }
            ]
        },
        "5": {
            "name": "Golgate-Palmolive-Peet AB.",
            "location": "Stockholm",
            "business": "Tillverkning av toalettprodukter och kosmetika",
            "contact": {
                "office": "N. Stationsg. 79—81",
                "telegraph": "Palmolive, Stockholm",
                "phone": "233610",
                "postgiro": "50285",
                "sales_offices": [
                    {
                        "location": "Lager",
                        "phone": "Östgö-tag. 50"
                    }
                ]
            },
            "financials": {
                "capital": "500,000 kr",
                "corporation_year": 1928
            },
            "board": [
                {
                    "name": "adv. Axel T. Nilsson",
                    "role": "Styrelse"
                },
                {
                    "name": "dir. W. L. Sims",
                    "role": "Styrelse"
                },
                {
                    "name": "dir. H. örtengren",
                    "role": "Styrelse"
                }
            ],
            "director": "H. örtengren",
            "manager": "C. G. Griiting",
            "engineer": "R. E. Janerud"
        },
        "6": {
            "name": "AB. Collan-Olje-Fabriken",
            "location": "Stockholm",
            "predecessor": "T. Oisens Fabriks AB."
        },
        "7": {
            "name": "AB. Gunnar Collijn",
            "location": "Stockholm",
            "business": "Tillverkning av konfektionskläder"
        },
        "8": {
            "name": "CoIlins Tekn. Industri",
            "location": "Göteborg",
            "business": "Tillverkning av färg- och fernissprodukter"
        },
        "9": {
            "name": "Condorverken AB.",
            "location": "Göteborg",
            "business": "Tillverkning av färg- och fernissprodukter",
            "contact": {
                "office": "Tuvevägen",
                "telegraph": "Cotein, Göteborg",
                "phone": "222040",
                "postgiro": "25421"
            },
            "financials": {
                "employees": {
                    "industriarb": 20
                },
                "annual_production_value": "1,600,000 kr"
            },
            "director": "Sven A. Höglund",
            "factory_manager": "Sven Ahlström"
        }
    }
}