{
    "original": "Lundb lad—Lundgren\n\nTelefon: Malmö 50264. Postgiro: 38922.\n\n—\tAntal industriarb.: 30. — Firman\netabl. 1924.\n\nÄgare o. chef: ing. Johnny Vigre.\n\n(Jfr annons nr 33.)\n\n\"Lundblad &amp; Nyholms Mek.\n\nVerkstad, Örnsköldsvik.\n\nSe A®- Maskinfabriken i Örnsköldsvik,\nÖrnsköldsvik.\n\n\"AB. Lundby Skönfärgeri &amp; Kem.\nTvättanstalt, Göteborg.\n\nUtför kemisk tvätt och färgning av\ndräkter, kappor, kostymer, gardiner,\nmattor m. m. samt konstsilketrikå.\n\nKontor: Säve Strandgata 3—4. Telefon:\n171210. Postgiro: 41032.\n\nAkt.-kap.: 280,000 kr. Antal\nindustriarb.: 125. Tillv.-värde pr år: 1,200,000 kr.\n\n—\tBolaget grundat 1898.\n\nStyrelse: kamrer E. Bunne (ordf.), ing.\nRudolf Jönsson, dir. Knut Martin.\nVerkst. dir.: Knut Martin.\nDisp.: Björn Hedberg.\n\nAug. Lundelis Gjuter! &amp; Mek.\nVerkstad, Bredaryd.\n\nSe AB. Bredaryds Mek. Verkstad,\nBredaryd.\n\nAB. Bengt Lundell, Borås.\n\nDamkonfektionsfabriker i Borås och i\nHerrljunga (Älvsb. l.). Tillverkar\nklänningar och blusar.\n\nKontor: Borås. Telefon: 18900.\nPostgiro: 263111. Repr. i Stockholm: Albert\nMårtensson, Riddarg. 18, telefon: 627425.\n\nAkt.-kap.: 50,000 kr. Antal\nindustriarb.: 52. — Bolaget grundat 1943.\n\nStyrelse o. verkst. dir.: Bengt Lundell.\n\n\"AB. Lundén &amp; Co., Stockholm.\nKonfektionsfabrik. Tillverkar\ngumme-rade och impregnerade kappor,\nplastic-kappor (märke: »Antivåt»), skidjackor,\nblusar m. m. Varumärken: »Lundens» o.\n»Lucos».\n\nKontor: Ranhammarsvägen 28,\nUlvsunda. Telegr.-adr.: Lundenkompani,\nStockholm. Telefon: Stockholm 284901\n—02—03. Postgiro: 54376.\n\nAkt.-kap.: 50,000 kr. Antal\nindustriarb.: 150. Tillv.-värde pr år: 3,000,000 kr.\n\n—\tFirman etabl. 1942.\n\nStyrelse: adv. Mauritz Griinberger\n(ordf.), fru O. Lagerheim-Thernell, dir.\nPer-Erik S:son Lundén.\n\nVerkst. dir.: Per-Erik S:son Lundén.\nDriftschef: Carl O. öhman.\n\no\n\n\"AB. Lundéns Möbler, Rosenfors.\n\nTillverkar möbler, stolar,\nkontorsmöbler samt inredningar vid fabrik i\nRosenfors (Kalmar l.).\n\nTelefon: 2. Postgiro: 23477. —\nAkt.-kap.: 60,000 kr. Antal industriarb.: 20.\nTillv.-värde pr år: 225,000 kr. —\nFirman etabl. 1904 under namn Rosenfors\nSnickeri- &amp; Möbelfabrik, bolag under\nnuv. namn 1945.\n\nStyrelse: disp. Harald Lundén (ordf.),\nmöbeltekn. Georg Lundén, verkm.\nHerbert Lundén.\n\nDisp.: Harald Lundén.\n\nLundgrens Fiskredskapsfabrik, AB.,\n\nStockholm.\n\nTillverkar fiskspön, drag, svirvlar,\nkrokar, fisksaxar, pimpeldon, angelredskap,\nrevar, linor, fisknät, kräftburar, håvar,\nryssjor, mjärdar, fiskfällor, mörtstugor\nm. m.\n\nKontor: Storkyrkobrinken 12. Telefon:\n102122. Postgiro: 2353. — Akt.-kap.:\n130,000 kr. — Firman etabl. 1892, bolag\n1922.\n\nStyrelse: kassör A. Govenius, dir. Arvid\nLindén, dir. Carl J. Löfqvist.\n\nVerkst. dir.: Carl J. Löfqvist.\n\nAB. Lundgrens Mek. Verkstad,\n\nMalmö.\n\nTillverkar maskiner för gummi- och\ntextilindustrier, för tvål-, kabel- och\nläderindustrier. Specialiteter:\ngolvslipma-skiner för mosaik samt hydrauliska hissar.\n\nKontor: Kopparbergsg. 5. Telefon:\n24494 o. 14744. Postgiro: 14198.\n\nAkt.-kap.: 75,000 kr. Antal\nindustriarb.: 40. Tillv.-värde pr år: 350,000 kr.\n— Firman etabl. 1912, bolag 1939.\n\nDisp.: Eric Jönsson.\n\n*AB. Lundgrens Söner, Malmö.\n\nUtför bok-, blankett-, affärs- och\nreklamtryck samt illustrations- och\nfärgtryck-\n\nKontor: Baltzarsg. 24. Telefon: 19081\no. 20106. Postgiro: 14044. — Akt.-kap.:\n180,000 kr. Antal industriarb.: 38.\nTillv.-värde pr år: 850,000 kr. — Firman etabl.\n1886, bolag 1903.\n\nStyrelse: boktr. Edvin»Lundgren (ordf.),\nfröken Anna Lisa Lundgren, boktr. Sven\nErik Lundgren.\n\nVerkst. direktörer: Edv. Lundgren o.\nS. E. Lundgren.",
    "structured": {
        "1": {
            "name": "Lundblad & Nyholms Mek. Verkstad",
            "location": "Örnsköldsvik",
            "business": "Maskinfabrik",
            "contact": {
                "phone": [
                    "Malmö 50264"
                ],
                "postgiro": "38922"
            },
            "financials": {
                "employees": {
                    "industriarb": 30
                },
                "capital": "Not Available"
            },
            "foundation_year": 1924,
            "director": "ing. Johnny Vigre"
        },
        "2": {
            "name": "AB. Lundby Skönfärgeri & Kem. Tvättanstalt",
            "location": "Göteborg",
            "business": "Kemisk tvätt och färgning",
            "contact": {
                "office": "Säve Strandgata 3—4",
                "phone": [
                    "171210"
                ],
                "postgiro": "41032"
            },
            "financials": {
                "capital": "280,000 kr",
                "employees": {
                    "industriarb": 125
                },
                "annual_production_value": "1,200,000 kr"
            },
            "foundation_year": 1898,
            "board": [
                {
                    "name": "kamrer E. Bunne",
                    "role": "ordf."
                },
                {
                    "name": "ing. Rudolf Jönsson",
                    "role": null
                },
                {
                    "name": "dir. Knut Martin",
                    "role": null
                }
            ],
            "manager": "Knut Martin"
        },
        "3": {
            "name": "AB. Bengt Lundell",
            "location": "Borås",
            "business": "Damkonfektionsfabriker",
            "contact": {
                "phone": [
                    "18900"
                ],
                "postgiro": "263111"
            },
            "financials": {
                "capital": "50,000 kr",
                "employees": {
                    "industriarb": 52
                }
            },
            "foundation_year": 1943,
            "board": [
                {
                    "name": "Bengt Lundell",
                    "role": "verkst. dir."
                }
            ]
        },
        "4": {
            "name": "AB. Lundén & Co.",
            "location": "Stockholm",
            "business": "Konfektionsfabrik",
            "contact": {
                "office": "Ranhammarsvägen 28, Ulvsunda",
                "phone": [
                    "Stockholm 284901—02—03"
                ],
                "postgiro": "54376"
            },
            "financials": {
                "capital": "50,000 kr",
                "employees": {
                    "industriarb": 150
                },
                "annual_production_value": "3,000,000 kr"
            },
            "foundation_year": 1942,
            "board": [
                {
                    "name": "adv. Mauritz Griinberger",
                    "role": "ordf."
                },
                {
                    "name": "fru O. Lagerheim-Thernell",
                    "role": null
                },
                {
                    "name": "dir. Per-Erik S:son Lundén",
                    "role": null
                }
            ],
            "manager": "Per-Erik S:son Lundén"
        },
        "5": {
            "name": "AB. Lundéns Möbler",
            "location": "Rosenfors",
            "business": "Möbeltillverkning",
            "contact": {
                "phone": [
                    "2"
                ],
                "postgiro": "23477"
            },
            "financials": {
                "capital": "60,000 kr",
                "employees": {
                    "industriarb": 20
                },
                "annual_production_value": "225,000 kr"
            },
            "foundation_year": 1904,
            "board": [
                {
                    "name": "disp. Harald Lundén",
                    "role": "ordf."
                },
                {
                    "name": "möbeltekn. Georg Lundén",
                    "role": null
                },
                {
                    "name": "verkm. Herbert Lundén",
                    "role": null
                }
            ]
        },
        "6": {
            "name": "Lundgrens Fiskredskapsfabrik, AB.",
            "location": "Stockholm",
            "business": "Tillverkning av fiskeredskap",
            "contact": {
                "office": "Storkyrkobrinken 12",
                "phone": [
                    "102122"
                ],
                "postgiro": "2353"
            },
            "financials": {
                "capital": "130,000 kr"
            },
            "foundation_year": 1892,
            "board": [
                {
                    "name": "kassör A. Govenius",
                    "role": null
                },
                {
                    "name": "dir. Arvid Lindén",
                    "role": null
                },
                {
                    "name": "dir. Carl J. Löfqvist",
                    "role": null
                }
            ],
            "director": "Carl J. Löfqvist"
        },
        "7": {
            "name": "AB. Lundgrens Mek. Verkstad",
            "location": "Malmö",
            "business": "Tillverkning av maskiner för olika industrier",
            "contact": {
                "office": "Kopparbergsg. 5",
                "phone": [
                    "24494",
                    "14744"
                ],
                "postgiro": "14198"
            },
            "financials": {
                "capital": "75,000 kr",
                "employees": {
                    "industriarb": 40
                },
                "annual_production_value": "350,000 kr"
            },
            "foundation_year": 1912,
            "manager": "Eric Jönsson"
        },
        "8": {
            "name": "AB. Lundgrens Söner",
            "location": "Malmö",
            "business": "Tryckeri",
            "contact": {
                "office": "Baltzarsg. 24",
                "phone": [
                    "19081",
                    "20106"
                ],
                "postgiro": "14044"
            },
            "financials": {
                "capital": "180,000 kr",
                "employees": {
                    "industriarb": 38
                },
                "annual_production_value": "850,000 kr"
            },
            "foundation_year": 1886,
            "board": [
                {
                    "name": "boktr. Edvin Lundgren",
                    "role": "ordf."
                },
                {
                    "name": "fröken Anna Lisa Lundgren",
                    "role": null
                },
                {
                    "name": "boktr. Sven Erik Lundgren",
                    "role": null
                }
            ],
            "managing_director": "Edv. Lundgren"
        }
    }
}