{
    "original": "Aurora—AvisO -systemet\n\nStyrelse: ing. O. Einar Augustsson,\nfröken Ester Augustsson, lantbr. Hans\nJönsson.\n\nVerTcst. dir.: O. Einar Augustsson.\n\nKamrer: Eric V. Augustsson.\n\n* Aurora, Tryckeri AB., Ystad.\n\nSe Tryckeri AB. Aurora, Ystad.\n\nAB. Automekan, Sundsvall.\n\nMek. verkstad. Tillverkar motordrivna\nhydrauliska tippanordningar. oljepumpar\nsamt hydrauliska verkstadspressar och\nuniversella motorställ.\n\nTelefon: 3232. Postgiro: 82505. —\nAkt.-kap.: 30,000 kr. Antal industriarb.:\n25. Tillv.-värde pr år: 350,000 kr. —\nFirman etabl. 1933.\n\nStyrelse o. verkst. dir.: disp. J. W.\nNorberg.\n\nAB. Auto-Metallfabrik, Ulvsunda.\n\nMetallfabrik och bleckslageri i\nUlvsunda, Stockholm. Tillverkar kylare och\nkylelement för motorer samt\nvärmebatterier, automobiltillbehör,\ncylinderlocks-packningar m. m.\n\nTelegr.-adr.: Autometall, Stockholm.\nTelefon: Stockholm 282695. Postgiro:\n75332. — Akt.-kap.: 100,000 kr. Antal\nindustriarb.: 130. — Firman etabl. 1914,\nbolag 1938.\n\nVerkst. dir.: fabr. Oscar Dahlberg.\n\n(Jfr annons nr 40.)\n\n*AB. Avancemotor, Eskilstuna.\n\nSe AB. Bolinder-Munktell, Eskilstuna.\n\nAB. A vant, Stockholm.\n\nMek. verkstad och metallskyltfabrik vid\nJakobsdal, Aspudden (Sthlm). Tillverkar\netsade skyltar och skalor, press- och\nstansverktyg, plåtpressnings- och\nsmides-arbeten, båtbojar, cykelbromsar,\nbiltillbehör m. m.\n\nKontor: Stockholm, Kungsg. 30.\nTelegr.-adr.: Avant, Stockholm. Telefon:\n230345. Postgiro: 1271.\n\nAkt.-kap.: 150,000 kr. Antal\nindustriarb.: 50. Tillv.-värde pr år: 600,000 kr.\n— Bolaget grundat 1930 under namn\nIndustri AB. Halba, nuv. namn 1945.\n\nVerkst. dir.: Gunnar Berglund.\n\nDisp.: Åke Hultberg.\n\n*Avesta Bryggeri AB., Avesta.\n\nTillverkar malt- och läskedrycker.\n\nTelefon: 5030. Postgiro: 98303. —\n\nAkt.-kap.: 200,000 kr. Antal industriarb.:\n15. — Bolaget grundat 1920.\n\nStyrelse o. verkst. dir.: Eric Åkesson.\n\nDisp.: I. Hintze.\n\n* Avesta Jer n verks AB., Avesta.\n\nMasugnar, legeringsugnar, martinverk,\nelektrostålverk, varm- och kallvalsverk,\npress- och svetsningsverk, mek. verkstad\noch gjuteri i Avesta, järnmalmsgruvor\nmed anriknings- och briketteringsverk vid\nNyberget, Smedjebacken (Kopparb. l.).\n\nTillverkar tackjärn, ferrolegeringar,\ngöten, stång- och fasonjärn, bergborrstål,\njärn- och stålplåt, pressade och svetsade\ngrovplåtsarbeten, pressade gasbehållare,\nkomprimerade och svarvade axlar, smiden,\nstål, och tackjärnsgjutgods m. m.\nSpecialitet: rostfritt, syrafast och\nvärmebestän-digt stål och gjutgods samt fabrikat\ndärav.\n\nKontor: Stockholm, Stureplan 3.\nTelegr.-adr.: Avestaverk, Stockholm.\nTelefon: »Johnsons», Stockholm. Postgiro:\n50730. Bruks- o. försäljn.-kontor: Avesta.\nTelegr.-adr. o. telefon: Jernverket, Avesta.\n\nAkt.-kap.: 8,000,000 kr. Antal\nindustriarb.: 2,200. Tillv.-värde pr år: 40,000,000\nkr.\n\nJärnverket leder sitt ursprung från\nbörjan av 1300-talet, övergick till\nbolagsform 1883. Bolaget äger Engelsbergs\nBruk, Högfors &amp; Persbo AB., Sala\nSilvergruva, Starbo Bruksägares AB., Krylbo\nTräförädlings AB. samt delar i Norbergs\nm. fl. gruvfält.\n\nStyrelse: generalkonsul Axel ^ Ax:son\nJohnson (ordf.), dir. Vilhelm Björkman,\ndisp. Walfrid Eriksson, bergsing. Axel\nAx:son Johnson J:r, dir. G. Raabe.\n\nVerkst. dir.: Axel Ax:son Johnson J:r.\n\nDisp.: Walfrid Eriksson.\n\nÖvering.: Sten Sandlund.\n\nKamrer: Sven Brinck-Erikson.\n\nPlatschef vid Nybergs gruvor: ing.\nAlbert Kättström.\n\n(Jfr annons efter Föreningsregistret.)\n\nAB. AvisO-systemet, Stockholm.\n\nTillverkar våningsregister, tavlor för\nvalutanoteringar, skyltning, utställningar,\nteater- och biografprogram, tidtabeller och\nmatsedlar samt orienteringstavlor för\nindustrier och ämbetsverk m. fl.\nVarumärke: »AvisO».\n\nKontor: Näckströmsg. 1. Telefon:\n110212. Postgiro: 3008. — Akt.-kap.:\n15,000 kr. Antal industriarb.: 6.\nTillv.-värde pr år: 125,000 kr. — Bolaget\ngrundat 1933.\n\nVerkst. dir.: ing. Walle Bergström.\n\n31",
    "structured": {
        "AuroraAvisO-Systemet": {
            "name": "Aurora AvisO-Systemet",
            "location": "Stockholm",
            "business": "Manufacturing of våningsregister, tavlor för valutanoteringar, skyltning, utställningar, teater- och biografprogram, tidtabeller and matsedlar",
            "products": "Orienteringstavlor för industrier and ämbetsverk",
            "contact": {
                "office": "Näckströmsg. 1",
                "phone": [
                    "110212"
                ],
                "postgiro": "3008"
            },
            "financials": {
                "capital": "15,000 kr",
                "employees": 6,
                "annual_turnover": "125,000 kr"
            },
            "foundation_year": 1933,
            "board": [
                {
                    "name": "ing. Walle Bergström",
                    "role": "Verkst. dir."
                }
            ]
        },
        "AvestaBryggeriAB": {
            "name": "Avesta Bryggeri AB",
            "location": "Avesta",
            "business": "Manufacturing of malt- and läskedrycker",
            "contact": {
                "phone": [
                    "5030"
                ],
                "postgiro": "98303"
            },
            "financials": {
                "capital": "200,000 kr",
                "employees": 15
            },
            "foundation_year": 1920,
            "board": [
                {
                    "name": "Eric Åkesson",
                    "role": "Styrelse o. verkst. dir."
                },
                {
                    "name": "I. Hintze",
                    "role": "Disp."
                }
            ]
        },
        "AvestaJernverksAB": {
            "name": "Avesta Jernverks AB",
            "location": "Avesta",
            "business": "Manufacturing of tackjärn, ferrolegeringar, göten, stång- and fasonjärn, bergborrstål, järn- och stålplåt, pressade and svetsade grovplåtsarbeten, pressade gasbehållare, komprimerade and svarvade axlar, smiden, stål, and tackjärnsgjutgods",
            "products": "Rostfritt, syrafast and värmebestän-digt stål and gjutgods",
            "contact": {
                "office": "Stureplan 3",
                "factory_office": "Avesta",
                "sales_offices": [
                    {
                        "location": "Stockholm",
                        "phone": "»Johnsons»"
                    }
                ],
                "postgiro": "50730"
            },
            "financials": {
                "capital": "8,000,000 kr",
                "employees": 2200,
                "annual_turnover": "40,000,000 kr"
            },
            "foundation_year": "Början av 1300-talet",
            "board": [
                {
                    "name": "Axel ^ Ax:sonJohnson",
                    "role": "Styrelse"
                },
                {
                    "name": "Vilhelm Björkman",
                    "role": "dir."
                },
                {
                    "name": "Walfrid Eriksson",
                    "role": "disp."
                },
                {
                    "name": "Axel Ax:sonJohnson J:r",
                    "role": "bergsing."
                },
                {
                    "name": "G. Raabe",
                    "role": "dir."
                }
            ],
            "director": "Axel Ax:son Johnson J:r",
            "managing_director": "Walfrid Eriksson",
            "sales_manager": "Sten Sandlund"
        },
        "Auto-MetallfabrikUlvsunda": {
            "name": "Auto-Metallfabrik Ulvsunda",
            "location": "Ulvsunda, Stockholm",
            "business": "Manufacturing of kylare and kylelement for motorer, värmebatterier, automobiltillbehör, cylinderlocks-packningar m. m.",
            "contact": {
                "telegraph": "Autometall, Stockholm",
                "phone": "Stockholm 282695",
                "postgiro": "75332"
            },
            "financials": {
                "capital": "100,000 kr",
                "employees": 130
            },
            "corporation_year": 1938,
            "board": [
                {
                    "name": "fabr. Oscar Dahlberg",
                    "role": "Verkst. dir."
                }
            ]
        },
        "AutomekanSundsvall": {
            "name": "Automekan Sundsvall",
            "location": "Sundsvall",
            "business": "Tillverkar motordrivna hydrauliska tippanordningar, oljepumpar samt hydrauliska verkstadspressar and universella motorställ",
            "contact": {
                "phone": "3232",
                "postgiro": "82505"
            },
            "financials": {
                "capital": "30,000 kr",
                "employees": 25,
                "annual_turnover": "350,000 kr"
            },
            "foundation_year": 1933,
            "board": [
                {
                    "name": "disp. J. W. Norberg",
                    "role": "Styrelse o. verkst. dir."
                }
            ]
        },
        "AvancemotorEskilstuna": {
            "name": "Avancemotor Eskilstuna",
            "location": "Eskilstuna",
            "business": "See AB. Bolinder-Munktell, Eskilstuna"
        },
        "A-vantStockholm": {
            "name": "A-vant Stockholm",
            "location": "Stockholm",
            "business": "Mek. verkstad and metallskyltfabrik",
            "products": "Etsade skyltar and skalor, press- and stansverktyg, plåtpressnings- and smides-arbeten, båtbojar, cykelbromsar, biltillbehör m. m.",
            "contact": {
                "office": "Stockholm, Kungsg. 30",
                "phone": [
                    "230345"
                ],
                "postgiro": "1271"
            },
            "financials": {
                "capital": "150,000 kr",
                "employees": 50,
                "annual_turnover": "600,000 kr"
            },
            "corporation_year": 1945,
            "board": [
                {
                    "name": "Gunnar Berglund",
                    "role": "Verkst. dir."
                },
                {
                    "name": "Åke Hultberg",
                    "role": "Disp."
                }
            ]
        }
    }
}