{
    "original": "Wäija—Värme ledning\n\nTelefon: 520430. Postgiro: 2248.\nAvd.-kontor: i Lund, telefon: 17345; i\nKarlstad, telefon: 15095; i Umeå, telefon:\n4498.\n\nAkt.-kap.: 1,000,000 kr.\nOmsättningsvärde pr år: 13,000,000 kr.\n\nBolaget, grundat 1918, äger Maskin AB.\nKristian, Stockholm.\n\nStyrelse: envoyé Hugo v. Heidenstam\n(ordf.), bergsing. J. A. Bonthron, adv.\nKleve Hultin, civiling. Hilmer Melin,\ning. Per Wretlind.\n\nVerkst. dir.: Hilmer Melin.\n\nArbetschefer: i Stockholm: civiling.\nW. Kruse; i Lund: civiling. Gunnar\nTranaeus; i Karlstad: civiling. Hj.\nSjöblom; i Umeå: civiling. P. Rönström.\n\n*Wäija Pappersbruk, Väja.\n\nSe Dynäs AB., Väja.\n\nVänerns Motor verkstad, Nordquist\n&amp; Co., Vänersborg.\n\nMek. verkstad och gjuteri. Tillverkar\nråoljemotorer och motorvinschar,\nankarspel samt gjutgods i järn och metall.\nVarumärke: »Vänern».\n\nTelegr.-adr.: Vänermotor, Vänersborg.\nTelefon: 533 o. 1325. Postgiro: 15298.\n\nAntal industriarb.: 45. Tillv.-värde pr\når: 400,000 kr. — Firman etabl. 1920.\n\nÄgare o. chefer: fabr. Robert Nordquist,\nfabr. Valfrid Nordquist, fabr. William\nNordquist o. fabr. Vendel Nordquist.\n\n*AB. Vänerns Träförädlingsfabrik,\n\nLidköping.\n\nSnickerifabrik, sågverk, hyvleri och\nlådfabrik. Tillverkar byggnadssnickerier,\nspec. lamelldörrar (märke:\n»Star-dör-ren»), sågade och hyvlade trävaror samt\nlådämnen. Bolaget idkar jämväl\nskogshantering.\n\nTelegr.-adr.: Vänersträ, Lidköping.\nTelefon: 22245. Postgiro: 85360.\n\nAkt.-kap.: 400,000 kr. Antal\nindustriarb.: 175. Tillv.-värde pr år: 3,000,000 kr.\n\nFöretaget grundades 1907 och äges av\nJönköpings och Vulcans\nTändsticksfabriks AB., Jönköping.\n\nStyrelse: dir. Torsten Jung (ordf.),\ndisp. Gösta Birgersson, disp. Einar\nOlau-son.\n\nVerkst. dir.: Gösta Birgersson.\n\nFabrikschef: S. Nordin.\n\nKontorschef: Erik Larson.\n\n* Vänersborgs Bryggeri,\n\nVänersborg.\n\nSe AB. Pripp &amp; Lyckholm, Göteborg.\n\n^Vänersborgs Sko- o. Läderfabrik,\n\nVänersborg.\n\nSe AB. A. F. Carlssons Skofabrik,\nVänersborg.\n\n*Vännäs Sko- &amp; Läderfabriks AB.,\n\nVännäsby.\n\nGarveri och skofabrik i Vännäsby\n(Västerbott. l.). Tillverkar pjäx- och\nsport-läder samt sportskor och norrlandspjäxor.\n\nVarumärke: »Vännässko».\n\nTelegr.-adr.: Vännässko, Vännäsby.\nTelefon: 1 o. 37. Postgiro: 62273.\n\nAkt.-kap.: 200,000 kr. Antal\nindustriarb.: 60. — Bolaget grundat 1923.\n\nStyrelse: riksdagsm. Nils Gabrielsson\n(ordf.), fänrik Matts Hamrén, disp. Olle\nHamrén, lantbr. Amelius Ohlsson,\nsko-handl. Olle Åström.\n\nDisp.: O. Hamrén.\n\nAB. Värends Glasbruk, Lenhovda.\n\nGlasbruk i Lenhovda (Kronob. l.) för\nmaskintillverkning av buteljer och\nlivsmedelsglas. Varumärke: »V».\n\nTelefon: 84 o. 86. — Akt.-kap.: 48,100\nkr. Antal industriarb.: 32. Tillv.-värde pr\når: 225,000 kr. — Firman etabl. 1936.\n\nVerkst. dir.: Eric Nilsson.\n\nVärings Textilindustri AB.,\n\nVäring.\n\nTillverkar charmeuseväv vid väveri i\nVäring (Skarab. l.).\n\nTelefon: 48. Postgiro: 168068. —\nAkt.-kap.: 45,000 kr. Arb.-antal: 7.\nTillv.-värde pr år: 400,000 kr. — Bolaget\ngrundat 1939.\n\nVerkst. dir.: Arvid Axelson.\n\n* Värme-Elektr. AB., Svenska,\n\nUlvsunda.\n\nSe Svenska Värme-Elektr. AB.,\nUlvsunda.\n\n^Värmelednings AB. Calor,\n\nUlvsunda.\n\nMek. verkstad i Ulvsunda (Stockholm).\nTillverkar maskiner och apparater för\nmaskintvätt, ångköks-, desinfektions- och\nsteriliseringsanläggningar,\nspecialcentri-fuger, autoklaver, kokare med\nomrörar-verk, maskiner för livsmedels- och kemisk\ntekniska industrier samt textilmaskiner;\nutför värmelednings- och sanitära\ninstallationer samt värmeanläggningar för\nhögtryck.",
    "structured": {
        "firms": [
            {
                "name": "Wäija—Värme ledning",
                "location": "Sweden",
                "contact": {
                    "phone": [
                        "520430"
                    ],
                    "postgiro": "2248",
                    "sales_offices": [
                        {
                            "location": "Lund",
                            "phone": "17345"
                        },
                        {
                            "location": "Karlstad",
                            "phone": "15095"
                        },
                        {
                            "location": "Umeå",
                            "phone": "4498"
                        }
                    ]
                },
                "financials": {
                    "capital": "1,000,000 kr",
                    "annual_turnover": "13,000,000 kr"
                },
                "foundation_year": 1918,
                "board": [
                    {
                        "name": "envoyé Hugo v. Heidenstam",
                        "role": "ordf."
                    },
                    {
                        "name": "bergsing. J. A. Bonthron",
                        "role": null
                    },
                    {
                        "name": "adv. Kleve Hultin",
                        "role": null
                    },
                    {
                        "name": "civiling. Hilmer Melin",
                        "role": null
                    },
                    {
                        "name": "ing. Per Wretlind",
                        "role": null
                    }
                ],
                "director": "Hilmer Melin",
                "managing_director": null,
                "sales_manager": null,
                "manager": null
            },
            {
                "name": "Vänerns Motor verkstad, Nordquist & Co.",
                "location": "Vänersborg, Sweden",
                "contact": {
                    "phone": [
                        "533",
                        "1325"
                    ],
                    "postgiro": "15298"
                },
                "financials": {
                    "employees": {
                        "industriarb": 45
                    },
                    "annual_production_value": "400,000 kr"
                },
                "foundation_year": 1920,
                "owners": [
                    "fabr. Robert Nordquist",
                    "fabr. Valfrid Nordquist",
                    "fabr. William Nordquist",
                    "fabr. Vendel Nordquist"
                ]
            },
            {
                "name": "AB. Vänerns Träförädlingsfabrik",
                "location": "Lidköping, Sweden",
                "contact": {
                    "phone": "22245",
                    "postgiro": "85360"
                },
                "financials": {
                    "capital": "400,000 kr",
                    "employees": {
                        "industriarb": 175
                    },
                    "annual_production_value": "3,000,000 kr"
                },
                "foundation_year": 1907,
                "owners": [
                    "Jönköpings och Vulcans Tändsticksfabriks AB., Jönköping"
                ]
            },
            {
                "name": "Vänersborgs Bryggeri",
                "location": "Vänersborg, Sweden"
            },
            {
                "name": "Vänersborgs Sko- o. Läderfabrik",
                "location": "Vänersborg, Sweden"
            },
            {
                "name": "Vännäs Sko- & Läderfabriks AB.",
                "location": "Vännäsby (Västerbotten), Sweden",
                "contact": {
                    "phone": [
                        "1",
                        "37"
                    ],
                    "postgiro": "62273"
                },
                "financials": {
                    "capital": "200,000 kr",
                    "employees": {
                        "industriarb": 60
                    }
                },
                "foundation_year": 1923,
                "board": [
                    {
                        "name": "riksdagsm. Nils Gabrielsson",
                        "role": "ordf."
                    },
                    {
                        "name": "fänrik Matts Hamrén",
                        "role": null
                    },
                    {
                        "name": "disp. Olle Hamrén",
                        "role": null
                    },
                    {
                        "name": "lantbr. Amelius Ohlsson",
                        "role": null
                    },
                    {
                        "name": "sko-handl. Olle Åström",
                        "role": null
                    }
                ],
                "director": null,
                "managing_director": null,
                "sales_manager": null,
                "manager": null
            },
            {
                "name": "AB. Värends Glasbruk",
                "location": "Lenhovda (Kronob. l.), Sweden",
                "contact": {
                    "phone": [
                        "84",
                        "86"
                    ]
                },
                "financials": {
                    "capital": "48,100 kr",
                    "employees": {
                        "industriarb": 32
                    },
                    "annual_production_value": "225,000 kr"
                },
                "foundation_year": 1936,
                "board": [
                    {
                        "name": "dir. Torsten Jung",
                        "role": "ordf."
                    },
                    {
                        "name": "disp. Gösta Birgersson",
                        "role": null
                    },
                    {
                        "name": "disp. Einar Olau-son",
                        "role": null
                    }
                ],
                "director": "Gösta Birgersson",
                "managing_director": null,
                "sales_manager": null,
                "manager": null
            },
            {
                "name": "Värings Textilindustri AB.",
                "location": "Väring (Skarab. l.), Sweden",
                "contact": {
                    "phone": "48",
                    "postgiro": "168068"
                },
                "financials": {
                    "capital": "45,000 kr",
                    "employees": {
                        "Arb.-antal": 7
                    },
                    "annual_production_value": "400,000 kr"
                },
                "foundation_year": 1939,
                "director": "Arvid Axelson",
                "managing_director": null,
                "sales_manager": null,
                "manager": null
            },
            {
                "name": "Värmelednings AB. Calor",
                "location": "Ulvsunda (Stockholm), Sweden"
            }
        ]
    }
}