{
    "original": "Slipers—Slutar p\n\nSlipers AB., Stockholm.\n\nUtför impregnering av kraftlednings-,\ntelefon- och telegrafstolpar,\njärnvägs-sliprar och sågat virke, även med å\njärnväg flyttbara impregneringsverk.\n\nKontor: Banérg. 4. Telegr.-adr.:\nSlipers, Stockholm. Telefon: 620027.\nPostgiro: 24524. Representanter: Malmö:\nJörgen Kocksg. 4, telefon: 26950; Göteborg:\nÖ. Hamng. 2, telefon: 116803.\n\nAkt.-kap.: 175,000 kr. Antal\nindustriarb.: 100. Prod.-värde pr år: 4,000,000 kr.\n— Bolaget grundat 1899.\n\nVerkst. dir.: ing. Tore Sjöholm.\n\n\"AB. Slipmaterial — Naxos,\n\nVästervik.\n\nFabriker i Västervik, Lomma\n(Malmöh. l.) och Baskarp (Skarab. l.).\n\nTillverkar slipskivor, brynen, slipstift,\nskurstenar, stensågklingor, kapskivor,\nslippapper och slipduk (»Kronmärket»)\nför trä-, läder-, järn- och\nmetallbearbetning m. m. såsom flintpapper\n(sandpapper), korundpapper, granatpapper,\nsmär-gelduk och korundduk, skoslipartiklar\netc., elektrokorund (alumo), kiselkarbid\n(sicto) och desoxil, stålsand, magnetiska\nehuckar, slip-, kap- och polérmaskiner,\nslipskiveavsvarvningsverktyg,\nstenslipma-skiner, stensågmaskiner samt\navmagneti-seringsapparater.\n\nHuvudkontor: Västervik. Telegr.-adr.\no. telefon: »Slipmaterial», Västervik.\nPostgiro: 14818. Fabrikskontor: Lomma\noch Baskarp. Filialkontor: Stockholm,\nJohn Ericssonsg. 9, telefon: 520990;\nGöteborg, Skeppsbroplatsen 1, telefon:\n139455.\n\nAkt.-kap.: 1,500,000 kr. Antal\nindustriarb.: 430. Tillv.-värde pr år: 10,000,000 kr.\n\nBolaget bildat år 1942 genom\nsammanslagning av AB. Slipmaterial, Västervik,\ngrundat 1913, och AB. Svenska Naxos,\nLomma, grundat 1895.\n\nStyrelse: dir. P. Eg. Gummeson (ordf.),\ndisp. Ossian Nilsson, dir. M. Schwartz.\n\nVerkst. dir.: Ossian Nilsson.\n\nFÖrsäljn.-dir.: Birger Börjesson.\n\nKamrer: Alb. Yourstone.\n\nFilialchefer: i Stockholm: ing. W.\nLöf-gren; i Göteborg: F. Hagström.\n\n(Jfr annons före\nTillverkningsregistret.)\n\nSlipsfabriken AB., Svenska, Malmö.\n\nSe Svenska Slipsfabriken AB., Malmö.\n\nSlipskivefabriken Svea AB.,\n\nStockholm.\n\nTillverkar keramiska-, silikat- och\nbakelitbundna slipskivor samt brynen vid\nfabrik i Norrtälje.\n\nKontor: Klarabergsg. 58. Telegr.-adr.:\nSlipsvea, Stockholm. Telefon: 108250.\nPostgiro: 51842.\n\nAkt.-kap.: 40,000 kr. Arb.-antal: 10.\nTillv.-värde pr år: 225,000 kr.\n\nFabriken anlagd 1916, nuv. bolag\ngrundat 1943.\n\nVerkst. dir.: Magnus Edlund.\n\nDriftsing.: Emil Zeland.\n\nSI i te Cement och Kalk AB., Slite.\n\nCementfabrik i Slite (Gotlands l.).\nTillverkar portlandcement.\n\nKontor: Slite. Telegr.-adr. o. telefon:\nSlitecement, Slite. Postgiro: 23131.\nEn-samförsälj.: Cementa, Svenska\nCement-försäljn. AB., Malmö, Stockholm o.\nGöteborg.\n\nAkt.-kap.: 3,057,500 kr. Antal\nindustriarb.: 250. — Bolaget grundat 1917.\n\nStyrelse: dir. Arendt de Jounge,\növerstelöjtn. Carl O. A. Nyström, dir.\nMalte Ström, dir. Ernst Wehtje, övering.\nDonovan Werner.\n\nVerkst. dir. o. disp.: Arendt de Jounge.\n\nKamrer: Fritz Olofsson.\n\n*Slitmanfabriken, Stockholm.\n\nSe Konfektions AB. S:t Erik,\nStockholm.\n\n\"Slottsbrons Sulfitfabrik, Slottsbron.\n\nSe Billeruds AB., Säffle.\n\n\"Slottsmöllans Tegelbruk, Halmstad.\n\nSe Wallbergs Fabriks AB., Halmstad.\n\n\"AB. Slutarps Möbelindustri,\n\nSlutarp.\n\nTillverkar möbler, speciellt\nkompletteringsmöbler vid fabrik i Slutarp\n(Skarab. l.).\n\nTelefon: Kinnarp 45. Postgiro: 33549.\n—. Akt.-kap.: 80,000 kr. Antal\nindustriarb.: 33. Tillv.-värde pr år: 300,000 kr.\n— Firman etabl. 1929, bolag 1935.\n\nStyrelse: fabr. Hädar Levinson (ordf.),\nfabr. Gunnar Gustavsson, köpm. Eric\nSamuelsson.\n\nVerkst. direktörer: Hadar Levinson o.\nGunnar Gustavsson.\n\n49*",
    "structured": {
        "1": {
            "name": "Slipers AB",
            "location": "Stockholm",
            "business": "Utför impregnering av kraftlednings-, telefon- och telegrafstolpar, järnvägs-sliprar och sågat virke, även med å järnväg flyttbara impregneringsverk.",
            "contact": {
                "office": "Banérg. 4",
                "phone": [
                    "620027"
                ],
                "postgiro": "24524",
                "sales_offices": [
                    {
                        "location": "Malmö",
                        "phone": "26950"
                    },
                    {
                        "location": "Göteborg",
                        "phone": "116803"
                    }
                ],
                "telegraph": "Slipers, Stockholm",
                "factory_office": "Not Available",
                "factory_phone": "Not Available"
            },
            "financials": {
                "capital": "175,000 kr",
                "employees": {
                    "industriarb": 100
                },
                "annual_turnover": "4,000,000 kr",
                "annual_production_value": "Not Available"
            },
            "foundation_year": 1899,
            "current_name_year": null,
            "predecessor": null,
            "original_name": "Not Available",
            "corporation_year": null,
            "board": [
                {
                    "name": "Not Available",
                    "role": "Not Available"
                }
            ],
            "owners": [
                "Not Available"
            ],
            "director": "ing. Tore Sjöholm",
            "managing_director": "Not Available",
            "sales_manager": "Not Available",
            "manager": "Not Available"
        },
        "2": {
            "name": "AB. Slipmaterial - Naxos",
            "location": "Västervik",
            "business": "Tillverkar slipskivor, brynen, slipstift, skurstenar, stensågklingor, kapskivor, slippapper och slipduk (»Kronmärket») för trä-, läder-, järn- och metallbearbetning m. m. såsom flintpapper (sandpapper), korundpapper, granatpapper, smär-gelduk och korundduk, skoslipartiklar etc., elektrokorund (alumo), kiselkarbid (sicto) och desoxil, stålsand, magnetiska ehuckar, slip-, kap- och polérmaskiner, slipskiveavsvarvningsverktyg, stenslipma-skiner, stensågmaskiner samt avmagneti-seringsapparater.",
            "contact": {
                "office": "Västervik",
                "phone": [
                    "Not Available"
                ],
                "postgiro": "14818",
                "sales_offices": [
                    {
                        "location": "Stockholm",
                        "phone": "520990"
                    },
                    {
                        "location": "Göteborg",
                        "phone": "139455"
                    }
                ],
                "telegraph": "Not Available",
                "factory_office": "Lomma and Baskarp",
                "factory_phone": "Not Available"
            },
            "financials": {
                "capital": "1,500,000 kr",
                "employees": {
                    "industriarb": 430
                },
                "annual_turnover": "10,000,000 kr",
                "annual_production_value": "Not Available"
            },
            "foundation_year": 1942,
            "current_name_year": null,
            "predecessor": "AB. Slipmaterial, Västervik, grundat 1913, and AB. Svenska Naxos, Lomma, grundat 1895",
            "original_name": "Not Available",
            "corporation_year": null,
            "board": [
                {
                    "name": "dir. P. Eg. Gummeson (ordf.)",
                    "role": "Not Available"
                },
                {
                    "name": "disp. Ossian Nilsson",
                    "role": "Not Available"
                },
                {
                    "name": "dir. M. Schwartz",
                    "role": "Not Available"
                }
            ],
            "owners": [
                "Not Available"
            ],
            "director": "Ossian Nilsson",
            "managing_director": "Not Available",
            "sales_manager": "Birger Börjesson",
            "manager": "Not Available"
        },
        "3": {
            "name": "Slipskivefabriken Svea AB",
            "location": "Stockholm",
            "business": "Tillverkar keramiska-, silikat- och bakelitbundna slipskivor samt brynen vid fabrik i Norrtälje.",
            "contact": {
                "office": "Klarabergsg. 58",
                "phone": [
                    "108250"
                ],
                "postgiro": "51842",
                "sales_offices": [],
                "telegraph": "Slipsvea, Stockholm",
                "factory_office": "Not Available",
                "factory_phone": "Not Available"
            },
            "financials": {
                "capital": "40,000 kr",
                "employees": {
                    "industriarb": 10
                },
                "annual_turnover": "225,000 kr",
                "annual_production_value": "Not Available"
            },
            "foundation_year": 1943,
            "current_name_year": null,
            "predecessor": null,
            "original_name": "Not Available",
            "corporation_year": null,
            "board": [
                {
                    "name": "Not Available",
                    "role": "Not Available"
                }
            ],
            "owners": [
                "Not Available"
            ],
            "director": "Magnus Edlund",
            "managing_director": "Not Available",
            "sales_manager": "Not Available",
            "manager": "Emil Zeland"
        },
        "4": {
            "name": "SI i te Cement och Kalk AB",
            "location": "Slite",
            "business": "Cementfabrik i Slite (Gotlands l.). Tillverkar portlandcement.",
            "contact": {
                "office": "Slite",
                "phone": [
                    "Not Available"
                ],
                "postgiro": "23131",
                "sales_offices": [],
                "telegraph": "Slitecement, Slite",
                "factory_office": "Not Available",
                "factory_phone": "Not Available"
            },
            "financials": {
                "capital": "3,057,500 kr",
                "employees": {
                    "industriarb": 250
                },
                "annual_turnover": "Not Available",
                "annual_production_value": "Not Available"
            },
            "foundation_year": 1917,
            "current_name_year": null,
            "predecessor": null,
            "original_name": "Not Available",
            "corporation_year": null,
            "board": [
                {
                    "name": "dir. Arendt de Jounge",
                    "role": "Not Available"
                },
                {
                    "name": "överstelöjtn. Carl O. A. Nyström",
                    "role": "Not Available"
                },
                {
                    "name": "dir. Malte Ström",
                    "role": "Not Available"
                },
                {
                    "name": "dir. Ernst Wehtje",
                    "role": "Not Available"
                },
                {
                    "name": "övering. Donovan Werner",
                    "role": "Not Available"
                }
            ],
            "owners": [
                "Not Available"
            ],
            "director": "Arendt de Jounge",
            "managing_director": "Not Available",
            "sales_manager": "Not Available",
            "manager": "Fritz Olofsson"
        },
        "5": {
            "name": "AB. Slutarps Möbelindustri",
            "location": "Slutarp",
            "business": "Tillverkar möbler, speciellt kompletteringsmöbler vid fabrik i Slutarp (Skarab. l.).",
            "contact": {
                "office": "Not Available",
                "phone": [
                    "Kinnarp 45"
                ],
                "postgiro": "33549",
                "sales_offices": [],
                "telegraph": "Not Available",
                "factory_office": "Not Available",
                "factory_phone": "Not Available"
            },
            "financials": {
                "capital": "80,000 kr",
                "employees": {
                    "industriarb": 33
                },
                "annual_turnover": "300,000 kr",
                "annual_production_value": "Not Available"
            },
            "foundation_year": 1935,
            "current_name_year": null,
            "predecessor": null,
            "original_name": "Not Available",
            "corporation_year": null,
            "board": [
                {
                    "name": "fabr. Hädar Levinson (ordf.)",
                    "role": "Not Available"
                },
                {
                    "name": "fabr. Gunnar Gustavsson",
                    "role": "Not Available"
                },
                {
                    "name": "köpm. Eric Samuelsson",
                    "role": "Not Available"
                }
            ],
            "owners": [
                "Not Available"
            ],
            "director": "Hadar Levinson o. Gunnar Gustavsson",
            "managing_director": "Not Available",
            "sales_manager": "Not Available",
            "manager": "Not Available"
        }
    }
}