{
    "original": "Delin—Djupafors\n\nTelefon: 21995 o. 30809. Postgiro:\n6870.\n\nAkt.-kap.: 75,000 kr. Antal\nindustriarb.: 28. Tillv.-värde pr år: 850,000 kr.\n\n—\tBolaget grundat 1932.\n\nStyrelse o. verkst. dir.: Sven Knutson.\nFörsäljn.-chef: Helge Peterson.\n\n’Delin &amp; Perslow, Stockholm.\n\nSe AB. Tekniska Byggnadsbyrån,\nDelin &amp; Perslow, Stockholm.\n\nDeltafor AB Örebro.\n\nKemisk teknisk fabrik. Tillverkar\nvitamin-, hormon- och kem. tekniska\npreparat för lantbruk. Varumärken:\n»Deltafor» o. »Deltaplex».\n\nTelefon: 16181. Postgiro: 34038. —\nAkt.-kap.: 20,000 kr. Antal industriarb.:\n15. Tillv.-värde pr år: 800,000 kr. —\nBolaget grundat 1942.\n\nVerkst. dir.: Lars-Eric Adler.\nDisp.: Fritz Ågren.\n\nAB. Dentatus, Aspudden.\n\nMek. verkstad i Aspudden, Stockholm.\nTillverkar apparater, instrument och\nförbrukningsartiklar för tandläkare.\nSpecialitet: Diamantslipinstrument\n(slipskivor och andra slipkroppar, bestående av\ndiamantpulver infattat i metall).\n\nTelegr.-adr.: Dentatus, Stockholm 9.\nTelefon: 452775. Postgiro: 56412.\n\nAkt.-kap.: 600,000 kr. Antal\nindustriarb.: 65. Tillv.-värde pr år: 900,000 kr.\n\n—\tBolaget grundat 1930.\n\nVerkst. dir.: ing. Gustaf E. Björklund.\n\nAB. Detre* Vejbystrand.\n\nTräförädlingsfabrik i Vejbystrand\n(Kristianst. l.). Tillverkar inredningar,\npentrys, bord för bordtennis, radiolådor\nm. m. Varumärke: »DETRE».\n\nTelefon: 100 o. 200. Postgiro: 299890.\n\n—\tAkt.-kap.: 50,000 kr. Antal\nindustriarb.: 40. — Firman etabl. 1945.\n\nVerkst. dir.: Gustaf Sandberg.\nDisp.: Axel Persson.\n\n’Diamantbergborrnings AB.,\n\nStockholm.\n\nSe Svenska Diamantbergborrnings AB.,\nStockholm.\n\nDidriksons Oljeklädersfabrik,\nLöfström &amp; Bäcker, iGrundsmid.\n\nTillverkar olje- och gummikläder för\nfiske, sjöfart, gruvarbete, lantbruk m. fl.\nändamål samt finare regnkläder m. m.\n\nvid fabrik i Grunclsund (Göteb. o. Bohus\n1.). Varumärke: »D O» (i femuddig\nstjärna).\n\nTelefon: 1. Postgiro: 9725.\nRepresentanter: grossh. John Persson,\nNorrköping, telefon: 21734; Olof Nilsson,\nHälsingborg, Färjemansg. 34, telefon:\n11919.\n\nAntal industriarb.: 30. Tillv.-värde pr\når: 300,000 kr. — Firman etabl. 1913\nunder namn Didrikson, Grunden 4 Co.,\nnuv. namn 1939.\n\nÄgare: disp. Lars E. Bäcker o. civiling.\nBernt Löfström.\n\nDisp.: Lars E. Bäcker.\n\n*Diesels Motorer, Saltsjö-Nacka.\n\nSe AB. Atlas Diesel, Stockholm.\n\nAB. Dissousgas, Vänersborg.\n\nGasverk i Vänersborg och Karlskrona.\nTillverkar acetyléngas i behållare för\nsvetsning, belysning och bildrift.\n\nHuvudkontor: Vänersborg. Telefon:\n553. Postgiro: 23155. Avd.-kontor:\nKarlskrona, telefon: 1077.—Akt.-kap.: 125,000\nkr. Arb.-antal: 7. Tillv.-värde pr år:\n200,000 kr. — Firman grundad 1913.\n\nStyrelse: överdir. T. Emers (ordf.),\ndir. Gunnar Dalén, ing. Curt Plass,\ndistriktschef L. Påhlson.\n\nVerkst. dir.: fröken Beth Wester.\n\n’Anders Diös, Uppsala.\n\nByggnadsfirma.\n\nTelefon: 39350. Postgiro: 5131.\nFilialkontor: Enköping o. Västerås. —\nProd.-värde pr år: 20,000,000 kr. — Firman\netabl,. 1921,\n\nChef: ing. Anders V. Diös.\n\nFilialchefer: Enköping: byggm. David\nSundström; Västerås: ing. Herman\nStjernberg.\n\nAB, Djeddi, Jönköping.\n\nKonfektionsfabrik, charmeuseväveri och\nfärgeri. Tillverkar korsettartiklar,\ndamunderkläder, blusar i charmeuse samt\nherr-och gosskjortbr^ Varumärke: »Djeddi».\n\nTelefon: 3056 o. 4787. Postgiro: 135625.\n\nAkt.-kap.: 65,000 kr. Antal\nindustriarb.: 50. — Bolaget grundat 1937.\n\nVerkst. dir.: fabr. Hjalmar Blomgren.\n\n’Djupafors Fabriks AB.,\n\nKallinge station.\n\nPapp- och kartongfabriker med\nträsliperi vid Djupafors, Kallinge station\n(Blekinge l.). Tillverkar papp och\nkartong.\n\n108*",
    "structured": {
        "1": {
            "name": "Delin—Djupafors",
            "location": "Kallinge station",
            "business": "Papp- och kartongfabriker",
            "products": "Tillverkar papp och kartong.",
            "contact": {
                "phone": [
                    "21995",
                    "30809"
                ],
                "postgiro": "6870"
            },
            "financials": {
                "capital": "75,000 kr",
                "employees": {
                    "industriarb": 28
                },
                "annual_turnover": "850,000 kr",
                "annual_production_value": "850,000 kr"
            },
            "foundation_year": 1932,
            "board": [
                {
                    "name": "Sven Knutson",
                    "role": "Styrelse o. verkst. dir."
                },
                {
                    "name": "Helge Peterson",
                    "role": "Försäljn.-chef"
                }
            ]
        },
        "2": {
            "name": "Deltafor AB Örebro",
            "location": "Örebro",
            "business": "Kemisk teknisk fabrik",
            "products": "Tillverkar vitamin-, hormon- och kem. tekniska preparat för lantbruk. Varumärken: »Deltafor» o. »Deltaplex».",
            "contact": {
                "phone": "16181",
                "postgiro": "34038"
            },
            "financials": {
                "capital": "20,000 kr",
                "employees": {
                    "industriarb": 15
                },
                "annual_turnover": "800,000 kr",
                "annual_production_value": "800,000 kr"
            },
            "foundation_year": 1942,
            "director": "Lars-Eric Adler",
            "sales_manager": "Fritz Ågren"
        },
        "3": {
            "name": "AB. Dentatus, Aspudden",
            "location": "Aspudden, Stockholm",
            "business": "Mek. verkstad",
            "products": "Tillverkar apparater, instrument och förbrukningsartiklar för tandläkare. Specialitet: Diamantslipinstrument (slipskivor och andra slipkroppar, bestående av diamantpulver infattat i metall).",
            "contact": {
                "office": "Mek. verkstad i Aspudden, Stockholm.",
                "phone": "452775",
                "postgiro": "56412"
            },
            "financials": {
                "capital": "600,000 kr",
                "employees": {
                    "industriarb": 65
                },
                "annual_turnover": "900,000 kr",
                "annual_production_value": "900,000 kr"
            },
            "foundation_year": 1930,
            "director": "ing. Gustaf E. Björklund"
        },
        "4": {
            "name": "AB. Detre* Vejbystrand",
            "location": "Vejbystrand (Kristianst. l.)",
            "business": "Träförädlingsfabrik",
            "products": "Tillverkar inredningar, pentrys, bord för bordtennis, radiolådor m. m. Varumärke: »DETRE».",
            "contact": {
                "phone": [
                    "100",
                    "200"
                ],
                "postgiro": "299890"
            },
            "financials": {
                "capital": "50,000 kr",
                "employees": {
                    "industriarb": 40
                }
            },
            "foundation_year": 1945,
            "director": "Gustaf Sandberg",
            "sales_manager": "Axel Persson"
        },
        "5": {
            "name": "Diamantbergborrnings AB., Stockholm",
            "business": "Se Svenska Diamantbergborrnings AB., Stockholm"
        },
        "6": {
            "name": "Didriksons Oljeklädersfabrik, Löfström & Bäcker",
            "location": "Grundsmid",
            "business": "Tillverkar olje- och gummikläder",
            "products": "Tillverkar olje- och gummikläder för fiske, sjöfart, gruvarbete, lantbruk m. fl. ändamål samt finare regnkläder m. m. Varumärke: »D O» (i femuddig stjärna).",
            "contact": {
                "phone": "1",
                "postgiro": "9725",
                "sales_offices": [
                    {
                        "location": "Norrköping",
                        "phone": "21734"
                    },
                    {
                        "location": "Hälsingborg, Färjemansg. 34",
                        "phone": "11919"
                    }
                ]
            },
            "financials": {
                "employees": {
                    "industriarb": 30
                },
                "annual_turnover": "300,000 kr"
            },
            "foundation_year": 1913,
            "current_name_year": 1939,
            "owners": [
                "disp. Lars E. Bäcker",
                "civiling. Bernt Löfström"
            ],
            "director": "Lars E. Bäcker"
        },
        "7": {
            "name": "Diesels Motorer, Saltsjö-Nacka",
            "business": "Se AB. Atlas Diesel, Stockholm"
        },
        "8": {
            "name": "AB. Dissousgas, Vänersborg",
            "location": "Vänersborg",
            "business": "Gasverk",
            "products": "Tillverkar acetyléngas i behållare för svetsning, belysning och bildrift.",
            "contact": {
                "phone": "553",
                "postgiro": "23155",
                "sales_offices": [
                    {
                        "location": "Karlskrona",
                        "phone": "1077"
                    }
                ]
            },
            "financials": {
                "capital": "125,000 kr",
                "employees": {
                    "Arb.-antal": 7
                },
                "annual_turnover": "200,000 kr"
            },
            "foundation_year": 1913,
            "board": [
                {
                    "name": "överdir. T. Emers",
                    "role": "ordf."
                },
                {
                    "name": "dir. Gunnar Dalén",
                    "role": "distriktschef"
                }
            ],
            "director": "fröken Beth Wester"
        },
        "9": {
            "name": "Anders Diös, Uppsala",
            "location": "Uppsala",
            "business": "Byggnadsfirma",
            "contact": {
                "phone": "39350",
                "postgiro": "5131"
            },
            "financials": {
                "annual_turnover": "20,000,000 kr"
            },
            "foundation_year": 1921,
            "director": "ing. Anders V. Diös",
            "sales_manager": "Filialchefer: Enköping: byggm. David Sundström; Västerås: ing. Herman Stjernberg"
        },
        "10": {
            "name": "AB, Djeddi, Jönköping",
            "location": "Jönköping",
            "business": "Konfektionsfabrik, charmeuseväveri och färgeri",
            "products": "Tillverkar korsettartiklar, damunderkläder, blusar i charmeuse samt herr- och gosskjortbr^. Varumärke: »Djeddi».",
            "contact": {
                "phone": [
                    "3056",
                    "4787"
                ],
                "postgiro": "135625"
            },
            "financials": {
                "capital": "65,000 kr",
                "employees": {
                    "industriarb": 50
                }
            },
            "foundation_year": 1937,
            "director": "fabr. Hjalmar Blomgren"
        },
        "11": {
            "name": "Djupafors Fabriks AB., Kallinge station",
            "business": "Papp- och kartongfabriker",
            "products": "Tillverkar papp och kartong."
        }
    }
}