{
    "original": "Västervik—Västkusten\n\nAkt.-kap.: 200.000 kr. Antal\nindustriarb.: 110. Årstillv.: 12,000 ton papp och\nkartong. — Fabriken anlagd 1915, nuv.\nbolag grundat 1923.\n\nStyrelse: adv. Gunnar Lewerth (ordf.),\ntandl. E. Rune, disp. E. V. Ulfsäter.\n\nVerkst. dir. o. disp.: E. V. Ulfsäter.\n\nInhöpschef: V. Lönnberg.\n\n\"Västerviks Trikå- &amp; Syfabrik,\n\nVästervik.\n\nSe AB. Victorin och Strand, Västervik.\n\n\"Västerviks Tändsticksfabrik,\n\nVästervik.\n\nSe Jönköpings och Vulcans\nTändsticksfabriks AB., Jönköping.\n\nVästerås.\n\n\"Westerås Bryggeri AB. (Gamla\nBryggeriet), Västerås.\n\nTillverkar maltdrycker, läskedrycker\nsamt mineralvatten.\n\nTelegr.-adr.: Bryggeribolaget, Västerås.\nTelefon: 30003, 30070 o. 30757. Postgiro:\n93100.\n\nAkt.-kap.: 270,000 kr. Antal\nindustriarb.: 35. Tillv.-värde pr år: 1,200,000 kr.\n\nFirman etabl. 1854 under namn Gamla\nBryggeriet, nuv. namn och bolag 1892.\n\nStyrelse: adv. F. Hydbom (ordf.), ing.\nCurt R. Widén, dir. Joel Widén.\n\nVerkst. dir. o. disp.: Joel Widén.\n\nDir.-assist.: Curt R. Widén.\n\nKamrer: Torsten Wahlberg.\n\nBryggmäst.: Torsten Omstedt.\n\n\"AB. Westeråsmaskiner,\n\nMorgongåva.\n\nMek. verkstad, gjuteri och sågverk i\nMorgongåva (Västmanl. l.). Tillverkar\nslåttermaskiner, självbindare, hästräfsor,\nradsåningsmaskiner, gödselspridare,\ntröskverk, linuppryckningsmaskiner, kvarnar\nm. m., gjutgods samt sågade och hyvlade\nträvaror.\n\nTelegr.-adr.: Westeråsmaskin,\nMorgongåva. Telefon: 1. Postgiro: 74898.\nEx-portförsäljn.-kontor: Stockholm, Kungsg.\n26; telegr.-adr.: Westeråsmaskin,\nStockholm; telefon: 231165. Ensamförsälj. för\nSverige: And. Fischer AB., Stockholm,\nKungsg. 26, telefon: 231165.\n\nAkt.-kap.: 2,000,000 kr. Antal\nindustriarb.: 450. — Bolaget grundat 1874,\nom-bildat 1908.\n\nStyrelse: adv. Clas Östberg (ordf.),\ndir. Th. E. Berg, dir. Erik O. G.\nBolin-der, bankdir. Ernst Åberg.\n\nVerkst. dir.: Erik O. G. Bolinder\n(Sthlm).\n\nPlatschef: disp. E. Hedqvist.\n\nVästerås Strå- &amp; Filthattfabrik AB.,\n\nVästerås.\n\nTillverkar damhattar.\nTelegr.-adr.: Hattfabriken, Västerås.\nTelefon: 31958 o. 30598. Postgiro: 22833.\nAvd.-kontor: Stockholm, Kungsg. 51,\ntelefon: 105912 o. 206030.\n\nAkt.-kap.: 300,000 kr. Antal\nindustriarb.: 80. Tillv.-värde pr år: 1,200,000 kr.\n—- Firman etabl. 1920, bolag 1932.\n\nStyrelse o. firmatechnare: avd.-chef E.\nFridlund, kamrer G. Kruhsberg,\ninköpschef W. Liljegren, avd.-chef G. Norstedt.\n\nAB. Wästgöta Konstsilke,\n\nStenstorp.\n\nTillverkar herr- och damunderkläder i\ncharmeuse vid fabrik i Stenstorp\n(Skarab. l.).\n\nTelefon: 106. Postgiro: 146398. Repr. i\nStockholm: AB. Importcentralen,\nKungs-holmsg. 31, telefon: 513060.\n\nAkt.-kap.: 57,000 kr. Antal\nindustriarb.: 30. Tillv.-värde pr år: 400,000 kr.\n\n—\tFirman etabl. 1938.\nDisp.: Erik Svensson.\n\nAB. Västgöta Täckfabrik,\n\nHerrljunga.\n\nTillverkar vadd, sticktäcken och\nmadrasser vid fabrik i Herrljunga (Älvsb.\n1.).\n\nTelefon: 154. Postgiro: 25090. —\nAkt.-kap.: 30,000 kr. Arb.-antal: 6.\nTillv.-värde pr år: 200,000 kr. — Bolaget\ngrundat 1939.\n\nVerkst. dir.: fabr. Per Enger.\n\nVästkusten.\n\nAB. Vestkustens Olje- &amp;\nGuano-fabrik, Lysekil.\n\nTillverkar sillolja och sillmjöl vid\nfabrik i Oxevik, Dragsmark (Göteb. o.\nBohus l.).\n\nKontor: Lysekil. Telegr.-adr.: Radhe,\nLysekil. Telefon: Lysekil 8 o. 430.\nPostgiro: 34528.\n\nAkt.-kap.: 50,000 kr. Arb.-antal: 12.\n\n—\tFirman etabl. 1898, bolag 1938.\nVerkst. dir.: Walter Börjesson.\n",
    "structured": {
        "1": {
            "name": "Västervik—Västkusten",
            "location": "Västervik",
            "business": "Papp och kartong tillverkning",
            "products": "12 000 ton papp och kartong",
            "contact": {
                "office": "Fabriken anlagd 1915, nuv. bolag grundat 1923.",
                "postgiro": "Not provided"
            },
            "financials": {
                "capital": "200 000 kr",
                "employees": {
                    "industriarb": 110
                },
                "annual_turnover": "Not provided",
                "annual_production_value": "Not provided"
            },
            "foundation_year": 1923,
            "board": [
                {
                    "name": "adv. Gunnar Lewerth",
                    "role": "ordf."
                },
                {
                    "name": "tandl. E. Rune",
                    "role": "Not provided"
                },
                {
                    "name": "disp. E. V. Ulfsäter",
                    "role": "Not provided"
                }
            ],
            "director": "E. V. Ulfsäter",
            "manager": "V. Lönnberg"
        },
        "2": {
            "name": "Westerås Bryggeri AB. (Gamla Bryggeriet)",
            "location": "Västerås",
            "business": "Dryckestillverkning",
            "products": "Maltdrycker, läskedrycker, mineralvatten",
            "contact": {
                "office": "Not provided",
                "phone": [
                    "30003",
                    "30070",
                    "30757"
                ],
                "postgiro": "93100"
            },
            "financials": {
                "capital": "270 000 kr",
                "employees": {
                    "industriarb": 35
                },
                "annual_turnover": "1 200 000 kr",
                "annual_production_value": "Not provided"
            },
            "foundation_year": 1892,
            "board": [
                {
                    "name": "adv. F. Hydbom",
                    "role": "ordf."
                },
                {
                    "name": "ing. Curt R. Widén",
                    "role": "Not provided"
                },
                {
                    "name": "dir. Joel Widén",
                    "role": "Not provided"
                }
            ],
            "director": "Joel Widén",
            "managing_director": "Curt R. Widén",
            "sales_manager": "Not provided"
        },
        "3": {
            "name": "AB. Westeråsmaskiner",
            "location": "Morgongåva",
            "business": "Mekanisk verkstad, gjuteri och sågverk",
            "products": "Slåttermaskiner, hästräfsor, tröskverk, trävaror m.m.",
            "contact": {
                "office": "Not provided",
                "phone": "1",
                "postgiro": "74898"
            },
            "financials": {
                "capital": "2 000 000 kr",
                "employees": {
                    "industriarb": 450
                },
                "annual_turnover": "Not provided",
                "annual_production_value": "Not provided"
            },
            "foundation_year": 1908,
            "board": [
                {
                    "name": "adv. Clas Östberg",
                    "role": "ordf."
                },
                {
                    "name": "dir. Th. E. Berg",
                    "role": "Not provided"
                },
                {
                    "name": "dir. Erik O. G. Bolinder",
                    "role": "bankdir. Ernst Åberg"
                }
            ],
            "director": "Erik O. G. Bolinder",
            "manager": "E. Hedqvist"
        },
        "4": {
            "name": "Västerås Strå- & Filthattfabrik AB.",
            "location": "Västerås",
            "business": "Tillverkning av damhattar",
            "products": "Damhattar",
            "contact": {
                "office": "Not provided",
                "phone": [
                    "31958",
                    "30598"
                ],
                "postgiro": "22833"
            },
            "financials": {
                "capital": "300 000 kr",
                "employees": {
                    "industriarb": 80
                },
                "annual_turnover": "1 200 000 kr",
                "annual_production_value": "Not provided"
            },
            "foundation_year": 1932,
            "board": [
                {
                    "name": "avd.-chef E. Fridlund",
                    "role": "Not provided"
                },
                {
                    "name": "kamrer G. Kruhsberg",
                    "role": "Not provided"
                },
                {
                    "name": "avd.-chef G. Norstedt",
                    "role": "Not provided"
                }
            ]
        },
        "5": {
            "name": "AB. Wästgöta Konstsilke",
            "location": "Stenstorp",
            "business": "Tillverkning av herr- och damunderkläder",
            "products": "Herr- och damunderkläder i charmeuse",
            "contact": {
                "director": "Erik Svensson"
            },
            "financials": {
                "capital": "57 000 kr",
                "employees": {
                    "industriarb": 30
                },
                "annual_turnover": "400 000 kr",
                "annual_production_value": "Not provided"
            },
            "foundation_year": 1938
        },
        "6": {
            "name": "AB. Västgöta Täckfabrik",
            "location": "Herrljunga",
            "business": "Tillverkning av vadd, sticktäcken och madrasser",
            "products": "Vadd, sticktäcken, madrasser",
            "contact": {
                "office": "Not provided",
                "phone": "154",
                "postgiro": "25090"
            },
            "financials": {
                "capital": "30 000 kr",
                "employees": {
                    "industriarb": 6
                },
                "annual_turnover": "200 000 kr",
                "annual_production_value": "Not provided"
            },
            "foundation_year": 1939,
            "director": "fabr. Per Enger"
        },
        "7": {
            "name": "AB. Vestkustens Olje- & Guano-fabrik",
            "location": "Lysekil",
            "business": "Tillverkning av sillolja och sillmjöl",
            "products": "Sillolja, sillmjöl",
            "contact": {
                "office": "Not provided",
                "phone": [
                    "Lysekil 8",
                    "430"
                ],
                "postgiro": "34528"
            },
            "financials": {
                "capital": "50 000 kr",
                "employees": {
                    "industriarb": 12
                },
                "annual_turnover": "Not provided",
                "annual_production_value": "Not provided"
            },
            "foundation_year": 1938,
            "director": "Walter Börjesson"
        }
    }
}