{
    "original": "Björk—Björne b or g\n\n*0. Björks Snickerifabrik, Bollnäs.\n\nTillverkar möbler och\nstoppmöbelstom-mar vid fabrik i Bollnäs (Gävleb. l.).\n\nTelefon: 10421. Postgiro: 95195. —\nAntal industriarb.: 10. Tillv.-värde pr\når: 75,000 kr. — Firman etabl. 1923.\n\nÄgare o. chef: fabr. Olof Björk.\n\nGustaf Björklund &amp; Son, Åkarp.\n\nSe Alnarps Redskapsverkstad, Gustaf\nBjörklund &amp; Son, Åkarp.\n\nBjörkshults Glasbruk, Nya AB.,\n\nBjörkedal.\n\nSe Nya AB. Björkshults Glasbruk,\nBjörkedal.\n\nBjörksätra Lädervaru AB.,\n\nAnderstorp.\n\nTillverkar shopping väskor,\nportmonnäer, plånböcker, portföljer,\nreklamartiklar m. m. vid fabrik i Anderstorp\n(Jönköp. l.).\n\nTelefon: 178. — Tillv.-värde pr år:\n400,000 kr. — Firman etabl. 1941.\n\nVerkst. dir.: fabr. Artur Karlsson.\n\n*AB. Björkträ, Viksjöfors.\n\nSnickerifabrik i Viksjöfors, sågverk i\nMållångstad (båda i Gävleb. l.).\nTillverkar kvastkäppar och skaft, pinnar av\nbjörk (dowels), trädgårdsmöbler,\ntältstänger, sparkstöttings- och kälkreden,\npenselskaft, svarvgods m. m.\n\nTelegr.-adr.: Björkträ, Bollnäs.\nTelefon: Viksjöfors 21. Postgiro: 36546. —\nAkt.-kap.: 45,000 kr. Antal industriarb.:\n72. — Firman etabl. 1923, bolag 1932.\n\nStyrelse: disp. Joh. Sahlin (ordf.), fru\nM. Ohlner, verkm. Erik Sahlin.\n\nChef: disp. Joh. Sahlin.\n\n*Björkå AB., Björkabruk.\n\nSågverk vid Lugn vik, träsliperi vid\nHallstanäs (båda i Västernorrl. l.).\nTillverkar sågade trävaror och mek. trämassa.\n\nHuvudkontor: Björkåbruk.\nTelegr.-adr.: Norberg, Nyland. Telefon: Nyland\n8. Postgiro: 13121. Avd.-kontor i\nLugnvik. Telegr.-adr.: Lugnviksåg, Nyland.\nTelefon: Nyland 9. Försal jn.-kontor:\nHärnösand, telefon: 2056.\n\nAkt.-kap.: 2,600,000 kr. Antal\nindustriarb.: 275. Årstillv.: 12,000 stds sågade\nträvaror, 100.000 ton våt vit mek.\nträmassa. — Bolaget grundat 1872, nuv.\nbolagsordning 1933.\n\nStyrelse: kapten Hjalmar Hedberg\n(ordf.), grossh. Emil Eriksson, dir.-assist.\nPer Olof Hedberg, dir. Theodor\nHedberg, bankdir. I. Wallmark.\n\nVerkst. dir.: Hjalmar Hedberg.\nFörvalt.: Bo Holmberg.\n\nBjörkå Glasbruk, Älghultsby.\n\nSe Kommanditbolaget Gleisner &amp; Co.,\nÄlghultsby.\n\n*AB. Björköby Lådfabrik, Björköby.\n\nSågverk, hyvleri och lådfabrik i\nBjörköby ( Jönköp. l.). Tillverkar lådämnen samt\nsågade och hyvlade trävaror.\n\nTelegr.-adr.: Boxes, Björköby. Telefon:\n37. Postgiro: 168040. Repr. i England:\nBritish Boxboard Agency, Ltd., Bath.\n\nAkt.-kap.: 45,000 kr. Antal\nindustriarb.: 30. Tillv.-värde pr år: 1,200,000 kr.\n— Bolaget grundat 1940.\n\nStyrelse: disp. Gustaf Ahnlid (ordf.),\ndir. Helgard Milton.\nDisp.: F. G. Ahnlid.\n\n*Björns Tegelbruk AB., Luleå.\n\nTillverkar murtegel vid tegelbruk i\nNorra Sunderbyn (Norrb. l.). Specialitet:\nhögporöst murtegel.\n\nKontor: Luleå. Telegr.-adr.: Aburman,\nLuleå. Telefon: 2028. Postgiro: 65252. —\nAkt.-kap.: 100,000 kr. Antal industriarb.:\n35. Årstillv.: 2 milj. st. tegel. — Bruket\ngrundat 1898, bolag 1945.\n\nVerkst. dir.: v. konsul Atle Burman.\nDisp.: Hardy Burman.\n\nAB. Björnbandsfabriken,\n\nKarlstad.\n\nTillverkar färgband för\nkontorsmaskiner samt kontorsklister och stämpeldynor.\nVarumärken: »Björnband», »Record-lim»\no. »Björndynan».\n\nTelegr.-adr.: Björnband, Karlstad.\nTelefon: 10540 o. 14540. Postgiro: 8200.\n\nAkt.-kap.: 18,000 kr. — Firman etabl.\n1912 under namn Skandinaviska\nSkriv-bandsfabriken, bolag 1923, nuv. namn\n1936.\n\nStyrelse o. verkst. dir.: disp. Lennart\nRehnborg.\n\nKamrer: Torgny Rehnborg.\n\n^Björneborgs Jernverks AB.,\n\nBjörneborg.\n\nJärnverk med masugnar, martinverk,\nånghammar- och manufaktursmedja, mek.\nverkstad och gjuteri vid Björneborg\n(Värml. L).",
    "structured": {
        "0": {
            "name": "Björks Snickerifabrik",
            "location": "Bollnäs",
            "business": "Tillverkar möbler och stoppmöbelstommar",
            "products": "vid fabrik i Bollnäs (Gävleb. l.)",
            "contact": {
                "office": "Bollnäs",
                "phone": [
                    "10421"
                ],
                "postgiro": "95195"
            },
            "financials": {
                "capital": "Not available",
                "employees": {
                    "industriarb": 10
                },
                "annual_turnover": "75,000 kr",
                "annual_production_value": "75,000 kr"
            },
            "foundation_year": 1923,
            "owner": "Olof Björk"
        },
        "1": {
            "name": "Gustaf Björklund & Son",
            "location": "Åkarp",
            "business": "Not available",
            "contact": {
                "office": "Åkarp"
            }
        },
        "2": {
            "name": "Björkshults Glasbruk, Nya AB.",
            "location": "Björkedal",
            "business": "Not available"
        },
        "3": {
            "name": "Björksätra Lädervaru AB.",
            "location": "Anderstorp",
            "business": "Tillverkar shopping väskor, portmonnäer, plånböcker, portföljer, reklamartiklar m.m.",
            "products": "vid fabrik i Anderstorp (Jönköp. l.)",
            "contact": {
                "office": "Anderstorp",
                "phone": [
                    "178"
                ],
                "postgiro": "Not available"
            },
            "financials": {
                "capital": "Not available",
                "employees": {
                    "industriarb": "Not available"
                },
                "annual_turnover": "400,000 kr",
                "annual_production_value": "400,000 kr"
            },
            "foundation_year": 1941,
            "director": "Artur Karlsson"
        },
        "4": {
            "name": "AB. Björkträ",
            "location": "Viksjöfors",
            "business": "Snickerifabrik i Viksjöfors, sågverk i Mållångstad (båda i Gävleb. l.)",
            "products": "Tillverkar kvastkäppar och skaft, pinnar av björk (dowels), trädgårdsmöbler, tältstänger, sparkstöttings- och kälkreden, penselskaft, svarvgods m.m.",
            "contact": {
                "office": "Viksjöfors",
                "phone": "Viksjöfors 21",
                "postgiro": "36546",
                "factory_office": "Not available",
                "factory_phone": "Not available"
            },
            "financials": {
                "capital": "45,000 kr",
                "employees": {
                    "industriarb": 72
                },
                "annual_turnover": "Not available",
                "annual_production_value": "Not available"
            },
            "foundation_year": 1923,
            "corporation_year": 1932,
            "board": [
                {
                    "name": "Joh. Sahlin",
                    "role": "disp."
                },
                {
                    "name": "fru M. Ohlner",
                    "role": "Not available"
                },
                {
                    "name": "verkm. Erik Sahlin",
                    "role": "Not available"
                }
            ],
            "director": "disp. Joh. Sahlin"
        },
        "5": {
            "name": "Björkå AB.",
            "location": "Björkabruk",
            "business": "Sågverk vid Lugn vik, träsliperi vid Hallstanäs (båda i Västernorrl. l.)",
            "products": "Tillverkar sågade trävaror och mek. trämassa",
            "contact": {
                "office": "Björkåbruk",
                "phone": "Nyland 8",
                "postgiro": "13121",
                "sales_offices": [
                    {
                        "location": "Lugnvik",
                        "phone": "Nyland 9"
                    },
                    {
                        "location": "Härnösand",
                        "phone": "2056"
                    }
                ]
            },
            "financials": {
                "capital": "2,600,000 kr",
                "employees": {
                    "industriarb": 275
                },
                "annual_turnover": "Not available",
                "annual_production_value": "Not available"
            },
            "foundation_year": 1872,
            "corporation_year": 1933,
            "board": [
                {
                    "name": "kapten Hjalmar Hedberg",
                    "role": "ordf."
                },
                {
                    "name": "grossh. Emil Eriksson",
                    "role": "Not available"
                },
                {
                    "name": "dir.-assist. Per Olof Hedberg",
                    "role": "Not available"
                },
                {
                    "name": "dir. Theodor Hedberg",
                    "role": "Not available"
                },
                {
                    "name": "bankdir. I. Wallmark",
                    "role": "Not available"
                }
            ],
            "director": "Hjalmar Hedberg"
        },
        "6": {
            "name": "Björkå Glasbruk",
            "location": "Älghultsby"
        },
        "7": {
            "name": "AB. Björköby Lådfabrik",
            "location": "Björköby",
            "business": "Sågverk, hyvleri och lådfabrik i Björköby (Jönköp. l.)",
            "products": "Tillverkar lådämnen samt sågade och hyvlade trävaror",
            "contact": {
                "office": "Björköby",
                "phone": "37",
                "postgiro": "168040"
            },
            "financials": {
                "capital": "45,000 kr",
                "employees": {
                    "industriarb": 30
                },
                "annual_turnover": "1,200,000 kr",
                "annual_production_value": "1,200,000 kr"
            },
            "foundation_year": 1940,
            "board": [
                {
                    "name": "disp. Gustaf Ahnlid",
                    "role": "ordf."
                },
                {
                    "name": "dir. Helgard Milton",
                    "role": "Not available"
                }
            ],
            "director": "disp. Gustaf Ahnlid"
        },
        "8": {
            "name": "Björns Tegelbruk AB.",
            "location": "Luleå",
            "business": "Tillverkar murtegel vid tegelbruk i Norra Sunderbyn (Norrb. l.)"
        },
        "9": {
            "name": "AB. Björnbandsfabriken",
            "location": "Karlstad",
            "business": "Tillverkar färgband för kontorsmaskiner samt kontorsklister och stämpeldynor",
            "products": "Varumärken: »Björnband», »Record-lim» o. »Björndynan»",
            "contact": {
                "office": "Karlstad",
                "phone": [
                    "10540",
                    "14540"
                ],
                "postgiro": "8200"
            },
            "financials": {
                "capital": "18,000 kr"
            },
            "foundation_year": 1912,
            "corporation_year": 1923,
            "current_name_year": 1936,
            "board": [
                {
                    "name": "disp. Lennart Rehnborg"
                }
            ],
            "managing_director": "disp. Lennart Rehnborg",
            "manager": "Torgny Rehnborg"
        },
        "10": {
            "name": "Björneborgs Jernverks AB.",
            "location": "Björneborg",
            "business": "Järnverk med masugnar, martinverk, ånghammar- och manufaktursmedja, mek. verkstad och gjuteri vid Björneborg (Värml. l.)"
        }
    }
}