{
    "original": "Hjort•—Hoffman\n\nTelefon: 544 o. 464. Postgiro: 241015.\n— Akt.-kap.: 25,600 kr. Antal\nindustriarb.: 60. — Bolaget grundat 1931.\n\nStyrelse o. verkst. dir.: Gustaf Törling.\n\nVerkstadschef: Gustaf Bjurström.\n\n’Hjorts Kritbruk, Kvarnby.\n\nSe AB. Kritbruksbolaget i Malmö,\nKvarnby.\n\n’AB. B. A. Hjorth &amp; Co., Stockholm.\n\nFörsäljningsbolag för dotterbolagen\nAB. Primus, Stockholm, och AB.\nEnköpings Verkstäders, Enköping,\ntillverkningar.\n\nUnder märket »Primus» försäljas bl. a.\nkok-, löd-, belysnings- och\nvärmeapparater för fotogen, bensin eller rödsprit,\nväxt sprutor, smörj kannor, mattrenare\n(»Matt-Primus») m. m. Under märket\n»jBahco» försäljas skift- och skruvnycklar,\nhylsnycklar, skruvmejslar, skru vt vingar,\nrörtänger, &gt;röravskärare, bultsaxar,\nbil-och cykel verktyg, trädgårdsverktyg,\nbad-stuberedare, byggtorkar m. m.\n\nKontor: Klara Norra Kyrkog. 31.\nTelegr.-adr.: Bahco, Stockholm. Telefon:\n»Hjorth &amp; Co.». Postgiro: 745.\nRepresentanter: för Väst-Sverige: Wallén &amp;\nCo., Göteborg, N. Larmg. 5, telefon:\n111876; för Skåne-distriktet: B.\nOller-stam, Malmö, Storg. 20, telefon: 17145.\n\nAkt.-kap.: 3,400,000 kr. — Firman\netabl. 1889, bolag 1899.\n\nStyrelse: generalkonsul Hugo Duhs\n(ordf.), dir. Arnold Hjorth, disp. Hannes\nBrynge, dir. Siver Hulthén, dir. Arvid\nUggla.\n\nVerkst. dir.: Arnold Hjorth.\n\nV. verkst. dir.: Hugo Duhs.\n\nKassadir.: Arvid Uggla.\n\nKamrer: N. Lindstedt.\n\nFÖrsaljn.-chefer: för export: I. Anell,\nF. Duhs o. Fr. Riesel; för Sverige: disp.\nE. Stenström.\n\nHjortqvarns Sågverks AB.y\n\nHjortkvarn.\n\nTillverkar sågade och hyvlade trävaror\nvid sågverk i Hjortkvarn (Örebro l.).\n\nTelefon: 1. — Akt.-kap.: 100,000 kr.\nAntal industriarb.: 30. Årstillv.: 2,000\nstds trävaror. — Bolaget grundat 1944.\n\nVerkst. dir.: frih. Hugo Hamilton.\n\n’Hjuisbro Tråddrageri &amp; Nätfabrik\n\nAB., Hjulsbro.\n\nGrov- och fintråddrageri,\nstängselnät-fabrik, förtennings- och\ngalvaniserings-verk vid Hjulsbro (Östergötl. l.).\n\n14\n\nTillverkar blank, förkopprad, glödgad,\nförzinkad och förtent järntråd,\nblomster-tråd, häfttråd, madrasstråd, ståltråd,\nstängselnät, rävnät samt taggtråd och\nstaglinor.\n\nTelegr.-adr.: Trådnät, Linköping.\nTelefon: Linköping 59155. Postgiro: 25260.\n\nAkt.-kap.: 250,000 kr. Antal\nindustriarb. : 90. Tillv.-värde pr år: 1,800,000 kr.\n— Bolaget grundat 1906, ombildat 1923\no. 1931.\n\nStyrelse: generalmajor Sig. Rahmqvist\n(ordf.), greve J. H. Falkenberg, fru I.\nRahmqvist.\n\nVerkst. dir.: Sig. Rahmqvist.\n\nKamrer: Carl G. Carlsson.\n\nFörsäljn.-chef: Erik Odefalk.\n\nDriftschef: ing. Eiler Carlsson.\n\n’Hjulsjö Bruk, Hjulsjö.\n\nSe AB. Stjernfors-Ställdalen,\nStälldalen.\n\n’Hjälmare Kanal- &amp; Slussverks AB.,\n\nArboga.\n\nTräsliperi, sågverk och varv vid Hällby\n(Västmanl. l.). Tillverkar mek. trämassa\noch sågade trävaror; utför reparationer\noch nybyggnader av fartyg, pråmar samt\nvarpbåtar.\n\nBolaget driver såsom huvudrörelse\nkanaldrift samt därjämte jordbruk och\nskogshantering.\n\nKontor: Hällby, Arboga. Telegr.-adr.:\nHellby, Arboga. Telefon: Arboga 49.\nPostgiro: 282415.\n\nAkt.-kap.: 333,900 kr. Antal\nindustriarb.: 45. Årstillv.: 2,200 ton våt, vit mek.\nträmassa, 200 stds trävaror. Tillv.-värde\nf. varvsrörelsen: 160,000 kr. — Bolaget\ngrundat 1816.\n\nStyrelse: kammarh. Ch. E. v. Oelreich\n(ordf.), landshÖvd. Bror Hasselrot\n(statens ombud), major Hugo Broms, disp.\nC.-B. Folin, kapten C.-F. Strokirk.\n\nJourh. styrelseled.: Ch. E. v. Oelreich.\n\nDisp.: S. Herming.\n\nHoffman &amp; Co., AB., Hagalund.\n\nTryckfärgsfabrik. Tillverkar\ntryckfärger och grafiska hjälpmedel.\nSpecialiteter: offsetfärger, torkpreparat och\nglansfernissor.\n\nKontor: Fabriksvägen 1, Hagalund.\nTelegr.-adr.: Tryckfärg, Stockholm.\nTelefon: Stockholm 272750. Postgiro: 2366.\nEnsamförsäljare: Georg Bolie AB.,\nStockholm, Herkulesg. 28 o. Göteborg, N.\nHamng. 8.",
    "structured": {
        "1": {
            "name": "Hjort•—Hoffman",
            "location": "Hagalund",
            "business": "Tryckfärgsfabrik",
            "contact": {
                "office": "Fabriksvägen 1, Hagalund",
                "phone": "Stockholm 272750",
                "telegraph": "Tryckfärg, Stockholm",
                "postgiro": "2366"
            },
            "board": [
                {
                    "name": "Georg Bolie AB.",
                    "role": "Ensamförsäljare"
                }
            ]
        },
        "2": {
            "name": "Hjorts Kritbruk, Kvarnby",
            "location": null,
            "business": "AB",
            "description": "Kritbruksbolaget i Malmö, Kvarnby"
        },
        "3": {
            "name": "AB. B. A. Hjorth & Co.",
            "location": "Stockholm",
            "business": "Försäljningsbolag",
            "products": "Kok-, löd-, belysnings- och värmeapparater för fotogen, bensin eller rödsprit, växt sprutor, smörj kannor, mattrenare (»Matt-Primus») m. m.",
            "contact": {
                "office": "Klara Norra Kyrkog. 31",
                "phone": "»Hjorth &amp; Co.»",
                "telegraph": "Bahco, Stockholm",
                "postgiro": "745"
            },
            "sales_offices": [
                {
                    "location": "Väst-Sverige",
                    "phone": "Wallén & Co., Göteborg, N. Larmg. 5, telefon: 111876"
                },
                {
                    "location": "Skåne-distriktet",
                    "phone": "B. Oller-stam, Malmö, Storg. 20, telefon: 17145"
                }
            ]
        },
        "4": {
            "name": "AB. Primus",
            "location": "Stockholm",
            "business": "Tillverkningar"
        },
        "5": {
            "name": "AB. Enköpings Verkstäders",
            "location": "Enköping",
            "business": "Tillverkningar"
        },
        "6": {
            "name": "Hvinbro Tråddrageri & Nätfabrik AB.",
            "location": "Hjulsbro",
            "business": "Grov- och fintråddrageri, stängselnät-fabrik, förtennings- och galvaniserings-verk"
        },
        "7": {
            "name": "AB. Stjernfors-Ställdalen",
            "location": "Ställdalen",
            "business": null
        },
        "8": {
            "name": "Hjulsjö Bruk",
            "location": "Hjulsjö",
            "business": "Sågverk"
        },
        "9": {
            "name": "Hjälmare Kanal- & Slussverks AB.",
            "location": "Arboga",
            "business": "Träsliperi, sågverk och varv"
        }
    }
}