{
    "original": "Mårtensson—Möbelfabriken\n\n\"A. Mårtenssons Orgelfabrik AB.,\n\nLund.\n\nTillverkar kyrkorglar.\n\nTelefon: 11119. — Akt.-kap.: 15,000\nkr. Antal industriarb.: 15. Tillv.-värde\npr år: 120,000 kr. — Firman etabl. 1914,\nbolag 1931.\n\nStyrelse: dir. Anders Mårtensson\n(ordf.), orgelbyggare Gunnar\nMårtensson, orgelbyggare Gösta Mårtensson.\n\nVerkst. dir.: Anders Mårtensson.\n\nNils Mårtenssons Cjuteri AB.,\n\nAlingsås.\n\nGjuteri och mek. verkstad. Tillverkar\nvanligt och speciallegerat järn- och\nme-tallgjutgods samt maskiner för verkstads-,\nlivsmedels- och läderindustrierna.\n\nTelefon: 53 o. 651. Postgiro: 32883. —\nAkt.-kap.: 50,000 kr. Antal industriarb.:\n60. Tillv.-värde pr år: 600,000 kr. —\nFirman etabl. 1925, bolag 1946.\n\nDisponenter: Sture Mårtensson o. Tage\nMårtensson.\n\nAB. Måttstockar, Lidingö.\n\nTrä-, metall- och\njärnvarumanufakturverk i Mellösa (Södermanl. l.).\nTillverkar tumstockar av trä och lättmetall,\njumperstickor av förnicklad lättmetall,\npressverktyg samt utför\npressningsarbeten. Varumärke: »Jim».\n\nKontor: Lidingö 3. Telegr.-adr.: Jim,\nStockholm. Telefon: Stockholm 656911.\nPostgiro: 53265.\n\nAkt.-kap.: 10,000 kr. Antal\nindustriarb.: 45.–Bolaget grundat 1930.\n\nDisp.: Carl Jonson (Mellösa).\n\nKamrer: Hilding Plante.\n\nMåttstockfabriken, AB. Nordiska,\n\nFristad.\n\nSe Nya AB. Nordiska\nMåttstockfabriken, Fristad.\n\n\"Mått- och Tumstockfabriken,\n\nHultafors.\n\nSe Svenska Mått- &amp; Tumstockfabriken,\nHultafors.\n\n\"AB. Mälardalens Tegelbruk,\n\nStockholm.\n\nTegelbruk vid Broby, Fittja, Hända,\nKiholm, Lina, Nora och Rimbo (samtl.\ni Sthlms l.), Bergsbrunna, Brogård och\nRöbo (Uppsala l.), Husby, Näsby och\nValla (Södermanl. l.). Tillverkar mur-\n\n24\n\noch fasadtegel, tak-, reveterings- och\nhåltegel, dräneringsrör m. m. Bolaget idkar\njämväl jordbruk, skogshantering samt\nrederirörelse.\n\nKontor: Eriksbergsg. 27. Telegr.-adr.:\nTegelbolaget, Stockholm. Telefon: 233365.\nPostgiro: 3581.\n\nAkt.-kap.: 2,665,500 kr. Antal\nindustriarb. (under säsong): 700. Årstillv.: 55\nmilj. st. tegelvaror. — Bolaget, grundat\n1914, har under kalenderns tryckning\nförsålts till Kooperativa Förbundet.\n\nStyrelse: jägmästare Arvid Carlander\n(ordf.), kamrer Einar Helenius, adv. frih.\nSten B:son Leijonhuvud.\n\nVerkst. dir.: Arvid Carlander.\n\nDisp.: E. Gemser.\n\nKamrer: Thure Karlström.\n\nFörsäljn.-chef: Ivar Ericson.\n\n\"Möbel AB. Larsson &amp; Co., Karlstad.\n\nTillverkar matrums-, sovrums- och\nkompletteringsmöbler.\n\nTelefon: 11331. Postgiro: 27637. —\nAkt.-kap.: 82,000 kr. Antal industriarb.:\n25. Tillv.-värde pr år: 240,000 kr. —\nFirman etabl. 1916, bolag 1935.\n\nStyrelse o. verkst. direktörer: fabr.\nAlfred Larsson o. fabr. Daniel Larsson.\n\nMöbel AB. Vasa, Vaggeryd.\n\nTillverkar möbler vid fabrik i\nVaggeryd (Jönköp. l.).\n\nTelefon: 153. Postgiro: 94433. —\nAkt.-kap.: 45,000 kr. Antal industriarb.: 40.\nTillv.-värde pr år: 420,000 kr. — Bolaget\ngrundat 1935.\tv\n\nDisp.: Carl Gustafsson.\n\nAB. Möbelfabriken Balder,\n\nVaggeryd.\n\nTillverkar matrums- och\nsittrumsmöbler vid fabrik i Vaggeryd (Jönköp. l.).\n\nTelefon: 59. Postgiro: 162280. —\nAkt.-kap.: 60,000 kr. Antal industriarb.: 35.\n\n—\tBolaget grundat 1939.\nDisp.: Rolf Grenthe.\n\n\"Möbelfabriken Ejdern, Karl\nMalmberg, Vimmerby.\n\nTillverkar bostadsmöbler, kontorsmöbler\nsamt inredningar för banker och\naffärslokaler.\n\nTelefon: 779 o. 229. Postgiro: 25629.\n\n—\tAntal industriarb.: 20. Tillv.-värde pr\når: 150,000 kr. — Firman etabl. 1924.\n\nÄgare o. chef: fabr. Karl Malmberg.",
    "structured": {
        "firms": [
            {
                "name": "A. Mårtenssons Orgelfabrik AB.",
                "location": "Lund",
                "business": "Tillverkar kyrkorglar",
                "contact": {
                    "office": "Lund",
                    "phone": [
                        "11119"
                    ],
                    "postgiro": null,
                    "head_office": null,
                    "sales_offices": null,
                    "telegraph": null,
                    "factory_office": null,
                    "factory_phone": null
                },
                "financials": {
                    "capital": "15,000 kr",
                    "employees": {
                        "industriarb": 15
                    },
                    "annual_turnover": "120,000 kr",
                    "annual_production_value": null
                },
                "foundation_year": 1914,
                "current_name_year": 1931,
                "predecessor": null,
                "original_name": null,
                "corporation_year": null,
                "board": [
                    {
                        "name": "Anders Mårtensson",
                        "role": "ordf."
                    },
                    {
                        "name": "Gunnar Mårtensson",
                        "role": "orgelbyggare"
                    },
                    {
                        "name": "Gösta Mårtensson",
                        "role": "orgelbyggare"
                    }
                ],
                "owners": null,
                "director": "Anders Mårtensson",
                "managing_director": null,
                "sales_manager": null,
                "manager": null
            },
            {
                "name": "Nils Mårtenssons Cjuteri AB.",
                "location": "Alingsås",
                "business": "Gjuteri och mek. verkstad",
                "contact": {
                    "office": "Alingsås",
                    "phone": [
                        "53",
                        "651"
                    ],
                    "postgiro": "32883",
                    "head_office": null,
                    "sales_offices": null,
                    "telegraph": null,
                    "factory_office": null,
                    "factory_phone": null
                },
                "financials": {
                    "capital": "50,000 kr",
                    "employees": {
                        "industriarb": 60
                    },
                    "annual_turnover": "600,000 kr",
                    "annual_production_value": null
                },
                "foundation_year": 1925,
                "current_name_year": 1946,
                "predecessor": null,
                "original_name": null,
                "corporation_year": null,
                "board": null,
                "owners": null,
                "director": null,
                "managing_director": null,
                "sales_manager": null,
                "manager": null
            },
            {
                "name": "AB. Måttstockar, Lidingö",
                "location": "Mellösa (Södermanl. l.)",
                "business": "Tillverkar tumstockar av trä och lättmetall, jumperstickor av förnicklad lättmetall, pressverktyg samt utför pressningsarbeten. Varumärke: »Jim».",
                "contact": {
                    "office": "Lidingö 3",
                    "phone": [
                        "Stockholm 656911"
                    ],
                    "postgiro": "53265",
                    "head_office": null,
                    "sales_offices": null,
                    "telegraph": "Jim, Stockholm",
                    "factory_office": null,
                    "factory_phone": null
                },
                "financials": {
                    "capital": "10,000 kr",
                    "employees": {
                        "industriarb": 45
                    },
                    "annual_turnover": null,
                    "annual_production_value": null
                },
                "foundation_year": 1930,
                "current_name_year": null,
                "predecessor": null,
                "original_name": null,
                "corporation_year": null,
                "board": null,
                "owners": null,
                "director": null,
                "managing_director": null,
                "sales_manager": null,
                "manager": null
            },
            {
                "name": "AB. Mälardalens Tegelbruk, Stockholm",
                "location": "Vid Broby, Fittja, Hända, Kiholm, Lina, Nora, Rimbo (samtl. i Sthlms l.), Bergsbrunna, Brogård, Röbo (Uppsala l.), Husby, Näsby, Valla (Södermanl. l.)",
                "business": "Tillverkar mur- och fasadtegel, tak-, reveterings- och håltegel, dräneringsrör m. m. Idkar jämväl jordbruk, skogshantering samt rederirörelse.",
                "contact": {
                    "office": "Eriksbergsg. 27",
                    "phone": [
                        "233365"
                    ],
                    "postgiro": "3581",
                    "head_office": null,
                    "sales_offices": null,
                    "telegraph": "Tegelbolaget, Stockholm",
                    "factory_office": null,
                    "factory_phone": null
                },
                "financials": {
                    "capital": "2,665,500 kr",
                    "employees": {
                        "under säsong": 700
                    },
                    "annual_turnover": null,
                    "annual_production_value": "55 milj. st. tegelvaror"
                },
                "foundation_year": 1914,
                "current_name_year": null,
                "predecessor": null,
                "original_name": null,
                "corporation_year": null,
                "board": [
                    {
                        "name": "Arvid Carlander",
                        "role": "ordf."
                    },
                    {
                        "name": "Einar Helenius",
                        "role": "kamrer"
                    },
                    {
                        "name": "Sten B:son Leijonhuvud",
                        "role": "adv. frih."
                    }
                ],
                "owners": null,
                "director": null,
                "managing_director": null,
                "sales_manager": "Ivar Ericson",
                "manager": null
            },
            {
                "name": "Möbel AB. Larsson & Co., Karlstad",
                "location": null,
                "business": "Tillverkar matrums-, sovrums- och kompletteringsmöbler",
                "contact": {
                    "office": null,
                    "phone": [
                        "11331"
                    ],
                    "postgiro": "27637",
                    "head_office": null,
                    "sales_offices": null,
                    "telegraph": null,
                    "factory_office": null,
                    "factory_phone": null
                },
                "financials": {
                    "capital": "82,000 kr",
                    "employees": {
                        "industriarb": 25
                    },
                    "annual_turnover": "240,000 kr",
                    "annual_production_value": null
                },
                "foundation_year": 1916,
                "current_name_year": 1935,
                "predecessor": null,
                "original_name": null,
                "corporation_year": null,
                "board": null,
                "owners": null,
                "director": null,
                "managing_director": null,
                "sales_manager": null,
                "manager": null
            },
            {
                "name": "Möbel AB. Vasa, Vaggeryd",
                "location": "Fabrik i Vaggeryd (Jönköp. l.)",
                "business": "Tillverkar möbler",
                "contact": {
                    "office": null,
                    "phone": [
                        "153"
                    ],
                    "postgiro": "94433",
                    "head_office": null,
                    "sales_offices": null,
                    "telegraph": null,
                    "factory_office": null,
                    "factory_phone": null
                },
                "financials": {
                    "capital": "45,000 kr",
                    "employees": {
                        "industriarb": 40
                    },
                    "annual_turnover": "420,000 kr",
                    "annual_production_value": null
                },
                "foundation_year": null,
                "current_name_year": null,
                "predecessor": null,
                "original_name": null,
                "corporation_year": 1935,
                "board": null,
                "owners": null,
                "director": null,
                "managing_director": null,
                "sales_manager": null,
                "manager": "Carl Gustafsson"
            },
            {
                "name": "AB. Möbelfabriken Balder, Vaggeryd",
                "location": "Fabrik i Vaggeryd (Jönköp. l.)",
                "business": "Tillverkar matrums- och sittrumsmöbler",
                "contact": {
                    "office": null,
                    "phone": [
                        "59"
                    ],
                    "postgiro": "162280",
                    "head_office": null,
                    "sales_offices": null,
                    "telegraph": null,
                    "factory_office": null,
                    "factory_phone": null
                },
                "financials": {
                    "capital": "60,000 kr",
                    "employees": {
                        "industriarb": 35
                    },
                    "annual_turnover": null,
                    "annual_production_value": null
                },
                "foundation_year": 1939,
                "current_name_year": null,
                "predecessor": null,
                "original_name": null,
                "corporation_year": null,
                "board": null,
                "owners": null,
                "director": null,
                "managing_director": null,
                "sales_manager": null,
                "manager": "Rolf Grenthe"
            },
            {
                "name": "Möbelfabriken Ejdern, Karl Malmberg, Vimmerby",
                "location": null,
                "business": "Tillverkar bostadsmöbler, kontorsmöbler samt inredningar för banker och affärslokaler",
                "contact": {
                    "office": null,
                    "phone": [
                        "779",
                        "229"
                    ],
                    "postgiro": "25629",
                    "head_office": null,
                    "sales_offices": null,
                    "telegraph": null,
                    "factory_office": null,
                    "factory_phone": null
                },
                "financials": {
                    "capital": null,
                    "employees": {
                        "industriarb": 20
                    },
                    "annual_turnover": "150,000 kr",
                    "annual_production_value": null
                },
                "foundation_year": 1924,
                "current_name_year": null,
                "predecessor": null,
                "original_name": null,
                "corporation_year": null,
                "board": null,
                "owners": [
                    "fabr. Karl Malmberg"
                ],
                "director": null,
                "managing_director": null,
                "sales_manager": null,
                "manager": null
            }
        ]
    }
}