{
    "original": "Upsala— Urivitz\n\nHuvudkontor: Gimo. Telefon: 103.\nPostgiro: 25288. — Prod.-värde pr år:\n1,000,000 kr. — Föreningen bildad 1942.\n\nDisp.: Ragnar Bystedt.\n\n*AB. Upsala Valskvarn, Uppsala.\n\nMjöl- och grynkvarnar. Tillverkar\nvetemjöl, samsikt, rågmjöl, ångprep.\nhavregryn, korngryn m. m. Varumärken:\n»Vasa-lyx», »Vasa-ax», »Vasa»-havregryn\nm. fl.\n\nTelegr.-adr. o. telefon: Valskvarn,\nUppsala. Postgiro: 23030. — Akt.-kap.:\n1,750,000 kr. Antal industriarb.: 100.\nProd.-värde pr år: 11,000,000 kr. (incl.\ndotterbolag: 21,000,000 kr.).\n\nFirman, etabl. 1904, bolag 1914, är\nhuvudintressent i AB. Upsala\nÄttiks-fabrik, AB. Slottsindustrier, AB. Upsala\nSidenväverier, AB. Upsala Kexfabrik,\nUpsala Foder- &amp; Spannmåls AB., AB.\nKniv-st aortens Lantmän och Åhléns Kvarn AB.\n\nStyrelse: dir. Martin Edlund (ordf.),\ndisp. Folke Edlund, grossh. Oskar\nHägg-lund, kapten Gunnar Lundqvist, dir. C.\nJ. Wiksell.\n\nVerkst. dir.: Martin Edlund.\n\nV. verkst. dir.: Folke Edlund.\n\nDriftsing.: R. Danielsson.\n\n\"Upsala Ångqvarns AB., Uppsala.\n\nKvarn, jästfabrik och makaronifabrik.\nTillverkar mjöl, pressjäst och makaroner.\nVarumärken: ^ »Blixtgyllen»,\n»Blixtråg-sikt», »Blixt-jäst», »Blixt-macearoni» o.\n»Blixt-spaghetti».\n\nTelegr.-adr. o. telefon: Ångqvarn,\nUpsala. Postgiro: 5365.\n\nAkt.-kap.: 2,400,000 kr. Antal\nindustri-ark: 100. Prod.-värde pr år: 9,500,000kr.\n— Bolaget grundat 1874.\n\nStyrelse: dir. Gust. Åkerlindh (ordf.),\nbankdir. Hilding Melin, översteiöjtn. Hj.\nOdqvist, dir. H. W. Söderman,\nbank-tjänstem. S. K:son Thunman.\n\nVerkst. dir.: H. W» Söderman.\n\nKontorschef: Tobias Urell.\n\nDriftsingenjörer: för kvarn o.\nmaka-ronifabr.: Werner Björck; för\njästfabriken: E. Karsvik.\n\nAB. Upsala Ättiksfabrlk,\n\nUppsala.\n\nTillverkar ättiksprit, senap,\nmajonnäs, nyponextrakt (»Nyponkraft») samt\nbordsdricka. Varumärken:\n»Slotts-ättik-sprit», »Slotts-senap» o.\n»Slotts-majonnäs».\n\nTelegr.-adr.: Upsalaättika, Uppsala.\n\nTelefon: 39880. Postgiro: 14870.\n\nAkt.-kap.: 600,000 kr. Antal\nindustriarb.: 100. Tillv.-värde pr år: 4,000,000 kr.\n\n—\tFirman etabl. 1885, bolag 1919.\nStyrelse: dir. Martin Edlund (ordf.),\n\ndisp. Folke Edlund, intendent Tore\nEdlund, dir. C. J. Wiksell, disp. Ragnar\nÅkerblom.\n\nDisp.: Swen Frohm.\n\n\"Urafors Yxfabrik, C. 0. Åberg &amp;\n\nCo., Edsbyn.\n\nManufaktursmedja i Edsbyn (Gävleb.\n1.). Tillverkar yxor och barkspadar.\nFabriksmärke: »Urafors».\n\nTelegr.-adr.: Urafors. Edsbyn.\nTelefon: 23 o. 33. Postgiro: 72383.\n\nAntal industriarb.: 16. Tillv.-värde pr\når: 210,000 kr. — Firman etabl. 1860.\n\nÄgare: fabr. O. O. Åberg o. fabr. Arvid\nJonsson.\n\n\"AB. Urfabriken, Svängsta.\n\nMek. verkstad i Svängsta (Blekinge l.).\nTillverkar taxametrar, telef onkontrollur,\nspinnrullar, flugrullar, spinnspön och\ndrag för sportfiske m. fl. finmekaniska\ntillverkningar. Varumärke: »Record».\n\nTelegr.-adr.: Urfabriken, Svängsta.\nTelefon: 18 o. 118. Postgiro: 22474.\n\nAkt.-kap.: 45,000 kr. Antal\nindustriarb.: 100. Tillv.-värde pr år: 900,000 kr.\n\n—\tBolaget grundat 1921.\n\nStyrelse: fabr. Göte Borgström (ordf.),\nfru I. Borgström.\n\nVerkst. dir.: Göte Borgström.\nKamrer: Axel Pettersson.\n\n\"Ursvikens Mek. Verkstads AB.,\n\nUr svik en.\n\nMek. verkstad i Ursviken (Västerbott.\n1.). Tillverkar turbiner och regulatorer\nsamt apparater för malmförädling och\nanrikning.\n\nTelegr.-adr.: Verkstaden, Skellefteå.\nTelefon: 30008. Postgiro: 61602.\n\nAkt.-kap.: 140,000 kr. Antal\nindustriarb.: 70. Tillv.-värde pr år: 700,000 kr.\n\n—\tBolaget grundat 1895.\n\nStyrelse: disp. Axel Ekeblom, ing.\nVictor Ekeblom, civiling. R. Insulander.\nVerkst. dir. o. disp.: Axel Ekeblom.\n\nAB. Gabriel Urwitz, Stockholm.\n\nTillverkar damskärp (märke:\n»Gabriella»), livremmar, hängslen,\nstrump-och ärmhållare, stickväskor m. m.\n\nKontor: Mariag. 8. Telefon: 407076 o.\n426666. Postgiro: 535^7.",
    "structured": {
        "1": {
            "name": "AB. Upsala Valskvarn",
            "location": "Uppsala",
            "business": "Mjöl- och grynkvarnar",
            "products": "Tillverkar vetemjöl, samsikt, rågmjöl, ångprep. havregryn, korngryn m.m. Varumärken: »Vasa-lyx», »Vasa-ax», »Vasa»-havregryn m.fl.",
            "contact": {
                "office": "Gimo",
                "phone": [
                    "103"
                ],
                "postgiro": "25288",
                "head_office": "Gimo",
                "telegraph": "Valskvarn, Uppsala",
                "factory_phone": "25288"
            },
            "financials": {
                "capital": "1,750,000 kr",
                "employees": {
                    "industriarb": 100
                },
                "annual_turnover": "11,000,000 kr",
                "annual_production_value": "21,000,000 kr (incl. dotterbolag: 21,000,000 kr)"
            },
            "foundation_year": 1904,
            "board": [
                {
                    "name": "Martin Edlund",
                    "role": "ordf."
                },
                {
                    "name": "Folke Edlund",
                    "role": "disp."
                },
                {
                    "name": "Oskar Hägglund",
                    "role": "grossh."
                },
                {
                    "name": "Gunnar Lundqvist",
                    "role": "kapten"
                },
                {
                    "name": "C. J. Wiksell",
                    "role": "dir."
                }
            ],
            "owners": [
                "Ragnar Bystedt"
            ],
            "director": "R. Danielsson",
            "managing_director": "Martin Edlund"
        },
        "2": {
            "name": "Upsala Ångqvarns AB.",
            "location": "Uppsala",
            "business": "Kvarn, jästfabrik och makaronifabrik",
            "products": "Tillverkar mjöl, pressjäst och makaroner. Varumärken: ^ »Blixtgyllen», »Blixtråg-sikt», »Blixt-jäst», »Blixt-macearoni» o. »Blixt-spaghetti».",
            "contact": {
                "office": "Ångqvarn, Upsala",
                "phone": [
                    "5365"
                ],
                "postgiro": "5365"
            },
            "financials": {
                "capital": "2,400,000 kr",
                "employees": {
                    "industriarb": 100
                },
                "annual_turnover": "9,500,000 kr"
            },
            "foundation_year": 1874,
            "director": "H. W» Söderman",
            "sales_manager": "Tobias Urell",
            "manager": "E. Karsvik"
        },
        "3": {
            "name": "AB. Upsala Ättiksfabrlk",
            "location": "Uppsala",
            "business": "Tillverkar ättiksprit, senap, majonnäs, nyponextrakt",
            "products": "Varumärken: »Slotts-ättik-sprit», »Slotts-senap» o. »Slotts-majonnäs».",
            "contact": {
                "office": "Uppsala",
                "phone": [
                    "39880"
                ],
                "postgiro": "14870"
            },
            "financials": {
                "capital": "600,000 kr",
                "employees": {
                    "industriarb": 100
                },
                "annual_turnover": "4,000,000 kr"
            },
            "foundation_year": 1885,
            "board": [
                {
                    "name": "Martin Edlund",
                    "role": "ordf."
                },
                {
                    "name": "Folke Edlund",
                    "role": "disp."
                },
                {
                    "name": "Tore Edlund",
                    "role": "intendent"
                },
                {
                    "name": "C. J. Wiksell",
                    "role": "dir."
                },
                {
                    "name": "Ragnar Åkerblom",
                    "role": "disp."
                }
            ],
            "director": "Swen Frohm"
        },
        "4": {
            "name": "Urafors Yxfabrik, C. 0. Åberg & Co.",
            "location": "Edsbyn",
            "business": "Manufaktursmedja",
            "products": "Tillverkar yxor och barkspadar. Fabriksmärke: »Urafors».",
            "contact": {
                "office": "Edsbyn",
                "phone": [
                    "23",
                    "33"
                ],
                "postgiro": "72383"
            },
            "financials": {
                "employees": {
                    "industriarb": 16
                },
                "annual_turnover": "210,000 kr"
            },
            "foundation_year": 1860,
            "owners": [
                "O. O. Åberg",
                "Arvid Jonsson"
            ]
        },
        "5": {
            "name": "AB. Urfabriken",
            "location": "Svängsta",
            "business": "Mek. verkstad",
            "products": "Tillverkar taxametrar, telef onkontrollur, spinnrullar, flugrullar, spinnspön och drag för sportfiske m. fl. finmekaniska tillverkningar. Varumärke: »Record».",
            "contact": {
                "office": "Svängsta",
                "phone": [
                    "18",
                    "118"
                ],
                "postgiro": "22474"
            },
            "financials": {
                "capital": "45,000 kr",
                "employees": {
                    "industriarb": 100
                },
                "annual_turnover": "900,000 kr"
            },
            "foundation_year": 1921,
            "owner": "Göte Borgström",
            "board": [
                {
                    "name": "Göte Borgström",
                    "role": "ordf."
                },
                {
                    "name": "Fru I. Borgström",
                    "role": ""
                }
            ],
            "director": "Göte Borgström",
            "manager": "Axel Pettersson"
        },
        "6": {
            "name": "Ursvikens Mek. Verkstads AB.",
            "location": "Ursviken",
            "business": "Mek. verkstad",
            "products": "Tillverkar turbiner och regulatorer samt apparater för malmförädling och anrikning.",
            "contact": {
                "office": "Ursviken",
                "phone": [
                    "30008"
                ],
                "postgiro": "61602"
            },
            "financials": {
                "capital": "140,000 kr",
                "employees": {
                    "industriarb": 70
                },
                "annual_turnover": "700,000 kr"
            },
            "foundation_year": 1895,
            "board": [
                {
                    "name": "Axel Ekeblom",
                    "role": "disp."
                },
                {
                    "name": "Victor Ekeblom",
                    "role": "ing."
                },
                {
                    "name": "R. Insulander",
                    "role": "civiling."
                }
            ],
            "director": "Axel Ekeblom"
        },
        "7": {
            "name": "AB. Gabriel Urwitz",
            "location": "Stockholm",
            "business": "Tillverkar damskärp, livremmar, hängslen, strump-och ärmhållare, stickväskor m.m.",
            "products": "märke: »Gabriella»",
            "contact": {
                "office": "Mariag. 8",
                "phone": [
                    "407076",
                    "426666"
                ],
                "postgiro": "535^7"
            }
        }
    }
}