{
    "original": "Hyssna—Håkansson\n\n* Hyss na Bobinfabrik, SJcene.\n\nTillverkar spinneribobiner och\nspol-pipor samt andra svarvade artiklar för\ntextilindustrien vid fabrik i Hyssna,\nSkene (Älvsb. l.).\n\nTelefon: Kinna 39005. Postgiro:\n146410. — Arb.-antal: 12. Tillv.-värde pr\når: 100,000 kr. — Firman etabl. 1895,\nnuv. namn 1942.\n\nÄgare o. chef: fabr. Bertil Johansson.\n\n*Håfreströms AB., Håverud.\n\nPappersbruk med träsliperi och elektr.\nkraftstation vid Håverud, pappersbruk,\nsulfitfabrik och blekeri vid Åsensbruk\n(båda i Älvsb. l.).\n\nTillverkar sulfitcellulosa för eget behov\nsamt omslags-, tryck-, koncept-, affisch-,\nskriv-, olifant-, pås- och smörpapper,\noblekt och blekt MG och glättat, vaxat och\npräglat papper samt klistrad kartong.\n\nHuvudkontor: Håverud. Telegr.-adr.:\nHofrestrom, Vänersborg. Telefon:\nMelle-rud, »Håfreström». Postgiro: 29795.\n\nAkt.-kap.: 2,500,000 kr. Antal\nindustriarb.: 460. Årstillv.: 20,000 ton papper. —\nBolaget grundat 1880.\n\nStyrelse: disp. Lennart Biesért, disp.\nLudvig Halling, dir. Nils Thenberg, dir.\nNils Troedsson.\n\nVerkst. dir. o. disp.: Ludvig Halling.\n\nFörsäljn.-chef: Curt Ranholm.\n\nKamrer: T. Torstensson.\n\nDriftsingenjörer: Gunnar Berglind o.\nBengt Halling.\n\nAB. Håkanssons Industrier, Åmål.\n\nMek. verkstad med gjuteri,\nsnickerifabrik och emaljerverk.\n\nTillverkar elektr. spisar,\nplanslipma-skiner, aducerat gjutgods,\nmetallbandsåg-blad samt trähjul och andra grövre\nsnickerier.\n\nTelegr.-adr.: Hawkind, Åmål. Telefon:\n»Håkanssons Industrier». Postgiro: 9001.\n\nAkt.-kap.: 550,000 kr. Antal\nindustriarb.: 300. — Bolaget grundat 1944.\n\nVerkst. dir.: Bror Håkansson\n(Karlstad).\n\növering.: Gustaf Håkansson.\n\nIntendent: Karl Håkansson.\n\n*AB. Claes Håkansson, Kinna.\n\nVäveri, färgeri och appreteringsverk\n(Kinnasands Mek. Väveri) i Kinna\n(Älvsb. l.). Tillverkar bomulls-, halvylle-,\nkonstsilke- och cellullvävnader.\n\nTelegr.-adr.: Claes, Kinna. Telefon:\n10655. Postgiro: 24823. Representanter: i\n\nGöteborg: J. Lindholm, Aschebergsg. 17,\ntelefon: 116190; för Stockholm: Alf\nBjur-quist, Storängen, Pilvägen 10, telefon:\n162142.\n\nAkt.-kap.: 401,000 kr. Antal\nindustriarb.: 145. Tillv.-värde pr år: 2,500,000 kr.\n—- Firman etabl. 1873, bolag 1918.\n\nStyrelse: major Sven Edvard Engdahl\n(ordf.), fru K. J. Engdahl, fil. lic. Per\nEngdahl.\n\nVerkst. dir.: Sven Edvard Engdahl\n\nDir.-assist.: Sven Engdahl J:or.\n\n*N. H. Håkänson, Snickerifabrik,\n\nStockholm.\n\nTillverkar ledstänger, trappor,\npaten-terade spiraltrappor, portaler,\nbutiksinredningar och andra byggnadssnickerier;\nutför träsvarvning.\n\nKontor: Frejgatan 103. Telefon:\n324274. Postgiro: 3562. — Antal\nindustriarb.: 12. Tillv.-värde pr år: 145,000\nkr. — Firman etabl. 1886.\n\nÄgare o. chef: fabr. N. Harald\nHåkanson.\n\nAB. P. Håkansson, Eslöv.\n\n^ Kem.-tekn. fabrik. Tillverkar\nantiseptiska preparat (»Salubrin»), spritättika\n(»Aroma»), liköressenser m. m.\n\nTelegr.-adr.: Ättikfabriken, Eslöv.\nTelefon: 64 o. 71. Postgiro: 37105.\n\nAkt.-kap.: 100,000 kr. Antal\nindustriarb.: 30. Tillv.-värde pr år: 800,000 kr.\n— Firman etabl. 1874, bolag 1919.\n\nStyrelse: dir. Ivar Sandberg (ordf.),\nmed. lic. Axel Tornberg (v. ordf.), dir. Y.\nHolmström, doktor Bo Sahlin, disp.\nDonald Thomson.\nDisp.: D. Thomson.\nKassör: E. Öhström.\n\nP. Håkanssons Konserver AB.,\n\nEslöv.\n\nTillverkar grönsakskonserver (spec.\ngurkor), fruktkonserver, äppelmos och\nlingonsylt.\n\nTelefon: 624 o. 652. Postgiro: 173325.\n\nAkt.-kap.: 150,000 kr. Antal\nindustriarb.: 100. — Bolaget grundat 1940.\n\nStyrelse: dir. Ivar Sandberg (ordf.),\ndoktor Bo Sahlin, med. lic. Axel\nTornberg.\n\nVerkst. dir.: Ivar Sandberg.\n\nDisp.: Herbert Felix.\n\nDriftsing.: civiling. Yngve Rosenqvist.\n\nInköpschef: Sigvard Eliasson.",
    "structured": {
        "1": {
            "name": "Hyssna Bobinfabrik",
            "location": "Hyssna, Skene",
            "business": "Tillverkar spinneribobiner och spol-pipor samt andra svarvade artiklar för textilindustrien",
            "products": "Description of products manufactured or services offered.",
            "contact": {
                "office": "Fabrik i Hyssna, Skene (Älvsb. l.)",
                "phone": [
                    "Kinna 39005"
                ],
                "postgiro": "146410",
                "head_office": "Head office address.",
                "sales_offices": [],
                "telegraph": "Telegraph address.",
                "factory_office": "Factory office address.",
                "factory_phone": "Factory phone number."
            },
            "financials": {
                "capital": "",
                "employees": {
                    "Arb.-antal": 12
                },
                "annual_turnover": "100,000 kr",
                "annual_production_value": "100,000 kr"
            },
            "foundation_year": 1895,
            "current_name_year": 1942,
            "director": "Bertil Johansson",
            "owners": [
                "Bertil Johansson"
            ]
        },
        "2": {
            "name": "Håfreströms AB.",
            "location": "Håverud, Åsensbruk",
            "business": "Pappersbruk med träsliperi och elektr. kraftstation",
            "products": "Tillverkar sulfitcellulosa för eget behov samt omslags-, tryck-, koncept-, affisch-, skriv-, olifant-, pås- och smörpapper, oblekt och blekt MG och glättat, vaxat och präglat papper samt klistrad kartong.",
            "contact": {
                "office": "",
                "phone": [
                    "Mellerud, »Håfreström»"
                ],
                "postgiro": "29795",
                "head_office": "Håverud",
                "sales_offices": [],
                "telegraph": "Hofrestrom, Vänersborg",
                "factory_office": "",
                "factory_phone": ""
            },
            "financials": {
                "capital": "2,500,000 kr",
                "employees": {
                    "Antal industriarb.": 460
                },
                "annual_turnover": "",
                "annual_production_value": "20,000 ton papper"
            },
            "foundation_year": 1880,
            "board": [
                {
                    "name": "Lennart Biesért",
                    "role": "disp."
                },
                {
                    "name": "Ludvig Halling",
                    "role": "disp."
                },
                {
                    "name": "Nils Thenberg",
                    "role": "dir."
                },
                {
                    "name": "Nils Troedsson",
                    "role": "dir."
                }
            ],
            "director": "",
            "owners": []
        },
        "3": {
            "name": "AB. Håkanssons Industrier",
            "location": "Åmål",
            "business": "Mek. verkstad med gjuteri, snickerifabrik och emaljerverk",
            "contact": {
                "office": "",
                "phone": [
                    "»Håkanssons Industrier»"
                ],
                "postgiro": "9001",
                "head_office": "",
                "sales_offices": [],
                "telegraph": "Hawkind, Åmål",
                "factory_office": "",
                "factory_phone": ""
            },
            "financials": {
                "capital": "550,000 kr",
                "employees": {
                    "Antal industriarb.": 300
                },
                "annual_turnover": "",
                "annual_production_value": ""
            },
            "foundation_year": 1944,
            "director": "Bror Håkansson (Karlstad)",
            "owners": [
                "Gustaf Håkansson"
            ]
        },
        "4": {
            "name": "AB. Claes Håkansson",
            "location": "Kinna",
            "business": "Väveri, färgeri och appreteringsverk",
            "products": "Tillverkar bomulls-, halvylle-, konstsilke- och cellullvävnader.",
            "contact": {
                "office": "Väveri, färgeri och appreteringsverk (Kinnasands Mek. Väveri) i Kinna (Älvsb. l.)",
                "phone": [
                    "10655"
                ],
                "postgiro": "24823",
                "head_office": "",
                "sales_offices": [],
                "telegraph": "Claes, Kinna",
                "factory_office": "",
                "factory_phone": ""
            },
            "financials": {
                "capital": "401,000 kr",
                "employees": {
                    "Antal industriarb.": 145
                },
                "annual_turnover": "2,500,000 kr",
                "annual_production_value": ""
            },
            "foundation_year": 1918,
            "board": [
                {
                    "name": "major Sven Edvard Engdahl",
                    "role": "ordf."
                },
                {
                    "name": "fru K. J. Engdahl",
                    "role": ""
                },
                {
                    "name": "fil. lic. Per Engdahl",
                    "role": ""
                }
            ],
            "director": "Sven Edvard Engdahl",
            "owners": []
        },
        "5": {
            "name": "N. H. Håkänson, Snickerifabrik",
            "location": "Stockholm",
            "business": "Tillverkar ledstänger, trappor, patenterade spiraltrappor, portaler, butiksinredningar och andra byggnadssnickerier; utför träsvarvning",
            "contact": {
                "office": "Stockholm",
                "phone": [
                    "324274"
                ],
                "postgiro": "3562",
                "head_office": "",
                "sales_offices": [],
                "telegraph": "",
                "factory_office": "",
                "factory_phone": ""
            },
            "financials": {
                "employees": {
                    "Arb.-antal": 12
                },
                "annual_turnover": "145,000 kr",
                "annual_production_value": "145,000 kr"
            },
            "foundation_year": 1886,
            "director": "N. Harald Håkanson",
            "owners": [
                "N. Harald Håkanson"
            ]
        },
        "6": {
            "name": "AB. P. Håkansson",
            "location": "Eslöv",
            "business": "Kem.-tekn. fabrik",
            "products": "Tillverkar antiseptiska preparat (»Salubrin»), spritättika (»Aroma»), liköressenser m. m.",
            "contact": {
                "office": "",
                "phone": [
                    "64 o. 71"
                ],
                "postgiro": "37105",
                "head_office": "",
                "sales_offices": [],
                "telegraph": "Ättikfabriken, Eslöv",
                "factory_office": "",
                "factory_phone": ""
            },
            "financials": {
                "capital": "100,000 kr",
                "employees": {
                    "Antal industriarb.": 30
                },
                "annual_turnover": "800,000 kr",
                "annual_production_value": "800,000 kr"
            },
            "foundation_year": 1919,
            "board": [
                {
                    "name": "dir. Ivar Sandberg",
                    "role": "ordf."
                },
                {
                    "name": "med. lic. Axel Tornberg",
                    "role": "v. ordf."
                },
                {
                    "name": "dir. Y. Holmström",
                    "role": ""
                },
                {
                    "name": "doktor Bo Sahlin",
                    "role": ""
                }
            ]
        },
        "7": {
            "name": "P. Håkanssons Konserver AB.",
            "location": "Eslöv",
            "business": "Tillverkar grönsakskonserver (spec. gurkor), fruktkonserver, äppelmos och lingonsylt.",
            "contact": {
                "office": "",
                "phone": [
                    "624 o. 652"
                ],
                "postgiro": "173325",
                "head_office": "",
                "sales_offices": [],
                "telegraph": "",
                "factory_office": "",
                "factory_phone": ""
            },
            "financials": {
                "capital": "150,000 kr",
                "employees": {
                    "Antal industriarb.": 100
                },
                "annual_turnover": "",
                "annual_production_value": ""
            },
            "foundation_year": 1940,
            "board": [
                {
                    "name": "dir. Ivar Sandberg",
                    "role": "ordf."
                },
                {
                    "name": "doktor Bo Sahlin",
                    "role": ""
                },
                {
                    "name": "med. lic. Axel Tornberg",
                    "role": ""
                },
                {
                    "name": "",
                    "role": ""
                }
            ],
            "director": "Ivar Sandberg",
            "managing_director": "",
            "sales_manager": "",
            "manager": ""
        }
    }
}