{
    "original": "Gasgenerator—Gemax\n\nAB. Gasgenerator, Örebro.\n\nTillverkar ved- och träkolsgeneratorer\nför bilar, traktorer, stationära motorer\noch för industriella ändamål.\n\nTelegr.-adr.: Gasgenerator, Örebro.\nTelefon: 19235. Postgiro: 99626. —\nAkt.-kap.: 80,000 kr. — Bolaget grundat 1929.\n\nStyrelse: jägmäst. Henrik Dieden\n(ordf.), ing. John Erikson, ing. Axel\nSvedlund.\n\nVerkst. dir.: Axel Svedlund.\n\nFörsäljn.-chef: Sune Pettersson.\n\nGas- o. Koksverkens Ekonomiska\n\nFörening u. p. a., Cokef, Stockholm.\n\nSe Gokef, Gas- o. Koksverkens\nEkonomiska Förening u. p. a., Stockholm.\n\n*AB. Gatu- och Byggnadssten,\n\nGöteborg.\tv\n\nSe AB. Geveko, Göteborg.\n\n*AB. Gatu- och\nVägbeläggnings-ämnen, Göteborg.\n\nSe AB. Geveko, Göteborg.\n\n*AB. Gavleverken, Gävle.\n\n,Mek. verkstad, gjuteri och emaljverk.\nTillverkar gas- och vedspisar,\nvattenvär-mare, värmeledningspannor, gjutgods av\ntackjärn och lättmetall,\njärnkonstruktioner samt plåtpressningsarbeten.\n\nTelegr.-adr.: Gavleverken, Gävle.\nTelefon: 43 o. 3643. Postgiro: 9962. Repr. i\nStockholm: AB. Byggnadsvaror,\nArse-nalsg. 4. Telefon: 231770.\n\nAkt.-kap.: 270,000 kr. Antal\nindustriarb.: 100. Tillv.-värde pr år: 1,400,000 kr.\n— Bolaget grundat 1912.\n\nStyrelse: konsul J. Wilh. Ericson,\n(ordf.), byråchef R. Edman, dir. Hans\nRydin, dir. Sven Wiklund.\n\nDisp.: Petrus Jacobsson.\n\nGeas Konstharts-industri, Gislaved.\n\nTillverkar massartiklar i bakelit vid\nfabrik i Gislaved (Jönköp. l.).\nSpecialitet: elektr. artiklar för staik- och\nsvagström. Varumärke: »Gaki».\n\nTelefon: 214. Postgiro: 288090. —\nAntal industriarb.: 10. — Firman etabl.\n1942.\n\nÄgare o. chef: fabr. Gustav\nAmbjörn-son.\n\nFredrik Gedin, Hälsingborg.\n\nTillverkar konstgjorda blommor,\ndekorationsartiklar, leksaksdjur i plastisk\nkonstmassa, begravningsartiklar samt\nscarves.\n\nTelegr.-adr.: Fregedin, Hälsingborg.\nTelefon: 20830. Postgiro: 90519.\n\nAntal industriarb.: 90. Tillv.-värde pr\når: 1,300,000 kr. — Firman etabl. 1937.\n\nÄgare o. chef: dir. Fredrik Gedin.\n\nCefa AB., Tranemo.\n\nTillverkar arbetskläder, byxor,\nsportjackor, skiddräkter m. m. vid fabrik i\nTranemo (Älvsb. l.).\n\nTelefon: Svenljunga 70100. Postgiro:\n134638. — Akt.-kap.: 52,000 kr. Antal\nindustriarb.: 90. — Bolaget grundat 1937.\n\nStyrelseordf. o. verkst. dir.: landsfiskal\nAnders Gustavson.\n\nGefle, se Gävle.\nGefleborg, se Gävleborg.\nAB. Geform, Hjo.\n\nKorsettfabrik i Hjo (Skarab. l.).\nTillverkar korsetter, korseletter samt\nbysthållare. Varumärke: »Geform».\n\nTelefon: 123. Postgiro: 82040. —\nAkt.-kap.: 16,000 kr. Antal industriarb.: 10.\nTillv.-värde pr år: 100,000 kr. — Bolaget\ngrundat 1939.\n\nVerkst. dir.: Ragnar Dahlgren.\n\n*Gegerfelt &amp; Weijdling AB.,\n\nGöteborg.\n\nMakaronifabrik. Tillverkar makaroner,\nsago- och potatisgryn, ris- och\nvetestärkelse, dextrin och torrklister.\n\nKontor: Vädursg. 2. Telegr.-adr.:\nGe-gerfelt, Göteborg. Telefon: 151970.\nPostgiro: 40478.\n\nAkt.-kap.: 125,000 kr. Antal\nindustriarb.: 25. Tillv.-värde pr år: 1,000,000 kr.\n\nFirman, etabl. 1882, bolag 1933, äger\nGårda Stärkelsefabrik, Göteborg.\n\nStyrelse: disp. Gunnar Loven (ordf.),\nadv. K. A. Vinge.\n\nDisp.: Gunnar Lovén.\n\nAB. Gemax-Clas, Bosersberg.\n\nTillverkar splitterfritt glas,\npansarglas samt härdat glas för trafikmedel,\nbyggnadsändamål och inredningar\nävensom for skyddsglasögon vid fabrik i\nRo-sersberg (Sthlms l.).",
    "structured": {
        "firms": [
            {
                "name": "AB. Gasgenerator",
                "location": "Örebro",
                "business": "Tillverkar ved- och träkolsgeneratorer för bilar, traktorer, stationära motorer och för industriella ändamål",
                "contact": {
                    "telegraph": "Gasgenerator, Örebro",
                    "phone": [
                        "19235"
                    ],
                    "postgiro": "99626"
                },
                "financials": {
                    "capital": "80,000 kr",
                    "foundation_year": 1929
                },
                "board": [
                    {
                        "name": "jägmäst. Henrik Dieden",
                        "role": "ordf."
                    },
                    {
                        "name": "ing. John Erikson",
                        "role": null
                    },
                    {
                        "name": "ing. Axel Svedlund",
                        "role": null
                    }
                ],
                "director": "Axel Svedlund",
                "sales_manager": "Sune Pettersson"
            },
            {
                "name": "AB. Gavleverken",
                "location": "Gävle",
                "business": "Mek. verkstad, gjuteri och emaljverk. Tillverkar gas- och vedspisar, vattenvär-mare, värmeledningspannor, gjutgods av tackjärn och lättmetall, järnkonstruktioner samt plåtpressningsarbeten",
                "contact": {
                    "telegraph": "Gavleverken, Gävle",
                    "phone": [
                        "43",
                        "3643"
                    ],
                    "postgiro": "9962",
                    "sales_offices": [
                        {
                            "location": "Stockholm",
                            "phone": "231770"
                        }
                    ]
                },
                "financials": {
                    "capital": "270,000 kr",
                    "employees": {
                        "industriarb": 100
                    },
                    "annual_turnover": "1,400,000 kr",
                    "foundation_year": 1912
                },
                "board": [
                    {
                        "name": "konsul J. Wilh. Ericson",
                        "role": "ordf."
                    },
                    {
                        "name": "byråchef R. Edman",
                        "role": null
                    },
                    {
                        "name": "dir. Hans Rydin",
                        "role": null
                    },
                    {
                        "name": "dir. Sven Wiklund",
                        "role": null
                    }
                ],
                "director": null,
                "managing_director": null
            },
            {
                "name": "Geas Konstharts-industri",
                "location": "Gislaved",
                "business": "Tillverkar massartiklar i bakelit vid fabrik i Gislaved (Jönköp. l.). Specialitet: elektr. artiklar för staik- och svagström. Varumärke: »Gaki»",
                "contact": {
                    "phone": [
                        "214"
                    ],
                    "postgiro": "288090"
                },
                "employees": {
                    "industriarb": 10
                },
                "ownership": "Ägare o. chef: fabr. Gustav Ambjörnson"
            },
            {
                "name": "Fredrik Gedin",
                "location": "Hälsingborg",
                "business": "Tillverkar konstgjorda blommor, dekorationsartiklar, leksaksdjur i plastisk konstmassa, begravningsartiklar samt scarves",
                "contact": {
                    "telegraph": "Fregedin, Hälsingborg",
                    "phone": [
                        "20830"
                    ],
                    "postgiro": "90519"
                },
                "financials": {
                    "employees": {
                        "industriarb": 90
                    },
                    "annual_turnover": "1,300,000 kr"
                },
                "ownership": "Ägare o. chef: dir. Fredrik Gedin"
            },
            {
                "name": "Cefa AB.",
                "location": "Tranemo",
                "business": "Tillverkar arbetskläder, byxor, sportjackor, skiddräkter m. m.",
                "contact": {
                    "phone": [
                        "70100"
                    ],
                    "postgiro": "134638"
                },
                "financials": {
                    "capital": "52,000 kr",
                    "employees": {
                        "industriarb": 90
                    },
                    "foundation_year": 1937
                },
                "board": [
                    {
                        "name": "landsfiskal Anders Gustavson",
                        "role": "Styrelseordf. o. verkst. dir."
                    }
                ]
            },
            {
                "name": "AB. Geform",
                "location": "Hjo",
                "business": "Korsettfabrik i Hjo (Skarab. l.). Tillverkar korsetter, korseletter samt bysthållare. Varumärke: »Geform»",
                "contact": {
                    "phone": [
                        "123"
                    ],
                    "postgiro": "82040"
                },
                "financials": {
                    "capital": "16,000 kr",
                    "employees": {
                        "industriarb": 10
                    },
                    "annual_turnover": "100,000 kr",
                    "foundation_year": 1939
                },
                "director": "Ragnar Dahlgren"
            },
            {
                "name": "Gegerfelt &amp; Weijdling AB.",
                "location": "Göteborg",
                "business": "Makaronifabrik. Tillverkar makaroner, sago- och potatisgryn, ris- och vetestärkelse, dextrin och torrklister",
                "contact": {
                    "office": "Vädursg. 2",
                    "telegraph": "Gegerfelt, Göteborg",
                    "phone": [
                        "151970"
                    ],
                    "postgiro": "40478"
                },
                "financials": {
                    "capital": "125,000 kr",
                    "employees": {
                        "industriarb": 25
                    },
                    "annual_turnover": "1,000,000 kr"
                },
                "board": [
                    {
                        "name": "disp. Gunnar Loven",
                        "role": "Styrelseordf."
                    },
                    {
                        "name": "adv. K. A. Vinge",
                        "role": null
                    }
                ],
                "director": null
            },
            {
                "name": "AB. Gemax-Clas",
                "location": "Bosersberg",
                "business": "Tillverkar splitterfritt glas, pansarglas samt härdat glas för trafikmedel, byggnadsändamål och inredningar ävensom for skyddsglasögon vid fabrik i Rosersberg (Sthlms l.).",
                "contact": {
                    "phone": null,
                    "postgiro": null
                }
            }
        ]
    }
}