{
    "original": "Bostad—Boxholm\n\n*\tBostads- &amp; Industribyggnads AB.,\n\nStockholm.\n\nByggnadsentreprenörfirma för\nbostads-och industribyggnader med\nbyggnadsverksamhet f. n. huvudsakligen i\nBlekinge och Skåne.\n\nHuvudkontor: Stockholm, Biblioteksg.\n3. Telefon: 109962. Postgiro: 56110.\nAvd.-kontor: Karlskrona, telefon: 2675—76;\nHässleholm, telefon: 455.\n\nAkt.-kap.: 150,000 kr. Antal\nindustriarb.: i Karlskrona: 90; i Hässleholm: 30.\nProd.-värde pr år: 3,300,000 kr. —\nBolaget grundat 1938.\n\nStyrelse o. verkst. dir.: arkitekt\nWol-ter Gahn (ordf.), arkitekt Georg\nLundgren.\n\nArbetschef o. avd.-chef i Karlskrona o.\nHässleholm: Georg Lundgren.\n\nKamrerare: Stockholm: Carl\nAndreasson; Karlskrona: Härved Thomsson.\n\nDriftsingenjörer: i Karlskrona: Sixten\nOlsson, Holger Rosén o. Egon Westrell.\n\n*\tBoston Blacking Company AB.,\n\nHälsingborg.\n\nKem. tekn. fabrik. Tillverkar preparat\nför sko- och läderindustrien såsom\nvatten- och kollodiumtäckfärger,\nkallpo-lersvärtor, kallpolerfärger,\novanlädersfernissor, läderfärg, skocement, skovax,\nskobeck, tåkappstyvnad,\nkorkbottenfyll-ning, skokräm och skorengöringsmedel\nsamt klistrings- och tätningsmedel\n(märke: »Bostik») för olika industriella\nändamål, blekt, raffinerad och avvaxad\nschel-lack för hatt-, lack-, spelkort-,\npolityr-m. fl. industrier. Bolaget idkar även\nengroshandel med andra\nskofabrikations-tillbehör såsom polérskivor och borstar.\n\nTelegr.-adr.: Bostonco, Hälsingborg.\nTelefon: »Boston Blacking». Postgiro:\n5566. Nederlag: Stockholm, Kungsg. 65,\noch Örebro.\n\nAkt.-kap.: 600,000 kr. Antal\nindustriarb.: 80. — Bolaget grundat 1912.\n\nStyrelse: adv. Ivan Atmer (ordf.), dir.\nK. A. A:son Bunke, dir. Arne Håkansson,\nadv. C. L. Schönmeyer, dir. A. W. Todd,\ndir. H. Webb Hyde.\n\nVerkst. dir.: K. A. A:son Bunke.\n\nKontorschef: Fredrik A. Svensson.\n\n*Botolfsen &amp; Co. Entreprenör AB.,\n\nStockholm.\n\nByggnadsentreprenörfirma för bro- och\nindustr iby ggn ader.\n\nKontor: V. Trädgårdsg. 19 B.\nTelegr.-adr.: Botolfsen, Stockholm. Telefon:\n231280. Postgiro: 155029.\n\n5\n\nAkt.-kap.: 100,000 kr. Prod.-värde pr\når: 1,750,000 kr. — Bolaget grundat 1905.\n\nStyrelse: dir. Oscar Botolfsen (ordf.),\ndipl.-ing. Lauritz S. Botolfsen.\nVerkst. dir.: L. S. Botolfsen.\n\nAB. Boviks Konservfabriker,\n\nLysekil.\n\nTillverkar ansjovis och sillkonserver,\nkaviar, fiskbullar m. m. samt\ngrönsakskonserver. Specialitet: »Vinga sill».\n\nTelegr.-adr.: Bovik, Lysekil. Telefon:\n56, 89 o. 274. Postgiro: 30300.\n\nAkt.-kap.: 402,000 kr. Antal\nindustriarb.: 82. Tillv.-värde pr år: 2,000,000 kr.\n— Firman etabl. 1892, bolag 1925.\n\nStyrelse: v. konsul Alfr. T. Bovik\n(ordf.), kamrer Erik G. Bovik.\n\nVerkst. dir.: Alfr. T. Bovik.\n\nKamrer: E. G. Bovik.\n\n* Boxholms AB., Boxholm.\n\nJärnverk med masugn,\nlancashiresmält-smedja, martin- och valsverk, drageri,\nkallvalsverk, gjuteri och mek. verkstad,\nsågverk, hyvleri, snickeri- och\nträrörs-fabrik samt elektr. kraftstationer i\nBoxholm, kalkstensbrott vid Gistad (båda i\nÖstergötl. l.) samt järnmalmsgruvor med\nanriknings- och sintringsverk vid\nKan-torp (Södermanl. l.).\n\nTillverkar tackjärn, varmvalsat # och\nkallbearbetat martin- och lancashirejärn,\nantimagnet. järn, svetsningstråd,\nvals-tråd, armerings järn, gjutgods, sågade\noch hyvlade trävaror; utför dörrar och\nfönster av svensk standardtyp,\nlamelldörrar samt trärör och träkar. Bolaget\nidkar jämväl jordbruk, skogshantering,\nkvarn- och mejerirörelse.\n\nTelegr.-adr.: Boxholmsbolaget,\nBoxholm. Telefon: 5, 16, 33 o. 77. Postgiro:\n29774.\n\nRepresentanter: Stockholm:\nRund-quist &amp; Schultz AB., Slussplan 9;\ntelefon: »Rundquist &amp; Schultz»; Göteborg:\nGustaf Fagerberg AB., Kronhusg. 16;\ntelefon: 170915; Landskrona: Cewers &amp;\nCo, telefon: 75; Alvesta: AB. Aug. Hall,\ntelefon: »Hallsbolag».\n\nAkt.-kap.: 6,000,000 kr. Antal\nindustriarb.: 1,100. Tillv.-värde pr år: 15,000,000\nkr.\n\nBolaget grundat 1872, nuv.\nbolagsordning antagen 1942. Bolaget har i sig\nupptagit f. d. AB. Kantorps Malmfält.\n\nStyrelse: dir. Carl Trygger (ordf.),\ndisp. N. Arvid Ericsson, disp. Jonas\nHult, civiling. Hakon Leffler, disp. Elis\nWettergren.",
    "structured": {
        "firms": [
            {
                "name": "Bostads- & Industribyggnads AB",
                "location": "Stockholm",
                "business": "Byggnadsentreprenörfirma för bostads- och industribyggnader",
                "contact": {
                    "office": "Biblioteksg. 3",
                    "phone": [
                        "109962"
                    ],
                    "postgiro": "56110",
                    "sales_offices": [
                        {
                            "location": "Karlskrona",
                            "phone": "2675—76"
                        },
                        {
                            "location": "Hässleholm",
                            "phone": "455"
                        }
                    ]
                },
                "financials": {
                    "capital": "150,000 kr",
                    "employees": {
                        "Karlskrona": 90,
                        "Hässleholm": 30
                    },
                    "annual_turnover": "3,300,000 kr",
                    "annual_production_value": "3,300,000 kr"
                },
                "foundation_year": 1938,
                "board": [
                    {
                        "name": "Wolter Gahn",
                        "role": "ordf."
                    },
                    {
                        "name": "Georg Lundgren",
                        "role": null
                    }
                ],
                "director": "Wolter Gahn",
                "managing_director": "Wolter Gahn",
                "owner": "Wolter Gahn"
            },
            {
                "name": "Boston Blacking Company AB",
                "location": "Hälsingborg",
                "business": "Kem. tekn. fabrik",
                "contact": {
                    "telegraph": "Bostonco",
                    "phone": "Boston Blacking",
                    "postgiro": "5566"
                },
                "financials": {
                    "capital": "600,000 kr",
                    "employees": null,
                    "annual_turnover": null,
                    "annual_production_value": null
                },
                "foundation_year": 1912,
                "board": [
                    {
                        "name": "Ivan Atmer",
                        "role": "ordf."
                    },
                    {
                        "name": "K. A. A:son Bunke",
                        "role": "dir."
                    },
                    {
                        "name": "Arne Håkansson",
                        "role": "dir."
                    },
                    {
                        "name": "C. L. Schönmeyer",
                        "role": "adv."
                    },
                    {
                        "name": "A. W. Todd",
                        "role": "dir."
                    },
                    {
                        "name": "H. Webb Hyde",
                        "role": "dir."
                    }
                ],
                "managing_director": "K. A. A:son Bunke"
            },
            {
                "name": "Botolfsen & Co. Entreprenör AB",
                "location": "Stockholm",
                "business": "Byggnadsentreprenörfirma för bro- och industr i byggn ader",
                "contact": {
                    "office": "V. Trädgårdsg. 19 B",
                    "telegraph": "Botolfsen",
                    "phone": "231280",
                    "postgiro": "155029"
                },
                "financials": {
                    "capital": "100,000 kr",
                    "employees": null,
                    "annual_turnover": null,
                    "annual_production_value": "1,750,000 kr"
                },
                "foundation_year": 1905,
                "board": [
                    {
                        "name": "Oscar Botolfsen",
                        "role": "ordf."
                    },
                    {
                        "name": "Lauritz S. Botolfsen",
                        "role": "dipl.-ing."
                    }
                ],
                "managing_director": "L. S. Botolfsen"
            },
            {
                "name": "AB. Boviks Konservfabriker",
                "location": "Lysekil",
                "business": "Tillverkar ansjovis och sillkonserver, kaviar, fiskbullar m.m. samt grönsakskonserver",
                "contact": {
                    "telegraph": "Bovik",
                    "phone": [
                        "56",
                        "89",
                        "274"
                    ],
                    "postgiro": "30300"
                },
                "financials": {
                    "capital": "402,000 kr",
                    "employees": null,
                    "annual_turnover": null,
                    "annual_production_value": "2,000,000 kr"
                },
                "foundation_year": 1892,
                "board": [
                    {
                        "name": "Alfr. T. Bovik",
                        "role": "ordf."
                    },
                    {
                        "name": "Erik G. Bovik",
                        "role": "kamrer"
                    }
                ],
                "managing_director": "Alfr. T. Bovik"
            },
            {
                "name": "Boxholms AB.",
                "location": "Boxholm",
                "business": "Järnverk med masugn, lancashiresmält smedja, martin- och valsverk, drageri, kallvalsverk, gjuteri och mek. verkstad, sågverk, hyvleri, snickeri- och trärörs-fabrik samt elektr. kraftstationer",
                "contact": {
                    "telegraph": "Boxholmsbolaget",
                    "phone": [
                        "5",
                        "16",
                        "33",
                        "77"
                    ],
                    "postgiro": "29774"
                },
                "financials": {
                    "capital": "6,000,000 kr",
                    "employees": null,
                    "annual_turnover": "15,000,000 kr",
                    "annual_production_value": "15,000,000 kr"
                },
                "foundation_year": 1872,
                "corporation_year": 1942,
                "board": [
                    {
                        "name": "Carl Trygger",
                        "role": "ordf."
                    },
                    {
                        "name": "N. Arvid Ericsson",
                        "role": "disp."
                    },
                    {
                        "name": "Jonas Hult",
                        "role": "disp."
                    },
                    {
                        "name": "Hakon Leffler",
                        "role": "civiling."
                    },
                    {
                        "name": "Elis Wettergren",
                        "role": "disp."
                    }
                ]
            }
        ]
    }
}