{
    "original": "Sydsvenska—Sågbladsfabriken\n\nSydsvenska Kraft AB., Malmö.\n\nElektr. kraftstationer vid vattenfall\ninom Hallands, Kronobergs, Kalmar,\nKristianstads och Blekinge län, elektr.\nångkraftverk i Malmö, elektr. diesel- och\nångkraftverk i Karlshamn samt under\nbyggnad varande vattenkraftstationer i\nVästernorrlands län.\n\nProducerar och inköper elektr. energi,\nsom distribueras inom Hallands,\nJönköpings, Kronobergs, Kalmar, Blekinge,\nKristianstads och Malmöhus län. Bygger\ngenom egen personal kraftverk, linjer,\ntransformatorstationer och nät.\n\nKontor: St. Nygatan 52—54.\nTelegr.-adr.: Sydkraft, Malmö. Telefon:\n»Sydkraft». Postgiro: 14192.\n\nAkt.-kap.: 29,723,800 kr. Distrib.-värde\npr år: 36,000,000 kr.\n\nBolaget, som grundades 1906, har år\n1920 övertagit Hemsjö Kraft AB:s\nsamtliga anläggningar samt äger Finsjö Kraft\nAB., Djupafors Fabriks AB., Hanefors\nNya Kraft AB. och Svalöfs Kraft AB.\n\nStyrelse: dir. Emil Olsson (ordf.),\nriksdagsm. Edwin Berling (v. ordf.),\nriksdagsman Olof Andersson, dir. Jonte\nHult-krantz, lokförare F. Hägertz, expeditör\nPer Larsson, civiling. Carl Axel Nilsson,\nlektor Sven Olsson, riksdagsm. Wald.\nOlsson, ombudsm. Nils O. Persson, ombudsm.\nHarald Schoug.\n\nVerkst. dir.: J. Hultkrantz.\n\nAndre dir.: Thure Strand.\n\nKamrer: R. Sternby.\n\növeringenjörer: Th. Björgerd, S. Stage\no. K. Ljunggren.\n\nInköpschef: Andreas Erixon.\n\n\"Sydsvenska Läder- &amp; Remfabriks\n\nAB., Ängelholm.\n\nTillverkar bottenläder (märke: »Star»),\nremläder och läder för tekn. ändamål,\nläderdrivremmar, lädersnören, sy- och\nryckremmar, pickers, manschetter,\nläder-packningar och andra tekniska\nläder-artiklar samt fot- och handbollar.\n\nTelegr.-adr.: Sydläder, Ängelholm.\nTelefon: 326, 726 o. 734. Postgiro: 33587.\n\nAkt.-kap.: 1,000,000 kr. Antal\nindustriarb.: 160. Tillv.-värde pr år: 5,000,000 kr.\n— Bolaget grundat 1914.\n\nStyrelse: bankdir. Richard Juhlin\n(ordf.), civiling. F. G. Liljenroth, dir.\nJoh. W. Rydinger.\n\nVerkst. dir. o. disp.: Joh. W. Rydinger.\n\nFabrikschef: ing. J. Brändström.\n\nKontorschef: kamrer Åke Jönsson.\n\n(Jfr annons nr 50.)\n\n\"Syfabriken Ekonomi AB.,\n\nSundsvall.\n\nKonfektionsfabrik. Tillverkar kappor,,\nbarnoveralls, klänningar, skid- och\nsportkläder.\n\nTelegr.-adr.: Ekonomifabriken,\nSundsvall. Telefon: 3043—44. Postgiro: 76638.\nRepr. i Stockholm: Karl Björklund,\nRe-geringsg. 37; telefon: 200lil.\n\nAkt.-kap.: 175,000 kr. Antal\nindustriarb.: 75. Tillv.-värde pr år: 600,000 kr„.\n— Firman etabl. 1931.\n\nStyrelse: dir. S. Felländer (ordf.).,\ndisp. G. Levål.\n\nVerkst. dir.: S. Felländer.\nDisp.: G. Levål.\n\n\"Sylva, Industribolaget, Landskrona„\nSe Industri AB. Sylva, Landskrona.\n\n\"AB. Syntes, Nol.\n\nKemisk fabrik i Nol (Älvsb. l.).\nTillverkar etyleter för narkos samt kem. och\ntekn. ren etyleter, kollodium av alla slag,,\netylacetat, formalin, ftalsyra,\nlösningsmedel samt kem.-tekn. preparat.\n\nTelefon: »Syntes», Nol. Avd.-kontor:\nStockholm, Apelbergsg. 44, telefon:\n205198. Postgiro: 1940.\n\nAkt.-kap.: 135,000 kr. Arb.-antal: 14.\nTillv.-värde pr år: 500,000 kr. — Bolaget\ngrundat 1913.\n\nStyrelse o. verkst. dir.: apot. Hj. A:n\nTesch (Stockholm). #\n\nFabrikschef: civiling. Lennart\nMattsson.\n\n\"AB. Syrabruk, Stockholm.\n\nTillverkar syra- och alkali fasta\nmurmassor (varumärke: »AX») vid fabrik i\nHärnösand samt utför dylika murningar\npå entreprenad.\n\nHuvud- o. försäljn.-kontor, Stockholm,\nKungsg. 27, telefon: 200048 o. 102348.\n\nAkt.-kap.: 50,000 kr. Arb.-antal: 14..\nProd.-värde pr år: 500,000 kr. — Bolaget\ngrundat 1939.\n\nStyrelse: ing. Fritz Ramström (ordf.);,,\ndir. Nils Ultvedt.\n\nVerkst. dir.: N. Ultvedt.\nDriftsing.: I. Björnstad.\n\n\"Syrgasfabriken Flytande Luft,\n\nMalmö.\n\nSe G. C. Faxe AB., Malmö.\n\n\"AB. Sågbladsfabriken i Nora, Nora„\n\nTillverkar sågblad och maskinhyveljärn.\nTelegr.-adr.: Sågbladsfabrik, Nora. Te-",
    "structured": {
        "1": {
            "name": "Sydsvenska Kraft AB",
            "location": "Malmö",
            "business": "Elektr. kraftstationer",
            "contact": {
                "office": "St. Nygatan 52—54",
                "telegraph": "Sydkraft, Malmö",
                "phone": [
                    "Sydkraft"
                ],
                "postgiro": "14192"
            },
            "financials": {
                "capital": "29,723,800 kr",
                "annual_turnover": "36,000,000 kr"
            },
            "foundation_year": 1906,
            "predecessor": "Hemsjö Kraft AB",
            "owners": [
                "Finsjö Kraft AB",
                "Djupafors Fabriks AB",
                "Hanefors Nya Kraft AB",
                "Svalöfs Kraft AB"
            ],
            "board": [
                {
                    "name": "Emil Olsson",
                    "role": "ordf."
                },
                {
                    "name": "Edwin Berling",
                    "role": "v. ordf."
                },
                {
                    "name": "Olof Andersson",
                    "role": "riksdagsman"
                },
                {
                    "name": "Jonte Hultkrantz",
                    "role": "dir."
                },
                {
                    "name": "F. Hägertz",
                    "role": "lokförare"
                },
                {
                    "name": "Per Larsson",
                    "role": "expeditör"
                },
                {
                    "name": "Carl Axel Nilsson",
                    "role": "civiling."
                },
                {
                    "name": "Sven Olsson",
                    "role": "lektor"
                },
                {
                    "name": "Wald. Olsson",
                    "role": "riksdagsman"
                },
                {
                    "name": "Nils O. Persson",
                    "role": "ombudsm."
                },
                {
                    "name": "Harald Schoug",
                    "role": "ombudsm."
                }
            ],
            "director": "J. Hultkrantz",
            "managing_director": "Thure Strand",
            "kamrer": "R. Sternby",
            "overingenjörer": [
                "Th. Björgerd",
                "S. Stage",
                "K. Ljunggren"
            ],
            "inköpschef": "Andreas Erixon"
        },
        "2": {
            "name": "Sydläder & Remfabriks AB",
            "location": "Ängelholm",
            "business": "Tillverkar bottenläder (märke: Star), remläder och läder för tekn. ändamål, läderdrivremmar, lädersnören, sy- och ryckremmar, pickers, manschetter, läder-packningar och andra tekniska läder-artiklar samt fot- och handbollar",
            "contact": {
                "telegraph": "Sydläder, Ängelholm",
                "phone": [
                    "326",
                    "726",
                    "734"
                ],
                "postgiro": "33587"
            },
            "financials": {
                "capital": "1,000,000 kr"
            },
            "foundation_year": 1914,
            "board": [
                {
                    "name": "Richard Juhlin",
                    "role": "bankdir."
                },
                {
                    "name": "F. G. Liljenroth",
                    "role": "civiling."
                },
                {
                    "name": "Joh. W. Rydinger",
                    "role": "dir."
                }
            ],
            "managing_director_disp": "Joh. W. Rydinger",
            "fabrikschef": "J. Brändström",
            "kontorschef": "Åke Jönsson"
        },
        "3": {
            "name": "Syfabriken Ekonomi AB",
            "location": "Sundsvall",
            "business": "Konfektionsfabrik. Tillverkar kappor, barnoveralls, klänningar, skid- och sportkläder",
            "contact": {
                "telegraph": "Ekonomifabriken, Sundsvall",
                "phone": [
                    "3043—44"
                ],
                "postgiro": "76638"
            },
            "financials": {
                "capital": "175,000 kr"
            },
            "foundation_year": 1931,
            "board": [
                {
                    "name": "S. Felländer",
                    "role": "dir."
                },
                {
                    "name": "G. Levål",
                    "role": "disp."
                }
            ],
            "managing_director": "S. Felländer",
            "disp": "G. Levål"
        },
        "4": {
            "name": "AB. Syntes",
            "location": "Nol",
            "business": "Kemisk fabrik i Nol (Älvsb. l.). Tillverkar etyleter för narkos samt kem. och tekn. ren etyleter, kollodium av alla slag,etylacetat, formalin, ftalsyra, lösningsmedel samt kem.-tekn. preparat",
            "contact": {
                "phone": [
                    "Syntes, Nol"
                ],
                "postgiro": "1940"
            },
            "financials": {
                "capital": "135,000 kr"
            },
            "foundation_year": 1913,
            "director": "apot. Hj. A:n Tesch",
            "fabrikschef": "civiling. Lennart Mattsson"
        },
        "5": {
            "name": "AB. Syrabruk",
            "location": "Stockholm",
            "business": "Tillverkar syra- och alkali fasta murmassor (varumärke: AX) vid fabrik i Härnösand samt utför dylika murningar på entreprenad",
            "contact": {
                "phone": [
                    "200048",
                    "102348"
                ]
            },
            "financials": {
                "capital": "50,000 kr"
            },
            "foundation_year": 1939,
            "director": "ing. Fritz Ramström",
            "verkst_dir": "Nils Ultvedt",
            "driftsing": "I. Björnstad"
        },
        "6": {
            "name": "Sågbladsfabriken i Nora",
            "location": "Nora",
            "business": "Tillverkar sågblad och maskinhyveljärn",
            "telegraph": "Sågbladsfabrik, Nora"
        }
    }
}