{
    "original": "Habo—Hagaverken\n\nH\n\n* utmärker till Sveriges Industriförbund anslutna företag.\n\n*Habo Laggkärlsfabrik, Habo.\n\nLaggkärlsfabrik med såg och hyvleri\ni Habo (Skarab. l.). Tillverkar\nvattenämbar, tvättbaljor, sylt- och saltkärl,\nvattentätt träemballage, tunnor, större kar\noch behållare för industriändamål m. m.\n\nTelefon: 16 o. 139. Postgiro: 81481. —\nAntal industriarb.: 85. Tillv.-värde pr år:\n1,100,000 kr. — Firman etabl. 1892.\n\nÄgare: F. E. Carlssons sterbhns.\n\nDisp.: Trygve Elwing.\n\nIng.: Karl Evert Hansson.\n\n*Habo Ullspinneri AB., Habo.\n\nUllspinneri, ylleväveri, färgeri och\nberedningsverk i Habo (Skarab. l.).\nTillverkar filtar och svenskullgarner.\nVarumärke: »Habo».\n\nTelegr.-adr.: Ullspinneriet, Habo.\nTelefon: 5. Postgiro: 23118.\n\nAkt.-kap.: 200,000 kr. Antal\nindustriarb.: 90. Tillv.-värde pr år: 1,500,000 kr.\n\n—\tFirman etabl. 1882, bolag 1931.\n\nStyrelse: fabr. Anders Werthén, fabr.\n\nBror Werthén.\n\nVerkst. dir,: Bror Werthén.\n\nHackefors Porslin AB., Hackefors.\n\nTillverkar kaffe-, te- och bordsserviser,\nrestaurantporslin i fältspatäkta kvalitet\nsamt elektrotekniskt porslin vid fabrik i\nHackefors (Östergötl. l.).\n\nTelegr.-adr.: Hackeforsbruk,\nLinköping. Telefon: Linköping 59150.\nPostgiro: 7688.\n\nAkt.-kap.: 250,000 kr. Antal\nindustriarb.: 125. Tillv.-värde pr år: 2,000,000 kr.\n\n—\tBolaget grundat 1929.\n\nStyrelse: dir. Jonn-Olof Nilson (ordf.),\ngreve Johan Falkenberg, förvalt.\nJonn-Olof Nilson. ;\n\nVerkst. dir.: Jonn-Olof Nilson.\n\nDisp.: Karl-Erik Möller.\n\nHaeggström, se H äggström.\n\nHaga Möbelfabrik, Värnamo.\n\nSe AB. Möbelfabriken Haga, Värnamo.\n\n*AB. Haga Skofabrik, Stockholm.\n\nSkofabrik i Örebro. Tillverkar\ndamskodon.\n\nHuvudkontor: Stockholm, Sveavägen\n82. Telefon: 317825. Postgiro: 150390.\n\nAkt.-kap.: 15,000 kr. Antal\nindustriarb.: 30. Tillv.-värde pr år: 500,000 kr.\n\n—\tFirman etabl. 1933, bolag 1934.\nStyrelse o. verkst. dir.: ing. Herman\n\nSeifert.\n\n*AB. Hagafors Stolfabrik, Nässjö.\n\nSnickerifabrik i Hok (Jönköp. l.).\nTillverkar stolar och bord av björk och ek.\n\nKontor: Nässjö. Telegr.-adr.:^\nHaga-forsstol, Nässjö. Telefon: Nässjö 990.\nPostgiro: 33331.\n\nAkt.-kap.: 150,000 kr. Antal\nindustriarb.: 50. Tillv.-värde pr år: 530,000 kr.\n\n—\tFirman etabl. 1863. bolag 1918.\nStyrelse: ing. J. Ljungqvist (ordf.),\n\nkamrer A. Herentz, disp. H. Thunander.\nVerkst. dir.: J. Ljungqvist.\n\n* Hagaströms Tegelbruks AB.,\n\nGävle.\n\nTillverkar murtegel, fasad tegel och\nmellanväggsplattor vid tegelbruk i\nHagaström (Gävleb. l.).\n\nTelefon: 58 o. 358. Postgiro: 22012. —\nAkt.-kap.: 80,000 kr. Antal industriarb.:\n20. Årstillv.: 1,5 milj. st. tegelvaror. —\nBolaget grundat 1890.\n\nStyrelse: ing. Vilhelm Nordström\n(ordf.), ing. J. E. Lindbom, ing. Erik\nNordström, maskindir. Fritz Nordström,\ning. Sten Nordström.\n\nVerkst. dir.: Erik Nordström.\n\n*AB. Hagaverken, Enköping.\n\nTegelbruk vid Haga, Enköping.\nTillverkar mur- och taktegel,\nmellanväggs-plattor, reveteringstegel samt\ndräneringsrör.\n\nTelefon: Enköping 293 o. 451.\nPostgiro: 6481.\n\nAkt.-kap.: 400,000 kr. Antal\nindustriarb.: 50. Årstillv.: 6,5 milj. st.\ntegelvaror.— Bruket anlagt 1884, nuv. bolag\ngrundat 1922.\n\n205*",
    "structured": {
        "1": {
            "namn": "Habo Laggkärlsfabrik",
            "plats": "Habo",
            "affärsbeskrivning": "Laggkärlsfabrik med såg och hyvleri i Habo (Skarab. l.). Tillverkar vattenämbar, tvättbaljor, sylt- och saltkärl, vattentätt träemballage, tunnor, större kar och behållare för industriändamål m. m.",
            "kontakt": {
                "telefon": [
                    "16",
                    "139"
                ],
                "postgiro": "81481"
            },
            "finansiell_information": {
                "ankapital": "Okänt",
                "anställda": {
                    "industriarb": 85
                },
                "årlig_omsättning": "1,100,000 kr",
                "årlig_produktionsvärde": "Okänt"
            },
            "grundande_år": 1892,
            "ägare": "F. E. Carlssons sterbhns",
            "disp": "Trygve Elwing",
            "ing": "Karl Evert Hansson"
        },
        "2": {
            "namn": "Habo Ullspinneri AB.",
            "plats": "Habo",
            "affärsbeskrivning": "Ullspinneri, ylleväveri, färgeri och beredningsverk i Habo (Skarab. l.). Tillverkar filtar och svenskullgarner. Varumärke: »Habo».",
            "kontakt": {
                "telefon": "5",
                "postgiro": "23118"
            },
            "finansiell_information": {
                "ankapital": "200,000 kr",
                "anställda": {
                    "industriarb": 90
                },
                "årlig_omsättning": "1,500,000 kr",
                "årlig_produktionsvärde": "Okänt"
            },
            "grundande_år": 1882,
            "styrelse": [
                "fabr. Anders Werthén",
                "fabr. Bror Werthén"
            ],
            "verkst_dir": "Bror Werthén"
        },
        "3": {
            "namn": "Hackefors Porslin AB.",
            "plats": "Hackefors",
            "affärsbeskrivning": "Tillverkar kaffe-, te- och bordsserviser, restaurantporslin i fältspatäkta kvalitet samt elektrotekniskt porslin vid fabrik i Hackefors (Östergötl. l.).",
            "kontakt": {
                "telefon": "Linköping 59150",
                "postgiro": "7688"
            },
            "finansiell_information": {
                "ankapital": "250,000 kr",
                "anställda": {
                    "industriarb": 125
                },
                "årlig_omsättning": "2,000,000 kr",
                "årlig_produktionsvärde": "Okänt"
            },
            "grundande_år": "Okänt",
            "styrelse": [
                "dir. Jonn-Olof Nilson (ordf.)",
                "greve Johan Falkenberg",
                "förvalt. Jonn-Olof Nilson"
            ],
            "verkst_dir": "Jonn-Olof Nilson",
            "disp": "Karl-Erik Möller"
        },
        "4": {
            "namn": "AB. Haga Skofabrik",
            "plats": "Stockholm, Sveavägen 82",
            "affärsbeskrivning": "Skofabrik i Örebro. Tillverkar damskodon.",
            "kontakt": {
                "telefon": "317825",
                "postgiro": "150390"
            },
            "finansiell_information": {
                "ankapital": "15,000 kr",
                "anställda": {
                    "industriarb": 30
                },
                "årlig_omsättning": "500,000 kr",
                "årlig_produktionsvärde": "Okänt"
            },
            "grundande_år": 1933,
            "styrelse_och_verkstdir": "ing. Herman Seifert"
        },
        "5": {
            "namn": "AB. Hagafors Stolfabrik",
            "plats": "Nässjö",
            "affärsbeskrivning": "Tillverkar stolar och bord av björk och ek.",
            "kontakt": {
                "telefon": "Nässjö 990",
                "postgiro": "33331"
            },
            "finansiell_information": {
                "ankapital": "150,000 kr",
                "anställda": {
                    "industriarb": 50
                },
                "årlig_omsättning": "530,000 kr",
                "årlig_produktionsvärde": "Okänt"
            },
            "grundande_år": 1863,
            "styrelse_och_verkstdir": "J. Ljungqvist"
        },
        "6": {
            "namn": "Hagaströms Tegelbruks AB.",
            "plats": "Gävle",
            "affärsbeskrivning": "Tillverkar murtegel, fasad tegel och mellanväggsplattor vid tegelbruk i Hagaström (Gävleb. l.).",
            "kontakt": {
                "telefon": [
                    "58",
                    "358"
                ],
                "postgiro": "22012"
            },
            "finansiell_information": {
                "ankapital": "80,000 kr",
                "anställda": {
                    "industriarb": 20
                },
                "årlig_omsättning": "Okänt",
                "årlig_produktionsvärde": "1,5 milj. st. tegelvaror"
            },
            "grundande_år": 1890,
            "styrelse_och_verkstdir": "Erik Nordström"
        },
        "7": {
            "namn": "AB. Hagaverken",
            "plats": "Enköping",
            "affärsbeskrivning": "Tillverkar mur- och taktegel, mellanväggs-plattor, reveteringstegel samt dräneringsrör vid Haga, Enköping.",
            "kontakt": {
                "telefon": [
                    "Enköping 293",
                    "451"
                ],
                "postgiro": "6481"
            },
            "finansiell_information": {
                "ankapital": "400,000 kr",
                "anställda": {
                    "industriarb": 50
                },
                "årlig_omsättning": "6,5 milj. st. tegelvaror",
                "årlig_produktionsvärde": "Okänt"
            },
            "grundande_år": 1922
        }
    }
}