{
    "original": "He llmdn—Hennig\n\nHellmans Gjuter! &amp; Mek. Verkstads\nAB., Norberg.\n\nTillverkar transportanordningar,\njärnkonstruktioner och gjutgrods samt utför\nmaskin-, plåt- och svetsningsarbeten vid\nverkstad i Norberg (Västmanl. l.).\n\nTelefon: 132 o. 199. Postgiro: 133019.\n\n—\tAkt.-kap.: 50,000 kr. Antal\nindustriarb.: 30. Tillv.-värde pr år: 400,000 kr.\n\n—\tFirman etabl. 1928, bolag 1930.\nStyrelse o. verkst. dir.: Alvar Hellman.\n\nB.\tHellman, Oskarshamn.\n\nSe Oscarshamns Pappersindustri, B.\nHellman, Oskarshamn.\n\n*AB. Max Hellmann, Norrköping.\n\nYlleväveri. Tillverkar finare\nkamgarns-tyger, cheviot och paletå. Specialitet:\n»Kungl. Motorbåtsklubbens cheviot».\n\nTelegr.-adr.: Maxmann. Norrköping.\nTelefon: 20002, 25001 o. 25012. Postgiro:\n92500.\n\nAkt.-kap.: 400,000 kr. Antal\nindustriarb.: 120. Tillv.-värde pr år: 3,800,000 kr.\n\nFirman etabl. 1894 under namn Gust.\nWahren J:or, bolag 1919.\n\nStyrelse: konsul Carl Fr. Hellmann\n(ordf.), disp. Gösta W. Hellmann,\nkontorschef Martin Petterson.\n\nVerkst. direktörer: Carl Fr. Hellmann.\no. Gösta W. Hellmann.\nKontorschef: Martin Petterson.\n\nAB. A. Heltqvist, Göteborg.\n\nPåsfabrik i Alingsås. Tillverkar\npapperspåsar, vaxpapper, tryckt\nomslagspapper, toalettpapper, hyllpapper samt\ngoff-rerat papper.\n\nHuvudkontor: Göteborg, Mellbyg.\nTelefon: 157001—04. Postgiro: 43438.\nFabrikskontor: Alingsås. Telefon: 135.\n\nAkt.-kap.: 60,000 kr. Antal\nindustriarb.: 30. Tillv.-värde pr år: 750,000 kr.\n\n—\tBolaget grundat 1920.\n\nVerkst. dir.: John Magnusson\n(Göteborg).\n\nFabriks förest.: ing. Folke Hansson.\n\nC.\tHellqwist &amp; Co., Tranås.\n\nSe AB. Pälsvaror, G. Hellqwist &amp; Co.,\nTranås.\n\nAB. Wilh. Hellströms Trikåindustri,\n\nGöteborg.\n\nCharmeuseväveri och-\ndamkonfektionsfabrik. ^ Tillverkar dam- och\nherrunderkläder i charmeuse, huvudsakligast dam-\n\nartiklar såsom linnen, benkläder,\nnattlinnen m. m.\n\nKontor: By fogdeg. 13. Telefon: 158116.\nPostgiro: 45776.\n\nAkt.-kap.: 40,000 kr. Antal\nindustriarb.: 18. Tillv.-värde pr år: 350,000 kr.\n— Firman etabl. 1938.\n\nVerkst. dir.: Erik L. Pedersen (Borås).\n\nHelmar AB., Göteborg.\n\nKem.-teknisk fabrik. Tillverkar\nolje-reningsfilter m. m.\n\nKontor: Kvilleg. 9 c. Telegr.-adr.:\nLa-tem, Göteborg. Telefon: 118500 o.\n225236. Postgiro: 48610. — Akt.-kap.:\n18,000 kr. Antal industriarb.: 5.\n—Bolaget grundat 1943.\n\nStyrelse o. verkst. dir. J. H.\nVester-lund.\n\n(Jfr annons nr 48.)\n\nHelsingborg, se Hälsingborg.\n\nAB. Hemper, Göteborg.\n\nSe xAB. Henning Persson, Göteborg.\n\nHemsjö Kraft AB., Malmö.\n\nSe Sydsvenska Kraft AB.V Malmö.\n\nHen jo AB., Malung.\n\nTillverkar tröjor, kavajer, rockar och\nvästar av skinn samt dam- och\nherrhandskar, sport- och arbetshandskar vid fabrik\ni Malung (Kopparb. l.).\n\nTelefon: 37. Postgiro: 11644. —\nAkt.-kap.: 75,000 kr. Antal industriarb.: 30.\nTillv.-värde pr år: 500,000 kr. —\nBolaget grundat 1937 under namn Henrik\nJohnsson &amp; Comp. Skinnindustri AB.,\nnuv. namn 1946.\n\nVerkst. dir.: Henrik Johnsson.\n\n*Henkel Kemiskt-Tekniskt AB.,\n\nStockholm.\n\nSe Helios Kemisk-Tekniska Fabriker\nAB., Stockholm.\n\n*AB. Hugo Hennig, Borås.\n\nBolaget, driver som huvudrörelse\nhandel med textilmaskiner och\nfabriksförnödenheter samt innehar Svenska\nStål-solffabriken, Borås, som tillverkar\nstål-solv, kompletta skaftramar jämte\ntillbehör, jacquardvikter m. m.\n\nTelegr.-adr.: Hennig. Borås. Telefon:\n10698, 11768 o. 11440. Postgiro: 6777. —",
    "structured": {
        "firms": [
            {
                "name": "Hellmans Gjuteri & Mek. Verkstad AB",
                "location": "Norberg",
                "business": "Tillverkar transportanordningar, järnkonstruktioner och gjutgods samt utför maskin-, plåt- och svetsningsarbeten vid verkstad i Norberg (Västmanlands län).",
                "contact": {
                    "office": "Telefon: 132 o. 199",
                    "postgiro": "133019"
                },
                "financials": {
                    "capital": "50,000 kr",
                    "employees": {
                        "industriarb.": 30
                    },
                    "annual_turnover": "400,000 kr",
                    "annual_production_value": "400,000 kr"
                },
                "foundation_year": 1928,
                "corporation_year": 1930,
                "board": [
                    {
                        "name": "Alvar Hellman",
                        "role": "Styrelse o. verkst. dir."
                    }
                ]
            },
            {
                "name": "AB. Max Hellmann",
                "location": "Norrköping",
                "business": "Ylleväveri. Tillverkar finare kamgarns-tyger, cheviot och paletå.",
                "contact": {
                    "telegraph": "Maxmann. Norrköping",
                    "phone": [
                        "20002",
                        "25001",
                        "25012"
                    ],
                    "postgiro": "92500"
                },
                "financials": {
                    "capital": "400,000 kr",
                    "employees": {
                        "industriarb.": 120
                    },
                    "annual_turnover": "3,800,000 kr",
                    "annual_production_value": "3,800,000 kr"
                },
                "foundation_year": 1894,
                "corporation_year": 1919,
                "board": [
                    {
                        "name": "konsul Carl Fr. Hellmann",
                        "role": "Styrelse"
                    },
                    {
                        "name": "disp. Gösta W. Hellmann",
                        "role": "Styrelse"
                    },
                    {
                        "name": "Martin Petterson",
                        "role": "Kontorschef"
                    }
                ],
                "director": "Carl Fr. Hellmann o. Gösta W. Hellmann",
                "manager": "Martin Petterson"
            },
            {
                "name": "AB. A. Heltqvist",
                "location": "Göteborg",
                "business": "Påsfabrik i Alingsås. Tillverkar papperspåsar, vaxpapper, tryckt omslagspapper, toalettpapper, hyllpapper samt goffrerat papper.",
                "contact": {
                    "office": "Huvudkontor: Göteborg, Mellbyg.",
                    "phone": "157001—04",
                    "postgiro": "43438",
                    "factory_office": "Fabrikskontor: Alingsås",
                    "factory_phone": "135"
                },
                "financials": {
                    "capital": "60,000 kr",
                    "employees": {
                        "industriarb.": 30
                    },
                    "annual_turnover": "750,000 kr",
                    "annual_production_value": "750,000 kr"
                },
                "corporation_year": 1920,
                "manager": "John Magnusson (Göteborg)"
            },
            {
                "name": "AB. Wilh. Hellströms Trikåindustri",
                "location": "Göteborg",
                "business": "Charmeuseväveri och damkonfektionsfabrik. Tillverkar dam- och herrunderkläder i charmeuse, huvudsakligen damartiklar såsom linnen, benkläder, nattlinnen m. m.",
                "contact": {
                    "office": "Kontor: Byfogdeg. 13",
                    "phone": "158116",
                    "postgiro": "45776"
                },
                "financials": {
                    "capital": "40,000 kr",
                    "employees": {
                        "industriarb.": 18
                    },
                    "annual_turnover": "350,000 kr",
                    "annual_production_value": "350,000 kr"
                },
                "foundation_year": 1938,
                "manager": "Erik L. Pedersen (Borås)"
            },
            {
                "name": "Helmar AB.",
                "location": "Göteborg",
                "business": "Kemisk-teknisk fabrik. Tillverkar oljereningsfilter m. m.",
                "contact": {
                    "office": "Kontor: Kvilleg. 9 c",
                    "telegraph": "La-tem, Göteborg",
                    "phone": [
                        "118500",
                        "225236"
                    ],
                    "postgiro": "48610"
                },
                "financials": {
                    "capital": "18,000 kr",
                    "employees": {
                        "industriarb.": 5
                    }
                },
                "corporation_year": 1943,
                "board": [
                    {
                        "name": "J. H. Vesterlund",
                        "role": "Styrelse o. verkst. dir."
                    }
                ]
            },
            {
                "name": "Henjo AB.",
                "location": "Malung",
                "business": "Tillverkar tröjor, kavajer, rockar och västar av skinn samt dam- och herrhandskar, sport- och arbetshandskar vid fabrik i Malung (Kopparbergs län).",
                "contact": {
                    "phone": "37",
                    "postgiro": "11644"
                },
                "financials": {
                    "capital": "75,000 kr",
                    "employees": {
                        "industriarb.": 30
                    },
                    "annual_turnover": "500,000 kr",
                    "annual_production_value": "500,000 kr"
                },
                "corporation_year": 1937,
                "director": "Henrik Johnsson"
            },
            {
                "name": "AB. Hugo Hennig",
                "location": "Borås",
                "business": "Handel med textilmaskiner och fabriksförnödenheter samt Svenska Stålsolfabriken, Borås, som tillverkar stålsolv, kompletta skaftramar jämte tillbehör, jacquardvikter m. m.",
                "contact": {
                    "telegraph": "Hennig. Borås",
                    "phone": [
                        "10698",
                        "11768",
                        "11440"
                    ],
                    "postgiro": "6777"
                }
            }
        ]
    }
}