{
    "original": "Wicander—Widtsköfle\n\n\"AB. Wicanders Korkfabriker,\n\nStockholm.\n\nKorkfabriker i Stockholm, Göteborg och\nÄlvängen (Älvsb. l.), mek. verkstad i\nLinköping. Tillverkar kork, natur- och\npresskorkskivor, presskorkpackningar,\nkronkork, skruvkapsyler med\nförseglings-ring, korkparkett,\nflasktillslutningsma-skiner (märke: »Alka») samt\nflaskför-slutningar såsom patentkork och\naluminiumkapslar.\n\nHuvudkontor: Stockholm, Brännkyrkag.\n66. Telegr.-adr.: Wicanders, Stockholm.\nTelefon: 440350. Postgiro: 715.\n\nAvd.-kontor: Linköping. Telegr.-adr.:\nAlka, Linköping. Telefon: »Alka» o.\n29830. Postgiro: 85370.\n\nAkt.-kap.: 6,000,000 kr. Antal\nindustriarb.: 350, varav i Linköping 100. —\nBolaget grundat 1889.\n\nStyrelse: dir. Carl August Wicander\n(ordf.), adv. Dick Bergman, dir. Hjalmar\nHensmar, dir. G. Rooth, kapten S.\nRud-berg, dir. Carl Gustaf Wicander.\n\nVerkst. dir.: Carl Gustaf Wicander.\n\nV. verkst. direktörer: Stockholm: Hj.\nHensmar; Linköping: G. Rooth o. Felix\nBerglund.\n\nDisp. i Göteborg: Axel Jörnell.\n\n\"Sten Wicéns Möbelindustri,\n\nSmålands Farstorp.\n\nTillverkar möbler, speciellt sittmöbler,\nvid fabrik i Smålands Farstorp\n(Jönköp. l.).\n\nTelefon: 28. Postgiro: 145390. — Antal\nindustriarb.: 15. — Firman etabl. 1937.\n\nÄgare o. chef: fabr. Sten Wicén.\n\n\"Victoria, Bryggeriet, Falköping.\n\nSe Bryggeriet Victoria, Falköping.\n\n\"Victoria, Fabriks AB., Hälsingborg.\n\nSe Fabriks AB. Victoria, Hälsingborg.\n\n\"Victoria, Skofabriken, Örebro.\n\nSe AB. Skofabriken Victoria, Örebro.\n\n\"AB. Victor in &amp; Strand, Västervik.\n\nTrikå-, strump- och syfabrik\n(Västerviks Trikå- &amp; Syfabrik). Tillverkar\nylle-trikåvaror, strumpor, arbets- och\nsportkläder samt skjortor. Varumärken: »VS»,\n»Victorins» o. »Lodbrok» (arbetskläder).\nFirman driver även engroshandel med\ngarn och vävnader.\n\n65\n\nTelegr.-adr.: Garnbolaget, Västervik.\nTelefon: 7, 147 o. 787. Postgiro: 26817.\n\nAkt.-kap.: 150,000 kr. Antal\nindustriarb.: 70. Tillv.-värde pr år: 900,000 kr.\n\n—\tFirman etabl. 1895, bolag 1915.\nVästerviks Trikå- &amp; Syfabrik etabl. 1932.\n\nStyrelse: f. bankdir. Josef Victorin\n(ordf.), dir. Hugo Landegren, dir. Nils\nVictorin.\n\nVerkst. dir.: Nils Victorin.\n\nWidebolaget AB., Malmö.\n\nKem.-teknisk fabrik. Tillverkar\nträim-pregneringsmedel (märke: »Aloxyl»),\nasfaltprodukter, färger och lösningsmedel.\nBolaget driver även handel med\nsmörjoljor och byggnadsmaterial.\n\nKontor: Gust. Ad. torg 8 A. Telefon:\n15340. Postgiro: 148230. — Akt.-kap.:\n100,000 kr. Ärb.-antal: 4. Tillv.-värde pr\når: 150,000 kr. — Firman etabl. 1940,\nnuv. bolag 1943.\n\nDisp.: Greger Bergström.\n\nFörsäljn.-chef: Arthur Strömer.\n\n\"AB. L. &amp; P. Widengren,\n\nVingåker.\n\nKonfektionsfabrik i Vingåker\n(Södermanl. l.). Tillverkar herr- och gosskläder\nsamt damdräkter.\n\nTelegr.-adr. o. telefon: »Widengrens»,\nVingåker. Postgiro: 3741.\n\nAkt.-kap.: 1,225,000 kr. Antal\nindustriarb.: 468. Tillv.-värde pr år: 7,800,000 kr.\n\n—\tFirman etabl. 1877, bolag 1903.\n\nStyrelse: dir. Henrik Widengren\n\n(ordf.), adv. Knut Strömberg, dir. Per\nWidengren.\n\nVerkst. dir.: Per Widengren.\n\nInköps- o. försäljn.-chef: A. Grahn.\n\n\"AB. Widsell &amp; Co., Norsholm.\n\nTillverkar speglar, spegel- och\nfotografiramar, ovala och runda ramar,\ntapet-och ramlister vid fabrik i Norsholm\n(ös-tergötl. !•)•\n\nTelefon: 96. Postgiro: 28336. —\nAkt.-kap.: 10,000 kr. Arb.-antal: 9. — Firman\netabl. 1926, bolag 1938.\n\nStyrelse, verkst. dir. o. disp.: Börje\nVilhelmson.\n\nAB. Widtsköfle, Vittskövle.\n\nTegelbruk och sågverk i Vittskövle\n(Kristianst. l.). Tillverkar kalksandstegel,\nsågade trävaror, takspån m. m. Firman\ndriver även jordbruk, handelsträdgård\nsamt skogshantering.\n\nL*",
    "structured": {
        "1": {
            "name": "AB. Wicanders Korkfabriker",
            "location": "Stockholm",
            "business": "Korkfabriker",
            "products": "Tillverkar kork, natur- och presskorkskivor, presskorkpackningar, kronkork, skruvkapsyler med förseglings-ring, korkparkett, flasktillslutningsma-skiner (märke: »Alka») samt flaskför-slutningar såsom patentkork och aluminiumkapslar.",
            "contact": {
                "office": "Stockholm, Brännkyrkag. 66",
                "phone": [
                    "440350"
                ],
                "postgiro": "715",
                "head_office": "Stockholm, Brännkyrkag. 66",
                "telegraph": "Wicanders, Stockholm"
            },
            "financials": {
                "capital": "6,000,000 kr",
                "employees": {
                    "total": 350,
                    "Linköping": 100
                }
            },
            "foundation_year": 1889,
            "board": [
                {
                    "name": "Carl August Wicander",
                    "role": "ordf."
                },
                {
                    "name": "Dick Bergman",
                    "role": "adv."
                },
                {
                    "name": "Hjalmar Hensmar",
                    "role": "dir."
                },
                {
                    "name": "G. Rooth",
                    "role": "dir."
                },
                {
                    "name": "S. Rud-berg",
                    "role": "kapten"
                },
                {
                    "name": "Carl Gustaf Wicander",
                    "role": "dir."
                }
            ],
            "director": "Carl Gustaf Wicander",
            "managing_director": "Carl Gustaf Wicander",
            "sales_manager": "Hj. Hensmar",
            "manager": "Carl Gustaf Wicander"
        },
        "2": {
            "name": "Sten Wicéns Möbelindustri",
            "location": "Smålands Farstorp",
            "business": "Möbelindustri",
            "products": "Tillverkar möbler, speciellt sittmöbler",
            "contact": {
                "phone": "28",
                "postgiro": "145390"
            },
            "financials": {
                "employees": {
                    "total": 15
                }
            },
            "foundation_year": 1937,
            "owners": [
                "Sten Wicén"
            ],
            "director": "Sten Wicén"
        },
        "3": {
            "name": "AB. Victorin & Strand",
            "location": "Västervik",
            "business": "Trikå-, strump- och syfabrik",
            "products": "Tillverkar ylle-trikåvaror, strumpor, arbets- och sportkläder samt skjortor. Firman driver även engroshandel med garn och vävnader.",
            "contact": {
                "phone": [
                    "7",
                    "147",
                    "787"
                ],
                "postgiro": "26817"
            },
            "financials": {
                "capital": "150,000 kr",
                "employees": {
                    "total": 70
                },
                "annual_production_value": "900,000 kr"
            },
            "foundation_year": 1895,
            "current_name_year": 1915,
            "owners": [
                "f. bankdir. Josef Victorin"
            ],
            "director": "Nils Victorin"
        },
        "4": {
            "name": "Widebolaget AB.",
            "location": "Malmö",
            "business": "Kem.-teknisk fabrik",
            "products": "Tillverkar träim-pregneringsmedel (märke: »Aloxyl»), asfaltprodukter, färger och lösningsmedel. Bolaget driver även handel med smörjoljor och byggnadsmaterial.",
            "contact": {
                "office": "Gust. Ad. torg 8 A",
                "phone": [
                    "15340"
                ],
                "postgiro": "148230"
            },
            "financials": {
                "capital": "100,000 kr",
                "employees": {
                    "total": 4
                },
                "annual_production_value": "150,000 kr"
            },
            "foundation_year": 1940,
            "corporation_year": 1943
        },
        "5": {
            "name": "AB. L. & P. Widengren",
            "location": "Vingåker",
            "business": "Konfektionsfabrik",
            "products": "Tillverkar herr- och gosskläder samt damdräkter.",
            "contact": {
                "phone": "Vingåker",
                "postgiro": "3741"
            },
            "financials": {
                "capital": "1,225,000 kr",
                "employees": {
                    "total": 468
                },
                "annual_production_value": "7,800,000 kr"
            },
            "foundation_year": 1877,
            "corporation_year": 1903,
            "board": [
                {
                    "name": "Henrik Widengren",
                    "role": "ordf."
                },
                {
                    "name": "Knut Strömberg",
                    "role": "adv."
                },
                {
                    "name": "Per Widengren",
                    "role": "dir."
                }
            ],
            "director": "Per Widengren",
            "sales_manager": "A. Grahn"
        },
        "6": {
            "name": "AB. Widsell & Co.",
            "location": "Norsholm",
            "business": "",
            "products": "Tillverkar speglar, spegel- och fotografiramar, ovala och runda ramar, tapet-och ramlister",
            "contact": {
                "phone": "96",
                "postgiro": "28336"
            },
            "financials": {
                "capital": "10,000 kr",
                "employees": {
                    "total": 9
                }
            },
            "foundation_year": 1926,
            "corporation_year": 1938,
            "director": "Börje Vilhelmson"
        },
        "7": {
            "name": "AB. Widtsköfle",
            "location": "Vittskövle",
            "business": "Tegelbruk och sågverk",
            "products": "Tillverkar kalksandstegel, sågade trävaror, takspån m. m. Firman driver även jordbruk, handelsträdgård samt skogshantering.",
            "financials": {
                "capital": "kr 0",
                "employees": {
                    "total": 0
                }
            }
        }
    }
}