{
    "original": "Danie Isson—D eg erfors\n\nAB* Danielssans Verkstäder, Ängby.\n\nPlåtslageri och mek. verkstad i Kårsta\n(Stockholms l.). Tillverkar brand-,\nkassa-välvs- och kylrumsdörrar, hissdörrar,\ngas-och splittersäkra dörrar, kassaskåp och\nhyllfack samt utför plåtslageri-,\nsvetsnings- och svarvningsarbeten.\n\nKontor: Bältarvägen 201; postadr.:\nÄhgby 3. Telefon: Stockholm 372444.\nPostgiro: 144830.\n\nAkt.-kap.: 10,000 kr. Antal\nindustriarb.: 24. Tillv.-värde pr år: 375,000 kr. —\nFirman etabl. 1927, bolag 1939.\n\nStyrelse o. verkst. dir.: Karl Theodor\nDanielsson.\n\nDisp.: Harald Danielsson.\n\n*AB. Dannemora Gruvor,\n\nBannemora.\n\nJärnmalmsgruvor i Dannemora\n(Uppsala l.). Bryter järnmalm. Bolaget driver\njämväl skogshantering och\nsågverksrörelse.\n\nTelegr.-adr.: Gruvkontoret, Dannemora.\nTelefon: 109. Postgiro: 135853. —\nAkt.-kap.: 3.000,000 kr. Antal industriarb.:\n150. Prod.-värde pr år: 1,500,000 kr. —\nBolaget bildat 1937.\n\nStyrelse: disp. Hj. Åselius (ordf.),\ndir. Nils Elfström, dir. Karl Rutberg,\ndir. Gunnar Sundblad.\n\nVerkst. dir.: E. Berggren.\n\nGruving.: Per Olov Holmstrand.\n\nKamrer: E. Breitholtz.\n\n* De Blindas Tekniska Fabrik, AB.\nTheo-Debas, Stockholm.\n\nKem. tekn. fabrik. Tillverkar\ntvätt-och rengöringsmedel såsom tvätt-,\ndisk-och skurpulver, tvål, bonvax,\nrengöringsmedel för golv, maskiner m. m.\nVarumärke: »Blifa».\n\nKontor: Virkesvägen 6. Telegr.-adr.:\nDeblifa, Stockholm. Telefon: 440280.\nPostgiro: 155667.\n\nAkt.-kap.: 100,000 kr. Antal\nindustriarb.: 20. — Firman etabl. 1937, nuv.\nbolag o. namn 1945.\n\nStyrelse: adv. Rolf Dillen (ordf.),\nherr Gunnar Alexanderson, sekr. Charles\nHedkvist, disp. Ernst Retsler, dir. Sven\nThörnstrand.\n\nVerkst. dir.: Sven Thörnstrand.\n\nAB. Defibrator, Stockholm.\n\nKonsulterande ingenjörsfirma för\nwall-board- och massaindustrierna.\nSpecialmaskiner enligt firmans konstruktioner\ntillverkas vid olika verkstäder.\n\nKontor: Kungsg. 32. Telegr.-adr.:\n\nDefibrator, Stockholm. Telefon: 235185.\n\n—\tAkt.-kap.: 600,000 kr. — Bolaget\ngrundat 1933.\n\nStyrelse: dir. Gunnar Magnuson\n(ordf.), ing. Arne Asplund, ing. Alvar\nBylund, civiling. Birger Dahlerus, jur.\nkand. Sven Widemar.\n\nVerkst. dir.: Gunnar Magnuson.\n\nV. verkst. dir.: Arne Asplund.\n\növering.: Alvar Bylund.\n\nKamrer: Erik Engström.\n\n(Jfr annons nr 12.)\n\n*De Förenade Kolsyrefabrikernas AB.,\n\nStockholm.\n\nKolsyrefabriker i Stockholm (Svenska\nKolsyrefabriken), Limhamn (Malmö) och\nGöteborg. Tillverkar kolsyra och\nkol-syreis (torris).\n\nKontor: Lövholmsbrinken 6,\nLiljeholmen, Postadr.: Stockholm 9. Telefon:\n452720. Telegr.-adr.: Kolsyre, Stockholm,\nGöteborg o. Malmö. Postgiro: 22207.\nAvd.-kontor: Limhamn o. Göteborg.\n\nAkt.-kap.: 1,011,960 kr. Antal\nindustriarb.: 44. Tillv.-värde pr år: 650,000 kr.\n\n—\tBolaget grundat 1900.\n\nStyrelse: dir. Max Nygren (ordf.),\napot. Hj. A:n Tesch (v. ordf.)&gt; disp. L.\nG. Loberg, civiling. Erik Olson, dir. T.\nM. Simonsson, dir. Walter Wehtje.\n\nVerkst. dir.: vakant.\n\nDisponenter: i Stockholm: N. Gäbel; i\nLimhamn: Thure Söderberg; i Göteborg:\nOve Aller.\n\nDe Ceersfors Bruk, Degeron.\n\nSe AB. Qvarnshammars Jernbruk,\nDegerön.\n\n*Degerfors Järnverks AB.,\n\nDeg erfors.\n\nJärnverk med elektr. masugn,\nsin-tringsverk, elektrostålverk, martinverk,\ngöt-, grov-, medium-, fin- och\ntrådvalsverk, grov- och tunnplåtvalsverk,\nkallvalsverk för rostfri plåt, anläggning för\ncen-terlesslipade axlar m. m.,\ntackjärnsgjute-rier, mekanisk verkstad, pressverk och\nsvetsningsverkstäder för pressade och\nsvetsade plåtarbeten, dissousgas- och\nsyr-gasfabrik m. m. samt elektr. kraftverk,\nsåg, skogs- och jordbruk m. m. vid\nDeger-fors samt kalkstensbrott vid Lannafors\n(båda i Örebro l.).\n\nTillverkar tackjärn, martin- och\nelek-trostålgöt, stångjärn, valstråd, grov- och\ntunnplåt även rostfri, pressade och\nsvetsade plåtarbeten, valsar m. m.;\nframställer dissousgas och syrgas samt driver\nkalkstensbrytning.",
    "structured": {
        "firms": [
            {
                "name": "Danie Isson—D eg erfors AB* Danielssans Verkstäder",
                "location": "Ängby",
                "business": "Plåtslageri och mek. verkstad i Kårsta (Stockholms l.)",
                "products": "Tillverkar brand-, kassa-välvs- och kylrumsdörrar, hissdörrar, gas-och splittersäkra dörrar, kassaskåp och hyllfack samt utför plåtslageri-, svetsnings- och svarvningsarbeten.",
                "contact": {
                    "office": "Bältarvägen 201",
                    "phone": [
                        "Stockholm 372444"
                    ],
                    "postgiro": "144830"
                },
                "financials": {
                    "capital": "10,000 kr",
                    "employees": {
                        "industriarb": 24
                    },
                    "annual_turnover": "375,000 kr",
                    "annual_production_value": "375,000 kr"
                },
                "foundation_year": 1927,
                "corporation_year": 1939,
                "board": [
                    {
                        "name": "Karl Theodor Danielsson",
                        "role": "verkst. dir."
                    }
                ],
                "director": "Harald Danielsson"
            },
            {
                "name": "AB. Dannemora Gruvor",
                "location": "Dannemora",
                "business": "Järnmalmsgruvor i Dannemora (Uppsala l.)",
                "products": "Bryter järnmalm. Bolaget driver jämväl skogshantering och sågverksrörelse.",
                "contact": {
                    "telegraph": "Gruvkontoret, Dannemora",
                    "phone": "109",
                    "postgiro": "135853"
                },
                "financials": {
                    "capital": "3,000,000 kr",
                    "employees": {
                        "industriarb": 150
                    },
                    "annual_production_value": "1,500,000 kr"
                },
                "corporation_year": 1937,
                "board": [
                    {
                        "name": "Hj. Åselius",
                        "role": "disp."
                    },
                    {
                        "name": "Nils Elfström",
                        "role": "dir."
                    },
                    {
                        "name": "Karl Rutberg",
                        "role": "dir."
                    },
                    {
                        "name": "Gunnar Sundblad",
                        "role": "dir."
                    }
                ],
                "director": "E. Berggren",
                "managing_director": "Per Olov Holmstrand",
                "manager": "E. Breitholtz"
            },
            {
                "name": "De Blindas Tekniska Fabrik, AB. Theo-Debas",
                "location": "Stockholm",
                "business": "Kem. tekn. fabrik",
                "products": "Tillverkar tvätt-och rengöringsmedel såsom tvätt-, disk-och skurpulver, tvål, bonvax, rengöringsmedel för golv, maskiner m. m.",
                "contact": {
                    "office": "Virkesvägen 6",
                    "telegraph": "Deblifa, Stockholm",
                    "phone": "440280",
                    "postgiro": "155667"
                },
                "financials": {
                    "capital": "100,000 kr",
                    "employees": {
                        "industriarb": 20
                    }
                },
                "foundation_year": 1937,
                "current_name_year": 1945,
                "board": [
                    {
                        "name": "Rolf Dillen",
                        "role": "adv."
                    },
                    {
                        "name": "Gunnar Alexanderson",
                        "role": "herr"
                    },
                    {
                        "name": "Charles Hedkvist",
                        "role": "sekr."
                    },
                    {
                        "name": "Ernst Retsler",
                        "role": "disp."
                    },
                    {
                        "name": "Sven Thörnstrand",
                        "role": "dir."
                    }
                ],
                "managing_director": "Sven Thörnstrand"
            },
            {
                "name": "AB. Defibrator",
                "location": "Stockholm",
                "business": "Konsulterande ingenjörsfirma för wall-board- och massaindustrierna. Specialmaskiner enligt firmans konstruktioner tillverkas vid olika verkstäder.",
                "contact": {
                    "office": "Kungsg. 32",
                    "telegraph": "Defibrator, Stockholm",
                    "phone": "235185"
                },
                "financials": {
                    "capital": "600,000 kr"
                },
                "corporation_year": 1933,
                "board": [
                    {
                        "name": "Gunnar Magnuson",
                        "role": "dir."
                    },
                    {
                        "name": "Arne Asplund",
                        "role": "ing."
                    },
                    {
                        "name": "Alvar Bylund",
                        "role": "ing."
                    },
                    {
                        "name": "Birger Dahlerus",
                        "role": "civiling."
                    },
                    {
                        "name": "Sven Widemar",
                        "role": "jur. kand."
                    }
                ],
                "director": "Gunnar Magnuson",
                "managing_director": "Arne Asplund"
            },
            {
                "name": "De Förenade Kolsyrefabrikernas AB.",
                "location": "Stockholm",
                "business": "Kolsyrefabriker i Stockholm (Svenska Kolsyrefabriken), Limhamn (Malmö) och Göteborg. Tillverkar kolsyra och kol-syreis (torris).",
                "contact": {
                    "office": "Lövholmsbrinken 6, Liljeholmen",
                    "phone": "452720",
                    "telegraph": "Kolsyre, Stockholm, Göteborg o. Malmö",
                    "postgiro": "22207",
                    "sales_offices": [
                        {
                            "location": "Limhamn",
                            "phone": "Thure Söderberg"
                        },
                        {
                            "location": "Göteborg",
                            "phone": "Ove Aller"
                        }
                    ]
                },
                "financials": {
                    "capital": "1,011,960 kr",
                    "employees": {
                        "industriarb": 44
                    },
                    "annual_production_value": "650,000 kr"
                },
                "corporation_year": 1900,
                "board": [
                    {
                        "name": "Max Nygren",
                        "role": "dir."
                    },
                    {
                        "name": "Hj. A:n Tesch",
                        "role": "apot."
                    },
                    {
                        "name": "L. G. Loberg",
                        "role": "disp."
                    },
                    {
                        "name": "Erik Olson",
                        "role": "civiling."
                    },
                    {
                        "name": "T. M. Simonsson",
                        "role": "dir."
                    },
                    {
                        "name": "Walter Wehtje",
                        "role": "dir."
                    }
                ]
            },
            {
                "name": "De Ceersfors Bruk",
                "location": "Degeron",
                "predecessor": "AB. Qvarnshammars Jernbruk, Degerön"
            },
            {
                "name": "Degerfors Järnverks AB.",
                "location": "Deg erfors",
                "business": "Järnverk med elektr. masugn"
            }
        ]
    }
}