{
    "original": "Eskilstuna\n\nExportchef: Edwin Willner.\n\nHuvudkamrer: Gustaf Modin.\n\nFörsäljn.-chef för Sverige: dir. S.\nForsberg.\n\nChef för materialavd.: Gunnar\nPettersson.\n\n’Eskilstuna Knivfabriks AB.,\n\nEskilstuna.\n\nSmidesverkstad och stålvarufabrik.\nTillverkar fickknivar och hopfällbara\nyrkesknivar samt maskinknivar för\ntobaksindustrien; utför förnickling och\nmetalletsning. Varumärke: EKA.\n\nTelefon: 30074 o. 30184. Postgiro:\n27775. — Akt.-kap.: 73,000 kr. Antal\nindustriarb.: 33. Tillv.-värde pr år: 220,000\nkr.\n\nFirman grundad 1882 under namn\nHadar Hallströms Kniffabriks AB., nuv.\nbolagsform 1917.\n\nStyrelse o. verkst. dir.: fru Betty\nElm-quist.\n\nVerkstadschef: civiling. Torbjörn\nEvrell.\n\n’Eskilstuna-Kurirens Tryckeri AB.,\n\nEskilstuna.\n\nTidningstryckeri. Utgiver tidningen\n» Eskilstuna-Kuriren».\n\nTelegr.-adr. o. telefon: Kuriren,\nEskilstuna. Postgiro: 27788.\n\nAkt.-kap.: 31,740 kr. Antal\nindustriarb.: 22. — Firman etabl. 1890, bolag\n1894, äger Arboga Boktryckeri AB.,\nArboga.\n\nStyrelse: chefred. Anton Selander\n(ordf.), stationsskrivare Albert Betts,\nskräddarmäst. Alfred Dufberg,\nkällar-mäst. Gottfrid Ekman, disp. Nils\nEriksson.\n\nEkonomichef : Stig Holm.\n\n’Eskilstuna Låsfabrik, Östmark &amp; Co.,\n\nEskilstuna.\n\nTillverkar patentlås (märke: »Elö»),\ndeuxbattantlås, lås för kylskåp och\ngrindar m. m. samt kassaskåpslås.\n\nTelefon: 31455. Postgiro: 33863. —\nAntal industriarb.: 40. — Firman etabl.\n1917.\n\nÄgare o. chefer: fabr. Carl östmark o.\nfabr. Eric östmark.\n\n’Eskilstuna Mesost- &amp;\nMargarinfabrik AB., Eskilstuna.\n\nTillverkar mesost och messmör.\nVarumärken: »Gyllen-ost», »Rut-ost»,\n»Gullans messmör» o. »Stintans messmör».\n\nBolagets margarin- och\nkokosfettill-verkning är utarrenderad.\nEnsamförsäljare: Margarinbolaget AB., Stockholm,\nVasag. 16, telefon: 230960.\n\nTeiegr.-adr.: Mesostfabriken,\nEskilstuna. Telefon: 30290. Postgiro: 10699. —\nAkt.-kap.: 100,000 kr. Antal industriarb.:\n33. — Firman etabl. 1887, bolag 1939.\n\nStyrelse: fru Kerstin Karlsson (ordf.),\ndisp. Gösta. Karnéus, disp. Ragnar\nKar-néus, ing. Tryggve Karnéus.\nVerkst. dir.: Gösta Karnéus.\nFörsäljn.-chef: Oscar Lind.\n\n’Eskilstuna Metall- och\nVagnslykt-fabrik AB., Eskilstuna.\n\nMetall varufabrik. Tillverkar\nköksinredningar såsom diskbänkar, hyllor nu m.\ni rostfritt stål samt kokkärl och övriga\nhusgeråd i aluminium, rostfritt och\n\nkoppar.\n\nTelegr.-adr.: Aluminium, Eskilstuna.\nTelefon: 31288. Postgiro: 10706. —\nAkt.-kap.: 90,000 kr. Antal industriarb.: 05.\nTillv.-värde pr år: 500,000 kr. — Firman\n\netabl. 1907, bolag 1943.\n\nStyrelse: dir. Sten Kjellberg, disp.\nBengt Malmberg, disp. Gunnar Ridseus.\nVerkst. dir.: Gunnar Ridseus.\n\n’Eskilstuna Metallindustri, Bröd.\nMalmgren &amp; Poréus, Eskilstuna.\n\nTillverkar nysilverartiklar såsom\nbrickor, brödkorgar, grädd- och kaffeserviser,\nkandelabrar och ljusstakar, fat m. m.,\ntennvaror samt elektr. kok- och\nvärme-apparater:\n\nTelefon: 31619. Postgiro: 26838. —\nAntal industriarb.: 40. — Firman etabl.\n1920.\n\nÄgare: fabr. Henning Malmgren, fabr.\nHugo Malmgren, fabr. Karl Poréus.\nDir.: Karl Poréus.\n\nVerkstadschefer: Henning Malmgren o.\nHugo Malmgren.\n\nEskilstunasteel, Torshälla.\n\nSmidesfabrik. Tillverkar putshyvlar av\njärn, hyveljärn, huggjärn,. skruv- och\nhuggmejslar, yrkesknivar såsom\nskoma-karknivar, tillskärarknivar,\ngummiknivar, läder- och linoleumknivar samt\nverktygsskaft, snickarklubbor m. m.\n\nTelegr.-adr.: Eskilstunasteel, Torshälla.\nTelefon: Eskilstuna 55316. Postgiro:\n97897. — Antal industriarb.: 40.\nTillv.-värde pr år: 375,000 kr. — Firman etabl.\n1936.\n\nÄgare o. chef: fabr. Gösta Pettersson.",
    "structured": {
        "1": {
            "name": "Eskilstuna Knivfabriks AB",
            "location": "Eskilstuna",
            "business": "Smidesverkstad och stålvarufabrik",
            "products": "Tillverkar fickknivar och hopfällbara yrkesknivar samt maskinknivar för tobaksindustrien; utför förnickling och metalletsning. Varumärke: EKA",
            "contact": {
                "office": "Telefon: 30074 o. 30184",
                "postgiro": "27775"
            },
            "financials": {
                "capital": "73,000 kr",
                "employees": {
                    "industriarb": 33
                },
                "annual_turnover": "220,000 kr",
                "annual_production_value": "220,000 kr"
            },
            "foundation_year": 1882
        },
        "2": {
            "name": "Eskilstuna-Kurirens Tryckeri AB",
            "location": "Eskilstuna",
            "business": "Tidningstryckeri",
            "contact": {
                "office": "Telefon: Kuriren, Eskilstuna",
                "postgiro": "27788"
            },
            "financials": {
                "capital": "31,740 kr",
                "employees": {
                    "industriarb": 22
                }
            },
            "foundation_year": 1890,
            "current_name_year": 1894
        },
        "3": {
            "name": "Eskilstuna Låsfabrik, Östmark & Co.",
            "location": "Eskilstuna",
            "business": "Tillverkar patentlås (märke: »Elö»), deuxbattantlås, lås för kylskåp och grindar m. m. samt kassaskåpslås",
            "contact": {
                "office": "Telefon: 31455",
                "postgiro": "33863"
            },
            "financials": {
                "employees": {
                    "industriarb": 40
                }
            },
            "foundation_year": 1917
        },
        "4": {
            "name": "Eskilstuna Mesost- & Margarinfabrik AB",
            "location": "Eskilstuna",
            "business": "Tillverkar mesost och messmör",
            "products": "Varumärken: »Gyllen-ost», »Rut-ost», »Gullans messmör» o. »Stintans messmör»",
            "contact": {
                "office": "Telefon: 30290",
                "postgiro": "10699"
            },
            "financials": {
                "capital": "100,000 kr",
                "employees": {
                    "industriarb": 33
                }
            },
            "foundation_year": 1887,
            "corporation_year": 1939
        },
        "5": {
            "name": "Eskilstuna Metall- och Vagnslyktfabrik AB",
            "location": "Eskilstuna",
            "business": "Metall varufabrik",
            "products": "Tillverkar köksinredningar såsom diskbänkar, hyllor nu m. i rostfritt stål samt kokkärl och övriga husgeråd i aluminium, rostfritt och koppar",
            "contact": {
                "office": "Telefon: 31288",
                "postgiro": "10706"
            },
            "financials": {
                "capital": "90,000 kr",
                "employees": {
                    "industriarb": 65
                },
                "annual_turnover": "500,000 kr"
            },
            "foundation_year": 1907,
            "corporation_year": 1943
        },
        "6": {
            "name": "Eskilstuna Metallindustri, Bröd. Malmgren & Poréus",
            "location": "Eskilstuna",
            "business": "Tillverkar nysilverartiklar såsom brickor, brödkorgar, grädd- och kaffeserviser, kandelabrar och ljusstakar, fat m. m., tennvaror samt elektr. kok- och värmeapparater",
            "contact": {
                "office": "Telefon: 31619",
                "postgiro": "26838"
            },
            "financials": {
                "employees": {
                    "industriarb": 40
                }
            },
            "foundation_year": 1920
        },
        "7": {
            "name": "Eskilstunasteel",
            "location": "Torshälla",
            "business": "Smidesfabrik",
            "products": "Tillverkar putshyvlar av järn, hyveljärn, huggjärn, skruv- och huggmejslar, yrkesknivar såsom skomakarknivar, tillskärarknivar, gummiknivar, läder- och linoleumknivar samt verktygsskaft, snickarklubbor m. m.",
            "contact": {
                "office": "Telefon: Eskilstuna 55316",
                "postgiro": "97897"
            },
            "financials": {
                "employees": {
                    "industriarb": 40
                },
                "annual_production_value": "375,000 kr"
            },
            "foundation_year": 1936
        }
    }
}