{
    "original": "Nordiska\n\nStyrelse: hovauditör Birger Barre,\nbokförläggare Tor Bonnier, dir. J. Farchy,\nciviling. Boris Hagelin, dir. Alfred Nobel,\nbankdir. Th. Raaschou.\n\nVerkst. dir.: J. Farchy.\n\n(Jfr annons nr 23.)\n\nAB. Nordiska Hattfabriken, Malmö.\n\nTillverkar barnhattar.\n\nKontor: ö. Promenaden 23. Telefon:\n75330 o. 24938. Postgiro: 37617. —\nAkt.-kap.: 40,000 kr. Antal industriarb.: 40.\n— Bolaget grundat 1928.\n\nVerkst. dir.: H. Tengblad.\n\n\"Nordiska Kappfabriken, Stockholm.\n\nSe Konfektions AB. Anér &amp; Nilsson,\nStockholm.\n\n\"AB. Nordiska Kartongfabriken,\n\nStockholm.\n\nSe Stockholms Kartong- &amp;\nLitografi ska AB., Stockholm.\n\n\"AB. Nordiska Kompaniet,\n\nStockholm.\n\nKonfektions- och tapetserareverkstäder,\ntextilkammare, tryckeri samt varuhus i\nStockholm, snickerifabrik, sågverk,\nmetallverkstad och tapetserareverkstad i\nNyköping.\n\nTillverkar herr- och damkonfektion,\nlinnekonfektion, damhattar, pälsvaror,\ninredningstextilier, möbler samt utför\ntapetserarearbeten, lokal- och\nbostadsinredningar i metall, trä och glas,\nbelysningsarmatur, byggnadsarmatur i metall\noch järn samt järnsängar. Driver som\nhuvudrörelse varuhus, engroshandel samt\ndetaljhandel med livsmedel.\n\nKontor: Hamng. 18 o. 20, postadr.:\nStockholm 7. Telegr.-adr.: Kompaniet,\nStockholm. Telefon: »N. K.». Postgiro:\n481.\n\nAkt.-kap.: 26,200,000 kr. Antal\nindustriarb.: 505. Tillv.-värde pr år: 9,000,000\nkr. — Bolaget grndat 1902.\n\nStyrelse: f. d. generalkonsul Josef\nSachs (ordf.), greve Folke Bernadotte\naf Wisborg, adv. Matts Fallenius, överint.\nHarald Lettström, f. d. bankdir. Mauritz\nPhilipson, hovmarskalk Nils Rudebeck,\ndir. Ragnar Sachs, civiling. Sten\nWesterberg, f. d. statssekr. Tage Wärn.\n\nVerkst. dir.: Ragnar Sachs.\n\nV. verkst. direktörer: Tom A.\nBjörklund och R. Kalderén.\n\nChef i Nyköping: disp. Lars Ericsson.\n\nBitr. dir.: Ragnar Torsslow.\n\n(Jfr annons nr 56.)\n\nNordiska Latexfabriken, Torekov.\n\nTillverkar dinappar, fingertutor,\ngummihandskar, gummiproppar och\npackningar vid gummivarufabrik i Torekov\n(Kristianst. l.). Varumärke: »Nolato».\n\nTelefon: 34. Postgiro: 145422. —\nAntal industriarb.: 30. Tillv.-värde pr år:\n400,000 kr. — Firman etabl. 1938.\n\nÄgare o. chefer: fabr. Sven Boström o»\nfabr. Bernh. Jorlén.\n\nNordiska Linnefabriken i Göteborg\n\nAB., Göteborg.\n\nTillverkar skjortor, pyjamas samt\nkragar. Varumärke: »NL».\n\nKontor: 3:dje Långg. 38—40.\nTelegr.-adr.: Nordlinne, Göteborg. Telefon;\n146411. Postgiro: 11551. — Akt.-kap.:\n5,000 kr. Tillv.-värde pr år: 450,000 kr.\n\nFirman, etabl. 1915, bolag 1924, är\ndotterbolag till AB. Linnefabriken\nMer-kur, Göteborg (se detta bolag).\n\nVerkst. dir.: disp. Folke Ellioth.\n\n\"AB. Nordiska Läderfabriken,\n\nSimrishamn.\n\nGarveri i Veberöd (Malmöh. l.).\nFramställer läder för handsk- och\nbeklädnads-ändamål, jackor, tröjor, västar, mössor\nsamt handskar och foderskinn.\nVarumärke: »Nordiska».\n\nHuvudkontor: Simrishamn. Telefon:\n»Ehrnbergsläder». Postgiro: 175571.\nAvd.-kontor: Veberöd. Telefon: 123.\nTelegr.-adr.: Nordskin, Simrishamn och Veberöd.\n\nAkt.-kap.: 300,000 kr. Antal\nindustriarb.: 20. Tillv.-värde pr år: 2,000,000 kr.\n— Bolaget grundat 1929.\n\nStyrelse: dir. Gösta Ehrnberg (ordf.)*\nbankdir. Alvar Ehrnberg, fröken A.-L.\nEhrnberg.\n\nVerkst. dir.: Gösta Ehrnberg.\n\n\"AB. Nordiska Margarinfabriken,\n\nStockholm.\n\nTillverkar margarin, cocosfett och\nmatolja. Varumärken: »Bryné», »Brynella&gt;\no. »Carina» för margarin samt\n»Gyllen-olja Huilor» för matolja.\n\nKontor: Sickla; postadr.: Stockholm 4.\nTelegr.-adr.: »Nordmargarin», Stockholm.\nTelefon: 440880. Postgiro: 56704. -\nAkt.-kap.: 20,000 kr. Arb.-antal: 25.— Bolaget\ngrundat 1933.\n\nStyrelse: dir. Malte Göransson (ordf.),\nfru K. Melin-Göransson,\n\nVerkst. dir.: M. Göransson.\n\nKamrer: Alvar Sundberg.\n\n*",
    "structured": {
        "1": {
            "name": "AB. Nordiska Hattfabriken",
            "location": "Malmö",
            "business": "Tillverkar barnhattar",
            "contact": {
                "office": "ö. Promenaden 23",
                "phone": [
                    "75330",
                    "24938"
                ],
                "postgiro": "37617"
            },
            "financials": {
                "capital": "40,000 kr",
                "employees": {
                    "industriarb": 40
                },
                "foundation_year": 1928
            }
        },
        "2": {
            "name": "AB. Nordiska Kompaniet",
            "location": "Stockholm",
            "business": "Konfektions- och tapetserareverkstäder, textilkammare, tryckeri samt varuhus i Stockholm, snickerifabrik, sågverk, metallverkstad och tapetserareverkstad i Nyköping.",
            "contact": {
                "office": "Hamng. 18 o. 20",
                "postgiro": "481"
            },
            "financials": {
                "capital": "26,200,000 kr",
                "employees": {
                    "industriarb": 505
                },
                "annual_production_value": "9,000,000 kr",
                "foundation_year": 1902
            }
        },
        "3": {
            "name": "Nordiska Latexfabriken",
            "location": "Torekov",
            "business": "Tillverkar dinappar, fingertutor, gummihandskar, gummiproppar och packningar.",
            "contact": {
                "phone": "34",
                "postgiro": "145422"
            },
            "financials": {
                "employees": {
                    "industriarb": 30
                },
                "annual_production_value": "400,000 kr",
                "foundation_year": 1938
            },
            "owners": [
                "fabr. Sven Boström",
                "fabr. Bernh. Jorlén"
            ]
        },
        "4": {
            "name": "Nordiska Linnefabriken i Göteborg AB.",
            "location": "Göteborg",
            "business": "Tillverkar skjortor, pyjamas samt kragar.",
            "contact": {
                "office": "3:dje Långg. 38—40",
                "phone": "146411",
                "postgiro": "11551"
            },
            "financials": {
                "capital": "5,000 kr",
                "annual_production_value": "450,000 kr",
                "foundation_year": 1915
            }
        },
        "5": {
            "name": "AB. Nordiska Läderfabriken",
            "location": "Simrishamn",
            "business": "Garveri i Veberöd. Framställer läder för handsk- och beklädnadsändamål, jackor, tröjor, västar, mössor samt handskar och foderskinn.",
            "contact": {
                "postgiro": "175571"
            },
            "financials": {
                "capital": "300,000 kr",
                "employees": {
                    "industriarb": 20
                },
                "annual_production_value": "2,000,000 kr",
                "foundation_year": 1929
            },
            "owners": [
                "dir. Gösta Ehrnberg",
                "bankdir. Alvar Ehrnberg",
                "fröken A.-L. Ehrnberg"
            ]
        },
        "6": {
            "name": "AB. Nordiska Margarinfabriken",
            "location": "Stockholm",
            "business": "Tillverkar margarin, cocosfett och matolja.",
            "contact": {
                "office": "Sickla",
                "postgiro": "56704"
            },
            "financials": {
                "capital": "20,000 kr",
                "employees": 25,
                "foundation_year": 1933
            },
            "owners": [
                "dir. Malte Göransson",
                "fru K. Melin-Göransson"
            ],
            "manager": "M. Göransson",
            "kamrer": "Alvar Sundberg"
        }
    }
}