{
    "original": "Dala—Da Ikarlsberg\n\n^Dala-Husby Snickerifabrik,\n\nDala-Husby.\n\nTillverkar byggnadssnickerier såsom\nfönster och dörrar, trappor samt\ninredningar vid fabrik i Dala-Husby\n(Kopparb. l.).\n\nTelefon: 80. Postgiro: 94713. — Antal\nindustriarb.: 15. — Firman etabl. 1923.\n\nÄgare o. chef: And. Ragnås.\n\n*\tDalarne, Cruvbolaget, Falun.\n\nSe Gruf AB. Dalarne, Falun.\n\n*\tDalarne, Trävarubolag, Vansbro.\n\nSe Trävaru AB. Dalarne, Vansbro.\n\n*AB. Dalarnes Karamellfabrik,\n\nRättvik.\n\nTillverkar konfekt, praliner,\nkarameller och pastiller samt saft och sylt vid\nfabrik i Rättvik (Kopparb. l.).\n\nTelegr.-adr.: Karamellbolaget, Rättvik.\nTelefon: 2 o. 104. Postgiro: 14770.\n\nAkt.-kap.: 74,550 kr. Antal\nindustriarb.: 30. Tillv.-värde pr år: 700,000 kr.\n\n—\tBolaget grundat 1905.\n\nStyrelse o. verkst. dir.: Karl Hallvares.\n\nAB. Dalasågen, Mora.\n\nSågverk, hyvleri och trähusfabrik i\nMora (Kopparb. l.). Tillverkar ^ sågade\noch hyvlade trävaror samt\nmonteringsfärdiga trähus.\n\nTelegr.-adr.: Dalasågen, Mora. Telefon:\n5 o. 419. Postgiro: 73707. Försälj, av\nträhus: AB. Svenska Trähus, Stockholm,\nBirger Jarlsg. 27, telefon: »Svenska\nTrähus». .\n\nAkt.-kap.: 400,000 kr.o Antal\nindustriarb.: 130. Årstillv. av sågade ö. hyvlade\nträvaror: 5,000 stds: — Bolaget grundat\n1929.\n\nStyrelse: dir. K.-I. Hising (ordf.),\ndisp. Augr. E. Andersson, disp.-assistent\nRolf. v. Heidenstam, prof. Oskar\nLindberg, disp. Axel Wiklund.\n\nVerkst. dir.: Aug. E. Andersson.\n\nSågverksförvalt.: S. Schäder.\n\nAB. Dalby Siporexfabrik, Dalby.\n\nTillverkar armerad och oarmerad sipo-\n\nrex (lättbetong) i block, plattor och\nbalkar vid fabrik i Dalby (Malmöh. l.).\n\nTelefon: Dalby 5 o. Lund 11805.\nPostgiro: 99468.\n\nAkt.-kap.: 1,020.000 kr. Antal\nindustriarb.: 88. Tillv.-värde pr år: 3,000,000 kr.\n\n—\tBolaget grundat 1935.\n\nStyrelse o: disp.: ing. H. Linse.\n\nDalby Stenkross AB., Dalby.\n\nGranitbrott och stenkrossanläggningar\ni Dalby (Malmöh. l.). Tillverkar\nmakadam för väglagnings- och\nbyggnadsändamål.\n\nHuvudkontor: Dalby. Telefon: Dalby\n5 o. Lund 11805. Postgiro: 15129.\nEnsamförsäljare för södra Skåne: Oalciuin,\nSvenska Kalkförsäljnings AB., Malmö.\n\nAkt.-kap.: 1,020,000 kr. Antal\nindustriarb.: 66. Tillv.-värde pr år: 600,000 kr.\n— Bolaget grundat 1914.\n\nStyrelse: dir. Ernst Wehtje (ordf.),\ning. H. Linse, dir. Fredrik Wehtje,\nryttm. Hugo Wehtje, dir. Walter Wehtje.\n\nDisp.: H. Linse.\n\n*Dalelfvarnes Flottningsförenlng,\n\nOr sa.\n\nBedriver flottning av virke i\nDalälvarna.\n\nTelegr.-adr.: Flottning, Orsa. Telefon:\n1. Postgiro: 95295. — Föreningen bildad\n1865.\n\nStyrelse: skogschef Carl Eric Barth\n(ordf.), skogschef Carl Gustaf Sundberg\n(v. ordf.), disp. Aug. Andersson,\növer-jägm. i Gävle-Dala distrikt Erik W.\nHöjer (allmänt ombud); flottningschef\nO. Dan. Olsson.\n\nFlottningschef: O. Dan. Olsson.\n\nChefsassistent: Gösta Hellstrand.\n\nKontorschef: kamrer Gylfe Keyser,\n\nDistriktschefer: i Malung: insp.\nGunnar Lundin; i Vansbro: insp. B.\nPåls-son; i Särna: insp. Per Oskar Söderlund;\ni Orsa: ing. Filip Hörberg; i Mora: ing.\nMartin Lidwall; i Torsång: insp. Tore\nEstberg; i Gysinge: insp., Sam.\nSöderlund.\n\n*AB. Dalhems Väfveri, Borås.\n\nTillverkar kulörta konstsilke- och\nbomullsvävnader.\n\nTelegr.-adr.: Dalhem, Borås. Telefon:\n10022. — Akt.-kap.: 500,000 kr. Antal\nindustriarb.: 105. Tillv.-värde pr år:\n2,500,000 kr. — Firman etabl. 1896,\nbolag 1913.\n\nStyrelse: läroverksadj. K. Elf män, dir.\nClas Erikson, disp. Ivar H. Nilsson,\növerstelöjtnanten frih. Nils S. Åkerhielm.\n\nDisp.: Ivar H. Nilsson.\n\n*Dalkarlsbergs AB., Striberg.\nSe Stribergs Grufve AB., Striberg.",
    "structured": {
        "1": {
            "name": "Dala-Husby Snickerifabrik",
            "location": "Dala-Husby",
            "business": "Tillverkar byggnadssnickerier såsom fönster och dörrar, trappor samt inredningar vid fabrik i Dala-Husby (Kopparb. l.)",
            "contact": {
                "office": "Dala-Husby",
                "phone": [
                    "80"
                ],
                "postgiro": "94713",
                "telegraph": null
            },
            "financials": {
                "capital": null,
                "employees": {
                    "industriarb": 15
                },
                "annual_turnover": null,
                "annual_production_value": null
            },
            "foundation_year": 1923,
            "owners": [
                "And. Ragnås"
            ],
            "director": null
        },
        "2": {
            "name": "Dalarnes Karamellfabrik",
            "location": "Rättvik",
            "business": "Tillverkar konfekt, praliner, karameller och pastiller samt saft och sylt vid fabrik i Rättvik (Kopparb. l.)",
            "contact": {
                "office": "Rättvik",
                "phone": [
                    "2",
                    "104"
                ],
                "postgiro": "14770",
                "telegraph": "Karamellbolaget, Rättvik"
            },
            "financials": {
                "capital": "74,550 kr",
                "employees": {
                    "industriarb": 30
                },
                "annual_turnover": "700,000 kr",
                "annual_production_value": "3,000,000 kr"
            },
            "foundation_year": 1905,
            "owners": [
                "Karl Hallvares"
            ],
            "director": "Karl Hallvares"
        },
        "3": {
            "name": "AB. Dalasågen",
            "location": "Mora",
            "business": "Sågverk, hyvleri och trähusfabrik i Mora (Kopparb. l.). Tillverkar sågade och hyvlade trävaror samt monteringsfärdiga trähus.",
            "contact": {
                "office": "Mora",
                "phone": [
                    "5",
                    "419"
                ],
                "postgiro": "73707",
                "telegraph": "Dalasågen, Mora",
                "sales_offices": [
                    {
                        "location": "Stockholm, Birger Jarlsg. 27",
                        "phone": "»Svenska Trähus»"
                    }
                ]
            },
            "financials": {
                "capital": "400,000 kr",
                "employees": {
                    "industriarb": 130
                },
                "annual_turnover": null,
                "annual_production_value": null
            },
            "foundation_year": 1929,
            "owners": null,
            "director": null
        },
        "4": {
            "name": "AB. Dalby Siporexfabrik",
            "location": "Dalby",
            "business": "Tillverkar armerad och oarmerad siporex (lättbetong) i block, plattor och balkar vid fabrik i Dalby (Malmöh. l.)",
            "contact": {
                "office": "Dalby",
                "phone": [
                    "Dalby 5",
                    "Lund 11805"
                ],
                "postgiro": "99468",
                "telegraph": null
            },
            "financials": {
                "capital": "1,020,000 kr",
                "employees": {
                    "industriarb": 88
                },
                "annual_turnover": "3,000,000 kr",
                "annual_production_value": null
            },
            "foundation_year": 1935,
            "owners": [
                "ing. H. Linse"
            ],
            "director": null
        },
        "5": {
            "name": "Dalby Stenkross AB.",
            "location": "Dalby",
            "business": "Granitbrott och stenkrossanläggningar i Dalby (Malmöh. l.). Tillverkar makadam för väglagnings- och byggnadsändamål.",
            "contact": {
                "office": "Dalby",
                "phone": [
                    "Dalby 5",
                    "Lund 11805"
                ],
                "postgiro": "15129",
                "telegraph": null
            },
            "financials": {
                "capital": "1,020,000 kr",
                "employees": {
                    "industriarb": 66
                },
                "annual_turnover": "600,000 kr",
                "annual_production_value": null
            },
            "foundation_year": 1914,
            "owners": [
                "dir. Ernst Wehtje",
                "ing. H. Linse",
                "dir. Fredrik Wehtje",
                "ryttm. Hugo Wehtje",
                "dir. Walter Wehtje"
            ],
            "director": null
        },
        "6": {
            "name": "AB. Dalhems Väfveri",
            "location": "Borås",
            "business": "Tillverkar kulörta konstsilke- och bomullsvävnader.",
            "contact": {
                "office": "Borås",
                "phone": [
                    "10022"
                ],
                "postgiro": null,
                "telegraph": "Dalhem, Borås"
            },
            "financials": {
                "capital": "500,000 kr",
                "employees": {
                    "industriarb": 105
                },
                "annual_turnover": "2,500,000 kr",
                "annual_production_value": null
            },
            "foundation_year": 1913,
            "owners": [
                "lär. K. Elfman",
                "dir. Clas Erikson",
                "disp. Ivar H. Nilsson",
                "överstelöjtnanten frih. Nils S. Åkerhielm"
            ],
            "director": null
        }
    }
}