{
    "original": "Olsson—O rig overken\n\nKontor: Hälsingborg. Telegr.-adr.:\nOlssons, Hälsingborg. Telefon: 20750.\nPostgiro: 29013.\n\nAkt.-kap.: 4,256,000 kr. Antal\nindustriarb.: Sennan 35, R,ögle 25. Årstillv. av\ntegelvaror: 6 milj. st. — Firman etabl.\n1853, bolag 1911.\n\nStyrelse: dir. Hjalmar Olsson (ordf.),\nryttm. Ulf Olsson, disp. C. G. Schultz,\ndir. Edvin Åberg, generaldir. David\nöstrand.\n\nVerkst. dir.: Edvin Åberg.\n\nDisp.: E. Ljunggren.\n\nP. d. Olssons Sängfabrik, Storvik.\n\nSnickerifabrik i Storvik, sågverk i\nÅs-hammar (båda i Gävleb. l.) samt sågverk\ni Lumsheden (Kopparb. l.). Tillverkar\nresårsängar, babysängar, schäslonger,\nstålresår- och övermadrasser, möbelresårer,\nplymåkärnor, bilsitsstommar,\nträdgårds-möbler samt sågade och hyvlade trävaror.\n\nTelefon: 10 o. 470. Postgiro: 6919. —\nAntal industriarb.: 45. — Firman etabl.\n1905.\n\nÄgare: fabr. Erik Olsson o. fröken\nHildur Olsson.\n\nFabrikschef: Erik Olsson.\n\nKontorschef: Alfred Jonsson.\n\n*S. &amp; H. Olssons Snickeribolag,\n\nMalmö.\n\nTillverkar skolmöbler samt inredningar\nför butiker, skolor och samlingslokaler.\n\nKontor: Kamrerg. 17. Telefon: 21395.\nPostgiro: 147888. — Arb.-antal: 8. —\nFirman etabl. 1894.\n\nÄgare: P. Olssons sterbhus.\n\nChef: fabr. Sam. Olsson.\n\n*Oppboga AB., Fellingsbro.\n\nPapp- och kartongfabrik med träsliperi\ni Fellingsbro (Örebro l.). Tillverkar papp\noch kartong samt mek. trämassa för eget\nbehov.\n\nTelegr.-adr.: Oppboga, Fellingsbro.\nTelefon: Fellingsbro 1, 100 o. 101.\nPostgiro: 163943. Representanter: i\nStockholm: AB. Svanströms Pappersagentur,\nStadsgården 14 o. 16, telefon: 440035; i\nGöteborg: Nordström &amp; Tinggren, S.\nLarmg. 4, telefon: »Nordström &amp;\nTinggren»; i Malmö: Nordström &amp; Tinggrens\nFilial AB., Skeppsbron 5, telefon: 71845.\n\nAgenter i utlandet: England: R. L.\nLundgren Ltd, 29, New Bridge Street,\nLondon E O 4; Holland: G. H.\nBiihr-mann’s Papiergroothandel N. V., Postbus\n749, Amsterdam C; Belgien: Marcel\nKamps, 45, Rue Marianne, Bruxelles ;\n\nDanmark: Bristol Papir Co., Niels Juels\nGade 9, Köbenhavn K.\n\nAkt.-kap.: 2,000,000 kr. Antal\nindustriarb.: 100. Årstillv.: 8,000 ton papp och\nkartong. — Bolaget grundat 1901.\n\nStyrelse: bankdir. Rich. Julin (ordf.),\ndisp. Hans Hulthén, kapten Carol\nWal-lenberg, disp. Jakob Winström.\n\nDisp.: J. Winström.\n\nKontorschef: Sven Axelson.\n\n*AB. Optimiis, Upplands Väsby.\n\nMek. verkstad och metallvarufabrik i\nUpplands Väsby (Sthlms l.).\n\nTillverkar fotogenkök, lödlampor,\nfoto-genvärmeapparater,# radiatorer,\nbelysningslampor, campingkök,\noljesmÖrjkan-nor, cykellås, hänglås m. m.\n\nTelegr.-adr.: Optimus, Stockholm.\nTelefon: »Optimus», Upplands Väsby.\nPostgiro: 5041.\n\nAkt.-kap.: 3,000,000 kr. Antal\nindustriarb.: 300. Tillv.-värde pr år: 5,000,000 kr.\n— Bolaget grundat 1899.\n\nStyrelse: bankdir. Th. Raaschou (ordf.),\ndir. O. R. Bildt, dir. Axel Elfström,\nbruksdisp. Wiking J ohnsson, civiling.\nCarl S:son Schmidt.\n\nVerkst. dir.: Axel Elf ström.\n\nVerkstadschef: Evert Sköld.\n\n*AB. Original-Odhner, Göteborg.\n\nSpecialfabrik för tillverkning av\nräkne-och additionsmaskiner.\n\nHuvudkontor: Gamlestadsvägen^\npostadr.: Göteborg 1. Telegr.-adr.:\nOriginal-odhner, Göteborg. Telefon: 192510.\nPostgiro: 25501. Försäljn.-kontor: Göteborg,\nDrottningg. 35, telefon: 111211;\nStockholm, Kungsg. 31—33, telefon: 109084 o.\n109311.\n\nAkt.-kap.: 2,000,000 kr. Antal\nindustriarb.; 600. — Bolaget, grundat 1918,\nombildat 1923, äges av AB. Åtvidabergs\nIndustrier.\n\nStyrelse: dir. Axel Adler (ordf.), dir.\nR. Dencker, övering. Albert Engvall,\ndisp. Elof Ericsson, dir. Gustaf Larson.\n\nPlatschef: dir. Sixten Carle.\n\nBitr. platschef: dir. Z. Guthe.\n\nKonstruktionschef: ing. Einar\nUddgren.\n\nVerkstadschef: ing. Gunnar Larsson.\n\nFörsäljn.-ledare vid försäljn.-kontoret\ni Stockholm: T. Folkeson.\n\nOrigoverken, Bröderna Johanson,\n\nHalmstad.\n\nSvetsnings- och mek. verkstad.\nTillverkar hydrauliska domkrafter,\ncykeldetaljer, svarvade, pressade och svetsade\nmassartiklar samt sportartiklar.",
    "structured": {
        "1": {
            "name": "Olsson—Origoverken",
            "location": "Hälsingborg",
            "contact": {
                "office": "Olssons, Hälsingborg",
                "phone": [
                    "20750"
                ],
                "postgiro": "29013"
            },
            "financials": {
                "capital": "4,256,000 kr",
                "employees": {
                    "Sennan": 35,
                    "Rögle": 25
                },
                "annual_turnover": "N/A",
                "annual_production_value": "6 milj. st"
            },
            "foundation_year": 1853,
            "corporation_year": 1911,
            "board": [
                {
                    "name": "Hjalmar Olsson",
                    "role": "ordf."
                },
                {
                    "name": "Ulf Olsson",
                    "role": "ryttm."
                },
                {
                    "name": "C. G. Schultz",
                    "role": "disp."
                },
                {
                    "name": "Edvin Åberg",
                    "role": "dir."
                },
                {
                    "name": "David Östrand",
                    "role": "generaldir."
                }
            ],
            "owners": [
                "fabr. Erik Olsson",
                "fröken Hildur Olsson"
            ],
            "director": "N/A",
            "managing_director": "Edvin Åberg",
            "sales_manager": "N/A",
            "manager": "N/A"
        },
        "2": {
            "name": "Olssons Sängfabrik, Storvik",
            "location": "Storvik",
            "contact": {
                "office": "N/A",
                "phone": [
                    "10",
                    "470"
                ],
                "postgiro": "6919"
            },
            "financials": {
                "capital": "N/A",
                "employees": 45,
                "annual_turnover": "N/A",
                "annual_production_value": "N/A"
            },
            "foundation_year": 1905,
            "board": [],
            "owners": [
                "fabr. Erik Olsson",
                "fröken Hildur Olsson"
            ],
            "director": "Erik Olsson",
            "managing_director": "N/A",
            "sales_manager": "N/A",
            "manager": "Alfred Jonsson"
        },
        "3": {
            "name": "S. & H. Olssons Snickeribolag, Malmö",
            "location": "Malmö",
            "contact": {
                "office": "Kamrerg. 17",
                "phone": [
                    "21395"
                ],
                "postgiro": "147888"
            },
            "financials": {
                "capital": "N/A",
                "employees": 8,
                "annual_turnover": "N/A",
                "annual_production_value": "N/A"
            },
            "foundation_year": 1894,
            "board": [],
            "owners": [
                "P. Olssons sterbhus"
            ],
            "director": "N/A",
            "managing_director": "fabr. Sam. Olsson",
            "sales_manager": "N/A",
            "manager": "N/A"
        },
        "4": {
            "name": "Oppboga AB., Fellingsbro",
            "location": "Fellingsbro",
            "contact": {
                "office": "Oppboga, Fellingsbro",
                "phone": [
                    "Fellingsbro 1",
                    "100",
                    "101"
                ],
                "postgiro": "163943"
            },
            "financials": {
                "capital": "2,000,000 kr",
                "employees": 100,
                "annual_turnover": "N/A",
                "annual_production_value": "8,000 ton papp och kartong"
            },
            "foundation_year": 1901,
            "board": [
                {
                    "name": "Rich. Julin",
                    "role": "bankdir. (ordf.)"
                },
                {
                    "name": "Hans Hulthén",
                    "role": "disp."
                },
                {
                    "name": "Carol Wallenberg",
                    "role": "kapten"
                },
                {
                    "name": "Jakob Winström",
                    "role": "disp."
                }
            ],
            "owners": [],
            "director": "N/A",
            "managing_director": "N/A",
            "sales_manager": "N/A",
            "manager": "Sven Axelson"
        },
        "5": {
            "name": "AB. Optimiis, Upplands Väsby",
            "location": "Upplands Väsby",
            "contact": {
                "office": "Optimus, Stockholm",
                "phone": [
                    "Optimus",
                    "Upplands Väsby"
                ],
                "postgiro": "5041"
            },
            "financials": {
                "capital": "3,000,000 kr",
                "employees": 300,
                "annual_turnover": "N/A",
                "annual_production_value": "5,000,000 kr"
            },
            "foundation_year": 1899,
            "board": [
                {
                    "name": "Th. Raaschou",
                    "role": "bankdir. (ordf.)"
                },
                {
                    "name": "O. R. Bildt",
                    "role": "dir."
                },
                {
                    "name": "Axel Elfström",
                    "role": "dir."
                },
                {
                    "name": "Wiking Johnsson",
                    "role": "bruksdisp."
                },
                {
                    "name": "Carl S:son Schmidt",
                    "role": "civiling."
                }
            ],
            "owners": [],
            "director": "N/A",
            "managing_director": "Axel Elfström",
            "sales_manager": "N/A",
            "manager": "N/A"
        },
        "6": {
            "name": "AB. Original-Odhner, Göteborg",
            "location": "Göteborg",
            "contact": {
                "office": "Original-Odhner, Göteborg",
                "phone": [
                    "192510"
                ],
                "postgiro": "25501"
            },
            "financials": {
                "capital": "2,000,000 kr",
                "employees": 600,
                "annual_turnover": "N/A",
                "annual_production_value": "N/A"
            },
            "foundation_year": 1918,
            "board": [
                {
                    "name": "Axel Adler",
                    "role": "dir. (ordf.)"
                },
                {
                    "name": "R. Dencker",
                    "role": "dir."
                },
                {
                    "name": "Albert Engvall",
                    "role": "övering."
                },
                {
                    "name": "Elof Ericsson",
                    "role": "disp."
                },
                {
                    "name": "Gustaf Larson",
                    "role": "dir."
                }
            ],
            "owners": [],
            "director": "N/A",
            "managing_director": "N/A",
            "sales_manager": "N/A",
            "manager": "N/A"
        },
        "7": {
            "name": "Origoverken, Bröderna Johanson, Halmstad",
            "location": "Halmstad",
            "contact": {
                "office": "N/A",
                "phone": [
                    "N/A"
                ],
                "postgiro": "N/A"
            },
            "financials": {
                "capital": "N/A",
                "employees": "N/A",
                "annual_turnover": "N/A",
                "annual_production_value": "N/A"
            },
            "foundation_year": "N/A",
            "board": [],
            "owners": [],
            "director": "N/A",
            "managing_director": "N/A",
            "sales_manager": "N/A",
            "manager": "N/A"
        }
    }
}