{
    "original": "Sverige\n\n45. Tillv.-värde pr år: 500,000 kr. —\nFirman etabl. 1892, bolag 1920.\n\nStyrelse o. verkst. direktörer: ing. Ph.\nRudd o. fru M. Svensson.\n\nAB. Sveriges Förenade Filfabriker,\n\nTraryd.\n\nTillverkar filar och raspar samt utför\nomhuggning av filar vid fabrik i Traryd\n(Kronob. l.). Varumärke: »SFF».\n\nTelegr.-adr.: Filfabrikerna, Traryd.\nTelefon: 20. Postgiro: 37590.\nAvd.-kontor: Stockholm, Kungsg. 84; telefon:\n533712.\n\nAkt.-kap.: 251,600 kr. Antal\nindustriarb.: 55. — Fabriken anlagd 1877, nuv.\nbolag grundat 1919.\n\nStyrelse: civiling. Olof Winkler (ordf.),\navd.-chef Karl Bouvin, disp. Wictor\nNiwén.\n\nDisp.: Wictor Niwén.\n\nAB. Sveriges Förenade\nHattfabriker, Malmö.\n\nBolaget utgör holding company för\nfabriksföretaget AB. Malmö\nStråhatt-fabrik i Malmö.\n\nKontor: Malmö, Baltzarsg. 41.\nTelegr.-adr.: Hattfabrikerna, Malmö. Telefon:\n71260. — Akt.-kap.: 200,000 kr. —\nBolaget grundat 1924.\n\nStyrelse: bankdir. Ivar Åkerman (ordf.),\ndir. Carl Hanström, o dir.-assist. Carl\nMalmberg, disp. C.-E. Åkerman.\n\nVerkst. dir.: Carl Hanström.\n\nKamrer: Klas Ringius.\n\n*AB. Sveriges Förenade\nKonservfabriker, Göteborg.\n\nTillverkar konserver av fisk, grönsaker,\nfrukt och kött samt såser vid fabriker\ni Göteborg, Lysekil, Strömstad,\nGrebbe-stad, Gullholmen, Hamburgsund\n(samtliga i Göteb. o. Bohus l.) och\nKristianstad.\n\n# Varunamn: »Fyrtornet»,\n»Fyrmästare-sill», »Grebbestads hummeransjovis»,\n»Kungssardiner», »Kungssill»,\n»Molin-ders», »Måsen», »Radhes\nhushållsansjovis», »Stjärnfiléer», »Vikend-Sill» m. fl.\n\nHuvudkontor: Göteborg, St. Nyg. 17.\nTelegr.-adr. o. telefon: Fyrtornet,\nGöteborg. Postgiro: 40347. Avd.-kontor:\nStockholm, David Bagaresg. 9—11,\ntelefon: 201442—43.\n\nAkt.-kap.: 3,000,000 kr. Antal\nindustriarb.: 600.\n\nBolaget, grundat 1898, har i sig\nupptagit AB.- Molinderska Konservfabriken,\nStockholm.\n\nStyrelse: prof. Åke Hassler (ordf.),\ndir. Sven Colliander, dir. Sven Engdahl,\ndisp. Franz Hartmann, dir. L.\nHill-Lindquist, dir. Ernfrid Samuelson.\n\nVerkst. dir.: Ernfrid Samuelson.\n\nFörsäljn.-chef : Knut S. Larson.\n\nInköpschef: L. Magnusson.\n\n’Sveriges Förenade Linnefabrikers\n\nAB., Alingsås.\n\nTillverkar vita och kulörta skjortor,\nstärkskjortor, herrkragar, pyjamas,\nblusar, klänningar m. m.\n\nHuvudkontor: Alingsås. Telegr.-adr.:\nLinne, Alingsås. Telefon: »SFL».\nPostgiro: 12012. Avd.-kontor: Stockholm,\nVasag. 26, telefon: 113315; Göteborg,\nLinnéplatsen 4, telefon: 118537.\n\nAkt.-kap.: 430,000 kr. Antal\nindustriarb.: 300. Tillv.-värde pr år: 3,000,000 kr.\n\nBolaget grundat 1919 genom\nsammanslagning av f. d. Linnefabr. Rich. Jonson\nAB., Julius Berteisen &amp; Co. Skjortfabrik\noch AB. Kinna Skjortfabrik.\n\nStyrelse: dir. Clas Erikson (ordf.),\nryttm. H. L. v. Bornstedt, dir. Hj. Grahl,\nbankdir. Bertil Odelfelt.\n\nVerkst. dir.: Hj. Grahl.\n\nKontorschef: A. Ennerdal.\n\n*AB. Sveriges Förenade\nTrikå-fabriker, Borås.\n\n^ Trikåfabriker med spinnerier och\nfärgerier. Tillverkar trikåvaror dels vid tio\nfabriker i Borås, dels vid fabriker i Malmö,\nMölndal, Fritsla, Strömsfors, Uddebo och\nVegby (sistnämnda fyra i Älvsb. l.).\nVarumärke: »Eiser».\n\nHuvudkontor: Borås. Telegr.-adr. o.\ntelefon: Eiser, Borås. Postgiro: 9350.\nRepresentant i Stockholm: Walther\nVet-terleins Söner, Centralpalatset; telefon:\n102686.\n\nAkt.-kap.: 10,100,000 kr. Antal\nindustriarb.: 2,500. Tillv.-värde pr år:\n34,000,000 kr. — Bolaget grundat 1913.\n\nStyrelse: dir. Carl Eiserman (ordf.),\nciviling. N. W. Hörstadius (v. ordf.),\ndir. S. Bergengren, dir. Petrus\nSkoglund, bankdir. Helmer Stén, grossh. S.\nVetterlein.\n\nVerkst. dir.: Carl Eiserman.\n\nKamrer: Sten Theorin.\n\nSveriges Hampodlareförening,\n\nu. p. a., Katrineholm.\n\nHampberedningsverk vid Värmbol,\nKatrineholm. Tillverkar tåga och blånor av\nhampa samt linblånor.",
    "structured": {
        "1": {
            "name": "AB. Sveriges Förenade Filfabriker",
            "location": "Traryd",
            "business": "Tillverkar filar och raspar samt utför omhuggning av filar vid fabrik i Traryd (Kronob. l.)",
            "products": "Varumärke: »SFF».",
            "contact": {
                "office": "avd.-kontor: Stockholm, Kungsg. 84",
                "phone": [
                    "533712"
                ],
                "postgiro": "37590",
                "telegraph": "Filfabrikerna, Traryd"
            },
            "financials": {
                "capital": "251,600 kr",
                "employees": {
                    "total": 55
                }
            },
            "foundation_year": 1892,
            "corporation_year": 1920,
            "board": [
                {
                    "name": "ing. Ph. Rudd",
                    "role": "Verkställande direktör"
                },
                {
                    "name": "fru M. Svensson",
                    "role": "Styrelsemedlem"
                }
            ]
        },
        "2": {
            "name": "AB. Sveriges Förenade Hattfabriker",
            "location": "Malmö",
            "business": "Bolaget utgör holding company för fabriksföretaget AB. Malmö Stråhatt-fabrik i Malmö",
            "contact": {
                "office": "Kontor: Malmö, Baltzarsg. 41",
                "phone": [
                    "71260"
                ],
                "telegraph": "Hattfabrikerna, Malmö"
            },
            "financials": {
                "capital": "200,000 kr"
            },
            "foundation_year": 1924,
            "board": [
                {
                    "name": "bankdir. Ivar Åkerman",
                    "role": "Styrelsens ordförande"
                },
                {
                    "name": "dir. Carl Hanström",
                    "role": "Verkställande direktör"
                },
                {
                    "name": "dir.-assist. Carl Malmberg",
                    "role": "Styrelsemedlem"
                },
                {
                    "name": "disp. C.-E. Åkerman",
                    "role": "Styrelsemedlem"
                }
            ]
        },
        "3": {
            "name": "AB. Sveriges Förenade Konservfabriker",
            "location": "Göteborg",
            "business": "Tillverkar konserver av fisk, grönsaker, frukt och kött samt såser vid fabriker i Göteborg, Lysekil, Strömstad, Grebbestad, Gullholmen, Hamburgsund och Kristianstad",
            "products": "Varunamn: »Fyrtornet», »Fyrmästare-sill», »Grebbestads hummeransjovis», »Kungssardiner», »Kungssill», »Molinders», »Måsen», »Radhes hushållsansjovis», »Stjärnfiléer», »Vikend-Sill» m. fl.",
            "contact": {
                "office": "Huvudkontor: Göteborg, St. Nyg. 17",
                "phone": [
                    "201442",
                    "201443"
                ],
                "telegraph": "Fyrtornet, Göteborg",
                "postgiro": "40347"
            },
            "financials": {
                "capital": "3,000,000 kr",
                "employees": {
                    "total": 600
                }
            },
            "foundation_year": 1898,
            "board": [
                {
                    "name": "prof. Åke Hassler",
                    "role": "Styrelsens ordförande"
                },
                {
                    "name": "dir. Sven Colliander",
                    "role": "Styrelsemedlem"
                },
                {
                    "name": "dir. Sven Engdahl",
                    "role": "Styrelsemedlem"
                },
                {
                    "name": "disp. Franz Hartmann",
                    "role": "Styrelsemedlem"
                },
                {
                    "name": "dir. L. Hill-Lindquist",
                    "role": "Styrelsemedlem"
                }
            ]
        },
        "4": {
            "name": "Sveriges Förenade Linnefabrikers AB.",
            "location": "Alingsås",
            "business": "Tillverkar vita och kulörta skjortor, stärkskjortor, herrkragar, pyjamas, blusar, klänningar m. m.",
            "contact": {
                "office": "Huvudkontor: Alingsås",
                "phone": [
                    "113315"
                ],
                "telegraph": "Linne, Alingsås",
                "postgiro": "12012"
            },
            "financials": {
                "capital": "430,000 kr",
                "employees": {
                    "total": 300
                },
                "annual_turnover": "3,000,000 kr"
            },
            "foundation_year": 1919,
            "board": [
                {
                    "name": "dir. Clas Erikson",
                    "role": "Styrelsens ordförande"
                },
                {
                    "name": "ryttm. H. L. v. Bornstedt",
                    "role": "Styrelsemedlem"
                },
                {
                    "name": "dir. Hj. Grahl",
                    "role": "Styrelsemedlem"
                },
                {
                    "name": "bankdir. Bertil Odelfelt",
                    "role": "Styrelsemedlem"
                }
            ],
            "manager": "Verkställande direktör: Hj. Grahl"
        },
        "5": {
            "name": "AB. Sveriges Förenade Trikå-fabriker",
            "location": "Borås",
            "business": "Trikåfabriker med spinnerier och färgerier. Tillverkar trikåvaror dels vid tio fabriker i Borås, dels vid fabriker i Malmö, Mölndal, Fritsla, Strömsfors, Uddebo och Vegby (sistnämnda fyra i Älvsb. l.)",
            "products": "Varumärke: »Eiser».",
            "contact": {
                "office": "Huvudkontor: Borås",
                "phone": [
                    "102686"
                ],
                "telegraph": "Eiser, Borås",
                "postgiro": "9350",
                "sales_offices": [
                    {
                        "location": "Stockholm",
                        "phone": "102686"
                    }
                ]
            },
            "financials": {
                "capital": "10,100,000 kr",
                "employees": {
                    "total": 2500
                },
                "annual_turnover": "34,000,000 kr"
            },
            "foundation_year": 1913,
            "board": [
                {
                    "name": "dir. Carl Eiserman",
                    "role": "Styrelsens ordförande"
                },
                {
                    "name": "civiling. N. W. Hörstadius",
                    "role": "Vice ordförande"
                },
                {
                    "name": "dir. S. Bergengren",
                    "role": "Styrelsemedlem"
                },
                {
                    "name": "dir. Petrus Skoglund",
                    "role": "Styrelsemedlem"
                },
                {
                    "name": "bankdir. Helmer Stén",
                    "role": "Styrelsemedlem"
                },
                {
                    "name": "grossh. S. Vetterlein",
                    "role": "Styrelsemedlem"
                }
            ],
            "manager": "Verkställande direktör: Carl Eiserman"
        }
    }
}