{
    "original": "Klaesson—Klichéanstalten\n\n*AB. A. Klaessons Möbelfabrik,\n\nFjugesta.\n\nMöbelfabrik i Fjugesta (Örebro l.).\nTillverkar möbler samt affärs-, sjukhus-,\nkonditori-, restaurant- och\nbankinredningar m. m.\n\nTelefon: 39. Postgiro: 75017. —\nAkt.-kap.: 200,000 kr. Antal industriarb.: 35.\nTillv.-värde pr år: 450,000 kr. — Firman\netabl. 1903, bolag 1933.\n\nStyrelse: fabr. Hjalmar Klaesson, disp.\nJohn Klaesson, fabr. Ragnar Klaesson.\nDisp.: John Klaesson.\n\n*AB. Klafreströms Bruk,\n\nKlavreström.\n\nMek. verkstad och gjuteri i Klavreström\n(Kronob. l.). Tillverkar spisar,\nvärmeledningspannor, kaminer och\nhandelsgjut-gods, smideshammare,\nventilationsmaterial och pumpar. Bolaget idkar jämväl\nlantbruk, skogshantering samt\nsågverksrörelse.\n\nTelegr.-adr.: Klafreström, Växjö.\nTelefon: ISTorrhult »Klavreströms Bruk».\nPostgiro: 6960.\n\nAkt.-kap.: 480,000 kr. Antal\nindustriarb.: 225. — Bruket anlagt 1736, bolag\n1911.\n\nStyrelse: bruksäg. Ivar Ekströmer\n(ordf.), bruksäg. Thorsten Ekströmer,\nbankdir. Ola Källqvist.\n\nVerkst. dir.: Ivar Ekströmer.\n\nDisp.: ryttm. Carl Johan Ekströmer.\n\n\"Klara Civiltryckeri AB., Stockholm.\n\nUtför affärs- och reklamtryck,\nbokarbeten, kataloger, tidskrifter och\ndagstidningar.\n\nKontor: Kl. V. Kyrkog. 7. Telefon:\n100023, 100025, 100041, 100047 o. 100085.\nPostgiro: 54944.\n\nAkt.-kap.: 167,000 kr. Antal\nindustriarb.: 80.\n\nTryckeriet etabl. 1869, nuv. bolag 1932.\n\nStyrelse: byråchef Rolf Broberg, disp.\nYngve Porsby, dir. Arne Sohlman.\n\nDisp.: Yngve Porsby.\n\nKamrer: Ingmar Gränsbo.\n\n(Jfr annons nr 98.)\n\n*AB. Klaraviks Tricotfabrik,\n\nKarlstad.\n\nTillverkar koftor, jumpers, klänningar,\npullovers, herrvästar, baddräkter,\ntrikå-underkläder m. m.\n\nTelefon: 10498 o. 10496. Postgiro:\n27960. Representanter: i Stockholm:\nThure Oscarson, Sveavägen 109, telefon:\n\n314830; i Göteborg: J. E. Carlsson,\nBur-gårdsg. 13, telefon: 120845.\n\nAkt.-kap.: 300,000 kr. Antal\nindustriarb.: 56. Tillv.-värde pr år: 900,000 kr.\n— Firman etabl. 1917, bolag 1930.\n\nStyrelse ^ o. verkst. direktörer: Emil!\nJonson o. ing. Sven Jonson.\n\nKassör: fröken T. Hultgren.\n\n* Ernst T. Klassons Möbeltillverkning;,\n\nSkillingaryd.\n\nTillverkar möbler vid fabrik i\nSkillingaryd (Jönköp. l.).\n\nTelefon: 116. Postgiro: 77383. —\nTillv.-värde pr år: 70,000 kr. — Firman*\netabl. 1930.\n\nÄgare o. chef: fabr. Ernst T. Klasson-\n\n*Carl Klein, Gävle.\n\nSe Dragéfabriken, Carl Klein, Gävle..\n\nAB. Kleist Konfektion, Borås.\n\nTillverkar herr- och gosskläder.\nVarumärke: »KK»-kläder.\n\nTelefon: 13435. Postgiro: 90041. —\nAkt.-kap.: 65,000 kr. Antal industriarb.::\n20. Tillv.-värde pr år: 300,000 kr. —\nFirman etabl. 1930, bolag 1938.\n\nStyrelse o. verkst. dir.: fabr. Gustaf\nKleist.\n\n*Klemensnäs Träsliperi, Klemensnäs^\n\nSe AB. Scharins Söner, Klemensnäs.\n\n*AB. Kliché, Stockholm.\n\nUtför gravyrarbeten, klichéer,\nkopparfällningar, maskinretusch, teckningar,\nreklamfotograferingar m. m. samt\nplu-ralis-klichéer, gummistämplar och\nsempe-ritklichéer.\n\nKontor: Gamla Brog. 27. Telegr.-adr.:\nKliché, Stockholm. Telefon: 231695.\nPostgiro: 4695.\n\nAkt.-kap.: 20,600 kr. Arb.-antal:\n10.-Tillv.-värde pr år: 200,000 kr. —\nBolaget grundat 1906.\n\nStyrelse: dir. Per O. S. Fjästad (ordf.),\nherr Jan Fjästad, herr Olof Fjästad, herr\nPer S. Fjästad.\n\nVerkst. dir.: Per O. S. Fjästad.\n\n*AB. Klichéanstalten Hj. Lindblom &amp;\nCo., Stockholm.\n\nTillverkar klichéer, teckningar och\nre-tuscher.\n\nKontor: Apelbergsg. 56. Telefon:\n112473 o. 203816. Postgiro: 4776.",
    "structured": {
        "1": {
            "name": "AB. A. Klaessons Möbelfabrik",
            "location": "Fjugesta",
            "business": "Möbelfabrik",
            "products": "Tillverkar möbler samt affärs-, sjukhus-, konditori-, restaurant- och bankinredningar m. m.",
            "contact": {
                "office": "Fjugesta",
                "phone": [
                    "39"
                ],
                "postgiro": "75017",
                "head_office": "Fjugesta",
                "telegraph": "",
                "factory_office": "",
                "factory_phone": ""
            },
            "financials": {
                "capital": "200,000 kr",
                "employees": {
                    "Antal industriarb.": 35
                },
                "annual_turnover": "",
                "annual_production_value": "450,000 kr"
            },
            "foundation_year": 1903,
            "current_name_year": 1933,
            "board": [
                {
                    "name": "fabr. Hjalmar Klaesson",
                    "role": ""
                },
                {
                    "name": "disp. John Klaesson",
                    "role": ""
                },
                {
                    "name": "fabr. Ragnar Klaesson",
                    "role": ""
                }
            ],
            "director": "",
            "managing_director": "",
            "sales_manager": "",
            "manager": ""
        },
        "2": {
            "name": "AB. Klafreströms Bruk",
            "location": "Klavreström",
            "business": "Mek. verkstad och gjuteri",
            "products": "Tillverkar spisar, värmeledningspannor, kaminer och handelsgjut-gods, smideshammare, ventilationsmaterial och pumpar. Idkar jämväl lantbruk, skogshantering samt sågverksrörelse.",
            "contact": {
                "office": "Klavreström",
                "phone": [
                    "ISTorrhult »Klavreströms Bruk»"
                ],
                "postgiro": "6960",
                "head_office": "",
                "telegraph": "Klafreström, Växjö",
                "factory_office": "",
                "factory_phone": ""
            },
            "financials": {
                "capital": "480,000 kr",
                "employees": {
                    "Antal industriarb.": 225
                },
                "annual_turnover": "",
                "annual_production_value": ""
            },
            "foundation_year": 1736,
            "current_name_year": 1911,
            "board": [
                {
                    "name": "bruksäg. Ivar Ekströmer",
                    "role": "ordf."
                },
                {
                    "name": "bruksäg. Thorsten Ekströmer",
                    "role": ""
                },
                {
                    "name": "bankdir. Ola Källqvist",
                    "role": ""
                }
            ],
            "director": "",
            "managing_director": "Ivar Ekströmer",
            "sales_manager": "",
            "manager": ""
        },
        "3": {
            "name": "Klara Civiltryckeri AB.",
            "location": "Stockholm",
            "business": "Tryckeri",
            "products": "Utför affärs- och reklamtryck, bokarbeten, kataloger, tidskrifter och dagstidningar.",
            "contact": {
                "office": "Kl. V. Kyrkog. 7",
                "phone": [
                    "100023",
                    "100025",
                    "100041",
                    "100047",
                    "100085"
                ],
                "postgiro": "54944",
                "head_office": "",
                "telegraph": "",
                "factory_office": "",
                "factory_phone": ""
            },
            "financials": {
                "capital": "167,000 kr",
                "employees": {
                    "Antal industriarb.": 80
                },
                "annual_turnover": "",
                "annual_production_value": ""
            },
            "foundation_year": 1869,
            "current_name_year": 1932,
            "board": [
                {
                    "name": "byråchef Rolf Broberg",
                    "role": ""
                },
                {
                    "name": "disp. Yngve Porsby",
                    "role": ""
                },
                {
                    "name": "dir. Arne Sohlman",
                    "role": ""
                }
            ],
            "director": "",
            "managing_director": "",
            "sales_manager": "",
            "manager": "Ingmar Gränsbo"
        },
        "4": {
            "name": "AB. Klaraviks Tricotfabrik",
            "location": "Karlstad",
            "business": "Tricotfabrik",
            "products": "Tillverkar koftor, jumpers, klänningar, pullovers, herrvästar, baddräkter, trikå-underkläder m. m.",
            "contact": {
                "office": "Karlstad",
                "phone": [
                    "10498",
                    "10496"
                ],
                "postgiro": "27960",
                "head_office": "",
                "telegraph": "",
                "factory_office": "",
                "factory_phone": ""
            },
            "financials": {
                "capital": "300,000 kr",
                "employees": {
                    "Antal industriarb.": 56
                },
                "annual_turnover": "",
                "annual_production_value": "900,000 kr"
            },
            "foundation_year": 1917,
            "current_name_year": 1930,
            "board": [
                {
                    "name": "Emil Jonson",
                    "role": "verkst. direktörer"
                },
                {
                    "name": "ing. Sven Jonson",
                    "role": ""
                },
                {
                    "name": "T. Hultgren",
                    "role": "Kassör"
                }
            ],
            "director": "",
            "managing_director": "",
            "sales_manager": "",
            "manager": ""
        },
        "5": {
            "name": "Ernst T. Klassons Möbeltillverkning",
            "location": "Skillingaryd",
            "business": "Möbeltillverkning",
            "products": "Tillverkar möbler",
            "contact": {
                "office": "Skillingaryd",
                "phone": [
                    "116"
                ],
                "postgiro": "77383",
                "head_office": "",
                "telegraph": "",
                "factory_office": "",
                "factory_phone": ""
            },
            "financials": {
                "capital": "",
                "employees": {
                    "": ""
                },
                "annual_turnover": "",
                "annual_production_value": "70,000 kr"
            },
            "foundation_year": 1930,
            "current_name_year": "",
            "board": [],
            "director": "",
            "managing_director": "",
            "sales_manager": "",
            "manager": "fabr. Ernst T. Klasson"
        },
        "6": {
            "name": "AB. Kleist Konfektion",
            "location": "Borås",
            "business": "Konfektion",
            "products": "Tillverkar herr- och gosskläder.",
            "contact": {
                "office": "Borås",
                "phone": [
                    "13435"
                ],
                "postgiro": "90041",
                "head_office": "",
                "telegraph": "",
                "factory_office": "",
                "factory_phone": ""
            },
            "financials": {
                "capital": "65,000 kr",
                "employees": {
                    "Antal industriarb.": 20
                },
                "annual_turnover": "",
                "annual_production_value": "300,000 kr"
            },
            "foundation_year": 1930,
            "current_name_year": 1938,
            "board": [
                {
                    "name": "fabr. Gustaf Kleist",
                    "role": "verkst. dir."
                }
            ],
            "director": "",
            "managing_director": "",
            "sales_manager": "",
            "manager": ""
        },
        "7": {
            "name": "AB. Kliché",
            "location": "Stockholm",
            "business": "Gravyrarbeten",
            "products": "Utför gravyrarbeten, klichéer, kopparfällningar, maskinretusch, teckningar, reklamfotograferingar m. m.",
            "contact": {
                "office": "Gamla Brog. 27",
                "phone": [
                    "231695"
                ],
                "postgiro": "4695",
                "head_office": "",
                "telegraph": "",
                "factory_office": "",
                "factory_phone": ""
            },
            "financials": {
                "capital": "20,600 kr",
                "employees": {
                    "Arb.-antal": 10
                },
                "annual_turnover": "",
                "annual_production_value": "200,000 kr"
            },
            "foundation_year": 1906,
            "current_name_year": "",
            "board": [
                {
                    "name": "dir. Per O. S. Fjästad",
                    "role": "ordf."
                },
                {
                    "name": "herr Jan Fjästad",
                    "role": ""
                },
                {
                    "name": "herr Olof Fjästad",
                    "role": ""
                }
            ],
            "director": "",
            "managing_director": "Per O. S. Fjästad",
            "sales_manager": "",
            "manager": ""
        },
        "8": {
            "name": "AB. Klichéanstalten Hj. Lindblom & Co.",
            "location": "Stockholm",
            "business": "Klichéer",
            "products": "Tillverkar klichéer, teckningar och retuscher.",
            "contact": {
                "office": "Apelbergsg. 56",
                "phone": [
                    "112473",
                    "203816"
                ],
                "postgiro": "4776",
                "head_office": "",
                "telegraph": "",
                "factory_office": "",
                "factory_phone": ""
            },
            "financials": {
                "capital": "",
                "employees": {
                    "": ""
                },
                "annual_turnover": "",
                "annual_production_value": ""
            },
            "foundation_year": "",
            "current_name_year": "",
            "board": [],
            "director": "",
            "managing_director": "",
            "sales_manager": "",
            "manager": ""
        }
    }
}