{
    "original": "Malmö\n\n\"Malmö Metallvarufabrik AB.,\n\nMalmö.\n\nTillverkar elektr. belysningsarmatur.\n\nKontor: Nya Vattenverksvägen 2B.\nTelegr.-adr.: Ljuskronan, Malmö. Telefon:\n25929. Postgiro: 37790.\n\nAkt.-kap.: 108,000 kr. Antal\nindustriarb.: 35. Tillv.-värde pr år: 800,000 kr.\n\n—\tBolaget grundat 1916.\n\nStyrelse: bankdir. Algot Riider (ordf.),\ndisp. Ivar Liljeqvist, ing. Bo Riider.\n\nDisp.: Ivar Liljeqvist.\n\n\"Malmö Nysilverfabrik, Malmö.\n\nTillverkar kuvertnysilver.\n\nKontor: Regementsg. 10. Telefon:\n22813. Postgiro: 38376. — Arb.-antal: 10.\n\n—\tFirman etabl. 1884.\n\nÄgare o. chef: Gustav Frost.\n\n\"Malmö Oljeslageri &amp; Happachs\nSåp-fabriks AB., Malmö.\n\nOljeslageri och kem.-teknisk fabrik.\nTillverkar lin- och rovolja, kakor av\nlin-och rapsfrö samt såpa, soda, tvätt- och\ntoalettvål, tvålflingor, tvättpulver,\nglyce-rin och vattenglas, parfymer, kosmetiska\noch farmaceutiska preparat. Varumärken:\n»Diamant», »Mohab» o. »Dido».\n\nKontor: Nobelvägen. Telegr.-adr.:\nMohab, Malmö. Telefon: 21762. Postgiro:\n38299. Nederlag: Stockholm, Närkesg. 1,\ntelefon: 408801; Göteborg, Mellang. 2 A,\ntelefon: 119851.\n\nAkt.-kap.: 1,502,000 kr. Antal\nindustriarb.: 150. Tillv.-värde pr år: 8,500,000 kr.\n\nBolaget utgör sedan 1920 en\nsammanslutning av f. d. Malmö Oljeslageri AB.,\ngrundat 1904, och f. d. Happachs\nSåp-fabriks AB., grundat 1905.\n\nStyrelse: v. konsul August Wingårdh\n(ordf.), disp. A. Christofferson, konsul\nEdw. H. Thomée, v. konsul Gustaf\nWingårdh.\n\nVerkst. dir.: Edw. H. Thomée.\n\nDisp.: A. Christofferson.\n\n\"Malmö Reklamfabrik AB., Malmö.\n\nSkylt- och kartongfabrik. Tillverkar\nreklamskyltar och kalenderryggar av\nkartong och celluloid, reklamartiklar samt\nkartonger. Specialiteter: Präglade\nreklamskyltar, kalenderryggar och\nmassartiklar.\n\nKontor: Barkg. 8. Telegr.-adr.:\nReklamfabriken, Malmö. Telefon: 24584,\n78384 o. 28103. Postgiro: 38312.\nFörsäljn.-kontor: Stockholm, Kungsg. 74, telefon:\n103936; Göteborg, Kaserntorget 6,\ntelefon: 133663.\n\nAkt.-kap.: 160,400 kr. Antal\nindustriarb.: 75. Tillv.-värde pr år: 1,000,000 kr.\n\n—\tFirman etabl. 1911, bolag 1937.\n\nStyrelse: disp. A. O. Lindh, fru E.\n\nLindh, dir. Arnold Sönnergård.\n\nVerkst. dir.: fru E. Lindh.\n\nDriftschef: A. O. Lindh.\n\nFörsäljn.-chef: Arnold Sönnergård.\n\n\"Malmö Sidenväveri AB., Malmö.\n\nTillverkar sidentyger.\n\nKontor: Industrigatan 14—18.\nTelegr.-adr.: Cocon, Malmö. Telefon: 72550.\nPostgiro: 39220.\n\nAkt.-kap.: 500,000 kr. Antal\nindustriarb.: 65. Tillv.-värde pr år: 3,000,000 kr.\n\n—\tBolaget grundat 1935.\n\nStyrelse: bankdir. Einar Beskow, adv.\nMatts Fallenius, dr Hans Gwalter.\n\nDisp.: Sten Tuweson.\n\nDriftschef: Heinrich Gut.\n\nAB. Malmö Skeppsfärgfabrik,\n\nHälsingborg.\n\nTillverkar färger och fernissor vid\nfabrik i Hälsingborg. Specialitet:\nskeppsfärger.\n\nHuvudkontor: Hälsingborg.\nTelegr.-adr.: Hempelfärger, Hälsingborg.\nTelefon: 20760. Postgiro: 39454.\nAvdeln.-kon-tor: Malmö, Norra Vallg. 70. Telefon:\n77300; Stockholm, Johannesgränd 3,\ntelefon: 115003; Göteborg, Fiskhamnen,\ntelefon: 140526.\n\nAkt.-kap.: 100,000 kr. Tillv.-värde pr\når: 750,000 kr. — Bolaget grundat 1924.\n\nVerkst. dir.: Erik B. Dupont.\n\n\"Malmö Skjortfabrik, Malmö.\n\nTillverkar skjortor, pyjamas och\nslipsar.\n\nKontor: Gustaf Adolfs torg 8 B.\nTelefon: 25230 o. 74030. Postgiro: 37630. —\nAntal industriarb.: 70. Tillv.-värde pr år:\n650,000 kr. — Firman etabl. 1925.\n\nÄgare o. chef: disp. Karl Palmkvist.\n\n\"Malmö Skofabriks AB., Malmö.\n\nTillverkar skodon. Varunamn:\n»Her-kules» o. »Gyllene Gripen».\n\nKontor: Industrig. 4. Telegr.-adr.:\nSkofabriken, Malmö. Telefon: 25094, 20586\no. 23485. Postgiro: 38651. Avd.-kontor:\nStockholm, Kungsgatan 37, telefon:\n107344; Göteborg, Kungsg. 32, telefon:\n134087.\n\nAkt.-kap.: 500,000 kr. Antal\nindustriarb.: 200. — Bolaget grundat 1893,\nom-bildat 1934.\n\n360*",
    "structured": {
        "firms": [
            {
                "name": "Malmö Metallvarufabrik AB.",
                "location": "Malmö",
                "business": "Tillverkar elektr. belysningsarmatur",
                "products": "Description of products manufactured or services offered.",
                "contact": {
                    "office": "Nya Vattenverksvägen 2B",
                    "phone": [
                        "25929"
                    ],
                    "postgiro": "37790"
                },
                "financials": {
                    "capital": "108,000 kr",
                    "employees": {
                        "industriarb": 35
                    },
                    "annual_turnover": "800,000 kr",
                    "annual_production_value": "800,000 kr"
                },
                "foundation_year": 1916,
                "board": [
                    {
                        "name": "bankdir. Algot Riider",
                        "role": "ordf."
                    },
                    {
                        "name": "disp. Ivar Liljeqvist",
                        "role": "ing."
                    },
                    {
                        "name": "ing. Bo Riider",
                        "role": ""
                    }
                ]
            },
            {
                "name": "Malmö Nysilverfabrik",
                "location": "Malmö",
                "business": "Tillverkar kuvertnysilver",
                "contact": {
                    "office": "Regementsg. 10",
                    "phone": [
                        "22813"
                    ],
                    "postgiro": "38376"
                },
                "foundation_year": 1884,
                "owners": [
                    "Gustav Frost"
                ]
            },
            {
                "name": "Malmö Oljeslageri & Happachs Såp-fabriks AB.",
                "location": "Malmö",
                "business": "Oljeslageri och kem.-teknisk fabrik",
                "products": "Tillverkar lin- och rovolja, kakor av lin-och rapsfrö samt såpa, soda, tvätt- och toalettvål, tvålflingor, tvättpulver, glyce-rin och vattenglas, parfymer, kosmetiska och farmaceutiska preparat. Varumärken: »Diamant», »Mohab» o. »Dido»",
                "contact": {
                    "office": "Nobelvägen",
                    "phone": [
                        "21762"
                    ],
                    "postgiro": "38299",
                    "sales_offices": [
                        {
                            "location": "Stockholm",
                            "phone": "408801"
                        },
                        {
                            "location": "Göteborg",
                            "phone": "119851"
                        }
                    ]
                },
                "financials": {
                    "capital": "1,502,000 kr",
                    "employees": {
                        "industriarb": 150
                    },
                    "annual_turnover": "8,500,000 kr",
                    "annual_production_value": "8,500,000 kr"
                },
                "predecessor": "utt.."
            },
            {
                "name": "Malmö Reklamfabrik AB.",
                "location": "Malmö",
                "business": "Skylt- och kartongfabrik",
                "products": "Tillverkar reklamskyltar och kalenderryggar av kartong och celluloid, reklamartiklar samt kartonger. Specialiteter: Präglade reklamskyltar, kalenderryggar och massartiklar",
                "contact": {
                    "office": "Barkg. 8",
                    "phone": [
                        "24584",
                        "78384",
                        "28103"
                    ],
                    "postgiro": "38312",
                    "sales_offices": [
                        {
                            "location": "Stockholm",
                            "phone": "103936"
                        },
                        {
                            "location": "Göteborg",
                            "phone": "133663"
                        }
                    ]
                },
                "financials": {
                    "capital": "160,400 kr",
                    "employees": {
                        "industriarb": 75
                    },
                    "annual_turnover": "1,000,000 kr",
                    "annual_production_value": "1,000,000 kr"
                },
                "corporation_year": 1937,
                "board": [
                    {
                        "name": "disp. A. O. Lindh",
                        "role": ""
                    },
                    {
                        "name": "fru E. Lindh",
                        "role": ""
                    },
                    {
                        "name": "Arnold Sönnergård",
                        "role": "dir."
                    }
                ]
            },
            {
                "name": "Malmö Sidenväveri AB.",
                "location": "Malmö",
                "business": "Tillverkar sidentyger",
                "contact": {
                    "office": "Industrigatan 14—18",
                    "phone": [
                        "72550"
                    ],
                    "postgiro": "39220"
                },
                "financials": {
                    "capital": "500,000 kr",
                    "employees": {
                        "industriarb": 65
                    },
                    "annual_turnover": "3,000,000 kr",
                    "annual_production_value": "3,000,000 kr"
                },
                "foundation_year": 1935,
                "board": [
                    {
                        "name": "bankdir. Einar Beskow",
                        "role": ""
                    },
                    {
                        "name": "adv. Matts Fallenius",
                        "role": ""
                    },
                    {
                        "name": "dr Hans Gwalter",
                        "role": ""
                    }
                ],
                "director": "Heinrich Gut"
            },
            {
                "name": "AB. Malmö Skeppsfärgfabrik",
                "location": "Hälsingborg",
                "business": "Tillverkar färger och fernissor vid fabrik i Hälsingborg",
                "products": "Specialitet: skeppsfärger",
                "contact": {
                    "office": "Hälsingborg",
                    "phone": [
                        "20760"
                    ],
                    "postgiro": "39454",
                    "sales_offices": [
                        {
                            "location": "Malmö",
                            "phone": "77300"
                        },
                        {
                            "location": "Stockholm",
                            "phone": "115003"
                        },
                        {
                            "location": "Göteborg",
                            "phone": "140526"
                        }
                    ]
                },
                "financials": {
                    "capital": "100,000 kr",
                    "annual_turnover": "750,000 kr"
                },
                "corporation_year": 1924,
                "director": "Erik B. Dupont"
            },
            {
                "name": "Malmö Skjortfabrik",
                "location": "Malmö",
                "business": "Tillverkar skjortor, pyjamas och slipsar",
                "contact": {
                    "office": "Gustaf Adolfs torg 8 B",
                    "phone": [
                        "25230",
                        "74030"
                    ],
                    "postgiro": "37630"
                },
                "employees": {
                    "industriarb": 70
                },
                "annual_turnover": "650,000 kr",
                "current_name_year": 1925,
                "director": "disp. Karl Palmkvist"
            },
            {
                "name": "Malmö Skofabriks AB.",
                "location": "Malmö",
                "business": "Tillverkar skodon",
                "products": "Varunamn: »Herkules» o. »Gyllene Gripen»",
                "contact": {
                    "office": "Industrig. 4",
                    "phone": [
                        "25094",
                        "20586",
                        "23485"
                    ],
                    "postgiro": "38651",
                    "sales_offices": [
                        {
                            "location": "Stockholm",
                            "phone": "107344"
                        },
                        {
                            "location": "Göteborg",
                            "phone": "134087"
                        }
                    ]
                },
                "financials": {
                    "capital": "500,000 kr",
                    "employees": {
                        "industriarb": 200
                    }
                },
                "corporation_year": 1934
            }
        ]
    }
}