{
    "original": "Karlskrona—Karlson\n\n\"Karlskrona Bryggerier, Karlskrona.\n\nSe AB. Förenade Bryggerierna i\nKarlskrona, Karlskrona.\n\nKarlskrona Hattfabriks AB.,\n\nKarlskrona.\n\nTillverkar herrhattar oeh filtstumpar.\nTelefon: 178 o. 179. Nederlag: G. A.\nHägg, Stockholm, Norrlandsg. 2.\nTelefon: 105889 o. 109187. Postgiro: 58490.\n\nAkt.-kap.: 400,000 kr. Antal\nindustriarb.: 200. Tillv.-värde pr år: 2,500,000 kr.\n\n—\tFabriken anlagd 1872, bolag 1900.\nStyrelse: dir. Sven Wahlund (ordf.),\n\nfröken Elsa Hägg, dir. Carl Rydberg,\ndisp. Olof Thorell, fru Anna-Stina\nWahlund.\n\nVerkst. dir.: Sven Wahlund (Sthlm).\nDirektör: Carl Rydberg.\nDisp.: Olof Thorell.\n\n\"Karlskrona Kakelfabrik, Karlskrona.\n\nSe Kakelfabriks AB. i Karlskrona,\nKarlskron a.\n\n\"AB. Karlskrona Lampfabrik,\n\nKarlskrona.\n\nLamp- och metallvaruf abrik, mek.\nverkstad samt elektr. installationsbyrå.\n\nTillverkar elektr. belysningsarmatur,\nkristallkronor, fotogenlampor,\nlampbrän-nare, signallyktor, lyktstolpar,\nkabelmuffar, järnarmar, stålmaster, svetsade\njärnkonstruktioner; utför\nmetalltrycknings-arbeten samt pressade, stansade och\nsvetsade tunnplåtsarbeten m. m.\n\nTelegr.-adr.: Lampfabriken,\nKarlskrona. Telefon: 153. Postgiro: 84500.\n\nAkt.-kap.: 427,000 kr. Antal\nindustriarb.: 50. — Firman etabl. 1884, bolag\n1920.\n\nStyrelse: dir. Ernst G. Lundgren\n(ordf.), ing. Björn Orvar Skantze,\nciviling. Lars Olof Skantze.\n\nVerkst. dir.: L. O. Skantze.\n\n\"AB. Karlskrona Porslinsfabrik,\n\nKarlskrona.\n\nTillverkar bordsserviser, kaffeserviser\n\noch restaurantporslin i fältspatäkta\nkvalitet.\n\nTelegr.-adr.: Porslin, Karlskrona.\nTelefon: 220 o. 535. Postgiro: 30697.\n\nAkt.-kap.: 625,000 kr. Antal\nindustriarb.: 375. Tillv.-värde pr år: 2,800,000 kr.\n\n—\tBolaget, grundat 1918, äges av\nUpsala-Ekeby AB., Ekebybruk.\n\n27\n\nStyrelse: dir. Nils V. Sterner (ordf.),\ndisp. O. Harald Lindström, dir. W. Meyer,\nprof. Folke Wetter, dr Ragnar Winbladh.\n\nVerkst. dir.: Nils V. Sterner\n(Ekeby-bruk).\n\nDisponenter: W. Rudmark o. John A.\nJohanson,\n\nAB. Karlslunda Pappersindustri,\n\nSmedby.\n\nTillverkar kuvert och kuvertpåsar,\nm. m. vid fabrik i Smedby (Kalmar l.).\n\nTelefon: 71. Postgiro: 77227. —\nAkt.-kap.: 50,000 kr. Antal industriarb.: 20.\n— Firman etabl. 1936. ^\n\nDir.: Hjalmar Edstein.\n\nKarlson &amp; Lundh, Örebro.\n\nSkofabrik. Tillverkar vända,\nbecksöm-sydda och agodamskodon.\n\nTelefon: 15569. — Antal industriarb.:\n30. Tillv.-värde pr år: 350,000 kr. —\nFirman etabl. 1929.\n\nÄgare o. chef: fabr. Emil Karlson.\n\n*AB. Karlsson &amp; Nilsson, Eskilstuna.\n\nKnivfabrik. Tillverkar\nförskärarkni-var, brödsågar, tomatknivar, skalknivar,\nköksverktygssatser monterade på plattor,\npincetter, allt i rostfritt stål.\n\nTelefon: 33159 o. 33149. Postgiro:\n96588. — Akt.-kap.: 123,400 kr. Antal\nindustriarb.: 70. Tillv.-värde pr år:\n1,000,000 kr. — Firman etabl. 1932, bolag\n1945.\n\nStyrelse o. verkst. direktörer: fabr.\nIngvar Karlsson o. fabr. Georg Nilsson.\n\n*Karlson &amp; Starck, Göteborg.\n\nSe Konfektions AB. Karlson &amp; Starck,\n\nGöteborg.\n\n^Karlssons Snickerifabrik, Bröderna,\n\nLaholm.\n\nSe Bröderna Karlssons Snickerifabrik,\nLaholm.\n\nKarlssons Verkstads AB., Bröderna,\n\nEnköping.\n\nSe Bröderna Karlssons Verkstads AB.,\nEnköping.\n\n*A. Karlsons Bryggeri AB., Lysekil.\n\nTillverkar maltdrycker av klass I och\nII samt läskedrycker och mineralvatten.\n\nTelefon: 19, 20 o. 48. Postgiro: 9151.\n-Akt.-kap.: 500,000 kr. Antal industri-\n\n8*",
    "structured": {
        "1": {
            "name": "Karlskrona Bryggerier",
            "location": "Karlskrona",
            "business": "Bryggeri",
            "contact": {
                "phone": [
                    "178",
                    "179"
                ],
                "postgiro": "58490"
            },
            "financials": {
                "capital": "400,000 kr",
                "employees": {
                    "industriarb": 200
                },
                "annual_turnover": "2,500,000 kr",
                "annual_production_value": "2,500,000 kr"
            },
            "foundation_year": 1872,
            "current_name_year": 1900,
            "board": [
                {
                    "name": "Sven Wahlund",
                    "role": "ordf."
                },
                {
                    "name": "Elsa Hägg",
                    "role": "fröken"
                },
                {
                    "name": "Carl Rydberg",
                    "role": "dir."
                },
                {
                    "name": "Olof Thorell",
                    "role": "disp."
                },
                {
                    "name": "Anna-Stina Wahlund",
                    "role": "fru"
                }
            ],
            "director": "Sven Wahlund",
            "managing_director": "Sven Wahlund",
            "sales_manager": "Carl Rydberg"
        },
        "2": {
            "name": "Karlskrona Hattfabriks AB.",
            "location": "Karlskrona",
            "business": "Tillverkning av herrhattar oeh filtstumpar",
            "contact": {
                "phone": [
                    "178",
                    "179"
                ],
                "postgiro": "58490"
            },
            "financials": {
                "capital": "400,000 kr",
                "employees": {
                    "industriarb": 200
                },
                "annual_turnover": "2,500,000 kr",
                "annual_production_value": "2,500,000 kr"
            },
            "foundation_year": 1872,
            "current_name_year": 1900,
            "board": [
                {
                    "name": "Sven Wahlund",
                    "role": "ordf."
                },
                {
                    "name": "Elsa Hägg",
                    "role": "fröken"
                },
                {
                    "name": "Carl Rydberg",
                    "role": "dir."
                },
                {
                    "name": "Olof Thorell",
                    "role": "disp."
                },
                {
                    "name": "Anna-Stina Wahlund",
                    "role": "fru"
                }
            ],
            "director": "Sven Wahlund",
            "managing_director": "Sven Wahlund",
            "sales_manager": "Carl Rydberg"
        },
        "3": {
            "name": "Karlskrona Kakelfabrik",
            "location": "Karlskrona",
            "business": "Kakel- och keramikindustri"
        },
        "4": {
            "name": "AB. Karlskrona Lampfabrik",
            "location": "Karlskrona",
            "business": "Lamp- och metallvaruf"
        },
        "5": {
            "name": "AB. Karlskrona Porslinsfabrik",
            "location": "Karlskrona",
            "business": "Tillverkning av bordsserviser, kaffeserviser och restaurantporslin i fältspatäkta kvalitet"
        },
        "6": {
            "name": "AB. Karlslunda Pappersindustri",
            "location": "Smedby",
            "business": "Tillverkning av kuvert och kuvertpåsar"
        },
        "7": {
            "name": "Karlson & Lundh",
            "location": "Örebro",
            "business": "Tillverkning av skor"
        },
        "8": {
            "name": "AB. Karlsson & Nilsson",
            "location": "Eskilstuna",
            "business": "Tillverkning av knivar, brödsågar, tomatknivar, skalknivar, köksverktygssatser monterade på plattor, pincetter, allt i rostfritt stål"
        },
        "9": {
            "name": "Karlson & Starck",
            "location": "Göteborg"
        },
        "10": {
            "name": "A. Karlsons Bryggeri AB.",
            "location": "Lysekil",
            "business": "Tillverkning av maltdrycker av klass I och II samt läskedrycker och mineralvatten",
            "contact": {
                "phone": [
                    "19",
                    "20",
                    "48"
                ],
                "postgiro": "9151"
            },
            "financials": {
                "capital": "500,000 kr",
                "employees": {
                    "industriarb": 8
                }
            },
            "foundation_year": null,
            "current_name_year": null,
            "board": null,
            "director": null,
            "managing_director": null,
            "sales_manager": null
        }
    }
}