{
    "original": "Scandia—Sc haub\n\nScandia Plywood AB., Skattkärr.\n\nSågverk och plywoodfabrik vid\nSkattkärr (Värml. l.). Tillverkar plywood och\nlamellträ.\n\nTelefon: 43 o. 47. Postgiro: 94374. —\nAkt.-kap.: 360,000 kr. Antal industriarb.:\n84. Årstillv.: 5,000 kbm plywood. —\nBolaget grundat 1935.\n\nStyrelse: timmer uppköp. Emil\nDanielsson, disp. Eric Ternqvist, fabr. Reinhold\nTernqvist, civilekonom Bengt Wästlund,\nbyggm. Olof Wästlund.\n\nVerkst. dir.: Olof Wästlund.\n\n*AB. Scania-Vabis, Södertälje.\n\nAutomobil- och motorfabrik. Tillverkar\nlastbilar och omnibusar, motorer för\ndiesel-, bensin-, bentyl- och gengasdrift,\nstålgjutgods, smiden m. m.\n\nTelegr.-adr.: Scania, Södertälje.\nTelefon: »Scania-Vabis». Postgiro: 8408.\n\nAgenter i utlandet:\n\nBelgien: Ateliers de Fabrications\nAuto-mobiles J E van Doorslaer, 45—47 Rue\nde 1’Instruction, Bruxelles;\n\njDanmarie: A/S Nordisk Dieselauto,\nFredriksholms Havnevej 14, Kobenhavn\nSV;\n\nEgypten: The Swedish Mediterranean\nCo, A Berggren &amp; Co, 31 Nebi Daniel,\nAlexandria;\n\nHolland: N V Adr. Beers Int.\nAutomo-bielhandel—Mij, Geestbrugkade 32,\nRijs-wijk;\n\nNorge: Norsk Scania-Vabis A/S,\nDram-mensveien 131, Oslo;\n\nTurhiet: Firma Nebil Baykent, Posta\nKutusu 1455 Galata, Istanbul.\n\nAkt.Tkap.: 5,200,000 kr. Antal\nindustriarb.: 1,300. — Bolaget grundat 1891,\nnuv. bolagsord. 1921.\n\nStyrelse: f. d. statssekr. Lars Rabenius\n(ordf.), bankdir. Marcus Wallenberg (v.\nordf.), bankdir. Rich. Julin, dir. C.-B.\nNathhorst, övering. August Nilsson.\n\nVerkst. dir.: O.-B. Nathhorst.\n\nTekn. chef: dir. K. T. Lidner.\n\nEkonomichef: dir. Erik Nilsson.\n\nScania-Vega AB., Margarinfabriken,\n\nMjölby.\n\nSe Margarinfabriken Scania-Vega x\\B.,\nMjölby.\n\n*AB. Scharins Söner, Klemensnäs.\n\nTräsliperi, sågverk, hyvleri och\nwall-boardfabrik vid Klemensnäs (Västerb. l.).\nTillverkar vit, våt och torr mek. trämassa,\nsågade och hyvlade trävaror samt\nwall-board (märke: »Ilnite»).\n\n4’\n\nPostadr.: Klemensnäs. Telefon:\nSkellefteå 30190. Postgiro: 60822.\nFörsäljn.-kontor för wallboard: Stockholm, Birger\nJarlsg. 13, telefon: 117292.\n\nAgenter i utlandet: för trämassa:\n\nEngland: Foy’s Woodpulp Ltd., 16,\nEastcheap, London E. C. 3;\n\nFranhrihe: Société Générale des Påtes\nå Papier Nordling, Macé &amp; Cie, 11, Rue\nde la Pépiniére, Paris;\n\nför trävaror:\n\nEngland: Thomas Simson &amp; Co., Ltd.,\n6, Great Winchester Street, London,\nE. 0.2;\n\nFranhrihe: Société Anonyme A. H.\nNordin, 11, Boulevard Malesherbes, Paris\n(8e);\n\nHolland: Firma Otto J. Faber,\nPost-bus 621, Amsterdam C;\n\nDanmark: Firma Philip Gottlieb,\nChristian IX:s Gade 7, Köpenhamn K;\n\nSpanien: Hans Hals, Apartado 505,\nMadrid.\n\nAkt.-kap. :o 3,000,000 kr. Antal\nindustriarb.: 550. Årstillv.: 50,000 ton trämassa\n(varav hälften kan torkas), 8,000 stds\nträvaror, 30,000 ton träfiberplattor.\n\nFirman etabl. 1824, bolag 1913.\n\nStyrelse: bankdir. Helmer Stén (ordf.),\ndisp. Erik Unander-Scharin, herr John\nUnander-Scharin, herr Nicke\nUnander-Scharin.\n\nVerkst. dir.: Erik Unander-Scharin.\n\nDir.-assistent: ing. Lennart Theorin.\n\nFabrikschef: ing. Simon Carlsson.\n\nFörsäljn.-chefer: för wallboard: Ivar\nSällvin; för trävaror o. massa: Nils\nPersson.\n\nAB. P. J. Scharin, Landskrona.\n\nFärg- och fernissfabrik. Tillverkar\noljerivna färger, spackelfärg, kitt,\nlackfärger och kopallacker.\n\nTelegr.-adr.: Scharin, Landskrona.\nTelefon: »Scharins Färghandel». Postgiro:\n14550. — Akt.-kap.: 40,000 kr. Arb.-antal:\n10. —- Firman etabl. 1897, bolag 1910.\n\nVerkst. dir.: Sture .Scharin.\n\nAB. Schaub &amp; Co., Stockholm,\nGöteborg o. Malmö.\n\nTarmrenserier och talgsmälterier i\nStockholm, Göteborg och Malmö.\nFörädlar tarmar för charkuteriändamål,\nframställer talg och fett. Varumärke:\n»Tri-pas». Firman driver även handel med\nkonsttarmar (märke: »Naturin»),\ncharkuteri- och bagerimaskiner samt\nutensilier.\n\nKontor: Stockholm; postadr.:\nStockholm 20, telefon: 492630, postgiro: 1859;\nGöteborg, telefon: 150320, postgiro:\n\n)*",
    "structured": {
        "firms": [
            {
                "name": "Scandia Plywood AB",
                "location": "Skattkärr",
                "business": "Sågverk och plywoodfabrik",
                "products": "Tillverkar plywood och lamellträ",
                "contact": {
                    "office": "Skattkärr",
                    "phone": [
                        "43",
                        "47"
                    ],
                    "postgiro": "94374",
                    "factory_phone": "",
                    "sales_offices": [],
                    "telegraph": ""
                },
                "financials": {
                    "capital": "360,000 kr",
                    "employees": {
                        "industriarb": 84
                    },
                    "annual_turnover": "",
                    "annual_production_value": ""
                },
                "foundation_year": 1935,
                "board": [
                    {
                        "name": "Emil Danielsson",
                        "role": "disp."
                    }
                ],
                "manager": ""
            },
            {
                "name": "AB. Scania-Vabis",
                "location": "Södertälje",
                "business": "Automobil- och motorfabrik",
                "products": "Tillverkar lastbilar, omnibusar, motorer, stålgjutgods, smiden m. m.",
                "contact": {
                    "office": "",
                    "phone": [
                        "Scania-Vabis"
                    ],
                    "postgiro": "8408",
                    "factory_phone": "",
                    "sales_offices": [],
                    "telegraph": "Scania, Södertälje"
                },
                "financials": {
                    "capital": "5,200,000 kr",
                    "employees": {
                        "industriarb": 1300
                    },
                    "annual_turnover": "",
                    "annual_production_value": ""
                },
                "foundation_year": 1891,
                "board": [
                    {
                        "name": "Lars Rabenius",
                        "role": "ordf."
                    }
                ],
                "manager": "",
                "managing_director": ""
            },
            {
                "name": "AB. Scharins Söner",
                "location": "Klemensnäs",
                "business": "Träsliperi, sågverk, hyvleri och wall-boardfabrik",
                "products": "Tillverkar vit, våt och torr mek. trämassa, sågade och hyvlade trävaror samt wall-board (märke: »Ilnite»)",
                "contact": {
                    "office": "Klemensnäs",
                    "phone": [
                        "Skellefteå 30190"
                    ],
                    "postgiro": "60822",
                    "factory_phone": "",
                    "sales_offices": [],
                    "telegraph": ""
                },
                "financials": {
                    "capital": "3,000,000 kr",
                    "employees": {
                        "industriarb": 550
                    },
                    "annual_turnover": "",
                    "annual_production_value": ""
                },
                "foundation_year": 1824,
                "board": [
                    {
                        "name": "Helmer Stén",
                        "role": "ordf."
                    }
                ],
                "manager": "",
                "director": "",
                "sales_manager": ""
            },
            {
                "name": "AB. P. J. Scharin",
                "location": "Landskrona",
                "business": "Färg- och fernissfabrik",
                "products": "Tillverkar oljerivna färger, spackelfärg, kitt, lackfärger och kopallacker",
                "contact": {
                    "office": "",
                    "phone": [
                        "Scharins Färghandel"
                    ],
                    "postgiro": "14550",
                    "factory_phone": "",
                    "sales_offices": [],
                    "telegraph": "Scharin, Landskrona"
                },
                "financials": {
                    "capital": "40,000 kr",
                    "employees": {
                        "arb": 10
                    },
                    "annual_turnover": "",
                    "annual_production_value": ""
                },
                "foundation_year": 1897,
                "board": [],
                "manager": "Sture .Scharin"
            },
            {
                "name": "AB. Schaub & Co.",
                "location": "Stockholm, Göteborg o. Malmö",
                "business": "Tarmrenserier och talgsmälterier",
                "products": "Förädlar tarmar för charkuteriändamål, framställer talg och fett. Varumärke: »Tri-pas». Firman driver även handel med konsttarmar (märke: »Naturin»), charkuteri- och bagerimaskiner samt utensilier",
                "contact": {
                    "office": "",
                    "phone": [
                        "492630",
                        "150320"
                    ],
                    "postgiro": "",
                    "factory_phone": "",
                    "sales_offices": [],
                    "telegraph": ""
                },
                "financials": {
                    "capital": "",
                    "employees": {},
                    "annual_turnover": "",
                    "annual_production_value": ""
                },
                "foundation_year": 0,
                "board": [],
                "manager": ""
            }
        ]
    }
}