{
    "original": "J ansson—J i-Te\n\nWitalis Jansson &amp; Co., Karlstad:\n\nSågverk och hyvleri (Kanikenässågen).\nTillverkar sågade och hyvlade trävaror.\n\nTelefon: 11626 o. 14626. Postgiro:\n75122. — Antal industriarb.: 35.\nÅrstillv.: 2,000 stds trävaror. — Firman\netabl. 1933,\n\nÄgare o. chefer: sågverksäg. Witalis\nJansson o. sågverksäg. John Westlund.\n\n*AB. japana, Göteborg.\n\nFärg- och fernissfabrik i Margretedal,\nGöteborg. Tillverkar linoleumfernissor,\nkopal- och spritfernissor, lack-, olje-,\nemulsions- och spritfärger,\nbrytningsfärger i tuber, spackelfärg samt\nfärgbort-tagningsmedel. Specialitet: golvfernissa.\nVarumärken: »Lackman», »Weggomatt»\no. »Japanazink». Bolaget driver även\nengroshandel med måleriutensilier.\n\nKontor: Margretedal; postadr.:\nGöteborg 5. Telegr.-adr.: Japana, Göteborg.\nTelefon: 166273, 185176 o. 186794.\nPostgiro: 25589. Avd.-kontor: Malmö, ö.\nFÖr-stadsg. 3, telefon: 33355.\n\nAkt.-kap.: 100,000 kr. Antal\nindustriarb.: 10. Tillv.-värde pr år: 1,200,000 kr.\n— Bolaget grundat 1920.\n\nStyrelse: dir. Ivar Körner, disp. Elof\nWilhelmsson.\n\nVerkst. dir.: I. Körner.\n\nDisp. i Malmö: E. Wilhelmsson.\n\nDriftsing.: Lennart Lundberg.\n\nFörsäljn.-chef: Helge Olausson.\n\nAB. Jawe, Göteborg.\n\nKonfektionsfabrik. Tillverkar\nbarn-och sportkläder.\n\nKontor: Wollins Trappor. Telegr.-adr.:\nJawe, Göteborg. Telefon: 126392.\nPostgiro: 43581.\n\nAkt.-kap.: 10,000 kr. — Bolaget,\ngrundat 1933, är dotterbolag till AB. J. A.\nWettergren &amp; Co., Göteborg.\n\nStyrelse: dir. ThorbjÖrn Holm (ordf.),\ndir. Fredrik Holm.\n\nVerkst. dir.: Thorbjörn Holm.\n\n*N. Chr. Jensen, Trävaru AB.,\n\nKarlstad.\n\nSe Trävaru AB. N. Chr. Jensen,\nKarlstad.\n\nJerfeds Mek. Verkstads AB.,\n\nÖrnsköldsvik.\n\nMek, verkstad i Örnsköldsvik samt\nplåtslageri och varv vid Bonässund,\nörn-sköldsvik. Tillverkar maskiner för cellu-\n\nlosaindustrien samt för flottningsleder,\nbygger och reparerar båtar. Specialiteter:\nkranar och traverser.\n\nKontor: Örnsköldsvik. Telegr.-adr.:\nJerfeds, Örnsköldsvik. Telefon: 2026.\nPostgiro: 62885.\n\nAkt.-kap.: 150,000 kr. Antal\nindustriarb.: 90. — Bolaget grundat 1878.\n\nStyrelse: dir. Carl Kempe, fil. dr Erik\nKempe, disp. Erik Wiklund.\n\nVerkst. dir.: Erik Wiklund.\n\nVerkstadsing.: Sixten Berglöf.\n\n*Jerie Torf AB., Järle.\n\nTorvströfabrik och sågverk i Ervalla,\nJärle (Örebro l.). Tillverkar torvströ och\ntorvmull samt sågade trävaror. Bolaget\nidkar jämväl skogshantering.\n\nTelefon: Närkes Järle 5. Postgiro:\n166954. — Akt.-kap.: 100,000 kr. Antal\nindustriarb.: 15. Tillv.-värde pr år:\n100,000 kr. — Firman grundad 1889.\n\nStyrelse: fil. dr K. G. Giöbel (ordf.),\nagronom Henning Hedberg, byggm. Hj.\nSelin.\n\nVerkst. dir.: Henning Hedberg.\n*Jerlins Konfektfabrik, Hudiksvall.\n\nTillverkar konfektyrer och karameller.\n\nTelefon: 49. Postgiro: 79930. —\nArb.-antal: 10. — Firman etabl. 1889.\n\nÄgare o. chefer: fru K. Jerlin o. fabr.\nErnst Jerlin.\n\nAB. Magnus Jernberg, Karlstad.\n\nSe Lavoné-fabriken, AB. Magnus\nJernberg, Karlstad.\n\n\"Sven Jesperssons Snickerifabrik,\n\nStockholm.\n\nTillverkar möbler, vånings-, bank- och\nbutiksinredningar, byggnadssnickerier m.\nm. samt lamelldörrar enl. eget patent.\n\nKontor: Surbrunnsg. 44. Telefon:\n332490 o. 302250. Postgiro: 154344.\n—-Antal industriarb.: 42. Tillv.-värde pr\når: 500,000 kr. — Firman etabl. 1903.\n\nÄgare o. chef: fabr. Sven Jespersson.\n\n*Ji-Te AB., Åstorp.\n\nTräförädlingsfabrik i Åstorp\n(Kristianst. l.). Tillverkar lamelldörrar med\nkarmar. (Specialitet: färdigbeslagna och\nytbehandlade dörrar, fanérade med\nädel-fanér eller genomfärgat furufanér\n(»Ji-Te ädelfur»), trämjöl, tunnstav och\nbottnar, speciellt för smördrittlar samt\nbilved. Firman driver jämväl handelsrörelse\nmed trävaror och byggnadsmaterialier\nsamt tunnband.\n\n259*",
    "structured": {
        "1": {
            "name": "Witalis Jansson & Co.",
            "location": "Karlstad",
            "business": "Sågverk och hyvleri (Kanikenässågen)",
            "products": "Tillverkar sågade och hyvlade trävaror",
            "contact": {
                "office": null,
                "phone": [
                    "11626",
                    "14626"
                ],
                "postgiro": "75122",
                "head_office": null,
                "sales_offices": null,
                "telegraph": null,
                "factory_office": null,
                "factory_phone": null
            },
            "financials": {
                "capital": null,
                "employees": {
                    "industriarb": 35
                },
                "annual_turnover": null,
                "annual_production_value": "2,000 stds trävaror"
            },
            "foundation_year": 1933,
            "owners": [
                "sågverksäg. Witalis Jansson",
                "sågverksäg. John Westlund"
            ],
            "board": null,
            "director": null,
            "managing_director": null,
            "sales_manager": null,
            "manager": null
        },
        "2": {
            "name": "AB. japana",
            "location": "Göteborg",
            "business": "Färg- och fernissfabrik i Margretedal",
            "products": "Tillverkar linoleumfernissor, kopal- och spritfernissor, lack-, olje-, emulsions- och spritfärger, brytningsfärger i tuber, spackelfärg samt färgborttagningsmedel",
            "contact": {
                "office": "Margretedal",
                "phone": [
                    "166273",
                    "185176",
                    "186794"
                ],
                "postgiro": "25589",
                "head_office": null,
                "sales_offices": [
                    {
                        "location": "Malmö",
                        "phone": "33355"
                    }
                ],
                "telegraph": "Japana",
                "factory_office": null,
                "factory_phone": null
            },
            "financials": {
                "capital": "100,000 kr",
                "employees": {
                    "industriarb": 10
                },
                "annual_turnover": "1,200,000 kr",
                "annual_production_value": null
            },
            "foundation_year": 1920,
            "owners": null,
            "board": [
                {
                    "name": "dir. Ivar Körner",
                    "role": "ordf."
                },
                {
                    "name": "disp. Elof Wilhelmsson",
                    "role": null
                }
            ],
            "director": "I. Körner",
            "managing_director": null,
            "sales_manager": "Helge Olausson",
            "manager": "Lennart Lundberg"
        },
        "3": {
            "name": "AB. Jawe",
            "location": "Göteborg",
            "business": "Konfektionsfabrik",
            "products": "Tillverkar barn-och sportkläder",
            "contact": {
                "office": "Wollins Trappor",
                "phone": [
                    "126392"
                ],
                "postgiro": "43581",
                "head_office": null,
                "sales_offices": null,
                "telegraph": "Jawe",
                "factory_office": null,
                "factory_phone": null
            },
            "financials": {
                "capital": "10,000 kr",
                "employees": null,
                "annual_turnover": null,
                "annual_production_value": null
            },
            "foundation_year": 1933,
            "owners": null,
            "board": [
                {
                    "name": "dir. ThorbjÖrn Holm",
                    "role": "ordf."
                },
                {
                    "name": "dir. Fredrik Holm",
                    "role": null
                }
            ],
            "director": "Thorbjörn Holm",
            "managing_director": null,
            "sales_manager": null,
            "manager": null
        },
        "4": {
            "name": "N. Chr. Jensen, Trävaru AB.",
            "location": "Karlstad",
            "business": "Se Trävaru AB. N. Chr. Jensen, Karlstad",
            "products": null,
            "contact": {
                "office": null,
                "phone": null,
                "postgiro": null,
                "head_office": null,
                "sales_offices": null,
                "telegraph": null,
                "factory_office": null,
                "factory_phone": null
            },
            "financials": null,
            "foundation_year": null,
            "owners": null,
            "board": null,
            "director": null,
            "managing_director": null,
            "sales_manager": null,
            "manager": null
        },
        "5": {
            "name": "Jerfeds Mek. Verkstads AB.",
            "location": "Örnsköldsvik",
            "business": "Mek, verkstad i Örnsköldsvik samt plåtslageri och varv vid Bonässund",
            "products": "Tillverkar maskiner för cellulosaindustrien samt för flottningsleder, bygger och reparerar båtar",
            "contact": {
                "office": null,
                "phone": [
                    "2026"
                ],
                "postgiro": "62885",
                "head_office": null,
                "sales_offices": null,
                "telegraph": "Jerfeds",
                "factory_office": null,
                "factory_phone": null
            },
            "financials": {
                "capital": "150,000 kr",
                "employees": {
                    "industriarb": 90
                },
                "annual_turnover": null,
                "annual_production_value": null
            },
            "foundation_year": 1878,
            "owners": null,
            "board": [
                {
                    "name": "dir. Carl Kempe",
                    "role": null
                },
                {
                    "name": "fil. dr Erik Kempe",
                    "role": null
                },
                {
                    "name": "disp. Erik Wiklund",
                    "role": null
                }
            ],
            "director": null,
            "managing_director": "Erik Wiklund",
            "sales_manager": null,
            "manager": "Sixten Berglöf"
        },
        "6": {
            "name": "Jerie Torf AB.",
            "location": "Järle",
            "business": "Torvströfabrik och sågverk i Ervalla",
            "products": "Tillverkar torvströ och torvmull samt sågade trävaror",
            "contact": {
                "office": null,
                "phone": [
                    "Närkes Järle 5"
                ],
                "postgiro": "166954",
                "head_office": null,
                "sales_offices": null,
                "telegraph": null,
                "factory_office": null,
                "factory_phone": null
            },
            "financials": {
                "capital": "100,000 kr",
                "employees": {
                    "industriarb": 15
                },
                "annual_turnover": null,
                "annual_production_value": "100,000 kr"
            },
            "foundation_year": 1889,
            "owners": null,
            "board": [
                {
                    "name": "fil. dr K. G. Giöbel",
                    "role": "ordf."
                },
                {
                    "name": "agronom Henning Hedberg",
                    "role": null
                },
                {
                    "name": "byggm. Hj. Selin",
                    "role": null
                }
            ],
            "director": "Henning Hedberg",
            "managing_director": null,
            "sales_manager": null,
            "manager": null
        },
        "7": {
            "name": "Jerlins Konfektfabrik",
            "location": "Hudiksvall",
            "business": "Tillverkar konfektyrer och karameller",
            "products": null,
            "contact": {
                "office": null,
                "phone": [
                    "49"
                ],
                "postgiro": "79930",
                "head_office": null,
                "sales_offices": null,
                "telegraph": null,
                "factory_office": null,
                "factory_phone": null
            },
            "financials": {
                "capital": null,
                "employees": null,
                "annual_turnover": null,
                "annual_production_value": null
            },
            "foundation_year": 1889,
            "owners": [
                "fru K. Jerlin",
                "fabr. Ernst Jerlin"
            ],
            "board": null,
            "director": null,
            "managing_director": null,
            "sales_manager": null,
            "manager": null
        },
        "8": {
            "name": "AB. Magnus Jernberg",
            "location": "Karlstad",
            "business": "Se Lavoné-fabriken, AB. Magnus Jernberg, Karlstad",
            "products": null,
            "contact": {
                "office": null,
                "phone": null,
                "postgiro": null,
                "head_office": null,
                "sales_offices": null,
                "telegraph": null,
                "factory_office": null,
                "factory_phone": null
            },
            "financials": null,
            "foundation_year": null,
            "owners": null,
            "board": null,
            "director": null,
            "managing_director": null,
            "sales_manager": null,
            "manager": null
        },
        "9": {
            "name": "Sven Jesperssons Snickerifabrik",
            "location": "Stockholm",
            "business": "Tillverkar möbler, vånings-, bank- och butiksinredningar, byggnadssnickerier m. m. samt lamelldörrar enl. eget patent",
            "products": null,
            "contact": {
                "office": "Surbrunnsg. 44",
                "phone": [
                    "332490",
                    "302250"
                ],
                "postgiro": "154344",
                "head_office": null,
                "sales_offices": null,
                "telegraph": null,
                "factory_office": null,
                "factory_phone": null
            },
            "financials": {
                "capital": null,
                "employees": {
                    "industriarb": 42
                },
                "annual_turnover": null,
                "annual_production_value": "500,000 kr"
            },
            "foundation_year": 1903,
            "owners": null,
            "board": null,
            "director": null,
            "managing_director": null,
            "sales_manager": null,
            "manager": "fabr. Sven Jespersson"
        },
        "10": {
            "name": "Ji-Te AB.",
            "location": "Åstorp",
            "business": "Träförädlingsfabrik i Åstorp (Kristianst. l.)",
            "products": "Tillverkar lamelldörrar med karmar, trämjöl, tunnstav och bottnar, speciellt för smördrittlar samt bilved. Firman driver jämväl handelsrörelse med trävaror och byggnadsmaterialier samt tunnband",
            "contact": {
                "office": null,
                "phone": [
                    "259"
                ],
                "postgiro": null,
                "head_office": null,
                "sales_offices": null,
                "telegraph": null,
                "factory_office": null,
                "factory_phone": null
            },
            "financials": {
                "capital": null,
                "employees": null,
                "annual_turnover": null,
                "annual_production_value": null
            },
            "foundation_year": null,
            "owners": null,
            "board": null,
            "director": null,
            "managing_director": null,
            "sales_manager": null,
            "manager": null
        }
    }
}