{
    "original": "Uddeholm\n\nBolaget äger elektr.\nvattenkraftsstationer om c:a 150,000 hkr i Munkfors,\nHag-fors, Forshult, Krakerud, Skymnäs,\nSko-ga, Malta, Knon, Nain, Råda och\nStjärns-fors (samtl. i Värml. l.) samt idkar jämväl\njordbruk, skogshantering och\nrederirörelse. Vidare äger bolaget Blombacka AB.,\nLindfors, Degerfors Järnverks AB.,\nDegerfors, och Sulfit AB. Göta, samt\nNordmark—Klarälvens Järnväg.\n\nHagfors Järnverk, Hagfors. Elektriska\nmasugnar, sintringsverk,\nferrolegerings-verk, bessemer- och martinverk,\nelektro-stålverk, valsverk, glödgverk,\nånghammare, tackjärns- och stålgjuteri samt\nmek. verkstad. Tillverkar tackjärn,\nferrolegeringar, stålgöt, billets, massiva\ntubämnen, stångstål, profilstål, valstråd,\nbandstål, fjäderstål, verktygsstål, massivt\noch ihåligt borrstål, filstål, magnetstål,\nkonstruktionsstål, eldhärdiga, rostfria och\nsyrafasta stål i form av stänger, profiler,\ntråd, band och gjutgods, väghyvelstål\nm. m. — Antal industriarb.: 1,600.\n\nMunkfors Bruk, Munkfors. Martinverk,\nlancashirehärdar, varm- och kallvalsverk,\nverkstäder för profilering av kallvalsade\nband, manufaktur smed ja, mek. verkstad,\ntråddrageri och fjäderfabrik. Tillverkar\nkallvalsat bandstål, såväl härdat som\nohärdat, såsom dragfjäderstål,\nbandsåg-stål, vedsågstål, måttbandstål,\nrakkling-stål och bandjärn för djuppressning,\nstansning etc., profilerat stål av\nkallvalsade band, sågblad, grammofonfjädrar,\nspiral- och vagnsfjädrar, harv-, räfs- och\nkultivatorpinnar, dragen tråd,\ncenterless-slipat stångstål, silverstål samt stålspett,\nbarkspadar m. m. — Antal industriarb.:\n1,300.\n\nStorfors Rör verk, Storfors. Rörvalsverk,\nrördrageri, rörmanufakturverkstäder, mek.\nverkstad, gjuteri och smedja. Tillverkar\nvarmvalsade och kalldragna sömlösa\nstålrör och tuber samt rostfria rör,\nrörspiraler och annan rörmanufaktur, ävensom\nheldragna och smidda gasflaskor. —\nAntal industriarb.: 1,000.\n\nNykroppa Järnverk, Nykroppa.\nMasugnar, sintringsverk, martinverk,\nvalsverk, ånghammarsmedja, gjuteri och mek.\nverkstad. Tillverkar tackjärn, martingöt,\nvalsat och smitt stål samt smiden. —\nAntal industriarb.: 800.\n\nSkoghallsverken, Skoghall. Sågverk och\nhyvleri, cellulosafabriker, pappersbruk,\nsäckfabrik, sprit- och biproduktsfabriker\nsamt elektrokem. fabrik. Tillverkar sågade\noch hyvlade trävaror, blekt sulfitcellulosa\nför konstsilke, blekt och oblekt\nsulfatcellulosa, papper, papperssäckar, gummerat\npapper, sulfitsprit, eter, terpentin,\nmetanol, harts, kaustik soda, flytande klor,\ntrikloretylen, etylcellulosa, cellulosalim\n\n(märke: »Majöl»),\nträimpregneringsme-del (märke: »Pentolat») m. m. — Antal\nindustriarb.: 1,750.\n\nHuvudkontor: Uddeholm. Telegr.-adr.:\n»Uddeholms», Uddeholm. Telefon:\n»Huvudkontoret», Uddeholm. Postgiro: 95000.\nFörsäljn.-kontor: i Stockholm: AB.\nUddeholmsagenturen, Strandvägen 25, telefon:\n670305; i Göteborg: AB.\nUddeholmsagenturen, Södra Hamng. 17, telefon: 172695,\ntelegr.-adr.: Uddeholmship, Göteborg;\ni Malmö: AB. Uddeholmsagenturen,\nKon-torscentrum, telefon: 30722; i Eskilstuna:\nAB. Uddeholmsagenturen, telefon: 34700;\ni Sundsvall: AB. Uddeholmsagenturen,\ntelefon: 4576.\n\nAkt.-kap.: 77,500,000 kr. Sammanlagt\nantal industriarbetare: c:a 6,450. —\nAktiebolaget grundat 1870.\n\nStyrelse: bankir Tage Cervin (ordf.),\ndir. Ragnar Blomquist, dir. Mauritz\nCarlson, disp. Nils Danielsen, bankdir.\nErland Geijer.\n\nVerkst. dir. o. disp.: Nils Danielsen.\nDisp.-assist.: dir. Kjell Åkerhielm.\nTeknisk chef för järnverken: dir.\nEdvin Fornander.\n\nSkogschef: Sven G. Ekman.\n\nFörsäljningschefer :\nför järn och stål: dir. J. Herlenius;\nför trävaror, celllulosa, papper och\nkemiska produkter: dir. Th. Ihre.\n\nChefer för:\n\nombudsmannaexp.: hovrättsnot. G.\nLarsson;\n\nekonomiavd.: kamrer Harald Falk;\ninköpsavd.: ing. W. Sjödén;\narkitektavd.: arkitekt Jöran Curman;\ncentrala byggnadsavd.: ing. Sture\nGöransson;\n\nlantbruksförvaltn.: int. Une Larsson;\nreklamavd.: ing. M. Åslund;\nkraftverken: övering. John Fletcher.\n\nPlatschefer:\n\nSkoghallsverken: dir. Waldemar\nHell-gren;\n\nHagfors: övering. Einar Nygren;\nMunkfors: övering. G. Vinell;\nStorfors: övering. Carl Skog;\nNykroppa: övering. Sven Kalling.\n\nChefer för AB. Uddeholmsagenturen:\ni Stockholm: dir. Harry Ahlström;\ni Göteborg: Hj. Rosenblad, o. för\nre-deriavd.: kapten Sune Tamm;\ni Malmö: Th. Flood;\ni Eskilstuna: civiling. Folke\nBengtsson ;\n\ni Sundsvall: ing. Karl Blomquist.\n\nt*",
    "structured": {
        "firms": [
            {
                "name": "Uddeholm",
                "location": "Uddeholm",
                "contact": {
                    "office": "Uddeholm",
                    "postgiro": "95000",
                    "head_office": "Uddeholm",
                    "telegraph": "Uddeholms",
                    "sales_offices": [
                        {
                            "location": "Stockholm",
                            "phone": "670305"
                        },
                        {
                            "location": "Göteborg",
                            "phone": "172695"
                        },
                        {
                            "location": "Malmö",
                            "phone": "30722"
                        },
                        {
                            "location": "Eskilstuna",
                            "phone": "34700"
                        },
                        {
                            "location": "Sundsvall",
                            "phone": "4576"
                        }
                    ]
                },
                "financials": {
                    "capital": "77,500,000 kr",
                    "employees": {
                        "industrial workers": 6450
                    }
                },
                "foundation_year": 1870,
                "board": [
                    {
                        "name": "Tage Cervin",
                        "role": "ordf."
                    },
                    {
                        "name": "Ragnar Blomquist",
                        "role": "dir."
                    },
                    {
                        "name": "Mauritz Carlson",
                        "role": "dir."
                    },
                    {
                        "name": "Nils Danielsen",
                        "role": "disp."
                    },
                    {
                        "name": "Erland Geijer",
                        "role": "bankdir."
                    }
                ],
                "director": "Nils Danielsen",
                "managing_director": "Nils Danielsen",
                "sales_manager": "J. Herlenius",
                "manager": "Nils Danielsen"
            }
        ]
    }
}