{
    "original": "Viola—Viskafors\n\nKontor: Mölndalsvägen 20. Telefon:\n161807. — Akt.-kap.: 50,000 kr. Antal\nindustriarb.: 10. Tillv.-värde pr år:\n200,000 kr. — Firman etabl. 1917, bolag\n1923.\n\nVerkst. dir.: Martin G. Johansson.\n\n\"Viola, Tvål- &amp; Parfymfabriken,\n\nGöteborg.\n\nSe Tvål- &amp; Parfymfabriken Viola AB.,\nGöteborg.\n\nJ. A. Wirén, Cjuteri o. Mek.\nVerkstad, Sävedalen.\n\nJärn- och metallgjuteri i Sävedalen\n(Göteb. o. Bohus l.). Tillverkar\nbrunnsborrningsmaskiner, pumpar, fläktar m. m.\nsamt verkstadsarbeten i järn och metall.\nVarumärke: »JAW».\n\nTelefon: Göteborg 260150, 261650 o.\n261750. Postgiro: 41081.\n\nAntal industriarb.: 65. Tillv.-värde pr\når: 700,000 kr. — Firman etabl. 1919.\n\nÄgare o. chef: dir. J. A. Wirén.\n\nFörsäljn.-chef: T. Björkman.\n\nAB. Wiro, Stockholm.\n\nFabrik för tillverkning av packningar\ni Stockholm, mek. verkstad\n(»Adrianverken») i Motala. Tillverkar packningar,\nstansade och pressade massartiklar,\nrör-klammer, expansionsbult, kilhakar och\ntryekluftskopplingar m. m. Varumärken:\n»Packman», »Wiro», »Wisolin» o.\n»Wiro-sol». Bolaget driver såsom huvudrörelse\nengroshandel med isoleringsmateriel och\nindustriförnödenheter.\n\nHuvud- o. försäljn.-kontor: Stockholm,\nYnglingag. 17; postadr.: Stockholm 6.\nTelegr.-adr.: Wirorör, Stockholm,\ntelefon: 233200. Postgiro: 57171.\nFabrikskontor i Motala, telefon: 1088.\nAvd.-kon-tor i Göteborg, Andréeg.—Dalag.;\ntelegr.-adr.: Wirorör, Göteborg; telefon: 145005\n\n0.\t129130.\n\nAkt.-kap.: 100,000 kr. Antal\nindustriarb.: 25. — Bolaget grundat 1923,\nombildat 1934.\n\nVerkst. dir.: ing. Rune G. Berggren.\n\nTekn. chef: ing. Sven Gladh.\n\nFabrikschef: i Motala: verkm. Eric\nOlsson.\n\n\"Wirsbo AB., Virsbo.\n\nMek. verkstad, manufaktursmedja,\nrörverk samt sågverk vid Virsbo (Västmanl.\n\n1.)..\n\nTillverkar svetsade gas- och ångrör,\ngalvaniserade vattenledningsrör, smidda\n\nrördelar och flänsar, hejar- och\nmanu-faktursmiden samt sågade och\nhyvlade-trävaror. Bolaget idkar jämväl jordbruk\noch skogshantering.\n\nTelegr.-adr.: Virsbobruk, Norberg.\nTelefon: Virsbo 31. Postgiro: 29740.\n\nAkt.-kap.: 2,874,000 kr. Antal\nindustriarb.: 300. Tillv.-värde pr år: 8,000,000 kr..\n\n—\tBolaget grundat 1892.\n\nStyrelse: bruksdisp. Helge Silverstolpe?\n(ordf.), frih. Magnus v. Essen, fru Eva,\nKleen, disp. Bror Lagercrantz.\n\nDisp.: Bror Lagercrantz.\n\nKamrer: E. Angberg.\n\nKassör: Folke Johnsson.\n\nVerkstadsing.: Nils Thorén.\n\nOrder- o. offerting.: G.-F. Nyqvist.\n\n\"Wirserums nya Möbelfabrik,\n\nHultarp.\n\nTillverkar möbler, speciellt\nmatrumsmöbler samt bokhyllor och tebord vid\nfabrik i Hultarp (Kalmar l.).\n\nTelefon: Virserum 16. Postgiro: 93644.\n\n—\tArb.-antal: 12. Tillv.-värde pr\når-155,000 kr. — Firman etabl. 1902.\n\nÄgare o. chef: fabr. Carl Nilsson.\n\n\"Virserums Hjulfabrik, Totebo.\n\nSe Totebo Hjulfabrik, Totebo.\n\n\"Visby Bryggeri, Visby.\n\nSe Nya AB. Visby Bryggeri, Visby.\n\nAB. Visby Silicat-Tegelfabrik,\n\nVisby.\n\nTillverkar kalk, murbruk och tegel.\n\nTelefon: 398. Postgiro: 189898. —\nAkt.-kap.: 50,100 kr. Arb.-antal: 16.\nTillv.-värde pr år: 130,000 kr. — Firman\netabl. 1903.\n\nVerkst. dir.: Carl Gardell.\nViskadalens Jacquardväveri, Kinna..\n\nTillverkar gardiner, draperier och\nborddukar vid väveri i Kinna (Älvsb. L).\n\nTelefon: 48058. Postgiro: 136.105. —\nAntal industriarb.: 5. Tillv.-värde pr årr\n100,000 kr. — Firman etabl. 1937.\n\nÄgare o. chef: fabr. Oscar V.\nAndersson.\n\nFörsäljn.-chef: Åke V. Oscarsson.\n\n\"Viskafors Cummifabrik, Viskafors_\n\nSe Skandinaviska Gummi AB.,\nViskafors.\n\n",
    "structured": {
        "1": {
            "name": "Viola—Viskafors",
            "location": "Mölndalsvägen 20",
            "business": "Tvål- & Parfymfabrik",
            "financials": {
                "capital": "50,000 kr",
                "employees": {
                    "industriarb": 10
                },
                "annual_turnover": "200,000 kr",
                "annual_production_value": "200,000 kr"
            },
            "foundation_year": 1917,
            "corporation_year": 1923,
            "director": "Martin G. Johansson"
        },
        "2": {
            "name": "J. A. Wirén, Cjuteri o. Mek. Verkstad",
            "location": "Sävedalen",
            "business": "Järn- och metallgjuteri",
            "contact": {
                "phone": [
                    "Göteborg 260150",
                    "261650",
                    "261750"
                ],
                "postgiro": "41081"
            },
            "financials": {
                "employees": {
                    "industriarb": 65
                },
                "annual_turnover": "700,000 kr"
            },
            "foundation_year": 1919,
            "owner": "dir. J. A. Wirén",
            "sales_manager": "T. Björkman"
        },
        "3": {
            "name": "AB. Wiro",
            "location": "Stockholm",
            "business": "Tillverkning av packningar",
            "contact": {
                "office": "Ynglingag. 17, Stockholm"
            },
            "financials": {
                "capital": "100,000 kr",
                "employees": {
                    "industriarb": 25
                }
            },
            "corporation_year": 1934,
            "board": [
                {
                    "name": "ing. Rune G. Berggren",
                    "role": "Verkst. dir."
                },
                {
                    "name": "ing. Sven Gladh",
                    "role": "Tekn. chef"
                }
            ],
            "manager": "verkm. Eric Olsson"
        },
        "4": {
            "name": "Wirsbo AB., Virsbo",
            "location": "Virsbo",
            "business": "Mek. verkstad, manufaktursmedja, rörverk samt sågverk",
            "contact": {
                "telegraph": "Virsbobruk, Norberg",
                "phone": "Virsbo 31",
                "postgiro": "29740"
            },
            "financials": {
                "capital": "2,874,000 kr",
                "employees": {
                    "industriarb": 300
                },
                "annual_turnover": "8,000,000 kr"
            },
            "corporation_year": 1892,
            "board": [
                {
                    "name": "bruksdisp. Helge Silverstolpe",
                    "role": "ordf."
                },
                {
                    "name": "frih. Magnus v. Essen"
                },
                {
                    "name": "fru Eva Kleen"
                },
                {
                    "name": "disp. Bror Lagercrantz"
                }
            ]
        },
        "5": {
            "name": "Wirserums nya Möbelfabrik",
            "location": "Hultarp",
            "business": "Tillverkning av möbler",
            "contact": {
                "phone": "Virserum 16",
                "postgiro": "93644"
            },
            "financials": {
                "capital": "50,100 kr",
                "employees": {
                    "arb.-antal": 12
                },
                "annual_turnover": "155,000 kr"
            },
            "foundation_year": 1902,
            "owner": "fabr. Carl Nilsson"
        },
        "6": {
            "name": "Visby Silicat-Tegelfabrik",
            "location": "Visby",
            "business": "Tillverkning av kalk, murbruk och tegel",
            "contact": {
                "phone": "398",
                "postgiro": "189898"
            },
            "financials": {
                "capital": "50,100 kr",
                "employees": {
                    "arb.-antal": 16
                },
                "annual_turnover": "130,000 kr"
            },
            "foundation_year": 1903,
            "director": "Carl Gardell"
        },
        "7": {
            "name": "Viskafors Cummifabrik",
            "location": "Viskafors",
            "business": "Gummi fabrik",
            "description": "Se Skandinaviska Gummi AB., Viskafors"
        }
    }
}