{
    "original": "Hammar—Hammar gren\n\napparater, cisterner,\nventilationstrummor, bleck- och plåtslageriarbeten,\nrostfria plåtarbeten m. m.\n\nFirman försäljer och installerar\njämväl nautiska instrument såsom ekolod,\nkompasser, gyrokompasser etc. av\nutländsk tillverkning.\n\nKontor: Bryggarg. 3. Telegr.-adr.:\nCemham, Göteborg. Telefon: 130519,\n130500 o. 131150. Postgiro: 45907.\n\nAntal industriarb.: 35. Tillv.-värde pr\når: 400,000 kr. — Firman etabl. 1857.\n\nÄgare: fabr. Gustaf Hammar, ing.\nGilbert Hammar o. fabr. Torild Hammar.\n\nChefer: Gustaf Hammar o. Torild\nHammar.\n\n’AB. Hammars Tegelbruk,\n\nGamleby.\n\nTillverkar mur?, reveterings-, rör- och\ntaktegel samt mellanväggs- och\nisoleringsplattor vid tegelbruk i Gamleby\n(Kalmar l.).\n\nTelefon: 9. Postgiro: 142394. —\nAkt.-kap.: 20,200 kr. Årstillv.: 1,5 milj. st.\ntegelvaror. — Bolaget grundat 1909.\n\nDisp.: Arne Torstensson.\n\nOlof Hammarberg, Nya Varvet\n\nOrgelfabrik vid Nya Varvet (Göteb. o.\nBohus l.). Tillverkar kyrkorglar.\n\nTelefon: Göteborg 291260. Postgiro:\n44554. — Arb.-antal: 12. Tillv.-värde pr\när: 150,000 kr. — Firman etabl. 1847.\n\nÄgare: änkefru Hulda Hammarberg.\n\nChef: orgelbygg. Nils-Olof\nHammarberg.\n\nHammarby Bakelit Industri AB.,\n\nStockholm.\n\nTillverkar pressade och sprutpressade\nkonsthartsartiklar såsom campingartiklar,\nradiotillbehör, elektr. materiel, tubhattar,\nkammar, solglasögon m. m. Varumärke:\n»Habia».\n\nKontor: Hammarby, postadr.:\nStockholm 20. Telegr.-adr.: Habia, Stockholm.\nTelefon: 440210. Postgiro: 190031.\n\nAkt.-kap.: 100,000 kr. Antal\nindustriarb.: 90. — Bolaget grundat 1941.\n\nStyrelse: dir. Carl Jacobson (ordf.),\nciviling. Carl-Herbert Jacobson, bankdir.\nRichard Julin.\n\nVerkst. dir.: C.-H. Jacobson.\n\n’AB. Hammarbylampan, Stockholm.\n\nSe Lumalampan AB., Stockholm.\n\n’Hammarby Sulfitfabrik, Storvik.\n\nSe Storviks Sulfit AB., Ockelbo.\n\n’AB. Hammarbyverken, Stockholm.\n\nSvetsnings- och mek. verkstäder saimt\nvarv med flytdockor.\n\nBygger fartyg upp till 1,000 ton samt\ntillverkar helsvetsade och nitade artiklar\nsåsom brobyggnader, balkar,\nhögtrycksbehållare, cisterner, kokare och apparater\nför värmetekniska och industriella\nändamål m. m.; utför fartygsreparationer\nsamt reparerar medelst elektrisk och\ngassvetsning maskiner, ångpannor, axlar,\nfartygsdelar m. m. samt förslitna\nmaskindelar och apparater av stål, järn,\ngjutjärn och metallegeringår.\n\nHuvudkontor: Henriksdal, Stockholm;\npostadr.: Stockholm 35. Telegr.-adr. o.\ntelefon: Hammarby verken, Stockholm.\nPostgiro: 4095.\n\nAkt.-kap.: 500,000 kr. Antal\nindustriarb.: 221. Tillv.-värde pr år: 3,800,000 kr.\n\nBolaget grundat 1907 under namn\nElektriska Svetsnings AB. i Stockholm,\nnuv. namn 1943.\n\nStyrelse: dir. Emanuel Högberg (ordf.),\ndir. Chr. Hansen.\n\nDisp.: Gustav Ericson.\n\n(Jfr annons nr 84.)\n\n’Hammare* Fabriken, AB.,\n\nEskilstuna.\n\nSe Fabriken Hammare, AB.,\nEskilstuna.\n\n’Hammarforsens Kraft AB.,\n\nSundsvall.\n\nElektr. vattenkraftverk vid\nHammarforsen (Jämtl. l.). Distribuerar elektr.\nenergi till städerna Sundsvall och\nHärnösand samt storindustrier i dessa distrikt\noch i Söderhamnsdistriktet.\n\nTelefon: 55585. Postgiro: 70334. —\nAkt.-kap.: 4,500,000 kr. Distrib.-värde pr\når: 5,500,000 kr. — Bolaget grundat 1917.\n\nStyrelse: bankdir. Per Wåhlin (ordf.),\ndir. Arved Arvedson, dir. John\nLindström, dir. K. Erik Nyberg, bankdir. Stig\nödmark.\n\nVerkst. dir.: Arved Årvedson.\n\n’Hammargren &amp; C:o AB., Anneberg.\n\nPyroteknisk fabrik i Anneberg\n(Hallands l.). Tillverkar fyrverkeriartiklar,\nfotoblixtar, signalmateriel för militära\nändamål och för järnvägar m. m., facklor\noch marschaller samt serpentiner.\n\nTelegr.-adr.: Hammargrens, Anneberg.\nTelefon: »Hammargren &amp; Co.» Postgiro:\n25444.",
    "structured": {
        "firms": [
            {
                "name": "Hammar—Hammar gren",
                "location": "",
                "business": "apparater, cisterner, ventilationstrummor, bleck- och plåtslageriarbeten, rostfria plåtarbeten m. m.",
                "contact": {
                    "office": "Bryggarg. 3",
                    "phone": [
                        "130519",
                        "130500",
                        "131150"
                    ],
                    "postgiro": "45907",
                    "telegraph": "Cemham, Göteborg",
                    "factory_office": "",
                    "factory_phone": ""
                },
                "financials": {
                    "capital": "",
                    "employees": {
                        "industrial_workers": 35
                    },
                    "annual_turnover": "400,000 kr",
                    "annual_production_value": "400,000 kr"
                },
                "foundation_year": 1857,
                "owners": [
                    "fabr. Gustaf Hammar",
                    "ing. Gilbert Hammar",
                    "fabr. Torild Hammar"
                ]
            },
            {
                "name": "AB. Hammars Tegelbruk",
                "location": "Gamleby",
                "business": "Tillverkar mur?, reveterings-, rör- och taktegel samt mellanväggss- och isoleringsplattor vid tegelbruk i Gamleby (Kalmar l.)",
                "contact": {
                    "phone": [
                        "9"
                    ],
                    "postgiro": "142394"
                },
                "financials": {
                    "capital": "20,200 kr",
                    "employees": {},
                    "annual_turnover": "1,5 milj. st. tegelvaror",
                    "annual_production_value": "1,5 milj. st. tegelvaror"
                },
                "foundation_year": 1909,
                "board": [
                    {
                        "name": "Arne Torstensson",
                        "role": ""
                    }
                ]
            },
            {
                "name": "Olof Hammarberg",
                "location": "Nya Varvet",
                "business": "Orgelfabrik vid Nya Varvet (Göteb. o. Bohus l.). Tillverkar kyrkorglar",
                "contact": {
                    "phone": [
                        "Göteborg 291260"
                    ],
                    "postgiro": "44554"
                },
                "financials": {
                    "capital": "",
                    "employees": {
                        "workers": 12
                    },
                    "annual_turnover": "150,000 kr",
                    "annual_production_value": "150,000 kr"
                },
                "foundation_year": 1847,
                "owners": [
                    "änkefru Hulda Hammarberg"
                ]
            },
            {
                "name": "Hammarby Bakelit Industri AB.",
                "location": "Stockholm",
                "business": "Tillverkar pressade och sprutpressade konsthartsartiklar såsom campingartiklar, radiotillbehör, elektr. materiel, tubhattar, kammar, solglasögon m. m. Varumärke: »Habia»",
                "contact": {
                    "office": "Hammarby",
                    "phone": [
                        "440210"
                    ],
                    "postgiro": "190031"
                },
                "financials": {
                    "capital": "100,000 kr",
                    "employees": {
                        "industrial_workers": 90
                    },
                    "annual_turnover": "",
                    "annual_production_value": ""
                },
                "foundation_year": 1941,
                "board": [
                    {
                        "name": "dir. Carl Jacobson",
                        "role": "(ordf.)"
                    },
                    {
                        "name": "civiling. Carl-Herbert Jacobson",
                        "role": ""
                    },
                    {
                        "name": "bankdir. Richard Julin",
                        "role": ""
                    }
                ],
                "director": "C.-H. Jacobson"
            },
            {
                "name": "AB. Hammarbyverken, Stockholm",
                "location": "",
                "business": "Svetsnings- och mek. verkstäder samt varv med flytdockor. Bygger fartyg upp till 1,000 ton samt tillverkar helsvetsade och nitade artiklar såsom brobyggnader, balkar, högtrycksbehållare, cisterner, kokare och apparater för värmetekniska och industriella ändamål m. m.; utför fartygsreparationer samt reparerar medelst elektrisk och gassvetsning maskiner, ångpannor, axlar, fartygsdelar m. m. samt förslitna maskindelar och apparater av stål, järn, gjutjärn och metallegeringar.",
                "contact": {
                    "office": "Henriksdal, Stockholm",
                    "phone": [
                        "Hammarby verken, Stockholm"
                    ],
                    "postgiro": "4095"
                },
                "financials": {
                    "capital": "500,000 kr",
                    "employees": {
                        "industrial_workers": 221
                    },
                    "annual_turnover": "3,800,000 kr",
                    "annual_production_value": "3,800,000 kr"
                },
                "board": [
                    {
                        "name": "dir. Emanuel Högberg",
                        "role": "(ordf.)"
                    },
                    {
                        "name": "dir. Chr. Hansen",
                        "role": ""
                    }
                ],
                "director": "Gustav Ericson"
            },
            {
                "name": "Hammargren & C:o AB., Anneberg",
                "location": "",
                "business": "Pyroteknisk fabrik i Anneberg (Hallands l.). Tillverkar fyrverkeriartiklar, fotoblixtar, signalmateriel för militära ändamål och för järnvägar m. m., facklor och marschaller samt serpentiner.",
                "contact": {
                    "telegraph": "Hammargrens, Anneberg",
                    "phone": [
                        "Hammargren & Co."
                    ],
                    "postgiro": "25444"
                },
                "financials": {
                    "capital": "",
                    "employees": {},
                    "annual_turnover": "",
                    "annual_production_value": ""
                }
            }
        ]
    }
}