{
    "original": "Svenskt—Svensson\n\nAB. Svenskt Mjölksocker, Mjölby.\n\nTillverkar tekniskt och farmaceutiskt\nrent mjölksocker vid fabrik i Mjölby\n(östergötl* l.).\n\nTelefon: 831. Postgiro: 75250. — Antal\nindustriarb.: 15. Tillv.-värde pr år:\n750,000 kr. — Bolaget grundat 1944.\n\nStyrelse: dir. Einar Sjögren (ordf.),\ndir. Aage Borup-Jörgensen, dir. Carl\nUtterström.\n\nVerkst. dir.: A. Borup-Jörgensen.\n\nSvenskt Tenn AB., Stockholm.\n\nTillverkar möbler och textilier,\nnytto-och prydnadsföremål av tenn, mässing,\nsilver m. m. Bolaget driver jämväl\ndetaljhandel med egna och främmande fabrikat.\n\nKontor: Strandvägen 5 A. Telefon:\n600672. Postgiro: 51906.\n\nAkt.-kap.: 100,000 kr. Antal\nindustriarb.: 15. — Firman etabl. 1924, bolag\n1933.\n\nStyrelse o. verkst. dir.: fru Estrid\nEricson.\n\n*AB. Svenson &amp; Hagberg, Borås.\n\nSyfabrik. Tillverkar arbetskläder,\nskjortor och pyjamas, herr- och damrockar.\nVarumärke: »SH».\n\nTelegr.-adr.: Rolf, Borås. Telefon:\n10929 o. 11108. Postgiro: 14946. Repr. för\nStockholm: Ruben Cedervik, Lilla\nBjörknäs, Klinten, telefon: Skuru 210.\n\nAkt.-kap.: 200,000 kr. Antal\nindustriarb.: 49. — Firman etabl. 1877, bolaget\ngrundat 1925.\n\nStyrelse o. verkst. direktörer: disp.\nHenning Hägglund o. dir. Rolf Svenson.\n\nKamrer: Holger Hedelin.\n\n\"Svensson &amp; Hellberg, Tranås.\n\nSe Tranås Guldlistfabrik, Svensson &amp;\nHellberg, Tranås.\n\nSvenssons Portföljfabrik, Gnosjö.\n\nTillverkar portmonnäer och plånböcker\nsamt reklamartiklar m. m. i skinn vid\nfabrik i Gnosjö (Jönköp. l.).\n\nTelefon: 57. Postgiro: 72023. — Antal\nindustriarb.: 25. Tillv.-värde pr år:\n200,000 kr. — Firman etabl. 1910.\n\nÄgare o. chef: fabr. Einar Svensson.\n\nAB. Svensson &amp; Skoglund,\n\nKinna.\n\nTillverkar damunderkläder i silke och\nbomull vid fabrik i örby, Kinna (Älvsb.\n1.).\n\nTelefon: 48053. Postgiro: 94040. —\nAkt.-kap.: 125,000 kr. Antal\nindustri-arb.: 30. Tillv.-värde pr år: 400,000 kr.\n— Firman etabl. 1919, bolag 1940.\n\nVerkst. dir.: Anders Skoglund.\n\nSvenssons Stenhuggeri, AB.\nBröderna, Emmaboda.\n\nSe AB|. Bröderna Svenssons\nStenhuggeri, Emmaboda.\n\nSvensson, Tengblad &amp; Co.,\n\nGöteborg.\n\nFörädlingsindustri för papper och\nalu-miniumfolio. Tillverkar vaxpapper och\nfruktomslag med och utan tryck,\nhyll-oeh spispapper, dekorationspapper samt\nvaxduksimitation.\n\nKontor: Tingstad. Telegr.-adr.:\nVax-tryck, Göteborg. Telefon: 220811 o.\n221063. Postgiro: 12304.\n\nAntal industriarb.: 40. Tillv.-värde pr\når: 1,300,000 kr. — Firman etabl. 1921.\n\nÄgare o. chefer: dir. Carl Svensson o.\nfabr. Hugo Svensson.\n\nFörsäljn.-chef: C. Å. Willman.\n\n\"Svenssons Träförädling, Skara.\n\nTillverkar W.C.-sitsar av trä och\nbakelit.\n\nTelefon: 10463. Postgiro: 174870. —\nAntal industriarb.: 25. Tillv.-värde pr\når: 400,000 kr. — Firman etabl. 1930.\n\nÄgare: dir. E. K. Järnåker.\n\nDisp.: Roy Mossbrant.\n\n\"AB. A. Svensson &amp; Co., Malmö.\n\nTillverkar snörmakerier för möbler,\ngardiner och dekorationer av alla slag,\nsilkesupphängningar för elektrisk\narmatur, tätningslister av ullgarn för tätning\nav fönster och dörrar,\nkonfektionssnör-makerier för hatt-, möss-, kapp- och\npälsfabrikationen samt sadelgjordar och\nmarkislinor m. m.\n\nKontor: Husarg. 3. Telegr.-adr.:\nClau-dius, Malmö. Telefon: 20556. Postgiro:\n38107. Representanter: i Stockholm: Edv.\nA. Hansen, Västmannag. 14, telefon:\n111374; i Göteborg: Gottfr. Bergquist,\nNya Allén 3, telefon: 116214.\n\nAkt.-kap.: 338,200 kr. Antal\nindustriarb.: 75. — Firman etabl. 1884, bolag\n1932.\n\nStyrelse: fröken E. Hallberg, disp. J.\nF. Hallén, grossh. Ch. Hjelm-Bang.\n\nDisp.: J. F. Hallén.",
    "structured": {
        "0": {
            "name": "AB. Svenskt Mjölksocker",
            "location": "Mjölby",
            "business": "Tillverkar tekniskt och farmaceutiskt rent mjölksocker",
            "contact": {
                "office": "Fabrik i Mjölby (östergötland)",
                "phone": [
                    "831"
                ],
                "postgiro": "75250"
            },
            "financials": {
                "capital": "Ej tillgängligt",
                "employees": {
                    "industriarb.": 15
                },
                "annual_turnover": "750,000 kr",
                "annual_production_value": "750,000 kr"
            },
            "foundation_year": 1944,
            "board": [
                {
                    "name": "Einar Sjögren",
                    "role": "Ordförande"
                },
                {
                    "name": "Aage Borup-Jörgensen",
                    "role": "Styrelseledamot"
                },
                {
                    "name": "Carl Utterström",
                    "role": "Styrelseledamot"
                }
            ],
            "director": "Ej tillgängligt",
            "managing_director": "A. Borup-Jörgensen"
        },
        "1": {
            "name": "Svenskt Tenn AB.",
            "location": "Stockholm",
            "business": "Tillverkar möbler och textilier, nytto-och prydnadsföremål av tenn, mässing, silver m. m.",
            "contact": {
                "office": "Strandvägen 5 A",
                "phone": [
                    "600672"
                ],
                "postgiro": "51906"
            },
            "financials": {
                "capital": "100,000 kr",
                "employees": {
                    "industriarb.": 15
                }
            },
            "foundation_year": 1924,
            "current_name_year": 1933,
            "board": [
                {
                    "name": "fru Estrid Ericson",
                    "role": "Styrelseledamot och verkställande direktör"
                }
            ]
        },
        "2": {
            "name": "AB. Svenson & Hagberg",
            "location": "Borås",
            "business": "Syfabrik. Tillverkar arbetskläder, skjortor och pyjamas, herr- och damrockar",
            "contact": {
                "telegraph": "Rolf, Borås",
                "phone": [
                    "10929",
                    "11108"
                ],
                "postgiro": "14946",
                "sales_offices": [
                    {
                        "location": "Stockholm",
                        "phone": "Skuru 210"
                    }
                ]
            },
            "financials": {
                "capital": "200,000 kr",
                "employees": {
                    "industriarb.": 49
                }
            },
            "foundation_year": 1877,
            "corporation_year": 1925,
            "board": [
                {
                    "name": "disp. Henning Hägglund",
                    "role": "Disponent"
                },
                {
                    "name": "dir. Rolf Svenson",
                    "role": "Styrelseledamot och verkställande direktör"
                }
            ],
            "manager": "Holger Hedelin"
        },
        "3": {
            "name": "Svenssons Portföljfabrik",
            "location": "Gnosjö",
            "business": "Tillverkar portmonnäer och plånböcker samt reklamartiklar m. m. i skinn vid fabrik i Gnosjö (Jönköping län)",
            "contact": {
                "office": "Fabrik i Gnosjö (Jönköping län)",
                "phone": [
                    "57"
                ],
                "postgiro": "72023"
            },
            "financials": {
                "capital": "Ej tillgängligt",
                "employees": {
                    "industriarb.": 25
                },
                "annual_production_value": "200,000 kr"
            },
            "foundation_year": 1910,
            "owners": [
                "fabr. Einar Svensson"
            ],
            "manager": "fabr. Einar Svensson"
        },
        "4": {
            "name": "AB. Svensson & Skoglund",
            "location": "Kinna",
            "business": "Tillverkar damunderkläder i silke och bomull vid fabrik i Örby, Kinna (Älvsborgs län)",
            "contact": {
                "office": "Fabrik i Örby, Kinna (Älvsborgs län)",
                "phone": [
                    "48053"
                ],
                "postgiro": "94040"
            },
            "financials": {
                "capital": "125,000 kr",
                "employees": {
                    "industriarb.": 30
                },
                "annual_production_value": "400,000 kr"
            },
            "foundation_year": 1919,
            "corporation_year": 1940,
            "manager": "Anders Skoglund"
        },
        "5": {
            "name": "Svenssons Stenhuggeri, AB. Bröderna",
            "location": "Emmaboda",
            "business": "Se AB. Bröderna Svenssons Stenhuggeri, Emmaboda",
            "description": "Se AB. Bröderna Svenssons Stenhuggeri, Emmaboda"
        },
        "6": {
            "name": "Svensson, Tengblad & Co.",
            "location": "Göteborg",
            "business": "Förädlingsindustri för papper och aluminiumfolio. Tillverkar vaxpapper och fruktomslag med och utan tryck, hyll- oeh spispapper, dekorationspapper samt vaxduksimitation",
            "contact": {
                "office": "Tingstad",
                "phone": [
                    "220811",
                    "221063"
                ],
                "postgiro": "12304"
            },
            "financials": {
                "capital": "Ej tillgängligt",
                "employees": {
                    "industriarb.": 40
                },
                "annual_turnover": "1,300,000 kr"
            },
            "foundation_year": 1921,
            "owners": [
                "dir. Carl Svensson",
                "fabr. Hugo Svensson"
            ],
            "sales_manager": "C. Å. Willman"
        },
        "7": {
            "name": "Svenssons Träförädling",
            "location": "Skara",
            "business": "Tillverkar W.C.-sitsar av trä och bakelit",
            "contact": {
                "office": "Ej tillgängligt",
                "phone": [
                    "10463"
                ],
                "postgiro": "174870"
            },
            "financials": {
                "capital": "Ej tillgängligt",
                "employees": {
                    "industriarb.": 25
                },
                "annual_production_value": "400,000 kr"
            },
            "foundation_year": 1930,
            "manager": "dir. E. K. Järnåker",
            "sales_manager": "Roy Mossbrant"
        },
        "8": {
            "name": "AB. A. Svensson & Co.",
            "location": "Malmö",
            "business": "Tillverkar snörmakerier för möbler, gardiner och dekorationer av alla slag, silkesupphängningar för elektrisk armatur, tätningslister av ullgarn för tätning av fönster och dörrar, konfektionssnör-makerier för hatt-, möss-, kapp- och pälsfabrikationen samt sadelgjordar och markislinor m. m.",
            "contact": {
                "office": "Husarg. 3",
                "phone": [
                    "20556"
                ],
                "postgiro": "38107"
            },
            "financials": {
                "capital": "338,200 kr",
                "employees": {
                    "industriarb.": 75
                }
            },
            "foundation_year": 1884,
            "corporation_year": 1932,
            "board": [
                {
                    "name": "fröken E. Hallberg",
                    "role": "Styrelseledamot"
                },
                {
                    "name": "disp. J. F. Hallén",
                    "role": "Disponent"
                },
                {
                    "name": "grossh. Ch. Hjelm-Bang",
                    "role": "Styrelseledamot"
                }
            ],
            "director": "Ej tillgängligt",
            "sales_manager": "J. F. Hallén"
        }
    }
}