{
    "original": "Nässjö—Nä äs\n\n150,000 kr. Antal industriarb.: 20.\nTillv.-värde pr år: 250,000 kr. — Bolaget\ngrundat 1943.\n\nVerkst. dir.: ing. Sven-Gösta Stenberg.\n\n\"Nässjö Jästfabrik, Nässjö.\nSe Svenska Jästfabriks AB., Stockholm.\n\n\"AB. Nässjö Lådfabrik, Nässjö.\n\nTillverkar lådbräder och lådor samt\nhågade och hyvlade trävaror.\n\nTelegr.-adr.: Ply, Nässjö. Telefon: 999.\nPostgiro: 136906. — Akt.-kap.: 100,000\nfa. Antal industriarb.: 75. Tillv.-värde\npr år: 1,200,000 kr. — Bolaget grundat\n1923.\n\nStyrelse: dir. Olle A. Fritz (ordf.),\n»disp. Bertil Fritz, disp. Birger Fritz.\nVerkst. dir.: Birger Fritz.\n\n\"AB. Nässjö Möbelkompani, Nässjö.\n\nTillverkar möbler, speciellt bord.\nTelefon: 598 o. 798. Postgiro: 37039.\n\n—\tAkt.-kap.: 5,100 kr. Arb.-antal: 12.\nTillv.-värde pr år: 100,000 kr. —\nFirman etabl. 1919, bolag 1924.\n\nStyrelse: disp. Sixten Natrup (ordf.),\nfru Siv Fogelberg, fru Elsa Natrup,\nkontorist Sivert Natrup, fabr. Edvin\n.^Svensson.\n\nVerkst. disp.: Sixten Natrup.\n\n\"AB. Nässjö Stolfabrik, Nässjö.\n\nTillverkar stolar och möbler för\nmatsalar, kaféer, samlingslokaler, sjukhus etc.\n\nTelegr.-adr.: Stolfabrik, Nässjö.\nTelefon: 18 o. 293. Postgiro: 11595.\n\nAkt.-kap.: 100,000 kr. Antal\nindustriarb.: 235. Tillv.-värde pr år: 3,000,000 kr.\n\nFabriken grundlagd 1870, bolag 1906,\nnuv. bolag 1940.\n\nStyrelse: hovjägm. frih. W. Klingspor\n(ordf.), ing. John Martins, adv. Hugo\nStenbeck.\n\nVerkst. dir.: John Martins.\nKamrer: Folke Rydin.\n\nNässjö Tricotfabrik, Nässjö.\n\nTillverkar trikåunderkläder.\nVarumärke: »Wallo».\n\nTelegr.-adr.: Trieot, Nässjö. Telefon:\n510. Postgiro: 30201. — Antal\nindustriarb.- 30. Tillv.-värde pr år: 500,000 kr.\n\n—\tFirman etabl. 1920.\n\nÄgare o. chef: fabr. Gustaf Wahlin.\n\n\"AB. Nässjö Yaddfabriker, Nässjö.\n\nVaddfabriker i Nässjö och Bodafors\n(Jönköp. l.). Tillverkar vadd och flock.\nSpecialitet: fetvadd för sjukhus.\n\nTelegr.-adr.: Vaddfabriken, Nässjö.\nTelefon: 14. Postgiro: 7831.\n\nAkt.-kap.: 200,000 kr. Antal\nindustriarb.: 14. Tillv.-värde pr år: 550,000 kr.\n— Firman etabl. 1887, bolag 1905.\n\nStyrelse: dir. Olle Fritz (ordf.), disp.\nBertil Fritz, disp. Birger Fritz.\n\nVerkst. dir.: Birger Fritz.\n\n\"Nät-AB., Stockholm.\n\nBolaget är försäljningsorgan för\nför-zinkade järntrådnät tillverkade av\nGryt-göls Bruks AB., Grytgöl, Hjulsbro\nTråd-drageri &amp; Nätfabrik AB., Hjulsbro, och\nSvenska Stängselnäts AB., Malmö.\n\nKontor: Jakobsbergsg. 6. Telefon:\n210881. — Akt.-kap.: 10,000 kr. —\nBolaget grundat 1929.\n\nStyrelse o. verkst. dir.: Bengt\nEiser-man.\n\nKontorschef: Hjalmar Nettelbladt.\n\nNättraby Bruks AB., Nättraby.\n\nPappersbruk i Nättraby (Blekinge l.).\n\nTillverkar sulfit- och sulfatpapper,\ncellulosavadd, baby-blöjor, fönstervadd,\nmjölkvadd och trasselvadd, hushållsrullar,\npappersservietter och -näsdukar samt\ntoalettpapper.\n\nTelegr.-adr.: Nettrabruk, Nättraby.\nTelefon: 4. Postgiro: 168450.\n\nAkt.-kap.: 75,000 kr. Antal\nindustriarb.: 20. Årstillv.: 1,000 ton sulfitpapper\neller 700 ton cellulosavadd. — Bolaget\ngrundat 1940.\n\nStyrelse: dir. Sven Sandberg (ordf.),\nfru Aina Sandberg.\n\nVerkst. dir. o. disp.: Sven Sandberg.\n\n\"Nääs Fabriks AB., Tollered.\n\nBomullsspinneri, blekeri och färgeri vid\nTollered (Älvsb. l.). Tillverkar\nbomullsgarner och vigognegarner. Bolaget driver\njämväl sågverk, hyvleri, snickerifabrik\noch kvarn samt idkar jordbruk och\nskogshantering.\n\nPostadr.: Nääs fabrik, Tollered.\nTelegr.-adr.: Nääsfabrik, Göteborg. Telefon:\nAlingsås 453, Göteborg 174058 o. Tollered\n15, 16 o. 17. Postgiro: 13294.\n\nAkt.-kap.: 3,200,000 kr. Antal\nindustriarb.: 400. Tillv.-värde pr år: 5,000,000 kr.\n\nFabriken anlagd 1833, bolaget grundat\n1880. Bolaget äger Alingsås\nBomulls-väfveri AB., Alingsås, och AB. Nordens\nTextilfabrik, Borås.\n\nStyrelse: f. d. landshövd. Axel v.\nSnei-dern (ordf.), civiling. Gunnar Berg,\nryttm. Nils Berg, greve Gösta Bonde,\növerstelöjtn. Nils Ingvarsson.\n\nVerkst. dir.: Gunnar Berg.\n\nKontorschef: Per Gustafson.",
    "structured": {
        "1": {
            "name": "Nässjö Jästfabrik",
            "location": "Nässjö",
            "business": "Jästfabrik",
            "original_name": "Svenska Jästfabriks AB., Stockholm",
            "contact": {
                "telegraph": "Ply, Nässjö",
                "phone": [
                    "999"
                ],
                "postgiro": "136906"
            },
            "financials": {
                "capital": "100,000 kr",
                "employees": {
                    "industriarb": 75
                },
                "annual_turnover": "1,200,000 kr",
                "annual_production_value": "not available"
            },
            "foundation_year": 1923,
            "board": [
                {
                    "name": "Olle A. Fritz",
                    "role": "ordförande"
                },
                {
                    "name": "Bertil Fritz",
                    "role": "disp."
                },
                {
                    "name": "Birger Fritz",
                    "role": "disp."
                }
            ],
            "manager": "Birger Fritz"
        },
        "2": {
            "name": "Nässjö Lådfabrik",
            "location": "Nässjö",
            "business": "Lådfabrik",
            "products": "Tillverkar lådbräder och lådor samt hågade och hyvlade trävaror",
            "contact": {
                "telegraph": "not available",
                "phone": [
                    "not available"
                ],
                "postgiro": "136906"
            },
            "financials": {
                "capital": "100,000 kr",
                "employees": {
                    "industriarb": 20
                },
                "annual_turnover": "250,000 kr",
                "annual_production_value": "250,000 kr"
            },
            "foundation_year": 1943,
            "director": "ing. Sven-Gösta Stenberg"
        },
        "3": {
            "name": "Nässjö Möbelkompani",
            "location": "Nässjö",
            "business": "Möbelkompani",
            "products": "Tillverkar möbler, speciellt bord",
            "contact": {
                "phone": [
                    "598",
                    "798"
                ],
                "postgiro": "37039"
            },
            "financials": {
                "capital": "5,100 kr",
                "employees": {
                    "Arb.-antal": 12
                },
                "annual_turnover": "100,000 kr",
                "annual_production_value": "not available"
            },
            "foundation_year": 1924,
            "board": [
                {
                    "name": "Sixten Natrup",
                    "role": "ordförande"
                },
                {
                    "name": "fru Siv Fogelberg",
                    "role": "not available"
                },
                {
                    "name": "fru Elsa Natrup",
                    "role": "not available"
                },
                {
                    "name": "kontorist Sivert Natrup",
                    "role": "not available"
                },
                {
                    "name": "fabr. Edvin .^Svensson",
                    "role": "not available"
                }
            ],
            "manager": "Sixten Natrup"
        },
        "4": {
            "name": "Nässjö Stolfabrik",
            "location": "Nässjö",
            "business": "Stolfabrik",
            "products": "Tillverkar stolar och möbler för matsalar, kaféer, samlingslokaler, sjukhus etc.",
            "contact": {
                "telegraph": "Stolfabrik, Nässjö",
                "phone": [
                    "18",
                    "293"
                ],
                "postgiro": "11595"
            },
            "financials": {
                "capital": "100,000 kr",
                "employees": {
                    "industriarb": 235
                },
                "annual_turnover": "3,000,000 kr",
                "annual_production_value": "not available"
            },
            "foundation_year": 1940,
            "board": [
                {
                    "name": "hovjägm. frih. W. Klingspor",
                    "role": "ordförande"
                },
                {
                    "name": "ing. John Martins",
                    "role": "not available"
                },
                {
                    "name": "adv. Hugo Stenbeck",
                    "role": "not available"
                }
            ],
            "manager": "John Martins"
        },
        "5": {
            "name": "Nässjö Tricotfabrik",
            "location": "Nässjö",
            "business": "Tricotfabrik",
            "products": "Tillverkar trikåunderkläder",
            "contact": {
                "telegraph": "Trieot, Nässjö",
                "phone": [
                    "510"
                ],
                "postgiro": "30201"
            },
            "financials": {
                "capital": "not available",
                "employees": {
                    "industriarb": 30
                },
                "annual_turnover": "500,000 kr",
                "annual_production_value": "not available"
            },
            "foundation_year": 1920,
            "director": "fabr. Gustaf Wahlin"
        },
        "6": {
            "name": "Nässjö Vaddfabriker",
            "location": "Nässjö",
            "business": "Vaddfabriker",
            "products": "Tillverkar vadd och flock. Specialitet: fetvadd för sjukhus",
            "contact": {
                "telegraph": "Vaddfabriken, Nässjö",
                "phone": [
                    "14"
                ],
                "postgiro": "7831"
            },
            "financials": {
                "capital": "200,000 kr",
                "employees": {
                    "industriarb": 14
                },
                "annual_turnover": "550,000 kr",
                "annual_production_value": "not available"
            },
            "foundation_year": 1905,
            "board": [
                {
                    "name": "Olle Fritz",
                    "role": "ordförande"
                },
                {
                    "name": "Bertil Fritz",
                    "role": "disp."
                },
                {
                    "name": "Birger Fritz",
                    "role": "disp."
                }
            ],
            "manager": "Birger Fritz"
        },
        "7": {
            "name": "Nät-AB.",
            "location": "Stockholm",
            "business": "Försäljningsorgan för för-zinkade järntrådnät",
            "contact": {
                "telegraph": "not available",
                "phone": [
                    "210881"
                ],
                "postgiro": "not available"
            },
            "financials": {
                "capital": "10,000 kr",
                "employees": {
                    "not available": 0
                },
                "annual_turnover": "not available",
                "annual_production_value": "not available"
            },
            "foundation_year": 1929,
            "manager": "Bengt Eiserman",
            "board": [
                {
                    "name": "Bengt Eiserman",
                    "role": "not available"
                }
            ],
            "director": "not available"
        },
        "8": {
            "name": "Nättraby Bruks AB.",
            "location": "Nättraby",
            "business": "Pappersbruk",
            "products": "Tillverkar sulfit- och sulfatpapper, cellulosavadd, baby-blöjor, fönstervadd, mjölkvadd etc.",
            "contact": {
                "telegraph": "Nettrabruk, Nättraby",
                "phone": [
                    "4"
                ],
                "postgiro": "168450"
            },
            "financials": {
                "capital": "75,000 kr",
                "employees": {
                    "industriarb": 20
                },
                "annual_turnover": "not available",
                "annual_production_value": "not available"
            },
            "foundation_year": 1940,
            "board": [
                {
                    "name": "Sven Sandberg",
                    "role": "ordförande"
                },
                {
                    "name": "Aina Sandberg",
                    "role": "not available"
                }
            ],
            "manager": "Sven Sandberg"
        },
        "9": {
            "name": "Nääs Fabriks AB.",
            "location": "Tollered",
            "business": "Bomullsspinneri, blekeri och färgeri",
            "products": "Tillverkar bomullsgarner och vigognegarner. Driver också sågverk, hyvleri, snickerifabrik och kvarn samt bedriver jordbruk och skogshantering",
            "contact": {
                "telegraph": "Nääsfabrik, Göteborg",
                "phone": [
                    "Alingsås 453",
                    "Göteborg 174058",
                    "Tollered 15, 16, 17"
                ],
                "postgiro": "13294"
            },
            "financials": {
                "capital": "3,200,000 kr",
                "employees": {
                    "industriarb": 400
                },
                "annual_turnover": "5,000,000 kr",
                "annual_production_value": "not available"
            },
            "foundation_year": 1880,
            "board": [
                {
                    "name": "Axel v. Sneidern",
                    "role": "ordförande"
                },
                {
                    "name": "Gunnar Berg",
                    "role": "not available"
                },
                {
                    "name": "Nils Berg",
                    "role": "not available"
                },
                {
                    "name": "Gösta Bonde",
                    "role": "not available"
                },
                {
                    "name": "Nils Ingvarsson",
                    "role": "not available"
                }
            ],
            "manager": "Gunnar Berg"
        }
    }
}