{
    "original": "S ågmyra—Säng fabriken\n\nlefon: 65 o. 565. Postgiro: 8619.\n\nAkt.-kap.: 300,000 kr. Antal\nindustriarb.: 60. Tillv.-värde pr år: 1,100,000 kr.\n\n—\tBolaget grundat 1898.\n\nStyrelse: disp. Einar Wibell (ordf.),\ning. K. R. Hulin, fru Ester Wibell.\nVerkst. dir. o. disp.: Einar Wibell.\nVerkstadschef: K. R. Hulin.\n\n*Sågmyra Yllefabrik, Sågmyra.\nSe Falu Yllefabriks AB., Sågmyra.\n\nAB. Säffle Gjuteri &amp; Mek.\nVerkstad, Säffle.\n\nGrovplåtslageri, gjuteri och mek.\nverkstad i Säffle (Värml. l.). Tillverkar\ncentrifugalpumpar för massa,\nlokvatten-kastare, metall- och tackjärnsgjutgods.\n\nTelegr.-adr.: Verkstaden, Säffle.\nTelefon: 31 o. 431. Postgiro: 81589.\n\nAkt.-kap.: 220,000 kr. Antal\nindustriarb.: 86. Tillv.-värde pr år: 900,000 kr.\n\n—\tBolaget grundat 1916.\n\nStyrelse: disp. Chr. Storjohann (ordf.),\ngrossh. C. Börjeson, disp. K. Gunnar\nLarsson, kamrer Gösta Larsson, övering.\nB. Pedersen.\n\nDisp.: K. Gunnar Lärsson.\nKamrer: Gösta Larsson.\nKassör: Georg Brodelius.\nVerkstadsing.: Per Lindberg.\n\nSäffle.\n\n*AB. Seffle Motorverkstad, Bröderna\nBruce, Säffle.\n\nMotorfabrik i Säffle (Värml. l.).\nTillverkar marina och stationära\nråoljemotorer (märke: »Seffle») samt\nmotorvinschar.\n\nTelegr.-adr.: Brucemotor, Säffle.\nTelefon: 110. Postgiro: 25733.\n\nAkt.-kap.: 650,000 kr. Antal\nindustriarb.: 125. Tillv.-värde pr år: 1,475,000 kr.\n\n—\tFirman etabl. 1908, bolag 1943.\nStyrelse o. verkst. direktörer: fabr.\n\nCarl L. Bruce o. fabr. J. Bernhard Bruce.\n\nSäffle.\n\n*AB. Seffle Möbelfabrik, Säffle.\n\nTillverkar möbler vid fabrik i Säffle\n(Värml. l.).\n\nTelefon: 127 o. 407. Postgiro: 131900.\nAkt.-kap.: 200,000 kr. Antal\nindustriarb.: 65. Tillv.-värde pr år: 750,000 kr.\n\n—\tBolaget grundat 1909.\n\nStyrelse: maskinsnickare Einar\nAndersson, polerare Erik Jansson, disp. Otto\nKarlsson.\n\nVerkst. dir.: Otto Karlsson.\n\nSäfsjö, se Sävsjö.\n\nSäfsjöström, se Sävsjöström.\n\n*Säfveåns AB., Göteborg.\n\nSågverk, hyvleri och lådfabrik vid\nSäve-näs i Göteborg. Tillverkar lådbräder och\npacklådor (märke: »Torroba»).\n\nKontor: Göteborg. Telefon: Göteborg\n170530. Postgiro: 41080.\n\nAkt.-kap.: 900,000 kr. Antal\nindustriarb.: 150. Årstillv.: 6,000 stds lådbräder.\n— Firman etabl. 1874.\n\nStyrelse: disp. Ivar Wendt (ordf.),\nbankdir. Ebbe Lundberg, adv. Torsten\nSetterberg.\n\nVerkst. dir.: disp. E. Christiansen.\n\nKamrer: E. Stiernfeldt.\n\n*Säiboda AB., Ottebol.\n\nSe Billeruds AB., Säffle.\n\nAB. Sängfabriken, Stockholm.\n\nJärnsängsfabrik, snickerifabrik och\ntapetserareverkstad i örbyhus (Uppsala\n1.). Tillverkar trä- och järnsängar,\nstål-rörsmöbler och sängkläder. Specialitet:\nsjukhussängar.\n\nHuvudkontor: Stockholm, Norrlandsg.\n16. Telegr.-adr.: Sängfabriken, Stockholm.\nTelefon: 101295. Postgiro: 1651.\nFabriks-kontor: örbyhus.\n\nAkt.-kap.: 325,000 kr. Antal\nindustriarb.: 200. Tillv.-värde pr år: 2,360,000 kr.\n\nFirman etabl. 1899, bolag 1926 under\nnamn AB. Stockholms Nya\nJärnsängsfabrik, namnändring 1934. Fabriken i\nörbyhus drives av dotterbolaget\nSmides-&amp; Järnsängsfabriks AB., örbyhus. (Se\ndetta bolag.)\n\nStyrelse: adv. Clas Östberg (ordf.),\ndir. Eric Ericsson, dir. Tore Ericsson.\n\nVerkst. dir.: Tore Ericsson.\n\nAB. Sängfabriken Princess,\n\nStockholm.\n\nJärnsängsfabrik i Bernshammar\n(Västmanl. l.). Tillverkar järnsängar,\nstålotto-maner, hopfällbara järnsängar,\nmanskapssängar (s. k. etagesängar) samt\npiskställningar och oljefatslyftare. Specialitet:\ntvärspända bandstålsbottnar med\ngnisselfria metallhakar. Varumärke:\n»Princess».\n\nKontor: Stockholm, Skeppsbron 36.\nTelegr.-adr.: Iron, Stockholm. Telefon:\n209317—18. Postgiro: 130252.\nFabrikskontor: Bernshammar. Telefon:\nSkinnskatteberg 3319.",
    "structured": {
        "1": {
            "name": "Sågmyra—Säng fabriken",
            "location": "Sågmyra",
            "financials": {
                "capital": "300,000 kr",
                "employees": {
                    "industriarb": 60
                },
                "annual_turnover": "1,100,000 kr",
                "annual_production_value": "1,100,000 kr"
            },
            "foundation_year": 1898,
            "board": [
                {
                    "name": "Einar Wibell",
                    "role": "disp."
                },
                {
                    "name": "K. R. Hulin",
                    "role": "ing."
                },
                {
                    "name": "Ester Wibell",
                    "role": "fru"
                }
            ],
            "director": "Einar Wibell",
            "managing_director": "Einar Wibell",
            "contact": {
                "phone": [
                    "65",
                    "565"
                ],
                "postgiro": "8619"
            }
        },
        "2": {
            "name": "AB. Säffle Gjuteri & Mek.",
            "location": "Säffle",
            "products": "Grovplåtslageri, gjuteri och mek. verkstad",
            "financials": {
                "capital": "220,000 kr",
                "employees": {
                    "industriarb": 86
                },
                "annual_turnover": "900,000 kr",
                "annual_production_value": "900,000 kr"
            },
            "foundation_year": 1916,
            "board": [
                {
                    "name": "Chr. Storjohann",
                    "role": "disp."
                },
                {
                    "name": "C. Börjeson",
                    "role": "grossh."
                },
                {
                    "name": "K. Gunnar Larsson",
                    "role": "disp."
                },
                {
                    "name": "Gösta Larsson",
                    "role": "kamrer"
                },
                {
                    "name": "B. Pedersen",
                    "role": "övering."
                }
            ],
            "director": "K. Gunnar Lärsson",
            "contact": {
                "phone": [
                    "31",
                    "431"
                ],
                "postgiro": "81589"
            }
        },
        "3": {
            "name": "AB. Seffle Motorverkstad, Bröderna Bruce",
            "location": "Säffle",
            "products": "Motorfabrik",
            "financials": {
                "capital": "650,000 kr",
                "employees": {
                    "industriarb": 125
                },
                "annual_turnover": "1,475,000 kr",
                "annual_production_value": "1,475,000 kr"
            },
            "foundation_year": 1908,
            "corporation_year": 1943,
            "board": [
                {
                    "name": "Carl L. Bruce",
                    "role": "fabr."
                },
                {
                    "name": "J. Bernhard Bruce",
                    "role": "fabr."
                }
            ],
            "director": "Carl L. Bruce",
            "contact": {
                "phone": "110",
                "postgiro": "25733"
            }
        },
        "4": {
            "name": "AB. Seffle Möbelfabrik",
            "location": "Säffle",
            "products": "Tillverkar möbler",
            "financials": {
                "capital": "200,000 kr",
                "employees": {
                    "industriarb": 65
                },
                "annual_turnover": "750,000 kr",
                "annual_production_value": "750,000 kr"
            },
            "foundation_year": 1909,
            "board": [
                {
                    "name": "Einar Andersson",
                    "role": "maskinsnickare"
                },
                {
                    "name": "Erik Jansson",
                    "role": "polerare"
                },
                {
                    "name": "Otto Karlsson",
                    "role": "disp."
                }
            ],
            "director": "Otto Karlsson",
            "contact": {
                "phone": [
                    "127",
                    "407"
                ],
                "postgiro": "131900"
            }
        },
        "5": {
            "name": "AB. Sängfabriken, Stockholm",
            "location": "örbyhus",
            "business": "Järnsängsfabrik, snickerifabrik och tapetserareverkstad",
            "products": "Tillverkar trä- och järnsängar, stål-rörsmöbler och sängkläder",
            "financials": {
                "capital": "325,000 kr",
                "employees": {
                    "industriarb": 200
                },
                "annual_turnover": "2,360,000 kr"
            },
            "foundation_year": 1899,
            "corporation_year": 1926,
            "current_name_year": 1934,
            "board": [
                {
                    "name": "Clas Östberg",
                    "role": "adv."
                },
                {
                    "name": "Eric Ericsson",
                    "role": "dir."
                },
                {
                    "name": "Tore Ericsson",
                    "role": "dir."
                }
            ],
            "director": "Tore Ericsson",
            "contact": {
                "phone": "101295",
                "postgiro": "1651"
            }
        },
        "6": {
            "name": "AB. Sängfabriken Princess, Stockholm",
            "location": "Bernshammar",
            "business": "Järnsängsfabrik",
            "products": "Tillverkar järnsängar, stålotto-maner, hopfällbara järnsängar",
            "financials": {
                "capital": "not available",
                "employees": {
                    "industriarb": 150
                }
            },
            "foundation_year": 1908,
            "board": [],
            "contact": {
                "phone": [
                    "209317",
                    "18"
                ],
                "postgiro": "130252"
            }
        }
    }
}