{
    "original": "Sandviken—S: t Erik\n\n*Sandvlkens Jernverks AB.,\n\nSandviken.\n\nJ ärnverk med masugnar, bessemer-,\nmartin- och elektrostålverk, varm- och\nkallvalsverk, smedjor, tråddrageri,\nsågbladsfabrik m. m. i Sandviken (Gävleb. l.).\nBolaget äger andelar i flera svenska\ngruvfält samt i vattenkraftanläggningar.\n\nTillverkar specialstål, såsom\nkonstruktionsstål för automobiler och\nflygmaskiner, verktygsstål, kallvalsat bandstål,\nsåväl härdat som ohärdat, även i profilerat\nutförande, sömlösa rör enligt svensk\nstandard SMS, såsom ångpannetuber,\nvärmeledningstuber samt gängade rör för gas,\nvatten och ånga, vidare rör för diverse\nspecialändamål, exempelvis kullagerrör,\nbakugnsrör, rostfria rör m. m., silverstål,\ndrivfjädrar, dragen tråd, hårdmetall och\nhårdmetallverktyg, sågar och sågblad,\nmaskinknivar och maskinhyvelstål,\nsten-och smidesredskap,\nstålbandstransportö-rer etc.\n\nTelegr.-adr.: Jern verket, Sandviken.\nTelefon: »Sandvikens Järnverk».\nPostgiro: 6714.\n\nRepresentanter: Sandviksstål\nStockholm AB., Stockholm, John Ericssonsg.\n10, telefon: 520080; AB. Sandviksstål,\nGöteborg, Norra Hamngatan 36, telefon:\n172610; Sandvikstål Malmö AB., Malmö,\nEngelbrektsg. 12, telefon: 72330;\nSandvikstål Jönköping AB., telefon: 6520;\nSandvikslagret i Sundsvall AB.,\nSundsvall, Storg. 30, telefon: 55410; Elis\nKarlson, Bruksg. 8, Eskilstuna, telefon: 31900\no. 31956.\n\nAkt.-kap.: 35,000,000 kr. Antal\nindustriarb.: 4,700.\n\nAnläggningsår 1862, bolag 1868.\nStyrelse: bruksdisp. K. F. Göransson\n(ordf.), disp. Erik W. Forsberg, dir.\nGunnar Magnuson, dir. Viktor Magnusson,\ndir. Erik G. Pehrsson, bankdir. Gustaf\nSöderlund, fd. statssekr. Tage Wärn.\nVerkst. dir. o. disp.: K. F. Göransson.\nTehn. chef: dir. Erik W. Forsberg.\nFörsäljn.-chef: dir. Viktor Magnusson.\nPr ad.-chef: dir. Carl Sebardt.\nAvd.-chef er vid försäljn. -av delningarna:\nutomskand. stålf örsäl jningsavd.:\nintendent R. Schultz:\n\nskand. stålförsäljningsavd.: intendent\nJoel D. E. Larsson;\n\nman ufakturf örsäl jningsavd.: intendent\nNils H. Eheström;\n\ntransportörf örsäljningsavd.: ing.\nDavid Söder;\n\nAvd.-chef er vid verkstäderna:\növeringenjör: Govert Helmer;\nallm. tekn. problem: bergsing. Per\nCarlberg ;\n\ndriftstekn. forskning: civiling. C. G.\nHård af Segerstad;\n\nlaboratoriet: bergsing. Gunnar Thalén;\nmetallurgiska avd.: ing. Torsten\nWahlberg;\n\nvarm vals verken: bergsing. Teofil\nLindblom;\n\nkallvalsverket: ing. Gösta Bleckert;\ntrådavd.: ing. Carl-Olof v. H of sten;\nhärdningen: civiling. Erik H.\nDider-holm;\n\nhårdmetallavd.: ing. Wilhelm Haglund;\nleveranskontrollen: mg. Walter Rössler;\nmanufakturen: ing. Olof Backman;\nmek. verkstadsavd.: ing. F.\nWenner-blom;\n\nkonstruktionsavd.: ing. H. Spärr.\növriga avd.-chef er:\nreklamavd.: ing. E. Langbert;\ninformationsavd.: sekr. Gotthard\nKarlström.\n\ndirektionens sekretariat: sekr. R. Bolie;\npersonalsekretariatet: kamrer Bengt\nBrändström;\n\narbetsbyrån: ing.^K. H. Stenhane;\nbyggnadsavd.: civiling. Y. Terenius;\nel.-avd.: civiling. C. Fr. Peterson;\nvärmetekn. avd.: civiling. Torsten\nWendt.\n\n(Jfr annons nr 61.)\n\nSandvikens Metallvarufabrik,\nWilliam Lööf, Sandviken.\n\nTillverkar spinnspön,\ninredningsdetaljer för butiksmontrar, hushållsartiklar av\nrostfritt stål, instrument och utensilier\nför tandläkare samt snöskrapor (märke:\n»Bennie») vid fabrik i Sandviken\n(Gävleb. l.).\n\nPostadr.: Box 1713, Sandviken.\nTelefon: 3574. Postgiro: 174680. —\nArb.-antal: 7, varav 5 hemarb. Tillv.-värde pr\når: 12,000 kr. — Firman etabl. 1941.\nÄgare och chef: fabr. William Lööf.\n\nSandvikens Sågverks AB., Dynas.\nSe Sandvikens Cellulosa AB., Dynäs.\n\n\"Sandö Sågverks AB., Sprängsviken.\nSe Strömnäs AB., Kramfors.\n\n*S:t Erik, Konfektions AB.,\n\nStockholm.\n\nSe Konfektions AB. S:t Erik,\nStockholm.\n\n468*",
    "structured": {
        "1": {
            "name": "Sandvikens Jernverks AB.",
            "location": "Sandviken (Gävleb. l.)",
            "business": "Järnverk med masugnar, bessemer-, martin- och elektrostålverk, varm- och kallvalsverk, smedjor, tråddrageri, sågbladsfabrik m. m.",
            "products": "Specialstål, konstruktionsstål för automobiler och flygmaskiner, verktygsstål, kallvalsat bandstål, ohärdat och profilerat, sömlösa rör enligt svensk standard SMS, ångpannetuber, värmeledningstuber, gängade rör för gas, vatten och ånga, rör för specialändamål, silverstål, drivfjädrar, dragen tråd, hårdmetall och hårdmetallverktyg, sågar och sågblad, maskinknivar och maskinhyvelstål, sten- och smidesredskap, stålbandstransportörer m.m.",
            "contact": {
                "office": "Jernverket, Sandviken",
                "phone": [
                    "Sandvikens Järnverk"
                ],
                "postgiro": "6714",
                "head_office": "(head office address)",
                "sales_offices": [
                    {
                        "location": "Stockholm",
                        "phone": "520080"
                    },
                    {
                        "location": "Göteborg",
                        "phone": "172610"
                    },
                    {
                        "location": "Malmö",
                        "phone": "72330"
                    },
                    {
                        "location": "Jönköping",
                        "phone": "6520"
                    },
                    {
                        "location": "Sundsvall",
                        "phone": "55410"
                    },
                    {
                        "location": "Eskilstuna",
                        "phone": "31900"
                    }
                ],
                "telegraph": "Jernverket, Sandviken",
                "factory_office": "(factory office address)",
                "factory_phone": "(factory phone number)"
            },
            "financials": {
                "capital": "35,000,000 kr",
                "employees": {
                    "industriarb": 4700
                },
                "foundation_year": 1862,
                "corporation_year": 1868
            },
            "board": [
                {
                    "name": "K. F. Göransson",
                    "role": "bruksdisp."
                },
                {
                    "name": "Erik W. Forsberg",
                    "role": "disp."
                },
                {
                    "name": "Gunnar Magnuson",
                    "role": "dir."
                },
                {
                    "name": "Viktor Magnusson",
                    "role": "dir."
                },
                {
                    "name": "Erik G. Pehrsson",
                    "role": "dir."
                },
                {
                    "name": "Gustaf Söderlund",
                    "role": "bankdir."
                },
                {
                    "name": "Tage Wärn",
                    "role": "fd. statssekr."
                }
            ],
            "director": "K. F. Göransson",
            "managing_director": "K. F. Göransson",
            "sales_manager": "Viktor Magnusson"
        },
        "2": {
            "name": "Sandvikens Metallvarufabrik",
            "location": "Sandviken (Gävleb. l.)",
            "products": "Spinnspön, inredningsdetaljer för butiksmontrar, hushållsartiklar av rostfritt stål, instrument och utensilier för tandläkare, snöskrapor (märke: »Bennie»)",
            "contact": {
                "office": "Box 1713, Sandviken",
                "phone": [
                    "3574"
                ],
                "postgiro": "174680"
            },
            "financials": {
                "employees": 7,
                "annual_production_value": "12,000 kr",
                "foundation_year": 1941
            },
            "owners": [
                "William Lööf"
            ]
        },
        "3": {
            "name": "S:t Erik, Konfektions AB.",
            "location": "Stockholm"
        }
    }
}