{
    "original": "Hälsingborg—Hälsingland\n\nHälsingborgs Sidenindustri och\nFabriken Konstblommor,\n\nHälsingborg.\n\nTillverkar konstgjorda blommor,\nfrukter och bär samt dekorationer och\njulartiklar.\n\nTelefon: 17139. Postgiro: 134571,—\nAntal industriarb.: 40. Tillv.-värde pr år:\n275,000 kr. — Firman etabl. 1941.\n\nÄgare o. chefer: fabr. Gustav Wettin\no. fru Agnes Wettin.\n\n\"Hälsingborgs Spikfabriks AB.,\n\nBarnlösa.\n\nTråddrageri och spikfabrik i Ramlösa\n(Malmöh. l.). Tillverkar trådspik och\ntrådstift samt krampor. Specialiteter:\nprecisionsspik och -stift, maskinspik,\n»Z»-spik, tapetserarstift samt tof\nfelkramp or.\n\nTelegr.-adr.: Spikfabriken, Ramlösa.\nTelefon: Hälsingborg 96250. Postgiro:\n13950.\n\nAkt.-kap.: 108,000 kr. Antal\nindustriarb.: 20. Tillv.-värde pr år: 600,000 kr.\n— Firman etabl. 1886, bolag 1905.\n\nStyrelse: disp. Chr. Rasch (ordf.),\nmajor C. G:son Follin, fru E. Rasch,\nverk-mäst. Henry Rasch, fabr. Nils Rasch.\n\nVerkst. dir.: Chr. Rasch.\n\nFabrikschef: Nils Rasch.\n\nHälsingborg.\n\n\"Helsingborgs Varfs AB.,\n\nHälsingborg.\n\nSkeppsvarv med mek. verkstad, gjuteri\noch snickerifabrik samt torrdockor.\n\nUtför nybyggnader av järnfartyg samt\nreparationer av järn- och träfartyg.\nTillverkar ångmaskiner och ångpannor samt\nsom specialitet däcksmaskiner såsom\nstyrmaskiner, vinschar, ankar- och\nförhal-ningsspel såväl för ånga som elektrisk\ndrift. Utför reparationer samt\nnytill-verkningar medelst elektrisk svetsning\nsåsom helsvetsade kokare, tryckkärl och\nångpannor.\n\nTelegr.-adr.: Warfsbolaget,\nHälsingborg. Telefon: »Varvet». Postgiro: 137114.\n\nAkt.-kap.: 977,200 kr. Antal\nindustriarb.: 800. Tillv.-värde pr år: 8,000,000 kr.\n\nVarvet grundlagt 1866, bolaget grundat\n1871, sammanslaget 1923 med\nHelsingborgs Elektriska Svetsnings AB., nuv.\nnamn 1932.\n\nStyrelse: v. konsul Otto H. Hillerström\n(ordf.), skeppsred. S. J. Redig (v. ordf.),\nskeppsred. J. Fänge, skeppsred. M. Jonas-\n\nson, skeppsred. Hans J. Lundgren, dir.\nBernh. J. Nordström, dir. Thor Thorsson.\n\nVerkst. dir.: Thor Thorsson.\n\nV. verkst. dir.: Otto H. Hillerström.\n\n(Jfr annons nr 82.)\n\nHälsingborg.\n\n\"Helsingborgs Angqvarns AB.,\n\nHälsingborg.\n\nTillverkar mjöl av vete och råg samt kli.\nVarunamn för vetemjöl: »Kungsörnen»\nm. fl.\n\nHuvudkontor: Malmö. Kvarnkontor:\nHälsingborg. Telegr.-adr.: Valskvarnen,\nHälsingborg. Telefon: 10189. Postgiro:\n14488.\n\nAkt.-kap.: 1,200,000 kr. Antal\nindustriarb.: 40. Prod.-värde pr år: 5,275,000 kr.\n\nBolaget, grundat 1885, tillhör AB.\nKvarnintressenter, Malmö.\n\nStyrelse: dir. Mauritz Carlson (ordf.),\ndir. Sven Malmberg, dir. Edvin Åberg.\n\nVerkst. dir.: S. Malmberg.\n\nPlatschef: disp. Erik Hansson.\n\nHälsingborg.\n\nAB. Helsingborgs Angtegelbruk,\n\nHälsingborg.\n\nTillverkar fasadtegel, syrafast tegel,\nskorstenstegel, olika slags klinker,\ntrottoarplattor m. m.\n\nTelegr.-adr.: Ångtegelbruket,\nHälsingborg. Telefon: 10546.\n\nAkt.-kap.: 150,000 kr. Antal\nindustriarb.: 125. Årstillv.: 30,000 ton\ntegelvaror. — Tegelbruket anlagt 1873, nuv.\nbolag grundat 1880.\n\nStyrelse: övering. Edward Schön\n(ordf.), avd. J. P. Möller, fru S. Peyron.\n\nVerkst. dir.: vakant.\n\nHälsinglands Linodlareförening\nu. p. a., Hybo.\n\nLinberedningsverk i Hybo (Gävleb. l.).\nTillverkar lintåga och linblånor.\n\nKontor: Hybo. Telefon: Ljusdal 3045.\nPostgiro: 178185. — Antal industriarb.:\n70. Tillv.-värde pr år: 750,000 kr. —\nFöreningen bildad 1941.\n\nDisp.: Erik Larsson.\n\nSkäktmäst.: Oscar Lyer.\n\nHälsinglands Repslagerl, Verner\nLlndwall, Jättendal.\n\nRepslageri och linhäckleri i Jättendal\n(Gävleb. l.). Tillverkar häcklat lin och\nlinkabelgarn, packningsgarn, nät- och\nsköttelnar, laxgarn, tågvirke, tömmar,",
    "structured": {
        "1": {
            "name": "Hälsingborgs Sidenindustri och Fabriken Konstblommor",
            "location": "Hälsingborg",
            "business": "Tillverkar konstgjorda blommor, frukter och bär samt dekorationer och julartiklar.",
            "contact": {
                "phone": [
                    "17139"
                ],
                "postgiro": "134571"
            },
            "financials": {
                "capital": "Unknown",
                "employees": {
                    "industriarb": 40
                },
                "annual_turnover": "275,000 kr",
                "annual_production_value": "Unknown"
            },
            "foundation_year": 1941,
            "owners": [
                "fabr. Gustav Wettin o. fru Agnes Wettin"
            ]
        },
        "2": {
            "name": "Hälsingborgs Spikfabriks AB.",
            "location": "Hälsingborg",
            "business": "Tillverkar trådspik och trådstift samt krampor.",
            "contact": {
                "phone": "Hälsingborg 96250",
                "postgiro": "13950"
            },
            "financials": {
                "capital": "108,000 kr",
                "employees": {
                    "industriarb": 20
                },
                "annual_turnover": "600,000 kr",
                "annual_production_value": "Unknown"
            },
            "foundation_year": 1886,
            "corporation_year": 1905,
            "board": [
                {
                    "name": "Chr. Rasch",
                    "role": "disp."
                },
                {
                    "name": "C. G:son Follin",
                    "role": "major"
                },
                {
                    "name": "E. Rasch",
                    "role": "fru"
                },
                {
                    "name": "Henry Rasch",
                    "role": "verk-mäst."
                },
                {
                    "name": "Nils Rasch",
                    "role": "fabr."
                }
            ],
            "director": "Chr. Rasch",
            "managing_director": "Nils Rasch"
        },
        "3": {
            "name": "Helsingborgs Varfs AB.",
            "location": "Hälsingborg",
            "business": "Skeppsvarv med mek. verkstad, gjuteri och snickerifabrik samt torrdockor.",
            "contact": {
                "phone": "Postgiro: 137114"
            },
            "financials": {
                "capital": "977,200 kr",
                "employees": {
                    "industriarb": 800
                },
                "annual_turnover": "8,000,000 kr",
                "annual_production_value": "Unknown"
            },
            "foundation_year": 1866,
            "corporation_year": 1871
        },
        "4": {
            "name": "Helsingborgs Angqvarns AB.",
            "location": "Hälsingborg",
            "business": "Tillverkar mjöl av vete och råg samt kli.",
            "contact": {
                "phone": "10189",
                "postgiro": "14488"
            },
            "financials": {
                "capital": "1,200,000 kr",
                "employees": {
                    "industriarb": 40
                },
                "annual_turnover": "5,275,000 kr",
                "annual_production_value": "Unknown"
            },
            "foundation_year": 1885
        },
        "5": {
            "name": "AB. Helsingborgs Angtegelbruk",
            "location": "Hälsingborg",
            "business": "Tillverkar fasadtegel, syrafast tegel, skorstenstegel, olika slags klinker, trottoarplattor m. m.",
            "contact": {
                "phone": "10546"
            },
            "financials": {
                "capital": "150,000 kr",
                "employees": {
                    "industriarb": 125
                },
                "annual_production_value": "30,000 ton tegelvaror"
            },
            "foundation_year": 1873,
            "corporation_year": 1880
        },
        "6": {
            "name": "Hälsinglands Linodlareförening u. p. a.",
            "location": "Hybo",
            "business": "Tillverkar lintåga och linblånor.",
            "contact": {
                "phone": "Ljusdal 3045",
                "postgiro": "178185"
            },
            "financials": {
                "employees": {
                    "industriarb": 70
                },
                "annual_turnover": "750,000 kr",
                "annual_production_value": "Unknown"
            },
            "foundation_year": 1941
        },
        "7": {
            "name": "Hälsinglands Repslagerl, Verner Llndwall",
            "location": "Jättendal",
            "business": "Tillverkar häcklat lin och linkabelgarn, packningsgarn, nät- och sköttelnar, laxgarn, tågvirke, tömmar",
            "contact": {
                "phone": "Unknown"
            }
        }
    }
}