{
    "original": "Stockholm\n\nAvd.-chefer: • försäljli.-avd. -;■ dir. Ivan\nNordgren; fastighetsavd.: kapten T»\nStenport ; redovisningsavd.: kamrer O. Dunér;\nbilavd.: dir. R. Steenhoff; forskningsavd.:\nfil. dr H. Lundin.\n\nStockholms Båtbyggerl AB.,\n\nSaltsjöbaden.\t,\n\nSe AB. Neglingevarvet, Saltsjöbaden.\n\nStockholms Fjäderfabrik, B. Wahl,\n\nStockholm.\n\nMek. verkstad. Tillverkar spiralfjädrar.\n\nKontor: Tuleg. 15. Telegr.-adr.:\nFjä-derwal, Stockholm. Telef op: 324850.\nPostgiro: 528Ö9.. — Antal industriarb.: 18. —\nFirman etabl. 1915.\n\nÄgare o. chef: fabr. B. Wahl.\n\n\"Stockholms Calvaniseringsfabrik\n\nAB., Liljeholmen.\n\nTillverkar varmgalvaniserad plåt, slät,\nkorrugerad och s. k. pannplåt,\ngalvanise-rade hinkar och baljor, kemiska\neldsläckningsapparater, soptunnor, skottkärror,\ngalvaniserade hydroforer och\nvarmvattenberedare m. m.; utför galvanisering av\njärneffekter.\n\nKontor: Lil jeholpien; postadr.:\nStockholm 9. Telegr.-adr.: Galvanus,\nStockholm. Telefon: »Galvanfabriken».\nPostgiro: 3703.\n\nAkt.-kap.: 1,800,000 kr. Antal\nindustriarb.: 330. Tillv.-värde pr år: 5,000,000 kr.\n\nFirman, etabl. 1895, bolag 1938, äger\nAB. Göteborgs Galvaniseringsfabrik,\nGöteborg.\n\nStyrelse: grossh. Erik Kistner (ordf.),\nfru Siri Collett, herr Åke Oollett, dir.\nGustaf Sundberg, disp. Yngve Westberg.\n\nVerkst. dir. o. disp.: Yngve Westberg.\n\n(Jfr annons nr 94.)\n\n\"Stockholms Gelatinfabrik,\n\nStockholm.\n\nTillverkar gelatin och gelatinlim, lim\nsamt valsmassa.\n\nKontor: Västgötag. 11. Telefon: 414228\no. 408002. Postgiro: 2802.\n\nAntal industriarb.: 30. — Firman etabl.\n1886.\n\nChef: disp. Tore Setterberg.\n\n\"Stockholms Golvmassefabrik,\n\nStockholm.\n\nTillverkar och inlägger\nförhydnings-massa (magnesiamassa) för fogfri\ngolvbeläggning och väggbeklädnad. Speciali-\n\ntet : brandbottnar och, fabriks^olv samt\ninläggning av syrafasta plattor.\nVarumärke: »ESSGE».\n\nKontor: Klinten pr Stockholm.\nTelefon : 151038. Postgiro: 9170. —’\nTillv.-värde pr år: 30,000 kr. —- Firman etabL\n1929.\n\nÄgare o, chef: fabr. C. Ivar Gustafsson.\n\n\"Stockholms Kartong- &amp;\nLltogra-fiska AB. (f. d. Jacob Bagges Söner),\n\nStockholm.\n\nLitografisk anstalt och ^ kartongfabrik.\nTillverkar kartonger, etiketter m. m.\nsamt utför offset- och litografiskt\ntryck-Varunamn: »Hermetet» o. »Hermeton».\n\nKontor: Vasag. 16. Telegr.-adr.:\nKartongen, Stockholm. Telefon: »Stockholms\nKartong och Lito». Postgiro: 57.\n\nBolaget är anslutet till AB. Sveriges\nLitografiska Tryckerier, Stockholm. (Se\ndetta bolag). Bolaget, som grundades\n1893, har i sig upptagit Svanboms\nKartongfabrik och AB. Nordiska\nKartongfabriken.\n\nStyrelse o. vérJcit. dir.: inäjér C. G.\nÅhlund.\n\nDisp.: John Holm.\n\n\"AB. Stockholms kexfabrik,\n\nStockholm.\n\nTillverkar kex och wafers.\n\nKontor: Åsögatan 140. Telegr.-adr.:\nKexfabriken, Stockholm. Telefon: 440545.\nPostgiro: 3036.\n\nAkt.-kap.: 400,000 kr. Antal\nindustriarb.: 65. — Firman etabl. 1927, ombildad\n1939.\n\nStyrelse: adv. Helmer? Persson (ordf.),\ndir. Johan Troedsson.\n\nVerkst. dir.: Johan Troedsson.\n\n\"AB. Stockholms Kolafabrik,\n\nStockholm.\n\nTillverkar kolakarameller.\nVarumärken: »Parad» o. »Pang».\n\nKontor: Skeppsbron 16. Telegr.-adr.:\nParadkola, Stockholm. Telefon: 214750.\nPostgiro: 52825.\n\nAkt,-kap.: 100,000 kr. Antal\nindustriarb.: 15. — Bolaget grundat 1931.\n\nStyrelse o. verkst. dir.: Oscar Fried.\n\nStockholms Markis- &amp;\nPresenningsfabrik, Stockholm.\n\nTillverkar markiser, presenningar, tält,\nflaggor o. gardiner. Varumärke: »S.M.P.».",
    "structured": {
        "1": {
            "name": "Stockholms Båtbyggerl AB.",
            "location": "Saltsjöbaden",
            "business": "Tillverkning av båtar",
            "products": "Tillverkar båtar",
            "contact": {
                "office": "Tuleg. 15",
                "phone": [
                    "324850"
                ],
                "postgiro": "52809",
                "telegraph": "Fjä-derwal, Stockholm"
            },
            "financials": {
                "capital": "",
                "employees": {
                    "industriarb": 18
                },
                "annual_turnover": "",
                "annual_production_value": ""
            },
            "foundation_year": 1915,
            "owner": "B. Wahl",
            "manager": "B. Wahl"
        },
        "2": {
            "name": "Stockholms Calvaniseringsfabrik AB.",
            "location": "Liljeholmen",
            "business": "Tillverkning av varmgalvaniserad plåt och produkter",
            "products": "Varmgalvaniserad plåt, slät, korrugerad och s. k. pannplåt, galvaniserade hinkar och baljor, kemiska eldsläckningsapparater, soptunnor, skottkärror, galvaniserade hydroforer och varmvattenberedare m. m.",
            "contact": {
                "office": "Liljeholmen",
                "phone": "Galvanfabriken",
                "postgiro": "3703",
                "telegraph": "Galvanus, Stockholm"
            },
            "financials": {
                "capital": "1,800,000 kr",
                "employees": {
                    "industriarb": 330
                },
                "annual_turnover": "5,000,000 kr",
                "annual_production_value": ""
            },
            "foundation_year": 1895,
            "corporation_year": 1938,
            "board": [
                {
                    "name": "grossh. Erik Kistner",
                    "role": "ordf."
                },
                {
                    "name": "fru Siri Collett",
                    "role": ""
                },
                {
                    "name": "herr Åke Oollett",
                    "role": ""
                },
                {
                    "name": "dir. Gustaf Sundberg",
                    "role": ""
                },
                {
                    "name": "disp. Yngve Westberg",
                    "role": ""
                }
            ],
            "owners": "",
            "director": "",
            "managing_director": "Yngve Westberg",
            "sales_manager": "",
            "manager": "Yngve Westberg"
        },
        "3": {
            "name": "Stockholms Gelatinfabrik",
            "location": "Stockholm",
            "business": "Tillverkning av gelatin och gelatinlim",
            "products": "Gelatin och gelatinlim, lim samt valsmassa",
            "contact": {
                "office": "Västgötag. 11",
                "phone": [
                    "414228",
                    "408002"
                ],
                "postgiro": "2802",
                "telegraph": ""
            },
            "financials": {
                "capital": "",
                "employees": {
                    "industriarb": 30
                },
                "annual_turnover": "",
                "annual_production_value": ""
            },
            "foundation_year": 1886,
            "director": "",
            "managing_director": "Tore Setterberg",
            "sales_manager": "",
            "manager": ""
        },
        "4": {
            "name": "Stockholms Golvmassefabrik",
            "location": "Stockholm",
            "business": "Tillverkning och inläggning av förhydningsmassa (magnesiamassa) för fogfri golvbeläggning och väggbeklädnad",
            "products": "Brandbottnar och, fabriksgolv samt inläggning av syrafasta plattor",
            "contact": {
                "office": "Klinten pr Stockholm",
                "phone": "151038",
                "postgiro": "9170",
                "telegraph": ""
            },
            "financials": {
                "capital": "",
                "employees": "",
                "annual_turnover": "",
                "annual_production_value": "30,000 kr"
            },
            "foundation_year": 1929,
            "owner": "fabr. C. Ivar Gustafsson",
            "manager": "fabr. C. Ivar Gustafsson"
        },
        "5": {
            "name": "Stockholms Kartong- & Litografiska AB.",
            "location": "Stockholm",
            "business": "Litografisk anstalt och kartongfabrik",
            "products": "Kartonger, etiketter m. m. samt utför offset- och litografiskt tryck-Varunamn: »Hermetet» o. »Hermeton»",
            "contact": {
                "office": "Vasag. 16",
                "phone": "Stockholms Kartong och Lito",
                "postgiro": "57",
                "telegraph": "Kartongen, Stockholm"
            },
            "financials": {
                "capital": "",
                "employees": "",
                "annual_turnover": "",
                "annual_production_value": ""
            },
            "foundation_year": 1893,
            "board": [
                {
                    "name": "inäjér C. G. Åhlund",
                    "role": "styrelse o. vérJcit. dir."
                },
                {
                    "name": "John Holm",
                    "role": "disp."
                }
            ],
            "owners": "",
            "director": "",
            "managing_director": "",
            "sales_manager": "",
            "manager": ""
        },
        "6": {
            "name": "AB. Stockholms kexfabrik",
            "location": "Stockholm",
            "business": "Tillverkning av kex och wafers",
            "products": "Kex och wafers",
            "contact": {
                "office": "Åsögatan 140",
                "phone": "440545",
                "postgiro": "3036",
                "telegraph": "Kexfabriken, Stockholm"
            },
            "financials": {
                "capital": "400,000 kr",
                "employees": {
                    "industriarb": 65
                },
                "annual_turnover": "",
                "annual_production_value": ""
            },
            "foundation_year": 1927,
            "board": [
                {
                    "name": "adv. Helmer? Persson",
                    "role": "ordf."
                },
                {
                    "name": "dir. Johan Troedsson",
                    "role": "verkst. dir."
                }
            ],
            "owners": "",
            "director": "",
            "managing_director": "Johan Troedsson",
            "sales_manager": "",
            "manager": "Johan Troedsson"
        },
        "7": {
            "name": "AB. Stockholms Kolafabrik",
            "location": "Stockholm",
            "business": "Tillverkning av kolakarameller",
            "products": "Kolakarameller",
            "contact": {
                "office": "Skeppsbron 16",
                "phone": "214750",
                "postgiro": "52825",
                "telegraph": "Paradkola, Stockholm"
            },
            "financials": {
                "capital": "100,000 kr",
                "employees": {
                    "industriarb": 15
                },
                "annual_turnover": "",
                "annual_production_value": ""
            },
            "foundation_year": 1931,
            "director": "",
            "managing_director": "",
            "sales_manager": "",
            "manager": "Oscar Fried"
        },
        "8": {
            "name": "Stockholms Markis- & Presenningsfabrik",
            "location": "Stockholm",
            "business": "Tillverkning av markiser, presenningar, tält, flaggor o. gardiner",
            "products": "Markiser, presenningar, tält, flaggor o. gardiner",
            "contact": {
                "office": "",
                "phone": "",
                "postgiro": "",
                "telegraph": ""
            },
            "financials": "",
            "foundation_year": "",
            "manager": ""
        }
    }
}