{
    "original": "Nya\n\nAkt.-kap.: 75,000 kr. Antal industriarb.:\n40, — Bolaget grundat 1936, ombildat\n1942.\n\nVerkst. dir. o. disp.: Hans Glemme.\n\nNya AB. Sanda Tegel, Stockholm.\n\nTillverkar tak- och murtegel samt\ndräneringsrör vid tegelbruk i Sanda,\nSträngnäs. Bolaget driver även jordbruk och\nskogshantering.\n\nKontor: Stockholm, Lilla Nygatan 4.\nTelefon: 203641 o. 203642. Postgiro:\n152143.\n\nAkt.-kap.: 50,000 kr. Antal\nindustriarb.: 25. Tillv.-värde pr år: 150,000 kr.\nBolaget grundat 1945 efter övertagande\nav f. d. AB. Sanda Tegelbruks rörelse.\n\nVerkst. dir.: Eric Hallström.\n\n*Nya Skofabriks AB. Örnen,\n\nÖrebro.\n\nTillverkar randsydda, durksydda samt\npliggade och stiftade skodon.\n\nTelefon: 19205. Postgiro: 25877.\nEn-samförsälj.: Skofabriks AB. Oscaria,\nÖrebro. — Akt.-kap.: 200,000 kr. Antal\nindustriarb.: 307. Tillv.-värde pr år: 6,735,000\nkr. — Bolaget grundat 1896.\n\nStyrelse: jur. kand. Gösta Åqvist, ing.\nKnut Åqvist, fru Lillie Åqvist, disp. Sven\nÅqvist.\n\nDisp.: Sven Åqvist.\n\n*Nya Snickerifabriken, A. Karlsson,\n\nGånghester.\n\nSågverk, hyvleri och snickerifabrik vid\nGånghester (Älvsb. l.). Tillverkar\nbyggnadssnickerier. Firman driver även\nträ-varuaffär\n\nTelefon: Borås 49040 o. 49185.\nPostgiro: 145450. — Antal industriarb.: 15.\nTillv.-värde pr år: 250,000 kr. — Firman\netabl. 1926.\n\nÄgare o. chef: fabr. Artur Karlsson.\n\nNya Snickerifabriken i Lindesberg\n\nAB., Lindesberg.\n\nTillverkar byggnadssnickerier såsom\ndörrar och fönster av furu och ek.\n\nTelefon: 137. Postgiro: 93506. —\nAkt.-kap.: 45,000 kr. Antal industriarb.: 20.\nTillv.-värde pr år: 275,000 kr. — Firman\netabl. 1911, bolag 1944.\n\nStyrelse: verkstadsarb. Hjalmar\nEngström, disp. Martin Karlson, verkm.\nOskar Karlsson.\n\nDisp.: Martin Karlson.\n\nKamrer: Richard Eriksson.\n\n\"Nya Snickerifabriken, Olofsson &amp;\nNilsson, Laholm.\n\nTillverkar byggnadssnickerier och\ninredningar.\n\nTelefon: 122. — Arb.-antal: 9. —\nFirman etabl. 1915.\n\nÄgare o. chefer: fabr. Ludvig Olofsson\no. fabr. Otto Nilsson.\n\n\"Nya AB. Sömmens Lådfabrik,\n\nSömmen.\n\nLådfabrik och hyvleri i Sömmen\n(Jönköp. l.). Tillverkar lådbräder och hyvlade\nträvaror.\n\nTelegr.-adr.: Nemmos, Sömmen.\nTelefon: 24. Postgiro: 75125.\n\nAkt.-kap.: 160,000 kr. Antal\nindustriarb.: 85. .Årstillv.: 6,000 stds lådbräder..\n\nFabriken anlagd och bolaget grundat\n1916, ombildat 1922, nuv. bolag 1928.\n\nStyrelse, verkst. dir. o. disp.: Nils A~\nÅman.\n\n\"Nya AB. Stängselfabriken,\n\nGöteborg.\n\nMek. verkstad. Tillverkar ståltråds- och\njärnstängsel, grindar och mek.\nmanöveranordningar för dylika, klädskåp,\nverktygsskåp, oljeskåp, gallerinredningar,,\nremskydd, fönster- och lanterninskydd\nm. m. av nätverk eller plåt.\n\nKontor: Tuvevägen; postadr.:\nGöteborg 8. Telegr.-adr.: Stängsel, Göteborg.\nTelefon: 220373. Postgiro: 42292.\n\nAkt.-kap.: 60,000 kr. Antal\nindustriarb.: 20. Tillv.-värde pr år: 300,000 kr.\n\n—\tBolaget grundat 1908, ombildat 1931.\n\nStyrelse: dir. Sven A. Höglund (ordf.).*\n\nkamrer Åke Eek, fru Gullan Höglund.\n\nVerkst. dir.: Sven A. Höglund.\n\n\"Nya AB. Stängselnät i Rydsgård,\n\nBydsgård.\n\nTråddrageri och galvaniseringsfabrik i\nRydsgård (Malmöh. l.). Tillverkar\njärntråd, stängselnät, taggtråd och trådspik-\n\nTelegr.-adr.: Stängselnät, Rydsgård.\nTelefon: 2. Postgiro: 143027.\n\nAkt.-kap.: 100,000 kr. Antal\nindustriarb.: 70. Tillv.-värde pr år: 1,500,000 kr.\n\n—\tBolaget grundat 1910.\n\nStyrelse o. disp.: Thorsten Barchan.\n\n\"Nya AB. Sveaverken, Eskilstuna.\n\nMek. verkstad. Tillverkar tröskverk,,\nsammälds- och gröpkvarnar, hö- och\nkärv-fläktar, halm-, sug- och blåsfläktar,\ncirkelsågverk, enkla kantverk, balans- och",
    "structured": {
        "1": {
            "name": "Nya AB. Sanda Tegel",
            "location": "Stockholm",
            "business": "Tillverkar tak- och murtegel samt dräneringsrör vid tegelbruk i Sanda, Strängnäs. Bolaget driver även jordbruk och skogshantering.",
            "contact": {
                "office": "Lilla Nygatan 4",
                "phone": [
                    "203641",
                    "203642"
                ],
                "postgiro": "152143"
            },
            "financials": {
                "capital": "75,000 kr",
                "employees": {
                    "industriarb": 40
                },
                "annual_turnover": "Not available",
                "annual_production_value": "Not available"
            },
            "foundation_year": 1936
        },
        "2": {
            "name": "Nya Skofabriks AB",
            "location": "Örebro",
            "business": "Tillverkar randsydda, durksydda samt pliggade och stiftade skodon.",
            "contact": {
                "phone": "19205",
                "postgiro": "25877"
            },
            "financials": {
                "capital": "50,000 kr",
                "employees": {
                    "industriarb": 25
                },
                "annual_turnover": "150,000 kr",
                "annual_production_value": "Not available"
            },
            "foundation_year": 1945
        },
        "3": {
            "name": "Nya Snickerifabriken, A. Karlsson",
            "location": "Gånghester",
            "business": "Tillverkar byggnadssnickerier. Firman driver även trä-varuaffär.",
            "contact": {
                "phone": [
                    "49040",
                    "49185"
                ],
                "postgiro": "145450"
            },
            "financials": {
                "capital": "Not available",
                "employees": {
                    "industriarb": 15
                },
                "annual_turnover": "250,000 kr",
                "annual_production_value": "Not available"
            },
            "foundation_year": 1926
        },
        "4": {
            "name": "Nya Snickerifabriken i Lindesberg AB.",
            "location": "Lindesberg",
            "business": "Tillverkar byggnadssnickerier såsom dörrar och fönster av furu och ek.",
            "contact": {
                "phone": "137",
                "postgiro": "93506"
            },
            "financials": {
                "capital": "45,000 kr",
                "employees": {
                    "industriarb": 20
                },
                "annual_turnover": "275,000 kr",
                "annual_production_value": "Not available"
            },
            "foundation_year": 1911
        },
        "5": {
            "name": "Nya Snickerifabriken, Olofsson & Nilsson",
            "location": "Laholm",
            "business": "Tillverkar byggnadssnickerier och inredningar.",
            "contact": {
                "phone": "122"
            },
            "financials": {
                "capital": "Not available",
                "employees": {
                    "antal": 9
                },
                "annual_turnover": "Not available",
                "annual_production_value": "Not available"
            },
            "foundation_year": 1915
        },
        "6": {
            "name": "Nya AB. Sömmens Lådfabrik",
            "location": "Sömmen",
            "business": "Tillverkar lådbräder och hyvlade trävaror.",
            "contact": {
                "telegraph": "Nemmos, Sömmen",
                "phone": "24",
                "postgiro": "75125"
            },
            "financials": {
                "capital": "160,000 kr",
                "employees": {
                    "industriarb": 85
                },
                "annual_turnover": "Not available",
                "annual_production_value": "6,000 stds lådbräder"
            },
            "foundation_year": 1916
        },
        "7": {
            "name": "Nya AB. Stängselfabriken",
            "location": "Göteborg",
            "business": "Tillverkar ståltråds- och järnstängsel, grindar och mek. manöveranordningar för dylika, klädskåp, verktygsskåp, oljeskåp, gallerinredningar, remsskydd, fönster- och lanterninskydd m. m. av nätverk eller plåt.",
            "contact": {
                "office": "Tuvevägen",
                "phone": "220373",
                "postgiro": "42292"
            },
            "financials": {
                "capital": "60,000 kr",
                "employees": {
                    "industriarb": 20
                },
                "annual_turnover": "300,000 kr",
                "annual_production_value": "Not available"
            },
            "foundation_year": 1908
        },
        "8": {
            "name": "Nya AB. Stängselnät i Rydsgård",
            "location": "Rydsgård",
            "business": "Tillverkar järntråd, stängselnät, taggtråd och trådspik.",
            "contact": {
                "telegraph": "Stängselnät, Rydsgård",
                "phone": "2",
                "postgiro": "143027"
            },
            "financials": {
                "capital": "100,000 kr",
                "employees": {
                    "industriarb": 70
                },
                "annual_turnover": "1,500,000 kr",
                "annual_production_value": "Not available"
            },
            "foundation_year": 1910
        },
        "9": {
            "name": "Nya AB. Sveaverken",
            "location": "Eskilstuna",
            "business": "Tillverkar tröskverk, sammälds- och gröpkvarnar, hö- och kärv-fläktar, halm-, sug- och blåsfläktar, cirkelsågverk, enkla kantverk, balans- och",
            "contact": {
                "telegraph": "Not available",
                "phone": "Not available",
                "postgiro": "Not available"
            },
            "financials": {
                "capital": "Not available",
                "employees": {
                    "industriarb": 1
                },
                "annual_turnover": "Not available",
                "annual_production_value": "Not available"
            },
            "foundation_year": "Not available"
        }
    }
}