{
    "original": "Elektriska\n\nElektriska AB. Morén, Partille.\n\nElektromek. verkstad i Partille (Göteb.\no. Bohus l.). Tillverkar elektr. maskiner\noch apparater såsom motorer, generatorer,\nenankareomformare och transformatorer,\nmotorskåp, pådragsapparater, motstånd,\nfrånskilj are, säkerhetsapparater,\nströmbrytare, kapslade ställverk,\ninstrumenttavlor, vedkapsågar samt\nremskiveslir-kopplingar och axelslirkopplingar m. m.\n\nTelegr.-adr.: Morén, Partille. Telefon:\n»Moréns fabriker». Postgiro: 8753.\n\nAkt.-kap.: 300,000 kr. Antal\nindustriarb.: 160. Tillv.-värde pr år: 2,000,000 kr.\n\nFabriken anlagd 1907, bolag 1917\nunder namn Elektr. AB. Eck, nuv. bolag\n1932.\n\nStyrelse o. verkst. dir.: ing. W. H.\nMorén.\n\n(Jfr annons nr 32.)\n\n^Elektriska AB. John Österman,\n\nStockholm.\n\nElektromek. verkstad. Tillverkar elektr.\ninstallationsmateriel, mätartavlor samt\nelektriska kok- och värmeapparater.\nSpecialiteter: Svenska\nElektricitetsverksföreningens standardmateriel (SEF),\nmätartavlor (Sthlms El.-verks modell) samt\nelektr. kaminer för tåguppvärmning och\nindustribehov.\n\nKontor: Hammarbyvägen 28.\nTelegr.-adr.: Elmateriel, Stockholm. Telefon:\n440050. Postgiro: 56919.\n\nAkt.-kap.: 980,000 kr. Antal\nindustriarb.: 102. Tillv.-värde pr år: 2,500,000 kr.\n\nBolaget grundat 1934 efter\növertagandet av AB. Osram-Elektraverkens\ntillverkning av elektr. installationsmateriel\noch elektr. kok- och värmeapparater.\n\nStyrelse: dir. John Österman (ordf.),\ning. Karl-Gustaf Gustafson, ing. Ragnar\nÖsterman.\n\nVerkst. dir.: J. Österman.\n\nFabrikschef: K.-G. Gustafson.\n\nFörsäljn.-chef: R. Österman.\n\nElektriska AB. Sivers &amp; Häger,\n\nJ önköping.\n\nTillverkar elektr. maskiner och\napparater; utför reparationer och omlindning-\n\nar. Specialiteter: elektr, slip-, puts- och\npolermaskiner, verktygsmotorer med\nböjlig axel samt laddningsanläggningar för\nackumulatorer.\n\nTelefon: 1175 o. 4460. Postgiro: 30220.\n\nAkt.-kap.: 100,000 kr. Antal\nindustriarb.: 120. Tillv.-värde pr år: 2,000,000 kr.\n— Firman etabl. 1924. ;\n\nStyrelse o. verkst. dir.: ing. K. E. v.\nSivers.\n\n* Elektriska AB. Skandia, Stockholm.\n\nElektromek. verkstäder i Stockholm\noch Arboga. Tillverkar elektr.\ninstallationsmateriel såsom kapslade centraler,\narmatur, rörtillbehör, motorkontakter,\nknivströmbrytare, pumpar och\nhydroforverk, likriktare m. m.; utför kraft-,\nbelysnings- och svagströmsanläggningar.\nBolaget driver även engroshandel med\nelektr. materiel, maskiner och\nradioartiklar, elstängsel, kylskåp, dammsugare,\ntvättmaskiner m. m.\n\nHuvudkontor: Stockholm, Norra\nSta-tionsg. 79—81. Telegr.-adr. o. telefon:\nElektroskandia, Stockholm. Postgiro:\n1810. Avd.-kontor: Göteborg, Malmö,\nNässjö, Karlstad, Gävle, Sundsvall,\nÖstersund o. Umeå.\n\nAkt.-kap.: 2,500,000 kr. Antal anställda:\n890, varav 460 industriarbetare.\n\nBolaget grundat 1917.\nHuvudintressent i bolaget är Svenska\nElektromeka-niska Industri AB., Hälsingborg, som är\nanslutet till Ericssongruppen.\n\nStyrelse: dir. I. L. la Cour (ordf.), dir.\nJ. Evald Holmqvist (v. ordf.), civiling’.\nP. Martin.\n\nVerkst. dir.: J. Evald Holmqvist.\n\nV. verkst. dir.: P. Martin.\n\n*Elektriska Svetsnings AB. (ESAB),\n\nGöteborg.\n\nSpecialfirma för elektrisk\nljusbågs-svetsning med elektrodfabrik och\nsvets-tekniska laboratorier i Göteborg samt\nsvetsmaskinfabrik i Laxå (Örebro l.).\nVarumärken: »ESAB» o. »OK». Tillverkar\näven gasskärningsmaskiner, magnetiska\nmaterialprovningsapparater jämte\nelektriska vthärdningsmaskiner.\n\nTelegr.-adr.: Esab, Göteborg. Telefon:\n»Esab». Postgiro: 42211. Filialkontor:\nStockholm, Blasieholmsg. 3, telefon:\n119501, 211207, 104148 o. 104135; Malmö:\nRundelsg. 23, telefon: 18333 o. 18337;\nSundsvall, telefon: 1366 o. 5450;\nLudvika, telefon: 905 o. Norrköping, telefon:\n32933. Maskinfabrikskontor: Laxå,\ntelefon: »Esab».\n\nAkt.-kap.: 7,000,000 kr. Antal\nindustriarb.: 500. Tillv.-värde pr år: 11,000,000\nkr. — Bolaget grundat 1904.\n\nStyrelse: skeppsred. Tor E. J:son\nBroström, dir. Walter Edström, f. d. bor gm.\nBernhard Lindberg, dir. Rolf Sörman,\nmarinöver-dir. Harald Q vis t g-a a rd (adj.\nled.).\n\nVerkst. dir.: Walter Edström.\n\n122*",
    "structured": {
        "1": {
            "name": "Elektriska AB. Morén",
            "location": "Partille",
            "business": "Tillverkar elektr. maskiner och apparater",
            "products": "motorer, generatorer, enankareomformare, transformatorer, motorskåp, pådragsapparater, motstånd, frånskiljare, säkerhetsapparater, strömbrytare, kapslade ställverk, instrumenttavlor, vedkapsågar, remskiveslir-kopplingar och axelslirkopplingar m.m.",
            "contact": {
                "telegraph": "Morén, Partille",
                "phone": [
                    "Moréns fabriker"
                ],
                "postgiro": "8753",
                "head_office": "Morén, Partille"
            },
            "financials": {
                "capital": "300,000 kr",
                "employees": {
                    "industriarb.": 160
                },
                "annual_turnover": "2,000,000 kr",
                "annual_production_value": "2,000,000 kr"
            },
            "foundation_year": 1907,
            "current_name_year": 1932,
            "board": [
                {
                    "name": "ing. W. H. Morén",
                    "role": "styrelse o. verkst. dir."
                }
            ]
        },
        "2": {
            "name": "Elektriska AB. John Österman",
            "location": "Stockholm",
            "business": "Tillverkar elektr. installa"
        },
        "3": {
            "name": "Elektriska AB. Sivers &amp; Häger",
            "location": "Jönköping",
            "business": "Tillverkar elektr. maskiner och apparater",
            "products": "elektr, slip-, puts- och polermaskiner, verktygsmotorer med böjlig axel samt laddningsanläggningar för ackumulatorer",
            "contact": {
                "phone": [
                    "1175",
                    "4460"
                ],
                "postgiro": "30220"
            },
            "financials": {
                "capital": "100,000 kr",
                "employees": {
                    "industriarb.": 120
                },
                "annual_turnover": "2,000,000 kr"
            },
            "foundation_year": 1924,
            "board": [
                {
                    "name": "ing. K. E. v. Sivers",
                    "role": "styrelse o. verkst. dir."
                }
            ]
        },
        "4": {
            "name": "Elektriska AB. Skandia",
            "location": "Stockholm",
            "business": "Elektromek. verkstäder"
        },
        "5": {
            "name": "Elektriska Svetsnings AB. (ESAB)",
            "location": "Göteborg",
            "business": "Specialfirma för elektrisk ljusbågssvetsning",
            "products": "gasskärningsmaskiner, magnetiska materialprovningsapparater, elektriska härdningsmaskiner",
            "contact": {
                "telegraph": "Esab, Göteborg",
                "phone": [
                    "Esab"
                ],
                "postgiro": "42211"
            },
            "financials": {
                "capital": "7,000,000 kr",
                "employees": {
                    "industriarb.": 500
                },
                "annual_turnover": "11,000,000 kr"
            },
            "foundation_year": 1904,
            "board": [
                {
                    "name": "skeppsred. Tor E. J:son Broström",
                    "role": "styrelse"
                },
                {
                    "name": "dir. Walter Edström",
                    "role": "verkst. dir."
                }
            ]
        }
    }
}