{
    "original": "Köping—Lagerblad\n\n189,400 kr. Antal industriarb.: 17. —\nBolaget grundat 1875.\n\nStyrelse: disp. Folke Bergendahl\n(ordf.), disp. Gösta Sverdrup, bryggm.\nGunnar öhrn.\n\nVerkst. dir.: Folke Bergendahl.\n\n\"Köpings Mekaniska Verkstads AB.,\n\nKöping.\n\nMek. verkstad och gjuteri. Tillverkar\nverktygsmaskiner, kugghjul samt\ngjut-gods.\t*\n\nTelegr.-adr.: Verkstaden, Köping.\nTelefon: »Mekaniska verkstaden». Postgiro:\n8067.\n\nAkt.-kap.: 540,000 kr. Antal\nindustriarb.: 900. Tillv.-värde pr år: 10,000,000\nkr. — Firman etabl. 1856, bolag 1872;\nhuvudintressent i bolaget är AB. Volvo.\n\nStyrelse: dir. Assar Gabrielsson (ordf.),\ndisp. Omar Hallström, dir. Gustaf\nLarson, dr Hilding Törnebohm.\n\nVerkst. dir.: Omar Hallström-\n\nFörsäljn.-chef: ing. Bengt Liljhagen.\n\nÖvering. o. tillv.-chef: civiling.\nHjalmar Hurtig.\n\nRitkontorschef: ing. Emerik Westberg.\n\nInköpschef: H. Bergsten.\n\nKontorschef: Per Ekström.\n\n\"Köpings Metallvarufabrik, Eriksson\n&amp; Co., Köping.\n\nTillverkar kokkärl samt utför\npressningsarbeten i koppar och mässing.\n\nTelefon: 510. Postgiro: 173756. —\nArb.-antal: 10. Tillv.-värde pr år:\n100,000 kr. — Firman etabl. 1925.\n\nChef: fabr. Gustav Eriksson.\n\n\"Köpings Tagelspinneri, Köping.\n\nSe Nya Tagelspinneriet, Janson &amp;\nArnold, Köping.\n\nKöpfinge Myrs Andélstorvströ-\n\nförening, U. p. a., Perstorp.\n\nTorvströfabrik vid Köpinge, Perstorp\n(Kristianst. l.). Tillverkar torvströ,\nbränntorv och torvmull.\n\nTelefon: 1. Postgiro: 135024. — Antal\nindustriarb.: 50. Årstillv.: 4,500 ton\ntorvprodukter. — Firman etabl. 1911.\n\nStyrelseordf.: f. riksdagsm. Svven\nJönsson.\n\nDisp.: Ored S. Jönsson.\n\n\"Köpmanholmens Sulfitfabrik,\n\nKöpmanholmen.\n\nSe Forss AB., Köpmanholmen.\n\n* utmärker till Sveriges Industriförbund anslutna företag\n\n\"Lagamilis AB., Jönköping.\n\nPappersbruk med träsliperi, sågverk\noch elektr. kraftstation vid Timsfors\n(Kronob. l.).\n\nTillverkar vit, brun och färgad\nduplex-och triplexkartong, kascherad papp,\nbyggnadspapp såsom asfalttakpapp, asfalterad\noch impregnerad förhydningspåppp,\nvagg-oeh grålumppapp m. m. samt\nmÖnster-papper, havannapapper, sulfit- och\nomslagspapper. Bolaget idkar jämväl\njordbruk och skogshantering.\n\nFörsäljningskontor: Jönköping.\nTelegr.-adr.: Lagamill, Jönköping. Telefon:\n»Munksjö», Jönköping. Fabrikskontor:\nTimsfors. Telegr.-adr.: Lagamill,\nHässleholm. Telefon: Markaryd 7 o. 65.\nPostgiro: 23530.\n\nAkt.-kap.: 2,800,200 kr. Antal industri-\n\narb.: 235. — Årstillv.: 16,000 ton papper\noch papp.\n\nBruket anlades 1896. Bolaget äges av\nMunksjö AB.\n\nStyrelse: konsul Oskar Gullander\n(ordf.), dir. Nils G. Arvedson, bankdir.\nAnton Dahlin, adv. Emil Heijne, disp.\nOtto Heijne, disp. Werner Bisberg.\n\nVerkst. dir.: Otto Heijne.\n\nRagnar Lagerblads Boktryckeri,\n\nKarlshamn.\n\nUtför affärs-, bok- och # tidningstryck\nsamt bokbinderiarbeten; tillverkar\nkontorsböcker, sorgpappersartiklar och\nkort-blanketter\n\nTelefon: 184 o. 96. Postgiro: 30276. —\nAntal industriarb.: 36. — Boktryckeriet\nanlagt 1864.\n\nÄgare o. chef: boktr. R. Lagerblad.\n\n&gt;16*",
    "structured": {
        "1": {
            "name": "Köpings Mekaniska Verkstads AB",
            "location": "Köping",
            "business": "Mekanisk verkstad och gjuteri",
            "products": "Tillverkar verktygsmaskiner, kugghjul samt gjut-gods",
            "contact": {
                "office": "Verkstaden, Köping",
                "phone": [
                    "Mekaniska verkstaden"
                ],
                "postgiro": "8067"
            },
            "financials": {
                "capital": "540,000 kr",
                "employees": {
                    "industriarb": 900
                },
                "annual_turnover": "10,000,000 kr",
                "annual_production_value": "10,000,000 kr"
            },
            "foundation_year": 1856,
            "corporation_year": 1872,
            "board": [
                {
                    "name": "Assar Gabrielsson",
                    "role": "ordf."
                },
                {
                    "name": "Omar Hallström",
                    "role": "disp."
                },
                {
                    "name": "Gustaf Larson",
                    "role": "dir."
                },
                {
                    "name": "Hilding Törnebohm",
                    "role": "dr"
                }
            ],
            "owners": [
                "AB. Volvo"
            ],
            "director": "Folke Bergendahl",
            "managing_director": "Omar Hallström",
            "sales_manager": "Bengt Liljhagen"
        },
        "2": {
            "name": "Köpings Metallvarufabrik, Eriksson & Co.",
            "location": "Köping",
            "products": "Tillverkar kokkärl samt utför pressningsarbeten i koppar och mässing",
            "contact": {
                "phone": [
                    "510"
                ],
                "postgiro": "173756"
            },
            "financials": {
                "employees": {
                    "antai": 10
                },
                "annual_production_value": "100,000 kr"
            },
            "foundation_year": 1925,
            "manager": "Gustav Eriksson"
        },
        "3": {
            "name": "Köpings Tagelspinneri",
            "location": "Köping",
            "description": "Se Nya Tagelspinneriet, Janson & Arnold, Köping"
        },
        "4": {
            "name": "Köpfinge Myrs Andélstorvströ-förening, U. p. a.",
            "location": "Perstorp",
            "products": "Tillverkar torvströ, bränntorv och torvmull",
            "contact": {
                "phone": [
                    "1"
                ],
                "postgiro": "135024"
            },
            "financials": {
                "employees": {
                    "antai": 50
                },
                "annual_production_value": "4,500 ton torvprodukter"
            },
            "foundation_year": 1911,
            "sales_manager": "Svven Jönsson"
        },
        "5": {
            "name": "Köpmanholmens Sulfitfabrik",
            "location": "Köpmanholmen",
            "description": "Se Forss AB., Köpmanholmen"
        },
        "6": {
            "name": "Lagamilis AB.",
            "location": "Jönköping",
            "products": "Pappersbruk med träsliperi, sågverk och elektr. kraftstation vid Timsfors (Kronob. l.)",
            "contact": {
                "office": "Timsfors",
                "phone": [
                    "Markaryd 7 o. 65"
                ],
                "postgiro": "23530"
            },
            "financials": {
                "capital": "2,800,200 kr",
                "employees": {
                    "industriarb": 235
                },
                "annual_production_value": "16,000 ton papper och papp"
            },
            "foundation_year": 1896,
            "owners": [
                "Munksjö AB"
            ],
            "board": [
                {
                    "name": "Oskar Gullander",
                    "role": "ordf."
                },
                {
                    "name": "Nils G. Arvedson",
                    "role": "dir."
                },
                {
                    "name": "Anton Dahlin",
                    "role": "bankdir"
                },
                {
                    "name": "Emil Heijne",
                    "role": "adv."
                },
                {
                    "name": "Otto Heijne",
                    "role": "disp."
                },
                {
                    "name": "Werner Bisberg",
                    "role": "disp."
                }
            ],
            "director": "Otto Heijne"
        },
        "7": {
            "name": "Ragnar Lagerblads Boktryckeri",
            "location": "Karlshamn",
            "products": "Utför affärs-, bok- och # tidningstryck samt bokbinderiarbeten; tillverkar kontorsböcker, sorgpappersartiklar och kort-blanketter",
            "contact": {
                "phone": [
                    "184 o. 96"
                ],
                "postgiro": "30276"
            },
            "financials": {
                "employees": {
                    "industriarb": 36
                }
            },
            "foundation_year": 1864,
            "manager": "R. Lagerblad"
        }
    }
}