{
    "original": "Malmskogen—Malmö\n\nKungsg. 4; Göteborg, Arkaden; Malmö,\nösterg. 11; Norrköping, Gävle, Örebro och\nLinköping.\n\nAkt.-kap.: 150,000 kr. — Firman, som\ngrundades 1843, ombildades till bolag\n1906 och äges av AB. Förenade Piano- &amp;\nÖrgelfabriker, Arvika. (Se vidare under\ndetta bolag.)\n\nStyrelse: disp. Alexis Anderson, dir.\nl£arl Högberg, dir. J. Sande J:or.\nDisp.: Alexis Anderson.\n\n\"AB. Malmskogens Träindustri,\n\nLinköping.\n\nTillverkar monteringsfärdiga trähus\nvid fabrik i Malmsäter, Linköping.\nBolaget driver även trävaruaffär och\nförsäljning av byggnadsmaterial.\n\nTelefon: 97074. Postgiro: 34116. —\nAkt.-kap.: 52,000 kr. Antal industriarb.:\n50. Tillv.-värde pr år: 2,000,000 kr. —\nFirman etabl. 1933, bolag 1942.\n\nStyrelse: dir. David A. Larsson (ordf.),\nbyggm. Elof O. Carlsson, disp. A. J.\nLarsson.\n\nVerkst. dir.: David A. Larsson.\n\nMalmqvists Möbelfabrik, AB.\nBröderna, Malmbäck.\n\nSe Industri AB. Mbk—W., Malmbäck.\n\nAB. Lars Malmstedt, Stockholm.\n\nMek. verkstad. Tillverkar borrgiggar,\npressverktyg och fixturer samt utför\nsvarvnings- och fräsningsarbeten.\n\nKontor: Råggatan 9. Telefon: 422329.\nPostgiro: 193048. — Akt.-kap.: 5,000 kr.\nAntal industriarb.: 9. Tillv.-värde pr år:\n100,000 kr. — Bolaget grundat 1943,\nom-bildat 1945.\n\nVerkst. dir.: fabr. Lars Malmstedt.\n\nMalmströms Metallvarufabrik,\n\nMalmö.\n\nSe Bröderna Malmströms\nMetallvarufabrik, Malmö.\n\n* AB. Malmö Armaturfabrik, Lomma.\n\nArmatur- och metallfabrik samt\nmetallgjuteri, förkromnings- och\nförnicklings-anstalt i Lomma (Malmöh. l.). Tillverkar\nmetallgjutgods och armatur, spec.\nsani-tets- och sjukhusarmatur samt\njärnvägs-och fartygsarmatur.\n\nKontor: Lomma. Telegr.-adr.:\nArmaturfabriken, Malmö. Telefon: Malmö\n462520. Postgiro: 38813.\n\no\n\nO.\n\nAkt.-kap.: 300,000 kr. Antal\nindustriarb.: 55. — Bolaget grundat 1907.\n\nStyrelse: kontorschef Carl Kristensson,\navd.-chef Gunnar Paulsson, ing. Olof\nWinkler.\n\nDisp.: Sture Wretborg.\n\n\"Malmö Chokolad- &amp; Konfektfabriks.\nAB., Malmö.\n\nTillverkar »Mazetti» choklad och cacao,\nmarmelad, lakrits, karameller, dragéer,\nkonfityrer och bageriartiklar samt glykos.\n\nHuvudkontor: Malmö, Skolg. 24.\nTelegr.-adr.: Mazetti, Malmö. Telefon:\n»Mazetti» o. 70610. Postgiro: 10050.\nAvd.-kontor: i Stockholm, Luntmakarg. 63,\ntelefon: 230185; i Göteborg. Postgatan\n5—7, telefon: 138208; i Norrköping,\ntelefon: 32898; i Sundsvall, telefon: 1855.\n\nAkt.-kap.: 1,600,000 kr. Antal\nindustriarb.: 420. — Bolaget grundat 1888.\n\nStyrelse: bankdir. Algot Riider (ordf.),\ndir. Gunnar Mazetti-Nissen, dir. Gösta\nMazetti-Nissen, dir. Hilding Ståhlbrandt.\n\nVerkst. direktörer: Gösta\nMazetti-Nissen o. Gunnar Mazetti-Nissen.\n\n\"AB. Malmö Förenade Bryggerier,\n\nMalmö.\n\nBolaget äger Malmquists Bryggeri,\nRichters Bryggeri och Richters Mälteri.\nTillverkar malt och maltdrycker.\n\nKontor: Ystadsvägen. Telegr.-adr.:\nBryggerierna, Malmö. Telefon: 25350.\n\nAkt.-kap.: 5,200,000 kr. x\\ntal\nindustriarb.: 105. Tillv.-värde pr år: 4,000,000 kr.\n\n—\tBolaget grundat 1912.\n\nStyrelse: dir. L. W. Malmquist (ordf.),\ndisp. C. E. Borgenstierna, dir. Rich.\nHain, disp. Fredrik Jungbeck, dir. Erik\nMalmquist.\n\nVerkst. dir.: Erik Malmquist.\nVice verkst. dir.: Gunnar Malmquist.\n\n\"AB. Malmö Grafiska Anstalt,\n\nMalmö.\n\nUtför klichéer, foto- och autolitografi\nsamt teckningar och maskinretusch.\n\nKontor: Kalendeg. 10. Telegr.-adr.:\nMalmögrafiska, Malmö. Telefon: 24544\no. 28280. Postgiro: 38099.\n\nAkt.-kap.: 35,000 kr. Antal\nindustriarb.: 24. Tillv.-värde pr år: 250,000 kr.\n\n—\tFirman etabl. 1909, bolag 1912.\nStyrelse: hovint. John Kroon (ordf.),\n\nkamrer Gösta Gustafsson, fru Ingrid\nKroon.\n\nVerkst. dir.: John Kroon.\nKamrer: Gösta Gustafsson.",
    "structured": {
        "1": {
            "name": "Malmskogen",
            "location": "Malmö",
            "business": "Träindustri",
            "contact": {
                "office": "Kungsg. 4",
                "sales_offices": [
                    {
                        "location": "Göteborg, Arkaden",
                        "phone": "unknown"
                    },
                    {
                        "location": "Malmö, österg. 11",
                        "phone": "unknown"
                    },
                    {
                        "location": "Norrköping",
                        "phone": "unknown"
                    },
                    {
                        "location": "Gävle",
                        "phone": "unknown"
                    },
                    {
                        "location": "Örebro",
                        "phone": "unknown"
                    },
                    {
                        "location": "Linköping",
                        "phone": "unknown"
                    }
                ],
                "postgiro": "34116",
                "telegraph": "unknown"
            },
            "financials": {
                "capital": "150,000 kr",
                "employees": {
                    "Antal industriarb.": 50
                },
                "annual_turnover": "unknown",
                "annual_production_value": "2,000,000 kr"
            },
            "foundation_year": 1843,
            "corporation_year": 1906,
            "board": [
                {
                    "name": "disp. Alexis Anderson",
                    "role": "unknown"
                },
                {
                    "name": "dir. l£arl Högberg",
                    "role": "unknown"
                },
                {
                    "name": "dir. J. Sande J:or",
                    "role": "unknown"
                }
            ],
            "owners": [
                "AB. Förenade Piano- & Örgelfabriker, Arvika"
            ],
            "director": "Alexis Anderson"
        },
        "2": {
            "name": "AB. Malmskogens Träindustri",
            "location": "Linköping",
            "business": "Tillverkar monteringsfärdiga trähus",
            "contact": {
                "phone": [
                    "97074"
                ],
                "postgiro": "34116"
            },
            "financials": {
                "capital": "52,000 kr",
                "employees": {
                    "Antal industriarb.": 50
                },
                "annual_turnover": "unknown",
                "annual_production_value": "2,000,000 kr"
            },
            "foundation_year": 1933,
            "current_name_year": 1942,
            "board": [
                {
                    "name": "dir. David A. Larsson (ordf.)",
                    "role": "unknown"
                },
                {
                    "name": "byggm. Elof O. Carlsson",
                    "role": "unknown"
                },
                {
                    "name": "disp. A. J. Larsson",
                    "role": "unknown"
                }
            ],
            "managing_director": "David A. Larsson"
        },
        "3": {
            "name": "AB. Lars Malmstedt",
            "location": "Stockholm",
            "business": "Mek. verkstad",
            "contact": {
                "office": "Råggatan 9",
                "phone": [
                    "422329"
                ],
                "postgiro": "193048"
            },
            "financials": {
                "capital": "5,000 kr",
                "employees": {
                    "Antal industriarb.": 9
                },
                "annual_turnover": "unknown",
                "annual_production_value": "100,000 kr"
            },
            "foundation_year": 1943,
            "corporation_year": 1945,
            "director": "fabr. Lars Malmstedt"
        },
        "4": {
            "name": "Malmö Armaturfabrik",
            "location": "Lomma",
            "business": "Armatur- och metallfabrik samt metallgjuteri, förkromnings- och fömicklings-anstalt",
            "contact": {
                "office": "Lomma",
                "phone": "Malmö 462520",
                "postgiro": "38813"
            },
            "financials": {
                "capital": "300,000 kr",
                "employees": {
                    "Antal industriarb.": 55
                },
                "corporation_year": 1907
            },
            "board": [
                {
                    "name": "kontorschef Carl Kristensson",
                    "role": "unknown"
                },
                {
                    "name": "avd.-chef Gunnar Paulsson",
                    "role": "unknown"
                },
                {
                    "name": "ing. Olof Winkler",
                    "role": "unknown"
                }
            ],
            "director": "Sture Wretborg"
        },
        "5": {
            "name": "Malmö Chokolad- & Konfektfabriks. AB.",
            "location": "Malmö",
            "business": "Tillverkar \"Mazetti\" choklad och cacao, marmelad, lakrits, karameller, dragéer, konfityrer och bageriartiklar samt glykos",
            "contact": {
                "office": "Malmö, Skolg. 24",
                "phone": [
                    "\"Mazetti\" o. 70610"
                ]
            },
            "financials": {
                "capital": "1,600,000 kr",
                "employees": {
                    "Antal industriarb.": 420
                },
                "corporation_year": 1888
            },
            "board": [
                {
                    "name": "bankdir. Algot Riider (ordf.)",
                    "role": "unknown"
                },
                {
                    "name": "dir. Gunnar Mazetti-Nissen",
                    "role": "unknown"
                },
                {
                    "name": "dir. Gösta Mazetti-Nissen",
                    "role": "unknown"
                },
                {
                    "name": "dir. Hilding Ståhlbrandt",
                    "role": "unknown"
                }
            ],
            "managing_director": "Gösta Mazetti-Nissen",
            "sales_manager": "Gunnar Mazetti-Nissen"
        },
        "6": {
            "name": "Malmö Förenade Bryggerier",
            "location": "Malmö",
            "business": "Äger Malmquists Bryggeri, Richters Bryggeri och Richters Mälteri. Tillverkar malt och maltdrycker",
            "contact": {
                "office": "Ystadsvägen",
                "phone": [
                    "25350"
                ],
                "postgiro": "unknown"
            },
            "financials": {
                "capital": "5,200,000 kr",
                "employees": {
                    "Antal industriarb.": 105
                },
                "annual_turnover": "4,000,000 kr"
            },
            "corporation_year": 1912,
            "board": [
                {
                    "name": "dir. L. W. Malmquist (ordf.)",
                    "role": "unknown"
                },
                {
                    "name": "disp. C. E. Borgenstierna",
                    "role": "unknown"
                },
                {
                    "name": "dir. Rich. Hain",
                    "role": "unknown"
                },
                {
                    "name": "disp. Fredrik Jungbeck",
                    "role": "unknown"
                },
                {
                    "name": "dir. Erik Malmquist",
                    "role": "unknown"
                }
            ],
            "director": "Erik Malmquist",
            "vice_director": "Gunnar Malmquist"
        },
        "7": {
            "name": "Malmö Grafiska Anstalt",
            "location": "Malmö",
            "business": "Utför klichéer, foto- och autolitografi samt teckningar och maskinretusch",
            "contact": {
                "office": "Kalendeg. 10",
                "phone": [
                    "24544",
                    "28280"
                ],
                "postgiro": "38099",
                "telegraph": "unknown"
            },
            "financials": {
                "capital": "35,000 kr",
                "employees": {
                    "Antal industriarb.": 24
                },
                "annual_production_value": "250,000 kr"
            },
            "corporation_year": 1912,
            "board": [
                {
                    "name": "hovint. John Kroon (ordf.)",
                    "role": "unknown"
                },
                {
                    "name": "kamrer Gösta Gustafsson",
                    "role": "unknown"
                },
                {
                    "name": "fru Ingrid Kroon",
                    "role": "unknown"
                }
            ],
            "director": "John Kroon",
            "kamrer": "Gösta Gustafsson"
        }
    }
}