{
    "original": "Bröderna\n\nAB. Bröderna Claesson,\nABC-fabrlkerna, Kungälv.\n\nTillverkar sport-, camping-, läder- och\nsadelmakeriartiklar, sportskodon,\nresef-fekter, trä- och järnmanufaktur.\n\nTelegr.-adr. o. telefon: Abcfabrikerna,\nKungälv. Postgiro: 7557. Repr. i\nStockholm: M. Åkerbloms Eftr., Tegnérg. 10,\ntelefon: 302212. — Akt.-kap.: 350,000 kr.\nAntal industriarb.: 850. Tillv.-värde pr\når: 10,000,000 kr. — Firman etabl. 1909,\nbolag 1921.\n\nVerTcst. dir.: Ivar S. Claesson.\n\nBröderna Christofferson,\n\nVingåker.\n\nHerrkonfektionsfabrik i Vingåker\n(Södermanl. l.). Tillverkar kostymer,\nsmoking- och frackkostymer samt överplagg.\nVarumärke: »Vinge».\n\nTelefon: 272. Postgiro: 84452. —\nAntal industriarb.: 85. Tillv.-värde pr år:\n900,000 kr. — Firman etabl. 1933.\n\nÄgare o. chefer: fabr. Nils\nChristofferson o. fabr. Eric Christofferson.\n\n* Bröderna Edfasts Skofabrik,\n\nRåneå.\n\nTillverkar sport- och arbetsskodon vid\nfabrik i Råneå (Norrb. l.). Specialitet:\nskidkängor.\n\nTelefon: 78. Postgiro: 60829. —\nAntal industriarb.: 35. Tillv.-värde pr år:\n500,000 kr. — Firman etabl. 1930.\n\nÄgare o. chefer: fabr. Filip Edfast o.\nfabr. John A. Edfast.\n\nBröderna Edmans Stolfabrik, Tibro.\n\nSpecialtillverkning av stolar vid fabrik\ni Tibro (Skarab. l.).\n\nTelefon: 436. — Antal industriarb.:\n23. — Firman etabl. 1941.\n\nÄgare o. chefer: fabr. Sture Edman o.\nfabr. Bertil Edman.\n\nBröderna Ekbergs Eftr. O. Ekberg,\n\nÖrnsköldsvik.\n\nPlåtslageri och mek. verkstad.\nTillverkar kemiska apparater samt\nplåtbearbet-ningsmaskiner såsom figursaxar och\nplåt-bockningsmaskiner.\n\nTelefon: 2417. Postgiro: 63371. —\nAntal industriarb.: 30. Tillv.-värde pr år:\n750,000 kr. — Firman etabl. 1919.\n\nÄgare o. chef: fabr. Oskar Ekberg.\n\nDriftschef: Hugo Ekberg.\n\nBröderna Engblom &amp; C:o.,\n\nKristinehamn.\n\nBorst- och penselfabrik. Tillverkar\nhushållsborstar, toalett.borstar, borstar för\nindustriella ändamål samt penslar och\nträartiklar.\n\nTelegr.-adr.: Enghloms, Kristinehamn.\nTelefon: 10499, 10182 o. 11820. Postgiro:\n27998. — Antal industriarb.: 60. —\nFirman etabl. 1917.\n\nÄgare o. chefer: fabr. Elis Engblom o.\nfabr. Gösta Engblom.\n\n*AB. Bröderna Engdahls Möbelfabrik,\n\nÖrserumsbrunn.\n\nTillverkar möbler vid fabrik i\nörserumsbrunn (Jönköp. l.). Specialitet:\nmatsalsmöbler.\n\nTelefon: 27. Postgiro: 145038.\n\nAkt.-kap.: 40,000 kr. Antal\nindustriarb.: 30. Tillv.-värde pr år: 275,000 kr.\n\n—\tFirman etabl. 1916, bolag 1936.\n\nVerkst. dir.: fabr. Gilbert Engdahl.\n\n*AB. Bröderna Envall, Fellingsbro.\n\nGjuteri, mek. verkstad och plåtslageri\ni Fellingsbro (Örebro l.). Tillverkar\ntransmissioner, ljuskopierings- och\nfram-kallningsmaskiner samt maskiner för\ngasverk och bränntorvindustrien, mekaniska\nverkstadsarbeten, metall- och\ntackjärns-gjutgods m. m.\n\nTelegr.-adr.: Envallbröderna,\nFellingsbro. Telefon: 25, 205. Postgiro: 23136.\nEnsamförsälj. f. ljuskopierings- o.\nfram-kallningsmaskiner: Svenska Kopierings\nAB., Stockholm (se detta bolag).\n\nAkt.-kap.: 75,000 kr. Antal\nindustriarb.: 75. Tillv.-värde pr år: 1,100,000 kr.\n\nFirman grundad 1909 under namn\nFellingsbro Gjuteri &amp; Mek. Verkstad,\nom-bildad till bolag 1925, nuv. namn 1942.\n\nStyrelse: disp. Karl Envall (ordf.),\ning. Bengt Envall, ing. Sven Envall.\n\nVerkst. dir.: Karl Envall.\n\n*Bröderna Eriksons Mek.\nSnickerifabrik, Örebro.\n\nTillverkar byggnadssnickerier och\nlistverk samt lamelldörrar.\n\nTelegr.-adr.: Eriksons Snickeri, Örebro.\nTelefon: 10292 o. 12092. Postgiro: 88399.\n\n—\tAntal industriarb.: 55. Tillv.-värde pr\når: 700,000 kr. — Firman etabl. 1885.\n\nÄgare o. chefer: kapten Oscar I.\nErikson o. ing. K. Gust. Erikson.\n\nKamrer: O. Welin.",
    "structured": {
        "1": {
            "name": "AB. Bröderna Claesson",
            "location": "ABC-fabrikerna, Kungälv",
            "business": "Tillverkar sport-, camping-, läder- och sadelmakeriartiklar, sportskodon, reseffekter, trä- och järnmanufaktur",
            "contact": {
                "office": "Abcfabrikerna, Kungälv",
                "phone": [
                    "302212"
                ],
                "postgiro": "7557"
            },
            "financials": {
                "capital": "350,000 kr",
                "employees": {
                    "industriarb": 850
                },
                "annual_turnover": "10,000,000 kr",
                "annual_production_value": "10,000,000 kr"
            },
            "foundation_year": 1909,
            "corporation_year": 1921,
            "director": "Ivar S. Claesson"
        },
        "2": {
            "name": "Bröderna Christofferson",
            "location": "Vingåker",
            "business": "Herrkonfektionsfabrik i Vingåker (Södermanl. l.). Tillverkar kostymer, smoking- och frackkostymer samt överplagg. Varumärke: »Vinge»",
            "contact": {
                "phone": [
                    "272"
                ],
                "postgiro": "84452"
            },
            "financials": {
                "employees": {
                    "industriarb": 85
                },
                "annual_turnover": "900,000 kr"
            },
            "foundation_year": 1933
        },
        "3": {
            "name": "Bröderna Edfasts Skofabrik",
            "location": "Råneå",
            "business": "Tillverkar sport- och arbetsskodon vid fabrik i Råneå (Norrb. l.). Specialitet: skidkängor",
            "contact": {
                "phone": "78",
                "postgiro": "60829"
            },
            "financials": {
                "employees": {
                    "industriarb": 35
                },
                "annual_turnover": "500,000 kr"
            },
            "foundation_year": 1930
        },
        "4": {
            "name": "Bröderna Edmans Stolfabrik",
            "location": "Tibro",
            "business": "Specialtillverkning av stolar vid fabrik i Tibro (Skarab. l.)",
            "contact": {
                "phone": "436"
            },
            "financials": {
                "employees": {
                    "industriarb": 23
                }
            },
            "foundation_year": 1941
        },
        "5": {
            "name": "Bröderna Ekbergs Eftr. O. Ekberg",
            "location": "Örnsköldsvik",
            "business": "Plåtslageri och mek. verkstad. Tillverkar kemiska apparater samt plåtbearbetningsmaskiner såsom figursaxar och plåtbokningsmaskiner",
            "contact": {
                "phone": "2417",
                "postgiro": "63371"
            },
            "financials": {
                "employees": {
                    "industriarb": 30
                },
                "annual_turnover": "750,000 kr"
            },
            "foundation_year": 1919,
            "director": "Oskar Ekberg",
            "sales_manager": "Hugo Ekberg"
        },
        "6": {
            "name": "Bröderna Engblom & C:o.",
            "location": "Kristinehamn",
            "business": "Borst- och penselfabrik. Tillverkar hushållsborstar, toalett.borstar, borstar för industriella ändamål samt penslar och träartiklar",
            "contact": {
                "phone": [
                    "10499",
                    "10182",
                    "11820"
                ],
                "postgiro": "27998"
            },
            "financials": {
                "employees": {
                    "industriarb": 60
                }
            },
            "foundation_year": 1917
        },
        "7": {
            "name": "AB. Bröderna Engdahls Möbelfabrik",
            "location": "Örserumsbrunn",
            "business": "Tillverkar möbler vid fabrik i Örserumsbrunn (Jönköp. l.). Specialitet: matsalsmöbler",
            "contact": {
                "phone": "27",
                "postgiro": "145038"
            },
            "financials": {
                "capital": "40,000 kr",
                "employees": {
                    "industriarb": 30
                },
                "annual_turnover": "275,000 kr"
            },
            "foundation_year": 1916,
            "corporation_year": 1936,
            "director": "Gilbert Engdahl"
        },
        "8": {
            "name": "AB. Bröderna Envall",
            "location": "Fellingsbro",
            "business": "Gjuteri, mek. verkstad och plåtslageri i Fellingsbro (Örebro l.). Tillverkar transmissioner, ljuskopierings- och framkallningsmaskiner samt maskiner för gasverk och bränntorvindustrien, mekaniska verkstadsarbeten, metall- och tackjärnsgjutgods m. m",
            "contact": {
                "phone": [
                    "25",
                    "205"
                ],
                "postgiro": "23136"
            },
            "financials": {
                "capital": "75,000 kr",
                "employees": {
                    "industriarb": 75
                },
                "annual_turnover": "1,100,000 kr"
            },
            "foundation_year": 1909,
            "corporation_year": 1942,
            "board": [
                {
                    "name": "Karl Envall",
                    "role": "disp."
                },
                {
                    "name": "Bengt Envall",
                    "role": "ing."
                },
                {
                    "name": "Sven Envall",
                    "role": "ing."
                }
            ],
            "director": "Karl Envall"
        },
        "9": {
            "name": "Bröderna Eriksons Mek. Snickerifabrik",
            "location": "Örebro",
            "business": "Tillverkar byggnadssnickerier och listverk samt lamelldörrar",
            "contact": {
                "phone": [
                    "10292",
                    "12092"
                ],
                "postgiro": "88399"
            },
            "financials": {
                "employees": {
                    "industriarb": 55
                },
                "annual_turnover": "700,000 kr"
            },
            "foundation_year": 1885,
            "manager": "O. Welin"
        }
    }
}