{
    "original": "Hallstahammar—Halmstad\n\nmerade stålaxlar samt kalldraget järn.,\nstål och automat järn. Bolaget idkar\njämväl jordbruk, skogshantering och\nsågverksrörelse.\n\nKontor: Hallstahammar. Telegr.-adr.:\nHallstahammar, Kolbäck. Telefon:\n»Hall-stahammars Bruk». Postgiro: 13379.\n\nAkt.-kap.: 2,000,000 kr. Antal\nindustriarb.: 300. Tillv.-värde pr år: 6,000,000 kr.\n— Bolaget grundat 1872.\n\nStyrelse; dir. Ivar O. Larson (ordf.),\ndisp. Hilding Agrell, disp. Per Gr.\nEkman, disp. Uno O. Larson.\nVerkst. dir.: Hilding Agrell.\nDriftsingenjörer: K. R. Trybom o. Arne\nWesterberg.\n\nKamrer: John Carlsson.\nFörsäljn. o. inköp.- H. Bosson.\n\n*Hallstahammars Bultfabrik,\n\nHallstahammar.\n\nSe Bultfabriks AB., Hallstahammar.\n\n\"Hallstanäs Träsliperi, Björhabruk.\nSe Björkå AB., Björkåbruk.\n\nHallströms Kassaskåps &amp; Mek.\nVerkstads AB., Ulvsunda.\n\nTillverkar kassaskåp, arkiv- och\ndokumentskåp, kassavalvsdörrar och isolerade\nbranddörrar samt vattenvärmare (märke:\n»Gurus») vid mek. verkstad i Ulvsunda,\nStockholm.\n\nKontor: Johannesfredsvägen 14,\nUlvsunda. Telefon: Stockholm 257363 och\n258216. Postgiro: 54060. — Akt.-kap.:\n14,200 kr. Antal industriarb.: 14.\nTillv.-värde pr år: 200,000 kr. — Firman etabl.\n1937.\n\nChef: fabr. John Hallström.\n\n\"Hallströms Möbelfabriks AB.,\nBröderna ,Tibro.\n\nSe Bröderna Hallströms Möbelfabrik\nAB., Tibro.\n\n\"Hallström &amp; Nisses,\nByggnadsbolaget, Sundsvall.\n\nSe Byggnads AB. Hallström &amp; Nisses,\nSundsvall.\n\n\"Halmstad-Falkenbergs Kvarn AB.,\n\nHalmstad.\n\nKvarnar i Halmstad och Falkenberg.\nTillverkar mjöl av vete och råg samt\nfodermjöl och kli. Varunamn för vetemjöl:\n»Kungsörnen», »örnen» m. fl.\n\n14\n\nHuvudkontor: Malmö. Avd.-kontor:\nHalmstad o. Falkenberg. Telegr.-adr.:\nKvarnarna, Halmstad. Telefon:\nHalmstad 1402 o. Falkenberg 271. Postgiro:\n15001.\n\nAkt.-kap.: 1,001,800 kr. Antal\nindustriarb.: i Halmstad 38, i Falkenberg 25.\nProd.-värde pr år: 7,250,000 kr.\n\nBolaget, som bildades 1929 genom\nsammanslagning av AB. Falkenbergs Elektr.\nValskvarn, etabl. 1904, och J. Jacobssons\nAB., Halmstad, etabl. 1890, tillhör AB.\nKvarnintressenter, Malmö.\n\nStyrelse: dir. Mauritz Carlson (ordf.),\ndir. Sven Malmberg, dir. Edvin Åberg.\nVerkst. dir.: S. Malmberg (Malmö).\nPlatschef: disp. Ad. Pehrson.\n\n* Halmstads Filtfabrik, Halmstad.\nSe AB. Malcus Holmquist, Halmstad.\n\n\"Halmstads Järnvaru AB., Halmstad.\nSe Aug. Hanssons Gjuteri, Halmstad.\n\n\"Halmstads Järnverks AB.,\n\nHalmstad.\n\nTillverkar martinjärn i form av göten,\nbillets, stång- och fasonjärn, band järn\nsamt valstråd. Specialiteter: valstråd och\narmeringsjärn.\n\nTelegr.-adr.: Stålverket, Halmstad.\nTelefon: 1333. Postgiro: 30537.\n\nAkt.-kap.: 1,080,000 kr. Antal\nindustriarb.: 230; Tillv.-värde pr år: 7,300,000 kr.\n\n—\tBolaget grundat 1916, ombildät 1921.\nStyrelse: disp. Allan Boo, disp. Bengt\n\nCarleson, disp. Hans v. Kantzow, frih.\nW. Klingspor, adv. Hugo Stenbeck,\nVerkst. dir. o. disp: Allan Boo.\nDir.-assist.: civiling. Göran Lindblom.\nKamrer: C. Dubois.\nDriftsingenjörer: C.-Hj. Forslund o.\nHans Söderberg.\n\n\"Halmstads Nya Verkstads AB.,\n\nHalmstad.\n\nMek. verkstad, gjuteri och plåtslageri.\nTillverkar lyftverktyg och kranar för\nhand- och elektr. kraft, gjuteri maskiner,\nsnack- och kuggväxlar,\ngummivaruma-skiner samt plåtslageriarbeten, gjutgods\nm. m.\n\nTelegr.-adr.: Verkstäderna. Halmstad.\nTelefon: »Malcus». Ensamförsälj. för\nlyftverktyg, kranar o. gjuterimaskiner:\nAB. Malcus Holmquist, Halmstad.\n\nAkt.-kap.: 525,000 kr. Antal\nindustriarb.: 120. Tillv.-värde pr år: 1,500,000 kr.\n\n—\tBolaget, grundat 1875 under namn",
    "structured": {
        "1": {
            "name": "Hallstahammars Bruk",
            "location": "Hallstahammar",
            "business": "Tillverkar stålaxlar samt kalldraget järn, stål och automatjärn.",
            "contact": {
                "office": "Hallstahammar",
                "phone": [
                    "Hall-stahammars Bruk"
                ],
                "postgiro": "13379"
            },
            "financials": {
                "capital": "2,000,000 kr",
                "employees": {
                    "industriarb": 300
                },
                "annual_turnover": "6,000,000 kr",
                "annual_production_value": "6,000,000 kr"
            },
            "foundation_year": 1872,
            "board": [
                {
                    "name": "Ivar O. Larson",
                    "role": "ordf."
                },
                {
                    "name": "Hilding Agrell",
                    "role": "disp."
                },
                {
                    "name": "Per Gr. Ekman",
                    "role": "disp."
                },
                {
                    "name": "Uno O. Larson",
                    "role": "disp."
                }
            ],
            "director": "Hilding Agrell",
            "kamrer": "John Carlsson",
            "sales_manager": "H. Bosson"
        },
        "2": {
            "name": "Hallströms Kassaskåps & Mek. Verkstads AB.",
            "location": "Ulvsunda",
            "business": "Tillverkar kassaskåp, arkiv- och dokumentskåp, kassavalvsdörrar samt isolerade branddörrar samt vattenvärmare (märke: Gurus)",
            "contact": {
                "office": "Johannesfredsvägen 14, Ulvsunda",
                "phone": [
                    "Stockholm 257363",
                    "258216"
                ],
                "postgiro": "54060"
            },
            "financials": {
                "capital": "14,200 kr",
                "employees": {
                    "industriarb": 14
                },
                "annual_turnover": "200,000 kr"
            },
            "foundation_year": 1937,
            "manager": "John Hallström"
        },
        "3": {
            "name": "Halmstad-Falkenbergs Kvarn AB.",
            "location": "Halmstad",
            "business": "Tillverkar mjöl av vete och råg samt fodermjöl och kli",
            "contact": {
                "head_office": "Malmö",
                "sales_offices": [
                    {
                        "location": "Halmstad",
                        "phone": "1402"
                    },
                    {
                        "location": "Falkenberg",
                        "phone": "271"
                    }
                ],
                "postgiro": "15001"
            },
            "financials": {
                "capital": "1,001,800 kr",
                "employees": {
                    "Halmstad": 38,
                    "Falkenberg": 25
                },
                "annual_production_value": "7,250,000 kr"
            },
            "corporation_year": 1929,
            "board": [
                {
                    "name": "Mauritz Carlson",
                    "role": "ordf."
                },
                {
                    "name": "Sven Malmberg",
                    "role": "dir."
                },
                {
                    "name": "Edvin Åberg",
                    "role": "dir."
                }
            ],
            "managing_director": "S. Malmberg"
        },
        "4": {
            "name": "Halmstads Järnverks AB.",
            "location": "Halmstad",
            "business": "Tillverkar martinjärn i form av göten, billets, stång- och fasonjärn, bandjärn samt valstråd.",
            "contact": {
                "office": "Halmstad",
                "phone": "1333",
                "postgiro": "30537"
            },
            "financials": {
                "capital": "1,080,000 kr",
                "employees": 230,
                "annual_production_value": "7,300,000 kr"
            },
            "corporation_year": 1921,
            "board": [
                {
                    "name": "Allan Boo",
                    "role": "disp."
                },
                {
                    "name": "Bengt Carleson",
                    "role": "disp."
                },
                {
                    "name": "Hans v. Kantzow",
                    "role": "disp."
                },
                {
                    "name": "W. Klingspor",
                    "role": "frih."
                },
                {
                    "name": "Hugo Stenbeck",
                    "role": "adv."
                }
            ],
            "managing_director": "Allan Boo"
        },
        "5": {
            "name": "Halmstads Nya Verkstads AB.",
            "location": "Halmstad",
            "business": "Mek. verkstad, gjuteri och plåtslageri. Tillverkar lyftverktyg och kranard",
            "contact": {
                "office": "Halmstad",
                "phone": "Malcus",
                "postgiro": null
            },
            "financials": {
                "capital": "525,000 kr",
                "employees": 120,
                "annual_production_value": "1,500,000 kr"
            },
            "foundation_year": 1875,
            "director": null,
            "manager": "AB. Malcus Holmquist"
        }
    }
}