{
    "original": "Lessebo—JAbo\n\nark; 500. Årstillv.: 11,500 ton finpapper\no. kartong, 10,000 ton sulfitcellulosa.\n\nBolaget äges av AB. Klippans\nFinpappersbruk.\n\nStyrelse: bankir Tage Cervin (ordf.),\nbankdir. Allan Alexanderson, dir. P. Eg.\nGummeson, f. d. bankdir. H. K.\nLaurit-zen, dir. Carl Joh. Malmros.\n\nVerkst. dir. o. disp.: Carl Joh.\nMalmros.\n\nPlatschef: jägmäst. Alf Winbladh.\n\nFabrikschef: ing. Tage Engström.\n\nKamrer: Karl-Gustaf Bergvall.\n\nAB. Lessebo Skogar, Klippan.\n\nSågverk, hyvleri, lådfabrik samt\nim-pregneringsanläggning enligt Bolidens\ntryckmetod vid Lessebo (Kronob. l.).\nTillverkar sågade och hyvlade trävaror, stav,\nlådbräder, träkol, tjära m. m. samt utför\nimpregnering av sågat virke, stolpar,\nslipers m. m. Bolaget driver även skogsbruk.\n\nHuvudkontor: Klippan.\nSågverkskontor: Lessebo. Telegr.-adr.: Woodex,\nLessebo. Telefon: Lessebo 1. Postgiro: 9243.\n\nAkt.-kap,: 1,200,000 kr. Antal\nindustriarb.: 112. Årstillv.: 1,000 stds sågade o,\n500 stds hyvlade trävaror, 2,500 stds\nstav o. lådbräder.\n\nBolaget, grundat 1903, äges av AB.\nKlippans Finpappersbruk.\n\nStyrelse: bankir Tage Cervin (ordf.),\nbankdir. Allan Alexanderson, dir. P. Eg.\nGummeson, f. d, bankdir. H. K.\nLaurit-zen, dir. Carl Joh. Malmros.\n\nVerkst. dir.: Carl Joh. Malmros.\n\nPlatschef: jägmäst. Alf Winbladh.\n\nIntendent: A. Abrahamsson.\n\n*Le$slie Konfektionsfabrik, Göteborg.\n\nSe Konfektions AB. Lesslie, Göteborg.\n\nLevanten, Färgeri AB., Göteborg.\n\nSe Färgeri AB. Levanten, Göteborg.\n\nAB. Levin Strå- &amp; Filthattfabrik,\n\nStockholm.\n\nTillverkar damhattar av strå och filt\nsamt dammössor. Bolaget driver jämväl\nengroshandel med modevaror.\n\nKontor: Svarvarg. 11. Telegr.-adr.:\nLabist, Stockholm. Telefon: 520215.\nPostgiro: 50280.\n\nAkt.-kap.: 250,000 kr. Antal\nindustriarb.: 85. Försäljn.-värde pr år: 1,800,000\nkr. — Firman etabl. 1886.\n\nStyrelse: dir. Josef Benno, adv. Tore\nLindell.\n\nVerkst. dir.: J. Benno.\n\n*AB. Herman Carlson Levin,\n\nGöteborg.\n\nMusikinstrumentfabrik. ^ Tillverkar\nstränginstrument såsom gitarrer, lutor\noch mandoliner samt trummor.\n\nKontor: Lilla Bommens torg 2.\nTelefon: 133116. Postgiro: 40680.\n\nAkt.-kap.: 204,000 kr. Antal\nindustriarb.: 112. Tillv.-värde pr år: 1,300,000 kr.\n\n—\tFirman etabl. 1900, bolag 1939.\nStyrelse o. verkst. dir.: Herman\nCarlson Levin.\n\nAB. K. J. Levin, Malmö.\n\nMek. verkstad. Tillverkar kommers,\nkylanläggningar och varuautomater.\nFirman driver även försäljning av kylskåp\nsamt tvätt- och köksmaskiner.\n\nKontor: Lövviksg. 13. Telegr.-adr.:\nLevinautomat, Malmö. Telefon: 71155.\nPostgiro: 38071.\n\nAkt.-kap.: 300,000 kr. Antal\nindustriarb.: 90. Tillv.-värde pr år: 800,000 kr.\n\n—\tBolaget grundat 1925. ^\nVerkst. dir.: K. J. Levin.\n\nMartin Levissons Söner,\n\nGöteborg.\n\nGarveri. Tillverkar bottenläder,\nbind-sulläder och plattläder.\n\nKontor: Mölndalsvägen 14.\nTelegr.-adr.: Levisoener, Göteborg, Telefon:\n161065. Postgiro: 42058. — Antal\nindustriarb.: 25. — Firman etabl. 1848.\nÄgare o. chef: disp. Einar Lamm.\n\n*Li Snickerifabrik AB., Stockholm.\n\nTillverkar möbler och inredningar vid\nfabrik i Liatorp (Kronob. l.).\n\nKontor: Stockholm; Drottningg. 14.\nTelefon: 207840. Postgiro: 274560.\n\nAkt.-kap.: 10,000 kr. Antal\nindustriarb.: 17. Tillv.-värde pr år: 200,000 kr.\n\n—\tBolaget grundat 1943. ■ »’\nStyrelse o. verkst, direktörer: ing.\n\nHenrik Mattsson o. ing. Henry\nWalle-stam.\n\n*B. &amp; O. Libergs Fabriks AB.,\n\nSkogstorp.\n\nSe Eskilstuna Jernmanuf åktur AB.r\nEskilstuna.\n\n*AB. Libo-Konfektiofi, Boras.\n\nKonfektions- och ylletrikåfabrik,\nTillverkar sport- och poplinskjortor samt\npyjamas för herrar och gossar, byxor,\nsportjackor, skiddräkter samt sommarkläder\n\n325*",
    "structured": {
        "firms": [
            {
                "name": "AB. Lessebo Skogar, Klippan",
                "location": "Klippan",
                "business": "Sågverk, hyvleri, lådfabrik samt impregneringsanläggning enligt Bolidens tryckmetod vid Lessebo (Kronob. l.)",
                "contact": {
                    "head_office": "Klippan",
                    "sales_offices": [
                        {
                            "location": "Lessebo",
                            "phone": "Lessebo 1"
                        }
                    ],
                    "telegraph": "Woodex, Lessebo",
                    "postgiro": "9243"
                },
                "financials": {
                    "capital": "1,200,000 kr",
                    "employees": {
                        "industriarb.": 112
                    },
                    "annual_production_value": "1,800,000 kr"
                },
                "foundation_year": 1903,
                "owners": [
                    "AB. Klippans Finpappersbruk"
                ],
                "board": [
                    {
                        "name": "bankir Tage Cervin",
                        "role": "ordf."
                    },
                    {
                        "name": "bankdir. Allan Alexanderson",
                        "role": ""
                    },
                    {
                        "name": "dir. P. Eg. Gummeson",
                        "role": ""
                    },
                    {
                        "name": "f. d. bankdir. H. K. Laurit-zen",
                        "role": ""
                    },
                    {
                        "name": "dir. Carl Joh. Malmros",
                        "role": ""
                    }
                ],
                "director": "Carl Joh. Malmros"
            },
            {
                "name": "AB. Levin Strå- & Filthattfabrik, Stockholm",
                "location": "Stockholm",
                "business": "Tillverkar damhattar av strå och filt samt dammössor",
                "contact": {
                    "office": "Svarvarg. 11",
                    "telegraph": "Labist, Stockholm",
                    "phone": "520215",
                    "postgiro": "50280"
                },
                "financials": {
                    "capital": "250,000 kr",
                    "employees": {
                        "industriarb.": 85
                    },
                    "annual_turnover": "1,800,000 kr"
                },
                "foundation_year": 1886,
                "board": [
                    {
                        "name": "dir. Josef Benno",
                        "role": ""
                    },
                    {
                        "name": "adv. Tore Lindell",
                        "role": ""
                    }
                ],
                "director": "J. Benno"
            },
            {
                "name": "AB. Herman Carlson Levin, Göteborg",
                "location": "Göteborg",
                "business": "Musikinstrumentfabrik. Tillverkar stränginstrument såsom gitarrer, lutor och mandoliner samt trummor",
                "contact": {
                    "office": "Lilla Bommens torg 2",
                    "phone": "133116",
                    "postgiro": "40680"
                },
                "financials": {
                    "capital": "204,000 kr",
                    "employees": {
                        "industriarb.": 112
                    },
                    "annual_production_value": "1,300,000 kr"
                },
                "foundation_year": 1900,
                "board": [
                    {
                        "name": "Herman Carlson Levin",
                        "role": ""
                    }
                ],
                "director": "Herman Carlson Levin"
            },
            {
                "name": "AB. K. J. Levin, Malmö",
                "location": "Malmö",
                "business": "Mek. verkstad. Tillverkar kommers, kylanläggningar och varuautomater. Firman driver även försäljning av kylskåp samt tvätt- och köksmaskiner",
                "contact": {
                    "office": "Lövviksg. 13",
                    "telegraph": "Levinautomat, Malmö",
                    "phone": "71155",
                    "postgiro": "38071"
                },
                "financials": {
                    "capital": "300,000 kr",
                    "employees": {
                        "industriarb.": 90
                    },
                    "annual_turnover": "800,000 kr"
                },
                "foundation_year": 1925,
                "director": "K. J. Levin"
            },
            {
                "name": "Martin Levissons Söner, Göteborg",
                "location": "Göteborg",
                "business": "Garveri. Tillverkar bottenläder, bindsulläder och plattläder",
                "contact": {
                    "office": "Mölndalsvägen 14",
                    "telegraph": "Levisoener, Göteborg",
                    "phone": "161065",
                    "postgiro": "42058"
                },
                "employees": 25,
                "director": "disp. Einar Lamm"
            },
            {
                "name": "Li Snickerifabrik AB., Stockholm",
                "location": "Stockholm",
                "business": "Tillverkar möbler och inredningar vid fabrik i Liatorp (Kronob. l.)",
                "contact": {
                    "office": "Drottningg. 14",
                    "phone": "207840",
                    "postgiro": "274560"
                },
                "financials": {
                    "capital": "10,000 kr",
                    "employees": {
                        "industriarb.": 17
                    },
                    "annual_production_value": "200,000 kr"
                },
                "foundation_year": 1943,
                "board": [
                    {
                        "name": "ing. Henrik Mattsson",
                        "role": ""
                    },
                    {
                        "name": "ing. Henry Wallestam",
                        "role": ""
                    }
                ]
            }
        ]
    }
}