{
    "original": "J ochnicJc—J ohannisberg\n\n—\tTelefon: »Ji-Te bolaget» eller 600.\nPostgiro: 9333. Repr. i Stockholm,\nLäst-makareg. 3, telefon: 234245.\n\nAkt.-kap.: 300,000 kr. Antal\nindustriarb.: 250. Tillv.-värde pr år: 4,000,000 kr.\n\nFirman etabl. 1902 under namn J.\nJohanssons Träförädlingsfabrik, nuv. bolag\n1937.\n\nStyrelse: dir. Paul Johansson (ordf.),\nkamrer Göte Johansson (v. ordf.), docent\nCarl-Hugo Johansson, fru Elsa\nJohansson, fröken H. Johansson.\n\nDir.: Paul Johansson.\n\nKamrer: Göte Johansson.\n\nFörsäljn.-chef er: för dörrfabr.: M.\nFranzén o. B. Åkesson; för trävaror o.\nbyggnadsmaterial: Nils Johansson.\n\nLaboratoriechef: dr H. Baumann.\n\nAB. Jochnick &amp; Norrmans Mek.\nVerkstad, Värnamo.\n\nTillverkar verktygsmaskiner samt utför\nvärme- och sanitetsanläggningar.\nSpecialitet: kipphyvlar (shapingmaskiner).\n\nTelegr.-adr.: Jochnick, Värnamo.\nTelefon: 10030 o. 10313. Postgiro: 26640.\n\nAkt.-kap.: 100,000 kr. Antal\nindustriarb.: 45. Tillv.-värde pr år: 750,000 kr.\n\n—\tFirman etabl. 1910, bolag 1943.\n\nVerkst. dir.: fabr. Gösta Jochnick.\n\n*Jofa, Jonssons Fabriker AB.,\n\nMalung.\n\nSportartikel- och lädervaruf abrik i\nMalung (Kopparb. !.).\n\nTillverkar sportartiklar såsom\nskid-stavar och -bindningar, ryggsäckar,\nsport-väskor, tält, sporthandskar,\narbetshand-skar, herr- och damhandskar, damväskor,\nportföljer, seldon och sportskodon,\nskinntröjor och -jackor, promenad- och\nsportpälsar, skiddräkter, sovsäckar,\nhängmattor, trädgårdsparasoller, vilstolar,\nrattkälkar och sparkstöttingar m. m.\nVarumärken: »Jofa» o, »Jofama». Firman är\nensamförsälj. av skidor och möbler för\nAB. Tallåsens Fabriker, Tallåsen.\n\nTelegr.-adr. o. telefon: »Jofabolaget»,\nMalung. Postgiro: 27363. Nederlag:\nStockholm, Eriksbergsg. 4, telefon:\n107534—35; Göteborg, Lilla Torget 2,\ntelefon: 131245; Malmö, Baltzarsg. 32,\ntelefon: 79320.\n\nAkt.-kap.: 600,000 kr. Antal\nindustriarb.: 150. Tillv.-värde pr år: 5,000,000 kr.\n\n—\tFirman etabl. 1926, bolag 1940.\n\nStyrelse: disp. Ewert Eriksson, dir. N.\n\nOskar Jonsson.\n\nVerkst. dir.: N. Oskar Jonsson.\n\nKontorschef: Ewert Eriksson.\n\nFörsäljn.-chef: Alfred Strömbäck.\n\nInhöpschef: Sven Bohm.\n\nAB. dofur, Stockholm.\n\nKem.-teknisk fabrik vid Lövholmen,\nStockholm. Tillverkar\nväxtbesprutnings-medel, konstgödselmedel samt preparat för\nhusdjursvård.\n\nKontor: Lövholmsgränd 12; postadr.:\nStockholm 1. Telefon: 453010 o. 453020.\nPostgiro: 153000. Ensamförsälj.:\nJofur-Sterisolbolagen, Lövholmsgränd 12.\n\nAkt.-kap.: 12,500 kr. — Bolaget,\ngrundat 1938, är dotterbolag till AB. Wilh.\nBecker, Stockholm.\n\nVerkst. dir.: Gösta Browall.\n\n*Johannedals Wallboardfabrik,\n\nSundsvall.\n\nSe Ankarsviks Ängsågs AB., Sundsvall.\n\n*Johannesbergs Lådfabrik, V.\nKriström, Stockholm.\n\nTillverkar lådor och lådämnen,\nramlister, bilflak, byggnadssnickerier samt\nbyggnadsställningar vid fabrik i\nUpplands Väsby (Sthlms l.).\n\nKontor: Kungsg. 50. Telefon: 115474 o.\n115574. Postgiro: 58625. — Antal\nindustriarb.: 20. Tillv.-värde pr år: 300,000\nkr. — Firman etabl. 1935.\n\nÄgare o. chef: grossh. Viktor Kriström.\n\nJohannesborgs Möbelfabriks AB.,\n\nLinköping.\n\nTillverkar möbler.\n\nTelefon: 21120. Postgiro:\n8480.-Akt.-kap.: 174,800 kr. Antal industriarb.: 58.\nTillv.-värde pr år: 600,000 kr. — Bolaget\ngrundat 1917.\n\nDisp.: Ivar Nyman.\n\nAB. Arne Johannessens\nShoddy-fabrik, Partille.\n\nShoddyfabrik i Partille (Göteb. o.\nBohus l.). Tillverkar bomulls- och ylleshoddy\nför textilindustrien samt vitt och kulört\ntrassel.\n\nTelegr.-adr.: Shoddyfabriken, Partille.\nTelefon: 21. Postgiro: 92828. —\nAkt.-kap.: 100,000 kr. Arb.-antal: 35.\nTillv.-värde pr år: 850,000 kr. — Firman etabl.\n1914, bolag 1942.\n\nDisp.: Einar Johannessen.\n\n*AB. Johannisbergs Bryggeri,\n\nJ ohannisberg.\n\nTillverkar maltdrycker och\nläskedrycker vid bryggeri i J ohannisberg\n(Västernorrl. l.),",
    "structured": {
        "1": {
            "name": "Johannisberg",
            "location": "Johannisberg",
            "business": "Tillverkar maltdrycker och läskedrycker",
            "contact": {
                "office": "Johannisberg",
                "phone": [
                    "N/A"
                ],
                "postgiro": "N/A",
                "head_office": "N/A",
                "sales_offices": [],
                "telegraph": "N/A",
                "factory_office": "N/A",
                "factory_phone": "N/A"
            },
            "financials": {
                "capital": "N/A",
                "employees": {},
                "annual_turnover": "N/A",
                "annual_production_value": "N/A"
            },
            "foundation_year": "N/A",
            "current_name_year": "N/A",
            "predecessor": "N/A",
            "original_name": "N/A",
            "corporation_year": "N/A",
            "board": [],
            "owners": [],
            "director": "N/A",
            "managing_director": "N/A",
            "sales_manager": "N/A",
            "manager": "N/A"
        },
        "2": {
            "name": "Jochnick & Norrmans Mek. Verkstad",
            "location": "Värnamo",
            "business": "Tillverkar verktygsmaskiner samt utför värme- och sanitetsanläggningar",
            "contact": {
                "office": "Jochnick & Norrmans Mek. Verkstad, Värnamo",
                "phone": [
                    "10030",
                    "10313"
                ],
                "postgiro": "26640",
                "head_office": "N/A",
                "sales_offices": [],
                "telegraph": "Jochnick, Värnamo",
                "factory_office": "N/A",
                "factory_phone": "N/A"
            },
            "financials": {
                "capital": "100,000 kr",
                "employees": {},
                "annual_turnover": "N/A",
                "annual_production_value": "750,000 kr"
            },
            "foundation_year": "N/A",
            "current_name_year": "N/A",
            "predecessor": "N/A",
            "original_name": "N/A",
            "corporation_year": "N/A",
            "board": [],
            "owners": [],
            "director": "Gösta Jochnick",
            "managing_director": "N/A",
            "sales_manager": "N/A",
            "manager": "N/A"
        },
        "3": {
            "name": "Jofa, Jonssons Fabriker AB.",
            "location": "Malung",
            "business": "Sportartikel- och lädervarufabrik",
            "contact": {
                "office": "Jofa, Jonssons Fabriker AB., Malung",
                "phone": [
                    "N/A"
                ],
                "postgiro": "27363",
                "head_office": "N/A",
                "sales_offices": [
                    {
                        "location": "Stockholm",
                        "phone": "107534–35"
                    },
                    {
                        "location": "Göteborg",
                        "phone": "131245"
                    },
                    {
                        "location": "Malmö",
                        "phone": "79320"
                    }
                ],
                "telegraph": "Jofabolaget, Malung",
                "factory_office": "N/A",
                "factory_phone": "N/A"
            },
            "financials": {
                "capital": "600,000 kr",
                "employees": {},
                "annual_turnover": "N/A",
                "annual_production_value": "5,000,000 kr"
            },
            "foundation_year": "N/A",
            "current_name_year": "N/A",
            "predecessor": "N/A",
            "original_name": "N/A",
            "corporation_year": "N/A",
            "board": [],
            "owners": [],
            "director": "N/A",
            "managing_director": "N/A",
            "sales_manager": "N/A",
            "manager": "N/A"
        },
        "4": {
            "name": "Johannedals Wallboardfabrik",
            "location": "Sundsvall",
            "business": "N/A",
            "contact": {
                "office": "N/A",
                "phone": [
                    "N/A"
                ],
                "postgiro": "N/A",
                "head_office": "N/A",
                "sales_offices": [],
                "telegraph": "N/A",
                "factory_office": "N/A",
                "factory_phone": "N/A"
            },
            "financials": {
                "capital": "N/A",
                "employees": {},
                "annual_turnover": "N/A",
                "annual_production_value": "N/A"
            },
            "foundation_year": "N/A",
            "current_name_year": "N/A",
            "predecessor": "N/A",
            "original_name": "N/A",
            "corporation_year": "N/A",
            "board": [],
            "owners": [],
            "director": "N/A",
            "managing_director": "N/A",
            "sales_manager": "N/A",
            "manager": "N/A"
        },
        "5": {
            "name": "Johannesbergs Lådfabrik",
            "location": "V. Kriström, Stockholm",
            "business": "Tillverkar lådor och lådämnen, ramlister, bilflak, byggnadssnickerier samt byggnadsställningar",
            "contact": {
                "office": "Kungsg. 50",
                "phone": [
                    "115474",
                    "115574"
                ],
                "postgiro": "58625",
                "head_office": "N/A",
                "sales_offices": [],
                "telegraph": "N/A",
                "factory_office": "N/A",
                "factory_phone": "N/A"
            },
            "financials": {
                "capital": "N/A",
                "employees": {},
                "annual_turnover": "N/A",
                "annual_production_value": "300,000 kr"
            },
            "foundation_year": 1935,
            "current_name_year": "N/A",
            "predecessor": "N/A",
            "original_name": "N/A",
            "corporation_year": "N/A",
            "board": [],
            "owners": [
                "Viktor Kriström"
            ],
            "director": "N/A",
            "managing_director": "N/A",
            "sales_manager": "N/A",
            "manager": "N/A"
        },
        "6": {
            "name": "Johannesborgs Möbelfabriks AB.",
            "location": "Linköping",
            "business": "Tillverkar möbler",
            "contact": {
                "office": "N/A",
                "phone": [
                    "21120"
                ],
                "postgiro": "8480",
                "head_office": "N/A",
                "sales_offices": [],
                "telegraph": "N/A",
                "factory_office": "N/A",
                "factory_phone": "N/A"
            },
            "financials": {
                "capital": "174,800 kr",
                "employees": {},
                "annual_turnover": "N/A",
                "annual_production_value": "600,000 kr"
            },
            "foundation_year": "N/A",
            "current_name_year": "N/A",
            "predecessor": "N/A",
            "original_name": "N/A",
            "corporation_year": "N/A",
            "board": [],
            "owners": [],
            "director": "N/A",
            "managing_director": "N/A",
            "sales_manager": "N/A",
            "manager": "Ivar Nyman"
        },
        "7": {
            "name": "AB. Arne Johannessens Shoddy-fabrik",
            "location": "Partille",
            "business": "Shoddyfabrik",
            "contact": {
                "office": "AB. Arne Johannessens Shoddy-fabrik, Partille",
                "phone": [
                    "21"
                ],
                "postgiro": "92828",
                "head_office": "N/A",
                "sales_offices": [],
                "telegraph": "Shoddyfabriken, Partille",
                "factory_office": "N/A",
                "factory_phone": "N/A"
            },
            "financials": {
                "capital": "100,000 kr",
                "employees": {},
                "annual_turnover": "N/A",
                "annual_production_value": "850,000 kr"
            },
            "foundation_year": 1914,
            "current_name_year": "N/A",
            "predecessor": "N/A",
            "original_name": "N/A",
            "corporation_year": "N/A",
            "board": [],
            "owners": [],
            "director": "N/A",
            "managing_director": "N/A",
            "sales_manager": "N/A",
            "manager": "Einar Johannessen"
        }
    }
}