{
    "original": "Marstrandsfjorden—Maskinfabrik\n\nTelegr.-adr.: Motorverkstaden,\nMarstrand. Telefon: 5 o. 45. Postgiro: 6936.\n\nAkt.-kap.: 270,000 kr. Antal\nindustriarb.: 150. Tillv.-värde pr år: 1,500,000 kr.\n—- Bolaget grundat 1904.\n\nStyrelse: dir. Bertil Egnell (ordf.),\ndir. Anders Melin-Högrell.\n\nVerkst. dir.: Bertil Egnell.\n\nMarstrandsfjordens Konservfabrik\n\nAB., Klädesholmen.\n\n^ Tillverkar sillkonserver, ansjovis,\nkaviar, herring, sardiner m. m. vid fabrik i\nKlädesholmen (Göteb. o. Bohus l.).\nVarumärken^ »Isbjörnens ansjovis» o.\n»Fru-kost-ansjovis».\n\nTelefon: 51. Postgiro: 30168. —\nAkt.-kap.: 66,600 kr. Antal industriarb.: 25.\nTillv.-värde pr år: 450,000 kr. —\nFirman etabl. 1912, bolag 1946.\n\nVerkst. direktörer: köpm. Thore\nPettersson o. köpm. Karl Pettersson.\n\nMarthails Syindustri AB.,\n\nLinköping.\n\nTillverkar mössor, flygdräkter,\nbil-klädselöverdrag samt kylarskydd.\n\nTelefon: 22932. Postgiro: 97420.\n\nAkt.-kap.: 20,000 kr. Antal\nindustriarb.: 20. Tillv.-värde pr år: 400,000 kr.\n— Firman etabl. 1932, bolag 1938.\n\nVerkst. direktörer: fabr. Sigurd\nMart-hall o. fabr. Henning Marthall.\n\nMaskin AB. Rior, Stockholm.\n\nArmaturfabrik och mek. verkstad i\nHallsberg (Örebro l.). Tillverkar armatur\nför cellulosafabriker, kemiska fabriker\noch för värmeanläggningar såsom\nav-stängningsventiler, backventiler,\nkikkra-nar, glasrörställ m. m. samt\nspecialartiklar i järn- och stålgjutgods, rostfritt och\nsyrafast stål avsedda för vatten, ånga och\nsyror.\n\nKontor: Stockholm, Kungsg. 37.\nTelegr.-adr.: Maskinrior, Stockholm. Telefon:\n117950. Postgiro: 57950. — Akt.-kap.:\n60,000 kr. Antal industriarb.: 15.\nTillv.-värde pr år: 250,000 kr. — Bolaget\ngrundat 1939.\n\nVerkst. dir.: C. A. Åmark.\n\nFörsäljn.-chef: John Antonsson.\n\nAB. Maskinfabriken Göta,\n\nStockholm.\n\nTillverkar centrifugalpumpar,\nvatten-ring- och kolvpumpar,\ndjupbrunnspum-par m. m.\n\nKontor: Londonviadukten. Telefon:\n432572. Postgiro: 57502.\n\nAkt.-kap.: 104,000 kr. Antal\nindustriarb.: 28. Tillv.-värde pr år: 700,000 kr.\n\n—\tBolaget grundat 1918.\n\nStyrelse: generalkonsul Karl Sauber\n(ordf.), civiling. Ragnar Forssman, dir.\nE. Wallerstedt.\n\nVerkst. dir.: Karl Sauber.\n\n\"AB. Maskinfabriken Rex,\n\nHalmstad.\n\nTillverkar motorcyklar och cyklar samt\ndelar därtill. Varumärke: »Rex».\n\nTelegr.-adr.: Maskinrex, Halmstad.\nTelefon: »Rexfabriken». Postgiro: 32466. —\nAkt.-kap.: 500,000 kr. Antal industriarb.:\n240. — Fabriken anlagd 1896, bolag 1909.\n\nStyrelse: disp. Allan Boo (ordf.), dir.\nErnst Rothstein, försäljn.-chef Åke\nRoth-stein, disp. Carl Åslund.\n\nVerkst. dir.: Ernst Rothstein.\n\nKamrer: Hugo Nilsson.\n\nMaskinfabriken Waco, Halmstad.\n\nSe Ingenjörsfirman Alb. J. Wahlbeck,\nHalmstad.\n\n\"AB. Maskinfabriken i Örnsköldsvik,\n\nÖrnsköldsvik.\n\nTillverkar cirkelsågar, klyvsågar,\nkantverk, kapverk, kapsågar, fläktar,\nslipmaskiner, kvarnmaskiner m. m. Varumärke:\n»Ari».\n\nTelegr.-adr. o. telefon: Maskinfabriken,\nÖrnsköldsvik. Postgiro: 62432.\n\nAkt.-kap.: 200,000 kr. Antal\nindustriarb.: 75. Tillv.-värde pr år: 1,000,000 kr.\n\nFirman etabl. 1918 under namn\nLundblad &amp; Nyholms Mek. Verkstad, nuv.\nnamn 1938.\n\nStyrelse: dir. Oscar Forslund (ordf.),\nadv. Henrik Lindblom, disp. E. August\nNyholm.\n\nVerkst. dir.: E. A. Nyholm.\n\n\"Maskinfabriks AB. Gothia, Höör.\n\nMek. verkstad i Höör (Malmöh. l.).\nTillverkar ångpumpar, remdrivna och\nelektr. drivna en- och flercylindriga\nkolv-och plunschpumpar.\n\nFabrikskontor: Höör. Telefon: Höör\n48. Telegr.-adr.: Maskingothia, Malmö o.\nHöör. Postgiro: 266384. Exportkontor:\nMalmö, Österg. 35. Telefon: 70700.\n\nAkt.-kap.: 100,000 kr. Antal\nindustriarb.: 22. Tillv.-värde pr år: 350,000 kr.\n\n—\tBolaget grundat 1916.\n\nStyrelse: ing. Olof Winkler (ordf.),",
    "structured": {
        "1": {
            "name": "Marstrandsfjorden—Maskinfabrik",
            "location": "Marstrand",
            "business": "Tillverkning av maskiner och industriutrustning",
            "contact": {
                "telegraph": "Motorverkstaden, Marstrand",
                "phone": [
                    "5",
                    "45"
                ],
                "postgiro": "6936"
            },
            "financials": {
                "capital": "270,000 kr",
                "employees": {
                    "industriarb": 150
                },
                "annual_turnover": "1,500,000 kr",
                "annual_production_value": "1,500,000 kr"
            },
            "foundation_year": 1904,
            "board": [
                {
                    "name": "Bertil Egnell",
                    "role": "ordf."
                },
                {
                    "name": "Anders Melin-Högrell",
                    "role": null
                }
            ],
            "director": "Bertil Egnell",
            "managing_director": "Bertil Egnell"
        },
        "2": {
            "name": "Marstrandsfjordens Konservfabrik AB",
            "location": "Klädesholmen",
            "business": "Tillverkning av sillkonserver, ansjovis, kaviar, herring, sardiner m. m.",
            "contact": {
                "phone": [
                    "51"
                ],
                "postgiro": "30168"
            },
            "financials": {
                "capital": "66,600 kr",
                "employees": {
                    "industriarb": 25
                },
                "annual_turnover": "450,000 kr",
                "annual_production_value": "450,000 kr"
            },
            "foundation_year": 1912,
            "board": null
        },
        "3": {
            "name": "Marthails Syindustri AB",
            "location": "Linköping",
            "business": "Tillverkning av mössor, flygdräkter, bil-klädselöverdrag samt kylarskydd",
            "contact": {
                "phone": [
                    "22932"
                ],
                "postgiro": "97420"
            },
            "financials": {
                "capital": "20,000 kr",
                "employees": {
                    "industriarb": 20
                },
                "annual_turnover": "400,000 kr",
                "annual_production_value": "400,000 kr"
            },
            "foundation_year": 1932,
            "board": null
        },
        "4": {
            "name": "Maskin AB. Rior",
            "location": "Stockholm",
            "business": "Tillverkning av armatur för cellulosafabriker, kemiska fabriker och för värmeanläggningar såsom avstängningsventiler, backventiler, kikkrör, glasrörställ m. m. samt specialartiklar i järn- och stålgjutgods, rostfritt och syrafast stål avsedda för vatten, ånga och syror",
            "contact": {
                "office": "Hallsberg (Örebro l.)",
                "phone": [
                    "117950"
                ],
                "postgiro": "57950"
            },
            "financials": {
                "capital": "60,000 kr",
                "employees": {
                    "industriarb": 15
                },
                "annual_turnover": "250,000 kr",
                "annual_production_value": "250,000 kr"
            },
            "foundation_year": 1939,
            "board": null,
            "director": "C. A. Åmark"
        },
        "5": {
            "name": "AB. Maskinfabriken Göta",
            "location": "Stockholm",
            "business": "Tillverkning av centrifugalpumpar, vatten-ring- och kolvpumpar, djupbrunnspumpar m. m.",
            "contact": {
                "office": "Londonviadukten",
                "phone": [
                    "432572"
                ],
                "postgiro": "57502"
            },
            "financials": {
                "capital": "104,000 kr",
                "employees": {
                    "industriarb": 28
                },
                "annual_turnover": "700,000 kr",
                "annual_production_value": "700,000 kr"
            },
            "foundation_year": 1918,
            "board": null,
            "director": "Karl Sauber"
        },
        "6": {
            "name": "AB. Maskinfabriken Rex",
            "location": "Halmstad",
            "business": "Tillverkning av motorcyklar och cyklar samt delar därtill",
            "contact": {
                "telegraph": "Maskinrex, Halmstad",
                "phone": [
                    "Rexfabriken"
                ],
                "postgiro": "32466"
            }
        },
        "7": {
            "name": "Maskinfabriken Waco",
            "location": "Halmstad",
            "business": "Se Ingenjörsfirman Alb. J. Wahlbeck, Halmstad"
        },
        "8": {
            "name": "AB. Maskinfabriken i Örnsköldsvik",
            "location": "Örnsköldsvik",
            "business": "Tillverkning av cirkelsågar, klyvsågar, kantverk, kapverk, kapsågar, fläktar, slipmaskiner, kvarnmaskiner m. m."
        },
        "9": {
            "name": "Maskinfabriks AB. Gothia",
            "location": "Höör",
            "business": "Tillverkning av ångpumpar, remdrivna och elektr. drivna en- och flercylindriga kolv-och plunschpumpar"
        }
    }
}