{
    "original": "Norrtelje—Nya\n\nstålgjutgods, syrafast gjutgods,\ntack-järnsgjutgods, ugnsdetaljer till\ngengasaggregat m. m. Specialitet: Eldhärdigt\ngjutgods.\n\nTelefon: »Norrtelje Gjuteri». Postgiro:\n88873. — Antal industriarb.: 80.\nTillv.-värde pr år: 1,300,000 kr. — Gjuteriet\ngrundat 1864.\n\nÄgare o. chefer: fabr. Eddie Greisz,\nfabr. Harry Greisz, fabr. Conny Greisz.\n\n\"Norrtelje Ångbryggeri AB., ,\n\nNorrtälje.\n\nBryggeri och läskedrycksfabrik.\nTillverkar malt- och läskedrycker.\n\nTelefon: »Bryggeribolaget». Postgiro:\n96880. — Akt.-kap.: 300,000 kr. Antal\nindustriarb.: 30. Tillv.-värde pr år:\n300,000 kr.\n\nBolaget grundat 1890. AB. Stockholms\nBryggerier är huvudintressent i bolaget.\n\nStyrelse: dir. Harald Engström (ordf.),\ndir. Carl Bille, disp. Adrian örtqvist.\n\nVerkst. dir.: Carl Bille (Stockholm).\n\nDisp.: A. örtqvist.\n\n\"AB. Norshro Sågverksegare,\n\nLeksand.\n\nSågverk, hyvleri och snickerifabrik\nvid Norsbro, Leksand (Kopparb. l.).\nTillverkar sågade och hyvlade trävaror,\ndörrar och fönster samt byggnadssnickerier.\n\nTelefon: 36. Postgiro: 5284. —\nAkt.-kap.: 400,000 kr. Antal industriarb.: 75.\nÅrstillv.: 3,500 stds sågade och hyvlade\nträvaror. — Bolaget grundat 1873.\n\nDisp.: Lars Flygar.\n\nKamrer: Riikard Eronn.\n\nSkogsförvalt.: J. Melander.\n\n\"AB. P. A. Norstedt &amp; Söner,\n\nStockholm.\n\nBoktryckeri, stilgjuteri och bokförlag.\nUtför bok- och tidningstryck samt\nstereotyper; tillverkar stil och materiel för\nboktryck. Bolaget^ driver även handelsrörelse\nmed skolmateriel och skolfilm.\n\nKontor: Tryckerig. 2. Telegr.-adr.:\nNorstedts, Stockholm. Telefon:\n»Norstedts Söner». Postgiro: 93. —\nAkt.-kap.: 9,600,000 kr. Antal anställda: 575,\ndärav 390 industriarb.\n\nFirman, etabl. 1823, bolag 1879, äger\nIsaac Marcus* Boktryckeri AB. Bolaget\när anslutet till AB. Sveriges Litografiska\nTryckerier.\n\nStyrelse: riksmarskalk Birger Ekeberg\n(ordf.), dir. Thorsten Laurin, f. d. hov-\n\nrättsrådet Johan Nordenfalk, dir. Knut\nÖstberg.\n\nVerkst. dir.: Johan Nordenfalk.\n\nAvd.-chef för litterära avd.: Thorsten\nLaurin.\n\n\"P. A. Norstedt &amp; Söners Bokbinderi\n\nAB., Stockholm.\n\nUtför parti- och privatbindning,\nkart-och planschuppfodring m. m. samt\ntillverkar lyxband och hyllningsadresser.\n\nKontor: Vasag. 16. Telefon: »Norstedts\nSöner». Postgiro: 1678.\n\nBolaget, grundat 1933, är anslutet till\nAB. Sveriges Litografiska Tryckerier.\n\nDisp.: ryttm. Åke G. Wickman.\n\nNorsälvens Sågverks AB.,\n\nKarlstad.\n\nSågverk, hyvleri och\nimpregnerings-verk. Tillverkar sågade och hyvlade\nträvaror samt impregnerade\nkraftlednings-stolpar, slipers m. m.\n\nTelegr.-adr.: Norsträ, Karlstad.\nTelefon: 16256, 16246 o. 13946. Postgiro:\n262877.\n\nAkt.-kap.: 450,000 kr. Antal\nindustriarb.: 50. Tillv.-värde pr år: 1,500,000 kr.\nÅrstillv.: 1,800 stds trävaror. — Bolaget\ngrundat 1941.\n\nStyrelse o. verkst. dir.: godsäg. Sten G.\nHelmer.\n\n\"AB. Notnäs Ångsåg, Torsby.\n\nSågverk med hyvleri i Torsby (Värml.\n1.). Tillverkar sågade och hyvlade\nträvaror.\n\nTelefon: 34 o. 35. Postgiro: 11930. —\nAkt.-kap.: 200,000 kr. Antal industriarb.:\n60. Tillv.-värde pr år: 900,000 kr. —\nBolaget grundat 1936.\n\nStyrelse: handl. Allan Skanse,\ninspektor Erik Skanse, dir. Per Skanse.\n\nVerkst. dir.: Per Skanse.\n\n\"Nya Asfalt AB., Stockholm.\n\nEntreprenadfirma för husbyggnader,\nväg-, vatten- och brobyggnader,\nisoleringar och asfaltbeläggningar. Tillverkar\nasfaltprodukter och betongrör samt trappor\noch plattor av cement och cementmosaik.\n\nHuvudkontor: Stockholm, Industrig. 6.\nTelegr.-adr. o. telefon: Asfaltbolaget,\nStockholm. Postgiro: 1802. Filialkontor:\ni Örebro, Engelbrektsg. 40—42; i Malmö,\nGust. Adolfs torg 49.\n\nAkt.-kap.: 1,000,000 kr. Prod.-värde pr\når: 15,000,000 kr. — Bolaget grundat\n1875.",
    "structured": {
        "1": {
            "name": "Norrtelje—Nya",
            "location": "Norrtälje",
            "business": "stålgjutgods, syrafast gjutgods, tack-järnsgjutgods, ugnsdetaljer till gengasaggregat m. m. Specialitet: Eldhärdigt gjutgods.",
            "contact": {
                "phone": [
                    "Norrtelje Gjuteri"
                ],
                "postgiro": "88873"
            },
            "financials": {
                "capital": "N/A",
                "employees": {
                    "industriarb": 80
                },
                "annual_turnover": "1,300,000 kr",
                "annual_production_value": "N/A"
            },
            "foundation_year": 1864,
            "owners": [
                "fabr. Eddie Greisz",
                "fabr. Harry Greisz",
                "fabr. Conny Greisz"
            ]
        },
        "2": {
            "name": "Norrtelje Ångbryggeri AB.",
            "location": "Norrtälje",
            "business": "Bryggeri och läskedrycksfabrik. Tillverkar malt- och läskedrycker.",
            "contact": {
                "phone": [
                    "Bryggeribolaget"
                ],
                "postgiro": "96880"
            },
            "financials": {
                "capital": "300,000 kr",
                "employees": {
                    "industriarb": 30
                },
                "annual_turnover": "300,000 kr",
                "annual_production_value": "N/A"
            },
            "foundation_year": 1890,
            "owners": [
                "AB. Stockholms Bryggerier"
            ]
        },
        "3": {
            "name": "AB. Norshro Sågverksegare",
            "location": "Leksand",
            "business": "Sågverk, hyvleri och snickerifabrik. Tillverkar sågade och hyvlade trävaror, dörrar och fönster samt byggnadssnickerier.",
            "contact": {
                "phone": "36",
                "postgiro": "5284"
            },
            "financials": {
                "capital": "400,000 kr",
                "employees": {
                    "industriarb": 75
                },
                "annual_turnover": "N/A",
                "annual_production_value": "3,500,000 kr"
            },
            "foundation_year": 1873,
            "board": {
                "name": "J. Melander",
                "role": "Skogsförvalt."
            }
        },
        "4": {
            "name": "AB. P. A. Norstedt & Söner",
            "location": "Stockholm",
            "business": "Boktryckeri, stilgjuteri och bokförlag. Utför bok- och tidningstryck samt stereotyper; tillverkar stil och materiel för boktryck. Bolaget driver även handelsrörelse med skolmateriel och skolfilm.",
            "contact": {
                "phone": [
                    "Norstedts Söner"
                ],
                "postgiro": "93"
            },
            "financials": {
                "capital": "9,600,000 kr",
                "employees": {
                    "industriarb": 390
                },
                "annual_turnover": "N/A",
                "annual_production_value": "N/A"
            },
            "foundation_year": 1879,
            "board": {
                "name": "Knut Östberg",
                "role": "dir."
            }
        },
        "5": {
            "name": "P. A. Norstedt & Söners Bokbinderi AB.",
            "location": "Stockholm",
            "business": "Utför parti- och privatbindning, kart-och planschuppfodring m. m. samt tillverkar lyxband och hyllningsadresser.",
            "contact": {
                "phone": [
                    "Norstedts Söner"
                ],
                "postgiro": "1678"
            },
            "financials": {
                "capital": "N/A",
                "employees": {
                    "industriarb": "N/A"
                },
                "annual_turnover": "N/A",
                "annual_production_value": "N/A"
            },
            "foundation_year": 1933
        },
        "6": {
            "name": "Norsälvens Sågverks AB.",
            "location": "Karlstad",
            "business": "Sågverk, hyvleri och impregnerings-verk. Tillverkar sågade och hyvlade trävaror samt impregnerade kraftlednings-stolpar, slipers m. m.",
            "contact": {
                "phone": [
                    "16256",
                    "16246",
                    "13946"
                ],
                "telegraph": "Norsträ",
                "postgiro": "262877"
            },
            "financials": {
                "capital": "450,000 kr",
                "employees": {
                    "industriarb": 50
                },
                "annual_turnover": "1,500,000 kr",
                "annual_production_value": "N/A"
            },
            "foundation_year": 1941
        },
        "7": {
            "name": "AB. Notnäs Ångsåg",
            "location": "Torsby",
            "business": "Sågverk med hyvleri i Torsby (Värml. 1.). Tillverkar sågade och hyvlade trävaror.",
            "contact": {
                "phone": [
                    "34",
                    "35"
                ],
                "postgiro": "11930"
            },
            "financials": {
                "capital": "200,000 kr",
                "employees": {
                    "industriarb": 60
                },
                "annual_turnover": "900,000 kr",
                "annual_production_value": "N/A"
            },
            "foundation_year": 1936
        },
        "8": {
            "name": "Nya Asfalt AB.",
            "location": "Stockholm",
            "business": "Entreprenadfirma för husbyggnader, väg-, vatten- och brobyggnader, isoleringar och asfaltbeläggningar. Tillverkar asfaltprodukter och betongrör samt trappor och plattor av cement och cementmosaik.",
            "contact": {
                "phone": [
                    "Asfaltbolaget"
                ],
                "postgiro": "1802"
            },
            "financials": {
                "capital": "1,000,000 kr",
                "employees": "N/A",
                "annual_turnover": "N/A",
                "annual_production_value": "15,000,000 kr"
            },
            "foundation_year": 1875
        }
    }
}