{
    "original": "Ka Imar—Kampenhof\n\nAkt.-kap.: 50,100 kr. Antal\nindustriarb.: 100. Årstillv.: 5,000 stds lådämnen.\n— Firman etabl. 1893 i Nässjö, nuv.\nbolag grundat 1932.\n\nVerkst. dir.: Oscar W. Möller.\n\n\"AB. Kalmar Nya Tapetfabrik,\n\nKalmar.\n\nTillverkar tapeter och bårder.\nTelegr.-adr.: Tapetfabriken, Kalmar.\nTelefon: 109 o. 1498. Postgiro: 13262.\n\nAkt.-kap.: 400,000 kr. Antal\nindustriarb.: 40. — Fabriken anlagd 1882,\nbolaget grundat 1902.\n\nStyrelse: konsul Ernst H. Lindh\n(ordf.), disp. H. Hofverberg, fru E.\nLindh.\n\nVerkst. dir.: Ernst H. Lindh.\n\n\"Kalmar Tändsticksfabrik, Kalmar.\n\nSe Jönköpings och Yulcans\nTändsticksfabriks AB., Jönköping.\n\n\"Kalmar Varv, Kalmar.\n\nSkeppsvarv. Utför nybyggnader och\nreparationer av fartyg. Varvet äges av\nÅngbåts AB. Kalmarsund, som driver\nrederi såsom huvudrörelse.\n\nTelegr.-adr.: Varvet, Kalmar. Telefon:\n39, 239, 3939 o. 3940. Postgiro: 140842.\n\nAkt.-kap.: 750,000 kr. Antal\nindustriarb.: 175. Prod.-värde pr år: 2,500,000 kr.\n— Varvet övertogs av nuv. ägare 1924.\n\nStyrelse: v. konsul John Jeansson\n(ordf.), ryttm. Birger Jeaiisson, dir.\nEbbe Jeansson.\n\nVerkst. dir.: Birger Jeansson.\n\nVarvsing.: Gunnar Byfors.\n\n\"Kalmar Verkstads AB., Kalmar.\n\nMek. verkstad. Tillverkar\njärnvägsvagnar, spårvagnar, lokomotiv m. m. samt\nutför reparationer av rullande material.\n\nTelegr.-adr.: Verkstadsbolag, Kalmar.\nTelefon: »Verkstadsbolaget». Postgiro:\n140960.\n\nAkt.-kap.: 860,000 kr. Antal\nindustriarb.: 350. Tillv.-värde pr år: 4,000,000 kr.\n— Bolaget grundat 1902.\n\nStyrelse: verkstadsdir. T. R. Norinder\n(ordf.), dir. Gustaf L. Johnsson,\nverk-stadsövering. Sixten Niklasson, övering.\nThure Ringqvist, bankdir. O. H. Trolle.\nVerkst. dir.: Sven Södervall.\nIntendent: David Ohlsson.\nKontorschef: Ernst Eriksson.\n\n2’74\n\n\"Kalmar Ängkvarns\nKommanditbolag, Kalmar.\n\nTillverkar vete-, råg-, ris- och\nhavremjöl, fodermjöl, vete- och rågkli,\nhavre-och risgryn.\n\nTelegr.-adr.: Ångkvarnen,\nKalmar-Telefon: 2. Postgiro: 8426.\nAgenturkontor: Stockholm, Runebergsg. 6, telefon:\n113800.\n\nLott.-kap.: 2,410,000 kr. Antal\nindustriarb.: 165. Prod.-värde pr år: 14,000,000*\nkr.\n\nFirman etabl. 1847,\nkommanditbolag-1922.\n\nAnsvariga delägare: v. konsul John,\nJeansson, ryttm. Birger Jeansson, dir.\nEbbe Jeansson.\n\nKalu Choklad &amp; Konfektfabrik AB.»\n\nGöteborg.\n\nTillverkar choklad, kola och konfekt.\nKontor: Sveagatan 8. Telefon: 113832^\no. 135734. Postgiro: 46782.\n\nAkt.-kap.: 30,000 kr. Antal\nindustriarb.: 25. Tillv.-värde pr år: 425,000 kr..\n\n—\tBolaget grundat 1941.\nVerkst. dir.: Knut Amundson.\n\nAB. Kamgarn, Borås.\n\nKamgarnsspinneri. Tillverkar kamgarn\noch ullgarner.\n\nTelegr.-adr.: Kamgarn, Borås. Telefon:\n10023. Postgiro: 91570.\n\nAkt.-kap.: 600,000 kr. Antal\nindustriarb.: 160. Tillv.-värde pr år: 5,000,000 kr.\n\n—\tBolaget grundat 1909.\n\nStyrelse: dir. Gustaf Werner (ordf.)„\ndir. Frans H. Nilsson, dir. C. O.\nSmedmark.\n\nVerkst. dir.: Frans H. Nilsson\n(Göteborg).\n\nDisp.: Sture Skoglund.\n\n\"Kamgarnsspinneri AB., Svenska,\n\nBorås.\n\nSe Svenska Kamgarnsspinneri AB.,.\nBorås.\n\n\"Kamko AB., Uddevalla.\nSe Kampenhofs AB., Uddevalla.\n\n\"Kampenhofs AB., Uddevalla.\n\nBomullsspinneri och -väveri, blekeri,\nfärgeri, vaddfabrik, och konfektionsfabrik\n(Kamko AB.). Tillverkar garner, oblekta,,\nblekta, färgade och kulörta vävnader av\nbomull och cellull, täckvadd och\nbomulls-konfektion.\n\n-&gt;r",
    "structured": {
        "1": {
            "name": "AB Kalmar Nya Tapetfabrik",
            "location": "Kalmar",
            "business": "Tillverkar tapeter och bårder",
            "contact": {
                "phone": [
                    "109",
                    "1498"
                ],
                "postgiro": "13262"
            },
            "financials": {
                "capital": "400,000 kr",
                "employees": {
                    "industriarb": 40
                },
                "annual_production_value": "Unknown"
            },
            "foundation_year": 1882,
            "current_name_year": 1902,
            "board": [
                {
                    "name": "konsul Ernst H. Lindh",
                    "role": "ordf."
                },
                {
                    "name": "disp. H. Hofverberg",
                    "role": null
                },
                {
                    "name": "fru E. Lindh",
                    "role": null
                }
            ],
            "director": "Ernst H. Lindh"
        },
        "2": {
            "name": "Kalmar Tändsticksfabrik",
            "location": "Kalmar",
            "business": "See Jönköpings and Yulcans Tändsticksfabriks AB., Jönköping"
        },
        "3": {
            "name": "Kalmar Varv",
            "location": "Kalmar",
            "business": "Utför nybyggnader och reparationer av fartyg",
            "contact": {
                "phone": [
                    "39",
                    "239",
                    "3939",
                    "3940"
                ],
                "postgiro": "140842"
            },
            "financials": {
                "capital": "750,000 kr",
                "employees": {
                    "industriarb": 175
                },
                "annual_turnover": "Unknown",
                "annual_production_value": "2,500,000 kr"
            },
            "board": [
                {
                    "name": "v. konsul John Jeansson",
                    "role": "ordf."
                },
                {
                    "name": "ryttm. Birger Jeaiisson",
                    "role": null
                },
                {
                    "name": "dir. Ebbe Jeansson",
                    "role": null
                }
            ],
            "director": "Birger Jeansson",
            "sales_manager": null
        },
        "4": {
            "name": "Kalmar Verkstads AB",
            "location": "Kalmar",
            "business": "Tillverkar järnvägsvagnar, spårvagnar, lokomotiv m. m. samt utför reparationer av rullande material",
            "contact": {
                "phone": "»Verkstadsbolaget»",
                "postgiro": "140960"
            },
            "financials": {
                "capital": "860,000 kr",
                "employees": {
                    "industriarb": 350
                },
                "annual_turnover": "Unknown",
                "annual_production_value": "4,000,000 kr"
            },
            "board": [
                {
                    "name": "verkstadsdir. T. R. Norinder",
                    "role": "ordf."
                },
                {
                    "name": "dir. Gustaf L. Johnsson",
                    "role": null
                },
                {
                    "name": "verk-stadsövering. Sixten Niklasson",
                    "role": null
                },
                {
                    "name": "övering. Thure Ringqvist",
                    "role": null
                },
                {
                    "name": "bankdir. O. H. Trolle",
                    "role": null
                }
            ],
            "director": "Sven Södervall",
            "manager": "Ernst Eriksson"
        },
        "5": {
            "name": "Kalmar Ängkvarns Kommanditbolag",
            "location": "Kalmar",
            "business": "Tillverkar vete-, råg-, ris- och havremjöl, fodermjöl, vete- och rågkli, havre-och risgryn",
            "contact": {
                "phone": "2",
                "postgiro": "8426"
            },
            "financials": {
                "capital": "2,410,000 kr",
                "employees": {
                    "industriarb": 165
                },
                "annual_production_value": "14,000,000 kr"
            },
            "foundation_year": 1847,
            "current_name_year": 1922,
            "owners": [
                "v. konsul John",
                "Jeansson",
                "ryttm. Birger Jeansson",
                "dir. Ebbe Jeansson"
            ]
        },
        "6": {
            "name": "Kalu Choklad & Konfektfabrik AB.",
            "location": "Göteborg",
            "business": "Tillverkar choklad, kola och konfekt"
        },
        "7": {
            "name": "AB Kamgarn",
            "location": "Borås",
            "business": "Kamgarnsspinneri. Tillverkar kamgarn och ullgarner",
            "contact": {
                "phone": "10023",
                "postgiro": "91570"
            },
            "financials": {
                "capital": "600,000 kr",
                "employees": {
                    "industriarb": 160
                },
                "annual_production_value": "5,000,000 kr"
            },
            "current_name_year": 1909,
            "board": [
                {
                    "name": "dir. Gustaf Werner",
                    "role": "ordf."
                },
                {
                    "name": "dir. Frans H. Nilsson",
                    "role": null
                },
                {
                    "name": "dir. C. O. Smedmark",
                    "role": null
                }
            ],
            "director": "Frans H. Nilsson (Göteborg)",
            "sales_manager": "Sture Skoglund"
        },
        "8": {
            "name": "Kampenhofs AB.",
            "location": "Uddevalla",
            "business": "Bomullsspinneri och -väveri, blekeri, färgeri, vaddfabrik, och konfektionsfabrik (Kamko AB.). Tillverkar garner, oblekta, blekta, färgade och kulörta vävnader av bomull och cellull, täckvadd och bomullskonfektion"
        }
    }
}