{
    "original": "Örebro\n\nstad (Örebro l.), samt anläggningar för\ndistribution av elektr. kraft på olika\nplatser inom Örebro län.\n\nKontor: Örebro. Telefon: 19035.\nPostgiro: 271035. — Akt.-kap.: 4,500,000 kr.\nDistrib.-värde pr år: 2,000,000 kr.\n\nBolaget, som grundades 1898, äges av\nKraft AB. Gullspång-Munkfors,\nMariestad.\n\nStyrelse: disp. John Hedin (ordf.),\ndisp. Gunnar Björkman, disp. Tore\nHedin, kapten Claes Sandels, disp. H. Seb.\nTham, dir. Gottfrid Thermaenius.\n\nVerkst. dir.: Tore Hedin.\n\nÖvering.: Konrad Schinkler.\n\n*AB. Örebro Kem. Tekn. Fabrik,\n\nÖrebro.\n\nSe Ekströms Kem. Tekn. AB., Örebro.\n\n*AB. Örebro Kexfabrik, Örebro.\n\nTillverkar kex, wafers, karameller och\ndragéer.\n\nTelegr.-adr.: Kexfabriken, Örebro.\nTelefon: 10431. Postgiro: 7832. Agent i\nStockholm: grossh. E. Melin, Tunnelg. 20,\ntelefon: 104718 o. 200334.\n\nAkt.-kap.: 1,800,000 kr. Antal\nindustriarb.: 250. Tillv.-värde pr år: 5,300,000\nkr. — Bolaget grundat 1896.\n\nStyrelse: disp. Paulus Källander\n(ordf.), civilekonom Erik Källander,\nlöjtn. Lars Källander, disp.-assist. Sven\nKällander.\n\nDisp.: Paulus Källander.\n\n*AB. Örebro Kvarn, Örebro.\n\nTillverkar mjöl och kli.\n\nTelegr.-adr. o. telefon: örebrokvarn,\nÖrebro. Postgiro: 9806.\n\nAkt.-kap.: 950,000 kr. Antal\nindustriarb.: 23. — Firman etablerades 1858,\nom-bildades till nuv. bolag 1922.\n\nStyrelse: disp. W. Risberg (ordf.), dir.\nGunnar Forsman, dir. Knut Lindström.\n\nVerkst. dir.: disp. Sven Svenson.\n\nAB. Örebro Nya Möbelfabrik,\n\nÖrebro.\n\nTillverkar affärsinredningar och\nmöbler.\n\nTelefon: 11867. Postgiro: 30332. —\nAkt.-kap.: 72,000 kr. Antal industriarb.:\n18. Tillv.-värde pr år: 215,000 kr. —\nFirman, etabl. 1914, bolag 1919, äges av\nSkofabriks AB. Oscaria, Örebro.\n\nVerkst. dir.: Sven Åqvist.\n\n*Örebro Pappersbruks AB., Örebro.\n\nPappersbruk och pappfabrik samt\nträsliperi.\n\nTillverkar kraft- och spinnpapper,\nkraftkreppapper, vattentätt kraftpapper,\npapperssäckar, vit papp, brun papp\n(läderpapp), duplexkartong, triplexpapp,\nkraftpapp och byggnadspapp samt för\neget behov mek. trämassa.\n\nTelegr.-adr.: Pappersbruket, Örebro.\nTelefon: 10766 (kamrer), 12766 (disp.),\n20800 (försäljn. o. exp.), 12817 (ing.).\nPostgiro: 8575.\n\nRepresentanter: för utlandet: Ekman &amp;\nCo., AB., Göteborg, V. Hamng. 7, telefon:\n174580; för Sverige: för papp: Edvard\nSchneidler AB., Stockholm,\nMalmskill-nadsgatan 54, telefon: 232420; för\nbyggnadspapp: Ernst Lennström, Göteborg,\nHolmia, telefon: 110689; för\npapperssäckar: AB. Gerber &amp; Hesslow, Stockholm,\nBirger Jarlsg. 6, telefon: 233710.\n\nAkt.-kap.: 4,693,000 kr. Antal\nindustriarb.: 250. Tillv.-värde pr år: 5,000,000 kr.\nÅrstillv.: 11,500 ton kraftpapper, 7,000\nton papp. — Bolaget, grundat 1901, äger\nFrövifors Bruks AB. och Bates Paper\nSack AB. Bolaget är anslutet till AB.\nSveriges Litografiska Tryckerier,\nStockholm.\n\nStyrelse: disp. Gunnar Björkman, f. d.\nhovrättsrådet Johan Nordenfalk, disp.\nGösta Reuterswärd, generalkonsul\nRagnar Söderberg, dir. Knut Östberg.\n\nVerkst. dir. o. disp.: Gunnar\nBjörkman.\n\nKamrer: L.-G. Burchardt.\n\növering.: Evert Nordin.\n\nFörsäljn.-chef: Ernst Högström.\n\nAB. Örebro Radiatorfabrik,\n\nÖrebro.\n\nMek. verkstad. Tillverkar\nplåtradiatorer.\n\nTelegr.-adr.: örebroradiator, Örebro.\nTelefon: 15123. Postgiro: 133304. —\nAkt.-kap.: 80,000 kr. Antal industriarb.:\n60. Tillv.-värde pr år: 550,000 kr. —\nBolaget grundat 1937.\n\nVerkst. dir.: fabr. Per A. Duberg.\n\nAB. Örebro Skjortfabrik, Örebro.\n\nTillverkar herr- och gosskjortor,\nfrack-och smokingskjortor, pyjamas och\nnattskjortor, kragar och kravatter.\nVarumärken: »Vici» o. »Maness».\n\nTelefon: 13093 o. 17380. Postgiro:\n91285. — Akt.-kap.: 15,000 kr. Antal\nindustriarb.: 50. Tillv.-värde pr år: 600,000\nkr. — Firman etabl. 1932, bolag 1942.",
    "structured": {
        "firms": [
            {
                "name": "Kraft AB",
                "location": "Örebro",
                "business": "Distribution av elektr. kraft",
                "contact": {
                    "office": "Örebro",
                    "phone": [
                        "19035"
                    ],
                    "postgiro": "271035"
                },
                "financials": {
                    "capital": "4,500,000 kr",
                    "annual_turnover": "2,000,000 kr"
                },
                "foundation_year": 1898,
                "owners": [
                    "Kraft AB. Gullspång-Munkfors",
                    "Mariestad"
                ],
                "board": [
                    {
                        "name": "John Hedin",
                        "role": "ordf."
                    },
                    {
                        "name": "Gunnar Björkman",
                        "role": "disp."
                    },
                    {
                        "name": "Tore Hedin",
                        "role": "disp."
                    },
                    {
                        "name": "Claes Sandels",
                        "role": "kapten"
                    },
                    {
                        "name": "H. Seb. Tham",
                        "role": "disp."
                    },
                    {
                        "name": "Gottfrid Thermaenius",
                        "role": "dir."
                    }
                ],
                "director": "Tore Hedin",
                "managing_director": "Konrad Schinkler"
            },
            {
                "name": "AB. Örebro Kexfabrik",
                "location": "Örebro",
                "business": "Tillverkar kex, wafers, karameller och dragéer",
                "contact": {
                    "office": "Örebro",
                    "phone": [
                        "10431"
                    ],
                    "postgiro": "7832",
                    "telegraph": "Kexfabriken, Örebro",
                    "factory_phone": "10431"
                },
                "financials": {
                    "capital": "1,800,000 kr",
                    "annual_production_value": "5,300,000 kr"
                },
                "foundation_year": 1896,
                "owners": [
                    "grossh. E. Melin, Tunnelg. 20"
                ]
            },
            {
                "name": "AB. Örebro Kvarn",
                "location": "Örebro",
                "business": "Tillverkar mjöl och kli",
                "contact": {
                    "office": "Örebro",
                    "phone": [
                        "örebrokvarn"
                    ]
                },
                "financials": {
                    "capital": "950,000 kr"
                },
                "foundation_year": 1858,
                "board": [
                    {
                        "name": "W. Risberg",
                        "role": "disp."
                    },
                    {
                        "name": "Gunnar Forsman",
                        "role": "dir."
                    },
                    {
                        "name": "Knut Lindström",
                        "role": "dir."
                    }
                ],
                "director": "Sven Svenson"
            },
            {
                "name": "AB. Örebro Nya Möbelfabrik",
                "location": "Örebro",
                "business": "Tillverkar affärsinredningar och möbler",
                "contact": {
                    "phone": [
                        "11867"
                    ],
                    "postgiro": "30332"
                },
                "financials": {
                    "capital": "72,000 kr",
                    "annual_production_value": "215,000 kr"
                },
                "foundation_year": 1914,
                "owners": [
                    "Skofabriks AB. Oscaria, Örebro"
                ],
                "director": "Sven Åqvist"
            },
            {
                "name": "Örebro Pappersbruks AB.",
                "location": "Örebro",
                "business": "Pappersbruk och pappfabrik samt träsliperi",
                "contact": {
                    "phone": [
                        "10766",
                        "12766",
                        "20800",
                        "12817"
                    ],
                    "postgiro": "8575"
                },
                "financials": {
                    "capital": "4,693,000 kr",
                    "annual_production_value": "5,000,000 kr"
                },
                "foundation_year": 1901
            },
            {
                "name": "AB. Örebro Radiatorfabrik",
                "location": "Örebro",
                "business": "Mek. verkstad. Tillverkar plåtradiatorer",
                "contact": {
                    "phone": [
                        "15123"
                    ],
                    "postgiro": "133304"
                },
                "financials": {
                    "capital": "80,000 kr",
                    "annual_production_value": "550,000 kr"
                },
                "foundation_year": 1937,
                "director": "Per A. Duberg"
            },
            {
                "name": "AB. Örebro Skjortfabrik",
                "location": "Örebro",
                "business": "Tillverkar herr- och gosskjortor, frack-och smokingskjortor, pyjamas och nattskjortor, kragar och kravatter",
                "contact": {
                    "phone": [
                        "13093",
                        "17380"
                    ],
                    "postgiro": "91285"
                },
                "financials": {
                    "capital": "15,000 kr",
                    "annual_production_value": "600,000 kr"
                },
                "foundation_year": 1932
            }
        ]
    }
}