{
    "original": "Dux—Dösebacka\n\nStyrelse: adv. H. Dahlin (ordf.),\nciviling. Nils A: son Strömberg, dir. Gustaf\nWinqvist.\n\nVerkst. dir.: Gustaf Winqvist.\nV ericstads chef: Nils A: son Strömberg.\nVerkstadsing.: Sven Winqvist.\n\nDux Madrassfabrik, AB., Malmö.\nSe Madrass-Fabriken Dux AB., Malmö.\n\n*Dux Radio AB., Stockholm.\n\nTillverkar radioapparater samt\nkvick-silverlikriktare och elektr. motorer.\nVarumärke: »Dux-radio».\n\nKontor: Svarvarg. 11. Telegr.-adr.:\nRadiodux, Stockholm. Telefon: 520380.\nPostgiro: 2977.\n\nAkt.-kap.: 200,000 kr. Antal\nindustriarb. : 63. — Firman etabl. 1926, nuv.\nnamn 1932.\n\nStyrelse o. verkst. dir.: Hilding\nLjung-feldt.\n\nDisp.: Olof R. Sjöquist.\n\nKamrer: Harald Agrander.\n\nFabrikschef: ing. F. Simonsson.\n\nDyita Bruk, Dyltabruk.\n\nSågverk och hyvleri vid Dyltabruk\n(Örebro l.). Tillverkar sågade och hyvlade\nträvaror. Driver jämväl jordbruk och\nskogsbruk.\n\nTelefon: Örebro 62000. Postgiro: 80067.\n— Årstillv.: 250 stds trävaror. —\nBruket anlagt såsom svavelbruk på 1750-talet.\n\nÄgare: frih. G. Åkerhielms sterbhus.\n\nFör valt.: frih. Gösta Åkerhielm.\n\nDyita Kaikbruk, Dyltabruk.\nSe AB. Strå Kalkbruk, Stockholm.\n\nAB. Dynamoborstfabriken*\n\nVadstena.\n\nTillverkar som specialiteter el-borstar\nför dynamomaskiner och elektromotorer,\ngnistkol till reläslutare. Varumärken:\n»Essdewe», »SD» o. »SDW».\n\nTelefon: 140. Postgiro: 9300. —\nAkt.-kap.: 100,000 kr. Antal industriarb.: 15.\n— Fabriken grundlagd 1888, bolag 1946.\n\nVerkst. dir..- fil. dr J. Heuberger.\n\nDriftschef: ing. Per-Olof Olsson.\n\n’Dynäs AB., Väja.\n\nSågverk, sulfatfabrik, pappersbruk och\nfabrik för tillverkning av papperssäckar\nvid Väja samt sågverk vid Dynäs (båda i\nVasternorrl. l.). Tillverkar sågade\nträvaror, sulfatcellulosa, kraftpapper, flytande\nharts och terpentin samt papperssäckar.\n\nHuvudkontor: Väja. Telegr.-adr.:\nDy-näsbolag, Kramfors. Telefon: Kramfors\n22, 163 o. 164.\n\nAkt.-kap.: 2,500,000 kr. Antal\nindustriarb.: 650. Årstillv.: 25,000 stds sågade\nträvaror, 40,000 ton sulfatcellulosa, 10,000\nton papper, 300,000 kg renad terpentin,\n1,500,000 kg flytande harts. — Bolaget,\ngrundat 1896, äger Wäija AB.\n\nStyrelse: konsul John Ekman (ordf.),\ndisp. Gunnar Berglund, bankdir. Ernst T.\nÅberg.\n\nVerkst. dir.: John Ekman.\n\növering.: Ragnar J. Johnsson.\n\nFörsäljningschefer: för trävaror o.\ncellulosa: Gunnar Berglund; för papper o.\nbiprodukter: Gustaf Bergström.\n\nDyviks Bruks AB., Stockholm.\n\nTräullsplattfabrik samt\nbetongvarufa-brik i Dy vik, östanå (Sthlms l.).\nTillverkar träullsplattor (märke: »Dykonit»)\nsamt lättbetongtegel och -block (märke:\n»Isorin»). Bolaget driver även jordbruk\noch skogshantering.\n\nKontor: Stockholm, Kungsg. 14.\nTelegr.-adr.: Axragn, Stockholm. Telefon:\n233830. Postgiro: 50413.\n\nAkt.-kap.: 250,000 kr. Antal\nindustriarb.: 75. Tillv.-värde pr år: 1?000,000 kr.\n— Fabrikationen startades 1932, bolag\n1940.\n\nStyrelse: dir. Axel Holmquist (ordf.),\njur. kand. Bertil Diedrichs, dir. Ragnar\nHolmquist, fru S. Holmquist.\n\nVerkst. dir.: Axel Holmquist.\n\nAB. Dösebacka Cementindustri,\n\nNol.\n\nSandtag och betonggjuteri i Dösebacka,\nNol (Göteb. o. Bohus l.). Tillverkar\nbetongrör, kulvertar, mursten och\ngrundsten, betonghålsten, mellanväggsplattor\nav »Tretong» m. m.\n\nTelefon: Kungälv 13 o. Dösebacka 40.\nPostgiro: 98833. — Akt.-kap.: 100,000 kr.\nAntal industriarb.: 25. — Firman etabl.\n1936, bolag 1937.\n\nVerkst. dir. o. disp.: Birger Jansson.\n\n-x-",
    "structured": {
        "1": {
            "name": "Dux Madrassfabrik, AB.",
            "location": "Malmö",
            "business": "Tillverkar radioapparater samt kvick-silverlikriktare och elektr. motorer.",
            "products": "Description of products manufactured or services offered.",
            "contact": {
                "office": "Svarvarg. 11",
                "phone": [
                    "520380"
                ],
                "postgiro": "2977"
            },
            "financials": {
                "capital": "200,000 kr",
                "employees": {
                    "industriarb.": 63
                },
                "annual_turnover": "Annual turnover of the firm.",
                "annual_production_value": "Annual production value."
            },
            "foundation_year": 1926,
            "current_name_year": 1932,
            "manager": "Hilding Ljung-feldt"
        },
        "2": {
            "name": "Dyita Bruk",
            "location": "Dyltabruk",
            "business": "Sågverk och hyvleri vid Dyltabruk (Örebro l.). Tillverkar sågade och hyvlade trävaror. Driver jämväl jordbruk och skogsbruk."
        },
        "3": {
            "name": "AB. Dynamoborstfabriken",
            "location": "Vadstena",
            "business": "Tillverkar som specialiteter el-borstar för dynamomaskiner och elektromotorer, gnistkol till reläslutare."
        },
        "4": {
            "name": "Dyñas AB.",
            "location": "Väja",
            "business": "Sågverk, sulfatfabrik, pappersbruk och fabrik för tillverkning av papperssäckar vid Väja samt sågverk vid Dynäs (båda i Vasternorrl. l.). Tillverkar sågade trävaror, sulfatcellulosa, kraftpapper, flytande harts och terpentin samt papperssäckar."
        },
        "5": {
            "name": "Dyviks Bruks AB.",
            "location": "Stockholm",
            "business": "Träullsplattfabrik samt betongvarufabrik i Dyvik, östanå (Sthlms l.). Tillverkar träullsplattor samt lättbetongtegel och block. Bolaget driver även jordbruk och skogshantering."
        },
        "6": {
            "name": "AB. Dösebacka Cementindustri",
            "location": "Nol",
            "business": "Sandtag och betonggjuteri i Dösebacka, Nol (Göteb. o. Bohus l.). Tillverkar betongrör, kulvertar, mursten och grundsten, betonghålsten, mellanväggsplattor av »Tretong» m. m."
        }
    }
}