{
    "original": "F igeho Inv—Finnb oda\n\nAkt.-kap.: 100,000 kr. Antal\nindustriarb.: 100. Tillv.-värde pr år: 2,000,000 kr.\n— Firman etabl. 1783, reseffektfabriken\nanlagd 1917, bolag 1929.\n: Styrelse: köpman Evald Johansson\n(ordf.), löjtn. N.-E. Gadelii, adv. Georg\nLindberg.\n\nVerkst. dir.: Evald Johansson.\n\nDisp.: N.-E. Gadelii.\n\nFabrihschef: B. Erlandssop.\n\n*AB. Figeholms Bruk, Figeholm.\n\nPresspanfabrik i Figeholm (Kalmar l.).\nTillverkar som specialiteter presspan och\npresspanrör jämte jacquardpapp,\njacqu-ardkort, registerkartong m. m.\n\nTelefon: 56. Postgiro: 165362. —\nAkt.-kap.: 125,000 kr. Antal industriarb.: 95.\nÅrstillv. : 1,000 ton presspan m. m. —\nBolaget grundat 1931.\n\nStyrelse: adv. R. Allmér, musikdir.\nBertil Håkansson, doktor Enar\nHåkansson, disp. Roland Håkansson, fru B,\nNor-denskjöld.\n\nDisp.: Roland Håkansson.\n\nFörsäljn.-chef: Willie Håkansson.\n\nAB. FSgo, Stockholm.\n\nMek. verkstad i Södertälje. Tillverkar\nfönsterbeslag såsom espagnoletter,\nhelautomatiska fönsterhållare och\nkoppel-hakar samt inspektionsluckor för badkar.\nVarumärke: »Figo».\n\nKontor: Stockholm, Furusundsg. 8.\nTelefon: 615828. Postgiro: 153123.\n\nAkt.-kap.: 25,000 kr. Antal\nindustriarb.: 6. Tillv.-värde pr år: 75,000 kr. —\nBolaget grundat 1937.\n\nVerkst. dir.: John II. Andreasson.\n\nFilfabriker, AB. Sveriges Förenade,\n\nTraryd.\n\nSe AB. Sveriges Förenade Filfabriker,\nTraryd.\n\nFilfabriks AB., Forserum.\n\nFilfabrik i Forserum (Jönköp. l.).\nTillverkar filar och raspar.\n\nTelefon: 28. Postgiro: 23409.\n\nAkt.-kap.: 30,000 kr. Antal\nindustriarb.: 50. Tillv.-värde pr år: 350,000 kr.\n— Firman etabl. 1890, bolag 1898.\n\nStyrelse: disp. Ernst A. Zetterstrand\n(ordf.), fru Gerda Bergman, herr\nEmanuel A. Pettersson.\n\nDisp. o. verkst. dir.: Ernst A.\nZetterstrand.\n\n*AB. Filling &amp; Co., Stockholm.\n\nSnickerifabrik. Tillverkar möbler och\ninredningar.\n\nKontor: Roslagsg. 33. Telefon: 323387.\nPostgiro: 195867. — Akt.-kap.: 10,000 kr.\nAntal industriarb.: 25. Tillv.-värde pr år:\n300,000 kr. — Firman etabl. 1927, bolag\n1941.\n\nStyrelse: adv. C. M. Fallenius, fabr. K.\nI. Filling, arkitekt D. Holmertz, dir. R.\nKalderén.\n\nVerkst. chef: K. I. Filling.\n\nFilmindustri, AB. Svensk,\n\nStockholm.\n\nSe AB. Svensk Filmindustri,\nStockholm.\n\nGust. Fimmerstad, Moholm.\n\nSågverk och hyvleri i Molholm (Skarab.\n1.). Tillverkar sågade och hyvlade\nträvaror m. m. Firman idkar jämväl\njordbruk.\n\nTelefon: Remmestorp 23. Postgiro:\n8436. — Antal industriarb.: 40. Årstillv,:\n800 stds sågat virke. — Firman etabl.\nunder namn Gust. Johansson, nuv. namn\n1939.\n\nÄgare o. chef: godsäg. Gust.\nFimmerstad.\n\n*Findus Konservfabrik, Bjuv.\n\nSe AB. Konservfabriken Findus, Bjuv,\n\n* Finlands Bryggeri, Kristianstad.\n\nSe AB. Skånebryggerier, Hälsingborg.\n\n*AB. Finnboda Varf, Stockholm.\n\nSkeppsvarv med flyt- och torrdockor\nsamt mek. verkstad vid Finnboda. Bygger\noch reparerar fartyg, båtar och pråmar\nav järn och stål.\n\nPostadr.: Stockholm 2. Telegr.-adr.:\nFinnboda, Stockholm. Telefon:\n»Finnboda Varf». Postgiro: 3298.\n\nAkt.-kap.: 2,100,000 kr. Antal\nindustriarb.: 500. Omsättn.-värde pr år: 8,000,000\nkr. — Varvet anlagt 1873, nuv. bolag\ngrundat 1916.\n\nStyrelse: dir. Eman^ Högberg (ordf.),\ndir. Sven Engwall, dir. Chr. Hansen,\nkapten P. Schollin-Borg, generalkonsul\nP. G. Thulin.\n\nVerkst. dir.: Chr. Hansen.\n\nVarvsing.: Erik Olin.\n\nKamrer: Clas G. Larsson.\n\n152*",
    "structured": {
        "1": {
            "name": "AB. Figeholms Bruk",
            "location": "Figeholm",
            "business": "Tillverkning av presspan och presspanrör, jacquardpapp, jacquardkort, registerkartong m.m.",
            "contact": {
                "office": "Figeholm",
                "phone": [
                    "56"
                ],
                "postgiro": "165362"
            },
            "financials": {
                "capital": "100,000 kr",
                "employees": {
                    "industriarb": 100
                },
                "annual_production_value": "2,000,000 kr"
            },
            "foundation_year": 1783,
            "board": [
                {
                    "name": "köpman Evald Johansson",
                    "role": "ordförande"
                },
                {
                    "name": "löjtn. N.-E. Gadelii",
                    "role": null
                },
                {
                    "name": "adv. Georg Lindberg",
                    "role": null
                }
            ],
            "owners": [],
            "director": "Evald Johansson"
        },
        "2": {
            "name": "AB. FSgo",
            "location": "Stockholm",
            "business": "Tillverkning av fönsterbeslag såsom espagnoletter, helautomatiska fönsterhållare, koppelhakar samt inspektionsluckor för badkar. Varumärke: »Figo».",
            "contact": {
                "office": "Stockholm, Furusundsg. 8",
                "phone": [
                    "615828"
                ],
                "postgiro": "153123"
            },
            "financials": {
                "capital": "125,000 kr",
                "employees": {
                    "industriarb": 95
                },
                "annual_production_value": "1,000 ton presspan m.m."
            },
            "foundation_year": 1931,
            "board": [
                {
                    "name": "adv. R. Allmér",
                    "role": "ordförande"
                },
                {
                    "name": "musikdir. Bertil Håkansson",
                    "role": null
                },
                {
                    "name": "doktor Enar Håkansson",
                    "role": null
                },
                {
                    "name": "disp. Roland Håkansson",
                    "role": null
                },
                {
                    "name": "fru B, Nordenskjöld",
                    "role": null
                }
            ],
            "owners": [],
            "director": "Roland Håkansson",
            "sales_manager": "Willie Håkansson"
        },
        "3": {
            "name": "Filfabriks AB., Forserum",
            "location": "Forserum (Jönköp. l.)",
            "business": "Tillverkning av filar och raspar.",
            "contact": {
                "office": null,
                "phone": [
                    "28"
                ],
                "postgiro": "23409"
            },
            "financials": {
                "capital": "30,000 kr",
                "employees": {
                    "industriarb": 50
                },
                "annual_production_value": "350,000 kr"
            },
            "foundation_year": 1890,
            "board": [
                {
                    "name": "disp. Ernst A. Zetterstrand",
                    "role": "ordförande"
                },
                {
                    "name": "fru Gerda Bergman",
                    "role": null
                },
                {
                    "name": "herr Emanuel A. Pettersson",
                    "role": null
                }
            ],
            "owners": [],
            "director": "Ernst A. Zetterstrand"
        },
        "4": {
            "name": "AB. Filling & Co.",
            "location": "Stockholm",
            "business": "Tillverkning av möbler och inredningar.",
            "contact": {
                "office": "Roslagsg. 33",
                "phone": [
                    "323387"
                ],
                "postgiro": "195867"
            },
            "financials": {
                "capital": "10,000 kr",
                "employees": {
                    "industriarb": 25
                },
                "annual_production_value": "300,000 kr"
            },
            "foundation_year": 1927,
            "board": [
                {
                    "name": "adv. C. M. Fallenius",
                    "role": "ordförande"
                },
                {
                    "name": "fabr. K. I. Filling",
                    "role": null
                },
                {
                    "name": "arkitekt D. Holmertz",
                    "role": null
                },
                {
                    "name": "dir. R. Kalderén",
                    "role": null
                }
            ],
            "owners": [],
            "director": "K. I. Filling"
        },
        "5": {
            "name": "AB. Finnboda Varf",
            "location": "Stockholm",
            "business": "Skeppsvarv med flyt- och torrdockor samt mek. verkstad. Bygger och reparerar fartyg, båtar och pråmar av järn och stål.",
            "contact": {
                "office": "Stockholm 2",
                "phone": [
                    "Finnboda Varf"
                ],
                "telegraph": "Finnboda, Stockholm",
                "postgiro": "3298"
            },
            "financials": {
                "capital": "2,100,000 kr",
                "employees": {
                    "industriarb": 500
                },
                "annual_production_value": "8,000,000 kr"
            },
            "corporation_year": 1916,
            "board": [
                {
                    "name": "dir. Eman^ Högberg",
                    "role": "ordförande"
                },
                {
                    "name": "dir. Sven Engwall",
                    "role": null
                },
                {
                    "name": "dir. Chr. Hansen",
                    "role": null
                },
                {
                    "name": "kapten P. Schollin-Borg",
                    "role": null
                },
                {
                    "name": "generalkonsul P. G. Thulin",
                    "role": null
                }
            ],
            "owners": [],
            "manager": "Erik Olin"
        }
    }
}