{
    "original": "A l um ii liiimkompan le i—A nä ell\n\ncialiteter: aluminiserade stekpannor och\ngjut flaskor*\n\nTelefon: 20612. Postgiro: 134397.\n—-Akt.-kap.: 175,000 kr. Antal\nindustriarb.: 20. Tillv.-värde pr år: 300,000 kr.\n\n—\tBolaget grundat 1937.\nVerkst. dir.: disp. Göran Möller.\n\n*Aluminiumkompanietf AB. Svenska,\n\nStockholm.\n\nSe AB. Svenska Aluminiumkompaniet,\nStockholm.\n\n*AB. Alunda Snickerifabrik &amp;\nMöbelaffär, Alunda.\n\nMöbelfabrik i Alunda (Uppsala l.).\nTillverkar möbler samt inredningar för\nprivatbruk, kontors- och butikslokaler.\nBolaget driver även jordbruk.\n\nTelefon: 9 a o. 9 b. Postgiro: 174560.\n\n—\tAkt.-kap.: 60,000 kr. Antal\nindustriarb.: 11. Tillv.-värde pr år: 71,000’kr. —\nFirman etabl. 1890, bolag 1938.\n\nStyrelse: hemmansäg. Filip Selen\n(ordf.), fröken Adéle Selen, fa.br. David\nSelen, fabr. Egron Selen, fabr. Josef\nSelen.\n\nVerkst. dir.: David Selen.\n\nAlvesta Gjuter i AB., Alvesta.\n\nTillverkar gjutgods för armatur,\nmedelstort maskingods samt maskinformat\nsmågods vid gjuteri i Alvesta\n(Kronob. l.).\n\nTelefon: 150. — Akt.-kap.: 52,000 kr.\nAntal industriarb.: 54. Tillv.-värde pr år:\n850,000 kr. — Firman etabl. 1923, bolag\n1943.\n\nVerkst. dir.: Gustaf Atliley.\n\nAlvesta Glasbruk, Lindahl &amp; Co.,\n\nAlvesta.\n\nTillverkar flaskor, burkar och\nmedicinglas, kem. tekniskt glas och\nemballageglas vid glasbruk i Alvesta (Kronob. l.).\n\nTelefon: 237 o. 227. Postgiro: 84348.\n\nAntal industriarb.: 90. Tillv.-värde pr\når: 700,000 kr. — Firman etabl. 1932.\n\nChef: fabr. Georg Lindahl.\n\n*AB. Alvesta Träförädling &amp; Mek.\nVerkstad, Alvesta.\n\nSågverk, hyvleri, trätoffelfabrik, mek.\nverkstad samt kvarn i Alvesta\n(Kronob. l.).\n\nTillverkar sågade och hyvlade trävaror,\n(specialitet: sågade sparrar o. bjälkar\n[kantholz]), trätoffelbottnar och läster\n\n150\n\nsamt turbiner, sågverksmaskiner och\nmaskiner för trätoffeltillverkning.\n\nTelefon: 99. Postgiro: 34216. —\nAkt.-kap.: 200,000 kr. Antal industriarb.: 50.\nTillv.-värde pr år: 900,000 kr. — Firman\netabl. 1904, bolag 1946.\n\nStyrelse: fabr. Ernst Andersson, disp.\nEvald Andersson, fru E. E. Andersson.\n\nVerkst. dir.: Evald Andersson.\n\n*Alviks Träförädlings AB., Alnö.\n\nHyvleri och fanérfabrik vid Alvik å\nAlnö (Västernorrl. l.). Tillverkar hyvlade\nträvaror samt lamellkryssfanér av furu\noch björk. Varunamn: »Sundsvall\nPly-wood».\n\nTelegr.-adr.: Alvik, Sundsvall.\nTelefon: Sundsvall 68141 o. 68110. Postgiro:\n30864.\n\nAkt.-kap.: 240,000 kr. Antal\nindustriarb.: 80. Årstillv.: 2,500 ton kryssfanér.\n— Bolaget, grundat 1927, äges av\nAnkarsviks Ångsågs AB., Sundsvall.\n\nStyrelse: konsul Hugo Nordgren\n(ordf.), skogschef Hugo Bäckström, disp.\nFr. Forsgren, disp. Wilhelm T. Lindgren,\nbankdir. Ivar Wallmark.\n\nDisp.: Fr. Forsgren.\n\nKamrer: Hugo Magnusson.\n\nDriftschef vid plywoodfabriken: G. D.\nTrolin.\n\nAma, Tekniska Fabriken,\n\nStockholm.\n\nSe Tekniska Fabriken Ama, Stockholm.\n\nAmbo, Bakelitfabriken, G i sia red.\n\nSe Bakelitfabriken Ambo, Gislaved.\n\n*Ameln, AB. Bröderne, Stockholm.\n\nSe AB. Bröderne Ameln, Stockholm.\n\nAndell &amp; Anderson AB., Göteborg.\n\nModevarukonfektion. Tillverkar\ndam-kragar, scarves samt modeartiklar.\nBolaget driver även engroshandel med\ntextil-och modevaror.\n\nKontor: Viktoriag. 16; postadr.:\nGöteborg 3. Telegr.-adr.: Andeländer,\nGöteborg. Telefon: 117267—68. Postgiro:\n240826. — Akt.-kap.: 500,000 kr.\nArb.-antal: 12. — Bolaget grundat 1946.\n\nStyrelse: rådman Nils Parkfelt (ordf.),\ndir. Max Andell, dir. Torsten Andell,\ndir. Oscar Anderson, dir. Bertil\nHassel-blad, godsäg. Da ge Ljungman.\n\nVerkst. direktörer: Oscar Anderson o.\nM. Andell.",
    "structured": {
        "1": {
            "name": "AB. Alunda Snickerifabrik & Möbelaffär",
            "location": "Alunda",
            "business": "Möbelfabrik",
            "products": "Tillverkar möbler samt inredningar för privatbruk, kontors- och butikslokaler. Bolaget driver även jordbruk.",
            "contact": {
                "phone": [
                    "9a",
                    "9b"
                ],
                "postgiro": "174560"
            },
            "financials": {
                "capital": "60,000 kr",
                "employees": {
                    "industriarb": 11
                },
                "annual_turnover": "71,000 kr"
            },
            "foundation_year": 1938,
            "board": [
                {
                    "name": "Filip Selen",
                    "role": "hemmansägare"
                },
                {
                    "name": "Adéle Selen",
                    "role": "fröken"
                },
                {
                    "name": "David Selen",
                    "role": "fa.br."
                },
                {
                    "name": "Egron Selen",
                    "role": "fabr."
                },
                {
                    "name": "Josef Selen",
                    "role": "fabr."
                }
            ],
            "director": "David Selen"
        },
        "2": {
            "name": "Alvesta Gjuteri AB",
            "location": "Alvesta",
            "business": "Tillverkar gjutgods för armatur, medelstort maskingods samt maskinformat smågods",
            "contact": {
                "phone": "150"
            },
            "financials": {
                "capital": "52,000 kr",
                "employees": {
                    "industriarb": 54
                },
                "annual_turnover": "850,000 kr"
            },
            "foundation_year": 1943,
            "original_name": "Alvesta Gjuteri i AB.",
            "board": [],
            "director": "Gustaf Atliley"
        },
        "3": {
            "name": "Alvesta Glasbruk, Lindahl & Co.",
            "location": "Alvesta",
            "business": "Tillverkar flaskor, burkar och medicinglas, kem. tekniskt glas och emballageglas",
            "contact": {
                "phone": [
                    "237",
                    "227"
                ],
                "postgiro": "84348"
            },
            "financials": {
                "employees": {
                    "industriarb": 90
                },
                "annual_turnover": "700,000 kr"
            },
            "foundation_year": 1932,
            "director": "fabr. Georg Lindahl"
        },
        "4": {
            "name": "AB. Alvesta Träförädling & Mek. Verkstad",
            "location": "Alvesta",
            "business": "Sågverk, hyvleri, trätoffelfabrik, mek. verkstad samt kvarn",
            "products": "Tillverkar sågade och hyvlade trävaror, (specialitet: sågade sparrar o. bjälkar [kantholz]), trätoffelbottnar och läster samt turbiner, sågverksmaskiner och maskiner för trätoffeltillverkning.",
            "contact": {
                "phone": "99",
                "postgiro": "34216"
            },
            "financials": {
                "capital": "200,000 kr",
                "employees": {
                    "industriarb": 50
                },
                "annual_turnover": "900,000 kr"
            },
            "foundation_year": 1946,
            "board": [
                {
                    "name": "Ernst Andersson",
                    "role": "fabr."
                },
                {
                    "name": "Evald Andersson",
                    "role": "disp."
                },
                {
                    "name": "E. E. Andersson",
                    "role": "fru"
                }
            ],
            "director": "Evald Andersson"
        },
        "5": {
            "name": "Alviks Träförädlings AB.",
            "location": "Alnö",
            "business": "Hyvleri och fanérfabrik",
            "products": "Tillverkar hyvlade trävaror samt lamellkryssfanér av furu och björk.",
            "contact": {
                "telegraph": "Alvik, Sundsvall",
                "phone": [
                    "68141",
                    "68110"
                ],
                "postgiro": "30864"
            },
            "financials": {
                "capital": "240,000 kr",
                "employees": {
                    "industriarb": 80
                },
                "annual_turnover": "2,500 ton kryssfanér"
            },
            "foundation_year": 1927,
            "owners": [
                "Ankarsviks Ångsågs AB., Sundsvall"
            ],
            "board": [
                {
                    "name": "Hugo Nordgren",
                    "role": "konsul"
                },
                {
                    "name": "Hugo Bäckström",
                    "role": "skogschef"
                },
                {
                    "name": "Fr. Forsgren",
                    "role": "disp."
                },
                {
                    "name": "Wilhelm T. Lindgren",
                    "role": "disp."
                },
                {
                    "name": "Ivar Wallmark",
                    "role": "bankdir."
                }
            ],
            "director": "Fr. Forsgren",
            "manager": "Hugo Magnusson",
            "sales_manager": "G. D. Trolin"
        },
        "6": {
            "name": "Andell & Anderson AB.",
            "location": "Göteborg",
            "business": "Modevarukonfektion",
            "products": "Tillverkar dam-kragar, scarves samt modeartiklar. Bolaget driver även engroshandel med textil-och modevaror.",
            "contact": {
                "location": "Viktoriag. 16",
                "postgiro": "240826"
            },
            "financials": {
                "capital": "500,000 kr",
                "employees": {
                    "Arb.-antal": 12
                }
            },
            "foundation_year": 1946,
            "board": [
                {
                    "name": "Nils Parkfelt",
                    "role": "rådman"
                },
                {
                    "name": "Max Andell",
                    "role": "dir."
                },
                {
                    "name": "Torsten Andell",
                    "role": "dir."
                },
                {
                    "name": "Oscar Anderson",
                    "role": "dir."
                },
                {
                    "name": "Bertil Hassel-blad",
                    "role": "dir."
                },
                {
                    "name": "Dage Ljungman",
                    "role": "godsäg."
                }
            ],
            "director": "Oscar Anderson",
            "manager": "M. Andell"
        }
    }
}