{
    "original": "Nya\n\nZinkgruvor, Falun (se detta bolag).\nBolaget driver jämväl skogshantering.\n\nKontor: Falun. Telefon: 3801. —\nAkt.-kap.: 89,600 kr. — Bolaget, grundat 1898,\när dotterbolag till AB. Zinkgruvor.\n\nStyrelse: dir. Sven Thorné, disp. Otto\nÅkerström, bankombudsm. Axel Å ström.\n\nVerkst. dir.: Sven Thorné.\n\nNya Lervarufabriken, V. Tunberg\n&amp; Co., Töreboda.\n\nTillverkar blomkrukor vid fabrik i\nTöreboda (Skarab. l.). Specialitet:\noglaserade blomkrukor.\n\nTelefon: 175. Postgiro: 83681. —\nArb.-antal: 12. Tillv.-värde pr år: 110,000 kr.\n\n—\tFirman etabl. 1926.\n\nÄgare: disp. Victor Tunberg o. lärare\nRichard Tunberg.\n\n*Nya AB. Liljeqvists Sågblads- &amp;\nRedskapsfabrik, Eskilstuna.\n\nTillverkar cirkel- och ramsågblad,\nämnen till rakklingor, maskinhyveljärn,\nmaskinknivar, murslevar samt spadar,\nskyfflar, grepar, högafflar och\nträdgårdsredskap.\n\nTelegr.-adr.: Liljeqvistbolag,\nEskilstuna. Telefon: 37440. Postgiro: 10705.\n\nAkt.-kap.: 250,000 kr. Antal\nindustriarb.: 75. Tillv.-värde pr år: 800,000 kr.\n\n—\tFirman etabl. 1877, nuv. bolag 1923.\nStyrelse: kapten Peter Schollin-Borg\n\n(ordf.), dir. Eric Benson, löjtn. A.\nGyl-lenberg, disp. Arvid H. Nilsson, med. lic.\nI. Ryott-Iohnson, bergsing. Allan\nSchollin-Borg, civiling. Gunnar Schollin-Borg,\nstiftsjägm. E. Wesström, kapten J.-E.\nÅlund.\n\nVerkst. dir.: A. Schollin-Borg.\n\n*Nya Linneindustri AB., Borås.\nSe AB. Libo-Konfektion, Borås.\n\nNya AB. Luleå Varv &amp; Verkstäder,\n\nImleå.\n\nMek. verkstad med gjuteri, plåtslageri\nsamt fartygsslipar. Tillverkar\njärnkonstruktioner, metall- och\ntackjärnsgjut-gods. Specialiteter: gruv-, tipp- och\ntorkugnsvagnar, ved- och kokspannor,\nbåtskrov samt landsvägsfärjor.\n\nTelegr.-adr.: Verkstäderna, Luleå.\nTelefon: 2191 o. 1809. Postgiro: 60980.\n\nAkt.-kap.: 100,000 kr. Antal\nindustriarb.: 140. Tillv.-värde pr år: 1,700,000 kr.\n— Företaget grundat 1887, ombildat\n1932.\n\nVerkst. dir.: Bengt Sandström.\n\n*Nya Läderfabriks AB. Göta,\n\nÖrebro.\n\nLäderfabrik i Alingsås.\n\nTillverkar ovanläder, speciellt svart och\nkulört hästchevreaux, boxsidor,\nsportläder och kalvskinn i olika färger\n(»Go-thiakalv»), impregnerat ovanläder\n(»Bi-sonläder») för skid- och sportskodon,\nmocca, boxkalv, spalt till arbetshandskar\nsamt foderskinn.\n\nHuvudkontor: Örebro. Telegr.-adr. t\nGötaläder, Örebro. Telefon: »Oscaria».\nFabrikskontor: Alingsås. Telefon: 106.\n\nAkt.-kap.: 150,000 kr. Antal\nindustriarb.: 114. Tillv.-värde pr år: 2,980,000 kr.\n— Bolaget, grundat 1904, ombildat 1937,\näges av Skofabriks AB. Oscaria, Örebro.\n\nStyrelse: fabrikschef B. Klinge, jur.\nkand. Gösta Åqvist, ing. Knut Åqvist, fru\nLillie Åqvist, disp. Sven Åqvist.\n\nFabrikschef: B. Klinge.\n\n*Nya Marmorbruks AB., Kolmården.\n\nMarmorbrott i Krokek (Östergötl. l.)\nför Kolmårdsmarmor och i Glanshammar\n(Örebro l.) för Ekebergsmarmor.\n\nLevererar råblock och råskivor samt\nutför marmor- och kalkstensarbeten —\näven av utländsk sten — såsom trappor\noch golv, pelare, pilastrar,\nfönsterplattor och diskbänkar m. m., disk- och\nvågskivor, möbelmarmor, marmor för elektr.\ninstrumenttavlor, gravvårdar och\nkrema-torieurnor, prydnads- och konstföremål\nm. m.\n\nKontor: Kolmården. Telegr.-adr.:\nMarmor, Norrköping. Telefon: Kolmården\n4-Postgiro: 7675.\n\nRepresentanter: ing. S. F. Samuelsson,\nStockholm, Kungsg. 15, telefon: 116621;\nAB. Västkustgranit, Göteborg,\nJärn-torgsg. 12, telefon: 137581.\n\nAkt.-kap.: 360,000 kr. Antal\nindustriarb.: 90. — Brytningen upptogs på\n1600-talet, nuv. bolag bildat 1866.\n\nStyrelse: grevinnan G. Reuterskiöld\n(ordf.), frih. Gustaf Lagerfelt, dir. Arvid\nReuterskiöld.\n\nDisp.: Sigurd Johansson.\n\nFörsäljn.-chef: Rikard Carlson.\n\n*Nya Mek. Strumpfabriken AB.,\n\nBorås.\n\nTillverkar damstrumpor i natursilke\noch konstsilke.\n\nTelefon: 10989. — Akt.-kap.: 60,000\nkr. Antal industriarb.: 20. Tillv.-värde",
    "structured": {
        "1": {
            "name": "Nya Zinkgruvor",
            "location": "Falun",
            "business": "Gruvdrift och skogshantering",
            "contact": {
                "office": "Falun",
                "phone": [
                    "3801"
                ],
                "postgiro": "83681"
            },
            "financials": {
                "capital": "89,600 kr",
                "employees": {
                    "total": 0,
                    "management": 0,
                    "production": 12
                },
                "annual_turnover": "Information saknas",
                "annual_production_value": "110,000 kr"
            },
            "foundation_year": 1898,
            "board": [
                {
                    "name": "Sven Thorné",
                    "role": "Direktör"
                },
                {
                    "name": "Otto Åkerström",
                    "role": "Dispens. King"
                },
                {
                    "name": "Axel Åström",
                    "role": "Bankombudsman"
                }
            ]
        },
        "2": {
            "name": "Nya Lervarufabriken, V. Tunberg & Co.",
            "location": "Töreboda",
            "products": "Blomkrukor, oglaserade blomkrukor",
            "contact": {
                "phone": [
                    "175"
                ],
                "postgiro": "83681"
            },
            "financials": {
                "employees": {
                    "total": 12
                },
                "annual_production_value": "110,000 kr"
            },
            "foundation_year": 1926,
            "owners": [
                "Victor Tunberg",
                "Richard Tunberg"
            ]
        },
        "3": {
            "name": "Nya AB. Liljeqvists Sågblads- & Redskapsfabrik",
            "location": "Eskilstuna",
            "products": "Cirkel- och ramsågblad, maskinhyveljärn, murslevar, spadar, skyfflar, grepar, högafflar, trädgårdsredskap",
            "contact": {
                "telegraph": "Liljeqvistbolag, Eskilstuna",
                "phone": [
                    "37440"
                ],
                "postgiro": "10705"
            },
            "financials": {
                "capital": "250,000 kr",
                "employees": {
                    "total": 75
                },
                "annual_turnover": "Information saknas",
                "annual_production_value": "800,000 kr"
            },
            "foundation_year": 1923,
            "board": [
                {
                    "name": "Peter Schollin-Borg",
                    "role": "Kapten, Ordförande"
                },
                {
                    "name": "Eric Benson",
                    "role": "Direktör"
                },
                {
                    "name": "A. Gyllenberg",
                    "role": "Löjtnant"
                },
                {
                    "name": "Arvid H. Nilsson",
                    "role": "Dispens."
                },
                {
                    "name": "I. Ryott-Iohnson",
                    "role": "Medicinsk doktor"
                },
                {
                    "name": "Allan Schollin-Borg",
                    "role": "Bergsingenjör"
                },
                {
                    "name": "Gunnar Schollin-Borg",
                    "role": "Civilingenjör"
                },
                {
                    "name": "E. Wesström",
                    "role": "Stiftsjägmästare"
                },
                {
                    "name": "J.-E. Ålund",
                    "role": "Kapten"
                }
            ]
        },
        "4": {
            "name": "Nya Linneindustri AB",
            "location": "Borås",
            "description": "Se AB. Libo-Konfektion, Borås"
        },
        "5": {
            "name": "Nya AB. Luleå Varv & Verkstäder",
            "location": "Luleå",
            "products": "Järnkonstruktioner, metall- och tackjärnsgjutgods, gruv-, tipp- och torkugnsvagnar, båtskrov, landsvägsfärjor",
            "contact": {
                "phone": [
                    "2191",
                    "1809"
                ],
                "postgiro": "60980"
            },
            "financials": {
                "capital": "100,000 kr",
                "employees": {
                    "total": 140
                },
                "annual_production_value": "1,700,000 kr"
            },
            "foundation_year": 1932,
            "director": "Bengt Sandström"
        },
        "6": {
            "name": "Nya Läderfabriks AB. Göta",
            "location": "Örebro",
            "products": "Ovanläder, hästchevreaux, boxsidor, sportläder, kalvskinn, impregnerat ovanläder, spalt till arbetshandskar, foderskinn",
            "contact": {
                "office": "Örebro",
                "phone": [
                    "Oscaria",
                    "106"
                ]
            },
            "financials": {
                "capital": "150,000 kr",
                "employees": {
                    "total": 114
                },
                "annual_production_value": "2,980,000 kr"
            },
            "foundation_year": 1937,
            "owners": [
                "Skofabriks AB. Oscaria, Örebro"
            ],
            "director": "B. Klinge"
        },
        "7": {
            "name": "Nya Marmorbruks AB.",
            "location": "Kolmården",
            "products": "Marmorblock, marmorskivor, marmor- och kalkstensarbeten, trappor, golv, pelare, pilastrar, fönsterplattor, diskbänkar, disk- och vågskivor, möbelmarmor, gravvårdar, krematorieurnor, prydnads- och konstföremål",
            "contact": {
                "office": "Kolmården",
                "phone": [
                    "Kolmården 4"
                ],
                "postgiro": "7675"
            },
            "financials": {
                "capital": "360,000 kr",
                "employees": {
                    "total": 90
                }
            },
            "foundation_year": 1866,
            "board": [
                {
                    "name": "G. Reuterskiöld",
                    "role": "Grevinna, Ordförande"
                },
                {
                    "name": "Gustaf Lagerfelt",
                    "role": "Friherre"
                },
                {
                    "name": "Arvid Reuterskiöld",
                    "role": "Direktör"
                }
            ],
            "sales_manager": "Rikard Carlson"
        },
        "8": {
            "name": "Nya Mek. Strumpfabriken AB.",
            "location": "Borås",
            "products": "Damstrumpor i natursilke och konstsilke",
            "contact": {
                "phone": [
                    "10989"
                ]
            },
            "financials": {
                "capital": "60,000 kr",
                "employees": {
                    "total": 20
                },
                "annual_production_value": "Information saknas"
            }
        }
    }
}