{
    "original": "S ävedalen—Söderb er g\n\nSävedalens Fläkt- &amp;\nSvetsningsverkstad AB., Sävedalen.\n\nSe Västsvenska Fläkt AB., Göteborg.\n\n*Säveåns AB., Göteborg.\nSe Säfveåns AB., Göteborg.\n\n*Sävsjö Bryggeri, Sävsjö.\nSe Nässjö Bryggeri AB., Nässjö.\n\nSävsjö-hus, Fabian Andersson,\n\nSävsjö.\n\nTillverkar monteringsfärdiga trähus vid\nsnickerifabrik i Sävsjö (Jönköp. l.).\nFirman driver även handel med trävaror och\nbyggnadsmateriel.\n\nTelefon: »Bygge». Antal industriarb.:\n20. — Firman etabl. 1920.\n\nÄgare o. chef: fabr. Fabian Andersson.\n\nSävsjös Mekaniska Borstfabrik,\n\nSävsjö.\n\nTillverkar hushållsborstar,\nindustribor-star samt penslar vid fabrik i Sävsjö\n(Jönköp. l.).\n\nTelegr.-adr.: Sävsjöborst, Sävsjö.\nTelefon: 314. Postgiro: # 280353. — Antal\nindustriarb.: 30. Tillv.-värde pr år:\n1,000,000 kr. — Firman etabl. 1943.\nÄgare o. chef: fabr. Kurt Hennig.\n\nSävsjö.\n\n*Säfsjö Skofabriks AB., Sävsjö.\n\nSkofabrik i Sävsjö (Jönköp. l.).\nTillverkar herr-, dam- och barnskor,\nsmär-tingskor. sandaler m. m.\n\nTelesrr.-adr.: Skofabriken, Sävsjö.\nTelefon: 7. Postgiro: 24698.\n\nAkt.-kap.: 150 000 kr. Antal\nindustriarb.: 40. Tillv.-värde pr år: 500,000 kr.\n\n—\tFirman etabl. 1876.\n\nStyrelse: godsäg. Gustaf Lundberg\n(ordf.), disp. Gunnar Danielsson, dir.\nEnoc Holmqvist.\n\nVerkst. dir.: Enoc Holmqvist.\nDisp.: Gunnar Danielsson.\n\n*AB. Sävsjö Snickerifabrik,\n\nSävsjö.\n\nTillverkar fönster, dörrar, trappor och\ninredningar vid fabrik i Sävsjö\n(Jönköp. l.).\n\nTelefon: 117. Postgiro: 136766. —\nAkt.-kap.: 30,000 kr. Antal industriarb.: 24.\n\n—\tFirman etabl. 1918, bolag#1930.\nStyrelse o. verkst. dir.: disp. Nils G.\n\nAndersson.\n\nSävsjö Trävaru &amp; Handels AB.,\n\nSävsjö.\n\nSågverk och hyvleri i Sävsjö, sågverk\ni Lägern, sågverk och hyvleri i Klefshult\nsamt stolfabrik i Skillingaryd (samtl. i\nJönköp. l.). Tillverkar sågade och\nhyvlade trävaror, sparrar, bjälkar, spånläkt,\ntakspån och laths, pinnstolar och\nstolsitsar, fåtöljer och andra möbler samt\nträkol.\n\nTelegr.-adr.: Träbolaget, Sävsjö.\nTelefon: 3. Postgiro: 15265.\n\nAkt.-kap.: 500,000 kr. Antal\nindustriarb.: 125. Årstillv.: 3,000 stds trävaror.\n— Firman grundad 1868, bolag 1921.\n\nStyrelse: grossh. Tobias Carlsson\n(ordf.), fru Ingrid Carlsson, bankkamrer\nO. Zakrisson.\n\nVerkst. dir.: Tobias Carlsson.\n\n*Sävsjöströms Bruk, Sävsjöström.\n\nSe AB. Brusafors-Hällefors,\nSilverdalen.\n\n*Sävsjöströms Lådfabrik,\n\nSävsjöström.\n\nSe AB. S-B Bygge, Växjö.\n\n*\tSöderbergs Metallgjuteri,\n\nEskilstuna.\n\nSe Bröderna Söderbergs Metallgjuteri,\nEskilstuna.\n\n*B. F. Söderberg &amp; C:o Skofabrik,\n\nGöteborg.\n\nTillverkar ago-, rand- och genomsydda\nskodon. Varunamn: »Excelda».\n\nKontor: Vindragaregatan 14. Telefon:\n220355 o. 222355. Postgiro: 41882.\n\nAntal industriarb.: 50. Tillv.-värde pr\når: 610,000 kr. — Firman etabl. 1900.\n\nÄgare o. chef: fabr. Bror F. Söderberg.\n\n*\tGustaf Söderbergs\nKonfektionsindustri, Eumla.\n\nKonfektionsfabrik i Kumla (Örebro l.).\nTillverkar herrkostymer och överplagg,\nuniformer samt damdräkter. Varumärke:\n»Geson».\n\nTelefon: Örebro »Geson» o. 70925.\nPostgiro: 86763. — Antal industriarb.:\n115. — Firman etabl. 1933.\n\nÄgare o. chef: fabr. Gustaf Söderberg.\n\n*AB. Hj. Söderberg, Uppsala.\n\nKonfektionsfabrik i Uppsala och\nsyfabrik i örbyhus (Uppsala l.). Tillverkar",
    "structured": {
        "1": {
            "name": "Sävedalens Fläkt- & Svetsningsverkstad AB.",
            "location": "Sävedalen.",
            "business": "Fläkt- & svetsningsverkstad.",
            "contact": {
                "office": "Sävedalen.",
                "phone": [],
                "head_office": "",
                "sales_offices": [],
                "factory_office": "",
                "factory_phone": ""
            },
            "financials": {
                "capital": "",
                "employees": {},
                "annual_turnover": "",
                "annual_production_value": ""
            },
            "foundation_year": 0,
            "current_name_year": 0,
            "board": [],
            "owners": [],
            "director": "",
            "managing_director": "",
            "sales_manager": "",
            "manager": ""
        },
        "2": {
            "name": "Säveåns AB.",
            "location": "Göteborg.",
            "business": "Se Säfveåns AB.",
            "contact": {
                "office": "",
                "phone": [],
                "postgiro": "",
                "head_office": "",
                "sales_offices": [],
                "telegraph": "",
                "factory_office": "",
                "factory_phone": ""
            },
            "financials": {
                "capital": "",
                "employees": {},
                "annual_turnover": "",
                "annual_production_value": ""
            },
            "foundation_year": 0,
            "current_name_year": 0,
            "board": [],
            "owners": [],
            "director": "",
            "managing_director": "",
            "sales_manager": "",
            "manager": ""
        },
        "3": {
            "name": "Se Västsvenska Fläkt AB.",
            "location": "Göteborg.",
            "business": "Fläkt AB.",
            "contact": {
                "office": "",
                "phone": [],
                "postgiro": "",
                "head_office": "",
                "sales_offices": [],
                "telegraph": "",
                "factory_office": "",
                "factory_phone": ""
            },
            "financials": {
                "capital": "",
                "employees": {},
                "annual_turnover": "",
                "annual_production_value": ""
            },
            "foundation_year": 0,
            "current_name_year": 0,
            "board": [],
            "owners": [],
            "director": "",
            "managing_director": "",
            "sales_manager": "",
            "manager": ""
        },
        "4": {
            "name": "Sävsjö-hus, Fabian Andersson",
            "location": "Sävsjö.",
            "business": "Monteringsfärdiga trähus, trävaror, byggnadsmateriel.",
            "contact": {
                "office": "Sävsjö (Jönköp. l.).",
                "phone": [],
                "head_office": "",
                "sales_offices": [],
                "telegraph": "",
                "factory_office": "",
                "factory_phone": ""
            },
            "financials": {
                "capital": "",
                "employees": {},
                "annual_turnover": "",
                "annual_production_value": ""
            },
            "foundation_year": 1920,
            "current_name_year": 0,
            "board": [],
            "owners": [],
            "director": "Fabian Andersson",
            "managing_director": "",
            "sales_manager": "",
            "manager": "Fabian Andersson"
        },
        "5": {
            "name": "Sävsjös Mekaniska Borstfabrik",
            "location": "Sävsjö.",
            "business": "Hushållsborstar, industriborstar, penslar.",
            "contact": {
                "office": "Sävsjö (Jönköp. l.).",
                "phone": [
                    "314"
                ],
                "postgiro": "# 280353",
                "head_office": "",
                "sales_offices": [],
                "telegraph": "Sävsjöborst, Sävsjö.",
                "factory_office": "",
                "factory_phone": ""
            },
            "financials": {
                "capital": "",
                "employees": {},
                "annual_turnover": "1,000,000 kr.",
                "annual_production_value": ""
            },
            "foundation_year": 1943,
            "current_name_year": 0,
            "board": [],
            "owners": [],
            "director": "Kurt Hennig",
            "managing_director": "",
            "sales_manager": "",
            "manager": "Kurt Hennig"
        },
        "6": {
            "name": "Säfsjö Skofabriks AB.",
            "location": "Sävsjö (Jönköp. l.).",
            "business": "Herr-, dam- och barnskor, smärtingskor, sandaler m. m.",
            "contact": {
                "office": "Sävsjö (Jönköp. l.).",
                "phone": [
                    "7"
                ],
                "postgiro": "24698",
                "head_office": "",
                "sales_offices": [],
                "telegraph": "Skofabriken, Sävsjö.",
                "factory_office": "",
                "factory_phone": ""
            },
            "financials": {
                "capital": "150 000 kr.",
                "employees": {},
                "annual_turnover": "500,000 kr.",
                "annual_production_value": ""
            },
            "foundation_year": 1876,
            "current_name_year": 0,
            "board": [
                {
                    "name": "Gustaf Lundberg",
                    "role": "Ordförande"
                },
                {
                    "name": "Gunnar Danielsson",
                    "role": "Disponent"
                },
                {
                    "name": "Enoc Holmqvist",
                    "role": "Direktör"
                }
            ],
            "owners": [],
            "director": "",
            "managing_director": "",
            "sales_manager": "",
            "manager": ""
        },
        "7": {
            "name": "AB. Sävsjö Snickerifabrik",
            "location": "Sävsjö (Jönköp. l.).",
            "business": "Fönster, dörrar, trappor, inredningar.",
            "contact": {
                "office": "Sävsjö (Jönköp. l.).",
                "phone": [
                    "117"
                ],
                "postgiro": "136766",
                "head_office": "",
                "sales_offices": [],
                "telegraph": "",
                "factory_office": "",
                "factory_phone": ""
            },
            "financials": {
                "capital": "30,000 kr.",
                "employees": {},
                "annual_turnover": "",
                "annual_production_value": ""
            },
            "foundation_year": 1918,
            "current_name_year": 1930,
            "board": [
                {
                    "name": "Nils G. Andersson",
                    "role": "Disponent"
                }
            ],
            "owners": [],
            "director": "",
            "managing_director": "",
            "sales_manager": "",
            "manager": ""
        },
        "8": {
            "name": "Sävsjö Trävaru & Handels AB.",
            "location": "Sävsjö.",
            "business": "Sågade och hyvlade trävaror, sparrar, bjälkar, spånläkt, takspån och laths, pinnstolar, stolsitsar, fåtöljer, möbler, träkol.",
            "contact": {
                "office": "Sävsjö, Lägern, Klefshult (Jönköp. l.).",
                "phone": [
                    "3"
                ],
                "postgiro": "15265",
                "head_office": "",
                "sales_offices": [],
                "telegraph": "Träbolaget, Sävsjö.",
                "factory_office": "",
                "factory_phone": ""
            },
            "financials": {
                "capital": "500,000 kr.",
                "employees": {},
                "annual_turnover": "",
                "annual_production_value": "3,000 stds trävaror"
            },
            "foundation_year": 1868,
            "current_name_year": 1921,
            "board": [
                {
                    "name": "Tobias Carlsson",
                    "role": "Ordförande"
                },
                {
                    "name": "Ingrid Carlsson",
                    "role": ""
                },
                {
                    "name": "O. Zakrisson",
                    "role": "Bankkamrer"
                }
            ],
            "owners": [],
            "director": "",
            "managing_director": "Tobias Carlsson",
            "sales_manager": "",
            "manager": ""
        },
        "9": {
            "name": "B. F. Söderberg & C:o Skofabrik",
            "location": "Göteborg.",
            "business": "Ago-, rand- och genomsydda skodon.",
            "contact": {
                "office": "Vindragaregatan 14.",
                "phone": [
                    "220355",
                    "222355"
                ],
                "postgiro": "41882",
                "head_office": "",
                "sales_offices": [],
                "telegraph": "",
                "factory_office": "",
                "factory_phone": ""
            },
            "financials": {
                "capital": "",
                "employees": {},
                "annual_turnover": "610,000 kr.",
                "annual_production_value": ""
            },
            "foundation_year": 1900,
            "current_name_year": 0,
            "board": [],
            "owners": [],
            "director": "",
            "managing_director": "",
            "sales_manager": "",
            "manager": "Bror F. Söderberg"
        },
        "10": {
            "name": "Gustaf Söderbergs Konfektionsindustri",
            "location": "Kumla (Örebro l.).",
            "business": "Herrkostymer, överplagg, uniformer, damdräkter.",
            "contact": {
                "office": "Uppsala, Örbyhus (Uppsala l.).",
                "phone": [
                    "Örebro Geson",
                    "70925"
                ],
                "postgiro": "86763",
                "head_office": "",
                "sales_offices": [],
                "telegraph": "",
                "factory_office": "",
                "factory_phone": ""
            },
            "financials": {
                "capital": "",
                "employees": {},
                "annual_turnover": "",
                "annual_production_value": ""
            },
            "foundation_year": 1933,
            "current_name_year": 0,
            "board": [],
            "owners": [],
            "director": "",
            "managing_director": "",
            "sales_manager": "",
            "manager": "Gustaf Söderberg"
        },
        "11": {
            "name": "AB. Hj. Söderberg",
            "location": "Uppsala.",
            "business": "Konfektionsfabrik, syfabrik.",
            "contact": {
                "office": "Uppsala, Örbyhus (Uppsala l.).",
                "phone": [],
                "postgiro": "",
                "head_office": "",
                "sales_offices": [],
                "telegraph": "",
                "factory_office": "",
                "factory_phone": ""
            },
            "financials": {
                "capital": "",
                "employees": {},
                "annual_turnover": "",
                "annual_production_value": ""
            },
            "foundation_year": 0,
            "current_name_year": 0,
            "board": [],
            "owners": [],
            "director": "",
            "managing_director": "",
            "sales_manager": "",
            "manager": ""
        }
    }
}