{
    "original": "Lindshammar—Lindström\n\nTelefon: 46 o. 115. Postgiro: 133112.\nAkt.-kap.: 30,000 kr. Antal\nindustriarb.: 35. Tillv.-värde pr år: 300,000 kr.\n\n—\tFirman etabl. 1900, bolag 1937.\nVerkst. dir.: köpm. Erik Bergh.\n\nAB. Lindshammars Glasbruk,\n\nMilletorp.\n\nGlasbruk vid Lindshammar, Milletorp\n(Kronob. l.). Tillverkar slätt och slipat\nhushålls- och prydnadsglas, pressglas,\nkonservglas, emballageglas samt\nkem.-tekniskt glas.\n\nTelegr.-adr.: Lindsglas, Vetlanda.\nTelefon: Lindshammar 7. Postgiro: 29752.\nRepresentant: H. ISTordenson AB.,\nStockholm, Döbelnsg. 16 B, telefon: 307687.\n\nAkt.-kap.: 67,000 kr. Antal\nindustriarb.: 55. Tillv.-värde pr år: 300,000 kr.\n\n—\tFirman etabl. 1916, bolag 1928.\nDisp.: Anton Peterson.\n\nFörsäljn.- o. inköpschef: Erik\nHov-hammar.\n\nKamrer: Walter Andersson.\n\nLindsjös Verkstäder AB.,\n\nTrelleborg.\n\nMaskinfabrik och mek. verkstad.\nTillverkar tvättmaskiner, centrifuger,\nstryk-pressar och manglar för\ntvätterianlägg-ningar, maskiner för kemisk tvätt,\nfärge-rimaskiner, ångpannor,\nvulkaniserings-apparater och -formar,\nvulkaniserings-pressar, luftkompressorer, glassmaskiner,\nkyldiskar, vispmaskiner m. m.\n\nTelefon: 274 o. 2056. Postgiro: 30303.\n\n—\tAkt.-kap.: 100,000 kr. Antal\nindustriarb.: 30. Tillv.-värde pr år; 520,000 kr.\n\n—\tFirman etabl. 1898, bolag 1923.\nVerkst. dir.; Arvid Lindsjö.\nDriftsing.: Erik Lindsjö.\nKontorschef: Anton Fogelberg.\n\n\"Lindström &amp; Andel!, Elektr. AB.,\n\nGöteborg.\n\nSe Elektr. AB. Lindström &amp; Andell,\nGöteborg.\n\nLindström &amp; Co., Konfektions AB.,\n\nStockholm.\n\nSe Konfektions AB. Lindström &amp; Co.,\nStockholm.\n\n\"Lindström &amp; Lundberg AB.,\n\nStockholm.\n\nSe Waldemar Lindström AB.,\nStockholm.\n\n\"AB. Abet Lindströms Tricotfabrik,\n\nNorrköping.\n\nTillverkar trikåunderkläder.\nVarumärken: »FIX-stjärnan» o. »Flamingo».\n\nKontor: Värmlandsg. 29. Telefon:\n22741 o. 26341. Postgiro: 29402.\n\nRepresentanter: Erik Lindström,\nStockholm, Kungsgatan 27, telefon: 109510;\nAlbert Jacobsson, Stockholm, Odeng. 74,\ntelefon: 321745; Axel Eliasson, Malmö,\nMariedalsvägen 17, telefon: 19468.\n\nAkt.-kap.: 212,000 kr. Antal\nindustriarb.: 90. Tillv.-värde pr år: 1,000,000 kr.\n\n—\tFirman etabl. 1913, bolag 1929.\nStyrelse o. verkst. direktörer; disp.\n\nAlf Lindström o. ing. Marion Lindström.\nKontorschef: John Jewert.\n\n\"Albert Lindström, Metallvaru- och\nNysilverfabrik, Eskilstuna.\n\nTillverkar kaffeserviser, korgar,\nskålar, brickor, fat, ljusstakar m. m, i\nnysilver samt kuvertnysilver.\n\nTelefon: 30108 o. 31828. Postgiro:\n27789. — AntaL industriarb.: 50. —\nFirman etabl. 1878.\n\nÄgare o. chef: fabr. Albert Lindström.\nDisp.: Harry Lindström.\n\nCarl Lindströms Eftr.\nKonst-smidesverkstad, Malmö.\n\nTillverkar järnkonstruktioner,\nkonst-och byggnadssmiden.\n\nKontor: Kattsundsg. 5. Telefon: 21151.\nPostgiro: 148883. — Antal industriarb.:\n29. Tillv.-värde pr år: 330,000 kr. —\nFirman etabl. 1904.\n\nÄgare o. chef: smedm. Einar Stern.\n\n\"F. E. Lindström AB., Eskilstuna.\n\nSpecialfabrik för tillverkning av alla\nslag av tänger.\n\nTelegr.-adr.: Tänger. Eskilstuna.\nTelefon: 37420. Postgiro: 10796.\n\nAkt.-kap.: 300,000 kr. Antal\nindustriarb.: 120. Tillv.-värde pr år: 1,400,000 kr.\n\n—\tFirman etabl. 1856, bolag 1930.\nStyrelse: dir. Mauritz Wedén (ordf.),\n\nfru Signe Wedén, disp. Sven Wedén.\nVerkst. dir.: Mauritz Wedén.\n\n\"AB. Gustaf Lindströms Boktryckeri,\n\nStockholm.\n\nUtför bok- och tidningstryck.\nKontor: Malmskillnadsg. 31. Telefon:\n106150 o. 109612. Postgiro: 58146.\n\n&gt;4*",
    "structured": {
        "0": {
            "name": "AB. Lindshammars Glasbruk",
            "location": "Milletorp, Kronob. l.",
            "business": "Glasbruk vid Lindshammar",
            "products": "Tillverkar slätt och slipat hushålls- och prydnadsglas, pressglas, konservglas, emballageglas samt kem.-tekniskt glas",
            "contact": {
                "office": "Milletorp",
                "phone": [
                    "Lindshammar 7"
                ],
                "postgiro": "29752",
                "telegraph": "Lindsglas, Vetlanda"
            },
            "financials": {
                "capital": "67,000 kr",
                "employees": {
                    "industriarb": 55
                },
                "annual_production_value": "300,000 kr"
            },
            "foundation_year": 1916,
            "corporation_year": 1928,
            "board": [
                {
                    "name": "Anton Peterson",
                    "role": "Disp."
                }
            ],
            "sales_manager": "Erik Hov-hammar",
            "manager": "Walter Andersson"
        },
        "1": {
            "name": "Lindsjös Verkstäder AB.",
            "location": "Trelleborg",
            "business": "Maskinfabrik och mek. verkstad",
            "products": "Tillverkar tvättmaskiner, centrifuger, stryk-pressar och manglar för tvätterianläggningar, maskiner för kemisk tvätt, färgerimaskiner, ångpannor, vulkaniserings-apparater och -formar, vulkaniserings-pressar, luftkompressorer, glassmaskiner, kyldiskar, vispmaskiner m. m.",
            "contact": {
                "phone": [
                    "274",
                    "2056"
                ],
                "postgiro": "30303"
            },
            "financials": {
                "capital": "100,000 kr",
                "employees": {
                    "industriarb": 30
                },
                "annual_production_value": "520,000 kr"
            },
            "foundation_year": 1898,
            "corporation_year": 1923,
            "board": [
                {
                    "name": "Arvid Lindsjö",
                    "role": "Verkst. dir."
                }
            ],
            "director": "Erik Lindsjö",
            "manager": "Anton Fogelberg"
        },
        "2": {
            "name": "AB. Abet Lindströms Tricotfabrik",
            "location": "Norrköping",
            "business": "Tillverkar trikåunderkläder",
            "products": "Varumärken: »FIX-stjärnan» o. »Flamingo»",
            "contact": {
                "office": "Värmlandsg. 29",
                "phone": [
                    "22741",
                    "26341"
                ],
                "postgiro": "29402",
                "telegraph": "Lindsglas, Vetlanda"
            },
            "financials": {
                "capital": "212,000 kr",
                "employees": {
                    "industriarb": 90
                },
                "annual_production_value": "1,000,000 kr"
            },
            "foundation_year": 1913,
            "corporation_year": 1929,
            "director": "disp. Alf Lindström",
            "manager": "John Jewert"
        },
        "3": {
            "name": "AB. Abet Lindströms Tricotfabrik",
            "location": "Norrköping",
            "business": "Tillverkar trikåunderkläder",
            "products": "Varumärken: »FIX-stjärnan» o. »Flamingo»",
            "contact": {
                "office": "Värmlandsg. 29",
                "phone": [
                    "22741",
                    "26341"
                ],
                "postgiro": "29402",
                "telegraph": "Lindsglas, Vetlanda"
            },
            "financials": {
                "capital": "212,000 kr",
                "employees": {
                    "industriarb": 90
                },
                "annual_production_value": "1,000,000 kr"
            },
            "foundation_year": 1913,
            "corporation_year": 1929,
            "director": "disp. Alf Lindström",
            "manager": "John Jewert"
        },
        "4": {
            "name": "Albert Lindström, Metallvaru- och Nysilverfabrik",
            "location": "Eskilstuna",
            "business": "Tillverkar kaffeserviser, korgar, skålar, brickor, fat, ljusstakar m. m, i nysilver samt kuvertnysilver",
            "contact": {
                "phone": [
                    "30108",
                    "31828"
                ],
                "postgiro": "27789"
            },
            "financials": {
                "employees": {
                    "industriarb": 50
                }
            },
            "foundation_year": 1878
        },
        "5": {
            "name": "Carl Lindströms Eftr. Konst-smidesverkstad",
            "location": "Malmö",
            "business": "Tillverkar järnkonstruktioner, konst-och byggnadssmiden",
            "contact": {
                "office": "Kattsundsg. 5",
                "phone": [
                    "21151"
                ],
                "postgiro": "148883"
            },
            "financials": {
                "employees": {
                    "industriarb": 29
                },
                "annual_production_value": "330,000 kr"
            },
            "foundation_year": 1904
        },
        "6": {
            "name": "F. E. Lindström AB.",
            "location": "Eskilstuna",
            "business": "Specialfabrik för tillverkning av alla slag av tänger",
            "contact": {
                "telegraph": "Tänger, Eskilstuna",
                "phone": [
                    "37420"
                ],
                "postgiro": "10796"
            },
            "financials": {
                "capital": "300,000 kr",
                "employees": {
                    "industriarb": 120
                },
                "annual_production_value": "1,400,000 kr"
            },
            "foundation_year": 1856,
            "corporation_year": 1930,
            "board": [
                {
                    "name": "Mauritz Wedén",
                    "role": "Styrelse"
                },
                {
                    "name": "fru Signe Wedén",
                    "role": "Styrelse"
                },
                {
                    "name": "Sven Wedén",
                    "role": "Disp."
                }
            ],
            "director": "Mauritz Wedén"
        },
        "7": {
            "name": "AB. Gustaf Lindströms Boktryckeri",
            "location": "Stockholm",
            "business": "Utför bok- och tidningstryck",
            "contact": {
                "office": "Malmskillnadsg. 31",
                "phone": [
                    "106150",
                    "109612"
                ],
                "postgiro": "58146"
            }
        }
    }
}