{
    "original": "Vä nn land— Värna m o\n\nKontor o. postadr.: Ulvsunda 1.\nTelegr.-adr.: Galor, Stockholm. Telefon:\nStockholm 282510. Postgiro: 1719. Filialer:\nGöteborg, Malmö, Karlstad, Karlskoga,\nÖstersund, Örebro o. Sundsvall.\n\nAkt.-kap.: 1,125,000 kr. Antal\nindustriarb.: 350. Tillv.-värde pr år: 4,300,000\nkr. — Bolaget, grundat 1902, äges av\nKooperativa Förbundet.\n\nStyrelse: dir. Albin Johansson (ordf.),\nfil. lic. Mauritz Bonow, dir. Hjalmar\nDegerstedt, dir. Hugo Edstam, dir.\nGustaf Osvald, dir. Ernst Persson.\n\nVerkst. dir.: C. L. Rydh.\n\növering.: Edvard Ryd.\n\nVärmland.\n\nAB. Wermlandsbryggerier,\n\nKarlstad.\n\nBolaget driver enligt\nkommissionärsav-tal bryggerirörelsen vid Färjestads\nBryggeri AB. och Karlstads Bryggeri AB.,\nbåda i Karlstad (se dessa bolag).\n\nTelefon: 11883. — Akt.-kap.: 1,500,000\nkr.\n\nBolaget grundat 1939.\n\nStyrelse: dir. Nils G. Arvedson (ordf.),\nt&gt;orgm. Stig Allsing, ing. Arved\nArvedson, dir. Amon Bäcklund, disp. Sven\nJansson, disp. John Löfgren.\n\nVerkst. dir.: Sven Jansson.\n\nAB. Värmlandshus, Skattkärr.\n\nTillverkar monteringsfärdiga trähus\nvid trähusfabrik i Skattkärr (Värml. l.).\n\nFabrikskontor: Skattkärr; telefon: 90 o.\n91. Försäljn.-kontor: Skagersvik; telefon:\nOullspång »Skagersviksbolagen».\nPostgiro: 81091.\n\nAkt.-kap.: 100,000 kr. Antal\nindustriarb.: 40. Tillv.-värde pr år: 2,500,000 kr.\n— Bolaget grundat 1942.\n\nDisp.: Göte Wästlund (Skagersvik).\n\n*AB. Värmlands Trikåfabrik,\n\nKarlstad.\n\nTrikåfabriker och färgerier i Karlstad\noch i Tidafors, Molkom (Värml. l.).\nTillverkar trikåvaror av ull, bomull och silke.\nVarumärken: »örntrikå» o. »Regatta».\n\nTelegr.-adr.: Trikå, Karlstad. Telefon:\n11160 o. 12610. Postgiro: 72545.\nRepresentanter: i Stockholm: Sven Lindberg,\nOalag. 45, telefon: 331356; i Malmö: W.\nJepsson, Verkstadsg. 1, telefon: 24755.\n\nAkt.-kap.: 300,000 kr. Antal\nindustriarb.: 150. — Bolaget grundat 1914.\n\nStyrelse: jur. kand. Otto Ågren\n(ordf.), dir. S. Felländer, kamrer\nHarry Nyman, dir. S. Warholm, dir. Gustaf\nWidén.\n\n63\n\nVerkst. dir.: S. Warholm.\n\nKamrer: Carl-Gust. Rundquist.\n\nFör sal jn.-chef: John Lundqvist.\n\nVärmlands Träindustri AB.,\n\nGöteborg.\n\nSågverk, hyvleri och lådfabrik vid\nSä-venäs, Göteborg. Tillverkar sågade och\nhyvlade trävaror samt lådbräder.\n\nKontor: Lilla Bommenstorg 2.\nTelegr.-adr.: Wejba, Göteborg. Telefon: 134386.\nPostgiro: 42617.\n\nAkt.-kap.: 200,000 kr. Antal\nindustriarb.: 50. Årstillv.: 4,000 stds trävaror.\n\nSågverket anlagt 1918, nuv. bolag\ngrundat 1925.\n\nStyrelse o. verkst. dir.: Ivan Andersson.\n\nKontorschef: Eric Anderson.\n\n*AB. Värnamo Bryggeri,\n\nVärnamo.\n\nTillverkar malt- och läskedrycker.\n\nTelefon: 9 o. 753. Postgiro: 74567. —\nAkt.-kap.: 200,000 kr. Antal industriarb.:\n15. Tillv.-värde pr år: 350,000 kr. -—\nBryggeriet anlagt 1849, bolag 1936.\n\nStyrelse: adv. J. Ramberg (ordf.),\nköpm. Henrik Andersson, fru Eva André.\n\nVerkst. dir.: Eva André.\n\nDisp.: Erik Boustedt.\n\nBryggm.: Gösta Harksen.\n\n*Värnamo Byggnadssnickeri, Cust.\nLindberg, Värnamo.\n\nTillverkar fönster, dörrar, trappor och\ninredningar.\n\nTelefon: 10164 o. 11011. Postgiro:\n130851. — Arb.-antal: 10. Tillv.-värde pr\når: 140,000 kr. — Firman etabl. 1925.\n\nÄgare o. chef: fabr. Gustaf Lindberg.\n\nAB. Värnamo Cummifabrik,\n\nVärnamo.\n\nTillverkar cykeldäck, cykelslangar, däck\nför skottkärror och transportvagnar,\ngummistövlar, galoscher, bottiner, tennis- och\ngymnastikskor, gummiparkett, gummerade\nvävnader, regnkappor, cykelhandtag,\npedalgummi, gummibeläggningar,\nskidgum-mi, gummiplattor, packningar,\nvattenslang och högtrycksslang, tekniska\nartiklar m. m.\n\nTelegr.-adr. o. telefon: Värnamogummi,.\nVärnamo. Postgiro: 134760.\n\nAkt.-kap.: 600,000 kr. Antal\nindustriarb.: 500. Tillv.-värde pr år: 9,000,000 kr.\n— Firman etabl. 1928, bolag 1936.\n\nStyrelse: disp. Tage Warborn.\n\nVerkst. dir.: Gösta ödmann.\n\nKontorschef; B. Sigfr. Nilsson.\n\nFörsäljn.-chef: Herlof Larsson.\n\n1*",
    "structured": {
        "firms": [
            {
                "name": "Vännland",
                "location": "Ulvsunda 1, Stockholm",
                "contact": {
                    "office": "Ulvsunda 1, Stockholm",
                    "phone": [
                        "Stockholm 282510"
                    ],
                    "postgiro": "1719",
                    "head_office": "Stockholm",
                    "sales_offices": [
                        {
                            "location": "Göteborg",
                            "phone": "xxx"
                        },
                        {
                            "location": "Malmö",
                            "phone": "xxx"
                        },
                        {
                            "location": "Karlstad",
                            "phone": "xxx"
                        },
                        {
                            "location": "Karlskoga",
                            "phone": "xxx"
                        },
                        {
                            "location": "Östersund",
                            "phone": "xxx"
                        },
                        {
                            "location": "Örebro",
                            "phone": "xxx"
                        },
                        {
                            "location": "Sundsvall",
                            "phone": "xxx"
                        }
                    ],
                    "telegraph": "Galor, Stockholm",
                    "factory_office": "xxx",
                    "factory_phone": "xxx"
                },
                "financials": {
                    "capital": "1,125,000 kr",
                    "employees": {
                        "industrial": 350
                    },
                    "annual_turnover": "xxx",
                    "annual_production_value": "4,300,000 kr"
                },
                "foundation_year": 1902,
                "owners": [
                    "Kooperativa Förbundet"
                ],
                "board": [
                    {
                        "name": "Albin Johansson",
                        "role": "Ordförande"
                    },
                    {
                        "name": "Mauritz Bonow",
                        "role": "Fil. Lic."
                    },
                    {
                        "name": "Hjalmar Degerstedt",
                        "role": "Direktör"
                    },
                    {
                        "name": "Hugo Edstam",
                        "role": "Direktör"
                    },
                    {
                        "name": "Gustaf Osvald",
                        "role": "Direktör"
                    },
                    {
                        "name": "Ernst Persson",
                        "role": "Direktör"
                    }
                ],
                "director": "C. L. Rydh",
                "managing_director": "C. L. Rydh",
                "sales_manager": "Edvard Ryd"
            },
            {
                "name": "AB. Wermlandsbryggerier",
                "location": "Karlstad",
                "products": "xxx",
                "contact": {
                    "office": "Karlsta",
                    "phone": [
                        "11883"
                    ],
                    "postgiro": "xxx",
                    "head_office": "xxx",
                    "sales_offices": [],
                    "telegraph": "xxx",
                    "factory_office": "xxx",
                    "factory_phone": "xxx"
                },
                "financials": {
                    "capital": "1,500,000 kr"
                },
                "foundation_year": 1939,
                "board": [
                    {
                        "name": "Nils G. Arvedson",
                        "role": "Ordförande"
                    },
                    {
                        "name": "Stig Allsing",
                        "role": "Torgm."
                    },
                    {
                        "name": "Arved Arvedson",
                        "role": "Ing."
                    },
                    {
                        "name": "Amon Bäcklund",
                        "role": "Direktör"
                    },
                    {
                        "name": "Sven Jansson",
                        "role": "Disp."
                    },
                    {
                        "name": "John Löfgren",
                        "role": "Disp."
                    }
                ],
                "director": "Sven Jansson"
            },
            {
                "name": "AB. Värmlandshus",
                "location": "Skattkärr",
                "products": "Monteringsfärdiga trähus",
                "contact": {
                    "office": "Skattkärr",
                    "phone": [
                        "90",
                        "91"
                    ],
                    "postgiro": "81091",
                    "head_office": "xxx",
                    "sales_offices": [
                        {
                            "location": "Oullspång",
                            "phone": "xxx"
                        }
                    ],
                    "telegraph": "xxx",
                    "factory_office": "Skattkärr",
                    "factory_phone": "xxx"
                },
                "financials": {
                    "capital": "100,000 kr",
                    "employees": {
                        "industrial": 40
                    },
                    "annual_production_value": "2,500,000 kr"
                },
                "foundation_year": 1942,
                "director": "Göte Wästlund"
            },
            {
                "name": "AB. Värmlands Trikåfabrik",
                "location": "Karlstad",
                "products": "Trikåvaror av ull, bomull och silke",
                "contact": {
                    "office": "Karlstad",
                    "phone": [
                        "11160",
                        "12610"
                    ],
                    "postgiro": "72545",
                    "head_office": "xxx",
                    "sales_offices": [
                        {
                            "location": "Stockholm",
                            "phone": "331356"
                        },
                        {
                            "location": "Malmö",
                            "phone": "24755"
                        }
                    ],
                    "telegraph": "Trikå, Karlstad",
                    "factory_office": "Tidafors, Molkom",
                    "factory_phone": "xxx"
                },
                "financials": {
                    "capital": "300,000 kr",
                    "employees": {
                        "industrial": 150
                    }
                },
                "foundation_year": 1914,
                "board": [
                    {
                        "name": "Otto Ågren",
                        "role": "Jur. Kand."
                    },
                    {
                        "name": "S. Felländer",
                        "role": "Direktör"
                    },
                    {
                        "name": "Harry Nyman",
                        "role": "Kamrer"
                    },
                    {
                        "name": "S. Warholm",
                        "role": "Direktör"
                    },
                    {
                        "name": "Gustaf Widén",
                        "role": "Direktör"
                    }
                ],
                "director": "S. Warholm",
                "sales_manager": "John Lundqvist"
            },
            {
                "name": "Värmlands Träindustri AB.",
                "location": "Göteborg",
                "products": "Sågade och hyvlade trävaror samt lådbräder",
                "contact": {
                    "office": "Lilla Bommenstorg 2, Göteborg",
                    "phone": [
                        "134386"
                    ],
                    "postgiro": "42617",
                    "head_office": "xxx",
                    "sales_offices": [],
                    "telegraph": "Wejba, Göteborg",
                    "factory_office": "Sävenäs, Göteborg",
                    "factory_phone": "xxx"
                },
                "financials": {
                    "capital": "200,000 kr",
                    "employees": {
                        "industrial": 50
                    },
                    "annual_production_value": "4,000 stds trävaror"
                },
                "foundation_year": 1925,
                "board": [
                    {
                        "name": "Ivan Andersson",
                        "role": "Verkst. Dir."
                    }
                ],
                "director": "Ivan Andersson",
                "manager": "Eric Anderson"
            },
            {
                "name": "AB. Värnamo Bryggeri",
                "location": "Värnamo",
                "products": "Malt- och läskedrycker",
                "contact": {
                    "phone": [
                        "9",
                        "753"
                    ],
                    "postgiro": "74567"
                },
                "financials": {
                    "capital": "200,000 kr",
                    "employees": {
                        "industrial": 15
                    },
                    "annual_production_value": "350,000 kr"
                },
                "foundation_year": 1936,
                "board": [
                    {
                        "name": "J. Ramberg",
                        "role": "Adv."
                    },
                    {
                        "name": "Henrik Andersson",
                        "role": "Köpm."
                    },
                    {
                        "name": "Eva André",
                        "role": "Frv"
                    }
                ],
                "director": "Eva André",
                "sales_manager": "Erik Boustedt",
                "manager": "Gösta Harksen"
            },
            {
                "name": "Värnamo Byggnadssnickeri, Cust. Lindberg",
                "location": "Värnamo",
                "products": "Fönster, dörrar, trappor och inredningar",
                "contact": {
                    "office": "Cust. Lindberg, Värnamo",
                    "phone": [
                        "10164",
                        "11011"
                    ],
                    "postgiro": "130851"
                },
                "financials": {
                    "employees": {
                        "industrial": 10
                    },
                    "annual_production_value": "140,000 kr"
                },
                "foundation_year": 1925,
                "manager": "Gustaf Lindberg"
            },
            {
                "name": "AB. Värnamo Cummifabrik",
                "location": "Värnamo",
                "products": "Cykeldäck, cykelslangar, gummistövlar, tennis- och gymnastikskor, tekniska artiklar m. m.",
                "contact": {
                    "phone": [
                        "9",
                        "753"
                    ],
                    "postgiro": "74567"
                },
                "financials": {
                    "capital": "600,000 kr",
                    "employees": {
                        "industrial": 500
                    },
                    "annual_production_value": "9,000,000 kr"
                },
                "foundation_year": 1936,
                "board": [
                    {
                        "name": "Tage Warborn",
                        "role": "Disp."
                    }
                ],
                "director": "Gösta ödmann",
                "managing_director": "B. Sigfr. Nilsson",
                "sales_manager": "Herlof Larsson"
            }
        ]
    }
}