{
    "original": "Fröberg—Fyleverken\n\nAkt.-kap.: 350,000 kr. Antal\nindustri-sarb.: 30. Tillv.-värde pr år (egen\ntillverkning): 400,000 kr. — Bolaget\ngrundat 1907.\n\nStyrelse o. verkst. direktörer:\nSieg-inund Eisner o. Sten Eisner.\n\n\"Fröbergs Fabriker, Borlänge.\n\nSvarveri och snickerifabrik i Borlänge\n(Kopparb. l.). Tillverkar golv- och\nbordslampor, ljusstakar, tamburhyllor,\nmurar-verktyg, verktygsskaft, rullar och\nsignalkorkar till angeldon samt träslöjdsaker\nsåsom skålar, fat, ordförandeklubbor m.m.\n\nTelefon: 10155. Postgiro: 180935. —\nAntal industriarb.: 13. Tillv.-värde pr\når: 120,000 kr. — Firman etabl. 1913,\nnuv. namn 1944.\n\nÄgare o. chef: fabr. Nils Fröberg.\n\nAB. John Fröberg, Finspång.\n\nAccidenstryckeri, stämpelfabrik och\npappersförädlingsindustri i Finspång\n(Östergötl. l.). Tillverkar trycksaker,\nstämplar, gummiklichéer för anilin- och\nboktryck, gummerat papper,\nförseglingsremsor, fönsterremsor, vaxpapper och\nt&gt;rödomslag, fuktapparater samt\nskylt-montrar (varumärken: »Visir» o. »Dixi»).\n\nTelefon: »John Fröberg». Postgiro:\n15432. — Akt.-kap.: 125.000 kr.\nTillv.-värde pr år: 1,300,000 kr. — Firman\n*3tabl. 1879, bolag 1926.\n\nStyrelse: bankdir. S. Mårtenson (ordf.),\nf. d. riksdagsm. Karl Andersson, disp.\nRolf Fröberg, dir. Stig Fröberg.\n\nVerkst. dir.: Stig Fröberg.\n\nDisp.: Rolf Fröberg.\n\nFrölings Paraplyindustri,\n\nNorrköping.\n\nTillverkar damparaplyer.\n\nKontor: V. S:t Persg. 83. Telefon:\n^1993. Postgiro: 14304. Repr. i Malmö:\nVictor Björkholm, Gyllenpalmsg. 2,\ntelefon: 76775.\n\nArb.-antal: 4. — Firman etabl. 1942.\n\nÄgare o. chef: köpm. Bernt Fröling.\n\n*Frövifors Bruks AB., Frövi.\n\nPappersbruk med sulfatfabrik vid\nFrö-vi (Örebro l.). Tillverkar kraft-,\nsäck-och spinnpapper samt sulfatcellulosa.\n\nTelegr.-adr.: Frövifors, Örebro.\nTelefon: Frövi 1, 65 o. 185. Postgiro: 80393.\n\nAkt.-kap.: 2,500,000 kr. Antal\nindustriarb.: 180. Årstillv.: 12,000 ton papper,\n30,000 ton sulfatcellulosa. — Bolaget,\ngrundat 1902, äges av Örebro\nPappersbruks AB.\n\nStyrelse: dir. Knut Östberg (ordf.),\ndisp. Gunnar Björkman, f. d.\nhovrättsrådet Johan Nordenfalk, disp. Gösta\nReuterswärd, generalkonsul Ragnar\nSöderberg.\n\nVerkst. dir.: Gunnar Björkman.\nV. verkst. dir.: Axel Ignander.\nDriftsing.: Georg W. Lundgren.\n\n*AB. Fundament, Stockholm.\n\nByggnadsentreprenörfirma för\nbostads-och affärshus, industribyggnader samt\nför bro- och vattenbyggnadsarbeten.\n\nKontor: Stureg. 7. Telegr.-adr.:\nFundament, Stockholm. Telefon: 234550.\nPostgiro: 4075.\n\nAkt.-kap.: 250,000 kr. Prod.-värde pr\når: 3,500,000 kr. — Bolaget grundat 1923.\n\nStyrelse: viceamiral Claes O.\nLinds-ström (ordf.), civiling. Anders Åhlén,\ning. Carl Semler, civiling. Georg v.\nZweigbergk.\n\nVerkst. dir.: Georg v. Zweigbergk.\nArbetschef: ing. Gunnar Björklund.\n\n*Fundator, Cjuteri AB., Sundbyberg.\nSe Gjuteri AB. Fundator, Sundbyberg.\n\nFunk, Konfektions AB., Borås.\nSe Konfektions AB. Funk, Borås.\n\n*Funkis, Tegelbruket, Heby.\nSe AB. Heby Tegelverk, Heby.\n\n* Furulunds Yllefabrik, Furulund.\nSe Malmö Yllefabriks AB., Malmö.\n\n*Furuplywood, Industri AB.,\n\nKristinehamn.\n\nSe Industri AB. Furuplywood,\nKristinehamn.\n\nFiirstenberg &amp; Söner, Kalmar.\n\nSe Kommanditbolaget Ellkå,\nFiirstenberg &amp; Söner, Kalmar.\n\nFyleverken AB., Eriksdal.\n\nRenar kvartssand för glastillverkning;\nframställer kornsorterad kvartssand i\nvarje önskad gradering; tillverkar\nlersandblandningar för stålverk och\ngjuterier samt kaolin i stycken och pulver;\nbryter eldfasta leror från fyndigheter\nvid Eriksdal (Malmöh. l.).\n\nh -v-\n\ni",
    "structured": {
        "1": {
            "name": "Fröbergs Fabriker",
            "location": "Borlänge",
            "business": "Svarveri och snickerifabrik",
            "products": "Tillverkar golv- och bordslampor, ljusstakar, tamburhyllor, murarverktyg, verktygsskaft, rullar och signalkorkar till angeldon samt träslöjdsaker såsom skålar, fat, ordförandeklubbor m.m.",
            "contact": {
                "office": "Fröbergs Fabriker, Borlänge",
                "phone": [
                    "10155"
                ],
                "postgiro": "180935"
            },
            "financials": {
                "capital": "350,000 kr",
                "employees": {
                    "industri-sarb": 30
                },
                "annual_production_value": "400,000 kr"
            },
            "foundation_year": 1907,
            "current_name_year": 1944,
            "owners": [
                "fabr. Nils Fröberg"
            ]
        },
        "2": {
            "name": "AB. John Fröberg",
            "location": "Finspång",
            "business": "Accidenstryckeri, stämpelfabrik och pappersförädlingsindustri",
            "products": "Tillverkar trycksaker, stämplar, gummiklichéer för anilin- och boktryck, gummerat papper, förseglingsremsor, fönsterremsor, vaxpapper, och t&gt;rödomslag, fuktapparater samt skylt-montrar (varumärken: »Visir» o. »Dixi»)",
            "contact": {
                "office": "John Fröberg, Finspång",
                "phone": [
                    "John Fröberg"
                ],
                "postgiro": "15432"
            },
            "financials": {
                "capital": "125,000 kr",
                "employees": {},
                "annual_production_value": "1,300,000 kr"
            },
            "foundation_year": 1879,
            "corporation_year": 1926,
            "board": [
                {
                    "name": "bankdir. S. Mårtenson",
                    "role": "ordf."
                },
                {
                    "name": "f. d. riksdagsm. Karl Andersson",
                    "role": ""
                },
                {
                    "name": "disp. Rolf Fröberg",
                    "role": ""
                },
                {
                    "name": "dir. Stig Fröberg",
                    "role": ""
                }
            ],
            "director": "Stig Fröberg",
            "owners": [],
            "managing_director": "Stig Fröberg",
            "sales_manager": "Rolf Fröberg"
        },
        "3": {
            "name": "Frölings Paraplyindustri",
            "location": "Norrköping",
            "business": "Tillverkar damparaplyer",
            "contact": {
                "office": "V. S:t Persg. 83",
                "phone": [
                    "1993"
                ],
                "postgiro": "14304"
            },
            "financials": {},
            "foundation_year": 1942,
            "owners": [
                "köpm. Bernt Fröling"
            ]
        },
        "4": {
            "name": "AB. Frövifors Bruks AB.",
            "location": "Frövi",
            "business": "Pappersbruk med sulfatfabrik",
            "products": "Tillverkar kraft-, säck-och spinnpapper samt sulfatcellulosa",
            "contact": {
                "telegraph": "Frövifors, Örebro",
                "phone": [
                    "Frövi 1",
                    "65",
                    "185"
                ],
                "postgiro": "80393"
            },
            "financials": {
                "capital": "2,500,000 kr",
                "employees": {
                    "industriarb": 180
                },
                "annual_turnover": "12,000 ton papper, 30,000 ton sulfatcellulosa"
            },
            "foundation_year": 1902,
            "current_name_year": "",
            "owners": [
                "Örebro Pappersbruks AB"
            ],
            "board": [
                {
                    "name": "dir. Knut Östberg",
                    "role": "ordf."
                },
                {
                    "name": "disp. Gunnar Björkman",
                    "role": ""
                },
                {
                    "name": "f. d. hovrättsrådet Johan Nordenfalk",
                    "role": ""
                },
                {
                    "name": "disp. Gösta Reuterswärd",
                    "role": ""
                },
                {
                    "name": "generalkonsul Ragnar Söderberg",
                    "role": ""
                }
            ],
            "director": "Gunnar Björkman"
        },
        "5": {
            "name": "AB. Fundament",
            "location": "Stockholm",
            "business": "Byggnadsentreprenörfirma",
            "contact": {
                "office": "Stureg. 7",
                "telegraph": "Fundament, Stockholm",
                "phone": [
                    "234550"
                ],
                "postgiro": "4075"
            },
            "financials": {
                "capital": "250,000 kr",
                "annual_production_value": "3,500,000 kr"
            },
            "foundation_year": 1923,
            "owners": [],
            "board": [
                {
                    "name": "viceamiral Claes O. Lindström",
                    "role": "ordf."
                },
                {
                    "name": "civiling. Anders Åhlén",
                    "role": ""
                },
                {
                    "name": "ing. Carl Semler",
                    "role": ""
                },
                {
                    "name": "civiling. Georg v. Zweigbergk",
                    "role": ""
                }
            ],
            "director": "Georg v. Zweigbergk",
            "sales_manager": "",
            "manager": ""
        }
    }
}