{
    "original": "Paragon—Pellén\n\nden 14 o. 16, telefon: 440035; i Göteborg:\nFirma Nordström &amp; Tinggren, S. Larmg.\n4, telefon: 171140.\n\nAkt.-kap.: 6,250,000 kr. Antal\nindustriarb.: 1,100. Tillverkningskapacitet:\n40,000 ton papper och kartong.\n\nBolaget, som grundades 1895, äger\nLjungaskogs AB. och AB. Mölndal.\n\nStyrelse: överståthållare Torsten\nNo-thin (ordf.), disp. Hans Hulthén,\nbank-dir. Rich. Julin, bankdir. Marcus\nWal-lenberg.\n\nVerkst. dir. o. disp.: Hans Hulthén.\n\nFabrikschef: William Tibell.\n\nKontorschef : Einar Harald.\n\nInköpschef: Arne Grundin.\n\nParagon AB., Stockholm.\n\nTryckeri för tillverkning av\ngenom-skriftsblanketter och genomskriftssystem\nav alla slag såsom paragonnotor,\nföljesedlar, fakturor samt ändlösa blanketter,\nhollerith- och powersblanketter m. m.,\nbiljetter och motböcker.\n\nKontor: Vasag. 14. Telegr.-adr.:\nCentraltryck, Stockholm. Telefon: »Esselte»\no. 112719. Postgiro: 2831.\n\nBolaget är anslutet till AB. Sveriges\nLitografiska Tryckerier.\n\nStyrelse: dir. Knut Östberg (ordf.),\ndisp. Gösta Smith, ryttm. Åke G.\nWick-man.\n\nDisp.: Anders Hedenström.\n\nFörsäljn.-chef : Göte Trobäcker.\n\nAB. Parajett, Landskrona.\n\nBok- och biljettryckeri, bokbinderi och\nkartongfabrik. Tillverkar formulär i\nändlös bana, järnvägs-, omnibus- och\nspårvägsbiljetter, fraktsedlar m. m.\nVarumärke: »Parajett».\n\nTelegr.-adr. o. telefon: Parajett,\nLandskrona. Postgiro: 13886.\n\nAkt.-kap.: 250,000 kr. Antal\nindustriarb.: 130. — Bolaget grundat 1906 under\nnamn AB. Sydsvenska Biljettryckeriet,\nnuv. namn 1946.\n\nStyrelse: boktr. Gustaf A. Lindblom\n(ordf.), disp. S. Bernstone, dir. Sture\nOhlsson, adv. G. Wihlborg.\n\nVerkst. dir..- Sture Ohlsson.\n\n*Paulis Fabriks AB., Stockholm.\n\nKem. teknisk fabrik. Tillverkar tvål,\nparfymer, eau de Cologne,\n»Azymol»-pre-parater, hudkräm, puder m. m.\nSpecialiteter: »Azymol»-preparater, »F. Paulis\näkta Liljemjölkcreme», »Ovicula»-tvål,\n»Lilola»-tvål, »Pe-Pe»-raktvål o.\n-rak-creme, »Bohéme»-parfymartiklar.\n\n4:\n\nHuvudkontor : Huvudstavägen 65;\npostadr.: Stockholm 30. Telegr.-adr.: »1841»,\nStockholm. Telefon: 507040, 534030 o.\n537005. Postgiro: 2425. Avd.-kontor i\nGöteborg, Malmö o. Jönköping.\n\nAkt.-kap.: 600,000 kr. Antal\nindustriarb.: 40. — Firman etabl. 1841, bolag\n1911.\n\nStyrelse o. verkst. dir.: ryttm. Åke\nPauli.\n\n*Pauliströms Bruk, Järnforsen,\n\nPappersbruk med träsliperi samt\nsågverk och snickerifabrik vid Pauliström,\nJärnforsen (Jönköp. l.). Tillverkar\nsulfitpapper, havannapapper, cellstoff samt\ntvättbräden.\n\nTelegr.-adr.: Pauliström, Järnforsen.\nTelefon: Hässlehult 11 o. 41. Postgiro:\n169698. Ensamförsäljare för\nhavannapapper för utlandet: AB. Hedström &lt;&amp;\nCo., Göteborg, St. Badhusg. 7. telefon:\n131493 o. 139204.\n\nAntal industriarb.: 60. Årstillv.: 1,200\nton cellstoff. — Firman grundad 1899.\n\nÄgare: godsäg. Hugo Drangel.\n\nDisp.: David Hedmar.\n\nJon Paulssons Fiskredskapsfabrik,\n\nDelsbo.\n\nTillverkar fiskredskap, spec. fisknät vid\nfabrik i Delsbo (Gävleb. l.).\n\nTelegr.-adr.: Paulsson, Delsbo. Telefon:\n37. Postgiro: 30121. — Antal\nindustriarb. (exkl. hemarbetare): 25. — Firman\netabl. 1895.\n\nÄgare: fru S. Paulsson.\n\nFabrikschef: Arvid Paulsson.\n\n*Sigfr. N. &amp; 0. Paulson AB., Lund.\n\nMöbel- och snickerifabrik. Tillverkar\nmöbler och inredningar.\n\nTelefon: 10071. — Akt.-kap.: 23,000\nkr. Arb.-antal: 10. Tillv.-värde pr år:\n100,000 kr. — Firman etabl. 1893, bolag\n1939.\n\nStyrelse: fabr. Sigfr. N. Paulson\n(ordf.), möbelarkitekt Olgard Andersson.\n\nVerkst. dir.: Sigfr. N. Paulson.\n\nPehrson, se Person.\n*Pellén &amp; Co. AB., Stockholm.\n\nKappfabrik. Tillverkar damkappor och\ndräkter.\n\nKontor: Hornsg. 54. Telefon: 432877\no. 432875. Postgiro: 4855. — Akt.-kap.:\n40,000 kr. Antal industriarb.: 45. —\nBolaget grundat 1928.\n\nStyrelse o. verkst. dir.: H. Andersson.\n\n4*",
    "structured": {
        "1": {
            "name": "Paragon—Pellén",
            "location": "Stockholm",
            "business": "Kappfabrik",
            "products": "Tillverkar damkappor och dräkter.",
            "contact": {
                "office": "Hornsg. 54",
                "phone": [
                    "432877",
                    "432875"
                ],
                "postgiro": "4855"
            },
            "financials": {
                "capital": "40,000 kr",
                "employees": {
                    "industriarb": 45
                }
            },
            "foundation_year": 1928,
            "board": [
                {
                    "name": "H. Andersson",
                    "role": "Verkst. dir."
                }
            ]
        },
        "2": {
            "name": "Paragon AB.",
            "location": "Stockholm",
            "business": "Tryckeri för tillverkning av genomskriftsblanketter och genomskriftssystem.",
            "products": "Genomskriftsblanketter, genomskriftssystem, paragonnotor, följesedlar, fakturor, ändlösa blanketter, hollerith- och powersblanketter, biljetter, motböcker.",
            "contact": {
                "office": "Vasag. 14",
                "telegraph": "Centraltryck, Stockholm",
                "phone": [
                    "'Esselte' o.",
                    "112719"
                ],
                "postgiro": "2831"
            },
            "foundation_year": 1895,
            "board": [
                {
                    "name": "Knut Östberg",
                    "role": "Styrelse"
                },
                {
                    "name": "Gösta Smith",
                    "role": "Disp."
                },
                {
                    "name": "Åke G. Wickman",
                    "role": "ryttm."
                },
                {
                    "name": "Anders Hedenström",
                    "role": "Disp."
                }
            ]
        },
        "3": {
            "name": "AB. Parajett",
            "location": "Landskrona",
            "business": "Bok- och biljettryckeri, bokbinderi och kartongfabrik.",
            "products": "Formulär i ändlös bana, järnvägs-, omnibus- och spårvägsbiljetter, fraktsedlar m.m.",
            "contact": {
                "office": "Parajett, Landskrona",
                "phone": "Parajett",
                "postgiro": "13886"
            },
            "financials": {
                "capital": "250,000 kr",
                "employees": {
                    "industriarb": 130
                }
            },
            "foundation_year": 1906,
            "board": [
                {
                    "name": "Gustaf A. Lindblom",
                    "role": "boktr."
                },
                {
                    "name": "S. Bernstone",
                    "role": "Disp."
                },
                {
                    "name": "Sture Ohlsson",
                    "role": "dir."
                },
                {
                    "name": "G. Wihlborg",
                    "role": "adv."
                }
            ]
        },
        "4": {
            "name": "Paulis Fabriks AB.",
            "location": "Stockholm",
            "business": "Kem. teknisk fabrik",
            "products": "Tvål, parfymer, eau de Cologne, 'Azymol'-preparater, hudkräm, puder m.m.",
            "contact": {
                "office": "Huvudstavägen 65",
                "telegraph": "'1841', Stockholm",
                "phone": [
                    "507040",
                    "534030",
                    "537005"
                ],
                "postgiro": "2425"
            },
            "financials": {
                "capital": "600,000 kr",
                "employees": {
                    "industriarb": 40
                }
            },
            "foundation_year": 1841,
            "board": [
                {
                    "name": "Åke Pauli",
                    "role": "ryttm."
                }
            ]
        },
        "5": {
            "name": "Pauliströms Bruk",
            "location": "Järnforsen",
            "business": "Pappersbruk med träsliperi samt sågverk och snickerifabrik.",
            "products": "Sulfitpapper, havannapapper, cellstoff, tvättbräden.",
            "contact": {
                "office": "Pauliström, Järnforsen",
                "phone": [
                    "Hässlehult 11",
                    "Hässlehult 41"
                ],
                "postgiro": "169698"
            },
            "financials": {
                "employees": {
                    "industriarb": 60
                }
            },
            "foundation_year": 1899,
            "owners": [
                "Hugo Drangel"
            ],
            "board": [
                {
                    "name": "David Hedmar",
                    "role": "Disp."
                }
            ]
        },
        "6": {
            "name": "Jon Paulssons Fiskredskapsfabrik",
            "location": "Delsbo",
            "business": "Tillverkar fiskredskap, spec. fisknät.",
            "contact": {
                "office": "Paulsson, Delsbo",
                "phone": "37",
                "postgiro": "30121"
            },
            "employees": {
                "industriarb": 25
            },
            "foundation_year": 1895,
            "owners": [
                "fru S. Paulsson"
            ],
            "board": [
                {
                    "name": "Arvid Paulsson",
                    "role": "Fabrikschef"
                }
            ]
        },
        "7": {
            "name": "Sigfr. N. & O. Paulson AB.",
            "location": "Lund",
            "business": "Möbel- och snickerifabrik",
            "products": "Möbler och inredningar.",
            "contact": {
                "phone": "10071"
            },
            "financials": {
                "capital": "23,000 kr",
                "employees": {
                    "arb.-antal": 10
                },
                "annual_turnover": "100,000 kr"
            },
            "foundation_year": 1893,
            "board": [
                {
                    "name": "Sigfr. N. Paulson",
                    "role": "Styrelse"
                },
                {
                    "name": "Olgard Andersson",
                    "role": "möbelarkitekt"
                }
            ]
        }
    }
}