{
    "original": "Grill—Gruf\n\nhållskärl m. m. samt plåtkaminer och\nkannor för A. I. V.-lösning. Bolaget\ndriver även försäljning av lågtryckspannor\noch vatten värmare, träslöjd m. m.-\n\nTelefon: 163. Postgiro: 71813. —\nAkt.-kap.: 30,000 kr. Antal industriarb.: 17.\nTillv.-värde pr år: 200,000 kr. — Firman\netabl. 1925.\n\nStyrelse: fabr. David Andersson, fabr.\nErnst Andersson, fabr. Karl Rosenqvist.\nVerkst. dir.: Karl Rosenqvist.\n\n*B. &amp; R. Grill, Kungsbacka.\n\nSnickerifabrik och trävaruaffär.\nTillverkar byggnadssnickerier.\n\nTelefon: 41 o. 415. Postgiro: 75961.\n— Arb.-antal: 15. — Firman etabl. 1899.\nÄgare o. chef: fabr. R. E. Grill.\n\nGrimsås Syfabrik, Erik Hägg,\n\nGrimsås.\n\nTillverkar skjortor och klänningar vid\nfabrik i Grimsås (Älvsb. l.).\n\nTelefon: Svenljunga 7424 o. 7436.\nPostgiro: 169774. — Antal industriarb.:\n40. Tillv.-värde pr år: 700,000 kr. —\nFirman etabl. 1931.\n\nÄgare o. chef: disp. Erik Hägg.\n\n’Gripen, Konfektions AB., Alingsås.\nSe Konfektions AB. Gripen, Alingsås.\n\nGripen, AB. Tekniska Fabriken,\n\nLinköping.\n\nSe AB. Tekniska Fabriken Gripen,\nLinköping.\n\nAB. Gripens Konservfabrik,\n\nGöteborg.\n\nFabrik för tillverkning av ansjovis,\nsillkonserver, kaviar, herring och\nsardiner samt fiskbullar och fiskpudding m. m.\nBolaget driver även engroshandel med salt\nsill och fisk. Varumärken: »Gripmärket»,\n»Bellmansbitar», »Fyra Ess» o.\n»Sexmäs-taresill» m. fl.\n\nKontor: Ringö vägen. Telegr,-adr.:\nGripens Konservfabrik, Göteborg.\nTelefon: 220438 o. 220439. Postgiro: 41855.\n\nAkt.-kap.: 25,500 kr. Antal\nindustriarb.: 40. Tillv.-värde pr år: 800,000 kr.\n— Bolaget grundat 1925.\n\nStyrelse o. verkst. dir.: Reinh.\nTiljänder.\n\n’AB. Crohmann &amp; Eichelberg,\n\nStockholm.\n\nUtför klichéer och fotografiska\nreproduktioner.\n\nKontor: Mästersamuelsg. 67. Telefon:\n231195. Postgiro: 2613.\n\nAkt.-kap.: 30,000 kr. Antal\nindustriarb.: 50. Tillv.-värde pr år: 550,000 kr.\n\n—\tFirman etabl. 1896, bolagr 1901.\n\nStyrelse: dir. Per Q. S. Fjästad.\n\nDisp.: Erik Cederquist.\n\n’Gropptorps Marmor AB.,\n\nKatrineholm.\n\nMarmorbrott, stenhuggeri och\nstensli-peri vid Gropptorp (Södermanl. L).\n\nBryter och förädlar speciellt svensk\nmarmor (Gropptorps- och\nEkebergsmar-mor) samt kalksten. Framställer råvara i\nblock och skivor, utför byggnadsarbeten\nav marmor (även av utländsk sten) såsom\nbalustrader, diskskivor, friser,\nfönsterbänkar, golvplattor, kakelugnsplaner,\nkolonner och socklar, lister, spis-,\ntrapp-och väggbeklädnader m. m., fasad- och\nandra utvändiga arbeten; tillverkar elektr.\ninstrumenttavlor, gravvårdar och\nmonument, mortlar, konst- och\nprydnadsföremål, möbelmarmor m. m. Varumärke:\n»G. M.».\n\nTelegr.-adr.: Gropptorp, Katrineholm.\nTelefon: Gropptorp 10 o. 35. Postgiro:\n36346. Filialkontor: Stockholm, Kungsg.\n44, telefon: 115724.\n\nAkt.-kap.: 100 000 ky. Antal\nindustriarb.: 120. Tillv.-värdé pr år: 1,060,ÖÖÖ kr.\n\n—\tFirman etabl. 1908, bolag 1918.\n\nStyrelse: f. d. konsul Jerker Henke\n\n(ordf.), dir. Folke Anger, dir. Bertil\nHenke.\n\nVerkst. dir.: F. Anger,\n\nKamrer: H. Fritzell.\n\nDriftsing.: S. Lundeli.\n\nInköpschef: H. Nohr.\n\nFilialchef i Stockholm: civiling. Nils\nLindberg.; ;\n\n(Jfr annons nr 14.)\n\n\"Sixten Groths Eftr., Sjötorp.\n\nVarv med torrdocka och sågverk vid\nSjötorp (Skarab. l.). Utför nybyggnader\noch reparationer av trä- och järnfartyg\nmed upp till 32 m. längd och 7 m. bredd\nsamt tillverkar sågade och hyvlade\nträvaror.\n\nTelegr.-adr.: Sjötorpsvarvet,\nMarie-stad. Telefon: Sjötorp 77.\nPostgiro:-33738. — Antal industriarb.: 90. —\nFirman etabl. 1877.\n\nÄgare o. chef: disp. Åke Groth.\n\nGruf, se Gruv.",
    "structured": {
        "1": {
            "name": "Grill—Gruf",
            "location": "Kungsbacka",
            "business": "Tillverkning av hållskärl, plåtkaminer, kannor för A.I.V.-lösning samt försäljning av lågtryckspannor och vatten värmare, träslöjd m.m.",
            "contact": {
                "phone": [
                    "163"
                ],
                "postgiro": "71813"
            },
            "financials": {
                "capital": "30,000 kr",
                "employees": {
                    "industriarb": 17
                },
                "annual_production_value": "200,000 kr"
            },
            "foundation_year": 1925,
            "board": [
                {
                    "name": "fabr. David Andersson",
                    "role": "fabrikör"
                },
                {
                    "name": "fabr. Ernst Andersson",
                    "role": "fabrikör"
                },
                {
                    "name": "fabr. Karl Rosenqvist",
                    "role": "fabrikör"
                }
            ],
            "director": "Karl Rosenqvist"
        },
        "2": {
            "name": "B. & R. Grill",
            "location": "Kungsbacka",
            "business": "Snickerifabrik och trävaruaffär som tillverkar byggnadssnickerier",
            "contact": {
                "phone": [
                    "41",
                    "415"
                ],
                "postgiro": "75961"
            },
            "financials": {
                "employees": {
                    "antal": 15
                }
            },
            "foundation_year": 1899,
            "owners": [
                "fabr. R. E. Grill"
            ]
        },
        "3": {
            "name": "Grimsås Syfabrik",
            "location": "Grimsås",
            "business": "Tillverkning av skjortor och klänningar",
            "contact": {
                "phone": [
                    "Svenljunga 7424",
                    "7436"
                ],
                "postgiro": "169774"
            },
            "financials": {
                "employees": {
                    "industriarb": 40
                },
                "annual_production_value": "700,000 kr"
            },
            "foundation_year": 1931,
            "owners": [
                "disp. Erik Hägg"
            ]
        },
        "4": {
            "name": "AB. Gripens Konservfabrik",
            "location": "Göteborg",
            "business": "Fabrik för tillverkning av ansjovis, sillkonserver, kaviar, herring, sardiner, fiskbullar, fiskpudding och engroshandel med salt sill och fisk",
            "contact": {
                "office": "Ringö vägen",
                "phone": "220438, 220439",
                "postgiro": "41855"
            },
            "financials": {
                "capital": "25,500 kr",
                "employees": {
                    "industriarb": 40
                },
                "annual_production_value": "800,000 kr"
            },
            "foundation_year": 1925,
            "director": "Reinh. Tiljänder"
        },
        "5": {
            "name": "AB. Crohmann & Eichelberg",
            "location": "Stockholm",
            "business": "Utför klichéer och fotografiska reproduktioner",
            "contact": {
                "office": "Mästersamuelsg. 67",
                "phone": "231195",
                "postgiro": "2613"
            },
            "financials": {
                "capital": "30,000 kr",
                "employees": {
                    "industriarb": 50
                },
                "annual_production_value": "550,000 kr"
            },
            "foundation_year": 1896,
            "corporation_year": 1901,
            "board": [
                {
                    "name": "dir. Per Q. S. Fjästad",
                    "role": "styrelseledamot"
                },
                {
                    "name": "Erik Cederquist",
                    "role": "dispens"
                }
            ]
        },
        "6": {
            "name": "Gropptorps Marmor AB.",
            "location": "Katrineholm",
            "business": "Marmorbrott, stenhuggeri och stenslipning, framställer råvara i block och skivor, elektriska instrumenttavlor, gravvårdar och monument, mortlar, konst- och prydnadsföremål, möbelmarmor m.m.",
            "contact": {
                "phone": [
                    "Gropptorp 10, 35"
                ],
                "postgiro": "36346"
            },
            "financials": {
                "capital": "100,000 kr",
                "employees": {
                    "industriarb": 120
                },
                "annual_production_value": "1,060,000 kr"
            },
            "foundation_year": 1908,
            "corporation_year": 1918,
            "board": [
                {
                    "name": "f.d. konsul Jerker Henke",
                    "role": "ordförande"
                },
                {
                    "name": "dir. Folke Anger",
                    "role": "styrelseledamot"
                },
                {
                    "name": "dir. Bertil Henke",
                    "role": "styrelseledamot"
                },
                {
                    "name": "F. Anger",
                    "role": "verkställande direktör"
                }
            ],
            "director": "F. Anger",
            "manager": "H. Fritzell",
            "sales_manager": "civiling. Nils Lindberg"
        },
        "7": {
            "name": "Sixten Groths Eftr.",
            "location": "Sjötorp",
            "business": "Varv med torrdocka och sågverk, nybyggnader och reparationer av trä- och järnfartyg, tillverkning av trävaror",
            "contact": {
                "phone": "Sjötorp 77",
                "postgiro": "33738"
            },
            "financials": {
                "employees": {
                    "industriarb": 90
                }
            },
            "foundation_year": 1877,
            "owners": [
                "disp. Åke Groth"
            ]
        }
    }
}