{
    "original": "Barmängen—Be eker\n\nAkt.-kap.: 50,000 kr. Antal\nindustriarb.: 60. Tillv.-värde pr år: 1,200,000 kr.\n— Bolaget, grundat 1938, är dotterbolag\ntill AB. Malmö Strumpfabrik.\nVerkst. dir.: Åke Wiberg.\n\n* Barnängens Tekniska Fabrikers AB.,\n\nStockholm.\n\nTillverkar munvatten och tandkräm\n(»Vademecum»), raktvål och rakkräm\n(»Parba»), hårvatten (»Capillo»),\nparfymer, eau de Cologne, farmaceu ti\nsk-kosmetiska preparat, bläck, radervatten,\ngummi, toalett- och tvättvål, såpa och\nputsmedel.\n\nKontor: Alvik, Stockholm; postadr.:\nStockholm 12. Télegr.-adr. och telefon:\n»Kemabolagen», Stockholm.\n\nAkt.-kap.: 2,000,000 kr. — Fabriken\nanlagd 1868. Bolaget ingår i\n»Kema-Bo-lagen», Stockholm.\n\nStyrelse: grossh. Robert Ljunglöf\n(ordf.), disp. Sverre Bröholdt, fil. dr\nHarald Nordenson, disp. Nils\nWester-dahl.\n\nVerkst. dir.: Tor Olsson.\n\nBarrsätra Järnmanufakturverk,\n\nHovslätt.\n\nTillverkar trädgårdsredskap,\ngräsklipp-ningsmaskiner, koks- och askskyfflar,\nbetningsmaskiner, rattkälkar, snöskyfflar\noch snörakor, leksaker m. m. vid mek.\nverkstad i Ilovslätt (Jönköp. l.).\n\nTelefon: 61. Postgiro: 29127. — Antal\nindustriarb.: 21. Tillv.-värde pr år:\n310,000 kr. — Firman grundad 1908.\n\nÄgare o. chef: ing. Hilding Lindskog.\n\n*Cust. Barthels AB., Göteborg.\n\nSnörmakerifabrik. Tillverkar\nsnörma-kerier för möbler, dekoration, armatur,\ntapisseri, hatt-, möss- och\npälsvarufabrika-tion, konfektion, vagn- och\nkartongfabrikation, ävensom ridåer samt drag-,\nper-sienne- och markissnören, flagglinor,\ntät-ningslister, flätade bomullspackningar\nm. m.\n\nKontor: Rosenlundsg. 4. Telefon:\n110884. Postgiro: 40119, Repr. i\nStockholm: Kapten R. Granström, Klara Norra\nKyrkog. 29. Telefon: 103960.\n\nAkt.-kap.: 50.000 kr. Antal\nindustriarb.: 20. Tillv.-värde pr år: 200,000 kr.\n— Firman grundad 1894, bolag 1934.\n\nStyrelse o. verkst. dir.: E. Moldén.\n\nKontorschef: löjtn. Alf Moldén.\n\n* * Bast kär ns Cruf AB., Stockholm.\n\nJärnmalmsgruvor vid Bastkärn,\nSilverhöjden (Örebro l.). Bryter manganhaltig\nsvartmalm.\n\nDisponentkontor: Stockholm,\nVirvel-vindsv. 52. Telefon: 254097. Gruvkontor:\nBastkärn. Telefon: Hörken 50 o. 51.\n\nAkt.-kap.: 400,000 kr. Antal\nindustriarb.: 52. Prod.-värde pr år: 800,000 kr.\n— Firman etabl. 1899.\n\nStyrelse: disp. Axel Alarik (ordf.),\ndisp. F. A. Cassel, dir. Erik G.\nPehrs-son.\n\nDisp.: Axel Alarik.\n\nPlatschef: bergsing. Rolf Erikson\n(Silverhöjden).\n\nBates Paper Sack AB., Örebro.\n\nPappersförädlingsfabrik. Tillverkar\nsydda och klistrade säckar av kraftpapper,\nspeciellt självslutande ventil\npapperssäckar. Varumärke: »Bates Ventil säckar».\nBolaget driver även försäljning av\nautomatiska fyllningsmaskiner för\npapperssäckar.\n\nTelegr.-adr.: Valvsax, Örebro. Telefon:\n14130. Postgiro: 30350. — Akt.-kap.:\n450,000 kr. Antal industriarb.: 80.\nTillv.-värde pr år: 4,000,000 kr. — Bolaget,\ngrundat 1925, är anslutet till AB.\nSveriges Litografiska Tryckerier, Stockholm.\n\nStyrelse: disp. Gunnar Björkman, ing.\nKlas Johnsson.\n\nVerkst. dir.: Klas Johnsson.\n\n*J. O. Baumgardts Pianofabrik,\n\nLinköping.\n\nTillverkar pianinon och flyglar.\n\nTelegr.-adr.: Baumgardt. Linköping.\nTelefon: 20124. Postgiro: 29429.\nRepresentanter: i Stockholm: Lengströms\nPia-nomag., Drottningg. 79; telefon: 109630;\ni Göteborg: AB. Waidele, Arkaden,\ntelefon: 170030.\n\nAntal industriarb.: 20. Tillv.-värde pr\når: 240,000 kr. — Firman etabl. 1857.\n\nChef: fabr. J. E. Baumgardt.\n\n*AB. Wilh. Becker, Stockholm.\n\nFärg- och fernissfabrik samt kem.-tekn.\nfabrik vid Lövholmen, Stockholm.\n\nTillverkar färger, fernissor,\nkonstnärsmaterial, förbandsartiklar, kosmetiska\noch farmaceutiska preparat,\ntextilhjälpmedel, växtskyddspreparat och andra\nkemisk-tekniska preparat.\n\nVarumärken: Beckers, Bianca, D. 10,\nD. 100, Ferro-Texit, Griffolit, Jofurs\nskuggfärg, Kisoflor, Kromoplast, Luxin^",
    "structured": {
        "1": {
            "name": "Barnängens Tekniska Fabrikers AB.",
            "location": "Stockholm",
            "business": "Manufacturing",
            "products": "Mouthwash, toothpaste, shaving soap, hair tonic, perfumes, eau de Cologne, pharmaceutical and cosmetic products, ink, rubber, toilet and laundry soap, cleaning products",
            "contact": {
                "office": "Alvik, Stockholm",
                "telegraph": "Kemabolagen, Stockholm",
                "phone": [
                    "Stockholm 12"
                ]
            },
            "financials": {
                "capital": "2,000,000 kr",
                "employees": {
                    "industriarb": 21
                },
                "annual_turnover": "310,000 kr"
            },
            "foundation_year": 1868,
            "board": [
                {
                    "name": "grossh. Robert Ljunglöf",
                    "role": "Chairman"
                },
                {
                    "name": "disp. Sverre Bröholdt",
                    "role": "Director"
                },
                {
                    "name": "fil. dr Harald Nordenson",
                    "role": "Director"
                },
                {
                    "name": "disp. Nils Westerdahl",
                    "role": "Director"
                }
            ],
            "director": "Åke Wiberg"
        },
        "2": {
            "name": "Barrsätra Järnmanufakturverk",
            "location": "Hovslätt",
            "business": "Manufacturing",
            "products": "Garden tools, lawn mowers, shovels, betning machines, steering sleds, snow shovels, and more",
            "contact": {
                "office": "Hovslätt (Jönköp. l.)",
                "phone": [
                    "61"
                ],
                "postgiro": "29127"
            },
            "financials": {
                "employees": {
                    "industriarb": 21
                },
                "annual_turnover": "310,000 kr"
            },
            "foundation_year": 1908,
            "manager": "ing. Hilding Lindskog"
        },
        "3": {
            "name": "Cust. Barthels AB.",
            "location": "Göteborg",
            "business": "Manufacturing",
            "products": "Shoelace for furniture, decoration, lighting, upholstery, hat, fur products manufacturing, clothing, carton production, as well as curtains and more",
            "contact": {
                "office": "Rosenlundsg. 4",
                "phone": [
                    "110884"
                ],
                "postgiro": "40119"
            },
            "financials": {
                "capital": "50,000 kr",
                "employees": {
                    "industriarb": 20
                },
                "annual_turnover": "200,000 kr"
            },
            "foundation_year": 1894,
            "board": [
                {
                    "name": "E. Moldén",
                    "role": "Director"
                }
            ],
            "director": "E. Moldén",
            "manager": "löjtn. Alf Moldén"
        },
        "4": {
            "name": "Bastkärns Cruf AB.",
            "location": "Stockholm",
            "business": "Mining",
            "products": "Manganese-rich black ore",
            "contact": {
                "office": "Stockholm, Virvelvindsv. 52",
                "phone": [
                    "254097"
                ],
                "gruvkontor": "Bastkärn, Hörken 50 o. 51"
            },
            "financials": {
                "capital": "400,000 kr",
                "employees": {
                    "industriarb": 52
                },
                "annual_turnover": "800,000 kr"
            },
            "foundation_year": 1899,
            "board": [
                {
                    "name": "disp. Axel Alarik",
                    "role": "Chairman"
                },
                {
                    "name": "disp. F. A. Cassel",
                    "role": "Director"
                },
                {
                    "name": "dir. Erik G. Pehrsson",
                    "role": "Director"
                }
            ],
            "director": "Axel Alarik",
            "sales_manager": "bergsing. Rolf Erikson"
        },
        "5": {
            "name": "Bates Paper Sack AB.",
            "location": "Örebro",
            "business": "Paper Manufacturing",
            "products": "Sewn and glued bags made of kraft paper, self-closing valve paper bags",
            "contact": {
                "telegraph": "Valvsax, Örebro",
                "phone": [
                    "14130"
                ],
                "postgiro": "30350"
            },
            "financials": {
                "capital": "450,000 kr",
                "employees": {
                    "industriarb": 80
                },
                "annual_turnover": "4,000,000 kr"
            },
            "foundation_year": 1925,
            "director": "Klas Johnsson"
        },
        "6": {
            "name": "J. O. Baumgardts Pianofabrik",
            "location": "Linköping",
            "business": "Manufacturing",
            "products": "Pianos and grand pianos",
            "contact": {
                "telegraph": "Baumgardt, Linköping",
                "phone": [
                    "20124"
                ],
                "postgiro": "29429"
            },
            "financials": {
                "employees": {
                    "industriarb": 20
                },
                "annual_turnover": "240,000 kr"
            },
            "foundation_year": 1857,
            "director": "J. E. Baumgardt"
        },
        "7": {
            "name": "AB. Wilh. Becker",
            "location": "Stockholm",
            "business": "Chemical and Technical",
            "products": "Paints, varnishes, artist supplies, bandages, cosmetic and pharmaceutical products, textile aids, plant protection products, and other chemical-technical products",
            "contact": {
                "telegraph": "Lövholmen, Stockholm"
            }
        }
    }
}