{
    "original": "Malvia—Manus\n\ngarn för väverier och trikåfabriker,\nylle-och silkesstrumpor samt bomullsgarn och\nbomullsvävnader.\n\nHuvudkontor: Malmö,\nTrelleborgsvä-gen 13. Telegr.-adr.: Yllefabriken,\nMalmö. Telefon: 70730, »MAB o. MYA».\nPostgiro: 37531.\n\nAkt.-kap.: 4,197,600 kr. Antal\nindustriarb.: 1,800. Tillv.-värde pr år: 30,000,000\nkr. — Bolaget grundat 1866. Manufaktur\nAB. i Malmö är huvudintressent i\nbolaget.\n\nStyrelse: dir. Nils W. Lundblad (ordf.),\nkonstnär Einar Bager, konsul Thorsten\nC. Bergh, bankdir. Ivar Åkerman.\n\nVerkst. dir.: Thorstön C. Bergh.\n\nOrganisationschef: dir. Tore Ericsson.\n\nFörsäljn.-chef: dir. Adalbert Schmitz.\n\nEkonomichef: Folke Thulin.\n\nTekn. chef: övering. John Reinholds.\n\nMalvia, AB. Fabriken, Malmö.\n\nSe AB. Fabriken Malvia, Malmö.\n\n*Mannerståls Snickerifabrik,\n\nVårgårda.\n\nTillverkar byggnadssnickerier såsom\nfönster, dörrar och trappor, inredningar\nför butiker och andra affärslokaler, kök,\nbostäder, sjukhus och samlingslokaler vid\nfabrik i Vårgårda (Älvsb. l.).\n\nTelefon: 300. Postgiro: 282460. —\nAntal industriarb.: 20. Tillv.-värde pr år:\n225,000 kr. — Firman etabl. 1945.\n\nÄgare o. chef: ing. Magni Mannerstål.\n\n\"Manufaktur AB. i Malmö, Malmö.\n\nBomullsspinneri och -väveri,\ntrikåfabrik, vaddfabrik, färgeri, blekeri och\nappreturverk.\n\nTillverkar bomullsgarn, oblekta, blekta,\nfärgade och mönstervävda\nbomullsvävnader, halvylletyger, flaneller, bolster,\ntrikå-varor såsom underkläder, barnkläder\nm. m. och täckvadd.\n\nTelegr.-adr.: Mabim, Malmö. Postadr.:\nMalmö 1. Telefon: »MAB o. MYA».\nPostgiro: 39345.\n\nAkt.-kap.: 4,200,000 kr. Antal\nindustriarb.: 750. Tillv.-värde pr år: 10,000,000\nkr.\n\nBolaget, grundat 1855, har 1940\növertagit den bomullsväverirörelse, som\nbedrivits av firman L. P. Kruse &amp; Son, Malmö,\ngrundad 1825, samt äger aktiemajoriteten\ni Malmö Yllefabriks AB.\n\nStyrelse: dir. Nils W. Lundblad (ordf.),\nkonstnär Einar Bager, disp. Carl Bergh,\nkonsul Thorsten O. Bergh, bankdir. Ivar\nÅkerman.\n\nVerkst. dir.: Thorsten C. Bergh.\nOrganisationschef: dir. Tore Ericsson.\nFörsäljn.-chef: Eric Myrhagen.\nEkonomichef: Folke Thulin.\nTekn. chef: övering. John Reinholds.\n\n\"Manufaktur AB. Svea, Borås.\nSe Kilsunds AB., Borås.\n\n\"AB. Manufaktur &amp; Konfektion,\n\nBorås.\n\nDamkonfektionsfabrik. Tillverkar\nklänningar, blusar och kjolar. Varumärke:\n»MK».\n\nTelefon: 11820 o. 11890. Postgiro:\n84262. — Akt.-kap.: 60,000 kr. Antal\nindustriarb.: 35. Tillv.-värde pr år: 700,000\nkr. — Firman etabl. 1931, bolag 1940.\nStyrelse o. verkst. dir.: Arvid Liljeros.\n\nAB. Manufaktursmiden,\n\nHalmstad.\n\nKättingfabrik. Tillverkar kortlänkad\noch långlänkad kätting.\n\nTelegr.-adr.: Manufaktursmide,\nHalmstad. Telefon: »Malcus». Postgiro: 72224.\n\n—\tAkt.-kap.: 62,500 kr. Arb.-antal: 6.\nTillv.-värde pr år: 75,000 kr. — Bolaget\ngrundat 1919.\n\nStyrelse: dir. Edw. Berger (ordf.), v.\nkonsul Oscar Hill, disp. Johan Wendt.\nVerkst. dir.: civiling. Bertil Junger.\n\nManufaktur &amp; Syfabriks AB.,\n\nÖrbyhus.\n\nSe AB. örby hus Syfabrik, örby hus.\n\n\"Manufakturverket Göta Bruk AB.,\n\nMalmö.\n\nMek. verkstad i Anderslöv (Malmöh. l.).\nTillverkar # reservdelar till plogar och\nskördemaskiner samt yxor och skruvbrodd.\nVarumärke: »Göta».\n\nKontor o. ensamförsälj.: Edw. H.\nTho-mée AB., Malmö, Engelbrektsg. 11 A.\nTe-legr.-adr.: Edwin, Malmö. Telefon:\n»Tho-méesjärn». Postgiro: 14063.\n\nAkt.-kap.: 46,000 kr. Antal\nindustriarb.: 35. Tillv.-värde pr år: 1,000,000 kr.\n\n—\tFirman etabl. 1915.\n\nStyrelse: konsul Edw. H. Thomée.\nVerkst. dir.: Allan Bäckman.\nPlatschef: Gunnar Martinsson.\n\n\"AB. Manus, Norrköping.\n\nMek. verkstad. Tillverkar\nmjölkningsmaskiner, vacuumpumpar och mjölkkylare",
    "structured": {
        "1": {
            "name": "Malvia—Manus",
            "location": "Malmö",
            "business": "garn för väverier och trikåfabriker, ylle-och silkesstrumpor samt bomullsgarn och bomullsvävnader",
            "contact": {
                "office": "Trelleborgsvä-gen 13",
                "phone": [
                    "70730"
                ],
                "postgiro": "37531",
                "head_office": "Malmö",
                "telegraph": "Yllefabriken",
                "factory_office": "Malmö",
                "factory_phone": "Se AB. Fabriken Malvia, Malmö"
            },
            "financials": {
                "capital": "4,197,600 kr",
                "employees": {
                    "industriarb": 1800
                },
                "annual_turnover": "30,000,000 kr",
                "annual_production_value": "30,000,000 kr"
            },
            "foundation_year": 1866,
            "board": [
                {
                    "name": "Nils W. Lundblad",
                    "role": "ordf."
                },
                {
                    "name": "Einar Bager",
                    "role": "konstnär"
                },
                {
                    "name": "Thorsten C. Bergh",
                    "role": "konsul"
                },
                {
                    "name": "Ivar Åkerman",
                    "role": "bankdir."
                }
            ],
            "owners": [
                "Manufaktur AB. i Malmö"
            ],
            "director": "Nils W. Lundblad",
            "managing_director": "Thorstön C. Bergh",
            "sales_manager": "Adalbert Schmitz",
            "manager": "Tore Ericsson"
        },
        "2": {
            "name": "Mannerståls Snickerifabrik",
            "location": "Vårgårda",
            "business": "Tillverkar byggnadssnickerier såsom fönster, dörrar och trappor",
            "contact": {
                "phone": [
                    "300"
                ],
                "postgiro": "282460"
            },
            "financials": {
                "employees": {
                    "industriarb": 20
                },
                "annual_production_value": "225,000 kr"
            },
            "foundation_year": 1945,
            "owner": "ing. Magni Mannerstål"
        },
        "3": {
            "name": "Manufaktur AB. i Malmö",
            "location": "Malmö",
            "business": "Bomullsspinneri och -väveri, trikåfabrik, vaddfabrik, färgeri, blekeri och appreturverk",
            "contact": {
                "telegraph": "Mabim",
                "office": "Malmö",
                "phone": [
                    "MAB",
                    "MYA"
                ],
                "postgiro": "39345"
            },
            "financials": {
                "capital": "4,200,000 kr",
                "employees": {
                    "industriarb": 750
                },
                "annual_production_value": "10,000,000 kr"
            },
            "foundation_year": 1855,
            "board": [
                {
                    "name": "Nils W. Lundblad",
                    "role": "ordf."
                },
                {
                    "name": "Einar Bager",
                    "role": "konstnär"
                },
                {
                    "name": "Carl Bergh",
                    "role": "disp."
                },
                {
                    "name": "Thorsten O. Bergh",
                    "role": "konsul"
                },
                {
                    "name": "Ivar Åkerman",
                    "role": "bankdir."
                }
            ],
            "director": "Thorsten C. Bergh",
            "sales_manager": "Eric Myrhagen",
            "manager": "Folke Thulin"
        },
        "4": {
            "name": "Manufaktur AB. Svea",
            "location": "Borås",
            "business": "Se Kilsunds AB., Borås"
        },
        "5": {
            "name": "AB. Manufaktur & Konfektion",
            "location": "Borås",
            "business": "Damkonfektionsfabrik. Tillverkar klänningar, blusar och kjolar. Varumärke: »MK»",
            "contact": {
                "phone": [
                    "11820",
                    "11890"
                ],
                "postgiro": "84262"
            },
            "financials": {
                "capital": "60,000 kr",
                "employees": {
                    "industriarb": 35
                },
                "annual_production_value": "700,000 kr"
            },
            "foundation_year": 1931,
            "board": [
                {
                    "name": "Arvid Liljeros",
                    "role": "verkst. dir.:"
                }
            ]
        },
        "6": {
            "name": "AB. Manufaktursmiden",
            "location": "Halmstad",
            "business": "Kättingfabrik. Tillverkar kortlänkad och långlänkad kätting",
            "contact": {
                "telegraph": "Manufaktursmide",
                "phone": [
                    "Malcus"
                ],
                "postgiro": "72224"
            },
            "financials": {
                "capital": "62,500 kr",
                "employees": {
                    "industriarb": 6
                },
                "annual_production_value": "75,000 kr"
            },
            "foundation_year": 1919,
            "board": [
                {
                    "name": "Edw. Berger",
                    "role": "ordf."
                },
                {
                    "name": "Oscar Hill",
                    "role": "v. konsul"
                },
                {
                    "name": "Johan Wendt",
                    "role": "disp."
                }
            ],
            "director": "Bertil Junger"
        },
        "7": {
            "name": "Manufaktur & Syfabriks AB.",
            "location": "Örbyhus",
            "business": "Se AB. örby hus Syfabrik, örby hus"
        },
        "8": {
            "name": "Manufakturverket Göta Bruk AB.",
            "location": "Malmö",
            "business": "Mek. verkstad i Anderslöv (Malmöh. l.). Tillverkar # reservdelar till plogar och skördemaskiner samt yxor och skruvbrodd. Varumärke: »Göta»",
            "contact": {
                "office": "Malmö, Engelbrektsg. 11 A",
                "phone": [
                    "Tho-méesjärn"
                ],
                "postgiro": "14063"
            },
            "financials": {
                "capital": "46,000 kr",
                "employees": {
                    "industriarb": 35
                },
                "annual_production_value": "1,000,000 kr"
            },
            "foundation_year": 1915,
            "director": "Allan Bäckman",
            "sales_manager": "Gunnar Martinsson"
        },
        "9": {
            "name": "AB. Manus",
            "location": "Norrköping",
            "business": "Mek. verkstad. Tillverkar mjölkningsmaskiner, vacuumpumpar och mjölkkylare"
        }
    }
}