{
    "original": "Ystad—Zadig\n\nTelefon: 1057 o. 2067. Postgiro: 96870.\n— Akt.-kap.: 70,000 kr. Antal\nindustriarb.: 60. — Bolaget grundat 1933.\n\nStyrelse: dir. Fred Nilsson (ordf.), fru\nE. Nilsson, bandi. Wilhelm Nilsson,\nkamrer Nils Söderman.\n\nVerkst. dir.: Fred Nilsson.\n\nKamrer: Nils Söderman.\n\nAB. Ystads Metallindustri, Ystad.\n\nMetallvarufabrik. Tillverkar nytto- och\nprydnadsföremål av silver, tenn, brons\noch järnsmide, skyltställ, kyrkoarmatur\nm. m. Varubenämningar: Ystad-Silver,\nYstad-Tenn, Ystad-Brons o. Ystad-Järn.\n\nTelegr.-adr.: Metallindustri, Ystad.\nTelefon: 339 o. 368. Postgiro: 74970.\n\nAkt.-kap.: 100,000 kr. Antal\nindustriarb.: 80. — Bolaget^ grundat 1919.\n\nDisp.: Ossian Raihle.\n\n*YSTA-maskiner, Ystads Cjuteri &amp;\nMek. Verkstads AB., Ystad.\n\nTillverkar lantbruksmaskiner och\n-redskap, manglar, vattenvärmare (fristående\ntvätthuspannor), stenkrossar samt\ngjutgods m. m. Varumärke: »Ysta».\n\nTelegr.-adr. o. telefon: »Ystamaskiner».\nPostgiro: 30299.\n\nAkt.-kap.: 800,000 kr. Antal\nindustriarb.: 185. — Firman etabl. 1853, bolag\n1887.\n\nStyrelse: dir. Axel Kemner (ordf.),\nfru Sigrid Kemner, övering. Wilhelm\nKemner.\n\nVerkst. dir.: Axel Kemner.\n\növering.: Wilhelm Kemner.\n\nKontorschef: Johan Andersson.\n\nKamrer: Ernst Svensson.\n\n*AB. Ytterstfors-Munksund, Luleå.\n\nSe Munksunds AB., Luleå.\n\nAB. YvY-Fabriken, Ystad.\n\nKem.-tekn. fabrik. Tillverkar tvål,\nhårolja, schamponeringspulver m. fl.\nkosmetiska preparat. Varunamn: »YvY».\n\nTelegr.-adr.: Yvy, Ystad. Telefon:\n2101—03. Postgiro: 8488. Repr. i\nStockholm: F. B. Charleville, Karlbergsvägen\n73, telefon: 332555.\n\nAkt.-kap.: 124,400 kr. Antal\nindustriarb.: 50. Tillv.-värde pr år: 850,000 kr.\n\n—\tFirman etabl. 1895, bolag 1922.\nStyrelse: fabr. A. J. österlin, disp.\n\nSture österlin.\n\nVerkst. dir.: A. J. österlin.\nKamrer: Emil Ståhl.\nKemist: Sture österlin.\n\n*Yxhults Stenhuggeri AB.,\n\nHällabrottet.\n\nStenhuggeri, lättbetongfabrik och\nkalk-bränneri i Hällabrottet (Örebro l.). Utför\nbyggnadssten i grön, vit m. fl. sorters\nmarmor, i kalksten och andra stenarter,\ntillverkar lättbetong (»Ytong») samt\nbränd kalk för jordbruks- och\nbyggnadsändamål. Bolaget idkar jämväl jordbruk\nsamt distribuerar elektr. energi.\n\nTelefon: Örebro 72070. Postgiro: 31508.\nEnsamförsälj. i Stockholm: Yxhults\nFörsäljnings AB., Lagerlöf sg. 4, telefon:\n520915.\n\nAkt.-kap.: 2,000,000 kr. Antal\nindustriarb.: 360. Tillv.-värde pr år: 5,000,000 kr.\n\n—\tBolaget grundat 1878.\n\nStyrelse: dir. C. Aug. Carlén (ordf.),\ning. Bertil Carlén, disp. Erik Carlén,\nbyggm. Olle Engkvist, adv. Claes Ljung.\n\nVerkst. dir.: C. Aug. Carlén.\nKamrer: A. Löwstedt.\n\n*AB. Yxsjö Gruvor, Yxsjöberg.\n\nBryter wolframmalm (scheelit) och\nkopparmalm vid gruva i Yxsjöberg\n(Örebro l.).\n\nAkt.-kap.: 5,000 kr. Antal industriarb.:\n125. — Gruvdriften började 1936, nuv.\nbolag grundat 1941.\n\nStyrelse: disp. Josef Berglund, dir.\nRagnar Nilson.\n\nDisp.: Josef Berglund.\n\nz\n\n* utmärker till Sveriges Industriförbund anslutna företag.\n\n*Wald. Zachrissons Boktryckeri AB.\n(Wezäta), Göteborg.\nSe Wezäta-Göteborgslitografen AB.,\nGöteborg.\n\n*M. Zadig AB., Malmö.\n\nKem.-teknisk fabrik. Tillverkar tvål,\nparfymer, hårvatten och andra kosmetiska\n\npreparat, tvättpulver m. m. Varunamn:",
    "structured": {
        "1": {
            "name": "AB Ystads Metallindustri",
            "location": "Ystad",
            "business": "Metallvarufabrik",
            "contact": {
                "phone": [
                    "1057",
                    "2067"
                ],
                "postgiro": "96870",
                "telegraph": "Metallindustri, Ystad",
                "factory_phone": "339, 368",
                "factory_office": "Ystad"
            },
            "financials": {
                "capital": "70,000 kr",
                "employees": {
                    "industriarb": 60
                }
            },
            "foundation_year": 1933,
            "board": [
                {
                    "name": "Fred Nilsson",
                    "role": "dir"
                },
                {
                    "name": "E. Nilsson",
                    "role": "fru"
                },
                {
                    "name": "Wilhelm Nilsson",
                    "role": "bandi"
                },
                {
                    "name": "Nils Söderman",
                    "role": "kamrer"
                }
            ],
            "director": "Fred Nilsson",
            "manager": "Nils Söderman"
        },
        "2": {
            "name": "YSTA-maskiner, Ystads Cjuteri & Mek. Verkstads AB",
            "location": "Ystad",
            "business": "Tillverkar lantbruksmaskiner och redskap, manglar, vattenvärmare (fristående tvätthuspannor), stenkrossar samt gjutgods",
            "contact": {
                "telegraph": "Ystamaskiner",
                "postgiro": "30299"
            },
            "financials": {
                "capital": "800,000 kr",
                "employees": {
                    "industriarb": 185
                }
            },
            "foundation_year": 1853,
            "board": [
                {
                    "name": "Axel Kemner",
                    "role": "dir"
                },
                {
                    "name": "Sigrid Kemner",
                    "role": "fru"
                },
                {
                    "name": "Wilhelm Kemner",
                    "role": "övering"
                }
            ],
            "director": "Axel Kemner",
            "manager": "Johan Andersson"
        },
        "3": {
            "name": "AB YvY-Fabriken",
            "location": "Ystad",
            "business": "Kem.-tekn. fabrik",
            "contact": {
                "phone": "2101—03",
                "postgiro": "8488",
                "telegraph": "Yvy, Ystad"
            },
            "financials": {
                "capital": "124,400 kr",
                "employees": {
                    "industriarb": 50
                },
                "annual_production_value": "850,000 kr"
            },
            "foundation_year": 1895,
            "board": [
                {
                    "name": "A. J. österlin",
                    "role": "fabr"
                },
                {
                    "name": "Sture österlin",
                    "role": "disp"
                }
            ],
            "director": "A. J. österlin",
            "manager": "Emil Ståhl"
        },
        "4": {
            "name": "Yxhults Stenhuggeri AB",
            "location": "Hällabrottet",
            "business": "Stenhuggeri, lättbetongfabrik och kalk-bränneri",
            "contact": {
                "phone": "Örebro 72070",
                "postgiro": "31508"
            },
            "financials": {
                "capital": "2,000,000 kr",
                "employees": {
                    "industriarb": 360
                },
                "annual_production_value": "5,000,000 kr"
            },
            "foundation_year": 1878,
            "board": [
                {
                    "name": "C. Aug. Carlén",
                    "role": "dir"
                },
                {
                    "name": "Bertil Carlén",
                    "role": "ing"
                },
                {
                    "name": "Erik Carlén",
                    "role": "disp"
                }
            ],
            "director": "C. Aug. Carlén",
            "manager": "A. Löwstedt"
        },
        "5": {
            "name": "AB. Yxsjö Gruvor",
            "location": "Yxsjöberg",
            "business": "Bryter wolframmalm (scheelit) och kopparmalm",
            "contact": {
                "postgiro": "5,000 kr"
            },
            "foundation_year": 1941,
            "board": [
                {
                    "name": "Josef Berglund",
                    "role": "disp"
                },
                {
                    "name": "Ragnar Nilson",
                    "role": "dir"
                }
            ],
            "director": "Josef Berglund"
        },
        "6": {
            "name": "M. Zadig AB",
            "location": "Malmö",
            "business": "Kem.-teknisk fabrik",
            "contact": {
                "postgiro": "N/A"
            }
        }
    }
}