{
    "original": "Bäxinol—Börser\n\nZanni Holmberg, Stockholm, Bergsg. 39,\ntelefon: 511060. — Antal industriarb.:\n30. — Firman etabl. 1918.\n\nÄgare o. chefer: fabr. Einar Bäckström\no. fabr. Sune Bäckström.\n\n*AB. Bäxinol, Göteborg.\n\nSe Oscar Bäcksins AB., Göteborg.\n\n*Böhlets Mangangruva, Karlsborg.\n\nSe Wargöns AB., Vargön.\n\n*AB. Arvid Böhlmarks Lampfabrik,\n\nStockholm.\n\nTillverkar elektrisk armatur och\nin-stallationsmateriel, neonskyltar,\nfotogenlampor, metallpressningar och andra\nmetallarbeten, butiksinredningar,\nstålmöbler m. m. vid fabrik i Stockholm;\nbelysningsglas, hushållsglas, prydnadsglas,\nbetongglas m. m. vid Pukebergs\nGlasbruk, Nybro (Kalmar l.).\n\nHuvudkontor: Stockholm, Högbergsg.\n25. Telegr.-adr. o. telefon: »Böhlmarks»,\nStockholm* Postgiro: 867. Brukskontor:\nNybro, telefon: Nybro 2 o. 102.\n\nAkt.-kap.: 1,200,000 kr. Antal\nindustriarb.: 150 i Stockholm, 100 i Pukeberg.\nTillv.-värde pr år: 3,500,000 kr. —\nFirman etabl. 1872, bolag 1897.\n\nStyrelse: disp. J. Kempe (ordf.), dir.\nE. A. Eworth, hovrättsrådet O. Löthner.\n\nVerkst. dir.: E. A. Eworth.\n\nFörsäljn.-chef: Sture Långh.\n\nBrukschef vid Pukeberg: förvalt. Sven\nJohansson.\n\n(Jfr annons nr 13.)\n\n*AB. Böksholms Sulfitfabrik,\n\nKlippan.\n\nSulfitfabrik och spritfabrik i\nBöks-hqlm, sågverk i Braås och Åseda\n(samtliga i Kronob. l.). Tillverkar\nsulfitcellulosa (huvudsakligen för Klippans\nFinpappersbruk), sulfitsprit, indunstad\nsulfitlut för vägpreparering, garvextrakt\nsamt sågade trävaror. Bolaget idkar\njämväl skogshantering.\n\nHuvudkontor: Klippan. Telegr.-adr.:\nPappersbruket, Klippan. Telefon:\n»Pappersbruket». Avd.-kontor: Braås och\nÅseda. Telegr.-adr.: Snickeri, Växjö.\n\nAkt.-kap.: 1,500,000 kr. Antal\nindustriarb.: 100. Årstillv.: 8,000 ton\nsulfitcellulosa.\n\nSulfitfabriken anlagd 1901, nuv. bolag\ngrundat 1914. Bolaget, som äges av AB.\nKlippans Finpappersbruk, har i sig\nupptagit f. d. Trävaru AB. Braås.\n\nStyrelse: bankir Tage Cervin (ordf.),\nbankdir. Allan Alexanderson, dir. P. Eg.\nGummeson, f. d. bankdir. H. K.\nLaurit-zen, dir. Carl Joh. Malmros.\n\nVerkst. dir. o. disp.: Carl Joh.\nMalmros.\n\nSkogschef: Bengt Eklundh.\n\nFabrikschef: Trygve Valeur.\n\nKamrer: Fritz Bergqvist.\n\nBöle Såg- &amp; Kvarn AB.,\n\nNäsviken.\n\nSågverk i Näsviken (Gävleb. l.).\nTillverkar sågade och hyvlade trävaror.\nBolaget driver jämväl kvarnrörelse.\n\nKontor o. ensamförsälj.: Forsså Bruks\nAB., Näs viken. Telefon: 7. — Antal\nindustriarb.: 30. Årstillv.: 800 stds\nträvaror. — Bolaget grundat 1897.\n\nVerkst. dir.: disp. Paul B. Burchardt.\n\nBöleå Snickerifabriks AB., Teg.\n\nTillverkar fönster och dörrar,\ninredningar och trappor vid fabrik i Böleå,\nTeg (Västerb. l.).\n\nTelefon: Umeå 1261. Postgiro: 63643.\n\n—\tAkt.-kap.: 100,000 kr. Arb.-antal: 14.\n\n—\tFirman etabl. 1925, bolag 1946.\nVerkst. dir.: Magnus Andersson.\n\n*Bönnelyche &amp; Thuröe, Malmö.\n\nSe Skånska Takpappfabriken,\nBönne-lyche &amp; Thuröe AB., Malmö.\n\n*AB. Börringe Tegelbruk,\n\nBörringe.\n\nTillverkar rött och gläcerat / fasad-,\nform- och taktegel vid tegelbruk i\nBörringe (Malmöh. l.).\n\nTelefon: Börringe 109. Postgiro: 148433.\n\n—\tAkt.-kap.: 150,000 kr. Antal\nindustriarb.: 35. Årstillv.: 2,5 milj. st. tegelvaror.\n\n—\tBolaget grundat 1942.\n\nStyrelse: greve Corfitz Beck-Friis,\nfrih. Sigvard Beck-Friis, greve Carl-Axet\nRudenschöld.\n\nVerkst. dir.: greve Corfitz Beck-Friis.\nKamrer: A. Selander.\n\nAB. P. C. Börser, Ljusdal.\n\nSågverk och hyvleri i Ljusdal (Gävleb.\n1.). Tillverkar sågade och hyvlade\nträvaror.\n\nTelefon: 1454 o. 1554. Postgiro: 80101.\n\n—\tAkt.-kap.: 84,000 kr. Antal industri-",
    "structured": {
        "1": {
            "name": "Bäxinol—Börser",
            "location": "Stockholm",
            "contact": {
                "office": "Bergsg. 39",
                "phone": [
                    "511060"
                ],
                "head_office": "Högbergsg. 25",
                "telegraph": "Böhlmarks",
                "postgiro": "867",
                "factory_office": "Pukebergs Glasbruk",
                "factory_phone": "Nybro 2 o. 102",
                "sales_offices": [
                    {
                        "location": "Stockholm",
                        "phone": "Högbergsg. 25"
                    },
                    {
                        "location": "Pukebergs Glasbruk",
                        "phone": "Nybro 2 o. 102"
                    }
                ]
            },
            "financials": {
                "capital": "1,200,000 kr",
                "employees": {
                    "Stockholm": 150,
                    "Pukeberg": 100
                },
                "annual_turnover": "3,500,000 kr",
                "annual_production_value": "3,500,000 kr"
            },
            "foundation_year": 1918,
            "owners": [
                "fabr. Einar Bäckström",
                "fabr. Sune Bäckström"
            ],
            "board": [
                {
                    "name": "disp. J. Kempe",
                    "role": "ordf."
                },
                {
                    "name": "dir. E. A. Eworth",
                    "role": null
                },
                {
                    "name": "hovrättsrådet O. Löthner",
                    "role": null
                }
            ],
            "director": "E. A. Eworth",
            "sales_manager": "Sture Långh"
        },
        "2": {
            "name": "AB. Bäxinol",
            "location": "Göteborg"
        },
        "3": {
            "name": "AB. Arvid Böhlmarks Lampfabrik",
            "location": "Stockholm",
            "products": "Tillverkar elektrisk armatur och installationsmateriel, neonskyltar, fotogenlampor, metallpressningar och andra metallarbeten, butiksinredningar, stålmöbler m. m. vid fabrik i Stockholm; belysningsglas, hushållsglas, prydnadsglas, betongglas m. m. vid Pukebergs Glasbruk, Nybro (Kalmar l.)",
            "contact": {
                "office": "Högbergsg. 25",
                "phone": [
                    "Böhlmarks"
                ],
                "head_office": "Högbergsg. 25",
                "postgiro": "867",
                "factory_office": "Pukebergs Glasbruk",
                "factory_phone": "Nybro 2 o. 102"
            },
            "financials": {
                "capital": "1,200,000 kr",
                "employees": {
                    "Stockholm": 150,
                    "Pukeberg": 100
                },
                "annual_turnover": "3,500,000 kr",
                "annual_production_value": "3,500,000 kr"
            },
            "foundation_year": 1872,
            "board": [
                {
                    "name": "disp. J. Kempe",
                    "role": "ordf."
                },
                {
                    "name": "dir. E. A. Eworth",
                    "role": null
                },
                {
                    "name": "hovrättsrådet O. Löthner",
                    "role": null
                }
            ],
            "director": "E. A. Eworth",
            "sales_manager": "Sture Långh"
        },
        "4": {
            "name": "AB. Böksholms Sulfitfabrik",
            "location": "Klippan",
            "products": "Tillverkar sulfitcellulosa (huvudsakligen för Klippans Finpappersbruk), sulfitsprit, indunstad sulfitlut för vägpreparering, garvextrakt samt sågade trävaror. Bolaget idkar jämväl skogshantering",
            "contact": {
                "office": "Klippan",
                "phone": [
                    "Pappersbruket"
                ],
                "sales_offices": [
                    {
                        "location": "Braås",
                        "phone": "Snickeri, Växjö"
                    },
                    {
                        "location": "Åseda",
                        "phone": "Snickeri, Växjö"
                    }
                ]
            },
            "financials": {
                "capital": "1,500,000 kr",
                "employees": {
                    "Klippan": 100
                },
                "annual_turnover": null,
                "annual_production_value": "8,000 ton sulfitcellulosa"
            },
            "foundation_year": 1901,
            "owners": [
                "AB. Klippans Finpappersbruk"
            ],
            "board": [
                {
                    "name": "bankir Tage Cervin",
                    "role": "ordf."
                },
                {
                    "name": "bankdir. Allan Alexanderson",
                    "role": null
                },
                {
                    "name": "dir. P. Eg. Gummeson",
                    "role": null
                },
                {
                    "name": "f. d. bankdir. H. K. Laurit-zen",
                    "role": null
                },
                {
                    "name": "dir. Carl Joh. Malmros",
                    "role": null
                }
            ],
            "director": "Carl Joh. Malmros"
        },
        "5": {
            "name": "Böle Såg- & Kvarn AB.",
            "location": "Näsviken",
            "products": "Tillverkar sågade och hyvlade trävaror. Bolaget driver jämväl kvarnrörelse",
            "contact": {
                "office": "Näsviken",
                "phone": [
                    "Forsså Bruks AB."
                ]
            },
            "financials": {
                "employees": {
                    "Näsviken": 30
                },
                "annual_production_value": "800 stds trävaror"
            },
            "foundation_year": 1897,
            "board": [
                {
                    "name": "disp. Paul B. Burchardt",
                    "role": null
                }
            ]
        },
        "6": {
            "name": "Böleå Snickerifabriks AB.",
            "location": "Teg",
            "products": "Tillverkar fönster och dörrar, inredningar och trappor vid fabrik i Böleå, Teg (Västerb. l.)",
            "contact": {
                "office": "Böleå",
                "phone": [
                    "Umeå 1261"
                ]
            },
            "financials": {
                "capital": "100,000 kr",
                "employees": {
                    "Teg": 14
                }
            },
            "foundation_year": 1925
        },
        "7": {
            "name": "AB. Börringe Tegelbruk",
            "location": "Börringe",
            "products": "Tillverkar rött och gläcerat / fasad-, form- och taktegel vid tegelbruk i Börringe (Malmöh. l.)",
            "contact": {
                "office": "Börringe",
                "phone": [
                    "Börringe 109"
                ]
            },
            "financials": {
                "capital": "150,000 kr",
                "employees": {
                    "Börringe": 35
                },
                "annual_production_value": "2,5 milj. st. tegelvaror"
            },
            "foundation_year": 1942,
            "board": [
                {
                    "name": "greve Corfitz Beck-Friis",
                    "role": null
                },
                {
                    "name": "frih. Sigvard Beck-Friis",
                    "role": null
                },
                {
                    "name": "greve Carl-Axet Rudenschöld",
                    "role": null
                }
            ],
            "director": "greve Corfitz Beck-Friis",
            "manager": "A. Selander"
        },
        "8": {
            "name": "AB. P. C. Börser",
            "location": "Ljusdal",
            "products": "Tillverkar sågade och hyvlade trävaror",
            "contact": {
                "office": "Ljusdal",
                "phone": [
                    "1454",
                    "1554"
                ]
            },
            "financials": {
                "capital": "84,000 kr"
            }
        }
    }
}