{
    "original": "Karlshamn-—Karlskoga\n\n* Karlshamns Bryggeri AB.,\n\nKarlshamn.\n\nSe Carlshamns Bryggeri AB.,\nKarlshamn.\n\nKarlshamns Konfektions AB.,\n\nKarlshamn.\n\nTillverkar arbetskläder och sportkläder.\nVarumärke: »KBK».\n\nTelefon: 585. Postgiro: 75524. -\nAkt.-kap.: 85,500 kr. Antal industriarb.: 30.\n— Firman etabl. 1931, bolag 1939.\n\nVerkst. dir.: köpm. Eskil Westlund.\n\n*AB. Karlshamns Oljefabriker,\n\nNorrköping.\n\nTillverkar vegetabiliska oljor och\nkraftfoder vid fabrik i Karlshamn.\nVarumärke: »AKO».\n\nHuvudkontor: Norrköping.\nTelegr.-adr.: Akofab, Norrköping. Telefon:\n29465. Postgiro: 152822. Fabrikskontor:\nKarlshamn.\n\nAkt.-kap.: 3,000,000 kr. Antal\nindustriarb.: 350. Tillv.-värde pr år: 104,000,000\nkr.\n\nBolaget, som äges av Kooperativa\nFörbundet, grundades 1932.\n\nStyrelse: dir. Albin Johansson (ordf.),\nkonsul S. H. Sörensen (v. ordf.), fil. lic.\nMauritz Bonow, dir. Hj. Degerstedt, dir.\nHugo Edstam, dir. G. Osvald, dir. Ernst\nPersson.\n\nVerkst. dir.: S. H. Sörensen.\n\nFörsäljn.-chef er: B. Anderberg o. Nils\nKjellberg.\n\n\"Karlshamns Stads Vatten- och\nElektricitetsverk, Karlshamn.\n\nDistribuerar elektr. energi från\nSydsvenska Kraft AB. samt driver stadens\nvattenledningsverk. Telefon: 178.\n\nChef: stadsing. Knut L:son Eneby.\n\n\"Karlshamns Yllefabriks AB.,\n\nÅkeholm.\n\nSpinneri, färgeri och trikåfabrik i\nÅkeholm (Blekinge l.). Tillverkar\nstreieh-och strumpgarn, hemslöjdsgarn samt\ntri-kåvaror. Specialitet: sportgarner för\ntri-kåfabriker. Bolaget idkar även jordbruk.\n\nTelegr.-adr.: Yllefabriken, Åkeholm.\nTelefon: 1. Postgiro: 36237.\n\nRepr.: för Stockholm: Edv. A. Hansen.\nVästmannag. 14, telefon: 111374; för\nNorrland: Simon Bergström, Falun,\ntelefon: 695; for övriga Sverige: Oscar L.\nWallin, Smålands Taberg, telefon: 103.\n\nAkt.-kap.: 180,000 kr. Antal\nindustriarb.: 90. Tillv.-värde pr år: 800,000 kr.\n\n—\tFabriken anlagd 1893, nuv. bolag\ngrundat 1903.\n\nStyrelse: disp. Hemil Wigstrand\n(ordf.), ing. Gunnar Wigstrand.\n\nVerkst. dir. o. disp.: Hemil Wigstrand.\n\nKontorschef: Arvid Berg.\n\n*Kar!shults Såg &amp; Tegelbruk, Patrik\nJacobson, Motala verkstad.\n\nTegelbruk och sågverk vid Motala\nverkstad (Österg. l.). Tillverkar murtegel och\ndräneringsrör samt sågade trävaror.\n\nTelefon: Motala 32. Postgiro: 84096.\n\n—\tAntal industriarb.: 36, varav vid\ntegelbruket 25. Tillv.-värde pr år: 180,000 kr.\n\n—\tFirman etabl. 1925.\n\nÄgare: Patrik Jacobsons sterbhus.\n\nDisp.: Sune Jacobson.\n\nAB. Karlshälls Cranitindustri,\n\nGöteborg.\n\nStenhuggerier å olika platser inom\nBlekinge län. Tillverkar gatsten, kantsten,\nbyggnadssten samt råblock.\n\nKontor: Göteborg, Järntorgsg. 12 o. 14.\nTelegr.-adr.: Stenbolaget, Göteborg.\nTelefon: 135509\n\nAkt.-kap.: 40,000 kr. Antal\nindustriarb. vid full drift: 100. — Bolaget\ngrundades 1908.\n\nStyrelse: dir. Carl Sjöstrand (ordf.),\nadv. E. Markfelt, civiling. Sven A.\nMattsson.\n\nVerkst. dir.: Carl Sjöstrand.\n\n\"Karlskoga Tegelbruk, Ericsson\n&amp; Co., Karlskoga.\n\nTegelbruk, cementvaru- och\nmurbruksfabrik i Bregårdstorp, Karlskoga (Örebro\n1.). Tillverkar murtegel, dräneringsrör,\ncementsten samt mur- och putsbruk.\n\nTelefon: 30662 o. 31108. Postgiro:\n288808. — Antal industriarb.: 20.\nÅrstillv.: 1,4 milj. st. tegelvaror. —\nTegelbruket anlagt 1897, nuv. firma etabl. 1938.\n\nÄgare: disp. Oskar Ericsson o. f.\nlandsfiskal Gustav Insulander.\n\nChef: Oskar Ericsson.\n\n\"Karlskoga Ångbryggeri, Karlskoga.\n\nTillverkar malt- och läskedrycker.\n\nTelefon: 32555. Postgiro: 74852.\n—-Antal industriarb.: 16. Tillv.-värde pr\når: 500,000 kr. — Firman etabl. 1850.\n\nÄgare o. chef: disp. Emil Blomquist.",
    "structured": {
        "1": {
            "name": "Karlshamns Bryggeri AB.",
            "location": "Karlshamn",
            "business": "Bryggeri",
            "products": "Tillverkar arbetskläder och sportkläder. Varumärke: »KBK».",
            "contact": {
                "phone": [
                    "585"
                ],
                "postgiro": "75524"
            },
            "financials": {
                "capital": "85,500 kr",
                "employees": {
                    "industriarb": 30
                }
            },
            "foundation_year": 1931,
            "current_name_year": 1939,
            "director": "köpm. Eskil Westlund"
        },
        "2": {
            "name": "AB. Karlshamns Oljefabriker",
            "location": "Norrköping",
            "business": "Tillverkar vegetabiliska oljor och kraftfoder",
            "products": "Tillverkar vegetabiliska oljor och kraftfoder vid fabrik i Karlshamn. Varumärke: »AKO».",
            "contact": {
                "office": "Huvudkontor: Norrköping",
                "phone": [
                    "29465"
                ],
                "postgiro": "152822",
                "head_office": "Karlshamn"
            },
            "financials": {
                "capital": "3,000,000 kr",
                "employees": {
                    "industriarb": 350
                },
                "annual_turnover": "104,000,000 kr"
            },
            "foundation_year": 1932,
            "board": [
                {
                    "name": "dir. Albin Johansson",
                    "role": "ordf."
                },
                {
                    "name": "konsul S. H. Sörensen",
                    "role": "v. ordf."
                },
                {
                    "name": "fil. lic. Mauritz Bonow",
                    "role": null
                },
                {
                    "name": "dir. Hj. Degerstedt",
                    "role": null
                },
                {
                    "name": "dir. Hugo Edstam",
                    "role": null
                },
                {
                    "name": "dir. G. Osvald",
                    "role": null
                },
                {
                    "name": "dir. Ernst Persson",
                    "role": null
                }
            ],
            "director": "S. H. Sörensen",
            "sales_manager": "B. Anderberg o. Nils Kjellberg"
        },
        "3": {
            "name": "Karlshamns Stads Vatten- och Elektricitetsverk",
            "location": "Karlshamn",
            "business": "Distribuerar elektr. energi"
        },
        "4": {
            "name": "Karlshamns Yllefabriks AB.",
            "location": "Åkeholm",
            "business": "Spinneri, färgeri och trikåfabrik"
        },
        "5": {
            "name": "Kar!shults Såg & Tegelbruk, Patrik Jacobson",
            "location": "Motala verkstad",
            "business": "Tegelbruk och sågverk"
        },
        "6": {
            "name": "AB. Karlshälls Cranitindustri",
            "location": "Göteborg",
            "business": "Stenhuggerier"
        },
        "7": {
            "name": "Karlskoga Tegelbruk, Ericsson & Co.",
            "location": "Karlskoga",
            "business": "Tegelbruk, cementvaru- och murbruksfabrik"
        },
        "8": {
            "name": "Karlskoga Ångbryggeri",
            "location": "Karlskoga",
            "business": "Tillverkar malt- och läskedrycker"
        }
    }
}