{
    "original": "Svensson\n\n*J. Svensson &amp; Bourghardt*\n\nGöteborg.\n\nTagelspinneri, f jäderrenseri, resår- och\nsängklädersfabrik, kapok- och vaddfabrik.\nTillverkar resårer och sängkläder,\nförädlar fjäder och dun, kapok, tagel, vadd,\naxelvaddar m. m. Varunamn: »Paradis».\nPirman driver även engroshandel med\nmöbleringsmateriel.\n\nHuvudkontor: Göteborg, Tuvevägen,\nHisingen. Telegr.-adr.: Svensbourg,\nGöteborg. Telefon: »Paradis». Postgiro:\n12396. Avd.-kontor: Stockholm, Kungsg.\n53, telefon: 202897 o. 118804.\n\nAntal industriarb.: 80. Tillv.-värde pr\når (egen tillverkning): 1,800,000 kr. —\nFirman grundad 1881.\n\nÄgare o. chef: konsul J. Bourghardt.\n\nDisp.: Torsten Krook.\n\nAB. Joh. Swensons\nKonfektionsfabrik, Sölvesborg.\n\nTillverkar damkappor, dräkter och\nkjolar\n\nTelefon: 10415. Postgiro: 171743. —\nAkt.-kap.: 50,000 kr. Antal industriarb.:\n25. Tillv.-värde pr år: 250,000 kr. —\nFirman etabl. 1921, bolag 1944.\n\nVerkst. dir.: Joh. Swenson.\n\nJ. A. Svenssons Metallfabrik AB.,\n\nJönköping.\n\nTillverkar armatur för gas, vatten och\nånga samt metallgjutgocls i mässing,\nröd-gods, lagermetall, aluminium m. m.\n\nTelefon: 103. Postgiro: 9355. —\nAkt.-kap.: 150,000 kr. Antal industriarb.: 50.\nTillv.-värde pr år: 500,000 kr. — Firman\netabl. 1875, bolag 1939.\n\nStyrelse o. chefer: ing. Ernst Svensson\no. ing. J. Kurz.\n\nJ. E. Svenssons Mek. Verkstad,\n\nHerrljunga.\n\nTillverkar stålmöbler, sjukhussängar,\nsvetsade järnkonstruktioner, pressade\nmassartiklar samt specialsmiden vid mek.\nverkstad i Herrljunga (Älvsb. l.).\n\nTelefon: 68 o. 124. Postgiro: 36654.\n— Antal industriarb.: 25. Tillv.-värde pr\når: 200,000 kr. — Firman etabl. 1892.\n\nÄgare o. chef: fabr. Håkan Svensson.\n\n*AB. Ludvig Svensson, Einna.\n\nBomulls väveri, färgeri, blekeri och\napp returverk (Kinnamarks Mekaniska\nVäveri) i Kinna (Älvsb. l.). Tillverkar\ngardiner, jaequardbolster- och korsetty-\n\nger, borddukar, näsdukar m. m.\nSpecialitet: gardiner.\n\nTelegr.-adr.: Ludvig, Kinna. Telefon t\n10385. Postgiro: 8747.\n\nAkt.-kap.: 800,000 kr. Antal\nindustriarb.: 125. — Firman etabl. 1887, bola^\n1928.\n\nStyrelse: dir. Ivan Ludvigson (ordf.)*\nnotarie Hugo Ludvigson, fru G. Svensson-\n\nVerkst. dir.: Ivan Ludvigson.\n\nDisp.: Hugo Ludvigson.\n\nN. Svenssons Mek. Verkstads AB*\n\nGlimåkra.\n\nMek. verkstad i Glimåkra (Kristianst.\n1.). Tillverkar ledstångs- och käppsvarvar,,\nputsmaskiner, virkestorkanläggningar för\nsågverk och snickerifabriker samt\nspecialmaskiner för träbearbetning och för\nstenindustrien.\n\nTelefon: 7. Postgiro: 91273. —\nAkt.-kap.: 18,000 kr. Antal industriarb.: 25&gt;~\nTillv.-värde pr år: 250,000 kr. — Bolaget\ngrundat 1924.\n\nDisp.: Nils Svensson.\n\nOtto Swensons Snickeri &amp; Trävarti\n\nAB., Ronneby.\n\nSågverk, hyvleri samt murbruksfabrik\ni Ronneby, sågverk i Backaryd (båda s\nBlekinge l.). Tillverkar sågade och\nhyvlade trävaror samt murbruk.\n\nTelefon: 140 o. 740. Postgiro: 98457.\nAkt.-kap.: 90,000 kr. Antal industriarb.:\n25. Årstillv.: 900 stds trävaror. —\nBolaget grundat 1942.\n\nVerkst. dir. o. disp.: Olle Borenberg.\n\nP. J. Svenssons Mek. Verkstad,\n\nHalmstad.\n\nTillverkar kokare för slakterier oefe\ntextilfabriker samt järnkonstruktioner;\nutför fartygsreparationer och elektr.\nsvetsning av kärl under tryck, ångpannor\no. d.\n\nTelefon: 179. Postgiro: 137570. —\nAntal industriarb.: 16. Tillv.-värde pr år:\n145,000 kr. — Firman etabl. 1879, nuv.\nägare 1935.\n\nÄgare o. chef: fabr. Oskar Johansson»\n\n*AB. Walfrid Svensson &amp; C:o.,\n\nKarlstad.\n\nMöbelfabrik. Tillverkar bonade ocb\nlackerade möbler.\n\nTelefon: 10121. Postgiro: 37002. —\nAkt.-kap.: 500,000 kr. Antal industriarb.:",
    "structured": {
        "SwedishFirms": [
            {
                "name": "J. Svensson & Bourghardt",
                "location": "Göteborg",
                "business": "Tagelspinneri, f jäderrenseri, resår- och sängklädersfabrik, kapok- och vaddfabrik. Tillverkar resårer och sängkläder, förädlar fjäder och dun, kapok, tagel, vadd, axelvaddar m. m. Varunamn: »Paradis». Pirman driver även engroshandel med möbleringsmateriel.",
                "contact": {
                    "office": "Göteborg, Tuvevägen, Hisingen",
                    "phone": [
                        "Paradis"
                    ],
                    "postgiro": "12396",
                    "head_office": "Göteborg, Tuvevägen, Hisingen",
                    "sales_offices": [
                        {
                            "location": "Stockholm, Kungsg. 53",
                            "phone": "202897 o. 118804"
                        }
                    ],
                    "telegraph": "Svensbourg, Göteborg"
                },
                "financials": {
                    "capital": "Not available",
                    "employees": {
                        "industriarb": 80
                    },
                    "annual_turnover": "Not available",
                    "annual_production_value": "1,800,000 kr"
                },
                "foundation_year": 1881,
                "owners": [
                    "konsul J. Bourghardt"
                ],
                "director": "Not available",
                "manager": "Not available"
            },
            {
                "name": "AB. Joh. Swensons Konfektionsfabrik",
                "location": "Sölvesborg",
                "business": "Tillverkar damkappor, dräkter och kjolar",
                "contact": {
                    "phone": [
                        "10415"
                    ],
                    "postgiro": "171743"
                },
                "financials": {
                    "capital": "50,000 kr",
                    "employees": {
                        "industriarb": 25
                    },
                    "annual_turnover": "Not available",
                    "annual_production_value": "250,000 kr"
                },
                "foundation_year": 1921,
                "owners": [
                    "Joh. Swenson"
                ],
                "director": "Joh. Swenson",
                "manager": "Not available"
            },
            {
                "name": "J. A. Svenssons Metallfabrik AB.",
                "location": "Jönköping",
                "business": "Tillverkar armatur för gas, vatten och ånga samt metallgjutgocls i mässing, röd-gods, lagermetall, aluminium m. m.",
                "contact": {
                    "phone": [
                        "103"
                    ],
                    "postgiro": "9355"
                },
                "financials": {
                    "capital": "150,000 kr",
                    "employees": {
                        "industriarb": 50
                    },
                    "annual_turnover": "Not available",
                    "annual_production_value": "500,000 kr"
                },
                "foundation_year": 1875,
                "owners": [
                    "ing. Ernst Svensson",
                    "ing. J. Kurz"
                ],
                "director": "Not available",
                "manager": "Not available"
            },
            {
                "name": "J. E. Svenssons Mek. Verkstad",
                "location": "Herrljunga",
                "business": "Tillverkar stålmöbler, sjukhussängar, svetsade järnkonstruktioner, pressade massartiklar samt specialsmiden vid mek. verkstad i Herrljunga (Älvsb. l.)",
                "contact": {
                    "phone": [
                        "68 o. 124"
                    ],
                    "postgiro": "36654"
                },
                "financials": {
                    "capital": "Not available",
                    "employees": {
                        "industriarb": 25
                    },
                    "annual_turnover": "Not available",
                    "annual_production_value": "200,000 kr"
                },
                "foundation_year": 1892,
                "owners": [
                    "fabr. Håkan Svensson"
                ],
                "director": "Not available",
                "manager": "Not available"
            },
            {
                "name": "AB. Ludvig Svensson, Einna",
                "location": "Kinna",
                "business": "Bomulls väveri, färgeri, blekeri och app returverk (Kinnamarks Mekaniska Väveri) i Kinna (Älvsb. l.). Tillverkar gardiner, jaequardbolster- och korsettyger, borddukar, näsdukar m. m. Specialitet: gardiner.",
                "contact": {
                    "phone": [
                        "10385"
                    ],
                    "postgiro": "8747"
                },
                "financials": {
                    "capital": "800,000 kr",
                    "employees": {
                        "industriarb": 125
                    },
                    "annual_turnover": "Not available",
                    "annual_production_value": "Not available"
                },
                "foundation_year": 1887,
                "owners": [
                    "dir. Ivan Ludvigson",
                    "notarie Hugo Ludvigson",
                    "fru G. Svensson"
                ],
                "director": "Ivan Ludvigson",
                "manager": "Not available"
            },
            {
                "name": "N. Svenssons Mek. Verkstads AB",
                "location": "Glimåkra",
                "business": "Mek. verkstad i Glimåkra (Kristianst. 1.). Tillverkar ledstångs- och käppsvarvar, putsmaskiner, virkestorkanläggningar för sågverk och snickerifabriker samt specialmaskiner för träbearbetning och för stenindustrien.",
                "contact": {
                    "phone": [
                        "7"
                    ],
                    "postgiro": "91273"
                },
                "financials": {
                    "capital": "18,000 kr",
                    "employees": {
                        "industriarb": 25
                    },
                    "annual_turnover": "Not available",
                    "annual_production_value": "250,000 kr"
                },
                "foundation_year": 1924,
                "owners": [
                    "Disp.: Nils Svensson"
                ],
                "director": "Not available",
                "manager": "Not available"
            },
            {
                "name": "Otto Swensons Snickeri & Trävarti AB.",
                "location": "Ronneby",
                "business": "Sågverk, hyvleri samt murbruksfabrik i Ronneby, sågverk i Backaryd (båda s Blekinge l.). Tillverkar sågade och hyvlade trävaror samt murbruk.",
                "contact": {
                    "phone": [
                        "140 o. 740"
                    ],
                    "postgiro": "98457"
                },
                "financials": {
                    "capital": "90,000 kr",
                    "employees": {
                        "industriarb": 25
                    },
                    "annual_turnover": "Not available",
                    "annual_production_value": "Not available"
                },
                "foundation_year": 1942,
                "owners": [
                    "Verkst. dir. o. disp.: Olle Borenberg"
                ],
                "director": "Not available",
                "manager": "Not available"
            },
            {
                "name": "P. J. Svenssons Mek. Verkstad",
                "location": "Halmstad",
                "business": "Tillverkar kokare för slakterier oefe textilfabriker samt järnkonstruktioner; utför fartygsreparationer och elektr. svetsning av kärl under tryck, ångpannor o. d.",
                "contact": {
                    "phone": [
                        "179"
                    ],
                    "postgiro": "137570"
                },
                "financials": {
                    "capital": "Not available",
                    "employees": {
                        "industriarb": 16
                    },
                    "annual_turnover": "Not available",
                    "annual_production_value": "145,000 kr"
                },
                "foundation_year": 1879,
                "owners": [
                    "ägare o. chef: fabr. Oskar Johansson"
                ],
                "director": "Not available",
                "manager": "Not available"
            },
            {
                "name": "AB. Walfrid Svensson & C:o.",
                "location": "Karlstad",
                "business": "Möbelfabrik. Tillverkar bonade ocb lackerade möbler.",
                "contact": {
                    "phone": [
                        "10121"
                    ],
                    "postgiro": "37002"
                },
                "financials": {
                    "capital": "500,000 kr",
                    "employees": {
                        "industriarb": "Not available"
                    },
                    "annual_turnover": "Not available",
                    "annual_production_value": "Not available"
                },
                "foundation_year": "Not available",
                "owners": "Not available",
                "director": "Not available",
                "manager": "Not available"
            }
        ]
    }
}