{
    "original": "Skandiakonserv—Skandinaviska\n\nSkandiakonserv, Hugo Hallgrens\nKonservfabriker AB., Stockholm.\n\nKonservfabriker i Lysekil och Ellös\n(Göteborg o. Bohus l.). Tillverkar\nfisk-och grönsakskonserver. Varumärken:\n»Skandia» o. »Gubben» m. fl.\n\nKontor: Stockholm, Stadsgården 6.\nTelegr.-adr.: Skandiakonserv, Stockholm.\nTelefon: 437091 o. 421620. Postgiro:\n12155.\n\nAkt.-kap.: 600,000 kr. Antal\nindustriarb.: 200. Tillv.-värde pr år: 4,000,000 kr.\n\nBolaget, som grundades 1917, äger\nfirmorna C. Hörman och C. Corneliusson,\nbåda i Lysekil. Kooperativa Förbundet\näger bolaget.\n\nStyrelse: dir. Albin Johansson (ordf.),\nfil. lic. Mauritz Bonow, dir. Hj.\nDeger-stedt, dir. Hugo Edstam, dir. G. Osvald,\ndir. Ernst Persson.\n\nVerkst. dir.: Sten Wehlin.\n\nSkandinavien, Fabriks AB., Malmö.\n\nSe Fabriks AB. Skandinavien, Malmö.\n\n\"Skandinavisk Pälsberederi &amp; Färgeri\n\nAB., Svenljunga.\n\nSkinnberederi och färgeri i Svenljunga\n(Älvsb. l.). Utför pälsskinnsberedning\nsamt driver engroshandel med hudar.\n\nTelegr.-adr.: Pälskalv, Svenljunga.\nTelefon: 1130, 1155 o. 1203. — Akt.-kap.:\n400,000 kr. Antal industriarb.: 300.\n\nFirman etabl. 1936 under namn Stig\nElmquists Läderfabrik, ombildad under\nnuv. namn 1937.\n\nStyrelse: ing. Stig Elmquist, civiling.\nTorsten Elmquist, adv. Sten Lindskog.\n\nVerkst. dir. o. disp.: Stig Elmquist.\n\nKontorschef: Stig Wallander.\n\nSkandinaviska Aero AB., Stockholm.\n\nMek. verkstad och motorverkstad i\nNorrtälje. Tillverkar flygplansdetaljer\nsamt utför översyner och reparationer av\nflygmaskiner. Bolaget driver såsom\nhuvudrörelse flygtrafik.\n\nHuvudkontor: Stockholm,\nMästersa-muelsgat. 18. Telegr.-adr.: Scanaer,\nStockholm. Telefon: 235080. Postgiro: 56467.\nVerkstadskontor: Norrtälje. Telegr.-adr.:\nScanaer, Norrtälje. Telefon: 1052.\n\nAkt.-kap.: 2,000,000 kr. Antal\nindustriarb.: 35. — Bolaget grundat 1942 såsom\ndotterbolag till AB. Björkvallsflyg (etabl.\n1939); de båda bolagen sammanslogs 1944\nunder nuv. namn.\n\nVerkst. dir.: Mörten P. Hoogland.\n\nV erhstadschef: civiling. Björn\nTörnblom.\n\nAB. Skandinaviska Bokb. &amp;\nKartongfabriken, Stockholm.\n\nTillverkar kartonger.\n\nKontor: Grevtureg. 11. Telefon:\n670675. Postgiro: 50315.\n\nAkt.-kap.: 50,000 kr. Antal\nindustriarb.: 20. Tillv.-värde pr år: 140,000 kr.\n\nFirman, etabl. 1901, bolag 1919, äges\nav Tryckeri AB. Svea.\n\nVerkst. dir.: Josef Holmquist.\n\nKassadir.: Ejnar Ohlsson.\n\n\"Skandinaviska Dun- &amp;\nFjäderfabriken AB., Sundbyberg.\n\nDun- och fjäderrenseri samt\nsängklä-dersfabrik. Tillverkar kuddar, dun- och\nvaddtäcken, sovsäckar m. m.\n\nTelegr.-adr.: Skandiadun, Stockholm.\nTelefon: 281765, 281769 o. 283656.\nPostgiro: 56621.\n\nAkt.-kap.: 50,000 kr. Antal\nindustriarb.: 20. — Bolaget grundat 1933.\n\nStyrelse: ing. Fritiof Ahlsell (ordf.),\ning. Tryggve Lewander, ing. Edmund\nLöchen, adv. Yngve Schartau.\n\nVerkst. dir.: Adolf Wahrendorf.\n\n\"AB. Skandinaviska\nElektricitetsverk, Stockholm.\n\nÄger elektricitetsverk och elektr.\ndistributionsanläggningar i Dalsland,\nSaltsjöbaden, Strömstad med omnejd, Orust,\nTjörn och Öckerö samt i Stockholms\nskärgård. Kontrollerar bl. a. A/S Assens\nElektricitetsverk, Bollnäs Kraft AB., AB.\nGotlands Kraftverk, AB. Ludvika\nKraftverk, Siljansbygdens Kraft AB.,\nSmålands Kraft ABV, Storviks Kraft AB.,\nVoxnans Kraft AB., AB. Vänersborgs\nElektricitetsverk och Västbo Kraft AB.\n\nHuvudkontor: Stockholm, Klarabergsg.\n21. Telegr.-adr.: Concession, Stockholm.\nTelefon: 233350. Postgiro: 4002. —\nAkt.-kap.: 8,000,000 kr.\n\nBolaget, grundat 1902, är dotterbolag\ntill Allm. Svenska Elektriska AB.,\nVästerås.\n\nStyrelse: dir. Thorsten Ericson, dir.\nJohn Lindström, övering. Torsten Staaf.\n\nVerkst. dir.: John Lindström.\n\nÖvering.: Torsten Staaf.\n\nKamrer: Ivan Holmgren.\n\n\"Skandinaviska Eternit AB.,\n\nLomma.\n\nTillverkar plattor för\ntaktäcknings-och väggbeklädnadsändamål samt\nevakueringstrummor m. m. vid fabrik i\n\n615*",
    "structured": {
        "1": {
            "name": "Skandiakonserv—Skandinaviska Konservfabriker AB",
            "location": "Stockholm",
            "business": "Tillverkar fisk-och grönsakskonserver.",
            "products": "Varumärken: »Skandia» o. »Gubben» m. fl.",
            "contact": {
                "office": "Stadsgården 6",
                "phone": [
                    "437091",
                    "421620"
                ],
                "postgiro": "12155",
                "telegraph": "Skandiakonserv, Stockholm",
                "factory_office": "Lysekil och Ellös",
                "factory_phone": "200"
            },
            "financials": {
                "capital": "600,000 kr",
                "employees": {
                    "industriarb": 200
                },
                "annual_turnover": "4,000,000 kr",
                "annual_production_value": "4,000,000 kr"
            },
            "foundation_year": 1917,
            "predecessor": "C. Hörman and C. Corneliusson",
            "owners": "Kooperativa Förbundet",
            "board": [
                {
                    "name": "Albin Johansson",
                    "role": "ordf."
                },
                {
                    "name": "Mauritz Bonow",
                    "role": "fil. lic."
                },
                {
                    "name": "Hj. Deger-stedt",
                    "role": "dir."
                },
                {
                    "name": "Hugo Edstam",
                    "role": "dir."
                },
                {
                    "name": "G. Osvald",
                    "role": "dir."
                },
                {
                    "name": "Ernst Persson",
                    "role": "dir."
                }
            ],
            "director": "Sten Wehlin"
        },
        "2": {
            "name": "Skandinavisk Pälsberederi & Färgeri AB",
            "location": "Svenljunga",
            "business": "Utför pälsskinnsberedning samt driver engroshandel med hudar.",
            "contact": {
                "telegraph": "Pälskalv, Svenljunga",
                "phone": [
                    "1130",
                    "1155",
                    "1203"
                ],
                "postgiro": "400,000 kr"
            },
            "financials": {
                "capital": "400,000 kr",
                "employees": {
                    "industriarb": 300
                }
            },
            "foundation_year": 1936,
            "original_name": "Stig Elmquists Läderfabrik",
            "current_name_year": 1937,
            "board": [
                {
                    "name": "Stig Elmquist",
                    "role": "ing."
                },
                {
                    "name": "Torsten Elmquist",
                    "role": "civiling."
                },
                {
                    "name": "Sten Lindskog",
                    "role": "adv."
                }
            ],
            "director": "Stig Elmquist",
            "manager": "Stig Wallander"
        },
        "3": {
            "name": "Skandinaviska Aero AB",
            "location": "Stockholm",
            "business": "Tillverkar flygplansdetaljer samt utför översyner och reparationer av flygmaskiner.",
            "contact": {
                "office": "Mäster Samuelsgat. 18",
                "phone": "235080",
                "postgiro": "56467",
                "sales_offices": [
                    {
                        "location": "Norrtälje",
                        "phone": "1052"
                    }
                ]
            },
            "financials": {
                "capital": "2,000,000 kr",
                "employees": {
                    "industriarb": 35
                }
            },
            "foundation_year": 1942,
            "predecessor": "AB. Björkvallsflyg",
            "corporation_year": 1944,
            "director": "Mörten P. Hoogland",
            "sales_manager": "Björn Törnblom"
        },
        "4": {
            "name": "AB. Skandinaviska Bokb. & Kartongfabriken",
            "location": "Stockholm",
            "business": "Tillverkar kartonger.",
            "contact": {
                "office": "Grevtureg. 11",
                "phone": "670675",
                "postgiro": "50315"
            },
            "financials": {
                "capital": "50,000 kr",
                "employees": {
                    "industriarb": 20
                },
                "annual_turnover": "140,000 kr"
            },
            "foundation_year": 1901,
            "corporation_year": 1919,
            "owners": "Tryckeri AB. Svea",
            "director": "Josef Holmquist",
            "manager": "Ejnar Ohlsson"
        },
        "5": {
            "name": "Skandinaviska Dun- & Fjäderfabriken AB",
            "location": "Sundbyberg",
            "business": "Dun- och fjäderrenseri samt sängklädersfabrik. Tillverkar kuddar, dun- och vaddtäcken, sovsäckar m. m.",
            "contact": {
                "telegraph": "Skandiadun, Stockholm",
                "phone": [
                    "281765",
                    "281769",
                    "283656"
                ],
                "postgiro": "56621"
            },
            "financials": {
                "capital": "50,000 kr",
                "employees": {
                    "industriarb": 20
                }
            },
            "foundation_year": 1933,
            "board": [
                {
                    "name": "Fritiof Ahlsell",
                    "role": "ing."
                },
                {
                    "name": "Tryggve Lewander",
                    "role": "ing."
                },
                {
                    "name": "Edmund Löchen",
                    "role": "ing."
                },
                {
                    "name": "Yngve Schartau",
                    "role": "adv."
                }
            ],
            "director": "Adolf Wahrendorf"
        },
        "6": {
            "name": "AB. Skandinaviska Elektricitetsverk",
            "location": "Stockholm",
            "business": "Äger elektricitetsverk och elektr. distributionsanläggningar.",
            "contact": {
                "office": "Klarabergsg. 21",
                "phone": "233350",
                "postgiro": "4002"
            },
            "financials": {
                "capital": "8,000,000 kr"
            },
            "foundation_year": 1902,
            "owners": "Allm. Svenska Elektriska AB., Västerås",
            "board": [
                {
                    "name": "Thorsten Ericson",
                    "role": "dir."
                },
                {
                    "name": "John Lindström",
                    "role": "dir."
                }
            ],
            "director": "John Lindström",
            "manager": "Torsten Staaf",
            "kamrer": "Ivan Holmgren"
        },
        "7": {
            "name": "Skandinaviska Eternit AB",
            "location": "Lomma",
            "business": "Tillverkar plattor för taktäcknings-och väggbeklädnadsändamål samt evakueringstrummor m. m.",
            "products": "Tillverkar plattor för taktäcknings-och väggbeklädnadsändamål samt evakueringstrummor m. m."
        }
    }
}