{
    "original": "Svenska\n\nFörsäljn.-chef: ing. Edwin Ek.\n\nDriftschef: Sten Järås.\n\nKamrer: Gösta Sjögren.\n\nInköpschef: Torsten Holmen.\n\n*AB. Svenska Metallverken, Västerås.\n\nMetallhalvfabrikatverk med gjuteri,\nvalsverk, pressverk och tråddrageri\nsamt ammunitionsfabrik i Västerås,\ngjuteri, valsverk, pressverk, tubdrageri och\nfolieverk i Finspång (Östergötl. l.),\ntubdrageri i Granefors, Asarum (Blekinge\n1.), metall- och pressgjuteri samt\nkokkärlsfabrik i Skultuna (Västmanl. l.),\nmanufakturverk och pressgjuteri i\nUpplands Väsby (Sthlms l.), sågverk med\nhyvleri och lådfabrik i Skultuna,\nsågverk, kvarn och tegelbruk vid\nHörnsjö-fors, Västerfärnebo (Västmanl. l.) samt\nzink- och blygruvor med anrikningsverk\nvid Kaveltorp, Kopparberg (Örebro l.).\n\nTillverkar plåt, rör, tråd, linor,\nlameller, band, stänger, profiler, nitar,\nmuttrar, skruvar, spik, gjutgods och pressat\ngods av koppar, mässing, zink, bly och\naluminium samt andra metaller och\nlegeringar, lagermetaller, kokkärl,\nmauser-ammunition, plåtslageriarbeten såsom\nlagerfat och lagertanks, jäskar m. m. i\nkoppar och kopparlegeringar samt\naluminium och lättmetall-legeringar,\nrörspiraler av koppar, pressgjutgods m. m.,\nävensom tegel; bryter och anrikar zink- och\nblymalm. Bolaget idkar jämväl\nkvarn-och mejerirörelse samt jordbruk och\nskogshantering.\n\nHuvudkontor: Västerås. Telegr.-adr. o.\ntelefon: »Metallverken». Postgiro: 5026.\n\nFörsäljningscentral: Stockholm,\nBeri-darbansg. 17, telefon: »Metallverken»;\npostgiro: 122.\n\nAvd.-kontor: Göteborg, Otterhall, N.\nLiden 2, telefon: »Metallverken»;\nMalmö: Jörgen Kocksg. 2, telefon:\n»Metallverken»; Jönköping, telefon: 1907;\nEskilstuna, telefon: 37330 o. 37331;\nSundsvall, telefon: 1411 o. 14-26.\n\nAkt.-kap.: 24,525,000 kr. Antal\nindustriarb.: 3,686. — Bolaget, grundat 1907,\nhar i sig upptagit f. d. Finspongs\nMetallverks AB.\n\nStyrelse: dir. Sten Westerberg (ordf.),\nf. d. häradshövd. K. Dahlberg,\ngeneral-löjtn. T. Friis, f. d. myntdir. A. Grabe,\ndir. Kjell Hägglöf, dir. öarl A.\nJacobs-son.\n\nVerkst. dir. o. disp.: Carl A. Jacobsson.\n\nFörsäljn.-chef o. chef f.\nförsäljn.-cen-tralen: dir. Per Odéen.\n\nTekn. chef: dir. I. Follin.\n\nEkonomichef: kamrer Carl T. Ericson.\n\nOmbudsm.: f. d. byråchef Nils Holmer.\n\nInköpschef: kapten K. V. Wenström.\n\nPlatschefer: i Västerås: övering. Folke\nPetrén; i Finspång: övering. Y. Zacco;\ni Skultuna: för verkstäderna: övering.\nC. O. Lindqvist; för egendomsförvaltn.:\ndisp. S. Schmidt; i Granefors:\nbruksför-valt. A. Uno Nilsson; i Upplands Väsby:\növering. B. Starck.\n\nAvd.-chefer: Göteborg: M. Koch;\nMalmö: Th. Hagström; Jönköping: A.\nLindeblad; Eskilstuna: A. Modin; Sundsvall:\nE. Åkesson.\n\n^ (Jfr annons efter\nTillverkningsregistret.)\n\n’Svenska Mjölkprodukter AB.,\n\nStockholm.\n\nTillverkar mjölkpulver, mjölkäggvita\nm. m. vid fabriker i Kimstad (Östergötl.\n1.) och Götene (Skarab. l.).\n\nKontor: Stockholm, Wahrendorffsg. 1.\nTelegr.-adr.: Swemilk, Stockholm.\nTelefon: 234570. Postgiro: 156278.\n\nAkt.-kap.: 250,000 kr. Antal\nindustriarb.; 150. Prod.-värde pr år: 14,000,000\nkr. — Bolaget grundat 1938.\n\nStyrelse: bankdir. C. Bert Lilja (ordf.),\ndir. Rolf Forshell, dir. Herbert Takman.\nVerkst. dir.: Rolf Forshell.\nV. verkst. dir.: Sven Sternberg.\nFörsäljn.-chef er: för Sverige: dir.\nBirger Strid; för utlandet: dir. Erland\nEkerman.\n\nInköpschef: disp. Sigurd Kander.\nChef för tekn. avd.: civiling. Bror\nHäll-qvist.\n\nFabrikschefer: i Kimstad: disp. Carl\nColliander; i Götene: disp. Verner Hall.\n\n’Svenska Mått- &amp; Tumstockfabriken,\n\nHultafors.\n\nSnickerifabrik i Hultafors (Älvsb. l.).\nTillverkar längdmått, skolmateriel,\nträdgårdsetiketter m. m. av trä.\n\nTelegr.-adr.: Måttfabriken, Hultafors.\nTelefon. # Borås 95003. Postgiro: 8163.\n\nAntal industriarb.: 55. Tillv.-värde pr\når: 400,000 kr. —- Firman etabl. 1883.\nÄgare o. chef: ing. Joel Kollen.\nDisp.: Hilmer Kollen.\n\n’AB. Svenska Möbelfabrikerna,\n\nBodafors.\n\nFabriker i Bodafors (Jönköp. l.) och\nVärnamo.\n\nTillverkar möbler och inredningar för\naffärslokaler, apotek, banker, biografer,\nkyrkor, butiker, fartyg, hotell, kontor,\nrestauranter, sjukhus, skolor, ämbetsverk,\nprivatvåningar etc.",
    "structured": {
        "firms": [
            {
                "name": "AB. Svenska Metallverken",
                "location": "Västerås",
                "business": "Metallhalvfabrikatverk",
                "products": "Plåt, rör, tråd, linor, lameller, band, stänger, profiler, nitar, muttrar, skruvar, spik, gjutgods och pressat gods av koppar, mässing, zink, bly och aluminium samt andra metaller och legeringar, lagermetaller, kokkärl, mauser-ammunition, plåtslageriarbeten såsom lagerfat och lagertanks, jäskar m. m. i koppar och kopparlegeringar samt aluminium och lättmetall-legeringar, rörspiraler av koppar, pressgjutgods m. m., ävensom tegel; bryter och anrikar zink- och blymalm",
                "contact": {
                    "office": "Västerås",
                    "phone": [
                        "Telefon: »Metallverken»"
                    ],
                    "postgiro": "5026",
                    "head_office": "Västerås",
                    "sales_offices": [
                        {
                            "location": "Stockholm",
                            "phone": "»Metallverken»"
                        }
                    ]
                },
                "financials": {
                    "capital": "24,525,000 kr",
                    "employees": {
                        "industriarb.": 3686
                    }
                },
                "foundation_year": 1907,
                "board": [
                    {
                        "name": "dir. Sten Westerberg",
                        "role": "ordf."
                    }
                ],
                "owners": [],
                "manager": "Carl A. Jacobsson"
            },
            {
                "name": "Svenska Mjölkprodukter AB.",
                "location": "Stockholm",
                "business": "Mjölkpulver och mjölkäggvita",
                "products": "Mjölkpulver, mjölkäggvita m. m.",
                "contact": {
                    "office": "Stockholm",
                    "phone": [
                        "Telefon: 234570"
                    ],
                    "postgiro": "156278"
                },
                "financials": {
                    "capital": "250,000 kr",
                    "employees": 150,
                    "annual_turnover": "14,000,000 kr"
                },
                "foundation_year": 1938,
                "board": [
                    {
                        "name": "bankdir. C. Bert Lilja",
                        "role": "ordf."
                    }
                ],
                "owners": [],
                "manager": "Rolf Forshell",
                "sales_manager": "dir. Birger Strid",
                "managing_director": "Sven Sternberg"
            },
            {
                "name": "Svenska Mått- & Tumstockfabriken",
                "location": "Hultafors",
                "business": "Snickerifabrik",
                "products": "Längdmått, skolmateriel, trädgårdsetiketter m. m. av trä",
                "contact": {
                    "office": "Hultafors",
                    "phone": [
                        "Telefon: # Borås 95003"
                    ],
                    "postgiro": "8163"
                },
                "financials": {
                    "employees": 55,
                    "annual_production_value": "400,000 kr"
                },
                "foundation_year": 1883,
                "owners": [
                    "ing. Joel Kollen"
                ],
                "manager": "Hilmer Kollen"
            },
            {
                "name": "AB. Svenska Möbelfabrikerna",
                "location": "Bodafors",
                "business": "Möbler och inredningar",
                "products": "Möbler och inredningar för affärslokaler, apotek, banker, biografer, kyrkor, butiker, fartyg, hotell, kontor, restauranger, sjukhus, skolor, ämbetsverk, privatvåningar etc.",
                "contact": {
                    "office": "Bodafors"
                },
                "financials": {
                    "annual_turnover": "Not available"
                },
                "foundation_year": "Not available",
                "owners": [],
                "manager": "Not available"
            }
        ]
    }
}