{
    "original": "Åstorp—Åtvidaberg\n\ntal industriarb.: 18. Tillv.-värde pr år:\n200,000 kr. — Bolaget, grundat 1933, äges\nav Lingheds Sågverks AB.\n\nStyrelse: dir. Carl Halvars (ordf.),\nfaktor Sven Hansson, disp. Erik\nHöglund.\n\nVerkst. dir o. disp.: Carl Halvars.\n\nPlatschef: verkm. Erik Hoffman.\n\nAB. Åstorps Mek. Verkstad,\n\nÅstorp.\n\nTillverkar aggregat för tröskverk\nsåsom agnfläktar, självmatare, kullager\nanordningar m. m., hö- och kärvblåsare\nsamt ^ spannmålstransportörer vid\nverkstad i Åstorp (Kristianst. l.).\n\nTelefon: 192 o. 292. Postgiro: 13659.\n\nAkt.-kap.: 56,000 kr. Antal\nindustriarb.: 16. Tillv.-värde pr år: 375,000 kr.\n— Firman etabl. 1916, bolag 1926.\n\nStyrelse o. chefer: fabr. Edvin\nAndersson (ordf.), fabr. Hugo Bengtsson,\nfabr. Gunnar Ohlsson.\n\nFörsäljn.-chef: Oscar H. Olsson.\n\nKontorschef: Walther Larson.\n\n\"Åstorps Tegelbruks AB., Åstorp.\n\nTillverkar murtegel, månghålstegel\nsamt dräneringsrör vid tegelbruk i\nAs-torp (Kristianst. l.). Bolaget driver även\njordbruk.\n\nTelefon: 84. Postgiro: 143811.\nEnsamförsälj.: Byggnadsvaru-AB. Sylvan &amp;\nQvibelius, Hälsingborg, telefon: 20535.\n\nAkt.-kap.: 150,000 kr. Antal\nindustriarb.: 20. Årstillv.: 3 milj. st. tegelvaror.\n\n—\tTegelbruket anlagt 1934 under namn\nVillekulla Tegelbruks AB., nuv. bolag\n1943.\n\nVerkst. dir.: konsul Kjell Friberg\n(Hälsingborg).\n\nTegelmäst.: Axel Qvarnström.\n\nKamrer: Sten-Yngve Åberg.\n\n\"AB. Åsundens Trikåfabrik,\n\nUlricehamn.\n\nTrikåfabrik med färgeri. Tillverkar\ntrikåunderkläder i bomull, silke och ylle.\nVarumärke: »Tre-kan-ten».\n\nTelefon: 275. Postgiro: 26722. Repr.\ni Göteborg: Eric Dahl, S. Hamng. 33,\ntelefon: 136720.\n\nAkt.-kap.: 125,000 kr. Antal\nindustriarb.: 50. Tillv.-värde pr år: 800,000 kr.\n\n—\tBolaget grundat 1917.\n\nStyrelse o. chefer: dir. Erik Pedersen,\ndisp. Hilding Pedersen, disp. Hans\nPedersen.\n\n\"Åtvidabergs Bryggeri AB.,\n\nÅtvidaberg.\n\nTillverkar maltdrycker och läskedrycker\nvid bryggeri i Åtvidaberg (Östergötl. l.).\n\nTelefon: 11. Postgiro: 85895. —\nAkt.-kap.: 50,000 kr. Arb.-antal: 10.\nTillv.-värde pr år: 250,000 kr. — Bolaget\ngrundat 1922.\n\nStyrelse, verkst. dir. o. disp.: Thor\nAnderson.\n\n\"AB. Åtvidabergs Industrier,\n\nÅtvidaberg.\n\nSågverk, träförädlingsfabrik,\nkem.-tekn. fabrik och tryckeri i Åtvidaberg\n(Östergötl. l.).\n\nTillverkar sågade och hyvlade trävaror,\nkontorsmöbler, butiksinredningar,\nauto-mobilkarosserier, lastbilshytter, kylskåp,\nparkettgolv, bonvax, möbelpolityr,\nsystem- och affärstryck samt, genom\ndotterbolaget AB. Facit,\nmultiplikationsmaskiner, genom dotterbolaget AB. Original\nOdhner, multiplikations- och\nadditionsmaskiner och genom dotterbolaget Halda\nAB., skrivmaskiner.\n\nTelegr.-adr. o. telefon: »Industrierna»,\nÅtvidaberg. Postgiro: 23307.\n\nFilialer och ^ försäljningskontor: i\nStockholm, Åtvidabergshuset,\nKungs-trädgårdsg. 20; i Göteborg, ö. Hamng.\n30; i Malmö, österg. 1; i Alingsås, Arvika,\nAvesta, Boden, Bollnäs, Borlänge, Borås,\nEskilstuna,. Falköping, Falun, Gävle,\nHalmstad, Hudiksvall, Hälsingborg,\nHärnösand, Hässleholm, Jönköping, Kalmar,\nKarlshamn, Karlskoga, Karlskrona,\nKarlstad, Katrineholm, Kristianstad,\nKristinehamn, Köping, Landskrona, Lidköping,\nLinköping, Ljungby, Luleå, Lund,\nMariestad, Mora, ^ Motala, Norrköping,\nNyköping, Nässjö, Oskarshamn, Skellefteå,\nSkövde, Sollefteå, Sundbyberg, Sundsvall,\nSödertälje, Trollhättan, Uddevalla,\nUlricehamn, Umeå, Uppsala, Varberg, Visby,\nVänersborg, Värnamo, Västervik,\nVästerås, Växjö, Ystad, Örebro,\nÖrnsköldsvik o. Östersund.\n\nAkt.-kap.: 5,600,000 kr. Antal\nindustriarb.: 545. Antal anställda inom\nkoncernen: 3,750.\n\nFirman grundad 1906 under namn av\nAB. Åtvidabergs Förenade Industrier,\nombildad 1922. Bolaget äger bl. a. AB.\nFacit, Åtvidaberg, Halda AB., Svängsta,\nAB. Original-Odhner, Göteborg, och AB.\nÖverums Bruk.\n\nStyrelse: jur. dr Axel Roos (ordf.),\ndisp. Elof Ericsson (v. ordf.), dir.\nThor-sten P. Ericsson, konsul Oscar\nGullan-der, bankdir. Th. Raaschou, konsul Edw.\nH. Thomée.\n\n644*",
    "structured": {
        "firms": [
            {
                "name": "AB. Åstorps Mek. Verkstad",
                "location": "Åstorp",
                "business": "Tillverkar aggregat för tröskverk s.m. agnfläktar, självmatare, kullager anordningar m.m., hö- och kärvblåsare samt spannmålstransportörer vid verkstad i Åstorp (Kristianst. l.)",
                "contact": {
                    "phone": [
                        "192",
                        "292"
                    ],
                    "postgiro": "13659"
                },
                "financials": {
                    "capital": "56,000 kr",
                    "employees": {
                        "industriarb": 16
                    },
                    "annual_turnover": "375,000 kr"
                },
                "foundation_year": 1916
            },
            {
                "name": "Åstorps Tegelbruks AB.",
                "location": "Åstorp",
                "business": "Tillverkar murtegel, månghålstegel samt dräneringsrör vid tegelbruk i Åstorp (Kristianst. l.)",
                "contact": {
                    "phone": "84",
                    "postgiro": "143811",
                    "sales_offices": [
                        {
                            "location": "Byggnadsvaru-AB. Sylvan & Qvibelius, Hälsingborg",
                            "phone": "20535"
                        }
                    ]
                },
                "financials": {
                    "capital": "150,000 kr",
                    "employees": {
                        "industriarb": 20
                    },
                    "annual_production_value": "3 milj. st. tegelvaror"
                },
                "foundation_year": 1934
            },
            {
                "name": "AB. Åsundens Trikåfabrik",
                "location": "Ulricehamn",
                "business": "Trikåfabrik med färgeri. Tillverkar trikåunderkläder i bomull, silke och ylle. Varumärke: »Tre-kan-ten».",
                "contact": {
                    "phone": "275",
                    "postgiro": "26722",
                    "sales_offices": [
                        {
                            "location": "Eric Dahl, S. Hamng. 33, Göteborg",
                            "phone": "136720"
                        }
                    ]
                },
                "financials": {
                    "capital": "125,000 kr",
                    "employees": {
                        "industriarb": 50
                    },
                    "annual_turnover": "800,000 kr"
                },
                "foundation_year": 1917
            },
            {
                "name": "Åtvidabergs Bryggeri AB.",
                "location": "Åtvidaberg",
                "business": "Tillverkar maltdrycker och läskedrycker vid bryggeri i Åtvidaberg (Östergötl. l.)",
                "contact": {
                    "phone": "11",
                    "postgiro": "85895"
                },
                "financials": {
                    "capital": "50,000 kr",
                    "employees": {
                        "arb-antal": 10
                    },
                    "annual_turnover": "250,000 kr"
                },
                "foundation_year": 1922
            },
            {
                "name": "AB. Åtvidabergs Industrier",
                "location": "Åtvidaberg",
                "business": "Sågverk, träförädlingsfabrik, kem.-tekn. fabrik och tryckeri i Åtvidaberg (Östergötl. l.)",
                "contact": {
                    "phone": "N/A",
                    "telegraph": "»Industrierna», Åtvidaberg",
                    "postgiro": "23307"
                },
                "financials": {
                    "capital": "5,600,000 kr",
                    "employees": {
                        "industriarb": 545
                    },
                    "annual_production_value": "N/A"
                },
                "foundation_year": 1906
            }
        ]
    }
}