{
    "original": "Fabriken—Fabriks\n\nTelefon: 33383. Postgiro: 5428.\nAkt.-kap.: 50,000 kr. Antal\nindustriarb.: 51. Tillv.-värde pr år: 700,000 kr.\n\n—\tFabriken anlagd 1911, nuv. bolag 1926.\nStyrelse: förvalt. Albert Ekman (ordf.),\n\nbankdir. Elof Ekman, dir. Rutger\nSun-din.\n\nVerkst. dir.: Rutger Sundin.\n\n(Jfr annons nr 20.)\n\n*AB. Fabriken Hjelm, Örkelljunga.\n\nTillverkar kostymer, rockar,\ntrench-coats, blazers, byxor, rök- och nattrockar\nm. m. vid fabrik i Hjelmsjö, örkelljunga\n(Kristianst. l.). Varumärke: »Hjelm».\n\nTelegr.-adr.: Hjelm. Klippan. Telefon:\n»Fabriken Hjelm». Postgiro: 23555.\n\nAkt.-kap.: 600,000 kr. Antal\nindustriarb.: 175. Tillv.-värde pr år: 2,900,000 kr.\n\nFirman etabl. 1889 i Hälsingborg\nunder namn Helsingborgs Ulsterfabrik,\növerflyttades till Hjelmsjö 1902, bolag\n1909 under namn AB. Svensk-Engelska\nHerrkonfektionsfabriken Hjelm, nuv.namn\n\n1940.\n\nStyrelse: konsul John\nHjelme-Lund-berg, fru Ada Werin.\n\nVerkst. dir. o. disp.: Eric Löfström.\n\nFabriken Konstblommor,\n\nHälsingborg.\n\nSe Hälsingborgs Sidenindustri o.\nFabriken Konstblommor, Hälsingborg.\n\nAB. Fabriken Malvia, Malmö.\n\nEssensfabrik. Tillverkar vanillin,\nessenser för parfym- och tvålfabriker, för\nbagerier, konditorier, chokladfabriker m. fl.,\nsyntetiska luktämnen, eteriska oljor,\nbak-och krämpulver m. m.\n\nKontor: Maltg. 5. Telegr.-adr.: Malvia,\nMalmö. Telefon: 71690. Postgiro: 38202.\n\n—\tAkt.-kap.: 65,000 kr. Tillv.-värde pr\når: 700,000 kr. — Bolaget grundat 1932.\n\nVerkst. dir.: Harry Malmqvist.\n\nFabriken Odin AB., Stockholm.\n\nMek. verkstad i Nyköping. Tillverkar\nfoder- och sädeshissar, magasins- och\nbyggnadshissar, handhissar, gödsel- och\nfodertransportörer, halm- och\nsädesfläk-tar, spannmålselevatorer, hängbanor,\nslakthusbanor, släpskopeanläggningar m. fl.\ntransportanordningar. Varunamn: »Odin».\n\nKontor: Stockholm, Norrlandsg. 16.\nTelegr.-adr.: Nido, Stockholm. Telefon:\n112113 o. 112116. Postgiro: 59463.\n\nAkt.-kap.: 200,000 kr. Antal\nindustriarb.: 35. — Firman etabl. 1918, bolag\n\n1941.\n\nVerkst. dir.: ing. Gösta Hedin.\n\nAB. Fabriken Orion, Lindesberg.\n\nMek. verkstad i Lindesberg (Örebro l.)*\nTillverkar hand- och fotpumpar med\nsnabbkopplingsnipplar, cykel- och\nmotorcykelstöd samt smörj- och oljesprutor.\nVarumärke: »Orion».\n\nTelefon: 86 o. 726. Postgiro: 28321. —\nAkt.-kap.: 75,000 kr. Antal industriarb.:\n35. Tillv.-värde pr år: 500,000 kr. —\nFirman etabl. 1898, bolag 1944.\n\nVerkst. dir.: Erik-Gustaf Wirén.\n\n*\tFabriken Rurik, Karlshamn.\n\nMek. verkstad. Tillverkar\ntvättmaskiner, vridmaskiner och manglar.\n\nTelefon: 372. Postgiro: 6598. — Antal\nindustriarb.: 15. — Firman etabl. 1898L\n\nÄgare o. chef: ing. P. Georg Carlson.\n\nKassör: E. Lindfors.\n\nAB. Fabriken Saturnus, Malmö.\n\nKem.-teknisk fabrik. Tillverkar\nessenser och extrakter för likör- och\nläskedrycksberedning, bak- och krämpulver\nför bagerier, eteriska oljor,\nlivsmedelsfärger, fruktvinaigre m. m.\n\nKontor: Lantmannag. 20. Telegr.-adr..\no. telefon: Saturnus, Malmö. Postgiro:\n38390. Avd.-kontor: Stockholm,\nNybrokajen 7, telefon: 205343; Göteborg,\nHed-åsg. 5, telefon: 180475.\n\nAkt.-kap.: 301,500 kr. Antal\nindustriarb.: 80. Tillv.-värde pr år: 2,250,000 kr.\n— Firman etabl. 1893, bolag 1905.\n\nStyrelse: fru Eva Liepe (ordf.), jur.\nkand. Nils-Håkan Håkansson, fil. lie.\nHarry Runnqvist.\n\nVerkst. dir.: N.-H. Håkansson.\n\nFabrihschef: G. F. Dieterle.\n\n*\tFabriken Tomten, Alex. Lagerman\n\nJsr AB., Stockholm.\n\nKem.-teknisk fabrik. Tillverkar\ntvättpulver (i»Tomtetvätt»), skurpulver\n(»Tomteskur»), putsmedel (»Häxan»),\nflug-fångare, tvål, raktvål, rakkräm och\nrakbalsam (»Silhouette»), skokräm, bak- och\npuddingpulver, majspreparat\n(»Mamsa-na»), vanillinsocker, lemonadpulver\n(»Tomtebrus») m. m.\n\nKontor: Alvik, Stockholm; postadr.:\nStockholm 1. Telegr.-adr. o. telefon:\nKe-mabolagen, Stockholm.\n\nAkt.-kap.: 3,000,000 kr. — Firman,\netabl. 1897, bolag 1911, ingår i\n»Kema-Bolagen», Stockholm.\n\nStyrelse: grossh. Robert Ljunglöf\n(ordf.),* fil. dr Harald Nordenson, disp.\nNils Westerdahl.\n\nVerkst. dir.: Tor Olsson.",
    "structured": {
        "1": {
            "name": "AB. Fabriken Hjelm, Örkelljunga",
            "location": "Hjelmsjö, Örkelljunga (Kristianst. l.)",
            "business": "Tillverkning av kostymer, rockar, trench-coats, blazers, byxor, rök- och nattrockar m.m.",
            "products": "Varumärke: »Hjelm».",
            "contact": {
                "office": "Maltg. 5",
                "phone": [
                    "33383"
                ],
                "postgiro": "23555"
            },
            "financials": {
                "capital": "600,000 kr",
                "employees": {
                    "industriarb.": 175
                },
                "annual_turnover": "2,900,000 kr"
            },
            "foundation_year": 1889,
            "current_name_year": 1940,
            "board": [
                {
                    "name": "John Hjelme-Lundberg",
                    "role": "Konsul"
                },
                {
                    "name": "Ada Werin",
                    "role": "Fru"
                }
            ],
            "director": "Eric Löfström"
        },
        "2": {
            "name": "AB. Fabriken Malvia, Malmö",
            "business": "Essensfabrik. Tillverkning av vanillin, essenser för parfym- och tvålfabriker, syntetiska luktämnen, eteriska oljor, bak-och krämpulver m.m.",
            "contact": {
                "office": "Maltg. 5",
                "phone": [
                    "71690"
                ],
                "postgiro": "38202"
            },
            "financials": {
                "capital": "65,000 kr",
                "annual_turnover": "700,000 kr"
            },
            "foundation_year": 1932,
            "director": "Harry Malmqvist"
        },
        "3": {
            "name": "Fabriken Odin AB., Stockholm",
            "location": "Nyköping",
            "business": "Tillverkning av foder- och sädeshissar, magasins- och byggnadshissar, gödsel- och fodertransportörer, halm- och sädesfläktar m.m.",
            "products": "Varunamn: »Odin».",
            "contact": {
                "office": "Stockholm, Norrlandsg. 16",
                "phone": [
                    "112113",
                    "112116"
                ],
                "postgiro": "59463"
            },
            "financials": {
                "capital": "200,000 kr",
                "employees": {
                    "industriarb.": 35
                },
                "annual_turnover": "N/A"
            },
            "foundation_year": 1918,
            "corporation_year": 1941,
            "director": "Ing. Gösta Hedin"
        },
        "4": {
            "name": "AB. Fabriken Orion, Lindesberg",
            "location": "Lindesberg (Örebro l.)",
            "business": "Tillverkning av hand- och fotpumpar med snabbkopplingsnipplar, cykel- och motorcykelstöd samt smörj- och oljesprutor m.m.",
            "products": "Varumärke: »Orion».",
            "contact": {
                "phone": [
                    "86",
                    "726"
                ],
                "postgiro": "28321"
            },
            "financials": {
                "capital": "75,000 kr",
                "employees": {
                    "industriarb.": 35
                },
                "annual_turnover": "500,000 kr"
            },
            "foundation_year": 1898,
            "corporation_year": 1944,
            "director": "Erik-Gustaf Wirén"
        },
        "5": {
            "name": "Fabriken Rurik, Karlshamn",
            "business": "Tillverkning av tvättmaskiner, vridmaskiner och manglar.",
            "contact": {
                "phone": [
                    "372"
                ],
                "postgiro": "6598"
            },
            "financials": {
                "employees": {
                    "industriarb.": 15
                }
            },
            "foundation_year": 1898,
            "director": "Ing. P. Georg Carlson"
        },
        "6": {
            "name": "AB. Fabriken Saturnus, Malmö",
            "business": "Tillverkning av essenser och extrakter för likör- och läskedrycksberedning, bak- och krämpulver för bagerier, eteriska oljor, livsmedelsfärger m.m.",
            "contact": {
                "office": "Lantmannag. 20",
                "phone": [
                    "N/A"
                ],
                "postgiro": "38390"
            },
            "financials": {
                "capital": "301,500 kr",
                "employees": {
                    "industriarb.": 80
                },
                "annual_turnover": "2,250,000 kr"
            },
            "foundation_year": 1893,
            "corporation_year": 1905,
            "board": [
                {
                    "name": "Eva Liepe",
                    "role": "Fru"
                },
                {
                    "name": "Nils-Håkan Håkansson",
                    "role": "Jur. kand."
                },
                {
                    "name": "Harry Runnqvist",
                    "role": "Fil. lie."
                }
            ],
            "director": "N.-H. Håkansson"
        },
        "7": {
            "name": "Fabriken Tomten, Alex. Lagerman Jsr AB., Stockholm",
            "business": "Tillverkning av tvättpulver, skurpulver, putsmedel, flugfångare, tvål, raktvål, rakkräm och rakbalsam, skokräm, bak- och puddingpulver, majspreparat, vanillinsocker, lemonadpulver m.m.",
            "contact": {
                "office": "Alvik, Stockholm",
                "phone": [
                    "N/A"
                ],
                "postgiro": "N/A"
            },
            "financials": {
                "capital": "3,000,000 kr"
            },
            "foundation_year": 1897,
            "corporation_year": 1911,
            "director": "Tor Olsson"
        }
    }
}