{
    "original": "Nyström—Nässjö\n\nT. Nyströms Ramindustri,\n\nGöteborg.\n\nTillverkar fotografiramar,\nornaments-ramar samt spegelramar. Varumärke:\n»T. N. R.»\n\nKontor: Fabriksg. 20. Telefon: 154216.\nPostgiro: 25539.\n\nAntal industriarb.: 15. Tillv.-värde pr\når: 125,000 kr. — Firman etabl. 1924.\n\nÄgare o. chef: Torsten Nyström.\n\n\"Nyviks Trähusfabrik, Alnö.\n\nSe Sunds AB., Sundsvall.\n\n\"AB. Näfveqvarns Bruk, Nävekvarn.\n\nMek. verkstad och gjuteri vid\nNävekvarn (Södermanl. l.).\n\nTillverkar spisar, kaminer, kokkärl,\nstekpannor, handvinschar,\nskruvdomkraf-ter, trädgårdsvältar och trädgårdsmöbler,\nmaskinformat gjutgods för\nmaskinfabriker m. m. Bolaget idkar jämväl jordbruk\noch skogshantering.\n\nHuvudkontor: Nävekvarn. Telegr.-adr.:\nNäfveqvarn, Nyköping. Telefon:\nNyköping 21. Postgiro: 26913. Avd.-kontor:\nStockholm, Majorsg. 9, telefon: 614500\no. 614580.\n\nAkt.-kap.: 550,000 kr. Antal\nindustriarb.: 220. Tillv.-värde pr år: 2,600,000 kr.\n\nBruket anlagt år 1623, bolaget grundat\n1917.\n\nStyrelse: adv. Matts Fallenius (ordf.),\nbankdir. Gustaf Hydén, herr Ivar Hök,\nherr Nils Hök, disp. Th. Lunden.\n\nVerkst. dir. o. disp.: Th. Lundén.\n\nKontorschef: G. Grette.\n\nDriftsing.: Y. Engström.\n\n\"Näldens Ullspinneri AB., Nälden.\n\nUllspinneri, ylleväveri och färgeri i\nNälden (Jämtl. l.). Tillverkar ullgarn,\nyllevävnader och filtar.\n\nTelefon: 40. Postgiro: 72321.\n\nAkt.-kap.: 240,000 kr. Antal\nindustriarb.: 70. Tillv.-värde pr år: 1,580,000 kr.\n— Bolaget grundat 1896.\n\nStyrelse: disp. Alg. Gunnarsson (ordf.),\ngrossh. E. F. Herlitz, disp. Axel G.\nJohansson.\n\nVerkst. dir. o. disp.: Alg. Gunnarsson.\n\nAB. Näldens Åkdonsfabrik,\n\nNälden.\n\nMöbel- och snickerifabrik i Nälden\n(Jämtl. l.). Tillverkar möbler,\nbyggnadssnickerier och butiksinredningar.\n\nTelegr.-adr.: Åkdonsfabriken, Nälden.\nTelefon: 24. Postgiro: 22252. — Akt.-\n\nkap.: 100,000 kr. Antal industriarb.: 32.\n\n—\tFirman etabl. 1900, bolag 1907.\nDisp.: Magnus Gunnarsson.\n\nNärkes Torf AB., Mosas.\n\nTorvströfabriker i Mosås och\nHjortkvarn (båda i Örebro l.), Fagersanna\n(Skarab. l.) samt i Nässjö (Jönköp. l.).\nTillverkar torvströ och torvmull.\n\nKontor: Mosås. Telefon: Örebro 75010.\nPostgiro: 3422.\n\nAkt.-kap.: 112,500 kr. Tillv.-värde pr\når: 400,000 kr. — Bolaget grundat 1905.\n\nStyrelse: disp. Viktor Dalen, dir.\nHerman Olson, fru G. Staaf.\n\nVerkst. dir.: Herman Olson (Sthlm).\nDisp.: Viktor Dalen.\n\n\"Näs Bruk, Näsbruk.\nSe Horndals Jernverks AB., Horndal.\n\n\"Näs Lådfabrik, Korsnäs.\nSe Kopparfors AB., Ockelbo.\n\n\"Näsby Tegelbruk, 8tallarholmen.\n\nSe AB. Mälardalens Tegelbruk,\nStockholm.\n\n\"Nässjö Bryggeri AB., Nässjö.\n\nBryggerier i Nässjö, Sävsjö och\nVetlanda (Vithala bryggeri), (samtl. i\nJönköp. l.). Tillverkar malt, malt- och\nläskedrycker.\n\nTelefon: »Bryggeribolaget». Postgiro:\n131199.^ — Akt.-kap.: 840,000 kr. Antal\nindustriarb.: 40. — Bolaget grundat. 1885.\n\nStyrelse: dir. Fredrik Anderzon, stud.\nNils Gäre, ing. Wilhelm Johanson.\nVerkst. dir.: F. Anderzon.\n\n\"AB. Nässjö Butiksinredningar,\n\nNässjö.\n\nSnickerifabrik i Fredriksdal (Jönköp.\n1.). Tillverkar butiksinredningar.\nSpecialiteter: kasettdiskar och skyltmontrar.\n\nKontor: Nässjö. Telegr.-adr.: Näbu,\nNässjö. Telefon: 340. Postgiro: 141470.\nAvd.-kontor: Stockholm, Atlasg. 2,\ntelefon: 304756.\n\nAkt.-kap.: 30,000 kr. Antal\nindustriarb.: 20. Tillv.-värde pr år: 500,000 kr.\n\n—\tBolaget grundat 1938.\n\nStyrelse o. verkst. dir.: Nils Hedström.\n\nNässjö Industri AB., Nässjö.\n\nMek. verkstad i Nässjö (Jönköp. l.).\nTillverkar snickeri- och bagerimaskiner.\nVarunamn: »Nian».\n\nTelegr.-adr.: Nian, Nässjö. Telefon:\n159. Postgiro: 271110. — Akt.-kap.:",
    "structured": {
        "firms": [
            {
                "name": "T. Nyströms Ramindustri",
                "location": "Göteborg",
                "business": "Tillverkar fotografiramar, ornaments-ramar samt spegelramar",
                "contact": {
                    "office": "Fabriksg. 20",
                    "phone": [
                        "154216"
                    ],
                    "postgiro": "25539"
                },
                "financials": {
                    "employees": {
                        "industriarb.": 15
                    },
                    "annual_turnover": "125,000 kr",
                    "annual_production_value": "125,000 kr"
                },
                "foundation_year": 1924,
                "director": "Torsten Nyström"
            },
            {
                "name": "AB. Näfveqvarns Bruk",
                "location": "Nävekvarn (Södermanl. l.)",
                "business": "Mek. verkstad och gjuteri",
                "products": "Tillverkar spisar, kaminer, kokkärl, stekpannor, handvinschar, skruvdomkraf-ter, trädgårdsvältar och trädgårdsmöbler",
                "contact": {
                    "office": "Huvudkontor: Nävekvarn",
                    "phone": [
                        "Nyköping 21"
                    ],
                    "postgiro": "26913",
                    "sales_offices": [
                        {
                            "location": "Stockholm",
                            "phone": "614500"
                        }
                    ]
                },
                "financials": {
                    "capital": "550,000 kr",
                    "employees": {
                        "industriarb.": 220
                    },
                    "annual_turnover": "2,600,000 kr"
                },
                "foundation_year": 1917,
                "board": [
                    {
                        "name": "adv. Matts Fallenius",
                        "role": "ordf."
                    },
                    {
                        "name": "bankdir. Gustaf Hydén",
                        "role": ""
                    },
                    {
                        "name": "herr Ivar Hök",
                        "role": ""
                    },
                    {
                        "name": "herr Nils Hök",
                        "role": ""
                    },
                    {
                        "name": "disp. Th. Lunden",
                        "role": ""
                    }
                ],
                "director": "Th. Lundén",
                "manager": "G. Grette",
                "sales_manager": "G. Grette"
            },
            {
                "name": "Näldens Ullspinneri AB.",
                "location": "Nälden (Jämtl. l.)",
                "business": "Tillverkar ullgarn, yllevävnader och filtar",
                "contact": {
                    "phone": [
                        "40"
                    ],
                    "postgiro": "72321"
                },
                "financials": {
                    "capital": "240,000 kr",
                    "employees": {
                        "industriarb.": 70
                    },
                    "annual_turnover": "1,580,000 kr"
                },
                "foundation_year": 1896,
                "board": [
                    {
                        "name": "disp. Alg. Gunnarsson",
                        "role": "ordf."
                    },
                    {
                        "name": "grossh. E. F. Herlitz",
                        "role": ""
                    },
                    {
                        "name": "disp. Axel G. Johansson",
                        "role": ""
                    }
                ],
                "director": "Alg. Gunnarsson"
            },
            {
                "name": "AB. Näldens Åkdonsfabrik",
                "location": "Nälden (Jämtl. l.)",
                "business": "Tillverkar möbler, byggnadssnickerier och butiksinredningar",
                "contact": {
                    "phone": [
                        "24"
                    ],
                    "postgiro": "22252"
                },
                "financials": {
                    "capital": "100,000 kr",
                    "employees": {
                        "industriarb.": 32
                    }
                },
                "foundation_year": 1900,
                "current_name_year": 1907,
                "director": "Magnus Gunnarsson"
            },
            {
                "name": "Närkes Torf AB.",
                "location": "Mosås (Örebro l.)",
                "business": "Tillverkar torvströ och torvmull",
                "contact": {
                    "office": "Kontor: Mosås",
                    "phone": [
                        "Örebro 75010"
                    ],
                    "postgiro": "3422"
                },
                "financials": {
                    "capital": "112,500 kr",
                    "annual_turnover": "400,000 kr"
                },
                "foundation_year": 1905,
                "board": [
                    {
                        "name": "disp. Viktor Dalen",
                        "role": ""
                    },
                    {
                        "name": "dir. Herman Olson",
                        "role": ""
                    },
                    {
                        "name": "fru G. Staaf",
                        "role": ""
                    }
                ],
                "director": "Herman Olson"
            },
            {
                "name": "Nässjö Bryggeri AB.",
                "location": "Nässjö, Sävsjö, and Vetlanda",
                "business": "Tillverkar malt, malt- och läskedrycker"
            },
            {
                "name": "AB. Nässjö Butiksinredningar",
                "location": "Fredriksdal (Jönköp. l.)",
                "business": "Tillverkar butiksinredningar",
                "products": "Specialiteter: kasettdiskar och skyltmontrar",
                "contact": {
                    "office": "Kontor: Nässjö",
                    "phone": [
                        "340"
                    ],
                    "postgiro": "141470",
                    "sales_offices": [
                        {
                            "location": "Stockholm",
                            "phone": "304756"
                        }
                    ]
                },
                "financials": {
                    "capital": "30,000 kr",
                    "employees": {
                        "industriarb.": 20
                    },
                    "annual_turnover": "500,000 kr"
                },
                "foundation_year": 1938,
                "director": "Nils Hedström"
            },
            {
                "name": "Nässjö Industri AB.",
                "location": "Nässjö (Jönköp. l.)",
                "business": "Tillverkar snickeri- och bagerimaskiner",
                "products": "Varunamn: »Nian»",
                "contact": {
                    "office": "Telegr.-adr.: Nian, Nässjö",
                    "phone": [
                        "159"
                    ],
                    "postgiro": "271110"
                }
            }
        ]
    }
}