{
    "original": "Fabriken—Fabriks\n\nFabriken Vimi, Karl Pehrsson,\n\nT rönninge.\n\nTillverkar malt och vacuumtorkade\ngrönsaker vid fabrik i Trönninge\n(Hallands l.). Specialitet: torkade sopprötter.\n\nTelefon: 15. Postgiro: 33498. — Antal\nindustriarb.: 10. Tillv.-värde pr år:\n100,000 kr. — Maltfabriken anlagd 1897,\ngrönsakstorkeriet 1935.\n\nÄgare o. chef: fabr. Karl Pehrsson.\n\n* Fabriken Zig-Zag, Malmköping.\nSe Nya Fabriken Zig-Zag, Malmköping.\n\nFabriks AB. Blokk, Eskilstuna.\n\nSmidesfabrik. Tillverkar fönster och\ndörrar, portar samt byggnadsbeslag.\nVarumärke: »Blokk».\n\nTelefon: 34808. Postgiro: 170489. —\nAkt.-kap.: 40,000 kr. Antal industriarb.:\n15. Tillv.-värde pr år: 250,000 kr. —\nBolaget grundat 1940.\n\nVerkst. dir.: Sigurd Lewerentz.\n\n* Fabriks AB. Bröderna Alström,\n\nBorås.\n\nKonfektionsfabrik. Tillverkar herr- och\ngosskjortor samt herr- och gosskläder.\nVarumärken: »Fabanex» o. »Leopard».\n\nTelefon: 13196 o. 14567. Postgiro:\n37429.\n\nAkt.-kap.: 120,000 kr. Antal\nindustriarb.: 115. Tillv.-värde pr år: 1,800,000 kr.\n— Bolaget grundat 1929.\n\nStyrelse: dir. Artur Alström, dir. Eric\nAlström, köpm. Stig Svensson.\n\nVerkst. direktörer: Artur Alström o.\nEric Alström.\n\n*Fabriks AB. Drev &amp; Trassel,\n\nGöteborg.\n\nTillverkar byggnadsdrev, trassel,\ntäck-vädd, madrasser och täcken.\n\nKontor: Tuvevägen, Hisingen;\npost-adr.: Göteborg 8. Telegr.-adr.: Fabeha,\nGöteborg. Telefon: 223493 o. 221460.\nPostgiro: 42026. Repr. i Stockholm: AB.\nHjalmar Söderström, V. Trädgårdsg.\n11 A, telefon: 112572.\n\nAkt.-kap.: 65,000 kr. Antal\nindustriarb.: 20. Tillv.-värde pr år: 700,000 kr. —\nFirman etabl. 1928.\n\nStyrelse o. verkst. dir.: O. Haitkin.\n\nFabriks AB. Ekå, Markaryd.\n\nTillverkar slipduk och slippapper för\nträvaru-, metall-, läder- och skoindustri\netc. såsom flinta, korund, granat,\nkisel-karbid och smärgel på duk och papper,\nfiberrondeller m. m. vid fabrik i\nMarkaryd (Kronob. l.).\n\nTelegr.-adr.: Ekåslip, Markaryd.\nTelefon: »Ekå». Postgiro: 20850. — Akt.-kap.:\n160,000 kr. Antal industriarb.: 25.\nTillv.-värde pr år: 700,000 kr. — Bolaget\ngrundat 1928.\n\nVerkst. dir. o. disp.: Ernst O.\nAndersson.\n\nFabriks AB. Elias, Stockholm.\n\nKem. tekn. fabrik. Tillverkar\ncham-poneringspulver, sårsalvor, djursalva med\nkloramin, örttéer, tabletter m. m.\nVarumärken: Syster Elias o. Pastor Seb.\nKneipp.\n\nKontor: Kvarng. 3 B. Telegr.-adr.:\nElias Fabriker, Stockholm. Telefon:\n411028—29. Postgiro: 3600.\n\nAkt.-kap.: 60,000 kr. Antal\nindustriarb.: 35. Tillv.-värde pr år: 500,000 kr. —\nBolaget grundat 1922.\n\nVerkst. dir.: Bo Holmberg.\n\nFabriks AB. Forslund &amp; Co.,\n\nSkellefteå.\n\nMek. verkstad i Skellefteå (Västerb. l.).\nTillverkar hydrauliska tippanordningar\nför lastautomobiler, garagedomkrafter\nsamt verkstadspressar.\n\nPostadr.: Postfack 73, Skellefteå.\nTelegr.-adr.: Forslundarna, Skellefteå.\nTelefon: 12211. Postgiro: 66467. - Akt.-kap.:\n102,000 kr. Antal industriarb,: 60.\nTillv.-värde pr år: 1,100,000 kr. — Bolaget\ngrundat 1945.\n\nVerkst. dir.: Johan Forslund.\n\nKamrer: Artur Lundgren.\n\nFabriks AB. Hageltorns,\n\nHälsingborg.\n\nKonfektionsfabrik. Tillverkar\ndamunderkläder.\n\nTelefon: 20195. Postgiro: 70326.\n\nAkt.-kap.: 100,000 kr. Driften f. n.\ninställd. — Firman etabl. 1931, bolag 1941.\n\nVerkst. dir.: Bror Hageltorn.\n\n* Fabriks AB. H aidataxametern,\n\nHalmstad.\n\nSe Verkstads-AB. Haldex, Halmstad.",
    "structured": {
        "1": {
            "name": "Fabriken Vimi",
            "location": "Trönninge",
            "business": "Tillverkar malt och vacuumtorkade grönsaker",
            "products": "Specialitet: torkade sopprötter",
            "contact": {
                "office": "Fabrik i Trönninge (Hallands l.)",
                "phone": [
                    "15"
                ],
                "postgiro": "33498"
            },
            "financials": {
                "capital": "Ej tillgängligt",
                "employees": {
                    "industriarbete": 10
                },
                "annual_turnover": "100,000 kr",
                "annual_production_value": "100,000 kr"
            },
            "foundation_year": 1897,
            "owner": "Karl Pehrsson"
        },
        "2": {
            "name": "Fabriken Zig-Zag",
            "location": "Malmköping",
            "business": "Ej tillgängligt",
            "original_name": "Nya Fabriken Zig-Zag",
            "financials": {
                "capital": "Ej tillgängligt",
                "employees": {
                    "industriarbete": "Ej tillgängligt"
                },
                "annual_turnover": "Ej tillgängligt",
                "annual_production_value": "Ej tillgängligt"
            }
        },
        "3": {
            "name": "Fabriks AB. Blokk",
            "location": "Eskilstuna",
            "business": "Smidesfabrik",
            "products": "Tillverkar fönster och dörrar, portar samt byggnadsbeslag",
            "financials": {
                "capital": "40,000 kr",
                "employees": {
                    "industriarbete": 15
                },
                "annual_turnover": "250,000 kr",
                "annual_production_value": "250,000 kr"
            },
            "corporation_year": 1940,
            "board": [
                {
                    "name": "Sigurd Lewerentz",
                    "role": "Verkst. dir."
                }
            ]
        },
        "4": {
            "name": "Fabriks AB. Bröderna Alström",
            "location": "Borås",
            "business": "Konfektionsfabrik",
            "products": "Tillverkar herr- och gosskjortor samt herr- och gosskläder",
            "financials": {
                "capital": "120,000 kr",
                "employees": {
                    "industriarbete": 115
                },
                "annual_turnover": "1,800,000 kr",
                "annual_production_value": "1,800,000 kr"
            },
            "corporation_year": 1929,
            "board": [
                {
                    "name": "Artur Alström",
                    "role": "Styrelse"
                },
                {
                    "name": "Eric Alström",
                    "role": "Styrelse"
                },
                {
                    "name": "Stig Svensson",
                    "role": "Köpm."
                }
            ],
            "director": "Artur Alström",
            "managing_director": "Eric Alström"
        },
        "5": {
            "name": "Fabriks AB. Drev & Trassel",
            "location": "Göteborg",
            "business": "Tillverkar byggnadsdrev, trassel, täck-vädd, madrasser och täcken",
            "contact": {
                "office": "Tuvevägen, Hisingen",
                "phone": [
                    "223493",
                    "221460"
                ],
                "postgiro": "42026",
                "telegraph": "Fabeha, Göteborg"
            },
            "financials": {
                "capital": "65,000 kr",
                "employees": {
                    "industriarbete": 20
                },
                "annual_turnover": "700,000 kr",
                "annual_production_value": "700,000 kr"
            },
            "foundation_year": 1928,
            "director": "O. Haitkin"
        },
        "6": {
            "name": "Fabriks AB. Ekå",
            "location": "Markaryd",
            "business": "Tillverkar slipduk och slippapper",
            "products": "För trävaru-, metall-, läder- och skoindustri etc.",
            "contact": {
                "telegraph": "Ekåslip, Markaryd",
                "phone": "»Ekå»",
                "postgiro": "20850"
            },
            "financials": {
                "capital": "160,000 kr",
                "employees": {
                    "industriarbete": 25
                },
                "annual_turnover": "700,000 kr",
                "annual_production_value": "700,000 kr"
            },
            "corporation_year": 1928,
            "director": "Ernst O. Andersson"
        },
        "7": {
            "name": "Fabriks AB. Elias",
            "location": "Stockholm",
            "business": "Kem. tekn. fabrik",
            "products": "Tillverkar champoneringspulver, sårsalvor, djursalva med kloramin, örttéer, tabletter m. m.",
            "financials": {
                "capital": "60,000 kr",
                "employees": {
                    "industriarbete": 35
                },
                "annual_turnover": "500,000 kr",
                "annual_production_value": "500,000 kr"
            },
            "corporation_year": 1922,
            "director": "Bo Holmberg"
        },
        "8": {
            "name": "Fabriks AB. Forslund & Co.",
            "location": "Skellefteå",
            "business": "Mek. verkstad",
            "products": "Tillverkar hydrauliska tippanordningar för lastautomobiler, garagedomkrafter samt verkstadspressar",
            "contact": {
                "office": "Skellefteå (Västerb. l.)",
                "phone": [
                    "12211"
                ],
                "postgiro": "66467"
            },
            "financials": {
                "capital": "102,000 kr",
                "employees": {
                    "industriarbete": 60
                },
                "annual_turnover": "1,100,000 kr",
                "annual_production_value": "1,100,000 kr"
            },
            "corporation_year": 1945,
            "director": "Johan Forslund",
            "manager": "Artur Lundgren"
        },
        "9": {
            "name": "Fabriks AB. Hageltorns",
            "location": "Hälsingborg",
            "business": "Konfektionsfabrik",
            "products": "Tillverkar damunderkläder",
            "contact": {
                "phone": "20195",
                "postgiro": "70326"
            },
            "financials": {
                "capital": "100,000 kr",
                "employees": {
                    "industriarbete": "Ej tillgängligt"
                }
            },
            "manager": "Bror Hageltorn"
        },
        "10": {
            "name": "Fabriks AB. Haidataxametern",
            "location": "Halmstad",
            "business": "Se Verkstads-AB. Haldex, Halmstad"
        }
    }
}