{
    "original": "Hudiksvall—Hultberg\n\nStyrelse: folkskoll. Anders Andréasson,\nombudsm. Oskar Bengtsson, ombudsm.\nFritjof Ekman, arkitekt Sven Wallander,\nbyggm. Hugo Åberg.\n\nDisp.: Valter Elmgren.\n\n\"Hudiksvalls Bryggeri AB.,\n\nHudiksvall.\n\nTillverkar malt- och läskedrycker.\n\nTelegr.-adr.: Bryggeribolaget,\nHudiksvall. Telefon: 13 o. 302. Postgiro: 29890.\n\nAkt.-kap.: 180,000 kr. Antal\nindustriarb.: 25. Tillv.-värde pr år: 940,000 kr.\n— Firman etabl. 1855, bolag 1886.\n\nStyrelse: dir. Gunnar Dahlquist, disp.\nNils G. Dahlquist, bankdir. M. Westbérg.\n\nVerkst. dir.: Gunnar Dahlquist.\n\nDisp. o. v. verkst dir.: Nils G.\nDahlquist.\n\nBryggmåst.: Gösta Olsson.\n\n\"Hudiksvalls Lådfabrik, Hudiksvall.\n\nLådfabrik och sågverk i Djuped,\nHudiksvall. Tillverkar lådämnen och lådor,\nsågade ^ trävaror samt fanéremballage.\nSpecialitet: bryggerilådor.\n\nTelefon: 649. Postgiro: 160265. —\nAntal industriarb.: 35, varav vid\nlådfabriken 25. Tillv.-värde pr år: 250,000\nkr. — Firman etabl. 1930.\n\nÄgare o. chef: fabr. Orwall Larsson.\n\nHugin Kassaregister AB.,\n\nStockholm.\n\nMek. verkstad. Tillverkar\nbutiksmaskiner, hushållsdammsugare och större\ndammsugare för industriella behov.\nVarumärke: »Hugin». Firman driver även\nförsäljning av kassakontrollapparater\nm. m.\n\nKontor: Stadsgården 10. Telegr.-adr.:\nHuginmaskin, Stockholm. Telefon:\n440505. Postgiro: 150699. Avd.-kontor:\nGöteborg, Centrumhuset, ö. Larmg. 17—\n21, telefon: 134556 o. 134979; Malmö,\nFöreningsg. 45, telefon: 19781.\n\nAkt.-kap.: 100,000 kr. Antal anställda:\n104. rrrr Bolaget, grundat 1936, äges av\nKooperativa Förbundet.\n\nStyrelse: dir. Albin Johansson (ordf.),\nfil. lic. Mauritz Bonow, dir. Hj.\nDeger-stedt, dir. Hugo Edstam, dir. Eric\nOlsson, dir. G. Osvald, dir. Ernst Persson.\n\nVerkst. dir.: Eric Olsson.\n\nAB. Hugoson &amp; Roberts,\n\nHälsingborg.\n\nEssens- och extraktfabrik. Tillverkar\nessenser, extrakter och sockerkulör.\n\nTelegr.-adr.: Hurob, Hälsingborg.\nTelefon: 14173. Postgiro: 34770. — Akt.-kap.:\n100,000 kr. Antal industriarb.: 5. —\nBolaget grundat 1930.\n\nVerkst. dir.: ing. Carl Hugoson.\n\n\"Huleviks Fabriker, Earlshamn.\n\nTräullsfabrik och sågverk vid Hulevik\n(Kronob. l.). Tillverkar träull, sågade\noch hyvlade trävaror samt träullsplattor.\n\nKontor: Karlshamn. Telegr.-adr.:\nSagonilsson, Karlshamn. Telefon: 98. Post-\n\nfiro: 30451. — Antal industriarb.: 45.\n\nrstillv.: 4,000 ton träull. — Fabriken\nanlagd 1913.\n\nÄgare: fabr. Jöns Nilsson, fabr. Anton\nNilsson o. fabr. Hugo Klämfeldt.\n\nDisp.: Oscar A. Johansson.\n\n\"Hulta Tegelbruks AB., Värnamo.\n\nTegelbruk vid Hulta, Berghem (Älvsb.\n1.). Tillverkar mur-, fasad- och\nrevete-ringstegel, taktegel samt tegelrör.\n\nHuvudkontor: Värnamo. Telefon:\nVärnamo 10098 o. 10638. Postgiro: 92910.\nFörsäljn.-kontor: Borås, telefon: 17170;\nGöteborg, telefon: 131368.\n\nAkt.-kap.: 100,000 kr. Antal\nindustriarb.: 85. Årstillv.: 8 milj. st. tegelvaror.\n— Bolaget grundat 1891.\n\nDisp.: Gunnar Thilén.\n\nKamrer: Lage Thilén.\n\n\"Hultafors Snickerifabrik, Hultafors.\n\nSe Svenska Mått- &amp; Tumstockfabriken,\nHultafors.\n\n\"AB. Hultagårds Snickerifabrik,\n\nHultagard.\n\nTillverkar byggnadssnickerier samt\nsågade och hyvlade trävaror vid fabrik i\nHultagård (Jönköp. l.).\n\nTelefon: 1. Postgiro: 283878. —\nAkt.-kap.: 30,000 kr. Arb.-antal: 13.\nTillv.-värde pr år: 120,000 kr. — Bolaget\ngrundat 1934.\n\nStyrelse: disp. Carl E. Johansson\n(ordf.), godsäg. Anders J. Carlsson,\nverkm. Birger Carlsson, maskinarb.\nLennart Carlsson, maskinist Tage Carlsson.\n\nDisp.: C. E. Johansson.\n\nClaes Hultberg AB., Stockholm.\n\nSnickeri- och möbelfabrik. Tillverkar\nramlister och ramar, speglar, konstmöbler\nm. m., utför förgylleri- och\nlackeringsarbeten samt rums- och butiksinredningar.\nBolaget driver även konsthandelsrörelse.",
    "structured": {
        "1": {
            "name": "Hudiksvalls Bryggeri AB.",
            "location": "Hudiksvall",
            "business": "Tillverkar malt- och läskedrycker",
            "contact": {
                "office": "Hudiksvall",
                "phone": [
                    "13",
                    "302"
                ],
                "postgiro": "29890"
            },
            "financials": {
                "capital": "180,000 kr",
                "employees": {
                    "industriarb": 25
                },
                "annual_turnover": "940,000 kr",
                "annual_production_value": "940,000 kr"
            },
            "foundation_year": 1855,
            "corporation_year": 1886,
            "board": [
                {
                    "name": "Gunnar Dahlquist",
                    "role": "Verkst. dir."
                },
                {
                    "name": "Nils G. Dahlquist",
                    "role": "Disp. o. v. verkst dir."
                }
            ]
        },
        "2": {
            "name": "Hudiksvalls Lådfabrik",
            "location": "Hudiksvall (Djuped)",
            "business": "Tillverkar lådämnen och lådor, sågade trävaror samt fanéremballage",
            "contact": {
                "office": "Hudiksvall",
                "phone": [
                    "649"
                ],
                "postgiro": "160265"
            },
            "financials": {
                "employees": {
                    "industriarb": 35
                },
                "annual_production_value": "250,000 kr"
            },
            "foundation_year": 1930,
            "owner": "fabr. Orwall Larsson"
        },
        "3": {
            "name": "Hugin Kassaregister AB.",
            "location": "Stockholm",
            "business": "Tillverkar butiksmaskiner, hushållsdammsugare och större dammsugare för industriella behov",
            "contact": {
                "office": "Stadsgården 10",
                "phone": [
                    "440505"
                ],
                "postgiro": "150699",
                "sales_offices": [
                    {
                        "location": "Göteborg",
                        "phone": "134556 o. 134979"
                    },
                    {
                        "location": "Malmö",
                        "phone": "19781"
                    }
                ]
            },
            "financials": {
                "capital": "100,000 kr",
                "employees": {
                    "anställda": 104
                }
            },
            "foundation_year": 1936,
            "owners": [
                "Kooperativa Förbundet"
            ],
            "board": [
                {
                    "name": "Albin Johansson",
                    "role": "Styrelseordförande"
                },
                {
                    "name": "Mauritz Bonow",
                    "role": "Fil. lic."
                },
                {
                    "name": "Hj. Deger-stedt",
                    "role": "Dir."
                },
                {
                    "name": "Hugo Edstam",
                    "role": "Dir."
                },
                {
                    "name": "Eric Olsson",
                    "role": "Dir."
                },
                {
                    "name": "G. Osvald",
                    "role": "Dir."
                },
                {
                    "name": "Ernst Persson",
                    "role": "Dir."
                }
            ],
            "director": "Eric Olsson"
        },
        "4": {
            "name": "AB. Hugoson & Roberts",
            "location": "Hälsingborg",
            "business": "Tillverkar essenser, extrakter och sockerkulör",
            "contact": {
                "office": "Hälsingborg",
                "phone": [
                    "14173"
                ],
                "postgiro": "34770"
            },
            "financials": {
                "capital": "100,000 kr",
                "employees": {
                    "industriarb": 5
                }
            },
            "foundation_year": 1930,
            "owner": [
                "fabr. Jöns Nilsson",
                "fabr. Anton Nilsson",
                "fabr. Hugo Klämfeldt"
            ],
            "director": "ing. Carl Hugoson"
        },
        "5": {
            "name": "Hulta Tegelbruks AB.",
            "location": "Värnamo (Hulta, Berghem)",
            "business": "Tillverkar mur-, fasad- och reveteringstegel, taktegel samt tegelrör",
            "contact": {
                "office": "Värnamo",
                "phone": [
                    "Värnamo 10098 o. 10638"
                ],
                "postgiro": "92910",
                "sales_offices": [
                    {
                        "location": "Borås",
                        "phone": "17170"
                    },
                    {
                        "location": "Göteborg",
                        "phone": "131368"
                    }
                ]
            },
            "financials": {
                "capital": "100,000 kr",
                "employees": {
                    "industriarb": 85
                },
                "annual_production_value": "8 milj. st. tegelvaror"
            },
            "foundation_year": 1891,
            "board": [
                {
                    "name": "Gunnar Thilén",
                    "role": "Disp."
                },
                {
                    "name": "Lage Thilén",
                    "role": "Kamrer"
                }
            ]
        }
    }
}