{
    "original": "Eau—Eccoverken\n\n* utmärker till Sveriges Industriförbund anslutna företag.\n\n*Eau de Cologne &amp; Parfymerifabriken\n4711, Ferd. MUlhens, Sundbyberg.\n\nTillverkar eau de Cologne, parfymer,\nhårmedel, rakmedel och kosmetiska\npreparat. Varumärken: »4711», »Tosca»,\n»Sir» (rakmedel), »Sparta» (hudkräm),\n»Captol» m. fl.\n\nTelegr.-adr.: »4711» o. »Tosca»,\nStockholm. Telefon: 282580. Postgiro: 4711.\n\nAntal industriarb.: 35. — Firman\netabl. 1890.\n\nDirektion: dir. N. E. Ternberg o.\nför-säljn.-chef Eric E. Boström.\n\n*Ebbamåla Cjuteri &amp; Mek. Verkstad,\n\nHovmansbygd.\n\nMek. verkstad och gjuteri vid\nHovmansbygd (Blekinge l.). Tillverkar\nträullsma-skiner samt träullspaekpressar.\n\nTelefon: 8. Postgiro: 168043. — Antal\nindustriarb.: 20. Tillv.-värde pr år:\n170,000 kr. — Firman etabl. 1886.\n\nÄgare: fabr. Ansgarius Sandberg,\nciviling. August A. Sandberg, fröken J.\nSandberg o. fröken A. Sandberg.\n\n*AB. Ebe, Malmö.\n\nChokladfabrik. Tillverkar choklad och\nkarameller.\n\nKontor: Fabriksg. 3. Telefon: 25139 o.\n78718. Postgiro: 24537. — Akt.-kap.:\n50,000 kr. Antal industriarb.: 20.\nTillv.-värde pr år: 500,000 kr. — Bolaget\ngrundat 1914.\n\nStyrelse: fru Ellen Andersson, disp.\nCurt Berwill, fru E. N. Schoug.\n\nVerkst. dir. o. disp.: Curt Berwill.\n\nEbe-Verken AB., Huskvarna.\n\nMek. verkstad, gjuteri och\nemalje-ringsverk vid Ebbes Bruk, Huskvarna.\n\nTillverkar varmluftsapparater,\nkokspisar, kaminer, isolerade strykjärn,\ndric-keshoar samt gjutgods, spec.\ncylinder-gjutgods, sanitetsgods, hushålls- och\nhan-delsgjutgods.\n\nTelegr.-adr. o. telefon: »Ebeverken»,\nHuskvarna. Postgiro: 13651.\n\nAkt.-kap.: 205,000 kr. Antal\nindustriarb.: 80. Tillv.-värde pr år: 1,200,000 kr.\n\nBruket anlagt 1870, bolaget grundat\n1914 under namn Ebbes Bruks Nya\nArrende AB., nuv. namn 1937.\n\nStyrelse: ing. Oskar Bergström, ing.\nLars Bergström, ing. Valter Bergström.\n\nVerkst. dir.: Oskar Bergström.\n\nVerkstadsing.: Valter Bergström.\n\nInköp o. försäljning: G. Granquist.\n\nKamrer: M. Sten.\n\nAB. Ebå Lädervarufabrik,\n\nAnderstorp.\n\nTillverkar skinn- och\nlädervaruartik-lar vid fabrik i Anderstorp (Jönköp. l.).\nSpecialiteter: plånböcker och\nportmonnäer.\n\nTelefon: 105. Postgiro: 73743. —\nAkt.-kap.: 15,000 kr. Antal industriarb.: 18.\nTillv.-värde pr år: 500,000 kr. — Bolaget\ngrundat 1936.\n\nDisponenter: Eric Carlson, Åke\nÅsgär-de o. Pontus Åsgärde.\n\nE. B. Ö:s Metallgjuteri AB.,\n\nEskilstuna.\n\nTillverkar kokillgjutet\naluminiumgjut-gods för byggnads-, husgeråds- och\nverkstadsindustrierna.\n\nTelefon: 31937. Postgiro: 74630. —\nAkt.-kap.: 35,000 kr. Antal industriarb.:\n25. Tillv.-värde pr år: 400,000 kr. —\nFirman etabl. 1922, bolag 1944.\n\nVerkst. direktörer: fabr. J. R. Eldin\no. fabr. Gunnar östlund.\n\nAB. Eccoverken, Skara.\n\nMek. verkstad. Tillverkar\nfärgsprut-apparater och luftkompressorer.\nVarumärke: »Ecco».\n\nTelegr.-adr. o. telefon: »Eccoverken»,\nSkara. Postgiro: 73481.\nEnsamförsäljare AB. Atlas Diesel, Stockholm 1.\n\nAkt.-kap.: 100,000 kr. Antal\nindustriarb.: 150. — Firman etabl. 1931, bolag\n1941.\n\nStyrelse: dir. E. Järnåker (ordf.), dir.\nH. Pyk, dir. Walter Wehtje.\n\nVerkst. dir.: E. Järnåker.\n\nVerkstadschef: ing. C.-O. Pernblad.\n\n113*",
    "structured": {
        "1": {
            "name": "Eau de Cologne & Parfymerifabriken 4711 Ferd. MUlhens",
            "location": "Sundbyberg",
            "business": "Tillverkar eau de Cologne, parfymer, hårmedel, rakmedel och kosmetiska preparat.",
            "contact": {
                "office": "Eau de Cologne & Parfymerifabriken 4711 Ferd. MUlhens, Sundbyberg",
                "phone": [
                    "282580"
                ],
                "postgiro": "4711",
                "telegraph": "4711, TOSCA, Stockholm"
            },
            "financials": {
                "capital": "Etablerad 1890"
            }
        },
        "2": {
            "name": "Ebbamåla Cjuteri & Mek. Verkstad",
            "location": "Hovmansbygd, Blekinge",
            "business": "Tillverkar träullsmaskiner samt träullspackpressar.",
            "contact": {
                "phone": [
                    "8"
                ],
                "postgiro": "168043"
            },
            "financials": {
                "capital": "Etablerad 1886",
                "annual_production_value": "170,000kr"
            },
            "owners": [
                "fabr. Ansgarius Sandberg",
                "civiling. August A. Sandberg",
                "fröken J. Sandberg",
                "fröken A. Sandberg"
            ]
        },
        "3": {
            "name": "AB. Ebe",
            "location": "Malmö",
            "business": "Tillverkar choklad och karameller.",
            "contact": {
                "office": "Fabriksg. 3",
                "phone": [
                    "25139",
                    "78718"
                ],
                "postgiro": "24537"
            },
            "financials": {
                "capital": "50,000 kr",
                "annual_production_value": "500,000 kr",
                "foundation_year": 1914
            },
            "board": [
                {
                    "name": "fru Ellen Andersson",
                    "role": ""
                },
                {
                    "name": "disp. Curt Berwill",
                    "role": ""
                },
                {
                    "name": "fru E. N. Schoug",
                    "role": ""
                }
            ],
            "director": "Curt Berwill"
        },
        "4": {
            "name": "Ebe-Verken AB.",
            "location": "Huskvarna",
            "business": "Tillverkar varmluftsapparater, kokspisar, kaminer, isolerade strykjärn, dryckeshoar samt gjutgods.",
            "contact": {
                "office": "Ebe-Verken AB., Ebbes Bruk, Huskvarna",
                "phone": "Ebeverken",
                "postgiro": "13651"
            },
            "financials": {
                "capital": "205,000 kr",
                "annual_production_value": "1,200,000 kr"
            },
            "board": [
                {
                    "name": "ing. Oskar Bergström",
                    "role": ""
                },
                {
                    "name": "ing. Lars Bergström",
                    "role": ""
                },
                {
                    "name": "ing. Valter Bergström",
                    "role": ""
                }
            ],
            "director": "Oskar Bergström",
            "managing_director": "Oskar Bergström",
            "sales_manager": "G. Granquist"
        },
        "5": {
            "name": "AB. Ebå Lädervarufabrik",
            "location": "Anderstorp, Jönköp. l.",
            "business": "Tillverkar skinn- och lädervaruartiklar.",
            "contact": {
                "phone": [
                    "105"
                ],
                "postgiro": "73743"
            },
            "financials": {
                "capital": "15,000 kr",
                "annual_production_value": "500,000 kr",
                "foundation_year": 1936
            },
            "owners": [
                "Eric Carlson",
                "Åke Åsgärde",
                "Pontus Åsgärde"
            ]
        },
        "6": {
            "name": "E. B. Ö:s Metallgjuteri AB.",
            "location": "Eskilstuna",
            "business": "Tillverkar kokillgjutet aluminiumgjutgods för byggnads-, husgeråds- och verkstadsindustrierna.",
            "contact": {
                "phone": [
                    "31937"
                ],
                "postgiro": "74630"
            },
            "financials": {
                "capital": "35,000 kr",
                "annual_production_value": "400,000 kr",
                "corporation_year": 1944
            },
            "director": "fabr. J. R. Eldin"
        },
        "7": {
            "name": "AB. Eccoverken",
            "location": "Skara",
            "business": "Tillverkar färgsprutapparater och luftkompressorer.",
            "contact": {
                "office": "Eccoverken, Skara",
                "phone": [
                    "Eccoverken"
                ],
                "postgiro": "73481"
            },
            "financials": {
                "capital": "100,000 kr",
                "employees": {
                    "Antal industriarb.": 150
                },
                "corporation_year": 1941
            },
            "board": [
                {
                    "name": "dir. E. Järnåker",
                    "role": "ordf."
                },
                {
                    "name": "dir. H. Pyk",
                    "role": ""
                },
                {
                    "name": "dir. Walter Wehtje",
                    "role": ""
                }
            ],
            "director": "E. Järnåker",
            "sales_manager": "C.-O. Pernblad"
        }
    }
}