{
    "original": "Essäs—Essinge\n\n\"AB. Essäs, Göteborg.\nSe AB. Geveko, Göteborg.\n\n\"Esselte AB., Stockholm.\n\nTryckeri, reproduktionsanstalt för\nklichéer och litografi m. m., notstickeri,\nbokbinderi, kontorsbokfabrik, ask- och\nkartongfabrik, kartografisk anstalt, fabrik\nför kortsystem och paragonartiklar samt\nstämpelfabrik.\n\nUtför boktryck, djuptryck, ljustryck,\nlitografi- och offsettryck, koppartryck,\nparagontryck, klichéer,\nfärgfotografering och bokbinderiarbeten samt\ntillverkar album, kontorsböcker, askar,\nkartonger, kortregister, kortpärmar, kortaskar,\nkautschukstämplar m. m., s. k.\ncolumbus-kartonger och wellpapp. Avd. för\nbokföringssystem såsom Acme, Taylorix,\nParagon och Viscard samt avd. för\nreklamartiklar och för blankettjänst.\nBolaget driver jämväl förlagsverksamhet.\n\nKontor: Vasag. 16. Telefon: »Esselte».\nPostgiro: 1221. — Bolaget, grundat 1933,\när anslutet till AB. Sveriges Litografiska\nTryckerier (se detta bolag).\n\nStyrelse: dir. Knut Östberg (ordf.),\ndisp. Gustaf Dahlbäck, disp. Oskar\nDahlström, disp. Gösta Smith, ryttm. Åke G.\nWickman, major C. G. Åhlund.\n\nVerkst. dir.: Knut Östberg.\n\nV. verkst. dir.: Åke G. Wickman.\n\nDisponenter: Gustaf Dahlbäck, ö. G.\nÅhlund, Gösta Smith o. Oskar Dahlström.\n\n(Jfr annons nr 88.)\n\n\"Esseltes Cöteborgsindustrier AB.,\n\nGöteborg.\n\nTill bolaget, som tillhör AB. Sveriges\nLitografiska Tryckerier, Stockholm, äro\nföljande företag anslutna:\n\nAB. Borås Tryckeri &amp; Kartongfabrik,\nBorås.\n\nHugo Brusewitz AB., Göteborg.\n\nAB. Esselte Kartonnage i Göteborg,\nGöteborg.\n\nGustaf Melins AB., Göteborg.\n\nWezäta-Göteborgslitografen AB.,\nGöteborg.\n\nAB. Konsumenttjänst, Stockholm.\n\nBolaget utför genom anslutna firmor\nboktryck, ståltryck, litografi och\noffsettryck, klichéer och bokbinderiarbeten\nsamt tillverkar album, askar,\nburkemballage, kartonger, ringböcker, biblar och\npsalmböcker samt diverse\nkontorsförnödenheter (se i övrigt betr. specialiteter\nresp. bolag). Bolaget driver även\nförlagsrörelse under namn »Svenska\nHushållsböcker».\n\nKontor: Göteborg, Lasarettsg. 4—6.\nTelegr.-adr. o. telefon: Esselte, Göteborg.\nPostgiro: 46361. — Bolaget grundat 1940.\nStyrelse o. verkst. dir.: Nils J. Åhlund.\nDisponenter: Aug. Sandberg, Bruno\nZachrisson o. Sam Widenfelt.\nKontorschef: Nils G. Englund.\n\n\"AB. Esselte Kartonnage i Göteborg,\n\nGöteborg.\n\nKartonnagefabrik i Mölndal. Tillverkar\nsom specialitet hopfällbara, dekorerade\nkartonger och burkemballage.\n\nKontor: Mölndal, Krokslättsg. 7;\npost-adr.: Göteborg 14. Telegr.-adr.:\nKartonnage, Göteborg. Telefon: 164061, 164146\no. »Esselte». Postgiro: 40607.\nAvd.-kon-tor: Stockholm, Drottningg. 20, telefon:\n113317; Malmö, Hamng. 4, telefon: 34098.\n— Bolaget är anslutet till Esseltes\nGöteborgsindustrier AB., Göteborg (se detta\nbolag).\n\nStyrelse: dir. Nils J. Åhlund (ordf.),\ndisp. Sam Widenfelt.\n\nVerkst. dir.: Nils J. Åhlund.\n\nFabrikschef: ing. Bengt Hedborg.\n\nFörsäljn.-chef: P. A. Atterbom.\n\nKontorschef: Nils G. Englund.\n\n\"AB. Essge-Konfektion, Göteborg.\n\nTillverkar herrkostymer och\nherröverplagg samt damdräkter.\n\nKontor: Järntorgsg. 12—14. Telefon:\n111312. Postgiro: 43164. — Akt.-kap.:\n250,000 kr. Antal industriarb.: 85. —\nFirman etabl. 1936, bolag 1942.\n\nStyrelse: disp. Benno Garellick, dir.\nSalomon Garellick.\n\nVerkst. dir.: S. Garellick.\n\nDisp.: B. Garellick.\n\nEssinge Bruks- och Fabriks AB.,\n\nStockholm.\n\nPapp- och pappersbruk å Stora\nEssingen, Stockholm. Tillverkar\nbyggnadspapp, lumppapp, råpapp för\nimpregne-ring, asbest- och annan isoleringspapp\nsamt omslagspapper.\n\nKontor: Norrlandsg. 2. Telefon: 208243.\nPostgiro: 50078.\n\nAkt.-kap.: 150,000 kr. Antal\nindustriarb.: 14. Årstillv.: 800 ton papp o.\npapper. — Bolaget grundat 1937.\n\nStyrelse: disp. Algot S. Eklund, dir.\nOskar A. Eklund, dir. Leander Tell.\n\nVerkst. dir.: Leander Tell.\n\n139*",
    "structured": {
        "1": {
            "name": "Esselte AB",
            "location": "Stockholm",
            "business": "Tryckeri, reproduktionsanstalt för klichéer och litografi m. m., notstickeri, bokbinderi, kontorsbokfabrik, ask- och kartongfabrik, kartografisk anstalt, fabrik för kortsystem och paragonartiklar samt stämpelfabrik. Utför boktryck, djuptryck, ljustryck, litografi- och offsettryck, koppartryck, paragontryck, klichéer, färgfotografering och bokbinderiarbeten samt tillverkar album, kontorsböcker, askar, kartonger, kortregister, kortpärmar, kortaskar, kautschukstämplar m. m., s. k. columbus-kartonger och wellpapp. Avd. för bokföringssystem såsom Acme, Taylorix, Paragon och Viscard samt avd. för reklamartiklar och för blankettjänst. Bolaget driver jämväl förlagsverksamhet.",
            "products": "Boktryck, djuptryck, ljustryck, litografi- och offsettryck, koppartryck, paragontryck, klichéer, färgfotografering och bokbinderiarbeten, album, kontorsböcker, askar, kartonger, kortregister, kortpärmar, kortaskar, kautschukstämplar, columbus-kartonger, wellpapp, bokföringssystem (Acme, Taylorix, Paragon, Viscard), reklamartiklar, blankettjänst, förlagsverksamhet",
            "contact": {
                "office": "Vasag. 16",
                "phone": [
                    "Esselte"
                ],
                "postgiro": "1221"
            },
            "financials": {
                "capital": "Not available",
                "annual_turnover": "Not available",
                "annual_production_value": "Not available"
            },
            "foundation_year": 1933,
            "board": [
                {
                    "name": "Knut Östberg",
                    "role": "Ordförande"
                },
                {
                    "name": "Gustaf Dahlbäck",
                    "role": "Disponent"
                },
                {
                    "name": "Oskar Dahlström",
                    "role": "Disponent"
                },
                {
                    "name": "Gösta Smith",
                    "role": "Disponent"
                },
                {
                    "name": "Åke G. Wickman",
                    "role": "Ryttmästare"
                },
                {
                    "name": "C. G. Åhlund",
                    "role": "Major"
                }
            ],
            "director": "Knut Östberg",
            "managing_director": "Knut Östberg",
            "original_name": "Not available"
        },
        "2": {
            "name": "Essge-Konfektion",
            "location": "Göteborg",
            "business": "Tillverkar herrkostymer och herröverplagg samt damdräkter.",
            "contact": {
                "office": "Järntorgsg. 12—14",
                "phone": [
                    "111312"
                ],
                "postgiro": "43164"
            },
            "financials": {
                "capital": "250,000 kr",
                "annual_turnover": "Not available",
                "annual_production_value": "Not available"
            },
            "foundation_year": 1936
        },
        "3": {
            "name": "Essinge Bruks- och Fabriks AB",
            "location": "Stockholm",
            "business": "Papp- och pappersbruk å Stora Essingen, Stockholm. Tillverkar byggnadspapp, lumppapp, råpapp för impregnering, asbest- och annan isoleringspapp samt omslagspapper.",
            "contact": {
                "office": "Norrlandsg. 2",
                "phone": [
                    "208243"
                ],
                "postgiro": "50078"
            },
            "financials": {
                "capital": "150,000 kr",
                "annual_turnover": "Not available",
                "annual_production_value": "800 ton papp o. papper"
            },
            "foundation_year": 1937
        }
    }
}