{
    "original": "B e r g vall—Berg v i k\n\nAB. Axel K. Bergvall &amp; Söner,\n\nNorrköping.\n\nTrikåfabrik, vaddfabrik och blekeri.\nTillverkar militär-, arbets- och\nsport-tröjor, jackor, jumpers och baddräkter\n(varumärke: »Bergiana»), förbandsbomull\nsamt silfilter till mjölksilar (varumärke:\n»Argus-Rex»).\n\nTelegr.-adr.: Bergvalls, Norrköping.\nTelefon: 20005 o. 25510. Postgiro: 11037.\n\nAkt.-kap.: 400,000 kr. Antal\nindustriarb.: 100. Tillv.-värde pr år: 2,000,000 kr.\n\n—\tFirman etabl. 1877,# bolag 1913.\nStyrelse: disp. Ludvig Bergvall (ordf.),\n\nfabr. Ivar Bergvall, kapten Karl-Axel\nBergvall.\n\nVerkst. dir.: Ludvig Bergvall.\n\nE. Bergwall, Värnamo.\n\nTräförädlingsfabrik. Tillverkar som\nsjDecialitet, tvättklämmor samt trämjöl.\n\nTelegr.-adr.: Bergvall, Värnamo.\nTelefon: 66.\n\nAntal industriarb.: 60. Tillv.-värde pr\når: 900,000 kr. — Firman etabl. 1930\nefter övertagandet av f. d. AB.\nTrämanufaktur.\n\nÄgare o. chef: disp. E. Bergwall.\nAB. Magn. Bergvall, Stockholm.\n\nSkrivboksfabrik. Tillverkar skriv- och\nritböcker samt utför accidenstryck\nhuvudsakligen för eget behov. Firman\ndriver även bok- och\nmusikförlagsverksamhet samt pappershandel.\n\nKontor: Drottningg. 108. Telefon:\n335156. Postgiro: 1414. — Akt.-kap.:\n700,000 kr. Antal industriarb.: 15.\nTillv.-värde pr år: 127,000 kr. — Firman etabl.\n1900, bolag 1918.\n\nStyrelse: folkskollärare K.-G. Rosberg\n(ordf.), dir. Magn. Bergvall, lektor E.\nHjalmar, lektor Ivar M. Holm,\növerlä-rare F. Lindskog.\n\nVerkst. dir.: Magn. Bergvall.\nKontorschef: fru Irma Rickenhoff.\n\nBergvalla Metallfabrik, Gnosjö.\n\nTillverkar brand- och rörarmatur,\nkranar, markisbeslag m. m. vid fabrik i\nGnosjö (Jönköp. l.).\n\nTelefon: 70. Postgiro: 13142. —\nArb.-antal: 16. Tillv.-värde pr år: 180,000 kr.\n\n—\tFirman etabl. 1929.\n\nÄgare o. chefer: fabr. K. J. Nevrén o.\nfabr. H. Norle.\n\nBergverks AB. Freja, Stockholm.\n\nGruvdrift vid Koskullskulle (Norrbott.\n1.). Bryter järnmalm (magnetit).\n\nKontor: Stockholm, Strandvägen 3.\nTelegr.-adr.: Frejamalm, Stockholm.\nTelefon: 670135. Inköps- och gruvkontor:\nKoskullskulle. Speditionskontor: Luleå.\n\nAkt.-kap.: 2,600,000 kr. Antal industrin\narb.: 250. — Bolaget grundat 1897.\n\nStyrelse: adv. Sune Wetter (ordf.),\nkabinettskammarh. Rolf v. Heidenstam?\nf. d. kommerserådet Ragnar Sohlman.\n\nVerkst. dir.: Sune Wetter.\n\nDisp.: bergsing. Erik Almin.\n\n*\tBergverks AB. Vulcanus,\n\nBlötberget.\n\nJärngruvor i Blötbergets och\nFred-mundbergets gruvfält samt\nanrikningsverk och mek. verkstad vid Blötberget\n(samti. i Kopparb. l.). Bryter och\nanrikar malmer samt tillverkar magnetiska\nseparatorer och malmskiljare.\n\nTelegr.-adr.: Vulcanus, Ludvika.\nTelefon: Blötberget 37022—23. Postgiro:\n167034.\n\nAkt.-kap.: 3,750,000 kr. Antal\nindustriarb.: 310. — Bolaget grundat 1900.\n\nStyrelse: dir. H. Hennemann (ordf.),\ndisp. John A. Hedlund, dir. C. J. P.\nHoedemakers, kamrer Eric Håkansson,\ndir. Paul O. Wickman.\n\nVerkst. dir.: H. Hennemann.\n\nDisp.: John A. Hedlund.\n\nKamrer: E. Håkansson.\n\nByggnadsing.: Sten Larson.\n\n*\tBergvik och Ala Nya AB.,\n\nSöderhamn.\n\nSågverk och hyvleri vid Ala,\nsulfitfabrik och sulfitspritfabrik vid Bergvik,\nsulfatfabrik och destillationsverk vid\nSandarne, kraftverk i Höljebro, Bergvik\noch Vifors (samtl. i Gävleb. l.).\n\nTillverkar sågade och hyvlade trävaror,\nträkol, sulfit- och sulfatcellulosa,\nsulfitsprit, sanotin (renad terpentin), såpa och\ntvål samt driver skogsbruk.\n\nHuvudkontor: Söderhamn.\nTelegr.-adr.: Bergvik, Söderhamn. Telefon:\nSöderhamn 1490. Postgiro: 163730.\nEnsam-försälj. för cellulosa: Svenska Cellulosa\nAB., Stockholm, V:a Trädgårdsg. 15.\nTelefon: »Cellulosabolaget».\n\nAkt.-kap.: 28,125,000 kr. Antal\nindustriarb.: 900. Årstillv.: 18,000 stds sågade\noch hyvlade trävaror, 54,000 ton\nsulfitcellulosa, 56,000 ton sulfatcellulosa.\n3,000,000 1. 100 % sulfitsprit, 2,000 ton\nsanotin (renad terpentin) samt 8,000 ton\n?åpa och tvål.",
    "structured": {
        "1": {
            "name": "Bergvall—Bergvik AB. Axel K. Bergvall & Söner",
            "location": "Norrköping",
            "business": "Trikåfabrik, vaddfabrik och blekeri",
            "products": "Tillverkar militär-, arbets- och sport-tröjor, jackor, jumpers och baddräkter (varumärke: »Bergiana»), förbandsbomull samt silfilter till mjölksilar (varumärke: »Argus-Rex»).",
            "contact": {
                "office": "Norrköping",
                "phone": [
                    "20005",
                    "25510"
                ],
                "postgiro": "11037",
                "telegraph": "Bergvalls, Norrköping"
            },
            "financials": {
                "capital": "400,000 kr",
                "employees": {
                    "industriarb": 100
                },
                "annual_turnover": "2,000,000 kr"
            },
            "foundation_year": 1877,
            "corporation_year": 1913,
            "board": [
                {
                    "name": "disp. Ludvig Bergvall",
                    "role": "ordf."
                },
                {
                    "name": "fabr. Ivar Bergvall",
                    "role": null
                },
                {
                    "name": "kapten Karl-Axel Bergvall",
                    "role": null
                }
            ],
            "director": "Ludvig Bergvall"
        },
        "2": {
            "name": "E. Bergwall",
            "location": "Värnamo",
            "business": "Träförädlingsfabrik",
            "products": "Tillverkar som specialist, tvättklämmor samt trämjöl.",
            "contact": {
                "office": "Värnamo",
                "phone": [
                    "66"
                ]
            },
            "financials": {
                "employees": {
                    "industriarb": 60
                },
                "annual_turnover": "900,000 kr"
            },
            "foundation_year": 1930,
            "board": null,
            "owners": [
                "disp. E. Bergwall"
            ],
            "manager": "E. Bergwall"
        },
        "3": {
            "name": "AB. Magn. Bergvall",
            "location": "Stockholm",
            "business": "Skrivboksfabrik",
            "products": "Tillverkar skriv- och ritböcker samt utför accidenstryck huvudsakligen för eget behov. Firman driver även bok- och musikförlagsverksamhet samt pappershandel.",
            "contact": {
                "office": "Drottningg. 108",
                "phone": [
                    "335156"
                ],
                "postgiro": "1414"
            },
            "financials": {
                "capital": "700,000 kr",
                "employees": {
                    "industriarb": 15
                },
                "annual_turnover": "127,000 kr"
            },
            "foundation_year": 1900,
            "corporation_year": 1918,
            "board": [
                {
                    "name": "folkskollärare K.-G. Rosberg",
                    "role": "ordf."
                },
                {
                    "name": "dir. Magn. Bergvall",
                    "role": null
                },
                {
                    "name": "lektor E. Hjalmar",
                    "role": null
                },
                {
                    "name": "lektor Ivar M. Holm",
                    "role": null
                },
                {
                    "name": "överlä-rare F. Lindskog",
                    "role": null
                }
            ],
            "director": "Magn. Bergvall",
            "manager": "fru Irma Rickenhoff"
        },
        "4": {
            "name": "Bergvalla Metallfabrik",
            "location": "Gnosjö",
            "business": "Tillverkar brand- och rörarmatur, kranar, markisbeslag m. m.",
            "contact": {
                "phone": [
                    "70"
                ],
                "postgiro": "13142"
            },
            "financials": {
                "employees": {
                    "Arb.-antal": 16
                },
                "annual_turnover": "180,000 kr"
            },
            "foundation_year": 1929,
            "owners": [
                "fabr. K. J. Nevrén",
                "fabr. H. Norle"
            ]
        },
        "5": {
            "name": "Bergverks AB. Freja",
            "location": "Stockholm",
            "business": "Gruvdrift",
            "products": "Bryter järnmalm (magnetit).",
            "contact": {
                "office": "Stockholm, Strandvägen 3",
                "phone": [
                    "670135"
                ],
                "speditionskontor": "Luleå",
                "telegraph": "Frejamalm, Stockholm"
            },
            "financials": {
                "capital": "2,600,000 kr",
                "employees": {
                    "industrin arb": 250
                }
            },
            "foundation_year": 1897,
            "board": [
                {
                    "name": "adv. Sune Wetter",
                    "role": "ordf."
                },
                {
                    "name": "kabinettskammarh. Rolf v. Heidenstam",
                    "role": null
                },
                {
                    "name": "f. d. kommerserådet Ragnar Sohlman",
                    "role": null
                }
            ],
            "director": "Sune Wetter",
            "manager": "bergsing. Erik Almin"
        },
        "6": {
            "name": "Bergverks AB. Vulcanus",
            "location": "Blötberget",
            "business": "Järngruvor",
            "products": "Bryter och anrikar malmer samt tillverkar magnetiska separatorer och malmskiljare.",
            "contact": {
                "telegraph": "Vulcanus, Ludvika",
                "phone": [
                    "Blötberget 37022—23"
                ],
                "postgiro": "167034"
            },
            "financials": {
                "capital": "3,750,000 kr",
                "employees": {
                    "industriarb": 310
                }
            },
            "foundation_year": 1900,
            "board": [
                {
                    "name": "dir. H. Hennemann",
                    "role": "ordf."
                },
                {
                    "name": "disp. John A. Hedlund",
                    "role": null
                },
                {
                    "name": "dir. C. J. P. Hoedemakers",
                    "role": null
                },
                {
                    "name": "kamrer Eric Håkansson",
                    "role": null
                },
                {
                    "name": "dir. Paul O. Wickman",
                    "role": null
                }
            ],
            "director": "H. Hennemann",
            "manager": "John A. Hedlund",
            "managing_director": "E. Håkansson",
            "sales_manager": "Sten Larson"
        },
        "7": {
            "name": "Bergvik och Ala Nya AB.",
            "location": "Söderhamn",
            "business": "Sågverk och hyvleri",
            "products": "Tillverkar sågade och hyvlade trävaror, träkol, sulfit- och sulfatcellulosa, sulfitsprit, sanotin (renad terpentin), såpa och tvål samt driver skogsbruk.",
            "contact": {
                "telegraph": "Bergvik, Söderhamn",
                "phone": [
                    "Söderhamn 1490"
                ],
                "postgiro": "163730"
            },
            "financials": {
                "capital": "28,125,000 kr",
                "employees": {
                    "industriarb": 900
                },
                "annual_turnover": "18,000 stds sågade och hyvlade trävaror, 54,000 ton sulfitcellulosa, 56,000 ton sulfatcellulosa, 3,000,000 1. 100 % sulfitsprit, 2,000 ton sanotin (renad terpentin), 8,000 ton ?åpa och tvål"
            }
        }
    }
}