{
    "original": "Bechman—Bendor\n\nMattol, Puriii, Rivalin, Sanetta, Santex,\nTerpinidin, Thermogéne, Webe,\nWebe-tonex, Vera, Webesan, Wrinkle.\n\nKontor: Lövholmsgränd 12; postadr.:\nBox 468, Stockholm 1. Telegr.-adr.:\nWil-becker, Stockholm, Telefon:\n»Wilhelm-becker». Postgiro: 584.\n\nBolaget driver jämväl detaljhandel\ngenom trettioen egna minutaffärer i\nStockholm.\n\nAkt.-kap.: 4,400,000 kr. Antal\nindustriarb.: 350. Tillv.-värde pr år: 8,000,000\nkr. — Firman etabl. 1864, bolag 1906.\n\nStyrelse: apot. Ilj. A:n Te^ch (ordf.),\ndir. Gösta Browall, grossh. Robert\nLjunglöf, rådman A. Stålbrand, dir. Walter\nWehtje.\n\nV erkst. dir.: Gösta Browall.\n\nEkonomichef o. dir.-assist.: K. A.\nÖström.\n\nFörsäljningschefer: Rune Berggren o.\nBirger Westholm.\n\nI ndustriavd.-chef: ing. W. Dahlén.\n\n7nkäpsrhef: O Ilolmen.\n\nFabrikschef: fil. mag. Stig Bergman.\n\n*K. L. Beckmans Boktryckeri,\n\nStockholm.\n\nBok- och accidenstryckeri samt\nbokbin-deri. Utför tabell- och boktryck samt\naffärstryck.\n\nKontor: Stv Nyg. 22. Telegr.-adr.:\nBok-beckman, Stockholm. Telefon: 100214 o.\n107505. Postgiro: 659.\n\nAntal industriarb.: 90. — Tryckeriet\netabl. i Åbo 1668, överflyttades till\nSverige 1713, nuv. firma sedan 1847.\n\nÄgare o. chef: Carl J. Beckman.\n\nKassör o. prokurist: Carl Wirström.\n\nSe även Bäckman.\n\n* C us t af Behrns Skobandfabrik,\n\nÖrebro.\n\nTillverkar skoband, kängsnören av\nma-co- och eisengarn samt imit.\nläderremmar, bollskobarVd och alla slags sportband\nsamt tätningslist av ylle och bomull för\ndörrar och fönster.\n\nTelefon: 10346. Postgiro: 30339. Repr.\ni Stockholm Carl Behrn, Upplandsg. 2,\ntelefon: 110438.\n\nAntal industriarb.: 10. Tillv.-värde pr\når: 150,000 kr. — Firman etabl. 1906.\n\nÄgare o. chef: fabr. Gust. Behrn.\n\nAB. Beijers Motorfabrik,\n\nVimmerby.\n\nTillverkar råoljemotorer och\nuniversal-fräsmäskiner.\n\nTelefon: 22. Postgiro: 23718. —\nAkt.-kap.: 150,000 kr. Antal industriarb.: 50.\nTillv.-värde pr år: 400,000 kr. — Firman\ngrundad 1907, nuv. bolag 1925.\n\nStyrelse: godsäg. Einar Karlsson\n(ordf.), dir. Carl E. Beijer (v. ordf.),\nkamrer Ivar Beijer.\n\nV erkst. dir.: Carl E. Beijer.\n\n*J. F. Bellanders AB., Gävle.\n\nKonfektionsfabrik. Tillverkar\narbetskläder, skjortor och pyjamas.\nVarumärken: »Björnkläder», »Björntvills» o.\n»Livvakten». Firman driver även\nengroshan-del med textilvaror.\n\nTelegr.-adr. o. telefon: Bellanderbolag,\nGävle. Postgiro: 5107. — Akt.-kap.:\n300,000 kr. Antal industriarb.: 104.\nTillv.-värde pr år: 1,500,000 kr. — Firman\netabl. 1891, bolag 1917.\n\nStyrelse: dir. Birger Bellander (ordf.),\nfabrikschef Filip Bellander, grossh. Gösta\nBellander.\n\nV erkst. dir.: Gösta Bellander.\n\nBelysningskultur G. Cronwin, AB.\nCorona, Stockholm.\n\nSe AB. Corona, Belysningskultur G*\nCronwin, Stockholm.\n\nBe Ma Måhl &amp; Normen, Gislaved.\n\nTillverkar massartiklar i bakelit,\nkniv-strömbrytare, symaskinsbelysningjar samt\ntredubbla stickkontakter vid fabrik i\nGislaved (Jönköp. l.).\n\nTelefon: 494. Postgiro: 288699. —\nAntal industriarb.: 5. Tillv.-värde pr år:\n150,000 kr. — Firman etabl. 1943.\"\n\nÄgare o. chefer: fabr. Martin Måhl o.\nfabr. Bertil Normen.\n\n*AB. Bendor, Stockholm.\n\nSkruv- och metallfabrik. Tillverkar\nsvarvad och pressad skruv, mutter, nit,\nmutterbrickor, nipplar, smörjkoppar,\nfasondelar och smärre detaljer av järn,\nmässing, koppar, brons, ebonit, fiber etc. samt\npressade mutterbrickor m. m.\n\nKontor: Bohusg. 23. Telegr.-adr.:\nBendor, Stockholm. Telefon: 440520.\nPostgiro: 4825. — Akt.-kap.: 300,000 kr. Antal\nindustriarb.: 100. Tillv.-värde pr år:\n1,800 000 kr. — Bolaget grundat 1928.\n\nStyrelse: ryttm. Adrian Florman\n(ordf.), dir. Gunnar Friman, dir. Ernst\nNilson.\n\nV erkst. dir.: Gunnar Friman.\n\nFabrikschef: fabr. Erik A. Olofsson.",
    "structured": {
        "1": {
            "name": "Bechman—Bendor",
            "location": "Stockholm",
            "business": "Skruv- och metallfabrik",
            "contact": {
                "office": "Bohusg. 23",
                "phone": [
                    "440520"
                ],
                "telegraph": "Bendor, Stockholm",
                "postgiro": "4825"
            },
            "products": "Tillverkar svarvad och pressad skruv, mutter, nit, mutterbrickor, nipplar, smörjkoppar, fasondelar och smärre detaljer av järn, mässing, koppar, brons, ebonit, fiber etc. samt pressade mutterbrickor m. m.",
            "financials": {
                "capital": "300,000 kr",
                "employees": {
                    "industriarb": 100
                },
                "annual_turnover": "1,800,000 kr"
            },
            "corporation_year": 1928,
            "board": {
                "1": {
                    "name": "ryttm. Adrian Florman",
                    "role": "ordf."
                },
                "2": {
                    "name": "dir. Gunnar Friman",
                    "role": ""
                },
                "3": {
                    "name": "dir. Ernst Nilson",
                    "role": ""
                }
            },
            "director": "Erik A. Olofsson",
            "managing_director": null,
            "sales_manager": null,
            "manager": null
        },
        "2": {
            "name": "K. L. Beckmans Boktryckeri",
            "location": "Stockholm",
            "business": "Bok- och accidenstryckeri samt bokbinderi",
            "contact": {
                "office": "Stv Nyg. 22",
                "phone": [
                    "100214",
                    "107505"
                ],
                "telegraph": "Bok-beckman, Stockholm",
                "postgiro": "659"
            },
            "products": "Utför tabell- och boktryck samt affärstryck.",
            "financials": {
                "capital": null,
                "employees": {
                    "industriarb": 90
                },
                "annual_turnover": null
            },
            "corporation_year": null,
            "board": {},
            "director": "Carl J. Beckman",
            "managing_director": "Carl Wirström",
            "sales_manager": null,
            "manager": null
        },
        "3": {
            "name": "Cus t af Behrns Skobandfabrik",
            "location": "Örebro",
            "business": "Tillverkar skoband, kängsnören av mako- och eisengarn samt imit. läderremmar, bollskobarVd och alla slags sportband samt tätningslist av ylle och bomull för dörrar och fönster",
            "contact": {
                "office": null,
                "phone": [
                    "10346"
                ],
                "telegraph": null,
                "postgiro": "30339"
            },
            "products": "",
            "financials": {
                "capital": null,
                "employees": {
                    "industriarb": 10
                },
                "annual_turnover": "150,000 kr"
            },
            "corporation_year": 1906,
            "board": {},
            "director": null,
            "managing_director": null,
            "sales_manager": null,
            "manager": null
        },
        "4": {
            "name": "AB. Beijers Motorfabrik",
            "location": "Vimmerby",
            "business": "Tillverkar råoljemotorer och universal-fräsmäskiner",
            "contact": {
                "office": null,
                "phone": [
                    "22"
                ],
                "telegraph": null,
                "postgiro": "23718"
            },
            "products": "",
            "financials": {
                "capital": "150,000 kr",
                "employees": {
                    "industriarb": 50
                },
                "annual_turnover": "400,000 kr"
            },
            "corporation_year": 1925,
            "board": {
                "1": {
                    "name": "godsäg. Einar Karlsson",
                    "role": "ordf."
                },
                "2": {
                    "name": "dir. Carl E. Beijer",
                    "role": "v. ordf."
                },
                "3": {
                    "name": "kamrer Ivar Beijer",
                    "role": ""
                }
            },
            "director": "Carl E. Beijer",
            "managing_director": null,
            "sales_manager": null,
            "manager": null
        },
        "5": {
            "name": "J. F. Bellanders AB.",
            "location": "Gävle",
            "business": "Konfektionsfabrik. Tillverkar arbetskläder, skjortor och pyjamas. Varumärken: Björnkläder, Björntvills o. Livvakten. Firman driver även engroshandel med textilvaror.",
            "contact": {
                "office": null,
                "phone": [
                    null
                ],
                "telegraph": "Bellanderbolag, Gävle",
                "postgiro": "5107"
            },
            "products": "",
            "financials": {
                "capital": "300,000 kr",
                "employees": {
                    "industriarb": 104
                },
                "annual_turnover": "1,500,000 kr"
            },
            "corporation_year": 1917,
            "board": {
                "1": {
                    "name": "dir. Birger Bellander",
                    "role": "ordf."
                },
                "2": {
                    "name": "fabrikschef Filip Bellander",
                    "role": ""
                },
                "3": {
                    "name": "grossh. Gösta Bellander",
                    "role": ""
                }
            },
            "director": null,
            "managing_director": null,
            "sales_manager": "Gösta Bellander",
            "manager": null
        },
        "6": {
            "name": "Belysningskultur G. Cronwin, AB.",
            "location": "Stockholm",
            "business": null,
            "contact": {
                "office": null,
                "phone": [
                    null
                ],
                "telegraph": null,
                "postgiro": null
            },
            "products": "",
            "financials": null,
            "corporation_year": null,
            "board": {},
            "director": null,
            "managing_director": null,
            "sales_manager": null,
            "manager": null
        },
        "7": {
            "name": "Be Ma Måhl & Normen",
            "location": "Gislaved",
            "business": "Tillverkar massartiklar i bakelit, kniv-strömbrytare, symaskinsbelysningjar samt tredubbla stickkontakter vid fabrik i Gislaved (Jönköp. l.)",
            "contact": {
                "office": null,
                "phone": [
                    "494"
                ],
                "telegraph": null,
                "postgiro": "288699"
            },
            "products": "",
            "financials": null,
            "corporation_year": 1943,
            "board": {},
            "director": null,
            "managing_director": null,
            "sales_manager": null,
            "manager": null
        }
    }
}