{
    "original": "B ergbom—Berggren\n\nTillverkar motorer för bensin och\nfotogen (märke: »Berg»), råolje- och\ndieselmotorer (märke: »Skandia»), motorlok,\ntraktorer, truckar, transporttrallor,\nmotorsprutor, cykel- och motordressiner,\nbyggnadsmaskiner, tvättmaskiner,\nmanglar, eldsläckningsapparater, oljerenare\nm. m. Bolaget driver även handel med\nsymaskiner, kylskåp och grävmaskiner av\nutländska tillverkningar.\n\nHuvudkontor: Lindesberg. Telegr.-adr.\no. telefon: Bergbolagen, Lindesberg.\nPostgiro: 7568. Avd.-kontor: Stockholm,\nKungsg. 10, telefon: 234540; Göteborg,\nS:a Hamng. 23, telefon: 174830; Malmö:\nOsterg. 21, telefon: 71125.\n\nAkt.-kap.: 480,000 kr. Antal\nindustriarb.: 750.\n\nFirman, etabl. 1903, bolag 1929, nuv.\nnamn 1946, arrenderar och driver\nSkandia ver ken AB., Lysekil, etabl. 1899, och\nAug. Stenborgs Gjuteri- och Fabriks AB.,\nTierp, etabl. 1894.\n\nStyrelse: konsul Wilh. Berg (ordf.),\nfabr. Theodor Berg, bankdit. Georg\nNilsson.\n\nVerkst. dir.: Tore Berg.\n\nEkonomichef: Helmer Skoglund.\n\nFörsäljn.- o. exportchef: ing. Eric\nWrethagen (Sthlm).\n\nPlatschefer: Lysekil: dir. Otto\nNilsson; Tierp: dir. Ivar Andersson.\n\nReklamchef: ing. H. Sköldebrand.\n\nBergbom &amp; Co. AB., Malmö.\n\nMek. verkstad. Tillverkar bageri- och\nkonditorimaskiner samt glassmaskiner.\n\nHuvudkontor: Malmö, Celsiusg. 41.\nTelefon: »Ljungs Industrier». Postgiro:\n147939. Avd.-kontor: Stockholm,\nGäst-rikeg. 17, telefon: 308191; Göteborg: St.\nNyg. 15, telefon: 119374.\n\nAkt.-kap.: 150,000 kr. Antal\nindustriarb.: 30. — Bolaget, grundat 1939, äges\nav Ljungs Industrier AB., Malmö.\n\nStyrelse: dir. Henry Ljung (ordf.),\ndisp. Eric Ljung, disp. Ernst Pettersson.\n\nVerkst. dir.: Henry Ljung.\n\nDisp.: Harry Arvidson.\n\nDriftsing.: Henry Brännberg.\n\nAB. Bergdala Glasbruk,\n\nHovmantorp.\n\nGlasbruk i Bergdala, Hovmantorp\nfKronob. l.). Tillverkar slätt, slipat och\npressat hushållsglas samt prydnadsglas.\n\nTelefon: Bergdala 22 a. Postgiro: 76196.\nRepr. i Stockholm: N. R. Hellsten,\nFuru–sundsg. 3, telefon: 600176.\n\nAkt.-kap.: 100,000 kr. Antal industri-\n\narb.: 60. Tillv.-värde pr år: 400,000 kr.\n— Bruket anlagt 1889, bolag 1922.\n\nStyrelse: dir. Gottfrid Dahl.\n\nDriftschef: Thage Dahl.\n\nKontorschef: Tor Johansson.\n\n*AB. Bergendahl och Höckert,\n\nGöteborg.\n\nByggnadsentreprenadfirma # för\nvägbyggnads- och vägbeläggningsarbeten,\nterasseringsarbeten, industribyggnader,\nhamn- och kanalarbeten samt tunnel- och\nbergrumsanläggningar m. m.\n\nHuvudkontor: Göteborg, Magasinsg.\n3. Telefon: 172955. Postgiro: 43210.\nAvd.-kontor: Stockholm, Tegnérlunden\n3, telefon: 231940.\n\nAkt.-kap.: 200,000 kr. Prod.-värde pr\når: 7,000,000 kr. — Firman etabl. 1932\nunder namn AB. Vägbeläggningar, npv.\nnamn 1943.\n\nStyrelse: civiling. Gunnar Bergendähl\n(ordf.), civiling. Gunnar Höckert.\n\nAvd.-chefer: Göteborg: ing. Gustaf\nAdolf Sander; Stockholm: civiling. Erik\nG. Hellström.\n\n\"Bergendahls Boktryckeri,\n\nGöteborg.\n\nBoktryckeri, offsettryckeri och\nbokbin-deri. Utför spec. affärs-, katalog- och\nreklamtryck, teckningar, retuscher och\nklichéer.\n\nKontor: Kyrkog. 9. Telegr.-adr.:\nBok-bergendahl, Göteborg. Telefon: 137023 o.\n136956. Postgiro: 12047. — Firman etabl.\n1905.\n\nÄgare o. chef: boktr. Nils Buskqvist.\n\nB. Bergendorffs Verkstäder,\n\nOskarström.\n\nMek. verkstad och skjdtfabrik i\nOskarström (Hallands l.). Tillverkar\nneonskyltar och järnkonstruktioner för dylika,\nplåtbokstäver och plåtskyltar, pressade,\nsvarvade och svetsade artiklar, skrivställ\nm. m.\n\nTelefon: 235. Postgiro: 267427. —\nAntal industriarb.: 25. Tillv.-värde pr år:\n175,000 kr. — Firman etabl. 1940.\n\nÄgare o. chef: fabr. Bertil Bergendorff.\n\n\"Bergfors Snickerifabrik, Åker.\n\nSe Industri- &amp; Handels AB. Oscar\nLjungbergh, Jönköping.\n\n\"Berggren &amp; Pettersson, Åtvidaberg.\n\nTillverkar herr- och damkläder vid\nkonfektionsfabrik i Åtvidaberg\n(Östergötl. l.).",
    "structured": {
        "1": {
            "name": "Bergbom—Berggren",
            "location": "Lindesberg",
            "business": "Manufacturing of engines, motor vehicles, construction machinery, and household appliances, as well as trading of sewing machines, refrigerators, and excavation machinery.",
            "contact": {
                "office": "Lindesberg",
                "phone": [
                    "234540",
                    "174830",
                    "71125"
                ],
                "postgiro": "7568",
                "head_office": "Lindesberg",
                "sales_offices": [
                    {
                        "location": "Stockholm",
                        "phone": "234540"
                    },
                    {
                        "location": "Göteborg",
                        "phone": "174830"
                    },
                    {
                        "location": "Malmö",
                        "phone": "71125"
                    }
                ],
                "telegraph": "Bergbolagen, Lindesberg",
                "factory_office": "",
                "factory_phone": ""
            },
            "financials": {
                "capital": "480,000 kr",
                "employees": {
                    "industriarb": 750
                }
            },
            "foundation_year": 1903,
            "current_name_year": 1946,
            "predecessor": "",
            "corporation_year": 1929,
            "board": [
                {
                    "name": "konsul Wilh. Berg",
                    "role": "ordf."
                },
                {
                    "name": "fabr. Theodor Berg",
                    "role": ""
                },
                {
                    "name": "bankdit. Georg Nilsson",
                    "role": ""
                }
            ],
            "director": "Tore Berg",
            "managing_director": "Tore Berg",
            "sales_manager": "ing. Eric Wrethagen",
            "manager": "Tore Berg"
        },
        "2": {
            "name": "Bergbom & Co. AB.",
            "location": "Malmö",
            "business": "Mechanical workshop manufacturing bakery and confectionery machinery as well as ice cream machines.",
            "contact": {
                "office": "Malmö",
                "phone": [
                    "308191",
                    "119374"
                ],
                "postgiro": "147939",
                "head_office": "Malmö, Celsiusg. 41",
                "sales_offices": [
                    {
                        "location": "Stockholm",
                        "phone": "308191"
                    },
                    {
                        "location": "Göteborg",
                        "phone": "119374"
                    }
                ],
                "telegraph": "Bergbom & Co. AB."
            },
            "financials": {
                "capital": "150,000 kr",
                "employees": {
                    "industriarb": 30
                }
            },
            "foundation_year": 1939,
            "current_name_year": "",
            "predecessor": "",
            "corporation_year": "",
            "board": [
                {
                    "name": "dir. Henry Ljung",
                    "role": "ordf."
                },
                {
                    "name": "disp. Eric Ljung",
                    "role": ""
                },
                {
                    "name": "disp. Ernst Pettersson",
                    "role": ""
                }
            ],
            "director": "Henry Ljung",
            "managing_director": "Henry Ljung",
            "sales_manager": "",
            "manager": "Henry Ljung"
        },
        "3": {
            "name": "AB. Bergdala Glasbruk",
            "location": "Hovmantorp",
            "business": "Glassworks producing household and decorative glassware.",
            "contact": {
                "office": "",
                "phone": [
                    "600176"
                ],
                "postgiro": "76196",
                "head_office": "",
                "sales_offices": [],
                "telegraph": ""
            },
            "financials": {
                "capital": "100,000 kr",
                "employees": {
                    "industriarb": 60
                },
                "annual_turnover": "400,000 kr"
            },
            "foundation_year": 1889,
            "current_name_year": "",
            "predecessor": "",
            "corporation_year": 1922,
            "board": [
                {
                    "name": "dir. Gottfrid Dahl",
                    "role": ""
                }
            ],
            "director": "",
            "managing_director": "",
            "sales_manager": "",
            "manager": ""
        },
        "4": {
            "name": "AB. Bergendahl och Höckert",
            "location": "Göteborg",
            "business": "Construction contractor specializing in road construction, terracing, industrial buildings, port and canal works, tunnel and underground facility constructions, etc.",
            "contact": {
                "office": "Göteborg, Magasinsg. 3",
                "phone": [
                    "172955"
                ],
                "postgiro": "43210",
                "head_office": "",
                "sales_offices": [
                    {
                        "location": "Stockholm",
                        "phone": "231940"
                    }
                ],
                "telegraph": ""
            },
            "financials": {
                "capital": "200,000 kr",
                "annual_turnover": "7,000,000 kr"
            },
            "foundation_year": 1932,
            "current_name_year": 1943,
            "predecessor": "AB. Vägbeläggningar",
            "corporation_year": "",
            "board": [
                {
                    "name": "civiling. Gunnar Bergendähl",
                    "role": "ordf."
                },
                {
                    "name": "civiling. Gunnar Höckert",
                    "role": ""
                }
            ],
            "director": "",
            "managing_director": "",
            "sales_manager": "",
            "manager": ""
        },
        "5": {
            "name": "Bergendahls Boktryckeri",
            "location": "Göteborg",
            "business": "Printing and bookbinding company specialized in business, catalog, and advertising printing, drawings, retouching, and clichés.",
            "contact": {
                "office": "Göteborg, Kyrkog. 9",
                "phone": [
                    "137023",
                    "136956"
                ],
                "postgiro": "12047",
                "head_office": "",
                "sales_offices": [],
                "telegraph": "Bokbergendahl, Göteborg"
            },
            "financials": {
                "capital": "",
                "employees": {},
                "annual_turnover": ""
            },
            "foundation_year": 1905,
            "current_name_year": "",
            "predecessor": "",
            "corporation_year": "",
            "board": [],
            "director": "Nils Buskqvist",
            "managing_director": "",
            "sales_manager": "",
            "manager": "boktr. Nils Buskqvist"
        },
        "6": {
            "name": "B. Bergendorffs Verkstäder",
            "location": "Oskarström",
            "business": "Mechanical workshop and steel factory manufacturing neon signs, iron structures, metal letters and plates, pressed, turned, and welded articles, writing desks, etc.",
            "contact": {
                "office": "Oskarström",
                "phone": [
                    "235"
                ],
                "postgiro": "267427",
                "head_office": "",
                "sales_offices": [],
                "telegraph": ""
            },
            "financials": {
                "capital": "",
                "employees": {
                    "industriarb": 25
                },
                "annual_turnover": "175,000 kr"
            },
            "foundation_year": 1940,
            "current_name_year": "",
            "predecessor": "",
            "corporation_year": "",
            "board": [],
            "director": "",
            "managing_director": "",
            "sales_manager": "",
            "manager": "fabr. Bertil Bergendorff"
        }
    }
}