{
    "original": "Skoghallsverken—Skogstorp\n\nStyrelse: dir. Erik G. Pehrsson, disp.\nSigfr. Höglund, disp. Joel Larsson, disp.\nHelge Silverstolpe, disp. Hj. Åselius.\nVerkst. dir.: Sigfr. Höglund.\nFörsäljningschef: Carl W. Jacobsson.\nDriftsing.: T. E. Tegelström.\nShogsförvalt.: Dan Höglund.\nAvd.-chef i Ornäs: förvalt. Erik\nWin-löf.\n\n\"Skoghallsverken, Skoghall.\n\nSe Uddeholms AB., Uddeholm.\n\n\"AB. Skoglund &amp; Olson, Gävle.\n\nTackjärnsgjuter i och mek. verkstad.\nTillverkar handelsgjutgods såsom\nvärmeledningspannor (märke: »SETO»), spisar,\nkaminer, vattenvärmare samt annat\nbyggnads- och hushållsgjutgods, industri- och\nhushållspumpar, elvärmeapparater för\nindustri och hushåll, ekonomiserrör m. m.\n\nHuvudkontor: Gävle. Telegr.-adr.:\nSkoglunds, Gävle. Telefon: »Skoglund &amp;\nOlson». Postgiro: 9239.\n\nRepresentanter:\n\nför handelsgjutgods o. elektr. artiklar\nför hushåll: Stockholm: Skoglund &amp;\nOlsons Upplag AB., S. Mälarstrand 5,\ntelefon: 440535; Göteborg: Gullbrand\nSandgren, Trollhätteg. 10, telefon: 155160;\nMalmö: Gullbrand Sandgren, österg. 10,\ntelefon: 78755;\n\nför värmeledningspannor: Stockholm:\nNordiska Rör AB., Kungsg. 18, telefon:\n»Nordiska Rörbolaget»; Malmö: AB. J. H.\nDieden J:r, S. Neptunig. 1, telefon:\n20827 o. AB. H. Järnhardt &amp; Co., Carlsg.\n54—56, telefon: »Järnhardt &amp; Co.»;\nGöteborg: AB. Wilh. Sonesson &amp; Co., L:a\nBommens torg 2, telefon: 136490;\n\nför pumpar: Stockholm: Elektr. AB.\nSkandia, N. Stationsg. 79—81, telefon:\n»Elektroskandia»;\n\nför elvärmeapparater för industrien o.\neconomiserrör: Stockholm: AB. A.\nEkströms Maskinaffär, Yattug. 10, telefon:\n231715.\n\nAkt.-kap.: 800,000 kr. Antal\nindustriarb.: 280. Tillv.-värde pr år: 2,800,000 kr.\n— Firman etabl. 1874, bolag 1914.\n\nStyrelse: ing. Erik Ahlgren (ordf.),\nciviling. Nils Ryström, civiling. Uno\nSöderström.\n\nVerkst. dir.: Uno Söderström.\n\nDriftschef: övering. Erik Eiritz.\n\nAvd.-chefer: för elektr. avd.: civiling.\nNils Ryström; för pumpavd.: civiling.\nTorsten Ygge.\n\nKontorschef: kamrer Sven Eiritz.\n\nSkogsfors Bruks AB., Reftele.\n\nMek. verkstad, gjuteri och\nsnickeriverkstad med såg och hyvleri för eget\nbehov vid Reftele (Jönköp. l.).\nTillverkar lantbruksmaskiner, hushållspumpar,\ngjutgods, hejarsmide m. m.\n\nTelegr.-adr.: Bruket, Reftele. Telefon:\n8 o. 88. Postgiro: 22560.\n\nAkt.-kap.: 100,000 kr. Antal\nindustriarb.: 70. Tillv.-värde pr år: 950,000 kr.\n\nBolaget, grundat 1911, äges av\nKooperativa Förbundet.\n\nStyrelse: dir. Albin Johansson (ordf.),\nfil. lic. Mauritz Bonow, dir. Hj.\nDeger-stedt, dir. Hugo Edstam, dir. G. Osvald,\ndir. Ernst Persson.\n\nDriftschef: ing. E. Schönberg.\n\n\"Skogslunds Fabrik, Gnosjö.\n\nTillverkar spiralfjädrar, tråd- och\njärnmanufaktur vid fabrik i Gnosjö (Jönköp.\n1.). Specialitet: massartiklar i kallvalsat\nstål och järntråd.\n\nTelefon: 46. Postgiro: 29694. —\nAntal industriarb.: 18. Tillv.-värde pr år:\n68,000 kr. — Firman etabl. 1914.\n\nÄgare o. chefer: fabr. Eric Ericsson o.\nfabr. C.-E. Ericsson.\n\nSkogs- &amp; Sågverks AB. Lind &amp;\nNorman, Sveg.\n\nTillverkar sågade trävaror vid sågverk\ninom Jämtlands och Kopparbergs län.\n\nTelefon: 106 o. 249. — Akt.-kap.:\n200,000 kr. Antal industriarb.: 30.\nTillv.-värde pr år: 600,000 kr. Årstillv.: 1,500\nstds trävaror. — Firman etabl. 1926,\nbolag 1945.\n\nVerkst. dir.: jägmäst. Torsten Lind.\n\nSkogstorps Sågverks AB.,\n\nSkogstorp.\n\nSågverk och hyvleri vid Skogstorp\n(Södermanl. l.). Tillverkar sågade och\nhyvlade trävaror.\n\nTelefon: Eskilstuna 26125 o. 25005.\nPostgiro: 25226. — Akt.-kap:.- 360,000\nkr. Årstillv.: 3,000 stds trävaror. —\nBolaget grundat 1915.\n\nVerkst. dir.: Erik F. Schenström.\n\n\"Skogstorps Valsverk, Skogstorp.\n\nSe Eskilstuna Stålpressnings AB.,\nEskilstuna.\n\n\"Skogstorps Ångsåg, Sävsjöström.\n\nSe AB. Brusafors-Hällefors,\nSilverdalen.\n\n-•K",
    "structured": {
        "1": {
            "name": "Skoghallsverken",
            "location": "Skoghall",
            "business": "Tackjärnsgjuteri och mekanisk verkstad",
            "contact": {
                "head_office": "Gävle",
                "telegraph": "Skoglunds, Gävle",
                "phone": [
                    "9239"
                ]
            },
            "financials": {
                "capital": "800,000 kr",
                "employees": {
                    "industriarb": 280
                },
                "annual_turnover": "2,800,000 kr"
            },
            "foundation_year": 1874,
            "corporation_year": 1914,
            "board": [
                {
                    "name": "Erik Ahlgren",
                    "role": "ordf."
                },
                {
                    "name": "Nils Ryström",
                    "role": "civiling."
                },
                {
                    "name": "Uno Söderström",
                    "role": "civiling."
                }
            ],
            "director": "Sigfr. Höglund",
            "managing_director": "Sigfr. Höglund",
            "sales_manager": "Carl W. Jacobsson",
            "manager": "T. E. Tegelström"
        },
        "2": {
            "name": "AB. Skoglund & Olson",
            "location": "Gävle",
            "business": "Tackjärnsgjuteri och mekanisk verkstad",
            "contact": {
                "telegraph": "Skoglunds, Gävle",
                "phone": [
                    "Skoglund & Olson",
                    "9239"
                ]
            },
            "financials": {
                "capital": "800,000 kr",
                "employees": {
                    "industriarb": 70
                },
                "annual_turnover": "950,000 kr"
            },
            "foundation_year": 1911,
            "owners": [
                "Kooperativa Förbundet"
            ],
            "board": [
                {
                    "name": "Albin Johansson",
                    "role": "ordf."
                },
                {
                    "name": "Mauritz Bonow",
                    "role": "fil. lic."
                },
                {
                    "name": "Hj. Deger-stedt",
                    "role": "dir."
                },
                {
                    "name": "Hugo Edstam",
                    "role": "dir."
                },
                {
                    "name": "G. Osvald",
                    "role": "dir."
                },
                {
                    "name": "Ernst Persson",
                    "role": "dir."
                }
            ],
            "director": "Uno Söderström",
            "sales_manager": "E. Schönberg"
        },
        "3": {
            "name": "Skogslunds Fabrik",
            "location": "Gnosjö",
            "business": "Spiralfjädrar, tråd- och järnmanufaktur",
            "contact": {
                "phone": [
                    "46"
                ],
                "postgiro": "29694"
            },
            "financials": {
                "employees": {
                    "industriarb": 18
                },
                "annual_turnover": "68,000 kr"
            },
            "foundation_year": 1914,
            "director": "fabr. Eric Ericsson",
            "manager": "fabr. C.-E. Ericsson"
        },
        "4": {
            "name": "Skogs- & Sågverks AB. Lind & Norman",
            "location": "Sveg",
            "business": "Tillverkning av sågade trävaror",
            "contact": {
                "phone": [
                    "106",
                    "249"
                ]
            },
            "financials": {
                "capital": "200,000 kr",
                "employees": {
                    "industriarb": 30
                },
                "annual_turnover": "600,000 kr"
            },
            "foundation_year": 1926,
            "corporation_year": 1945,
            "board": [
                {
                    "name": "Torsten Lind",
                    "role": "jägmäst."
                }
            ]
        },
        "5": {
            "name": "Skogstorps Sågverks AB.",
            "location": "Skogstorp",
            "business": "Tillverkning av sågade och hyvlade trävaror",
            "contact": {
                "phone": [
                    "Eskilstuna 26125",
                    "25005"
                ],
                "postgiro": "25226"
            },
            "financials": {
                "capital": "360,000 kr",
                "annual_turnover": "Info not available"
            },
            "corporation_year": 1915,
            "director": "Erik F. Schenström"
        }
    }
}