{
    "original": "Eickhoff—Ekengård\n\nAkt.-kap.: 3,000,000 kr. Antal\nindustriarb.: 400. Tillv.-värde pr år: 12,000,000\nkr. — Firman etabl. 1808, bolag 1898.\n\nStyrelse: dir. Gösta Ehrnberg (ordf.),\nbankdir. Alvar Ehrnberg, dir. P. Eg.\nGummeson.\n\nVerkst. dir.: Gösta Ehrnberg.\n\n*H. Eickhoff, Norrköping.\n\nYlleväveri. Tillverkar foulé, cheviot,\nkamgarnstyger, paletå-, sportdräkts- och\ndamkapptyger m. m. samt vattolin och\ntagelduk. Varumärke: H E Y.\n\nTelegr.-adr.: Eickhoff, Norrköping.\nTelefon: 24912. Postgiro: 8945.\n\nAntal industriarb.: 26. Tillv.-värde pr\når: 500,000 kr. — Firman, etabl. 1926,\nsamarbetar med Abrahamsons\nBerednings AB., Norrköping (se detta bolag).\n\nÄgare o. chef: fabr. Heinrich Eickhoff.\n\n*AB, Eilas, Linköping.\n\nMöbelfabrik. Tillverkar stoppade\nmöbler och möbelstommar samt kuddar och\nplymåer. Specialitet: bäddsoffor.\n\nTelefon: 23645 o. 27617. Postgiro:\n72271. — Akt.-kap.: 80,000 kr. Antal\nindustriarb.: 34. Tillv.-värde pr år: 600,000\nkr. — Firman etabl. 1929 i Moholm under\nnamn E. G. Johansson &amp; Co., nuv. namn\noch adress 1931.\n\nStyrelse: disp. Ivar Nyman (ordf.),\ndisp. Erik Hjällsten, fabr. Laban\nJohansson.\n\nVerkst. dir.: Erik Hjällsten.\n\nEkbergs Eftr. O. Ekberg,\n\nÖrnsköldsvik.\n\nSe Bröderna Ekbergs Eftr. O. Ekberg,\nÖrnsköldsvik.\n\n*AB. C. Ö. Ekblad &amp; Co., Västervik.\n\nBoktryckeri, bokbinderi och\nförlagsrörelse. Utför tidnings-, bok- och\naffärs-tryck samt utgiver\n»Västerviks-Tidning-en» och »Vimmerby Dagblad».\n\nTelefon: 98, 928 o. 698. Postgiro:\n6411.\n\nAkt.-kap.: 240,000 kr. Antal\nindustriarb.: 28. — Firman etabl. 1834, bolag\n1917.\n\nStyrelse: adv. A. N. Lindskog (ordf.),\nbokhandl. Erik Hultgren, boktr. Franklin\nHultgren, dir. Olle Hultgren, disp.\nGunnar Nordström.\n\nVerkst. dir.: Olle Hultgren.\n\nBror Ekegrens Boktryckeri,\n\nSödertälje.\n\nBok- och accidenstryckeri. Specialitet:\naffisch- och reklamtryck.\n\nTelefon: 30258 o. 31458. Postgiro:\n134778. — Arb.-antal: 12. Tillv.-värde\npr år: 175,000 kr. — Firman etabl. 1924.\nÄgare o. chef: boktr. Bror Ekegren.\n\nAB. Ekelund &amp; Söderbom, Kinna.\n\nRaschel- och trikåfabrik i Risäng,\nKinna (Älvsb. l.). Tillverkar trikåvaror,\nschalar, scarves, chinjonger och hårnät.\n\nTelegr.-adr.: Eochs, Kinna. Telefon:\n10133. Postgiro: 75576. Repr. i\nStockholm: Julius Strauss, Jungfrug. 6,\ntelefon: 614046.\n\nAkt.-kap.: 50,000 kr. Antal\nindustriarb.: 30. — Bolaget grundat 1924.\n\nVerkst. dir.: Olof Söderbom.\n\nTekn. ledare: fabr. Einar Rudhner.\n\n\"Oscar Edv. Ekelunds Snickerifabriks\n\nAB., Virserum.\n\nMöbelfabrik i Virserum (Kalmar l.).\nTillverkar matsalsmöbler m. m.\n\nTelefon: 4. Postgiro: 133232. —\nAkt.-kap.: 270,000 kr. Antal industriarb.: 100.\nTillv.-värde pr år: 800,000 kr. — Bolaget\ngrundat 1899.\n\nStyrelse: adv. Gösta Sandstedt (ordf.),\ndisp. J. Ekelund, järnhandl. E. Norrman,\nkassör Folke Sandstedt, lantbr. Manne\nSjölander, handl. H. Teurnberg.\n\nVerkst. dir.: Gösta Sandstedt.\n\nKassör: F. Sandstedt.\n\nAB. C. Ekengren Mösskonfektion,\n\nStockholm.\n\nTillverkar skol- och klädesmössor samt\nsom specialiteter sport- och skidmössor.\n\nKontor: S:t Eriksterrassen 72 A.\nTelefon: 516488. Postgiro: 51259.\n\nAkt.-kap.: 30,000 kr. Antal\nindustriarb.: 25. — Firman etabl. 1933, bolag\n1938.\n\nVerkst. dir.: Gotthard Ekengren.\n\nEkengårds Maskinfabrik, S. B.\n\nNelson, Sölvesborg.\n\nMek. verkstad i Ysane, Sölvesborg\n(Blekinge l.). Tillverkar\nlantbruksmaskiner såsom maskiner för potatisodling\nm. m. samt transportvagnar.\n\nTelefon: Sölvesborg 29050. Postgiro:\n164060. Representanter: Stockholm:\nSöderberg &amp; Haak AB., Drottningg. 2;\nMalmö: Andersson &amp; Mattsson AB.,\n\n",
    "structured": {
        "1": {
            "name": "Eickhoff—Ekengård",
            "business": "Ylleväveri",
            "foundation_year": 1808,
            "financials": {
                "capital": "3,000,000 kr",
                "employees": {
                    "industriarb": 400
                },
                "annual_turnover": "12,000,000 kr"
            },
            "board": [
                {
                    "name": "Gösta Ehrnberg",
                    "role": "ordf."
                },
                {
                    "name": "Alvar Ehrnberg",
                    "role": "bankdir."
                },
                {
                    "name": "P. Eg. Gummeson",
                    "role": "dir."
                }
            ],
            "director": "Gösta Ehrnberg",
            "contact": {
                "office": "H. Eickhoff, Norrköping",
                "phone": [
                    "24912"
                ],
                "postgiro": "8945",
                "telegraph": "Eickhoff, Norrköping"
            }
        },
        "2": {
            "name": "H. Eickhoff",
            "business": "Textile Manufacturing",
            "products": "foulé, cheviot, kamgarnstyger, paletå-, sportdräkts- och damkapptyger m. m. samt vattolin och tagelduk.",
            "location": "Norrköping",
            "employees": {
                "industriarb": 26
            },
            "financials": {
                "capital": "Unknown",
                "annual_turnover": "500,000 kr"
            },
            "contact": {
                "office": "H. Eickhoff, Norrköping",
                "phone": [
                    "24912"
                ],
                "postgiro": "8945",
                "telegraph": "Eickhoff, Norrköping"
            },
            "owner": "Heinrich Eickhoff"
        },
        "3": {
            "name": "AB, Eilas",
            "business": "Furniture Manufacturing",
            "products": "stoppade möbler och möbelstommar samt kuddar och plymåer. Specialitet: bäddsoffor.",
            "location": "Linköping",
            "employees": {
                "industriarb": 34
            },
            "financials": {
                "capital": "80,000 kr",
                "annual_turnover": "600,000 kr"
            },
            "board": [
                {
                    "name": "Ivar Nyman",
                    "role": "disp."
                },
                {
                    "name": "Erik Hjällsten",
                    "role": "disp."
                },
                {
                    "name": "Laban Johansson",
                    "role": "fabr."
                }
            ],
            "director": "Erik Hjällsten",
            "contact": {
                "office": "AB, Eilas, Linköping",
                "phone": [
                    "23645",
                    "27617"
                ],
                "postgiro": "72271"
            }
        },
        "4": {
            "name": "Ekbergs Eftr. O. Ekberg",
            "location": "Örnsköldsvik"
        },
        "5": {
            "name": "AB. C. Ö. Ekblad & Co.",
            "business": "Printing and Publishing",
            "location": "Västervik",
            "products": "tidnings-, bok- and affärs-tryck samt utgiver 'Västerviks-Tidning-en' and 'Vimmerby Dagblad'.",
            "financials": {
                "capital": "240,000 kr",
                "annual_turnover": "Unknown"
            },
            "board": [
                {
                    "name": "A. N. Lindskog",
                    "role": "adv."
                },
                {
                    "name": "Erik Hultgren",
                    "role": "bokhandl."
                },
                {
                    "name": "Franklin Hultgren",
                    "role": "boktr."
                },
                {
                    "name": "Olle Hultgren",
                    "role": "dir."
                },
                {
                    "name": "Gunnar Nordström",
                    "role": "disp."
                }
            ],
            "director": "Olle Hultgren",
            "contact": {
                "office": "AB. C. Ö. Ekblad & Co., Västervik",
                "phone": [
                    "98",
                    "928",
                    "698"
                ],
                "postgiro": "6411"
            }
        },
        "6": {
            "name": "Bror Ekegrens Boktryckeri",
            "business": "Printing and Publishing",
            "location": "Södertälje",
            "products": "affisch- and reklamtryck",
            "employees": {
                "antal": 12
            },
            "financials": {
                "annual_turnover": "175,000 kr"
            },
            "director": "Bror Ekegren",
            "contact": {
                "office": "Bror Ekegrens Boktryckeri, Södertälje",
                "phone": [
                    "30258",
                    "31458"
                ],
                "postgiro": "134778"
            }
        },
        "7": {
            "name": "AB. Ekelund & Söderbom",
            "business": "Textile Manufacturing",
            "location": "Kinna",
            "products": "trikåvaror, schalar, scarves, chinjonger and hårnät",
            "employees": {
                "industriarb": 30
            },
            "financials": {
                "capital": "50,000 kr"
            },
            "board": [
                {
                    "name": "Einar Rudhner",
                    "role": "fabr."
                }
            ],
            "contact": {
                "office": "AB. Ekelund & Söderbom, Kinna",
                "phone": [
                    "10133"
                ],
                "postgiro": "75576"
            }
        },
        "8": {
            "name": "Oscar Edv. Ekelunds Snickerifabriks AB.",
            "business": "Furniture Manufacturing",
            "location": "Virserum",
            "products": "matsalsmöbler m. m.",
            "employees": {
                "industriarb": 100
            },
            "financials": {
                "capital": "270,000 kr",
                "annual_turnover": "800,000 kr"
            },
            "board": [
                {
                    "name": "Gösta Sandstedt",
                    "role": "adv."
                },
                {
                    "name": "J. Ekelund",
                    "role": "disp."
                },
                {
                    "name": "E. Norrman",
                    "role": "järnhandl."
                },
                {
                    "name": "Folke Sandstedt",
                    "role": "kassör"
                },
                {
                    "name": "Manne Sjölander",
                    "role": "lantbr."
                },
                {
                    "name": "H. Teurnberg",
                    "role": "handl."
                }
            ],
            "director": "Gösta Sandstedt",
            "contact": {
                "office": "Oscar Edv. Ekelunds Snickerifabriks AB., Virserum",
                "phone": [
                    "4"
                ],
                "postgiro": "133232"
            }
        },
        "9": {
            "name": "AB. C. Ekengren Mösskonfektion",
            "business": "Clothing Manufacturing",
            "location": "Stockholm",
            "products": "skol- and klädesmössor samt sport- and skidmössor",
            "employees": {
                "industriarb": 25
            },
            "financials": {
                "capital": "30,000 kr",
                "annual_turnover": "Unknown"
            },
            "director": "Gotthard Ekengren",
            "contact": {
                "office": "AB. C. Ekengren Mösskonfektion, Stockholm",
                "phone": [
                    "516488"
                ],
                "postgiro": "51259"
            }
        },
        "10": {
            "name": "Ekengårds Maskinfabrik, S. B. Nelson",
            "business": "Machinery Manufacturing",
            "location": "Sölvesborg",
            "products": "lantbruksmaskiner såsom maskiner för potatisodling m. m. samt transportvagnar",
            "contact": {
                "office": "Ekengårds Maskinfabrik, S. B. Nelson, Sölvesborg",
                "phone": [
                    "29050"
                ],
                "postgiro": "164060"
            }
        }
    }
}