{
    "original": "Svenska\n\n\"AB. Svenska Kullagerfabriken,\nKatrineholmsverken, Katrineholm.\n\nMek. verkstad och gjuteri i\nKatrineholm. Tillverkar transmissionselement,\nkul- och rullagerinbyggnader samt\ngjut-gods.\n\nTelegr.-adr. o. telefon: Kullager,\nKatrineholm. — Antal industriarb.: 1,000.\n\nVerkstaden anlades 1886 under namn\nGrönkwists Mek. Verkstad.\n\növering. o. platschef: civiling. O.\nWarne.\n\n(Jfr AB. Svenska Kullagerfabriken,\nGöteborg.)\n\nSvenska Käpp- &amp; Paraplyfabriken\nAB., Stockholm.\n\nTillverkar käppar och paraplyer.\n\nKontor: S:t Paulsg. 11. Telefoner:\n405575 o. 430309. Postgiro: 54629.\n\nAkt.-kap.: 40,000 kr. Antal\nindustriarb.: 7. Tillv.-värde pr år: 150,000 kr. —\nFirman etabl. 1903, bolag 1931.\n\nVerkst. dir.: Herbert Alwert.\n\nKamrer: Olof Alwert.\n\nSvenska AB. Le Carbone,\n\nSundbyberg.\n\nTorrbatterifabrik. Tillverkar\ntorrelement (luftdepolariserande), anod- och\nf icklampsbatterier (salmiakf örf arande).\nVarumärken: »AD» o. »WRIL». Firman\ndriver även försäljning av kolborstar och\nbåglampskol.\n\nTelegr.-adr.: Lecarbone, Sundbyberg.\nTelefon: Stockholm 282615. Postgiro:\n51208.\n\nAkt.-kap.: 100,000 kr. Antal\nindustriarb.: 80. Tillv.-värde pr år: 1,000,000 kr.\n\nFirman etabl. år 1928 i Linköping\nunder namn W. Ramsays Torrbatterifabrik,\nombildad under nuv. namn och\növerflyttad till Sundbyberg 1931.\n\nStyrelse: ing. W. Ramsay (ordf.),\nkamrer Helge Berg, dir. W. Gast.\n\nVerkst. dir.: W. Gast.\n\nKamrer: Helge Berg.\n\nSvenska Leksaksfabriken,\n\nHälsingborg.\n\nTräförädlingsfabrik i Tyringe\n(Kristianst. l.). Tillverkar leksaker av trä.\n\nKontor o. försäljn.: AB. Bröderna\nBo-réus, Hälsingborg. Telefon: 13732.\nPostgiro: 13800.\n\nAntal industriarb.: 45. Tillv.-värde pr\når: 260,000 kr. — Firman etabl. 1917.\n\nÄgare: dir. H. Boréus o. sjökapten J.\nIngvarsson.\n\nDisp.: Sture Ljung.\n\n\"Svenska Limämnesfabriken AB.,\n\nLandskrona.\n\nKem.-tekn. fabrik. Tillverkar\nlimämnen, klister, appreturmedel, valsmassa,\nhartslim, dextrin m. m. Varumärken:\n»Atlantine», »Plattol» o. »Landora».\n\nTelegr.-adr.: Atlantine, Landskrona.\nTelefon: 245, 607 o. 617. Postgiro: 23170.\nRepr.: Göran Wendel, Helenelund,\ntelefon: Stockholm 350707.\n\nAkt.-kap.: 150,000 kr. Antal\nindustriarb.: 25. Tillv.-värde pr år: 2,000,000 kr.\n\nFirman etabl. 1901, bolag 1934.\n\nStyrelse o. verkst. dir.: Franz Meyer.\n\nAB. Svenska Luterma, Malmö.\n\nTunn- och emballagefabrik. Tillverkar\ntunnor, varu- och transportlådor,\nindustribackar, ^ prappers- och mangelkorgar\nm. m. av björkkryssfanér. Bolaget driver\näven handel med kryssfanér, lamellplattor^\nstolsitsar m. m.\n\nKontor: Industrig. 15. Telegr.-adr.:\nLuterma, Malmö. Telefon: 72315.\nPostgiro: 38945.\n\nAkt.-kap.: 200,000 kr. Antal\nindustriarb.: 50. — Bolaget grundat 1933.\n\nVerkst. dir.: Kristian Staerk.\n\nDisp.: Carl Rasmusson.\n\n\"Svenska Lyxmöbelfabriken,\n\nBlikstorp.\n\nMöbel- och snickerifabrik i Blikstorp\n(Skarab. l.). Tillverkar inredningar för\nbutiker, skolor och sjukhus, hotell- och\nrestaurangmöbler, dörrar och fönster,\nköksinredningar, köksskåp m. m.\n\nTelefoner: Fridene 8. Postgiro: 276377.\n\nAntal industriarb.: 35. Tillv.-värde pr\når: 450,000 kr. — Firman grundad 1904.\n\nÄgare o. chef: disp. Karl-Axel\nRitt-feldt.\n\nSvenska Låsmutter AB.,\n\nStockholm.\n\nTillverkar kvicksilverreläer och\nströmbrytare samt trappljusautomater\n(»In-reco»). Bolaget driver även försäljning av\nlåsmuttrar (»Elastic Stop»).\n\nKontor: Södermalmstorg 4.\nTelegr.-adr.: Elasticstop, Stockholm. Telefon:\n403700 o. 403766. Postgiro: 58820.\n\nAkt.-kap.: 150,000 kr. Antal\nindustriarb.: 10. Tillv.-värde pr år: 400,000 kr.\n— Bolaget grundat 1927.\n\nStyrelse: civiling. Harry Nyström\n(ordf.), disp. Bertil Monthan, major\nAllan Winge.\n\nDisp.: Bertil Monthan.\n\n9*",
    "structured": {
        "1": {
            "name": "AB. Svenska Kullagerfabriken",
            "location": "Katrineholmsverken, Katrineholm",
            "business": "Mekanisk verkstad och gjuteri",
            "products": "Transmissionselement, kul- och rullagerinbyggnader samt gjutgods",
            "contact": {
                "office": "Katrineholm",
                "phone": [
                    "Kullager"
                ],
                "postgiro": null,
                "head_office": null,
                "sales_offices": [
                    {
                        "location": "Göteborg",
                        "phone": null
                    }
                ],
                "telegraph": null,
                "factory_office": null,
                "factory_phone": null
            },
            "financials": {
                "capital": null,
                "employees": {
                    "industriarb": 1000
                },
                "annual_turnover": null,
                "annual_production_value": null
            },
            "foundation_year": 1886,
            "predecessor": "Grönkwists Mek. Verkstad",
            "board": [
                {
                    "name": "civiling. O. Warne",
                    "role": "övering. o. platschef"
                }
            ]
        },
        "2": {
            "name": "Svenska Käpp- & Paraplyfabriken AB.",
            "location": "Stockholm",
            "business": "Tillverkning av käppar och paraplyer",
            "products": null,
            "contact": {
                "office": "S:t Paulsg. 11",
                "phone": [
                    "405575",
                    "430309"
                ],
                "postgiro": "54629",
                "head_office": null,
                "sales_offices": null,
                "telegraph": null,
                "factory_office": null,
                "factory_phone": null
            },
            "financials": {
                "capital": "40,000 kr",
                "employees": {
                    "industriarb": 7
                },
                "annual_turnover": "150,000 kr",
                "annual_production_value": null
            },
            "foundation_year": 1903,
            "corporation_year": 1931,
            "director": "Herbert Alwert",
            "manager": "Olof Alwert"
        },
        "3": {
            "name": "Svenska AB. Le Carbone",
            "location": "Sundbyberg",
            "business": "Torrbatterifabrik",
            "products": "Torrelement, anod- och ficklampsbatterier, försäljning av kolborstar och båglampskol",
            "contact": {
                "office": null,
                "phone": [
                    "Stockholm 282615"
                ],
                "postgiro": "51208",
                "head_office": null,
                "sales_offices": null,
                "telegraph": "Lecarbone, Sundbyberg",
                "factory_office": null,
                "factory_phone": null
            },
            "financials": {
                "capital": "100,000 kr",
                "employees": {
                    "industriarb": 80
                },
                "annual_turnover": "1,000,000 kr",
                "annual_production_value": null
            },
            "foundation_year": 1928,
            "predecessor": "W. Ramsays Torrbatterifabrik",
            "corporation_year": 1931,
            "board": [
                {
                    "name": "ing. W. Ramsay",
                    "role": "ordf."
                },
                {
                    "name": "kamrer Helge Berg",
                    "role": null
                },
                {
                    "name": "dir. W. Gast",
                    "role": null
                }
            ]
        },
        "4": {
            "name": "Svenska Leksaksfabriken",
            "location": "Hälsingborg",
            "business": "Träförädlingsfabrik",
            "products": "Leksaker av trä",
            "contact": {
                "office": "AB. Bröderna Boréus, Hälsingborg",
                "phone": [
                    "13732"
                ],
                "postgiro": "13800",
                "head_office": null,
                "sales_offices": null,
                "telegraph": null,
                "factory_office": null,
                "factory_phone": null
            },
            "financials": {
                "capital": null,
                "employees": {
                    "industriarb": 45
                },
                "annual_turnover": "260,000 kr",
                "annual_production_value": null
            },
            "foundation_year": 1917,
            "owners": [
                "dir. H. Boréus",
                "sjökapten J. Ingvarsson"
            ],
            "director": "Sture Ljung"
        },
        "5": {
            "name": "Svenska Limämnesfabriken AB.",
            "location": "Landskrona",
            "business": "Kemisk-teknisk fabrik",
            "products": "Limämnen, klister, appreturmedel, valsmassa, hartslim, dextrin m.m.",
            "contact": {
                "office": "Atlantine, Landskrona",
                "phone": [
                    "245",
                    "607",
                    "617"
                ],
                "postgiro": "23170",
                "head_office": null,
                "sales_offices": [
                    {
                        "location": "Göran Wendel, Helenelund",
                        "phone": "Stockholm 350707"
                    }
                ],
                "telegraph": null,
                "factory_office": null,
                "factory_phone": null
            },
            "financials": {
                "capital": "150,000 kr",
                "employees": {
                    "industriarb": 25
                },
                "annual_turnover": "2,000,000 kr",
                "annual_production_value": null
            },
            "corporation_year": 1934,
            "board": [
                {
                    "name": "Franz Meyer",
                    "role": "verkst. dir."
                }
            ]
        },
        "6": {
            "name": "AB. Svenska Luterma",
            "location": "Malmö",
            "business": "Tunn- och emballagefabrik",
            "products": "Tunnor, varu- och transportlådor, industribackar, prappers- och mangelkorgar m.m.",
            "contact": {
                "office": "Industrig. 15",
                "phone": [
                    "72315"
                ],
                "postgiro": "38945",
                "head_office": null,
                "sales_offices": null,
                "telegraph": "Luterma, Malmö",
                "factory_office": null,
                "factory_phone": null
            },
            "financials": {
                "capital": "200,000 kr",
                "employees": {
                    "industriarb": 50
                },
                "annual_turnover": null,
                "annual_production_value": null
            },
            "corporation_year": 1933,
            "board": [
                {
                    "name": "Kristian Staerk",
                    "role": "verkst. dir."
                },
                {
                    "name": "Carl Rasmusson",
                    "role": "disp."
                }
            ]
        },
        "7": {
            "name": "Svenska Lyxmöbelfabriken",
            "location": "Blikstorp",
            "business": "Möbel- och snickerifabrik",
            "products": "Inredningar för butiker, skolor och sjukhus, hotell- och restaurangmöbler, dörrar och fönster, köksinredningar, köksskåp m.m.",
            "contact": {
                "office": null,
                "phone": [
                    "Fridene 8"
                ],
                "postgiro": "276377",
                "head_office": null,
                "sales_offices": null,
                "telegraph": null,
                "factory_office": null,
                "factory_phone": null
            },
            "financials": {
                "capital": null,
                "employees": {
                    "industriarb": 35
                },
                "annual_turnover": "450,000 kr",
                "annual_production_value": null
            },
            "foundation_year": 1904,
            "director": "disp. Karl-Axel Rittfeldt"
        },
        "8": {
            "name": "Svenska Låsmutter AB.",
            "location": "Stockholm",
            "business": "Tillverkning av kvicksilverreläer och strömbrytare samt trappljusautomater",
            "products": "Försäljning av låsmuttrar",
            "contact": {
                "office": "Södermalmstorg 4",
                "phone": [
                    "403700",
                    "403766"
                ],
                "postgiro": "58820",
                "head_office": null,
                "sales_offices": null,
                "telegraph": "Elasticstop, Stockholm",
                "factory_office": null,
                "factory_phone": null
            },
            "financials": {
                "capital": "150,000 kr",
                "employees": {
                    "industriarb": 10
                },
                "annual_turnover": "400,000 kr",
                "annual_production_value": null
            },
            "corporation_year": 1927,
            "board": [
                {
                    "name": "civiling. Harry Nyström",
                    "role": "ordf."
                },
                {
                    "name": "disp. Bertil Monthan",
                    "role": null
                },
                {
                    "name": "major Allan Winge",
                    "role": null
                }
            ]
        }
    }
}