{
    "original": "Linköping—Lino leum\n\nLinköpings Tagelspinneri, Wilh.\nMalmesten, Linköping..\n\nTillverkar tagel för möbler och\nsängutrustningar m. m.\n\nTelegr.-adr.: Tagelspinneriet,\nLinköping. Telefon: 21595. Postgiro: 11366. —\nAntal industriarb.: 20. — Firman etabl.\n1919.\n\nÄgare o. chef: disp. Wilh. Malmesten.\n\nLinköpings Tekniska Industri AB.,\n\nLinköping.\n\nTillverkar skydds- och svetsarglasögon,\narbetarskyddsmateriel samt tillbehör för\nmösstillverkning såsom mösskärmar,\nstormremmar m. m. Varumärke: »Ellti».\nBolaget driver även handel med\nsjuk-vårdsmateriel.\n\nHuvudkontor: Linköping. Telegr.-adr.:\nEllti, Linköping. Telefon: 29790.\nPostgiro: 96970. Avd.-kontor: Stockholm,\nGasverksvägen, telefon: 206411.\n\nAkt.-kap.: 12,200 kr. Antal\nindustriarb.: 25. Tillv.-värde pr år: 300,000 kr.\n— Firman etabl. 1935, bolag 1939.\n\nVerkst. dir.-. Gustaf Bigfeldt.\n\nKamrer: Lennart Lönn.\n\nLinköpings Trikåfabrik,\n\nLinköping.\n\nTillverkar trikåvaror i konstsilke och\nbomull, spec. dam- o. barnunderkläder.\n\nTelefon: 23558. Postgiro: 75033. —\nAntal industriarb.: 10. Tillv.-värde pr år:\n120,000 kr. — Firman etabl. 1930.\nÄgare o. chef: ing. Rolf Darnolf.\n\nAB. Linköpings Wellpappfabrik,\n\nLinköping.\n\nWellpappfabrik vid Malmslätt\n(Östergötl. l.).\n\nKontor: Linköping. Telefon: 20418.\nPostgiro: 25305. — Akt.-kap.: 20,000 kr.\nArb.-antal: 8. Tillv.-värde pr år: 300,000\nkr. — Fabriken anlagd 1919, bolag 1945.\n\nVerkst. direktörer: disp. Erik Ziegler\no. fabr. Gösta Ziegler.\n\nLinnefabriken Ideal, Göteborg.\n\nSyfabrik. Tillverkar skjortor, kragar,\npyjamas, skyddsrockar och slipsar m. m.\n\nKontor: Cederbourgsg. 8. Telefon:\n180636. Postgiro: 41558. — Tillv.-värde\npr år: 175,000 kr. — Firman etabl. 1925.\nChef: dir. Hj. Hellsén.\n\n473*\n\n*Linnefabriken Rich. Jonson, AB.,\n\nGöteborg.\n\nSe Sveriges Förenade Linnefabrikers\nAB., Alingsås.\n\n*AB. Linnefabriken Merkur,\n\nGöteborg.\n\nVitvarufabrik. Tillverkar kragar,\nskjortor, pyjamas, halsdukar m. m.\nVarumärken: »Merkurhuvudet», »USA» o.\n»Uni-part».\n\nKontor: 3:dje Långgatan 38 o. 40.\nTelegr.-adr.: Merkur, Göteborg. Telefon:\n145002. Postgiro: 8884.\n\nAkt.-kap.: 350,000 kr. Antal\nindustriarb.: 280. Tillv.-värde pr år: 3,000,000 kr.\n— Bolaget grundat 1919.\n\nStyrelse: disp. Folke Ellioth, fru M.\nEllioth, kontorschef Gösta Johnson.\nVerkst. dir. o. disp.: Folke Ellioth.\nKontorschef: Gösta Johnson.\n\n*AB Linnefabriken Weco,\n\nÄngelholm.\n\nKonfektionsfabrik i Rebbelberga,\nÄngelholm. Tillverkar städrockar, klänningar,\nförkläden, gymnastikbyxor, örngott och\nlakan m. m.\n\nTelefon: 444. Postgiro: 99333. —\nAkt.-kap.: 100,000 kr. Antal industriarb.: 75.\nTillv.-värde pr år: 900,000 kr. — Bolaget\ngrundat 1927.\n\nStyrelse: disp. Erik Flyger, konsul\nLars Ringborg, civiling. Sven Skoglund.\nDisp.: Erik Flyger.\n\n* Linnefabriker, Sveriges Förenade,\n\nAlingsås.\n\nSe Sveriges Förenade Linnefabrikers\nAB., Alingsås.\n\n*Linoleum AB. Forshaga, Göteborg.\n\nFabrik för tillverkning av linoleum\noch mattor av filtpapp (de sistnämnda\nav märket »Götaleum»).\n\nHuvudkontor: Göteborg; postadr.:\nGöteborg 5. Telegr.-adr.: Forshaga,\nGöteborg. Telefon: 162034—36, 165184 o.\n169734. Postgiro: 44440.\n\nStyrelsens kontor: Stockholm,\nBränn-kyrkag. 66; postadr.: Stockholm 17.\nEnsamförsäljare: Linoleum-AB. Forshagas\nFörsäljningscentral, Kungsg. 38,\nStockholm 3, telefon: 230575; Göteborg,\ntelefon: 162034—35.\n\nAkt.-kap.: 4,000,000 kr. Antal\nindustriarb.: 250. Tillv.-värde pr år: 10,350,000\nkr. — Bolaget grundat 1896.",
    "structured": {
        "firms": [
            {
                "name": "Linköpings Tagelspinneri, Wilh. Malmesten",
                "location": "Linköping",
                "business": "Tillverkar tagel för möbler och sängutrustningar m. m.",
                "contact": {
                    "telegraph": "Tagelspinneriet, Linköping",
                    "phone": [
                        "21595"
                    ],
                    "postgiro": "11366"
                },
                "financials": {
                    "capital": "N/A",
                    "employees": {
                        "industriarb": 20
                    },
                    "annual_turnover": "N/A",
                    "annual_production_value": "N/A"
                },
                "foundation_year": 1919,
                "director": "disp. Wilh. Malmesten"
            },
            {
                "name": "Linköpings Tekniska Industri AB.",
                "location": "Linköping",
                "business": "Tillverkar skydds- och svetsarglasögon, arbetarskyddsmateriel samt tillbehör för mösstillverkning såsom mösskärmar, stormremmar m. m. Bolaget driver även handel med sjuk-vårdsmateriel.",
                "contact": {
                    "telegraph": "Ellti, Linköping",
                    "phone": [
                        "29790"
                    ],
                    "postgiro": "96970",
                    "sales_offices": [
                        {
                            "location": "Stockholm, Gasverksvägen",
                            "phone": "206411"
                        }
                    ]
                },
                "financials": {
                    "capital": "12,200 kr",
                    "employees": {
                        "industriarb": 25
                    },
                    "annual_turnover": "N/A",
                    "annual_production_value": "300,000 kr"
                },
                "foundation_year": 1935,
                "corporation_year": 1939,
                "director": "Verkst. dir.-. Gustaf Bigfeldt",
                "board": [
                    {
                        "name": "Gustaf Bigfeldt",
                        "role": "Verkst. dir.-"
                    },
                    {
                        "name": "Lennart Lönn",
                        "role": "Kamrer"
                    }
                ]
            },
            {
                "name": "Linköpings Trikåfabrik",
                "location": "Linköping",
                "business": "Tillverkar trikåvaror i konstsilke och bomull, spec. dam- o. barnunderkläder.",
                "contact": {
                    "phone": [
                        "23558"
                    ],
                    "postgiro": "75033"
                },
                "financials": {
                    "employees": {
                        "industriarb": 10
                    },
                    "annual_production_value": "120,000 kr"
                },
                "foundation_year": 1930,
                "director": "ing. Rolf Darnolf"
            },
            {
                "name": "AB. Linköpings Wellpappfabrik",
                "location": "Linköping",
                "business": "Wellpappfabrik vid Malmslätt (Östergötl. l.).",
                "contact": {
                    "phone": [
                        "20418"
                    ],
                    "postgiro": "25305"
                },
                "financials": {
                    "capital": "20,000 kr",
                    "employees": {
                        "industriarb": 8
                    },
                    "annual_production_value": "300,000 kr"
                },
                "foundation_year": 1919,
                "corporation_year": 1945,
                "board": [
                    {
                        "name": "Erik Ziegler",
                        "role": "Verkst. direktör"
                    },
                    {
                        "name": "Gösta Ziegler",
                        "role": "Fabr."
                    }
                ]
            },
            {
                "name": "Linnefabriken Ideal",
                "location": "Göteborg",
                "business": "Syfabrik. Tillverkar skjortor, kragar, pyjamas, skyddsrockar och slipsar m. m.",
                "contact": {
                    "phone": [
                        "180636"
                    ],
                    "postgiro": "41558"
                },
                "financials": {
                    "annual_production_value": "175,000 kr"
                },
                "foundation_year": 1925,
                "director": "dir. Hj. Hellsén"
            },
            {
                "name": "AB. Linnefabriken Merkur",
                "location": "Göteborg",
                "business": "Vitvarufabrik. Tillverkar kragar, skjortor, pyjamas, halsdukar m. m.",
                "contact": {
                    "phone": [
                        "145002"
                    ],
                    "postgiro": "8884"
                },
                "financials": {
                    "capital": "350,000 kr",
                    "employees": {
                        "industriarb": 280
                    },
                    "annual_production_value": "3,000,000 kr"
                },
                "foundation_year": 1919,
                "board": [
                    {
                        "name": "Folke Ellioth",
                        "role": "disp."
                    },
                    {
                        "name": "fru M. Ellioth",
                        "role": "Styrelse"
                    },
                    {
                        "name": "Gösta Johnson",
                        "role": "Kontorschef"
                    }
                ]
            },
            {
                "name": "AB Linnefabriken Weco",
                "location": "Ängelholm",
                "business": "Konfektionsfabrik i Rebbelberga, Ängelholm. Tillverkar städrockar, klänningar, förkläden, gymnastikbyxor, örngott och lakan m. m.",
                "contact": {
                    "phone": [
                        "444"
                    ],
                    "postgiro": "99333"
                },
                "financials": {
                    "capital": "100,000 kr",
                    "employees": {
                        "industriarb": 75
                    },
                    "annual_production_value": "900,000 kr"
                },
                "foundation_year": 1927,
                "board": [
                    {
                        "name": "Erik Flyger",
                        "role": "disp."
                    },
                    {
                        "name": "konsul Lars Ringborg",
                        "role": "Styrelse"
                    },
                    {
                        "name": "civiling. Sven Skoglund",
                        "role": "Styrelse"
                    }
                ]
            },
            {
                "name": "Linoleum AB. Forshaga",
                "location": "Göteborg",
                "business": "Fabrik för tillverkning av linoleum och mattor av filtpapp (de sistnämnda av märket »Götaleum»).",
                "contact": {
                    "phone": [
                        "162034—36",
                        "165184",
                        "169734"
                    ],
                    "postgiro": "44440",
                    "sales_offices": [
                        {
                            "location": "Stockholm",
                            "phone": "230575"
                        },
                        {
                            "location": "Göteborg",
                            "phone": "162034—35"
                        }
                    ]
                },
                "financials": {
                    "capital": "4,000,000 kr",
                    "employees": {
                        "industriarb": 250
                    },
                    "annual_production_value": "10,350,000 kr"
                },
                "foundation_year": 1896
            }
        ]
    }
}