{
    "original": "Timsfors—Toll\n\nAntal industriarb.: 35. Årstillv.: 2 milj.\nst. murtegel. — Tegelbruket anlagt 1905.\nChef: dir. E. Prytz.\n\n’Timsfors Pappersbruk, Timsfors.\nSe Lagamilis AB., Jönköping.\n\n*E. Tingströms Möbelfabriks AB.,\n\nValdemarsvik.\n\nTillverkar möbler, fåtöljstommar,\nbygg-nadssnickerier och inredningar vid fabrik\ni Valdemarsvik (Östergötl. l.).\n\n# Telegr.-adr.: Tingsmöbler.\nValdemarsvik. Telefon: »Tingströms möbler».\nPostgiro: 87945.\n\nAkt.-kap.: 100,000 kr. Antal\nindustriarb.: 42. Tillv.-värde pr år: 500,000 kr.\n\n— Firman etabl. 1924 såsom handelsbolag,\nombildad 1931.\n\nStyrelse o. verkst. dir.: Valfrid\nTing-ström.\n\nFörsäljn.-chef: Eric Tingström.\n\nTlngvalla Bryggeri AB., Karlstad.\n\nTillverkar skattefria maltdrycker och\nkolsyrade drycker.\n\nTelefon: 10319. Postgiro: 140331. —\nAkt.-kap.: 1(55,000 kr. Arb.-antal: 9. —■\nFirman etabl. 1898, bolag 1928.\n\nStyrelse. fabr. Reinhold Ternqvist\n(ordf.), dir. Nils G. Arvedson, disp. Sven\nJansson.\n\nDisp.: Erik Ternqvist.\n’Tjernelds Radiofabrik, Stockholm.\n\nTillverkar radiomottagare,\nradiogrammofoner samt grammofon bord.\nVarumärke: »Tjerneld».\n\nKontor: Iludiksvallsg. 4. Telegr.-adr.:\nTjerneldradio, Stockholm. Telef.: 332001.\nPostgiro: 53914. Utställningslokal:\nRegeringsgatan 56. — Tillv.-värde pr år:\n700,000 kr. — Firman etabl. 1923.\nÄgare o. chef: ing. Olof Tjerneld.\nDisp.: Eric Åström.\n\n’Tjustbygdens Fruktförening u.pa.,\n\nGamleby.\n\nTillverkar äppelmos, marmelad, sylter,\nsafter, frukt- och bärkonserver, geléer\noch syltade frukter vid fabrik i Gamleby\n(Kalmar l.).\n\nTelefon: 125 o. 308. Postgiro: 33756.\nRepresentanter: Stockholm: Gebo AB.,\nSveavägen 91, telefon: 305904; Göteborg:\nNordqvist &amp; Fulton AB., V. Hamng. 9,\ntelefon: 134423; Malmö: E. Trägårdh:\nSkansg. 4 B, telefon: 16871.\n\nAndelskap.: 77,600 kr. Antal\nindustriarb.: 16. Tillv.-värde pr år: 1,000,000 kr.\n\n—\tFöreningen bildad 1922, ombildad\n1929.\n\nStyrelse: köpm. Helge Petersson\n(ordf.), disp. Seth Björk, fröken Vera\nFleetwood, folkskoll. Henrik Grim,\nträd-gårdsm. Albert Jacobson, lantbr. Knut\nJakobsson, trädgårdskonsulent Eric\nPalmgård.\n\nDisp.: Seth Björk.\n\nKamrer: Karl Arthur Edenbrandt.\n\n*Tjärby Tegelbruks AB., Genevad.\n\nTillverkar murtegel, lättegel, högporöst\ntegel, taktegel samt dräneringsrör vid\ntegelbruk i Genevad (Hallands l.).\n\nTelefon: Genevad 10. Postgiro: 79545.\n\n—\tAkt.-kap.: 130,000 kr. # Antal\nindustriarb.: 30. Årstillv.: 5 milj. st. tegelvaror.\n\n—\tFirman etabl. 1898.\n\nVerkst. dir. o. disp.: N. Herbert\nAndersson.\n\n*0. Tjärnberg, Örnsköldsvik.\n\nByggnadsentreprenörfirma för\nbostadshus, industribyggnader, skolor och\nbiografer.\n\nTelefon: 2489 o. 1539. Postgiro: 62962.\n\n—\tAntal byggnadsarb.: 180. Prod.-värde\npr år: 2,000,000 kr. — Firman etabl.\n1925.\n\nÄgare o. chef: byggm. Oscar Tjärnberg.\nKamrer: Erik Österberg.\n\n’Tobaksmonopolet, Stockholm.\n\nSe AB. Svenska Tobaksmonopolet,\nStockholm.\n\nAB. Tobo Bruk, Tobo.\n\nRadiofabrik, mek. verkstad, ^\nkjolnats-fabrik, sportvarufabrik samt skidfabrik i\nTobo (Uppsala l.).\n\nTillverkar radioapparater och\nradiolådor, cykeldelar såsom ramar, fälgar,\nkjolnät och fälgband m. m.,\nlantbruksvagnar, transportvagnar samt skidor,\nskidbindningar och skidstavar. Bolaget\ndriver även jordbruk och skogshantering.\n\nTelegr.-adr.: Tobobruk, Tobo. Telefon:\n46. Postgiro: 168139.\n\nAkt.-kap.: 500,000 kr. Antal\nindustriarb.: 220. Tillv.-värde pr år: 2,600,000 kr.\n\nBolaget, grundat 1937, är dotterbolag\ntill AB. Cykelfabriken Monark, Varberg.\nStyrelse o. disp.: Thor Warborn.\n\n’Tolls Byggnads AB., Stockholm.\n\nUtför bostads- och fabriksbyggnader,\nvattenverksbyggnader, bro- och\nkajbyggnader, grundläggningar m. m.",
    "structured": {
        "1": {
            "name": "E. Tingströms Möbelfabriks AB.",
            "location": "Valdemarsvik",
            "business": "Tillverkar möbler, fåtöljstommar, byggnadssnickerier och inredningar",
            "contact": {
                "telegraph": "Tingsmöbler",
                "phone": [
                    "Tingströms möbler"
                ],
                "postgiro": "87945"
            },
            "financials": {
                "capital": "100,000 kr",
                "employees": {
                    "Antal industriarb.": 42
                },
                "annual_production_value": "500,000 kr"
            },
            "foundation_year": 1924,
            "predecessor": "såsom handelsbolag",
            "board": [
                {
                    "name": "Valfrid Tingström",
                    "role": "Styrelse o. verkst. dir."
                },
                {
                    "name": "Eric Tingström",
                    "role": "Försäljn.-chef"
                }
            ]
        },
        "2": {
            "name": "Tlngvalla Bryggeri AB.",
            "location": "Karlstad",
            "business": "Tillverkar skattefria maltdrycker och kolsyrade drycker",
            "contact": {
                "phone": "10319",
                "postgiro": "140331"
            },
            "financials": {
                "capital": "155,000 kr",
                "employees": {
                    "Arb.-antal": 9
                }
            },
            "foundation_year": 1898,
            "board": [
                {
                    "name": "Reinhold Ternqvist",
                    "role": "Styrelse, fabr."
                },
                {
                    "name": "Nils G. Arvedson",
                    "role": "dir."
                },
                {
                    "name": "Sven Jansson",
                    "role": "disp."
                }
            ]
        },
        "3": {
            "name": "Tjernelds Radiofabrik",
            "location": "Stockholm",
            "business": "Tillverkar radiomottagare, radiogrammofoner samt grammofon bord",
            "contact": {
                "office": "Iludiksvallsg. 4",
                "telegraph": "Tjerneldradio",
                "phone": "332001",
                "postgiro": "53914",
                "sales_offices": [
                    {
                        "location": "Regeringsgatan 56",
                        "phone": "Unknown"
                    }
                ]
            },
            "financials": {
                "annual_production_value": "700,000 kr"
            },
            "foundation_year": 1923,
            "owner": "ing. Olof Tjerneld",
            "board": [
                {
                    "name": "Olof Tjerneld",
                    "role": "Ägare o. chef"
                },
                {
                    "name": "Eric Åström",
                    "role": "Disp."
                }
            ]
        },
        "4": {
            "name": "Tjustbygdens Fruktförening u.pa.",
            "location": "Gamleby",
            "business": "Tillverkar äppelmos, marmelad, sylter, safter, frukt- och bärkonserver, geléer och syltade frukter",
            "contact": {
                "phone": [
                    "125",
                    "308"
                ],
                "postgiro": "33756"
            },
            "financials": {
                "employees": {
                    "Antal industriarb.": 16
                },
                "annual_production_value": "1,000,000 kr"
            },
            "foundation_year": 1922,
            "board": [
                {
                    "name": "Helge Petersson",
                    "role": "Styrelse"
                },
                {
                    "name": "Seth Björk",
                    "role": "Disp."
                }
            ]
        },
        "5": {
            "name": "Tjärby Tegelbruks AB.",
            "location": "Genevad",
            "business": "Tillverkar murtegel, lättegel, högporöst tegel, taktegel samt dräneringsrör",
            "contact": {
                "phone": "Genevad 10",
                "postgiro": "79545"
            },
            "financials": {
                "capital": "130,000 kr",
                "employees": {
                    "Antal industriarb.": 30
                },
                "annual_production_value": "5 milj. st. tegelvaror"
            },
            "foundation_year": 1898,
            "director": "N. Herbert Andersson"
        },
        "6": {
            "name": "O. Tjärnberg",
            "location": "Örnsköldsvik",
            "business": "Byggnadsentreprenörfirma för bostadshus, industribyggnader, skolor och biografer",
            "contact": {
                "phone": [
                    "2489",
                    "1539"
                ],
                "postgiro": "62962"
            },
            "financials": {
                "employees": {
                    "Antal byggnadsarb.": 180
                },
                "annual_production_value": "2,000,000 kr"
            },
            "foundation_year": 1925,
            "owner": "Oscar Tjärnberg",
            "manager": "Erik Österberg"
        },
        "7": {
            "name": "AB. Tobo Bruk",
            "location": "Tobo",
            "business": "Radiofabrik, mek. verkstad, kjolnatsfabrik, sportvarufabrik samt skidfabrik",
            "contact": {
                "telegraph": "Tobobruk",
                "phone": "46",
                "postgiro": "168139"
            },
            "financials": {
                "capital": "500,000 kr",
                "employees": {
                    "Antal industriarb.": 220
                },
                "annual_production_value": "2,600,000 kr"
            },
            "foundation_year": 1937,
            "board": [
                {
                    "name": "Thor Warborn",
                    "role": "Styrelse o. disp."
                }
            ]
        },
        "8": {
            "name": "Tolls Byggnads AB.",
            "location": "Stockholm",
            "business": "Utför bostads- och fabriksbyggnader, vattenverksbyggnader, bro- och kajbyggnader, grundläggningar",
            "financials": {
                "employees": {
                    "unknown": "Unknown"
                }
            }
        }
    }
}