{
    "original": "Verktygsfabriken—-Wesström\n\n1.200,000 kr. — Bolaget grundat 1941,\näges av AB. Odelberg &amp; Olson, Stockholm.\n\nStyrelse: dir. Sven Ponsbach, dir.\nKarl-Erik Tiblom, ing. Olof Tiblom.\nVerkst. dir.: Olof Tiblom.\nDriftsing.: Gösta Hullner.\nKamrer: Seve Hoffström.\n\nVerktygsfabriken, doe Fielding,\n\nKristinehamn.\n\nTillverkar chassidelar för automobiler,\nkontrollmått, mätverktyg, giggar och\nfix-turer samt andra finmekaniska arbeten\npå beställning.\n\nTelefon: 10911. Postgiro: 28601. —\nAntal industriarb,: 15. Tillv.-värde pr år:\n100,000 kr. — Firman etabl. 1919.\nÄgare o. chef: fabr. Joe Fielding.\n\nAB. Verktygsfabriken Virserum,\n\nVirserum.\n\nTillverkar verktyg vid mek. verkstad i\nVirserum (Kalmar l.).\n\nTelefon: 229 o. 339. Postgiro: 266900.\n\n—\tAkt.-kap.: 25,000 kr. Antal\nindustriarb.: 25. Tillv.-värde pr år: 250,000 kr.\n\n—\tBolaget grundat 1943.\n\nVerkst. dir.: Nils Welinder (Malmö).\nVerkstadsing.: K.-J. Böiers.\nKontorschef: Sigvard Lindvall.\n\nVerktygsindustri, Johansson &amp; Co.,\n\nGnosjö.\n\nMek. verkstad i Gnosjö (Jönköp. l.).\nTillverkar excenterpressar, götpressar,\npressverktyg och automatverktyg samt\npressade massartiklar. Specialitet: 6—8\ntons excenterpressar och pressverktyg.\n\nTelefon: 147. Postgiro: 266559.\n—-Delägarekap.: 15,000 kr. Antal\nindustriarb.: 14. Tillv.-värde pr år: 190,000 kr.\n\n—\tFirman etabl. 1941,\n\nÄgare o. chefer: fabr. Nils Johansson\no. fabr. Olof Pettersson.\n\n*Wermlands-Tidningens AB.,\n\nKarlstad.\n\nSe Nya Wermlands-Tidningens AB.,\nKarlstad.\n\nVermiand, se Värmland.\n\nAug. Werner &amp; C ris Fabriks- &amp;\nHandels AB., Göteborg.\n\nBomullsspinneri, vaddfabrik och\nfärgeri (Eriksbergs Färgeri) i Anderstorp,\nLindome (Hallands l.).\n\nTillverkar bomullsgarner och täekvadd\nsamt bleker och färgar garner, strumpor,\nband, vävnader m. m. Specialitet:\nfärg-ning och appretering av\nkonstsilkevävna-der. Bolaget driver jämväl engroshandel\nmed garner, vävnader, tricotage, strumpor\nm. m.\n\nHuvudkontor: Göteborg, Kanaltorget 1.\nTelegr.-adr.: Werners, Göteborg. Telefon:\n170865. Postgiro: 12076.\n\nAkt.-kap.: 1,500,000 kr. Antal\nindustriarb.: 121 i spinneriet, 200 i färgeriet.\n\nBolaget, grundat 1894, har i sig\nupptagit Eriksbergs Färgeri AB., Göteborg.\n\nStyrelse: dir. Gustaf Werner (ordf.),\ndir. Frans H. Nilsson, dir. Axel\nNordlund.\n\nVerkst. dir.: Axel Nordlund.\n\nWernqvists Mek. Verkstads AB.,\n\nStockholm.\n\nTillverkar variabla kondensatorer för\nradioändamål.\n\nKontor: Tunnelg. 19B. Telefon: 211528.\nPostgiro: 59477. — Akt.-kap.: 25,000 kr.\nAntal industriarb.: 30. Tillv.-värde pr år:\n400,000 kr. — Bolaget grundat 1936.\n\nVerkst. dir.: K. B. Wernqvist.\n\n\"Versalefabriken, Melzer &amp; Österblom,\n\nStockholm.\n\nKemisk fabrik i Saltsjö-Nacka (Sthlms\n1.). Tillverkar tvättmedel,\nrengöringsmedel, limämnen samt lackförtunning.\nVarumärke: »Versale».\n\nKontor: Stockholm, Tjärhovsg. 6.\nTelegr.-adr.: Versale, Stockholm. Telefon:\n402464, 437998 o. 441000. Postgiro: 2958.\n\nAntal industriarb.: 15. Tillv.-värde pr\når: 750,000 kr. -— Firman etabl. 1922.\n\nÄgare o. chefer: dir. Rob. österblom o.\ning. K. Melzer.\n\nWessel &amp; Co. AB., Stockholm.\n\nElektromek. fabrik. Tillverkar\nström-st ällare. Varumärke: »Wesco».\n\nKontor: Lindhagensg. 124.\nTelegr.-adr.: Abwesco, Stockholm. Telefon:\n520200. Postgiro: 156660.\n\nAkt.-kap.: 100,000 kr. Antal\nindustriarb.: 90. Tillv.-värde pr år: 1,300,000 kr.\n— Firman etabl. 1939 under namn AB.\nWesco, nuv. bolag 1944.\n\nVerkst. dir.: ing. Alvar Mattsson.\n\n*AB. Alfr. Wesströms\nVerktygsfabrik, Rotebro.\n\nVerktygsfabrik i Rotebro (Sthlms l.).\nTillverkar verktyg för mek. verkstäder,\nsågverk, hyvlerier, råsockerfabriker etc.\n\n616*",
    "structured": {
        "firms": [
            {
                "name": "Verktygsfabriken—-Wesström",
                "location": "Kristinehamn",
                "business": "Tillverkar chassidelar för automobiler, kontrollmått, mätverktyg, giggar och fix-turer samt andra finmekaniska arbeten på beställning.",
                "contact": {
                    "phone": [
                        "10911"
                    ],
                    "postgiro": "28601"
                },
                "financials": {
                    "capital": "1,200,000 kr",
                    "employees": {
                        "industriarb": 15
                    },
                    "annual_turnover": "100,000 kr",
                    "annual_production_value": "100,000 kr"
                },
                "foundation_year": 1919,
                "owners": [
                    "fabr. Joe Fielding"
                ],
                "director": "Olof Tiblom",
                "managing_director": "Olof Tiblom",
                "sales_manager": "Gösta Hullner"
            },
            {
                "name": "AB. Verktygsfabriken Virserum",
                "location": "Virserum",
                "business": "Tillverkar verktyg vid mek. verkstad i Virserum (Kalmar l.).",
                "contact": {
                    "phone": [
                        "229",
                        "339"
                    ],
                    "postgiro": "266900"
                },
                "financials": {
                    "capital": "25,000 kr",
                    "employees": {
                        "industriarb": 25
                    },
                    "annual_turnover": "250,000 kr"
                },
                "foundation_year": 1943,
                "director": "Nils Welinder",
                "managing_director": "Nils Welinder",
                "manager": "Sigvard Lindvall"
            },
            {
                "name": "Verktygsindustri, Johansson &amp; Co.",
                "location": "Gnosjö",
                "business": "Tillverkar excenterpressar, götpressar, pressverktyg och automatverktyg samt pressade massartiklar. Specialitet: 6—8 tons excenterpressar och pressverktyg.",
                "contact": {
                    "phone": [
                        "147"
                    ],
                    "postgiro": "266559"
                },
                "financials": {
                    "capital": "15,000 kr",
                    "employees": {
                        "industriarb": 14
                    },
                    "annual_turnover": "190,000 kr"
                },
                "foundation_year": 1941,
                "owners": [
                    "fabr. Nils Johansson",
                    "fabr. Olof Pettersson"
                ]
            },
            {
                "name": "Wernqvists Mek. Verkstads AB.",
                "location": "Stockholm",
                "business": "Tillverkar variabla kondensatorer för radioändamål.",
                "contact": {
                    "office": "Tunnelg. 19B",
                    "phone": [
                        "211528"
                    ],
                    "postgiro": "59477"
                },
                "financials": {
                    "capital": "25,000 kr",
                    "employees": {
                        "industriarb": 30
                    },
                    "annual_turnover": "400,000 kr"
                },
                "foundation_year": 1936,
                "manager": "K. B. Wernqvist"
            },
            {
                "name": "Versalefabriken, Melzer &amp; Österblom",
                "location": "Stockholm",
                "business": "Kemisk fabrik i Saltsjö-Nacka (Sthlms 1.). Tillverkar tvättmedel, rengöringsmedel, limämnen samt lackförtunning.",
                "contact": {
                    "office": "Stockholm, Tjärhovsg. 6",
                    "phone": [
                        "402464",
                        "437998",
                        "441000"
                    ],
                    "postgiro": "2958"
                },
                "financials": {
                    "employees": {
                        "industriarb": 15
                    },
                    "annual_turnover": "750,000 kr"
                },
                "foundation_year": 1922,
                "owners": [
                    "dir. Rob. österblom",
                    "ing. K. Melzer"
                ]
            },
            {
                "name": "Wessel &amp; Co. AB.",
                "location": "Stockholm",
                "business": "Elektromek. fabrik. Tillverkar strömställare.",
                "contact": {
                    "office": "Lindhagensg. 124",
                    "phone": [
                        "520200"
                    ],
                    "postgiro": "156660"
                },
                "financials": {
                    "capital": "100,000 kr",
                    "employees": {
                        "industriarb": 90
                    },
                    "annual_turnover": "1,300,000 kr"
                },
                "corporation_year": 1944,
                "manager": "ing. Alvar Mattsson"
            }
        ]
    }
}