{
    "original": "Bergström—Bergsöe\n\n* Bergström &amp; Co. Klichéanstalt AB.,\n\nStockholm.\n\nTillverkar klichéer, stereotyper,\nteckningar och retuscher.\n\nKontor: Malmskillnadsg. 54. Telefon:\n230485. Postgiro: 51283. — Akt.-kap.:\n30,000 kr. Antal industriarb.: 25.\nTillv.-värde pr år: 300,000 kr. — Firman etabl.\n1918, bolag 1937.\n\nStyrelse o. verkst. dir.: fabr. Gustaf\nF. Svensson.\n\nAB. B. Bergström &amp; Co., Stockholm.\n\nKem. tekn. fabrik och svampfabrik i\nVästervik. Tillverkar tvål för industrien,\ndiskmedel för mejerier och bryggerier,\n&lt;iisktabletter, metafosfat samt\ncellulosasvamp. Varumärken: »Metso», »Mylose»,\n»Ortosil», »Bergosol», »Bergolin» o.\n»Ber-goi».\n\nHuvudkontor: Stockholm, S:t Eriksg.\n54. Telefon: 538800 o. 538828.\nPostgiro: 151635. Avd.-kontor: Göteborg, ö.\nIlamng. 14, telefon: 118281; Malmö,\nSmedjeg. 6 B, telefon: 74955.\n\nAkt.-kap.: 100,000 kr. Antal\nindustriarb.: 25. Tillv.-värde pr år (egen\ntillverkning): 1,000,000 kr. — Bolaget\ngrundat 1934.\n\nVerkst. dir.: disp. Bonde Bergström.\n\nFörsäljn.-chef: ing. Alvar Sjögren.\n\nAvd.-chefer: Göteborg: disp. Lauritz\nSandell; Malmö: disp. H. G:son Hogner.\n\nFabrihschef i Västervik: Torsten\nEklund.\n\n*AB. B. Bergströms Borstfabrik,\n\nLandskrona.\n\nTillverkar kvastar och borstar.\n\nHuvudkontor: Stockholm, S:t Eriksg.\n54. Telefon: 538800. Postgiro: 195424.\nFabrikskontor: Landskrona. Telefon:\n1281.\n\nAkt.-kap.: 40,000 kr. Antal\nindustriarb.: 15. Tillv.-värde pr år: 150,000 kr.\n— Firman etabl. 1911, bolag 1943 under\nnamn AB. Sj. Åkerlunds Borstfabrik,\nnuv. namn 1946.\n\nStyrelse: disp. Bonde Bergström (ordf.),\ndir. Kjell Beijer.\n\nVerkst. dir.: Bonde Bergström.\n\nDisp.: Bengt Olofsson.\n\n*Herman Bergström, Gävle.\n\nKonfektyrfabrik. Tillverkar\nbröstpa-stiller, dragéer, lakrits varor, kola m. m.\n\nTelefon: 2253. Postgiro: 72898. —\nFirman etabl. 1928.\n\nÄgare o. chef: fabr. Herman\nBergström.\n\n*J. L. Bergströms Snickerifabrik,\n\nSöderköping.\n\nTillverkar soffor och duschateller.\n\nTelefon: 337. Postgiro: 93161. —\nAntal industriarb.: 12. Tillv.-värde pr år:\n110,000 kr. — Firman etabl. under\n1880-talet.\n\nÄgare o. chefer: disp. Alrik Hillerås\no. fabr. A. Ingvar Björklund.\n\n*Karl Bergström, Stockholm.\n\nByggnadsentreprenörfirma för\nbostads-och affärshus, offentliga byggnader,\nindustribyggnader m. m.\n\nKontor: Drottningg. 11. Telefon:\n105806 o. 108070. Postgiro: 52322. —\nFirman etabl. 1930.\n\nÄgare o. chef: byggnadsing. Karl\nBergström.\n\n*PauI U. Bergströms AB., Stockholm.\n\nSkrädderi. Tillverkar och försäljer\nherr-, dam- och barnkläder.\nVarumärken: PUB o. PUB SON. Bolaget driver\nsåsom huvudrörelse varuhus.\n\nKontor: Gamla Brog. 20; postadr.:\nStockholm 3. Telegr.-adr.: Pub,\nStockholm. Telefon: »Paul U. Bergström».\nPostgiro: 1191.\n\nAkt.-kap.: 6,000,000 kr. — Firman,\netabl. 1882, bolag 1905, äges av\nKonsumtionsföreningen Stockholm med omnejd\nu. p. a.\n\nStyrelse: dir. Albin Johansson (ordf.),\ndir. Carl Albert Anderson, dir. Albin\nBergström, dir. Hugo Edstam, dir. Sten\nEricson, dir. Fredric Hellberg, dir.\nVitalis Johansson.\n\nVerkst. dir.: Albin Bergström.\n\n*Paul Bergsöe &amp; Son AB.,\n\nLandskrona.\n\nMetallraffinaderi och blyhytta.\nTillverkar lagermetall, bly och tenn,\naluminium- och bly legeringar, tryckerimetall,\nlöd tenn, löd tenn tråd massiv och med\nharts, finsilver, rödgods, brons och\nmässinglegeringar; raffinerar tenn- och\nblyskrot, tenn- och blyaska, rödgodsskrot\nm. m. samt slig till mjukbly.\n\nTelegr.-adr.: B ERA, Landskrona.\nTelefon: 2660—63. Postgiro: 263489.\n\nAkt.-kap.: 315,000 kr. Antal\nindustriarb.: 100. — Bolaget grundat 1942.\n\nStyrelse: adv. Henry Ljunggren (ordf.),\ndisp. Svend Bergsöe, adv. Bengt Linders.\n\nDisp.: greve Jens Frijs.\n\nKamrer: Sune Mörne.\n\nDriftsing.: Poul Christensen.\n\nLab.-chef: Niels Krarup Basse.",
    "structured": {
        "1": {
            "name": "Bergström & Co. Klichéanstalt AB.",
            "location": "Stockholm",
            "business": "Tillverkar klichéer, stereotyper, teckningar och retuscher.",
            "contact": {
                "office": "Malmskillnadsg. 54",
                "phone": [
                    "230485"
                ],
                "postgiro": "51283"
            },
            "financials": {
                "capital": "30,000 kr",
                "employees": {
                    "industriarb": 25
                },
                "annual_turnover": "300,000 kr",
                "annual_production_value": "300,000 kr"
            },
            "foundation_year": 1918,
            "corporation_year": 1937,
            "board": [
                {
                    "name": "fabr. Gustaf F. Svensson",
                    "role": "Styrelse o. verkst. dir."
                }
            ]
        },
        "2": {
            "name": "AB. B. Bergström & Co.",
            "location": "Stockholm",
            "business": "Kem. tekn. fabrik och svampfabrik i Västervik.",
            "products": "Tillverkar tvål för industrien, diskmedel för mejerier och bryggerier, isktabletter, metafosfat samt cellulosasvamp.",
            "contact": {
                "office": "S:t Eriksg. 54",
                "phone": [
                    "538800",
                    "538828"
                ],
                "postgiro": "151635",
                "sales_offices": [
                    {
                        "location": "Göteborg",
                        "phone": "118281"
                    },
                    {
                        "location": "Malmö",
                        "phone": "74955"
                    }
                ]
            },
            "financials": {
                "capital": "100,000 kr",
                "employees": {
                    "industriarb": 25
                },
                "annual_production_value": "1,000,000 kr"
            },
            "corporation_year": 1934,
            "board": [
                {
                    "name": "disp. Bonde Bergström",
                    "role": "Verkst. dir."
                },
                {
                    "name": "ing. Alvar Sjögren",
                    "role": "Försäljn.-chef"
                },
                {
                    "name": "disp. Lauritz Sandell",
                    "role": "Avd.-chef"
                },
                {
                    "name": "disp. H. G:son Hogner",
                    "role": "Avd.-chef"
                }
            ]
        },
        "3": {
            "name": "AB. B. Bergströms Borstfabrik",
            "location": "Landskrona",
            "business": "Tillverkar kvastar och borstar.",
            "contact": {
                "office": "S:t Eriksg. 54",
                "phone": "538800",
                "postgiro": "195424",
                "factory_office": "Landskrona",
                "factory_phone": "1281"
            },
            "financials": {
                "capital": "40,000 kr",
                "employees": {
                    "industriarb": 15
                },
                "annual_production_value": "150,000 kr"
            },
            "corporation_year": 1943,
            "original_name": "AB. Sj. Åkerlunds Borstfabrik",
            "current_name_year": 1946,
            "board": [
                {
                    "name": "disp. Bonde Bergström",
                    "role": "Styrelse"
                },
                {
                    "name": "dir. Kjell Beijer",
                    "role": "Styrelse"
                }
            ]
        },
        "4": {
            "name": "Herman Bergström",
            "location": "Gävle",
            "business": "Konfektyrfabrik. Tillverkar bröstpa-stiller, dragéer, lakrits varor, kola m. m.",
            "contact": {
                "phone": "2253",
                "postgiro": "72898"
            }
        },
        "5": {
            "name": "J. L. Bergströms Snickerifabrik",
            "location": "Söderköping",
            "business": "Tillverkar soffor och duschateller.",
            "contact": {
                "phone": "337",
                "postgiro": "93161"
            },
            "financials": {
                "employees": {
                    "industriarb": 12
                },
                "annual_production_value": "110,000 kr"
            }
        },
        "6": {
            "name": "Karl Bergström",
            "location": "Stockholm",
            "business": "Byggnadsentreprenörfirma för bostads-och affärshus, offentliga byggnader, industribyggnader m. m.",
            "contact": {
                "office": "Drottningg. 11",
                "phone": [
                    "105806",
                    "108070"
                ],
                "postgiro": "52322"
            }
        },
        "7": {
            "name": "PauI U. Bergströms AB.",
            "location": "Stockholm",
            "business": "Skrädderi. Tillverkar och försäljer herr-, dam- och barnkläder.",
            "products": "Varumärken: PUB o. PUB SON.",
            "financials": {
                "capital": "6,000,000 kr"
            },
            "corporation_year": 1905,
            "ownership": "äges av Konsumtionsföreningen Stockholm med omnejd u. p. a.",
            "board": [
                {
                    "name": "dir. Albin Johansson",
                    "role": "Styrelse"
                },
                {
                    "name": "dir. Carl Albert Anderson",
                    "role": "Styrelse"
                },
                {
                    "name": "dir. Albin Bergström",
                    "role": "Styrelse"
                },
                {
                    "name": "dir. Hugo Edstam",
                    "role": "Styrelse"
                },
                {
                    "name": "dir. Sten Ericson",
                    "role": "Styrelse"
                },
                {
                    "name": "dir. Fredric Hellberg",
                    "role": "Styrelse"
                },
                {
                    "name": "dir. Vitalis Johansson",
                    "role": "Styrelse"
                }
            ]
        },
        "8": {
            "name": "Paul Bergsöe & Son AB.",
            "location": "Landskrona",
            "business": "Metallraffinaderi och blyhytta.",
            "products": "Tillverkar lagermetall, bly och tenn, aluminium- och blylegeringar, tryckerimetall, löd tenn, finsilver, rödgods, brons och mässinglegeringar.",
            "contact": {
                "telegraph": "B ERA, Landskrona",
                "phone": "2660",
                "postgiro": "263489"
            },
            "financials": {
                "capital": "315,000 kr",
                "employees": {
                    "industriarb": 100
                }
            },
            "corporation_year": 1942,
            "board": [
                {
                    "name": "adv. Henry Ljunggren",
                    "role": "Styrelse"
                },
                {
                    "name": "disp. Svend Bergsöe",
                    "role": "Styrelse"
                },
                {
                    "name": "adv. Bengt Linders",
                    "role": "Styrelse"
                }
            ],
            "manager": "Poul Christensen",
            "lab_chief": "Niels Krarup Basse"
        }
    }
}