{
    "original": "Klippan—Kloster\n\n\"Klippans Karosserifabri k,\n\nKlippan.\n\nSnickeri-, plåt-, smides- och\ntapetseri-verkstäder i Klippan (Kristianst. l.).\nTillverkar karosserier.\n\nTelefon: 306 o. 452. — Antal\nindustriarb.: 50. Tillv.-värde pr år: 700,000 kr.\n\n—\tFirman etabl. 1926.\nDisp.: Sven Danielsson.\n\n\"AB. Klippans Läderfabrik,\n\nKlippan.\n\nLäderfabrik i Klippan (Kristianst. l.).\nTillverkar boxkalv, boxsidor, phönixkalv,\nsportkalv, sportläder, bokbinderi- och\nmöbelläder. Varumärken: »Phönix»,\n»Va-nessa», »Nordland» o. »Engelkid».\n\nTelegr.-adr.: Läderfabriken, Klippan.\nTelefon: »Klippans Läder». Postgiro:\n76060.\n\nAkt.-kap.: 750,000 kr. Antal\nindustriarb.: 150. Tillv.-värde pr år: 5,000,000 kr.\n\nFabriken uppfördes 1906. Förutv.\nfirmanamn Chromgarveriet Klippan AB.,\nnuv. namn 1938.\n\nStyrelse: bankdir. O. D. Bill sten\n(ordf.), dir. I. Ekblom, disp. Gösta\nGrönvall, med. dr Herman Grönvall, dir.\nSture Grön vall, ing. Knut Hjort, disp.\nAllan Holm.\n\nVerkst. dir. o. disp.: Allan Holm.\nFabrikschef: Knut Hjort.\n\n\"Klippans Tegelbruks AB.,\n\nKlippan.\n\nTillverkar mur- och taktegel samt\ndräneringsrör vid tegelbruk i Klippan\n(Kristianst. l.). Bolaget driver även jordbruk.\n\nTelefon. 65. Postgiro: 91555. —\nAkt.-kap.: 198,000 kr. Antal industriarb.: 52.\nÅrstillv.: 4 milj. st. tegelvaror. —\nBolaget grundat 1898.\n\nStyrelse: kamrer Gustaf Plöjel (ordf.),\nfru Hanna Larsson, disp. Ivar Plöjel.\nVerkst. dir.: Ivar Plöjel.\n\n\"Klippans Yllefabrik &amp; Färgeri AB.,\n\nKlippan.\n\nUllspinneri och färgeri i Klippan\n(Kristianst. l.). Tillverkar strump- och\nväv-garner samt hemslöjdsgarner.\n\nTelegr.-adr.: Yllefabriken, Klippan.\nTelefon: 139. Postgiro: 84200. —\nAkt.-kap.: 216,000 kr. Antal industriarb.: 30.\n\n—\tFirman etabl. 1882, bolag 1919.\nStyrelse; jur. kand. Gustaf Magnusson,\n\ning. Sven Magnusson, disp. Ivar\nSjunnes-son.\n\nVerkst. dir.: Sven Magnusson.\n\n\"Klockrike Tegelbruk, Klockrihe.\n\nTegelbruk vid Norra Tororp,\nKlockrike, samt vid Kungs Norrby, Borensberg\n(båda i Östergötl. l.). Tillverkar en- och\ntvåkupigt taktekel samt murtegel,\nnock-tegel och dräneringsrör.\n\nKontor: Klockrike. Telefon: 40.\nPostgiro: Norra Tororp: 76884; Kungs\nNorrby: 76883.\n\nAntal industriarb.: 35, varav vid Norra\nTororp 20. Årstillv.: 1,6 milj. st.\ntegelvaror. — Firman etabl. 1918 under namn\nNorra Tororps &amp; Kungs Norrby\nTegelbruk, nuv. namn 1946.\n\nDisp.: Roland Gustafsson.\n\n\"Klosters AB., Långshyttan.\n\nJärnverk med masugn, martin- och\nelektrostålverk, götvalsverk, band- och\ntrådvalsverk, kallvalsverk, gjuteri och\nmek. verkstad i Långshyttan (Kopparb.\n1.). Betr. tillverkningar, se under\nFager-sta Bruks AB., Fagersta.\n\nKontor: Långshyttan. Telegr.-adr.:\nKloster, Hedemora. Telefon:\nLångshyttan 380. — Akt.-kap.: 1,000,000 kr.\n\nBolaget grundat 1871. Bolagets verk\noch anläggningar arrenderas av Fagersta\nBruks AB., som även handhar\nförsäljningen av brukets produkter.\n\nStyrelse: disp. Hj. Åselius (ordf.), dir.\nNils Elfström, övering. Gösta Sterky.\n\nPlatschef: Gösta Sterky.\n\n\"AB. Klosters Fabriker,\n\nJ önJcöping.\n\nFabriker för tillverkning av takpapp\noch kem. tekn. produkter i Bankeryd\n(Jönköp. l.).\n\nTillverkar asfaltpapp, underhållsfri\npapp (»Klosterit»), förhydnings- och\nisoleringspapp, bitumenfilt samt\nbitumen-mattor, asfaltemulsioner (»To ron» o.\n»Ydrolén») för isolerings- och\nklistrings-ändamål och golvläggning, asfaltlösningar\n(»Bitumol» o. »Klosterol»), asfaltlim för\nklistring av parkett, mattcement,\nträkonserveringsmedel (»Cupon»), golvpolish,\nschellackmassa för grammofonskivor,\ngolvplattor av tile-typ samt konsthartser\n(bakelit o. karbamid) i form av rena\nhartser, läcker, pressmassa, lim m. m.\nFirman utför även isoleringar och\ntaktäckningar.\n\nTelegr.-adr.: Hermans, Jönköping.\nTelefon: Jönköping 137 o. 147 o. Bankeryd\n4 o. 137. Postgiro: 11562.\n\nAkt.-kap.: 500,000 kr. Antal\nindustriarb.: 50. Tillv.-värde pr år: 2,500,000 kr.\n— Bolaget grundat 1903.",
    "structured": {
        "1": {
            "name": "Klippans Karosserifabrik",
            "location": "Klippan",
            "business": "Snickeri-, plåt-, smides- och tapetseri-verkstäder",
            "contact": {
                "phone": [
                    "306",
                    "452"
                ]
            },
            "financials": {
                "employees": {
                    "industriarb": 50
                },
                "annual_turnover": "700,000 kr",
                "annual_production_value": "700,000 kr"
            },
            "foundation_year": 1926,
            "director": "Sven Danielsson"
        },
        "2": {
            "name": "AB. Klippans Läderfabrik",
            "location": "Klippan",
            "business": "Läderfabrik",
            "products": "Tillverkar boxkalv, boxsidor, phönixkalv, sportkalv, sportläder, bokbinderi- och möbelläder",
            "contact": {
                "telegraph": "Läderfabriken, Klippan",
                "phone": "Klippans Läder",
                "postgiro": "76060"
            },
            "financials": {
                "capital": "750,000 kr",
                "employees": {
                    "industriarb": 150
                },
                "annual_turnover": "5,000,000 kr"
            },
            "foundation_year": 1906,
            "current_name_year": 1938,
            "board": [
                {
                    "name": "O. D. Billsten",
                    "role": "ordf."
                },
                {
                    "name": "I. Ekblom",
                    "role": "disp."
                },
                {
                    "name": "Gösta Grönvall",
                    "role": "disp."
                },
                {
                    "name": "Herman Grönvall",
                    "role": "med. dr"
                },
                {
                    "name": "Sture Grönvall",
                    "role": "disp."
                },
                {
                    "name": "Knut Hjort",
                    "role": "ing."
                },
                {
                    "name": "Allan Holm",
                    "role": "disp."
                }
            ],
            "manager": "Allan Holm"
        },
        "3": {
            "name": "Klippans Tegelbruks AB.",
            "location": "Klippan",
            "business": "Tillverkar mur- och taktegel samt dräneringsrör",
            "contact": {
                "phone": "65",
                "postgiro": "91555"
            },
            "financials": {
                "capital": "198,000 kr",
                "employees": {
                    "industriarb": 52
                },
                "annual_production_value": "4 milj. st. tegelvaror"
            },
            "foundation_year": 1898,
            "board": [
                {
                    "name": "Gustaf Plöjel",
                    "role": "kamrer"
                },
                {
                    "name": "Hanna Larsson",
                    "role": "fru"
                },
                {
                    "name": "Ivar Plöjel",
                    "role": "disp."
                }
            ],
            "manager": "Ivar Plöjel"
        },
        "4": {
            "name": "Klippans Yllefabrik & Färgeri AB.",
            "location": "Klippan",
            "business": "Ullspinneri och färgeri",
            "products": "Tillverkar strump- och väv-garner samt hemslöjdsgarner",
            "contact": {
                "telegraph": "Yllefabriken, Klippan",
                "phone": "139",
                "postgiro": "84200"
            },
            "financials": {
                "capital": "216,000 kr",
                "employees": {
                    "industriarb": 30
                }
            },
            "foundation_year": 1882,
            "corporation_year": 1919,
            "board": [
                {
                    "name": "Gustaf Magnusson",
                    "role": "jur. kand."
                },
                {
                    "name": "Sven Magnusson",
                    "role": "ing."
                },
                {
                    "name": "Ivar Sjunnes-son",
                    "role": "disp."
                }
            ],
            "manager": "Sven Magnusson"
        },
        "5": {
            "name": "Klockrike Tegelbruk",
            "location": "Klockrihe",
            "business": "Tegelbruk",
            "products": "Tillverkar en- och tvåkupigt taktekel samt murtegel, nock-tegel och dräneringsrör",
            "contact": {
                "phone": "40",
                "postgiro": "Norra Tororp: 76884; Kungs Norrby: 76883"
            },
            "financials": {
                "employees": {
                    "industriarb": 35
                },
                "annual_production_value": "1,6 milj. st. tegelvaror"
            },
            "foundation_year": 1918,
            "current_name_year": 1946,
            "director": "Roland Gustafsson"
        },
        "6": {
            "name": "Klosters AB",
            "location": "Långshyttan",
            "business": "Järnverk med masugn, martin- och elektrostålverk, götvalsverk, band- och trådvalsverk, kallvalsverk, gjuteri och mek. verkstad",
            "contact": {
                "telegraph": "Kloster, Hedemora",
                "phone": "Långshyttan 380"
            },
            "financials": {
                "capital": "1,000,000 kr"
            },
            "foundation_year": 1871,
            "board": [
                {
                    "name": "Hj. Åselius",
                    "role": "disp."
                },
                {
                    "name": "Nils Elfström",
                    "role": "dir."
                },
                {
                    "name": "Gösta Sterky",
                    "role": "övering."
                }
            ],
            "manager": "Gösta Sterky"
        },
        "7": {
            "name": "AB. Klosters Fabriker",
            "location": "Jönköping",
            "business": "Fabriker för tillverkning av takpapp och kem. tekn. produkter",
            "products": "Tillverkar asfaltpapp, underhållsfri papp (»Klosterit»), förhydnings- och isoleringspapp, bitumenfilt samt bitumen-mattor, asfaltemulsioner (»Toron» o. »Ydrolén») för isolerings- och klistrings-ändamål och golvläggning, asfaltlösningar (»Bitumol» o. »Klosterol»), asfaltlim för klistring av parkett, mattcement, träkonserveringsmedel (»Cupon»), golvpolish, schellackmassa för grammofonskivor, golvplattor av tile-typ samt konsthartser (bakelit o. karbamid) i form av rena hartser, läcker, pressmassa, lim m. m.",
            "contact": {
                "telegraph": "Hermans, Jönköping",
                "phone": "Jönköping 137 o. 147 o. Bankeryd 4 o. 137",
                "postgiro": "11562"
            },
            "financials": {
                "capital": "500,000 kr",
                "employees": {
                    "industriarb": 50
                },
                "annual_turnover": "2,500,000 kr"
            },
            "foundation_year": 1903
        }
    }
}