{
    "original": "Fliseryd—Flygsfors\n\n*Fllseryds Ackumulatorfabrik,\n\nFliseryd.\n\nSe Svenska Ackumulator AB. Jungner,\nStockholm.\n\n*\tFloby Industri AB., Floby.\n\nTrätoffelfabrik och karosserifabrik i\nFloby (Skarab. l.). Tillverkar trätofflor,\nstrandtofflor, träbottenkängor m. m. samt\nförarhytter och flak för lastbilar,\nkaros-serier för skåpbilar, för brand- och\nambulansbilar, för omnibussar m. m.\n\nTelefon: 180 o. 20. Postgiro: 87530\n(trätoffelfabriken) o. 268826\n(karosserifabriken).\n\nAkt.-kap.: 41,000 kr. Antal\nindustriarb.: 27, varav 22 vid karosserifabriken.\nTillv.-värde pr år: 275,000 kr. — Bolaget\ngrundat 1928.\n\nStyrelse: handl. Arvid öman (ordf.),\nhandl. Bengt Kringlund, hemmansäg.\nSven Samuelsson.\n\nVerkst. dir.: Arvid öman.\nFörest, för trätof felfabriken: verkm.\nOlof Olsson.\n\nFörest, för karosserifabriken: verkm.\nErland Persson.\n\nAB. Floby SSSketrikå, Floby.\n\nTillverkar herr- och damunderkläder i\npläterat macco och interlockutförande\nvid trikåfabrik i Floby (Skarab. l.).\nVarumärke: »AB. F. S. T.-trikå».\n\nTelefon: 80. Postgiro: 93518. —\nAkt.-kap.: 48,000 kr. Antal industriarb.: 25.\nTillv.-värde pr år: 460,000 kr. — Bolaget\ngrundat 1930.\n\nDisp.: Valentin Johansson.\n\n*\tFloby Snickerifabrik, Floby.\n\nTillverkar byggnadssnickerier vid\nfabrik i Floby (Skarab. l.).#\n\nTelefon: 22. — Antal industriarb.: 15.\n— Firman etabl. 1915.\n\nÄgare o. chef: fabr. Karl Thiel.\n\n*AB. Flobyverken, Göteborg.\n\nMek. verkstad i Floby (Skarab. l.).\nTillverkar maskiner och -delar för\nlivsmedels- och kemisk-teknisk industri,\ngrov-och tunnplåtsarbeten, speciellt för\nventilations- och\nluftkonditioneringsanläggningar, smidesarbeten, järnkonstruktioner\nsamt transportanordningar, utför el- och\ngassvetsning.\n\nKontor o. ensamförsälj.: AB. Calvert\n&amp; Co., Göteborg, N. Larmg. 11—13.\nTelefon: »Calvert &amp; Compani». Postgiro:\n240825.\n\nAkt.-kap.: 100,000 kr. Antal\nindustriarb.: 20. Tillv.-värde pr år: 300,000 kr.\n— Verkstaden anlagd 1942 som avdelning\ntill AB. Calvert &amp; Co., Göteborg, särskilt\nbolag 1946.\n\nStyrelse: dir. Axel Calvert (ordf.), dir.\nJohan Kinde, civiling. Axel Weilenmann.\n\nVerkst. dir.: A. Weilenmann.\n\nAB. Flöda Parkettfabrik, Flöda.\n\nTillverkar parkettstav samt sågat\nlöv-trävirke vid fabrik i Flöda (Älvsb. l.).\n\nTelefon: Flöda 110. — Akt.-kap.:\n60,000 kr. Antal industriarb.: 30.\nTillv.-värde pr år: 500,000 kr. — Bolaget\ngrundat 1940.\n\nStyrelse o. verkst. dir.: Henrik Spak.\n\nFlora, Tekniska Fabriken, Gävle.\n\nSe Tekniska AB. Flora, Gävle.\n\nSven Floréns Kravattlndustri AB.,\n\nKumla.\n\nTillverkar slipsar, kravatter,\nbutter-flies och rosetter vid fabrik i Kumla\n(Örebro l.). Varumärke: »Barry».\n\nTelefon: Örebro 70258. Postgiro:\n131360. — Akt.-kap.: 15,000 kr. Antal\nindustriarb.: 20. Tillv.-värde pr år:\n200,000 kr. — Bolaget grundat^ 1936.\n\nVerkst. dir.: Sven-Olof Floren.\n\nAB. Floretta, Stockholm.\n\nTrikåfabrik. Tillverkar dam- och\nherrunderkläder. Varumärke: »Floretta».\n\nKontor: Herkulesg. 11. Telefon: 207270\no. 207170. Postgiro: 3176.\n\nAkt.-kap.: 100,000 kr. Antal\nindustriarb.: 75. — Bolagt grundat 1926.\n\nStyrelse o. verkst. dir.: Leon Gruvén.\n\n*Flugeby Ullspinneri AB., Nässjö.\n\nTillverkar allgarn och filtar.\n\nTelefon: 530 o. 532. Postgiro: 6842. —\nAkt.-kap.: 210,000 kr. Antal industriarb.:\n15. Tillv.-värde pr år: 400,000 kr. —\nFirman etabl. 1886, bolag 1924.\n\nStyrelse: disp. Emil Fredriksson\n(ordf.), köpman Erik Fredriksson, fabr.\nWiktor Fredriksson.\n\nVerkst. dir. o. disp.: Emil Fredriksson.\n\n*AB. Flygsfors Glasbruk,\n\nOrrefors.\n\nGlasbruk vid Flygsfors (Kalmar l.).\nTillverkar belysningsglas och konservglas,\nkem. tekn. glas samt glas för speceriskåp.",
    "structured": {
        "firms": [
            {
                "name": "Fllseryds Ackumulatorfabrik",
                "location": "Fliseryd",
                "business": "Ackumulatorer",
                "contact": {
                    "office": "Fliseryd",
                    "postgiro": "87530",
                    "head_office": "Stockholm"
                },
                "financials": {
                    "capital": "41,000 kr",
                    "employees": {
                        "total": 27
                    },
                    "annual_turnover": "275,000 kr"
                }
            },
            {
                "name": "Floby Industri AB.",
                "location": "Floby",
                "business": "Trätofflor, karosserier",
                "contact": {
                    "office": "Floby",
                    "phone": [
                        "180",
                        "20"
                    ],
                    "postgiro": "87530",
                    "head_office": "Stockholm"
                },
                "financials": {
                    "capital": "41,000 kr",
                    "employees": {
                        "karosserifabriken": 22,
                        "total": 27
                    },
                    "annual_turnover": "275,000 kr"
                }
            },
            {
                "name": "AB. Floby SSSketrikå",
                "location": "Floby",
                "business": "Herr- och damunderkläder",
                "contact": {
                    "office": "Floby",
                    "phone": "80",
                    "postgiro": "93518"
                },
                "financials": {
                    "capital": "48,000 kr",
                    "employees": {
                        "total": 25
                    },
                    "annual_turnover": "460,000 kr"
                }
            },
            {
                "name": "Floby Snickerifabrik",
                "location": "Floby",
                "business": "Byggnadssnickerier"
            },
            {
                "name": "AB. Flobyverken",
                "location": "Göteborg (Floby)",
                "business": "Mekanisk verkstad"
            },
            {
                "name": "AB. Flöda Parkettfabrik",
                "location": "Flöda",
                "business": "Parketttillverkning"
            },
            {
                "name": "Sven Floréns Kravattlndustri AB.",
                "location": "Kumla",
                "business": "Slipsar, kravatter, butterflys and rosetter"
            },
            {
                "name": "AB. Floretta",
                "location": "Stockholm",
                "business": "Trikåfabrik"
            },
            {
                "name": "Flugeby Ullspinneri AB.",
                "location": "Nässjö",
                "business": "Allgarn och filtar"
            },
            {
                "name": "AB. Flygsfors Glasbruk",
                "location": "Orrefors",
                "business": "Glasbruk"
            }
        ]
    }
}