{
    "original": "Fermefors—Fiedler\n\nAkt.-kap.: 174,000 kr. Antal\nindustriarb.: 55. Tillv.-värde pr år: 1,000,000 kr.\n\n—\tFirman etabl. 1894, bolag 1897.\nStyrelse: dir. Carl W. Persson (ordf.),\n\nadv. S. de Maré, ing. Bertil Persson.\nVerJcst. dir.: C. W. Persson.\n\n*Fermefors Fabriks AB., Borås.\n\nToffelfabrik. Tillverkar skinn- och\nfilttofflor med mjuk sula.\n\nTelegr.-adr.: Fermab, Borås. Telefon:\n18480. Postgiro: 133490.\n\nAkt.-kap.: 45,000 kr. Antal\nindustri-ar!). : 27. Tillv.-värde pr år: 500,000 kr.\n\n—\tBolaget grundat 1945.\n\nStyrelse o. verJcst. dir.: fabr. Olle\nFermefors.\n\n*Fermia, Hälsingborg.\nSe Nya AB. Fermia, Hälsingborg.\n\nGust. Ferngrens Verktygsfabrik,\n\nNorrtälje.\n\nTillverkar brotsehar, fräs ar och\ngäng-verktyg.\n\nTelefon: 390 o. 690. Postgiro: 29235. —\nAntal industriarb.: 30. — Firman etabl.\n1916.\n\nÄgare o. chef: fabr. Gust. Ferngren.\nVerJc stads chef: Karl-Axel Ferngren.\nKamrer: Hans Alvén.\n\nAB. Holger Fernlund, Borås.\nKonfektionsfabrik. Tillverkar herr- och\ndamtrenchcoats, byxor och fritidskläder.\nVarumärke: »Holfer».\n\nTelegr.-adr.: Holfer, Borås. Telefon:\n54270. Postgiro: 264504.\n\nAkt.-kap.: 250,000 kr. Antal\nindustriarb.: 75. Tillv.-värde pr år: 800,000 kr.\n\n—\tBolaget grundat 1943.\nVerJcst. dir.: Holger Fernlund.\nKamrer: Erik Zachrisson.\n\n*A. E. Fernstedt &amp; C:o, Motala\nTekniska Fabrik, Motala.\n\nKem.-tekn. fabrik. Tillverkar\nmaskinsmörjor, impregneringsoljor samt\nrem-och kugghjulssmörjor.\n\nTelegr.-adr.: Fernstedtco, Motala.\nTelefon: 107. Postgiro: 28205. — Arb.-antal:\n5. — Firman etabl. 1890.\n\nÄgare o. chef: disp. Gotthard Fernstedt.\n(Jfr annons nr 93.)\n\n*AB. A. K. Fernströms Granit-\n\nindustrier, Karlshamn.\n\nStenhuggerier på olika platser inom\nKristianstads, Blekinge, Kalmar och Kro-\n\nli\n\nnobergs län, Göteborgs och Bohus län\nsamt i Norge. Tillverkar blocksten,\nbyggnadssten, gat- och smågatsten, kantsten,\nmakadam samt div. granitprodukter.\n\nHuvudkontor: Karlshamn. Telegr.-adr.:\nFernström, Karlshamn. Telefon: »A. K.\nFernström». Postgiro: 6132.\n\nAkt.-kap.: 1,800,000 kr. — Firman\netabl. 1885, bolag 1925.\n\nStyrelse: dir. Eric K. Fernström (ordf.),\nfru Emma Fernström, disp. Holger K.\nFernström, jur. dr Axel Boos, bankdir.\nAlgot Riider.\n\nVerkst. dir.: Eric K. Fernström.\n\nV. verkst. dir.: Sten Hedén.\n\nAvd.-chefer: för blockstensavd.:\nHerman Strömberg; för byggnadsstensavd.:\nBertil Gustafsson; för gatstensavd.: E. V.\nWerkström; för kassaavd.: Edvin Nyhlén.\n\n*AB. F er ro legeringar, Stockholm.\n\nTillverkar f errolegeringar, kromalun\noch galvaniserad plåt genom sitt\ndotterbolag, AB. Metallurgisk Industri,\nTrollhättan. Bolaget idkar jämväl handel med\nlegeringar av främmande fabrikat.\n\nKontor: Stockholm, Arsenalsg. 2.\nTelegr.-adr.: Legeringar, Stockholm. Telefon:\n235130. Postgiro: 53989. — Akt.-kap.:\n4,000,000 kr. — Bolaget grundat 1913.\n\nStyrelse: civiling. O. Drakenberg, dir.\nV. A. Eriksson, dir. S. W. Roos.\n\nVerkst. dir.: O. Drakenberg.\n\nFabrikschef: bergsing. H. Willners.\n\n(Jfr annons nr 14.)\n\n*AB. Ferrosan, Malmö.\n\nLäkemedelsfabrik. Tillverkar läkemedel\nsåsom järnpreparat, kalkpreparat,\nvitaminpreparat m. fl. Fabriksmärke: IDO.\n\nKontor: Celsiusg. 35. Telegr.-adr.:\nFerrosan, Malmö. Telefon: 71850.\nPostgiro: 38256. — Akt.-kap.: 250,000 kr.\nAntal industriarb.: 40. — Firman etabl.\n1919.\n\nStyrelse: bankdir. Alexius Söderberg\n(ordf.), dir. S. Andersen, dir. J. Ryné.\n\nVerJcst. dir.: J. Ryné.\n\nDisp.: J. Nörgård.\n\nKamrer: Göte Svärd.\n\n*AB. Fiedler &amp; Lundgren, Göteborg.\n\nReseffektfabrik. Tillverkar reseffekter\nsåsom kappsäckar, resväskor och etuier.\nSpecialiteter: damhandväskor, portföljer,\nplånböcker och portmonnäer.\n\nKontor: Mölndalsv. 46—48, postadr.:\nGöteborg 14. Telegr.-adr.: Ladybags,\nGöteborg. Telefon: 187110. Postgiro: 12362.",
    "structured": {
        "firms": [
            {
                "name": "Fermefors Fabriks AB",
                "location": "Borås",
                "business": "Toffelfabrik",
                "products": "Tillverkar skinn- och filtttofflor med mjuk sula.",
                "contact": {
                    "office": "Borås",
                    "phone": [
                        "18480"
                    ],
                    "postgiro": "133490",
                    "telegraph": "Fermab",
                    "factory_office": "Borås",
                    "factory_phone": "Not provided"
                },
                "financials": {
                    "capital": "174,000 kr",
                    "employees": {
                        "industriarb": 55
                    },
                    "annual_turnover": "1,000,000 kr",
                    "annual_production_value": "Not provided"
                },
                "foundation_year": 1894,
                "corporation_year": 1897,
                "board": [
                    {
                        "name": "Carl W. Persson",
                        "role": "ordf."
                    },
                    {
                        "name": "S. de Maré",
                        "role": "Not provided"
                    },
                    {
                        "name": "Bertil Persson",
                        "role": "Not provided"
                    }
                ],
                "owner": "Not provided",
                "director": "C. W. Persson",
                "managing_director": "Not provided",
                "sales_manager": "Not provided",
                "manager": "Not provided"
            },
            {
                "name": "Fermia",
                "location": "Hälsingborg",
                "business": "Not provided",
                "products": "Not provided",
                "contact": {
                    "office": "Not provided",
                    "phone": [
                        "Not provided"
                    ],
                    "postgiro": "Not provided",
                    "telegraph": "Not provided",
                    "factory_office": "Not provided",
                    "factory_phone": "Not provided"
                },
                "financials": {
                    "capital": "45,000 kr",
                    "employees": {
                        "industri-arb!": 27
                    },
                    "annual_turnover": "500,000 kr",
                    "annual_production_value": "Not provided"
                },
                "foundation_year": 1945,
                "corporation_year": "Not provided",
                "board": [
                    {
                        "name": "Olle Fermefors",
                        "role": "Not provided"
                    }
                ],
                "owner": "Not provided",
                "director": "Not provided",
                "managing_director": "Not provided",
                "sales_manager": "Not provided",
                "manager": "Not provided"
            },
            {
                "name": "Gust. Ferngrens Verktygsfabrik",
                "location": "Norrtälje",
                "business": "Tillverkar brotsehar, fräs ar och gäng-verktyg.",
                "products": "Not provided",
                "contact": {
                    "office": "Morrtälje",
                    "phone": [
                        "390",
                        "690"
                    ],
                    "postgiro": "29235",
                    "telegraph": "Not provided",
                    "factory_office": "Not provided",
                    "factory_phone": "Not provided"
                },
                "financials": {
                    "capital": "Not provided",
                    "employees": {
                        "Antal industriarb": 30
                    },
                    "annual_turnover": "Not provided",
                    "annual_production_value": "Not provided"
                },
                "foundation_year": 1916,
                "corporation_year": "Not provided",
                "board": [
                    {
                        "name": "Gust. Ferngren",
                        "role": "Ägare o. chef"
                    },
                    {
                        "name": "Karl-Axel Ferngren",
                        "role": "VerJc stads chef"
                    },
                    {
                        "name": "Hans Alvén",
                        "role": "Kamrer"
                    }
                ],
                "owner": "Not provided",
                "director": "Not provided",
                "managing_director": "Not provided",
                "sales_manager": "Not provided",
                "manager": "Not provided"
            },
            {
                "name": "AB. Holger Fernlund",
                "location": "Borås",
                "business": "Konfektionsfabrik",
                "products": "Tillverkar herr- och damtrenchcoats, byxor och fritidskläder.",
                "contact": {
                    "office": "Borås",
                    "phone": [
                        "54270"
                    ],
                    "postgiro": "264504",
                    "telegraph": "Holfer",
                    "factory_office": "Not provided",
                    "factory_phone": "Not provided"
                },
                "financials": {
                    "capital": "250,000 kr",
                    "employees": {
                        "industriarb": 75
                    },
                    "annual_turnover": "800,000 kr",
                    "annual_production_value": "Not provided"
                },
                "foundation_year": 1943,
                "corporation_year": "Not provided",
                "board": [
                    {
                        "name": "Holger Fernlund",
                        "role": "VerJcst. dir."
                    },
                    {
                        "name": "Erik Zachrisson",
                        "role": "Kamrer"
                    }
                ],
                "owner": "Not provided",
                "director": "Not provided",
                "managing_director": "Not provided",
                "sales_manager": "Not provided",
                "manager": "Not provided"
            },
            {
                "name": "A. E. Fernstedt &amp; C:o",
                "location": "Motala Tekniska Fabrik",
                "business": "Kem.-tekn. fabrik",
                "products": "Tillverkar maskinsmörjor, impregneringsoljor samt rem-och kugghjulssmörjor.",
                "contact": {
                    "office": "Motala",
                    "phone": [
                        "107"
                    ],
                    "postgiro": "28205",
                    "telegraph": "Fernstedtco",
                    "factory_office": "Not provided",
                    "factory_phone": "Not provided"
                },
                "financials": {
                    "capital": "Not provided",
                    "employees": {
                        "Antal industriarb": 5
                    },
                    "annual_turnover": "Not provided",
                    "annual_production_value": "Not provided"
                },
                "foundation_year": 1890,
                "corporation_year": "Not provided",
                "board": [
                    {
                        "name": "Gotthard Fernstedt",
                        "role": "Ägare o. chef"
                    }
                ],
                "owner": "Not provided",
                "director": "Not provided",
                "managing_director": "Not provided",
                "sales_manager": "Not provided",
                "manager": "Not provided"
            },
            {
                "name": "AB. A. K. Fernströms Granit-industrier",
                "location": "Karlshamn",
                "business": "Stenhuggerier",
                "products": "Tillverkar blocksten, byggnadssten, gat- och smågatsten, kantsten, makadam samt div. granitprodukter.",
                "contact": {
                    "office": "Karlshamn",
                    "phone": [
                        "Not provided"
                    ],
                    "postgiro": "6132",
                    "telegraph": "Fernström",
                    "factory_office": "Not provided",
                    "factory_phone": "Not provided"
                },
                "financials": {
                    "capital": "1,800,000 kr",
                    "employees": {
                        "Antal industriarb": "Not provided"
                    },
                    "annual_turnover": "Not provided",
                    "annual_production_value": "Not provided"
                },
                "foundation_year": 1885,
                "corporation_year": 1925,
                "board": [
                    {
                        "name": "Eric K. Fernström",
                        "role": "ordf."
                    },
                    {
                        "name": "fru Emma Fernström",
                        "role": "Not provided"
                    },
                    {
                        "name": "Holger K. Fernström",
                        "role": "Not provided"
                    },
                    {
                        "name": "Axel Boos",
                        "role": "Not provided"
                    },
                    {
                        "name": "Algot Riider",
                        "role": "Not provided"
                    }
                ],
                "owner": "Not provided",
                "director": "Eric K. Fernström",
                "managing_director": "Sten Hedén",
                "sales_manager": "Not provided",
                "manager": "Not provided"
            },
            {
                "name": "AB. Ferro Legeringar",
                "location": "Stockholm",
                "business": "Tillverkar ferrolegeringar, kromalun och galvaniserad plåt genom sitt dotterbolag, AB. Metallurgisk Industri",
                "products": "Bolaget idkar jämväl handel med legeringar av främmande fabrikat.",
                "contact": {
                    "office": "Stockholm",
                    "phone": [
                        "235130"
                    ],
                    "postgiro": "53989",
                    "telegraph": "Legeringar",
                    "factory_office": "Not provided",
                    "factory_phone": "Not provided"
                },
                "financials": {
                    "capital": "4,000,000 kr",
                    "employees": {
                        "Antal industriarb": "Not provided"
                    },
                    "annual_turnover": "Not provided",
                    "annual_production_value": "Not provided"
                },
                "foundation_year": 1913,
                "corporation_year": "Not provided",
                "board": [
                    {
                        "name": "O. Drakenberg",
                        "role": "Not provided"
                    },
                    {
                        "name": "V. A. Eriksson",
                        "role": "Not provided"
                    },
                    {
                        "name": "S. W. Roos",
                        "role": "Not provided"
                    }
                ],
                "owner": "Not provided",
                "director": "O. Drakenberg",
                "managing_director": "H. Willners",
                "sales_manager": "Not provided",
                "manager": "Not provided"
            },
            {
                "name": "AB. Ferrosan",
                "location": "Malmö",
                "business": "Läkemedelsfabrik",
                "products": "Tillverkar läkemedel såsom järnpreparat, kalkpreparat, vitaminpreparat m. fl.",
                "contact": {
                    "office": "Malmö",
                    "phone": [
                        "71850"
                    ],
                    "postgiro": "38256",
                    "telegraph": "Ferrosan",
                    "factory_office": "Not provided",
                    "factory_phone": "Not provided"
                },
                "financials": {
                    "capital": "250,000 kr",
                    "employees": {
                        "industriarb": 40
                    },
                    "annual_turnover": "Not provided",
                    "annual_production_value": "Not provided"
                },
                "foundation_year": 1919,
                "corporation_year": "Not provided",
                "board": [
                    {
                        "name": "Alexius Söderberg",
                        "role": "ordf."
                    },
                    {
                        "name": "S. Andersen",
                        "role": "Not provided"
                    },
                    {
                        "name": "J. Ryné",
                        "role": "VerJcst. dir."
                    },
                    {
                        "name": "Göte Svärd",
                        "role": "Kamrer"
                    }
                ],
                "owner": "Not provided",
                "director": "J. Ryné",
                "managing_director": "Not provided",
                "sales_manager": "Not provided",
                "manager": "Not provided"
            },
            {
                "name": "AB. Fiedler &amp; Lundgren",
                "location": "Göteborg",
                "business": "Reseffektfabrik",
                "products": "Tillverkar reseffekter såsom kappsäckar, resväskor och etuier. Specialiteter: damhandväskor, portföljer, plånböcker och portmonnäer.",
                "contact": {
                    "office": "Göteborg",
                    "phone": [
                        "187110"
                    ],
                    "postgiro": "12362",
                    "telegraph": "Ladybags",
                    "factory_office": "Not provided",
                    "factory_phone": "Not provided"
                },
                "financials": {
                    "capital": "Not provided",
                    "employees": {
                        "industriarb": "Not provided"
                    },
                    "annual_turnover": "Not provided",
                    "annual_production_value": "Not provided"
                },
                "foundation_year": "Not provided",
                "corporation_year": "Not provided",
                "board": [
                    {
                        "name": "Not provided",
                        "role": "Not provided"
                    }
                ],
                "owner": "Not provided",
                "director": "Not provided",
                "managing_director": "Not provided",
                "sales_manager": "Not provided",
                "manager": "Not provided"
            }
        ]
    }
}