{
    "original": "Utansjö—Wadman\n\nAkt.-kap.: 144,000 kr. Antal\nindustriarb.: 40, ävensom 60 hemsömmerskor.\n— Firman etabl. 1905, bolag 1926.\n\nVerkst. dir.: fru Henny Levin.\n\nt)isp.: Richard Urwitz.\n\nUtansjö Cellulosa AB., TJtansjö.\n\nSulfitfabrik vid Utansjö, Veda\n(Västernorrl. l.). Tillverkar sulfitcellulosa.\nBolaget idkar jämväl skogsbruk.\n\nHuvudkontor: Utansjö. Telegr.-adr.:\nUtansjö, Kramfors. Telefon: Ramvik 9.\nSkogskontor: Sollefteå.\nFörsäljn.-kon-tor: Graningeverkens Försäljningskontor,\nStockholm, Stureplan 6, telefon: 600312\no. 600344.\n\nAkt.-kap.: 2,400,000 kr. Antal\nindustriarb.: 225. Årskapacitet: 50,000 ton torr,\noblekt, stark sulfitcellulosa. — Bolaget\ngrundat 1897.\n\nStyrelse: adv. Tom Forssner (ordf.),\ndir. G. J. Versteegh (v. ordf.), disp. J.\nGotthard Janson.\n\nVerkst. dir.: G. J. Versteegh\n(Stockholm).\n\növering. o. platschef: S. Schöldström.\n\nFörsäljn.-chef i Stockholm: intendent\nKarl Wingstedt.\n\n*AB. Utländskt Trä, Göteborg.\n\nSågverk och fanerfabrik. Tillverkar\nsågade trävaror och faner. Bolaget\ndriver som huvudrörelse handel med in- och\nutländska träslag samt faner.\n\nKontor: Trolihätteg. 3. Telegr.-adr.:\nUtlandsträ, Göteborg. Telefon: 151494.\nPostgiro: 42111.\n\nAkt.-kap.: 183,000 kr. Antal\nindustriarb.: 30. Prod.-värde pr år: 1,000,000 kr.\n— Bolaget grundat 1912, ombildat 1922.\nStyrelse o. verkst. dir.: Sven J. Larson.\nKontorschef: Hjalmar Johansson.\n\n*AB. Utnäs Tegelbruk, Prästmon.\n\nTillverkar murtegel och högporöst tegel\nvid tegelbruk i Utnäs, Prästmon\n(Västernorrl. l.).\n\nTelefon: 53. Postgiro: 97538. —\nAkt.-kap.: 25,000 kr. Antal industriarb.: 25.\nÅrstillv.: 1 milj. st. tegel. — Bolaget\ngrundat 1913.\n\nVerkst. dir. o. tegelmäst.: ing. Ivar J.\nDahlén.\n\n* Utsiktens Bryggeri, Uddevalla.\nSe AB. Pripp &amp; Lyckholm, Göteborg.\n\n*AB. Uvakläder, Uddevalla.\n\nKonfektionsfabrik. Tillverkar kostymer\noch överplagg samt trench-coats.\n\nTelefon: »Schwartzman &amp; Nordström».\nPostgiro: 92678. — Akt.-kap.: 12,500\nkr. — Bolaget, grundat 1934, äges av AB.\nSchwartzman &amp; Nordström, Uddevalla.\n\nStyrelse o. verkst. dir.: Marcus\nSchwartzman.\n\n* utmärker till Sveriges Industriförbund anslutna företag\n\n*Vacuum Oii Company AB.,\n\nStockholm.\n\nOljefabrik i Henriksdal (Stockholms\nI.). Tillverkar specialoljor och specialfett\nför marina och industriella ändamål samt\nför automobiler och traktorer, borr- och\ngängoljor, läderoljor, bromsvätskor,\nlösningsmedel och rostskyddsmedel.\nVarumärke: »Gargoyle». Bolaget driver såsom\nhuvudrörelse engroshandel med oljor och\nfett.\n\nKontor: Stockholm, Kungsg. 70.\nTele-gr.-adr.: Vacuum. Stockholm. Telefon:\n»Vacuum Oil». Postgiro: 665.\n\nAkt.-kap.: 1,800,000 kr. Arb.-antal: 10.\n— Firman etabl. 1900.\n\nStyrelse: dir. Axel Zetterholm (ordf.),\ndir. Einar Bristedt, dir. Sune Schéle.\nVerkst. dir.: Sune Schéle.\n\nWaddfabriken, Svenska, Jönköping.\nSe Svenska Waddfabriken, Jönköping.\n\n*Vads Såg o. Trähusfabrik, Vad.\n\nSe Barkens Sågverks AB., Vad.\n\n*Wadmans Bryggeri AB.,\n\nGävle.\n\nSe AB. Gefle Förenade Bryggerier,\nGävle.\n\n605*",
    "structured": {
        "1": {
            "name": "Utansjö Cellulosa AB.",
            "location": "Utansjö, Veda (Västernorrl. l.)",
            "business": "Sulfitfabrik",
            "products": "Tillverkar sulfitcellulosa",
            "contact": {
                "office": "Utansjö",
                "telegraph": "Utansjö, Kramfors",
                "phone": [
                    "Ramvik 9"
                ],
                "sales_offices": [
                    {
                        "location": "Graningeverkens Försäljningskontor, Stockholm",
                        "phone": "600312 o. 600344"
                    }
                ]
            },
            "financials": {
                "capital": "2,400,000 kr",
                "employees": {
                    "industriarb": 225
                },
                "annual_turnover": "Not provided",
                "annual_production_value": "50,000 ton torr, oblekt, stark sulfitcellulosa"
            },
            "foundation_year": 1897,
            "board": [
                {
                    "name": "Tom Forssner",
                    "role": "adv"
                },
                {
                    "name": "G. J. Versteegh",
                    "role": "dir"
                },
                {
                    "name": "J. Gotthard Janson",
                    "role": "disp"
                }
            ]
        },
        "2": {
            "name": "AB. Utländskt Trä",
            "location": "Göteborg",
            "business": "Sågverk och fanerfabrik",
            "products": "Tillverkar sågade trävaror och faner",
            "contact": {
                "office": "Trolihätteg. 3",
                "telegraph": "Utlandsträ, Göteborg",
                "phone": [
                    "151494"
                ],
                "postgiro": "42111"
            },
            "financials": {
                "capital": "183,000 kr",
                "employees": {
                    "industriarb": 30
                },
                "annual_turnover": "1,000,000 kr",
                "annual_production_value": "Not provided"
            },
            "foundation_year": 1912,
            "board": [
                {
                    "name": "Sven J. Larson",
                    "role": "Verkst. dir."
                },
                {
                    "name": "Hjalmar Johansson",
                    "role": "Kontorschef"
                }
            ]
        },
        "3": {
            "name": "AB. Utnäs Tegelbruk",
            "location": "Prästmon",
            "business": "Tillverkar murtegel och högporöst tegel",
            "contact": {
                "phone": "53",
                "postgiro": "97538"
            },
            "financials": {
                "capital": "25,000 kr",
                "employees": {
                    "industriarb": 25
                },
                "annual_turnover": "Not provided",
                "annual_production_value": "1 milj. st. tegel"
            },
            "foundation_year": 1913,
            "director": "ing. Ivar J. Dahlén"
        },
        "4": {
            "name": "Utsiktens Bryggeri",
            "location": "Uddevalla",
            "business": "Se AB. Pripp &amp; Lyckholm, Göteborg"
        }
    }
}