{
    "original": "Rosengren—Rubberfilm\n\nFirman etabl. 1886, aktiebolag 1910.\n\nStytelse: dir. Herman Lindquist\n(ordf.), disp. Franz Hartmann, dir. L.\nHill-Lindquist.\n\nVerkst. dir.: Erik Håkanson.\n\nÖvering.: G. L. Sjölander.\n\nFörsäljn.-chef: dir. Tnre Larsson.\n\n*J. N. Rosengrens Metallgjuteri AB.,\n\nLimhamn.\n\nMetall- och aluminiumgjuteri i\nLimhamn, Malmö. Tillverkar gjutgods,\nme-tallgjtltgods och lättmetallegeringar samt\nutför: konstgjutningar och\ncentrifugal-gjutningar. Varumärke för vita\nlager-metaller: »Göta».\n\nKontor: Järnvägsg. 42, Limhamn.\nTelegr.-adr.: Metallgjuteriet, Malmö.\nTelefon: Malmö 51669 o. 51667. Postgiro:\n30685.\n\nAkt.-kap.: 132,000 kr. Antal\nindustriarb.: 60. Tillv.-värde pr år: 1,000,000 kr.\n— Firman etabl. 1909, bolag 1930.\n\nStyrelse: dir. Gunnar Rosengren\n(ordf.), sekr. Arne Rosengren, ing.\nEdward Rosengren, gjutmäst. Erik\nRosengren.\n\nVerkst. dir.: Gunnar Rosengren.\n\nDriftsing.: Arne Rosengren.\n\n(Jfr annons nr 21.)\n\n* Rosenlunds Järn- &amp;\nTräförädlingsfabrik, Gustaf Andersson &amp; Söner,\n\nHjo.\n\nTillverkar parkettgolv, fönster, dörrar\noch trappor samt köks- och\nbutiksinredningar.\n\nTelefon: 211. Postgiro: 265915. Repr.:\nAxel Rydholm, Göteborg, Södra vägen 65,\ntelefon: 167799. — Arb.-antal: 6.\nTillv.-värde pr år: 100,000 kr. — Fabriken\nanlagd 1901, nuv. firma etabl. 1910.\n\nDelägare: fabr. Gustaf Andersson,\nsnickare Ingemar Andersson, snickare Folke\nAndersson o. snickare Rune Andersson.\n\nChef: Gustaf Andersson.\n\nRoss AB., Göteborg.\n\nTillverkar apparater för fotografiskt\nändamål.\n\nKontor: Odinsg. 28. Telegr.-adr.:\nRossverken, Göteborg. Telefon: 159633.\nPostgiro: 46768. — Antal industriarb.: 40. —\nFirman etabl. 1941.\n\nVerkst. dir.: Victor Hasselblad.\n\n*Elnär Rostedt, Nya Möbelfabriken,\n\nSävsjö.\n\nSe Nya Möbelfabriken, Einar Rostedt,\nSävsjö.\n\n*\tRostfria Andersson, Sundbyberg.\n\nSe J. R. Andersson &amp; Co. AB.,\nSundbyberg.\n\n*\tRostskyddsbolaget Lidén &amp; Co.,\n\nStockholm.\n\nSe AB. Kemicano, Stockholm.\n\n*Rotogravyr, Stockholm.\n\nSe Nordisk Rotogravyr, Stockholm.\n\nRottne Snickerifabriks AB.,\n\nRottne.\n\nTillverkar möbler vid fabrik i Rottne\n(Kronob. l.).\n\nTelefon: 26. Postgiro: 146420. —\nAkt.-kap.: 28,500 kr. Antal industriarb.: 33.\nTillv.-värde pr år: 220,000 kr. — Firman\netabl. 1905, bolag 1917.\n\nVerkst. dir.: Tor Svensson.\n\n*AB. Rottneros Bruk, Rottneros.\n\nTräsliperi, sågverk, mek. verkstad och\nelektr. vattenkraftstationer vid\nRottneros samt sågverk vid Slottsbron (båda i\nVärml. l.). Tillverkar mek. trämassa\noch sågade trävaror samt idkar elektrisk\ndistributionsrörelse, skogshantering,\njordbruk och kvarnrörelse.\n\nTelegr.-adr.: Rottnerosbruk, Sunne.\nTelefon: Sunne 18, 231, 420 o.\nRottneros 39. Postgiro: 13808.\n\nAkt.-kap.: 4,000,000 kr. Antal\nindustriarb.: 300. Tillv.-värde pr år: 10,000,000\nkr- Årstillv.: 100,000 ton våt mek.\nträmassa, 3,000 stds sågade trävaror.\n\nVerkstaden anlagd 1882, träsliperiet\n1887, ombyggt 1935—36, bolaget grundat\n1916. Bolaget äger Slottsbrons\nTräförädlings AB., Grums och Rottneros Kraft\nAB.\n\nStyrelse: dir. Nils G. Arvedson (ordf.),\nbankdir. Anton Dahlin, kraftverksdir.\nOve Harder, major Svante Påhlson, disp.\nGösta Schotte.\n\nVerkst. dir. o. disp.: Svante Påhlson.\n\nVice verkst. dir.: Ove Harder.\n\nAvd.-chefer: i Rottneros: kamrer\nMi-les Carlsson, driftsing. E. Nilsen,\navd.-chef Aug. Ericsson, skogsförvalt. Olof\nPersson, inköpschef Gösta Svensson o.\ning. Gunnar Ohlsson; i Slottsbron:\nförvalt. Emil Nordström.\n\n*AB. Rubberfilm, Åmål.\n\nGummivarufabrik. Tillverkar sanitära\ngummi varor, batister, gummiduk,\ngum-mitaft till trench-coats, gummerade tyger",
    "structured": {
        "1": {
            "name": "J. N. Rosengrens Metallgjuteri AB.",
            "location": "Limhamn, Malmö",
            "business": "Metall- och aluminiumgjuteri",
            "products": "Tillverkar gjutgods, metallgjutgods och lättmetallegeringar samt utför: konstgjutningar och centrifugalgjutningar. Varumärke för vita lagermetaller: »Göta».",
            "contact": {
                "office": "Järnvägsg. 42, Limhamn",
                "phone": [
                    "Malmö 51669",
                    "Malmö 51667"
                ],
                "postgiro": "30685",
                "telegraph": "Metallgjuteriet, Malmö"
            },
            "financials": {
                "capital": "132,000 kr",
                "employees": {
                    "industriarb": 60
                },
                "annual_turnover": "1,000,000 kr",
                "annual_production_value": "1,000,000 kr"
            },
            "foundation_year": 1909
        },
        "2": {
            "name": "Rosenlunds Järn- & Träförädlingsfabrik, Gustaf Andersson & Söner",
            "location": "Hjo",
            "products": "Tillverkar parkettgolv, fönster, dörrar och trappor samt köks- och butiksinredningar.",
            "contact": {
                "phone": "211",
                "postgiro": "265915",
                "sales_offices": [
                    {
                        "location": "Göteborg, Södra vägen 65",
                        "phone": "167799"
                    }
                ]
            },
            "financials": {
                "annual_production_value": "100,000 kr"
            },
            "foundation_year": 1910
        },
        "3": {
            "name": "Ross AB.",
            "location": "Göteborg",
            "products": "Tillverkar apparater för fotografiskt ändamål."
        },
        "4": {
            "name": "Elnär Rostedt, Nya Möbelfabriken",
            "location": "Sävsjö"
        },
        "5": {
            "name": "Rostfria Andersson",
            "location": "Sundbyberg"
        },
        "6": {
            "name": "Rostskyddsbolaget Lidén & Co.",
            "location": "Stockholm"
        },
        "7": {
            "name": "Rotogravyr",
            "location": "Stockholm"
        },
        "8": {
            "name": "Rottne Snickerifabriks AB.",
            "location": "Rottne",
            "products": "Tillverkar möbler vid fabrik i Rottne (Kronob. l.).",
            "contact": {
                "phone": "26",
                "postgiro": "146420"
            },
            "financials": {
                "capital": "28,500 kr",
                "employees": {
                    "industriarb": 33
                },
                "annual_production_value": "220,000 kr"
            },
            "foundation_year": 1905
        },
        "9": {
            "name": "AB. Rottneros Bruk",
            "location": "Rottneros",
            "products": "Träsliperi, sågverk, mek. verkstad och elektr. vattenkraftstationer vid Rottneros samt sågverk vid Slottsbron (båda i Värml. l.). Tillverkar mek. trämassa och sågade trävaror samt idkar elektrisk distributionsrörelse, skogshantering, jordbruk och kvarnrörelse."
        },
        "10": {
            "name": "AB. Rubberfilm",
            "location": "Åmål",
            "business": "Gummivarufabrik",
            "products": "Tillverkar sanitära gummi varor, batister, gummiduk, gummitaft till trench-coats, gummerade tyger."
        }
    }
}