{
    "original": "Arbit—Arboga\n\n*AB. Arbit, Arboga.\n\nElektr. sintringsverk och smältverk.\nTillverkar: sintrad hårdmetall (»Vivax»\no. »Sintram») samt gjuten hårdmetall\n(»Pansar» o. »Arbit»); dragverktyg av\nsintrad hårdmetall för dragning av järn\noch metall, dragskivor, runda och\nprofilerade, fasta samt ställbara för tråd,\nstänger och rör, dragdornar för runda\noch profilerade rör, dragdynor för\nkopp-ning och hylsdragning, diverse andra\ndragverktyg; slitdetaljer av gjuten\nhårdmetall, runda och profilerade\nsandbläster-munstycken samt diverse verktyg och\nmaskindetaljer utsatta för förslitning.\n\nTelegr.-adr.: Arbit, Arboga. Telefon:\n226. Postgiro: 51462. — Akt.-kap.:\n100,000 kr. Tillv.-värde pr år: 500,000\nkr.\n\nBolaget grundat 1930. Dess verk och\nanläggningar arrenderas av Fagersta\nBruks AB. Försäljningen av verkets\nprodukter handhaves av Fagersta Bruks\nAB., Fagersta, och platskontoret i Arboga.\n\nStyrelse: disp. Hj. Åselius (ordf.), dir.\nNils Elfström, dir. Zacheus Olson.\n\nPlatschef: ing. Rolf Pauly.\n\n*\tArboga Boktryckeri AB., Arboga.\n\nUtför tidnings-, bok- och accidenstryck,\naffärstryck, kataloger m. m. Bolaget\nutger »Arboga Tidning».\n\nTelefon: »Arboga tidning». Postgiro:\n28543.\n\nAkt.-kap.: 124,000 kr. Antal\nindustriarb.: 15. Tillv.-värde pr år av tidnings-,\nbok- och accidenstryck: 290,000 kr. —\nFirman etabl. på 1850-talet, bolag 1911.\nBolaget äges av Eskilstuna-Kurirens\nTryckeri AB.\n\nStyrelse: kamrer Stig Holm (ordf.),\nchefred. J. Anton Selander, red. John\nWall ström.\n\nVerkst. dir.: John Wallström.\n\n*\tArboga Bryggeri AB., Arboga.\n\nTillverkar malt- och läskedrycker.\n\nTelegr.-adr.: Bryggeribolaget, Arboga.\nTelefon: 31. Postgiro: 6361. — Akt.-kap.:\n400,000 kr. Antal industriarb.: 20. —\nBolaget grundat 1899.\n\nStyrelse: tandläk. Ernst* Arosenius,\ngrossh. Ivar Levert, dir. Nils Levert.\n\nVerkst. dir.: Nils Levert.\n\n*AB. Arboga Kvarn &amp; Maltfabrik,\n\nArboga.\n\nTillverkar vete- och rågmjöl samt\npilsnermalt. Varumärke: »Guldsnö»vetemjöl.\nFirman driver även engroshandel med\nkraftfoder och gödningsämnen.\n\nTelegr.-adr.: Kvarnmalt, Arboga.\nTelefon: 238 o. 237. Postgiro: 10078.\n\nAkt.-kap.: 226,250 kr. Antal\nindustriarb.: 7. Prod.-värde pr år: 900,000 kr. —\nFirman etabl. 1821, bolag 1919, nuv.\nbolag 1923.\n\nStyrelse: bankdir. Ivar Fredholm\n(ordf.), dir. Tage Lindblom, dir.\nCarl-Hugo Peterson.\n\nVerkst. dir.: C.-H. Peterson.\n\n*AB. Arboga Margarinfabrik, Arboga.\n\nTillverkar växtmargarin, animalisk\nmargarin, kokossmör och konstister.\n\nTelegr.-adr.: Margarinfabrik, Arboga.\nTelefon: 188. Postgiro: 6352.\n\nFörsäljningen sker genom\nMargarinbolaget AB., Stockholm, Vasag. 16.\nTelefon: 230960.\n\nAkt.-kap.: 2,500,000 kr. Antal\nindustriarb.: 27. Tillv.-värde pr år: 4,500,000 kr.\n— Firman etabl. 1888, bolag 1928.\n\nStyrelse: herr Johan Biesért, disp.\nAnders Göransson, dir. Gillis Husberg,, fru\nEster Husberg, adv. Ivar Morssing, dir.\nGustaf Settergren.\n\nVerkst. dir. o. disp.: Gillis Husberg.\nKontorschef: Anders Göransson.\nDriftsin g.: Holger Omoe.\n\n*AB. Arbogamaskiner, Arboga.\n\nMek. verkstad. Tillverkar elektriskt\ndirektdrivna verktygsmaskiner.\n\nTelegr.-adr.: Elektrofabrik, Arboga.\nTelefon: 20. Postgiro: 77023.\n\nAkt.-kap.: 500,000 kr. Antal\nindustriarb.: 100. Tillv.-värde pr år: 1,800,000 kr.\n— Bolaget, grundat 1937, har i sig\nupptagit f. d. Elektriska Fabriken Jonsson &amp;\nLarsson.\n\nStyrelse: disp. H. de la Cour, fabr»\nGunnar E. Jonsson, dir. E. Albin\nLarsson.\n\nVerkst. dir.: E. Albin Larsson.\n\nFörsaljn.-chef: H. de la Cour.\n\nKamrer: T. Briide.\n\n*AB. Arboga Mekaniska Verkstad,\n\nArboga.\n\nMek. verkstad med gjuteri och elektr»\nvattenkraftstation (Grindberga).\n\nTillverkar maskiner för järn-, stål- och\nmetallverk samt tråddragerimaskiner,\nexcenterpressar, bockningspressar,\nfrik-tionsskruvpressar, gradsaxar, kugghjul\nm. m. Bolaget distribuerar jämväl elektr»\nenergi.\n\nTelegr.-adr. o. telefon: Verkstaden,.\nArboga. Postgiro: 25175.",
    "structured": {
        "1": {
            "name": "AB. Arbit",
            "location": "Arboga",
            "business": "Elektr. sintringsverk och smältverk",
            "products": "Sintrad hårdmetall (»Vivax» o. »Sintram») samt gjuten hårdmetall (»Pansar» o. »Arbit»); dragverktyg av sintrad hårdmetall för dragning av järn och metall, dragskivor, runda och profilerade, fasta samt ställbara för tråd, stänger och rör, dragdornar för runda och profilerade rör, dragdynor för kopp-ning och hylsdragning, diverse andra dragverktyg; slitdetaljer av gjuten hårdmetall, runda och profilerade sandbläster-munstycken samt diverse verktyg och maskindetaljer utsatta för förslitning",
            "contact": {
                "office": "Arbit, Arboga",
                "phone": [
                    "226"
                ],
                "postgiro": "51462",
                "head_office": "Fagersta Bruks AB, Fagersta",
                "sales_offices": [
                    {
                        "location": "Fagersta",
                        "phone": "Unknown"
                    },
                    {
                        "location": "Arboga",
                        "phone": "Unknown"
                    }
                ],
                "telegraph": "Arbit, Arboga",
                "description": "Contact information for the firm."
            },
            "financials": {
                "capital": "100,000 kr",
                "annual_turnover": "500,000 kr",
                "description": "Financial information of the firm."
            },
            "foundation_year": 1930,
            "board": [
                {
                    "name": "disp. Hj. Åselius",
                    "role": "ordf."
                },
                {
                    "name": "dir. Nils Elfström",
                    "role": "Unknown"
                },
                {
                    "name": "dir. Zacheus Olson",
                    "role": "Unknown"
                }
            ]
        },
        "2": {
            "name": "Arboga Boktryckeri AB.",
            "location": "Arboga",
            "business": "Utför tidnings-, bok- och accidenstryck, affärstryck, kataloger m. m.",
            "products": "Unknown",
            "contact": {
                "phone": [
                    "Arboga tidning"
                ],
                "postgiro": "28543"
            },
            "financials": {
                "capital": "124,000 kr",
                "description": "Financial information of the firm."
            },
            "foundation_year": 1911,
            "board": [
                {
                    "name": "kamrer Stig Holm",
                    "role": "ordf."
                },
                {
                    "name": "chefred. J. Anton Selander",
                    "role": "Unknown"
                },
                {
                    "name": "red. John Wallström",
                    "role": "Unknown"
                }
            ],
            "director": "John Wallström"
        },
        "3": {
            "name": "Arboga Bryggeri AB.",
            "location": "Arboga",
            "business": "Tillverkar malt- och läskedrycker",
            "products": "Unknown",
            "contact": {
                "telegraph": "Bryggeribolaget, Arboga",
                "phone": [
                    "31"
                ],
                "postgiro": "6361"
            },
            "financials": {
                "capital": "400,000 kr",
                "description": "Financial information of the firm."
            },
            "foundation_year": 1899
        },
        "4": {
            "name": "AB. Arboga Kvarn & Maltfabrik",
            "location": "Arboga",
            "business": "Tillverkar vete- och rågmjöl samt pilsnermalt.",
            "products": "Varumärke: »Guldsnö»vetemjöl. Firman driver även engroshandel med kraftfoder och gödningsämnen",
            "contact": {
                "telegraph": "Kvarnmalt, Arboga",
                "phone": [
                    "238",
                    "237"
                ],
                "postgiro": "10078"
            },
            "financials": {
                "capital": "226,250 kr",
                "description": "Financial information of the firm."
            },
            "foundation_year": 1923
        },
        "5": {
            "name": "AB. Arboga Margarinfabrik",
            "location": "Arboga",
            "business": "Tillverkar växtmargarin, animalisk margarin, kokossmör och konstister",
            "products": "Unknown",
            "contact": {
                "telegraph": "Margarinfabrik, Arboga",
                "phone": [
                    "188"
                ],
                "postgiro": "6352"
            },
            "financials": {
                "capital": "2,500,000 kr",
                "description": "Financial information of the firm."
            },
            "foundation_year": 1928
        },
        "6": {
            "name": "AB. Arbogamaskiner",
            "location": "Arboga",
            "business": "Mek. verkstad. Tillverkar elektriskt direktdrivna verktygsmaskiner",
            "products": "Unknown",
            "contact": {
                "telegraph": "Elektrofabrik, Arboga",
                "phone": [
                    "20"
                ],
                "postgiro": "77023"
            },
            "financials": {
                "capital": "500,000 kr",
                "description": "Financial information of the firm."
            },
            "foundation_year": 1937
        },
        "7": {
            "name": "AB. Arboga Mekaniska Verkstad",
            "location": "Arboga",
            "business": "Mek. verkstad med gjuteri och elektr» vattenkraftstation (Grindberga).",
            "products": "Unknown",
            "contact": {
                "telegraph": "Verkstaden, Arboga",
                "phone": "Unknown",
                "postgiro": "25175"
            },
            "financials": {
                "capital": "Unknown",
                "description": "Financial information of the firm."
            },
            "foundation_year": "Unknown"
        }
    }
}