{
    "original": "Bobin—Bofors\n\nAB. Bobin &amp; Trä, Kalmar.\n\nSågverk, hyvleri och lådfabrik i\nFager-hult (Kalmar l.). Tillverkar lådämnen.\n\nKontor: Kalmar. Telegr.-adr.:\nBobinträ, Kalmar. Telefon: 2445. – Akt.-kap.:\n36,400 kr. Antal industriarb.: 100.\nTillv.-värde pr år: 1,000,000 kr. — Bolaget\ngrundat 1935.\n\nVerkst. dir.: Oscar B. Johansson.\n\nDisp.: Stig Obing.\n\nBoda Bruks AB., Boda glasbruk.\n\nGlasbruk vid Boda glasbruk (Kronob.\n1.). Tillverkar slipat, etsat, graverat,\npressat och målat hushålls- och prydnadsglas\nm. m.\n\nTelegr.-adr.: Bodaglas, Kalmar.\nTelefon: Boda Glasbruk 1 o. 2. Postgiro:\n145590.\n\nAkt.-kap.: 200,000 kr. Antal\nindustriarb.: 122. Tillv.-värde pr år: 800,000 kr.\n— Glasbruket anlagt 1864, bolag 1918.\n\nVerkst. dir.: Lars Gabrielson (Sthlm).\n♦ Platschef: G. Cassing.\n\nAB. Boda Kalk, Kärvsåsen.\n\nKalkbruk vid Kärvsåsen (Kopparb. l.).\nBryter och bränner kalk för byggnads-,\nindustri- och jordbruksändamål.\nVarumärke: »Boda Kalk».\n\nKontor: Stockholm, Kungsg. 37.\nTelefon: 116361 o. 116362. Fabrikskontor:\nKärvsåsen. Telefon: Kärvsåsen 42014.\nPostgiro: 51380.\n\nAkt.-kap.: 110,000 kr. Antal\nindustriarb.: 29. Årstillv.: 12,000 ton bränd kalk.\n— Bolaget grundat 1930.\n\nStyrelse: grossh. Verner Nordström\n(ordf.), ing. Edvin Johansson, byggm.\nG. Anders Svensson.\n\nVerkst. dir.: G. A. Svensson.\n\nDisp.: E. Hansson.\n\n*\tBodafors Möbelfabrik, Bodafors.\n\nSe AB. Svenska Möbelfabrikerna,\nBoda-fors.\n\n*\tBodafors Snickerifabrik, Fransson &amp;\nNilsson, Bodafors.\n\nTillverkar möbler speciellt fåtöljer och\nsoffstommar vid fabrik i Bodafors\n(Jönköp. l.).\n\nTelefon: 97. — Antal industriarb.: 11.\nTillv.-värde pr år: 125,000 kr. — Firman\netabl. 1944 (f. d. Gunnar Lagerqvists\nMöbelfabrik).\n\nÄgare o. chefer: fabr. Bertil Fransson\no. fabr. Elmer Nilsson.\n\nA. F. Bodecker, Stockholm.\n\nHattfabrik. Tillverkar herrhattar\nsåsom höga hattar, filthattar,\nuniformshattar samt doktorshattar.\n\nKontor o. utställningslokal: Fredsg. 6.\nTelegr.-adr.: Bodeckerhat, Stockholm.\nTelefon: 201570. Postgiro: 2171.\n\nAntal industriarb.: 10. Tillv.-värde pr\når: 100,000 kr. — Firman, etabl. 1882,\ndriver såsom huvudrörelse engros- och\ndetaljförsäljning av hattar.\n\nÄgare o. chef: kapten Ludwig Graucob.\n\n*Axel Bodéns Handels AB.,\n\nStockholm.\n\nGarveri i Alingsås. Tillverkar\nbeklädnads- och handskskinn samt skofoder.\nBolaget driver såsom huvudrörelse\nimport- och agenturaffär i läder och skinn.\n\nKontor: Stockholm, Birger Jarlsg. 32.\nTelegr.-adr.: »Bodénbolag», Stockholm.\nTelefon: 200703. Postgiro: 4767.\n\nAkt.-kap.: 350,000 kr. Antal\nindustriarb.: 25. Tillv.-värde pr år: 1,300,000 kr.\n— Firman etabl. 1862, bolag 1921;\ngarveriet anlagt 1937.\n\nStyrelse: kapten Sven-Axel Boden\n(ordf.), grossh. Artur Boden, löjtn. Hans\nBoden, disp. Richard Boden.\nVerkst. dir.: Sven-Axel Boden.\nGarveriförest.: verkm. K. Reschke.\n\n*AB. Bofors, Bofors.\n\nJärnverh med masugnar, stålverk,\nstål-gjuterier, valsverk, smedjor och mekaniska\nverkstäder vid Bofors (Örebro l.).\nTillverkar tackjärn, göt, stålgjutgods, valsat stål,\npressmiden, hammar- och hejarsmiden,\nartillerimateriel och större\nverkstadsarbeten.\n\nTelegr.-adr.: Boforsco, Bofors. Telefon:\n»Bofors», Karlskoga. Postgiro: 6500.\nFilialkontor o. representanter för stål:\nStockholm: AB. Bofors,\nStockholmskontoret, Sveavägen 48, telefon: 234480;\nGöteborg: AB. Bofors, Göteborgskontoret,\nSkeppsbroplatsen 1, telefon: 132950 o.\n132960; Malmö: AB. Bofors,\nMalmökontoret. Neptunig. 21, telefon: 79210 o.\n78030; Värmland o. Bergslagen: AB.\nBofors, Bergslagskontoret, Bofors, telefon:\n»Bofors», Karlskoga; Eskilstuna: AB.\nBofors, Eskilstunakontoret, telefon: 36350\no. 36351; Sundsvall: AB. N. O. Rönne,\ntelefon: 55850. Reserepresentant för\nMellansverige: Th. Svensson, Agenturfirma,\nEskilstuna, telefon: 31562.\n\n55*",
    "structured": {
        "1": {
            "name": "Bobin—Bofors AB. Bobin & Trä",
            "location": "Kalmar",
            "business": "Sågverk, hyvleri och lådfabrik",
            "products": "Tillverkar lådämnen",
            "contact": {
                "office": "Kalmar",
                "telegraph": "Bobinträ, Kalmar",
                "phone": [
                    "2445"
                ],
                "postgiro": "N/A"
            },
            "financials": {
                "capital": "36,400 kr",
                "employees": {
                    "industriarb": 100
                },
                "annual_turnover": "1,000,000 kr",
                "annual_production_value": "1,000,000 kr"
            },
            "foundation_year": 1935,
            "director": "Oscar B. Johansson",
            "managing_director": "N/A",
            "sales_manager": "N/A",
            "manager": "N/A"
        },
        "2": {
            "name": "Boda Bruks AB., Boda glasbruk",
            "location": "Kronob. 1.",
            "business": "Glasbruk",
            "products": "Slipat, etsat, graverat, pressat och målat hushålls- och prydnadsglas m. m.",
            "contact": {
                "telegraph": "Bodaglas, Kalmar",
                "phone": [
                    "Boda Glasbruk 1",
                    "Boda Glasbruk 2"
                ],
                "postgiro": "145590"
            },
            "financials": {
                "capital": "200,000 kr",
                "employees": {
                    "industriarb": 122
                },
                "annual_turnover": "800,000 kr",
                "annual_production_value": "800,000 kr"
            },
            "foundation_year": 1864,
            "director": "Lars Gabrielson",
            "managing_director": "N/A",
            "sales_manager": "N/A",
            "manager": "G. Cassing"
        },
        "3": {
            "name": "AB. Boda Kalk, Kärvsåsen",
            "location": "Kärvsåsen",
            "business": "Kalkbruk",
            "products": "Bryter och bränner kalk för byggnads-, industri- och jordbruksändamål",
            "contact": {
                "office": "Stockholm, Kungsg. 37",
                "phone": [
                    "116361",
                    "116362"
                ],
                "factory_office": "Kärvsåsen",
                "factory_phone": "Kärvsåsen 42014",
                "postgiro": "51380"
            },
            "financials": {
                "capital": "110,000 kr",
                "employees": {
                    "industriarb": 29
                },
                "annual_production_value": "12,000 ton bränd kalk"
            },
            "foundation_year": 1930,
            "director": "G. A. Svensson",
            "managing_director": "N/A",
            "sales_manager": "N/A",
            "manager": "N/A"
        },
        "4": {
            "name": "Bodafors Snickerifabrik, Fransson & Nilsson",
            "location": "Bodafors",
            "business": "Möbelfabrik",
            "products": "Tillverkar möbler speciellt fåtöljer och soffstommar",
            "contact": {
                "phone": [
                    "97"
                ]
            },
            "financials": {
                "employees": {
                    "industriarb": 11
                },
                "annual_turnover": "125,000 kr"
            },
            "foundation_year": 1944,
            "owners": [
                "fabr. Bertil Fransson",
                "fabr. Elmer Nilsson"
            ]
        },
        "5": {
            "name": "A. F. Bodecker",
            "location": "Stockholm",
            "business": "Hattfabrik",
            "products": "Tillverkar herrhattar såsom höga hattar, filthattar, uniformshattar samt doktorshattar",
            "contact": {
                "office": "Fredsg. 6",
                "telegraph": "Bodeckerhat, Stockholm",
                "phone": [
                    "201570"
                ],
                "postgiro": "2171"
            },
            "financials": {
                "employees": {
                    "industriarb": 10
                },
                "annual_turnover": "100,000 kr"
            },
            "foundation_year": 1882,
            "director": "kapten Ludwig Graucob",
            "managing_director": "N/A",
            "sales_manager": "N/A",
            "manager": "N/A"
        },
        "6": {
            "name": "Axel Bodéns Handels AB.",
            "location": "Stockholm",
            "business": "Garveri",
            "products": "Tillverkar beklädnads- och handskskinn samt skofoder",
            "contact": {
                "office": "Stockholm, Birger Jarlsg. 32",
                "telegraph": "Bodénbolag, Stockholm",
                "phone": [
                    "200703"
                ],
                "postgiro": "4767"
            },
            "financials": {
                "capital": "350,000 kr",
                "employees": {
                    "industriarb": 25
                },
                "annual_turnover": "1,300,000 kr"
            },
            "foundation_year": 1862,
            "director": "Sven-Axel Boden",
            "managing_director": "N/A",
            "sales_manager": "N/A",
            "manager": "N/A"
        },
        "7": {
            "name": "AB. Bofors",
            "location": "Bofors (Örebro l.)",
            "business": "Järnverk",
            "products": "Tillverkar tackjärn, göt, stålgjutgods, valsat stål, pressmiden, hammar- och hejarsmiden, artillerimateriel och större verkstadsarbeten",
            "contact": {
                "telegraph": "Boforsco, Bofors",
                "phone": [
                    "Bofors",
                    "Karlskoga"
                ],
                "postgiro": "6500"
            },
            "financials": {
                "employees": {
                    "industriarb": "N/A"
                }
            },
            "corporation_year": "N/A",
            "board": [
                {
                    "name": "grossh. Verner Nordström",
                    "role": "ordf."
                },
                {
                    "name": "ing. Edvin Johansson",
                    "role": "N/A"
                },
                {
                    "name": "byggm. G. Anders Svensson",
                    "role": "N/A"
                }
            ],
            "owners": [
                "N/A"
            ],
            "director": "N/A",
            "managing_director": "N/A",
            "sales_manager": "N/A",
            "manager": "N/A"
        }
    }
}