{
    "original": "Häggåstrand—Hälsingb or g\n\nBolaget grundat 1909.\nAlmedahl-Dal-sjöfors AB. är huvudintressent i bolaget.\n\nStyrelse: disp. Axel Leraan (ordf.),\ndir. Erik Kullgren, major Herman\nSundelin.\n\nVerkst. dir.: Herman Sundelin\n(Göteborg).\n\nPlatschef: Gunnar Ivarson.\n\n*H äggåstrands Jacquard väveri,\n\nKinna.\n\nSe Marks Textilfabrik, Kinna.\n\nHäggåstrands Väveri AB.,\n\nKinnahult.\n\nTillverkar allmogegardiner,\nmarkisetter, draperier, tryckta gardiner och\nmöbeltyger vid väveri i Kinnahult (Älvsb. l.).\n\nTelefon: Kinna 10475. Postgiro:\n143436.\n\nAkt.-kap.: 50,000 kr. Antal\nindustriarb.: 35. — Firman etabl. 1938, bolag\n1939.\n\nStyrelse o. chefer: fabr. Harald\nHåkanson, fabr. Erik Skoglund o. fabr. Per\nSkoglund.\n\n\"AB. Hällarydsverken, SJcede.\n\nMek. verkstad och gjuteri vid Hällaryd,\nSkede (Jönköp. l.). Tillverkar\nvattenturbiner, hydrauliska regulatorer,\ntrycksvarvar, universalfräsmaskiner,\nbordhyvelma-skiner m. m.\n\nTelegr.-adr.: Turbo, Vetlanda.\nTelefon: Skedeby 47. Postgiro: 275480.\n\nAkt.-kap.: 66,200 kr. Antal\nindustriarb.: 50. Tillv.-värde pr år: 500,000 kr.\n— Verkstaden anlagd 1870, nuv. bolag\ngrundat 1933.\n\nStyrelse: disp. Sverker Brunius (ordf.),\nfru Greta Brunius, bankdir. Axel\nGustafsson.\n\nVerkst. dir.: Sverker Brunius\n(Töcks-fors).\n\nPlatschef; ing. Ragnar Hagberg.\n(Jfr annons nr 97.)\n\n\"Hällefors Järnbruk, Hällefors.\nSe Hellefors Bruks AB., Hällefors.\n\n\"Hällefors Manufakturverk,\n\nHällefors.\n\nSe Hellefors Bruks AB., Hällefors.\n\n\"Hällefors Pappersbruk, Lönneberga.\n\nSe AB. Brusafors-Hällefors,\nSilverdalen.\n\nHäller &amp; Co., Smögen.\n\nKonservfabriker i Smögen och\nGrebbe-stad (båda i Göteb. o. Bohus l.).\nTillverkar sill-, fisk- och skaldjurskonserver\nm. m. Firman driver även handel med\nfärsk saltvattensfisk, hummer och räkor.\n\nKontor: Smögen. Telegr.-adr.: Häller,\nSmögen. Telefon: »Häller &amp; Oo.»\nPostgiro: 33053.\n\nAntal industriarb.: 45. Tillv.-värde för\nkonserver: 500,000 kr. — Firman\ngrundad 1880, nuv. namn 1922.\n\nÄgare o. chefer: fabr. Reinhold Häller\no. fabr. Olof Häller.\n\nChef för fiskavd. o. salteri: Torsten\nHäller.\n\njFabrikschef: Leif Häller.\n\nKamrer: Nils Lorentzon.\n\nHälleviks Konservfabrik, A. T.\nBovik &amp; Co., Hälleviksstrand.\n\nTillverkar grönsakskonserver, fisk- och\nsillkonserver vid fabrik i Hälleviksstrand\n(Göteb. o. Bohus l.).\n\nKontor o. ensamförsälj.: AB. Boviks\nKonservfabriker, Lysekil. Telegr.-adr.:\nBovik, Lysekil. Telefon: 89. Postgiro:\n30300.\n\nAntal industriarb.: 45. Tillv.-värde pr\når: 700,000 kr. — Firman, etabl. 1934,\näges av AB. Boviks Konservfabriker.\n\nChef: v. konsul Alfr. T. Bovik.\n\n\"Hälsingborgs Bryggeri,\n\nHälsingborg.\n\nSe AB. Skånebryggerier, Hälsingborg.\n\n\"AB. Hälsingborgs Choklad- &amp;\nKonfektfabrik Kärnan, Hälsingborg.\n\nTillverkar kakao, choklad, konfekt,\nkarameller och kola.\n\nTelefon: 20705. Postgiro: 291699. —\nAkt.-kap.: 450,000 kr. Antal industriarb.:\n150. Tillv.-värde pr år: 4,000,000 kr. —\nBolaget grundat 1903.\n\nStyrelse o. verkst. dir.: dir. Gust. G.\nJohnsson.\n\nKontorschef: Hugo Isgren.\n\nFabrikschef: Nils Johnsson.\n\nHälsingborg.\n\n\"Helsingborgs Cummifabriks AB.,\n\nHälsingborg.\n\nTillverkar galoscher och andra\nytter-skodon (snowboots och bottiner),\ngummistövlar, gummikängor, gummibottnar,",
    "structured": {
        "1": {
            "name": "Häggåstrands Väveri AB.",
            "location": "Kinnahult",
            "business": "Tillverkar allmogegardiner, markisetter, draperier, tryckta gardiner och möbeltyger vid väveri i Kinnahult (Älvsb. l.)",
            "contact": {
                "office": "Häggåstrands Jacquard väveri, Kinna",
                "phone": [
                    "Kinna 10475"
                ],
                "postgiro": "143436",
                "factory_office": "Kinnahult",
                "factory_phone": "Kinnahult",
                "description": "Contact information for the firm."
            },
            "financials": {
                "capital": "50,000 kr",
                "employees": {
                    "industriarb": 35
                },
                "annual_turnover": "",
                "annual_production_value": "",
                "description": "Financial information of the firm."
            },
            "foundation_year": 1938,
            "corporation_year": 1939,
            "board": [
                {
                    "name": "fabr. Harald Håkanson",
                    "role": null
                },
                {
                    "name": "fabr. Erik Skoglund",
                    "role": null
                },
                {
                    "name": "fabr. Per Skoglund",
                    "role": null
                }
            ]
        },
        "2": {
            "name": "AB. Hällarydsverken",
            "location": "SJcede",
            "business": "Mek. verkstad och gjuteri vid Hällaryd, Skede (Jönköp. l.). Tillverkar vattenturbiner, hydrauliska regulatorer, trycksvarvar, universalfräsmaskiner, bordhyvelma-skiner m. m.",
            "contact": {
                "telegraph": "Turbo, Vetlanda",
                "phone": "Skedeby 47",
                "postgiro": "275480",
                "description": "Contact information for the firm."
            },
            "financials": {
                "capital": "66,200 kr",
                "employees": {
                    "industriarb": 50
                },
                "annual_turnover": "500,000 kr",
                "annual_production_value": "",
                "description": "Financial information of the firm."
            },
            "corporation_year": 1933,
            "board": [
                {
                    "name": "disp. Sverker Brunius",
                    "role": "ordf."
                },
                {
                    "name": "fru Greta Brunius",
                    "role": null
                },
                {
                    "name": "bankdir. Axel Gustafsson",
                    "role": null
                }
            ]
        },
        "3": {
            "name": "Häller & Co., Smögen",
            "business": "Konservfabriker i Smögen och Grebbestad (båda i Göteb. o. Bohus l.). Tillverkar sill-, fisk- och skaldjurskonserver m. m.",
            "contact": {
                "office": "Smögen",
                "telegraph": "Häller, Smögen",
                "phone": "»Häller & Oo.",
                "postgiro": "33053",
                "description": "Contact information for the firm."
            },
            "financials": {
                "employees": 45,
                "annual_production_value": "500,000 kr",
                "description": "Financial information of the firm."
            },
            "original_name": "Firman grundad 1880, nuv. namn 1922",
            "owners": [
                "fabr. Reinhold Häller",
                "fabr. Olof Häller"
            ],
            "director": "Leif Häller",
            "sales_manager": "Torsten Häller",
            "manager": "Nils Lorentzon"
        },
        "4": {
            "name": "Hälleviks Konservfabrik, A. T. Bovik & Co.",
            "location": "Hälleviksstrand",
            "business": "Tillverkar grönsakskonserver, fisk- och sillkonserver vid fabrik i Hälleviksstrand (Göteb. o. Bohus l.)",
            "contact": {
                "office": "AB. Boviks Konservfabriker, Lysekil",
                "telegraph": "Bovik, Lysekil",
                "phone": "89",
                "postgiro": "30300",
                "description": "Contact information for the firm."
            },
            "financials": {
                "employees": 45,
                "annual_production_value": "700,000 kr",
                "description": "Financial information of the firm."
            },
            "owners": [
                "AB. Boviks Konservfabriker"
            ],
            "sales_manager": "v. konsul Alfr. T. Bovik"
        },
        "5": {
            "name": "AB. Hälsingborgs Choklad- & Konfektfabrik Kärnan",
            "location": "Hälsingborg",
            "business": "Tillverkar kakao, choklad, konfekt, karameller och kola",
            "contact": {
                "phone": "20705",
                "postgiro": "291699",
                "description": "Contact information for the firm."
            },
            "financials": {
                "capital": "450,000 kr",
                "employees": 150,
                "annual_production_value": "4,000,000 kr",
                "description": "Financial information of the firm."
            },
            "foundation_year": 1903
        }
    }
}