{
    "original": "Färg—Färjenäs\n\nStyrelse: dir. Arvid Lindgren (ordf.),\nkamrer G. Bergendorff, ing. Gunnar\nBjörklund.\n\nVerkst. dir.: Arvid Lindgren.\nFabrikschef: Gunnar Björklund.\nFörsäljn.-chef: disp. A. Kruse.\nKontorschef: G. Bergendorff.\n\nFärg &amp; Ferniss Fabriks AB.\n\nStandard, Trelleborg.\n\nTillverkar emalj-, maskin-, olje- och\nrostskyddande färger,\nfärgborttagnings-medel, eellulosalacker och\ncellulosalackfärger, fernissor, sickativer, asfalt-,\ncykel- och isolationslacker m. m.\n\nVarumärken: Antilackolin, Albolin,\nCabinet, Cellulac, Cellulin, Combialac,\nExteriol, Fenestra, Fulgentin, G.P.T.,\nHartsolin, K.S.S.S.-båtlack, Negrocite,\nNipanic, Occa, Pansarit, Sanitarol,\nSimson, Stahama, Strolit o. Vineta.\n\nHuvudkontor: Trelleborg. Telegr.-adr.:\nStandard, Trelleborg. Telefon: 1590.\nPostgiro: 6238.\n\nAkt.-kap.: 300,000 kr. Antal\nindustriarb.: 35. Tillv.-värde pr år: 2,500,000 kr.\n— Bolaget grundat 1906.\n\nStyrelse: dir. Ernst R. Rickard (ordf.),\nadv. Eric A. Andersson, fru Britt Rickard.\n\nVerkst. dir.: Ernst R. Rickard.\n\nDisp.: Oscar Rosvall.\n\nAB. Färgelanda Sågverk,\n\nFärgelanda.\n\nb Tillverkar sågade och hyvlade trävaror\nvid sågverk i Färgelanda (Älvsb. l.).\n\nTelefon: 33. Postgiro: 88895. —\nAkt.-kap.: 60,700 kr. Antal industriarb.: 34.\nÅrstillv.: 2,000 stds trävaror. — Firman\netabl. 1906, bolag 1939.\n\nVerkst. styrelseledamot: förvalt. Fritz\nV. Norborg.\n\nKamrer: Ivar Jansson.\n\nFärgeri &amp; Appretur AB. i\nNorrköping, Norrköping.\n\nUtför färgning och appretering av\n\ntyger.\n\nTelefon: 20873. Postgiro: 271942. —\nAkt.-kap.: 100,000 kr. Antal industriarb.:\n40. Prod.-värde pr år: 1,000,000 kr. —\nBolaget grundat 1921.\n\nStyrelse: konsul Carl Fr. Hellmann,\ndisp. Gösta W. Hellmann, kamrer Martin\nPetterson, fabr. Arthur Wadström.\nVerkst. dir.: Martin Petterson.\n\nFärgeri AB. Levanten, Göteborg.\n\nFärgeri, blekeri och appreturverk.\nUtför blekning, färgning och appretering av\nbomullsvävnader, färgning och blekning\nav ull- och bomullsgarner, strumpor m. m.\n\nTelegr.-adr.: Levanten, Göteborg.\nTelefon: 161302 o. 161528. Postgiro: 41552.\n\nAkt.-kap.: 300,000 kr. Antal\nindustriarb.: 105. — Firman etabl. 1874.\n\nStyrelse: disp. E. S:son Boysen, dir.\nLinus Höglund, dir. Jakob W. Kinde.\n\nDisp.: E. S:son Boysen.\n\n’Färgeri AB. Lind &amp; Co., Borås.\n\nUtför blekning, färgning och\nappretering, impregnering av sidentyger,\nfo-dervävnader och regnkappstyger,\nblekning och färgning av trikå samt garner\nav bomull och cellull å korsrullar;\nutrustar konstsilke- och cellullvävnader samt\nbomulls- och halvyllevaror.\n\nTelefon: 17475. Postgiro: 134300.\n\nAkt.-kap.: 176,000 kr. Antal\nindustriarb.: 95. Prod.-värde pr år: 1,500,000 kr.\n\n—\tFärgeriet grundat 1824, nuv. firma\netabl. 1900, bolag 1911.\n\nStyrelse: färgm. Alvar L. Andersson,\ndisp. Ivar Lind, bankdir. Erik D.\nNorrman.\n\nDisp.: Ivar Lind.\n\nFärg- &amp; Kritverken, AB. Svenska,\n\nKvarnby.\n\nSe AB. Svenska Färg- &amp; Kritverken,\nKvarnby.\n\nAB. Färgverken, Malmö.\n\nTillverkar färger, fernissor samt\nmålerimaterial. Varumärke: »Japan White».\n\nHuvudkontor: Malmö, Torng. 11.\nTelegr.-adr.: Färgverken, Malmö. Telefon:\n25818 o. 28444. Postgiro: 14189.\n\nAkt.-kap.: 100,000 kr. Antal\nindustriarb.: 14. Tillv.-värde pr år: 900,000 kr.\n—- Firman etabl. 1913, bolag 1918.\n\nVerkst. dir.: Albin Kjellker.\n\n’Färjenäs AB., Göteborg.\n\nSågverksrörelse och trävaruexport.\nTillverkar sågade trävaror, tunnstav,\nlådbrä-der och lådämnen.\n\nKontor: Postg. 2. Telegr.-adr.:\nFärjenäs, Göteborg. Telefon: 118498. Postgiro:\n40778.\n\nAkt.-kap.: 755,000 kr. Antal\nindustriarb.: 30. Tillv.-värde pr år: 540,000 kr.\n\n—\tBolaget grundat 1893.\n\nStyrelse: disp. P. B. Burchardt, disp.\nBror Colliander, dir. Erland Colliander.\n\nVerkst. dir.: Bror Colliander.\n\nV. verkst. dir.: Erland Colliander.\n\n169*",
    "structured": {
        "1": {
            "name": "Färg & Ferniss Fabriks AB",
            "location": "Trelleborg",
            "business": "Tillverkar emalj-, maskin-, olje- och rostskyddande färger, färgborttagnings-medel, cellulosalacker och cellulosalackfärger, fernissor, sickativer, asfalt-, cykel- och isolationslacker m. m.",
            "contact": {
                "head_office": "Trelleborg",
                "telegraph": "Standard, Trelleborg",
                "phone": [
                    "1590"
                ],
                "postgiro": "6238"
            },
            "financials": {
                "capital": "300,000 kr",
                "employees": {
                    "industriarb": 35
                },
                "annual_turnover": "2,500,000 kr",
                "annual_production_value": "2,500,000 kr"
            },
            "foundation_year": 1906
        },
        "2": {
            "name": "AB. Färgelanda Sågverk",
            "location": "Färgelanda",
            "business": "Tillverkar sågade och hyvlade trävaror vid sågverk i Färgelanda (Älvsb. l.)",
            "contact": {
                "phone": [
                    "33"
                ],
                "postgiro": "88895"
            },
            "financials": {
                "capital": "60,700 kr",
                "employees": {
                    "industriarb": 34
                },
                "annual_production_value": "2,000 stds trävaror"
            },
            "foundation_year": 1906,
            "corporation_year": 1939
        },
        "3": {
            "name": "Färgeri & Appretur AB",
            "location": "Norrköping",
            "business": "Utför färgning och appretering av tyger",
            "contact": {
                "phone": [
                    "20873"
                ],
                "postgiro": "271942"
            },
            "financials": {
                "capital": "100,000 kr",
                "employees": {
                    "industriarb": 40
                },
                "annual_production_value": "1,000,000 kr"
            },
            "foundation_year": 1921
        },
        "4": {
            "name": "Färgeri AB. Levanten",
            "location": "Göteborg",
            "business": "Färgeri, blekeri och appreturverk. Utför blekning, färgning och appretering av bomullsvävnader, färgning och blekning av ull- och bomullsgarner, strumpor m. m.",
            "contact": {
                "telegraph": "Levanten, Göteborg",
                "phone": [
                    "161302",
                    "161528"
                ],
                "postgiro": "41552"
            },
            "financials": {
                "capital": "300,000 kr",
                "employees": {
                    "industriarb": 105
                }
            },
            "foundation_year": 1874
        },
        "5": {
            "name": "Färgeri AB. Lind & Co.",
            "location": "Borås",
            "business": "Utför blekning, färgning och appretering, impregnering av sidentyger, fodervävnader och regnkappstyger, blekning och färgning av trikå samt garner av bomull och cellull å korsrullar; utrustar konstsilke- och cellullvävnader samt bomulls- och halvyllevaror.",
            "contact": {
                "phone": [
                    "17475"
                ],
                "postgiro": "134300"
            },
            "financials": {
                "capital": "176,000 kr",
                "employees": {
                    "industriarb": 95
                },
                "annual_production_value": "1,500,000 kr"
            },
            "foundation_year": 1900,
            "corporation_year": 1911
        },
        "6": {
            "name": "AB. Färgverken",
            "location": "Malmö",
            "business": "Tillverkar färger, fernissor samt målerimaterial. Varumärke: »Japan White»",
            "contact": {
                "head_office": "Malmö, Torng. 11",
                "telegraph": "Färgverken, Malmö",
                "phone": [
                    "25818",
                    "28444"
                ],
                "postgiro": "14189"
            },
            "financials": {
                "capital": "100,000 kr",
                "employees": {
                    "industriarb": 14
                },
                "annual_production_value": "900,000 kr"
            },
            "foundation_year": 1913,
            "corporation_year": 1918
        },
        "7": {
            "name": "Färjenäs AB.",
            "location": "Göteborg",
            "business": "Sågverksrörelse och trävaruexport. Tillverkar sågade trävaror, tunnstav, lådbräder och lådämnen.",
            "contact": {
                "office": "Postg. 2",
                "telegraph": "Färjenäs, Göteborg",
                "phone": [
                    "118498"
                ],
                "postgiro": "40778"
            },
            "financials": {
                "capital": "755,000 kr",
                "employees": {
                    "industriarb": 30
                },
                "annual_production_value": "540,000 kr"
            },
            "foundation_year": 1893
        }
    }
}