{
    "original": "Pettersson—Piano fabrik\n\nkvarnar, fruktpressar, passérmaskiner och\nsilar m. m.\n\nTelegr.-adr.: Levier, Anderstorp.\nTelefon: 19 o. 202. Postgiro: 22575. —\nAkt.-kap.: 150,000 kr. Antal industriarb.: 75.\nTillv.-värde pr år: 1,300,000 kr. —\nFirman etabl. 1914, bolag 1944.\n\nVerkst. dir.: Levi Peterson.\n\nDriftsing,: Kurt Idin.\n\nKamrer: Hartvig Idin.\n\n*N. Petterssons Snickerifabrik,\nBröderna Pettersson, Hestra.\n\nTillverkar butiksinredningar,\nkontorsmöbler m. m. vid fabrik i Hestra\n(Jönköp. l.).\n\nTelefon: 3. Postgiro: 168849. —\nAntal industriarb.: 17. Tillv.-värde pr år:\n270,000 kr. — Firman etabl. 1900.\n\nÄgare o. chefer: fabr. Ernst Petersson\no. fabr. Tage Petersson.\n\nTh. Petterssons Snickeri- &amp;\nBåtfabrik, Broddbo.\n\nSnickerifabrik och båtvarv i Broddbo\n(Västmanl. l.), båtvarv vid Smedsudden,\nStockholm. Tillverkar byggnadssnickerier\noch inredningar, monteringsfärdiga\nträhus, motor- och roddbåtar, kanoter samt\npontoner. Varumärken: »Atos» (spantlösa\nbåtar) o. »T. P.»-dörren.\n\nTelefon: 15 o. 25. Postgiro: 135953.\nVarvet i Stockholm, telefon: 516636.\nRepr. i Stockholm för snickerier:\nSnickericentralen AB., Klarabergsg. 60,\ntelefon: 231755.\n\nAntal industriarb.: 30. Tillv.-värde pr\når: 350,000 kr. — Firman etabl. 1914.\n\nÄgare o. chef: byggm. Theodor\nPettersson.\n\n\"Victor Pettersons Bokindustri AB.,\n\nStockholm.\n\nBoktryckeri, litografi, bokbinderi,\nkar-tonage, reklamateljé och bokförlag.\n\nUtför text- och illustrerade arbeten,\naffärs-, katalog-, reklam- och\nblanketttryck; litografiska arbeten såsom\netiketter, konstnärliga omslag, planscher och\naffischer; kontorsböcker; bok- och\npartiarbeten, kartonger, litografiska\nförpackningar, fönsterskyltar m. m.\n\nKontor: Holländarg. 10. Telegr.-adr.\no. telefon: »Victor Petterson»,\nStockholm. Postgiro: 939.\n\nAkt.-kap.: 500,000 kr. Antal\nindustriarb.: 185. — Firman etabl. 1874.\n\nStyrelse: dir. Alfr. Petterson (ordf.),\n\nfru Sigrid Petterson, herr B. Rundin,\nherr Per Arne Ström, dr Gunnar Ågren.\n\nVerkst. dir.: Alfr. Petterson.\n\nKamrer: Mårten Lind.\n\nFabriksförest.: A. Frändberg.\n\nBertil Petzén AB., Borås.\n\nTillverkar arbetskläder, skjortor, byxor,\ndamklänningar, förkläden, städrockar,\nnattlinnen och pyjamas. Varumärken:\nSparkronan, Styrbjörn Starke,\nStarkod-der o. Smeden.\n\nTelefon: 10413 o. 12655. Postgiro:\n37297.\n\nAkt.-kap.: 100,000 kr. Tillv.-värde pr\når: 600,000 kr. — Firman etabl. 1900,\nbolag 1928 under namn AB. Trikå- &amp;\nSyfabriken Standard, nuv. namn 1945.\n\nVerkst. dir. o. disp.: Bertil Petzén.\n\n\"AB. Pharmacia, Stockholm.\n\nFarmaceutisk-kemisk fabrik.\nTillverkar farmaceutiska preparat och\nkem.-tekn. artiklar.\n\nKontor: Lövholmsvägen 5,\nLiljeholmen; postadr.: Stockholm 9.\nTelegr.-adr.: Pharmacia, Stockholm. Telefon:\n452610. Postgiro: 1307.\n\nAkt.-kap.: 600,000 kr. Antal\nindustriarb.: 125. Tillv.-värde pr år: 6,400,000 kr.\n— Bolaget grundat 1911.\n\nStyrelse: apot. J. A. Berke, civiling.\nElis Göth, dir. Gottfrid^ Lundberg, dir.\nIvan Rothlin, övering. Birger Sundfeldt,\napot. Emil Thulin.\n\nVerkst. dir.: Elis Göth.\n\nFabrikschef: civiling. Ragnar\nAhl-strÖm.\n\nVetenskapliga rådgivare: prof. Gösta\nEdman, prof. Gustav Hulphers o. prof.\nKarl Myrbäck.\n\n\"Philips Svenska AB., Stockholm,\n\nSe Svenska AB. Philips, Stockholm.\n\n\"Pianofabriken, AB. Svenska,\n\nStockholm.\n\nSe AB. Svenska Pianofabriken,\nStockholm.\n\n\"Pianofabriks AB. Gustafson &amp;\nLjungqvist, Norrköping.\n\nTillverkar pianon.\n\nTelefon: 21839. Utställningar: i\nStockholm, Kungsg. 4; i Göteborg, Arkaden;\ni Malmö: österg. 11; i Norrköping, Gävle,\nÖrebro o. Linköping. —■ Akt.-kap.:\n150,000 kr.",
    "structured": {
        "firms": [
            {
                "name": "Pettersson—Piano fabrik",
                "location": "Anderstorp",
                "business": "Tillverkning av kvarnar, fruktpressar, passérmaskiner och silar m. m.",
                "contact": {
                    "telegraph": "Levier, Anderstorp",
                    "phone": [
                        "19",
                        "202"
                    ],
                    "postgiro": "22575"
                },
                "financials": {
                    "capital": "150,000 kr",
                    "employees": {
                        "industriarb.": 75
                    },
                    "annual_turnover": "1,300,000 kr",
                    "annual_production_value": "1,300,000 kr"
                },
                "foundation_year": 1914,
                "corporation_year": 1944,
                "director": "Levi Peterson",
                "managing_director": "Kurt Idin"
            },
            {
                "name": "N. Petterssons Snickerifabrik",
                "location": "Hestra (Jönköp. l.)",
                "business": "Tillverkning av butiksinredningar och kontorsmöbler m. m.",
                "contact": {
                    "phone": "3",
                    "postgiro": "168849"
                },
                "financials": {
                    "employees": {
                        "industriarb.": 17
                    },
                    "annual_production_value": "270,000 kr"
                },
                "foundation_year": 1900,
                "owners": [
                    "fabr. Ernst Petersson",
                    "fabr. Tage Petersson"
                ]
            },
            {
                "name": "Th. Petterssons Snickeri- & Båtfabrik",
                "location": "Broddbo (Västmanl. l.)",
                "business": "Tillverkning av byggnadssnickerier och inredningar, monteringsfärdiga trähus, motor- och roddbåtar, kanoter samt pontoner.",
                "contact": {
                    "phone": [
                        "15",
                        "25"
                    ],
                    "postgiro": "135953"
                },
                "financials": {
                    "employees": {
                        "industriarb.": 30
                    },
                    "annual_production_value": "350,000 kr"
                },
                "foundation_year": 1914,
                "owner": "byggm. Theodor Pettersson"
            },
            {
                "name": "Victor Pettersons Bokindustri AB.",
                "location": "Stockholm",
                "business": "Boktryckeri, litografi, bokbinderi, kartongage, reklamateljé och bokförlag.",
                "contact": {
                    "office": "Holländarg. 10",
                    "phone": "Victor Petterson, Stockholm",
                    "postgiro": "939"
                },
                "financials": {
                    "capital": "500,000 kr",
                    "employees": {
                        "industriarb.": 185
                    }
                },
                "foundation_year": 1874,
                "board": [
                    {
                        "name": "dir. Alfr. Petterson",
                        "role": "ordf."
                    },
                    {
                        "name": "fru Sigrid Petterson"
                    },
                    {
                        "name": "herr B. Rundin"
                    },
                    {
                        "name": "herr Per Arne Ström"
                    },
                    {
                        "name": "dr Gunnar Ågren"
                    }
                ],
                "director": "Alfr. Petterson"
            },
            {
                "name": "Bertil Petzén AB.",
                "location": "Borås",
                "business": "Tillverkning av arbetskläder, skjortor, byxor, damklänningar, förkläden, städrockar, nattlinnen och pyjamas.",
                "contact": {
                    "phone": [
                        "10413",
                        "12655"
                    ],
                    "postgiro": "37297"
                },
                "financials": {
                    "capital": "100,000 kr",
                    "annual_production_value": "600,000 kr"
                },
                "corporation_year": 1928,
                "current_name_year": 1945,
                "director": "Bertil Petzén"
            },
            {
                "name": "AB. Pharmacia",
                "location": "Stockholm",
                "business": "Farmaceutisk-kemisk fabrik. Tillverkning av farmaceutiska preparat och kem.-tekn. artiklar.",
                "contact": {
                    "office": "Lövholmsvägen 5, Liljeholmen",
                    "phone": "Pharmacia, Stockholm",
                    "postgiro": "1307"
                },
                "financials": {
                    "capital": "600,000 kr",
                    "employees": {
                        "industriarb.": 125
                    },
                    "annual_turnover": "6,400,000 kr"
                },
                "foundation_year": 1911,
                "board": [
                    {
                        "name": "apot. J. A. Berke"
                    },
                    {
                        "name": "civiling. Elis Göth"
                    },
                    {
                        "name": "dir. Gottfrid Lundberg"
                    },
                    {
                        "name": "dir. Ivan Rothlin"
                    },
                    {
                        "name": "övering. Birger Sundfeldt"
                    },
                    {
                        "name": "apot. Emil Thulin"
                    }
                ],
                "director": "Elis Göth"
            },
            {
                "name": "Pianofabriks AB. Gustafson & Ljungqvist",
                "location": "Norrköping",
                "business": "Tillverkning av pianon.",
                "contact": {
                    "phone": "21839"
                },
                "corporation_year": 1945
            }
        ]
    }
}