{
    "original": "A Iran v e rken—Öde borg\n\nÄtranverken AB., Falkenberg.\n\nTillverkar cykelsadlar (märke:\n»Elas-iic»), ryggsäcksmesar, detaljer för\nbelysningsarmatur samt stansade och pressade\njärn- och metallvaror.\n\nTelegr.-adr.: Ätranverken, Falkenberg.\nTelefon: 857. Postgiro: 183379.\n\nAkt.:kap.: 75,000 kr. Antal industri-\n\narb.: 40. — Bolaget grundat 1937. #\n\nStyrelse: major Ragnar Aaby-Ericsson\n(ordf.), adv. I. Skogh, dir. Georg\nTorstenson.\n\nVerkst. dir.: Georg Torstenson\n(Alvesta).\n\nDisp.: Erik Thorell.\n\nFabrihschef: P. Harms.\n\n* utmärker till Sveriges Industriförbund anslutna företag.\n\n\"\"C. O. Öberg &amp; Co:s AB.,\n\nEskilstuna.\n\nFilfabrik. Tillverkar filar och raspar,\npansarfilar, diagonalfilar, roterande\nfilar, skavstål samt glasborrar.\nVarumärken: »Halvmåne», »Pansar» o. »Wasa».\n\nTelegr.-adr.: Öbergs, Eskilstuna.\nTelefon: 37460. Postgiro: 10079.\n\nAkt.-kap.: 2,800,000 kr. Antal\nindustriarb.: 460. — Fabriken anlagd 1850, bolag\n1907.\n\nStyrelse: f. rådman J. Au g. Hedin\n&lt;ordf.), disp. Arvid H. Nilsson, herr\nIvar Nilsson.\n\nVerkst. dir.: Arvid H. Nilsson.\n\n(Jfr annons nr 58.)\n\n*AB. J. O. Öberg &amp; Son,\n\nEskilstuna.\n\nKontorsbokf abrik, offsettryckeri,\nklichéanstalt och boktryckeri, spelkortsfabrik.\n\nTillverkar kontorsböcker,\nlösbladsböc-ker och kortsystem, anteckningsböcker,\nmillimeterpapper, samlingskartonger och\nsamlingspärmar, portföljer, spelkort,\nde-kalkomanier, allmänna blanketter m. m.\nsamt reklam-, affärs- och banktryck.\n\nHuvudkontor: Eskilstuna.\nTelegr.-adr.: öbergson, Eskilstuna. Telefon:\n»Öberg &amp; Son». Postgiro: 6087.\nAvd.-kontor: i Stockholm, Klara V. Kyrkog.\n15, telefon: 232625; i Malmö, Mårtensg.\n\ntelefon: 71205. — Antal industriarb.:\n440.\n\nFirman grundades 1845 och är\nansluten till AB. Sveriges Litografiska\nTryckerier, Stockholm. (Se detta bolag.)\n\nStyrelse: kapten Tore H. Bendz (ordf.),\ndisp. Tage A. Bendz.\n\nVerkst. dir.: disp. Tage A. Bendz.\n\nFörsäljn.-chef: Olof Redin.\n\nAvd.-chef er: i Stockholm: kamrer Axel\nKarlsson; i Malmö: Bertil Bendz.\n\nÖdbogårdens Kalkbruks AB.,\n\nKinnemalma.\n\nTillverkar kalk för jordbruks- och\nbyggnadsändamål vid kalkbruk i Kinnemalma\n(Skarab. l.). Bolaget driver även\njordbruk.\n\nTelefon: Kinne Kleva 58. — Akt.-kap.:\n200,000 kr. Antal industriarb.: 30. Tillv.-\n\nvärde pr år: 250,000 kr. — Bolaget\ngrundat 1917.\n\nStyrelse: dir. Knut Karlsson (ordf.),\nfru Jennie Beckman, förvalt. Eric\nWer-mel.\n\nFörvalt.: Eric Wermel.\n\n\"Ödeborgs Bruks AB., Ödeborg.\n\nJärnbruk med presspikfabrik,\nklipp-spikfabrik, tråddrageri, trådspikfabrik,\nmek. verkstad samt sågverk, tegelbruk\noch elektr. vattenkraftstationer vid\nödeborg och Färgelanda (båda i Älvsb. l.).\n\nTillverkar presspik, klippspik,\ntrådspik, skotacks, dragen järntråd, sågade\nträvaror samt mur-, tak- och rörtegel.\n\nTelegr.-adr.: ödeborgsbruket,\nUddevalla. Telefon: Uddevalla 10428 samt\nFärgelanda 9, 90 o. 109. Postgiro: 84330.\n\nAkt.-kap.: 1,000,000 kr. Antal\nindustriarb.: 200. Tillv.-värde pr år: 4,600,000 kr.\n— Bolaget grundat 1898.\n\nStyrelse: dir. Claes Wahlund (ordf.),\nflygdir. Per Anjou, disp. Åke Anjou.\n\nVerkst. dir.: Åke Anjou.\n\nÖvering.: Per Anjou.\n\nFörsäljn.- o. hontorschef: int. Ragnar\nHillström.\n\n(Jfr annons nr 60.)\n\n647*",
    "structured": {
        "1": {
            "name": "Ätranverken AB",
            "location": "Falkenberg",
            "business": "Tillverkar cykelsadlar (märke: »Elas-iic»), ryggsäcksmesar, detaljer för belysningsarmatur samt stansade och pressade järn- och metallvaror.",
            "contact": {
                "telegraph": "Ätranverken, Falkenberg",
                "phone": [
                    "857"
                ],
                "postgiro": "183379"
            },
            "financials": {
                "capital": "75,000 kr",
                "employees": {
                    "industriarb": 40
                }
            },
            "foundation_year": 1937,
            "board": [
                {
                    "name": "major Ragnar Aaby-Ericsson",
                    "role": "ordf."
                },
                {
                    "name": "adv. I. Skogh",
                    "role": ""
                },
                {
                    "name": "dir. Georg Torstenson",
                    "role": ""
                }
            ],
            "director": "Georg Torstenson",
            "managing_director": "Georg Torstenson",
            "manager": "Erik Thorell",
            "factory_office": "P. Harms"
        },
        "2": {
            "name": "C. O. Öberg & Co:s AB",
            "location": "Eskilstuna",
            "business": "Filfabrik. Tillverkar filar och raspar, pansarfilar, diagonalfilar, roterande filar, skavstål samt glasborrar. Varumärken: »Halvmåne», »Pansar» o. »Wasa».",
            "contact": {
                "telegraph": "Öbergs, Eskilstuna",
                "phone": [
                    "37460"
                ],
                "postgiro": "10079"
            },
            "financials": {
                "capital": "2,800,000 kr",
                "employees": {
                    "industriarb": 460
                }
            },
            "foundation_year": 1850,
            "corporation_year": 1907,
            "board": [
                {
                    "name": "f. rådman J. Au g. Hedin",
                    "role": "ordf."
                },
                {
                    "name": "disp. Arvid H. Nilsson",
                    "role": ""
                },
                {
                    "name": "herr Ivar Nilsson",
                    "role": ""
                }
            ],
            "director": "Arvid H. Nilsson"
        },
        "3": {
            "name": "AB. J. O. Öberg & Son",
            "location": "Eskilstuna",
            "business": "Kontorsbokfabrik, offsettryckeri, klichéanstalt och boktryckeri, spelkortsfabrik. Tillverkar kontorsböcker, lösbladsböcker och kortsystem, anteckningsböcker, millimeterpapper, samlingskartonger och samlingspärmar, portföljer, spelkort, dekalkomanier, allmänna blanketter m. m. samt reklam-, affärs- och banktryck.",
            "contact": {
                "telegraph": "öbergson, Eskilstuna",
                "phone": [
                    "Öberg & Son"
                ],
                "postgiro": "6087"
            },
            "financials": {
                "employees": {
                    "industriarb": 440
                }
            },
            "foundation_year": 1845
        },
        "4": {
            "name": "Ödbogårdens Kalkbruks AB",
            "location": "Kinnemalma",
            "business": "Tillverkar kalk för jordbruks- och byggnadsändamål vid kalkbruk i Kinnemalma (Skarab. l.). Bolaget driver även jordbruk.",
            "contact": {
                "phone": [
                    "Kinne Kleva 58"
                ]
            },
            "financials": {
                "capital": "200,000 kr",
                "employees": {
                    "industriarb": 30
                },
                "annual_production_value": "250,000 kr"
            },
            "foundation_year": 1917,
            "board": [
                {
                    "name": "dir. Knut Karlsson",
                    "role": "ordf."
                },
                {
                    "name": "fru Jennie Beckman",
                    "role": ""
                },
                {
                    "name": "förvalt. Eric Wermel",
                    "role": ""
                }
            ],
            "manager": "Eric Wermel"
        },
        "5": {
            "name": "Ödeborgs Bruks AB",
            "location": "Ödeborg",
            "business": "Järnbruk med presspikfabrik, klipp-spikfabrik, tråddrageri, trådspikfabrik, mek. verkstad samt sågverk, tegelbruk och elektr. vattenkraftstationer vid ödeborg och Färgelanda (båda i Älvsb. l.). Tillverkar presspik, klippspik, trådspik, skotacks, dragen järntråd, sågade trävaror samt mur-, tak- och rörtegel.",
            "contact": {
                "telegraph": "ödeborgsbruket, Uddevalla",
                "phone": [
                    "Uddevalla 10428",
                    "Färgelanda 9",
                    "Färgelanda 90",
                    "Färgelanda 109"
                ],
                "postgiro": "84330"
            },
            "financials": {
                "capital": "1,000,000 kr",
                "employees": {
                    "industriarb": 200
                },
                "annual_turnover": "4,600,000 kr"
            },
            "foundation_year": 1898,
            "board": [
                {
                    "name": "dir. Claes Wahlund",
                    "role": "ordf."
                },
                {
                    "name": "flygdir. Per Anjou",
                    "role": ""
                },
                {
                    "name": "disp. Åke Anjou",
                    "role": ""
                }
            ],
            "director": "Åke Anjou",
            "managing_director": "Per Anjou",
            "sales_manager": "Ragnar Hillström"
        }
    }
}