{
    "original": "Halmstad—Hammar\n\nHalmstads Gjuteri AB., nuv. bolag 1907,\när dotterbolag till AB. Malcus Holmquist,\nHalmstad.\n\nStyrelse: dir. Edw. Berger (ordf.),\nv. konsul A. O. Hill, ing. Johan Wendt.\nVerkst. dir.: Edw. Berger.\nDisp.: civiling. Bertil Junger.\n\n\"Halmstads Snickerifabrik,\n\nHalmstad.\n\nTillverkar byggnadssnickerier och\ninredningar.\n\nTelefon: 946. — Antal industriarb.: 25.\nTillv.-värde pr år: 250,000 kr. — Firman\netabl. 1926.\n\nÄgare o. chef: arkitekt Artur Alf sjö.\n\n\"AB. Halmstads Spik- &amp; Trådverk,\n\nHalmstad.\n\nTillverkar trådspik, glödgad,\ngalvani-serad och blankdragen järntråd,\nbloms-tertråd, säckbindare, öglad tråd, kapad\noch riktad tråd samt band järn, såväl\nkallvalsat som galvaniserat.\n\nTelegr.-adr.: Spikfabriken, Halmstad.\nTelefon: 1507. Postgiro: 33102.\n\nAkt.-kap.: 350,000 kr. Antal\nindustriarb.: 45. Tillv.-värde pr år: 1,100,000 kr.\n\n—\tBolaget grundat 1921.\n\nStyrelse: disp. Rudolf Sunström (ordf.),\nkanslisekr. Allan Tigerschiöld, dir. Folke\nWilhelmson.\n\nDisp.: Helge Malmberg.\n\nHalmstads Trikåindustri AB.,\n\nHalmstad.\n\nTillverkar trikåvaror i charmeuse.\nTelefon: 4675. Postgiro: 264931. —\nAkt.-kap.: 25,000 kr. Antal industriarb.:\n20. — Bolaget grundat 1942.\nVerkst. dir.: Oscar Olving.\n\n\"Halmstads Valskvarn, Halmstad.\n\nSe Halmstad-Falkenbergs Kvarn AB.,\n\nHalmstad.\n\n\"Halmstads Varvs Nya AB.,\n\nHalmstad.\n\nUtför nybyggnader och reparationer av\nhuvudsakligen träfartyg.\n\nTelefon: 632. Postgiro: 34134.\nAkt.-kap.: 55,000 kr. Antal\nindustriarb.: 20. Prod.-värde pr år: 160,000 kr.\n\n—\tBolaget grundat 1922.\n\nStyrelse: skeppsmäkl. A. Th. Jonasson\n(ordf.), järnhandl. John Holm, disp. Åke\nHolm, skeppsbyggmäst. Einar Johanson.\nVerkst. dir.: Åke Holm.\n\nH. Halmö AB., Malmö.\n\nTält- och presenningfabrik. Tillverkar\ntält, segel, presenningar, markiser och\nflaggor. Varumärke: »Jambo».\n\nKontor: Djäkneg. 24—26. Telegr.-adr.:\nTälthalmö, Malmö. Telefon: 10151 o.\n77775. Postgiro: 37723.\n\nAkt.-kap.: 25,000 kr. Antal\nindustriarb.: 25. Tillv.-värde pr år: 200,000 kr.\n\n—\tBolaget grundat 1922.\n\nStyrelse: dir. Georg Jaeppelt.\n\nDisp.: Gunnar Wittgren.\n\n\"Hamburger Bryggeriet, Stockholm.\n\nSe AB. Stockholms Bryggerier,\nStockholm.\n\n\"Hammars Glasbruks AB.,\n\nHammar.\n\nGlasbruk vid Hammar (Örebro l.).\nTillverkar buteljer. Bolaget idkar\njämväl jordbruk.\n\nTelegr.-adr.: Glasbruket, Askersund.\nTelefon: Hammar 3 o. 4. Postgiro: 83954.\nEnsamförsälj.: Buteljglasbrukens\nFörsäljnings AB., Stockholm, Birger Jarlsg.\n2. Telefon: 619920—23.\n\nAkt.-kan.: 600,000 kr. Antal\nindustriarb.: 55. Försäljn.-värde pr år: 1,200,000\nkr. — Glasbruket anlagt 1854, bolag 1874.\n\nStyrelse: dir. Sven Schwartz (ordf.),\ndir. Harald Engström, civiling. Carl\nGustaf Piehi.\n\nVerkst. dir.: Sven Schwartz (Sthlm).\n\nDisp.: civiling. C.-A. Larsson.\n\nAB. Hammars Mek. Verkstad,\n\nNyland.\n\nMek. verkstad, gjuteri och fartygsslip\ni Nyland (Västernorrl. l.). Tillverkar\nmetall- och tackjärnsgjutgods, cisterner och\ntryckluftkärl, transportrullar och\ntransportörer, varpspelsbåtar och motorfärjor\nsamt utför anläggningar för vattenrening\noch träimpregnering.\n\nTelegr.-adr.: Verkstaden, Nyland.\nTelefon: 34. Postgiro: 172320.\n\nAkt.-kap.: 60,000 kr. Antal\nindustriarb.: 50. Tillv.-värde pr år: 700,000 kr.\n\n—\tBolaget grundat 1902.\n\nStyrelse: ing. Gustav A. Andersson,\nverkm. Lars-Erik Fridlund, ing. Folke\nHolmberg.\n\nVerkst. dir.: Folke Holmberg.\n\nC. M. Hammars Metallvarufabrik,\n\nGöteborg.\n\nArmaturfabrik, koppar-, bleck- och\nplåtslageri. Tillverkar kompasser,\nlanternor och skeppslampor, armatur, kok-",
    "structured": {
        "1": {
            "name": "Halmstads Gjuteri AB",
            "location": "Halmstad",
            "foundation_year": 1907,
            "corporation_year": 1907,
            "board": [
                {
                    "name": "dir. Edw. Berger",
                    "role": "ordf."
                },
                {
                    "name": "v. konsul A. O. Hill",
                    "role": ""
                },
                {
                    "name": "ing. Johan Wendt",
                    "role": ""
                }
            ],
            "director": "Edw. Berger",
            "financials": {
                "capital": "",
                "employees": {},
                "annual_turnover": "",
                "annual_production_value": ""
            }
        },
        "2": {
            "name": "Halmstads Snickerifabrik",
            "business": "Tillverkar byggnadssnickerier och inredningar",
            "location": "Halmstad",
            "products": "",
            "contact": {
                "office": "",
                "phone": [
                    "946"
                ],
                "postgiro": "",
                "head_office": "",
                "sales_offices": [],
                "telegraph": "",
                "factory_office": "",
                "factory_phone": ""
            },
            "foundation_year": 1926
        },
        "3": {
            "name": "AB. Halmstads Spik- & Trådverk",
            "business": "Tillverkar trådspik, glödgad, galvani-serad och blankdragen järntråd",
            "location": "Halmstad",
            "products": "bloms-tertråd, säckbindare, öglad tråd, kapad och riktad tråd samt band järn, såväl kallvalsat som galvaniserat",
            "contact": {
                "office": "",
                "phone": [
                    "1507"
                ],
                "postgiro": "33102",
                "head_office": "",
                "sales_offices": [],
                "telegraph": "Spikfabriken, Halmstad",
                "factory_office": "",
                "factory_phone": ""
            },
            "foundation_year": 1921,
            "financials": {
                "capital": "350,000 kr",
                "employees": {},
                "annual_turnover": "",
                "annual_production_value": "1,100,000 kr"
            }
        },
        "4": {
            "name": "Halmstads Trikåindustri AB",
            "business": "Tillverkar trikåvaror i charmeuse",
            "location": "Halmstad",
            "products": "",
            "contact": {
                "office": "",
                "phone": [
                    "4675"
                ],
                "postgiro": "264931",
                "head_office": "",
                "sales_offices": [],
                "telegraph": "",
                "factory_office": "",
                "factory_phone": ""
            },
            "foundation_year": 1942,
            "financials": {
                "capital": "25,000 kr",
                "employees": {},
                "annual_turnover": "",
                "annual_production_value": ""
            }
        },
        "5": {
            "name": "Halmstads Valskvarn",
            "location": "Halmstad",
            "products": "",
            "contact": {
                "office": "",
                "phone": [],
                "postgiro": "",
                "head_office": "",
                "sales_offices": [],
                "telegraph": "",
                "factory_office": "",
                "factory_phone": ""
            },
            "foundation_year": 1922
        },
        "6": {
            "name": "Halmstads Varvs Nya AB",
            "business": "Utför nybyggnader och reparationer av huvudsakligen träfartyg",
            "location": "Halmstad",
            "products": "",
            "contact": {
                "office": "",
                "phone": [
                    "632"
                ],
                "postgiro": "34134",
                "head_office": "",
                "sales_offices": [],
                "telegraph": "",
                "factory_office": "",
                "factory_phone": ""
            },
            "foundation_year": 1922,
            "financials": {
                "capital": "55,000 kr",
                "employees": {},
                "annual_turnover": "",
                "annual_production_value": "160,000 kr"
            }
        },
        "7": {
            "name": "H. Halmö AB",
            "business": "Tält- och presenningfabrik",
            "location": "Malmö",
            "products": "Tillverkar tält, segel, presenningar, markiser och flaggor",
            "contact": {
                "office": "Djäkneg. 24—26",
                "phone": [
                    "10151",
                    "77775"
                ],
                "postgiro": "37723",
                "head_office": "",
                "sales_offices": [],
                "telegraph": "Tälthalmö, Malmö",
                "factory_office": "",
                "factory_phone": ""
            },
            "foundation_year": 1922,
            "financials": {
                "capital": "25,000 kr",
                "employees": {},
                "annual_turnover": "",
                "annual_production_value": "200,000 kr"
            },
            "owner": "Georg Jaeppelt"
        },
        "8": {
            "name": "Hamburger Bryggeriet",
            "location": "Stockholm",
            "products": "",
            "contact": {
                "office": "",
                "phone": [],
                "postgiro": "",
                "head_office": "",
                "sales_offices": [],
                "telegraph": "",
                "factory_office": "",
                "factory_phone": ""
            }
        },
        "9": {
            "name": "Hammars Glasbruks AB",
            "location": "Hammar",
            "products": "Tillverkar buteljer",
            "contact": {
                "office": "",
                "phone": [
                    "Hammar 3",
                    "4"
                ],
                "postgiro": "83954",
                "head_office": "",
                "sales_offices": [],
                "telegraph": "Glasbruket, Askersund",
                "factory_office": "",
                "factory_phone": ""
            },
            "foundation_year": 1874,
            "financials": {
                "capital": "600,000 kr",
                "employees": {},
                "annual_turnover": "",
                "annual_production_value": "1,200,000 kr"
            }
        },
        "10": {
            "name": "AB. Hammars Mek. Verkstad",
            "location": "Nyland",
            "products": "Tillverkar metall- och tackjärnsgjutgods, cisterner och tryckluftkärl, transportrullar och transportörer, varpspelsbåtar och motorfärjor samt utför anläggningar för vattenrening och träimpregnering",
            "contact": {
                "office": "Verkstaden, Nyland",
                "phone": [
                    "34"
                ],
                "postgiro": "172320",
                "head_office": "",
                "sales_offices": [],
                "telegraph": "",
                "factory_office": "",
                "factory_phone": ""
            },
            "foundation_year": 1902,
            "owner": [
                "Gustav A. Andersson"
            ]
        },
        "11": {
            "name": "C. M. Hammars Metallvarufabrik",
            "location": "Göteborg",
            "business": "Armaturfabrik, koppar-, bleck- och plåtslageri",
            "products": "Tillverkar kompasser, lanternor och skeppslampor, armatur, kok-.",
            "contact": {
                "office": "",
                "phone": [],
                "postgiro": "",
                "head_office": "",
                "sales_offices": [],
                "telegraph": "",
                "factory_office": "",
                "factory_phone": ""
            }
        }
    }
}