{
    "original": "Flen—Flisby\n\nTelefon: 376. Postgiro: 174257. —\nAntal industriarb.: 17. Tillv.-värde pr år:\n200,000 kr. — Firman etabl. 1931.\n\nÄgare o. chef: fabr. Per R.\nPettersson.\n\n*AB. Flens Tegelbruk, Flen.\n\nTillverkar mur- och taktegel samt\ndrä-näringsrör vid tegelbruk i Flen\n(Södermanl. l.).\n\nTelefon: 206. Postgiro: 24156. —\nAkt.-kap.: 126,800 kr. Antal industriarb.: 20.\nTillv.-värde pr år: 125,000 kr. — Bolaget\ngrundat 1914.\n\nVerkst. dir.: disp. Carl-Werner\nJohanson.\n\nTegelmåst.: Gust. Adolf Larsson.\n\nFlerohopps Bruks AB.,\n\nFlerohopp.\n\nGlasbruk och sågverk vid Flerohopp\n(Kalmar l.). Tillverkar glasrör,\nglaskolvar till termosflaskor, glödlampor,\nradiorör och röntgenrör m. m. samt sågade\nträvaror.\n\nTelegr.-adr.: Fleroglas, Kalmar.\nTelefon: Flerohopp 9 o. 10. Postgiro: 97448.\n-—Akt.-kap.: 54 000 kr. Antal\nindustriarb.: 150. — Firman etabl. 1908.\n\nStyrelse: disp. Håkan Sterner (ordf.),\ndir. H. Klette.\n\nDisp.: Håkan Sterner.\n\nKamrer: Gustaf Svensson.\n\n*AB. E. Fleron, Malmö.\n\nMek. verkstad. Tillverkar\nfilhuggnings-maskiner, maskiner för\nmotorrenoveringar såsom vevaxelslipmaskiner,\nfin-borrverk för vevstakar, brotch- och\npoler-maskiner, ramlagerborrverk,\nkolvbearbet-ningsmaskiner, lagergjutningsmaskiner,\navfettningstankar, härdtankar m. fl.,\nmotorcykel- och automobilreservdelar,\nväxellådor, cylindriska och koniska kugghjul,\nkedjehjul samt bearbetade kuggväxlar.\n\nKontor: Malmg. 4. Telegr.-adr.:\nFle-ronmaskin, Malmö. Telefon: 24118,22141,\n33343 o. 22116. Postgiro: 37843.\n\nAkt.-kap.: 150,000 kr. Tillv.-värde pr\når: 600 000 kr. — Bolaget, grundat 1912,\näger AB. Motorslip, Malmö.\n\nStyrelse: landssekr. Hjalmar P. Kjäll\n(ordf.), dir. Axel Löfström, kamrer Gösta\nS. Nilsson.\n\nVerkst. dir.: Axel Löf ström.\n\növering.: Claes Andrén.\n\nKamrer: Gösta S. Nilsson.\n\nInköpschef: Arne Kanne.\n\nIi\n\n*AB. Flexo, Stockholm.\n\nMek. verkstad i Orsa (Kopparb. l.).\nTillverkar trädgårdsredskap, elektr.\nin-stallationsmateriel, pressade massartiklar\nsamt pressverktyg. Specialitet:\n»Flexo»-trädgårdsräfsor. Bolaget driver även\nengroshandel med järnvaror.\n\nKontor: Stockholm, Tuleg. 19.\nTelegr.-adr.: Flexoab, Stockholm. Telefon: 318515\no. 303979. Postgiro: 155440.\n\nAkt.-kap.: 20,000 kr. Antal\nindustriarb.: 65. Tillv.-värde pr år: 700,000 kr. —\nBolaget grundat 1938.\n\nStyrelse: dir. Gunnar Östberg (ordf.),\nfabr. Anders Lind.\n\nVerkst. dir.: Gunnar Östberg.\n\nFlinks Cranitstenhuggeri,\nBröderna, Västervik.\n\nSe AB. Bröderna Flinks\nGranitsten-huggeri i Westervik, Västervik.\n\nAB. C. J. Flinks Söner, Västervik.\n\nStenhuggeri och stensliperi.\nTillverkar som specialitet gravvårdar och\ngravramar av svart Västerviksgranit ävensom\nbyggnadssten.\n\nTelefon: 189. Postgiro: 81451. Repr.:\nJohn R. Mikaelsson, Kalmar, telefon:\n528.\n\nAkt.-kap.: 100,000 kr. Antal\nindustriarb.: 30. Prod.-värde pr år: 450,000 kr.\n\n—\tFirman etabl. 1881, bolag 1927.\nVerkst. dir.: Josef E. Flink.\nKamrer: Harald Stenberg.\n\n*AB. Gustaf Flinta, Hedemora.\n\nMöbelfabrik. Tillverkar finare möbler\noch butiksinredningar.\n\nTelegr.-adr.: Flinta, Hedemora.\nTelefon: 325. — Akt.-kap.: 100,000 kr.\nArb.-antal: 15. Tillv.-värde pr år: 100,000 kr.\n\n—\tFirman etabl. 1887, bolag 1904.\nStyrelse: dir. Wilhelm Björkman, disp.\n\nRuben Persson, dir. Gustav Raabe.\nVerkst. dir.: Ruben Persson.\n\n* Flisby Tegelbruk, Flisby.\n\nTillverkar murtegel vid tegelbruk i\nFlisby (Jönköp. l.).\n\nTelefon: 3. Repr.: AB. J. E. Sundberg\n&amp; Co., Nässjö. — Antal industriarb.: 27.\nÅrsprod.: 1,25 milj. st. tegelvaror. —\nFirman etabl. 1909.\n\nÄgare o. chef: fru A.-L.\nLjunggren-Hellström.",
    "structured": {
        "1": {
            "name": "Flens Tegelbruk",
            "location": "Flen",
            "business": "Tillverkar mur- och taktegel samt drä-näringsrör vid tegelbruk i Flen (Södermanl. l.)",
            "contact": {
                "phone": [
                    "376"
                ],
                "postgiro": "174257"
            },
            "financials": {
                "capital": "126,800 kr",
                "employees": {
                    "industriarb": 20
                },
                "annual_production_value": "125,000 kr"
            },
            "foundation_year": 1931,
            "director": "fabr. Per R. Pettersson"
        },
        "2": {
            "name": "Flerohopps Bruks AB.",
            "location": "Flerohopp",
            "business": "Tillverkar glasrör, glaskolvar till termosflaskor, glödlampor, radiorör och röntgenrör m. m. samt sågade trävaror.",
            "contact": {
                "phone": [
                    "Flerohopp 9",
                    "Flerohopp 10"
                ],
                "postgiro": "97448"
            },
            "financials": {
                "capital": "54,000 kr",
                "employees": {
                    "industriarb": 150
                }
            },
            "foundation_year": 1908,
            "board": [
                {
                    "name": "disp. Håkan Sterner",
                    "role": "ordf."
                },
                {
                    "name": "dir. H. Klette",
                    "role": ""
                }
            ],
            "director": "disp. Håkan Sterner",
            "sales_manager": "disp. Håkan Sterner",
            "manager": "disp. Håkan Sterner",
            "managing_director": "disp. Håkan Sterner"
        },
        "3": {
            "name": "AB. E. Fleron",
            "location": "Malmö",
            "business": "Tillverkar filhuggnings-maskiner, maskiner för motorrenoveringar såsom vevaxelslipmaskiner, fin-borrverk för vevstakar, brotch- och poler-maskiner, ramlagerborrverk, kolvbearbet-ningsmaskiner, lagergjutningsmaskiner, avfettningstankar, härdtankar m. fl., motorcykel- och automobilreservdelar, växellådor, cylindriska och koniska kugghjul, kedjehjul samt bearbetade kuggväxlar.",
            "contact": {
                "office": "Malmg. 4",
                "phone": [
                    "24118",
                    "22141",
                    "33343",
                    "22116"
                ],
                "postgiro": "37843"
            },
            "financials": {
                "capital": "150,000 kr",
                "annual_turnover": "600,000 kr"
            },
            "foundation_year": 1912,
            "board": [
                {
                    "name": "landssekr. Hjalmar P. Kjäll",
                    "role": "ordf."
                },
                {
                    "name": "dir. Axel Löfström",
                    "role": ""
                },
                {
                    "name": "kamrer Gösta S. Nilsson",
                    "role": ""
                },
                {
                    "name": "verkst. dir. Axel Löfström",
                    "role": ""
                },
                {
                    "name": "övering. Claes Andrén",
                    "role": ""
                },
                {
                    "name": "inköpschef Arne Kanne",
                    "role": ""
                }
            ]
        },
        "4": {
            "name": "AB. Flexo",
            "location": "Stockholm",
            "business": "Tillverkar trädgårdsredskap, elektr. in-stallationsmateriel, pressade massartiklar samt pressverktyg. Specialitet: »Flexo»-trädgårdsräfsor. Bolaget driver även engroshandel med järnvaror.",
            "contact": {
                "office": "Stockholm, Tuleg. 19",
                "phone": [
                    "318515",
                    "303979"
                ],
                "postgiro": "155440"
            },
            "financials": {
                "capital": "20,000 kr",
                "employees": {
                    "industriarb": 65
                },
                "annual_turnover": "700,000 kr"
            },
            "foundation_year": 1938,
            "board": [
                {
                    "name": "dir. Gunnar Östberg",
                    "role": "ordf."
                },
                {
                    "name": "fabr. Anders Lind",
                    "role": ""
                },
                {
                    "name": "verkst. dir. Gunnar Östberg",
                    "role": ""
                }
            ]
        },
        "5": {
            "name": "AB. C. J. Flinks Söner",
            "location": "Västervik",
            "business": "Tillverkar som specialitet gravvårdar och gravramar av svart Västerviksgranit ävensom byggnadssten.",
            "contact": {
                "phone": [
                    "189"
                ],
                "postgiro": "81451",
                "representative": "John R. Mikaelsson, Kalmar",
                "representative_phone": "528"
            },
            "financials": {
                "capital": "100,000 kr",
                "employees": {
                    "industriarb": 30
                },
                "annual_production_value": "450,000 kr"
            },
            "foundation_year": 1881,
            "corporation_year": 1927,
            "board": [
                {
                    "name": "Verkst. dir. Josef E. Flink",
                    "role": ""
                },
                {
                    "name": "Kamrer Harald Stenberg",
                    "role": ""
                }
            ]
        },
        "6": {
            "name": "AB. Gustaf Flinta",
            "location": "Hedemora",
            "business": "Tillverkar finare möbler och butiksinredningar.",
            "contact": {
                "telegraph": "Flinta, Hedemora",
                "phone": [
                    "325"
                ]
            },
            "financials": {
                "capital": "100,000 kr",
                "employees": {
                    "industriarb": 15
                },
                "annual_production_value": "100,000 kr"
            },
            "foundation_year": 1887,
            "corporation_year": 1904,
            "board": [
                {
                    "name": "dir. Wilhelm Björkman",
                    "role": ""
                },
                {
                    "name": "disp. Ruben Persson",
                    "role": ""
                },
                {
                    "name": "dir. Gustav Raabe",
                    "role": ""
                },
                {
                    "name": "verkst. dir. Ruben Persson",
                    "role": ""
                }
            ]
        },
        "7": {
            "name": "Flisby Tegelbruk",
            "location": "Flisby",
            "business": "Tillverkar murtegel vid tegelbruk i Flisby (Jönköp. l.)",
            "contact": {
                "phone": [
                    "3"
                ],
                "representative": "AB. J. E. Sundberg & Co., Nässjö"
            },
            "financials": {
                "employees": {
                    "industriarb": 27
                },
                "annual_production_value": "1,250,000 st. tegelvaror"
            },
            "foundation_year": 1909,
            "director": "fru A.-L. Ljunggren-Hellström"
        }
    }
}