{
    "original": "Z andelin—Zuckerman\n\nLejon, Divi, Divinia, Oral, Barberin,\nZaba, Grace m. fl.\n\nKontor: Stora Ny g. 35. Telegr.-adr.:\nZadig, Malmö. Telefon: 20657 o. 24200.\nPostgiro: 38218. Avd.-kontor: Stockholm,\nSmedsbacksg. 5, telefon: 673656.\n\nAkt.-kap.: 300,000 kr. Antal\nindustriarb.: 40. Tillv.-värde pr år: 1,000,000 kr.\n— Firman etabl. 1865, bolag 1931.\n\nStyrelse: disp. Harry Sandnes, dir.\nAxel Svanberg, apot. Karl-Gustav\nSvanberg.\n\nVerkst. dir.: Axel Svanberg.\n\nDisp.: Harry Sandnes.\n\nFabrihschef: K.-G. Svanberg.\n\nAvd.-chef i Stockholm: John Byström.\n\nZandelins Tryckeri AB., Malmö.\n\nTryckeri, bokbinderi och kartongfabrik.\nUtför trycksaker samt tillverkar\nlagerblanketter och kartonger.\n\nKontor: Hjulhamnsg. 3. Telefon: 27852\no. 27868. Postgiro: 24522. — Akt.-kap.:\n25,000 kr. Antal industriarb.: 40.\nTillv.-värde pr år: 500,000 kr. — Bolaget\ngrundat 1926.\n\nTrycherichef: Torsten Flintberg.\n\n*T. Zander, Shönnarbo.\n\nSe Lämneå Bruk, T. Zander,\nSkön-narbo.\n\n*Zeniths Margarinfabrik, Malmö.\nSe Margarin AB. Zenith, Malmö.\n\n*Zenks Bryggeri AB., Örebro.\n\nTillverkar maltdrycker, läskedrycker\noch mineralvatten.\n\nTelefon: »Zenksbryggeri». Postgiro:\n11268. — Akt.-kap.: 300,000 kr. Antal\nindustriarb.: 25. — Firman etabl. 1860,\nbolag 1919.\n\nStyrelse: bryggeriing. Tobias Åkesson\n(ordf.), adv. Torsten Malm, bankdir. Sven\nRassback.\n\nVerkst. dir.: Tobias Åkesson.\n\n\"Zetterberg AB., Byggnadsfirman,\n\nStockholm.\n\nByggnadsentreprenörfirma för\nbostads-och affärshus, industribyggnader m. m.\n\nHuvudkontor: Stockholm, Artillerig.\n28. Telegr.-adr.: Byggzeta, Stockholm.\nTelefon: 620833 o. 610402. Postgiro:\n53188. Avd.-kontor: Göteborg, ö. Hamng.\n30—34.\n\nAkt.-kap.: 500,000 kr. — Bolaget\ngrundat 1917.\n\nStyrelse: byggnadsing. Carl\nZetterberg (ordf.), civiling. Gunnar Zetterberg,\narkitekt Mander Zetterberg.\n\nVerkst. dir.: Carl Zetterberg.\nPlatschef i Göteborg: Gunnar\nZetterberg.\n\nZetterlund &amp; Thelanders Boktryckeri\nAB., Stockholm.\n\nUtför bok-, tidskrifts-, biljett- och\naccidenstryck.\n\nKontor: Skeppsbron 40. Telegr.-adr.:\nZetate, Stockholm. Telefon: 231180.\nPostgiro: 3959.\n\nAkt.-kap.: 90,000 kr. Antal\nindustriarb.: 45. Tillv.-värde pr år: 850,000 kr.\n— Firman etabl. 1903, bolag 1907.\nVerkst. dir.: Otto Virgin.\nTrycheriförest.: J. Kragsterman.\n\n*Zig-Zag Fabriken, Malmköping.\nSe Nya Fabriken Zig-Zag, Malmköping.\n\n*AB. Zinkgruvor, Falun.\n\nGruvor i Svärdsjöfältet, Nya\nKalv-bäcksgruvan, Lövåsfältet, Ryllshyttefältet\noch Saxbergsfältet (samtl. i Kopparb. l.);\nanrikningsverk i Kalvbäcken, Ryllshyttan,\nRävvåla och Lövås (samtl. i Kopparb.\n1.). Bryter och anrikar zink-, bly- och\nkopparmalm samt järnmalm och svavelkis.\n\nKontor: Falun. Telegr.-adr.:\nZinkgruvor, Falun. Telefon: 3801.\n\nAkt.-kap.: 4,000,000 kr. Antal\nindustriarb.: 300. — Bolaget grundat 1923.\n\nStyrelse: dir. Martin Waldenström\n(ordf.), dir. Oscar Falkman, dir. Sven\nSchwartz, bankdir. Gustaf Söderlund,»\nbergsing. Sven Thorné, bankombudsm.\nAxel Åström.\n\nVerkst. dir.: Sven Thorné.\nPlatschefer: övering. John Nyholm\n(Dala-Finnhyttan), bergsing. Karl G.\nWallin (Rävvåla) o. bergsing. Erik Knubb\n(St. Skedvi).\n\nKamrerare: Helge Edfors o. Hj.\nSund-ling.\n\nInhöpschef: R. Stenlund.\n\n*Zober, Konfektions AB., Tranås.\nSe Konfektions AB. Zober, Tranås.\n\n*Zonen, Oljeraffinaderi AB., Malmö.\n\nSe Oljeraffinaderi AB. Zonen, Malmö.\n\nZuckerman &amp; Jonasson Metallfabrik\n\nAB., Stockholm.\n\nTillverkar fotografiramar i metall vid\nfabrik i Aspudden, Stockholm. Kontor:\nHägerstensv. 186, Aspudden. Telefon:\n450540. Postgiro: 154577.\n\nAkt.-kap.: 11,900 kr. Antal\nindustriarb.: 30. Tillv.-värde pr år: 400,000 kr.\n— Bolaget grundat 1936.\n\nVerkst. dir.: fabr. Gösta Zuckerman.",
    "structured": {
        "1": {
            "name": "Z andelin—Zuckerman",
            "location": "Malmö",
            "business": "Tryckeri, bokbinderi och kartongfabrik",
            "contact": {
                "office": "Stora Ny g. 35, Malmö",
                "phone": [
                    "20657",
                    "24200"
                ],
                "postgiro": "38218",
                "head_office": "Stora Ny g. 35, Malmö",
                "sales_offices": [
                    {
                        "location": "Stockholm",
                        "phone": "673656"
                    }
                ]
            },
            "financials": {
                "capital": "300,000 kr",
                "employees": {
                    "industriarb": 40
                },
                "annual_turnover": "1,000,000 kr",
                "annual_production_value": "1,000,000 kr"
            },
            "foundation_year": 1865,
            "corporation_year": 1931,
            "board": [
                {
                    "name": "Harry Sandnes",
                    "role": "disp."
                },
                {
                    "name": "Axel Svanberg",
                    "role": "dir."
                },
                {
                    "name": "Karl-Gustav Svanberg",
                    "role": "apot."
                }
            ],
            "director": "Axel Svanberg",
            "managing_director": "Axel Svanberg",
            "sales_manager": "John Byström"
        },
        "2": {
            "name": "Zandelins Tryckeri AB.",
            "location": "Malmö",
            "business": "Tryckeri, bokbinderi och kartongfabrik",
            "contact": {
                "office": "Hjulhamnsg. 3, Malmö",
                "phone": [
                    "27852",
                    "27868"
                ],
                "postgiro": "24522"
            },
            "financials": {
                "capital": "25,000 kr",
                "employees": {
                    "industriarb": 40
                },
                "annual_turnover": "500,000 kr",
                "annual_production_value": "500,000 kr"
            },
            "foundation_year": 1926,
            "board": [
                {
                    "name": "Torsten Flintberg",
                    "role": "Tryckerichef"
                }
            ]
        },
        "3": {
            "name": "Zenks Bryggeri AB.",
            "location": "Örebro",
            "business": "Tillverkar maltdrycker, läskedrycker och mineralvatten",
            "contact": {
                "phone": "Zenksbryggeri",
                "postgiro": "11268"
            },
            "financials": {
                "capital": "300,000 kr",
                "employees": {
                    "industriarb": 25
                }
            },
            "foundation_year": 1860,
            "corporation_year": 1919,
            "board": [
                {
                    "name": "Tobias Åkesson",
                    "role": "bryggeriing."
                },
                {
                    "name": "Torsten Malm",
                    "role": "adv."
                },
                {
                    "name": "Sven Rassback",
                    "role": "bankdir."
                }
            ],
            "director": "Tobias Åkesson"
        },
        "4": {
            "name": "Zetterberg AB.",
            "location": "Stockholm",
            "business": "Byggnadsentreprenörfirma för bostads-och affärshus, industribyggnader m. m.",
            "contact": {
                "office": "Stockholm, Artillerig. 28",
                "phone": [
                    "620833",
                    "610402"
                ],
                "postgiro": "53188",
                "sales_offices": [
                    {
                        "location": "Göteborg",
                        "phone": "ö. Hamng. 30—34"
                    }
                ]
            },
            "financials": {
                "capital": "500,000 kr"
            },
            "foundation_year": 1917,
            "board": [
                {
                    "name": "Carl Zetterberg",
                    "role": "byggnadsing."
                },
                {
                    "name": "Gunnar Zetterberg",
                    "role": "civiling."
                },
                {
                    "name": "Mander Zetterberg",
                    "role": "arkitekt"
                }
            ],
            "director": "Carl Zetterberg"
        },
        "5": {
            "name": "Zetterlund & Thelanders Boktryckeri AB.",
            "location": "Stockholm",
            "business": "Utför bok-, tidskrifts-, biljett- och accidenstryck",
            "contact": {
                "office": "Skeppsbron 40",
                "phone": "231180",
                "postgiro": "3959"
            },
            "financials": {
                "capital": "90,000 kr",
                "employees": {
                    "industriarb": 45
                },
                "annual_turnover": "850,000 kr"
            },
            "foundation_year": 1903,
            "corporation_year": 1907,
            "director": "Otto Virgin"
        },
        "6": {
            "name": "AB. Zinkgruvor",
            "location": "Falun",
            "business": "Gruvor i Svärdsjöfältet, Nya Kalv-bäcksgruvan, Lövåsfältet, Ryllshyttefältet och Saxbergsfältet (samtl. i Kopparb. l.); anrikningsverk i Kalvbäcken, Ryllshyttan, Rävvåla och Lövås (samtl. i Kopparb. 1.). Bryter och anrikar zink-, bly- och kopparmalm samt järnmalm och svavelkis",
            "contact": {
                "office": "Falun",
                "phone": "3801"
            },
            "financials": {
                "capital": "4,000,000 kr",
                "employees": {
                    "industriarb": 300
                }
            },
            "foundation_year": 1923,
            "board": [
                {
                    "name": "Martin Waldenström",
                    "role": "dir."
                },
                {
                    "name": "Oscar Falkman",
                    "role": "dir."
                },
                {
                    "name": "Sven Schwartz",
                    "role": "dir."
                },
                {
                    "name": "Gustaf Söderlund",
                    "role": "bankdir."
                },
                {
                    "name": "Sven Thorné",
                    "role": "bergsing."
                },
                {
                    "name": "Axel Åström",
                    "role": "bankombudsm."
                }
            ],
            "director": "Sven Thorné"
        },
        "7": {
            "name": "Zuckerman & Jonasson Metallfabrik AB.",
            "location": "Stockholm",
            "business": "Tillverkar fotografiramar i metall vid fabrik i Aspudden, Stockholm"
        }
    }
}