{
    "original": "Konga—Konst gödnings fabrik\n\nAntal industriarb.: 40 samt 60\nhemarbetare. Tillv.-värde pr år: 350,000 kr. —\nFirman etabl. 1939.\n\nÄgare o. chef: ing. Gustaf Eriksson.\n\n\"Konga AB., Konga.\n\nTrähusfabrik i Konga (Kronob. l.).\nTillverkar monteringsfärdiga trähus m.m.\nBolaget idkar jämväl jordbruk och\nskogsbruk.\n\nTelegr.-adr.: Konga, Ronneby. Telefon:\nTingsryd 13. Postgiro: 139807.\n\nAkt.-kap.: 100,000 kr. Antal\nindustriarb.: 140. — Bolaget, grundat 1888,\ntillhör Klippan-koncernen.\n\nStyrelse: bankir Tage Cervin (ordf.),\nbankdir. Allan Alexanderson, dir. P. Eg.\nGummeson, f. d. bankdir. H. K.\nLaurit-zen, dir. Carl Joh. Malmros.\n\nVerkst. dir.: Carl Joh. Malmros.\n\nDriftsing.: Lennart Peterson.\n\n\"Kongelfs Glasbruks AB., Kungälv.\n\nSe AB. Surte Glasbruk, Surte.\n\n\"Konserverings AB. Atlantic,\n\nMörrum.\n\nKonservfabrik i Mörrum (Blekinge l.).\nTillverkar marmelad, konserver av frukt,\ngrönsaker, kött och fisk; sillinläggningar\nsåsom kryddsill och gaffelbitar samt rökta\nsillfiléer. Varumärke: »Atlantic».\n\nTelegr.-adr.: Atlanticbolag, Mörrum.\nTelefon: »Atlantic». Postgiro: 130875.\n\nAkt.-kap.: 110,000 kr. Antal\nindustriarb.: 80. Tillv.-värde pr år: 2,000,000 kr.\n— Firman etabl. 1926.\n\nStyrelse: kapten Torsten Lundell\n(ordf.), adv. R. Allmér, disp. Axel\nMejåre.\n\nVerkst. dir.: Axel Mejåre (Kalmar).\n\nKamrer: John E. Johansson.\n\nKonservfabriken Bore, Lyse.\n\nTillverkar ansjovis, kaviar, sill-, fisk\noch fruktkonserver vid fabrik i Sjöbol,\nLyse (Göteb. o. Bohus l.). Varumärken:\n3»Bore» o. Hof».\n\nTelefon: Lyse 175. Postgiro: 81009. —\nAntal industri-arb.: 35. Tillv.-värde pr\når: 450,000 kr. — Firman etabl. 1932.\n\nÄgare o. chef: fabr. Carl Olsson.\n\nDisp.: Olof Olsson.\n\n\"AB. Konservfabriken Findus, Bjuv.\n\nTillverkar konserverade livsmedel, spec.\nav frukt och grönsaker vid fabrik i Bjuv\n(Malmöh. l.). Bolaget driver även\ngrönsaks- och fruktodlingar.\n\n31*\n\nTelegr.-adr.: Findus, Bjuv. Telefon:\n46, 162, 163, 275 o. 276. Postgiro: 6190.\n\nAkt.-kap.: 60,200 kr. Antal industriarb.:\n392. — Firman, etabl. 1905, är sedan 1942\nkommissionärsbolag för AB.\nChoklad-fabriken Marabou, Sundbyberg.\n\nStyrelse: disp. H. Throne-Holst (ordf.),\ndir. Lars Anderfelt, kamrer Erik\nLindgren.\n\nVerkst. dir.: Lars Anderfelt\n(Stockholm).\n\nPlatschef: civiling. Tore Lauritzson.\n\nAB. Konservfabriken Sirius,\n\nGöteborg.\n\nTillverkar kött-, fisk- och\ngrönsakskonserver vid fabriker i Göteborg och\nLinköping. Specialiteter: ärtkonserver,\ntomatbönor, fiskbullar och leverpastej.\nVarumärke: »Sirius».\n\nKontor: Göteborg, Byfogdeg. 11.\nTe-legr.-adr.: Siricon, Göteborg. Telefon:\n192130. Postgiro: 40969.\n\nAkt.-kap.: 400,000 kr. Antal\nindustriarb.: 80, varav i Göteborg 50. Tillv.-värde\npr år: 3,000,000 kr. — Bolaget grundat\n1929.\n\nVerkst. dir.: civiling. Anders Wiberg.\n\nFörsäljn.-chef: Albin Björklund.\n\nKamrer: Gunnar Westin.\n\n\"Konservfabrikerna, AB. Sveriges\nFörenade, Göteborg.\n\nSe AB. Sveriges Förenade\nKonservfabriker, Göteborg.\n\nKonservsönerna, P. &amp; L. Carlsson,\n\nKlädesholmen.\n\nTillverkar grönsakskonserver,\nsillkonserver, fiskbullar samt konserverade\nskaldjur vid fabrik å Klädesholmen (Göteb.\no. Bohus l.).\n\nTelegr.-adr.: Konservsöner,\nKlädesholmen. Telefon: 34 o. 54. Postgiro:\n80820. Representanter: Alex H:hielm\nLundberg, Stockholm, Brunnsg. 18,\ntelefon: 110308; Eric Peterson, Malmö,\nStall-mästareg. 13, telefon: 75064.\n\nAntal industriarb.: 35. Tillv.-värde pr\når: 575,000 kr. — Firman etabl. 1920.\n\nÄgare o. chefer: köpm. Pontus\nCarlsson, köpm. Linus Carlsson o. köpm. Kurt\nCarlsson.\n\n\"Konstgödningsfabriks AB. i\nLandskrona, Landskrona.\n\nSe AB. Förenade Superfosfatfabriker,\nHälsingborg.",
    "structured": {
        "1": {
            "name": "Konga AB",
            "location": "Konga, Ronneby",
            "business": "Trähusfabrik, jordbruk, skogsbruk",
            "contact": {
                "office": "Konga, Kronob. l.",
                "phone": [
                    "Tingsryd 13"
                ],
                "postgiro": "139807"
            },
            "financials": {
                "capital": "100,000 kr",
                "employees": {
                    "industriarb.": 140
                },
                "annual_turnover": "2,000,000 kr"
            },
            "foundation_year": 1888,
            "board": [
                {
                    "name": "Tage Cervin",
                    "role": "bankir (ordf.)"
                },
                {
                    "name": "Allan Alexanderson",
                    "role": "bankdir."
                },
                {
                    "name": "P. Eg. Gummeson",
                    "role": "disp."
                },
                {
                    "name": "H. K. Laurit-zen",
                    "role": "f.d. bankdir."
                },
                {
                    "name": "Carl Joh. Malmros",
                    "role": "dir."
                }
            ],
            "director": "Carl Joh. Malmros",
            "managing_director": "Carl Joh. Malmros"
        },
        "2": {
            "name": "Kongelfs Glasbruks AB",
            "location": "Kungälv",
            "predecessor": "AB. Surte Glasbruk, Surte"
        },
        "3": {
            "name": "Konserverings AB. Atlantic",
            "location": "Mörrum",
            "business": "Konservfabrik",
            "contact": {
                "telegraph": "Atlanticbolag, Mörrum",
                "phone": [
                    "Atlantic"
                ],
                "postgiro": "130875"
            },
            "financials": {
                "capital": "110,000 kr",
                "employees": {
                    "industriarb.": 80
                },
                "annual_turnover": "2,000,000 kr"
            },
            "foundation_year": 1926,
            "board": [
                {
                    "name": "Torsten Lundell",
                    "role": "kapten (ordf.)"
                },
                {
                    "name": "R. Allmér",
                    "role": "adv."
                },
                {
                    "name": "Axel Mejåre",
                    "role": "disp."
                }
            ],
            "director": "Axel Mejåre"
        },
        "4": {
            "name": "Konservfabriken Bore",
            "location": "Lyse",
            "business": "Konservfabrik",
            "contact": {
                "phone": [
                    "Lyse 175"
                ],
                "postgiro": "81009"
            },
            "financials": {
                "employees": {
                    "industri-arb.": 35
                },
                "annual_turnover": "450,000 kr"
            },
            "foundation_year": 1932,
            "director": "Carl Olsson"
        },
        "5": {
            "name": "AB. Konservfabriken Findus",
            "location": "Bjuv",
            "business": "Konservfabrik, grönsaks- & fruktodlingar",
            "contact": {
                "telegraph": "Findus, Bjuv",
                "phone": [
                    "46",
                    "162",
                    "163",
                    "275",
                    "276"
                ],
                "postgiro": "6190"
            },
            "financials": {
                "capital": "60,200 kr",
                "employees": {
                    "industriarb.": 392
                }
            },
            "foundation_year": 1905,
            "board": [
                {
                    "name": "H. Throne-Holst",
                    "role": "disp. (ordf.)"
                },
                {
                    "name": "Lars Anderfelt",
                    "role": "dir."
                },
                {
                    "name": "Erik Lindgren",
                    "role": "kamrer"
                }
            ],
            "director": "Lars Anderfelt"
        },
        "6": {
            "name": "AB. Konservfabriken Sirius",
            "location": "Göteborg, Linköping",
            "business": "Kött-, fisk- & grönsakskonserver",
            "contact": {
                "office": "Göteborg, Byfogdeg. 11",
                "phone": [
                    "192130"
                ],
                "postgiro": "40969"
            },
            "financials": {
                "capital": "400,000 kr",
                "employees": {
                    "industriarb.": 80,
                    "Göteborg": 50
                },
                "annual_turnover": "3,000,000 kr"
            },
            "foundation_year": 1929,
            "board": [
                {
                    "name": "Anders Wiberg",
                    "role": "civiling. (verkst. dir.)"
                }
            ],
            "managing_director": "Anders Wiberg"
        },
        "7": {
            "name": "Konservsönerna, P. & L. Carlsson",
            "location": "Klädesholmen",
            "business": "Grönsakskonserver, sillkonserver, fiskbullar, skaldjurkonservering",
            "contact": {
                "telegraph": "Konservsöner, Klädesholmen",
                "phone": [
                    "34",
                    "54"
                ],
                "postgiro": "80820"
            },
            "financials": {
                "employees": {
                    "industriarb.": 35
                },
                "annual_turnover": "575,000 kr"
            },
            "foundation_year": 1920,
            "owners": [
                "Pontus Carlsson",
                "Linus Carlsson",
                "Kurt Carlsson"
            ]
        },
        "8": {
            "name": "Konstgödningsfabriks AB. i Landskrona",
            "location": "Landskrona",
            "predecessor": "AB. Förenade Superfosfatfabriker, Hälsingborg"
        }
    }
}