{
    "original": "Gamlestaden—Gasaccumulator\n\nTelefon: 9. Postgiro: 289209. —\nAkt.-kap.: 100,000 kr. Antal industriarb.: 10.\n— Bolaget grundat 1945.\n\nVerkst. dir.: disp. Arne Torstensson.\n\n*Camlestadens Fabrikers AB.,\n\nGöteborg.\n\nBomullsspinneri, väveri, färgeri,\nblekeri och appreturverk, konfektionsfabrik\n(AB. Carma) samt nätfabrik. Tillverkar\nbomullsgarn, bomullsvävnader, herr- och\ndamkonfektion samt fisknät.\n\nKontor: Gamlestaden. Telegr.-adr.:\nCarlander, Göteborg. Telefon:\n»Gamlestadens Fabriker». Postgiro: 8820.\nAvd.-kontor: Gamlestadens Fabrikers\nStockholmskontor AB., Stockholm, Drottningg.\n26. Telegr.-adr.: Herkulesväv, Stockholm.\nTelefon: 232060.\n\nAkt.-kap.: 12,500,000 kr. Antal\nindustriarb.: 1,100. Tillv.-värde pr år:\n10,000,000 kr. — Bolaget grundat 1891.\n\nStyrelse: dir. Knut J:son Mark (ordf.),\ning. Gösta Blum, bankdir. Nils Bökman,\nförsäljn.-chef Bertil Carlander, civiling.\nHakon Leffler.\n\nVerkst. dir.: Hakon Leffler.\n\nKamrer: O^ear Wennp.\n\nFörsäljn.-chef: Karl Nord vall.\n\nKontorschef i Stockholm: G. Uppman.\n\n*Camlestadens Pappersbruks AB.,\n\nGöteborg.\n\nPappersbruk i Gamlestaden, Göteborg.\nTillverkar M. G.-sulfitpapper och\nfruktomslagspapper.\n\nKontor: Tingstad. Telegr.-adr.:\nGamlestaden, Göteborg. Telefon: 222110.\n\nAkt.-kap.: 309,000 kr. Årstillv.: 3,000\nton papper.\n\nFirman, etabl. 1916, arbetar under\ngemensam förvaltning med AB. Göteborg\nDals Pappersbruk och Göteborgs\nPappersbruks AB.\n\nStyrelse: dir. Nils Troedsson (ordf.),\nadv. Gunnar Lewerth, dir. Nils Thenberg,\nköpm. Nathan Troedsson.\n\nFörsäljn.-dir.: Yngve Olin.\n\nÖvering.: Bo Enderlein.\n\n*Cardinfabriken, Svenska, Göteborg.\n\nSe AB. Svenska Gardinfabriken,\nGöteborg.\n\n*Gardinfabriken Tången, Stockholm.\n\nSe Tångens Gardinfabrik AB.,\nStockholm.\n\nCarpen, Konfektions AB., Åseda.\n\nSe Konfektions AB. Garpen, Åseda.\n\n17*\n\n*AB. Carphytte Bruk, Garphyttan.\n\nManufakturverk med tråddrageri,\nstål-line- och fjäderfabrik samt mek.\nverkstad, såg och elektr. kraftstation vid\nGarphyttan (Örebro l.).\n\nTillverkar järn- och ståltråd,\nfjäder-stål, pianotråd, silverstål, ståltråd för\ntextiländamål, svetsningstråd och\nelektroder, rostbeständig ståltråd, stållinor,\nprecisionsfjädrar, vävskedar och andra\ntextilutensilier samt dragskivor av\nhårdmetall och av diamanter.\n\nTelegr.-adr.. Garphyttan, Örebro.\nTelefon: Örebro 98000. Postgiro: 8266.\nFör-säljn.-kontor för textilutensilier: Borås\nMek. Wäf skedsfabrik, Borås, telefon:\n11028.\n\nAkt.-kap.: 2,500,000 kr. Antal\nindustriarb.: 550. Tillv.-värde pr år: 9,000,000 kr.\n\n—\tBrukets nuvarande tillverkning av\ntråd och stållinor började 1906.\n\nStyrelse: bergsing. Th. Ekstrand, frih.\nMagnus v. Essen.\n\nVerkst. dir. o. disp.: Th. Ekstrand.\n\nKamrer: IL Hålen.\n\nFörsäljn.-chef: Sture Samuelsson.\n\növering.: Niord Gustafson.\n\nDriftsingenjörer: bergsing. Erik v.\nWachenfeldt o. bergsing. Gösta Ekstrand.\n\nKassör: J. Dickson.\n\n\"Garvämnes AB. Weibull,\n\nLandskrona.\n\nGarvämnesfabrik vid Weibullsholm,\nLandskrona. Tillverkar vegetabiliska\ngarv-ämnesextrakter, såväl flytande som fasta\no. pulvriserade. Varumärken: »Triumph»,\n»Monopol», »Globus», »Scania», »Svecia»,\n»Landskrona», »Novozym» o. »Weibull\nCutch».\n\nTelegr.-adr.: Weibull, Landskrona.\nTelefon: 744 o. 745. Postgiro: 71899.\n\nAkt.-kap.: 1,200 000 kr. Antal\nindustriarb.: 175. Tillv.-värde pr år: 7,500,000 kr.\n\n—\tFirman etabl. 1870, bolag: 1921.\n\nStyrelse: dir. John Weibull (ordf.),\n\nkontorschef David R. Bergman, konsul\nErik Weibull, dir. Torbjörn Weibull,\nkonsul Widar Weibull, agronom William\nWeibull.\n\nVerkst. dir.: John Weibull.\n\nV. verkst. direktörer: E. Weibull o. T.\nWeibull.\n\nKontorschef: D. R. Bergman.\n\nFörsäljn.-chef: Carl Lavestam.\n\nFabrikschef: dr A. Wipfler.\n\n*Casaccumulator, Stockholm-Lidingö.\n\nSe Svenska AB. Gasaccumulator,\nStock-holm-Lidingö.",
    "structured": {
        "1": {
            "name": "Camlestadens Fabrikers AB.",
            "location": "Göteborg",
            "business": "Bomullsspinneri, väveri, färgeri, blekeri och appreturverk, konfektionsfabrik (AB. Carma) samt nätfabrik. Tillverkar bomullsgarn, bomullsvävnader, herr- och damkonfektion samt fisknät.",
            "contact": {
                "office": "Gamlestaden",
                "phone": [
                    "Telefon: \"Gamlestadens Fabriker\""
                ],
                "postgiro": "8820",
                "sales_offices": [
                    {
                        "location": "Gamlestadens Fabrikers Stockholmskontor AB., Stockholm",
                        "phone": "232060"
                    }
                ],
                "telegraph": "Carlander, Göteborg"
            },
            "financials": {
                "capital": "12,500,000 kr",
                "employees": {
                    "industriarb": 1100
                },
                "annual_production_value": "10,000,000 kr"
            },
            "foundation_year": 1891,
            "board": [
                {
                    "name": "dir. Knut J:son Mark",
                    "role": "ordf."
                },
                {
                    "name": "ing. Gösta Blum",
                    "role": "None"
                },
                {
                    "name": "bankdir. Nils Bökman",
                    "role": "None"
                },
                {
                    "name": "försäljn.-chef Bertil Carlander",
                    "role": "None"
                },
                {
                    "name": "civiling. Hakon Leffler",
                    "role": "None"
                }
            ],
            "manager": "None"
        },
        "2": {
            "name": "Camlestadens Pappersbruks AB.",
            "location": "Göteborg",
            "business": "Pappersbruk i Gamlestaden, Göteborg. Tillverkar M. G.-sulfitpapper och fruktomslagspapper.",
            "contact": {
                "office": "Tingstad",
                "phone": [
                    "Telefon: 222110"
                ],
                "telegraph": "Gamlestaden, Göteborg"
            },
            "financials": {
                "capital": "309,000 kr",
                "annual_production_value": "3,000 ton papper"
            },
            "foundation_year": 1916,
            "board": [
                {
                    "name": "dir. Nils Troedsson",
                    "role": "ordf."
                },
                {
                    "name": "adv. Gunnar Lewerth",
                    "role": "None"
                },
                {
                    "name": "dir. Nils Thenberg",
                    "role": "None"
                },
                {
                    "name": "köpm. Nathan Troedsson",
                    "role": "None"
                }
            ],
            "manager": "None"
        },
        "3": {
            "name": "AB. Carphytte Bruk",
            "location": "Garphyttan",
            "business": "Manufakturverk med tråddrageri, stål-line- och fjäderfabrik samt mek. verkstad, såg och elektr. kraftstation vid Garphyttan (Örebro l.). Tillverkar järn- och ståltråd, fjäder-stål, pianotråd, silverstål, ståltråd för textiländamål, svetsningstråd och elektroder, rostbeständig ståltråd, stållinor, precisionsfjädrar, vävskedar och andra textilutensilier samt dragskivor av hårdmetall och av diamanter.",
            "contact": {
                "office": "Garphyttan, Örebro",
                "phone": [
                    "Telefon: Örebro 98000"
                ],
                "postgiro": "8266",
                "sales_offices": [
                    {
                        "location": "Borås Mek. Wäf skedsfabrik, Borås",
                        "phone": "11028"
                    }
                ],
                "telegraph": "Garphyttan, Örebro"
            },
            "financials": {
                "capital": "2,500,000 kr",
                "employees": {
                    "industriarb": 550
                },
                "annual_production_value": "9,000,000 kr"
            },
            "foundation_year": "None",
            "board": [
                {
                    "name": "bergsing. Th. Ekstrand",
                    "role": "None"
                },
                {
                    "name": "frih. Magnus v. Essen",
                    "role": "None"
                }
            ],
            "manager": "None"
        },
        "4": {
            "name": "Garvämnes AB. Weibull",
            "location": "Landskrona",
            "business": "Garvämnesfabrik vid Weibullsholm, Landskrona. Tillverkar vegetabiliska garv-ämnesextrakter, såväl flytande som fasta o. pulvriserade. Varumärken: »Triumph», »Monopol», »Globus», »Scania», »Svecia», »Landskrona», »Novozym» o. »Weibull Cutch».",
            "contact": {
                "office": "Weibullsholm, Landskrona",
                "phone": [
                    "Telefon: 744 o. 745"
                ],
                "postgiro": "71899",
                "telegraph": "Weibull, Landskrona"
            },
            "financials": {
                "capital": "1,200 000 kr",
                "employees": {
                    "industriarb": 175
                },
                "annual_production_value": "7,500,000 kr"
            },
            "foundation_year": 1870,
            "board": [
                {
                    "name": "dir. John Weibull",
                    "role": "ordf."
                },
                {
                    "name": "kontorschef David R. Bergman",
                    "role": "None"
                },
                {
                    "name": "konsul Erik Weibull",
                    "role": "None"
                },
                {
                    "name": "dir. Torbjörn Weibull",
                    "role": "None"
                },
                {
                    "name": "konsul Widar Weibull",
                    "role": "None"
                },
                {
                    "name": "agronom William Weibull",
                    "role": "None"
                }
            ],
            "manager": "None"
        }
    }
}