{
    "original": "Kohlswa—Kolbäck\n\nNils Holmström, dir. Frans Kockum, dir.\nCr. Lundeqvist, skeppsred. Jarl W.\nMalm-tos, dir. Harry Tranchell.\n\nVerkst. dir.: G. Lundeqvist.\n\nVice verkst. dir.: Nils Holmström.\n\nTeknisk dir..- Kurt Söderlund.\n\nAvd.-chefer o. ställföreträdare:\nkontoret : kamrer Gottfried Kockum;\ninköps-:avd.: B. Hedenblad; försäljn.-avd.:\nSigfrid Lindahl; planeringsavd.: övering. C.\nE. v. Seth o. ing. Harry Jönsson; varvet:\nvarvsing. Per Stenberg o. ing. O. Egnell;\nmaskinverkstaden: ing. G. Allenmark\no. ing. Y. Fransson; gjuteriet: ing.\nB. Ekeblom; vagnavd. o. smedja: ing.\ni!Gunnar Kockum; fartygsritkontoret: ing.\nOlaes Bröden; marinavd.: ing. J.\nLjunggren o. ing. H. Hillander;\nmaskinritkontoret: ing. Erik Hjort o. ing. Erik\nHolmdahl; elektr. avd.: ing. Nils Frenning;\nångpanneavd.: ing. K. Sandwall; bro- o.\nkranritkontoret: ing. I. Almqvist;\ntyfon-»avd.: ing. Gustaf Bröden.\n\n(Jfr annons före Branschregistret.)\n\nKohlswa Fältspatgruva,\n\nStockholm.\n\nBryter fältspat och kvarts vid\nfyndig-fieter i Kolsva (Västmanl. l.).\n\nEnsamförsälj.: AB. Feltspatkompaniet,\nStockholm, Hamng. 10. Telegr.-adr.:\nFeltspat, Stockholm. Telefon: 233015.\n\nAntal industriarb.: 30. Prod.-värde pr\når: 300,000 kr. — Försäljningsbolaget\ngrundat 1928.\n\nChef: ing. Erik K. Huldt.\n\nDriftschef i Kolsva: A. Ludvigson.\n\n\"Kohlswa Jernverks AB., Kolsva.\n\nJärnverk med elektrostål- och\nmartin-cignar, valsverk, stålgjuterier, press- och\nsmidesverk, härdverk och mek. verkstad i\nKolsva samt kättingfabrik i Köping (båda\ni Västmanl. l.).\n\nTillverkar göten, billets, valsat och\nsmitt järn och stål, legerat och olegerat\nstålgjutgods, rost-, värme- och\nsyrabestän-cliga stållegeringar samt höglegerat\nma-ganstål i valsad, smidd och gjuten form,\npressgods. smiden, smidesstäd, projektiler,\nEwarts-stålkätting, rullkätting m. m.\nBolaget idkar jämväl jordbruk,\nskogshantering samt sågverks- och kvarnrörelse.\n\nHuvudkontor: Kolsva. Telegr.-adr.:\nJernverket, Kolsva. Telefon:\n»Brukskontoret», Kolsva. Postgiro: 6477.\n\nAkt.-kap.: 2,250,000 kr. Antal\nindustriarb.: 850.\n\nBruket anlagt på 1500-talet, nuv. bolag\ngrundat 1892.\n\nStyrelse: dir. Claes Wahlund (ordf.),\n\nf. statssekr. L. Rabenius (v. ordf.), dir.\nDavid Dalin, bankdir. Rich. Julin, disp.\nGunnar Nordström, byråchef Karl-Arvid\nNorlin, bankdir. Marc. Wallenberg.\nVerkst. dir. o. disp.: G. Nordström.\nV. verkst. dir.t försäljn.- o. inköpschef:\nDavy Nilson.\n\nÖvering.: Sten Dillner.\nDriftsingenjörer: Stig Hj:son Ljung-\n\n5ren, Olof Rahm, Ch. Blomquist o. N.\nstnäs. Metallograf: H. Lagerström.\nKemist: Axel Persson. Byggnadsing.: G. B.\nWester.\n\nKamrer: Torsten Thorgren.\n(Jfr annons nr 34.)\n\nKokkärlsfabriken E. Bergman &amp; Co.,\n\nEskilstuna.\n\nTillverkar kokkärl av aluminium och\nkoppar.\n\nTelefon: 31036. Postgiro: 22777. —\nArb.-antal: 10. Tillv.-värde pr år: 100,000\nkr. — Firman etabl. 1919.\n\nÄgare o. chef: fabr. Emil Bergman.\n\n\"Kolafabriken Aroma, Stockholm.\n\nTillverkar kola, karameller, lakrits och\ntabletter.\n\nKontor: Gävleg. 12 A. Telegr.-adr.:\nAromakola, Stockholm. Telefon: 231765.\nPostgiro: 2338. — Antal industriarb.: 37.\n— Firman etabl. 1922.\n\nÄgare o. chef: fabr. Gottfrid Eklund.\n\nKolborstfabriken Bunge AB.,\n\nStockholm.\n\nTillverkar kol-, grafit-,\nelektrografit-och metallgrafitborstar för elektr.\nmotorer och generatorer samt kontaktstycken\nför kontaktorer och reläer.\n\nKontor: Katrineberg 24, Liljeholmen;\npostadr.: Stockholm 9. Telegr.-adr.:\nBungekol, Stockholm. Telefon: 451141 o.\n451541. Postgiro: 58705.\n\nAkt.-kap.: 100,000 kr. Antal\nindustriarb.: 40. Tillv.-värde pr år: 600,000 kr.\nFirman etabl. 1915, bolag 1937.\n\nVerkst. dir.: ing. Hadar Sundström.\n\n\"Kolbäcks Cementgjuter i, Kolbäck.\n\nSe Nya AB. Kolbäcks Cementgjuteri,\nKolbäck.\n\n\"Kolbäcks Elektriska Verkstad,\n\nKolbäck.\n\nElektro-mek. verkstad i Kolbäck\n(Västmanl. l.). Tillverkar elektr. materiel så-\n\n295*",
    "structured": {
        "1": {
            "name": "Kohlswa Fältspatgruva",
            "location": "Stockholm",
            "business": "Bryter fältspat och kvarts vid fyndig-fieter i Kolsva (Västmanl. l.).",
            "products": "Ensamförsälj.: AB. Feltspatkompaniet, Stockholm, Hamng. 10. Telefon: 233015.",
            "contact": {
                "office": "Not provided",
                "phone": [
                    "233015"
                ],
                "postgiro": "Not provided",
                "head_office": "Not provided",
                "sales_offices": [],
                "telegraph": "Not provided",
                "factory_office": "Not provided",
                "factory_phone": "Not provided"
            },
            "financials": {
                "capital": "Not provided",
                "employees": {
                    "industriarb": 30
                },
                "annual_turnover": "Not provided",
                "annual_production_value": "300,000 kr"
            },
            "foundation_year": 1928
        },
        "2": {
            "name": "Kohlswa Jernverks AB., Kolsva",
            "location": "Kolsva",
            "business": "Järnverk med elektrostål- och martin-cignar, valsverk, stålgjuterier, press- och smidesverk, härdverk och mek. verkstad i Kolsva samt kättingfabrik i Köping (båda i Västmanl. l.). Tillverkar göten, billets, valsat och smitt järn och stål, legerat och olegerat stålgjutgods, rost-, värme- och syrabestän-cliga stållegeringar samt höglegerat ma-ganstål i valsad, smidd och gjuten form, pressgods. smiden, smidesstäd, projektiler, Ewarts-stålkätting, rullkätting m. m. Bolaget idkar jämväl jordbruk, skogshantering samt sågverks- och kvarnrörelse.",
            "products": "Not provided",
            "contact": {
                "office": "Not provided",
                "phone": [
                    "Not provided"
                ],
                "postgiro": "6477",
                "head_office": "Kolsva",
                "sales_offices": [],
                "telegraph": "Jernverket, Kolsva",
                "factory_office": "Not provided",
                "factory_phone": "Not provided"
            },
            "financials": {
                "capital": "2,250,000 kr",
                "employees": {
                    "industriarb": 850
                },
                "annual_turnover": "Not provided",
                "annual_production_value": "Not provided"
            },
            "foundation_year": 1892
        },
        "3": {
            "name": "Kokkärlsfabriken E. Bergman & Co.",
            "location": "Eskilstuna",
            "business": "Tillverkar kokkärl av aluminium och koppar.",
            "products": "Not provided",
            "contact": {
                "office": "Not provided",
                "phone": [
                    "31036"
                ],
                "postgiro": "22777",
                "head_office": "Not provided",
                "sales_offices": [],
                "telegraph": "Not provided",
                "factory_office": "Not provided",
                "factory_phone": "Not provided"
            },
            "financials": {
                "capital": "Not provided",
                "employees": {
                    "industriarb": 10
                },
                "annual_turnover": "Not provided",
                "annual_production_value": "100,000 kr"
            },
            "foundation_year": 1919
        },
        "4": {
            "name": "Kolafabriken Aroma",
            "location": "Stockholm",
            "business": "Tillverkar kola, karameller, lakrits och tabletter.",
            "products": "Not provided",
            "contact": {
                "office": "Gävleg. 12 A",
                "phone": [
                    "231765"
                ],
                "postgiro": "2338",
                "head_office": "Not provided",
                "sales_offices": [],
                "telegraph": "Aromakola, Stockholm",
                "factory_office": "Not provided",
                "factory_phone": "Not provided"
            },
            "financials": {
                "capital": "Not provided",
                "employees": {
                    "industriarb": 37
                },
                "annual_turnover": "Not provided",
                "annual_production_value": "Not provided"
            },
            "foundation_year": 1922
        },
        "5": {
            "name": "Kolborstfabriken Bunge AB.",
            "location": "Stockholm",
            "business": "Tillverkar kol-, grafit-, elektrografit-och metallgrafitborstar för elektr. motorer och generatorer samt kontaktstycken för kontaktorer och reläer.",
            "products": "Not provided",
            "contact": {
                "office": "Katrineberg 24, Liljeholmen",
                "phone": [
                    "451141",
                    "451541"
                ],
                "postgiro": "58705",
                "head_office": "Not provided",
                "sales_offices": [],
                "telegraph": "Bungekol, Stockholm",
                "factory_office": "Not provided",
                "factory_phone": "Not provided"
            },
            "financials": {
                "capital": "100,000 kr",
                "employees": {
                    "industriarb": 40
                },
                "annual_turnover": "Not provided",
                "annual_production_value": "600,000 kr"
            },
            "foundation_year": 1915
        }
    }
}