{
    "original": "Svenska\n\nAkt.-kap.: 3,000,000 kr. Antal\nindustriarb.: 930. Tillv.-värde pr år: 18,000,000\nkr. — Bolaget, grundat 1895, äges av\nKooperativa Förbundet.\n\n^ Styrelse: dir. Albin Johansson (ordf.),\nfil. lic. Mauritz Bonow, dir. Hj.\nDeger-stedt, dir. Hugo Edstam, dir. G. Osvald,\ndir. Ernst Persson.\n\nDisp.: Einar Holmberg.\n\nInköpschef: John Enquist.\n\nFörsäljn.-chef: Thure Magnusson.\n\nKontorschef: Primus Söderström.\n\nSvenska Gummistrumpfabriken AB.,\n\nStockholm.\n\nResårstickeri. Tillverkar\nåderbråcks-strumpor. Varumärke: »Servus».\n\nKontor: Mästersamuelsg. 34. Telefon:\n118434. Postgiro: 152480.\n\nAkt.-kap.: 15,000 kr. Antal\nindustriarb.: 10. Tillv.-värde pr år: 40,000 kr. —\nBolaget grundat 1937.\n\nVerkst. dir.: köpm. Eric Fransen.\n\nSvenska Havregryn Gylienhammar\n&amp; Co. Kommanditbolag,\n\nGöteborg.\n\nTillverkar havregryn, havremjöl och\nhavremust vid kvarn i Agnesberg (P. O.\nStokkebyes Kvarn AB., Göteborg).\n\nKontor o. ensamförsälj.: AB.\nHavremust, L. Bommens torg 2. Telegr.-adr.:\nHavremust, Göteborg. Telefon: 134105.\nPostgiro: 43404. — Lottkap.: 100,000 kr.\nTillv.-värde pr år: 2,000,000 kr. —\nBolaget grundat 1922.\n\nAnsvarig chef: dir. Gustaf Hammar.\n\nAB. Svenska Häftstiftsfabriken,\n\nÖrebro.\n\nJärnmanufakturverk i Pålsboda\n(Örebro l.). Tillverkar häftstift, såväl\nför-mässingade som förnicklade,\ndubbel-nitade, metallöverkapslade, lackerade och\ncelluloid-överkapslade stift samt\npap-persklämmor, häftklammer,\nprovpåskläm-mor och metallbygglådor. Varumärken:\n»S. H. F.», »Olfa» o. »Stjärnstift».\n\nKontor: Örebro. Telegr.-adr.: Stift,\nÖrebro. Telefon: 12818. Postgiro: 130505.\n\nAkt.-kap.: 50,000 kr. Antal\nindustriarb.: 35. Tillv.-värde pr år: 500,000 kr.\n— Fabriken anlagd 1934, bolaget grundat\n1936.\n\nVerkst. dir.: Fritz Johansson.\n\n*AB. Svenska Icopal- &amp;\nTakpix-fabriken, Malmö.\n\nTakpapp-, tjär- och\nasfaltemulsions-fabrik.\n\nTillverkar underhållsfri takpapp\n(»Icopal»), asfaltpapp (»Triumph», »Elg» o.\n»Sirius»), underlagspapp och\nförhydnings-papp, mattunderlägg (»Korcopal» o.\n»Linolag»), bitumenplattor (» Villadrit»),\ntak-tjära (»Svensk Patent Takpixtjära» o.\n»Icopix»), bitumen (»Klisterpix»),\nkallflytande asfalt (»Icoflux»),\nasfaltpasta-emulsion (»Kifas»), asbesttätningskitt\n(»Kitti»), takfärger (»Svensk Patent\nTakpixfärg») och aluminiumfärg\n(»Sil-verflux»), träimpregneringsmedel\n(»Vil-ladol 39»), pulverasfalt\n(»Kvartsit-Stah-las»), tjärbetongmassa (»Tjär-Stahlas»),\nvägasf altemulsion (»Koldmex» o.\n»Ico-bit»), tjäremulsion (»Icotar»), vägtjära\n(»Tarox») samt tjärasfalt (»Taroxas»).\nUtför taktäckningar, isoleringar,\nglas-lanterniner (system »Svita»),\nspecialfönster för snedtak (»Svita-fönstret»)\nsamt vägarbeten.\n\nKontor: Skeppsbron 11. Telegr.-adr.:\nIcopal, Malmö. Telefon:\n»Icopalfabri-ken». Postgiro: 25111.\nFörsäljningskontor: Stockholm: Drottningg. 30. Telefon:\n111571 o. 111572.\n\nAkt.-kap.: 200,000 kr. Tillv.-värde pr\når: 8,000,000 kr.\n\nFirman etabl. 1907, bolag 1915.\n\nStyrelse: bankdir. Ivar Åkerman\n(ordf.), adv. Wilhelm Kjellström (v.\nordf.), dir. Chr. Villadsen.\n\nDisp.: K. Varfeldt.\n\nKontorschef: J. Nivall.\n\nAB. Svenska Idealhus, Hultsfred.\n\nSnickerifabrik, sågverk och hyvleri i\nHultsfred (Kalmar l.). Tillverkar\nbyggnadssnickerier och monteringsfärdiga\nträhus.\n\nAkt.-kap.: 500,000 kr. — Bolaget\ngrundat 1944. Bolagets anläggningar samt\ntillverkningar av byggnadssnickerier och\nmonteringsfärdiga trähus äro\nutarrenderade till Hultsfreds Träförädlings AB.,\nHultsfred (se detta bolag).\n\nStyrelse: godsägare Hadar Hedborg\n(ordf.), dir. G. Edström, ryttm. B.\nHyl-tén-Cavallius, landstingsm. David\nJohansson, godsäg. Arvid Nilsson, friherre L.\nWrede.\n\nVerkst. dir.: G. Edström (Växjö).\n\nPlatschef: disp. T. Wahlquist.\n\nSvenska Industribyggen AB.,\n\nStockholm.\n\nByggnadsentreprenörfirma speciellt för\nindustribyggnader. Firmamärke: »SIAB».\n\nKontor: Sveavägen 29 (efter den 1/5\n1947 N. Stationsg. 75—77). Telegr.-adr.:\nIndustribvggen, Stockholm. Telefon:\n231525. Postgiro: 199720.",
    "structured": {
        "1": {
            "name": "Svenska Gummistrumpfabriken AB.",
            "location": "Stockholm",
            "business": "Resårstickeri",
            "products": "Tillverkar åderbråcks-strumpor. Varumärke: »Servus».",
            "contact": {
                "office": "Mästersamuelsg. 34",
                "phone": [
                    "118434"
                ],
                "postgiro": "152480"
            },
            "financials": {
                "capital": "15,000 kr",
                "employees": {
                    "industriarb": 10
                },
                "annual_turnover": "40,000 kr"
            },
            "foundation_year": 1937,
            "board": [
                {
                    "name": "dir. Albin Johansson",
                    "role": "ordf."
                },
                {
                    "name": "fil. lic. Mauritz Bonow",
                    "role": ""
                },
                {
                    "name": "dir. Hj. Deger-stedt",
                    "role": ""
                },
                {
                    "name": "dir. Hugo Edstam",
                    "role": ""
                },
                {
                    "name": "dir. G. Osvald",
                    "role": ""
                },
                {
                    "name": "dir. Ernst Persson",
                    "role": ""
                }
            ]
        },
        "2": {
            "name": "Svenska Havregryn Gylienhammar & Co. Kommanditbolag",
            "location": "Göteborg",
            "products": "Tillverkar havregryn, havremjöl och havremust",
            "contact": {
                "office": "AB. Havremust, L. Bommens torg 2",
                "phone": [
                    "134105"
                ],
                "telegraph": "Havremust, Göteborg",
                "postgiro": "43404"
            },
            "financials": {
                "capital": "100,000 kr",
                "employees": {
                    "industriarb": null
                },
                "annual_turnover": "2,000,000 kr"
            },
            "foundation_year": 1922,
            "description": "Ansvarig chef: dir. Gustaf Hammar"
        },
        "3": {
            "name": "AB. Svenska Häftstiftsfabriken",
            "location": "Örebro",
            "description": "Järnmanufakturverk i Pålsboda (Örebro l.). Tillverkar häftstift, såväl för-mässingade som förnicklade, dubbel-nitade, metallöverkapslade, lackerade och celluloid-överkapslade stift samt pappersklämmor, häftklammer, provpåsklämmor och metallbygglådor. Varumärken: »S. H. F.», »Olfa» o. »Stjärnstift».",
            "contact": {
                "office": "Örebro",
                "phone": [
                    "12818"
                ],
                "postgiro": "130505"
            },
            "financials": {
                "capital": "50,000 kr",
                "employees": {
                    "industriarb": 35
                },
                "annual_turnover": "500,000 kr"
            },
            "corporation_year": 1936,
            "board": [
                {
                    "name": "Fritz Johansson",
                    "role": "Verkst. dir."
                }
            ]
        },
        "4": {
            "name": "AB. Svenska Icopal- & Takpix-fabriken",
            "location": "Malmö",
            "business": "Takpapp-, tjär- och asfaltemulsions-fabrik",
            "products": "Tillverkar underhållsfri takpapp (»Icopal»), asfaltpapp (»Triumph», »Elg» o. »Sirius»), underlagspapp och förhydningspapp, mattunderlägg (»Korcopal» o. »Linolag»), bitumenplattor (» Villadrit»), tak-tjära (»Svensk Patent Takpixtjära» o. »Icopix»), bitumen (»Klisterpix»), kallflytande asfalt (»Icoflux»), asfaltpasta-emulsion (»Kifas»), asbesttätningskitt (»Kitti»), takfärger (»Svensk Patent Takpixfärg») och aluminiumfärg (»Silverflux»), träimpregneringsmedel (»Villadol 39»), pulverasfalt (»Kvartsit-Stahlas»), tjärbetongmassa (»Tjär-Stahlas»), vägasf altemulsion (»Koldmex» o. »Ico-bit»), tjäremulsion (»Icotar»), vägtjära (»Tarox») samt tjärasfalt (»Taroxas»). Utför taktäckningar, isoleringar, glaslanterniner (system »Svita»), specialfönster för snedtak (»Svita-fönstret») samt vägarbeten.",
            "contact": {
                "office": "Skeppsbron 11",
                "phone": [
                    "Icopalfabriken"
                ],
                "postgiro": "25111"
            },
            "financials": {
                "capital": "200,000 kr",
                "annual_turnover": "8,000,000 kr"
            },
            "corporation_year": 1915,
            "board": [
                {
                    "name": "bankdir. Ivar Åkerman",
                    "role": "ordf."
                },
                {
                    "name": "adv. Wilhelm Kjellström",
                    "role": "v. ordf."
                },
                {
                    "name": "dir. Chr. Villadsen",
                    "role": ""
                }
            ]
        },
        "5": {
            "name": "AB. Svenska Idealhus",
            "location": "Hultsfred",
            "description": "Snickerifabrik, sågverk och hyvleri i Hultsfred (Kalmar l.). Tillverkar byggnadssnickerier och monteringsfärdiga trähus.",
            "financials": {
                "capital": "500,000 kr"
            },
            "foundation_year": 1944,
            "board": [
                {
                    "name": "godsägare Hadar Hedborg",
                    "role": "ordf."
                },
                {
                    "name": "dir. G. Edström",
                    "role": ""
                },
                {
                    "name": "ryttm. B. Hyl-tén-Cavallius",
                    "role": ""
                },
                {
                    "name": "landstingsm. David Johansson",
                    "role": ""
                },
                {
                    "name": "godsäg. Arvid Nilsson",
                    "role": ""
                },
                {
                    "name": "friherre L. Wrede",
                    "role": ""
                }
            ]
        },
        "6": {
            "name": "Svenska Industribyggen AB.",
            "location": "Stockholm",
            "description": "Byggnadsentreprenörfirma speciellt för industribyggnader. Firmamärke: »SIAB».",
            "contact": {
                "office": "Sveavägen 29 (efter den 1/5 1947 N. Stationsg. 75—77)",
                "phone": [
                    "231525"
                ],
                "postgiro": "199720"
            }
        }
    }
}