{
    "original": "Carlving—C eder vall\n\nAkt.-kap.: 160,000 kr. Antal industriarb.:\n30. — Bolaget grundat 1919.\n\nStyrelse o. verkst. direktörer: dir.\nJohan Gustafsson, fru Selma Svensson o.\ngrossh. John A. Gustafsson.\n\nAB. Carlving &amp; Co., Borås.\n\nBarnkonfektionsfabrik. Tillverkar\nkostymer, trenchcoats, byxor, overalls,\nbla-zers, rockar m. m. Varumärke: »Skotty».\n\nTelefon: 19010. Postgiro: 264210.\n\nAkt.-kap.: 100,000 kr. Antal\nindustriarb.: 60. Tillv.-värde pr år: 1,000,000 kr.\n\n—\tBolaget grundat 1943.\n\nVerkst. dir.: Sven Carlving.\n\nDisp.: Bertil Blomberg.\n\n*AB. Carma, Göteborg.\n\nSe Gamlestadens Fabrikers AB.,\nGöteborg.\n\n*D. Carnegie &amp; Co., Göteborg.\n\nSe Porterbryggeri AB. D. Carnegie &amp;\nCo., Göteborg.\n\nCasparsson &amp; Schmidt, Handels- &amp;\nFabriks AB., Stockholm.\n\nKravattfabrik. Tillverkar herrhalsdukar\nm. m. Varumärke: »Cetes». Firman\ndriver även engroshandel med sidenvaror.\n\nKontor: Kungsg. 4 A; postadr.:\nStockholm 7. Telgr.-adr.: Casparssons,\nStockholm. Telefon: 101146, 101145 o. 109276.\nPostgiro: 4822.\n\nAkt.-kap.: 250,000 kr. Antal\nindustriarb.: 50. — Firman etabl. 1804, bolag\n1932.\n\nVerkst. dir.: Arvid Wahlin.\n\nDisponenter: Swen Wahlin o. Ragnar\nÖberg.\n\nAB. Ceaverken, Strängnäs.\n\nKem. teknisk fabrik. Tillverkar\nröntgenfilm samt fotografiskt papper.\nVarumärke: »Cea».\n\nTelefon: 404 o. 740. Postgiro: 163755.\n\n—\tAkt.-kap.: 600,000 kr. Antal\nindustriarb.: 40. — Bolaget, grundat 1938, äges\nav svenska staten.\n\nStyrelse: övering. Rolf Steenhoff\n(ordf.), med. dr E. B. E. Bager, byråchef\nAllan Broomé, övering. Birger Sundfeldt,\nprof. The Svedberg, kommendörkapten\nRagnar Thorén.\n\nVerkst. dir.: kapten Lars O. Högström.\n\nKamrer: Per Ekwall.\n\n*Cebe AB., Svalöv.\n\nElektromek. verkstad, gjuteri och\narmaturfabrik i Svalöv (Malmöh. l.).\n\nTillverkar elektr. belysningsarmatur,\nstrålkastare för lok, automobiler och\ncyklar, ^ marinmateriel, järnvägsmateriel,\ngjutjärnskapslad materiel, järn- och\nme-tallgjutgods.\n\nTelegr.-adr. o. telefon: Cebe, Svalöv.\nPostgiro: 72450.\n\nAkt.-kap.: 250,000 kr. Antal\nindustriarb.: 220. Tillv.-värde pr år: 2,000,000 kr.\n\nFirman, grundad 1909, bolag 1915 under\nnamn Elektriska AB. Chr. Bergh &amp; Co.,\nnuv. namn 1943, tillhör Asea-koncernen.\n\nStyrelse: dir. Thorsten Ericson (ordf.),\ndir. Hugo Edström, dir. Alb. Elfström,\nkamrer O. W. Rahl.\n\nVerkst. dir.: Hugo Edström (Sthlm).\n\nPlatschef i Svalöv: O. W. Rahl.\n\n’John Cederblad, Örebro.\n\nByggnadsentreprenörfirma för\nbostads-och affärshus, industribyggnader samt\nför väg- och vattenbyggnadsarbeten.\n\nTelefon: 15404 o. 21282. Postgiro:\n33648. — Firman etabl. 1929.\n\nÄgare o. chef: major John M.\nCederblad.\n\nCederquists Grafiska AB.,\n\nStockholm.\n\nKemigrafisk anstalt och boktryckeri.\nUtför klichéer samt boktrycksarbeten.\n\nKontor: Vasag. 16. Telefon:\n»Stabs-litografen». — Bolaget, som grundades\n1908, är anslutet till AB. Sveriges\nLitografiska Tryckerier, Stockholm. (Se detta\nbolag.)\n\nStyrelse o. verkst. dir.: ryttm. Åke G.\nWickman.\n\nCederroths Tekniska Fabrik,\n\nStockholm.\n\nTillverkar fruktsalt. Varumärke:\n»Sa-marin».\n\nKontor: Sveavägen 86. Telegr.-adr.:\nSamarin, Stockholm. Telefon: 335440.\nPostgiro: 644. — Antal industriarb.: 32.\n— Firman etabl. 1895.\n\nÄgare o. chef: fabr. Sture Cederroth.\n\nKontorschef: kamrer H. Källström.\n\nFabrihschef: civiling. Birger\nSalomon-son.\n\n’AB. F. R. Cedervall &amp; Söner,\n\nGöteborg.\n\nMek. verkstad och metallgjuteri.\nTillverkar skyddsboxar för propelleraxlar\nsamt metallgjutgods.",
    "structured": {
        "1": {
            "name": "AB. Carlving & Co.",
            "location": "Borås",
            "business": "Barnkonfektionsfabrik",
            "products": "Tillverkar kostymer, trenchcoats, byxor, overalls, blazers, rockar m. m.",
            "contact": {
                "office": "N/A",
                "phone": [
                    "19010"
                ],
                "postgiro": "264210"
            },
            "financials": {
                "capital": "160,000 kr",
                "employees": {
                    "industriarb": 30
                },
                "annual_production_value": "N/A"
            },
            "foundation_year": 1919,
            "board": [
                {
                    "name": "Johan Gustafsson",
                    "role": "direktör"
                },
                {
                    "name": "fru Selma Svensson",
                    "role": "N/A"
                },
                {
                    "name": "grossh. John A. Gustafsson",
                    "role": "N/A"
                }
            ],
            "owners": [],
            "director": "Sven Carlving"
        },
        "2": {
            "name": "D. Carnegie & Co.",
            "location": "Göteborg",
            "business": "N/A",
            "products": "N/A",
            "contact": {
                "office": "N/A",
                "phone": [],
                "postgiro": "N/A"
            },
            "financials": {
                "capital": "100,000 kr",
                "employees": {
                    "industriarb": 60
                },
                "annual_production_value": "N/A"
            },
            "foundation_year": 1943,
            "board": [],
            "owners": [],
            "director": "Sven Carlving"
        },
        "3": {
            "name": "Casparsson & Schmidt, Handels- & Fabriks AB.",
            "location": "Stockholm",
            "business": "Kravattfabrik",
            "products": "Tillverkar herrhalsdukar m. m.",
            "contact": {
                "office": "Kungsg. 4 A",
                "phone": [
                    "101146",
                    "101145",
                    "109276"
                ],
                "postgiro": "4822"
            },
            "financials": {
                "capital": "250,000 kr",
                "employees": {
                    "industriarb": 50
                },
                "annual_production_value": "1,000,000 kr"
            },
            "foundation_year": 1804,
            "board": [],
            "owners": [],
            "director": "Arvid Wahlin"
        },
        "4": {
            "name": "Ceaverken",
            "location": "Strängnäs",
            "business": "Kem. teknisk fabrik",
            "products": "Tillverkar röntgenfilm samt fotografiskt papper",
            "contact": {
                "office": "N/A",
                "phone": [
                    "404",
                    "740"
                ],
                "postgiro": "163755"
            },
            "financials": {
                "capital": "600,000 kr",
                "employees": {
                    "industriarb": 40
                },
                "annual_production_value": "N/A"
            },
            "foundation_year": 1938,
            "board": [
                {
                    "name": "övering. Rolf Steenhoff",
                    "role": "ordf."
                },
                {
                    "name": "med. dr E. B. E. Bager",
                    "role": "byråchef"
                },
                {
                    "name": "Allan Broomé",
                    "role": "N/A"
                },
                {
                    "name": "övering. Birger Sundfeldt",
                    "role": "N/A"
                },
                {
                    "name": "prof. The Svedberg",
                    "role": "N/A"
                },
                {
                    "name": "kommendörkapten Ragnar Thorén",
                    "role": "N/A"
                }
            ],
            "owners": [],
            "director": "kapten Lars O. Högström"
        },
        "5": {
            "name": "Cebe AB.",
            "location": "Svalöv",
            "business": "Elektromek. verkstad, gjuteri och armaturfabrik",
            "products": "Tillverkar elektr. belysningsarmatur, strålkastare för lok, automobiler och cyklar, marinmateriel, järnvägsmateriel, gjutjärnskapslad materiel, järn- och metallgjutgods",
            "contact": {
                "office": "N/A",
                "phone": [],
                "postgiro": "72450"
            },
            "financials": {
                "capital": "250,000 kr",
                "employees": {
                    "industriarb": 220
                },
                "annual_production_value": "2,000,000 kr"
            },
            "foundation_year": 1909,
            "board": [
                {
                    "name": "dir. Thorsten Ericson",
                    "role": "ordf."
                },
                {
                    "name": "dir. Hugo Edström",
                    "role": "N/A"
                },
                {
                    "name": "dir. Alb. Elfström",
                    "role": "N/A"
                },
                {
                    "name": "kamrer O. W. Rahl",
                    "role": "N/A"
                }
            ],
            "owners": [],
            "director": "Hugo Edström"
        },
        "6": {
            "name": "John Cederblad",
            "location": "Örebro",
            "business": "Byggnadsentreprenörfirma",
            "products": "Byggnadsentreprenörfirma för bostads-och affärshus, industribyggnader samt för väg- och vattenbyggnadsarbeten",
            "contact": {
                "office": "N/A",
                "phone": [
                    "15404",
                    "21282"
                ],
                "postgiro": "33648"
            },
            "financials": {
                "capital": "N/A",
                "employees": {
                    "industriarb": "N/A"
                },
                "annual_production_value": "N/A"
            },
            "foundation_year": 1929,
            "board": [],
            "owners": [
                "major John M. Cederblad"
            ],
            "director": "N/A"
        },
        "7": {
            "name": "Cederquists Grafiska AB.",
            "location": "Stockholm",
            "business": "Kemigrafisk anstalt och boktryckeri",
            "products": "Utför klichéer samt boktrycksarbeten",
            "contact": {
                "office": "Vasag. 16",
                "phone": [
                    "N/A"
                ],
                "postgiro": "N/A"
            },
            "financials": {
                "capital": "N/A",
                "employees": {
                    "industriarb": "N/A"
                },
                "annual_production_value": "N/A"
            },
            "foundation_year": 1908,
            "board": [
                {
                    "name": "ryttm. Åke G. Wickman",
                    "role": "N/A"
                }
            ],
            "owners": [],
            "director": "N/A"
        },
        "8": {
            "name": "Cederroths Tekniska Fabrik",
            "location": "Stockholm",
            "business": "Tillverkar fruktsalt",
            "products": "Tillverkar fruktsalt",
            "contact": {
                "office": "Sveavägen 86",
                "phone": [
                    "335440"
                ],
                "postgiro": "644"
            },
            "financials": {
                "capital": "N/A",
                "employees": {
                    "industriarb": 32
                },
                "annual_production_value": "N/A"
            },
            "foundation_year": 1895,
            "board": [],
            "owners": [],
            "director": "fabr. Sture Cederroth"
        },
        "9": {
            "name": "AB. F. R. Cedervall & Söner",
            "location": "Göteborg",
            "business": "Mek. verkstad och metallgjuteri",
            "products": "Tillverkar skyddsboxar för propelleraxlar samt metallgjutgods",
            "contact": {
                "office": "N/A",
                "phone": [
                    "N/A"
                ],
                "postgiro": "N/A"
            },
            "financials": {
                "capital": "N/A",
                "employees": {
                    "industriarb": "N/A"
                },
                "annual_production_value": "N/A"
            },
            "foundation_year": "N/A",
            "board": [],
            "owners": [],
            "director": "N/A"
        }
    }
}