{
    "original": "Holts—HSB\n\n\" Aug. Holts Culddragerifabriks AB.,\n\nStockholm.\n\nTillverkar uniformseffekter såsom\nguld-och silvergaloner, axelklaffar,\nmössremmar m. m.\n\nKontor: Mästersamuelsg. 67. Telefon:\n100533. Postgiro: 51538.\n\nAkt.-kap.: 75,000 kr. Antal\nindustriarb.: 15. Tillv.-värde pr år: 180,000 kr.\n\n—\tFabriken anlagd 1885, bolag 1909.\n\nStyrelse o. verkst. dir.: Otto Kugelberg.\n\n*Aug. Holts Pels- och Mössfabriks\nAB., Stockholm.\n\nTillverkar pälsgarnityr och pälsmössor\nsamt hattar och mössor av tyg.\n\nKontor: Drottningg. 82. Telefon:\n230410. Postgiro: 51617.\n\nAkt.-kap.: 250,000 kr. Antal\nindustriarb.: 50. Tillv.-värde pr år: 1,040,000 kr.\n\n—\tFirman etabl. 1881, bolag 1909.\n\nStyrelse o. verkst. dir.: Knut\nJohansson.\n\nGust. W. Hoorn, Vetlanda.\n\nMek. verkstad och metallgjuteri.\nTillverkar registreringsskyltar för bilar,\nmarkeringsskyltar för gas- och\nvattenledningar, vägvisare och trafikmärken,\nfirmaskyltar m. m.\n\nTelefon: 165. Postgiro: 36297. —\nArb.-antal: 8. — Firman etabl. 1896.\n\nÄgare: fabr. Victor Hoorn, fabr.\nRichard Hoorn o. fru A. Hoprn.\n\nAB. Hörda Möbelfabrik, Hörda.\n\nTillverkar möbler vid fabrik i Hörda\n(Jönköp. l.).\n\nTelefon: Värnamo 54022 o. 54050.\nPostgiro: 27028. — Akt.-kap.: 25,000 kr.\nAntal industriarb.: 20. Tillv.-värde pr år:\n240,000 kr. — Firman etabl. 1910.\n\nDisp.: Eric Nordén.\n\n*Horndals Jernverks AB., Horndal.\n\nMasugn, martinugn, lancashiresmedja,\ngöt-, grov- och mediumvalsverk, gjuteri\noch mek. verkstad i Horndal, tråd- och\nfinvalsverk vid Näs Bruk (båda i\nKopparb. l.).\n\nBetr. tillverkningar se under Fagersta\nBruks AB., Fagersta.\n\nKontor: Horndal. Telegr.-adr.:\nHorn-dalsverken, Krylbo. Telefon: Krylbo\n40170. — Akt.-kap.: 500,000 kr.\n\nBruket anlagt 1652, bolag 1872.\nVerksamheten arrenderas och försäljningen av\nbrukets produkter handhaves av Fagersta\nBruks AB., Fagersta (se detta bolag).\n\nStyrelse: disp. Hj. Åselius (ordf.), dir.\nNils Elf ström, dir. Z. Olson, övering.\nCarl Tallberg.\n\nPlatschef: C. Tallberg.\n\n*\tHorndals Sågverk, Horndal.\n\nSe AB. Statens Skogsindustrier,\nStockholm.\n\nHovids Trävaru AB., Sundsvall.\nSe Ankars viks Ångsågs AB., Sundsvall.\n\n*\tAB. Hovmantorps Glasbruk,\n\nHovmantorp.\n\nGlasbruk med sliperi och glasmåleri i\nHovmantorp (Kronob. l.). Tillverkar\nslätt, slipat och pressat hushållsglas,\nkristallglas, prydnadsglas m. m.\n\nTelefon: 4 o. 55. Postgiro: 70827.\nAkt.-kap.: 148,000 kr. Antal\nindustriarb.: 95. Tillv.-värde pr år: 700,000 kr.\n\n—\tBolaget grundat 1905.\n\nStyrelse: bankkamrer A. Gunnar\nPeterson (ordf.), fru E. Schmidt.\nDisp.: frih. Carl F. Hermelin.\nKamrer: H. Vogel.\n\n*AB. Hovslätts Mekaniska\nSnickerifabrik, Hov slätt,\n\nSnickerifabrik med sågverk och hyvleri\ni Hovslätt (Jönköp. l.). Tillverkar sågade\noch hyvlade trävaror samt\nbyggnads-snickerier\n\nTelefon: 8 o. 80. Postgiro: 75950.\nAkt.-kap.: 60,000 kr. Antal\nindustriarb.: 30. Tillv.-värde pr år: 500,000 kr.\n\n—\tFirman, etabl. 1906, bolag 1908, ages\nav Jönköpings och Vulcans\nTändsticksfabriks AB., Jönköping.\n\nStyrelse: dir. Torsten Jung (ordf.),\ndisp. Gösta Birgersson, dir. And.\nGranberg.\n\nVerkst. dir.: ing. Helmer Knutsson\n(Jönköping).\n\nHSB:s Snickerifabrik i Sparreholm\n\nAB., Sparreholm.\n\nSnickerifabrik i Sparreholm\n(Södermanl. l.). Tillverkar byggnadssnickerier\noch inredningar samt parkett.\n\nTelefon: 3, 123 o. 133. Postgiro:\n165887. — Akt.-kap.: 20,000 kr. Antal\nindustriarb.: 90. Tillv.-värde pr år:\n2,000,000 kr.\n\nFabriken anlagd 1887, bolag 1907 under\nnamn AB. Sparreholms Snickerifabrik,\nnuv. namn 1939.",
    "structured": {
        "1": {
            "name": "Aug. Holts Culddragerifabriks AB",
            "location": "Stockholm",
            "business": "Tillverkar uniformseffekter såsom guld-och silvergaloner, axelklaffar, mössremmar m. m.",
            "products": "Description of products manufactured or services offered.",
            "contact": {
                "office": "Mästersamuelsg. 67",
                "phone": [
                    "100533"
                ],
                "postgiro": "51538"
            },
            "financials": {
                "capital": "75,000 kr",
                "employees": {
                    "industriarb": 15
                },
                "annual_turnover": "180,000 kr",
                "annual_production_value": "180,000 kr"
            },
            "foundation_year": 1885,
            "corporation_year": 1909,
            "board": [
                {
                    "name": "Otto Kugelberg",
                    "role": "Styrelse o. verkst. dir."
                }
            ]
        },
        "2": {
            "name": "Aug. Holts Pels- och Mössfabriks AB",
            "location": "Stockholm",
            "business": "Tillverkar pälsgarnityr och pälsmössor samt hattar och mössor av tyg",
            "products": "Description of products manufactured or services offered.",
            "contact": {
                "office": "Drottningg. 82",
                "phone": [
                    "230410"
                ],
                "postgiro": "51617"
            },
            "financials": {
                "capital": "250,000 kr",
                "employees": {
                    "industriarb": 50
                },
                "annual_turnover": "1,040,000 kr",
                "annual_production_value": "1,040,000 kr"
            },
            "foundation_year": 1881,
            "corporation_year": 1909,
            "board": [
                {
                    "name": "Knut Johansson",
                    "role": "Styrelse o. verkst. dir."
                }
            ]
        },
        "3": {
            "name": "Gust. W. Hoorn",
            "location": "Vetlanda",
            "business": "Mek. verkstad och metallgjuteri",
            "products": "Tillverkar registreringsskyltar för bilar, markeringsskyltar för gas- och vattenledningar, vägvisare och trafikmärken, firmaskyltar m. m.",
            "contact": {
                "phone": [
                    "165"
                ],
                "postgiro": "36297"
            },
            "financials": {
                "employees": {
                    "arb": 8
                }
            },
            "foundation_year": 1896,
            "owners": [
                "fabr. Victor Hoorn",
                "fabr. Richard Hoorn",
                "fru A. Hoprn"
            ]
        },
        "4": {
            "name": "AB. Hörda Möbelfabrik",
            "location": "Hörda",
            "business": "Tillverkar möbler",
            "contact": {
                "phone": [
                    "Värnamo 54022",
                    "Värnamo 54050"
                ],
                "postgiro": "27028"
            },
            "financials": {
                "capital": "25,000 kr",
                "employees": {
                    "industriarb": 20
                },
                "annual_turnover": "240,000 kr"
            },
            "foundation_year": 1910,
            "owners": [
                "Disp.: Eric Nordén"
            ]
        },
        "5": {
            "name": "Horndals Jernverks AB",
            "location": "Horndal",
            "business": "Masugn, martinugn, lancashiresmedja, göt-, grov- och mediumvalsverk, gjuteri och mek. verkstad",
            "contact": {
                "telegraph": "Horn-dalsverken, Krylbo",
                "phone": [
                    "Krylbo 40170"
                ]
            },
            "financials": {
                "capital": "500,000 kr"
            },
            "foundation_year": 1652,
            "corporation_year": 1872,
            "board": [
                {
                    "name": "disp. Hj. Åselius",
                    "role": "Styrelse"
                }
            ],
            "director": "Platschef: C. Tallberg"
        },
        "6": {
            "name": "AB. Hovmantorps Glasbruk",
            "location": "Hovmantorp",
            "business": "Glasbruk med sliperi och glasmåleri i Hovmantorp (Kronob. l.). Tillverkar slätt, slipat och pressat hushållsglas, kristallglas, prydnadsglas m. m.",
            "contact": {
                "phone": [
                    "4",
                    "55"
                ],
                "postgiro": "70827"
            },
            "financials": {
                "capital": "148,000 kr",
                "employees": {
                    "industriarb": 95
                },
                "annual_turnover": "700,000 kr"
            },
            "foundation_year": 1905,
            "board": [
                {
                    "name": "bankkamrer A. Gunnar Peterson",
                    "role": "Styrelse"
                },
                {
                    "name": "freih. Carl F. Hermelin",
                    "role": "Disp."
                }
            ],
            "manager": "Kamrer: H. Vogel"
        },
        "7": {
            "name": "AB. Hovslätts Mekaniska Snickerifabrik",
            "location": "Hovslätt",
            "business": "Snickerifabrik med sågverk och hyvleri i Hovslätt (Jönköp. l.). Tillverkar sågade och hyvlade trävaror samt byggnads-snickerier",
            "contact": {
                "phone": [
                    "8",
                    "80"
                ],
                "postgiro": "75950"
            },
            "financials": {
                "capital": "60,000 kr",
                "employees": {
                    "industriarb": 30
                },
                "annual_turnover": "500,000 kr"
            },
            "foundation_year": 1906,
            "corporation_year": 1908,
            "owners": [
                "agesav Jönköpings och Vulcans Tändsticksfabriks AB., Jönköping"
            ],
            "board": [
                {
                    "name": "dir. Torsten Jung",
                    "role": "Styrelse"
                },
                {
                    "name": "disp. Gösta Birgersson",
                    "role": "Disp."
                }
            ],
            "manager": "Verkst. dir.: ing. Helmer Knutsson (Jönköping)"
        },
        "8": {
            "name": "HSB:s Snickerifabrik i Sparreholm AB",
            "location": "Sparreholm",
            "business": "Snickerifabrik i Sparreholm (Södermanl. l.). Tillverkar byggnadssnickerier och inredningar samt parkett",
            "contact": {
                "phone": [
                    "3",
                    "123",
                    "133"
                ],
                "postgiro": "165887"
            },
            "financials": {
                "capital": "20,000 kr",
                "employees": {
                    "industriarb": 90
                },
                "annual_turnover": "2,000,000 kr"
            },
            "foundation_year": 1887,
            "corporation_year": 1907,
            "current_name_year": 1939
        }
    }
}