{
    "original": "Stjernqvist—Stockholm\n\npås- och annat sulfitpapper samt\nsulfit-cellulosa. Från egna kraftstationer\nerhål-les elektrisk energi till bolagets olika\nanläggningar. Bolaget idkar jämväl\njordbruk oeh skogshantering.\n\nHuvudkontor: Ställdalen. Telegr.-adr.:\nStälldalsbruk, Kopparberg. Telefon:\nStälldalen 200, 201 o. 202. Postgiro: 33195.\n\nBrukskontor: Bredsjö. Télefon:\nHjulsjö 2 o Bredsjö 14.\n\nAkt.-kap.: 3,750,000 kr. Antal\nindustriarb.: 500. Tillv.-värde pr år: 15,000,000\nkr. Årstillv.: 24,000 ton tackjärn, 2,000\nstds sågade trävaror, 16,000 ton\nsulfit-cellulosa, 9,000 ton papper.\n\nBolaget grundat 1896.\n\nStyrelse: disp. N. Arvid Ericsson\n(ordf.), disp. Fredrik Cassel, bergsing.\nAxel Ax:son Johnson J:r, bankdir. Rich.\nJulin, adv. Wilhelm Moberg.\n\nVerkst. dir. o. disp.: Fredrik Cassel.\n\nDriftsingenjörer: i Bredsjö: Hj.\nWin-qvist; i Ställdalen: Tage Holmgren o.\nRutger Larson.\n\nFörsäljn.-dir. för papper o. massa:\nGunnar Hulthén.\n\nInhöpschef: Nils Blomquist.\n\nKamrer: E. Bratt.\n\nAB. Stjernqvist Metallfabrik,\n\nStockholm.\n\nMetall var ufabriker i Stockholm och\nHedlandet, Läggesta (Södermänl. l.).\nTillverkar metallarbeten såsom\nnyttokonst och hushållsartiklar.\n\nKontor: Hornsg. 160. Telefon: 433875.\nPostgiro: 155630.\n\nAkt.-kap.: 100,000 kr. Antal\nindustriarb.: 100, varav i Stockholm 50.\nTillv.-värde pr år: 600,000 kr. — Firman etabl.\n1919, bolag 1939.\n\nVerkst. dir.: Carl Viktor Stjernqvist.\n\nDriftschef i Läggestä: ing. Olov Borgö.\n\nKamrer: Otto W essman.\n\nAB. Stjernsunds Bruk,\n\nStjärnsund.\n\nSågverk och hyvleri i Stjärnsund\n(Kopparb. l.). Tillverkar sågade och hyvlade\nträvaror. Bolaget driver även jordbruk\noch skogshantering.\n\nTelegr.-adr.: Starmill, Hedemora.\nTelefon: Stjärnsund 1, 42 o. 43. Postgiro:\n91655.\n\nAkt.-kap.: 2,000,000 kr. Antal\nindustriarb.: 55. — Bolaget grundat 1934.\n\nStyrelse: dir. C. R. Bildt, adv. Wilhelm\nMoberg, bankdir. Th. Raaschou, disp.\nJohn Qvarnström.\n\nVerkst. dir.: John Qvarnström.\n\n*Stoeka Sågverk, Strömsbruk.\n\nSe Ströms Bruks AB., Strömsbruk.\n\n*Stockamöllans AB., Stockamöllan,\n\nSågverk, snickerifabrik och mek.\nverkstad vid Stockamöllan (Malmöh. l.).\n\nTillverkar sågade trävaror av lövträ,\nhjulkuggar, verktygsskaft, hyvelbänkar,\nstansblock och kötthuggblock,\nträdgårdsmöbler, stegar, skott- och magasinskärror,\nlyfttransportvagnar (märke: »Stocka»),\ntransportvagnar och -kärror för fabriker\noch varulager, transportanordningar\nsåsom rullbanor, transportörer och\nstap-lingsapparater, hjul, länkrullar och\nhjulsatser samt mjölkningsskjul och\npotatis-sorteringsmaskiner (märke: »Pär»).\n\nTelefon: »Stockamöllans Aktiebolag».\nPostgiro: 7900.\n\nRepresentanter: i Stockholm: ing* E.\nLarsson-Palm, Kungsholms Hamnplan 3,\ntelefon: 533077; i Göteborg: Ing.-firma\nRob. Hellström, Skeppsbroplatsen,\ntelefon: 135032.\n\nAkt.-kap.: 750,000 kr. Antal\nindustriarb.: 100. Tillv.-värde pr år: 1,800,000 kr.\n\nFirman etabl. 1851, bolag 1906.\n\nStyrelse: fru A. Sonesson (ordf.), disp.\nJacob Clemensson, ing. Sven Sonesson.\n\nVerkst. dir.: Sven Sonesson.\n\nStockaryds Nya Torv AB.,\n\nKalmar.\n\nTillverkar torvströ (spec. för export)\nvid fabrik i Stockaryd (Jönköp. l.).\nVarumärke: »Stocka».\n\nHuvudkontor o. försäljn.: E. Th.\nLudvigssons Trävaruaffär, Kalmar.\nTelegr.-adr.: Ludvigsson, Kalmar. Telefon: 271.\nPostgiro: 98243. Fabrikskontor:\nStockaryd. Telegr.-adr.: Torvbolaget, Stockaryd.\n\nAkt.-kap.: 20,400 kr. Tillv.-värde pr\når: 100,000 kr. — Bolaget grundat 1928.\n\nStyrelse; grossh. E. Th. Ludvigsson,\ninsp. Thorbjörn Ludvigsson, disp. Nils\nWesterberg.\n\nDisp.: Nils Westerberg.\n\n^Stockholms Aether &amp; Essencefabrik,\n\nStockholm.\n\nTillverkar frukteter, essencer,\njästjml-ver samt giftfria färger för konditorier\nm. m. Varumärke: »Herba». Firman\ndriver även engroshandel med kolonialvaror.\n\nKontor: Walling. 14. Telefon: 114686.\nPostgiro: 2913.\n\nArb.-antal: 6. Tillv.-värde pr år:\n200,000 kr. — Firman etabl. 1889.\n\nÄgare o. chef: fabr. Ragnar Lilieblad.\n\nFörsäljn.-chef: Carl R. Ohlsson.",
    "structured": {
        "1": {
            "name": "AB Stjernqvist",
            "location": "Stockholm",
            "business": "pås- och annat sulfitpapper samt sulfit-cellulosa. Från egna kraftstationer erhål-les elektrisk energi till bolagets olika anläggningar. Bolaget idkar jämväl jordbruk oeh skogshantering.",
            "contact": {
                "office": "Huvudkontor: Ställdalen",
                "phone": [
                    "Ställdalen 200",
                    "Ställdalen 201",
                    "Ställdalen 202"
                ],
                "postgiro": "33195",
                "sales_offices": [
                    {
                        "location": "Bredsjö",
                        "phone": "Hjulsjö 2 o Bredsjö 14"
                    }
                ]
            },
            "financials": {
                "capital": "3,750,000 kr",
                "employees": {
                    "industriarb": 500
                },
                "annual_turnover": "15,000,000 kr",
                "annual_production_value": "24,000 ton tackjärn, 2,000 stds sågade trävaror, 16,000 ton sulfit-cellulosa, 9,000 ton papper"
            },
            "foundation_year": 1896,
            "board": [
                {
                    "name": "disp. N. Arvid Ericsson",
                    "role": "ordf."
                },
                {
                    "name": "disp. Fredrik Cassel",
                    "role": "bergsing."
                },
                {
                    "name": "Axel Ax:son Johnson J:r",
                    "role": "bankdir."
                },
                {
                    "name": "Rich. Julin",
                    "role": "adv."
                },
                {
                    "name": "Wilhelm Moberg",
                    "role": "adv."
                }
            ],
            "director": "Fredrik Cassel",
            "sales_manager": "Gunnar Hulthén",
            "manager": "Nils Blomquist"
        },
        "2": {
            "name": "AB. Stjernqvist Metallfabrik",
            "location": "Stockholm",
            "business": "Metall var ufabriker i Stockholm och Hedlandet, Läggesta (Södermänl. l.). Tillverkar metallarbeten såsom nytto konst och hushållsartiklar.",
            "contact": {
                "office": "Kontor: Hornsg. 160",
                "phone": "433875",
                "postgiro": "155630"
            },
            "financials": {
                "capital": "100,000 kr",
                "employees": {
                    "industriarb": 100
                },
                "annual_turnover": "600,000 kr"
            },
            "foundation_year": 1919,
            "corporation_year": 1939,
            "director": "Carl Viktor Stjernqvist"
        },
        "3": {
            "name": "AB Stjernsunds Bruk",
            "location": "Stjärnsund",
            "business": "Sågverk och hyvleri i Stjärnsund (Kopparb. l.). Tillverkar sågade och hyvlade trävaror. Bolaget driver även jordbruk och skogshantering.",
            "contact": {
                "office": "Telegr.-adr.: Starmill, Hedemora",
                "phone": [
                    "Stjärnsund 1",
                    "Stjärnsund 42",
                    "Stjärnsund 43"
                ],
                "postgiro": "91655"
            },
            "financials": {
                "capital": "2,000,000 kr",
                "employees": {
                    "industriarb": 55
                }
            },
            "foundation_year": 1934,
            "board": [
                {
                    "name": "C. R. Bildt",
                    "role": "dir."
                },
                {
                    "name": "Wilhelm Moberg",
                    "role": "adv."
                },
                {
                    "name": "Th. Raaschou",
                    "role": "bankdir."
                },
                {
                    "name": "John Qvarnström",
                    "role": "disp."
                }
            ],
            "director": "John Qvarnström"
        },
        "4": {
            "name": "Stockamöllans AB",
            "location": "Stockamöllan",
            "business": "Sågverk, snickerifabrik och mek. verkstad vid Stockamöllan (Malmöh. l.). Tillverkar sågade trävaror av lövträ, hjulkuggar, verktygsskaft, hyvelbänkar, stansblock och kötthuggblock, trädgårdsmöbler, stegar, skott- och magasinskärror, lyfttransportvagnar (märke: »Stocka»), transportvagnar och -kärror för fabriker och varulager, transportanordningar såsom rullbanor, transportörer och stap-lingsapparater, hjul, länkrullar och hjulsatser samt mjölkningsskjul och potatis-sorteringsmaskiner (märke: »Pär»).",
            "contact": {
                "phone": "»Stockamöllans Aktiebolag»",
                "postgiro": "7900"
            },
            "financials": {
                "capital": "750,000 kr",
                "employees": {
                    "industriarb": 100
                },
                "annual_turnover": "1,800,000 kr"
            },
            "foundation_year": 1851,
            "corporation_year": 1906,
            "board": [
                {
                    "name": "fru A. Sonesson",
                    "role": "ordf."
                },
                {
                    "name": "Jacob Clemensson",
                    "role": "disp."
                },
                {
                    "name": "Sven Sonesson",
                    "role": "ing."
                }
            ],
            "director": "Sven Sonesson"
        },
        "5": {
            "name": "Stockaryds Nya Torv AB",
            "location": "Kalmar",
            "business": "Tillverkar torvströ (spec. för export) vid fabrik i Stockaryd (Jönköp. l.). Varumärke: »Stocka».",
            "contact": {
                "office": "Huvudkontor o. försäljn.: E. Th. Ludvigssons Trävaruaffär, Kalmar",
                "phone": "Kalmar: 271",
                "postgiro": "98243"
            },
            "financials": {
                "capital": "20,400 kr",
                "annual_turnover": "100,000 kr"
            },
            "foundation_year": 1928,
            "board": [
                {
                    "name": "grossh. E. Th. Ludvigsson",
                    "role": "h."
                },
                {
                    "name": "Thorbjörn Ludvigsson",
                    "role": "insp."
                },
                {
                    "name": "Nils Westerberg",
                    "role": "disp."
                }
            ],
            "director": "Nils Westerberg"
        },
        "6": {
            "name": "Stockholms Aether & Essencefabrik",
            "location": "Stockholm",
            "business": "Tillverkar frukteter, essencer, jästjml-ver samt giftfria färger för konditorier m. m. Varumärke: »Herba». Firman driver även engroshandel med kolonialvaror.",
            "contact": {
                "office": "Kontor: Walling. 14",
                "phone": "114686",
                "postgiro": "2913"
            },
            "financials": {
                "employees": {
                    "arb.-antal": 6
                },
                "annual_turnover": "200,000 kr"
            },
            "foundation_year": 1889,
            "director": "Ragnar Lilieblad",
            "sales_manager": "Carl R. Ohlsson"
        }
    }
}