{
    "original": "Nya\n\nStyrelse: dir. Tore Grönwall (ordf.),\nciviling. Harald Freden, civiling. K. J.\nGendt, bankdir. Richard Julin, ing. A.\nKleist.\n\nVerkst. dir.: A. Kleist.\n\nKontorschef: G. Lindblad.\n\nDriftsingenjörer: för byggnadsavd.:\ning. K. M. Breitow; för asfaltavd.: ing.\nR. JSchultz; för väg- o. anläggningsavd.:\nciviling. Per Lagerberg.\n\nPlatschefer: Malmö: civiling. Harald\nFreden; Örebro: ing. Rud. Jonsson.\n\nNya Asfalt- &amp; Gementgjuteriet,\n\nLinköping.\n\nTillverkar betongvaror såsom\nbetongrör till brunnar och avloppsledningar,\ntrappsteg, planstenar, betonghålsten m. m.\nsamt utför betongarbeteri,\nasfaltbeläggningar, isoleringar, massabeläggningar,\nmosaikarbeten m. m.\n\nTelefon: 22174 o. 28178. Postgiro:\n77007. — Antal industriarb.: 25.\nTillv.-värde pr år: 300,000 kr. — Firman etabl.\n1920.\n\nÄgare o. chef: fabr. Axel Karlsson.\n\nNya AB. Björkshults Glasbruk,\n\nBjörkedal.\n\nTillverkar hushållsglas, lamp- och\nlyktglas, preparatrör, kaffekulor samt\nhård-härdat glas vid glasbruk i Björkedal\n(Kalmar l.).\n\nTelefon: Grönskåra 5. Postgiro: 137766.\n\nAkt.-kap.: 38,000 kr. Antal\nindustriarb.: 90. Tillv.-värde pr år: 650,000 kr.\n\n—\tBruket anlagt 1892, nuv. bolag\ngrundat 1935.\n\nVerkst. dir. o. disp.: Chr. Björkander.\n\n*AB. Nya Bryggeriet i Borås, Borås.\n\nTillverkar malt- och läskedrycker.\n\nTelegr.-adr. o. telefon: Nya Bryggeriet,\nBorås. Postgiro: 72009. Bolaget har\nnederlag i Ulricehamn.\n\nAkt.-kap.: 500,000 kr. Antal\nindustriarb.: 35. Tillv.-värde pr år: 1,000,000 kr.\n\n—\tBolaget grundat 1898.\n\nStyrelse: fabr. Sven Sandwall (ordf.),\nbankdir. Elof Björck, adv. Erik Grepiors.\n\nVerkst. dir.: Sven Sandwall.\n\nNya Bryggeri- och Mälteri AB. i\nVästerås, Västerås.\n\nTillverkar malt och maltdrycker samt\nmineralvatten och läskedrycker\n(Mineralvattenfabriken Källan).\n\nTelefon: 30039, 30182 o. 31624. —\nAkt.-kap.: 300,200 kr. Antal industri-\n\narb.: 25. Tillv.-värde pr år: 900,000 kr.\n\n—\tBolaget grundat 1931.\n\nStyrelse, verkst. dir. o. disp.: Hugo\nAnderson.\n\n*AB. Nya Centralbryggeriet,\n\nLinköping.\n\nBryggerier i Hultsfred, Kisa,\nLinköping, Mjölby, Oskarshamn, Vadstena,\nVimmerby och Västervik (Hultsfred i\nKalmar 1., Kisa i Östergötl. l.).\nTillverkar malt-* och läskedrycker, kolsyrat\nvatten samt malt.\n\nHuvudkontor: Linköping. Telegr.-adr.:\nOentralbryggeriet, Linköping. Telefon:\n22849 o. 25504. Postgiro: 90380.\nAvd.-kontor vid samtliga bryggerier.\n\nAkt.-kap.: 2,500,000 kr. Antal\nindustriarb. : 120. — Bolaget grundat 1918.\n\nStyrelse: dir. Hjalmar Hensmar (ordf.),\ning. A. Anderson (v. ordf.), dir. Pehr\nCarlson, dir. Birger Paulson, major E. O.\nPålman, civiling. Tore Segerdahl.\n\nVerkst. dir.: Birger Paulson.\n\nDisponenter: i Linköping: Birger\nPaulson; i Västervik: Bertil Svensson; i\nOskarshamn: B. Wolke; i Vimmerby:\nHans Jacobsson.\n\n*Nya AB. Chokladfabriken Coody,\n\nMalmö.\n\nTillverkar choklad, karameller, kola,\ndrageer och skumartiklar.\n\nKontor: Geijersg. 13. Telefon: 51305\no. 51313. Postgiro: 148172.\n\nAkt.-kap.: 10,000 kr. Antal\nindustriarb.: 35. Tillv.-värde pr år: 450,000 kr.\n\n—\tBolaget grundat 1940.\n\nStyrelse: disp. Ragnar Dahlquist\n(ordf.), disp. Kjell Jakobsson,\n\nVerkst. dir.: R. Dahlquist.\n\nNya AB. Ekmöbler, Virserum.\n\nTillverkar möbler vid fabrik i\nVirserum (Kalmar l.).\n\nTelefon: 79. Postgiro: 132810. —\nAkt.-kap-: 33,600 kr. Antal industriarb.: 40.\nTillv.-värde pr år: 270,000 kr. — Firman\netabl. 1927.\n\nVerkst. dir. o. disp.: Josef Petersson.\n\n*Nya AB. Eos, Nässjö.\n\nMetallvarufabrik, mek. verkstad,\ngjuteri, galvaniserings- och\nförnicklingsan-stalt. Tillverkar elektr. armatur,\nmetallmanufaktur och metallgjutgods; utför\nmetalltryckning, metallpressning m. m.\n\nTelefon: 250. Postgiro: 30212.\n—Akt.-kap.: 133,000 kr. Antal industriarb.: 60.",
    "structured": {
        "1": {
            "name": "Nya Asfalt- & Gementgjuteriet",
            "location": "Linköping",
            "business": "Tillverkar betongvaror såsom betongrör till brunnar och avloppsledningar, trappsteg, planstenar, betonghålsten m. m. samt utför betongarbeteri, asfaltbeläggningar, isoleringar, massabeläggningar, mosaikarbeten m. m.",
            "contact": {
                "phone": [
                    "22174",
                    "28178"
                ],
                "postgiro": "77007"
            },
            "financials": {
                "employees": {
                    "industriarb": 25
                },
                "annual_production_value": "300,000 kr"
            },
            "foundation_year": 1920,
            "manager": "Axel Karlsson"
        },
        "2": {
            "name": "Nya AB. Björkshults Glasbruk",
            "location": "Björkedal",
            "business": "Tillverkar hushållsglas, lamp- och lyktglas, preparatrör, kaffekulor samt hård-härdat glas vid glasbruk i Björkedal (Kalmar l.)",
            "contact": {
                "phone": "Grönskåra 5",
                "postgiro": "137766"
            },
            "financials": {
                "employees": {
                    "industriarb": 90
                },
                "annual_production_value": "650,000 kr"
            },
            "foundation_year": 1935,
            "director": "Chr. Björkander"
        },
        "3": {
            "name": "AB. Nya Bryggeriet i Borås",
            "location": "Borås",
            "business": "Tillverkar malt- och läskedrycker",
            "contact": {
                "telegraph": "Nya Bryggeriet, Borås",
                "postgiro": "72009"
            },
            "financials": {
                "employees": {
                    "industriarb": 35
                },
                "annual_production_value": "1,000,000 kr"
            },
            "foundation_year": 1898,
            "director": "Sven Sandwall"
        },
        "4": {
            "name": "Nya Bryggeri- och Mälteri AB. i Västerås",
            "location": "Västerås",
            "business": "Tillverkar malt och maltdrycker samt mineralvatten och läskedrycker (Mineralvattenfabriken Källan)",
            "contact": {
                "phone": [
                    "30039",
                    "30182",
                    "31624"
                ]
            },
            "financials": {
                "employees": {
                    "industriarb": 25
                },
                "annual_production_value": "900,000 kr"
            },
            "foundation_year": 1931,
            "director": "Hugo Anderson"
        },
        "5": {
            "name": "AB. Nya Centralbryggeriet",
            "location": "Linköping",
            "business": "Tillverkar malt-* och läskedrycker, kolsyrat vatten samt malt",
            "contact": {
                "phone": [
                    "22849",
                    "25504"
                ],
                "telegraph": "Centralbryggeriet, Linköping",
                "postgiro": "90380"
            },
            "financials": {
                "employees": {
                    "industriarb": 120
                },
                "annual_production_value": "2,500,000 kr"
            },
            "foundation_year": 1918,
            "director": "Birger Paulson"
        },
        "6": {
            "name": "AB. Nya AB. Chokladfabriken Coody",
            "location": "Malmö",
            "business": "Tillverkar choklad, karameller, kola, drageer och skumartiklar",
            "contact": {
                "office": "Geijersg. 13",
                "phone": [
                    "51305",
                    "51313"
                ],
                "postgiro": "148172"
            },
            "financials": {
                "employees": {
                    "industriarb": 35
                },
                "annual_production_value": "450,000 kr"
            },
            "foundation_year": 1940,
            "director": "R. Dahlquist"
        },
        "7": {
            "name": "Nya AB. Ekmöbler",
            "location": "Virserum",
            "business": "Tillverkar möbler vid fabrik i Virserum (Kalmar l.)",
            "contact": {
                "phone": "79",
                "postgiro": "132810"
            },
            "financials": {
                "employees": {
                    "industriarb": 40
                },
                "annual_production_value": "270,000 kr"
            },
            "foundation_year": 1927,
            "director": "Josef Petersson"
        },
        "8": {
            "name": "AB. Nya AB. Eos",
            "location": "Nässjö",
            "business": "Metallvarufabrik, mek. verkstad, gjuteri, galvaniserings- och förnicklingsan-stalt. Tillverkar elektr. armatur, metallmanufaktur och metallgjutgods; utför metalltryckning, metallpressning m. m.",
            "contact": {
                "phone": "250",
                "postgiro": "30212"
            },
            "financials": {
                "employees": {
                    "industriarb": 60
                },
                "annual_production_value": "133,000 kr"
            }
        }
    }
}