{
    "original": "Wulcan—V äg förbättringar\n\nWulcan, Nitfabriken, Ture Emilsson\n\nSt Co., Anderstorp.\n\nSe Nitfabriken Wulkan, Ture Emilsson\n&amp; Co., Anderstorp.\n\n’Vulcans Tändsticksfabrik,\n\nTidaholm.\n\nSe Jönköpings och Vulcans\nTändsticksfabriks AB., Jönköping.\n\n*Vulcanus, Bergverksbolaget,\n\nBlötberget.\n\nSe Bergverks AB. Vulcanus, Blötberget.\n\n*AB. Vulcanverken, Göteborg.\n\nSe Coronaverken AB.. Göteborg.\n\n’Wulf &amp; Co. AB., Vänersborg.\n\nBolaget arrenderar tegelbruk vid\nTeng-grenstorp (Älvsb. l.) och äger mek.\nverkstad i Vänersborg. Tillverkar mur- och\ntaktegel, dräneringsrör samt släpvagnar\nav alla slag. Bolaget driver såsom\nhuvud-rörelse agenturaffärer och bilimport.\n\nHuvudkontor: Vänersborg. Telegr.-adr.:\nWulf, Vänersborg. Telefon: 1251.\nPostgiro: 84706. Avd.-kontor: Stockholm,\nRoslagsg. 64, telefon: 311550.\n\nAkt.-kap.: 270,000 kr. Antal\nindustriarb.: 100. Årstillv. av tegelvaror: 10 milj.\nst. — Tegelbruket anlagt 1907.\n\nStyrelse: bruksäg. Gunnar Wulf (ordf.),\ning. Ivar Wulf, dir. Kurt Wulf.\n\nVerkst. dir.: Kurt Wulf.\n\nDriftsing.: Ivar Wulf.\n\nKamrer: Gösta Koren.\n\n’yålbackens Tegelbruks; AB.,\n\nÖstersund.\n\nTegelbruk (Vålbackens och Tegellunds\ntegelbruk) vid Brunflo (Jämtl. l.).\nTillverkar murtegel och dräneringsrör.\n\nKontor: Östersund. Telefon: 1385.\nPostgiro: 30737.\n\nAkt.-kap.: 150,000 kr. Antal\nindustriarb.: 80 (under säsong). Årstillv.: 5 milj.\nst. tegelvaror. — Firman etabl. 1901, nuv.\nbolag 1918.\n\nVerkst. dir.: Eric Myrberg.\n\nTegelmäst.: Thure Lindström.\n\nVålbergs Bohinfabrik, Vålberg.\n\nSe öström &amp; Fischer AB., Vålberg.\n\n*Wångmark &amp; Co., Konfektions AB.,\n\nTranås.\n\nSe Konfektions AB. Wångmark &amp; Co.,\nTranås.\n\n’AB. Yårgårda Armaturfabrik,\n\nVårgårda.\n\nArmaturfabrik i Vårgårda^ (Älvsb. l.).\nTillverkar som specialitet sanitetsarmatnr\nför bad- och toalettrum, kök, sjukhus m.\nm. samt armatur för vatten, ånga och gas;\nutför förnickling, förkromning,\nförkopp-ring, förmässning, kadmiering och\noxi-dering.\n\nTelefon: 10, 124 o. 310. Postgiro: 83760.\n\nAkt.-kap.: 225,000 kr. Antal\nindustriarb.: 160. — Firman etabl. 1920, bolag\n1924.\n\nStyrelse o. verkst. dir.: John Bengtson.\n\nVice direktörer: Olof Sjöberg o. Nils\nBake.\n\nDisp.: P. Sölvell.\n\nKontorschef: Harald Olsson.\n\nRitkontorschef: ing. Ch. Nilsson.\n\n’Vårgårda Kvarn, Vårgårda.\n\nSe AB. A. Heyman, Vårgårda.\n\nVårgårda Mekaniska Verkstad,\n\nFilipstad.\n\nMek. verkstad i Filipstad. Tillverkar\nautomobilbult, skruvar och fräsverktyg.\n\nTelegr.-adr.: Verkstaden, Filipstad.\nTelefon: 579 o. 580. Postgiro: 22691.\n\nAntal industriarb.: 45. Tillv.-värde pr\når: 400,000 kr. — Firman etabl. 1919 i\nVårgårda, överflyttades till Filipstad\n1937.\n\nÄgare o. chef: fabr. John Grönberg.\n’Vårgårda Snickerifabrik, Vårgårda.\n\nTillverkar byggnadssnickerier vid\nfabrik i Vårgårda (Älvsb. l.).\n\nTelegr.-adr.: Snickerifabrik, Vårgårda.\nTelefon: 74. Postgiro: 85244. — Antal\nindustriarb.: 30. Tillv.-värde pr år:\n400,000 kr. — Firman etabl. 1920.\n\nÄgare: dir. M. Ahldrén, fabr. Johan\nHaglund, herr Amandus Henriksson o.\nbyggm. Martin Henrikssons sterbhus.\n\n’AB. Vägförbättringar, Stockholm.\n\nUtför väg-, vatten- och brobyggnader,\nvägunderhåll, idrottsplatser,\nterrasserings-arbeten, vägbeläggningar av betong, sten,\nasfalt och tjära, skyddsrum,\nbetongbyggnader, kraftstations- och kanalarbeten,\nindustribyggnader samt vatten- och\navlopp sarbeten. Betongvarufabriker i\nPilgrimstad (Jämtl. l.) och Finja\n(Kristianst. l.).\n\nKontor: Stockholm, Fridhemsg. 15.\nTelegr.-adr.: Vägförbättring, Stockholm.",
    "structured": {
        "firms": [
            {
                "name": "Wulcan",
                "location": "Anderstorp",
                "business": "Nitfabrik",
                "contact": {
                    "telegraph": "Wulcan, Anderstorp",
                    "office": "Nitfabriken, Ture Emilsson & Co., Anderstorp",
                    "postgiro": "Not available",
                    "sales_offices": [
                        {
                            "location": "Stockholm",
                            "phone": "311550"
                        }
                    ]
                },
                "financials": {
                    "capital": "270,000 kr",
                    "employees": {
                        "industriarb": 100
                    },
                    "annual_turnover": "Not available",
                    "annual_production_value": "10 milj. st."
                },
                "foundation_year": 1907,
                "board": [
                    {
                        "name": "Gunnar Wulf",
                        "role": "ordförande"
                    },
                    {
                        "name": "Ivar Wulf",
                        "role": "ingenjör"
                    },
                    {
                        "name": "Kurt Wulf",
                        "role": "direktör"
                    }
                ],
                "manager": "Gunnar Wulf",
                "sales_manager": "Not available",
                "director": "Not available",
                "managing_director": "Kurt Wulf"
            },
            {
                "name": "Vulcanus",
                "location": "Blötberget",
                "business": "Bergverksbolag",
                "original_name": "Bergverks AB. Vulcanus",
                "predecessor": "Not available"
            },
            {
                "name": "Vulcanverken",
                "location": "Göteborg",
                "business": "Not available",
                "original_name": "Coronaverken AB.",
                "predecessor": "Not available"
            },
            {
                "name": "Wulf & Co. AB.",
                "location": "Vänersborg",
                "business": "Tegelbruk arrendator och mekanisk verkstad",
                "contact": {
                    "telegraph": "Wulf, Vänersborg",
                    "office": "Tegelbruk vid Tenggrenstorp (Älvsb. l.) och äger mek. verkstad i Vänersborg",
                    "phone": [
                        "1251"
                    ],
                    "postgiro": "84706",
                    "sales_offices": [
                        {
                            "location": "Stockholm",
                            "phone": "311550"
                        }
                    ]
                },
                "financials": {
                    "capital": "270,000 kr",
                    "employees": {
                        "industriarb": 100
                    },
                    "annual_turnover": "Not available",
                    "annual_production_value": "10 milj. st."
                },
                "foundation_year": 1907,
                "board": [
                    {
                        "name": "Gunnar Wulf",
                        "role": "ordförande"
                    },
                    {
                        "name": "Ivar Wulf",
                        "role": "ingenjör"
                    },
                    {
                        "name": "Kurt Wulf",
                        "role": "direktör"
                    }
                ],
                "manager": "Gunnar Wulf",
                "sales_manager": "Not available",
                "director": "Not available",
                "managing_director": "Kurt Wulf"
            },
            {
                "name": "Yålgårda Armaturfabrik",
                "location": "Vårgårda",
                "business": "Armaturfabrik",
                "contact": {
                    "telegraph": "Not available",
                    "office": "Armaturfabrik i Vårgårda^ (Älvsb. l.)",
                    "phone": [
                        "10",
                        "124",
                        "310"
                    ],
                    "postgiro": "83760"
                },
                "financials": {
                    "capital": "225,000 kr",
                    "employees": {
                        "industriarb": 160
                    },
                    "annual_turnover": "Not available",
                    "annual_production_value": "Not available"
                },
                "foundation_year": 1920,
                "board": [
                    {
                        "name": "John Bengtson",
                        "role": "verkställande direktör"
                    }
                ],
                "manager": "Not available",
                "sales_manager": "Not available",
                "director": "Not available",
                "managing_director": "Not available"
            },
            {
                "name": "Vägförbättringar",
                "location": "Stockholm",
                "business": "Utför väg-, vatten- och brobyggnader",
                "contact": {
                    "telegraph": "Vägförbättring, Stockholm",
                    "office": "Not available",
                    "postgiro": "Not available"
                },
                "financials": {
                    "capital": "Not available",
                    "employees": {
                        "Not available": "Not available"
                    },
                    "annual_turnover": "Not available",
                    "annual_production_value": "Not available"
                },
                "foundation_year": "Not available",
                "board": "Not available",
                "manager": "Not available",
                "sales_manager": "Not available",
                "director": "Not available",
                "managing_director": "Not available"
            }
        ]
    }
}