{
    "original": "S kandinaviska\n\nLomma (Malmöh. l.). Varumärke:\n»Eter-nit».\n\nTelegr.-adr.: Eternitbolaget, Lomma.\nTelefon: Malmö 462500. Postgiro: 72470.\nAvd.-kontor: Stockholm, Kungsg. 32,\ntelefon: 231650; Göteborg, V. Hamng. 24,\ntelefon: 113527. Nederlag i Halmstad,\ntelefon: 3955.\n\nAkt.-kap.: 2,500,000 kr. Antal\nindustriarb.: 400. Tillv.-värde pr år: 8,000,000 kr.\n\n—\tBolaget grundat 1906.\n\nStyrelse: dir. Ernst Wehtje (ordf.),\ndir. Frederik Smidth, dir. Malte Ström.\nVerkst. dir.: Bertil H. Kylberg.\nDisp.: Bernh. Hansson.\nDriftsing.: Erwin de Shårengrad.\nFörsäljn.-chef: Ivar Håkansson.\nKamrer: John Holmberg.\n(Jfr annons nr 16.)\n\nAB. Skandinaviska Etuifabriken,\n\nMalmö.\n\nTillverkar etuier för guld- och\nsilverarbeten, för bestick, optiska och andra\ninstrument, provkoffertar och skyltställ\nsamt kartonnage.\n\nKontor: Ystadsg. 22 A. Telegr.-adr.:\nSkandetui, Malmö. Telefon: 24456 o.\n78056. Postgiro: 38580.\n\nAkt.-kap.: 30,000 kr. Antal\nindustriarb.: 180. Tillv.-värde pr år: 850,000 kr.\n\n—\tFirman etabl. 1894, bolag 1941.\nVerkst. dir.: Ph. Wolf.\n\n*AB. Skandinaviska\nCiödlamp-fabriken, Nyköping.\n\nGlödlampfabrik med glasbruk.\nTillverkar koltråds- och metalltrådslampor.\nVarumärke: »Skandia».\n\nTelegr.-adr. o. telefon: Skandialampan,\nNyköping. Postgiro: 8840. Nederlag: i\nStockholm, Grevg. 7, telefon: 625591,\n615591; i Göteborg, Ingenjörsg. 5,\ntelefon: 117172; i Malmö, Munkg. 1, telefon:\n21484; i Örnsköldsvik, telefon: 2545.\n\nAkt.-kap.: 1,800,000 kr. Antal\nindustriarb.: 285. Tillv.-värde pr år: 5,000,000 kr.\n\n—\tBolaget grundat 1898.\n\nStyrelse: dir. K. Gust. Almén (ordf.),\nborgm. G. Fant, adv. Hans Ihre.\nVerkst. dir.: K. Gust. Almén.\nFabrikschef: P. H. Kok.\n\n^Skandinaviska Crafitindustri AB.,\n\nTrollhättan.\n\nElektriskt grafiteringsverk. Tillverkar\ngrafitpulver och grafitelektroder.\n\nTelegr.-adr.: Skangrafit, Trollhättan.\nTelefon: 10427 o. 12447. Postgiro: 34661.\n\nAkt.-kap.: 1,040,000 kr. Antal\nindustriarb.: 45. — Bolaget grundat 1917.\n\nStyrelse: fil. dr Jakob Forssell (ordf.),\nadv. Axel T. Nilsson, mr A. M.\nWilliamson.\n\nVerkst. dir.: Jakob Forssell.\n\n\"Skandinaviska Granit AB.,\n\nGöteborg.\n\nGranitbrott och stenhuggerier vid flera\nplatser inom Halland och Bohuslän.\nTillverkar gatsten, smågatsten, kantsten,\nbyggnadssten, gravvårdar, kajsten, råblock\noch makadam.\n\nHuvudkontor: Göteborg, Järntorgsg. 12\no. 14. Telegr.-adr.: Stenbolaget, Göteborg.\nTelefon: 135509. Postgiro: 44678.\n\nAkt.-kap.: 1,000,000 kr. Antal\nindustriarb. : 400 (vid inskränkt drift).\nTillv.-värde pr år: 2,000,000 kr. — Bolaget\ngrundat 1905.\n\nStyrelse: bankdir. Ebbe Lundberg, adv.\nElias Markfelt, dir. Garl Sjöstrand.\n\nVerkst. dir.: Carl Sjöstrand.\n\nSkandinaviska Cruv AB., Hedemora.\n\nÄger Bäckgruvan m. fl. gruvor i\nFagersta stad (Västmanl. l.), Vikers gruvor,\nVikersvik, och Nybergs gruvor, Striberg\n(båda i Örebro l.).\n\nHuvudkontor: Hedemora. Telefon: 48\no. 749.\n\nAkt.-kap.: 2,300,000 kr. Antal\nindustriarb.: 30. — Bolaget grundat 1907 under\nnamn Skandinaviska Montanindustri AB.,\nnuv. namn 1941.\n\nStyrelse: disp. Algot Goldkuhl, adv.\nGösta Grönberg.\n\nKamrer: Eric Lind.\n\n\"Skandinaviska Gummi AB.,\n\nViskafors.\n\nGummifabrik vid Viskafors (Älvsb. l.).\nTillverkar automobilringar, transportband\noch drivremmar, gummislangar, galoscher\noch gummiskor, gummiklackar,\ngummisulor, gummi beläggning av valsar för\npappers- och textilindustrierna,\ngummimattor, regnkläder m. m. samt tekn.\ngummivaror.\n\nHuvudkontor: Viskafors. Telegr.-adr.:\nGummi, Borås. Telefon:\n»Gummifabriken», Borås. Postgiro: 30862.\nAvd.»kontor: Stockholm, Sveavägen 83, telefon:\n230795; Göteborg, Norra Hamng. 4,\ntelefon: 175142; Örebro, telefon: 17692.\n\nAkt.-kap.: 430,000 kr. Antal\nindustriarb.: 580. — Bolaget grundat 1890.\n\nStyrelse: kapten Wilhelm Österman\n(ordf.), kamrer Helge Johansson, fru E.\nNilsson, herr Gösta Österman.",
    "structured": {
        "1": {
            "name": "AB. Skandinaviska Lomma (Malmöh. l.)",
            "location": "Lomma (Malmö)",
            "business": "Eternit",
            "contact": {
                "office": "Eternitbolaget, Lomma",
                "phone": [
                    "Malmö 462500"
                ],
                "postgiro": "72470",
                "sales_offices": [
                    {
                        "location": "Stockholm, Kungsg. 32",
                        "phone": "231650"
                    },
                    {
                        "location": "Göteborg, V. Hamng. 24",
                        "phone": "113527"
                    },
                    {
                        "location": "Halmstad",
                        "phone": "3955"
                    }
                ]
            },
            "financials": {
                "capital": "2,500,000 kr",
                "employees": {
                    "industriarb": 400
                },
                "annual_turnover": "8,000,000 kr",
                "annual_production_value": "8,000,000 kr"
            },
            "foundation_year": 1906,
            "board": [
                {
                    "name": "dir. Ernst Wehtje",
                    "role": "ordf."
                },
                {
                    "name": "dir. Frederik Smidth",
                    "role": null
                },
                {
                    "name": "dir. Malte Ström",
                    "role": null
                }
            ]
        },
        "2": {
            "name": "AB. Skandinaviska Etuifabriken, Malmö",
            "location": "Malmö",
            "business": "Etuier för guld- och silverarbeten",
            "products": "Etuier för guld- och silverarbeten, för bestick, optiska och andra instrument, provkoffertar och skyltställ samt kartonnage",
            "contact": {
                "office": "Ystadsg. 22 A",
                "phone": [
                    "Malmö 24456",
                    "Malmö 78056"
                ],
                "postgiro": "38580"
            },
            "financials": {
                "capital": "30,000 kr",
                "employees": {
                    "industriarb": 180
                },
                "annual_turnover": "850,000 kr",
                "annual_production_value": "850,000 kr"
            },
            "foundation_year": 1894,
            "board": [
                {
                    "name": "Verkst. dir. Ph. Wolf",
                    "role": null
                }
            ],
            "corporation_year": 1941
        },
        "3": {
            "name": "AB. Skandinaviska Glödlampfabriken, Nyköping",
            "location": "Nyköping",
            "business": "Glödlampfabrik med glasbruk",
            "products": "Koltråds- och metalltrådslampor",
            "contact": {
                "office": "Nyköping",
                "phone": [
                    "Nyköping",
                    "Nyköping",
                    "Nyköping",
                    "Örnsköldsvik"
                ],
                "postgiro": "8840"
            },
            "financials": {
                "capital": "1,800,000 kr",
                "employees": {
                    "industriarb": 285
                },
                "annual_turnover": "5,000,000 kr",
                "annual_production_value": "5,000,000 kr"
            },
            "foundation_year": 1898,
            "board": [
                {
                    "name": "Verkst. dir. K. Gust. Almén",
                    "role": "ordf."
                },
                {
                    "name": "borgm. G. Fant",
                    "role": null
                },
                {
                    "name": "adv. Hans Ihre",
                    "role": null
                }
            ]
        },
        "4": {
            "name": "AB. Skandinaviska Grafiteringsverk, Trollhättan",
            "location": "Trollhättan",
            "business": "Elektriskt grafiteringsverk",
            "products": "Grafitpulver och grafitelektroder",
            "contact": {
                "office": "Skangrafit, Trollhättan",
                "phone": [
                    "10427",
                    "12447"
                ],
                "postgiro": "34661"
            },
            "financials": {
                "capital": "1,040,000 kr",
                "employees": {
                    "industriarb": 45
                }
            },
            "foundation_year": 1917,
            "board": [
                {
                    "name": "fil. dr Jakob Forssell",
                    "role": "ordf."
                },
                {
                    "name": "adv. Axel T. Nilsson",
                    "role": null
                },
                {
                    "name": "mr A. M. Williamson",
                    "role": null
                }
            ]
        },
        "5": {
            "name": "AB. Skandinaviska Granit AB., Göteborg",
            "location": "Göteborg",
            "business": "Granitbrott och stenhuggerier",
            "products": "Gatsten, smågatsten, kantsten, byggnadssten, gravvårdar, kajsten, råblock och makadam",
            "contact": {
                "office": "Göteborg, Järntorgsg. 12 o. 14",
                "phone": [
                    "Göteborg 135509"
                ],
                "postgiro": "44678"
            },
            "financials": {
                "capital": "1,000,000 kr",
                "employees": {
                    "industriarb": 400
                },
                "annual_turnover": "2,000,000 kr",
                "corporation_year": 1905
            },
            "board": [
                {
                    "name": "bankdir. Ebbe Lundberg",
                    "role": "ordf."
                },
                {
                    "name": "adv. Elias Markfelt",
                    "role": null
                },
                {
                    "name": "dir. Garl Sjöstrand",
                    "role": null
                }
            ]
        },
        "6": {
            "name": "AB. Skandinaviska Cruv AB., Hedemora",
            "location": "Hedemora",
            "business": "Äger Bäckgruvan m. fl. gruvor",
            "contact": {
                "office": "Hedemora",
                "phone": [
                    "Hedemora"
                ]
            },
            "financials": {
                "capital": "2,300,000 kr",
                "employees": {
                    "industriarb": 30
                },
                "corporation_year": 1941
            },
            "board": [
                {
                    "name": "disp. Algot Goldkuhl",
                    "role": null
                },
                {
                    "name": "adv. Gösta Grönberg",
                    "role": null
                }
            ]
        },
        "7": {
            "name": "AB. Skandinaviska Gummi AB., Viskafors",
            "location": "Viskafors",
            "business": "Gummifabrik",
            "products": "Automobilringar, transportband och drivremmar, gummislangar, galoscher och gummiskor, gummiklackar, gummisulor, gummi beläggning av valsar för pappers- och textilindustrierna, gummimattor, regnkläder m. m. samt tekn. gummivaror",
            "contact": {
                "office": "Viskafors",
                "phone": [
                    "Borås"
                ]
            },
            "financials": {
                "capital": "430,000 kr",
                "employees": {
                    "industriarb": 580
                },
                "corporation_year": 1890
            },
            "board": [
                {
                    "name": "kapten Wilhelm Österman",
                    "role": "ordf."
                },
                {
                    "name": "kamrer Helge Johansson",
                    "role": null
                },
                {
                    "name": "fru E. Nilsson",
                    "role": null
                },
                {
                    "name": "herr Gösta Österman",
                    "role": null
                }
            ]
        }
    }
}