{
    "original": "Bröderna\n\nBröderna Erikssons Metallfabrik,\n\nStockholm.\n\nTillverkar belysningsarmatur och\nlampskärmsställningar samt utför\nmetalltryckning och pressningar.\n\nKontor: Tuleg. 19. Telefon: 814011 o.\n314024. Postgiro: 56206. — Antal\nindustriarb.: 34. Tillv.-värde pr år: 470,000\nkr. — Firman etabl. 1919.\n\nÄgare o. chef: fabr. J. Ejnar Eriksson.\n\nBröderna Eriksons Metallgjuteri AB.,\n\nBorlänge.\n\nMetallgjuteri och metallfabrik.\nTillverkar armatur och förgasare till motorer,\nbåtbeslag, rörceller för automobilvärmare,\nkolvämnen av lättmetall m. m. samt\nutför metallgjutgods upp till 500 kg\nstyckevikt.\n\nTelefon: 10501. Postgiro: 26259. —\nAkt.-kap.: 48,500 kr. Antal industriarb.:\n15. Tillv.-värde pr år: 100,000 kr. —\nFirman etabl. 1905, bolag 1944.\n\nVerkst. dir.: ing. Bertil Erikson.\n\n(Jfr annons nr 101.)\n\n* Bröderna Falk &amp; Co., Motala.\n\nManufakturverk. Tillverkar rörskopor,\nspadar och skyfflar. Varumärken: MKH\no. B. F.\n\nTelefon: 157. Postgiro: 26548.\nRepresentanter: AB. Emil Sjögren, Stockholm.\nBryggarg. 6 A, telefon: 111035;\nHalmstads Järnvaru AB., Halmstad, telefon:\n»Järnbolaget»; G. V. Rundström &amp; Co.\nAB., Norrköping, telefon: »Rundströms».\n\nAntal industriarb.: 14. —\nManufakturverket anlagt 1684.\n\nÄgare o. chefer: fabr. Pontus Falk o.\nfabr. Oscar Falk.\n\nAB. Bröderna Flinks\nCranitsten-huggeri i Westervik, Västervik.\n\nGranitbrott i Törnsfalla och\nLoftaham-mar (båda i Kalmar l.), stenhuggeri och\nsliperi i Västervik. Tillverkar som\nspecialitet gravvårdar av svart granit.\n\nHuvudkontor: Västervik. Telegr.-adr.:\nFlinks, Västervik. Telefon: 2. Postgiro:\n73552. Filialer i Stockholm (Enskede)\noch Gävle.\n\nAkt.-kap.: 258,000 kr. Antal\nindustriarb.: 60. Tillv.-värde pr år: 720,000 kr.\n— Firman etabl. 1881, bolas- 1806.\n\nStyrelse: jur. kand. Yngve Flink\n(ordf.), friherrinnan Stina Fleetwood,\narkitekt Albert Flink, fru Anna Flink,\nkamrer P. Westerlund.\n\nVerkst. dir. o. disp.: Yngve Flink.\n\n’Bröderna Fohlströms\nSnickerifabrik, Visby.\n\nTillverkar byggnadssnickerier och\nmöbler.\n\nTelefon: 1420. Postgiro: 189604. —\nArb.-antal: 4. Tillv.-värde pr år: 80,000\nkr. — Firman etabl. 1935.\n\nÄgare o. chefer: fabr. Otto Fohlström\no. fabr. Thure Fohlström.\n\n*Bröderna Forss, Mjölby.\n\n^Mek. verkstäder i Mjölby (Östergötl. l.).\nTillverkar släpvagnar, påhängsvagnar\n(semitrailers), hästvagnar, chassier,\nindustrivagnar samt kärror.\n\nTelegr.-adr.: Brödernaforss, Mjölby.\nTelefon: »Bröderna Forss». Postgiro:\n143055. Repr. i Stockholm: ing. Per\nWer-sén, Artillerig. 89, telefon: 617303.\n\nAntal industriarb.: 70. Tillv.-värde pr\når: 1,500,000 kr. — Firman etabl. 1938.\n\nÄgare o. chefer: disp. Lars-Erik Forss\no. fabr. Ola Forss.\n\n’Bröderna Gustafssons Stenhuggerier,\nAB., Stockholm.\n\nStenhuggerier i Stockholm och Mölnbo\n(Sthlms l.) samt sandstensbrott vid\nVam-lingbo (Gotl. l.), marmorbrott i Mölnbo\noch Glanshammar samt kalkstensbrott i\nAsker (Örebro l.).\n\nTillverkar stenarbeten för\nbyggnadsändamål, gravanordningar, monument m.\nm.. såsom socklar, fasadsten, trappor,\ngolv, väggbeklädnader, öppna spisar,\nornament. gravhällar m. m.\n\nHuvudkontor: Stockholm, Hornsg. 89.\nTelegr.-adr.: Natursten, Stockholm.\nTelefon: 413864 o. 437017. Postgiro: 2757.\nAvd.-kontor: Mölnbo. telefon: 34\n\nAkt.-kap.: 50,000 kr. Antal\nindustriarb.: i Stockholm: 8, i Mölnbo: 28.\nTillv.-värde pr år: 300,000 kr. — Firman\netabl. 1888, bolag 1931.\n\nStyrelse o. verkst. dir.: Torsten\nKum-feldt.\n\n’Bröderna Hallströms Möbelfabrik\n\nAB., Tibro.\n\nTillverkar enrumsmöbler och\nkompletteringsmöbler vid fabrik i Tibro\n(Skarab. l.).\n\nTelefon: 277. — Akt.-kap.: 50.000 kr.\nAntal industriarb.: 25. Tillv.-värde pr år:\n350,000 kr. — Firman etabl. 1936, bolag\n1938.\n\nStyrelse: fabr. Magnus Hallström\n(ordf.), verkm. Håkan Hallström,\nkontorist Sune Hallström.\n\nDisp.: Magnus Hallström.",
    "structured": {
        "firms": [
            {
                "name": "Bröderna Erikssons Metallfabrik",
                "location": "Stockholm",
                "business": "Tillverkar belysningsarmatur och lampskärmsställningar samt utför metalltryckning och pressningar",
                "contact": {
                    "office": "Tuleg. 19",
                    "phone": [
                        "814011",
                        "314024"
                    ],
                    "postgiro": "56206",
                    "head_office": "Stockholm",
                    "contact_offices": [
                        {
                            "location": "Stockholm",
                            "phone": "Unknown"
                        }
                    ]
                },
                "financials": {
                    "capital": "Unknown",
                    "employees": {
                        "Unknown": 34
                    },
                    "annual_turnover": "470,000 kr",
                    "annual_production_value": "Unknown"
                },
                "foundation_year": 1919,
                "owner_and_manager": "fabr. J. Ejnar Eriksson"
            },
            {
                "name": "Bröderna Eriksons Metallgjuteri AB",
                "location": "Borlänge",
                "business": "Metallgjuteri och metallfabrik. Tillverkar armatur och förgasare till motorer, båtbeslag, rörceller för automobilvärmare, kolvämnen av lättmetall m. m. samt utför metallgjutgods upp till 500 kg styckevikt",
                "contact": {
                    "phone": "10501",
                    "postgiro": "26259"
                },
                "financials": {
                    "capital": "48,500 kr",
                    "employees": {
                        "Unknown": 15
                    },
                    "annual_turnover": "100,000 kr",
                    "annual_production_value": "Unknown"
                },
                "foundation_year": 1905,
                "corporation_year": 1944,
                "owner_and_manager": "ing. Bertil Erikson"
            },
            {
                "name": "Bröderna Falk & Co.",
                "location": "Motala",
                "business": "Manufakturverk. Tillverkar rörskopor, spadar och skyfflar",
                "contact": {
                    "phone": "157",
                    "postgiro": "26548",
                    "representatives": [
                        "AB. Emil Sjögren, Stockholm",
                        "Halmstads Järnvaru AB., Halmstad",
                        "G. V. Rundström & Co. AB., Norrköping"
                    ]
                },
                "financials": {
                    "capital": "Unknown",
                    "employees": {
                        "Unknown": 14
                    },
                    "annual_turnover": "Unknown",
                    "annual_production_value": "Unknown"
                },
                "foundation_year": "Anlagt 1684",
                "owner_and_manager": "fabr. Pontus Falk o. fabr. Oscar Falk"
            }
        ]
    }
}