{
    "original": "Fabriks—Facit\n\nFabriks AB. Taicum, Duved.\n\nTillverkar talk för pappers-,\ntakpapps-och gummiindustrin samt tälj stenstegel\nför cellulosaindustrin vid fabriker i\nStrömsund och Nordhallen (båda i Jämtl.\n1.).\n\nKontor: Nordhallen, Duved. Telefon:\nNordhallen 12. Postgiro: 130990. Repr. i\nStockholm: AB. Industrimetoder,\nNorr-landsg. 7—9, telefon: 115661. —\nAkt.-kap.: 60,000 kr. Årsprod.: 3,500 ton talk o.\ntälj stensmjöl, 1,000 ton täljstenstegel. —\nFirman etabl. 1917, bolag 1925.\n\nVerkst. dir.: iur. stud. Curt Weidling\n(Sthlm).\n\nPlatschef: A. Attergaard.\n\n*Fabriks AB. Klas Törnblom,\n\nEskilstuna.\n\nSmidesfabrik. Tillverkar rostfria\nknivar, gafflar och skedar, rostfria\nslaktknivar, rostfria köttkrokar,\ngummitapp-ningsknivar, hovknivar samt\nhovbesticks-knivar, hammare samt ställbara\nespagno-letter (märke: »Magistern G.») och\nkop-pelhakar.\n\nTelefon: 30655. Postgiro: 263000. —\nAkt.-kap.: 62,500 kr. Antal industriarb.:\n25. Tillv.-värde pr år: 300,000 kr. —\nFirman grundad 1807, bolag 1916.\n\nStyrelse: byggm. Ferdinand Malmberg\n(ordf.), disp. Bengt Malmberg, disp. G.\nRidaeus.\n\nDisp.: B. Malmberg.\n\n*Fabriks AB. Victoria, Hälsingborg.\n\nMargarinfabrik med tillverkning av\nbords- och bagerimargarin samt kokos och\nkonstister.\n\nKemisk-tekn. fabrik med tillverkning\nav toalett- och tvättvål, såpa, tvålflingor\nm. fl. kem.-tekniska preparat.\n\nMarsipanfabrik för tillverkning av\nmarsipanvaror.\n\nTelegr.-adr. o. telefon: Victoria,\nHälsingborg. Postgiro: 5052.\n\nAkt.-kap.: 900,000 kr. Antal\nindustriarb.: 60. Tillv.-värde pr år: 10,000,000 kr.\n-— Fabriken anlagd 1905, bolag 1916.\n\nStyrelse: disp. Henry Dunker (ordf.),\ndisp. Ernst Elfgren, disp. Hj. Magnuson.\n\nVerkst. dir.: E. Elfgren.\n\nKamrer: K. Ilaaek.\n\nF ör sal jn.-chef: Ture Ågren.\n\nInhöpschef: Gunnar Gustavsson.\n\nAB. Fabriksprodukter, Hestra.\n\nMek. verkstad i Hestra (Jönköp. l.).\nTillverkar häftapparater, häftklammer,\n\n10\n\nhårklämmor, mekaniska leksaker m. m.\nsamt svagströmselektr. artiklar såsom\nringklockor.\n\nHuvudkontor: Hestra; postbox 74.\nTelefon: 39. Postgiro: 178660.\nFörsäljn.-kontor: Stockholm, Kungsgat. 37.\n\nAkt.-kap.: 30,000 kr. Antal\nindustriarb.: 35. Tillv.-värde pr år: 500,000 kr.\n— Firman etabl. 1939, bolag 1941.\n\nVerkst. dir.: Simon Brick\n(Stockholm).\n\nDisp.: A. Olof Westlund.\n*AB. Fabriksskorsten, Malmö.\n\nUtför fabriksskorstenar,\nångpannein-murningar och ugnsmurningar m. m.\n\nKontor: österg. 19. Telegr.-adr.:\nFabriksskorsten, Malmö. Telefon:\n»Armerad-betong». Postgiro: 37821.\nAvd.-kontor: Stockholm, Stureplan 19, telefon:\n214414; Göteborg, N. Hamng. 18,\ntelefon: 135321; Norrköping, telefon: 24740;\nÖrebro, telefon: 14004; Skövde, telefon:\n1555.\n\nAkt.-kap.: 200.000 kr. Antal\nindustriarb.: 100. — Bolaget grundat 1916.\n\nStyrelse: dir. Harald G. Evers (ordf.),\növering. David Andersson, övering. Hj.\nJ epsson.\n\nVerkst. dir,: H. G. Evers.\n\növering.: Hj. Jepsson.\n\nKamrer: A. Mårde.\n\nAvd.-chefer: i Stockholm: civiling. Bo\nEkelund; i Göteborg: civiling. Sven B.\nAskling; i Norrköping: ing. I. Rustner;\ni Örebro: ing. J. S. Ekhem; i Skövde:\ning. G. Alvemo.\n\n*AB. Facit, Åtvidaberg.\n\nSpecialfabrik för tillverkning av\nräknemaskiner i Åtvidaberg (Östergötl. l.).\nVarumärke: »Facit».\n\nTelegr.-adr.: Facit, Åtvidaberg.\nTelefon: »Industrierna». Postgiro: 72363.\n\nEnsamförsälj. för Sverige: AB.\nÅtvidabergs Industrier (se detta bolag).\nFörsäljningen på utlandet av bolagets\nräknemaskiner och av »Halda» skrivmaskiner\nhandhaves av bolaget i egen regi.\n\nAkt.-kap.: 500,000 kr. Antal\nindustriarb.: 340. — Bolaget, grundat 1922, äges\nav AB. Åtvidabergs Industrier.\n\nStyrelse: jur. dr Axel Roos (ordf.),\ngreve Folke Bernadotte af Visborg, disp.\nElof Ericsson.\n\nVerkst. dir.: Elof Ericsson.\n\nExportchef: L. Jacoby.\n\nTehn. dir.: Albert Engvall.\n\nÖvering.: R. E. Annerén.\n\nKonstruhtionschef: Erik Grip.",
    "structured": {
        "1": {
            "name": "Fabriks—Facit",
            "location": "Duved",
            "business": "Tillverkar talk för pappers-, takpapps-och gummiindustrin samt tälj stenstegel för cellulosaindustrin",
            "contact": {
                "office": "Nordhallen, Duved",
                "phone": [
                    "Nordhallen 12"
                ],
                "postgiro": "130990"
            },
            "financials": {
                "capital": "60,000 kr",
                "annual_turnover": "3,500 ton talk o. tälj stensmjöl, 1,000 ton täljstenstegel"
            },
            "foundation_year": 1917,
            "corporation_year": 1925,
            "board": [
                {
                    "name": "iur. stud. Curt Weidling",
                    "role": "Verkst. dir."
                },
                {
                    "name": "A. Attergaard",
                    "role": "Platschef"
                }
            ]
        },
        "2": {
            "name": "Fabriks AB. Klas Törnblom",
            "location": "Eskilstuna",
            "business": "Smidesfabrik. Tillverkar rostfria knivar, gafflar och skedar, rostfria slaktknivar, rostfria köttkrokar, gummitapp-ningsknivar, hovknivar samt hovbesticks-knivar, hammare samt ställbara espagno-letter (märke: »Magistern G.») och kop-pelhakar",
            "contact": {
                "phone": [
                    "30655"
                ],
                "postgiro": "263000"
            },
            "financials": {
                "capital": "62,500 kr",
                "employees": {
                    "industriarb.": 25
                },
                "annual_production_value": "300,000 kr"
            },
            "foundation_year": 1807,
            "corporation_year": 1916,
            "board": [
                {
                    "name": "byggm. Ferdinand Malmberg",
                    "role": "Styrelse: ordf."
                },
                {
                    "name": "disp. Bengt Malmberg",
                    "role": "Styrelse: disp."
                },
                {
                    "name": "disp. G. Ridaeus",
                    "role": "Disp.: B. Malmberg"
                }
            ]
        },
        "3": {
            "name": "Fabriks AB. Victoria",
            "location": "Hälsingborg",
            "business": "Margarinfabrik med tillverkning av bords- och bagerimargarin samt kokos och konstister. Kemisk-tekn. fabrik med tillverkning av toalett- och tvättvål, såpa, tvålflingor m. fl. kem.-tekniska preparat. Marsipanfabrik för tillverkning av marsipanvaror",
            "contact": {
                "office": "Victoria, Hälsingborg",
                "telegraph": "Victoria, Hälsingborg",
                "phone": [
                    "Victoria, Hälsingborg"
                ],
                "postgiro": "5052"
            },
            "financials": {
                "capital": "900,000 kr",
                "employees": {
                    "industriarb.": 60
                },
                "annual_production_value": "10,000,000 kr"
            },
            "foundation_year": 1905,
            "corporation_year": 1916,
            "board": [
                {
                    "name": "disp. Henry Dunker",
                    "role": "Styrelse: ordf."
                },
                {
                    "name": "disp. Ernst Elfgren",
                    "role": "Styrelse: disp."
                },
                {
                    "name": "disp. Hj. Magnuson",
                    "role": "Styrelse: disp."
                }
            ],
            "manager": "Gunnar Gustavsson",
            "sales_manager": "Ture Ågren"
        },
        "4": {
            "name": "AB. Fabriksprodukter",
            "location": "Hestra",
            "business": "Mek. verkstad i Hestra (Jönköp. l.). Tillverkar häftapparater, häftklammer, hårklämmor, mekaniska leksaker m. m. samt svagströmselektr. artiklar såsom ringklockor",
            "contact": {
                "office": "Hestra",
                "phone": [
                    "39"
                ],
                "postgiro": "178660"
            },
            "financials": {
                "capital": "30,000 kr",
                "employees": {
                    "industriarb.": 35
                },
                "annual_production_value": "500,000 kr"
            },
            "foundation_year": 1939,
            "corporation_year": 1941,
            "board": [
                {
                    "name": "Simon Brick",
                    "role": "Verkst. dir."
                },
                {
                    "name": "A. Olof Westlund",
                    "role": "Disp."
                }
            ]
        },
        "5": {
            "name": "AB. Fabriksskorsten",
            "location": "Malmö",
            "business": "Utför fabriksskorstenar, ångpannein-murningar och ugnsmurningar m. m.",
            "contact": {
                "office": "österg. 19, Malmö",
                "telegraph": "Fabriksskorsten, Malmö",
                "phone": [
                    "»Armerad-betong»"
                ],
                "postgiro": "37821"
            },
            "financials": {
                "capital": "200,000 kr",
                "employees": {
                    "industriarb.": 100
                }
            },
            "corporation_year": 1916,
            "board": [
                {
                    "name": "dir. Harald G. Evers",
                    "role": "Styrelse: ordf."
                },
                {
                    "name": "övering. David Andersson",
                    "role": "Styrelse: övering."
                },
                {
                    "name": "övering. Hj. J epsson",
                    "role": "övering."
                }
            ],
            "manager": "A. Mårde"
        },
        "6": {
            "name": "AB. Facit",
            "location": "Åtvidaberg",
            "business": "Specialfabrik för tillverkning av räknemaskiner i Åtvidaberg (Östergötl. l.). Varumärke: »Facit»",
            "contact": {
                "telegraph": "Facit, Åtvidaberg",
                "phone": [
                    "»Industrierna»"
                ],
                "postgiro": "72363"
            },
            "financials": {
                "capital": "500,000 kr",
                "employees": {
                    "industriarb.": 340
                }
            },
            "foundation_year": 1922,
            "board": [
                {
                    "name": "jur. dr Axel Roos",
                    "role": "Styrelse: ordf."
                },
                {
                    "name": "greve Folke Bernadotte af Visborg",
                    "role": "Styrelse: disp."
                },
                {
                    "name": "disp. Elof Ericsson",
                    "role": "Disp."
                },
                {
                    "name": "L. Jacoby",
                    "role": "Exportchef"
                },
                {
                    "name": "Albert Engvall",
                    "role": "Tehn. dir."
                },
                {
                    "name": "R. E. Annerén",
                    "role": "Övering."
                }
            ]
        }
    }
}