{
    "original": "Gahm—Gamleby\n\nTelefon: 20. — Arb.-antal: 7. —\nFirman etabl. 1928.\n\nÄgare: köpm. Oskar V. Montelius, fru\nA. E. Montelius o. kassör Per Montelius.\n\nChef: O. V. Montelius.\n\n*AB. John A. Gahm, Göteborg.\n\nReseffekt- och lädervarufabrik.\nTillverkar koffertar, kappsäckar, res- och\ndamväskor, portföljer, portmonnäer,\nplånböcker m. m.\n\nKontor: Lindholmen; postadr.:\nGöteborg 9. Telegr.-adr.: Citybags, Göteborg.\nTelefon: 221425. Postgiro: 41871.\n\nAkt.-kap.: 1,200,000 kr. Antal\nindustriarb.: 166. Tillv.-värde pr år: 3,000,000 kr.\n— Firman etabl. 1874, bolag 1907.\n\nStyrelse: dir. Arthur Gahm (ordf.),\nköpm. Carl Olof Anderzon, adv. Edvin\nGidén, dir. Carl Johnsson.\n\nVerkst. dir.: Arthur Gahm.\n\nKamrer: Martin Palmer.\n\n*Henrik Gahns AB., Uppsala.\n\nKem.-tekn. fabrik. Tillverkar tvål,\nsåpa, kosmetiska medel, hårvatten, eau de\nCologne, parfymer, munvatten, bläck\nm. m. Varumärken: »Amykos»,\n»Bor-zita», »Do Do», »Epolan», »Hega»,\n»Maniol», »Farena», »Mitzi», »Watzin»,\n»Nadea», »Christl» m. fl.\n\nHuvudkontor: Uppsala. Telegr.-adr. o.\ntelefon: Gahns, Uppsala. Postgiro: 12642.\nAvd.-kontor: Stockholm, Bryggarg. 17,\ntelefon: 231260; Göteborg. Stampg. 8,\ntelefon: 192690; Malmö, Norreg. 8 A,\ntelefon: 27449 o. 75690.\n\nAkt.-kap.: 1,000,000 kr. Antal\nindustriarb.: 169. Tillv.-värde pr år: 9,800,000 kr.\n— Firman etabl. 1867, bolag 1872.\n\nStyrelse: arkitekt Wolter Gahn (ordf.),\nrevisor John H. Arnberg, dir. Ragnar\nFredrikson, disp. P. Gahn, kapten E. G.\nWersäll.\n\nVerkst. dir.: Ragnar Fredrikson.\n\n*AB. Galco, Stockholm.\n\nSpecialfabrik för plåtpressning.\nTillverkar under märket »Agrippa»\nbrevpärmar och överflyttningspärmar,\nkortpärmar (»Iduns yiscard-Agrippa»),\nhålslag m. m., smörjkoppar (»Conus») för\nflytande smörjmedel, låsmuttrar\n(»Ve-lock»), elektriska lödkolvar samt\nmassartiklar i plåtpressning.\n\nKontor: Gävleg. 12 A. Telegr.-adr.:\nGalco, Stockholm. Telefon: 230365. Postgiro:\n871.\n\nAkt.-kap.: 300 000 kr. Antal\nindustriarb.: 65. Tillv.-värde pr år: 1,200,000 kr.\n— Firman etabl. 1912, nuv. namn och\nbolagsordning 1923.\n\nStyrelse: adv. Harald Dahlin (ordf.),,\ndir. Gustaf Larson, dir. Gust. Winqvist-\n\nVerkst. dir.: Gust. Winqvist*\n\n*Camla Wellpappfabriken AB.,\n\nStockholm.\n\nTillverkar wellpapp i rullar och arky\nwellpappkartonger och wellpappemballage.\n\nKontor: Gasverksvägen. Postadr.:\nStockholm 5. Telegr.-adr.: Wellpapp,.\nStockholm. Telefon: 110138—39—40.\nPostgiro: 4690.\n\nAkt.-kap.: 300,000 kr. Antal\nindustriarb.: 45. — Firman etabl. 1905, bolag\n1939.\n\nStyrelse: fabr. C. T. Norén (ordf.),\ndisp. W. Gauert.\n\nVerkst. dir.: C. T. Norén.\n\nGamlabro AB., Norrköping.\n\nUllspinneri och väveri. Tillverkar\nklädesvaror såsom kamgarnstyger,\nkostymtyger, dofflar, ulstertyger m. m.\n\nTelegr.-adr.: Gamlabro,\nNorrköping-Telefon: 20061. Postgiro: 92420.\n\nAkt.-kap.: 850,000 kr. Antal\nindustriarb.: 100. Tillv.-värde pr år: 1,300,000 kr.\n— Fabriken anlagd 1860, nuv. bolag\ngrundat 1864.\n\nStyrelse: fabr. John Lind (ordf.),\nassessor Anders Lind.\n\nVerkst. dir. o. disp.: John Lind.\n\nGamleby Mek. Verkstad AB.,\n\nGamleby.\n\nTillverkar plåtslagerimaskiner, utför\nbil- och maskinreparationer samt\ninstallationer för värme, vatten, sanitet och\nelektricitet vid verkstad i Gamleby\n(Kalmar l.).\n\nTelefon: 70 o. 370. o Postgiro: 14417.\nEnsamförsälj. för plåtslagerimaskiner:\nLindahl &amp; Nermark AB., Alingsås.\n\nAkt.-kap.: 30,000 kr. Antal\nindustriarb.: 30. Tillv.-värde pr år: 450,000 kr. —\nFirman etabl. 1942.\n\nVerkst. dir.: disp. Valdemar Carlsson^\nKontorschef: Sture Jernström.\n\nGamleby Trävaru AB., Gamleby.\n\nSågverk och hyvleri i Gamleby\n(Kalmar l.). Tillverkar sågade och hyvlade\n\nträvaror samt lådor.\n\n174*",
    "structured": {
        "1": {
            "name": "AB. John A. Gahm, Göteborg",
            "location": "Göteborg",
            "business": "Reseffekt- och lädervarufabrik",
            "products": "Tillverkar koffertar, kappsäckar, res- och damväskor, portföljer, portmonnäer, plånböcker m. m.",
            "contact": {
                "office": "Lindholmen",
                "phone": [
                    "221425"
                ],
                "postgiro": "41871",
                "head_office": "Göteborg 9",
                "telegraph": "Citybags, Göteborg"
            },
            "financials": {
                "capital": "1,200,000 kr",
                "employees": {
                    "industriarb": 166
                },
                "annual_turnover": "3,000,000 kr",
                "annual_production_value": "3,000,000 kr"
            },
            "foundation_year": 1874,
            "corporation_year": 1907,
            "board": [
                {
                    "name": "dir. Arthur Gahm",
                    "role": "ordf."
                },
                {
                    "name": "köpm. Carl Olof Anderzon",
                    "role": ""
                },
                {
                    "name": "adv. Edvin Gidén",
                    "role": ""
                },
                {
                    "name": "dir. Carl Johnsson",
                    "role": ""
                }
            ],
            "owners": [
                "Arthur Gahm"
            ]
        },
        "2": {
            "name": "Henrik Gahns AB., Uppsala",
            "location": "Uppsala",
            "business": "Kem.-tekn. fabrik",
            "products": "Tillverkar tvål, såpa, kosmetiska medel, hårvatten, eau de Cologne, parfymer, munvatten, bläck m. m.",
            "contact": {
                "office": "Uppsala",
                "phone": [
                    "Gahns, Uppsala",
                    "231260"
                ],
                "postgiro": "12642",
                "sales_offices": [
                    {
                        "location": "Stockholm",
                        "phone": "231260"
                    },
                    {
                        "location": "Göteborg",
                        "phone": "192690"
                    },
                    {
                        "location": "Malmö",
                        "phone": "27449 o. 75690"
                    }
                ]
            },
            "financials": {
                "capital": "1,000,000 kr",
                "employees": {
                    "industriarb": 169
                },
                "annual_turnover": "9,800,000 kr",
                "annual_production_value": "9,800,000 kr"
            },
            "foundation_year": 1867,
            "corporation_year": 1872,
            "board": [
                {
                    "name": "arkitekt Wolter Gahn",
                    "role": "ordf."
                },
                {
                    "name": "revisor John H. Arnberg",
                    "role": ""
                },
                {
                    "name": "dir. Ragnar Fredrikson",
                    "role": ""
                },
                {
                    "name": "disp. P. Gahn",
                    "role": ""
                },
                {
                    "name": "kapten E. G. Wersäll",
                    "role": ""
                }
            ],
            "owners": [
                "Ragnar Fredrikson"
            ]
        },
        "3": {
            "name": "AB. Galco, Stockholm",
            "location": "Stockholm",
            "business": "Specialfabrik för plåtpressning",
            "products": "Tillverkar under märket »Agrippa» brevpärmar och överflyttningspärmar, kortpärmar (»Iduns yiscard-Agrippa»), hålslag m. m., smörjkoppar (»Conus») för flytande smörjmedel, låsmuttrar (»Ve-lock»), elektriska lödkolvar samt massartiklar i plåtpressning.",
            "contact": {
                "office": "Gävleg. 12 A",
                "phone": [
                    "230365"
                ],
                "postgiro": "871"
            },
            "financials": {
                "capital": "300,000 kr",
                "employees": {
                    "industriarb": 65
                },
                "annual_turnover": "1,200,000 kr",
                "annual_production_value": "1,200,000 kr"
            },
            "foundation_year": 1912,
            "corporation_year": 1923,
            "board": [
                {
                    "name": "adv. Harald Dahlin",
                    "role": "ordf."
                },
                {
                    "name": "dir. Gustaf Larson",
                    "role": ""
                },
                {
                    "name": "dir. Gust. Winqvist",
                    "role": ""
                }
            ],
            "owners": [
                "Gust. Winqvist"
            ]
        },
        "4": {
            "name": "Camla Wellpappfabriken AB., Stockholm",
            "location": "Stockholm",
            "business": "Tillverkar wellpapp i rullar och arky wellpappkartonger och wellpappemballage."
        },
        "5": {
            "name": "Gamlabro AB., Norrköping",
            "location": "Norrköping",
            "business": "Ullspinneri och väveri",
            "products": "Tillverkar klädesvaror såsom kamgarnstyger, kostymtyger, dofflar, ulstertyger m. m.",
            "contact": {
                "telegraph": "Gamlabro, Norrköping",
                "phone": [
                    "20061"
                ],
                "postgiro": "92420"
            },
            "financials": {
                "capital": "850,000 kr",
                "employees": {
                    "industriarb": 100
                },
                "annual_turnover": "1,300,000 kr",
                "annual_production_value": "1,300,000 kr"
            },
            "corporation_year": 1864,
            "board": [
                {
                    "name": "fabr. John Lind",
                    "role": "ordf."
                },
                {
                    "name": "assessor Anders Lind",
                    "role": ""
                }
            ],
            "owners": [
                "John Lind"
            ]
        },
        "6": {
            "name": "Gamleby Mek. Verkstad AB., Gamleby",
            "location": "Gamleby",
            "business": "Tillverkar plåtslagerimaskiner, utför bil- och maskinreparationer samt installationer för värme, vatten, sanitet och elektricitet vid verkstad i Gamleby (Kalmar l.)",
            "contact": {
                "phone": [
                    "70",
                    "370"
                ],
                "postgiro": "14417"
            },
            "financials": {
                "capital": "30,000 kr",
                "employees": {
                    "industriarb": 30
                },
                "annual_turnover": "450,000 kr"
            },
            "foundation_year": 1942
        },
        "7": {
            "name": "Gamleby Trävaru AB., Gamleby",
            "location": "Gamleby",
            "business": "Sågverk och hyvleri i Gamleby (Kalmar l.)",
            "products": "Tillverkar sågade och hyvlade trävaror samt lådor."
        }
    }
}