{
    "original": "Sängfabriken—Sätra\n\nAkt.-kap.: 50,000 kr. Arb.-antal: 10.\n\n—\tBolaget grundat 1937.\nVerkst. dir.: Gösta Lindström.\n\nDisp. i Bernshammar: Alfred\nGustafson.\n\n\"Säng- &amp; Svarverifabrlken Göta,\n\nForserum.\n\nTillverkar barn- och turistsängar vid\nfabrik i Forserum (Jönköp. l.).\n\nTelegr.-adr.: Göta, Forserum. Telefon:\n66. Postgiro: 94728. — Antal\nindustriarb.: 15. Tillv.-värde pr år: 150,000 kr.\n\n—\tFirman etabl. 1932.\n\nÄgare: fabr. Arvid Sandahls sterbhus.\nKontorschef: fröken Solweig Sandahl.\n\n\"Sängresårfabriken, Skandinaviska,\n\nKarlstad.\n\nSe AB. Skandinaviska\nSängresårfabri-ken, Karlstad.\n\n\"AB. Carl Särenholm,\n\nEskilstuna.\n\nJärn- och metallindustri. Tillverkar\nsom specialitet pressade massartiklar i\njärn och metall såsom »S-krok»,\nskoskydd, slangklämmor, pappersklämmor,\nkabelskor, sockertänger,\nskidbindnings-beslag, skridskor, cykelväxlar (märke:\n»ORK»), hopfällbara järnsängar, krattor,\nhörnskydd, skorstensgaller, ställbara\nespagnoletter, byggnadsbeslag m. m.\n\nTelefon: 30213 o. 31313. Postgiro:\n10802.\n\nAkt.-kap.: 300,000 kr. Antal\nindustriarb.: 125. Tillv.-värde pr år: 1,500,000 kr.\n\n—\tFirman etabl. 1895, bolag 1934.\nStyrelse o. verkst. dir.: Einar\nSärenholm.\n\nDriftsing.: Joel Ågren.\n\nAB. Säters Träförädling, Stockholm.\n\nTräförädlingsfabrik i Säter. Tillverkar\ndalamålade möbler (s. k. dalaslöjd),\nträvita möbler, hyvelbänkar,\nmodellbyggsatser, leksaker, gardinbräden m. m.\n\nKontor: Stockholm, Värtavägen 55.\nTelegr.-adr.: Abalga, Stockholm. Telefon:\n670860. Postgiro: 70966.\n\nAkt.-kap.: 5,000 kr. Antal industriarb.:\n50. Tillv.-värde pr år: 250 000 kr. —\nFirman etabl. 1924, bolag 1945.\nVerkst. dir.: G. Holmqvist.\n\n\"Säters Väveri AB., Säter.\n\nBomull sväveri. färgeri och\nappretur-verk. Tillverkar kulörta bomulls- och\ncell-ullstyger, gardiner och möbeltyger.\n\nTelegr.-adr.: Väveriet, Säter. Telefon:\n61 o. 139. Postgiro: 27754.\n\nAkt.-kap.: 300,300 kr. Antal\nindustriarb.: 90. Tillv.-värde pr år: 1,500,000 kr.\n\n—\tBolaget grundat 1914.\n\nStyrelse: dir. Erik W. Panes (ordf.),\ning. L. Norlander, dir. Thure Öberg, dir.\nArvid öhlin, herr Erik öhlin.\n\nVerkst. dir.: A. öhlin (Stockholm).\nPlatschef: L. Norlander.\n\n\"AB. Säters Yxfabrik, Stockholm.\n\nYxfabrik i Säter. Tillverkar yxor och\nbilor. Varumärke: »Banko».\n\nHuvudkontor och ensamförsälj.: AB.\nOdelberg &amp; Olson. Stockholm. Kungsg.\n4 A. Telegr.-adr. o. telefon: Odelbergolson,\nStockholm. Postgiro: 1408.\nFabrikskontor: Säter. Telegr.-adr.: Yxbolaget. Säter.\nTelefon: Säter 13.\n\nAkt.-kap.: 100,000 kr. Antal\nindustriarb.: 40. Tillv.-värde pr år: 400,000 kr.\n\n—\tBolaget grundat 1906.\n\nStyrelse: bruksdisp. Olof Hjorth (ordf.),\nadv. L. Levy, dir. S. Ponsbach, dir.\nKarl-Erik Tiblom, ing. Olof Tiblom.\nVerkst. dir.: Olof Tiblom.\nDisp. i Säter: Sven-Börje Lundberg.\n\nSäters Ångsågs AB., Säter.\n\nSågverk och hyvleri. Tillverkar sågade\noch hyvlade trävaror samt listverk.\n\nTelefon: 82 o. 282. Postgiro: 130522.\nAkt.-kap.: 120,000 kr. Antal\nindustriarb.: 25. Tillv.-värde pr år: 350,000 kr.\n\n—\tFirman etabl. 1916, bolag 1936.\nDisp.: Folke Isakson.\n\n\"Sätherlund &amp; Krook, Tryckeri AB.,\n\nStockholm.\n\nSe Tryckeri AB. Sätherlund &amp; Krook,\nStockholm.\n\nSätra Bruk AB., Sätrafabriker.\n\nSågverk och elektr. kraftstationer vid\nSätrafabriker (Skarab. l.). Tillverkar\nsågade trävaror samt distribuerar elektr.\nenergi. Bolaget driver såsom huvudrörelse\nskogshantering och lantbruk.\n\nTelegr.-adr.: Sätrabruk, Mariestad.\nTelefon: Ilalna 25. Postgiro: 95618.\n\nAkt.-kap.: 1,400,000 kr. Antal\nindustriarb.: 30. Årstillv.: 500 stds trävaror. —\nBolaget grundat 1932.\n\nStyrelsey o. verkst. dir.: överstelöjtn.\nKnut Stanler (Urshult).\n\nPlatschef: jägmäst. Enar Johansson.",
    "structured": {
        "1": {
            "name": "Sängfabriken—Sätra",
            "location": "Sätra",
            "financials": {
                "capital": "50,000 kr",
                "employees": {
                    "Arb.-antal": 10
                }
            },
            "foundation_year": 1937,
            "director": "Gösta Lindström"
        },
        "2": {
            "name": "Säng- & Svarverifabrlken Göta",
            "location": "Forserum",
            "contact": {
                "telegraph": "Göta, Forserum",
                "phone": [
                    "66"
                ],
                "postgiro": "94728"
            },
            "financials": {
                "employees": {
                    "antal industriarb.": 15
                },
                "annual_turnover": "150,000 kr"
            },
            "foundation_year": 1932,
            "owners": [
                "fabr. Arvid Sandahls sterbhus"
            ],
            "manager": "fröken Solweig Sandahl"
        },
        "3": {
            "name": "AB. Carl Särenholm",
            "location": "Eskilstuna",
            "business": "Järn- och metallindustri",
            "products": "Tryckeri AB. Sätherlund & Krook, Stockholm",
            "contact": {
                "phone": "30213 o. 31313",
                "postgiro": "10802"
            },
            "financials": {
                "capital": "300,000 kr",
                "employees": {
                    "Antal industriarb.": 125
                },
                "annual_turnover": "1,500,000 kr"
            },
            "foundation_year": 1895,
            "corporation_year": 1934,
            "board": [
                {
                    "name": "Einar Särenholm",
                    "role": "Styrelse o. verkst. dir."
                }
            ],
            "director": "Einar Särenholm",
            "managing_director": "Joel Ågren"
        },
        "4": {
            "name": "AB. Säters Träförädling",
            "location": "Stockholm",
            "business": "Träförädlingsfabrik",
            "products": "dalamålade möbler, trävita möbler, hyvelbänkar, modellbyggsatser, leksaker, gardinbräden m. m.",
            "contact": {
                "office": "Stockholm, Värtavägen 55",
                "telegraph": "Abalga, Stockholm",
                "phone": "670860",
                "postgiro": "70966"
            },
            "financials": {
                "capital": "5,000 kr",
                "employees": {
                    "Antal industriarb.": 50
                },
                "annual_turnover": "250,000 kr"
            },
            "foundation_year": 1924,
            "corporation_year": 1945,
            "director": "G. Holmqvist"
        },
        "5": {
            "name": "Säters Väveri AB.",
            "location": "Säter",
            "business": "Bomull sväveri, färgeri och appreturverk",
            "products": "kulörta bomulls- och cellullstyger, gardiner och möbeltyger",
            "contact": {
                "telegraph": "Väveriet, Säter",
                "phone": "61 o. 139",
                "postgiro": "27754"
            },
            "financials": {
                "capital": "300,300 kr",
                "employees": {
                    "Antal industriarb.": 90
                },
                "annual_turnover": "1,500,000 kr"
            },
            "foundation_year": 1914,
            "board": [
                {
                    "name": "Erik W. Panes",
                    "role": "ordf."
                },
                {
                    "name": "L. Norlander",
                    "role": "ing."
                },
                {
                    "name": "Thure Öberg",
                    "role": "dir."
                },
                {
                    "name": "Arvid öhlin",
                    "role": "dir."
                },
                {
                    "name": "Erik öhlin",
                    "role": "herr"
                }
            ],
            "director": "A. öhlin",
            "sales_manager": "L. Norlander"
        },
        "6": {
            "name": "AB. Säters Yxfabrik",
            "location": "Stockholm",
            "business": "Yxfabrik",
            "products": "yxor och bilor",
            "contact": {
                "office": "Kungsg. 4 A",
                "telegraph": "Odelbergolson, Stockholm",
                "phone": "Odelbergolson, Stockholm",
                "postgiro": "1408",
                "factory_office": "Säter",
                "factory_phone": "Säter 13"
            },
            "financials": {
                "capital": "100,000 kr",
                "employees": {
                    "Antal industriarb.": 40
                },
                "annual_turnover": "400,000 kr"
            },
            "foundation_year": 1906,
            "board": [
                {
                    "name": "Olof Hjorth",
                    "role": "bruksdisp. (ordf.)"
                },
                {
                    "name": "L. Levy",
                    "role": "adv."
                },
                {
                    "name": "S. Ponsbach",
                    "role": "dir."
                },
                {
                    "name": "Karl-Erik Tiblom",
                    "role": "dir."
                },
                {
                    "name": "Olof Tiblom",
                    "role": "ing."
                }
            ],
            "director": "Olof Tiblom",
            "sales_manager": "Sven-Börje Lundberg"
        },
        "7": {
            "name": "Säters Ångsågs AB.",
            "location": "Säter",
            "business": "Sågverk och hyvleri",
            "products": "sågade och hyvlade trävaror samt listverk",
            "contact": {
                "phone": "82 o. 282",
                "postgiro": "130522"
            },
            "financials": {
                "capital": "120,000 kr",
                "employees": {
                    "Antal industriarb.": 25
                },
                "annual_turnover": "350,000 kr"
            },
            "foundation_year": 1916,
            "corporation_year": 1936,
            "manager": "Folke Isakson"
        },
        "8": {
            "name": "Sätherlund & Krook, Tryckeri AB.",
            "location": "Stockholm"
        },
        "9": {
            "name": "Sätra Bruk AB.",
            "location": "Sätrafabriker",
            "business": "Sågverk och elektr. kraftstationer",
            "products": "sågade trävaror samt distribuerar elektr. energi",
            "contact": {
                "telegraph": "Sätrabruk, Mariestad",
                "phone": "Ilalna 25",
                "postgiro": "95618"
            },
            "financials": {
                "capital": "1,400,000 kr",
                "employees": {
                    "Antal industriarb.": 30
                },
                "annual_production_value": "500 stds trävaror"
            },
            "foundation_year": 1932,
            "board": [
                {
                    "name": "överstelöjtn. Knut Stanler",
                    "role": "(ordf.)"
                },
                {
                    "name": "ing. L. Norlander"
                },
                {
                    "name": "dir. Thure Öberg"
                },
                {
                    "name": "dir. Arvid öhlin"
                },
                {
                    "name": "herr Erik öhlin"
                }
            ],
            "director": "överstelöjtn. Knut Stanler",
            "manager": "jägmäst. Enar Johansson"
        }
    }
}