{
    "original": "Ä Igarås—A tra dal\n\n1,5 milj. st. tegelvaror. — Firman etabl.\n1905.\n\nÄgare: disp. I. Mannerborn o. fru M.\nKilström.\n\nDisp.: I. Mannerborn.\n\nAlgarås Sågverks AB., Hjo.\n\nTillverkar sågade och hyvlade trävaror\nvid sågverk i Älgarås (Skarab. l.).\n\nKontor: Hjo. Telefon: 603. —\nAkt.-kap.: 100,000 kr. Antal industriarb.: 20.\nÅrstillv.: 1,000 stds trävaror. — Bolaget\ngrundat 1932.\n\nVerkst. dir. o. disp.: Gustaf Törling\n(Hjo).\n\nSågverlcsinsp.: Adolf Backman.\nAB. Älgefors, Forsheda,\n\nFjäderfabrik och meik. verkstad i\nFors-heda (Jönköp. l.). Tillverkar\nspiralfjädrar, fjädrar för korsetter, planschetter,\nremlås, spiralkablar för cykelbelysningar\nm. m. Varumärke: »Älgen».\n\nTelefon: 12. Postgiro: 70796. —\nAkt.-kap.: 70,000 kr. Antal industriarb.: 20.\nTillv.-värde pr år: 210,000 kr. — Firman\netabl. 1921, bolag 1943.\n\nVerkst. dir.: Gunnar J. Petersson.\n\nAlgen, Konfektions AB., Sjuntorp.\n\nSe Konfektions AB. Älgen, Sjuntorp.\n\n*ÄlmhuIts Spikfabrik, Älmhult.\n\nTillverkar trådspik och stift alla slag\nvid fabrik i Älmhult (Kronob. l.).\n\nTelefon: 157. Postgiro: 37185. —\nTillv.-värde pr år: 100,000 kr. — Firman\netabl. 1926.\n\nÄgare o. chef: fabr. Erik S. Forsberg.\n\nÄlvdalens Sågverks AB., Rot.\n\nSågverk, hyvleri, milkolning och\nbilreparationsverkstad i Rot, Älvdalen\n(Kopparb. l.). Tillverkar sågade och hyvlade\nträvaror, slipers, fanértimmer,\ntelegrafstolpar, fyllnadsspån, ribb- och bakved,\nmassaved samt träkol; utför\nbilreparationer.\n\nTelefon: Älvdalen 118. Postgiro: 89495.\n— Akt.-kap.: 150,500 kr. Antal\nindustriarb.: 40. Årstillv.: 1,100 stds trävaror o.\n2,900 kbm. träkol. — Firman etabl. 1932,\nbolag 1945.\n\nDisp.: Viktor Nygren.\n\nKamrer: Gustaf Adolfsson.\n\nÄlvsborg, se Elfsborg.\n\nAB. Älvsereds Syfabrik, Älvsered.\n\nTillverkar herr- och barnkläder vid\nfabrik i Älvsered (Älvsb. l.).\n\nTelefon: 1. Ensamförsälj.: Västgöta\nVäfnads AB., Älvsered, telefon: 1 o. 67,\npostgiro: 34404. — Akt.-kap.: 72,000 kr.\nTillv.-värde pr år: 500,000 kr. — Bolaget,\ngrundat 1910, äges av Västgöta\nVäfnads AB.\n\nDisponenter: Olof Gustafsson o. Sven\nManhem.\n\nAB. Älvsereds Trikåfabrik,\n\nÄlvsered.\n\nTillverkar herrstrumpor vid fabrik i\nÄlvsered (Älvsb. l.). Varumärke: »Elfse».\n\nTelefon: 9. Postgiro: 77165.\nRepresentanter i Stockholm: AB. Hilding\nHedberg, Regeringsg. 9, telefon: 109665, o.\nAlbert Mårtensson, Riddarg. 18, telefon:\n627425.\n\nAkt.-kap.: 25,000 kr. Antal\nindustriarb.: 20. Tillv.-värde pr år: 250,000 kr.\n\n—\tBolaget grundat 1928.\nStyrelse o. disp.: Åke Gustafsson.\n\n*Ängelholms Bryggeri, Ängelholm.\nSe AB. Skånebryggerier, Hälsingborg.\n\n*Ängsfors Snickerifabrikers AB.,\n\nHovslätt.\n\nSnickerifabriker, hyvlerier och sågverk\ni Hovslätt och Månsarp (båda i Jönköp.\n1.). Tillverkar byggnadssnickerier,\nek-inredningar samt hyvlade och sågade\nträvaror.\n\nTelefon: 1 o. 100. Postgiro: 23003.\nAkt.-kap.: 180,000 kr. Antal\nindustriarb.: 60. Tillv.-värde pr år: 800,000 kr.\n\n—\tFirman grundad 1896, bolag 1914.\nStyrelse: disp. J. A. Nyrén (ordf.),\n\ning. Karl Ängfors, ing. Oskar Ängfors.\nDisp.: J. A. Nyrén.\nKontorschef: Oskar Ängfors.\n\nÄtradals Konfektions AB.,\n\nTimmele.\n\nTillverkar ^ herr- och gosskostymer,\ndam- och flickkappor samt trenchcoats\nvid fabrik i Timmele (Älvsb. l.).\n\nTelefon: 154. Postgiro: 143265. —\nAkt.-kap.: 50,000 kr. Antal industriarb.:\n30. Tillv.-värde pr år: 700,000 kr. —\nBolaget grundat 1938.\n\nVerkst. dir. o. disp.: fabr. John\nLars-son.\n\n646*",
    "structured": {
        "1": {
            "name": "Algarås Sågverks AB.",
            "location": "Hjo",
            "business": "Tillverkar sågade och hyvlade trävaror vid sågverk i Älgarås (Skarab. l.)",
            "financials": {
                "capital": "100,000 kr",
                "employees": {
                    "industriarb": 20
                },
                "annual_turnover": "Inte tillgänglig",
                "annual_production_value": "1,000 stds trävaror"
            },
            "foundation_year": 1932,
            "board": {
                "name": "Gustaf Törling",
                "role": "Verkst. dir. o. disp."
            },
            "owners": [
                "I. Mannerborn",
                "M. Kilström"
            ],
            "director": "Gustaf Törling"
        },
        "2": {
            "name": "AB. Älgefors, Forsheda",
            "location": "Forsheda, Jönköp. l.",
            "business": "Tillverkar spiralfjädrar, fjädrar för korsetter, planschetter, remlås, spiralkablar för cykelbelysningar",
            "products": "Varumärke: »Älgen»",
            "contact": {
                "phone": "12",
                "postgiro": "70796"
            },
            "financials": {
                "capital": "70,000 kr",
                "employees": {
                    "industriarb": 20
                },
                "annual_turnover": "Inte tillgänglig",
                "annual_production_value": "210,000 kr"
            },
            "foundation_year": 1921,
            "director": "Gunnar J. Petersson"
        },
        "3": {
            "name": "ÄlmhuIts Spikfabrik, Älmhult",
            "location": "Älmhult, Kronob. l.",
            "business": "Tillverkar trådspik och stift alla slag vid fabrik i Älmhult",
            "contact": {
                "phone": "157",
                "postgiro": "37185"
            },
            "financials": {
                "capital": "Inte tillgänglig",
                "annual_production_value": "100,000 kr"
            },
            "foundation_year": 1926,
            "director": "Erik S. Forsberg"
        },
        "4": {
            "name": "Älvdalens Sågverks AB.",
            "location": "Rot, Älvdalen, Kopparb. l.",
            "business": "Tillverkar sågade och hyvlade trävaror, slipers, fanértimmer, telegrafstolpar, fyllnadsspån, ribb- och bakved, massaved samt träkol; utför bilreparationer",
            "contact": {
                "phone": "Älvdalen 118",
                "postgiro": "89495"
            },
            "financials": {
                "capital": "150,500 kr",
                "employees": {
                    "industriarb": 40
                },
                "annual_turnover": "Inte tillgänglig",
                "annual_production_value": "1,100 stds trävaror o. 2,900 kbm. träkol"
            },
            "foundation_year": 1932,
            "board": {
                "name": "Viktor Nygren",
                "role": "Disp."
            },
            "manager": "Gustaf Adolfsson"
        },
        "5": {
            "name": "AB. Älvsereds Syfabrik",
            "location": "Älvsered, Älvsb. l.",
            "business": "Tillverkar herr- och barnkläder vid fabrik i Älvsered",
            "contact": {
                "phone": "1"
            },
            "financials": {
                "capital": "72,000 kr",
                "annual_production_value": "500,000 kr"
            },
            "director": "Olof Gustafsson"
        },
        "6": {
            "name": "AB. Älvsereds Trikåfabrik",
            "location": "Älvsered, Älvsb. l.",
            "business": "Tillverkar herrstrumpor vid fabrik i Älvsered",
            "products": "Varumärke: »Elfse»",
            "contact": {
                "phone": "9",
                "postgiro": "77165",
                "representatives": [
                    {
                        "location": "Stockholm",
                        "phone": "109665"
                    },
                    {
                        "location": "Stockholm",
                        "phone": "627425"
                    }
                ]
            },
            "financials": {
                "capital": "25,000 kr",
                "employees": {
                    "industriarb": 20
                },
                "annual_production_value": "250,000 kr"
            },
            "director": "Åke Gustafsson"
        },
        "7": {
            "name": "Ängsfors Snickerifabrikers AB.",
            "location": "Hovslätt, Jönköp. l.",
            "business": "Tillverkar byggnadssnickerier, ek-inredningar samt hyvlade och sågade trävaror",
            "contact": {
                "phone": "1 o. 100",
                "postgiro": "23003"
            },
            "financials": {
                "capital": "180,000 kr",
                "employees": {
                    "industriarb": 60
                },
                "annual_production_value": "800,000 kr"
            },
            "foundation_year": 1914,
            "board": {
                "name": "J. A. Nyrén",
                "role": "Styrelse o. disp."
            },
            "manager": "Oskar Ängfors"
        },
        "8": {
            "name": "Ätradals Konfektions AB.",
            "location": "Timmele, Älvsb. l.",
            "business": "Tillverkar ^ herr- och gosskostymer, dam- och flickkappor samt trenchcoats vid fabrik i Timmele",
            "contact": {
                "phone": "154",
                "postgiro": "143265"
            },
            "financials": {
                "capital": "50,000 kr",
                "employees": {
                    "industriarb": 30
                },
                "annual_production_value": "700,000 kr"
            },
            "director": "John Larsson"
        }
    }
}