{
    "original": "Tanneforsm öbler—Tegeborg\n\nsängöverkast, dukar, spetsar, stores m. m.\nvid väveri å Tången, Stockholm.\nVarumärke: »Tången».\n\nPost- o. telegr.-adr.: Tången,\nStockholm. Telefon: 252525. Postgiro: 53052.\n\nAkt.-kap.: 1,000,000 kr. Antal\nindustriarb.: 66.\n\nFirman grundad 1897 under namn AB.\nSkandinaviska Trådgardinfabriken.\n\nStyrelse: dir. Erik A. Gillberg (ordf.),\ndir. Nils Berglöf, adv. Wilhelm Moberg.\n\nVerkst. dir.: Nils Berglöf.\n\nDriftsing.: Verner Lindsjö.\n\n*AB. Tanneforsmöbler, Tannefors.\n\nTillverkar möbler vid fabrik i\nTannefors (Östergötl. l.).\n\nTelefon: Linköping 21297. Postgiro:\n71504.\n\nAkt.-kap.: 41,000 kr. Antal\nindustriarb.: 20. Tillv.-värde pr år: 250,000 kr.\n— Firman etabl. 1912, bolag 1928 under\nnamn AB. Edfeldt &amp; Karlssons\nMöbelfabrik, nuv. namn 1945.\n\nStyrelse: fabr. Anders Edfeldt, disp.\nBertil Edfeldt.\n\nVerkst. dir.: Anders Edfeldt.\n\nDisp.: Bertil Edfeldt.\n\n*AB. Tannin, Västervik.\n\nGarvämnesfabrik, sågverk och kem.\ntekn. fabrik. Tillverkar garvextrakter,\nfurfurol, metanol, beck, cellulosalack,\nbonvax och kallim, ekämnen för\nmöbeltillverkning och byggnadsindustrien,\npar-kettråstav samt tomfat av ek och bok.\n\nTelegr.-adr. o. telefon: Tannin,\nVästervik. Postgiro: 8627. — Akt.-kap.:\n625,000 kr. Antal industriarb.: 205.\nTillv.-värde pr år: 4,900,000 kr. —\nBolaget grundat 1909.\n\nStyrelse: dir. Mauritz Carlson (ordf.),\ndir. Gösta Albin, bankdir. Claes Lindskog.\n\nVerkst. dir.: Gösta Albin.\n\n*Tanto Sockerbruk, Stockholm.\n\nSe Svenska Sockerfabriks AB., Malmö.\n\n\"Tapetfabriks AB. Centrum,\n\nStockholm.\n\nSe AB. Durotapet, Hagaström.\n\n*AB. Tebe Mek. Verkstad,\n\nLindesberg.\n\nTillverkar betongblandare, hästfordon,\nautomobilsläpvagnar, transportvagnar\nsamt lågtrycksångpannor vid mek.\nverkstad i Lindesberg (Örebro l.).\n\nTelefon: 835 o. 836. Postgiro: 130577.\n\nAkt.-kap.: 120,000 kr. Antal\nindustriarb.: 50. Tillv.-värde pr år: 800,000 kr.\n\n—\tFirman etabl. 1936.\n\nStyrelse: dir. Anders Klingberg (ordf.),\nfabr. Theodor Berg, dir. Tore Berg,\nkonsul Wilhelm Berg.\n\nVerkst. dir.: Anders Klingberg.\n\nTeckomatorps Skofabrik AB.,\n\nTeckomatorp.\n\nTillverkar damskodon vid fabrik i\nTeckomatorp (Malmöh. l.). Varumärke:\n» Teckosko»\n\nTelefon: 75. Postgiro: 72687. —\nAkt.-kap.: 75,000 kr. Antal industriarb.: 20.\nTillv.-värde pr år: 250,000 kr. — Firman\netabl. 1920, bolag 1941.\n\nVerkst. dir.: Adrian Nilsson.\n\n*Tefako AB., Stockholm.\n\nDamkonfektionsfabrik. Tillverkar\nklänningar, blusar och kjolar. Bolaget driver\näven engroshandel med damkonfektion av\nfrämmande fabrikat.\n\nKontor: Regeringsg. 45. Telefon:\n103319. Postgiro: 157104.\n\nAkt.-kap.: 35,000 kr. Antal\nindustriarb.: 37. Tillv.-värde pr år: 500,000 kr.\n\n—\tBolaget grundat 1939.\n\nStyrelse o. verkst. dir.: E. Lepiorz.\n\nAB. TefCO, Göteborg.\n\nPappersförädlingsfabrik i Tingstad,\nGöteborg. Tillverkar vaxpapper och\nfruktomslag, hyllpapper,\ndekorationspapper samt vaxduksimitation; förädlar\nalu-rniniumfolio. Varumärke: »Vi to vax».\n\nKontor: Tingstad; postadr.: Box 17,\nGöteborg 1. Telegr.-adr.: Tefcomp,\nGöteborg. Telefon: 224804 o. 221063.\nPostgiro: 40432. Representanter:\nJohannsen &amp; Svensson, Stockholm, Torsg. 75,\ntelefon: 339800; Sixten Torne, Malmö,\nAmiralsg. 14 A, telefon: 15523.\n\nAntal industriarb.: 40. Tillv.-värde pr\når: 800,000 kr. — Bolaget grundat 1934.\n\nVerkst. dir.: Carl Svensson.\n\nDisp.: C.-Å. Willman.\n\n*Tegeborgs Tegelbruk, Knislinge.\n\nTillverkar rött fasadtegel, lättegel,\nbrunnstegel och bjälklagstegel,\nmellanväggsplattor samt dräneringsrör vid\ntegelbruk i Knislinge (Kristianst. l.).\n\nTelefon: 180. — Antal industriarb.:\n12. Årstillv.: 1 milj. st. tegelvaror. —\nTegelbruket anlagt 1878, nuv. firma\netabl. 1912.\n\nÄgare o. chef: fabr. Ture Persson.\n\n707*",
    "structured": {
        "firms": [
            {
                "name": "Tanneforsm öbler—Tegeborg",
                "location": "Tången, Stockholm",
                "business": "sängöverkast, dukar, spetsar, stores m. m. vid väveri",
                "contact": {
                    "office": "Tången, Stockholm",
                    "phone": [
                        "252525"
                    ],
                    "postgiro": "53052"
                },
                "financials": {
                    "capital": "1,000,000 kr",
                    "employees": {
                        "industriarb": 66
                    }
                },
                "foundation_year": 1897,
                "original_name": "AB. Skandinaviska Trådgardinfabriken",
                "board": [
                    {
                        "name": "Erik A. Gillberg",
                        "role": "ordf."
                    },
                    {
                        "name": "Nils Berglöf",
                        "role": "dir."
                    },
                    {
                        "name": "Wilhelm Moberg",
                        "role": "adv."
                    }
                ],
                "director": "Nils Berglöf",
                "managing_director": "Verner Lindsjö"
            },
            {
                "name": "AB. Tanneforsmöbler, Tannefors",
                "location": "Tannefors (Östergötl. l.)",
                "business": "Tillverkar möbler",
                "contact": {
                    "phone": [
                        "Linköping 21297"
                    ],
                    "postgiro": "71504"
                },
                "financials": {
                    "capital": "41,000 kr",
                    "employees": {
                        "industriarb": 20
                    },
                    "annual_production_value": "250,000 kr"
                },
                "foundation_year": 1912,
                "corporation_year": 1928,
                "original_name": "AB. Edfeldt & Karlssons Möbelfabrik",
                "current_name_year": 1945,
                "board": [
                    {
                        "name": "Anders Edfeldt",
                        "role": "fabr."
                    },
                    {
                        "name": "Bertil Edfeldt",
                        "role": "disp."
                    }
                ],
                "director": "Anders Edfeldt"
            },
            {
                "name": "AB. Tannin, Västervik",
                "location": "Tannin, Västervik",
                "business": "Garvämnesfabrik, sågverk och kem. tekn. fabrik",
                "contact": {
                    "phone": "Tannin, Västervik",
                    "postgiro": "8627"
                },
                "financials": {
                    "capital": "625,000 kr",
                    "employees": {
                        "industriarb": 205
                    },
                    "annual_turnover": "4,900,000 kr"
                },
                "foundation_year": 1909,
                "board": [
                    {
                        "name": "Mauritz Carlson",
                        "role": "ordf."
                    },
                    {
                        "name": "Gösta Albin",
                        "role": "dir."
                    },
                    {
                        "name": "Claes Lindskog",
                        "role": "bankdir."
                    }
                ],
                "director": "Gösta Albin"
            },
            {
                "name": "Teckomatorps Skofabrik AB., Teckomatorp",
                "location": "Teckomatorp (Malmöh. l.)",
                "business": "Tillverkar damskodon",
                "contact": {
                    "phone": "75",
                    "postgiro": "72687"
                },
                "financials": {
                    "capital": "75,000 kr",
                    "employees": {
                        "industriarb": 20
                    },
                    "annual_production_value": "250,000 kr"
                },
                "foundation_year": 1920,
                "corporation_year": 1941,
                "director": "Adrian Nilsson"
            },
            {
                "name": "Tefako AB., Stockholm",
                "business": "Damkonfektionsfabrik",
                "contact": {
                    "office": "Regeringsg. 45",
                    "phone": [
                        "103319"
                    ],
                    "postgiro": "157104"
                },
                "financials": {
                    "capital": "35,000 kr",
                    "employees": {
                        "industriarb": 37
                    },
                    "annual_production_value": "500,000 kr"
                },
                "foundation_year": 1939,
                "director": "E. Lepiorz"
            },
            {
                "name": "AB. TefCO, Göteborg",
                "location": "Tingstad, Göteborg",
                "business": "Pappersförädlingsfabrik",
                "contact": {
                    "office": "Tingstad, Göteborg",
                    "phone": [
                        "224804",
                        "221063"
                    ],
                    "postgiro": "40432",
                    "representatives": [
                        {
                            "name": "Johannsen & Svensson",
                            "location": "Stockholm",
                            "phone": "339800"
                        },
                        {
                            "name": "Sixten Torne",
                            "location": "Malmö",
                            "phone": "15523"
                        }
                    ]
                },
                "financials": {
                    "employees": {
                        "industriarb": 40
                    },
                    "annual_production_value": "800,000 kr"
                },
                "foundation_year": 1934,
                "director": "Carl Svensson",
                "managing_director": "C.-Å. Willman"
            },
            {
                "name": "Tegeborgs Tegelbruk, Knislinge",
                "location": "Knislinge (Kristianst. l.)",
                "business": "Tillverkar rött fasadtegel, lättegel, brunnstegel och bjälklagstegel, mellanväggsplattor samt dräneringsrör",
                "contact": {
                    "phone": "180"
                },
                "financials": {
                    "employees": {
                        "industriarb": 12
                    },
                    "annual_production_value": "1 milj. st. tegelvaror"
                },
                "foundation_year": 1912,
                "owner": "fabr. Ture Persson"
            }
        ]
    }
}