{
    "original": "Larsson\n\nLeander Larsson &amp; Co., Malung.\n\nTillverkar skinnbeklädnadsartiklar\nsåsom skinntröjor, -jackor och -rockar,\npälsar, handskar m. m. vid fabrik i Malung\n(Kopparb. l.).\n\nTelegr.-adr.: Lelaco, Malung. Telefon:\n114. Postgiro: 15146. —Antal\nindustriarb.: 12. Tillv.-värde pr år: 140,000 kr.\n— Firman etabl. 1924.\n\nÄgare: ’ fru Anna Larsson o. fabr. P.\nAlbert Olsson.\n\nKontorschef: Herman Josén.\n\n\"AB. L. E. Larsson &amp; Co., Uppsala.\n\nSkofabrik. Tillverkar alla slags\nläderskodon. Varumärke: »Hästen».\n\nTelegr.-adr.: Hästen, Uppsala. Telefon:\n»Larsson &amp; Compani». Postgiro: 23391.\n— Akt.-kap.: 1,500,000 kr. Antal\nindustriarb.: 250. Tillv.-värde pr år: 3,500,000\nkr. — Bolaget grundat 1914.\n\nStyrelse: disp. Arne Larshammar\n(ordf.), dr Elon Jonsson, fru Edla\nLarsson.\n\nVerkst. dir- o. disp.: Arne Larshämmar.\n\nKontorschef: Frans Johansson.\n\nAB. Mats Larsson, Malung.\n\nSkinnklädersfabrik i Malung #\n(Kopparb. l.). Tillverkar handskar,\nskinnkläder och pälsar. Varumärke: »ML».\n\nTelefon: 10. Postgiro: 163377. —\nAkt.-kap.: 50,000 kr. Antal industriarb.: 40.\n— Bolaget grundat 1941.\n\nVerkst. dir.: Erland Lissdaniels.\n\n\"Mauritz Larsson Byggnads AB.,\n\nEskilstuna.\n\nByggnadsentreprenörfirma för\nindustribyggnader, bostads- och affärshus m. m.\n\n* Telefon: 30712 o. 33712. Postgiro:\n80053. — Akt.-kap.: 100,000 kr.\nProd.-värde pr år: 3,000,000 kr. — Firman\netabl. 1913.\n\nStyrelse: byggnadsing. Mauritz\nLarsson (ordf.), byggnadsing. Gunnar\nLarsson.\n\nVerkst. dir.: Mauritz Larsson.\n\nDriftsingenjörer: Gunnar Larsson o.\nKarl Holm.\n\nKamrer: Filip Ericsson.\n\n\"Mikael Larssons Skidfabrik,\n\nHudiksvall.\n\nSe AB. Tallåsens Fabriker, Tallåsen.\n\n21\n\nAB. 0. Larsson &amp; Co., Gävle.\n\nSågverk, hyvleri, listfabrik,\nsnickeri-och skopliggfabrik. Tillverkar sågade och\nhyvlade trävaror^ listverk,\nbyggnadssnickerier, transportabla\nutställningshallar, inredningar, grövre möbler samt\nsko-pligg och pliggband m. m.\n\nTelegr.-adr.: Larco, Gävle. Telefon:\n8090. Postgiro: 70221,\n\nAkt.-kap.: 140,000 kr. Antal\nindustriarb.: 60. — Firman etabl. 1872, bolag\n1908.\n\nStyrelse: ingenjör B. J. Wesström\n(ordf.), adv. Curt Ekdahl, dir. Harald\nSjöström.\n\nVerkst. dir.; Harald Sjöström.\n\nOskar Larsons Smidesverkstad AB.,\n\nStockholm.\n\nSmidesverkstad och grovplåtslageri.\nTillverkar hydroforer,\nvattenreningsfil-ter, värmepannor, byggnad^smiden och\nrörsmiden.\n\nKontor: Gasverksvägen, Hjorthagen.\nTelefon: 118428. Postgiro: 56136.\n\nAkt.-kap.: 80,000 kr. Antal\nindustriarb.: 35. Tillv.-värde pr år: 500,000 kr.\n\n—\tFirman etabl. 1921.\n\nVerkst. dir.: fabr. Oskar Larson.\n\nAB. P. A. Larssons Cjuteri &amp;\nAdu-ceringsverk, Eskilstuna.\n\nTillverkar Ewarts- och stålbultskedjor,\nkättinghjul, elevatorskopor samt vanligt\noch aducerat gjutgods.\n\nTelegr.-adr.: Aducerverk, Eskilstuna.\nTelefon: 30038. Postgiro: 10707.\n\nAkt.-kap.: 232,000 kr. Antal\nindustriarb.: 225. Tillv.-värde pr år: 3,000,000 kr.\n\n—\tFirman etabl. 1889, bolag 1907.\nStyrelse: dir. Per Johansson (ordf.),\n\nfru Karin Johansson, grossh. Elis\nKarlson.\n\nVerkst. dir.: Per Johansson.\nKontorschef: D. Ufer.\n\n\"Ragnar Larson &amp; Co. AB.,\nIngenjörsfirman, Sundsvall.\n\nSe Ingeniörsfirman Ragnar Larson &amp;\nCo. AB., Sundsvall.\n\nÖ. Ernst Larsson, Malung.\n\nSkinnvarufabrik i Malung (Kopparb.\n1.). Tillverkar handskar och skinnkläder.\n\nTelegr.-adr.: öjesernst, Malung.\nTelefon: 125. Postgiro: 74554. — Antal\nindustriarb.: 20. Tillv.-värde pr år: 350,000\nkr. — Firman etabl. 1923.\n\nÄgare o. chef: fabr. ö. Ernst Larsson.\nKontorschef: Hilding Larsson.",
    "structured": {
        "1": {
            "name": "L. E. Larsson & Co.",
            "location": "Malung",
            "business": "Tillverkar skinnbeklädnadsartiklar såsom skinntröjor, -jackor och -rockar, pälsar, handskar m. m.",
            "contact": {
                "telegraph": "Lelaco, Malung",
                "phone": [
                    "114"
                ],
                "postgiro": "15146",
                "factory_office": "Malung (Kopparb. l.)",
                "factory_phone": "10"
            },
            "financials": {
                "capital": "1,500,000 kr",
                "employees": {
                    "industriarb.": 12
                },
                "annual_turnover": "140,000 kr"
            },
            "foundation_year": 1924,
            "owners": [
                "fru Anna Larsson",
                "P. Albert Olsson"
            ],
            "director": "Herman Josén"
        },
        "2": {
            "name": "AB. L. E. Larsson & Co.",
            "location": "Uppsala",
            "business": "Skofabrik. Tillverkar alla slags läderskodon",
            "contact": {
                "telegraph": "Hästen, Uppsala",
                "phone": [
                    "Larsson & Compani"
                ],
                "postgiro": "23391"
            },
            "financials": {
                "capital": "1,500,000 kr",
                "employees": {
                    "industriarb.": 250
                },
                "annual_turnover": "3,500,000 kr"
            },
            "foundation_year": 1914,
            "board": [
                {
                    "name": "disp. Arne Larshammar",
                    "role": "ordf."
                },
                {
                    "name": "dr Elon Jonsson",
                    "role": ""
                },
                {
                    "name": "fru Edla Larsson",
                    "role": ""
                }
            ],
            "director": "Arne Larshämmar",
            "sales_manager": "Frans Johansson"
        },
        "3": {
            "name": "AB. Mats Larsson",
            "location": "Malung",
            "business": "Skinnklädersfabrik",
            "contact": {
                "phone": [
                    "10"
                ],
                "postgiro": "163377"
            },
            "financials": {
                "capital": "50,000 kr",
                "employees": {
                    "industriarb.": 40
                }
            },
            "foundation_year": 1941,
            "director": "Erland Lissdaniels"
        },
        "4": {
            "name": "Mauritz Larsson Byggnads AB.",
            "location": "Eskilstuna",
            "business": "Byggnadsentreprenörfirma för industribyggnader, bostads- och affärshus m. m.",
            "contact": {
                "phone": [
                    "30712",
                    "33712"
                ],
                "postgiro": "80053"
            },
            "financials": {
                "capital": "100,000 kr",
                "annual_turnover": "3,000,000 kr"
            },
            "foundation_year": 1913,
            "board": [
                {
                    "name": "byggnadsing. Mauritz Larsson",
                    "role": "ordf."
                },
                {
                    "name": "byggnadsing. Gunnar Larsson",
                    "role": ""
                }
            ],
            "director": "Mauritz Larsson",
            "sales_manager": "Filip Ericsson"
        },
        "5": {
            "name": "AB. O. Larsson & Co.",
            "location": "Gävle",
            "business": "Sågverk, hyvleri, listfabrik, snickeri-och skopliggfabrik. Tillverkar sågade och hyvlade trävaror, listverk, byggnadssnickerier, transportabla utställningshallar, inredningar, grövre möbler samt sko-pligg och pliggband m. m.",
            "contact": {
                "telegraph": "Larco, Gävle",
                "phone": [
                    "8090"
                ],
                "postgiro": "70221"
            },
            "financials": {
                "capital": "140,000 kr",
                "employees": {
                    "industriarb.": 60
                }
            },
            "foundation_year": 1872,
            "corporation_year": 1908,
            "board": [
                {
                    "name": "ingenjör B. J. Wesström",
                    "role": "ordf."
                },
                {
                    "name": "adv. Curt Ekdahl",
                    "role": ""
                },
                {
                    "name": "dir. Harald Sjöström",
                    "role": ""
                }
            ],
            "director": "Harald Sjöström"
        },
        "6": {
            "name": "Oskar Larsons Smidesverkstad AB.",
            "location": "Stockholm",
            "business": "Smidesverkstad och grovplåtslageri. Tillverkar hydroforer, vattenreningsfil-ter, värmepannor, byggnad^smiden och rörsmiden.",
            "contact": {
                "office": "Gasverksvägen, Hjorthagen",
                "phone": [
                    "118428"
                ],
                "postgiro": "56136"
            },
            "financials": {
                "capital": "80,000 kr",
                "employees": {
                    "industriarb.": 35
                },
                "annual_turnover": "500,000 kr"
            },
            "foundation_year": 1921,
            "director": "fabr. Oskar Larson"
        },
        "7": {
            "name": "AB. P. A. Larssons Gjuteri & Aduceringsverk",
            "location": "Eskilstuna",
            "business": "Tillverkar Ewarts- och stålbultskedjor, kättinghjul, elevatorskopor samt vanligt och aducerat gjutgods.",
            "contact": {
                "telegraph": "Aducerverk, Eskilstuna",
                "phone": [
                    "30038"
                ],
                "postgiro": "10707"
            },
            "financials": {
                "capital": "232,000 kr",
                "employees": {
                    "industriarb.": 225
                },
                "annual_turnover": "3,000,000 kr"
            },
            "foundation_year": 1889,
            "corporation_year": 1907,
            "board": [
                {
                    "name": "dir. Per Johansson",
                    "role": "ordf."
                },
                {
                    "name": "fru Karin Johansson",
                    "role": ""
                },
                {
                    "name": "grossh. Elis Karlson",
                    "role": ""
                }
            ],
            "director": "Per Johansson",
            "manager": "D. Ufer"
        },
        "8": {
            "name": "Ragnar Larson & Co. AB.",
            "location": "Sundsvall",
            "business": "Ingenjörsfirman",
            "description": "Se Ingeniörsfirman Ragnar Larson & Co. AB., Sundsvall.",
            "foundation_year": 0
        },
        "9": {
            "name": "Ö. Ernst Larsson",
            "location": "Malung",
            "business": "Skinnvarufabrik i Malung (Kopparb. 1.). Tillverkar handskar och skinnkläder.",
            "contact": {
                "office": "Hilding Larsson"
            },
            "financials": {
                "capital": "50,000 kr",
                "employees": {
                    "industriarb.": 20
                },
                "annual_turnover": "350,000 kr"
            },
            "foundation_year": 1923,
            "owner": "fabr. ö. Ernst Larsson"
        }
    }
}