{
    "original": "Norrköping—Nörrlandshus\n\n\"AB. Norrköpings Tricotfabrik, Aib.\nWesterholm, Norrköping.\n\nTillverkar trikåunderkläder och\nstrumpor vid fabriker i Norrköping och Mjölby\n’(Strumpfabriks AB. Sphinx).\nVarumärken: »Lamasan», »Westerholms»,\n»Mig-non» o. »Rigolette».\n\nTelegr.-adr.: Tricotf abriken,\nNorrköping. Telefon: 29385. Postgiro: 11095.\nRepresentant i Stockholm: Erik\nLindqvist, Kungsg. 53, telefon: 214104.\n\nAkt.-kap.: 1,300,000 kr. Antal\nindustriarb.: 405, varav i Mjölby 125. Tillv.-värde\npr år: 4,000,000 kr. — Firman etabl. 1894,\nt)olag 1898.\n\nStyrelse: bankdir. Alb. Änder (ordf.),\ndir. Elis Sköld, godsäg. Harald Thalin,\ndisp. Gustaf Westerholm.\n\nVerkst. dir.: Gustaf Westerholm.\n\nKamrer: Bengt Nordell.\n\nNorrköpings Trottoarplattfabrik,\n\nNorrköping.\n\nTillverkar vibrerade\ntrottoarbetongplattor och ånghärdade »Vibro»-block.\n\nTelefon: »Vedcentralen», Norrköping.\nPostgiro: 95707. — Arb.-antal: 10.\nTillv.-värde pr år: 200,000 kr. — Fabriken,\nanlagd 1929, äges av Vedcentralen i\nNorrköping AB.\n\nChef: vakant.\n\n\"Norrköpings Träimport AB.,\n\nNorrköping.\n\nSågverk. Utför sågning av lövträ,\nek-parkettstav, ekfyrkanter, tröskelämnen\noch andra ämnen för möbel- och\nsnickerifabrikation. Bolaget driver såsom\nhuvudrörelse handel med in- och utländska\nträslag samt fanér.\n\nTelegr.-adr.: Träimport, Norrköping.\nTelefon: 23784. Postgiro: 9917.\n\nAkt.-kap.: 100,000 kr. Antal\nindustriarb.: 44. — Firman, etabl. 1923, äges av\nSkandinaviska Träimport AB.\n\nStyrelse: fastighetsdir. Carl\nLand-»qvist (ordf.), dir. Hans Brun, dir. Hans\nTh. Holm.\n\nVerkst. dir.: Hans Bruu (Sthlm).\n\nDisp.: Harald Lundqvist.\n\nAB. Norrköpings Varv &amp; Verkstad,\n\nNorrköping.\n\nVarv och mek. verkstad vid Karlsro,\nNorrköping. Utför fartygsreparationer\nsamt nybyggen av fartyg; tillverkar\njärnkonstruktioner till broar och vägportar,\nräcken och kantskoningar,\nplåtslageri-.arbeten såsom cisterner samt\nmaskinarbeten m. m.\n\nTelefon: 20466 o. 24778. Postgiro:\n84417. — Akt.-kap.: 30,000 kr. Antal\nindustriarb.: 75. Tillv.-värde pr år: 900,000\nkr. — Firman etabl. 1932.\n\nVerkst. dir.: kommendörkapten Olof\nHedenström (Flen).\n\nDriftschef: Edvin Mossberg.\n\n\"AB. Norrköpings Yllefabrik,\n\nNorrköping.\n\nYlleväveri. Tillverkar\nkamgarnsvävna-der och blandyllevaror.\n\nTelefon: 24999. Postgiro: 99107.\n\nAkt.-kap.: 75,000 kr. Antal\nindustriarb.: 20. Tillv.-värde pr år:’ 400,000 kr.\n— Firman etabl. 1935, bolag 1938.\n\nStyrelse: disp. Evert Björkne, disp.\nEric Hylén, disp. Ragnar Öländer.\n\nVerkst. dir.: Eric Hylén.\n\nNorrlands Cementrörfabrik,\n\nSollefteå.\n\nBetongvarufabrik vid övergård,\nSollefteå (Västernorrl. l.). Tillverkar\nbetongrör och andra betongvaror.\n\nTelefon: Sollefteå 380 o. 240. Postgiro:\n75376. — Antal industriarb.: 11.\nTillv.-värde pr år: 200,000 kr. — Firman etabl.\n1916.\n\nÄgare o. chef: disp. Gustaf Lundgren.\n\nAB. Norrlandshus, Ange.\n\nTrähusfabriker i Erikslund (AB.\nErikslunds Ångsåg) (se detta bolag)\n(Västernorrl. l.), i Arvesund (Arvesunds\nSåg-förening u. p. a.) (Jämtl. l.), i Luleå\n(Norrbottens Träförädlings AB.) (se\ndetta bolag), i Bräcke (AB. Bräcke\nTrähusfabrik) (se detta bolag) (Jämtl. l.) och\ni Orrviken (AB. Orrvikens Såg &amp;\nSnickerifabrik) (se detta bolag) (Jämtl. l.).\n\nTillverkar genom anslutna företag\nmonteringsfärdiga trähus samt sågade\noch hyvlade trävaror. Bolaget driver även\nskogshantering samt engroshandel med\nbyggnadsmateriel.\n\nKontor: Ånge. Telefon: 150, 151 o. 205.\nPostgiro: 162022. Exportförsäljn.:\nFörenade Trähusfabriker, Förening u. p. a.,\nStockholm, Kungsg. 39, telefon: 202416.\n\nAkt.-kap.: 55,000 kr. Tillv.-värde pr\når: 3,500,000 kr. — Bolaget grundat 1938.\n\nStyrelse: dir. R. Flygt (ordf.), disp.\nGustaf Lindqvist, förvalt. K. H. Strand,\ndir. Rudolf Strand.\n\nVerkst. dir.: Rudolf Strand, j\n\nFörsäljn.-chef: Helge N. Svensson.\n\nDisponenter: i Erikslund: Gustaf\nLindqvist; i Luleå: Fritz Forsberg; i\nArvesund: Eric Voxlägd; i Bräcke: Adolf\nEricson; i Orrviken: P. O. Viklund.",
    "structured": {
        "SwedishFirms": [
            {
                "name": "AB. Norrköpings Tricotfabrik, Aib. Westerholm, Norrköping.",
                "location": "Norrköping",
                "description": "Tillverkar trikåunderkläder och strumpor vid fabriker i Norrköping och Mjölby (Strumpfabriks AB. Sphinx). Varumärken: »Lamasan», »Westerholms», »Mig-non» o. »Rigolette».",
                "contact": {
                    "office": "Tricotf abriken, Norrköping",
                    "phone": [
                        "29385"
                    ],
                    "postgiro": "11095",
                    "sales_offices": [
                        {
                            "location": "Stockholm",
                            "phone": "214104"
                        }
                    ]
                },
                "financials": {
                    "capital": "1,300,000 kr",
                    "employees": {
                        "total": 405,
                        "Mjölby": 125
                    },
                    "annual_turnover": "4,000,000 kr",
                    "annual_production_value": "4,000,000 kr"
                },
                "foundation_year": 1894,
                "corporation_year": 1898,
                "board": [
                    {
                        "name": "Alb. Änder",
                        "role": "bankdir (ordf.)"
                    },
                    {
                        "name": "Elis Sköld",
                        "role": "dir."
                    },
                    {
                        "name": "Harald Thalin",
                        "role": "godsäg."
                    },
                    {
                        "name": "Gustaf Westerholm",
                        "role": "disp."
                    }
                ],
                "director": "Gustaf Westerholm"
            },
            {
                "name": "Norrköpings Trottoarplattfabrik",
                "location": "Norrköping",
                "description": "Tillverkar vibrerade trottoarbetongplattor och ånghärdade »Vibro»-block.",
                "contact": {
                    "office": "Vedcentralen, Norrköping",
                    "phone": [
                        "Vedcentralen",
                        "Norrköping"
                    ],
                    "postgiro": "95707"
                },
                "financials": {
                    "employees": 10,
                    "annual_production_value": "200,000 kr"
                }
            },
            {
                "name": "AB. Norrköpings Träimport AB.",
                "location": "Norrköping",
                "description": "Sågverk. Utför sågning av lövträ, ek-parkettstav, ekfyrkanter, tröskelämnen och andra ämnen för möbel- och snickerifabrikation. Bolaget driver såsom huvudrörelse handel med in- och utländska träslag samt fanér.",
                "contact": {
                    "office": "Träimport, Norrköping",
                    "phone": [
                        "23784"
                    ],
                    "postgiro": "9917"
                },
                "financials": {
                    "employees": 44
                }
            },
            {
                "name": "AB. Norrköpings Varv & Verkstad",
                "location": "Norrköping",
                "description": "Varv och mek. verkstad vid Karlsro, Norrköping. Utför fartygsreparationer samt nybyggen av fartyg; tillverkar järnkonstruktioner till broar och vägportar, räcken och kantskoningar, plåtslageri-.arbeten såsom cisterner samt maskinarbeten m. m.",
                "contact": {
                    "office": "Karlsro, Norrköping",
                    "phone": [
                        "20466",
                        "24778"
                    ],
                    "postgiro": "84417"
                },
                "financials": {
                    "capital": "30,000 kr",
                    "employees": 75,
                    "annual_turnover": "900,000 kr"
                },
                "corporation_year": 1932,
                "director": "kommendörkapten Olof Hedenström"
            },
            {
                "name": "AB. Norrköpings Yllefabrik",
                "location": "Norrköping",
                "description": "Ylleväveri. Tillverkar kamgarnsvävna-der och blandyllevaror.",
                "contact": {
                    "office": "Norrköping",
                    "phone": [
                        "24999"
                    ],
                    "postgiro": "99107"
                },
                "financials": {
                    "capital": "75,000 kr",
                    "employees": 20,
                    "annual_turnover": "400,000 kr"
                }
            },
            {
                "name": "Norrlands Cementrörfabrik",
                "location": "Sollefteå",
                "description": "Betongvarufabrik vid övergård, Sollefteå (Västernorrl. l.). Tillverkar betongrör och andra betongvaror.",
                "contact": {
                    "office": "Sollefteå",
                    "phone": [
                        "Sollefteå 380",
                        "240"
                    ],
                    "postgiro": "75376"
                },
                "financials": {
                    "employees": 11,
                    "annual_production_value": "200,000 kr"
                }
            },
            {
                "name": "AB. Norrlandshus",
                "location": "Ange",
                "description": "Trähusfabriker i Erikslund (AB. Erikslunds Ångsåg) (Västernorrl. l.), i Arvesund (Arvesunds Såg-förening u. p. a.) (Jämtl. l.), i Luleå (Norrbottens Träförädlings AB.) (se detta bolag), i Bräcke (AB. Bräcke Trähusfabrik) (se detta bolag) (Jämtl. l.) och i Orrviken (AB. Orrvikens Såg & Snickerifabrik) (se detta bolag) (Jämtl. l.). Tillverkar genom anslutna företag monteringsfärdiga trähus samt sågade och hyvlade trävaror.",
                "contact": {
                    "office": "Ånge",
                    "phone": [
                        "150",
                        "151",
                        "205"
                    ],
                    "postgiro": "162022",
                    "sales_offices": [
                        {
                            "location": "Stockholm",
                            "phone": "202416"
                        }
                    ]
                },
                "financials": {
                    "capital": "55,000 kr",
                    "annual_production_value": "3,500,000 kr"
                },
                "foundation_year": 1938,
                "board": [
                    {
                        "name": "R. Flygt",
                        "role": "dir."
                    },
                    {
                        "name": "Gustaf Lindqvist",
                        "role": "disp."
                    },
                    {
                        "name": "K. H. Strand",
                        "role": "förvalt."
                    },
                    {
                        "name": "Rudolf Strand",
                        "role": "dir."
                    }
                ],
                "manager": "Rudolf Strand",
                "sales_manager": "Helge N. Svensson",
                "owners": [
                    "Förenade Trähusfabriker, Förening u. p. a."
                ]
            }
        ]
    }
}