{
    "original": "A rv ika—A ske rsund\n\nSchollin-Borg, stiftsjägm. Eric\nWes-ström, kapten Jan-Erik Ålund.\nVerkst. dir.: Allan Schollin-Borg.\nKontorschef: Erik Rygård.\n\nArvika Ullspinneri &amp; Väfveri AB.,\n\nArvika.\n\nUllspinneri, väveri, färgeri och\nappre-turverk. Tillverkar ullgarner, ylletyger,\nfiltar och plaids samt sovsäckar och tält.\nVarumärken: »Duplex»- o.\n»Triplexfil-ten», »Pånchå»-sovsäck.\n\nTelegr.-adr.: Yllefab, Arvika. Telefon:\n2010—12. Postgiro: 72430. Avd.-kontor:\nStockholm, L:a Ny g. 19. Telefon:\n203529.\n\nAkt.-kap.: 376,500 kr. Antal\nindustriarb.: 200. Tillv.-värde pr år: 2,000,000 kr.\n— Bolaget grundat 1898.\n\nStyrelse: disp. Harald Wallin (ordf.),\ndir. K. Herman Nilsson, fru C.-M.\nWal-lin-Nygren.\n\nDisp.: Harald Wallin.\n\nFörest, f. Stockholmskontoret: Knut\nÅkerlundh.\n\n*AB. Arvika-Verken, Arvika.\n\nGjuteri och mek. verkstäder i Arvika,\nvattenkraftstation vid Perserud, Arvika.\nTillverkar lantbruksmaskiner såsom\nslåt-termaskiner, självbindare, räfsor.\nradså-ningsmaskiner, plogar, potatisupptagare\nm. m. Varumärken: »Herkules»,\n»Triumf», »Radix» o. »Salix».\n\nTelegr.-adr. o. telefon: Arvikaverken.\nArvika. Postgiro: 8484. Ensamförsälj.\nför Sverige: Kullberer &amp; Co. AB..\nKatrineholm, telefon: »Kullbergs», och\nAr-vikaverkens Försäljnings AB.,\nKatrineholm.\n\nAkt.-kap.: 3,000,000 kr. Antal\nindustriarb.: 1,000.\n\nFirman, etabl. 1893, nuv. bolagsform\n1916. har i sig upptagit AB. Gävle\nÅkerredskap. Bolaget äger AB. Joh.\nThermae-nius &amp; Son, Hallsberg. Kullberg &amp; Do.\nAB., ^ Katrineholm, Arvikaverkens\nFörsäljnings AB., Katrineholm, och AB.\nWalla Tröskmaskiner, Katrineholm.\n\nStyrelse: bankdir. Gustaf Söderlund\n(ordf.), dir. Mauritz Carlson, greve\nPontus De la Gardie, landstingsm. Ferdinand\nFredgardh, dir. Carl Kihlgren.\n\nVerkst. dir.: Sven Alwerud.\n\nKontorschef: E. Thorée.\n\növering.: Gustaf Jedeur-Palmgren.\n\nFörsäljn.-chef: And. Odenhall.\n\nInhöpschef: H. Lundevall.\n\nAsarums Classliperi &amp; Spegelfabrik,\nE. Carlsson St Co., Karlshamn.\n\nTillverkar speglar samt glas för\nmobiler och inredningar.\n\nTelefon: 762. Postgiro: 22476. —\nAntal industriarb.: 22. Tillv.-värde pr år:\n250,000 kr. — Firman etabl. 1927.\nChef: fabr. Eric W. Carlsson.\n\n*Asea, Västerås.\n\nSe Allmänna Svenska Elektriska AB.y\nVästerås.\n\n*AB. Asea Svetsmaskiner, Stockholm.\n\nElektromek. verkstad vid N.\nHammarby i Stockholm och elektrodfabrik i\nVästerås.\n\nTillverkar motståndssvetsmaskiner,.\nsvetsautomater, varmstukmaskiner,\nnit-och smidesvärmare, lödmaskiner,\nsvets-transformatorer samt svetselektroder.\nBolaget driver även försäljning av\nsvets-omformare av Aseas tillverkning.\n\nHuvudkontor: Heliosvägen 8—10, N»\nHammarby; postadr.: Stockholm 20.\nTelegr.-adr. o. telefon: Aseasvets,\nStockholm. Postgiro: 57066. Avd.-kontor:\nMalmö, Rejsrementsgr. 52, telefon: 10750\n79380; Sundsvall, telefon: »Asea».\n\nAkt.-kap.: 500,000 kr. Antal\nindustriarb.: 140. — Bolaget, grundat 1938,\ntillhör Asea-koncernen.\n\nStyrelse: dir. Thorsten Ericson (ordf.)»\ndir. Bror Anderson.\n\nVerkst. dir.: Bror Anderson.\nKamrer: Nils Otterström.\nVerkstadschef: E. Granå.\n\n* Asfalt AB., Stockholm.\nSe Nya Asfalt AB., Stockholm.\n\n*Askersunds Bryggeri AB.,\n\nA sker sund.\n\nTillverkar malt, malt- och läskedrycker.\nTelefon: 8. Postgiro: 93816. —\nAkt.-kap.: 180,000 kr. Antal industriarb.: 10.\nTillv.-värde pr år: 300,000 kr. —\nBryggeriet anlagt 1841, bolag 1875.\n\nStyrelse: disp. Fredrik Nilsson (ordf.),,\nfru A. Nilsson, ing. Åke F. Nilsson.\nVerkst. dir.: Fredrik Nilsson.\nDriftsing.: Åke F. Nilsson.\n\n*AB. Askersunds Trikåfabrik,\n\nA sker sund.\n\nTrikå- och syfabrik. Tillverkar\nbom-ulls-, konstsilke- och ylleunderkläder.\n\nTelo*gr.-adr.: Trikåfabriken, Askersund.\nTelefon: 69. Postgiro: 10004,",
    "structured": {
        "1": {
            "name": "Arvika Ullspinneri & Väfveri AB.",
            "location": "Arvika",
            "business": "Ullspinneri and väveri",
            "products": "Ullgarner, ylletyger, filtar, plaids, sovsäckar, tält",
            "contact": {
                "office": "Arvika",
                "phone": [
                    "2010",
                    "2011",
                    "2012"
                ],
                "postgiro": "72430",
                "sales_offices": [
                    {
                        "location": "Stockholm, L:a Ny g. 19",
                        "phone": "203529"
                    }
                ],
                "telegraph": "Yllefab, Arvika"
            },
            "financials": {
                "capital": "376,500 kr",
                "employees": {
                    "industrial": 200
                },
                "annual_turnover": "2,000,000 kr"
            },
            "foundation_year": 1898,
            "board": [
                {
                    "name": "disp. Harald Wallin",
                    "role": "ordf."
                },
                {
                    "name": "dir. K. Herman Nilsson",
                    "role": null
                },
                {
                    "name": "fru C.-M. Wallin-Nygren",
                    "role": null
                }
            ]
        },
        "2": {
            "name": "AB. Arvika-Verken",
            "location": "Arvika",
            "business": "Gjuteri and mek. verkstäder",
            "products": "Lantbruksmaskiner",
            "contact": {
                "office": "Arvika",
                "phone": "Arvikaverken",
                "postgiro": "8484"
            },
            "financials": {
                "capital": "3,000,000 kr",
                "employees": {
                    "industrial": 1000
                }
            },
            "foundation_year": 1893,
            "board": [
                {
                    "name": "bankdir. Gustaf Söderlund",
                    "role": "ordf."
                },
                {
                    "name": "dir. Mauritz Carlson",
                    "role": null
                },
                {
                    "name": "greve Pontus De la Gardie",
                    "role": null
                },
                {
                    "name": "landstingsm. Ferdinand Fredgardh",
                    "role": null
                },
                {
                    "name": "dir. Carl Kihlgren",
                    "role": null
                }
            ]
        },
        "3": {
            "name": "Asarums Classliperi & Spegelfabrik, E. Carlsson & Co.",
            "location": "Karlshamn",
            "business": "Tillverkar speglar samt glas för mobiler and inredningar",
            "contact": {
                "phone": "762",
                "postgiro": "22476"
            },
            "financials": {
                "employees": {
                    "industrial": 22
                },
                "annual_turnover": "250,000 kr"
            },
            "foundation_year": 1927
        },
        "4": {
            "name": "Asea",
            "location": "Västerås",
            "description": "Se Allmänna Svenska Elektriska AB.y Västerås."
        },
        "5": {
            "name": "AB. Asea Svetsmaskiner",
            "location": "Stockholm",
            "description": "Elektromek. verkstad vid N. Hammarby i Stockholm and elektrodfabrik i Västerås.",
            "products": "Motståndssvetsmaskiner, svetsautomater, varmstukmaskiner and more",
            "contact": {
                "office": "Stockholm",
                "phone": "Aseasvets",
                "postgiro": "57066",
                "sales_offices": [
                    {
                        "location": "Malmö, Rejsrementsgr. 52",
                        "phone": "1075079380"
                    },
                    {
                        "location": "Sundsvall",
                        "phone": "Asea"
                    }
                ]
            },
            "financials": {
                "capital": "500,000 kr",
                "employees": {
                    "industrial": 140
                }
            }
        },
        "6": {
            "name": "Askersunds Bryggeri AB.",
            "location": "Askersund",
            "business": "Bryggeriet",
            "products": "Malt, malt- and läskedrycker",
            "contact": {
                "phone": "8",
                "postgiro": "93816"
            },
            "financials": {
                "capital": "180,000 kr",
                "employees": {
                    "industrial": 10
                },
                "annual_turnover": "300,000 kr"
            },
            "foundation_year": 1875
        },
        "7": {
            "name": "AB. Askersunds Trikåfabrik",
            "location": "Askersund",
            "business": "Trikå- and syfabrik",
            "products": "Bom-ulls-, konstsilke- and ylleunderkläder",
            "contact": {
                "phone": "69",
                "postgiro": "10004"
            },
            "foundation_year": 1927
        }
    }
}