{
    "original": "Höglund—Hprle\n\nHöglunds Vagnfabrik, H. Höglund\nA Co., Säffle.\n\nTillverkar omnibuskarosserier för\nlandsvägsbussar vid fabrik i Säffle (Värml. l.).\n\nTelefon: 178 o. 778. Postgiro: 136278.\n— Antal industriarb.: 40. Tillv.-värde pr\når: 500,000 kr. — Firman etabl. 1913.\n\nÄgare: fabr. K. G. Höglunds sterbhus.\n\nChef: fabr. Helge Höglund.\n\n*AB. Kasper Höglund, Stockholm.\n\nByggnad sentreprenörfirma för\nbostads-och affärshus, industribyggnader samt\nför väg- och vattenbyggnadsarbeten,\ntun-nel- och bergrumsanläggningar m. m.\n\nKontor: Drottningg. 27. Telegr.-adr.:\nKasplund, Stockholm. Telefon: 234290.\nPostgiro: 56067. Avd.-kontor: Göteborg,\nKungsg. 28. telefon: 116263—64.\n\nAkt.-kap.: 600,000 kr. Prod.-värde pr\når: c:a 7,000,000 kr. — Firman etabl.\n1889, bolag 1910.\n\nStyrelse: bankdir. Gösta Winbergh\n(ordf.), dir. G. Fredrik Hazén, bankdir.\nSigurd Melin, civiling. Archim\nSkjölde-brand, dir. Bertil Skjöldebrand.\n\nVerkst. dir.: B. Skjöldebrand.\n\nKamrer: Harald Eliaeson.\n\nArbetschef: kapten Gunnar Ekander.\n\nAvd.-chefer: för byggnadsavd.: kapten\nPaul E. östlihn; för vägavd.: ing. Helge\nMattsson.\n\nAvd.-chef i Göteborg.: ing. Harry\nNorén.\n\n* Högoms Tegelbruk, Sundsvall.\n\nSe AB. Kolirnporten-Laurents,\nSundsvall.\n\n*Högs Tegelbruk, Västanhög.\n\nTillverkar murtegel, lättmurtegel,\nhög-poröst murtegel, fasadtegel, brunntegel\noch dräneringsrör vid tegelbruk i Hög,\nVästanhög (Malmöh. l.).\n\nTelefon: Kävlinge 25. Postgiro: 97429.\n\nAntal industriarb.: 25. Årstillv.: 2,5\nmilj. st. tegelvaror. — Firman etabl. 1923.\n\nÄgare o. chef: ing. John Ahlström.\n\nDriftsing.: Thord Ahlström.\n\nHögsby Möbelfabriks AB.,\n\nHögsby.\n\nTillverkar beställningsmöbler vid fabrik\ni Högsby (Kalmar l.).\n\nTelefon: 32. Postgiro: 23756. —\nAkt.-kap.: 72,000 kr. Antal industriarb.: 29.\nTillv.-värde pr år: 155,000 kr. — Firman\ngrundad 1899, bolag 1925.\n\nVerkst. dir. o. disp.: Hjalmar Kullberg.\n\n* Högsby Tegelbruk A Lervarufabrik,\n\nHögsby.\n\nTillverkar taktegel, murtegel och\ndräneringsrör vid tegelbruk i Högsby\n(Kalmar l.).\n\nTelefon: 111. Postgiro: 23084. —\nAntal industriarb.: 22. Årstillv.: 2 milj. st.\ntegelvaror. — Firman etabl. 1921.\n\nÄgare o. chef: disp. Algot Ullman.\n\nKamrer: Filip Ericson.\n\n*Högsjö Maskinfiltfabrik, Högsjö.\n\nSe Schullström &amp; Sjöströms Fabriks\nAB., Högsjö.\n\nCarl Högström, Göteborg.\n\nSe Svenska Konfektionsfabriken, Carl\nHögström AB., Göteborg.\n\n*Einar Höij Cjuteri A Mek. Verkstad,\n\nNybro.\n\nTillverkar beställningsgjutgods\nspeciellt smågjutgods för maskin- och\nbyggnadsindustrin jämte gjutgods för formar\ntill glasbruk, byggnadsgjutgods,\nidrottsredskap, drickeshoar, badrumstillbehör,\ntallriksventiler, vattenlås för tvättställ\noch diskbänkar, handels- och\nsanitetsgjut-gods, ångpanneroster m. m. Varumärke:\n»E. H. N.».\n\nTelefon: 223 o. 523. Postgiro: 20579.\n— Antal industriarb.: 10. Tillv.-värde pr\når: 150,000 kr. — Firman etabl. 1924.\n\nÄgare o. chef: fabr. Einar Höij.\n\n*AB. Hörle Tråd- A Spikfabrik,\n\nMalmö.\n\nTråddrageri och spikfabrik i Hörle\n(Jönköp. l.). Tillverkar blank, glödgad,\ngalvaniserad eller förtent dragen\njärntråd, trådspik, krampor, formstift,\ntagg-tråd samt blank, glödgad, galvaniserad\neller förtent kallvalsad plattråd.\n\nKontor o. ensamförsälj.: Edw. H.\nTho-mée AB., Malmö, Engelbrektsg. 11.\nTelegr.-adr.: Edwin, Malmö. Telefon:\n»Tho-mées järn». Postgiro: 14063.\n\nAkt.-kap.: 200,000 kr. Antal\nindustriarb.: 40. Tillv.-värde pr år: 1,200,000 kr.\n— Bolaget grundat 1918.\n\nStyrelse: konsul Edw. H. Thomée\n(ordf.), fil. lic. iUlan Bäckman.\n\nVerkst. dir.: Allan Bäckman.\n\nPlatschef: John Persson",
    "structured": {
        "1": {
            "name": "Höglunds Vagnfabrik, H. Höglund A Co.",
            "location": "Säffle",
            "business": "Tillverkar omnibuskarosserier för landsvägsbussar",
            "contact": {
                "office": "Fabrik i Säffle (Värml. l.)",
                "phone": [
                    "178",
                    "778"
                ],
                "postgiro": "136278"
            },
            "financials": {
                "capital": null,
                "employees": {
                    "Antal industriarb.": 40
                },
                "annual_turnover": "500,000 kr",
                "annual_production_value": null
            },
            "foundation_year": 1913,
            "current_name_year": null,
            "predecessor": null,
            "original_name": null,
            "corporation_year": null,
            "board": null,
            "owners": [
                "fabr. K. G. Höglunds sterbhus"
            ],
            "director": "fabr. Helge Höglund",
            "managing_director": null,
            "sales_manager": null,
            "manager": null
        },
        "2": {
            "name": "AB. Kasper Höglund",
            "location": "Stockholm",
            "business": "Byggnad sentreprenörfirma för bostads-och affärshus, industribyggnader samt för väg- och vattenbyggnadsarbeten, tun-nel- och bergrumsanläggningar m. m.",
            "contact": {
                "office": "Drottningg. 27",
                "phone": [
                    "234290"
                ],
                "postgiro": "56067",
                "sales_offices": [
                    {
                        "location": "Göteborg",
                        "phone": "116263—64"
                    }
                ],
                "telegraph": "Kasplund, Stockholm"
            },
            "financials": {
                "capital": "600,000 kr",
                "employees": null,
                "annual_turnover": "c:a 7,000,000 kr",
                "annual_production_value": null
            },
            "foundation_year": 1889,
            "current_name_year": 1910,
            "predecessor": null,
            "original_name": null,
            "corporation_year": null,
            "board": [
                {
                    "name": "bankdir. Gösta Winbergh",
                    "role": "(ordf.)"
                },
                {
                    "name": "dir. G. Fredrik Hazén",
                    "role": ""
                },
                {
                    "name": "bankdir. Sigurd Melin",
                    "role": ""
                },
                {
                    "name": "civiling. Archim Skjöldebrand",
                    "role": ""
                },
                {
                    "name": "dir. Bertil Skjöldebrand",
                    "role": ""
                }
            ],
            "owners": null,
            "director": null,
            "managing_director": "B. Skjöldebrand",
            "sales_manager": null,
            "manager": "Harald Eliaeson"
        },
        "3": {
            "name": "Högoms Tegelbruk",
            "location": "Sundsvall",
            "business": null,
            "contact": null,
            "financials": null,
            "foundation_year": null,
            "current_name_year": null,
            "predecessor": "AB. Kolirnporten-Laurents, Sundsvall",
            "original_name": null,
            "corporation_year": null,
            "board": null,
            "owners": null,
            "director": null,
            "managing_director": null,
            "sales_manager": null,
            "manager": null
        },
        "4": {
            "name": "Högs Tegelbruk",
            "location": "Västanhög",
            "business": "Tillverkar murtegel, lättmurtegel, hög-poröst murtegel, fasadtegel, brunntegel och dräneringsrör vid tegelbruk i Hög, Västanhög (Malmöh. l.)",
            "contact": {
                "phone": [
                    "Kävlinge 25"
                ],
                "postgiro": "97429"
            },
            "financials": {
                "capital": null,
                "employees": {
                    "Antal industriarb.": 25
                },
                "annual_turnover": null,
                "annual_production_value": "2,5 milj. st. tegelvaror"
            },
            "foundation_year": 1923,
            "current_name_year": null,
            "predecessor": null,
            "original_name": null,
            "corporation_year": null,
            "board": null,
            "owners": [
                "ing. John Ahlström"
            ],
            "director": "ing. John Ahlström",
            "managing_director": "Thord Ahlström",
            "sales_manager": null,
            "manager": null
        },
        "5": {
            "name": "Högsby Möbelfabriks AB.",
            "location": "Högsby",
            "business": "Tillverkar beställningsmöbler",
            "contact": {
                "phone": [
                    "32"
                ],
                "postgiro": "23756"
            },
            "financials": {
                "capital": "72,000 kr",
                "employees": {
                    "Antal industriarb.": 29
                },
                "annual_turnover": "155,000 kr",
                "annual_production_value": null
            },
            "foundation_year": 1899,
            "current_name_year": 1925,
            "predecessor": null,
            "original_name": null,
            "corporation_year": null,
            "board": null,
            "owners": null,
            "director": null,
            "managing_director": "Hjalmar Kullberg",
            "sales_manager": null,
            "manager": null
        },
        "6": {
            "name": "Högsby Tegelbruk A Lervarufabrik",
            "location": "Högsby",
            "business": "Tillverkar taktegel, murtegel och dräneringsrör vid tegelbruk i Högsby (Kalmar l.)",
            "contact": {
                "phone": [
                    "111"
                ],
                "postgiro": "23084"
            },
            "financials": {
                "capital": null,
                "employees": {
                    "Antal industriarb.": 22
                },
                "annual_turnover": null,
                "annual_production_value": "2 milj. st. tegelvaror"
            },
            "foundation_year": 1921,
            "current_name_year": null,
            "predecessor": null,
            "original_name": null,
            "corporation_year": null,
            "board": null,
            "owners": null,
            "director": "disp. Algot Ullman",
            "managing_director": null,
            "sales_manager": null,
            "manager": "Filip Ericson"
        },
        "7": {
            "name": "Högsjö Maskinfiltfabrik",
            "location": "Högsjö",
            "business": "Se Schullström & Sjöströms Fabriks AB.",
            "contact": null,
            "financials": null,
            "foundation_year": null,
            "current_name_year": null,
            "predecessor": null,
            "original_name": null,
            "corporation_year": null,
            "board": null,
            "owners": null,
            "director": null,
            "managing_director": null,
            "sales_manager": null,
            "manager": null
        },
        "8": {
            "name": "Carl Högström",
            "location": "Göteborg",
            "business": "Se Svenska Konfektionsfabriken, Carl Högström AB.",
            "contact": null,
            "financials": null,
            "foundation_year": null,
            "current_name_year": null,
            "predecessor": null,
            "original_name": null,
            "corporation_year": null,
            "board": null,
            "owners": null,
            "director": null,
            "managing_director": null,
            "sales_manager": null,
            "manager": null
        },
        "9": {
            "name": "Einar Höij Cjuteri A Mek. Verkstad",
            "location": "Nybro",
            "business": "Tillverkar beställningsgjutgods speciellt smågjutgods för maskin- och byggnadsindustrin",
            "contact": {
                "phone": [
                    "223",
                    "523"
                ],
                "postgiro": "20579"
            },
            "financials": {
                "capital": null,
                "employees": {
                    "Antal industriarb.": 10
                },
                "annual_turnover": "150,000 kr",
                "annual_production_value": null
            },
            "foundation_year": 1924,
            "current_name_year": null,
            "predecessor": null,
            "original_name": null,
            "corporation_year": null,
            "board": null,
            "owners": null,
            "director": "fabr. Einar Höij",
            "managing_director": null,
            "sales_manager": null,
            "manager": null
        },
        "10": {
            "name": "AB. Hörle Tråd- A Spikfabrik",
            "location": "Malmö",
            "business": "Tråddrageri och spikfabrik i Hörle (Jönköp. l.)",
            "contact": {
                "office": "kallvalsad plattråd",
                "phone": [
                    "»Tho-mées järn»"
                ],
                "postgiro": "14063",
                "sales_offices": [
                    {
                        "location": "Malmö",
                        "phone": "Engelbrektsg. 11"
                    }
                ],
                "telegraph": "Edwin, Malmö"
            },
            "financials": {
                "capital": "200,000 kr",
                "employees": {
                    "Antal industriarb.": 40
                },
                "annual_turnover": "1,200,000 kr",
                "annual_production_value": null
            },
            "foundation_year": null,
            "current_name_year": 1918,
            "predecessor": null,
            "original_name": null,
            "corporation_year": null,
            "board": [
                {
                    "name": "konsul Edw. H. Thomée",
                    "role": "(ordf.)"
                },
                {
                    "name": "fil. lic. iUlan Bäckman",
                    "role": ""
                }
            ],
            "owners": null,
            "director": null,
            "managing_director": "Allan Bäckman",
            "sales_manager": null,
            "manager": "John Persson"
        }
    }
}