{
    "original": "Wäse—Västervik\n\nAB. Wäs© Gryn ver k, Väse.\n\nKvarn och sågverk vid Väse (Värml.\n1.)-Tillverkar havregryn och havremjöl samt\nsågade trävaror. Firman driver även\nengroshandel med foder och spannmål.\n\nTelefon: 7. Postgiro: 6750.\n\nAkt.-kap.: 175,000 kr. Arb.-antal: 12.\nTillv.-värde pr år: 840,000 kr. — Firman\netabl. 1898, bolag 1921.\n\nVerkst. dir.: S. W. Hidén.\n\n*Väsk-Fabriks AB., Stockholm.\n\nTillverkar damväskor och necessärer.\n\nKontor: N:a Stationsg. 79—81.\nTele-gr.-adr.: Lederfab, Stockholm. Telefon:\n331104. Postgiro: 4667.\n\nAkt.-kap.: 25,000 kr. Antal\nindustriarb.: 65. Tillv.-värde pr år: 600,000 kr.\n— Bolaget grundat 1934.\n\nStyrelse: disp. N. Adlerstam, fru R.\nHerzog, dir. L. M. Joseph.\n\nVerkst. dir.: L. M. Joseph.\n\nVäskindustri, Andersson &amp;\nJohansson, Göteborg.\n\nTillverkar damväskor.\n\nKontor: Sänkverksg. 1. Telefon: 142367\no. 125969. Postgiro: 43215. Repr. i\nStockholm: John Lindholm. Walling. 37,\ntelefon: 203287.\n\nAntal industriarb.: 70. Tillv.-värde pr\når: 1,500,000 kr. — Firman etabl. 1932.\n\nÄgare o. chefer: fabr. Knut R.\nAndersson o. fabr. Verner Johansson.\n\nVästanfors Smidesfabrik, Västan-fors.\n\nTillverkar handredskap för lantbruk\noch för skogs- och cellulosaindustrien\nsamt cykelställ; utför smides-,\nsvetsnings-, plåt- och mekaniska arbeten.\n\nTelefoner: 40410 o. 40798. Postgiro:\n173311. — Antal industriarb.: 45.\nTillv.-värde pr år: 500,000 kr. — Firman etabl.\n1928.\n\nÄgare o. chef: ing. Jae. E. Jacobsson.\n\"Västerbo Tegelbruk, Broddbo.\n\nTillverkar tak- och murtegel samt\ndräneringsrör vid tegelbruk i Västerbo,\nBroddbo (Västmanl. l.).\n\nTelefon: Norrvad 13. — Antal\nindustriarb.: 7. Årstillv.: 0,3 milj. st.\ntegelvaror. — Tegelbruket anlagt 1874.\n\nÄgare o. chef: tegelbruksäg. Axel\nHolmgren.\n\n\"AB. Västergötlands Förenade\nKalkindustrier, Falköping.\n\nKalkstensbrott och kalkugnar. Bolaget\nbryter kalksten och bränner kalk för jord-\n\nbruks-, murbruks- och kem.-tekn. behov\nvid Berga och Rössberga Kalkbruk,\nValtorp, Ulunda Kalkbruk, Värnhem,\nHag-gårdens Kalkbruk, Kinnemalma, Kavlås\nKalkbruk, Ekedalen samt Uddagårdens\nKalkbruk, Falköping (samtl. i Skarab. l.) ;\ntillverkar plattor (»Margaretaplattan»)\nför trädgårdsgångar och terrassplaner\nsamt kalksten för trädgårdsarbeten såsom\nmurar, trappsteg m. m. Bolaget idkar\njämväl jordbruk.\n\nTelegr.-adr.: Kalkindustrien,\nFalköping. Telefon: 283. Postgiro: 24242.\nEn-samförsälj. för bränd kalk: Mellersta\nSveriges Kalkbruks Centralförening m. b.\np. a., Falköping.\n\nAkt.-kap.: 1,575,000 kr. Antal\nindustriarb.: 230. — Bolaget grundat 1918.\n\nStyrelse: adv. E. D. Halbert (ordf.),\ndir. G. W. Nymberg, dir. J. E.\nThorse-lius.\n\nVerkst. dir.: G. W. Nymberg.\n\nKontors- o. försäljn.-chef: H.\nSunde-lius.\n\n\"Västergötlands Yllefabriks AB.,\n\nTidan.\n\nSe Svenska Yllekoncernen, AB., Tidan.\n\n\"Västerviks Bryggeri, Västervik.\n\nSe AB. Nya Centralbryggeriet,\nLinkö-köping.\n\n\"AB. Västerviks Motorfabrik,\n\nVästervik.\n\nTillverkar råoljemotorer och\nautomatiska smörjapparater; utför mek.\nverkstadsarbeten och maskinreparationer.\n\nTelefon: 1821. Postgiro: 30290.\n\nAkt.-kap.: 90,000 kr. Antal\nindustriarb.: 30. Tillv.-värde pr år: 300,000 kr.\n\nFirman etabl. 1910, bolag 1936 under\nnamn AB. Bröderna Nilssons Mek.\nVerkstad, ombildad 1941, nuv. namn 1946.\n\nVerkst. dir.: Bror Edberg.\n\nVästervik.\n\n\"Westerviks Pappersbruks AB.,\n\nVästervik.\n\nPapp- och kartongfabrik. Tillverkar vit\noch brun trämassepapp, gråpapp,\ntest-liner, kraftliner och chromoersatz.\n\nTelegr.-adr.: Pappbruket, Västervik.\nTelefon: »Pappersbruket».\n\nEnsamförsäljare för Sverige:\nBjörckan-der &gt;&amp; Co. AB., Stockholm, telefon:\n231655; Göteborg, telefon: 170150;\nMalmö, telefon: 14291.",
    "structured": {
        "firms": [
            {
                "name": "AB. Wäs© Gryn ver k",
                "location": "Väse",
                "business": "Kvarn och sågverk",
                "products": "Tillverkar havregryn och havremjöl samt sågade trävaror. Firman driver även engroshandel med foder och spannmål.",
                "contact": {
                    "office": "Väse",
                    "phone": [
                        "7"
                    ],
                    "postgiro": "6750"
                },
                "financials": {
                    "capital": "175,000 kr",
                    "employees": {
                        "Arb.-antal": 12
                    },
                    "annual_turnover": "840,000 kr",
                    "annual_production_value": "840,000 kr"
                },
                "foundation_year": 1898,
                "corporation_year": 1921,
                "director": "S. W. Hidén"
            },
            {
                "name": "Väsk-Fabriks AB.",
                "location": "Stockholm",
                "business": "Tillverkar damväskor och necessärer.",
                "contact": {
                    "office": "N:a Stationsg. 79—81",
                    "phone": "331104",
                    "postgiro": "4667"
                },
                "financials": {
                    "capital": "25,000 kr",
                    "employees": {
                        "Antal industriarb.": 65
                    },
                    "annual_production_value": "600,000 kr"
                },
                "foundation_year": 1934,
                "board": [
                    {
                        "name": "disp. N. Adlerstam",
                        "role": "fru R. Herzog"
                    },
                    {
                        "name": "dir. L. M. Joseph"
                    }
                ],
                "director": "L. M. Joseph"
            },
            {
                "name": "Väskindustri, Andersson & Johansson",
                "location": "Göteborg",
                "business": "Tillverkar damväskor.",
                "contact": {
                    "office": "Sänkverksg. 1",
                    "phone": [
                        "142367",
                        "125969"
                    ],
                    "postgiro": "43215",
                    "sales_offices": [
                        {
                            "location": "Stockholm",
                            "phone": "203287"
                        }
                    ]
                },
                "financials": {
                    "employees": {
                        "Antal industriarb.": 70
                    },
                    "annual_production_value": "1,500,000 kr"
                },
                "foundation_year": 1932,
                "owners": [
                    "fabr. Knut R. Andersson",
                    "fabr. Verner Johansson"
                ]
            },
            {
                "name": "Västanfors Smidesfabrik",
                "location": "Västanfors",
                "business": "Tillverkar handredskap för lantbruk och för skogs- och cellulosaindustrien samt cykelställ; utför smides-, svetsnings-, plåt- och mekaniska arbeten.",
                "contact": {
                    "phone": [
                        "40410",
                        "40798"
                    ],
                    "postgiro": "173311"
                },
                "financials": {
                    "employees": {
                        "Antal industriarb.": 45
                    },
                    "annual_production_value": "500,000 kr"
                },
                "foundation_year": 1928,
                "director": "ing. Jae. E. Jacobsson"
            },
            {
                "name": "Västerbo Tegelbruk",
                "location": "Broddbo",
                "business": "Tillverkar tak- och murtegel samt dräneringsrör vid tegelbruk i Västerbo, Broddbo (Västmanl. l.).",
                "contact": {
                    "phone": "Norrvad 13"
                },
                "employees": {
                    "industriarb.": 7
                },
                "annual_production_value": "0,3 milj. st. tegelvaror",
                "foundation_year": 1874,
                "director": "tegelbruksäg. Axel Holmgren"
            },
            {
                "name": "AB. Västergötlands Förenade Kalkindustrier",
                "location": "Falköping",
                "business": "Kalkstensbrott och kalkugnar.",
                "contact": {
                    "phone": "283",
                    "postgiro": "24242"
                },
                "financials": {
                    "capital": "1,575,000 kr",
                    "employees": {
                        "Antal industriarb.": 230
                    }
                },
                "foundation_year": 1918,
                "board": [
                    {
                        "name": "adv. E. D. Halbert",
                        "role": "ordf."
                    },
                    {
                        "name": "dir. G. W. Nymberg"
                    },
                    {
                        "name": "dir. J. E. Thorse-lius"
                    }
                ],
                "director": "G. W. Nymberg",
                "manager": "H. Sunde-lius"
            },
            {
                "name": "AB. Västerviks Motorfabrik",
                "location": "Västervik",
                "business": "Tillverkar råoljemotorer och automatiska smörjapparater; utför mek. verkstadsarbeten och maskinreparationer.",
                "contact": {
                    "phone": "1821",
                    "postgiro": "30290"
                },
                "financials": {
                    "capital": "90,000 kr",
                    "employees": {
                        "Antal industriarb.": 30
                    },
                    "annual_production_value": "300,000 kr"
                },
                "foundation_year": 1910,
                "corporation_year": 1936,
                "current_name_year": 1946,
                "director": "Bror Edberg"
            },
            {
                "name": "Westerviks Pappersbruks AB.",
                "location": "Västervik",
                "business": "Papp- och kartongfabrik.",
                "products": "Tillverkar vit och brun trämassepapp, gråpapp, testliner, kraftliner och chromoersatz.",
                "contact": {
                    "telegraph": "Pappbruket, Västervik",
                    "phone": "»Pappersbruket»"
                }
            }
        ]
    }
}