{
    "original": "Lund—Luossavaara\n\nKontor: Brunkebergstorg 9.\nTelegr.-adr.: Standshelf, Stockholm. Telefon:\n100353—54 o. 208642. Postgiro: 154626.\n\n—\tAntal industriarb.: 40. Tillv.-värde pr\når: 720,000 kr. — Firman etabl. 1937.\n\nÄgare o. chef: fabr. Harald Lundqvist.\n\n\"Lunds Bryggeri AB., Lund.\n\nTillverkar maltdrycker.\n\nTelefon: 17080. Postgiro: 141640. —\nAkt.-kap.: 600,000 kr. Antal industriarb.:\n23. Tillv.-värde pr år: 650,000 kr. —\nBryggeriet anlagt 1870, bolag 1897.\n\nStyrelse: dir. L. W. Malmquist (ordf.),\ndisp. C. E. Borgenstierna, dir. E.\nMalmquist, magistratssekr. N. G. Melander.\n\nDisp.: O. E. Borgenstierna.\n\nKamrer: Malte Ericsson.\n\n\"AB. Lunds Mek. Verkstad, Lund.\n\nMek. verkstad och gjuteri. Tillverkar\nmaskiner för fil-, cement- och\nsockerfabriker samt för renhållningsverk,\napparater för kemiska industrier,\nångpannor, transportanordningar för mäss- och\nstyckegods, fackverksarbeten,\ncentrifugal-pumpar, kolvpumpar, luftkompressorer,\nbetong- och murbruksblandare,\nplåtarbeten samt kondensvattenåterledare,\nvarjämte bolaget utför installationer av\nåter-ledningssystem vid ånganläggningar.\nVarumärke: »LMV».\n\nTelegr.-adr.: Lundsverkstad, Lund.\nTelefon: 10061 o. 10990. Postgiro: 71735.\n\nAkt.-kap.: 306,000 kr. Antal\nindustriarb.: 75. Tillv.-värde pr år: 1,000,000 kr.\n\n—\tBolaget grundat 1897.\n\nStyrelse: konsul Edw. H. Thomée\n(ordf.), adv. Erik Halbert, disp. Malte\nNeuendorff, bankdir. J. Aug. Nilsson.\n\nVerkst. dir. o. disp.: Malte Neuendorff.\n\n\"AB. Lunds Skofabrik, Lund.\n\nTillverkar rand-, vänd- och genomsydda\nskodon. Varumärken: »Philip» (herr- o.\ndamskor) o. »Frosta» (sportkängor).\n\nTe]egr.-adr.: Skofabriken, Lund.\nTelefon: 10453. Postgiro: 6830.\n\nAkt.-kap.: 200,000 kr. Antal\nindustriarb.: 62. Tillv.-värde pr år: 700,000 kr.\n\n—\tFabriken grundad 1880, bolag 1931.\n\nStyrelse o. verkst. dir.: Philip\nAndersson.\n\n\"Carl Lunds Fabriks AB., Malmö.\n\nStålpressnings-, emaljerings-,\nförtennings-, galvaniserings- och lackeringsverk.\nTillverkar hushållskärl av rostfri plåt och\nav emaljerad eller lackerad stålplåt, emal-\n\njerade reklamskyltar, galvaniserade och\nförtenta spannar, tunnplåtsemballage och\nandra pressade, svetsade, falsade och\nnitade tunnplåtsarbeten samt vägmärken.\n\nKontor: Fagerstag.; postadr.: Malmö 1.\nTelegr.-adr.: Lundsfabriker, Malmö.\nTelefon: »Carl Lunds Fabriker». Postgiro:\n38000. Nederlag i Stockholm, Brunnsg.\n21 A, telefon: 235700. Huvudkontor: AB.\nPlåtmanufaktur, Stockholm, Biblioteksg.\n26, telefon: 235700.\n\nAntal industriarb.: 240. Tillv.-värde pr\når: 4,000,000 kr.\n\nFirman, etabl. 1879, bolag 1888, är\nansluten till AB. Plåtmanufaktur,\nStockholm. (Se detta bolag.)\n\nDisp.: Frank G. Nelson.\n\nKamrer: Gösta Jönsson.\n\nFörsäljn.-chef: Einar Olsson.\n\n\"AB. Baltzar Lundström, Stockholm.\n\nByggnadsentreprenörfirma. Utför\nbo-stads- och industribyggnader samt\nstadsplaneprojektering.\n\nKontor: östermalmsg. 40. Telefon:\n234740. Postgiro: 155972.\n\nAkt.-kap.: 500,000 kr. Prod.-värde pr\når: 15,000,000 kr. — Firman etabl. 1938,\nbolag 1944.\n\nStyrelse: ing. Baltzar Lundström\n(ordf.), adv. Gösta Ekelund, dir. Anders\nMalmström.\n\nVerkst. dir.: Baltzar Lundström.\n\nV. verkst. dir.: Anders Malmström.\n\nChefsarhiteht: Nils Rissén.\n\nInhöpschef: Lars Henschen.\n\nE. W. Lundströms Mek. Verkstad\n\nAB., Limhamn.\n\nTillverkar motorlok vid mek. verkstad i\nLimhamn (Malmöh. l.). Bolaget driver\näven serviceverksamhet för AB.\nVibro-Verken, Stockholm, samt för\nbyggnads-maskiner\n\nTelefon: Malmö 50298. Postgiro: 30591.\n— Akt.-kap.: 42,000 kr. Antal\nindustriarb.: 20. Tillv.-värde pr år: 250,000 kr. —\nFirman etabl. 1894, bolag 1943.\n\nVerkst. dir.: ing. Albert Lundström.\n\n\"Luossavaara—Kiirunavaara AB.,\n\nStockholm.\n\nGruvor vid Gällivare, Kiirunavaara o.\nLuossavaara malmfält, anrikningsverk i\nMalmberget (samtl. i Norrb. l.). Bryter\noch anrikar järnmalm.\n\nHuvudkontor: Stockholm, Gustav Adolfs\ntorg 18. Telegr.-adr.: Luossavaara,\nStockholm. Telefon: »Grängesbergsbolaget».\nAvd.-kontor: Luleå, Malmberget, Kiruna\n\noch Narvik.\n\n*",
    "structured": {
        "firms": [
            {
                "name": "Lund—Luossavaara",
                "location": "Brunkebergstorg 9",
                "contact": {
                    "telegraph": "Standshelf, Stockholm",
                    "phone": [
                        "100353",
                        "54",
                        "208642"
                    ],
                    "postgiro": "154626"
                },
                "financials": {
                    "employees": {
                        "industriarb": 40
                    },
                    "annual_production_value": "720,000 kr"
                },
                "foundation_year": 1937,
                "manager": "fabr. Harald Lundqvist"
            },
            {
                "name": "Lunds Bryggeri AB., Lund",
                "products": "maltdrycker",
                "contact": {
                    "phone": "17080",
                    "postgiro": "141640"
                },
                "financials": {
                    "capital": "600,000 kr",
                    "employees": {
                        "industriarb": 23
                    },
                    "annual_production_value": "650,000 kr"
                },
                "foundation_year": 1870,
                "board": [
                    {
                        "name": "dir. L. W. Malmquist",
                        "role": "ordf."
                    },
                    {
                        "name": "disp. C. E. Borgenstierna",
                        "role": null
                    },
                    {
                        "name": "dir. E. Malmquist",
                        "role": null
                    },
                    {
                        "name": "magistratssekr. N. G. Melander",
                        "role": null
                    },
                    {
                        "name": "disp.: O. E. Borgenstierna",
                        "role": null
                    }
                ],
                "director": "O. E. Borgenstierna",
                "managing_director": "Malte Ericsson"
            },
            {
                "name": "AB. Lunds Mek. Verkstad, Lund",
                "business": "Mek. verkstad och gjuteri",
                "products": "maskiner för fil-, cement- och sockerfabriker samt för renhållningsverk, apparater för kemiska industrier, ångpannor, transportanordningar för mäss- och styckegods, fackverksarbeten, centrifugal-pumpar, kolvpumpar, luftkompressorer, betong- och murbruksblandare, plåtarbeten samt kondensvattenåterledare, varjämte bolaget utför installationer av åter-ledningssystem vid ånganläggningar",
                "contact": {
                    "telegraph": "Lundsverkstad, Lund",
                    "phone": [
                        "10061",
                        "10990"
                    ],
                    "postgiro": "71735"
                },
                "financials": {
                    "capital": "306,000 kr",
                    "employees": {
                        "industriarb": 75
                    },
                    "annual_production_value": "1,000,000 kr"
                },
                "foundation_year": 1897,
                "board": [
                    {
                        "name": "konsul Edw. H. Thomée",
                        "role": "ordf."
                    },
                    {
                        "name": "adv. Erik Halbert",
                        "role": null
                    },
                    {
                        "name": "disp. Malte Neuendorff",
                        "role": null
                    },
                    {
                        "name": "bankdir. J. Aug. Nilsson",
                        "role": null
                    }
                ],
                "director": "Malte Neuendorff"
            },
            {
                "name": "AB. Lunds Skofabrik, Lund",
                "business": "Tillverkar rand-, vänd- och genomsydda skodon",
                "products": "Varumärken: »Philip» (herr- o. damskor) o. »Frosta» (sportkängor)",
                "contact": {
                    "telegraph": "Skofabriken, Lund",
                    "phone": "10453",
                    "postgiro": "6830"
                },
                "financials": {
                    "capital": "200,000 kr",
                    "employees": {
                        "industriarb": 62
                    },
                    "annual_production_value": "700,000 kr"
                },
                "foundation_year": 1880,
                "director": "Philip Andersson"
            },
            {
                "name": "Carl Lunds Fabriks AB., Malmö",
                "business": "Stålpressnings-, emaljerings-, förtennings-, galvaniserings- och lackeringsverk",
                "products": "Tillverkar hushållskärl av rostfri plåt och av emaljerad eller lackerad stålplåt, emaljerade reklamskyltar, galvaniserade och för-tenta spannar, tunnplåtsemballage och andra pressade, svetsade, falsade och nitade tunnplåtsarbeten samt vägmärken",
                "contact": {
                    "telegraph": "Lundsfabriker, Malmö",
                    "phone": "Carl Lunds Fabriker",
                    "postgiro": "38000"
                },
                "financials": {
                    "employees": {
                        "industriarb": 240
                    },
                    "annual_production_value": "4,000,000 kr"
                },
                "foundation_year": 1879,
                "disp": "Frank G. Nelson",
                "kamrer": "Gösta Jönsson",
                "sales_manager": "Einar Olsson"
            },
            {
                "name": "AB. Baltzar Lundström, Stockholm",
                "business": "Byggnadsentreprenörfirma",
                "products": "Utför bo-stads- och industribyggnader samt stadsplaneprojektering",
                "contact": {
                    "location": "östermalmsg. 40",
                    "phone": "234740",
                    "postgiro": "155972"
                },
                "financials": {
                    "capital": "500,000 kr",
                    "annual_turnover": "15,000,000 kr"
                },
                "foundation_year": 1938,
                "board": [
                    {
                        "name": "ing. Baltzar Lundström",
                        "role": "ordf."
                    },
                    {
                        "name": "adv. Gösta Ekelund",
                        "role": null
                    },
                    {
                        "name": "dir. Anders Malmström",
                        "role": null
                    }
                ],
                "director": "Baltzar Lundström",
                "manager": "Anders Malmström",
                "sales_manager": "Lars Henschen"
            },
            {
                "name": "E. W. Lundströms Mek. Verkstad AB., Limhamn",
                "business": "Tillverkar motorlok vid mek. verkstad i Limhamn. Bolaget driver även serviceverksamhet för AB. Vibro-Verken, Stockholm, samt för byggnads-maskiner",
                "contact": {
                    "phone": "Malmö 50298",
                    "postgiro": "30591"
                },
                "financials": {
                    "capital": "42,000 kr",
                    "employees": {
                        "industriarb": 20
                    },
                    "annual_production_value": "250,000 kr"
                },
                "foundation_year": 1894,
                "director": "ing. Albert Lundström"
            },
            {
                "name": "Luossavaara—Kiirunavaara AB., Stockholm",
                "business": "Gruvor vid Gällivare, Kiirunavaara o. Luossavaara malmfält, anrikningsverk i Malmberget (samtl. i Norrb. l.). Bryter och anrikar järnmalm",
                "contact": {
                    "location": "Gustav Adolfs torg 18",
                    "telegraph": "Luossavaara, Stockholm",
                    "phone": "»Grängesbergsbolaget»"
                },
                "financials": {
                    "capital": "unspecified",
                    "employees": {
                        "industriarb": "unspecified"
                    }
                },
                "foundation_year": "unspecified"
            }
        ]
    }
}