{
    "original": "J ohansson—Jonsson\n\n*P. O. Johansson Stackes\nTräförädling, Gnosjö.\n\nSe P. O. Staekes Träförädling, Gnosjö.\n\n’Rudolf Johanssons Möbelfabrik,\n\nTibro.\n\nTillverkar möbler (speciellt bokhyllor)\nvid fabrik i Tibro (Skarab. l.).\n\nTelefon: 135. Postgiro: 134779. —\nArb.-antal: 6. Tillv.-värde pr år: 82,000\nkr. — Firman etabl. 1919.\n\nÄgare o. chef: snickaremäst. Bertil\nRudolfsson.\n\n’Samuel Johansson, Möbelfabrik,\n\nTibro.\n\nSe S. Bogeryds Möbelfabrik, Tibro.\n\n*Sv. M. Johansson, Ulricehamn.\n\nTillverkar möbler vid möbelfabrik i\nUlricehamn. Specialitet:\nsängkammarmöbler.\n\nTelefon: 796 o. 96. Postgiro: 95666. —\nAntal industriarb.: 20. Tillv.-värde pr\når: 150,000 kr. — Firman etabl. 1902.\n\nDelägare o. chef: disp. Sven Ola\nTeng-sjö.\n\nVald. Johansson, Falu\nSpisbrödsfabrik, Falun.\n\n• Se Falu Spisbrödsfabrik, Vald.\nJohansson, Falun.\n\n’Jonsereds Fabrikers AB., Jonsered.\n\nBomulls-, lin-, hamp- och\njutespinnerier och väverier, blekeri och\nimpregne-ringsanläggning, mek. verkstad samt\nelektr. vattenkraftstation i Jonsered\n(Göteb. o. Bohus l.).\n\n^ Tillverkar presenningsduk och\npresenningar, brandslangar, drivremmar,\nsegelduk, säckar, emballageväv, pressduk,\ndomestik, smerting m. m. samt garner av\nlin, hampa, jute och bomull;\nträbearbet-ningsmaskiner för byggnads-, möbel- och\nmodellsnickerier, för lådfabriker,\nhyvlerier, parkettfabriker och för fabriker för\nmonteringsfärdiga trähus m. fl.\n\nTelegr.-adr.: Jonsereds, Göteborg.\nTelefon: Göteborg »Jonsereds fabriker» o.\n172200. Postgiro: 10300.\n\nRepresentanter i Stockholm: för\nvävnader m. m.: C. C. Wetterlind &amp; Co.,\nSkeppsbron 6, telefon: 100624; för\nmaskiner: C. G. Remming, Rörstrandsg. 27,\ntelefon: 309144.\n\nAkt.-kap.: 5,070,000 kr. Antal\nindustriarb.: 850. Tillv.-värde pr år: 18,200,000\nkr. — Firman grundad 1833, bolag 1873.\n\nStyrelse: f. kommendörkapten William\nGibson (ordf.), civiling. Eric Brodén,\nrevisor John W. Gibson, bergsing. Lennart\nNordenfelt, disp. Ivar Wendt.\nVerkst. dir.: Eric Brodén.\n\nAvd.-chef för maskinavd.: Arvid B.\nStenberg.\n\nFörsäljn.-chef er: för textilavd.: E.\nBjörkenius; för maskinavd.: Karl Ekdahl.\nKamrer: Gerh. Eigert.\nDriftsing.: Birger Norinder.\n\nJonson, Jonsson, Johnson, Johnsson.\nJonsson, Hallsjö &amp; Co., Malung.\n\nSkinnbeklädnadsfabrik i Malung\n(Kopparb. l.). Tillverkar skinntröjor, -jackor\noch -västar, skinnrockar, pälsar och\nhandskar.\n\nTelegr.-adr.: Skinnbeklädnad, Malung.\nTelefon: 50. Postgiro: 30182. — Antal\nindustriarb.: 10. — Firman etabl. 1915.\n\nÄgare o. chefer: fabr. Albert Jonsson,\nfabr. Johan Hallsjö o. fabr. Petrus\nJonsson.\n\nJohnson Hill AB., Örebro.\n\nKuvert- och påsfabrik, litografisk\nanstalt samt boktryckeri. Tillverkar kuvert,\npapperspåsar och kortblanketter; utför\nlitografiskt tryck och boktryck.\n\nTelegr.-adr. o. telefon: »Johnsonhill»,\nÖrebro. Postgiro: 9107. Avd.-kontor:\nStockholm, Regeringsg. 9. Telefon:\n204927.\n\nAkt.-kap.: 500,000 kr. Antal\nindustriarb.: 165. Omsättn.-värde pr år: 4,800,000\nkr. — Firman etabl. 1900, bolag 1938.\n\nStyrelse: dir. Erland Johnson, disp.\nOlof Johnson.\n\nVerkst. dir.: Erland Johnson.\n\n’AB. Jonsson &amp; Kjellin, Kumla.\n\nSkofabrik i Kumla (Örebro l.).\nTillverkar randsydda och agodamskodon.\n\nTelefon: 70186 o. 70524. Postgiro:\n20807. — Akt.-kap.: 150,000 kr. Antal\nindustriarb.: 60. Tillv.-värde pr år:\n975,000 kr. — Firman etabl. 1919, bolag\n1934.\n\nStyrelse: fabr. Erik Kjellin (ordf.),\nkassör Sigurd Johansson.\n\nVerkst. dir.: Erik Kjellin.\n\n*",
    "structured": {
        "1": {
            "name": "P. O. Johansson Stackes Träförädling",
            "location": "Gnosjö",
            "business": "Träförädling",
            "products": "Tillverkar möbler (speciellt bokhyllor) vid fabrik i Tibro (Skarab. l.)",
            "contact": {
                "office": "P. O. Johansson Stackes Träförädling, Gnosjö",
                "phone": [
                    "135"
                ],
                "postgiro": "134779",
                "factory_office": "Tibro",
                "factory_phone": "135"
            },
            "financials": {
                "capital": "N/A",
                "annual_turnover": "82,000 kr",
                "annual_production_value": "82,000 kr"
            },
            "foundation_year": 1919,
            "board": [
                {
                    "name": "snickaremäst. Bertil Rudolfsson",
                    "role": "Ägare o. chef"
                }
            ]
        },
        "2": {
            "name": "Samuel Johansson, Möbelfabrik",
            "location": "Tibro",
            "business": "Möbelfabrik",
            "products": "Se S. Bogeryds Möbelfabrik, Tibro",
            "contact": {
                "office": "Samuel Johansson, Möbelfabrik, Tibro",
                "phone": [
                    "N/A"
                ],
                "postgiro": "N/A"
            },
            "financials": {
                "capital": "N/A",
                "annual_turnover": "N/A",
                "annual_production_value": "N/A"
            },
            "foundation_year": 1902
        },
        "3": {
            "name": "Sv. M. Johansson",
            "location": "Ulricehamn",
            "business": "Möbelfabrik",
            "products": "Tillverkar möbler vid möbelfabrik i Ulricehamn. Specialitet: sängkammarmöbler.",
            "contact": {
                "office": "Sv. M. Johansson, Ulricehamn",
                "phone": [
                    "796",
                    "96"
                ],
                "postgiro": "95666"
            },
            "financials": {
                "capital": "N/A",
                "annual_turnover": "150,000 kr",
                "annual_production_value": "150,000 kr"
            },
            "foundation_year": 1902,
            "board": [
                {
                    "name": "disp. Sven Ola Teng-sjö",
                    "role": "Delägare o. chef"
                }
            ]
        },
        "4": {
            "name": "Vald. Johansson, Falu Spisbrödsfabrik",
            "location": "Falun",
            "business": "Spisbrödsfabrik",
            "contact": {
                "office": "Vald. Johansson, Falu Spisbrödsfabrik, Falun",
                "phone": [
                    "N/A"
                ]
            },
            "financials": {
                "capital": "N/A",
                "annual_turnover": "N/A",
                "annual_production_value": "N/A"
            },
            "foundation_year": 1915
        },
        "5": {
            "name": "Jonsereds Fabrikers AB.",
            "location": "Jonsered",
            "business": "Bomulls-, lin-, hamp- och jutespinnerier och väverier",
            "products": "Tillverkar presenningsduk och presenningar, brandslangar, drivremmar, segelduk, säckar, emballageväv, pressduk, domestik, smerting m. m. samt garner av lin, hampa, jute och bomull; träbearbetningsmaskiner för byggnads-, möbel- och modellsnickerier, för lådfabriker, hyvlerier, parkettfabriker och för fabriker för monteringsfärdiga trähus m. fl.",
            "contact": {
                "office": "Jonsereds Fabrikers AB., Jonsered",
                "phone": [
                    "N/A"
                ],
                "telegraph": "Jonsereds, Göteborg",
                "sales_offices": [
                    {
                        "location": "Stockholm",
                        "phone": "100624"
                    },
                    {
                        "location": "Stockholm",
                        "phone": "309144"
                    }
                ],
                "postgiro": "10300"
            },
            "financials": {
                "capital": "5,070,000 kr",
                "annual_turnover": "18,200,000 kr",
                "annual_production_value": "18,200,000 kr"
            },
            "foundation_year": 1833,
            "corporation_year": 1873,
            "board": [
                {
                    "name": "f. kommendörkapten William Gibson",
                    "role": "ordf."
                },
                {
                    "name": "civiling. Eric Brodén",
                    "role": "N/A"
                },
                {
                    "name": "revisor John W. Gibson",
                    "role": "N/A"
                },
                {
                    "name": "bergsing. Lennart Nordenfelt",
                    "role": "N/A"
                },
                {
                    "name": "disp. Ivar Wendt",
                    "role": "N/A"
                }
            ],
            "director": "Eric Brodén",
            "sales_manager": "N/A",
            "manager": "N/A"
        },
        "6": {
            "name": "Jonsson, Jonsson, Johnson, Johnsson. Jonsson, Hallsjö & Co.",
            "location": "Malung",
            "business": "Skinnbeklädnadsfabrik",
            "products": "Tillverkar skinntröjor, -jackor och -västar, skinnrockar, pälsar och handskar.",
            "contact": {
                "office": "Jonsson, Hallsjö & Co., Malung",
                "phone": [
                    "50"
                ],
                "postgiro": "30182"
            },
            "financials": {
                "capital": "N/A",
                "annual_turnover": "N/A",
                "annual_production_value": "N/A"
            },
            "foundation_year": 1915,
            "board": [
                {
                    "name": "fabr. Albert Jonsson",
                    "role": "Ägare o. chefer"
                },
                {
                    "name": "fabr. Johan Hallsjö",
                    "role": "Ägare o. chefer"
                },
                {
                    "name": "fabr. Petrus Jonsson",
                    "role": "Ägare o. chefer"
                }
            ]
        },
        "7": {
            "name": "Johnson Hill AB.",
            "location": "Örebro",
            "business": "Kuvert- och påsfabrik, litografisk anstalt samt boktryckeri",
            "products": "Tillverkar kuvert, papperspåsar och kortblanketter; utför litografiskt tryck och boktryck.",
            "contact": {
                "office": "Johnson Hill AB., Örebro",
                "phone": [
                    "N/A"
                ],
                "telegraph": "Johnsonhill, Örebro",
                "postgiro": "9107",
                "sales_offices": [
                    {
                        "location": "Stockholm",
                        "phone": "204927"
                    }
                ]
            },
            "financials": {
                "capital": "500,000 kr",
                "annual_turnover": "4,800,000 kr",
                "annual_production_value": "4,800,000 kr"
            },
            "foundation_year": 1900,
            "corporation_year": 1938,
            "board": [
                {
                    "name": "dir. Erland Johnson",
                    "role": "N/A"
                },
                {
                    "name": "disp. Olof Johnson",
                    "role": "N/A"
                }
            ],
            "director": "Erland Johnson",
            "manager": "N/A"
        },
        "8": {
            "name": "AB. Jonsson & Kjellin",
            "location": "Kumla",
            "business": "Skofabrik",
            "products": "Tillverkar randsydda och agodamskodon.",
            "contact": {
                "office": "AB. Jonsson & Kjellin, Kumla",
                "phone": [
                    "70186",
                    "70524"
                ],
                "postgiro": "20807"
            },
            "financials": {
                "capital": "150,000 kr",
                "annual_turnover": "975,000 kr",
                "annual_production_value": "975,000 kr"
            },
            "foundation_year": 1919,
            "corporation_year": 1934,
            "board": [
                {
                    "name": "fabr. Erik Kjellin",
                    "role": "ordf."
                },
                {
                    "name": "kassör Sigurd Johansson",
                    "role": "N/A"
                }
            ],
            "director": "N/A",
            "manager": "Erik Kjellin"
        }
    }
}