{
    "original": "Österlind—Östlund\n\nBolagets verk och allläggningar\narrenderas av Fagersta Bruks AB. Betr.\ntillverkningar, se under Fagersta Bruks AB.,\nFagersta.\n\nFörsaljn.-kontor: Fagersta Bruks AB.,\nFagersta. Telefon: »Fagersta Bruk».\nPostgiro: 10035. Avd.-kontor:\nösterby-bruk. Telefon: Dannemora 25.\n\nAkt.-kap.: 1,400,000 kr. — Bolaget\ngrundat 1937 efter övertagande av\nGimo-österby Bruks järn- och stålverk.\n\nStyrelse: disp. Hj. Åselius (ordf.),\ndir. Nils Elfström, övering. Johan Palm.\n\nPlatschef: Johan Palm.\n\nÖsterlind &amp; Son, Tiohög.\n\nEmaljerverk och plåtmanufaktur i\nHo-hög, Malmö. Tillverkar emaljskyltar,\n\n*emaljerad belysningsarmatur,\nneonskyltar, vägmärken, pressningsarbeten och\nplåtmanufaktur m. m.\n\nTelegr.-adr.: österlindson, Malmö.\nTelefon: Malmö 490610. Postgiro: 37607.\nAvd.-kontor: Stockholm, S:t Paulsg. 35 A,\ntelefon: 420128. — Antal industriarb.:\n€5. — Firman etabl. 1912.\n\nÄgare o. chef: disp. R. österlind.\n\nAB. Alfred Österlunds Fabriker,\n\nMalmö.\n\nLådfabrik. Tillverkar lådor och\nlåd-ämnen.\n\nTelegr.-adr.: österlund, Malmö.\nTelefon: 20471. Postgiro: 38284.\n\nAkt.-kap.: 250,000 kr. Antal\nindustriarb.: 40. Tillv.-värde pr år: 230,000 kr.\n— Firman etabl. 1902, bolag 1917.\n\nStyrelse: dir. Alfred österlund (ordf.),\nkonsul Arvid P. Sjöberg.\n\nVerkst. dir.: Alfred österlund.\n\n* Öster näs Ångsåg, Ljusdal.\n\nSe AB. Jon Jonsson &amp; Co., Ljusdal.\n\n*AB. Östersunds Ångbryggerl,\n\nÖstersund.\n\nTillverkar malt- och läskedrycker.\n\nTelegr.-adr. o. telefon: Ångbryggeriet,\nÖstersund. Postgiro: 77400.\n\nAkt.-kap.: 600,000 kr. Antal\nindustriarb.: 50. Tillv.-värde pr år: 2,400,000 kr.\n\nFirman, etabl. 1883. bolag 1899, äger\nDalhems Bryggeri, Östersund,\nStrömsunds Bryggeri AB., AB. Svegs\nÅngbryg-geri och Bräcke Bryggeri.\n\nStyrelse o. verkst. direktörer: disp.\n\n• Einar Winström o. civiling. Gunnar\nEnglund.\n\n6;\n\nöstertälje Snickeri- &amp; Trävaru AB.,\n\nÖstertälje.\n\nTillverkar sågade och hyvlade trävaror,\n\nbyggnadssnickerier och monteringsfärdiga\nträhus vid fabrik i östertälje (Sthlms l.).\n\nTelegr.-adr.: Bosal, Södertälje. Telefon:\nSödertälje 31173 o. 31153. Postgiro:\n34008. Repr. i Stockholm: Firma\nSystemhus, S:t Paulsg. 14. Telefon: 445560 o.\n444490.\n\nAkt.-kap.: 100,000 kr. Antal\nindustriarb.: 20. — Bolaget grundat 1930.\n\nVerkst. dir. o. disp.: Elof Bohestedt.\n\nKamrer: Vidar Sahlin.\n\nÖstgöta Mattfabriks AB., Motala.\n\nTillverkar mattor. Varumärke:\n»öst-göta-Mattan».\n\nTelefon: »Engel-Fabrikerna». Postgiro:\n174620.\n\nAkt.-kap.: 25,000 kr. Antal\nindustriarb.: 25. Tillv.-värde pr år: 300,000 kr.\n\n—\tBolaget, grundat 1941, tillhör\nEngel-koncernen, Motala.\n\nStyrelse: bankdir. Gösta Gyllensvärd\n(ordf.), dir. Gösta Engel, bankdir. Sigurd\nHellgrén.\n\nVerkst. dir.: Gösta Engel.\n\n*AB. Östlind &amp; Almquist, Arvika.\n\nPiano- och orgelfabriker. Tillverkar\nflyglar, pianon och orglar.\n\nTelegr.-adr.: Orgelpiano, Arvika.\nTelefon: 14. Utställningar: Stockholm*\nKungsg. 4; Göteborg, Arkaden; Malmö,\nösterg. 11; Norrköping, Gävle, Örebro\noch Linköping.\n\nAkt.-kap.: 425,000 kr. — Firman, som\netablerades 1888, ombildades till\naktiebolag 1906 och äges sedan 1917 av AB.\nFörenade Piano- &amp; Orgelfabriker, Arvika.\n(Se vidare under detta bolag.)\n\nStyrelse: disp. Alexis Anderson, dir.\nKarl Högberg, dir. Johan Sande J:or.\n\nVerkst. dir.: Karl Högberg.\n\n*AB. P. E. Östlunds Maskinfabrik,\n\nEungsör.\n\nTillverkar bagerimaskiner såsom\nuppslagningsmaskiner för knäckebröd, kakor\noch småbröd, handredskap m. m., blanka\nbultvaror samt velocipeddetaljer såsom\nskruv, mutter, nippel, axlar, konor,\nhandtagsbeslag m. m.\n\nTelegr.-adr.: Maskiner, Kungsör.\nTelefon: »östlunds Maskinfabrik». Postgiro:\n26278.\n\nAkt.-kap.: 210,000 kr. Antal\nindustriarb.: 110. Tillv.-värde pr år: 2,000,000 kr.\n\n—\tBolaget grundat 1918.\n\n3*",
    "structured": {
        "1": {
            "name": "Österlind—Östlund",
            "location": "Fagersta",
            "business": "Arrenderas av Fagersta Bruks AB",
            "contact": {
                "office": "Fagersta Bruks AB",
                "phone": [
                    "Fagersta Bruk",
                    "Dannemora 25"
                ],
                "postgiro": "10035",
                "head_office": "Fagersta",
                "sales_offices": [
                    {
                        "location": "österby-bruk",
                        "phone": "Dannemora 25"
                    }
                ],
                "telegraph": "österlindson, Malmö"
            },
            "financials": {
                "capital": "1,400,000 kr",
                "foundation_year": 1937
            },
            "board": [
                {
                    "name": "disp. Hj. Åselius",
                    "role": "(ordf.)"
                },
                {
                    "name": "dir. Nils Elfström",
                    "role": null
                },
                {
                    "name": "övering. Johan Palm",
                    "role": null
                }
            ],
            "manager": "Johan Palm"
        },
        "2": {
            "name": "Österlind & Son",
            "location": "Tiohög",
            "products": "Emaljskyltar, emaljerad belysningsarmatur, neonskyltar, vägmärken, pressningsarbeten och plåtmanufaktur m.m.",
            "contact": {
                "office": "österlindson, Malmö",
                "phone": [
                    "Malmö 490610"
                ],
                "postgiro": "37607",
                "sales_offices": [
                    {
                        "location": "Stockholm",
                        "phone": "420128"
                    }
                ]
            },
            "financials": {
                "foundation_year": 1912
            },
            "owners": [
                "disp. R. österlind"
            ]
        },
        "3": {
            "name": "AB. Alfred Österlunds Fabriker",
            "location": "Malmö",
            "business": "Lådfabrik",
            "products": "Tillverkar lådor och låd-ämnen",
            "contact": {
                "office": "österlund, Malmö",
                "phone": "20471",
                "postgiro": "38284"
            },
            "financials": {
                "capital": "250,000 kr",
                "employees": {
                    "industriarb": 40
                },
                "annual_turnover": "230,000 kr",
                "foundation_year": 1902,
                "corporation_year": 1917
            },
            "board": [
                {
                    "name": "dir. Alfred österlund",
                    "role": "(ordf.)"
                },
                {
                    "name": "konsul Arvid P. Sjöberg",
                    "role": null
                }
            ],
            "manager": "Alfred österlund"
        },
        "4": {
            "name": "AB. Östersunds Ångbryggeri",
            "location": "Östersund",
            "business": "Tillverkar malt- och läskedrycker",
            "contact": {
                "office": "Ångbryggeriet, Östersund",
                "phone": "Ångbryggeriet, Östersund",
                "postgiro": "77400"
            },
            "financials": {
                "capital": "600,000 kr",
                "employees": {
                    "industriarb": 50
                },
                "annual_turnover": "2,400,000 kr"
            },
            "owners": [
                "AB. Förenade Piano- & Orgelfabriker",
                "Arvika"
            ],
            "manager": "disp. Einar Winström o. civiling. Gunnar Englund"
        },
        "5": {
            "name": "östertälje Snickeri- & Trävaru AB.",
            "location": "Östertälje",
            "products": "Tillverkar sågade och hyvlade trävaror, byggnadssnickerier och monteringsfärdiga trähus vid fabrik i östertälje (Sthlms l.)",
            "contact": {
                "office": "Bosal, Södertälje",
                "phone": [
                    "Södertälje 31173",
                    "Södertälje 31153"
                ],
                "postgiro": "34008"
            },
            "financials": {
                "capital": "100,000 kr",
                "employees": {
                    "industriarb": 20
                },
                "corporation_year": 1930
            },
            "manager": "Elof Bohestedt",
            "sales_manager": "Vidar Sahlin"
        },
        "6": {
            "name": "Östgöta Mattfabriks AB.",
            "location": "Motala",
            "business": "Tillverkar mattor",
            "products": "Varumärke: »öst-göta-Mattan»",
            "contact": {
                "phone": "»Engel-Fabrikerna»",
                "postgiro": "174620"
            },
            "financials": {
                "capital": "25,000 kr",
                "employees": {
                    "industriarb": 25
                },
                "annual_turnover": "300,000 kr"
            },
            "owners": [
                "Engel-koncernen",
                "Motala"
            ],
            "manager": "Gösta Engel"
        },
        "7": {
            "name": "AB. Östlind & Almquist",
            "location": "Arvika",
            "business": "Piano- och orgelfabriker",
            "products": "Tillverkar flyglar, pianon och orglar",
            "contact": {
                "office": "Orgelpiano, Arvika",
                "phone": "14"
            },
            "financials": {
                "capital": "425,000 kr",
                "foundation_year": 1888,
                "corporation_year": 1906
            },
            "board": [
                {
                    "name": "disp. Alexis Anderson",
                    "role": null
                },
                {
                    "name": "dir. Karl Högberg",
                    "role": null
                },
                {
                    "name": "dir. Johan Sande J:or",
                    "role": null
                }
            ],
            "manager": "Karl Högberg"
        },
        "8": {
            "name": "AB. P. E. Östlunds Maskinfabrik",
            "location": "Kungsör",
            "business": "Tillverkar bagerimaskiner",
            "products": "Uppslagningsmaskiner för knäckebröd, kakor och småbröd, handredskap m.m., velocipeddetaljer såsom skruv, mutter, nippel, axlar, konor, handtagsbeslag m.m.",
            "contact": {
                "office": "Maskiner, Kungsör",
                "phone": "östlunds Maskinfabrik",
                "postgiro": "26278"
            },
            "financials": {
                "capital": "210,000 kr",
                "employees": {
                    "industriarb": 110
                },
                "annual_turnover": "2,000,000 kr"
            }
        }
    }
}