{
    "original": "Faxe—Ferm\n\nautomobiler, radio m. fl. ändamål, press-,\nstans- och formverktyg samt syrgas.\n\nKontor: Larocheg. 4. Telegr.-adr. o.\ntelefon: Faxius, Malmö. Postgiro: 39090.\nLaddningsstationer o. lager: Göteborg,\nOdinsplatsen 5, telefon: 150259;\nSundsvall, telefon: 3408.\n\nAkt.-kap.: 500,000 kr. Antal\nindustriarb.: 90. Tillv.-värde pr år: 4,000,000 kr.\n— Firman etabl. 1906, bolag 1943.\n\nStyrelse: fru Ingrid Faxe, dir. Jörgen\nFaxe.\n\nVerkst. dir.: Jörgen Faxe.\n\nKamrer: E. H. Sökjer-Petersen.\n\nAyd.-chefer: f. batteriförsäljn.: ing.\nEmil Olsson; för syrgasförsäljn.,\nexport-o. inköpsavd.: frih. S. Gyllenstierna; för\npress verktyg: ing. Henrik Olsson.\n\nFaxes Skyddskofabrik, Smålands\n\nBurseryd.\n\nMek. verkstad och snickerifabrik i\nSmålands Burseryd (Jönköp. l.).\nTillverkar skyddshästskor (trugor),\nbeteskultur-harvar, vedklyvningsmaskiner,\nträremski-vor m. m.\n\nTelefon: 8. Postgiro: 22585. — Antal\nindustriarb.: 12. Tillv.-värde pr år:\n110,000 kr. — Firman etabl. 1907.\n\nÄgare o. chef: fabr. Lars Davidsson.\n\n*AB. Fegens Låd- &amp; Tunnfabrik,\n\nFegen.\n\nLåd- och tunnfabrik samt sågverk och\nhyvleri vid Fegen (Hallands l.).\nTillverkar lister, lådämnen, tunnstäver och\nbottnar m. m. samt sågade och hyvlade\nträvaror.\n\nTelegr.-adr.: Lådfabriken, Fegen.\nTelefon: 1. Postgiro: 275100. — Akt.-kap.:\n70,000 kr. Antal industriarb.: 20.\nTillv.-värde pr år: 170,000 kr. — Firman etabl.\n1912, bolag 1943.\n\nStyrelse: disp. Bertil Magnusson\n(ordf.), kamrer Levi Leonardsson,\nkontorist Torsten Magnusson, köpm. Nils\nRowell, fabr. Sven Rowell.\n\nDisp.: Bertil Magnusson.\n\n*FeIlingsbro Cjuteri &amp; Mek.\nVerkstad, Fellingsbro.\n\nSe AB. Bröderna Envall, Fellingsbro.\n\nAB. Fellingsbro Verkstäder,\n\nFellingsbro.\n\nMek. verkstad i Fellingsbro (Örebro l.).\nTillverkar plåtradiatorer.\n\nTelegr.-adr.: Ferrum, Fellingsbro.\nTelefon: 182. Postgiro: 133991. Repr.: AB.\n\n15\n\nAskania, Stockholm, Välling. 38; telefon:\n232200, o. Örebro, telefon: 15568.\n\nAkt.-kap.: 250,000 kr. Antal\nindustriarb.: 25. — Bolaget grundat 1936.\n\nStyrelse o. verkst. dir.: Erik Landberg\n(Sthlm).\n\nPlatschef: ing. Nils Nilson.\n\n*Fengersfors Bruks AB., Tösse.\n\nPappersbruk med sulfatfabrik vid\nFen-gersfors, Tösse (Älvsb. l.). Tillverkar\nkraftpapper, även blekt, såsom kabel-,\nspinn-, kuvert- och emballagepapper, vitt\npapper för olika ändamål,\ngenomslagspost, vattentätt omslagspapper\n(Oceanpapper) samt vaxat och kräppat papper.\n\nAgenter i utlandet:\n\nEngland: The Northern Paper Co. Ltd.,\n31/32, Budge Row, London E. C. 4;\n\nDanmark: Ole Heye, Köbmagergade 67\n—69, Köpenhamn K;\n\nBelgien.- Au g. Öaspers, 3, Avenue des\nMésanges, Auderghem-Bruxelles;\n\nArgentina: H. M. Spens, Oorrientes\n456, Buenos Aires;\n\nAustralien: S. Lie, 31, Queen Street,\nMelbourne.\n\nTelegr.-adr.: Fengersfors, Åmål.\nTelefon: Tösse 2348 o. 2350. Postgiro: 9464.\n\nAkt.-kap.: 1,005,000 kr. Antal\nindustriarb.: 205. Årstillv.: 7,000 ton papper. —\nFirman etabl. 1900, bolag 1938.\n\nStyrelse: ad v. W. Kristensen (ordf.),\nfru E. Beskow, banktjänstem. Albert\nFenger-Krog, ing. Eilert Fenger-Krog,\ndisp. John Fenger-Krog.\n\nDisp.: John Fenger-Krog.\n\nDriftsing.: Eilert Fenger-Krog.\n\nFörsäljn.-chef: J. Torsell.\n\nFenja, Handels- o. Entreprenad AB.,\n\nStockholm.\n\nSe Handels- o. Entreprenad AB. Fenja,\nStockholm.\n\n*AB. Ferm &amp; Persson, Göteborg.\n\nGlasindustri och glasmästeri,\nförgylleri-, snickeri- och metallfabrik.\n\nUtför glasslipning och spegelfoliering,\nblyinfattningar, förgylleriarbeten såsom\nspeglar, ramar och inramningar,\nrenoveringar och omförgyllningar,\nsnickeriarbeten såsom affärsinredningar, montrar,\ndiskar m. m. samt förkromningsarbeten;\ntillverkar butiksfasader i järn, metall och\nrostfritt samt glastak och fartygsventiler\nm. m. (märke: »CEWE»).\n\nKontor: Kungsg. 22. Telegr.-adr.:\nFermpersson, Göteborg. Telefon: 138035.\nPostgiro: 12231.\n\n0*",
    "structured": {
        "1": {
            "name": "Faxe—Ferm",
            "location": "Malmö",
            "business": "automobiler, radio m. fl. ändamål, press-, stans- och formverktyg samt syrgas",
            "contact": {
                "office": "Larocheg. 4",
                "phone": [
                    "Faxius, Malmö"
                ],
                "postgiro": "39090",
                "sales_offices": [
                    {
                        "location": "Göteborg, Odinsplatsen 5",
                        "phone": "150259"
                    },
                    {
                        "location": "Sundsvall",
                        "phone": "3408"
                    }
                ],
                "telegraph": "",
                "factory_office": "",
                "factory_phone": ""
            },
            "financials": {
                "capital": "500,000 kr",
                "employees": {
                    "industriarb.": 90
                },
                "annual_turnover": "4,000,000 kr",
                "annual_production_value": "4,000,000 kr"
            },
            "foundation_year": 1906,
            "corporation_year": 1943,
            "board": [
                {
                    "name": "fru Ingrid Faxe",
                    "role": ""
                },
                {
                    "name": "dir. Jörgen Faxe",
                    "role": ""
                }
            ],
            "director": "Jörgen Faxe",
            "managing_director": "",
            "sales_manager": "",
            "manager": ""
        },
        "2": {
            "name": "Faxes Skyddskofabrik",
            "location": "Smålands Burseryd",
            "business": "Mek. verkstad och snickerifabrik i Smålands Burseryd (Jönköp. l.). Tillverkar skyddshästskor (trugor), beteskultur-harvar, vedklyvningsmaskiner, träremskivor m. m",
            "contact": {
                "office": "",
                "phone": [
                    "8"
                ],
                "postgiro": "22585",
                "head_office": "",
                "sales_offices": [],
                "telegraph": "",
                "factory_office": "",
                "factory_phone": ""
            },
            "financials": {
                "capital": "",
                "employees": {
                    "industriarb.": 12
                },
                "annual_turnover": "110,000 kr",
                "annual_production_value": "110,000 kr"
            },
            "foundation_year": 1907,
            "corporation_year": "",
            "board": [],
            "owners": [],
            "director": "",
            "managing_director": "",
            "sales_manager": "",
            "manager": "fabr. Lars Davidsson"
        },
        "3": {
            "name": "AB. Fegens Låd- & Tunnfabrik",
            "location": "Fegen",
            "business": "Låd- och tunnfabrik samt sågverk och hyvleri vid Fegen (Hallands l.). Tillverkar lister, lådämnen, tunnstäver och bottnar m. m. samt sågade och hyvlade trävaror",
            "contact": {
                "office": "",
                "phone": [
                    "1"
                ],
                "postgiro": "275100",
                "head_office": "",
                "sales_offices": [],
                "telegraph": "Lådfabriken, Fegen",
                "factory_office": "",
                "factory_phone": ""
            },
            "financials": {
                "capital": "70,000 kr",
                "employees": {
                    "industriarb.": 20
                },
                "annual_turnover": "170,000 kr",
                "annual_production_value": "170,000 kr"
            },
            "foundation_year": 1912,
            "corporation_year": 1943,
            "board": [
                {
                    "name": "disp. Bertil Magnusson",
                    "role": "ordf."
                },
                {
                    "name": "kamrer Levi Leonardsson",
                    "role": ""
                },
                {
                    "name": "kontorist Torsten Magnusson",
                    "role": ""
                },
                {
                    "name": "köpm. Nils Rowell",
                    "role": ""
                },
                {
                    "name": "fabr. Sven Rowell",
                    "role": ""
                }
            ],
            "director": "",
            "managing_director": "",
            "sales_manager": "",
            "manager": ""
        },
        "4": {
            "name": "AB. Fellingsbro Verkstäder",
            "location": "Fellingsbro",
            "business": "Mek. verkstad i Fellingsbro (Örebro l.). Tillverkar plåtradiatorer",
            "contact": {
                "office": "",
                "phone": [
                    "182"
                ],
                "postgiro": "133991",
                "head_office": "",
                "sales_offices": [],
                "telegraph": "Ferrum, Fellingsbro",
                "factory_office": "",
                "factory_phone": ""
            },
            "financials": {
                "capital": "250,000 kr",
                "employees": {
                    "industriarb.": 25
                },
                "annual_turnover": "",
                "annual_production_value": ""
            },
            "foundation_year": "",
            "corporation_year": 1936,
            "board": [],
            "director": "",
            "managing_director": "",
            "sales_manager": "",
            "manager": "Erik Landberg (Sthlm)"
        },
        "5": {
            "name": "Fengersfors Bruks AB.",
            "location": "Tösse",
            "business": "Pappersbruk med sulfatfabrik vid Fengersfors, Tösse (Älvsb. l.). Tillverkar kraftpapper, även blekt, såsom kabel-, spinn-, kuvert- och emballagepapper, vitt papper för olika ändamål, genomslagspost, vattentätt omslagspapper (Oceanpapper) samt vaxat och kräppat papper",
            "contact": {
                "office": "",
                "phone": [
                    "Tösse 2348 o. 2350"
                ],
                "postgiro": "9464",
                "head_office": "",
                "sales_offices": [],
                "telegraph": "Fengersfors, Åmål",
                "factory_office": "",
                "factory_phone": ""
            },
            "financials": {
                "capital": "1,005,000 kr",
                "employees": {
                    "industriarb.": 205
                },
                "annual_turnover": "",
                "annual_production_value": "7,000 ton papper"
            },
            "foundation_year": 1900,
            "corporation_year": 1938,
            "board": [
                {
                    "name": "ad v. W. Kristensen",
                    "role": "ordf."
                },
                {
                    "name": "fru E. Beskow",
                    "role": ""
                },
                {
                    "name": "banktjänstem. Albert Fenger-Krog",
                    "role": ""
                },
                {
                    "name": "ing. Eilert Fenger-Krog",
                    "role": ""
                },
                {
                    "name": "disp. John Fenger-Krog",
                    "role": ""
                }
            ],
            "director": "",
            "managing_director": "Eilert Fenger-Krog",
            "sales_manager": "J. Torsell",
            "manager": ""
        },
        "6": {
            "name": "AB. Ferm & Persson",
            "location": "Göteborg",
            "business": "Glasindustri och glasmästeri, förgylleri-, snickeri- och metallfabrik",
            "contact": {
                "office": "Kungsg. 22",
                "phone": [
                    "138035"
                ],
                "postgiro": "12231",
                "sales_offices": [],
                "telegraph": "Fermpersson, Göteborg",
                "factory_office": "",
                "factory_phone": ""
            },
            "financials": {
                "capital": "",
                "employees": {},
                "annual_turnover": "",
                "annual_production_value": ""
            },
            "foundation_year": "",
            "corporation_year": "",
            "board": [],
            "owners": [],
            "director": "",
            "managing_director": "",
            "sales_manager": "",
            "manager": ""
        }
    }
}