{
    "original": "Sievert—Silfa\n\nTelegr.-adr.: Manilla, Kalmar. Telefon:\n7, 215, 1515 o. 1819. Postgiro: 6409.\n\nAkt.-kap.: 600,000 kr. Antal\nindustriarb.: 175. Tillv.-värde pr år: 2,000,000 kr.\n— Firman grundad 1877.\n\nStyrelse: dir. Gunnar Ekström.\n\nVerkst. dir.: Hilding Linde.\n\n*AB. Max Sievert, Sundbyberg.\n\nMek. verkstäder i Sundbyberg och\nUlvsunda (Stockholm). Tillverkningen\nomfattar :\n\nvid Sundbyberg sv ericstäderna:\nlödlam-por, motorlampor, fotogenkök och andra\nvärmeapparater samt serietillverkade\nprecisionsdetaljer;\n\nvid Ulv sundaverkstäderna: elektr.\nindustriugnar för värmebehandling av järn,\nstål, metaller och keramiska produkter\nsåsom muffelugnar, degelugnar,\nsaltbads-ugnar (system: »Ajax-Hultgren»),\nkonvektionsugnar för anlöpning,\noljebads-ugnar, bränningsugnar för keramik och\ndekor, lacktorkningsugnar,\ninduktions-ugnar, galvaniseringsugnar, elektr.\nlaboratorieugnar m. fl. specialugnar,\ndestillationsapparater för industri, laboratorier\noch sjukhus, avfettningsapparater för\njärn- och metalldelar, ljudisolerade\ntalhytter för telefon etc. samt eldfast cement\n(märke: »Refractite») och eldfast\nstampmassa (märke: »Duromax»).\n\nVid Ulvsundakontoret bedrives även\nhandel med bl. a. mätinstrument för\nelektriska, kemiska och mekaniska\nstorheter samt med eldfasta tegel och\nisoleringstegel.\n\nDirektions- o. kassakontor:\nSundbyberg. Postbox 55. Telefon: Stockholm\n282530. Telegr.-adr.: Sievert, Stockholm.\nPostgiro: 626. Avd.-kontor: Ulvsunda,\ntelefon: Stockholm 252600.\n\nAkt.-kap.: 1,200,000 kr. Antal\nindustriarb.: 200. — Firman grundad 1882, bolag\n1906.\n\nStyrelse: dir. Hans Georg Sievert\n(ordf.), fru Signe Sievert, kapten R.\nG:son Sjöberg.\n\nVerkst. dir.: H. G. Sievert.\n\n*Max Sieverts Fabriks AB., Sieverts\nKabelverk, Sundbyberg.\n\nTillverkar telefonkablar,\nstarkströmskablar för hög- och lågspänning,\nkabel-garnityr, trycktäta kabelmuffar,\nkabelskåp, kondensatorer för kraftteknik,\ngum-miblyledningar, vulkaniserade ledningar,\nisolerad ledningstråd, armatur för\nsyra-haltiga, brand- och explosionsfarliga\nlokaler, armatur för lysrör. Varumärke:\n»Gebe»-armatur.\n\n4’\n\nFabrik och huvudkontor i Sundbyberg.\nPostadr.: Sundbyberg. Telegr.-adr.:\nSie-vertsfabrik, Stockholm. Telefon:\nStockholm »Sieverts Kabelverk». Postgiro:\n24000. Filialkontor i Stockholm,\nGöteborg, Malmö, Sundsvall och Örebro.\n\nAkt.-kap.: 7,500,000 kr. Antal\nindustriarb.: 1,200.\n\nBolaget, grundat 1888, äges av Telefon\nAB. L. M. Ericsson.\n\nStyrelse: bankdir. Marcus Wallenberg\n(ordf.), dir. Hemming Johansson, dir.\nGösta Klemming, dir. Georg Olsson.\n\nVerkst. dir.: Georg Olsson.\n\nSignalbolaget, Stockholm.\n\nSe L. M. Ericssons Signal AB., Sthlm.\n\nAB. Sigtuna Såg, Sigtuna.\n\nSågverk, hyvleri och snickerifabrik.\nTillverkar sågade och hyvlade trävaror\nsamt sportstugor.\n\nTelefon: 34. Postgiro: 26751. Repr. i\nStockholm: AB. Lundquist &amp; Lindroth,\nGötg. 93; telefon: 406070.\n\nAkt.-kap.: 150,000 kr. Antal\nindustriarb.: 25. Årstillv.: 900 stds trävaror. —\nFirman etabl. 1918, bolag 1935.\n\nVerkst. dir.: Börje Nordström.\n\nPlatschef i Sigtuna: K. Walter\nLarsson.\n\n*Sikfors Bruk, Sikfors.\n\nSe Hellefors Bruks AB., Hällefors.\n\nAB. Si-Ko, Stockholm.\n\nKemisk-teknisk industri. Tillverkar\ntandkräm och munvatten. Varumärken:\n»Si-Ko», »Si-Ko-Mint» o. »Si-Ko-Tol».\n\nKontor: Sickla; postadr.: Stockholm\n11. Telegr.-adr.: Siko, Stockholm.\nTelefon: 440800. Postgiro: 51800.\nAvd.-kontor: Göteborg, Odinsg. 6—8; Malmö,\nJacob Baggesg. 6; Jönköping.\n\nAkt.-kap.: 285,000 kr. Antal\nindustriarb.: 12. — Bolaget grundat 1929.\n\nVerkst. dir.: disp. Georg Palm.\n\nReklamchef: Ragnar F. Stange.\n\n*Silfa Fabriks AB., Alingsås.\n\nSilkefärgeri, filmtryckeri och\nappre-turverk. Utför tryckning av\nklädnings-tyger, dekorations- och möbeltyger,\nborddukar, schalar m. m.\n\nTelegr.-adr. o. telefon: Silfa, Alingsås\nPostgiro: 143941.\n\n4*",
    "structured": {
        "firms": {
            "1": {
                "name": "Sievert—Silfa",
                "location": "Manilla, Kalmar",
                "contact": {
                    "telegraph": "Manilla, Kalmar",
                    "phone": [
                        "7",
                        "215",
                        "1515",
                        "1819"
                    ],
                    "postgiro": "6409"
                },
                "financials": {
                    "capital": "600,000 kr",
                    "employees": {
                        "industriarb": 175
                    },
                    "annual_turnover": "2,000,000 kr",
                    "annual_production_value": "2,000,000 kr"
                },
                "foundation_year": 1877,
                "board": [
                    {
                        "name": "Gunnar Ekström",
                        "role": "dir"
                    }
                ],
                "manager": "Hilding Linde"
            },
            "2": {
                "name": "AB. Max Sievert",
                "location": "Sundbyberg",
                "contact": {
                    "office": "Sundbyberg",
                    "phone": "Stockholm 282530",
                    "postgiro": "626",
                    "sales_offices": [
                        {
                            "location": "Ulvsunda",
                            "phone": "Stockholm 252600"
                        }
                    ]
                },
                "financials": {
                    "capital": "1,200,000 kr",
                    "employees": {
                        "industriarb": 200
                    }
                },
                "foundation_year": 1882,
                "corporation_year": 1906,
                "board": [
                    {
                        "name": "Hans Georg Sievert",
                        "role": "ordf"
                    },
                    {
                        "name": "fru Signe Sievert"
                    },
                    {
                        "name": "kapten R. G:son Sjöberg"
                    }
                ],
                "manager": "H. G. Sievert"
            },
            "3": {
                "name": "Max Sieverts Fabriks AB.",
                "location": "Sundbyberg",
                "contact": {
                    "office": "Sundbyberg",
                    "phone": "Stockholm »Sieverts Kabelverk»",
                    "postgiro": "24000"
                },
                "financials": {
                    "capital": "7,500,000 kr",
                    "employees": {
                        "industriarb": 1,
                        "additionalProperties": 200
                    }
                },
                "corporation_year": 1888,
                "owners": [
                    "Telefon AB. L. M. Ericsson"
                ],
                "board": [
                    {
                        "name": "bankdir. Marcus Wallenberg",
                        "role": "ordf"
                    },
                    {
                        "name": "dir. Hemming Johansson"
                    },
                    {
                        "name": "dir. Gösta Klemming"
                    }
                ],
                "manager": "Georg Olsson"
            },
            "4": {
                "name": "AB. Sigtuna Såg",
                "location": "Sigtuna",
                "contact": {
                    "phone": "34",
                    "postgiro": "26751",
                    "sales_offices": [
                        {
                            "location": "Stockholm",
                            "phone": "AB. Lundquist & Lindroth, Götg. 93, telefon: 406070"
                        }
                    ]
                },
                "financials": {
                    "capital": "150,000 kr",
                    "employees": {
                        "industriarb": 25
                    },
                    "annual_production_value": "900 stds trävaror"
                },
                "foundation_year": 1918,
                "corporation_year": 1935,
                "manager": "Börje Nordström",
                "platschef": "K. Walter Larsson"
            },
            "5": {
                "name": "AB. Si-Ko",
                "location": "Stockholm",
                "contact": {
                    "office": "Sickla",
                    "phone": "Stockholm 11",
                    "postgiro": "51800",
                    "sales_offices": [
                        {
                            "location": "Göteborg",
                            "phone": "Odinsg. 6—8"
                        },
                        {
                            "location": "Malmö",
                            "phone": "Jacob Baggesg. 6"
                        },
                        {
                            "location": "Jönköping"
                        }
                    ]
                },
                "financials": {
                    "capital": "285,000 kr",
                    "employees": {
                        "industriarb": 12
                    }
                },
                "foundation_year": 1929,
                "board": [
                    {
                        "name": "disp. Georg Palm",
                        "role": "verkst"
                    },
                    {
                        "name": "Ragnar F. Stange",
                        "role": "reklamchef"
                    }
                ]
            },
            "6": {
                "name": "Silfa Fabriks AB.",
                "location": "Alingsås",
                "contact": {
                    "telegraph": "Alingsås",
                    "phone": "Alingsås",
                    "postgiro": "143941"
                },
                "foundation_year": 1877
            }
        }
    }
}