{
    "original": "Karlstad—Karosseriverkstäderna\n\näven engroshandel med\nmonteringsartik-lar.\n\nTelegr.-adr.: Stråfilt, Karlstad.\nTelefon: 10375 o. 10689. Postgiro: 27951.\nAvd.-kontor: Stockholm, Regeringsg. 56,\ntelefon: 110821; Göteborg, Knngsg. 50,\ntelefon: 133440.\n\nAkt.-kap.: 60,000 kr. Antal\nindustriarb.: 78. Tillv.-värde pr år: 300,000 kr.\n— Firman etabl. 1901, bolag 1934.\n\nStyrelse: byggm. O. Wästlund (ordf.),\nfröken H. Adler, fru S. Linderholm, disp.\nA. Wallentinson, apot. A. Öländer.\n\nVerkst. dir.: O. Wästlund.\n\nDisp.: A. Wallentinson.\n\nAB. Karlstads Syrgasfabrik,\n\nKarlstad.\n\nTillverkar syrgas.\n\nTelefon: 15435. Postgiro: 36146. —\nAkt.-kap.: 200,000 kr. Arb.-antal: 6.\nTillv.-värde pr år: 200,000 kr. — Bolaget\ngrundat 1922.\n\nStyrelse: byggm. O. Wästlund (ordf.),\ndir. Gunnar Dalén, ing. R. Ströberg.\nVerkst. dir.: Erik Wästlund.\nKontorschef: Folke Nilson.\n\n\"Karlstads Tagelspinneri, Adolf\nNyhlén AB., Karlstad.\n\nTillverkar spunnet tagel, kuddar och\ndynor av s. k. gummitagel (»Hairlok»),\ntagel för stoppningsändamål, tagel för\nborstbinderi-, pensel- och textilindustri.\n\nTelegr.-adr.: Tagelspinn, Karlstad.\nTelefon: 10562 o. 13562. Postgiro: 8952.\n\nAkt.-kap.: 200,000 kr. Antal\nindustriarb.: 30. Tillv.-värde pr år: 720,000 kr.\n— Firman etabl. 1904, bolag 1927.\n\nStyrelse: dir. Gunnar Nyhlén (ordf.),\ndisp. Bertil Nyhlén, fröken Brita Nyhlén.\n\nVerkst. dir.: Gunnar Nyhlén.\n\n\"Karlstads Varv, Karlstad.\n\nMek. verkstad, grovplåtslageri och\nfartygsslip för upp till 500 ton d. w. Utför\nnybyggnader av stålfartyg samt\nreparationer av stål- och träfartyg, elektr.\nsvetsningsarbeten, maskinarbeten,\ngrovplåts-och cisternarbeten. Varvet äges av\nVärmlands Rederi AB., Karlstad, och drives\njämsides med rederirörelsen.\n\nTelegr.-adr.: Slipen, Karlstad. Telefon:\n15200 o. 11599 (varvet). — Akt.-kap.:\n415,250 kr. Antal industriarb.: 50.\nTillv.-värde pr år: 500,000 kr. — Varvsrörelsen\netabl. 1918.\n\nStyrelse: dir. Hjalmar Nerman (ordf.),\ndir. Gustaf Hemmingson, dir. Bror\nPettersson.\n\nChef: Bror Pettersson.\n\nDriftschef: skeppsbyggm. Wilhelm\nAndersson.\n\nKarlströms Syfabriks AB.,\n\nStockholm.\n\nSe Kasy AB., Stockholm.\n\n\"Karlsviks Sågverk, Sundsvall.\n\nSe Ankarsviks Ångsågs AB., Sundsvall.\n\n\"Karmansbo Bruks AB.,\n\nKarmansbo.\n\nJärnbruk med lancashireverk, grov-,\nmedium- och universalvalsverk i\nKarmansbo (Västmanl. l.). Tillverkar smitt\noch valsat lancashirejärn, råstänger m. m.\nBolaget driver även jordbruk och\nkvarnrörelse samt distribuerar elektrisk kraft.\n\nFörsäljn.-kontor: Stockholm,\nSkeppsbron 34. Telegr.-adr.: Karmansboverken,\nStockholm. Telefon: 113942. Postgiro:\n3218. Brukskontor: Karmansbo. Telefon:\nSkinnskatteberg 3011.\n\nAkt.-kap.: 75,000 kr. Antal\nindustriarb.: 30. Tillv.-värde pr år: 540,000 kr.\n\nBruket anlagt 1611, nuv. bolag grundat\n1922.\n\nStyrelse: dir. Carl Fr. Löwenhielm\n(ordf.), bankdir. Erik Dahlberg, disp. L.\nPress.\n\nVerkst. dir. o. disp.: L. Press (Sthlm).\n\nPlatschef: M. Broström.\n\nKarosseri AB. Norrmalm,\n\nStockholm.\n\nVagn- och sadelmakeri, måleri och mek.\nverkstad samt plåtslageri. Tillverkar\nka-rosserier samt utför\nautomobilreparatio-ner.\n\nKontor: Norrbackag. 33. Telefon:\n233185. Postgiro: 4812.\n\nAkt.-kap.: 60,000 kr. Antal\nindustriarb.: 30. Tillv.-värde pr år: 250,000 kr.\n— Firman etabl. 1919, nuv. bolag\ngrundat 1925.\n\nStyrelse: dir. Arvid Johansson (ordf.),\nverkm. Gunnar Espelund, kamrer Lars\nTorsmark.\n\nVerkst. dir.: Arvid Johansson.\n\n\" Karosser iver kstäderna, Katrineholm.\n\nSe Svenska Karosseri Verkstäderna\nAB., Katrineholm.",
    "structured": {
        "1": {
            "name": "Karosseriverkstäderna",
            "location": "Karlstad",
            "business": "Vagn- och sadelmakeri, måleri och mek. verkstad samt plåtslageri.",
            "contact": {
                "office": "Stråfilt, Karlstad",
                "phone": [
                    "10375",
                    "10689"
                ],
                "postgiro": "27951",
                "sales_offices": [
                    {
                        "location": "Stockholm, Regeringsg. 56",
                        "phone": "110821"
                    },
                    {
                        "location": "Göteborg, Knngsg. 50",
                        "phone": "133440"
                    }
                ]
            },
            "financials": {
                "capital": "60,000 kr",
                "employees": {
                    "industriarb": 78
                },
                "annual_turnover": "300,000 kr",
                "annual_production_value": "300,000 kr"
            },
            "foundation_year": 1901,
            "corporation_year": 1934,
            "board": [
                {
                    "name": "byggm. O. Wästlund",
                    "role": "ordf."
                },
                {
                    "name": "fröken H. Adler",
                    "role": " "
                },
                {
                    "name": "fru S. Linderholm",
                    "role": ""
                },
                {
                    "name": "disp. A. Wallentinson",
                    "role": ""
                },
                {
                    "name": "apot. A. Öländer",
                    "role": ""
                }
            ],
            "director": "O. Wästlund"
        },
        "2": {
            "name": "AB. Karlstads Syrgasfabrik",
            "location": "Karlstad",
            "business": "Tillverkar syrgas",
            "contact": {
                "office": "",
                "phone": [
                    "15435"
                ],
                "postgiro": "36146"
            },
            "financials": {
                "capital": "200,000 kr",
                "employees": {
                    "arb": 6
                },
                "annual_turnover": "",
                "annual_production_value": "200,000 kr"
            },
            "foundation_year": 1922,
            "board": [
                {
                    "name": "byggm. O. Wästlund",
                    "role": "ordf."
                },
                {
                    "name": "dir. Gunnar Dalén",
                    "role": ""
                },
                {
                    "name": "ing. R. Ströberg",
                    "role": ""
                }
            ],
            "director": "Erik Wästlund",
            "manager": "Folke Nilson"
        },
        "3": {
            "name": "Karlstads Tagelspinneri, Adolf Nyhlén AB.",
            "location": "Karlstad",
            "business": "Tillverkar spunnet tagel, kuddar och dynor av s. k. gummitagel (»Hairlok»), tagel för stoppningsändamål, tagel för borstbinderi-, pensel- och textilindustri.",
            "contact": {
                "office": "Tagelspinn, Karlstad",
                "phone": [
                    "10562",
                    "13562"
                ],
                "postgiro": "8952"
            },
            "financials": {
                "capital": "200,000 kr",
                "employees": {
                    "industriarb.": 30
                },
                "annual_turnover": "720,000 kr",
                "annual_production_value": "720,000 kr"
            },
            "foundation_year": 1904,
            "corporation_year": 1927,
            "board": [
                {
                    "name": "dir. Gunnar Nyhlén",
                    "role": "ordf."
                },
                {
                    "name": "disp. Bertil Nyhlén",
                    "role": ""
                },
                {
                    "name": "fröken Brita Nyhlén",
                    "role": ""
                }
            ],
            "director": "Gunnar Nyhlén"
        },
        "4": {
            "name": "Karlstads Varv",
            "location": "Karlstad",
            "business": "Mek. verkstad, grovplåtslageri och fartygsslip för upp till 500 ton d. w.",
            "contact": {
                "office": "Slipen, Karlstad",
                "phone": [
                    "15200",
                    "11599 (varvet)"
                ]
            },
            "financials": {
                "capital": "415,250 kr",
                "employees": {
                    "industriarb.": 50
                },
                "annual_turnover": "500,000 kr",
                "annual_production_value": "500,000 kr"
            },
            "corporation_year": 1918,
            "board": [
                {
                    "name": "dir. Hjalmar Nerman",
                    "role": "ordf."
                },
                {
                    "name": "dir. Gustaf Hemmingson",
                    "role": ""
                },
                {
                    "name": "dir. Bror Pettersson",
                    "role": ""
                }
            ],
            "manager": "Bror Pettersson",
            "sales_manager": "skeppsbyggm. Wilhelm Andersson"
        },
        "5": {
            "name": "Karmansbo Bruks AB.",
            "location": "Karmansbo (Västmanl. l.)",
            "business": "Järnbruk med lancashireverk, grov-, medium- och universalvalsverk i Karmansbo (Västmanl. l.).",
            "contact": {
                "office": "",
                "phone": "Skinnskatteberg 3011",
                "postgiro": "3718"
            },
            "financials": {
                "capital": "75,000 kr",
                "employees": {
                    "industriarb.": 30
                },
                "annual_turnover": "540,000 kr"
            },
            "corporation_year": 1922,
            "board": [
                {
                    "name": "dir. Carl Fr. Löwenhielm",
                    "role": "ordf."
                },
                {
                    "name": "bankdir. Erik Dahlberg",
                    "role": ""
                },
                {
                    "name": "disp. L. Press",
                    "role": ""
                }
            ],
            "director": "Verkst. dir. o. disp.: L. Press (Sthlm)",
            "manager": "M. Broström"
        },
        "6": {
            "name": "Karosseri AB. Norrmalm",
            "location": "Stockholm",
            "business": "Tillverkar karosserier samt utför automobilreparationer.",
            "contact": {
                "office": "Norrbackag. 33",
                "phone": "233185",
                "postgiro": "4812"
            },
            "financials": {
                "capital": "60,000 kr",
                "employees": {
                    "industriarb.": 30
                },
                "annual_turnover": "",
                "annual_production_value": "250,000 kr"
            },
            "corporation_year": 1925,
            "board": [
                {
                    "name": "dir. Arvid Johansson",
                    "role": "ordf."
                },
                {
                    "name": "verkm. Gunnar Espelund",
                    "role": ""
                },
                {
                    "name": "kamrer Lars Torsmark",
                    "role": ""
                }
            ],
            "director": "Arvid Johansson"
        }
    }
}