{
    "original": "Nordiska\n\n*AB. Nordiska Armaturfabrikerna,\n(Nordarmatur), Linköping.\n\nFabriker i Linköping, Kungsör, Lund\noch Solna.\n\nBolaget tillverkar armatur av stål,\ngjutjärn och metall för ång- och\nvärmetekniska anläggningar, gas, vatten m. m.,\nsyrafast armatur för mejerier och\ncellulosafabriker, manometrar, vakuummetrar\noch termometrar, flyginstrument,\njärn-vägsmateriel, tryckluftbromsar (system\nKunze-Knorr och Hildebrand-Knorr),\nen-kammarbromsar (system Knorr),\nsmörj-dynor (patent Klein-NAF) samt\noljeeldningsapparater och\nvattenreningsanläggningar, vattenmätare,\ncirkulationsutrustningar (system NAF-Schauffelberger) för\ncellulosakokare ävensom silplåtar,\nperforerad plåt, metall- och lättmetallgjutgods,\nvarmpressat och pressgjutet metallgods\nm. m. Varumärken: »Nordarmatur» o.\n»NAF». Bolaget säljer även slussventiler\nför vatten och gas samt\nregleringsinstrument av främmande fabrikat.\n\nHuvudkontor: Linköping. Telegr.-adr.\no. telefon: »Armaturbolaget». Postgiro:\n560. Försäljn.-kontor: Stockholm,\nRege-ringsg. 61; postadr.: box 7141,\nStockholm 7; telegr.-adr. o. telefon:\n»Armaturbolaget»; Göteborg, Kronhusg. 16;\ntelefon: 170915; telegr.-adr.:\n»Armaturbolaget», Göteborg; Malmö, Lodg. 4\n(Industrihamnen); telefon: 71195;\ntelegr.-adr.: »Lundarmatur», Malmö; Sundsvall;\ntelefon: 4042 o. 5440; telegr.-adr.:\n»Armaturbolaget», Sundsvall.\n\nAkt.-kap.: 8,850,000 kr. Antal\nindustriarb.: 1,100.\n\nBolaget grundat år 1919 såsom\nfortsättning på Nordiska Armatur AB.,\nbildat 1911 genom sammanslagning av äldre\nföretag inom armaturbranschen, av vilka\ndet äldsta startades 1889. ^\n\nStyrelse: bruksdisp. Wiking Johnsson\n(ordf.), kommerserådet Axel F. Enström,\ndir. Helge Norlander, dir. B. R.\nGyllenram, dir. Kjell Hägglöf, generalkonsul\nRagnar Söderberg.\n\nVerkst. dir.: B. R. Gyllenram.\nEkonomichef: kamrer I. Rothlind.\nFörsäljn.-chef: civiling. G. Lundgren.\nInköpschef: Wictor Nilsson.\nÖveringenjörer: för fabrikationen: Erik\nLarsson o. C.-G. Syren; för konstr.-avd.\nErland Jung.\n\nAvd.-chefer för försäljningen:\nanläggningar för cellulosaindustrien:\nO. Wirén;\n\nbyggnadsarmatur: F. Wellin (Sthlm);\nindustriarmatur: G. Dorff;\njärnvägsmateriel: Olof Tunell;\nvattenrening: Erik Kantelius;\nexport: O. Wirén.\n\n\"Nordiska Bleckemballagefabriken,\n\nOävle.\n\nTillverkar blankt och dekorerat\nbleckemballage, kärl och innerlådor för apotek;\nutför pressningar i tunnplåt.\n\nTelefon: 3509. Postgiro: 32395. —\nAntal industriarb.: 10. — Firman etabl. 1922.\n\nÄgare o. chef: Wilhard Dahlgren.\n\nAB. Nordiska Fanérfabriken,\n\nVimmerby.\n\nTillverkar fanér vid fabrik i Vimmerby\n(Kalmar l.).\n\nTelegr.-adr.: Nordf anér, Vimmerby.\nTelefon: 175 o. 715. Postgiro: 269660.\n\nAkt.-kap.: 100,000 kr. Antal\nindustriarb.: 20. — Bolaget grundat 1944.\n\nVerkst. dir.: Axel Bohman\n(Oskarshamn).\n\nFabrikschef: Tage Köhler.\n\n\"Nordiska Fjäderfabriken AB.,\n\nMalmö.\n\nTillverkar fjäder, dun och kapock,\ndun-och vaddtäcken, kuddar, vaddmadrasser,\ndun- och vaddsovsäckar, babypåsar m. m.\nVarumärken: »Sveamadrassen» o.\n»Cara-vansovsäcken».\n\nHuvudkontor: Malmö, Regementsg. 52.\nTelegr.-adr.: Chinaimport, Malmö.\nTelefon: 71730. Postgiro: 39015.\nAvd.-kontor: Stockholm, Regeringsg. 109, telefon:\n214175—76; Göteborg, Första Långg. 21,\ntelefon: 120612.\n\nAkt.-kap.: 100,000 kr. Antal\nindustriarb.: 100. — Bolaget grundat 1929.\n\nStyrelse: adv. Rolf Nordenstedt (ordf.),\nciviling. Frans G. Liljenroth.\n\nDisp.: Henning Larsen.\n\nKamrer: Bengt Engberg.\n\nFilialchefer: i Stockholm: Thomas\nMor-tensen; i Göteborg: Åke Gustafson.\n\n\"Nordiska Gummifabriks AB.\nÖverman, Sundbyberg.\n\nTillverkar halvpneumatiska\nautomobil-ringar, massiva ringar för vägmaskiner,\nläderpackningar och läderdetaljer för\nindustrien, packningar och andra\ngummiartiklar, plastics folier och plattor;\nut-utför vibrationsfri lagring. Varumärken:\n»Pendelastic», »Överman», »Nopoline» o.\n»Nordover».\n\nTelegr.-adr.: Nordover, Stockholm.\nTelefon: 282650. Postgiro: 1446. —\nAkt.-kap.: 700,000 kr. Antal industriarb.: 120.\n— Firman etabl. 1922.",
    "structured": {
        "firms": [
            {
                "name": "AB. Nordiska Armaturfabrikerna",
                "location": "Linköping",
                "business": "Tillverkning av armatur av stål, gjutjärn och metall för ång- och värmetekniska anläggningar, gas, vatten m. m., syrafast armatur för mejerier och cellulosafabriker, manometrar, vakuummetrar och termometrar, flyginstrument, järn-vägsmateriel, tryckluftbromsar (system Kunze-Knorr och Hildebrand-Knorr), en-kammarbromsar (system Knorr), smörj-dynor (patent Klein-NAF) samt oljeeldningsapparater och vattenreningsanläggningar, vattenmätare, cirkulationsutrustningar (system NAF-Schauffelberger) för cellulosakokare ävensom silplåtar, perforerad plåt, metall- och lättmetallgjutgods, varmpressat och pressgjutet metallgods m. m. Bolaget säljer även slussventiler för vatten och gas samt regleringsinstrument av främmande fabrikat.",
                "contact": {
                    "office": "Linköping",
                    "phone": [
                        "Armaturbolaget"
                    ],
                    "postgiro": "560",
                    "head_office": "Linköping",
                    "sales_offices": [
                        {
                            "location": "Stockholm",
                            "phone": "Regeringsg. 61"
                        },
                        {
                            "location": "Göteborg",
                            "phone": "Kronhusg. 16"
                        },
                        {
                            "location": "Malmö",
                            "phone": "Lodg. 4 (Industrihamnen)"
                        },
                        {
                            "location": "Sundsvall",
                            "phone": "4042 o. 5440"
                        }
                    ]
                },
                "financials": {
                    "capital": "8,850,000 kr",
                    "employees": {
                        "industriarb.": 1100
                    }
                },
                "foundation_year": 1919,
                "predecessor": "Nordiska Armatur AB."
            },
            {
                "name": "Nordiska Bleckemballagefabriken",
                "location": "Uävle",
                "business": "Tillverkning av blankt och dekorerat bleckemballage, kärl och innerlådor för apotek; utför pressningar i tunnplåt.",
                "contact": {
                    "phone": "3509",
                    "postgiro": "32395"
                },
                "financials": {
                    "employees": {
                        "industriarb.": 10
                    }
                },
                "foundation_year": 1922,
                "director": "Wilhard Dahlgren"
            },
            {
                "name": "AB. Nordiska Fanérfabriken",
                "location": "Vimmerby",
                "business": "Tillverkning av fanér",
                "contact": {
                    "telegraph": "Nordfanér",
                    "phone": [
                        "175",
                        "715"
                    ],
                    "postgiro": "269660"
                },
                "financials": {
                    "capital": "100,000 kr",
                    "employees": {
                        "industriarb.": 20
                    }
                },
                "corporation_year": 1944,
                "director": "Axel Bohman"
            },
            {
                "name": "Nordiska Fjäderfabriken AB.",
                "location": "Malmö",
                "business": "Tillverkning av fjäder, dun och kapock, dun-och vaddtäcken, kuddar, vaddmadrasser, dun- och vaddsovsäckar, babypåsar m. m. Varumärken: »Sveamadrassen» o. »Caravansovsäcken».",
                "contact": {
                    "office": "Malmö",
                    "phone": [
                        "Chinaimport"
                    ],
                    "postgiro": "39015",
                    "sales_offices": [
                        {
                            "location": "Stockholm",
                            "phone": "Regeringsg. 109"
                        },
                        {
                            "location": "Göteborg",
                            "phone": "Första Långg. 21"
                        }
                    ]
                },
                "financials": {
                    "capital": "100,000 kr",
                    "employees": {
                        "industriarb.": 100
                    }
                },
                "foundation_year": 1929
            },
            {
                "name": "Nordiska Gummifabriks AB.",
                "location": "Sundbyberg",
                "business": "Tillverkning av halvpneumatiska automobil-ringar, massiva ringar för vägmaskiner, läderpackningar och läderdetaljer för industrin, packningar och andra gummiartiklar, plastfolier och plattor; utför vibrationsfri lagring. Varumärken: »Pendelastic», »Överman», »Nopoline» o. »Nordover».",
                "contact": {
                    "telegraph": "Nordover",
                    "phone": "282650",
                    "postgiro": "1446"
                },
                "financials": {
                    "capital": "700,000 kr",
                    "employees": {
                        "industriarb.": 120
                    }
                },
                "corporation_year": 1922
            }
        ]
    }
}