{
    "original": "Pe llerin—Pershyttan\n\n*AB. Pellerins Margarinfabrik,\n\nGöteborg.\n\nTillverkar margarin, konstister och\nkokossmör.\n\nKontor: Riddarg. 15. Telegr.-adr.:\nPel-lerin, Göteborg. Telefon: 172360.\nPostgiro: 5550. Försäljningen sker genom\nMargarinbolaget AB., Stockholm (se detta\nbolag).\n\nAkt.-kap.: 6,000,000 kr. Antal\nindustriarb.: 70. Tillv.-värde pr år: 8,000,000 kr.\n\n—\tFirman etabl. 1894, bolag 1918.\n\nStyrelse: konsul Carl Ekman (ordf.),\n\ndir. Sven Malmberg, fil. dr Harald\nNordenson, kammarh. Fredrik af Sandeberg,\ndir. Sigfrid Wedel.\n\nVerkst. dir.: S. Wedel.\n\nFabrikschef: Johan Eriksson.\n\n*Penselfabriken Perfect AB.,\n\nBankeryd.\n\nPensel- och kamfabrik i Bankeryd\n(Jönköp. l.). Tillverkar penslar,\nmålarbor-star, rakborstar och kammar samt div.\nträartiklar.\n\nTelegr.-adr. o. telefon: Perfect,\nBankeryd. Postgiro: 31477.\n\nAkt.-kap.: 275,400 kr. Antal\nindustriarb.: 140. Tillv.-värde pr år: 2,000,000 kr.\n\n—\tFirman grundad 1920, bolag 1946.\n\nStyrelse o. verkst. dir.: Harry Isaksson.\n\nAB. Penta Utombordsmotorer,\n\nStockholm.\n\nFörsäljer »Penta»-utombordsmotorer o.\nbåtar.\n\nKontor: S:t Eriksg. 63. Telegr.-adr.:\nPentaoutboards, Stockholm. Telefon:\n522002. Postgiro: 2621.\n\nAkt.-kap.: 25,000 kr. — Bolaget\ngrundat 1943.\n\nStyrelse: dir. K. Hyllén, dir. S. Widell.\n\nFörsäljn.-chef: ing. Otto Virgin.\n\n*Pentaverken, Skövde.\n\nSe AB. Volvo, Göteborg.\n\nPerfekt, Konfektions AB.,\n\nLandskrona.\n\nSe Konfektions AB. Perfekt,\nLandskrona.\n\nAB. Perfekta-Tryck, Arlöv.\n\nBoktryckeri. Utför bok- och\ntidningstryck, vetenskapliga arbeten,\nmaskinbok-föringskort, reklamtryck m. m. samt\ntillverkar kulturpappkrukor (märke:\n»Perfekta»).\n\nTelefon: »Perfektatryck». Postgiro:\n31583. — Akt.-kap.: 110,000 kr. Antal\nindustriarb.: 49. Tillv.-värde pr år: 610,000\nkr. — Firman etabl. 1927, bolag 1931.\n\nVerkst. dir.: boktr. Martin Jönsson.\n\n*AB. Perforerad Plåt, Storvik.\n\nStansar plåt, träfiberplattor m. m. vid\nfabrik i Storvik (Gävleb. l.).\n\nTelefon: 312. Postgiro: 80437. —\nAkt.-kap.: 48,000 kr. Antal industriarb.: 30.\nTillv.-värde pr år: 700,000 kr. —- Bolaget\ngrundat 1932.\n\nStyrelse o. chefer: E. Widström, J. E.\nWestlund o. A. Isberg.\n\n(Jfr annons nr 32.)\n\n*AB. Perioden, Norrköping.\n\nBomullsspinneri i Nyköping.\nTillverkar bomullsgarn.\n\nHuvudkontor: Norrköping.\nTelegr.-adr.: Perioden, Norrköping. Telefon:\n20024 o. 20613. Postgiro: 11088.\nFabriks-kontor: Nyköping. Telefon: 24.\n\nAkt.-kap.: 846,000 kr. Antal\nindustriarb.: 140. Tillv.-värde pr år: 1,300,000 kr.\n\n—\tBolaget grundat 1872.\n\nStyrelse: bankdir. L. O. Hessner,\nciviling. Martin Ljungberg, disp. And. J.\nMalmberg.\n\nVerkst. dir. o. disp.: And. J.\nMalmberg.\n\nVerkmäst.: ing. O. Hansson.\n\n*Persbergs Gruf ve AB., Persberg.\n\nJärnmalmsgruvor vid Persberg (VärmL\n1.). Bryter järnmalm och förarbetar\nhuvuddelen därav till slig. Bolaget idkar\njämväl jordbruk och skogshantering samt\nkalkstensbrytning.\n\nTelegr.-adr.: Gruvorna, Filipstad.\nTelefon: Persberg 21. Postgiro: 10624.\n\nAkt.-kap.: 2,750,000 kr. Antal\nindustriarb.: 135. Prod.-värde pr år: 900,000 kr.\n\n—\tBolaget grundat 1865.\n\nStyrelse: disp. N. Danielsen (ordf.),\ndisp. Gunnar Wallroth, disp. Thorsten\nWigelius.\n\nDisp.: Gunnar Wallroth.\n\nKamrer: Gösta Hallgren.\tV\n\nAB. Pershyttan, Nora.\n\nMasugn vid Pershyttan (Örebro ^ l.).\nTillverkar tackjärn,. Bolaget idkar\njäim-väl jordbruk och skogshantering.\n\nHuvudkontor o. ensamförsäljn.:\nStockholm, A. Johnson &amp; Co., Stureplan 3.\nTelegr.-adr. o. telefon: Johnsons,\nStockholm. Brukskontor: Nora. Telegr.-adr.:\nPershyttan, Nora.",
    "structured": {
        "1": {
            "name": "AB. Pellerins Margarinfabrik",
            "location": "Göteborg",
            "business": "Margarintillverkning, konstister och kokossmör",
            "contact": {
                "office": "Riddarg. 15",
                "phone": [
                    "172360"
                ],
                "postgiro": "5550",
                "telegraph": "Pel-lerin, Göteborg"
            },
            "financials": {
                "capital": "6,000,000 kr",
                "employees": {
                    "industriarb": 70
                },
                "annual_turnover": "8,000,000 kr",
                "annual_production_value": "8,000,000 kr"
            },
            "foundation_year": 1894,
            "corporation_year": 1918,
            "board": [
                {
                    "name": "konsul Carl Ekman",
                    "role": "ordf"
                },
                {
                    "name": "dir. Sven Malmberg",
                    "role": ""
                },
                {
                    "name": "fil. dr Harald Nordenson",
                    "role": ""
                },
                {
                    "name": "kammarh. Fredrik af Sandeberg",
                    "role": ""
                },
                {
                    "name": "dir. Sigfrid Wedel",
                    "role": ""
                }
            ]
        },
        "2": {
            "name": "Penselfabriken Perfect AB.",
            "location": "Bankeryd",
            "business": "Pensel- och kamtillverkning",
            "contact": {
                "office": "",
                "phone": [],
                "postgiro": "31477",
                "telegraph": "Perfect, Bankeryd"
            },
            "financials": {
                "capital": "275,400 kr",
                "employees": {
                    "industriarb": 140
                },
                "annual_turnover": "2,000,000 kr",
                "annual_production_value": "2,000,000 kr"
            },
            "foundation_year": 1920,
            "corporation_year": 1946,
            "board": [
                {
                    "name": "Harry Isaksson",
                    "role": ""
                }
            ]
        },
        "3": {
            "name": "AB. Penta Utombordsmotorer",
            "location": "Stockholm",
            "business": "Försäljning av »Penta»-utombordsmotorer och båtar",
            "contact": {
                "office": "S:t Eriksg. 63",
                "phone": [
                    "522002"
                ],
                "postgiro": "2621",
                "telegraph": "Pentaoutboards, Stockholm"
            },
            "financials": {
                "capital": "25,000 kr"
            },
            "corporation_year": 1943,
            "board": [
                {
                    "name": "dir. K. Hyllén",
                    "role": ""
                },
                {
                    "name": "dir. S. Widell",
                    "role": ""
                }
            ],
            "sales_manager": "ing. Otto Virgin"
        },
        "4": {
            "name": "AB. Perfekta-Tryck",
            "location": "Arlöv",
            "business": "Boktryckeri och tillverkning av kulturpappkrukor (märke: »Perfekta»)"
        },
        "5": {
            "name": "AB. Perforerad Plåt",
            "location": "Storvik",
            "business": "Stansning av plåt, träfiberplattor m.m.",
            "contact": {
                "phone": [
                    "312"
                ],
                "postgiro": "80437"
            },
            "financials": {
                "capital": "48,000 kr",
                "employees": {
                    "industriarb": 30
                },
                "annual_turnover": "700,000 kr",
                "annual_production_value": "700,000 kr"
            },
            "corporation_year": 1932,
            "board": [
                {
                    "name": "E. Widström",
                    "role": ""
                },
                {
                    "name": "J. E. Westlund",
                    "role": ""
                },
                {
                    "name": "A. Isberg",
                    "role": ""
                }
            ]
        },
        "6": {
            "name": "AB. Perioden",
            "location": "Norrköping",
            "business": "Bomullsspinneri och tillverkning av bomullsgarn",
            "contact": {
                "office": "Norrköping",
                "phone": [
                    "20024",
                    "20613"
                ],
                "postgiro": "11088"
            },
            "financials": {
                "capital": "846,000 kr",
                "employees": {
                    "industriarb": 140
                },
                "annual_turnover": "1,300,000 kr",
                "annual_production_value": "1,300,000 kr"
            },
            "corporation_year": 1872,
            "board": [
                {
                    "name": "bankdir. L. O. Hessner",
                    "role": ""
                },
                {
                    "name": "civiling. Martin Ljungberg",
                    "role": ""
                },
                {
                    "name": "disp. And. J. Malmberg",
                    "role": ""
                }
            ],
            "managing_director": "And. J. Malmberg",
            "sales_manager": "ing. O. Hansson"
        },
        "7": {
            "name": "Persbergs Grufve AB.",
            "location": "Persberg",
            "business": "Järnmalmsbrytning, jordbruk, skogshantering och kalkstensbrytning",
            "contact": {
                "phone": [
                    "Persberg 21"
                ],
                "postgiro": "10624"
            },
            "financials": {
                "capital": "2,750,000 kr",
                "employees": {
                    "industriarb": 135
                },
                "annual_turnover": "900,000 kr",
                "annual_production_value": "900,000 kr"
            },
            "corporation_year": 1865,
            "board": [
                {
                    "name": "disp. N. Danielsen",
                    "role": "ordf."
                },
                {
                    "name": "disp. Gunnar Wallroth",
                    "role": ""
                },
                {
                    "name": "disp. Thorsten Wigelius",
                    "role": ""
                }
            ],
            "sales_manager": "Gunnar Wallroth"
        },
        "8": {
            "name": "AB. Pershyttan",
            "location": "Nora",
            "business": "Tackjärnstillverkning, jordbruk och skogshantering",
            "contact": {
                "office": "Stockholm, A. Johnson & Co., Stureplan 3",
                "telegraph": "Pershyttan, Nora"
            }
        }
    }
}