{
    "original": "S hyllb e rg—S Jcåne b ryg ge rie r\n\nTelegr.-adr.: Skyddskläder, Fristad.\nTelefon: Borås 60016, 60126 o. 60055.\nPostgiro: 720.\n\nAkt.-kap.: 250,000 kr. Antal\nindustriarb.: 85. — Bolaget grundat 1925.\n\nStyrelse: dir. John Magnuson (ordf.),\nadv. T. Bertoldy.\n\nVerkst. dir.: J. Magnuson.\n\n\"Skyiibergs Bruks AB.y SJcyllberg.\n\nSnickerifabrik och mek. verkstad vid\nSkyllberg; järnmanufakturverk vid\nKårberg, Skyllberg, torvströfabrik vid\nMariedam (samtl. i Örebro l.).\n\nTillverkar järntråd, taggtråd, staglinor,\npress- och trådspik, sågade och hyvlade\nträvaror, slipers, oimpregnerade och\nimpregnerade stolpar, sulfit- och sulfatved,\nbyggnadssnickerier, träkol, A- och B-tjära,\nmetanol, bränntorv, torvströ och torvmull.\nBolaget idkar jämväl jordbruk och\nskogshantering och kvarnrörelse samt\ndistribution av elkraft.\n\nTelegr.-adr.: Skyllberg, Askersund.\nTelefon: »Bruket», Skyllberg. Postgiro:\n25870.\n\nAkt.-kap.: 3,000,000 kr. Arb.-antal:\n800, varav 350 industriarb. Tillv.-värde\npr år: 8,000,000 kr.\n\nBolaget grundat 1876.\n\nRepresentanter för järnvaror: i S t o c\nk-holm: AB. Odelberg &amp; Olson, Kungsg.\n4 A, telefon: »Odelbergolson»; Nils\nAhlgren AB., Skeppsbron 32, telefon: 207701\no. Rundquist &amp; Schultz AB., Slussplan 9,\ntelefon: »Rundquist &amp; Schultz»; i\nGöteborg: Axel H. Ågren AB., St. Badhusg.\n38, telefon: »Axel H. Ågren», o. Larsson,\nSeaton &amp; Co. AB., Marieholmsg. 36,\ntelefon: »Larsson-Seaton»; i Falun: AB.\nJ. A. Göthes Järnvaruaffär, telefon:\n»Göthes järn»; i Karlstad: Herman\nGeijer &amp; Co. AB., telefon: 15445; för\nexport: Acierex AB., Stockholm,\nArse-nalsg. 2, telefon: 235355; för\nträvaror: i Stockholm: Gustaf öhrn AB.,\nArsenalsg. 6, telefon: 104119; i\nGöteborg: Harald Wennerberg, V. Hamng. 5,\ntelefon: 131017 o. AB. Trätälja, V.\nHamng. 5, telefon: 132142; i London:\nPrice &amp; Pierce, Ltd., 27, Clements Lane,\nLondon E. C. 4.\n\nStyrelse: bruksäg. Ivan Svensson\n(ordf.), bankdir. Wilhelm Graf (v. ordf.),\nfru Valborg Hjelt, major Sten Sandgren.\n\nVerkst. dir.: Ivan Svensson.\n\nKontorschef: B. Wirsén.\n\nFabrikschef er: för\njärnmanufakturverket: Gunnar Folkeson; för verkstäderna i\nSkyllberg: ing. Olov Bergquist; för\nsågverket : B. Modin; för kraftförvalt.: ing.\nCarl Erik Andersson.\n\nSkogschef: jägm. Herman Eriksson.\n\nSkyltfabriken, AB. Svenska,\n\nHagalund.\n\nSe AB. Svenska Skyltfabriken,\nHagalund.\n\n*Skyttorps Snickerifabrik, Shyttorp.\n\nTillverkar trappor och\nbyggnadssnickerier, spec. köksinredningar, vid fabrik i\nSkyttorp (Uppsala l.).\n\nTelefon: 14. Postgiro: 166420. —\nAntal industriarb.: 40. Tillv.-värde pr år:\n500,000 kr. — Firman etabl. 1927.\n\nÄgare o. chef: byggm. Gottfrid\nLindgren.\n\nDisp.: Sven Jansson.\n\nSkåne, AB. Tekniska Fabriken,\n\nMalmö.\n\nSe AB. Tekniska Fabriken Skåne,\nMalmö. •\n\n\"AB. Skånebryggerier,\n\nHälsingborg.\n\nBryggerier i Hälsingborg, Eslöv,\nKristianstad (Finlands Bryggeri) och\nKlippan (Kristianst. l.), Landskrona\n(Krön-leins Bryggeri), Sölvesborg och\nÄngelholm. Tillverkar öl, malt, läskedrycker\noch kolsyrat vatten.\n\nHuvudkontor: Hälsingborg.\nTelegr.-adr.: Skånebryggerier, Hälsingborg.\nTelefon: 20740. Postgiro: 14260. Avd.-kontor\nvid samtliga bryggerier. Ensamförsälj. av\nmalt: Christian Berner, Göteborg, St.\nNygatan 5, telefon: 171010.\n\nAkt.-kap.: 5,200,000 kr. Antal\nindustriarb.: 214, varav i Hälsingborg 59, i Eslöv\n22, i Kristianstad 39, i Klippan 41, i\nLandskrona 21, i Sölvesborg 10 och i\nÄngelholm 22. Tillv.-värde pr år:\n3,000,000 kr.\n\nBolaget grundat 1918.\n\nStyrelse: f. d. landshövd. Johan Nilsson\n(ordf.), v. konsul O. Löfwall (v. ordf.),\ndisp. Arvid Jönsson, dir. Anders\nKrön-lein, dir. K.-E. Löfwall, disp. Nils\nRosander, dir. Ivar Sandberg.\n\nVerkst. dir.: K.-E. Löfwall.\n\nV. verkst. dir.: Arvid Jönsson.\n\nKamrer: Kjell Stewénius.\n\nDisponenter:\n\ni Hälsingborg: K.-E. Löfwall;\n\ni Klippan: J. Sonesson;\n\ni Landskrona: Hugo Aspegrén;\n\ni Ängelholm: Nils Rosander;\n\ni Eslöv: S. Hacksell;\n\ni Kristianstad: Gustav Rosander;\n\ni Sölvesborg: E. Alsén.",
    "structured": {
        "1": {
            "name": "Skyddskläder, Fristad",
            "location": "Sjönie",
            "contact": {
                "telegraph": "Skyddskläder, Fristad",
                "phone": [
                    "Borås 60016",
                    "60126",
                    "60055"
                ],
                "postgiro": "720"
            },
            "financials": {
                "capital": "250,000 kr",
                "employees": {
                    "industriarb": 85
                },
                "annual_turnover": "N/A",
                "annual_production_value": "N/A"
            },
            "foundation_year": 1925,
            "board": [
                {
                    "name": "John Magnuson",
                    "role": "ordf."
                },
                {
                    "name": "T. Bertoldy",
                    "role": "adv."
                }
            ],
            "director": "J. Magnuson"
        },
        "2": {
            "name": "Skyllberg",
            "location": "Sjönie",
            "contact": {
                "telegraph": "Skyllberg, Askersund",
                "phone": "»Bruket», Skyllberg",
                "postgiro": "25870"
            },
            "financials": {
                "capital": "3,000,000 kr",
                "employees": {
                    "total": 800,
                    "industriarb": 350
                },
                "annual_turnover": "8,000,000 kr",
                "annual_production_value": "N/A"
            },
            "foundation_year": 1876,
            "board": [
                {
                    "name": "Ivan Svensson",
                    "role": "ordf."
                },
                {
                    "name": "Wilhelm Graf",
                    "role": "v. ordf."
                },
                {
                    "name": "Valborg Hjelt",
                    "role": "fru"
                },
                {
                    "name": "Sten Sandgren",
                    "role": "major"
                }
            ],
            "director": "Ivan Svensson",
            "managing_director": "B. Wirsén"
        },
        "3": {
            "name": "Skyttorps Snickerifabrik",
            "location": "Shyttorp",
            "contact": {
                "phone": "14",
                "postgiro": "166420"
            },
            "financials": {
                "employees": {
                    "industriarb": 40
                },
                "annual_turnover": "500,000 kr",
                "annual_production_value": "N/A"
            },
            "foundation_year": 1927,
            "owner": "Gottfrid Lindgren",
            "director": "Sven Jansson"
        },
        "4": {
            "name": "AB. Skånebryggerier",
            "location": "Hälsingborg",
            "contact": {
                "telegraph": "Skånebryggerier, Hälsingborg",
                "phone": "20740",
                "postgiro": "14260"
            },
            "financials": {
                "capital": "5,200,000 kr",
                "employees": {
                    "total": 214,
                    "Hälsingborg": 59,
                    "Eslöv": 22,
                    "Kristianstad": 39,
                    "Klippan": 41,
                    "Landskrona": 21,
                    "Sölvesborg": 10,
                    "Ängelholm": 22
                },
                "annual_turnover": "3,000,000 kr",
                "annual_production_value": "N/A"
            },
            "foundation_year": 1918,
            "board": [
                {
                    "name": "Johan Nilsson",
                    "role": "förre landshövding"
                },
                {
                    "name": "O. Löfwall",
                    "role": "v. konsul"
                },
                {
                    "name": "Arvid Jönsson",
                    "role": "disp."
                },
                {
                    "name": "Anders Krön-lein",
                    "role": "dir."
                },
                {
                    "name": "K.-E. Löfwall",
                    "role": "dir."
                },
                {
                    "name": "Nils Rosander",
                    "role": "disp."
                },
                {
                    "name": "Ivar Sandberg",
                    "role": "dir."
                }
            ],
            "director": "K.-E. Löfwall",
            "vice_director": "Arvid Jönsson",
            "treasurer": "Kjell Stewénius"
        }
    }
}