{
    "original": "S porthönfehtion—Stallarholmen\n\n\"Sportkonfektion AB,, Boras.\n\nTillverkar sportkläder, trenchcoats och\nbyxor.\n\nTelefon: 17590. Postgiro: 140060. —\nAkt.-kap.: 100,000 kr. Antal industriarb.:\n60 samt 70 hemarbetare. Tillv.-värde pr\når: l,300;000 kr.-— Bolaget grundat 1938.\n\nStyrelse: disp. Sigurcl Bäckström\n(ordf.), köpm. Olof Jacobsson, köpm.\nGösta Järnbladh.\n\nVerkst. dir.: Sigurd Bäckström.\n\nSprakareds Emalj verk, Kinnahult.\n\nEmaljeringsverk i Kinnahult (Älvsb.\n1.). Tillverkar emaljerade skyltar,\nreflektorer, skajor samt utför emaljering.\n\nTelefon: Kinna 10045. Postgiro: 76776,\n— Antal industriarb.: 7. — Firman\netabl. 1893.\n\nÄgare o. chef: ing. Sölve Ericson.\n\n*AB. Spånga Ved- &amp; Brädgårdar,\n\nSpånga.\n\nSågverk, hyvleri och snickerifabrik i\nSpånga (Sthlms l.). Tillverkar sågade och\nhyvlade trävaror samt\nbyggnadssnickerier. Firman driver även handel med ved\noeh kol.\n\nTelefon: 360111 o. 360951. Postgiro:\n95070. — Akt.-kap.: 25,400 kr. Antal\nindustriarb.: 14. — Firman etabl. 1913,\nbolag 1932.\n\nStyrelse: byggm. Filip Falk (ordf.),\nkassör Ellen Carlsson, verkm. H. P. Falk,\nchaufför Ernst Gustavsson.\n\nVerkst. dir.: Filip Falk.\n\n\"Spångsholms Bruks AB., Sy a.\n\nTråddrageri, spik- och kättingf abrik\nvid Spångsholm, Sya (Östergötl. l.).\nTillverkar dragen stål- och järntråd,\nstållinor, svetstråd, taggtråd, trådspik,\nkät-ting&gt; kättingmanufåktur, smide,\nsnökedjor, stängsel, armeringsnät, saxsprintar\noch pappersklammer. Bolaget idkar\njämväl jordbruk.\n\nHuvudkontor o. ensamförsäljn.:\nBröderna Edstrand AB., Malmö och Stockholm;\ntelefon: »Bröderna Edstrand», Malmö o.\nStockholm. Fabrikskontor: Sya.\nTelegr.-adr.: Spångsholm, Mjölby. Telefon:\nMjölby 780.\n\nr Akt,-kap.:. 1,015,000 kr. Antal\nindustriarb.: 155.\n\nBolaget grundat 1898 under namn\nÅs-brohammar-Spångsholms B rukk Nya ÄB.,\nuuv. namn 1941.\ti ,\n\nStyrelse: bergsing. Gunmar Edstrand\n\n(ordf.), disp. Carl Gustaf Edstrand,\nkonsul Knut R. Edstrand.\n\nDisp.: Carl Gustaf Edstrand.\n\növering.: B. O. Graner.\n\n\"Spännartiytte Bruk, Kärrgruvan.\n\nSe Surahammars Bruks AB.,\nSurahammar.\n\n*P. 0. Stackes Träförädling, Gnosjö.\n\nTillverkar pennlådor, husgeråd och\nslöjdsaker in. m. av trä vid fabrik i\nGno-sjo (Jönköp. l.).\n\nTelefon: 164. Postgiro: 86829. —\nArb.-antal: 6. — Firman etabl. 1934.\n\nÄgare o. chef : fabr. Oscar Stacke.\n\nStafnäs Ullspinneri &amp; Väver i AB.,\n\nKlässbol. .\n\nUllspinneri, väveri, färgeri och\nberedningsverk i Klässbol (Värml. l.),\nTillverkar ullgarn, hel- och halvyllevävnader\nsamt filtar.\n\nTelefon: 22. Postgiro: 10600.\n\nAkt.-kap.: 33,500 kr. Antal\nindustriarb.: 60. — Fabriken anlagd 1888, bolag\n1940.\n\nStyrelse: fru Elsa Wennerholm, disp.\nThorild Wennerholm.\n\nVerkst. dir.: Thorild Wennerholm.\n\n*Stafsjö Bruk, Hedin, Lindström &amp;\nCo., Stavsjöbruk.\n\nMek. verkstad samt tackjärns- och\nme-tallgjuteri i Stavsjöbruk (Södermanl. l.).\nTillverkar gängskärningssvarvar och\nex-centerpressar, maskinskruvstycken,\nmembranventiler, massaventiler, »Pulvis»\nslir-kopplingar samt gjutgods.\n\nTelegr.-adr.: Stafsjö, Norrköping.\nTelefon: Stavsjöbruk 38 o. 44. Postgiro:\n98916.\n\nAntal industriarb.: 50. Tillv.-värde pr\når: 660,000 kr.\n\nVerkstaden anlagd 1873, nuv. firma\ngrundad 1936.\n\nÄgare: adv. Julius Lindström o. dir.\nKnut Lindström.\n\nIng.: Curt Lindström.\n\nKamrer: Carl-Gösta Olson.\n\n\"Stal, Finspång.\n\nSe Svenska Turbinfabriks AB.\nLjungström, Finspång.\n\n\"Stal lar holmens Industri AB.,\n\nSträngnäs.\n\nSmidesverkstad i Stallarholmen\n(Söderifrån!. l.). Tillverkar stålottömaner och\njärnsängar. -",
    "structured": {
        "1": {
            "name": "Sportkonfektion AB",
            "location": "Boras",
            "business": "Tillverkar sportkläder, trenchcoats och byxor",
            "contact": {
                "phone": [
                    "17590"
                ],
                "postgiro": "140060"
            },
            "financials": {
                "capital": "100,000 kr",
                "employees": {
                    "industriarb": 60,
                    "hemarbetare": 70
                },
                "annual_turnover": "l,300,000 kr"
            },
            "foundation_year": 1938,
            "board": [
                {
                    "name": "Sigurcl Bäckström",
                    "role": "disp."
                },
                {
                    "name": "Olof Jacobsson",
                    "role": "köpm."
                },
                {
                    "name": "Gösta Järnbladh",
                    "role": "köpm."
                }
            ],
            "director": "Sigurd Bäckström"
        },
        "2": {
            "name": "Sprakareds Emalj verk",
            "location": "Kinnahult",
            "products": "Tillverkar emaljerade skyltar, reflektorer, skajor samt utför emaljering",
            "contact": {
                "phone": "Kinna 10045",
                "postgiro": "76776"
            },
            "financials": {
                "employees": 7
            },
            "foundation_year": 1893,
            "director": "ing. Sölve Ericson"
        },
        "3": {
            "name": "AB. Spånga Ved- & Brädgårdar",
            "location": "Spånga",
            "business": "Sågverk, hyvleri och snickerifabrik",
            "contact": {
                "phone": [
                    "360111",
                    "360951"
                ],
                "postgiro": "95070"
            },
            "financials": {
                "capital": "25,400 kr",
                "employees": 14
            },
            "foundation_year": 1913,
            "board": [
                {
                    "name": "Filip Falk",
                    "role": "byggm."
                },
                {
                    "name": "Ellen Carlsson",
                    "role": "kassör"
                },
                {
                    "name": "H. P. Falk",
                    "role": "verkm."
                },
                {
                    "name": "Ernst Gustavsson",
                    "role": "chaufför"
                }
            ],
            "director": "Filip Falk"
        },
        "4": {
            "name": "Spångsholms Bruks AB.",
            "location": "Sya",
            "business": "Tråddrageri, spik- och kättingfabrik",
            "contact": {
                "phone": "Mjölby 780",
                "postgiro": "Disponibel"
            },
            "financials": {
                "capital": "1,015,000 kr",
                "employees": 155
            },
            "foundation_year": 1898,
            "current_name_year": 1941,
            "board": [
                {
                    "name": "Gunmar Edstrand",
                    "role": "bergsing."
                },
                {
                    "name": "Carl Gustaf Edstrand",
                    "role": "disp."
                },
                {
                    "name": "Knut R. Edstrand",
                    "role": "konsul"
                }
            ],
            "managing_director": "B. O. Graner"
        },
        "5": {
            "name": "P. O. Stackes Träförädling",
            "location": "Gnosjö",
            "business": "Tillverkar pennlådor, husgeråd och slöjdsaker in. m. av trä",
            "contact": {
                "phone": "164",
                "postgiro": "86829"
            },
            "financials": {
                "employees": 6
            },
            "foundation_year": 1934,
            "director": "fabr. Oscar Stacke"
        },
        "6": {
            "name": "Stafnäs Ullspinneri & Väver i AB.",
            "location": "Klässbol",
            "business": "Ullspinneri, väveri, färgeri och beredningsverk",
            "products": "Tillverkar ullgarn, hel- och halvyllevävnader samt filtar",
            "contact": {
                "phone": "22",
                "postgiro": "10600"
            },
            "financials": {
                "capital": "33,500 kr",
                "employees": 60
            },
            "foundation_year": 1888,
            "corporation_year": 1940,
            "board": [
                {
                    "name": "fru Elsa Wennerholm",
                    "role": "disp."
                },
                {
                    "name": "Thorild Wennerholm",
                    "role": "disp."
                }
            ],
            "managing_director": "Thorild Wennerholm"
        },
        "7": {
            "name": "Stafsjö Bruk, Hedin, Lindström & Co.",
            "location": "Stavsjöbruk",
            "business": "Mek. verkstad samt tackjärns- och met allguteri",
            "products": "Tillverkar gängskärningssvarvar och ex-centerpressar, maskinskruvstycken, membranventiler, massaventiler, »Pulvis» slir-kopplingar samt gjutgods",
            "contact": {
                "phone": "Stavsjöbruk 38 o. 44",
                "postgiro": "98916"
            },
            "financials": {
                "employees": 50,
                "annual_production_value": "660,000 kr"
            },
            "foundation_year": 1936,
            "owners": [
                "adv. Julius Lindström",
                "dir. Knut Lindström"
            ],
            "director": "Ing. Curt Lindström",
            "sales_manager": "Carl-Gösta Olson"
        },
        "8": {
            "name": "Stallarholmens Industri AB.",
            "location": "Strängnäs",
            "business": "Smidesverkstad",
            "products": "Tillverkar stålottömaner och järnsängar"
        }
    }
}