{
    "original": "Texo—Textilmaskiner\n\nTexo AB. Maskinfabrik,\n\nNorrköping.\n\nTillverkar maskiner för\ntextilindustrien såsom vävstolar och\nvävskedar, appretur- och beredningsmaskiner,\nbomflänsar för vävbommar,\nbomställningar, lameller för väverier, skaftramar\nsamt spolmaskiner. Bolaget driver även\nengroshandel med textilförnödenheter.\n\nTelegr.-adr.: Texo, Norrköping. Telefon:\n»Vävstolsfabriken». Postgiro: 271150. —\nAkt.-kap.: 35,000 kr. Antal industriarb.:\n70. Tillv.-värde pr år: 1,000,000 kr. —\nBolaget grundat 1940.\n\nVerkst. dir..- Axel Sundgren.\n\n\"Textil AB. Nilsson &amp; Co.,\n\nSmålandsstenar.\n\nHerrkonfektionsfabrik i Smålandsstenar\n(Jönköp. l.). Tillverkar stärkskjortor,\narbetsskjortor och blåkläder.\n\nTelefon: 30 o. 90. Postgiro: 22593.\n\nAkt.-kap.: 200,000 kr. Antal\nindustriarb.: 115 (ävensom 150 hemarbetare).\nTillv.-värde pr år: 1,800,000 kr. —\nBolaget grundat 1919.\n\nStyrelse: dir. Fritz Nilsson (ordf.),\ndisp. Artur Anderson, souschef Johannes\nNilsson.\n\nVerkst. dir. o. disp.: Fritz Nilsson.\n\nKontorschef: Ragnar Peterson.\n\n\"AB. Textilfabriken Merkur,\n\nBorås.\n\nTrikåfabrik. Tillverkar trikåvaror och\nstrumpor.\n\nTelegr.-adr.: Merkur, Borås. Telefon:\n17130. Postgiro: 34652. Representanter: i\nStockholm: H. Guggenberger,\nMalmskill-nadsg. 48 A, telefon: 203627; i Borås: J.\nOlausson, telefon: 11913 o. H. Halén,\ntelefon: 13304.\n\nAkt.-kap.: 700,000 kr. Antal\nindustriarb.: 200 (exkl. hemarbetare). Tillv.-värde\npr år: 4,000,000 kr. — Firman etabl.\n1922, bolag 1936.\n\nStyrelse: dir. Olof Nilsson (ordf.),\nförsäljn.-chef Hadar Halén, kamrer Nils\nHalén, fru A.-G. Nilsson.\n\nVerkst. dir.: Olof Nilsson.\n\nTextilindustri AB. Stiab, Svenska,\n\nUlricehamn,\n\nSe Svenska Textilindustri AB. Stiab,\nUlricehamn.\n\n\"Textilindustrien Gust. Carlsson,\n\nUlricehamn.\n\nTrikåfabrik i Ulricehamn (Älvsb. l.).\nTillverkar stickade yllevaror såsom\ndamjumpers, bluskoftor samt herr- och\ndam-cardigan.\n\nTelefon: 434. Postgiro: 82443. — Antal\nindustriarb.: 9. — Firman etabl. 1930.\n\nÄgare o. chef: fabr. Gustaf Carlsson.\n\n\"AB. Textilkompaniet, Bollebygd.\n\nHerrkonfektionsfabrik i Bollebygd\n(Älvsb. l.). Tillverkar arbets- och\nsportkläder samt skjortor. Varumärke:\n»T. K.».\n\nTelegr.-adr.: Textilkompaniet,\nBollebygd. Telefon: 20150. Postgiro: 14947.\n\nAkt.-kap.: 600,000 kr. Antal\nindustriarb.: 148. Tillv.-värde pr år: 4,100,000 kr.\n— Bolaget grundat 1919.\n\nStyrelse: prof. Gunnar Olin (ordf.),\nförsäljn.-chef Elof Areqvist, dir. Stig\nArvidson, dir. Patrick Lithander, dir.\nUno Murray.\n\nChef: P. Lithander.\n\nFörsäljn.-chef: Elof Areqvist.\n\nAB. Textilkonst, Malmö.\n\nTillverkar band och snörmakeriartiklar\nsamt spetsar.\n\nKontor: Norbergsgatan 7. Telegr.-adr.:\nTextilkonst, Malmö. Telefon: 71210.\nPostgiro: 39273. Representanter: Gust.\nUddenberg, Göteborg, S. Larmg. 4, telefon:\n116810; Arvid Svensson, Stockholm, S:t\nEriksg. 90, telefon: 332878.\n\nAkt.-kap.: 100,000 kr. Antal\nindustriarb.: 50. — Bolaget grundat 1933.\n\nStyrelse: fru Gertrud Ehnimb (ordf.),\nadv. Gerlach Richter.\n\nVerkst. dir.: Erik Ehnimb.\n\n\"AB. Textilmaskiner, Norrköping.\n\nMek. verkstad. Tillverkar maskiner och\nutensilier m. m. för textilindustrien.\n\nPostadr.: Norrköping 5. Telegr.-adr.:\nTextilmaskiner, Norrköping. Telefon:\n29045. Postgiro: 29410.\n\nAkt.-kap.: 100,000 kr. Antal\nindustriarb.; 70. Tillv.-värde pr år: 700,000 kr.\n\nBolaget bildades 1918 och övertog den\nav Firma G. Welander &amp; Kellner sedan\n1848 bedrivna rörelsen.\n\nStyrelse: ing. Robert Dott (ordf.),\nciviling. Birger Dott, fru Siri Dott.\n\nVerkst. dir.: Robert Dott.\n\nKontorschef: Gust. Edoff.\n\n(Jfr annons nr 96.)",
    "structured": {
        "1": {
            "name": "Texo AB. Maskinfabrik",
            "location": "Norrköping",
            "business": "Tillverkar maskiner för textilindustrien såsom vävstolar och vävskedar, appretur- och beredningsmaskiner, bomflänsar för vävbommar, bomställningar, lameller för väverier, skaftramar samt spolmaskiner. Bolaget driver även engroshandel med textilförnödenheter.",
            "contact": {
                "telegraph": "Texo, Norrköping",
                "phone": [
                    "Vävstolsfabriken"
                ],
                "postgiro": "271150"
            },
            "financials": {
                "capital": "35,000 kr",
                "employees": {
                    "industriarb": 70
                },
                "annual_turnover": "1,000,000 kr",
                "annual_production_value": "1,000,000 kr"
            },
            "foundation_year": 1940,
            "director": "Axel Sundgren"
        },
        "2": {
            "name": "Textil AB. Nilsson & Co.",
            "location": "Smålandsstenar",
            "business": "Herrkonfektionsfabrik i Smålandsstenar (Jönköp. l.). Tillverkar stärkskjortor, arbetsskjortor och blåkläder.",
            "contact": {
                "phone": [
                    "30",
                    "90"
                ],
                "postgiro": "22593"
            },
            "financials": {
                "capital": "200,000 kr",
                "employees": {
                    "industriarb": 115,
                    "hemarbetare": 150
                },
                "annual_turnover": "1,800,000 kr"
            },
            "foundation_year": 1919,
            "board": [
                {
                    "name": "Fritz Nilsson",
                    "role": "ordf."
                },
                {
                    "name": "Artur Anderson",
                    "role": "disp."
                },
                {
                    "name": "Johannes Nilsson",
                    "role": "souschef"
                }
            ],
            "director": "Fritz Nilsson",
            "manager": "Ragnar Peterson"
        },
        "3": {
            "name": "AB. Textilfabriken Merkur",
            "location": "Borås",
            "business": "Trikåfabrik. Tillverkar trikåvaror och strumpor.",
            "contact": {
                "telegraph": "Merkur, Borås",
                "phone": "17130",
                "postgiro": "34652"
            },
            "financials": {
                "capital": "700,000 kr",
                "employees": {
                    "industriarb": 200
                },
                "annual_turnover": "4,000,000 kr"
            },
            "foundation_year": 1922,
            "board": [
                {
                    "name": "Olof Nilsson",
                    "role": "ordf."
                },
                {
                    "name": "Hadar Halén",
                    "role": "försäljn.-chef"
                },
                {
                    "name": "Nils Halén",
                    "role": "kamrer"
                },
                {
                    "name": "fru A.-G. Nilsson",
                    "role": ""
                }
            ],
            "director": "Olof Nilsson"
        },
        "4": {
            "name": "Textilindustri AB. Stiab, Svenska",
            "location": "Ulricehamn",
            "business": "Se Svenska Textilindustri AB. Stiab, Ulricehamn."
        },
        "5": {
            "name": "Textilindustrien Gust. Carlsson",
            "location": "Ulricehamn",
            "business": "Trikåfabrik i Ulricehamn (Älvsb. l.). Tillverkar stickade yllevaror såsom damjumpers, bluskoftor samt herr- och dam-cardigan.",
            "contact": {
                "phone": "434",
                "postgiro": "82443"
            },
            "financials": {
                "employees": {
                    "industriarb": 9
                }
            },
            "owner": "fabr. Gustaf Carlsson"
        },
        "6": {
            "name": "AB. Textilkompaniet",
            "location": "Bollebygd",
            "business": "Herrkonfektionsfabrik i Bollebygd (Älvsb. l.). Tillverkar arbets- och sportkläder samt skjortor. Varumärke: »T. K.».",
            "contact": {
                "telegraph": "Textilkompaniet, Bollebygd",
                "phone": "20150",
                "postgiro": "14947"
            },
            "financials": {
                "capital": "600,000 kr",
                "employees": {
                    "industriarb": 148
                },
                "annual_turnover": "4,100,000 kr"
            },
            "foundation_year": 1919,
            "board": [
                {
                    "name": "prof. Gunnar Olin",
                    "role": "ordf."
                },
                {
                    "name": "Elof Areqvist",
                    "role": "försäljn.-chef"
                },
                {
                    "name": "Stig Arvidson",
                    "role": "dir."
                },
                {
                    "name": "Patrick Lithander",
                    "role": "dir."
                },
                {
                    "name": "Uno Murray",
                    "role": "dir."
                }
            ],
            "director": "P. Lithander",
            "sales_manager": "Elof Areqvist"
        },
        "7": {
            "name": "AB. Textilkonst",
            "location": "Malmö",
            "business": "Tillverkar band och snörmakeriartiklar samt spetsar.",
            "contact": {
                "office": "Norbergsgatan 7",
                "telegraph": "Textilkonst, Malmö",
                "phone": "71210",
                "postgiro": "39273"
            },
            "financials": {
                "capital": "100,000 kr",
                "employees": {
                    "industriarb": 50
                }
            },
            "foundation_year": 1933,
            "board": [
                {
                    "name": "fru Gertrud Ehnimb",
                    "role": "ordf."
                },
                {
                    "name": "adv. Gerlach Richter",
                    "role": ""
                }
            ],
            "director": "Erik Ehnimb"
        },
        "8": {
            "name": "AB. Textilmaskiner",
            "location": "Norrköping",
            "business": "Mek. verkstad. Tillverkar maskiner och utensilier m. m. för textilindustrien.",
            "contact": {
                "office": "Norrköping 5",
                "telegraph": "Textilmaskiner, Norrköping",
                "phone": "29045",
                "postgiro": "29410"
            },
            "financials": {
                "capital": "100,000 kr",
                "employees": {
                    "industriarb": 70
                },
                "annual_turnover": "700,000 kr"
            },
            "foundation_year": 1918,
            "predecessor": "Firma G. Welander & Kellner",
            "board": [
                {
                    "name": "ing. Robert Dott",
                    "role": "ordf."
                },
                {
                    "name": "civiling. Birger Dott",
                    "role": ""
                },
                {
                    "name": "fru Siri Dott",
                    "role": ""
                }
            ],
            "director": "Robert Dott",
            "manager": "Gust. Edoff"
        }
    }
}