{
    "original": "Maskinfa b rik—Ma tfo rs\n\ning. Johan Andersson, avd.-chef Einar\nLöfqvist.\n\nVerkst. dir.: Olof Winkler.\nPlatschef: ing. Erik T. Werner.\n\n’Maskinfabriks AB. Norrbacken,\n\nBlomstermåla.\n\nMek. verkstad och gjuteri i\nBlomster-måla (Kalmar l.). Tillverkar\nhyvelmaski-ner för metallbearbetning, maskiner för\nrenhållningsverk, latrinkärl, sopkärl,\nanordningar och vagnar för dammfri\nsoptömning, tjärspridare för makadamgator,\ncisterner, kvarnmaskiner,\ncellullsmaski-ner, svetsningsstavar samt gjutgods.\n\nTelegr.-adr.: Norrbacken,\nBlomster-måla. Telefon: 12 o. 54. Postgiro: 8615.\n\nAkt.-kap.: 420,000 kr. Antal\nindustriarb.: 160. Tillv.-värde pr år: 2,000,000 kr.\n\n—\tBolaget grundat 1914.\nStyrelse: dir. Gunnar Ekström.\nVerkst. dir.: Hilding Linde.\n\n\"Maskinfabriks AB. Thule,\n\nMalmö.\n\nMek. verkstad och gjuteri. Tillverkar\nverktygsmaskiner. Specialiteter:\nshaping-maskiner, bordhyvelmaskiner,\nstickmaskiner för järn och metall, planslipmaskiner\noch snabbkallsågar. Varumärke: »Thule».\n\nKontor: Lönng. 32. Telegr.-adr.:\nMa-skinthule, Malmö. Telefon: 22854 o.\n22850.\n\nAkt.-kap.: 500,000 kr. Antal\nindustriarb.: 125. — Bolaget grundat 1908.\n\nStyrelse: bankombudsm. Eric Paulson\n(ordf.), dir. Harald G. Evers, fru Greta\nLinander.\n\nAffärschef: kamrer John Landgren.\nDriftsing.: Arne Holmberg.\n(Jfr annons nr 75.)\n\nMaskin- &amp; Gjuteri AB., Kalmar.\n\nTillverkar transportanordningar såsom\nremtransportörer, kranar, traverser,\nele-vatorer, rullbanor, höj- och sänkbara\ntransportvagnar m. m. samt handels- och\nvattenledningsgjutgods.\n\nTelegr.-adr.: Gjuteribolaget. Kalmar.\nTelefon: 1393 o. 2893. Postgiro: 84315.\n\nAkt.-kap.: 51,200 kr. Antal\nindustriarb.: 95. Tillv.-värde pr år: 1,400,000 kr.\n\n—\tBolaget grundat 1924.\n\nStyrelse: adv. R. Allmér (ordf.), insr,\nRobert Garme, kamrer K. A. Kronzell.\nVerkst. dir.: Robert Garme.\nKamrer: K. A. Kronzell.\n\n\"Maskinverken, Svenska, Södertälje.\n\nSe AB. Svenska Maskinverken,\nSödertälje.\n\n24\n\nMaster hand AB., Malmö.\n\nKonfektionsfabrik. Tillverkar herr- och\ndamkläder.\n\nKontor: Västanforsg. 21. Telegr.-adr.:\nMasterhand, Malmö. Telefon: 72030.\nPostgiro: 38249.\n\nAkt.-kap.: 500,000 kr. Antal\nindustriarb.: 150. Tillv.-värde pr år: 2,500,000 kr.\n\n—\tBolaget grundat 1924.\n\nVerkst. dir.: konsul Edvin Ohlsson.\n\nDir.-assistent: fru S. Ohlsson.\n\n*AB. Matador ver ken, Halmstad.\n\nMekanisk verkstad. Tillverkar rakblad\noch rakhyvlar. Varumärken: »Matador»\no. »National».\n\nTelegr.-adr. o. telefon: Matadorverken,\nHalmstad. Postgiro: 72288. Avd.-kontor:\nStockholm, Drottningg. 10, telefon:\n204554.\n\nAkt.-kap.: 150,000 kr. Antal\nindustriarb.: 110. Tillv.-värde pr år: 3,000,000 kr.\n\n—\tFirman etabl. 1927, bolag 1930.\n\nStyrelse o. verkst. dir.: Carl Åslund.\n\nKontorschef: Johnny Junfors.\n\nAvd.-chef för Stockholmskontoret: disp.\n\nArtur Åquist.\n\n\"AB. Mataki, Malmö.\n\nTakpapp- och vägmaterialfabriker samt\nkem.-teknisk industri.\n\nTillverkar underhållsfri papp\n(»Ini-ton»), asfaltpapp (»Atlas»), bitumenpapp\n(»Grip»), bitumenmatta (»Mataki»), beck,\nträcement, goudron, adiodon, taktjära,\nvägtjära och asfaltemulsion (»Mataki»),\nkallasf altbetong (»Kallmak»),\nkarboli-neum och andra tj är oljor samt\nfönster-kitt, fruktträdskarbolineum m. m.; utför\ntaktäckningar (specialitet: s. k.\nträcement-och compoundtak) samt\nvägbeläggnings-arbeten. Bolaget driver även import och\npartihandel med kemikalier.\n\nKontor: Djäknegatan 2. Telegr.-adr. o.\ntelefon: Mataki, Malmö. Postgiro: 14017.\n\n—\tAkt.-kap.: 1,000,000 kr. Antal\nindustriarb.: 125.\n\nBolaget grundat 1904 under namn AB.\nMalmö Takpappfabrik, nuv. namn 1946.\n\nStyrelse: dir. N. P. Mathiasson (ordf.),\nadv. R. Stevelius, dir. F. Thomsen.\n\nVerkst. dir.: F. Thomsen.\n\nDisp.: Erik Möller.\n\nKamrerare: Henning Andersson o.\nAnders Åkesson.\n\n\"Matfors Träsliperi o. Pappersbruk,\n\nMatfors.\n\nSe Skönviks AB., Sundsvall.",
    "structured": {
        "1": {
            "name": "Maskinfabriks AB. Norrbacken",
            "location": "Blomstermåla",
            "business": "Mek. verkstad och gjuteri",
            "products": "Tillverkar hyvelmaskiner för metallbearbetning, maskiner för renhållningsverk, latrinkärl, sopkärl, anordningar och vagnar för dammfri soptömning, tjärspridare för makadamgator, cisterner, kvarnmaskiner, cellulsmaskiner, svetsningsstavar samt gjutgods.",
            "contact": {
                "office": "Norrbacken, Blomstermåla",
                "phone": [
                    "12",
                    "54"
                ],
                "postgiro": "8615"
            },
            "financials": {
                "capital": "420,000 kr",
                "employees": {
                    "industriarb": 160
                },
                "annual_turnover": "2,000,000 kr",
                "annual_production_value": "2,000,000 kr"
            },
            "foundation_year": 1914,
            "board": [
                {
                    "name": "dir. Gunnar Ekström",
                    "role": null
                },
                {
                    "name": "Verkst. dir.: Hilding Linde",
                    "role": null
                }
            ]
        },
        "2": {
            "name": "Maskinfabriks AB. Thule",
            "location": "Malmö",
            "business": "Mek. verkstad och gjuteri",
            "products": "Tillverkar verktygsmaskiner. Specialiteter: shaping-maskiner, bordhyvelmaskiner, stickmaskiner för järn och metall, planslipmaskiner och snabbkallsågar.",
            "contact": {
                "office": "Lönng. 32",
                "phone": [
                    "22854",
                    "22850"
                ]
            },
            "financials": {
                "capital": "500,000 kr",
                "employees": {
                    "industriarb": 125
                }
            },
            "foundation_year": 1908,
            "board": [
                {
                    "name": "bankombudsm. Eric Paulson",
                    "role": "ordf."
                },
                {
                    "name": "dir. Harald G. Evers",
                    "role": null
                },
                {
                    "name": "fru Greta Linander",
                    "role": null
                }
            ]
        },
        "3": {
            "name": "Maskin- & Gjuteri AB.",
            "location": "Kalmar",
            "business": "Mekanisk verkstad",
            "products": "Tillverkar transportanordningar såsom remtransportörer, kranar, traverser, elevatorer, rullbanor, höj- och sänkbara transportvagnar m. m. samt handels- och vattenledningsgjutgods.",
            "contact": {
                "office": "Gjuteribolaget, Kalmar",
                "phone": [
                    "1393",
                    "2893"
                ],
                "postgiro": "84315"
            },
            "financials": {
                "capital": "51,200 kr",
                "employees": {
                    "industriarb": 95
                },
                "annual_turnover": "1,400,000 kr"
            },
            "foundation_year": 1924,
            "board": [
                {
                    "name": "adv. R. Allmér",
                    "role": "ordf."
                },
                {
                    "name": "insr, Robert Garme",
                    "role": null
                },
                {
                    "name": "kamrer K. A. Kronzell",
                    "role": null
                },
                {
                    "name": "Verkst. dir.: Robert Garme",
                    "role": null
                },
                {
                    "name": "Kamrer: K. A. Kronzell",
                    "role": null
                }
            ]
        },
        "4": {
            "name": "Master hand AB.",
            "location": "Malmö",
            "business": "Konfektionsfabrik",
            "products": "Tillverkar herr- och damkläder.",
            "contact": {
                "office": "Västanforsg. 21",
                "phone": [
                    "72030"
                ],
                "postgiro": "38249"
            },
            "financials": {
                "capital": "500,000 kr",
                "employees": {
                    "industriarb": 150
                },
                "annual_turnover": "2,500,000 kr"
            },
            "foundation_year": 1924,
            "board": null
        },
        "5": {
            "name": "AB. Matador verken",
            "location": "Halmstad",
            "business": "Mekanisk verkstad",
            "products": "Tillverkar rakblad och rakhyvlar",
            "contact": {
                "office": "Matadorverken, Halmstad",
                "phone": null,
                "postgiro": "72288",
                "head_office": "Stockholm, Drottningg. 10",
                "sales_offices": [
                    {
                        "location": "Stockholm",
                        "phone": "204554"
                    }
                ]
            },
            "financials": {
                "capital": "150,000 kr",
                "employees": {
                    "industriarb": 110
                },
                "annual_turnover": "3,000,000 kr"
            },
            "foundation_year": 1930,
            "corporation_year": 1927,
            "board": [
                {
                    "name": "Carl Åslund",
                    "role": "verkst. dir."
                },
                {
                    "name": "Johnny Junfors",
                    "role": "Kontorschef"
                },
                {
                    "name": "disp. Artur Åquist",
                    "role": "Avd.-chef för Stockholmskontoret"
                }
            ]
        },
        "6": {
            "name": "AB. Mataki",
            "location": "Malmö",
            "business": "Takpapp- och vägmaterialfabriker samt kem.-teknisk industri",
            "products": "Tillverkar underhållsfri papp (»Initon»), asfaltpapp (»Atlas»), bitumenpapp (»Grip»), bitumenmatta (»Mataki»), beck, träcement, goudron, adiodon, taktjära, vägtjära och asfaltemulsion (»Mataki»), kallasfaltbetong (»Kallmak»), karbolin",
            "contact": {
                "office": "Djäknegatan 2",
                "phone": [
                    "Mataki, Malmö"
                ],
                "postgiro": "14017"
            },
            "financials": {
                "capital": "1,000,000 kr",
                "employees": {
                    "industriarb": 125
                }
            },
            "foundation_year": 1904,
            "corporation_year": 1946,
            "board": [
                {
                    "name": "dir. N. P. Mathiasson",
                    "role": "ordf."
                },
                {
                    "name": "adv. R. Stevelius",
                    "role": null
                },
                {
                    "name": "dir. F. Thomsen",
                    "role": null
                },
                {
                    "name": "Verkst. dir.: F. Thomsen",
                    "role": null
                },
                {
                    "name": "Disp.: Erik Möller",
                    "role": null
                },
                {
                    "name": "Kamrerare: Henning Andersson",
                    "role": null
                },
                {
                    "name": "Anders Åkesson",
                    "role": null
                }
            ]
        }
    }
}