{
    "original": "Bröderna\n\n* Bröderna Lagerström AB.,\n\nStockholm.\n\nBoktryckeri, litografisk anstalt,\nbok-binderi och bokförlag. Utför bok- och\naffärstryck, litografi, offset och notstick.\n\nKontor: Flemingg. 16. Telefon: 520185.\nPostgiro: 2323. — Akt.-kap.: 267,000 kr.\nAntal industriarb.: 83. Tillv.-värde pr år:\n1,550,000 kr. — Firman grundad 1903,\nbolag 1906.\n\nStyrelse: dir. Hugo Lagerström\n(ordf.), musikhandl. Emil Oarelius, dir.\nArthur Lagerström.\n\nVerkst. dir.: Arthur Lagerström.\nDisp.: Sten Lagerström.\n\nBröderna Larsson, Kristinehamn.\n\nVarv och mek. verkstad. Tillverkar\nmindre fartyg, motor- och segelbåtar pamt\nmarinmotorer, grovplåtsarbeten och\njärnkonstruktioner.\n\nTelefon: 10319 o. 10625. Postgiro:\n25252. — Antal industriarb.: 35.\nTillv.-värde pr år: 350,000 kr. — Firman etabl.\n1904.\n\nÄgare o. chef: fabr. G. Hugo Larsson.\n\n*AB. Bröderna Larsson, Borås.\n\nKonfektionsfabrik. Tillverkar\narbetskläder (märke: »B. L.»).\n\nTelegr.-adr.: Arbetskläder, Borås.\nTelefon: 17555. Postgiro: 10564. — Akt.-kap.:\n300,000 kr. Antal industriarb.: 75.\nTillv.-värde pr år: 2,000,000 kr. — Bolaget\ngrundat 1933.\n\nStyrelse o. verkst. direktörer: köpm.\nAxel G. Larsson o. grossh. Karl O.\nLarsson.\n\nBröderna Larsson, Mek. Verkstad,\n\nArentorp.\n\nMek. verkstad i Arentorp (Skarab. l.).\nTillverkar tröskverk, kvarnar och\nhalmfläktar samt gödselspridare för naturlig\ngödsel.\n\nTelefon: 4. Postgiro: 31452. — Antal\nindustriarb.: 32. Tillv.-värde pr år:\n330,000 kr. — Firman etabl. 1914.\n\nÄgare o. chef: fabr. Nils A. Larsson.\n\n* Bröderna Larssons Fabriks AB.,\n\nÖrbyhus.\n\nTräförädlingsfabrik i örbyhus\n(Uppsala l.). Tillverkar skidor och skidstavar,\nsparkstöttingar, styrbara kälkar, vilstolar,\nträdgårdsmöbler m. m. Specialitet: skidor.\n\nTelefon: 19. Postgiro: 30633. —\nAkt.-kap.: 151,500 kr. Antal industriarb.: 40.\nTillv.-värde pr år: 400,000 kr. — Firman\netabl. 1900, bolag 1945.\n\nStyrelse: f. d. riksdagsm. Joh. Larsson\n(ordf.), fil. mag. Astrid Larsson, ing.\nBertil Larsson.\n\nVerkst. dir.: Bertil Larsson.\n\nAB. Bröderna Liljenberg,\n\nStockholm.\n\nGummifabrik vid Västberga\nindustriområde, Stockholm. Tillverkar formgjorda\ngummidetaljer för industriella ändamål.\n\nKontor: Vretensborgsv. 16. Telefon:\n458455—56. Postgiro: 51358. —\nAkt.-kap.: 25,000 kr. Arb.-antal: 25.\nTillv.-värde pr år: 250,000 kr. — Firman etabl.\n1941, bolag 1942.\n\nVerkst. dir.: Eric Liljenberg.\n\nBröderna Lindbergs Mek. Verkstad,\n\nStorsjö.\n\nTillverkar verktyg och pumpar samt\nutför bearbetning av beställningsgods vid\nmek. verkstad i Storsjö (Kalmar l.).\n\nTelefon: Uknadalen 57. Postgiro:\n86252. — Antal industriarb.: 20.\nTillv.-värde pr år: 100,000 kr. — Firman etabl.\n1937 i överum, flyttad till Storsjö 1939.\n\nÄgare o. chefer: ing. Rudolf Lindberg\noch fabr. Thor-Ivar Lindberg.\n\n*AB« Bröderna Lindéns\nChoklad-fabrik, Vellinge.\n\nTillverkar choklad och skumsaker vid\nfabrik i Vellinge (Malmöh. l.).\n\nTelefon: 284 o. 317. Postgiro: 268724,\n\nAkt.-kap.: 30,000 kr. Antal\nindustriarb.: 30. Tillv.-värde pr år: 400,000 kr.\n— Bolaget grundat 1943.\n\nStyrelse: dir. Carl Linden (ordf.),\nförsäljn.-chef Olle Andersson, disp. Hans\nLindén.\n\nVerkst. dir.: Carl Lindén.\n\nKamrer: Hans Lindén.\n\n*Bröderna Lindmarks Snickerifabrik,\n\nJ okkmokk.\n\nTillverkar byggnadssnickerier,\nköks-och butiksinredningar vid snickerifabrik\ni Jokkmokk (Norrb. l.).\n\nTelefon: 144. Postgiro: 67767. — Antal\nindustriarb.: 10. Tillv.-värde pr år:\n130,000 kr. — Firman etabl. 1938.\n\nÄgare o. chefer; fabr. Signar\nLindmark o. fabr. Halvard Lindmark.",
    "structured": {
        "1": {
            "name": "Bröderna Lagerström AB",
            "location": "Stockholm",
            "business": "Boktryckeri, litografisk anstalt, bok-binderi och bokförlag.",
            "products": "Utför bok- och affärstryck, litografi, offset och notstick.",
            "contact": {
                "office": "Flemingg. 16",
                "phone": [
                    "520185"
                ],
                "postgiro": "2323"
            },
            "financials": {
                "capital": "267,000 kr",
                "employees": {
                    "industriarb": 83
                },
                "annual_turnover": "1,550,000 kr",
                "annual_production_value": "1,550,000 kr"
            },
            "foundation_year": 1903,
            "corporation_year": 1906,
            "board": [
                {
                    "name": "Hugo Lagerström",
                    "role": "ordf."
                },
                {
                    "name": "Emil Oarelius",
                    "role": "musikhandl."
                },
                {
                    "name": "Arthur Lagerström",
                    "role": "dir."
                }
            ]
        },
        "2": {
            "name": "Bröderna Larsson, Kristinehamn",
            "location": "Kristinehamn",
            "business": "Varv och mek. verkstad.",
            "products": "Tillverkar mindre fartyg, motor- och segelbåtar pamt marinmotorer, grovplåtsarbeten och järnkonstruktioner.",
            "contact": {
                "phone": [
                    "10319",
                    "10625"
                ],
                "postgiro": "25252"
            },
            "financials": {
                "employees": {
                    "industriarb": 35
                },
                "annual_turnover": "350,000 kr",
                "annual_production_value": "350,000 kr"
            },
            "foundation_year": 1904,
            "owner": "fabr. G. Hugo Larsson"
        },
        "3": {
            "name": "AB. Bröderna Larsson, Borås",
            "location": "Borås",
            "business": "Konfektionsfabrik.",
            "products": "Tillverkar arbetskläder (märke: »B. L.»).",
            "contact": {
                "telegraph": "Arbetskläder, Borås",
                "phone": [
                    "17555"
                ],
                "postgiro": "10564"
            },
            "financials": {
                "capital": "300,000 kr",
                "employees": {
                    "industriarb": 75
                },
                "annual_turnover": "2,000,000 kr"
            },
            "corporation_year": 1933,
            "board": [
                {
                    "name": "Axel G. Larsson",
                    "role": "köpm."
                },
                {
                    "name": "Karl O. Larsson",
                    "role": "grossh."
                }
            ]
        },
        "4": {
            "name": "Bröderna Larsson, Mek. Verkstad, Arentorp",
            "location": "Arentorp",
            "business": "Mek. verkstad",
            "products": "Tillverkar tröskverk, kvarnar och halmfläktar samt gödselspridare för naturlig gödsel.",
            "contact": {
                "phone": [
                    "4"
                ],
                "postgiro": "31452"
            },
            "financials": {
                "employees": {
                    "industriarb": 32
                },
                "annual_turnover": "330,000 kr"
            },
            "foundation_year": 1914,
            "owner": "fabr. Nils A. Larsson"
        },
        "5": {
            "name": "Bröderna Larssons Fabriks AB., Örbyhus",
            "location": "Örbyhus",
            "business": "Träförädlingsfabrik",
            "products": "Tillverkar skidor och skidstavar, sparkstöttingar, styrbara kälkar, vilstolar, trädgårdsmöbler m. m.",
            "contact": {
                "phone": [
                    "19"
                ],
                "postgiro": "30633"
            },
            "financials": {
                "capital": "151,500 kr",
                "employees": {
                    "industriarb": 40
                },
                "annual_turnover": "400,000 kr"
            },
            "foundation_year": 1900,
            "corporation_year": 1945,
            "board": [
                {
                    "name": "Joh. Larsson",
                    "role": "f. d. riksdagsm."
                },
                {
                    "name": "Astrid Larsson",
                    "role": "fil. mag."
                },
                {
                    "name": "Bertil Larsson",
                    "role": "ing."
                }
            ]
        },
        "6": {
            "name": "AB. Bröderna Liljenberg, Stockholm",
            "location": "Stockholm",
            "business": "Gummifabrik",
            "products": "Tillverkar formgjorda gummidetaljer för industriella ändamål.",
            "contact": {
                "office": "Vretensborgsv. 16",
                "phone": [
                    "458455",
                    "56"
                ],
                "postgiro": "51358"
            },
            "financials": {
                "capital": "25,000 kr",
                "employees": {
                    "arb": 25
                },
                "annual_turnover": "250,000 kr"
            },
            "corporation_year": 1942,
            "manager": "Eric Liljenberg"
        },
        "7": {
            "name": "Bröderna Lindbergs Mek. Verkstad, Storsjö",
            "location": "Storsjö",
            "business": "Mek. verkstad",
            "products": "Tillverkar verktyg och pumpar samt utför bearbetning av beställningsgods.",
            "contact": {
                "telegraph": "Uknadalen 57",
                "phone": [
                    "86252"
                ]
            },
            "financials": {
                "employees": {
                    "industriarb": 20
                },
                "annual_turnover": "100,000 kr"
            },
            "corporation_year": 1939,
            "owners": [
                "ing. Rudolf Lindberg",
                "fabr. Thor-Ivar Lindberg"
            ]
        },
        "8": {
            "name": "AB« Bröderna Lindéns Choklad-fabrik, Vellinge",
            "location": "Vellinge",
            "business": "Choklad- och skumproduktion",
            "products": "Tillverkar choklad och skumsaker.",
            "contact": {
                "phone": [
                    "284",
                    "317"
                ],
                "postgiro": "268724"
            },
            "financials": {
                "capital": "30,000 kr",
                "employees": {
                    "industriarb": 30
                },
                "annual_turnover": "400,000 kr"
            },
            "corporation_year": 1943,
            "board": [
                {
                    "name": "Carl Linden",
                    "role": "dir."
                },
                {
                    "name": "Olle Andersson",
                    "role": "försäljn.-chef"
                },
                {
                    "name": "Hans Lindén",
                    "role": "disp."
                }
            ],
            "manager": "Carl Lindén",
            "sales_manager": "Olle Andersson",
            "director": "Hans Lindén"
        },
        "9": {
            "name": "Bröderna Lindmarks Snickerifabrik, Jokkmokk",
            "location": "Jokkmokk",
            "business": "Snickerifabrik",
            "products": "Tillverkar byggnadssnickerier, köks- och butiksinredningar.",
            "contact": {
                "phone": [
                    "144"
                ],
                "postgiro": "67767"
            },
            "financials": {
                "employees": {
                    "industriarb": 10
                },
                "annual_turnover": "130,000 kr"
            },
            "foundation_year": 1938,
            "owners": [
                "fabr. Signar Lindmark",
                "fabr. Halvard Lindmark"
            ]
        }
    }
}