{
    "original": "Sköld—Slettengren\n\nson, disp. Sven Olsson, lantbr. Olof\nSi-lén.\n\nVerkst. dir.: J. Hanson.\n\nDisp.: S. Olsson.\n\nAB. Sköld &amp; Co-, Ulricehamn.\n\nTillverkar genom s. k. hemstickning\ngrövre herrstrumpor samt sockor och\nvantar i ölsremma, Ulricehamn (Älvsb. l.).\n\nTelefon: ölsremma 45. Postgiro:\n138312. — Akt.-kap.: 25,000 kr. Antal\narb.: 110 hemarbetare. — Firman etabl.\n1937, bolag 1939.\n\nStyrelse o. verkst. dir.: Allan Sköld.\n\nR. A. Skölins Mek. Verkstad, Rasbo.\n\nTillverkar väghyvelskär, spridare för\nklorkalcium, klorex och singel,\nhandkranar, kärror (märke: »Lenna-kärran») och\ntimmerlastare vid mek. verkstad i Rasbo\n(Uppsala l.).\n\nTelefon: Uppsala 77033. Postgiro:\n76763. — Antal industriarb.: 15. —\nFirman etabl. 1918.\n\nÄgare o. chef: fabr. R. A. Skölin.\n\n\"Skönviks AB., Sundsvall.\n\nSågverk, hvvleri och mek. verkstad i\nSkönvik, trämassefabrik och pappersbruk\ni Matfors, sulfitfabrik och\nsulfitspritfabrik i Ortviken, sågverk i Tunadal,\nelektrisk vattenkraftstation vid\nNedan-sjö (samtl. i Västernorrl. l.).\n\nTillverkar sågade och hyvlade trävaror,\nsulfitcellulosa och sulfitsprit, trämassa,\ntidningspapper och omslagspapper, mek.\nverkstadsprodukter för cellulosa- och\nsågverksindustrierna samt distribuerar elektr.\nenergi. Bolaget idkar jämväl jordbruk\noch skogshantering.\n\nHuvudkontor: Sundsvall (se\nSunds-vallsbqlagen). Ensamförsäljare för\nsul-f itcellulosa: Svenska Cellulosa AB.,\nStockholm, V. Trädgårdsgatan 15,\ntelefon: »Cellulosabolaget».\n\nÅkt.-kap.; 19,600,000 kr. Antal\nindustriarb.: 1,100. Årskapacitet: 30,000 stds\nsågade o. hyvlade trävaror, 45,000 ton\nsulfitcellulosa, 3,5 milj. lit. sulfitsprit,\n40,000 ton tidningspapper, samt för eget\nbehov 60,000 ton våt mek. trämassa.\n\nBolaget grundades 1861.\nAktiemajoriteten i bolaget innehaves av Svenska\nCellulosa AB., Stockholm.\n\nStyrelse: dir. Torsten Hérnod (ordf.),\ndir. Gust. Göranson, greve W. A. H.\nHa-miltoh, dir. Gust. J. Sahlin, bankdir. P.\nF. Wåhlin.\n\nVerkst. dir.: Gust. Göranson.\n\nIngenjörer: i Matfors: E. Gleditsch; i\nOrtviken: Carl Hjalmar Bäckström.\n\nSågverksfÖrvalt.: S. Stigenberg.\n\n\"Skövde Gasbetong AB., Skövde.\n\nKalkstensbrott vid Carlsro, Skövde,\nsamt stenhuggeri, kalkbruk och\ngasbetong-fabrik (ånghärdningsmetod) vid Skövde.\n\nTillverkar kalk för murbruks- och\njordbruksändamål, levererar förädlad\nkalksten, tillverkar ånghärdade\ngasbetongplattor för byggnadsändamål, armerade\ngasbetongplattor till tak samt skifferkalk.\n\nTelegr.-adr.: Gasbetongf ab, Skövde.\nTelefon: 2270. Postgiro: 30882.\nEnsamförsälj. för kalk: Mellersta Sveriges\nKalkbruks Centralförening, Falköping.\nTelefon: 280 o. 281.\n\nAkt.-kap.: 338,200 kr. Antal\nindustriarb.: 140.\n\nFirman etabl. på 1870-talet, bolag 1917\nunder namn Skövde Mek. Stenhuggeri k\nKalkbruks AB., nuv. namn 1943.\n\nStyrelse: dir. Gunnar Dalen (ordf.),\nbankdir. Frans Andersson, dir. A. R.\nGrane, ing. M. Neuendorf, borgm. Axel\nB. Svensson.\n\nVerkst. dir : A. R. Grane.\n\n\"Skövde Mek. Stenhuggeri &amp;\nKalk-bruks AB., Skövde.\n\nSe Skövde Gasbetong AB., Skövde.\n\nSlagteri AB. i Stockholm,\n\nStockholm.\n\nCharkuteri- och konservfabrik. Bolaget\ndriver jämväl detaljhandel genom tretton\negna minutaffärer i Stockholm.\nVarunamn: »Sabis».\n\nKontor: Malmgårdsv. 22; postadr.:\nBox 11036, Stockholm 11. Telegr.-adr. o.\ntelefon: Sabis, Stockholm. Postgiro: 1110.\n\nAkt.-kap.: 1,040,000 kr. Antal\nindustriarb.: 40. —- Bolaget grundat 1874.\n\nVerkst. dir.: Eric Andersson.\n\nKontorschef: Börje Barner.\n\nFabrikschef: Åke Samson.\n\nSlakteri AB. Norrmalm,\n\nStockholm.\n\nSe Norrmalms Livsmedels AB., Sthlm.\n\nKnut Slettengren, Kalmar.\n\nPappförädlingsfabrik. Tillverkar\nge-länk, bak- och tåkappor för skoindustrien,\npapp, strimlor och skärmar för\nmössfabrikation samt såsom specialitet\nmar-garinkartonger.\n\nTelegr.-adr.: Gelänk, Kalmar. Telefon:\n1423 o. 1426. Postgiro: 74777. Repr. i\nÖrebro: A. F. Tönnies, telefon: 20255.\n\nAntal industriarb.: 15. Tillv.-värde pr\når: 120,000 kr. — Firman etabl. 1923.\n\nÄgare o. chef: disp. Knut Slettengren.",
    "structured": {
        "1": {
            "name": "AB. Sköld & Co-",
            "location": "Ulricehamn, Älvsborgs län",
            "business": "Tillverkar genom s. k. hemstickning grövre herrstrumpor samt sockor och vantar i ölsremma",
            "contact": {
                "office": "Ulricehamn",
                "phone": [
                    "ölsremma 45"
                ],
                "postgiro": "138312"
            },
            "financials": {
                "capital": "25,000 kr",
                "employees": {
                    "hemarbetare": 110
                }
            },
            "foundation_year": 1937,
            "corporation_year": 1939,
            "board": [
                {
                    "name": "Allan Sköld",
                    "role": "Styrelse o. verkst. dir."
                }
            ]
        },
        "2": {
            "name": "R. A. Skölins Mek. Verkstad",
            "location": "Rasbo, Uppsala län",
            "business": "Tillverkar väghyvelskär, spridare för klorkalcium, klorex och singel, handkranar, kärror (märke: »Lenna-kärran») och timmerlastare vid mek. verkstad i Rasbo",
            "contact": {
                "office": "Rasbo",
                "phone": [
                    "Uppsala 77033"
                ],
                "postgiro": "76763"
            },
            "financials": {
                "employees": {
                    "industriarb.": 15
                }
            },
            "foundation_year": 1918,
            "owner": "fabr. R. A. Skölin"
        },
        "3": {
            "name": "Skönviks AB.",
            "location": "Sundsvall, Västernorrlands län",
            "business": "Tillverkar sågade och hyvlade trävaror, sulfitcellulosa och sulfitsprit, trämassa, tidningspapper och omslagspapper, mek. verkstadsprodukter för cellulosa- och sågverksindustrierna samt distribuerar elektr. energi",
            "contact": {
                "office": "Sundsvall"
            },
            "financials": {
                "capital": "19,600,000 kr",
                "employees": {
                    "industriarb.": 1,
                    ", ": 100
                },
                "annual_turnover": "30,000 stds sågade o. hyvlade trävaror, 45,000 ton sulfitcellulosa, 3,5 milj. lit. sulfitsprit, 40,000 ton tidningspapper"
            },
            "foundation_year": 1861,
            "owners": [
                "Svenska Cellulosa AB., Stockholm"
            ],
            "board": [
                {
                    "name": "Torsten Hérnod",
                    "role": "Styrelse o. verkst. dir."
                },
                {
                    "name": "Gust. Göranson",
                    "role": "Styrelse"
                },
                {
                    "name": "greve W. A. H. Hamilton",
                    "role": "Styrelse"
                },
                {
                    "name": "Gust. J. Sahlin",
                    "role": "Styrelse"
                },
                {
                    "name": "P. F. Wåhlin",
                    "role": "Styrelse"
                }
            ],
            "director": "Gust. Göranson",
            "managing_director": "Gust. Göranson"
        },
        "4": {
            "name": "Skövde Gasbetong AB.",
            "location": "Skövde",
            "business": "Tillverkar kalk för murbruks- och jordbruksändamål, levererar förädlad kalksten, tillverkar ånghärdade gasbetongplattor för byggnadsändamål, armerade gasbetongplattor till tak samt skifferkalk",
            "contact": {
                "office": "Skövde",
                "phone": [
                    "2270"
                ],
                "postgiro": "30882"
            },
            "financials": {
                "capital": "338,200 kr",
                "employees": {
                    "industriarb.": 140
                }
            },
            "corporation_year": 1917,
            "board": [
                {
                    "name": "Gunnar Dalen",
                    "role": "Styrelse o. verkst. dir."
                },
                {
                    "name": "Frans Andersson",
                    "role": "Styrelse"
                },
                {
                    "name": "A. R. Grane",
                    "role": "Styrelse"
                },
                {
                    "name": "M. Neuendorf",
                    "role": "Styrelse"
                },
                {
                    "name": "Axel B. Svensson",
                    "role": "Styrelse"
                }
            ],
            "director": "A. R. Grane"
        },
        "5": {
            "name": "Slagteri AB. i Stockholm",
            "location": "Stockholm",
            "business": "Charkuteri- och konservfabrik. Bolaget driver jämväl detaljhandel genom tretton egna minutaffärer i Stockholm",
            "contact": {
                "office": "Stockholm",
                "postgiro": "1110"
            },
            "financials": {
                "capital": "1,040,000 kr",
                "employees": {
                    "industriarb.": 40
                }
            },
            "board": [
                {
                    "name": "Eric Andersson",
                    "role": "Verkst. dir."
                },
                {
                    "name": "Börje Barner",
                    "role": "Kontorschef"
                },
                {
                    "name": "Åke Samson",
                    "role": "Fabrikschef"
                }
            ]
        },
        "6": {
            "name": "Slakteri AB. Norrmalm",
            "location": "Stockholm",
            "business": "Slakteri",
            "contact": {
                "office": "Stockholm"
            }
        },
        "7": {
            "name": "Knut Slettengren",
            "location": "Kalmar",
            "business": "Pappförädlingsfabrik. Tillverkar ge-länk, bak- och tåkappor för skoindustrien, papp, strimlor och skärmar för mössfabrikation samt såsom specialitet margarinkartonger",
            "contact": {
                "office": "Kalmar",
                "phone": [
                    "1423",
                    "1426"
                ],
                "postgiro": "74777",
                "representative": "A. F. Tönnies"
            },
            "financials": {
                "employees": {
                    "industriarb.": 15
                },
                "annual_production_value": "120,000 kr"
            },
            "foundation_year": 1923,
            "owner": "disp. Knut Slettengren"
        }
    }
}