{
    "original": "A sker sundsverken—A st ra\n\nFörsäljare: för Göteborg: m. fl. platser:\nAxel Hj. Westman, Kyrkog. 25, telefon:\n117948; för Boras o. mellersta Sverige:\nJ~oh. Olausson, Borås, telefon: 11913; för\nMalmö o. södra Sverige: Leo Flensby,\nMalmö, Amiralsg. 1, telefon: 18639; för\nöstra Sverige: George Hallberg, Enskede,\ntelefon: 491880; för Norrland: Ferd.\nHäggmark, Sundsvall, telefon: 78490.\n\nAkt.-kap.: 150,000 kr. Antal\nindustriarb.: 90. Tillv.-värde pr år: 1,800,000 kr.\n— Bolaget grundat 1910.\n\nStyrelse: disp. Karl G. Nilson (ordf.),\nfru S. Nilson, bankkamrer A. R. Norry.\n\nVerkst. dir.: Karl G. Nilson.\n\nKamrer: M. Berglund.\n\nDirektris: Lisa Fors.\n\n*Askersundsverken AB., A sker sund.\n\nGjuteri och mek. verkstad. Tillverkar\nvärmeledningspannor, shuntventiler och\nplåtfat.\n\nTelegr.-adr.: Avaverken, Askersund.\nTelefon: 60 o. 212. Postgiro: 33715.\n\nAkt.-kap.: 150,000 kr. Antal\nindustriarb.: 45. Tillv.-värde pr år: 700,000 kr. —\nVerkstaden anlagd 1906, nuv. bolag\ngrundat 1932.\n\nStyrelse: dir. John Franzén (ordf.),\nfabr. Gustav Franzén, fabr. Harry\nFranzén.\n\nVerkst. dir.: John Franzén.\n\n*AB. Asklunds Yllefabrik,\n\nNorrköping.\n\nYllefabrik samt ångtvättinrättning\n(»Gamla Ångtvätten»). Tillverkar\nylletyger och filtar samt utför vittvätt.\nSpecialiteter: filtar o. kapptvger.\n\nTelefon: 20546. Postgiro: 10915. —\nAkt.-kap.: 150,000 kr. Antal industriarb.:\n65, varav vid yllefabriken 45. — Firman\n«tabl. 1888, bolag 1941.\n\nStyrelse: ing. Hj. Asklund, ad v. Erik\nHalidén.\n\nVerkst. dir.: Carl Johan Ohlsson.\n\nOlof Asklunds Ångbageri AB.,\n\nGöteborg.\n\nTillverkar mjukt bröd. spis- och\nknäckebröd samt konditorivaror.\n\nKontor: övra Husarg. 13. Telegr.-adr.:\nOlask, Göteborg. Telefon: »Olof\nAsklunds Bröd». Postgiro: 40622. —-\nAkt.-kap.: 200,000 kr. — Firman etabl. 1874,\nbolag 1909.\n\nStyrelse: dir. David Asklund, disp.\nKnut Asklund, bagarm. Olof Asklund.\n\nVerkst. dir.: D. Asklund.\n\nAsmundtorps Borstfabriks AB.,\n\nAsmundtorp.\n\nTillverkar borstar och penslar vid\nfabrik i Asmundtorp (Malmöh. l.).\nSpecialitet: borstar för mejerier och industrier.\n\nTelefon: 16. Postgiro: 23231. —\nAkt.-kap.: 10,500 kr. Antal industriarb.: 24.\nTillv.-värde pr år: 100,000 kr. — Firman\netabl. 1902.\n\nDisp.: Bror Bengtsson.\n\n*Aspa Bruk, Aspabruk.\n\nSe Munksjö AB., Jönköping.\n\n*Asps Yllefabriks AB., Motala.\n\nSe Engel-Fabrikerna AB., Motala.\n\n*A. E. Asplunds Snickerifabrik,\n\nM almberget.\n\nTillverkar dörrar, fönster, trappor,\nledstänger, köksinredningar och\nbutiksinredningar samt kompletteringsmöbler vid\nsnickerifabrik i Malmberget (Norrb. l.).\nFirman driver även glasmästeri.\n\nTelefon: 233. Postgiro: 61165. — Antal\nindustriarb.: 11. Tillv.-värde pr år: 89,000\nkr. — Firman etabl. 1924.\n\nÄgare o. chef: snickarmäst. A. Edvin\nAsplund.\n\n*S. 0. Asplunds Byggnads AB.,\n\nÖrebro.\n\nByggnadsentreprenörfirma för väg- och\nvattenbyggnadsarbeten, industribyggnader\nm. m.\n\nTelefon: 13737. Postgiro: 141943. —\nAkt.-kap.: 20,000 kr. Antal industriarb.:\n30. Tillv.-värde pr år: 600,000 kr. —\nBolaget grundat 1931.\n\nStyrelse: tekn. dr Sven Olof Asplund\n(ordf.), fru A. E. Asplund.\n\nVerkst. dir.: S. O. Asplund.\n\n*AB. Astra, Apotekarnes Kem.\n\nFabriker, Södertälje.\n\nFarmaceutisk-kemisk fabrik. Tillverkar\nfarmaceutiska preparat och\nförbandsartiklar. Varumärke: »Astra».\n\nTelegr.-adr. o. telefon: Astra,\nSödertälje. Postgiro: 9297.\n\nAkt.-kap.: 3,000,000 kr. Antal\nindustriarb.: 425. — Bolaget grundat 1913.\n\nStyrelse: bankdir. Rich. Julin (ordf.),\ndir. Alb. M. Elfström, dir. Börje\nGabrielsson, grossh. E. Kistner.\n\nVerkst. dir.: B. Gabrielsson.\n\n29*",
    "structured": {
        "1": {
            "name": "Askersundsverken AB.",
            "location": "Askersund",
            "business": "Gjuteri och mek. verkstad",
            "products": "Tillverkar värmeledningspannor, shuntventiler och plåtfat",
            "contact": {
                "office": "Avaverken, Askersund",
                "phone": [
                    "60",
                    "212"
                ],
                "postgiro": "33715"
            },
            "financials": {
                "capital": "150,000 kr",
                "employees": {
                    "industriarb": 45
                },
                "annual_turnover": "700,000 kr"
            },
            "foundation_year": 1932,
            "board": [
                {
                    "name": "John Franzén",
                    "role": "Verkst. dir."
                },
                {
                    "name": "Gustav Franzén",
                    "role": "fabr."
                },
                {
                    "name": "Harry Franzén",
                    "role": "fabr."
                }
            ]
        },
        "2": {
            "name": "AB. Asklunds Yllefabrik",
            "location": "Norrköping",
            "business": "Yllefabrik samt ångtvättinrättning (»Gamla Ångtvätten»)",
            "products": "Tillverkar ylletyger och filtar samt utför vittvätt",
            "contact": {
                "phone": "20546",
                "postgiro": "10915"
            },
            "financials": {
                "capital": "150,000 kr",
                "employees": {
                    "industriarb": 65
                },
                "annual_turnover": "N/A"
            },
            "foundation_year": 1941,
            "board": [
                {
                    "name": "ing. Hj. Asklund",
                    "role": "Styrelse"
                },
                {
                    "name": "ad v. Erik Halidén",
                    "role": "Styrelse"
                }
            ],
            "director": "Carl Johan Ohlsson"
        },
        "3": {
            "name": "Olof Asklunds Ångbageri AB.",
            "location": "Göteborg",
            "business": "Tillverkar mjukt bröd, spis- och knäckebröd samt konditorivaror",
            "contact": {
                "office": "övra Husarg. 13",
                "phone": [
                    "»Olof Asklunds Bröd»"
                ],
                "postgiro": "40622"
            },
            "financials": {
                "capital": "200,000 kr",
                "annual_turnover": "N/A"
            },
            "foundation_year": 1909,
            "board": [
                {
                    "name": "David Asklund",
                    "role": "dir."
                },
                {
                    "name": "Knut Asklund",
                    "role": "disp."
                },
                {
                    "name": "Olof Asklund",
                    "role": "bagarm."
                }
            ],
            "director": "D. Asklund"
        },
        "4": {
            "name": "Asmundtorps Borstfabriks AB.",
            "location": "Asmundtorp",
            "business": "Tillverkar borstar och penslar",
            "products": "Specialitet: borstar för mejerier och industrier",
            "contact": {
                "phone": "16",
                "postgiro": "23231"
            },
            "financials": {
                "capital": "10,500 kr",
                "employees": {
                    "industriarb": 24
                },
                "annual_turnover": "100,000 kr"
            },
            "foundation_year": 1902,
            "board": [
                {
                    "name": "Bror Bengtsson",
                    "role": "Disp."
                }
            ]
        },
        "5": {
            "name": "A. E. Asplunds Snickerifabrik",
            "location": "Malmberget",
            "business": "Tillverkar dörrar, fönster, trappor, ledstänger, köksinredningar och butiksinredningar samt kompletteringsmöbler",
            "products": "Firman driver även glasmästeri",
            "contact": {
                "phone": "233",
                "postgiro": "61165"
            },
            "financials": {
                "capital": "N/A",
                "employees": {
                    "industriarb": 11
                },
                "annual_turnover": "89,000 kr"
            },
            "foundation_year": 1924,
            "manager": "A. Edvin Asplund"
        },
        "6": {
            "name": "S. 0. Asplunds Byggnads AB.",
            "location": "Örebro",
            "business": "Byggnadsentreprenörfirma för väg- och vattenbyggnadsarbeten, industribyggnader m. m.",
            "contact": {
                "phone": "13737",
                "postgiro": "141943"
            },
            "financials": {
                "capital": "20,000 kr",
                "employees": {
                    "industriarb": 30
                },
                "annual_turnover": "600,000 kr"
            },
            "foundation_year": 1931,
            "board": [
                {
                    "name": "tekn. dr Sven Olof Asplund",
                    "role": "Styrelse"
                },
                {
                    "name": "fru A. E. Asplund",
                    "role": "N/A"
                }
            ],
            "manager": "S. O. Asplund"
        },
        "7": {
            "name": "AB. Astra, Apotekarnes Kem. Fabriker",
            "location": "Södertälje",
            "business": "Farmaceutisk-kemisk fabrik",
            "products": "Tillverkar farmaceutiska preparat och förbandsartiklar",
            "contact": {
                "phone": "Astra, Södertälje",
                "postgiro": "9297"
            },
            "financials": {
                "capital": "3,000,000 kr",
                "employees": {
                    "industriarb": 425
                },
                "annual_turnover": "N/A"
            },
            "foundation_year": 1913,
            "board": [
                {
                    "name": "bankdir. Rich. Julin",
                    "role": "Styrelse"
                },
                {
                    "name": "dir. Alb. M. Elfström",
                    "role": "Styrelse"
                },
                {
                    "name": "dir. Börje Gabrielsson",
                    "role": "Styrelse"
                },
                {
                    "name": "grossh. E. Kistner",
                    "role": "N/A"
                }
            ],
            "director": "B. Gabrielsson"
        }
    }
}