{
    "original": "J ohansson\n\n*E. Jonson, Armaturfabrik &amp;\nMetall-gjuteri, Sundbyberg.\n\nTillverkar utblåsnings- och\nglasrörs-kranar, elektr. belysningsarmatur,\nbryggeriarmatur, mejeri armatur samt\nmjölk-rnätningsapparaten »Eok».\n\nTelefon: Stockholm 281226. Postgiro:\n14231. — Arb.-antal: 10. Tillv.-värde pr\når: 75,000 kr. — Firman etabl. 1912.\n\nÄgare o. chef: fabr. Evald Jonson.\n\n\"C. Jonsson &amp; Co-, Böleå\nSnickerifabrik, Teg.\n\nSe Böleå Snickerifabrik, G. Jonsson &amp;\nCo., Teg.\n\nHenrik Johnsson &amp; Comp.\nSkinnindustri AB., Malung.\n\nSe Hen jo AB., Malung.\n\"Johan Jonsson, Överhörnäs.\n\nKonfektions-, trikå- och pälsvarufabrik\ni Överhörnäs (Västernorrl. l.). Tillverkar\nherrkläder, res-, promenad- och\nsportpälsar, pälsmössor, ylletrikå m. m. Firman\ninnehar sju egna minutaffärer samt\nidkar jämväl jordbruk.\n\nTelegr.-adr.: Pälsvaror, Örnsköldsvik.\nTelefon: Örnsköldsvik 72041. Postgiro:\n62396. — Antal industriarb.: 45. —\nFirman etabl. 1909.\n\nÄgare o. chef: fabr. Johan Jonsson.\n\nJohn Johnsons Bokbinderi,\n\nGöteborg.\n\nUtför bindning av privat- och\nbiblioteksband samt av massupplagor.\n\nKontor: Kyrkog. 58. Telefon: 134165.\nPostgiro: 42905. — Antal industriarb.:\n20. — Firman etabl. 1924.\n\nÄgare o. chef: bokbindaremäst. John\nJ ohnson.\n\n\"AB. Jon Jonsson &amp; Co., Ljusdal.\n\nSågverk och kol ugnar i Ljusdal\n(östernäs Såg), sågverk vid Tallåsen\n(Bäcke-bo Ångsåg) (båda i Gävleb. l.). Tillverkar\nsågade och hyvlade trävaror, listverk.\nstav, bilade spar rar m. m. samt träkol.\ngengaskol och trätjära. Varumärke för\nträtjära: »Jojo». Bolaget driver även\nskogshantering.\n\nTelegr.-adr.: Jonssons. Ljusdal.\nTelefon: 1001 o. 1755. Postgiro: 77088.\n\nAkt.-kap.: 1,150,000 kr. Antal\nindustriarb.: 135. Årstillv.: 5 500 stds trävaror.\n— Bolaget grundat 1887.\n\nStyrelse: dir. Jonas Jonsson (ordf.),\nkommunalnämndsordf. Jon Hansson,\nhemmansäg. Johan Jonsson, kontorschef\nMårten Jonsson, förvalt. Olof Wådell.\n\nVerkst. dir.. Jonas Jonsson.\n\nKontorschef: Mårten Jonsson.\n\n*L. A. Jonssons Skidfabriks AB.,\n\nÖstersund.\n\nTillverkar skidor. Specialitet:\nkvalitetsskidor av hiekory och björk.\n\nTelegr.-adr.: Jonssonskidor, Östersund.\nTelefon: 245. Postgiro: 133982.\n\nAkt.-kap.: 50,000 kr. Arb.-antal: 40.\nTillv.-värde pr år: 500,000 kr. — Firman\netabl. 1888, bolag 1937.\n\nVerkst. dir.: Clarence Hammar.\n\n\"AB. N. Johnson &amp; Co., Eslöv.\n\nSnickerifabrik och hyvleri i Eslöv.\nTillverkar byggnadssnickerier samt\nsågade och hyvlade trävaror. Bolaget\ndriver även engros- och minuthandel med\nträvaror, byggnadsmateriel, mjöl,\nspannmål m. m.\n\nTelegr.-adr.: Johan, Eslöv. Telefon:\n»Johnson &amp; Co.». Postgiro: 7559. —\nAkt.-kap.: 1,000,000 kr. Antal\nindustriarb.: 100. — Firman etabl. 1868, bolag\n1929.\n\nVerkst. dir.: Harry Johnson.\n\"Nils Jonssons Möbelsnickeri, Tibro.\n\nTillverkar som specialité\nkompletteringsmöbler vid verkstad i Tibro\n(Skarab. l.).\n\nTelefon: 104. Postgiro: 85399. —\nAntal industriarb.: 3. — Firman etabl. 1916.\n\nÄgare o. chef: snickaremäst. Nils\nJonsson.\n\nAB. Ossvald Jonsson &amp; G:o-,\n\nEskilstuna.\n\nMek. verkstad. Tillverkar hejarstansar\noch pressverktyg; utför hejnings- och\nplåtpressningsarbeten samt massartiklar\nav metall och järn. Specialitet: beslag för\npärm ti 11 verkning.\n\nTelefon: 31304 o. 31105. Postgiro:\n98599. — Akt.-kap.: 150,000 kr. Antal\nindustriarb.: 100. Tillv.-värde pr år:\n1,000,000 kr. — Firman etabl. 1922, bolag\n1941.\n\nStyrelse o. verkst. direktörer: fabr.\nOssvald Jonsson o. fabr. Oscar Persson.\n\nS. E. Jonsson, Malung.\n\nTillverkar skinntröjor och -västar,\nbilkläder, bilhandskar samt dam- och\nsportjackor vid fabrik i Malung (Kopparb. l.).",
    "structured": {
        "firms": [
            {
                "name": "E. Jonson",
                "location": "Sundbyberg",
                "business": "Armaturfabrik & Metall-gjuteri",
                "products": "Tillverkar utblåsnings- och glasrörs-kranar, elektr. belysningsarmatur, bryggeriarmatur, mejeri armatur samt mjölk-rnätningsapparaten »Eok».",
                "contact": {
                    "office": "Sundbyberg",
                    "phone": [
                        "Stockholm 281226"
                    ],
                    "postgiro": "14231",
                    "factory_office": "Sundbyberg",
                    "factory_phone": "Sundbyberg",
                    "telegraph": "Sundbyberg"
                },
                "financials": {
                    "capital": "Not specified",
                    "employees": {
                        "total": 10
                    },
                    "annual_turnover": "75,000 kr",
                    "annual_production_value": "Not specified"
                },
                "foundation_year": 1912,
                "owner": "fabr. Evald Jonson"
            },
            {
                "name": "C. Jonsson & Co-",
                "location": "Teg",
                "business": "Böleå Snickerifabrik",
                "products": "Not specified",
                "contact": {
                    "office": "Böleå",
                    "phone": [],
                    "postgiro": "Not specified"
                },
                "financials": {
                    "capital": "Not specified",
                    "employees": {
                        "total": "Not specified"
                    },
                    "annual_turnover": "Not specified",
                    "annual_production_value": "Not specified"
                },
                "foundation_year": "Not specified",
                "owner": "G. Jonsson & Co., Teg"
            },
            {
                "name": "Henrik Johnsson & Comp. Skinnindustri AB.",
                "location": "Malung",
                "business": "Skinnindustri",
                "products": "Not specified",
                "contact": {
                    "office": "Malung",
                    "phone": [
                        "Malung 72041"
                    ],
                    "postgiro": "62396"
                },
                "financials": {
                    "capital": "Not specified",
                    "employees": {
                        "total": "Not specified"
                    },
                    "annual_turnover": "Not specified",
                    "annual_production_value": "Not specified"
                },
                "foundation_year": 1909,
                "owner": "fabr. Johan Jonsson"
            },
            {
                "name": "John Johnsons Bokbinderi",
                "location": "Göteborg",
                "business": "Bokbinderi",
                "products": "Utför bindning av privat- och biblioteksband samt av massupplagor.",
                "contact": {
                    "office": "Göteborg",
                    "phone": [
                        "134165"
                    ],
                    "postgiro": "42905"
                },
                "financials": {
                    "capital": "Not specified",
                    "employees": {
                        "total": 20
                    },
                    "annual_turnover": "Not specified",
                    "annual_production_value": "Not specified"
                },
                "foundation_year": 1924,
                "owner": "bokbindaremäst. John J ohnson"
            },
            {
                "name": "AB. Jon Jonsson & Co.",
                "location": "Ljusdal",
                "business": "Sågverk och kolugnar",
                "products": "Tillverkar sågade och hyvlade trävaror, listverk, stav, bilade sparrar m. m. samt träkol, gengaskol och trätjära.",
                "contact": {
                    "office": "Ljusdal",
                    "phone": [
                        "1001",
                        "1755"
                    ],
                    "postgiro": "77088"
                },
                "financials": {
                    "capital": "1,150,000 kr",
                    "employees": {
                        "total": 135
                    },
                    "annual_turnover": "5,500,000 kr",
                    "annual_production_value": "Not specified"
                },
                "foundation_year": 1887,
                "owners": [
                    "dir. Jonas Jonsson"
                ]
            },
            {
                "name": "L. A. Jonssons Skidfabriks AB.",
                "location": "Östersund",
                "business": "Tillverkar skidor",
                "products": "Specialitet: kvalitetsskidor av hiekory och björk.",
                "contact": {
                    "office": "Östersund",
                    "phone": [
                        "245"
                    ],
                    "postgiro": "133982"
                },
                "financials": {
                    "capital": "50,000 kr",
                    "employees": {
                        "total": 40
                    },
                    "annual_turnover": "500,000 kr",
                    "annual_production_value": "Not specified"
                },
                "foundation_year": 1888,
                "board": [
                    {
                        "name": "Clarence Hammar",
                        "role": "Verkst. dir."
                    }
                ]
            },
            {
                "name": "AB. N. Johnson & Co.",
                "location": "Eslöv",
                "business": "Snickerifabrik och hyvleri",
                "products": "Tillverkar byggnadssnickerier samt sågade och hyvlade trävaror.",
                "contact": {
                    "office": "Eslöv",
                    "phone": [
                        "Not specified"
                    ],
                    "postgiro": "7559"
                },
                "financials": {
                    "capital": "1,000,000 kr",
                    "employees": {
                        "total": 100
                    },
                    "annual_turnover": "Not specified",
                    "annual_production_value": "Not specified"
                },
                "foundation_year": 1868,
                "director": "Harry Johnson"
            },
            {
                "name": "Nils Jonssons Möbelsnickeri",
                "location": "Tibro",
                "business": "Möbelsnickeri",
                "products": "Tillverkar som specialité kompletteringsmöbler vid verkstad i Tibro (Skarab. l.).",
                "contact": {
                    "office": "Tibro",
                    "phone": [
                        "104"
                    ],
                    "postgiro": "85399"
                },
                "financials": {
                    "capital": "Not specified",
                    "employees": {
                        "total": 3
                    },
                    "annual_turnover": "Not specified",
                    "annual_production_value": "Not specified"
                },
                "foundation_year": 1916,
                "owner": "snickaremäst. Nils Jonsson"
            },
            {
                "name": "AB. Ossvald Jonsson & G:o-",
                "location": "Eskilstuna",
                "business": "Mek. verkstad",
                "products": "Tillverkar hejarstansar och pressverktyg; utför hejnings- och plåtpressningsarbeten samt massartiklar av metall och järn.",
                "contact": {
                    "office": "Eskilstuna",
                    "phone": [
                        "31304",
                        "31105"
                    ],
                    "postgiro": "98599"
                },
                "financials": {
                    "capital": "150,000 kr",
                    "employees": {
                        "total": 100
                    },
                    "annual_turnover": "1,000,000 kr",
                    "annual_production_value": "Not specified"
                },
                "foundation_year": 1922,
                "owners": [
                    "fabr. Ossvald Jonsson",
                    "fabr. Oscar Persson"
                ]
            },
            {
                "name": "S. E. Jonsson",
                "location": "Malung",
                "business": "Tillverkar skinntröjor och -västar, bilkläder, bilhandskar samt dam- och sportjackor",
                "products": "Not specified",
                "contact": {
                    "office": "Malung",
                    "phone": [
                        "Not specified"
                    ]
                },
                "financials": {
                    "capital": "Not specified",
                    "employees": {
                        "total": "Not specified"
                    },
                    "annual_turnover": "Not specified",
                    "annual_production_value": "Not specified"
                },
                "foundation_year": "Not specified"
            }
        ]
    }
}