{
    "original": "Nyköping—Ny silver fabriken\n\nAB. Nyköpings Träindustri,\n\nNyköping.\n\nTillverkar fotografiramar, ramlist,\nförgyllda kompletteringsmöbler och\nsnickeriarbeten.\n\nTelegr.-adr.: Nyträ, Nyköping. Telefon:\n880 o. 2917. Postgiro: 177182. —\nAkt.-kap.: 60,000 kr. Antal industriarb.: 120.\nTillv.-värde pr år: 1,000,000 kr. —\nBolaget grundat 1941.\n\nVerkst. dir.: Ivan Thor.\nDisp.: Lennart Thor.\n\nAB. Nyköpingsverken, Nyköping.\n\nMek. verkstad och plåtslageri i\nNyköping (Södermanl. l.). Tillverkar svetsade\nvärmeledningspannor samt cykeltillbehör.\nVarumärke: »Durospeed».\n\nTelefon: 2267. Postgiro: 272246. Repr.\nför cykeltillbehör: AB. Bendroth &amp;\nGabrielsson, Stockholm, Kungsg. 4 B,\ntelefon: 110994.\n\nAkt.-kap.: 100,000 kr. Antal\nindustriarb.: 40. Tillv.-värde pr år: 725,000 kr.\n\n—\tBolaget grundat 1944.\nVerkst. dir.: Nils Wålinder.\n\n\"Nylund &amp; Son Pianofabrik,\n\nU ppsala.\n\nTillverkar pianon och kammarpianon.\nTelefon: 31519 o. 32519. Postgiro:\n88140.\n\nAkt.-kap.: 125,000 kr. Antal\nindustriarb.: 29. Tillv.-värde pr år: 375,000 kr.\n\n—\tFirman etabl. 1906.\n\nÄgare o chef: fabr. Emil Nylund.\n\nAB. I. Nylunds Litografiska Anstalt,\n\nStockholm.\n\nUtför reklamtryck, affischer och\netiketter.\n\nKontor: Döbelnsg. 3. Telefon: 116107\no. 204343. Postgiro: 4054.\n\nAkt.-kap.: 75,000 kr. Antal\nindustriarb.: 30. Tillv.-värde pr år: 400,000 kr.\n\n—\tFirman etabl. 1873, bolag 1905.\nVerkst. dir.: Carl-Erik Nylund.\n\nNyma Manufaktur AB., Flen.\n\nTillverkar baddräkter och badkappor\nvid trikåfabrik i Flen (Södermanl. l.).\nVarumärke: »Solelastik».\n\nTelefon: 260. Postgiro: 174537. Repr.\ni Stockholm: W. Meyer, Hagagatan 24,\ntelefon: 334883.\n\nAkt.-kap.: 25,000 kr. Antal\nindustriarb.: 20. Tillv.-värde pr år: 250,000 kr.\n\n—\tFirman etabl. 1940, bolag 1944.\nVerkst. dir.: Curt Weissenberg.\n\n\"Nyman &amp; Nyman, Höganäs.\n\nSe Höganäskeramik, Nyman &amp; Nyman,\nHöganäs.\n\nNyman, Bröderna, Länghem.\n\nSe Bröderna Nyman, Länghem.\n\n\"AB. Nymans Verkstäder, Uppsala.\n\nVelocipedfabrik och mek. verkstad.\nTillverkar cyklar och cykeldelar.\nSpecialmärken: »Hermes», »Crescent»,\n»Nord-st jernan» o. »Vega».\n\nTelegr.-adr.: Nymännerna, Uppsala.\nTelefon: »Nymans». Postgiro: 9922.\nAvd.-kontor: i Stockholm, Regeringsg. 109,\ntelefon: 110122 o. 110182; i Malmö,\nNor-reg, 6, telefon: 28534—36; i Göteborg,\nOding. 26, telefon: »Nymanbolagen»; i\nLinköping o. Luleå.\n\nAkt.-kap.: 4,500,000 kr. Antal\nindustriarb.: 1,016. — Bolaget grundat 1899.\n\nStyrelse: dir. Helge Norlander (ordf.),\ndir. Erik G. Pehrsson (v. ordf.),\nintendent Nils Eneström, dir. Erik A.\nGill-berg, dir. Gustaf Grahn, ing. Erland\nStåhlnacke, bankdir. Eric Tofte.\n\nVerkst. dir.: Gustaf Grahn.\n\nFörsäljn.-chef: Edvin Lundgren.\n\nInköpschef: E. Krigström.\n\n(Jfr annons nr 67.)\n\n\"Nynäshamns Tryckeri AB.,\n\nNynäshamn.\n\nUtför civiltryck, blanketter, formulär\noch affärstryck vid tryckeri i\nNynäshamn (Sthlms l.).\n\nTelefon: 128 o. 818. Postgiro: 28442.\n\n—\tAkt.-kap.: 9,600 kr. Arb.-antal: 7.\nTillv.-värde pr år: 142,000 kr. — Firman\netabl. 1916, bolag 1933.\n\nStyrelse: red. Gunnar Norberg (ordf.),\navsynare Algot Andersson, verkm. Axel\nFredlund, # montör Hjalmar Holmstedt,\nkontorsskriv. Karl-Olof Virén.\n\nTryckeriföreståndare: Aino Nyholm.\n\n\"Nysilverfabriken Aurora AB.,\n\nGöteborg.\n\nTillverkar som specialitet\nkuvertnysilver samt utför förkromning,\nomförsilv-ring och andra galvaniska utfällningar.\n\nKontor: Norra Kustbanegatan 19.\nTelegr.-adr.: Aurora, Göteborg. Telefon:\n155401. Postgiro: 12333.\n\nAkt.-kap.: 200,000 kr. Antal\nindustriarb.: 26. Tillv.-värde pr år: 400,000 kr.\n\n—\tFabriken anlagd 1911, bolag 1945.\n\nStyrelse: fru A. Gustafson (ordf.),\n\ndisp. John Hellsing.\n\nVerkst. dir.: John Hellsing,",
    "structured": {
        "1": {
            "name": "AB. Nyköpings Träindustri",
            "location": "Nyköping",
            "business": "Tillverkar fotografiramar, ramlist, förgyllda kompletteringsmöbler och snickeriarbeten",
            "contact": {
                "office": "",
                "phone": [
                    "880",
                    "2917"
                ],
                "postgiro": "177182",
                "head_office": "",
                "sales_offices": [],
                "telegraph": "Nyträ, Nyköping",
                "factory_office": "",
                "factory_phone": ""
            },
            "financials": {
                "capital": "60,000 kr",
                "employees": {
                    "industriarb": 120
                },
                "annual_turnover": "1,000,000 kr",
                "annual_production_value": "1,000,000 kr"
            },
            "foundation_year": 1941,
            "board": [],
            "owners": [],
            "director": "Ivan Thor",
            "managing_director": "Lennart Thor"
        },
        "2": {
            "name": "AB. Nyköpingsverken",
            "location": "Nyköping (Södermanl. l.)",
            "business": "Tillverkar svetsade värmeledningspannor samt cykeltillbehör. Varumärke: »Durospeed»",
            "contact": {
                "office": "",
                "phone": [
                    "2267"
                ],
                "postgiro": "272246",
                "head_office": "",
                "sales_offices": [
                    {
                        "location": "Stockholm",
                        "phone": "110994"
                    }
                ],
                "telegraph": "",
                "factory_office": "",
                "factory_phone": ""
            },
            "financials": {
                "capital": "100,000 kr",
                "employees": {
                    "industriarb": 40
                },
                "annual_turnover": "725,000 kr",
                "annual_production_value": "725,000 kr"
            },
            "foundation_year": 1944,
            "board": [],
            "owners": [],
            "director": "Nils Wålinder"
        },
        "3": {
            "name": "Nylund & Son Pianofabrik",
            "location": "Uppsala",
            "business": "Tillverkar pianon och kammarpianon",
            "contact": {
                "office": "",
                "phone": [
                    "31519",
                    "32519"
                ],
                "postgiro": "88140",
                "head_office": "",
                "sales_offices": [],
                "telegraph": "",
                "factory_office": "",
                "factory_phone": ""
            },
            "financials": {
                "capital": "125,000 kr",
                "employees": {
                    "industriarb": 29
                },
                "annual_turnover": "375,000 kr",
                "annual_production_value": "375,000 kr"
            },
            "foundation_year": 1906,
            "board": [],
            "owners": [
                "fabr. Emil Nylund"
            ],
            "director": ""
        },
        "4": {
            "name": "AB. I. Nylunds Litografiska Anstalt",
            "location": "Stockholm",
            "business": "Utför reklamtryck, affischer och etiketter",
            "contact": {
                "office": "Döbelnsg. 3",
                "phone": [
                    "116107",
                    "204343"
                ],
                "postgiro": "4054",
                "head_office": "",
                "sales_offices": [],
                "telegraph": "",
                "factory_office": "",
                "factory_phone": ""
            },
            "financials": {
                "capital": "75,000 kr",
                "employees": {
                    "industriarb": 30
                },
                "annual_turnover": "400,000 kr",
                "annual_production_value": "400,000 kr"
            },
            "foundation_year": 1873,
            "corporation_year": 1905,
            "board": [],
            "owners": [],
            "director": "Carl-Erik Nylund"
        },
        "5": {
            "name": "Nyma Manufaktur AB.",
            "location": "Flen (Södermanl. l.)",
            "business": "Tillverkar baddräkter och badkappor",
            "contact": {
                "office": "",
                "phone": [
                    "260"
                ],
                "postgiro": "174537",
                "head_office": "",
                "sales_offices": [
                    {
                        "location": "Stockholm",
                        "phone": "334883"
                    }
                ],
                "telegraph": "",
                "factory_office": "",
                "factory_phone": ""
            },
            "financials": {
                "capital": "25,000 kr",
                "employees": {
                    "industriarb": 20
                },
                "annual_turnover": "250,000 kr",
                "annual_production_value": "250,000 kr"
            },
            "foundation_year": 1940,
            "board": [],
            "owners": [],
            "director": "Curt Weissenberg"
        },
        "6": {
            "name": "AB. Nymans Verkstäder",
            "location": "Uppsala",
            "business": "Tillverkar cyklar och cykeldelar. Specialmärken: »Hermes», »Crescent», »Nord-st jernan» o. »Vega»",
            "contact": {
                "office": "",
                "phone": [
                    "Nymans"
                ],
                "postgiro": "9922",
                "head_office": "",
                "sales_offices": [
                    {
                        "location": "Stockholm",
                        "phone": [
                            "110122",
                            "110182"
                        ]
                    },
                    {
                        "location": "Malmö",
                        "phone": "28534—36"
                    },
                    {
                        "location": "Göteborg",
                        "phone": "Nymanbolagen"
                    },
                    {
                        "location": "Linköping"
                    },
                    {
                        "location": "Luleå"
                    }
                ],
                "telegraph": "Nymännerna, Uppsala",
                "factory_office": "",
                "factory_phone": ""
            },
            "financials": {
                "capital": "4,500,000 kr",
                "employees": {
                    "industriarb": 1016
                },
                "annual_turnover": "",
                "annual_production_value": ""
            },
            "foundation_year": 1899,
            "board": [
                {
                    "name": "Helge Norlander",
                    "role": "ordf."
                },
                {
                    "name": "Erik G. Pehrsson",
                    "role": "v. ordf."
                },
                {
                    "name": "Nils Eneström",
                    "role": "intendent"
                },
                {
                    "name": "Erik A. Gill-berg",
                    "role": "dir."
                },
                {
                    "name": "Gustaf Grahn",
                    "role": "dir."
                },
                {
                    "name": "Erland Ståhlnacke",
                    "role": "ing."
                },
                {
                    "name": "Eric Tofte",
                    "role": "bankdir."
                }
            ],
            "owners": [],
            "director": "Gustaf Grahn",
            "sales_manager": "Edvin Lundgren",
            "manager": "E. Krigström"
        },
        "7": {
            "name": "Nynäshamns Tryckeri AB.",
            "location": "Nynäshamn",
            "business": "Utför civiltryck, blanketter, formulär och affärstryck vid tryckeri i Nynäshamn",
            "contact": {
                "office": "",
                "phone": [
                    "128",
                    "818"
                ],
                "postgiro": "28442",
                "head_office": "",
                "sales_offices": [],
                "telegraph": "",
                "factory_office": "",
                "factory_phone": ""
            },
            "financials": {
                "capital": "9,600 kr",
                "employees": {
                    "Arb.-antal": 7
                },
                "annual_turnover": "142,000 kr",
                "annual_production_value": "142,000 kr"
            },
            "foundation_year": 1916,
            "corporation_year": 1933,
            "board": [
                {
                    "name": "Gunnar Norberg",
                    "role": "ordf."
                },
                {
                    "name": "Algot Andersson",
                    "role": "avsynare"
                },
                {
                    "name": "Axel Fredlund",
                    "role": "verkm."
                },
                {
                    "name": "Hjalmar Holmstedt",
                    "role": "montör"
                },
                {
                    "name": "Karl-Olof Virén",
                    "role": "kontorsskriv."
                }
            ],
            "owners": [],
            "director": "Aino Nyholm"
        },
        "8": {
            "name": "Nysilverfabriken Aurora AB.",
            "location": "Göteborg",
            "business": "Tillverkar som specialitet kuvertnysilver samt utför förkromning, omförsilv-ring och andra galvaniska utfällningar",
            "contact": {
                "office": "Norra Kustbanegatan 19",
                "phone": [
                    "155401"
                ],
                "postgiro": "12333",
                "head_office": "",
                "sales_offices": [],
                "telegraph": "Aurora, Göteborg",
                "factory_office": "",
                "factory_phone": ""
            },
            "financials": {
                "capital": "200,000 kr",
                "employees": {
                    "industriarb": 26
                },
                "annual_turnover": "400,000 kr",
                "annual_production_value": "400,000 kr"
            },
            "foundation_year": 1911,
            "corporation_year": 1945,
            "board": [
                {
                    "name": "fru A. Gustafson",
                    "role": "ordf."
                },
                {
                    "name": "John Hellsing",
                    "role": "disp."
                }
            ],
            "owners": [],
            "director": "John Hellsing"
        }
    }
}