{
    "original": "F jugesta—Flen\n\nTelefon: 269 o. 930. Postgiro: 30157.\n\n—\tAkt.-kap.: 100,000 kr. Antal\nindustriarb.: 75. — Firman etabl. 1914, bolag\n1938.\n\nStyrelse: fabr. Axel Fjellman (ordf.),\nIng. Rune Fjellman, ing. Tore Fjellman.\nVerkst. dir.: Axel Fjellman.\n\n*AB. Fjugesta Möbelindustri,\n\nFjugesta.\n\nTillverkar möbler vid fabrik i Fjugesta\n(Örebro l.).\n\nTelefon: 48. Postgiro: 266681. —\nAkt.-kap.: 35,000 kr. Antal industriarb.: 20.\n\n—\tFirman etabl. 1923, bolag 1934.\nStyrelse: fabr. Erhard Berg (ordf.), fru\n\nAlma Berg, fru Ester Berg, fabr. Filip\nBerg, fabr. Helmer Lindmark.\nVerkst. dir.: Erhard Berg.\n\n*AB. Fjugesta Nya Tegelbruk,\n\nFjugesta.\n\nTillverkar murtegel, tak- och nocktegel,\nmellanväggsplattor samt dräneringsrör\nvid tegelbruk i Fjugesta (Örebro l.).\n\nTelefon: 7. Postgiro: 95355. —\nAkt.-ikap.: 40,000 kr. Antal industriarb.: 35.\nArstillv.: 2,3 milj. st. tegelvaror. —\nBolaget grundat 1910.\n\nVerkst. dir.: Petrus Wahlberg.\n\nAB. Fjugesta Rullgardinfabrik,\n\nFjugesta.\n\nTräförädlingsfabrik i Fjugesta (Örebro\n1.). Tillverkar rullgardinkäppar och\nrullgardiner.\n\nTelefon: 8. Postgiro: 23281. —\nAkt.-kap.: 150,000 kr. Antal industriarb.: 40.\nTillv.-värde pr år: 600,000 kr. — Firman\netabl. 1909, bolag 1918.\n\nStyrelse: godsäg. C. Wetter (ordf.),\nigodsäg. Eric Nilsson, godsäg. J. Roth,\ndisp. Ivar Wirén, kamrer Stig Wirén.\nDisp.: I. Wirén.\n\n* Fjäderfabriken Spiros AB.,\n\nUlv sunda.\n\nSpecialfabrik för tillverkning av\nspiralfjädrar såsom spiral-, platt-,\nvrid-och fasonfjädrar, muskelstärkare,\nspiralfjädrar för korsetter, böjliga axlar,\nfjäderbrickor, startmotor- och ventilfjädrar\nm. m. Varunamn: »Spiros» o. »Stella».\n\nKontor: Ranhammarsv. 11. Telefon:\n254808. 254809 o. 254810. Postgiro: 4028.\n\nAkt.-kap.: 300,000 kr. Antal\nindustriarb.: 45. Tillv.-värde pr år: 800,000 kr.\n\n—\tFirman etabl. 1919, bolag 1930.\n\nStyrelse: dir. L. Tell (ordf.), disp.\nAlgot S. Eklund, dir. Oskär A. Eklund.\n\nVerkst. dir.: Oskar A. Eklund.\n\nVerkstadschef: Algot S. Eklund.\n\nKamrer: Carl G. Eklund.\n\n(Jfr annons nr 97.)\n\nFjällbacka Stenhuggeri AB.,\n\nUddevalla.\n\nTillverkar gatsten, smågatsten och\nkantsten vid stenhuggeri i Fjällbacka\n(Göteb. o. Bohus l.).\n\nHuvudkontor o. ensam försälj.: Granit\nAB. O. A. Kullgrens Enka, Uddevalla.\nTelegr.-adr.: Kullgrens, Uddevalla.\nTelefon; 11158 o. 11668. Avd.-kontor:\nFjällbacka. Telefon: 15.\n\nAkt.-kap.: 10,000 kr. — Bolaget\ngrundat 1904.\n\nStyrelse o. verkst. dir.: Viktor\nKullgren.\n\nPlatsförest.: B. Truedson.\n\nAB. Fjäråsgneis, Göteborg.\n\nStenhuggeri i Fjärås (Hallands l.).\nTillverkar byggnadssten.\n\nKontor: Göteborg, Sannaplan 8.\nTelefon: 146423. Postgiro: 41632. —\nAkt.-kap.: 15,000 kr. Antal industriarb.: 25.\nProd.-värde pr år: 125,000 kr. — Bolaget\ngrundat 1929.\n\nVerkst. dir.: Roland Andersson.\n\nFlagg- &amp; Rullgardinsfabriken\n\"Kronan\" AB., Hälsingborg.\n\nTillverkar flaggor och rullgardiner.\n\nTelefon: 14182. Postgiro: 91682. —\nAkt.-kap.: 8,000 kr. Antal industriarb.:\n5. Tillv.-värde pr år: 150,000 kr. —\nBolaget grundat 1932.\n\nVerkst. dir.: fru Olga Ohlsson.\n\n*Flens Bryggeri AB., Flen.\n\nTillverkar svagdricka vid bryggeri i\nFlen (Södermanl. l.).\n\nTelefon: 271. — Akt.-kap.: 60,000 kr.\nArb.-antal: 10. Tillv.-värde pr år: 50,000\nkr. — Bolaget grundat 1930.\n\nStyrelse: disp. Gösta Sverdrup (ordf.),\ndisp. Carl Axel Andersson.\n\nVerkst. dir.: Carl Axel Andersson.\n\nFlens Elektro-Mek. Verkstad, Flen.\n\nTillverkar gjutjärnskapslade\ntriangelomkopplare samt trespoliga strömbrytare\nvid mek. verkstad i Flen (Södermanl. l.).",
    "structured": {
        "1": {
            "name": "AB. Fjugesta Möbelindustri",
            "location": "Fjugesta",
            "business": "Tillverkar möbler vid fabrik i Fjugesta (Örebro l.)",
            "contact": {
                "phone": [
                    "48"
                ],
                "postgiro": "266681"
            },
            "financials": {
                "capital": "35,000 kr",
                "employees": {
                    "antal industriarb.": 20
                }
            },
            "foundation_year": 1923,
            "corporation_year": 1934,
            "board": [
                {
                    "name": "fabr. Erhard Berg",
                    "role": "ordf."
                },
                {
                    "name": "fru Alma Berg",
                    "role": "other"
                },
                {
                    "name": "fru Ester Berg",
                    "role": "other"
                },
                {
                    "name": "fabr. Filip Berg",
                    "role": "other"
                },
                {
                    "name": "fabr. Helmer Lindmark",
                    "role": "other"
                }
            ],
            "director": "Erhard Berg"
        },
        "2": {
            "name": "AB. Fjugesta Nya Tegelbruk",
            "location": "Fjugesta",
            "business": "Tillverkar murtegel, tak- och nocktegel, mellanväggsplattor samt dräneringsrör vid tegelbruk i Fjugesta (Örebro l.)",
            "contact": {
                "phone": [
                    "7"
                ],
                "postgiro": "95355"
            },
            "financials": {
                "capital": "40,000 kr",
                "employees": {
                    "antal industriarb.": 35
                },
                "annual_production_value": "2,3 milj. st. tegelvaror"
            },
            "foundation_year": 1910,
            "owner": "verkst. dir.: Petrus Wahlberg"
        },
        "3": {
            "name": "AB. Fjugesta Rullgardinfabrik",
            "location": "Fjugesta",
            "business": "Träförädlingsfabrik i Fjugesta (Örebro l.). Tillverkar rullgardinkäppar och rullgardiner.",
            "contact": {
                "phone": [
                    "8"
                ],
                "postgiro": "23281"
            },
            "financials": {
                "capital": "150,000 kr",
                "employees": {
                    "antal industriarb.": 40
                },
                "annual_turnover": "600,000 kr"
            },
            "foundation_year": 1909,
            "corporation_year": 1918,
            "board": [
                {
                    "name": "godsäg. C. Wetter",
                    "role": "ordf."
                },
                {
                    "name": "igodsäg. Eric Nilsson",
                    "role": "other"
                },
                {
                    "name": "godsäg. J. Roth",
                    "role": "other"
                },
                {
                    "name": "disp. Ivar Wirén",
                    "role": "other"
                },
                {
                    "name": "kamrer Stig Wirén",
                    "role": "other"
                },
                {
                    "name": "disp.: I. Wirén",
                    "role": "other"
                }
            ]
        },
        "4": {
            "name": "Fjäderfabriken Spiros AB.",
            "location": "Ulv sunda",
            "business": "Specialfabrik för tillverkning av spiralfjädrar samt olika typer av fjädrar och fjäderprodukter.",
            "contact": {
                "phone": [
                    "254808",
                    "254809",
                    "254810"
                ],
                "postgiro": "4028"
            },
            "capital": "300,000 kr",
            "employees": {
                "antal industriarb.": 45
            },
            "annual_turnover": "800,000 kr",
            "foundation_year": 1919,
            "corporation_year": 1930,
            "board": [
                {
                    "name": "dir. L. Tell",
                    "role": "ordf."
                },
                {
                    "name": "disp. Algot S. Eklund",
                    "role": "other"
                },
                {
                    "name": "dir. Oskär A. Eklund",
                    "role": "other"
                }
            ],
            "director": "Oskar A. Eklund",
            "managing_director": "Oskär A. Eklund",
            "sales_manager": "Algot S. Eklund"
        },
        "5": {
            "name": "Fjällbacka Stenhuggeri AB.",
            "location": "Uddevalla",
            "business": "Tillverkar gatsten, smågatsten och kantsten vid stenhuggeri i Fjällbacka (Göteb. o. Bohus l.).",
            "contact": {
                "phone": [
                    "11158",
                    "11668"
                ]
            },
            "capital": "10,000 kr",
            "foundation_year": 1904,
            "director": "Viktor Kullgren",
            "platsförest": "B. Truedson"
        },
        "6": {
            "name": "AB. Fjäråsgneis",
            "location": "Göteborg",
            "business": "Stenhuggeri i Fjärås (Hallands l.). Tillverkar byggnadssten.",
            "contact": {
                "phone": [
                    "146423"
                ],
                "postgiro": "41632"
            },
            "capital": "15,000 kr",
            "employees": {
                "antal industriarb.": 25
            },
            "annual_production_value": "125,000 kr",
            "foundation_year": 1929,
            "director": "Roland Andersson"
        },
        "7": {
            "name": "Flagg- & Rullgardinsfabriken 'Kronan' AB.",
            "location": "Hälsingborg",
            "business": "Tillverkar flaggor och rullgardiner.",
            "contact": {
                "phone": [
                    "14182"
                ],
                "postgiro": "91682"
            },
            "capital": "8,000 kr",
            "employees": {
                "antal industriarb.": 5
            },
            "annual_turnover": "150,000 kr",
            "foundation_year": 1932,
            "director": "fru Olga Ohlsson"
        },
        "8": {
            "name": "Flens Bryggeri AB.",
            "location": "Flen",
            "business": "Tillverkar svagdricka vid bryggeri i Flen (Södermanl. l.).",
            "contact": {
                "phone": [
                    "271"
                ]
            },
            "capital": "60,000 kr",
            "employees": {
                "arb.-antal": 10
            },
            "annual_turnover": "50,000 kr",
            "foundation_year": 1930,
            "board": [
                {
                    "name": "disp. Gösta Sverdrup",
                    "role": "ordf."
                },
                {
                    "name": "disp. Carl Axel Andersson",
                    "role": "other"
                }
            ],
            "director": "Carl Axel Andersson"
        },
        "9": {
            "name": "Flens Elektro-Mek. Verkstad",
            "location": "Flen",
            "business": "Tillverkar gjutjärnskapslade triangelomkopplare samt trespoliga strömbrytare vid mek. verkstad i Flen (Södermanl. l.).",
            "contact": {
                "phone": [
                    "염271"
                ]
            }
        }
    }
}