{
    "original": "Rockström—Rosén\n\ndir. Allan. Ahrel, ing. Ingemar Ahrel,\nadv. Claes Ljiing, dir. O. Melin.\n\nVerkst, dir.: A. Ahrel.\n\nRoqkströms Fabriker Goa AB.,\n\nNorrköping.\n\nEssensfabrik. Tillverkar fruktessenser,\nfruktextrakter och fruktkoncentrater för\nläskedrycks-, saft-, likör- och\nsötvaru-industrien samt för konditorier och\nbagerier. Varumärke: »Goa». Firman driver\näven engroshandel med salter för\nmineralvatten, glycos och fruktsyror.\n\nTelegr.-adr.: GOA, Norrköping.\nTelefon: 27295. Postgiro: 31555.\n\nAkt.-kap.: 50,000 kr. Arb.-antal: 21.\n\n—\tFirman etabl. 1934, nuv. bolag 1942.\n\nVerkst. dir.: Ivar I:son Rockström.\n\nDisp,: ing. Kurt Rockström.\n\nKamrer: Harry Holmqvist.\n\n\"Rockwool AB., Skövde.\n\nIsoleringsmaterialfabrik vid Carlsro,\nSkövde. Tillverkar mineralull och\nfärdigfabrikat hära¥ för värme-, köld- och\nljudisolering samt för ljudabsorption.\nVarumärken: »Rockwool», »Stenull» o.\n»Svensk stenull».\n\nTelegr.-adr.: Rockwool, Skövde.\nTelefon: 2270. Postgiro: 134062. —\nAkt.-kap.: 300,000 kr. Antal industriarb.: 80.\n\n—\tBolaget grundat 1938.\n\nVerkst. dir.: ing. Eric Grane.\n\n(Jfr annons nr 25.)\n\nRölling Fabriks AB., Stockholm,.\n\nMek. verkstad. Tillverkar\nbandslipma-skiner. Varumärke: »Rolling».\n\nKontor: Stockholm, Strandv. 3.\nTelegr.-adr.: Rollingbolag, Stockholm. Telefon:\n070760.\n\nAkt.-kap.: 25,000 kr. Antal\nindustriarb.: 5, Tillv.-värde pr år: 250,000 kr. —\nBolaget grundat 1945.\n\nVerkst. dir.: Richard Rönström.\n\nKamrer: Oscar ^Ohlson.\n\n(Jfr annons nr 87.)\n\nA B. Roos Skyltreklam, Västerås.\n\nTillverkar neonskyltar, lysrör,\nglasskyltar och fasad bokstäver.\n\nHuvudkontor: Västerås. Telefon: 31550.\nPostgiro: 26113. Avd.-kontor: Stockholm,\nMästersamuelsg. 20. telefon: 105161.\nRepr. i Göteborg: Erik Kjellström,\ntelefon: 115679.\n\nAkt.-kap.: 10.000 kr. Antal\nindustriarb.: 50. Tillv.-värde pr år: 1,000,000 kr.\n—- Firman etabl. 1916, bolag 1923.\n\nChefer: fabr. Sigurd Roos o. fabr.\nRagnar Roos.\n\nDriftsing.: Bertil Sundberg.\n\nE. S. ROOS AB., Perstorp.\t1\n\nTräförädlingsfabrik i Perstorp\n(Kristianst. l.). Tillverkar rundstav (donyels),\nsvarvade massartiklar, husgerådsartikjar\nm. m. Specialiteter: karamellpinnar,’och\nparaplykäppar.\n\nTelegr.-adr.: Roosab, Perstorp.\nTelefon: 37. Postgiro: 287928. — Akt.-kap.:\n200,000 kr. Antal industriarb.: 30.\nTillv.-värde pr år: 600,000 kr. — Firman, etabl.\n1905, bolag 1944.\n\nVerkst. dir. o. disp.: Ilenric Lennås.\n\n*AB. Rory, Borås.\n\nHerrkonfektionsfabrik. Tillverkar\nherrkläder. Varumärke: »Rory».\n\nTelegr.-adr. o. telefon: Rory, Borås.\nPostgiro: 5377.\n\nAkt.-kap.: 350,000 kr. Antal\nindustriarb.: 250. Tillv.-värde pr år: 4,700,000 kr.\n\nFirman etabl. 1899, bolag 1915 under\nnamn Rob. Rydins Handels- &amp; Fabriks\nAB., nuv. namn 1937.\n\nStyrelse: dir. Gunnar Roos, fru Signe\nRoos.\n\nVerkst. dir.: Gunnar Roos.\n\n*AB. Rosdala Glasbruk, Norrhult:\n\nGlasbruk vid Norrhult (Kronob. l.) för\ntillverkning av belysningsglas,^ speciellt\nlampglas samt glas för elektrisk\nbelysning.\n\nTelefon: 2. Postgiro: 36521. —\nAkt.-kap.: 400,000 kr. Antal industriarb.: 90.\nTillv.-värde pr år: 800,000 kr. — Bolaget\ngrundat 1900.\n\nStyrelse: grossh. Emil Karlsson (ordf.),\ndisp. Oscar Nyrén, disp. Theodor Ny ren.\n\nVerkst. dir.: Theodor Nyrén.\n\nRoselis Fabriks- &amp; Handelsbolag,\n\nSkövde.\n\nSyfabrik. Tillverkar dam- och\nbarnkläder, klänningar, blusar m. m. Bolaget\ndriver även engroshandel med\nmanufaktur- och kortyaror.\n\nTelefon: 837 o. 997. — Antal\nindustriarb.: 22. — Firman etabl. 1935. 0:\n\nDir.: Erik Roseli.\n\nRoséns Trikåindustri,\n\nUlricehamn.\n\nTillverkar herr- och damunderkläder.\n\nTelefon: 482. Postgiro: 172794. —\nArb.-antal: 10. Tillv.-värde pr år: 95,000 kr.\n— Firman etabl. 1934.\n\nÄgare o. chef : fabr. Isac Rosén.",
    "structured": {
        "SwedishFirms": [
            {
                "name": "Rockströms Fabriker Goa AB.",
                "location": "Norrköping",
                "business": "Essensfabrik",
                "products": "Tillverkar fruktessenser, fruktextrakter och fruktkoncentrater för läskedrycks-, saft-, likör- och sötvaru-industrien samt för konditorier och bagerier. Driver även engroshandel med salter för mineralvatten, glycos och fruktsyror.",
                "contact": {
                    "office": "Norrköping",
                    "phone": [
                        "27295"
                    ],
                    "postgiro": "31555",
                    "telegraph": "GOA, Norrköping"
                },
                "financials": {
                    "capital": "50,000 kr",
                    "employees": {
                        "Arb.-antal": 21
                    },
                    "foundation_year": 1934,
                    "current_name_year": 1942
                },
                "board": [
                    {
                        "name": "Ivar I:son Rockström",
                        "role": "Verkst. dir."
                    },
                    {
                        "name": "Ing. Kurt Rockström",
                        "role": "Disp."
                    },
                    {
                        "name": "Harry Holmqvist",
                        "role": "Kamrer"
                    }
                ]
            },
            {
                "name": "Rockwool AB.",
                "location": "Skövde",
                "business": "Isoleringsmaterialfabrik",
                "products": "Tillverkar mineralull och färdigfabrikat hära¥ för värme-, köld- och ljudisolering samt för ljudabsorption.",
                "contact": {
                    "office": "Carlsro, Skövde",
                    "phone": [
                        "2270"
                    ],
                    "postgiro": "134062",
                    "telegraph": "Rockwool, Skövde"
                },
                "financials": {
                    "capital": "300,000 kr",
                    "employees": {
                        "Antal industriarb.": 80
                    },
                    "foundation_year": 1938
                },
                "board": [
                    {
                        "name": "Ing. Eric Grane",
                        "role": "Verkst. dir."
                    }
                ]
            },
            {
                "name": "Rölling Fabriks AB.",
                "location": "Stockholm",
                "business": "Mek. verkstad",
                "products": "Tillverkar bandslipma-skiner.",
                "contact": {
                    "office": "Stockholm, Strandv. 3",
                    "phone": [
                        "070760"
                    ],
                    "postgiro": null,
                    "telegraph": "Rollingbolag, Stockholm"
                },
                "financials": {
                    "capital": "25,000 kr",
                    "employees": {
                        "Antal industriarb.": 5,
                        "Tillv.-värde pr år": 250,
                        "000 kr": 250000
                    },
                    "corporation_year": 1945
                },
                "board": [
                    {
                        "name": "Richard Rönström",
                        "role": "Verkst. dir."
                    },
                    {
                        "name": "Oscar ^Ohlson",
                        "role": "Kamrer"
                    }
                ]
            },
            {
                "name": "A B. Roos Skyltreklam",
                "location": "Västerås",
                "business": "Tillverkar neonskyltar, lysrör, glasskyltar och fasad bokstäver.",
                "contact": {
                    "office": "Västerås",
                    "phone": [
                        "31550"
                    ],
                    "postgiro": "26113",
                    "sales_offices": [
                        {
                            "location": "Stockholm, Mästersamuelsg. 20",
                            "phone": "105161"
                        }
                    ]
                },
                "financials": {
                    "capital": "10,000 kr",
                    "employees": {
                        "Antal industriarb.": 50,
                        "Tillv.-värde pr år": 1000,
                        "000 kr": 1000000
                    },
                    "corporation_year": 1923
                },
                "owners": [
                    "Fabr. Sigurd Roos",
                    "Fabr. Ragnar Roos"
                ],
                "director": "Bertil Sundberg"
            },
            {
                "name": "E. S. ROOS AB.",
                "location": "Perstorp",
                "business": "Träförädlingsfabrik",
                "products": "Tillverkar rundstav (donyels), svarvade massartiklar, husgerådsartikjar m. m. Specialiteter: karamellpinnar,’och paraplykäppar.",
                "contact": {
                    "office": "Perstorp (Kristianst. l.)",
                    "phone": [
                        "37"
                    ],
                    "postgiro": "287928",
                    "telegraph": "Roosab, Perstorp"
                },
                "financials": {
                    "capital": "200,000 kr",
                    "employees": {
                        "Antal industriarb.": 30,
                        "Tillv.-värde pr år": 600,
                        "000 kr": 600000
                    },
                    "corporation_year": 1944
                },
                "director": "Ilenric Lennås"
            },
            {
                "name": "AB. Rory",
                "location": "Borås",
                "business": "Herrkonfektionsfabrik",
                "products": "Tillverkar herrkläder.",
                "contact": {
                    "office": "Borås",
                    "phone": null,
                    "postgiro": "5377"
                },
                "financials": {
                    "capital": "350,000 kr",
                    "employees": {
                        "Antal industriarb.": 250,
                        "Tillv.-värde pr år": 4700,
                        "000 kr": 4700000
                    },
                    "corporation_year": 1915,
                    "original_name": "Rob. Rydins Handels- &amp; Fabriks AB.",
                    "current_name_year": 1937
                },
                "board": [
                    {
                        "name": "Gunnar Roos",
                        "role": "Styrelse"
                    },
                    {
                        "name": "Fru Signe Roos",
                        "role": "Styrelse"
                    },
                    {
                        "name": "Gunnar Roos",
                        "role": "Verkst. dir."
                    }
                ]
            },
            {
                "name": "AB. Rosdala Glasbruk",
                "location": "Norrhult",
                "business": "Glasbruk",
                "products": "För tillverkning av belysningsglas,^ speciellt lampglas samt glas för elektrisk belysning.",
                "contact": {
                    "office": "Norrhult (Kronob. l.)",
                    "phone": [
                        "2"
                    ],
                    "postgiro": "36521",
                    "telegraph": "Roosab, Perstorp"
                },
                "financials": {
                    "capital": "400,000 kr",
                    "employees": {
                        "Antal industriarb.": 90,
                        "Tillv.-värde pr år": 800,
                        "000 kr": 800000
                    },
                    "foundation_year": 1900
                },
                "board": [
                    {
                        "name": "Grossh. Emil Karlsson",
                        "role": "Styrelse"
                    },
                    {
                        "name": "Disp. Oscar Nyrén",
                        "role": "Styrelse"
                    },
                    {
                        "name": "Theodor Nyrén",
                        "role": "Verkst. dir."
                    }
                ]
            },
            {
                "name": "Roselis Fabriks- &amp; Handelsbolag",
                "location": "Skövde",
                "business": "Syfabrik",
                "products": "Tillverkar dam- och barnkläder, klänningar, blusar m. m. Driver även engroshandel med manufaktur- och kortyaror.",
                "contact": {
                    "office": "Skövde",
                    "phone": [
                        "837",
                        "997"
                    ]
                },
                "financials": {
                    "employees": {
                        "Arb.-antal": 22
                    },
                    "foundation_year": 1935
                },
                "director": "Erik Roseli"
            },
            {
                "name": "Roséns Trikåindustri",
                "location": "Ulricehamn",
                "business": "Tillverkar herr- och damunderkläder",
                "contact": {
                    "phone": [
                        "482"
                    ],
                    "postgiro": "172794"
                },
                "financials": {
                    "employees": {
                        "Arb.-antal": 10,
                        "Tillv.-värde pr år": 95,
                        "000 kr": 95000
                    },
                    "foundation_year": 1934
                },
                "manager": "fabr. Isac Rosén."
            }
        ]
    }
}