{
    "original": "Kolbäck—Kommanditbolaget\n\nsom strömbrytare, säkringslådor,\ncentraler för belysning och kraft m. m.\nVarumärke: »KEV».\n\nTelegr.-adr.: Elektriska, Kolbäck.\nTelefon: 2 o. 12. Postgiro: 25170.\n\nAntal industriarb.: 45. Tillv.-värde pr\når: 1,000,000 kr. — Firman etabl. 1919.\n\nÄgare o. chef: fabr. David Karlsson.\n\n\"AB. Kolbäcks Träindustrier,\n\nKolbäck.\n\nTillverkar byggnadssnickerier samt\nsågade och hyvlade trävaror vid\nsnickerifabrik och sågverk i Kolbäck (Västmanl. l.).\nTelefon: 116 o. 117. Postgiro: 266500.\n\n—\tAkt.-kap.: 41,000 kr. Antal\nindustriarb.: 25. Tillv.-värde pr år: 4Q0,000 kr.\n\n—\tBolaget grundat 1926.\n\nStyrelse: banmäst. Oskar W.\nAndersson (ordf.), folkskollärare Knut\nBjörklund, lantbr. Nils Laggberg, disp.\nGottfrid Larsson, lantbr. Petrus Peterson.\nVerkst. dir. o. disp.: Gottfrid Larsson.\n\n\"AB. Kolimporten—Laurents,\n\nSundsvall.\n\nSågverk och hyvleri i Sundsvall,\ntegelbruk i Högom och Nacksta (Västernorrl.\n1.). Tillverkar sågade och hyvlade\nträvaror samt murtegel. Bolaget driver\njämväl engroshandel med kol, koks och\nbyggnadsmaterial.\n\nTelefon: »Kolimporten—Laurents»,\nSundsvall. Postgiro: 28190.\n\nAkt.-kap.: 300,000 kr. Antal\nindustriarb.: 125. Årstillv.: 1,500 stds trävaror,\n5 milj. murtegel. — Firman grundlagd\n1897, nuv. bolag 1938.\n\nStyrelse: dir. Kjell Beijer, dir. B.\nHjerpstedt, dir. H. Lönnegårdh.\n\nVerkst. dir.: B. Hjerpstedt.\n\nAB. Kollin &amp; Ström, Borlänge.\n\nMek. verkstad och grovplåtslageri i\nBorlänge (Kopparb. l.). Tillverkar\nperforerad plåt och värmeradiatorer samt\nutför grovplåtsarbeten och\njärnkonstruktioner.\n\nTelegr.-adr.: Grovplåt, Borlänge.\nTelefon: 10117 o. 11017. Postgiro: 28717.\n\nAkt.-kap.: 300,000 kr. Antal\nindustriarb.: 65. Tillv.-värde pr år: 800,000 kr.\n— Firman etabl. 1900, bolag 1911.\n\nStyrelse: generalkonsul Torsten O.\nSöderberg (ordf.), dir. Joel Björklund,\nkonsul H. Bursie.\n\nVerkst. dir.: Joel Björklund.\n\n(Jfr annons nr 28.)\n\n\"Kolningbergs Crufve AB.,\n\nKärrgruvan.\n\nSe Norbergs Grufförvaltning,\nKärrgruvan.\n\n\"Kolsyrefabrikernas AB.,\n\nLiljeholmen.\n\nSe De Förenade Kolsyrefabrikerna»\nAB., Stockholm.\n\n\"Kommanditbolaget Albin Motor,\n\nKristinehamn.\n\nSe Albin Motor Kommanditbol., L. A»\nLarsson, Kristinehamn.\n\nKommanditbolaget Betong, Sander\n&amp; Co., Hednoret.\n\n. Cementvarufabriker i Hednoret och\nKalix (Norrbott. l.) samt i Bastuträsk\n(Västerbott. l.) och Umeå. Tillverkar\nbetongrör till avloppsledningar och\nväg-trummor, stolpar, husbyggnadsblock m. m.\n\nKontor: Hednoret. Telefon: Boden\n65016 o. 65060. Postgiro: 61211.\n\nAkt.-kap.: 38,600 kr. Antal\nindustriarb.: 62. Tillv.-värde pr år: 850,000 kr.\n— Bolaget grundat 1926.\n\nVerkst. dir.: vägmäst. Oskar Sander\n(Brännland).\nDisp.: ing. Bengt Sander.\nKamrer: Rune Larsson.\nDriftsing.: Wilhelm Hult.\n(Jfr annons nr 101.)\n\n\"Kommanditbolaget Bröderna Wallins\nNysilverfabrik, Lidköping.\n\nTillverkar kuvertartiklar av nysilver\noch rostfritt stål.\n\nTelefon: 20783. Postgiro: 70752. —\nAntal industriarb.: 80. Tillv.-värde pr år:\n1,500,000 kr. — Firman etabl. 1930.\n\nStyrelse: fabr. Einar Wallin (ordf.)v\nförsäljn.-chef Nils H. Lind, kamrer K. G.\nTunblad, fabr. Folke Wallin.\nVerkst. dir.: Einar Wallin.\n\nKommanditbolaget Ellkå, Fursten»\nberg &amp; Söner, Kalmar.\n\nSyfabrik. Tillverkar arbets- och\nsportkläder samt skjortor. Varumärke: »L.K.»\n\nTelefon: 1650. Postgiro: 263533. Repr.\ni Stockholm: Ivar Tardell, Drottningg^\n23, telefon: 104190. — Antal\nindustriarb.: 45. — Fabriken grundad 1927, nuv..\nfirma etabl. 1943.\n\nChef: dir. Sigismund Fiirstenberg.",
    "structured": {
        "1": {
            "name": "Kolbäck—Kommanditbolaget",
            "location": "Kolbäck",
            "business": "strömbrytare, säkringslådor, centraler för belysning och kraft m. m.",
            "products": "Varumärke: »KEV»",
            "contact": {
                "office": "Elektriska, Kolbäck",
                "phone": [
                    "2",
                    "12"
                ],
                "postgiro": "25170"
            },
            "financials": {
                "capital": "Not available (N/A)",
                "employees": {
                    "industriarb": 45
                },
                "annual_turnover": "1,000,000 kr",
                "annual_production_value": "N/A"
            },
            "foundation_year": 1919,
            "owners": [
                "fabr. David Karlsson"
            ]
        },
        "2": {
            "name": "AB. Kolbäcks Träindustrier",
            "location": "Kolbäck",
            "business": "byggnadssnickerier samt sågade och hyvlade trävaror",
            "contact": {
                "office": "Kolbäck",
                "phone": [
                    "116",
                    "117"
                ],
                "postgiro": "266500"
            },
            "financials": {
                "capital": "41,000 kr",
                "employees": {
                    "industriarb": 25
                },
                "annual_turnover": "400,000 kr",
                "annual_production_value": "N/A"
            },
            "foundation_year": 1926,
            "board": [
                {
                    "name": "banmäst. Oskar W. Andersson",
                    "role": "ordf."
                },
                {
                    "name": "folkskollärare Knut Björklund",
                    "role": "N/A"
                },
                {
                    "name": "lantbr. Nils Laggberg",
                    "role": "N/A"
                },
                {
                    "name": "disp. Gottfrid Larsson",
                    "role": "N/A"
                },
                {
                    "name": "lantbr. Petrus Peterson",
                    "role": "N/A"
                }
            ],
            "director": "Gottfrid Larsson"
        },
        "3": {
            "name": "AB. Kolimporten—Laurents",
            "location": "Sundsvall",
            "business": "Sågverk och hyvleri",
            "contact": {
                "office": "Sundsvall",
                "phone": [
                    "Kolimporten—Laurents"
                ],
                "postgiro": "28190"
            },
            "financials": {
                "capital": "300,000 kr",
                "employees": {
                    "industriarb": 125
                },
                "annual_turnover": "1,500 stds trävaror, 5 milj. murtegel",
                "annual_production_value": "N/A"
            },
            "foundation_year": 1897,
            "board": [
                {
                    "name": "dir. Kjell Beijer",
                    "role": "N/A"
                },
                {
                    "name": "dir. B. Hjerpstedt",
                    "role": "N/A"
                },
                {
                    "name": "dir. H. Lönnegårdh",
                    "role": "N/A"
                }
            ],
            "director": "B. Hjerpstedt"
        },
        "4": {
            "name": "AB. Kollin &amp; Ström",
            "location": "Borlänge",
            "business": "Mek. verkstad och grovplåtslageri",
            "products": "Tillverkar perforerad plåt och värmeradiatorer samt utför grovplåtsarbeten och järnkonstruktioner",
            "contact": {
                "office": "Borlänge",
                "phone": [
                    "10117",
                    "11017"
                ],
                "postgiro": "28717"
            },
            "financials": {
                "capital": "300,000 kr",
                "employees": {
                    "industriarb": 65
                },
                "annual_turnover": "800,000 kr",
                "annual_production_value": "N/A"
            },
            "foundation_year": 1900,
            "board": [
                {
                    "name": "generalkonsul Torsten O. Söderberg",
                    "role": "ordf."
                },
                {
                    "name": "dir. Joel Björklund",
                    "role": "N/A"
                },
                {
                    "name": "konsul H. Bursie",
                    "role": "N/A"
                }
            ],
            "director": "Joel Björklund"
        },
        "5": {
            "name": "Kommanditbolaget Betong, Sander &amp; Co.",
            "location": "Hednoret",
            "business": "Cementvarufabriker",
            "products": "Tillverkar betongrör till avloppsledningar och väg-trummor, stolpar, husbyggnadsblock m. m.",
            "contact": {
                "office": "Hednoret",
                "phone": [
                    "Boden 65016",
                    "65060"
                ],
                "postgiro": "61211"
            },
            "financials": {
                "capital": "38,600 kr",
                "employees": {
                    "industriarb": 62
                },
                "annual_turnover": "850,000 kr",
                "annual_production_value": "N/A"
            },
            "foundation_year": 1926,
            "director": "vägmäst. Oskar Sander (Brännland)"
        },
        "6": {
            "name": "Kommanditbolaget Bröderna Wallins Nysilverfabrik",
            "location": "Lidköping",
            "business": "Tillverkar kuvertartiklar av nysilver och rostfritt stål",
            "contact": {
                "phone": "20783",
                "postgiro": "70752"
            },
            "financials": {
                "employees": {
                    "industriarb": 80
                },
                "annual_turnover": "1,500,000 kr",
                "annual_production_value": "N/A"
            },
            "foundation_year": 1930,
            "board": [
                {
                    "name": "fabr. Einar Wallin",
                    "role": "ordf."
                },
                {
                    "name": "försäljn.-chef Nils H. Lind",
                    "role": "N/A"
                },
                {
                    "name": "kamrer K. G. Tunblad",
                    "role": "N/A"
                },
                {
                    "name": "fabr. Folke Wallin",
                    "role": "N/A"
                }
            ],
            "director": "Einar Wallin"
        },
        "7": {
            "name": "Kommanditbolaget Ellkå, Furstenberg &amp; Söner",
            "location": "Kalmar",
            "business": "Syfabrik",
            "products": "Tillverkar arbets- och sportkläder samt skjortor",
            "contact": {
                "phone": "1650",
                "postgiro": "263533",
                "repr. i Stockholm": "Ivar Tardell, Drottningg^ 23, telefon: 104190"
            },
            "financials": {
                "employees": {
                    "industriarb": 45
                },
                "foundation_year": 1927
            },
            "director": "dir. Sigismund Fiirstenberg"
        }
    }
}