{
    "original": "Strömsholmen—Stählbom\n\nStrömsholmens Mek. Verkstad,\n\nTranås.\n\nTillverkar friktionskopplingar och\nfrik-tionsremskivor, variatorer,\ntackjärnsgjut-gods, maskiner för pälsskinnsindnstrin\nm. m. samt utför beställningsarbeten och\nmaskinreparationer.\n\nTelefon: 4363. Postgiro: 89821. —\nAntal industriarb.: 25. Tillv.-värde pr år:\n330,000 kr. — Firman etabl. 1876.\n\nÄgare o. chefer: ing. Stig M. Carlsson\no. järnhandl. Bo Carlsson.\n\n\"Strömsnäs Bruks AB., Ströms-\n\nnäsbruJc.\n\nPappersbruk och sulfitfabrik vid\nStrömsnäsbruk, sulfatfabrik vid Delary\n(båda i Kronob. l.).\n\nTillverkar kraftpapper, säckpapper,\nkabelpapper, sulfitpapper för påsar,\nsmörpapper, klistrad papp, impregnerat\npapper, kräppat papper, pappersgarn,\npapperssäckar, papplådor för ytteremballage\nsamt sulfat- och sulfitcellulosa. Bolaget\nidkar jämväl skogshantering.\n\nTelegr.-adr.: Papermill, Hässleholm.\nTelefon: Strömsnäsbruk 7, 14, 18, 21 o.\n25. Postgiro: 23535.\n\nAkt.-kap.: 5,600,000 kr. Antal\nindustriarb.: 750. Årstillv.: 14,000 ton\nsulfatcellulosa, 9,000 ton sulfitcellulosa, 22,000 ton\npapper och papp. — Bolaget grundat\n1896.\n\nStyrelse: f. d. landshövd. Johan\nNilsson (ordf.), bankir Tage Cervin, dir.\nCarl Joh. Malmros, dir. Malte Ström, dir.\nErnst Wehtje.\n\nVerkst. dir. o. disp.: Sture André.\n\nFörsäljn.-chef: Fr. Skarborg.\n\nKontorschef: H. Svensén.\n\nDriftsingenjörer: pappersbruket o.\nsulfitfabriken: Y. Hjelte o. C. U. Willers;\nsulfatfabriken: C. G. v. Essen; verkstad\no. ångcentral: E. Christiansson.\n\n\"Strömsnäs Järnverks AB.,\n\nDegerfors.\n\nSe Degerfors Järnverks AB., Degerfors.\n\n\"Strömstads Bryggeri, Strömstad.\n\nSe AB. Pripp &amp; Lyckholm, Göteborg.\n\nStrömstad Canning Co. AB.,\n\nStrömstad.\n\nKonservfabrik. Tillverkar fiskkonserver\nsåsom sardiner, herrings, inlagd makrill\nm. m. Varumärken: »Kung Gustaf»,\n»Gloria» o. »West Coast».\n\nTelegr.-adr.: Canning, Strömstad.\nTelefon: »Strömstad Canning». Postgiro:\n75650. Representanter: Johannsen &amp;\nSvensson, Stockholm, Torsg. 75, telefon:\n339800; Lybeck, Rönne &amp; Co. AB.,\nGöteborg, ö. Hamng. 16, telefon: 170845.\n\nAkt.-kap.: 220,000 kr. Antal\nindustriarb.: 150. Tillv.-värde pr år: 2,500,000 kr.\n— Firman etabl. 1930.\n\nStyrelse: rådman A. F. Forell (ordf.),\nhandl. H. Hanson Nsess, fru A. Åsland,\ndisp. Harald Åsland.\n\nDisp.: Harald Åsland.\n\n\"AB. Sture Konfektions Industri,\n\nSäffle.\n\nTillverkar herr- och gosskjortor samt\ndamblusar, kjolar och skyddsrockar vid\nfabrik i Säffle (Värml. l.).\n\nTelefon: 810. Postgiro: 144690. —\nAkt.-kap.: 32,000 kr. Tillv.-värde pr år:\n800,000 kr. — Bolaget grundat 1939.\n\nStyrelse o. chefer: dir. Carl Jansson\n(ordf.), kamrer C.-E. Lindell, fabrikschef\nKarl Norman.\n\nAB. Sthyr &amp; Söner, Grythyttan.\n\nMek. verkstad i Grythyttan (Örebro l.).\nTillverkar järnkonstruktioner och\ngrov-plåtsarbeten samt installerar värme- och\nsanitetsanläggningar.\n\nTelefon: 67 o. 88. Postgiro: 13141. —\nAkt.-kap.: 75,000 kr. Antal industriarb.:\n20. Tillv.-värde pr år: 300,000 kr. —\nFirman etabl. 1921, bolag 1944.\n\nVerkst. dir.: fabr. Hjalmar Sthyr.\n\n\"Styrenius Stenhuggeri AB.,\n\nVästervik.\n\nSe Bröderna Styrenius Stenhuggeri\nAB., Västervik.\n\nAxel Ståhls Möbelfabriks AB.,\n\nVimmerby.\n\nTillverkar sängkammarmöbler och\nstyckesaker vid fabrik i Vimmerby\n(Kalmar l.).\n\nTelefon: 119. Postgiro: 25781. —\nAkt.-kap.: 51,700 kr. Antal industriarb.: 30.\nTillv.-värde pr år: 380,000 kr. — Firman\netabl. 1902, bolag 1932.\n\nVerkst. dir.: Axel Ståhl.\n\nDisp.: Nils Ståhl.\n\n\"Ståhlbom &amp; Co. Kvarn AB.,\n\nNorrköping.\n\nKvarn och kraftfoderfabrik i\nNorrköping. Tillverkar vete- och rågmjöl, korn-",
    "structured": {
        "1": {
            "name": "Strömsholmen—Stählbom",
            "location": "Tranås",
            "business": "Tillverkar friktionskopplingar och friktionsremskivor, variatorer, tackjärnsgjut-gods, maskiner för pälsskinnsindnstrin m.m. samt utför beställningsarbeten och maskinreparationer.",
            "contact": {
                "phone": [
                    "4363"
                ],
                "postgiro": "89821"
            },
            "financials": {
                "employees": {
                    "industriarb": 25
                },
                "annual_turnover": "330,000 kr",
                "annual_production_value": "330,000 kr",
                "capital": "N/A"
            },
            "foundation_year": 1876,
            "owners": [
                "ing. Stig M. Carlsson",
                "järnhandl. Bo Carlsson"
            ]
        },
        "2": {
            "name": "Strömsnäs Bruks AB.",
            "location": "Strömsnäsbruk",
            "business": "Pappersbruk och sulfitfabrik.",
            "products": "Tillverkar kraftpapper, säckpapper, kabelpapper, sulfitpapper för påsar, smörpapper, klistrad papp, impregnerat papper, kräppat papper, pappersgarn, papperssäckar, papplådor för ytteremballage samt sulfat- och sulfitcellulosa. Idkar jämväl skogshantering.",
            "contact": {
                "telegraph": "Papermill, Hässleholm",
                "phone": [
                    "Strömsnäsbruk 7",
                    "Strömsnäsbruk 14",
                    "Strömsnäsbruk 18",
                    "Strömsnäsbruk 21",
                    "Strömsnäsbruk 25"
                ],
                "postgiro": "23535"
            },
            "financials": {
                "capital": "5,600,000 kr",
                "employees": {
                    "industriarb": 750
                },
                "annual_turnover": "N/A",
                "annual_production_value": "14,000 ton sulfatcellulosa, 9,000 ton sulfitcellulosa, 22,000 ton papper och papp"
            },
            "foundation_year": 1896,
            "board": [
                {
                    "name": "f. d. landshövd. Johan Nilsson",
                    "role": "ordf."
                },
                {
                    "name": "bankir Tage Cervin",
                    "role": "dir."
                },
                {
                    "name": "dir. Carl Joh. Malmros",
                    "role": "dir."
                },
                {
                    "name": "dir. Malte Ström",
                    "role": "dir."
                },
                {
                    "name": "dir. Ernst Wehtje",
                    "role": "dir."
                }
            ],
            "director": "Sture André",
            "sales_manager": "Fr. Skarborg",
            "manager": "N/A"
        },
        "3": {
            "name": "Strömstad Canning Co. AB.",
            "location": "Strömstad",
            "business": "Konservfabrik",
            "products": "Tillverkar fiskkonserver såsom sardiner, herrings, inlagd makrill m.m. Varumärken: »Kung Gustaf», »Gloria» o. »West Coast»",
            "contact": {
                "telegraph": "Canning, Strömstad",
                "phone": [
                    "Strömstad Canning"
                ],
                "postgiro": "75650"
            },
            "financials": {
                "capital": "220,000 kr",
                "employees": {
                    "industriarb": 150
                },
                "annual_turnover": "2,500,000 kr",
                "annual_production_value": "2,500,000 kr"
            },
            "foundation_year": 1930,
            "board": [
                {
                    "name": "rådman A. F. Forell",
                    "role": "ordf."
                },
                {
                    "name": "handl. H. Hanson Nsess",
                    "role": "N/A"
                },
                {
                    "name": "fru A. Åsland",
                    "role": "N/A"
                },
                {
                    "name": "disp. Harald Åsland",
                    "role": "N/A"
                }
            ],
            "director": "Harald Åsland",
            "manager": "N/A"
        },
        "4": {
            "name": "AB. Sture Konfektions Industri",
            "location": "Säffle",
            "business": "Tillverkar herr- och gosskjortor samt damblusar, kjolar och skyddsrockar vid fabrik",
            "contact": {
                "phone": [
                    "810"
                ],
                "postgiro": "144690"
            },
            "financials": {
                "capital": "32,000 kr",
                "employees": {
                    "industriarb": "N/A"
                },
                "annual_turnover": "800,000 kr",
                "annual_production_value": "800,000 kr"
            },
            "foundation_year": 1939,
            "board": [
                {
                    "name": "dir. Carl Jansson",
                    "role": "ordf."
                },
                {
                    "name": "kamrer C.-E. Lindell",
                    "role": "N/A"
                },
                {
                    "name": "fabrikschef Karl Norman",
                    "role": "N/A"
                }
            ],
            "director": "N/A",
            "manager": "N/A"
        },
        "5": {
            "name": "AB. Sthyr & Söner",
            "location": "Grythyttan",
            "business": "Mek. verkstad",
            "products": "Tillverkar järnkonstruktioner och grov-plåtsarbeten samt installerar värme- och sanitetsanläggningar",
            "contact": {
                "phone": [
                    "67",
                    "88"
                ],
                "postgiro": "13141"
            },
            "financials": {
                "capital": "75,000 kr",
                "employees": {
                    "industriarb": 20
                },
                "annual_turnover": "300,000 kr",
                "annual_production_value": "300,000 kr"
            },
            "foundation_year": 1944,
            "director": "fabr. Hjalmar Sthyr",
            "manager": "N/A"
        },
        "6": {
            "original_name": "Bröderna Styrenius Stenhuggeri",
            "current_name_year": "N/A"
        },
        "7": {
            "name": "Axel Ståhls Möbelfabriks AB.",
            "location": "Vimmerby",
            "business": "Tillverkar sängkammarmöbler och styckesaker vid fabrik",
            "contact": {
                "phone": [
                    "119"
                ],
                "postgiro": "25781"
            },
            "financials": {
                "capital": "51,700 kr",
                "employees": {
                    "industriarb": 30
                },
                "annual_turnover": "380,000 kr",
                "annual_production_value": "380,000 kr"
            },
            "foundation_year": 1932,
            "director": "Axel Ståhl",
            "manager": "N/A"
        },
        "8": {
            "name": "Ståhlbom & Co. Kvarn AB.",
            "location": "Norrköping",
            "business": "Kvarn och kraftfoderfabrik",
            "products": "Tillverkar vete- och rågmjöl, korn-",
            "contact": {
                "postgiro": "N/A"
            },
            "financials": {
                "capital": "N/A",
                "employees": {
                    "industriarb": "N/A"
                },
                "annual_turnover": "N/A",
                "annual_production_value": "N/A"
            },
            "foundation_year": "N/A",
            "board": [
                {
                    "name": "N/A",
                    "role": "N/A"
                }
            ],
            "director": "N/A",
            "manager": "N/A"
        }
    }
}