{
    "original": "L jugarn—Ljungbergh\n\nspårvagnar, automobiler och bussar, för\nfartyg och flygmaskiner, kylskåpsbeslag\nm. m. samt utför förkromning och\nför-nickling. Varumärke: »Ljuders».\n\nTelegr.-adr.: Ljuders, Hovmantorp.\nTelefon: 6. Postgiro: 179566.\n\nAkt.-kap.: 60,000 kr. Antal\nindustriarb.: 40. — Firman etabl. 1876, bolag\n1941.\n\nDriftsing.: Allan Svensson.\n\nKamrer: Göte Johansson.\n\n*Ljugarns Snickerifabrik, Bergman\n&amp; Co., Ljugam.\n\nTillverkar byggnadssnickerier, trappor,\nköksinredningar samt furumöbler vid\nfabrik i Ljugarn (Gotl. l.).\n\nTelefon: 24. Postgiro: 34221. —\nArb.-antal: 10. Tillv.-värde pr år: 80,000 kr.\n\n—\tFirman etabl. 1925.\n\nDelägare: verkmäst. Fritz Bergman o.\nverkmäst. Ivar Bergman.\n\n\"Ljungs Choklad- &amp; Cacao-Fabrik,\nAB., Malmö.\n\nTillverkar choklad, cacao, cacaosmör,\nkonfektyrer och karameller.\n\nKontor: Celsiusg. 41. Telegr.-adr.:\nLjungen, Malmö. Telefon: »Ljungs\nIndustrier» o. 73030. Postgiro: ^ 38539.\nRepresentanter: i Stockholm: Ljungs\nChokladfabriks Nederlag, Gästrikeg. 17,\ntelefon: 314148; Göteborg: Ljungs\nChokladfabriks Nederlag, St. Nygatan 15, telefon:\n119374.\n\nAkt.-kap.: 350,000 kr. Antal\nindustriarb.: 135. — Firman etabl. 1916, bolag\n1935.\n\nStyrelse: fabr. A. Efraim Ljung (ordf.),\nadv. G. Delvert, dir.-assist. Henry Ljung.\nVerkst. dir.: A. E. Ljung.\nDir.-assistent: Henry Ljung.\nDisp.: Ernst Pettersson.\n\n*AB. Ljungs Tegelbruk,\n\nLinköping.\n\nTillverkar mur- och taktegel,\nbeklädnadstegel, högporösa mellanväggsplattor\nsamt dräneringsrör vid tegelbruk i\nLjungsbro (Östergötl. l.).\n\nKontor o. ensamförsälj.: AB. Förenade\nTegelbruken, Linköping. Telefon: 20201.\nPostgiro: 97587.\n\nAkt.-kap.: 137,000 kr. Antal\nindustriarb.: 30. Årstillv.: 2,5 milj. st. tegelvaror.\n\n—\tBolaget, grundat 1910, äges av AB.\nFörenade Tegelbruken.\n\nStyrelse: f. stadsläkare Carl Schoug\n(ordf.), ing. Harald Giöbel, grossh.\nJacob Henricson, länsjägm. Einar Magni,\ndisp. Nils Mårtensson, fil. dr Stellan\n\nVennersten.\n\nVerkst. dir.: Nils Mårtensson.\n\nLjungaskogs AB., Mölndal.\n\nTräsliperi i Svenljunga (Älvsb. l.).\nTillverkar mek. trämassa.\n\nKontor: Mölndal. Telegr.-adr. o.\ntelefon: Papyrus, Göteborg.\n\nAkt.-kap.: 150,000 kr. Arb.-antal: 10.\nTillverkningskapacitet: 14,000 ton våt,\nvit trämassa för Papyrus pappersbruk. —\nBolaget, grundat 1910, äges av AB.\nPapyrus, Mölndal.\n\nStyrelse: disp. Hans Hulthén (ordf.)*\nkamrer Einar Harald, ing. William\nTibell.\n\nVerkst. dir.: Hans Hulthén.\n\n\"Ljunga Verk, Ljungaverk.\n\nSe Stockholms Superfosfat Fabriks\nAB., Stockholm.\n\nAB. J. C. Ljungbergs Metallfabrik,\n\nJ önköping.\n\nTillverkar möbel-, byggnads- och\nbåtbeslag.\n\nTelefon: 908. Postgiro: 23119. —\nAkt.-kap.: 102,000 kr. Antal industriarb.: 36v\nTillv.-värde pr år: 300,000 kr. — Firman\netabl. 1889, bolag 1917.\n\nVerkst. dir.: Carl-Axel Gawelli.\nDriftsingenjör: Ebbe Granath.\n\n\"AB. N. H. Ljungbergs Läderfabrik,\n\nBorås.\n\nTillverkar bottenläder. Varumärke:\n»Wiskania». Firman driver även\nengros-handel med skodon och galoscher samt\ndetaljhandel med läder och\nskoinakeri-artiklar.\n\nTelegr.-adr.: Ljungbergia, Borås.\nTelefon: 17650. Postgiro: 33786. — Akt.-kap.:\n777,000 kr. Antal industriarb.: 65. —\nBolaget grundat 1916.\n\nStyrelse: fru E. Ljungberg, med. lic. G.\nWihman, disp. Tore Wihman.\nDisp.: Tore Wihman.\n\n\"Ljungberghs Åkdonsfabrik,\n\nJ önköping.\n\nSe Industri- &amp; Handels AB. Oscar\nLjungbergh, Jönköping.\n\n339*",
    "structured": {
        "1": {
            "name": "Ljugarns Snickerifabrik, Bergman & Co.",
            "location": "Ljugarn, Gotl. l.",
            "business": "Tillverkar byggnadssnickerier, trappor, köksinredningar samt furumöbler",
            "contact": {
                "phone": "24",
                "postgiro": "34221"
            },
            "financials": {
                "employees": {
                    "arb.-antal": 10
                },
                "annual_production_value": "80,000 kr"
            },
            "foundation_year": 1925
        },
        "2": {
            "name": "Ljungs Choklad- & Cacao-Fabrik, AB.",
            "location": "Malmö",
            "business": "Tillverkar choklad, cacao, cacaosmör, konfektyrer och karameller",
            "contact": {
                "office": "Celsiusg. 41",
                "phone": "»Ljungs Industrier» o. 73030",
                "postgiro": "38539"
            },
            "financials": {
                "capital": "350,000 kr",
                "employees": {
                    "antal industriarb.": 135
                }
            },
            "foundation_year": 1916,
            "corporation_year": 1935,
            "board": [
                {
                    "name": "fabr. A. Efraim Ljung",
                    "role": "ordf."
                },
                {
                    "name": "adv. G. Delvert",
                    "role": ""
                },
                {
                    "name": "dir.-assist. Henry Ljung",
                    "role": ""
                }
            ],
            "director": "A. E. Ljung",
            "managing_director": "A. E. Ljung",
            "sales_manager": "Henry Ljung"
        },
        "3": {
            "name": "AB. Ljungs Tegelbruk",
            "location": "Linköping",
            "business": "Tillverkar mur- och taktegel, beklädnadstegel, högporösa mellanväggsplattor samt dräneringsrör",
            "contact": {
                "office": "AB. Förenade Tegelbruken, Linköping",
                "phone": "20201",
                "postgiro": "97587"
            },
            "financials": {
                "capital": "137,000 kr",
                "employees": {
                    "antal industriarb.": 30
                },
                "annual_turnover": "2,5 milj. st. tegelvaror"
            },
            "foundation_year": 1910
        },
        "4": {
            "name": "Ljungaskogs AB.",
            "location": "Mölndal",
            "business": "Träsliperi i Svenljunga (Älvsb. l.). Tillverkar mek. trämassa",
            "contact": {
                "office": "Mölndal",
                "phone": "Papyrus, Göteborg"
            },
            "financials": {
                "capital": "150,000 kr",
                "employees": {
                    "Arb.-antal": 10
                },
                "annual_production_value": "14,000 ton våt, vit trämassa för Papyrus pappersbruk"
            },
            "foundation_year": 1910
        },
        "5": {
            "name": "AB. J. C. Ljungbergs Metallfabrik",
            "location": "Jönköping",
            "business": "Tillverkar möbel-, byggnads- och båtbeslag",
            "contact": {
                "phone": "908",
                "postgiro": "23119"
            },
            "financials": {
                "capital": "102,000 kr",
                "employees": {
                    "antal industriarb.": 36
                },
                "annual_production_value": "300,000 kr"
            },
            "foundation_year": 1889,
            "corporation_year": 1917
        },
        "6": {
            "name": "AB. N. H. Ljungbergs Läderfabrik",
            "location": "Borås",
            "business": "Tillverkar bottenläder",
            "contact": {
                "phone": "17650",
                "postgiro": "33786"
            },
            "financials": {
                "capital": "777,000 kr",
                "employees": {
                    "antal industriarb.": 65
                }
            },
            "foundation_year": 1916,
            "board": [
                {
                    "name": "fru E. Ljungberg",
                    "role": ""
                },
                {
                    "name": "med. lic. G. Wihman",
                    "role": ""
                },
                {
                    "name": "disp. Tore Wihman",
                    "role": ""
                }
            ]
        }
    }
}