{
    "original": "Germa—GeveJco\n\n*AB. Germa, Sundbyberg.\n\nKonfektions- och trikåfabrik.\nTillverkar korsetter samt herr- och\ndamunderkläder. Varumärke: »Germa»,\n\nTelegr.-adr.: Germa, Sundbyberg.\nTelefon: Stockholm 282590. Postgiro: 1174.\n\nAkt.-kap.: 500,000 kr. Antal\nindustriarb.: 150. Tillv.-värde pr år: 1,700,000 kr.\n\n—\tFirman etabl. 1925.\n\nStyrelse: grossh. Artur Winberg (ordf.),\ndisp. Å. H. Bruhn, dir. Erik Winberg.\n\nVerkst. dir.: Erik Winberg.\n\nDir.-assist.: Bertil Winberg.\n\nFörsäljn.-chef: Å. H. Bruhn.\n\nKamrer: Torsten Espling.\n\n*J. C. E. Cernandt, Stockholm.\n\nTjär-, färg- och fernissfabrik.\nTillverkar asfalt- och tjärprodukter,\nträkonserveringsmedel, cellulosalaeker oeh färger\nför automobil-, möbel- och\nläderindustrien, syntetiska emaljer, synt.\nemulsionsfärger, ugnstorkande läcker,\nisole-ringslacker samt kallim och golvpolish.\nVarumärken: »Anora», »Dominit»,\n»Ge-ralin», »Geralyx», »Geranit», »Geranol»,\no. »Reginol».\n\nKontor: Västberga; postadr.:\nStockholm 32. Telegr.-adr.: Gernandter,.\nStockholm. Telefon: 452590. Postgiro: 2755.\n\n—\tAntal industriarb.: 25. — Firman\ngrundad år 1876.\n\nÄgare o. chef: fabr. Ernest Gernandt.\n\nFörsäljn.-chef : disp. Stig Gernandt.\n\nCestrikland, se Gästrikland.\n\nGethällens Såg, Falun.\n\nSe Falu Tegelverks AB., Falun.\n\n’Getinge Mek. Verkstads AB.,\n\nGetinge.\n\nMek. verkstad och gjuteri i Getinge\n(Hallands l.). Tillverkar kokapparater\nför storkök och industri,\nsteriliserings-och desinfektionsapparater,\npotatisskal-ningsmaskiner, elektr. stekbord, elektr.\nvärme- och lågtrycksångpannor,\nvindmotorer, invallningspumpverk, hö- och\nsä-deshissar, transportbanor samt\ntackjärns-gjutgods upp till 1,500 kg.\n\nTelegr.-adr. o. telefon:\n»Getingever-ken», Getinge. Postgiro: 22622.\nUtställning: Stockholm, Birger Jarlsg. 6.\n\nAkt.-kap.: 60,000 kr. Antal\nindustriarb.: 110. Tillv.-värde pr år: 2,000,000 kr.\n— Firman etabl. 1888, bolag 1904,\nom-bildat 1932.\n\nStyrelse: trävaruhandl. Gösta\nEwer-hard (ordf.), disp. Carl Steen, fru Ellen\nSteen.\n\nDisp.: Carl Steen.\n\nKontorschef: Bror Börjesson.\n\nFörsäljn.-chef: Lars Ekman.\n\nVerkstadschef: Sven Hultman.\n\n’Getinge Sågverk, Einar Nilsson,\n\nGetinge.\n\nTillverkar plank, spåntade och hyvlade\nträvaror, blockvaror i ek, alm, ask och\nbok, tegelbrukslattor samt råparkett i ek\noch bok vid sågverk med hyvleri i\nGetinge (Hallands l.).\n\nTelefon: 91. Postgiro: 168891. —\nAntal industriarb.: 20. Tillv.-värde pr år:\n500?000 kr. — Firman etabl. 1940.\n\nÄgare o. chef: fabr. Einar G. Nilsson.\n\nFörsäljn.-chef: Sten Nilsson.\n\n’Getinge Tegelbruk, Getinge.\n\nTillverkar murtegel och dräneringsrör\nvid tegelbruk i Getinge (Hallands l.).\n\nKontor: Getinge. Telegr.-adr. o.\ntelefon: Frökontoret, Getinge. Postgiro:\n23000. — Antal industriarb.: 50.\nÅrstillv.: 2 milj. st. tegelvaror.\n\nTegelbruket äges av AB. Hallands\nFrö-kontor, som driver såsom huvudrörelse\nodling, förädling och försäljning av fröer\noch utsädesspannmål.\n\nChef: dir. Sture Niléhn.\n\nTegelmåst.: Tage Haaker.\n\nGevalia, Svenska Skolmateriel AB.,\n\nGävle.\n\nSe Svenska Skolmateriel AB. Gevalia,\nGävle.\n\n*AB. Geveko, Göteborg.\n\nHoldingbolag för fabriksbolagen AB.\nBitumuls och AB. Essäs med fabriker i\nGöteborg och Karlstad samt för\nförsäljningsbolagen AB. Gatu- och\nVägbelägg-ningsämnen och AB. Gatu- och\nByggnadssten, samtliga i Göteborg. Vid\nfabriksbolagen tillverkas asfaltprodukter\nför beläggnings- och isoleringsändamål.\n\nKontor: Göteborg, Magasinsg. 3.\nTelegr.-adr.: Geveko, Göteborg. Telefon:\n172950. Postgiro: 40163.\n\nAkt.-kap.: 1,000,000 kr. — Bolaget,\ngrundat 1926, äger AB. Grafit och AB.\nBergendahl och Höckert, båda i Göteborg\n(se dessa bolag).\n\nStyrelse: kapten Emil Clemedtson\n(ordf.), civiling. Gunnar Bergendahl,\nciviling. Gunnar Höckert.\n\nVerkst. dir.: Gunnar Bergendahl.\n\nKamrer: Gunnar Mattsson.",
    "structured": {
        "firms": [
            {
                "name": "AB. Germa",
                "location": "Sundbyberg",
                "business": "Konfektions- och trikåfabrik",
                "products": "Tillverkar korsetter samt herr- och damunderkläder. Varumärke: »Germa»",
                "contact": {
                    "office": "Sundbyberg",
                    "phone": [
                        "Stockholm 282590"
                    ],
                    "postgiro": "1174",
                    "telegraph": "Germa, Sundbyberg"
                },
                "financials": {
                    "capital": "500,000 kr",
                    "employees": {
                        "industriarb": 150
                    },
                    "annual_turnover": "1,700,000 kr"
                },
                "foundation_year": 1925,
                "board": [
                    {
                        "name": "grossh. Artur Winberg",
                        "role": "ordf."
                    },
                    {
                        "name": "disp. Å. H. Bruhn",
                        "role": "disp."
                    },
                    {
                        "name": "dir. Erik Winberg",
                        "role": "dir."
                    },
                    {
                        "name": "Erik Winberg",
                        "role": "Verkst. dir."
                    },
                    {
                        "name": "Bertil Winberg",
                        "role": "Dir.-assist."
                    },
                    {
                        "name": "Torsten Espling",
                        "role": "Kamrer"
                    }
                ]
            },
            {
                "name": "J. C. E. Cernandt",
                "location": "Stockholm",
                "business": "Tjär-, färg- och fernissfabrik",
                "products": "Tillverkar diverse kemiska produkter för olika industrier.",
                "contact": {
                    "office": "Västberga",
                    "phone": [
                        "Stockholm 452590"
                    ],
                    "postgiro": "2755",
                    "telegraph": "Gernandter, Stockholm"
                },
                "financials": {
                    "employees": {
                        "industriarb": 25
                    }
                },
                "foundation_year": 1876,
                "owners": [
                    "fabr. Ernest Gernandt"
                ],
                "board": [
                    {
                        "name": "fabr. Ernest Gernandt",
                        "role": "Ägare o. chef"
                    },
                    {
                        "name": "disp. Stig Gernandt",
                        "role": "Försäljn.-chef"
                    }
                ]
            },
            {
                "name": "Getinge Mek. Verkstads AB.",
                "location": "Getinge",
                "business": "Mek. verkstad och gjuteri",
                "products": "Tillverkar diverse tekniska produkter för olika användningsområden.",
                "contact": {
                    "office": "Getinge",
                    "phone": [
                        "Getinge"
                    ],
                    "postgiro": "22622",
                    "telegraph": "Getingeverken, Getinge"
                },
                "financials": {
                    "capital": "60,000 kr",
                    "employees": {
                        "industriarb": 110
                    },
                    "annual_turnover": "2,000,000 kr"
                },
                "foundation_year": 1888,
                "corporation_year": 1904,
                "board": [
                    {
                        "name": "trävaruhandl. Gösta Ewerhard",
                        "role": "ordf."
                    },
                    {
                        "name": "disp. Carl Steen, fru Ellen Steen",
                        "role": "Disp."
                    },
                    {
                        "name": "Carl Steen",
                        "role": "Disp."
                    },
                    {
                        "name": "Bror Börjesson",
                        "role": "Kontorschef"
                    },
                    {
                        "name": "Lars Ekman",
                        "role": "Försäljn.-chef"
                    },
                    {
                        "name": "Sven Hultman",
                        "role": "Verkstadschef"
                    }
                ]
            },
            {
                "name": "Getinge Sågverk, Einar Nilsson",
                "location": "Getinge",
                "business": "Tillverkning av trävaror",
                "products": "Tillverkar plank, spåntade och hyvlade trävaror, blockvaror i ek, alm, ask och bok, tegelbrukslattor samt råparkett i ek och bok vid sågverk med hyvleri",
                "contact": {
                    "phone": [
                        "91"
                    ],
                    "postgiro": "168891"
                },
                "financials": {
                    "employees": {
                        "industriarb": 20
                    },
                    "annual_turnover": "500,000 kr"
                },
                "foundation_year": 1940,
                "owners": [
                    "fabr. Einar G. Nilsson"
                ],
                "board": [
                    {
                        "name": "fabr. Einar G. Nilsson",
                        "role": "Ägare o. chef"
                    },
                    {
                        "name": "Sten Nilsson",
                        "role": "Försäljn.-chef"
                    }
                ]
            },
            {
                "name": "Getinge Tegelbruk",
                "location": "Getinge",
                "business": "Tillverkning av murtegel och dräneringsrör",
                "products": "Tillverkar murtegel och dräneringsrör vid tegelbruk i Getinge",
                "contact": {
                    "office": "Getinge",
                    "phone": [
                        "Getinge"
                    ],
                    "postgiro": "23000"
                },
                "financials": {
                    "employees": {
                        "industriarb": 50
                    }
                }
            },
            {
                "name": "AB. Geveko",
                "location": "Göteborg",
                "business": "Holdingbolag för fabriksbolagen",
                "products": "Holdingbolag för fabriksbolagen AB. Bitumuls och AB. Essäs med fabriker i Göteborg och Karlstad samt för försäljningsbolagen AB. Gatu- och Vägbeläggningsämnen och AB. Gatu- och Byggnadssten, samtliga i Göteborg.",
                "contact": {
                    "office": "Göteborg, Magasinsg. 3",
                    "phone": [
                        "172950"
                    ],
                    "postgiro": "40163",
                    "telegraph": "Geveko, Göteborg"
                },
                "financials": {
                    "capital": "1,000,000 kr"
                },
                "corporation_year": 1926,
                "board": [
                    {
                        "name": "kapten Emil Clemedtson",
                        "role": "ordf."
                    },
                    {
                        "name": "civiling. Gunnar Bergendahl",
                        "role": "Verkst. dir."
                    },
                    {
                        "name": "Gunnar Mattsson",
                        "role": "Kamrer"
                    }
                ]
            }
        ]
    }
}