{
    "original": "Eken—Ekolsund\n\nCarlsg. 22, — Antal industriarb.: 15.\nTillv.-värde pr år: 250,000 kr. — Firman\netabl. 1939.\n\nÄgare o. chef: fabr. Sven Bertil Nelson.\n\nKontorschef: Hugo Jeppsson.\n\nAB. Ekens Fabriker, Tollarp.\n\nVadd-, täck- och madrassfabrik samt\nväveri i Tollarp (Kristianst. l.).\nTillverkar täcken, madrasser och kuddar samt\nmöbeltyger. Bolaget driver även\nengros-handel med gardiner, mattor och filtar.\n\nTelefon: 327 o. 328. Postgiro: 160003.\n\nAkt.-kap.: 85,400 kr. Antal\nindustriarb.: 30. Tillv.-värde pr år: 500,000 kr.\n— Firman etabl. 1938, bolag 1944,\növerflyttades 1945 från Karlshamn till\nTollarp.\n\nVerkst. dir.: Frans Sandberg.\n\n*AB. Ekensbergs Varv, Stockholm.\n\nSkeppsvarv och mek. verkstad med\nflyt-dockor och upphalningsslipar, plåtslageri,\nmaskinverkstad och snickeriverkstad.\n\nUtför fartygsbyggnader och\nreparationer, grovplåtsarbeten, cisterner,\nfackverkskonstruktioner och brobyggnader,\nsmiden, maskin-, rör- och träarbeten samt\nelektr. svetsade arbeten m. m.\n\nPostadr.: Stockholm 9. Telegr.-adr.:\nEkenvarv, Stockholm. Telefon: 452745.\nPostgiro: 151293.\n\nAkt.-kap.: 600,000 kr. Antal\nindustriarb.: 370. — Varvet anlagt 1870, nuv.\nbolag grundat 1925.\n\nStyrelse: skeppsred. Sven Salén\n(ordf.), bankdir. Herrman Nachmanson,\ndir. Helge G. Norlander, maskininsp.\nKarl Ohlsson, civiling. Åke Tygård.\n\nVerkst. dir.: Åke Tygård.\n\nKamrer: Hans Arfwedson.\n\nVarvsing.: Halvor Åkeson.\n\n* (fikenäs Bruks AB., Ekenässjön.\n\nGlasbruk vid Ekenäs (Jönköp. l.).\nTillverkar kristallglas, hushållsglas,\nprydnadsglas, konservglas, textade och\notextade ståndkärl, glas för kem.-tekn.\nindustri samt medicin- och laboratorieglas.\n\nTelegr -adr.: Glasbruket, Vetlanda.\nTelefon: Ekenässjön 18 o. 46. Postgiro:\n133300.\n\nAkt.-kap.: 62,400 kr. Antal\nindustriarb.: 145. — Bolaget grundat 1923.\n\nStyrelse o. verkst. dir.: disp. Sven\nWestberg.\n\n*Ekenäs Skid- &amp; Träindustri,\n\nEkenässjön.\n\nSe AB. Esti (Ekenäs Skid- &amp;\nTräindustri), Ekenässjön.\n\nAB. Joh. Ekhoims Skofabrik,\n\nUppsala.\n\nTillverkar arbets- och barnskodon.\n\nTelefon: 31348 o. 34437. Postgiro:\n32898. — Akt.-kap.: 400,000 kr. Antal\nindustriarb.: 50. Tillv.-värde pr år:\n700,000 kr. — Firman etabl. 1902, bolag\n1932.\n\nStyrelse: dir, Torsten Ekholm, fru V.\nEkholm, fru Anna Mattsson.\n\nVerkst. dir.: Torsten Ekholm.\n\nDisp.: Carl Linderoth.\n\nEklund &amp; Co., Gislaved.\n\nSe Bakelit-Eklund &amp; Co., Gislaved.\n\nEklund &amp; Co. Textil AB., Göteborg.\n\nUllspinneri i Bollebygd (Älvsb. l.).\nTillverkar kardgarner samt hemstickade\ntrikåvaror. Varumärke: »Bohusgarn».\nBolaget driver även handel med\nmanufakturvaror.\n\nKontor: Göteborg, Kungstorget 8.\nTelefon: 136411.\n\nAkt.-kap.: 85,000 kr. Tillv.-värde pr år\nför spinneriet: 115,000 kr. — Bolaget\ngrundat 1943 genom sammanslagning av\nEklund &amp; Co., etabl. 1907, och Hedängens\nUllspinneri, etabl. 1922.\n\nVerkst. dir.: fru Anna Lorentzon.\n\n*AB. Helmer Ekman Kartongindustri,\n\nJ önköping.\n\nKartongfabrik med tryckeri. Tillverkar\nkonfektionskartonger,\nindustriförpackningar i massupplagor, konditori- och\nbagerikartonger samt tårtpapper.\n\nTelegr.-adr.: Ekartong, Jönköping.\nTelefon: 4271—73. Postgiro: 36878.\n\nAkt.-kap.: 10,000 kr. Antal\nindustriarb.: 27. Tillv.-värde pr år: 500,000 kr.\n— Fabriken grundad 1927, flyttad från\nTrollhättan till Jönköping 1938, bolag\n1943.\t-\n\nStyrelse o. disponenter: Anders Billing\no. Lars Billing.\n\nEkmöbler, Nya AB., Virserum.\n\nSe Nya AB. Ekmöbler, Virserum.\n\n*Ekolsunds Tegelbruk &amp; Sågverk,\nOscar &amp; Axel Johansson,\n\nStockholm.\n\nTegelbruk, sågverk och hyvleri vid\nEkolsund (Uppsala l.). Tillverkar\nmur-och taktegel, klint- och reveteringstegel,\ndräneringsrör m. m. samt sågade och\nhyvlade trävaror.\n\ni*",
    "structured": {
        "1": {
            "name": "AB Ekens Fabriker",
            "location": "Tollarp",
            "business": "Vadd-, täck- och madrassfabrik samt väveri",
            "description": "Tillverkar täcken, madrasser och kuddar samt möbeltyger. Bolaget driver även engros-handel med gardiner, mattor och filtar.",
            "contact": {
                "office": "Carlsg. 22",
                "phone": [
                    "327",
                    "328"
                ],
                "postgiro": "160003"
            },
            "financials": {
                "capital": "85,400 kr",
                "employees": {
                    "industriarb": 30
                },
                "annual_turnover": "500,000 kr",
                "annual_production_value": "250,000 kr"
            },
            "foundation_year": 1939,
            "director": "fabr. Sven Bertil Nelson",
            "contact_person": "Hugo Jeppsson"
        },
        "2": {
            "name": "AB Ekensbergs Varv",
            "location": "Stockholm",
            "business": "Skeppsvarv och mek. verkstad",
            "description": "Utför fartygsbyggnader och reparationer, grovplåtsarbeten, cisterner, fackverkskonstruktioner och brobyggnader, smiden, maskin-, rör- och träarbeten samt elektr. svetsade arbeten m. m.",
            "contact": {
                "office": "Postadr.: Stockholm 9",
                "phone": "452745",
                "telegraph": "Ekenvarv, Stockholm",
                "postgiro": "151293"
            },
            "financials": {
                "capital": "600,000 kr",
                "employees": {
                    "industriarb": 370
                }
            },
            "foundation_year": 1870,
            "director": "Åke Tygård",
            "board": [
                {
                    "name": "Sven Salén",
                    "role": "skeppsred."
                },
                {
                    "name": "Herrman Nachmanson",
                    "role": "bankdir."
                },
                {
                    "name": "Helge G. Norlander",
                    "role": "dir."
                },
                {
                    "name": "Karl Ohlsson",
                    "role": "maskininsp."
                },
                {
                    "name": "Åke Tygård",
                    "role": "civiling."
                }
            ]
        },
        "3": {
            "name": "Ekenäs Glasbruk AB.",
            "location": "Ekenäs (Jönköp. l.)",
            "business": "Glasbruk",
            "description": "Tillverkar kristallglas, hushållsglas, prydnadsglas, konservglas, textade och otextade ståndkärl, glas för kem.-tekn. industri samt medicin- och laboratorieglas.",
            "contact": {
                "telegraph": "Glasbruket, Vetlanda",
                "phone": [
                    "Ekenässjön 18",
                    "46"
                ],
                "postgiro": "133300"
            },
            "financials": {
                "capital": "62,400 kr",
                "employees": {
                    "industriarb": 145
                }
            }
        },
        "4": {
            "name": "AB. Joh. Ekhoims Skofabrik",
            "location": "Uppsala",
            "business": "Tillverkar arbets- och barnskodon",
            "description": "",
            "contact": {
                "phone": [
                    "31348",
                    "34437"
                ],
                "postgiro": "32898"
            },
            "financials": {
                "capital": "400,000 kr",
                "employees": {
                    "industriarb": 50
                },
                "annual_turnover": "700,000 kr"
            }
        },
        "5": {
            "name": "Eklund & Co. Textil AB.",
            "location": "Göteborg",
            "business": "Ullspinneri",
            "description": "Tillverkar kardgarner samt hemstickade trikåvaror. Varumärke: »Bohusgarn». Bolaget driver även handel med manufakturvaror.",
            "contact": {
                "office": "Kungstorget 8",
                "phone": "136411"
            },
            "financials": {
                "capital": "85,000 kr"
            }
        },
        "6": {
            "name": "AB. Helmer Ekman Kartongindustri",
            "location": "Jönköping",
            "business": "Kartongfabrik med tryckeri",
            "description": "Tillverkar konfektionskartonger, industriförpackningar i massupplagor, konditori- och bagerikartonger samt tårtpapper.",
            "contact": {
                "telegraph": "Ekartong, Jönköping",
                "phone": "4271—73",
                "postgiro": "36878"
            },
            "financials": {
                "capital": "10,000 kr",
                "employees": {
                    "industriarb": 27
                },
                "annual_turnover": "500,000 kr"
            }
        },
        "7": {
            "name": "Ekolsunds Tegelbruk & Sågverk",
            "location": "Ekolsund (Uppsala l.)",
            "business": "Tegelbruk, sågverk och hyvleri",
            "description": "Tillverkar mur-och taktegel, klint- och reveteringstegel, dräneringsrör m.m. samt sågade och hyvlade trävaror."
        }
    }
}