{
    "original": "Ryd—-Rydén\n\nindustriarb^ 45.,i v- Firman etabl* 1925,\nbolag 1940.\n\nVerkst. dir.: Edvin Rydh.\n\nIng(.:•.. C. Malmcrantz.\n\nRyds Glasbruk, Wiking &amp;\nJohansson, Ryd.\n\nGlasbruk i Ryd (Kronob. L).\nTillverkar medicinglas och tekniskt glas samt\noslipat och slipat hushållsglas.\n\nTelefon: 77. Postgiro: 22517. — Antal\nindustriarb.: 44. Tillv.-värde pr år:\n400,000. kr.:— Glasbruket anlagt 1918,\nnuv. firma etabl. 1923.\n\nÄgare o. chefer: bruksäg. August\nWiking o. bruksäg. Rigot Johansson.\n\nKamrer: Er ii5 Kar låta: * ? ;\n\n*Rydahls Manufaktur AB., Rydal.\n\nBomullsspinneri i Seglora (Älv&amp;b. l.).\nTillverkar bomullsgarn. Specialitet:\nef-fektgarner.\n\nTelegr.-adr.: Rydahlsbolaget, Borås.\nTelefon: Kinna 4311. Postgiro: 37135.\n\nAkt.-kap.: 1,251,000 kr. Antal\nindustriarb.: 314. Tillv.-värde pr år: 5,600,000 kr.\n— Bolaget grundat 1853.\n\nStyrelse: dir. Clas Erikson (ordf.), ing.\nTorsten Ek, dir. John, O, Erikson* dir.\nEdvin Leffler.\n\nVerkst. dir.: Torsten Ek.\n\nKamrer: D. Bodin.\n\nAB. Ernst Hj. Rydahl,\nBromsband-fabrik, Karlstad.\n\nTillverkar bromsband, bromsbelägg,\nlamellbelägg och konbelägg. Varumärken:\n»Friktionid», »Rytex» o. »Skandibest».\n\nTelefon: 10620. Postgiro: 85353. •\n\nAkt.-kap.: 60,000 kr. Antal\nindustriarb.: 2&amp; Tillv.-värde pr år: 400,000 kr. —\nFirman etabl. 1914, bolag 1943.\n\nVerkst. dir.: fabr. Knut Rydahl.\n\n*Rydaholms Tråd &amp; Järnförädling,\n\nSmålands Rydaholm.\n\nTillverkar emballagetråd alla slag,\nspiktråd samt förkopprad och\nblankdragen järntråd vid tråddrageri ivSiMlands\nRydaholm (Jönköp. l.).\n\nTelefon: 70. — Arb.-antal: 7.\nTillv.-värde pr år:, 100,000 kr. — Firman etabl.\n1934.\t’ &lt; :\n\nÄgare: fabr. Axel Carlsson, fabr. Erik\nCarlsson o. fabr. John Lindbladh.\n\nChéé:: Axel Carlsson.\n\n*Sven Rydberg, Möbelfaåirik, 7 ^/v\n\nTillverkar matsals- oeh\nkompletterings-möbler vid fabrik i Tibro (Skarab. l.).\n\nTelefon: 280. Postgiro: 174967. —\n\nArb.-antal: 12. Tillv.-värde pr år: 175,000\nkr. — Firman etabl. 1935.\n\nÄgare o. chef: fabr. Sven Rydberg;\n\n*Rydboholms AB., Rydboholm.\n\nVäveri och* spinneri 4 Visk#f qrs, samt\nblekeri, färgeri, tryckeri och äppréturvérk\ni Rydboholm (båda i Älvsb. l.). Tillverkar\nblekta, färgade och tryckta bomulls- och\nkonstsilkevavnader samt bomullsr och\ncellullgarn.\t•\n\nTelegr.-adr.: Rydboholmsbolag,\nfRydboholm. Telefon: »Ry dboholmsholaget»,\nBorås. Postgiro: 7714.\n\nAkt.-kap.: 4,500,000 kr. Antal\nindustriarb.: 850. Tillv.-värde pr år; 15,000,000\nkr. — Firrnan etabl. 1,834, bolag 188%\n\nStyrelse: adv. Hugo Stenbéck (ordf-)»\ndir. Clas Erikson (v. ordf.), ing. Torsten\nEk. dir. Edvin Leffler, major T. Odqvist.\n\nVerkst. dir.: Clas Erikson.\n\nDir assist.: Arne Erikson.\n\nKamrer o. inköpschef: Gustaf. Bäck,\n\nFörsäljn.-chef er: Håkan Lidman o.\nBror Malmberg.\n\nRydefors Glasbruk, Rydefors.\n\nGlasbruk vid Rydefors (Kronob. L).\nTillverkar tekniskt glas, parfym- och\nmedicinglas. Firman driver även jordbruk\noch skogshantering samt distribuerar\nelektr. energi.\n\nTelefon: Hohultslätt 25. Postgiro:\n32200. — Antal industriarb.: 50.\nTillv.-värde pr år: 830,000 kr.\n\nÄgare: Meijer &amp; Co.\n\nDisp.: Emil Meijer.\n\nDriftsing.: Albin Meijer.\t’ ..;.\"’\n\n*AB. A. W. Rydén, Nybro.\n\nTräförädlingsfabrik i Nybro (EJalmar\n1.). Tillverkar likkistor och sarkofager,\nklädhängare m. m. Pirmaii driver jätiaväl\nengroshandel med begravningsartiklar,\nkompletteringsmöbler och träarmatur.\n\nTelefon: 58 o. 84. Postgiro: 30071.\n\nAkt.-kap.: 200,000 kr. Antal\nindustriarb.: 90. — Firman, etabl. 1904, bolag\n1919, äger Viby Fabriker, Viby.\n\nStyrelse: fabr. A. W. Rydén (ordf.),\ning. G. Rydén, disp. Sture Rydén. ; ;\n\nVerkst. dir.: A. W. Rydén.-\ti\n\nDisp.: Sture Rydén.\t\\",
    "structured": {
        "1": {
            "name": "Ryds Glasbruk, Wiking & Johansson",
            "location": "Ryd",
            "business": "Glasbruk",
            "products": "Tillverkar medicinglas och tekniskt glas samt oslipat och slipat hushållsglas",
            "contact": {
                "office": "Ej angiven",
                "phone": [
                    "77"
                ],
                "postgiro": "22517"
            },
            "financials": {
                "capital": "Ej angiven",
                "employees": {
                    "industriarb": 44
                },
                "annual_turnover": "400,000 kr",
                "annual_production_value": "Ej angiven"
            },
            "foundation_year": 1923,
            "owners": [
                "August Wiking",
                "Rigot Johansson"
            ],
            "director": "Ej angiven"
        },
        "2": {
            "name": "Rydahls Manufaktur AB",
            "location": "Rydal",
            "business": "Bomullsspinneri",
            "products": "Tillverkar bomullsgarn. Specialitet: effektgarner",
            "contact": {
                "office": "Ej angiven",
                "phone": [
                    "Kinna 4311"
                ],
                "postgiro": "37135"
            },
            "financials": {
                "capital": "1,251,000 kr",
                "employees": {
                    "industriarb": 314
                },
                "annual_turnover": "5,600,000 kr",
                "annual_production_value": "Ej angiven"
            },
            "foundation_year": 1853,
            "board": [
                {
                    "name": "Clas Erikson",
                    "role": "ordf."
                },
                {
                    "name": "Torsten Ek",
                    "role": "ing."
                },
                {
                    "name": "John, O, Erikson",
                    "role": "dir."
                },
                {
                    "name": "Edvin Leffler",
                    "role": "dir."
                }
            ],
            "owner": "Ej angiven",
            "manager": "Ej angiven"
        },
        "3": {
            "name": "AB. Ernst Hj. Rydahl",
            "location": "Karlstad",
            "business": "Bromsband-fabrik",
            "products": "Tillverkar bromsband, bromsbelägg, lamellbelägg och konbelägg",
            "contact": {
                "office": "Ej angiven",
                "phone": [
                    "10620"
                ],
                "postgiro": "85353"
            },
            "financials": {
                "capital": "60,000 kr",
                "employees": {
                    "industriarb": 28
                },
                "annual_turnover": "400,000 kr",
                "annual_production_value": "Ej angiven"
            },
            "foundation_year": 1914,
            "director": "fabr. Knut Rydahl"
        },
        "4": {
            "name": "Rydaholms Tråd & Järnförädling",
            "location": "Smålands Rydaholm",
            "business": "Tillverkar emballagetråd alla slag, spiktråd samt förkopprad och blankdragen järntråd",
            "contact": {
                "office": "Ej angiven",
                "phone": [
                    "70"
                ],
                "postgiro": "Ej angiven"
            },
            "financials": {
                "capital": "Ej angiven",
                "employees": {
                    "industriarb": 7
                },
                "annual_turnover": "Ej angiven",
                "annual_production_value": "100,000 kr"
            },
            "foundation_year": 1934,
            "owner": "fabr. Axel Carlsson, fabr. Erik Carlsson, fabr. John Lindbladh",
            "manager": "Axel Carlsson"
        },
        "5": {
            "name": "Sven Rydberg, Möbelfabrik",
            "location": "Tibro",
            "business": "Tillverkar matsals- och kompletteringsmöbler",
            "contact": {
                "office": "Ej angiven",
                "phone": [
                    "280"
                ],
                "postgiro": "174967"
            },
            "financials": {
                "capital": "Ej angiven",
                "employees": {
                    "industriarb": 12
                },
                "annual_turnover": "175,000 kr",
                "annual_production_value": "Ej angiven"
            },
            "foundation_year": 1935,
            "owner": "fabr. Sven Rydberg",
            "manager": "Ej angiven"
        },
        "6": {
            "name": "Rydboholms AB.",
            "location": "Rydboholm",
            "business": "Väveri och spinneri",
            "products": "Tillverkar blekta, färgade och tryckta bomulls- och konstsilkevavnader samt bomullsgarn",
            "contact": {
                "office": "Ej angiven",
                "phone": [
                    "Ej angiven"
                ],
                "postgiro": "7714"
            },
            "financials": {
                "capital": "4,500,000 kr",
                "employees": {
                    "industriarb": 850
                },
                "annual_turnover": "15,000,000 kr",
                "annual_production_value": "Ej angiven"
            },
            "foundation_year": 1834,
            "board": [
                {
                    "name": "Hugo Stenbéck",
                    "role": "ordf."
                },
                {
                    "name": "Clas Erikson",
                    "role": "v. ordf."
                },
                {
                    "name": "Torsten Ek",
                    "role": "ing."
                },
                {
                    "name": "Edvin Leffler",
                    "role": "dir."
                },
                {
                    "name": "T. Odqvist",
                    "role": "major"
                }
            ],
            "manager": "Ej angiven"
        },
        "7": {
            "name": "Rydefors Glasbruk",
            "location": "Rydefors",
            "business": "Glasbruk",
            "products": "Tillverkar tekniskt glas, parfym- och medicinglas",
            "contact": {
                "office": "Ej angiven",
                "phone": [
                    "Hohultslätt 25"
                ],
                "postgiro": "32200"
            },
            "financials": {
                "capital": "Ej angiven",
                "employees": {
                    "industriarb": 50
                },
                "annual_turnover": "830,000 kr",
                "annual_production_value": "Ej angiven"
            },
            "owner": "Meijer & Co",
            "director": "Emil Meijer"
        },
        "8": {
            "name": "AB. A. W. Rydén",
            "location": "Nybro",
            "business": "Träförädlingsfabrik",
            "products": "Tillverkar likkistor och sarkofager, klädhängare m.m",
            "contact": {
                "office": "Ej angiven",
                "phone": [
                    "58",
                    "84"
                ],
                "postgiro": "30071"
            },
            "financials": {
                "capital": "200,000 kr",
                "employees": {
                    "industriarb": 90
                },
                "annual_turnover": "Ej angiven",
                "annual_production_value": "Ej angiven"
            },
            "foundation_year": 1904,
            "manager": "A. W. Rydén"
        }
    }
}