{
    "original": "Svenska\n\nHuvudkontor: Bodafors. Telegr.-adr.:\nMöbelfabrikerna, Bodafors. Telefon:\n»Svenska Möbelfabrikerna». Postgiro:\n6463. Avd.-kontor: Stockholm, Vasag.\n52, telefon: 207130.\n\nAkt.-kap.: 400,000 kr. Antal\nindustriarb.: 390. Tillv.-värde pr år: 4,100,000 kr.\n\nBolaget grundat 1918.\n\nStyrelse: ing. Gust. ödqvist (ordf.),\ning. Einar Egnell, ing. S. Stridsberg, dir.\nVictor Strömberg.\n\nVerkst. dir.: Gunnar Lindeberg.\n\nKamrer: Edg. Sundberg.\n\n*Svenska Möbeltygs- &amp; Mattfabriks\nAB., Göteborg.\n\nSe Nya Svenska Möbeltygs- &amp;\nMattfabriks AB., Göteborg.\n\n*AB. Svenska Naxos, Västervik.\n\nSe AB. Slipmaterial—Naxos, Västervik.\n\n*Svenska Oljeslageri AB., Göteborg.\n\nTillverkar vegetabiliska oljor,\noljefernissor, ftalsyreanhydrid,\nmaleinsyrean-hydrid, lackkonsthartser,\nmjukgörings-medel, sickativer, textilhjälpmedel samt\nfoderkakor vid fabriker i Mölndal\n(Göteb. o. Bohus l.) och Henriksborg\n(Sthlms l.).\n\nHuvudkontor: Mölndal; postadr.:\nGöteborg 5. Telegr.-adr.: Delbanco,\nGöteborg. Telefon: 272000. Postgiro: 46490.\nAvd.-kontor: Henriksborg; postadr.:\nStockholm 2; telefon: 437071. Postgiro:\n190390.\n\nAkt.-kap.: 3.600,000 kr. Antal\nindustriarb.: 220. Tillv.-värde pr år: 20,000,000\nkr.\n\nFabriken i Mölndal anlagd 1826, i\nHenriksborg 1841, nuv. bolag grundat 1916.\n\nStyrelse: konsul Oscar Gullander\n(ordf.), dir. Ernst Persson (v. ordf.), dir.\nGunnar Engberg, dir. H. E. Helmerson,\ndir. Emanuel Högberg, konsul S. H.\nSörensen.\n\nVerkst. dir.: H. E. Helmerson.\n\nKontorschef: Ralph Fischer.\n\nDisp. i Henriksborg: Helge Peterson.\n\n*Svenska AB. Philips, Stockholm.\n\nFirman utgör ett försäljningsbolag för\ninom Philipskoncernen (bl. a. Norrköpings\nElektr otekniska Fabriker AB. (NE FA),\nNorrköping, och Dux Radio AB.,\nStockholm) tillverkade svenska elektrotekniska\nprodukter såsom radiomottagare,\nskiv-bytare, mottagar- och sändarrör,\nelektriska mätinstrument, röntgenanläggningar\nför industri och medicin, lampor av olika\n\n35*\n\nslag, armaturer, delar till\nbiografmaskiner, förstärkare, likriktare,\nsvetsaggre-gat och -elektroder samt vitamin och\nDDT-preparat m. m. Bolaget försäljer\njämväl utländska tillverkningar inom\nsamma branscher som de svenska\nprodukterna.\n\nHuvudkontor: Stockholm, Gävleg. 18.\nTelefon: »Philips lampor». Postgiro: 845.\nFilialkontor: Göteborg, Burggreveg. 15,\ntelefon: 192550; Malmö, Kontorscentrum\nD, telefon: 72290. Telegr.-adr.: Philamp,\nStockholm, Göteborg o. Malmö.\n\nAkt.-kap.: 1,500,000 kr. Antal\nanställda: 340. — Bolaget grundat 1919.\n\nStyrelse: envoyé Christian Gunther\n(ordf.), dir. Herbert Kastengren,\ngeneralmajor H. Kellgren, generaldir. Tarras\nSällfors, dir. Åke Wetterlind.\n\nVerkst. dir.: Herbert Kastengren.\n\nChefer för sekretariat o. kem. farm.\navd.: dir. Allan Enström; för finansiella\no. administrativa avd.: dir. Nicolas\nWo-ensdregt.\n\nFörsäljn.-chef er: för radioavd.: dir.\nAlfons Edelgardt; för belysningsavd.: dir.\nBertil Schröder.\n\nReklamchef: ing. S. F. Elmquist.\n\nAvd.-chefer: svetsavd.: G. A.\nJohannesson; mätinstrumentavd.: civiling. Rolf\nMilles; industriavd.: civiling. Stig\nSwe-rup; biografmaskiner, förstärkare o.\nrakapparater: disp. Sven Wadell;\nröntgen-avd.: civiling. Einar Wastenson;\nkame-ralavd.: kamrer Hjalmar Fornstedt.\n\n*AB. Svenska Pianofabriken,\n\nStockholm.\n\nTillverkar pianon vid fabrik i\nSundbyberg. Bolaget driver även handel med\npianon av främmande fabrikat.\n\nKontor: Stockholm, Vasag. 23—25.\nTelefon: 102882 o. 102885.\n\nAkt.-kap.: 120,000 kr. Antal\nindustriarb.: 15. — Bolaget grundat 1917,\n\nStyrelse: f. verkstadschef Valfrid\nLindh (ordf.), bankkamrer Karl David\nThalén, fru Linnea Thalén.\n\nVerkst. dir.: Karl David Thalén.\n\nDisp.: Adolf Schaller.\n\nAB. Svenska Precisionsverktyg,\n\nNacka.\n\nMek. verkstad i Nacka (Sthlms l.).\nTillverkar gängmaskiner och\ngängapparater samt mätinstrument för gängor och\nkugghjul.\n\nTelegr.-adr.: Espeve, Stockholm.\nTelefon: Stockholm 162860 o. 162172.\nPostgiro: 58952. Repr. AB. Servus,\nStockholm, Malmskillnadsg. 46, telefon: 232425.",
    "structured": {
        "1": {
            "name": "Svenska Möbelfabrikerna",
            "location": "Bodafors",
            "business": "Möbelfabrik",
            "contact": {
                "office": "Bodafors",
                "phone": [
                    "Svenska Möbelfabrikerna",
                    "Vasag. 52, Stockholm, telefon: 207130"
                ],
                "postgiro": "6463",
                "head_office": "Bodafors",
                "sales_offices": [
                    {
                        "location": "Stockholm",
                        "phone": "207130"
                    }
                ],
                "telegraph": "Möbelfabrikerna, Bodafors",
                "factory_office": "Mölndal",
                "factory_phone": "272000"
            },
            "financials": {
                "capital": "400,000 kr",
                "employees": {
                    "industriarb.": 390
                },
                "annual_turnover": "4,100,000 kr",
                "annual_production_value": "20,000,000 kr"
            },
            "foundation_year": 1918,
            "board": [
                {
                    "name": "ing. Gust. ödqvist",
                    "role": "ordf."
                },
                {
                    "name": "ing. Einar Egnell",
                    "role": "member"
                },
                {
                    "name": "ing. S. Stridsberg",
                    "role": "member"
                },
                {
                    "name": "dir. Victor Strömberg",
                    "role": "member"
                }
            ],
            "director": "Gunnar Lindeberg"
        },
        "2": {
            "name": "AB. Svenska Oljeslageri",
            "location": "Göteborg",
            "business": "Tillverkar vegetabiliska oljor, oljefernissor, ftalsyreanhydrid, maleinsyrean-hydrid, lackkonsthartser, mjukgörings-medel, sickativer, textilhjälpmedel samt foderkakor",
            "contact": {
                "office": "Mölndal",
                "phone": [
                    "AB. Svenska Oljeslageri",
                    "Göteborg 5, telefon: 272000"
                ],
                "postgiro": "46490",
                "head_office": "Mölndal",
                "sales_offices": [
                    {
                        "location": "Henriksborg",
                        "phone": "437071"
                    }
                ],
                "telegraph": "Delbanco, Göteborg",
                "factory_office": "Henriksborg",
                "factory_phone": "437071"
            },
            "financials": {
                "capital": "3,600,000 kr",
                "employees": {
                    "industriarb.": 220
                },
                "annual_turnover": "20,000,000 kr"
            },
            "foundation_year": 1916,
            "board": [
                {
                    "name": "konsul Oscar Gullander",
                    "role": "ordf."
                },
                {
                    "name": "dir. Ernst Persson",
                    "role": "v. ordf."
                },
                {
                    "name": "dir. Gunnar Engberg",
                    "role": "member"
                },
                {
                    "name": "dir. H. E. Helmerson",
                    "role": "member"
                },
                {
                    "name": "dir. Emanuel Högberg",
                    "role": "member"
                },
                {
                    "name": "konsul S. H. Sörensen",
                    "role": "member"
                }
            ],
            "director": "H. E. Helmerson"
        },
        "3": {
            "name": "AB. Svenska Pianofabriken",
            "location": "Stockholm",
            "business": "Tillverkar pianon"
        },
        "4": {
            "name": "AB. Svenska Precisionsverktyg",
            "location": "Nacka",
            "business": "Mek. verkstad",
            "contact": {
                "office": "Nacka",
                "phone": [
                    "Espeve, Stockholm",
                    "Stockholm 162860 o. 162172"
                ],
                "postgiro": "58952",
                "representative_office": "Stockholm, Malmskillnadsg. 46",
                "representative_phone": "232425"
            }
        },
        "5": {
            "name": "AB. Svenska Naxos",
            "location": "Västervik"
        },
        "6": {
            "name": "AB. Svenska AB. Philips",
            "location": "Stockholm",
            "business": "Försäljningsbolag för svenska elektrotekniska produkter"
        }
    }
}