{
    "original": "Piano fa b rike ma—Plåt för ädling\n\nFabriken, som anlades 1888, ombildades\ntill bolag 1897 och äges av AB. Förenade\nPiano- &amp; Orgelfabriker, Arvika. (Se\n\nvidare under detta bolag,.).\n\nStyrelse: disp. G. A. Hadell, dir. Karl\nHögberg, dir. J. Sande J:or.\n\nDisp. : G. A. Hadell.\n\n*\tPiano- &amp; Orgelfabrikerna, Förenade,\n\nA rvika.\n\nSe AB. Förenade Piano- &lt;&amp;\nOrgelfabriker, Arvika.\n\n*AB. Pickers, Södertälje.\n\nTillverkar pickers av råhud och läder,\nryck- och slagremmar, syremmar m. m.;\nspecialitet: råhudspickers.\n\nTelegr.-adr.: Pickers, Södertälje.\nTelefon: 30252. Postgiro: 33286. — Akt.-kap.:\n50.000 kr. Arb.-antal: 10. Tillv.-värde pr\når: 200,000 kr. — Bolaget grundat 1914.\n\nStyrelse: bankdir. Rich. Juhlin (ordf.),\ndir. John W. Rydinger.\nRydinger.\n\nVerkst. dir.: va kant.\n\nFÖrsäljn.-chef: H. Wilhelmsson.\n\nV ericstads chef: verkm. K. R.\nAndersson.\n\n*\tGustaf Piehls Bryggeri AB.,\n\nStockholm,\n\nKontor: Götgatan 106. Telefon: 427900\no. 427901. Postgiro: 2144.\n\nAkt.-kap.: 2,000,000 kr. — Firman\netabl. 1891, bolag 1897. Tillverkningen av\nmaltdrycker nedlagd.\n\nStyrelse: ing. Carl-Gustaf Piehl\n(ordf.), kamrer Sigurd Klingman,\nvice-amiral C. F. Riben.\n\nVerkst dir.: Carl-Gustaf Piehl.\n\nAB. Pilgrimsta Sågverk,\n\nPilgrimstad.\n\nSågverk och hyvleri i Pilgrimstad\n(Jämtl. l.). Tillverkar sågade och hyvlade\nträvaror, stav och battens.\n\nTelegr.-adr.: Sawmill, Pilgrimstad.\nTelefon: 1 o. 30. Postgiro: 83470.\n\nAkt.-kap.: 150,000 kr. Antal\nindustriarb.: 50. Årstillv.: 3,500 stds trävaror o.\n250 stds stav. — Bolaget grundat 1925.\n\nStyrelse: adv. Adolf Sjöberg (ordf.),\ndisp. Tor Busch, disp. Ernst Pettersson.\n\nDisp.: Tor Busch.\n\n*Piteå Bryggeri AB., Piteå.\n\nTillverkar malt och läskedrycker.\n\nTelegr.-adr.: Ångbryggeriet, Piteå.\nTelefon: 1006. Postgiro: 60002.\n\nAkt.-kap.: 120,000 kr. Antal\nindustriarb.: 15. Tillv.-värde pr år: 490,000 kr.\n\n—\tBryggeriet anlagt 1891, nuv. bolag\n1935, äges av AB. Luleå Bryggeri.\n\nStyrelse o. disp.: Folke Burström.\n\nBryggmäst.: Dag Röing.\n\n* Piteå Träkemiska Fabriker, Piteå.\n\nSe AB. Statens Skogsindustrier,\nStockholm.\n\n*Pix AB. (f. d. Ericson &amp; Rabenius),\n\nGävle.\n\nSpecialfabrik för tillverkning av\ntabletter, pastiller och engelsk lakrits,\nkaramellfabrik med tillverkning av\nkarameller, dragéer och konfekt samt\nchokladfabrik. Specialiteter: »Pix»-tabletter,\nCoryfin-pastiller o. -bonbons.\n\nTelegr.-adr.: Pix, Gävle. Telefon: 588.\nPostgiro: 76100. Representant i\nStockholm: Pix AB:s Nederlag, Hagag. 31—33,\ntelefon: 234755.\n\nAkt.-kap.: 1,000,000 kr. Antal\nindustriarb.: 75. Tillv.-värde pr år: 2,500,000 kr.\n\n—\tFirman etabl. 1897, bolag 1919.\n\nStyrelse: konsul Wilh. Ericson, dir.\n\nJohn Sjödahl.\n\nVerkst. dir.: John Sjödahl.\n\nAB. Plastiska Pluralis-Klichéer,\n\nStockholm,\n\nKlichéfabrik. Tillverkar plastiska\nklichéer och matriser.\n\nKontor: Gamla Brog. 27. Telegr.-adr.:\nKliché, Stockholm. Telefon: 231695.\nPostgiro: 150850. — Akt.-kap.: 18,000 kr.\nAntal industriarb.: 5. Tillv.-värde pr år:\n100,000 kr. — Bolaget grundat 1935.\n\nVerkst. dir.: Per O. S. Fjästad.\n\nKamrer: Börje Abelmann.\n\nPlastolit AB., Brastad.\n\nTillverkar konsthartsprodukter vid\nfabrik i Brastad (Göteb. o. Bohus l.).\nVarumärke: »Plastolit».\n\nTelefon: 149. Postgiro: 253043. —\nAkt.-kap.: 100,000 kr. Antal industriarb.:\n35. Tillv.-värde pr år: 800,000 kr. —\nBolaget grundat 1945.\n\nStyrelse: dir. Nils Kärrlander (ordf.),\nciviling. Eric Brodén, disp. Waldemar\nEwerlöf, ing. Olaf Kristoffersen, ryttm.\nSven Oleinikoff.\n\nVerkst. dir.: Nils Kärrlander.\n\n*AB. Plåtförädling, Hälsingborg.\n\nMek. verkstad, dissous- och\nsyrgasfa-brik. Tillverkar värmeledningselement",
    "structured": {
        "1": {
            "name": "Piano fabrike ma—Plåt för ädling",
            "foundation_year": 1888,
            "corporation_year": 1897,
            "foundation_name": "AB. Förenade Piano- & Orgelfabriker",
            "board": [
                {
                    "name": "G. A. Hadell",
                    "role": "disp."
                },
                {
                    "name": "Karl Högberg",
                    "role": "dir."
                },
                {
                    "name": "J. Sande J:or",
                    "role": "dir."
                }
            ]
        },
        "2": {
            "name": "AB. Pickers",
            "location": "Södertälje",
            "products": "Tillverkar pickers av råhud och läder, ryck- och slagremmar, syremmar m. m.; specialitet: råhudspickers.",
            "contact": {
                "phone": [
                    "30252"
                ],
                "postgiro": "33286"
            },
            "financials": {
                "capital": "50,000 kr",
                "employees": {
                    "Arb.-antal": 10
                },
                "annual_turnover": "200,000 kr",
                "annual_production_value": "200,000 kr"
            },
            "foundation_year": 1914,
            "board": [
                {
                    "name": "Rich. Juhlin",
                    "role": "bankdir."
                },
                {
                    "name": "John W. Rydinger",
                    "role": "dir."
                }
            ],
            "director": "va kant",
            "sales_manager": "H. Wilhelmsson",
            "manager": "verkm. K. R. Andersson"
        },
        "3": {
            "name": "Gustaf Piehls Bryggeri AB.",
            "location": "Stockholm",
            "contact": {
                "office": "Götgatan 106",
                "phone": [
                    "427900",
                    "427901"
                ],
                "postgiro": "2144"
            },
            "financials": {
                "capital": "2,000,000 kr"
            },
            "foundation_year": 1891,
            "corporation_year": 1897,
            "products": "Tillverkningen av maltdrycker nedlagd.",
            "board": [
                {
                    "name": "Carl-Gustaf Piehl",
                    "role": "ing."
                },
                {
                    "name": "Sigurd Klingman",
                    "role": "kamrer"
                },
                {
                    "name": "C. F. Riben",
                    "role": "vice-amiral"
                }
            ],
            "director": "Carl-Gustaf Piehl"
        },
        "4": {
            "name": "AB. Pilgrimsta Sågverk",
            "location": "Pilgrimstad",
            "products": "Tillverkar sågade och hyvlade trävaror, stav och battens.",
            "contact": {
                "phone": [
                    "1",
                    "30"
                ],
                "postgiro": "83470"
            },
            "financials": {
                "capital": "150,000 kr",
                "employees": {
                    "Antal industriarb.": 50
                },
                "annual_production_value": "3,500 stds trävaror o. 250 stds stav"
            },
            "foundation_year": 1925,
            "board": [
                {
                    "name": "Adolf Sjöberg",
                    "role": "adv."
                },
                {
                    "name": "Tor Busch",
                    "role": "disp."
                },
                {
                    "name": "Ernst Pettersson",
                    "role": "disp."
                }
            ],
            "director": "Disp.: Tor Busch"
        },
        "5": {
            "name": "Piteå Bryggeri AB.",
            "location": "Piteå",
            "products": "Tillverkar malt och läskedrycker.",
            "contact": {
                "phone": [
                    "1006"
                ],
                "postgiro": "60002"
            },
            "financials": {
                "capital": "120,000 kr",
                "employees": {
                    "Antal industriarb.": 15
                },
                "annual_turnover": "490,000 kr"
            },
            "foundation_year": 1891,
            "corporation_year": 1935,
            "predecessor": "AB. Luleå Bryggeri",
            "director": "Styrelse o. disp.: Folke Burström",
            "sales_manager": "Bryggmäst.: Dag Röing"
        },
        "6": {
            "name": "Piteå Träkemiska Fabriker",
            "location": "Piteå",
            "predecessor": "AB. Statens Skogsindustrier, Stockholm"
        },
        "7": {
            "name": "Pix AB. (f. d. Ericson & Rabenius)",
            "location": "Gävle",
            "products": "Specialfabrik för tillverkning av tabletter, pastiller och engelsk lakrits, karamellfabrik med tillverkning av karameller, dragéer och konfekt samt chokladfabrik.",
            "contact": {
                "phone": [
                    "588"
                ],
                "postgiro": "76100",
                "representant_stockholm": "Pix AB:s Nederlag, Hagag. 31—33, telefon: 234755"
            },
            "financials": {
                "capital": "1,000,000 kr",
                "employees": {
                    "Antal industriarb.": 75
                },
                "annual_turnover": "2,500,000 kr"
            },
            "foundation_year": 1897,
            "board": [
                {
                    "name": "Wilh. Ericson",
                    "role": "konsul"
                },
                {
                    "name": "John Sjödahl",
                    "role": "dir."
                }
            ],
            "director": "Verkst. dir.: John Sjödahl"
        },
        "8": {
            "name": "AB. Plastiska Pluralis-Klichéer",
            "location": "Stockholm",
            "products": "Tillverkar plastiska klichéer och matriser.",
            "contact": {
                "office": "Gamla Brog. 27",
                "phone": [
                    "231695"
                ],
                "postgiro": "150850"
            },
            "financials": {
                "capital": "18,000 kr",
                "employees": {
                    "Antal industriarb.": 5
                },
                "annual_turnover": "100,000 kr"
            },
            "foundation_year": 1935,
            "director": "Verkst. dir.: Per O. S. Fjästad",
            "manager": "Kamrer: Börje Abelmann"
        },
        "9": {
            "name": "Plastolit AB.",
            "location": "Brastad",
            "products": "Tillverkar konsthartsprodukter vid fabrik i Brastad (Göteb. o. Bohus l.). Varumärke: »Plastolit».",
            "contact": {
                "phone": [
                    "149"
                ],
                "postgiro": "253043"
            },
            "financials": {
                "capital": "100,000 kr",
                "employees": {
                    "Antal industriarb.": 35
                },
                "annual_turnover": "800,000 kr"
            },
            "foundation_year": 1945,
            "board": [
                {
                    "name": "Nils Kärrlander",
                    "role": "dir."
                },
                {
                    "name": "Eric Brodén",
                    "role": "civiling."
                },
                {
                    "name": "Waldemar Ewerlöf",
                    "role": "disp."
                },
                {
                    "name": "Olaf Kristoffersen",
                    "role": "ing."
                },
                {
                    "name": "Sven Oleinikoff",
                    "role": "ryttm."
                }
            ],
            "director": "Verkst. dir.: Nils Kärrlander"
        },
        "10": {
            "name": "AB. Plåtförädling",
            "location": "Hälsingborg",
            "products": "Tennpläterad bakelitkapasistet."
        }
    }
}