{
    "original": "Stol fabrik—Stora\n\nkakmjöl. Varumärken: »Axa» o. »Peos».\n\nHuvudkontor: Göteborg, Odinsg. 6.\nTelegr.-adr.: Stokkebye, Göteborg.\nTelefon: »Axa kvarn». Postgiro: 12300.\n\nAkt.-kap.: 1,000,000 kr. Antal\nindustriarb.: 150. Tillv.-värde pr år: 8,000,000 kr.\n\n—\tBolaget grundat 1901.\n\nStyrelse: rådm. Sten Lindquist, dir.\nRolf Stokkebye.\n\nVerkst. dir.: Gösta Cederryd.\n\nV. verkst. dir.: Rolf Stokkebye.\n\n\"Stolfabriks AB., Smålandsstenar.\n\nSnickerifabrik i Smålandsstenar\n(Jönköp. l.). Tillverkar pinnstolar,\nmöbelstolar, skrivstolar av björk och ek, bord,\npiedestaler, soffor m. m.\n\nTelegr.-adr.: Stolfabriken,\nSmålandsstenar. Telefon: 14. Postgiro: 22594.\n\nAkt.-kap.: 110,500 kr. Antal\nindustriarb.: 40. Tillv.-värde pr år: 425,000 kr.\n\n—\tBolaget grundat 1907.\n\nStyrelse: f. riksdagsm. Malkolm\nPetterson (ordf.), disp. Oscar André, kamrer\nCarl Odin.\n\nDisp.: Oscar André.\n\n\"AB. Stol I bergs Crufvor o.\nAnrikningsverk, Håksberg.\n\nGruvor i Stollbergs-, Dambergs- och\nS vartbergsf äl ten, Torrstensbergsf ältet\nsamt Valsarvsgruvan (samtl. i Kopparb.\n1.). anrikningsverk och flotationsverk för\nzink och bly.\n\nBryter järnmalm samt producerar\nzink-och blyslig. Bolaget driver även\nskogshantering.\n\nKontor: Håksberg. Telegr.-adr.:\nSilf-hvttan, Ludvika. Telefon: Ludvika 818.\nPostgiro: 167348.\n\nAkt.-kap.: 1,030,000 kr. Antal\nindustriarb.: 135. — Bolaget grundat 1911.\n\nStyrelse: dir. II. Hennemann (ordf.),\ndisp. John A. Hedlund, adv. Nils\nHögberg.\n\nVerkst. dir.: H. Hennemann.\n\nDisp.: John A. Hedlund.\n\nGruving.: P. Norrman.\n\n\"Stomatolfabriken, Stockholm.\n\nSe AB. Grumme &amp; Son, Stockholm.\n\n\"AB. Stora Borgs Tegelbruk,\n\nLilla Edet.\n\nTillverkar murtegel, mellanväggsplattor\noch annat poröst tegel vid tegelbruk i\nStora Borg, Lilla Edet (Göteb. o.\nBohus l.).\n\nTelefon: Lilla Edet 24. Repr. för Göte-\n\n33\n\nborg: Göteborgs Tegel AB., Göteborg,\nMagasinsg. 3, telefon: 131348.\n\nAkt.-kap.: 100,000 kr. Antal\nindustriarb.: 40. Årstillv.: 2,5 milj. st. tegelvaror.\n— Bolaget grundat 1907.\n\nVerkst. dir.: Fredrik Anderson.\n\n\"Stora Kopparbergs Bergslags AB.,\n\nFalun.\n\nBolaget äger Falu Kopparverk,\nDomn-arfvets Jernverk, Bysjöverken,\nKvarnsvedens Pappersbruk (samtl. i Kopparb. l.),\nSkutskärs Sågverk och Skutskärs\nFabriker, Söderfors Bruk samt Älfkarleö Bruk\n(samtl. i Uppsala l.). (Betr.\ntillverkningar etc., se vidare under resp. verks namn.)\n\nBolaget äger jämväl skogs- och\njordbruksdomäner, elektr.\nvattenkraftstationer, järngruvor i Grängesbergs,\nBlötbergets, Ramhälls, Idkerbergets, Vintjärns,\nDannemora, Bispbergs, Norbergs m. fl.\ngruvfält, kalk- och kvartsbrott m. m.\nsamt idkar skogshantering,\njärnmalmsbrytning och vattenkraftsdistribution\nävensom kvarnrörelse.\n\nHuvudkontor: Falun. Telefon och\ntelegr.-adr.: »Bergslaget». Postgiro: 75.\nSpeditionsavd.: Stockholm, Jakobsbergsg.\n2, samt i Gävle.\n\nAkt.-kap.: 90,000,000 kr. Antal\nindustriarb.: 6,600.\n\nBolaget bildat på 1200-talet, aktiebolag\n1888.\n\nStyrelse: grossh. Robert Ljunglöf\n(ordf.), disp. Ejnar Rodling, överste E.\nR. Salwén, dir. Claes Wahlund, bankdir.\nJacob Wallenberg, bankdir. Marcus\nWal-lenberg.\n\nVerkst. dir. o. disp.: Ejnar Rodling.\n\nV. verkst. dir.: H. Abenius^\n\nKassadir.: Sven Linder.\n\nVerks- och driftschefer: för\nkraftverken: dir. Sam Malmfors; för skogarna:\njägm. C. G. Sundberg; för järngruvorna:\ndir. K. Rutberg; för lantbruken: förv.\nHerman Dahlström (Strömsberg).\n(Chefer för Övriga verk, se under resp.\nortsnamn.)\n\nFörsäljn.-chef er: vid huvudkontoret: f.\npapper, cellulosa och trävaror: dir. H.\nG. Gullander; för kem. prod.: intend.\nBo Stenberg. (Domnarfvets, Söderfors och\nÄlfkarleö produkter försäljas från résp.\nbruk.)\n\nInköpsavd.: intend. Percy Betts.\n\nPubl.-avd.: fil. dr Alvar Silow.\n\n(Jfr annons å Bokmärket.)\n\n\"Stora Långviks Gruf AB.,\n\nHedemora.\n\nJärnmalmsgruvor vid Intrånget pr\nHedemora (Kopparb. l.) samt Askö pr",
    "structured": {
        "firms": [
            {
                "name": "Stol fabrik—Stora kakmjöl",
                "location": "Göteborg, Odinsg. 6",
                "contact": {
                    "telegraph": "Stokkebye, Göteborg",
                    "phone": [
                        "Axa kvarn"
                    ],
                    "postgiro": "12300"
                },
                "financials": {
                    "capital": "1,000,000 kr",
                    "employees": {
                        "industriarb": 150
                    },
                    "annual_turnover": "8,000,000 kr",
                    "annual_production_value": "8,000,000 kr"
                },
                "foundation_year": 1901,
                "board": [
                    {
                        "name": "rådm. Sten Lindquist",
                        "role": "dir."
                    },
                    {
                        "name": "Rolf Stokkebye",
                        "role": "dir."
                    }
                ],
                "director": "Gösta Cederryd",
                "managing_director": "Rolf Stokkebye"
            },
            {
                "name": "Stolfabriks AB., Smålandsstenar",
                "location": "Smålandsstenar (Jönköp. l.)",
                "contact": {
                    "telegraph": "Stolfabriken, Smålandsstenar",
                    "phone": "14",
                    "postgiro": "22594"
                },
                "financials": {
                    "capital": "110,500 kr",
                    "employees": {
                        "industriarb": 40
                    },
                    "annual_turnover": "425,000 kr",
                    "annual_production_value": "425,000 kr"
                },
                "foundation_year": 1907,
                "board": [
                    {
                        "name": "f. riksdagsm. Malkolm Petterson",
                        "role": "ordf."
                    },
                    {
                        "name": "disp. Oscar André",
                        "role": "disp."
                    },
                    {
                        "name": "kamrer Carl Odin",
                        "role": "kamrer"
                    }
                ],
                "director": "Oscar André"
            },
            {
                "name": "AB. Stol I bergs Crufvor o. Anrikningsverk, Håksberg",
                "location": "Håksberg",
                "contact": {
                    "telegraph": "Silf-hvttan, Ludvika",
                    "phone": "Ludvika 818",
                    "postgiro": "167348"
                },
                "financials": {
                    "capital": "1,030,000 kr",
                    "employees": {
                        "industriarb": 135
                    }
                },
                "foundation_year": 1911,
                "board": [
                    {
                        "name": "dir. H. Hennemann",
                        "role": "ordf."
                    },
                    {
                        "name": "disp. John A. Hedlund",
                        "role": "disp."
                    },
                    {
                        "name": "adv. Nils Högberg",
                        "role": "adv."
                    }
                ],
                "director": "H. Hennemann",
                "managing_director": "H. Hennemann"
            },
            {
                "name": "AB. Stora Borgs Tegelbruk, Lilla Edet",
                "location": "Stora Borg, Lilla Edet (Göteb. o. Bohus l.)",
                "contact": {
                    "phone": "Lilla Edet 24"
                },
                "financials": {
                    "capital": "100,000 kr",
                    "employees": {
                        "industriarb": 40
                    },
                    "annual_production_value": "2,500,000 st. tegelvaror"
                },
                "foundation_year": 1907,
                "director": "Fredrik Anderson"
            },
            {
                "name": "AB. Stora Kopparbergs Bergslags AB., Falun",
                "location": "Falun",
                "contact": {
                    "telegraph": "Bergslaget",
                    "phone": "Bergslaget",
                    "postgiro": "75"
                },
                "financials": {
                    "capital": "90,000,000 kr",
                    "employees": {
                        "industriarb": 6,
                        "unit": "600"
                    }
                },
                "foundation_year": "1200-talet",
                "current_name_year": 1888,
                "board": [
                    {
                        "name": "grossh. Robert Ljunglöf",
                        "role": "ordf."
                    },
                    {
                        "name": "disp. Ejnar Rodling",
                        "role": "disp."
                    },
                    {
                        "name": "överste E. R. Salwén",
                        "role": "överste"
                    },
                    {
                        "name": "dir. Claes Wahlund",
                        "role": "dir."
                    },
                    {
                        "name": "bankdir. Jacob Wallenberg",
                        "role": "bankdir."
                    },
                    {
                        "name": "bankdir. Marcus Wallenberg",
                        "role": "bankdir."
                    }
                ],
                "director": "Ejnar Rodling",
                "managing_director": "Ejnar Rodling"
            },
            {
                "name": "Stora Långviks Gruf AB., Hedemora",
                "location": "Hedemora (Kopparb. l.)"
            }
        ]
    }
}