{
    "original": "Sko fa b riken—Sko ge n\n\nsamförsälj.: Skofabriks AB. Oscaria,\nÖrebro. — Akt.-kap.: 448,000 kr. Antal\nindustriarb.: 270. Tillv.-värde pr år:\n3,985,000 kr. — Bolaget grundat 1907.\n\nStyrelse: verkm. J. W. Ringquist, dir.\nGösta Åqvist, ing. Knut Åqvist, fru L.\nÅqvist, dir. Sven Åqvist.\n\nDisp.: Sven Åqvist.\n\n*AB. Skofabriken Standard, Lund.\n\nTillverkar damskodon. % Varumärke:\n»Stiletto».\n\nTelefon: 11916 o. 11856. Postgiro:\n37003. — Akt.-kap.: 120,000 kr. Antal\nindustriarb.: 55. Tillv.-värde pr år: 900,000\nkr. — Firman etabl. 1922, bolag 1930.\n\nStyrelse: bankdir. A. J. Ingemanson\n(ordf.), fabr. Per Helander, fabr. Thure\nHelander, fabr. Hj. Malmkvist, dir. Kuno\nMöller.\n\nVerkst. dir.: Johan Helander.\n\n*AB. Skofabriken Svea,Örebro.\n\nSe AB. Örebro Sköfabrik, Örebro.\n\n\"AB. Skofabriken Victoria, Örebro.\n\nTillverkar skodon. Varumärken:\n»Victoria» o. »Abisko».\n\nTelegr.-adr.: Skovictoria, Örebro.\nTelefon: 10647. Postgiro: 141247.\nEnsamförsälj.: AB. Carlsson &amp; Åqvist, Örebro,\ntelefon: »Carlssonåqvist». Repr. i\nStockholm: Nils Olsson, Vasag. 16, telefon:\n100129.\n\nAkt.-kap.: 600,000 kr. Antal\nindustriarb.: 125. Tillv.-värde pr år: 2,100,000 kr.\n— Bolaget grundat 1908.\n\nStyrelse: grossh. Erik Åqvist (ordf.),\ndisp. Erik Johansson, dir. Torsten Åqvist.\n\nDisp.: Erik Johansson.\n\n\"Skofabriken Wändia, C. Ståhlberg\n\n&amp; Co., Kumla.\n\nTillverkar dam- och flickskodon vid\nfabrik i Kumla (Örebro l.). Varumärke:\n»Elly».\n\nTelefon: 70461. — Antal industriarb.:\n15. Tillv.-värde pr år: 205,000 kr. —\nFirman etabl. 1934.\n\nÄgare o. chefer: fabr. John Ljungberg\no. fabr. Gunnar Stålberg.\n\n\"Skofabriks AB. Kronan, Örebro.\n\nTillverkar randsydda och\nbecksöm-sydda skodon. Specialiteter:\nherrlågskorna »Master», »Masterhand» o.\n»Master-cord».\n\nTelefon: 19455. Postgiro: 20793.\nEnsamförsälj.: Kommanditbol. Master,\nÖrebro, telefon: 19455.\n\nAkt.-kap.: 250,000 kr. Antal\nindustriarb.: 120. — Bolaget, grundat 1913 äger\nAB. P. Sjökvists Skofabrik, Lindesberg.\n\nStyrelse o. verkst. direktörer: dir.\nHåkan Perman o. dir. Arthur Larsson.\n\nKontorschef: K. A. Heijdenberg.\n\n\"Skofabriks AB. Oscaria, Örebro.\n\nTillverkar och försäljer skodon.\nBolaget innehar 267 egna minutaffärer i\nlandet. Varunamn: »Oscaria», »Roland»,\n»Marta»-skon, »Skönex», »Starkex»,\n»Kraftex», »Sportex», »Piggelin»,\n»Gra-ziella», »Samarit» o. »Rustibus».\n\nTelegr.-adr. o. telefon: »Oscaria»,\nöre-bro.Postgiro: 29191.\n\nAkt.-kap.: 2,006,000 kr. Antal\nindustriarb.: 624. Tillv.-värde pr år:. 9,000,000 kr.\n— Bolaget grundat 1908.\n\nStyrelse: avd.-chef Sven Edstam,\nverkim Victor Persson, dir.-assist. E.\nRydén, dir. Gösta Åqvist, dir. Knut Åqvist,\nfru L. Åqvist, dir. Sven Åqvist.\n\nVerkst. dir.: Gösta Åqvist.\n\n\"Skofabriks AB. Tärnan, Örebro.\n\nTillverkar dam- och barnskodon.\nVarumärken: »Tärnsko» o. »Stjärnsko».\n\nTelefon: 10961. — Akt.-kap.: 45,000\nkr. Antal industriarb.: 50. Tillv.-värde pr\når: 600,000 kr. — Firman etabl. 1920\nunder namn Samuel Petersons Skofabrik,\nnuv. namn o. bolag 1945.\n\nStyrelse: fabr. Alvar Persson (ordf.),\nfabr. Erik Persson, fabr. Samuel\nPeterson.\n\nVerkst. direktörer; Alvar Persson o.\nSamuel Peterson.\n\n\"Skofabriks AB. Örnen, Örebro.\n\nSe Nya Skofabriks AB. örnen, Örebro.\n\n\"Skogens Kol AB., Kilafors.\n\nKolugnar, sågverk och hyvleri i Sibo,\nKilafors (Gävleb. l.) och i Ornäs\n(Kopparb. l.). Tillverkar träkol, trätjära,\ntjär-och terpentinolja, träsprit, kem. och tekn.\nren ättiksyra, sågade och hyvlade\nträvaror. Bolaget idkar jämväl skogsbruk.\n\nHuvudkontor: Kilafors. Telegr.-adr.:\nSkogensbolag, Kilafors. Telefon:\n»Skogensbolag». Postgiro: 15416.\nAvd.-kon-tor: Ornäs.\n\nAkt.-kap.: 1,570,800 kr. Antal\nindustriarb.: 400. Årstillv.: 2,000 stds sågade o.\n1,000 stds hyvlade trävaror, 210,000 kbm.\nträkol, 5,000 ton trätjära. — Bolaget\ngrundat 1877.",
    "structured": {
        "1": {
            "name": "Sko fabriken Standard",
            "location": "Lund",
            "business": "Tillverkar damskodon",
            "products": "Varumärke: »Stiletto»",
            "contact": {
                "phone": [
                    "11916",
                    "11856"
                ],
                "postgiro": "37003"
            },
            "financials": {
                "capital": "120,000 kr",
                "employees": {
                    "industriarb": 55
                },
                "annual_turnover": "900,000 kr"
            },
            "foundation_year": 1922
        },
        "2": {
            "name": "Sko fabriken Victoria",
            "location": "Örebro",
            "business": "Tillverkar skodon",
            "products": "Varumärken: »Victoria» o. »Abisko»",
            "contact": {
                "telegraph": "Skovictoria, Örebro",
                "phone": "10647",
                "postgiro": "141247"
            },
            "financials": {
                "capital": "600,000 kr",
                "employees": {
                    "industriarb": 125
                },
                "annual_turnover": "2,100,000 kr"
            },
            "foundation_year": 1908
        },
        "3": {
            "name": "Skofabriken Wändia, C. Ståhlberg & Co.",
            "location": "Kumla",
            "business": "Tillverkar dam- och flickskodon",
            "products": "Varumärke: »Elly»",
            "contact": {
                "phone": "70461"
            },
            "financials": {
                "employees": {
                    "industriarb": 15
                },
                "annual_turnover": "205,000 kr"
            },
            "foundation_year": 1934
        },
        "4": {
            "name": "Skofabriks AB. Kronan",
            "location": "Örebro",
            "business": "Tillverkar randsydda och becksömsydda skodon",
            "products": "Specialiteter: herrlågskorna »Master», »Masterhand» o. »Master-cord»",
            "contact": {
                "phone": "19455",
                "postgiro": "20793"
            },
            "financials": {
                "capital": "250,000 kr",
                "employees": {
                    "industriarb": 120
                }
            },
            "foundation_year": 1913
        },
        "5": {
            "name": "Skofabriks AB. Oscaria",
            "location": "Örebro",
            "business": "Tillverkar och försäljer skodon"
        },
        "6": {
            "name": "Skofabriks AB. Tärnan",
            "location": "Örebro",
            "business": "Tillverkar dam- och barnskodon",
            "products": "Varumärken: »Tärnsko» o. »Stjärnsko»",
            "contact": {
                "phone": "10961"
            },
            "financials": {
                "capital": "45,000 kr",
                "employees": {
                    "industriarb": 50
                },
                "annual_turnover": "600,000 kr"
            },
            "foundation_year": 1945
        },
        "7": {
            "name": "Skofabriks AB. Örnen",
            "location": "Örebro"
        }
    }
}