{
    "original": "A Isé n—A luminiseringsv e rketi\n\nM. AlsénsSnickerifabrik Eftr.,\n\n, Stockholm.\t.\n\nTillverkar byggnadssnickerier,\nlager-och butiksinredningar samt utför\nvå-siingsreparationer och fartygsinredningar.\n\nKontor: Pipersg. 7. Telefon: 530545.\nPostgiro: 195268. — Antal industriarb.:\n10. Tillv.-värde pr år: 120,000 kr. —\nFirman etabl. 1916.\n\nÄgare o. Qjfief:, fabr, Axel Stenfelt.\n\nAB. Alsterbro Glasbruk, Alsterbro.\n\nGlasbruk vid Alsterbro (Kalmar l.).\nTillverkar blåst, pressat och slipat\nhus-hållsglas, flaskor samt konservglas.\n\nTelegr.-adr.: Glasbruket, Alsterbro.\nTelefon : 40. Postgiro: 90930. Försäl\njn.-kontor: Stockholm, Drottningg. 30.\nTelefon: 214711.\n\nAkt.-kap.: 50,000 kr. Antal\nindustriarb.: 85. Tillv.-värde pr år: 525,000 kr. —\nBruket anlagt 1871, bolag 1930.\n\nStyrelse: bankkamrer Emil Jonsson\n{ordf.), fru K. Lillienberg, dir. Hubert\nOhlsson, hyttmäst. Ernst Svensson.\n\nVerkst. dir. o. disp.: Hubert Ohlsson.\n\nFörest, f. försäljn.-kontoret i\nStockholm: köpman J. O. Stilling.\n\nAB. Alsterfors Glasbruk, Målerås.\n\nGlasbruk och sågverk vid Alsterfors,\nMålerås (Kronob. Tillverkar pressat,\nhand- och maskinblåst glas, glas för\nkem.-tekniskt bruk, servis- och\nrestaurang-glas, prydnadsglas samt sågat virke.\nBolaget driver även skogshantering.\n\nTelefon: Målerås 1 o. 36. Postgiro:\n90390. — Akt.-kap.: 50,000 kr. Antal\nindustriarb.: 100. Tillv.-värde pr år:\n600,000 kr. — Bruket anlagt 1886, bolag\n1930.\tv v\n\nVerkst. dir.: Martin Jakobsson.\n\nDisp.: Gunnar Andersson.\n\nKamrer: Jarl Weidow.\n\n*Alstermo Bruks AB., Hohultslätt.\n\nPapp- och resef fektfabrik vid Als\ntermo, Hohultslätt (Kronob. l.).\n\nTillverkar slät och präglad\nkoffertpapp, konstläderpapp, skopapp (märke:\n»Norna»), bokbindarepapp och\nmatrispapp, jacquardpapp och jacquardkort för\ntextilindustrien samt reseffekter m. m.\n\nHuvudkontor: Hohultslätt.\nTelegr.-adr.: Alstermo, Kalmar. Telefon:\nHohultslätt 2. Postgiro: 37212.\n\nEnsamförsäl j. för papp för Sverige:\nGrubbens &amp; Co. AB., Stockholm,\nFer-kensgränd 1, post-, telefon- o. telegr.-adr.:\nGrubbens, Stockholm, postgiro: 4786.\n\nAkt.-kap.: 437,500 kr. Antal\nindustriarb.: 185. Tillv.-värde pr år: 2,200,000 kr.\nArstillv.: 3,000 ton papp. — Firman\netabl. 1865, bolag 1893.\n\nStyrelse: dir. Folke Lindqvist (ordf.),\ndisp. C. Gunnar Hseger, adv. Axel T.\nNilsson.\n\nVerkst. dir.: O. Gunnar Hseger.\n\nKåfrfrer: Edvin JoKånsfeon.\n\nFörsäljn.-chef: Eric Nilsson.\n\n*AB. Alsters Industrier, Alster.\n\ntYalskvarn och tegelfabriker (Alsters\nBfuk) vid Alster (Värml. t). Tillverkar\nmjöl och kli, mur- och taktegel samt\nårä-neringsrör.\n\nTelegr.-adr.: Alsterindustrin, Karlstad.\nTelefon: Karlstad 12295. Postgiro: 36200.\n\nAkt.-kap.: 600,000 kr. Antal\nindustriarb.: 74, varav vid kvarnen 32, vid\ntegelbruket 42.\n\nFirman etabl. 1865, bolag 1901 under\nnamn Handels AB. P. G. Jansson, nuv.\nnamn 1936. Bolaget är anslutet till AB.\nKvarnintressenter, Malmö.\n\nStyrelse; dir. Mauritz Carlson, dir.\nSven Malmberg.\n\nVerkst. dir.: Sven Malmberg.\n\nPlatschef: disp. Hugo Almgren.\n\n*AB. Alströms Trlkåfabrifc, Floby.\n\nTillverkar dam- och herrunderkläder i\nsilke- och bomullstrikå vid fabrik i Floby\n(Skarab. l.).\n\nTelefon: 46. Postgiro: 95442. —\nAkt.-kap.: 20,200 kr. Antal indiistriarb.: 10. —\nBolaget grundat 1935.\n\nStyrelse: dir. K. Rich. Alström (ordf.),\ndir. Eric Alström, köpm. Sigge Alström.\n\nVerkst. dir.: K. Rich. Alström.\n\nRagnar Alström AB., Borås.\n\nKonfektionsfabrik. Tillverkar herr- och\ngosskläder. Varumärke: »Jaguar».\n\nTelefon: 12405 o. 19455. Postgiro:\n33009. — Akt.-kap.: 100,000 kr.\nTillv.-värde pr år: 1,000,000 kr. — Bolaget\ngrundat 1943.\n\nStyrelse o. verkst. dir.: Ragnar\nAlström.\n\nFörsäljn.-chef: Erik H. Karlsson.\nSe även Ahlström.\n\nAlumlniseringsverken AB.,\n\nLidköping.\n\nTillverkar och aluminiserar härdlådor\noch andra värmebeständiga föremål;\nutför aluminiseringar som rostskydd. Spe-",
    "structured": {
        "1": {
            "name": "M. Alséns Snickerifabrik Eftr.",
            "location": "Stockholm",
            "business": "Tillverkar byggnadssnickerier, lager-och butiksinredningar samt utför vå-siingsreparationer och fartygsinredningar.",
            "contact": {
                "office": "Pipersg. 7",
                "phone": [
                    "530545"
                ],
                "postgiro": "195268"
            },
            "financials": {
                "capital": "N/A",
                "employees": {
                    "industriarb": 10
                },
                "annual_turnover": "120,000 kr",
                "annual_production_value": "N/A"
            },
            "foundation_year": 1916,
            "owners": [
                "Axel Stenfelt"
            ]
        },
        "2": {
            "name": "AB. Alsterbro Glasbruk",
            "location": "Alsterbro",
            "business": "Tillverkar blåst, pressat och slipat hus-hållsglas, flaskor samt konservglas.",
            "contact": {
                "telegraph": "Glasbruket, Alsterbro",
                "phone": "40",
                "postgiro": "90930"
            },
            "financials": {
                "capital": "50,000 kr",
                "employees": {
                    "industriarb": 85
                },
                "annual_turnover": "525,000 kr",
                "annual_production_value": "N/A"
            },
            "foundation_year": 1871,
            "board": [
                {
                    "name": "bankkamrer Emil Jonsson",
                    "role": "ordf."
                },
                {
                    "name": "fru K. Lillienberg",
                    "role": "N/A"
                },
                {
                    "name": "dir. Hubert Ohlsson",
                    "role": "N/A"
                },
                {
                    "name": "hyttmäst. Ernst Svensson",
                    "role": "N/A"
                }
            ],
            "owners": [
                "N/A"
            ],
            "director": "Hubert Ohlsson",
            "managing_director": "N/A",
            "sales_manager": "N/A",
            "manager": "N/A"
        },
        "3": {
            "name": "AB. Alsterfors Glasbruk",
            "location": "Målerås",
            "business": "Tillverkar pressat, hand- och maskinblåst glas, glas för kem.-tekniskt bruk, servis- och restaurang-glas, prydnadsglas samt sågat virke.",
            "contact": {
                "telegraph": "N/A",
                "phone": "Målerås 1 o. 36",
                "postgiro": "90390"
            },
            "financials": {
                "capital": "50,000 kr",
                "employees": {
                    "industriarb": 100
                },
                "annual_turnover": "600,000 kr",
                "annual_production_value": "N/A"
            },
            "foundation_year": 1886,
            "board": [
                {
                    "name": "N/A",
                    "role": "N/A"
                }
            ],
            "owners": [
                "N/A"
            ],
            "director": "Martin Jakobsson",
            "managing_director": "N/A",
            "sales_manager": "N/A",
            "manager": "N/A"
        },
        "4": {
            "name": "Alstermo Bruks AB.",
            "location": "Hohultslätt",
            "business": "Tillverkar slät och präglad koffertpapp, konstläderpapp, skopapp (märke: »Norna»), bokbindarepapp och matrispapp, jacquardpapp och jacquardkort för textilindustrien samt reseffekter m. m.",
            "contact": {
                "office": "Hohultslätt",
                "phone": [
                    "Hohultslätt 2"
                ],
                "postgiro": "37212"
            },
            "financials": {
                "capital": "437,500 kr",
                "employees": {
                    "industriarb": 185
                },
                "annual_turnover": "2,200,000 kr",
                "annual_production_value": "3,000 ton papp"
            },
            "foundation_year": 1865,
            "board": [
                {
                    "name": "dir. Folke Lindqvist",
                    "role": "ordf."
                }
            ],
            "owners": [
                "N/A"
            ],
            "director": "N/A",
            "managing_director": "O. Gunnar Hseger",
            "sales_manager": "Eric Nilsson",
            "manager": "Edvin JoKånsfeon"
        },
        "5": {
            "name": "AB. Alsters Industrier",
            "location": "Alster",
            "business": "Tillverkar mjöl och kli, mur- och taktegel samt årä-neringsrör.",
            "contact": {
                "telegraph": "Alsterindustrin, Karlstad",
                "phone": "Karlstad 12295",
                "postgiro": "36200"
            },
            "financials": {
                "capital": "600,000 kr",
                "employees": {
                    "industriarb": 74
                },
                "annual_turnover": "N/A",
                "annual_production_value": "N/A"
            },
            "foundation_year": 1865,
            "board": [
                {
                    "name": "dir. Mauritz Carlson",
                    "role": "N/A"
                }
            ],
            "owners": [
                "N/A"
            ],
            "director": "Sven Malmberg",
            "managing_director": "N/A",
            "sales_manager": "N/A",
            "manager": "disp. Hugo Almgren"
        },
        "6": {
            "name": "AB. Alströms Trikåfabrik",
            "location": "Floby",
            "business": "Tillverkar dam- och herrunderkläder i silke- och bomullstrikå vid fabrik i Floby.",
            "contact": {
                "phone": "46",
                "postgiro": "95442"
            },
            "financials": {
                "capital": "20,200 kr",
                "employees": {
                    "industriarb": 10
                },
                "annual_turnover": "N/A",
                "annual_production_value": "N/A"
            },
            "foundation_year": 1935,
            "board": [
                {
                    "name": "dir. K. Rich. Alström",
                    "role": "ordf."
                }
            ],
            "owners": [
                "N/A"
            ],
            "director": "K. Rich. Alström",
            "managing_director": "N/A",
            "sales_manager": "N/A",
            "manager": "N/A"
        },
        "7": {
            "name": "Ragnar Alström AB.",
            "location": "Borås",
            "business": "Tillverkar herr- och gosskläder.",
            "contact": {
                "phone": [
                    "12405",
                    "19455"
                ],
                "postgiro": "33009"
            },
            "financials": {
                "capital": "100,000 kr",
                "employees": {
                    "industriarb": "N/A"
                },
                "annual_turnover": "1,000,000 kr",
                "annual_production_value": "N/A"
            },
            "foundation_year": 1943,
            "board": [
                {
                    "name": "Ragnar Alström",
                    "role": "verkst. dir."
                }
            ],
            "owners": [
                "N/A"
            ],
            "director": "N/A",
            "managing_director": "N/A",
            "sales_manager": "Erik H. Karlsson",
            "manager": "N/A"
        },
        "8": {
            "name": "Aluminiseringsverken AB.",
            "location": "Lidköping",
            "business": "Tillverkar och aluminiserar härdlådor och andra värmebeständiga föremål; utför aluminiseringar som rostskydd.",
            "contact": {
                "phone": "N/A",
                "postgiro": "N/A"
            },
            "financials": {
                "capital": "N/A",
                "employees": {
                    "industriarb": "N/A"
                },
                "annual_turnover": "N/A",
                "annual_production_value": "N/A"
            },
            "foundation_year": "N/A",
            "board": [
                {
                    "name": "N/A",
                    "role": "N/A"
                }
            ],
            "owners": [
                "N/A"
            ],
            "director": "N/A",
            "managing_director": "N/A",
            "sales_manager": "N/A",
            "manager": "N/A"
        }
    }
}