{
    "original": "Rydén—Rätt vik\n\nRydéns Metallindustri, Gnosjö.\n\nMetallvarufabrik i Gnosjö (Jönköp. l.).\nTillverkar handdukshangare, skohorn,\nskyltmateriel m. m, samt utför\nförnick-ling, iförkromning och kadmiering.\n\nTelefon: 81. Postgiro: 76257. — Antal\nindustriarb.: 12. Tillv.-värde pr år:\n150,000 kr. — Firman etabl. 1928.\n\nÄgare o. chef: fabr. Adolf Rydén.\n\nAB. Littorin Rydén Boktryckeri,\n\nÖrebro.\n\nBoktryckeri. Utför trycksaker i\nbok-och offsettryck.\n\nTelefon: 19160. Postgiro: 31077. / —\nAkt.-kap.: 77,000 kr. Antal industriarb.:\n45. — Firman etabl. 1906, bolag 1915.\nDisp.: Bror Lewander.\n\n\"Rob. Rydins Handels- o. Fabriks\nAB., Borås.\n\nSe AB. Rory, Borås.\n\nRylander &amp; Rudolphs Fabriks AB.,\n\nStockholm.\n\nKolelektrod- och elementfabriker vid\nHenriksborg och Nacka (Sthlms l.).\nTillverkar torr- och våtelement, kolborstar,\ngrafitkopparborstar, mikrofon- och\nbelysningskol, kolelektroder och kolkärnor,\nkol-pulvertabletter för medicinskt bruk m. m.\nVarumärke: »R. R.».\n\nKontor: Ilenriksdal; postadr.:\nStockholm 35. Telegr.-adr.: Rudolphs,\nStockholm, Telef on: Stockholm 414441.\n\nAkt.-kap.: 750,000 kr. Antal\nindustriarb.: 37. — Firman etabl. 1882, bolag\n1889.\n\nStyrelse: dir. Charles Rudolphs (ordf.),\ning. Bertil Rudolphs, herr Karl Erik\nRudolphs.\n\nVerkst. dir.: Charles Rudolphs.\n\n\"AB. Rymans Bryggeri, Varberg.\n\nSvagdricksbryggeri. Tillverkar färsk\nsvagdricka.\n\nTelefon: 234. Postgiro: 73308. —\nAkt.-kap.: , 150,000 kr. Arb.-antal: 10.\nTillv.-värde pr år: 200,000 kr. — Bolaget\ngrundat 19,30.\n\nStyrelse: v. konsul Erland Skantze\n(ordf.), bankdir. Knut Olow, bryggm.\nOlof Skantze.\n\nVerkst. dir. • Erland Skantze.\n\nBryggm.: Georg Ström.\n\n598*\n\n\"Georg Rymans Snickeriverkstäder,\n\nStockholm.\n\nTillverkar möbler, inredningar för\nbutiker och fartyg samt byggnadssnickerier\nvid fabrik i Skrubba, Stockholm.\n\nPostadr.: Skrubba, Stockholm 4f\nTelefon: 282194 o. Älta 5. Postgiro: 57189.\n— Arb.-antal: 10. Tillv.-värde pr år:\n90,000 kr. — Firman etabl. 1872, nuv.\nägare 1921.\ti\n\nÄgare o. chef: snickarmäst. Georg\nRy-man.\n\n\"Ryska Gummifabriks AB., Malmö.\n\nSe AB. Tretorn, Hälsingborg.\n\nRyttaren, Torvströ AB., Sandhem,\n\nSe Torvströ AB. Ryttaren, Sandhem.\n\n\"Rågsvedens Snickeri, P. 0. Olsson\n\n&amp; C:o, Rågsveden.\n\nTillverkar köksinredningar vid\nsnickeriverkstad i Rågs veden (Kopparb. l.).\n\nTelefon: 51 o. 58. — Antal\nindustriarb.: 14. Tillv.-värde pr år: 130,000 kr —\nFirman etabl. 1936.\n\nChef : fabr. Per Olof Olsson.\n\n\"Rånäs Bruks AB,, Stockholm.\n\nTillverkar zinkvitt vid fabrik i Rånäs\n(Sthlms l.).\n\nFörsäljn.-kontor: Stockholm, Nybrog.\n60. Telefon: 674788. Postgiro: 197172. —\nAkt.-kap.: 400,000 kr. Antal industriarb.:\n15. — Bolaget grundat 1940.\n\nStyrelse: dir. Herman Iluldt (ordf.),\ndir. Bo Iluldt, övering. Andreas\nJohansson, konsul T. Thoresen, dir. Nils\nWåg-berg.\n\nVerkst. dir.: Herman Iluldt.\n\n\"C. C. Råström, Silver- och Nysilver-\n\nfabrik, Stockholm.\n\nTillverkar silver- och nysilvervaror\nsamt utför försilvring och förgyllning.\nSpecialitet: restaurantförsilvring.\n\nKontor: Tunnelg. 11. Telefon: 212462.\nPostgiro: 195321. — Firman etabl. 1915.\n\nÄgare o. chef: fabr. Carl G. Råström.\n\n\"Rämshyttans Grufvor, Rämshyttan.\n\nSe Gruf AB. Dalarne, Falun.\n\nAB. Rättviks Spisbrödsfabrik,\n\nRättvik.\n\nTillverkar spisbröd vid fabrik i Rättvik\n(Kopparb. L). Varumärken: »Rättviks-\n\n",
    "structured": {
        "1": {
            "name": "Rydéns Metallindustri",
            "location": "Gnosjö",
            "business": "Metallvarufabrik",
            "products": "Tillverkar handdukshängare, skohorn, skyltmateriel m.m., samt utför förnickling, förkromning och kadmiering",
            "contact": {
                "office": "Gnosjö (Jönköp. l.)",
                "phone": [
                    "81"
                ],
                "postgiro": "76257",
                "factory_phone": "81"
            },
            "financials": {
                "employees": {
                    "industriarb": 12
                },
                "annual_turnover": "150,000 kr",
                "annual_production_value": "150,000 kr"
            },
            "foundation_year": 1928,
            "owners": [
                "Adolf Rydén"
            ],
            "manager": "Adolf Rydén"
        },
        "2": {
            "name": "AB. Littorin Rydén Boktryckeri",
            "location": "Örebro",
            "business": "Boktryckeri",
            "contact": {
                "office": "Örebro",
                "phone": [
                    "19160"
                ],
                "postgiro": "31077"
            },
            "financials": {
                "capital": "77,000 kr",
                "employees": {
                    "industriarb": 45
                }
            },
            "foundation_year": 1906,
            "corporation_year": 1915,
            "board": [
                {
                    "name": "Bror Lewander",
                    "role": "Disp."
                }
            ]
        },
        "3": {
            "name": "AB. Rymans Bryggeri",
            "location": "Varberg",
            "business": "Svagdricksbryggeri",
            "products": "Tillverkar färsk svagdricka",
            "contact": {
                "office": "Varberg",
                "phone": [
                    "234"
                ],
                "postgiro": "73308"
            },
            "financials": {
                "capital": "150,000 kr",
                "employees": {
                    "arb-antal": 10
                },
                "annual_turnover": "200,000 kr"
            },
            "corporation_year": 1930,
            "board": [
                {
                    "name": "Erland Skantze",
                    "role": "Styrelse"
                },
                {
                    "name": "Knut Olow",
                    "role": "Styrelse"
                },
                {
                    "name": "Olof Skantze",
                    "role": "Bryggm."
                }
            ],
            "director": "Erland Skantze",
            "manager": "Erland Skantze",
            "sales_manager": "Georg Ström"
        },
        "4": {
            "name": "Georg Rymans Snickeriverkstäder",
            "location": "Stockholm",
            "business": "Möbeltillverkare",
            "products": "Tillverkar möbler, inredningar för butiker och fartyg samt byggnadssnickerier",
            "contact": {
                "office": "Skrubba, Stockholm",
                "phone": [
                    "282194",
                    "Älta 5"
                ],
                "postgiro": "57189"
            },
            "financials": {
                "employees": {
                    "arb-antal": 10
                },
                "annual_turnover": "90,000 kr"
            },
            "foundation_year": 1872,
            "owners": [
                "Georg Ryman"
            ],
            "manager": "Georg Ryman"
        },
        "5": {
            "name": "Rågsvedens Snickeri, P. O. Olsson & C:o",
            "location": "Rågsveden",
            "business": "Snickeriverkstad",
            "products": "Tillverkar köksinredningar",
            "contact": {
                "office": "Rågsveden (Kopparb. l.)",
                "phone": [
                    "51",
                    "58"
                ]
            },
            "financials": {
                "employees": {
                    "industriarb": 14
                },
                "annual_turnover": "130,000 kr"
            },
            "foundation_year": 1936,
            "manager": "Per Olof Olsson"
        },
        "6": {
            "name": "Rånäs Bruks AB.",
            "location": "Stockholm",
            "business": "Tillverkar zinkvitt",
            "products": "Tillverkar zinkvitt",
            "contact": {
                "office": "Rånäs (Sthlms l.)",
                "phone": [
                    "674788"
                ],
                "postgiro": "197172"
            },
            "financials": {
                "capital": "400,000 kr",
                "employees": {
                    "industriarb": 15
                }
            },
            "corporation_year": 1940,
            "board": [
                {
                    "name": "Herman Huldt",
                    "role": "Styrelse"
                },
                {
                    "name": "Bo Huldt",
                    "role": "Styrelse"
                },
                {
                    "name": "Andreas Johansson",
                    "role": "Övering."
                },
                {
                    "name": "T. Thoresen",
                    "role": "Konsul"
                },
                {
                    "name": "Nils Wågberg",
                    "role": "Dir."
                }
            ],
            "director": "Herman Huldt",
            "manager": "Herman Huldt"
        },
        "7": {
            "name": "C. C. Råström, Silver- och Nysilver-fabrik",
            "location": "Stockholm",
            "business": "Tillverkar silver- och nysilvervaror",
            "products": "Specialitet: restaurantförsilvring",
            "contact": {
                "office": "Tunnelg. 11",
                "phone": [
                    "212462"
                ],
                "postgiro": "195321"
            },
            "financials": {
                "capital": "Not specified"
            },
            "foundation_year": 1915,
            "owners": [
                "Carl G. Råström"
            ],
            "manager": "Carl G. Råström"
        },
        "8": {
            "name": "AB. Rättviks Spisbrödsfabrik",
            "location": "Rättvik (Kopparb. L)",
            "business": "Tillverkar spisbröd"
        }
    }
}