{
    "original": "Hedesunda—Hegert\n\nbruk, träsliperier, kemiska fabriker,\nkol-ningsanläggningar, gruvindustri m. m.\nsamt plåtradiatorer (värmeelement).\n\nTelegr.-adr.: Verkstad, Hedemora.\nTelefon: »Hedemora verkstäder». Postgiro:\n27757. Repr. i Stockholm: för\nplåtradiatorer: Nordiska Rör AB., Kungsg. 18,\ntelefon: »Nordiska Rörbolaget»; för\növriga tillverkningar: AB. öfvergård &amp; Co.,\nHovslagarg. 3, telefon: 105919—20.\n\nAkt.-kap.: 900,000 kr. Antal\nindustriarb.: 300. Tillv.-värde pr år: 7,000,000 kr.\n\nBolaget grundat 1903 under namn AB.\nSödra Dalarnes Gjuteri &amp;\nMaskinverkstad, ombildat till nuvarande bolag 1924.\n\nStyrelse: dir. -Gustav Raabe (ordf.),\ndir. Vilhelm Björkman, f. rådman K.\nIsidor Persson, disp. Ruben Persson.\n\nVerkst. dir.: Ruben Persson.\n\nKamrer: Johan Johanson.\n\nRitkontorschef: R. Sillen.\n\nVerkstadsing.: C. Wassberg.\n\nOfferting.: Nils Hedlund.\n\nInköpschef: G. B. Hulthén.\n\n(Jfr annons nr 72.)\n\nHedesunda Industri AB.9\n\nHedesunda.\n\nSågverk och snickerifabrik i ölbo,\nHedesunda (Gävleb. l.). Tillverkar sågade\nträvaror, möbler, inredningar och\nbyggnadssnickerier.\n\nTelefon: 14. Postgiro: 13985. —\nAkt.-kap.: 150,000 kr. Antal industriarb.: 50.\nTillv.-värde pr år: 350,000 kr. — Bolaget\ngrundat 1908.\n\nStyrelse: fabr. E. Lund (ordf.), fabr.\nAnd. Eriksson, fabr. Per Gustafsson.\n\nVerkst. dir.: And. Eriksson.\n\nAB. Karl Hedin, Västanfors.\n\nSågverk, hyvleri och lådfabrik i\nVästanfors, Fagersta (Västmanl. l.).\nTillverkar sågade och hyvlade trävaror samt\nlistverk och träkol.\n\nTelegr.-adr.: Karl, Västanfors.\nTelefon: Fagersta 40301. Postgiro: 98888.\n\nAkt.-kap.: 150,300 kr. Antal\nindustriarb.: 60. Tillv.-värde pr år: 1,500,000 kr.\nÅrstillv. av trävaror: 4,000 stds. —\nFirman etabl. 1917, bolag 1935.\n\nVerkst. dir.: disp. Karl Hedin.\n\nKamrer: G. H. Hiller.\n\n\"Hedlunds Mek. Verkstad, Stockholm.\n\nSe AB. Bröderna Hedlund, Stockholm.\n\nBernhard Hedlunds Mek. Verkstad,\n\nHedemora.\n\nSe Verkstads AB. Bernhard Hedlund.\nHedemora.\n\nHedlunds Trävara AB.* Furudal.\n\nSågverk och hyvleri i östan vik,\nFurudal (Kopparb. l.). Tillverkar sågade och\nhyvlade trävaror, listverk m. m. samt\nmonteringsfärdiga trähus\n(»Hedlundshus»).\n\nTelefon: »Hedlunds bolag». Postgiro:\n168396. — Akt.-kap.: 50,000 kr. Antal\nindustriarb.: 200. Årstillv.: 3,000 stds\nträvaror. ■— Bolaget grundat 1934.\n\nDirektör: Erik R. Hedlund.\n\nE. Hedman AB., Stockholm.\n\nSportartikelf abrik. Tillverkar tält,\nryggsäckar, packfickor, jakt- och\naxelväskor, shoppingväskor, kartfodral m. m.\nFirman driver även engroshandel med\nsportartiklar.\n\nKontor: Hornsg. 69. Telefon: 440010.\nPostgiro: 192627.\n\nAkt.-kap.: 10,000 kr. Antal\nindustriarb.: 25, — Bolaget grundat 1942.\n\nStyrelse o. verkst. dir.: Eric Hedman.\n\nAB; I. Hedström Kravattfabrik,\n\nGöteborg.\n\nTillverkar herrhalsdukar.\n\nKontor: Drottningg. 17—19. Telefon:\n110471 o. 131417. Postgiro: 42999.\n\nAkt.-kap.: 400,000 kr. Antal\nindustriarb.: 40. Tillv.-värde pr år: 700,000 kr.\n— Firman etabl. 1894, bolag 1937.\n\nVerkst. dir.: Ingemar Hedström.\n\n*N. F. Hedvall &amp; C:o, Skofabrik,\n\nBoden.\n\nSkofabrik i Svartbyn, Boden.\nTillverkar norrlandspjäxor, skidskor,\nfiltskid-kängor, arbetskängor, sportskodon och\ngrövre smorläderskor.\n\nTelegr.-adr.: Skofabriken, Boden.\nTelefon: 2212. Postgiro: 60329.\n\nAntal industriarb.: 22. Tillv.-värde pr\når: 500,000 kr. — Firman etabl. 1892.\n\nÄgare: fabr. Walfrid Hedvall o. fabr.\nRudolf Hedvall.\n\n\"Oscar Hegert, Stockholm.\n\nByggnadsentreprenörfirma för\nbostads-och affärshus, industribyggnader m. m.\n\nKontor: Birger Jarlsg. 36. Telegr.-adr.:\nBygghegert, Stockholm. Telefon: 107742,\n210109 o. 204321. Postgiro: 50357. —\nProd.-värde pr år: 2,500,000 kr. —\nFirman etabl. 1906.\n\nÄgare o. chef: ing. Oscar Hegert.\n\nArbetschefer: ing. Lennart Hegert o.\ning. Åke Persson.",
    "structured": {
        "1": {
            "name": "Hedesunda—Hegert bruk",
            "location": "Hedesunda",
            "business": "träsliperier, kemiska fabriker, kol-ningsanläggningar, gruvindustri m. m. samt plåtradiatorer (värmeelement)",
            "contact": {
                "office": "Verkstad, Hedemora",
                "phone": [
                    "Hedemora verkstäder"
                ],
                "postgiro": "27757",
                "head_office": "",
                "sales_offices": [
                    {
                        "location": "Nordiska Rör AB., Kungsg. 18",
                        "phone": "Nordiska Rörbolaget"
                    },
                    {
                        "location": "AB. övergård & Co., Hovslagarg. 3",
                        "phone": "105919—20"
                    }
                ],
                "telegraph": "",
                "factory_office": "",
                "factory_phone": ""
            },
            "financials": {
                "capital": "900,000 kr",
                "employees": {
                    "industriarb": 300
                },
                "annual_turnover": "7,000,000 kr",
                "annual_production_value": "7,000,000 kr"
            },
            "foundation_year": 1903,
            "current_name_year": 1924,
            "corporation_year": "",
            "board": [
                {
                    "name": "Gustav Raabe",
                    "role": "ordf."
                },
                {
                    "name": "Vilhelm Björkman",
                    "role": "dir."
                },
                {
                    "name": "K. Isidor Persson",
                    "role": "f. rådman"
                },
                {
                    "name": "Ruben Persson",
                    "role": "disp."
                }
            ],
            "director": "Ruben Persson",
            "managing_director": "",
            "sales_manager": "",
            "manager": ""
        },
        "2": {
            "name": "Hedesunda Industri AB",
            "location": "Hedesunda",
            "business": "Sågverk och snickerifabrik",
            "contact": {
                "office": "",
                "phone": [
                    "Hedemora verkstäder"
                ],
                "postgiro": "13985",
                "head_office": "",
                "sales_offices": [],
                "telegraph": "",
                "factory_office": "",
                "factory_phone": ""
            },
            "financials": {
                "capital": "150,000 kr",
                "employees": {
                    "industriarb": 50
                },
                "annual_turnover": "350,000 kr",
                "annual_production_value": "350,000 kr"
            },
            "foundation_year": 1908,
            "current_name_year": "",
            "corporation_year": "",
            "board": [
                {
                    "name": "E. Lund",
                    "role": "fabr."
                },
                {
                    "name": "And. Eriksson",
                    "role": "fabr."
                },
                {
                    "name": "Per Gustafsson",
                    "role": "fabr."
                }
            ],
            "director": "And. Eriksson",
            "managing_director": "",
            "sales_manager": "",
            "manager": ""
        },
        "3": {
            "name": "AB. Karl Hedin",
            "location": "Västanfors",
            "business": "Sågverk, hyvleri och lådfabrik",
            "contact": {
                "office": "Karl, Västanfors",
                "phone": [
                    "Fagersta 40301"
                ],
                "postgiro": "98888",
                "head_office": "",
                "sales_offices": [],
                "telegraph": "",
                "factory_office": "",
                "factory_phone": ""
            },
            "financials": {
                "capital": "150,300 kr",
                "employees": {
                    "industriarb": 60
                },
                "annual_turnover": "1,500,000 kr",
                "annual_production_value": "1,500,000 kr"
            },
            "foundation_year": 1917,
            "current_name_year": "",
            "corporation_year": 1935,
            "board": [],
            "director": "disp. Karl Hedin",
            "managing_director": "",
            "sales_manager": "",
            "manager": ""
        },
        "4": {
            "name": "Hedlunds Trävara AB",
            "location": "Furudal",
            "business": "Sågverk och hyvleri",
            "contact": {
                "office": "",
                "phone": [
                    "Hedlunds bolag"
                ],
                "postgiro": "168396",
                "head_office": "",
                "sales_offices": [],
                "telegraph": "",
                "factory_office": "",
                "factory_phone": ""
            },
            "financials": {
                "capital": "50,000 kr",
                "employees": {
                    "industriarb": 200
                },
                "annual_turnover": "",
                "annual_production_value": ""
            },
            "foundation_year": 1934,
            "current_name_year": "",
            "corporation_year": "",
            "board": [],
            "director": "Erik R. Hedlund",
            "managing_director": "",
            "sales_manager": "",
            "manager": ""
        },
        "5": {
            "name": "E. Hedman AB",
            "location": "Stockholm",
            "business": "Sportartikelfabrik",
            "contact": {
                "office": "Hornsg. 69",
                "phone": [
                    "440010"
                ],
                "postgiro": "192627",
                "head_office": "",
                "sales_offices": [],
                "telegraph": "",
                "factory_office": "",
                "factory_phone": ""
            },
            "financials": {
                "capital": "10,000 kr",
                "employees": {
                    "industriarb": 25
                },
                "annual_turnover": "",
                "annual_production_value": ""
            },
            "foundation_year": 1942,
            "current_name_year": "",
            "corporation_year": "",
            "board": [],
            "director": "Eric Hedman",
            "managing_director": "",
            "sales_manager": "",
            "manager": ""
        },
        "6": {
            "name": "AB; I. Hedström Kravattfabrik",
            "location": "Göteborg",
            "business": "Tillverkar herrhalsdukar",
            "contact": {
                "office": "Drottningg. 17—19",
                "phone": [
                    "110471",
                    "131417"
                ],
                "postgiro": "42999",
                "head_office": "",
                "sales_offices": [],
                "telegraph": "",
                "factory_office": "",
                "factory_phone": ""
            },
            "financials": {
                "capital": "400,000 kr",
                "employees": {
                    "industriarb": 40
                },
                "annual_turnover": "700,000 kr",
                "annual_production_value": "700,000 kr"
            },
            "foundation_year": 1894,
            "current_name_year": "",
            "corporation_year": 1937,
            "board": [],
            "director": "Ingemar Hedström",
            "managing_director": "",
            "sales_manager": "",
            "manager": ""
        },
        "7": {
            "name": "N. F. Hedvall & C:o",
            "location": "Boden",
            "business": "Skofabrik",
            "contact": {
                "office": "Skofabriken, Boden",
                "phone": [
                    "2212"
                ],
                "postgiro": "60329",
                "head_office": "",
                "sales_offices": [],
                "telegraph": "",
                "factory_office": "",
                "factory_phone": ""
            },
            "financials": {
                "capital": "",
                "employees": {
                    "industriarb": 22
                },
                "annual_turnover": "500,000 kr",
                "annual_production_value": "500,000 kr"
            },
            "foundation_year": 1892,
            "current_name_year": "",
            "corporation_year": "",
            "board": [],
            "director": "fabr. Walfrid Hedvall o. fabr. Rudolf Hedvall",
            "managing_director": "",
            "sales_manager": "",
            "manager": ""
        },
        "8": {
            "name": "Oscar Hegert",
            "location": "Stockholm",
            "business": "Byggnadsentreprenörfirma för bostads-och affärshus, industribyggnader m. m.",
            "contact": {
                "office": "Birger Jarlsg. 36",
                "phone": [
                    "107742",
                    "210109",
                    "204321"
                ],
                "postgiro": "50357",
                "head_office": "",
                "sales_offices": [],
                "telegraph": "",
                "factory_office": "",
                "factory_phone": ""
            },
            "financials": {
                "capital": "",
                "employees": "",
                "annual_turnover": "2,500,000 kr",
                "annual_production_value": "2,500,000 kr"
            },
            "foundation_year": 1906,
            "current_name_year": "",
            "corporation_year": "",
            "board": [],
            "director": "ing. Oscar Hegert",
            "managing_director": "",
            "sales_manager": "",
            "manager": "ing. Lennart Hegert o. ing. Åke Persson"
        }
    }
}