{
    "original": "J önsson—Kalkbränneri\n\n*AB. Göran Jönsson &amp; Co., Klippan.\n\nTillverkar byggnadssnickerier,\ninredningar och möbler vid fabrik i Klippan\n(Kristianst. l.). Bolaget driver även\nträ-varur och möbelaffär.\n\nTelegr.-adr.: Trägöran, Klippan.\nTelefon: 54 o. 454. Postgiro: 97712.\n\nAkt.-kap.: 125,000 kr. Antal\nindustriarb.: 23. Tillv.-värde pr år: 235,000 kr.\n\n—\tFirman etabl. 1897, bolag 1917.\nStyrelse: lantbr. Eric Meisner (ordf.),\n\ndisp. Malte Nytzén, kamrer Carl Uddling.\nVerkst. dir. o. disp.: Malte Nytzén.\nKamrer: Carl Uddling.\n\n*AB. J. W. Jönsson, Borås.\n\nHerrkonfektionsfabrik. Tillverkar\növerplagg, kostymer och byxor.\n\nTelegr.-adr.: Jiwe, Borås. Telefon:\n12589 o. 13031. Postgiro: 88267.\n\nAkt.-kap.: 230,000 kr. Antal\nindustriarb.: 125. Tillv.-värde pr år: 2,300,000 kr.\n\n—\tBolaget grundat 1925.\n\nStyrelse: disp. Holger Fernlund, fru J.\nFernlund, kamrer Erik Zachrisson.\nVerkst. dir.: H. Fernlund.\nKontorschef: E. Zachrisson.\n\n*M. Jönsson &amp; Son, Eslöv.\n\nVagn- och snickerifabrik. Tillverkar\nsportartiklar såsom bandy- och\nishockeyklubbor, travsulky m. m. samt\nreservdelar till lantbruksmaskiner.\n\nTelefon: 130. Postgiro: 71584. —\nAntal industriarb.: 15. — Firman etabl.\n1889, bolag 1919.\n\nÄgare o. chef: fabr. Alb. Jönsson.\n\nMartin Jönssons Mek. Verkstad,\n\nSödra Sandby.\n\nSe AB. Sandbymaskiner, Södra Sandby.\n\nP. Jönssons Skyffelfabrik AB.,\n\nHälsingborg.\n\nTillverkar spadar och skyfflar.\nSpecialitet: s. k. skånska skyfflar.\n\nTelefon: 10346. Postgiro: 30581. —\nAkt.-kap.: 120,000 kr. Antal industriarb.:\n12. Tillv.-värde pr år: 250,000 kr. —\nFirman etabl. 1888, bolag 1946.\n\nVerkst. dir.: Nils Göthe.\n\n*Jössefors AB., Ottebol.\n\nSe Billeruds AB., Säffle.\n\nK\n\nutmärker till Sveriges Industriförbund anslutna företag.\n\nKabelfabriken Effekt, Thure\nBengtsson, Smalandsstenar.\n\nTillverkar spiralkablar för\ncykelbelysningar vid fabrik i Smålandsstenar\n(Jönköp. l.).\n\nTelefon: 166. Postgiro: 162302. —\nAntal industriarb.: 7. Tillv.-värde pr år:\n100,000 kr. — Firman etabl. 1935.\n\nÄgare o. chef: fabr. Thure Bengtsson.\n\nKaffe- &amp; Kolonial AB., Malmö.\n\nMarsipan- och syltfabrik. Tillverkar\nbakmassor för konditorier och bagerier\nsamt sylter, marmelad, safter m. m.\nVarumärke: »Kå Kå».\n\nKontor: Per Weijersg. 3. Telegr.-adr.:\nKåkå, Malmö. Telefon: 70250. Postgiro:\n24597.\n\nAkt.-kap.: 275,000 kr. Antal\nindustriarb.: 48. Tillv.-värde pr år: 2,000,000 kr.\n— Bolaget grundat 1927.\n\nVerkst. dir.: Fritz Möller.\n\nDisp.: Rudolf Möller.\n\nFabrikschefer: Geert Jiirgensen o. Bela\nBalint.\n\n*Kakelfabriks AB. i Karlskrona,\n\nKarlskrona.\n\nTillverkar kakelugnar och spisar,\nspiskakel och beklädnadsplattor.\n\nTelegr.-adr.: Kakelfabriken,\nKarlskrona. Telefon: 154. Postgiro: 30277.\n\nAkt.-kap.: 441,500 kr. Antal\nindustriarb.: 120. Tillv.-värde pr år: 2,000,000 kr.\n— Bolaget grundat 1884.\n\nStyrelse: v. konsul S. A. Liljevall,\ndisp. Harald Lindström, dr J. Swanlund.\n\nVerkst. dir.: Harald Lindström.\n\n*Kalkbränneri- &amp; Kalkstens AB.,\n\nStockholm.\n\nKalkbruk i Vagnhärad (Södermanl. l.).\nTillverkar släckt och osläckt bränd kalk\nsamt bryter rå kalksten.\n\n272*",
    "structured": {
        "1": {
            "name": "AB. Göran Jönsson & Co.",
            "location": "Klippan",
            "business": "Byggnadssnickerier, inredningar och möbler",
            "products": "Tillverkar byggnadssnickerier, inredningar och möbler vid fabrik i Klippan (Kristianst. l.). Bolaget driver även trä-varur och möbelaffär.",
            "contact": {
                "telegraph": "Trägöran, Klippan",
                "phone": [
                    "54",
                    "454"
                ],
                "postgiro": "97712"
            },
            "financials": {
                "capital": "125,000 kr",
                "employees": {
                    "industriarb": 23
                },
                "annual_turnover": "235,000 kr",
                "annual_production_value": "235,000 kr"
            },
            "foundation_year": 1897,
            "corporation_year": 1917,
            "board": [
                {
                    "name": "lantbr. Eric Meisner",
                    "role": "ordf."
                },
                {
                    "name": "disp. Malte Nytzén",
                    "role": "disp."
                },
                {
                    "name": "kamrer Carl Uddling",
                    "role": "kamrer"
                }
            ]
        },
        "2": {
            "name": "AB. J. W. Jönsson",
            "location": "Borås",
            "business": "Herrkonfektionsfabrik",
            "products": "Tillverkar överplagg, kostymer och byxor.",
            "contact": {
                "telegraph": "Jiwe, Borås",
                "phone": [
                    "12589",
                    "13031"
                ],
                "postgiro": "88267"
            },
            "financials": {
                "capital": "230,000 kr",
                "employees": {
                    "industriarb": 125
                },
                "annual_turnover": "2,300,000 kr",
                "annual_production_value": "2,300,000 kr"
            },
            "foundation_year": 1925,
            "board": [
                {
                    "name": "disp. Holger Fernlund",
                    "role": "disp."
                },
                {
                    "name": "fru J. Fernlund",
                    "role": "fru"
                },
                {
                    "name": "kamrer Erik Zachrisson",
                    "role": "kamrer"
                }
            ]
        },
        "3": {
            "name": "M. Jönsson & Son",
            "location": "Eslöv",
            "business": "Vagn- och snickerifabrik",
            "products": "Tillverkar sportartiklar såsom bandy- och ishockeyklubbor, travsulky m. m. samt reservdelar till lantbruksmaskiner.",
            "contact": {
                "phone": "130",
                "postgiro": "71584"
            },
            "financials": {
                "employees": {
                    "industriarb": 15
                }
            },
            "foundation_year": 1889,
            "corporation_year": 1919,
            "owners": [
                "fabr. Alb. Jönsson"
            ]
        },
        "4": {
            "name": "P. Jönssons Skyffelfabrik AB.",
            "location": "Hälsingborg",
            "business": "Tillverkar spadar och skyfflar",
            "products": "Specialitet: s. k. skånska skyfflar.",
            "contact": {
                "phone": "10346",
                "postgiro": "30581"
            },
            "financials": {
                "capital": "120,000 kr",
                "employees": {
                    "industriarb": 12
                },
                "annual_turnover": "250,000 kr"
            },
            "foundation_year": 1888,
            "corporation_year": 1946,
            "director": "Nils Göthe"
        },
        "5": {
            "name": "Kabelfabriken Effekt",
            "location": "Smalandsstenar",
            "business": "Tillverkar spiralkablar",
            "products": "Tillverkar spiralkablar för cykelbelysningar vid fabrik i Smålandsstenar (Jönköp. l.).",
            "contact": {
                "telegraph": "Kåkå, Smalandsstenar",
                "phone": "166",
                "postgiro": "162302"
            },
            "financials": {
                "employees": {
                    "industriarb": 7
                },
                "annual_turnover": "100,000 kr"
            },
            "foundation_year": 1935,
            "director": "fabr. Thure Bengtsson"
        },
        "6": {
            "name": "Kaffe- & Kolonial AB.",
            "location": "Malmö",
            "business": "Marsipan- och syltfabrik",
            "products": "Tillverkar bakmassor för konditorier och bagerier samt sylter, marmelad, safter m. m. Varumärke: »Kå Kå».",
            "contact": {
                "kontor": "Per Weijersg. 3",
                "telegraph": "Kåkå, Malmö",
                "phone": "70250",
                "postgiro": "24597"
            },
            "financials": {
                "capital": "275,000 kr",
                "employees": {
                    "industriarb": 48
                },
                "annual_turnover": "2,000,000 kr"
            },
            "foundation_year": 1927,
            "board": [
                {
                    "name": "Fritz Möller",
                    "role": "Verkst. dir."
                },
                {
                    "name": "Rudolf Möller",
                    "role": "Disp."
                }
            ]
        },
        "7": {
            "name": "Kakelfabriks AB. i Karlskrona",
            "location": "Karlskrona",
            "business": "Tillverkar kakelugnar och spisar",
            "products": "Tillverkar kakelugnar och spisar, spiskakel och beklädnadsplattor.",
            "contact": {
                "telegraph": "Kakelfabriken, Karlskrona",
                "phone": "154",
                "postgiro": "30277"
            },
            "financials": {
                "capital": "441,500 kr",
                "employees": {
                    "industriarb": 120
                },
                "annual_turnover": "2,000,000 kr"
            },
            "foundation_year": 1884,
            "board": [
                {
                    "name": "v. konsul S. A. Liljevall",
                    "role": "v. konsul"
                },
                {
                    "name": "disp. Harald Lindström",
                    "role": "disp."
                },
                {
                    "name": "dr J. Swanlund",
                    "role": "dr."
                }
            ],
            "director": "Harald Lindström"
        },
        "8": {
            "name": "Kalkbränneri- & Kalkstens AB.",
            "location": "Stockholm",
            "business": "Kalkbruk",
            "products": "Tillverkar släckt och osläckt bränd kalk samt bryter rå kalksten.",
            "contact": {
                "phone": "272"
            },
            "foundation_year": null,
            "board": []
        }
    }
}