{
    "original": "Hammarstedt—Handel\n\nÄkti-kap.: 25,000 kr. Antal\nindustriarb.: 150. Tillv.-värde pr år: 1,200,000 kr.\n—- Firman etabl. 1879, bolag 1944.\n\nStyrelse: dir. Tor Hammargren (ordf.),\ndisp. Per Uno Hammargren.\n\nDisp,: Per Uno Hammargren.\n\nHammarstedts Mek. Verkstad,\nAB. Bröderna, Växjö.\n\nSe AB. Bröderna Hammarstedt, Mek.\nVerkstad, Växjö.\n\nAB. Hammerdals Liefabrik,\n\nHammerdal.\n\nTillverkar liar vid fabrik i Hammerdal\n(Jämtl. l.).\n\nTelefon: 18. — Akt.-kap.: 41,000 kr.\nAntal idustriarb.: 10. — Bolaget grundat\n1920.\n\nVerkst. dir.: Jonas Jonsson.\n\n* Hamnbyggnadsbyrån AB.,\n\nStockholm.\n\nByggnadsentreprenörfirma för\nhamnbyggnadsarbeten, brobyggnader samt\nhusbyggnader.\n\nHuvudkontor: Stockholm, Sveavägen\n25—27. Telegr.-adr.: Hamnbygge,\nStockholm. Telefon: 206060—63. Postgiro:\n51720, Avd.-kontor: Luleå, telefon: 3831;\nUddevalla, telefon: 11706.\n\nAkt.-kap.: 300,000 kr. Prod.-värde pr\når: 5,000,000 kr. — Bolaget grundat 1930.\n\nStyrelse: major Gunnar Sehiitz (ordf.),\ning. Axel Bristulf, adv. Gösta\nWenner-holm.\n\nVerkst. dir.: Gunnar Sehiitz.\n\növering.: Axel Bristulf.\n\nArbetschef: kapten Olle Rinman.\n\nKamrer: Folke Ifvarsson.\n\nAvd.-chef i Uddevalla: ing. Herman\nEnström.\n\nAB. Hampberedning, Visby.\n\nTillverkar tåga och blånor av hampa\nvid hampberedningsverk i Visby.\n\nPostadr.: Box 14, Visby. Telefon:\n104, 2271 o. 2412. Postgiro: 189978.\nEnsamförsälj.: Riksförbundet Lin och\nHampa, Stockholm, Valhallavägen 132,\ntelefon: 614068.\n\nAkt.-kap.: 150,000 kr. Antal\nindustriarb.: 120. Prod.-värde pr år: 1,500,000 kr.\n— Bolaget grundat 1941.\n\nStyrelse: major Fredr. Nyström (ordf.),\nlantbr. Ivar Hoppe, landstingsman\nEf-raim Larsson, dir. Gustaf Nelson,\nriks-dagsm. Per Svensson.\n\nVerkst. dir.: Fredr. Nyström.\n\nKamrer: Tor Bergström.\n\nHanaskogs Kalkbruk, Hanaskog.\n\nTillverkar jordbrukskalk och murkalk\nvid kalkbruk i Hanaskog (Kristianst. l.).\n\nTelefon: 14. Postgiro: 137091.\nEnsamförsäljare: Svenska Kalkförsäljnings AB.\n(Calcium), Malmö.\n\nAntal industriarb.: 20. Prod.-värde pr\når: 240,000 kr. — Tillverkningen började\n1872.\n\nÄgare: frih. Arvid De Geer.\n\n*\tHandels AB. Henrikssons\nBrandredskap, Stockholm.\n\nMek. verkstad vid Liljeholmen,\nStockholm. Tillverkar brandredskap såsom\nbrandsprutor, kemiska eldslackare,\nbrandarmatur, redskapskärror m. m.\nVarumärke: »Hebra». Firman försäljer även\növriga inom branschen förekommande\nredskap och tillbehör.\n\nKontor: Jakobsg. 14. Telegr.-adr.:\nSprutbolaget, Stockholm. Telefon: 207822\n—23, —24, —25. Postgiro: 3321.\n\nAkt.-kap.: 20,000 kr. Antal\nindustriarb.: 20. — Verksamheten grundad 1828.\n\nStyrelse: bankdir. Robert Sundvik\n(ordf.), dir. Olov Eriksson, kamrer Karl\nHansen.\n\nVerkst. dir.: Olov Eriksson.\n\nDriftsing.: Gustaf Henriksson.\n\n\"Handels AB. P. C. Jansson, Alster.\n\nSe AB. Alsters Industrier, Alster.\n\nHandels- o. Entreprenad AB. Fenja,\n\nStockholm.\n\nSyfabrik. Tillverkar skjortor, pyjamas\noch skyddsrockar. Varumärken: »Fenja»\no. »Derpe».\n\nKontor: Kungsgatan 36. Telegr.-adr.:\nFenja, Stockholm. Telefon: 100698 o.\n109933. Postgiro: 54426.\n\nAkt.-kap.: 50,000 kr. Antal\nindustriarb.: 30. Tillv.-värde pr år: 200,000 kr. —\nBolaget grundat 1932.\n\nVerkst. dir.: ing. Hugo Eneström.\n\n*\tHandels- &amp; Möbelindustribolaget,\n\nRörvik.\n\nTillverkar möbler vid fabrik i Rörvik\n(Jönköp. l.).\n\nTelefon: 6. Postgiro: 287027. — Antal\nindustriarb.: 10. Tillv.-värde pr år:\n100,000 kr. — Firman etabl. 1938, nuv.\nnamn 1945.\n\nÄgare o. chefer: fabr. Erhard\nAndersson, fabr. Wilhelm Andersson o. fabr.\nArtos Andersson.",
    "structured": {
        "firms": [
            {
                "name": "Hammarstedt—Handel",
                "financials": {
                    "capital": "25,000 kr",
                    "employees": {
                        "industriarb": 150
                    },
                    "annual_production_value": "1,200,000 kr"
                },
                "foundation_year": 1879,
                "corporation_year": 1944,
                "board": [
                    {
                        "name": "Tor Hammargren",
                        "role": "Ordinary Director"
                    },
                    {
                        "name": "Per Uno Hammargren",
                        "role": "Director"
                    }
                ]
            },
            {
                "name": "AB. Hammerdals Liefabrik",
                "location": "Hammerdal",
                "products": "Tillverkar liar vid fabrik i Hammerdal (Jämtl. l.)",
                "contact": {
                    "phone": [
                        "18"
                    ],
                    "postgiro": "N/A"
                },
                "financials": {
                    "capital": "41,000 kr",
                    "employees": {
                        "industriarb": 10
                    },
                    "annual_production_value": "N/A"
                },
                "foundation_year": 1920
            },
            {
                "name": "AB. Hamnbyggnadsbyrån",
                "location": "Stockholm",
                "business": "Byggnadsentreprenörfirma för hamnbyggnadsarbeten, brobyggnader samt husbyggnader",
                "contact": {
                    "office": "Sveavägen 25—27",
                    "telegraph": "Hamnbygge, Stockholm",
                    "phone": [
                        "206060—63"
                    ],
                    "postgiro": "51720",
                    "sales_offices": [
                        {
                            "location": "Luleå",
                            "phone": "3831"
                        },
                        {
                            "location": "Uddevalla",
                            "phone": "11706"
                        }
                    ]
                },
                "financials": {
                    "capital": "300,000 kr",
                    "annual_turnover": "5,000,000 kr"
                },
                "foundation_year": 1930,
                "board": [
                    {
                        "name": "Major Gunnar Sehiitz",
                        "role": "Ordinary Director"
                    },
                    {
                        "name": "Ing. Axel Bristulf",
                        "role": "Director"
                    },
                    {
                        "name": "Adv. Gösta Wenner-holm",
                        "role": "Director"
                    }
                ],
                "director": "Gunnar Sehiitz",
                "manager": "Gunnar Sehiitz",
                "sales_manager": "N/A"
            },
            {
                "name": "AB. Hampberedning",
                "location": "Visby",
                "products": "Tillverkar tåga och blånor av hampa vid hampberedningsverk i Visby.",
                "contact": {
                    "office": "Box 14, Visby",
                    "phone": [
                        "104",
                        "2271",
                        "2412"
                    ],
                    "postgiro": "189978"
                },
                "financials": {
                    "capital": "150,000 kr",
                    "employees": {
                        "industriarb": 120
                    },
                    "annual_production_value": "1,500,000 kr"
                },
                "foundation_year": 1941,
                "board": [
                    {
                        "name": "Major Fredr. Nyström",
                        "role": "Ordinary Director"
                    },
                    {
                        "name": "Lantbr. Ivar Hoppe",
                        "role": "Director"
                    },
                    {
                        "name": "Landstingsman Ef-raim Larsson",
                        "role": "Director"
                    },
                    {
                        "name": "Dir. Gustaf Nelson",
                        "role": "Director"
                    },
                    {
                        "name": "Riksdagsm. Per Svensson",
                        "role": "Director"
                    }
                ],
                "director": "Fredr. Nyström",
                "manager": "N/A",
                "sales_manager": "N/A"
            },
            {
                "name": "Handels AB. Henrikssons Brandredskap",
                "location": "Stockholm",
                "products": "Tillverkar brandredskap såsom brandsprutor, kemiska eldslackare, brandarmatur, redskapskärror m. m.",
                "contact": {
                    "office": "Jakobsg. 14",
                    "telegraph": "Sprutbolaget, Stockholm",
                    "phone": [
                        "207822—23",
                        "207824—25"
                    ],
                    "postgiro": "3321"
                },
                "financials": {
                    "capital": "20,000 kr",
                    "employees": {
                        "industriarb": 20
                    }
                },
                "foundation_year": 1828,
                "board": [
                    {
                        "name": "Bankdir. Robert Sundvik",
                        "role": "Ordinary Director"
                    },
                    {
                        "name": "Dir. Olov Eriksson",
                        "role": "Director"
                    },
                    {
                        "name": "Kamrer Karl Hansen",
                        "role": "Director"
                    }
                ],
                "director": "Olov Eriksson",
                "manager": "N/A",
                "sales_manager": "N/A"
            },
            {
                "name": "Handels- o. Entreprenad AB. Fenja",
                "location": "Stockholm",
                "products": "Tillverkar skjortor, pyjamas och skyddsrockar",
                "contact": {
                    "office": "Kungsgatan 36",
                    "telegraph": "Fenja, Stockholm",
                    "phone": [
                        "100698",
                        "109933"
                    ],
                    "postgiro": "54426"
                },
                "financials": {
                    "capital": "50,000 kr",
                    "employees": {
                        "industriarb": 30
                    },
                    "annual_production_value": "200,000 kr"
                },
                "foundation_year": 1932,
                "board": [
                    {
                        "name": "Ing. Hugo Eneström",
                        "role": "Ordinary Director"
                    }
                ],
                "director": "Hugo Eneström",
                "manager": "N/A",
                "sales_manager": "N/A"
            },
            {
                "name": "Handels- & Möbelindustribolaget",
                "location": "Rörvik",
                "products": "Tillverkar möbler",
                "contact": {
                    "phone": [
                        "6"
                    ],
                    "postgiro": "287027"
                },
                "financials": {
                    "capital": "N/A",
                    "employees": {
                        "industriarb": 10
                    },
                    "annual_production_value": "100,000 kr"
                },
                "foundation_year": 1938
            }
        ]
    }
}