{
    "original": "Lind—Lindberg\n\nIvar Linds Eftr. Sågbladsfabrik,\n\nTorshälla.\n\nTillverkar bandsågblad, handsågar,\nvedsågar och sticksågar, sicklingar samt\nfilklo var.\n\nTelefon: Eskilstuna 55144. Postgiro:\n•265335. — Antal industriarb.: 6.\nTillv.-värde pr år: 100,000 kr. — Firman etabl.\n1930.\n\nÄgare o. chefer: fabr. Helmer Swärd\no. fabr. Vidar Andersson.\n\n*J. Linds Snickerifabriks AB., Gimo.\n\nTillverkar byggnadssnickerier vid\nfabrik i Gimo (Uppsala l.).\n\nTelefon: 18. Postgiro: 13667. —\nAkt.-kap.: 45,000 kr. Antal industriarb.: 17.\nTillv.-värde pr år: 175,000 kr. — Firman\netabl. 1927, bolag 1944.\n\nStyrelse: fabr. Janne Lind (ordf.),\nverkm. Ernst Thornberg, kamrer Harald\nThornberg.\n\nVerkst. dir.: J. Lind.\n\nLindahl &amp; Co., Alvesta.\n\nSe Alvesta Glasbruk, Lindahl &amp; Oo.,\nAlvesta.\n\n*AB. A. Lindahls Fabriker,\n\nStockholm.\n\nKemisk-teknisk^ fabrik. Tillverkar\ntekniska och kosmetiska artiklar samt\nkon-fektyrer och näringsmedel.\n\nKontor o. ensamförsälj.: Alifabolaget\nAB., JSTybrog. 27. Postadr.: Stockholm 5.\nTelegr.-adr.: Alifabolaget, Stockholm.\nTelefon: 670400. Postgiro: 4000.\n\nAkt.-kap.: 200,000 kr. Antal\nindustriarb.: 60. — Firman etabl. 1902, bolag\n1932.\n\nStyrelse: ryttm. Erik Lindahl, disp.\nFrithiof Lindahl.\n\nVerkst. dir.: Erik Lindahl.\n\nDisp.: Frithiof Lindahl.\n\nFörsäljn.-chef: Arne Bjelkström.\n\nFabrikschef: ing. Sture H. U.\nGrönvall.\n\nLindbacka AB., Örebro.\n\nGummivarufabrik i Lindbacka, Örebro.\nTillverkar gummi klackar och -sulor samt\ngummiplattor. Varumärke: »Liba».\n\nTelegr.-adr.: Liba, Örebro. Telefon:\n19383. Postgiro: 161661. — Akt.-kap.:\n80,000 kr. Antal industriarb.: 22. —\nBolaget grundat 1938.\n\nStyrelse: disp. Lennart Jonsson, dir.\nOösta Åqvist, dir. Torsten Åqvist.\n\nVerkst. dir.: Gösta Åqvist.\n\nAB. Lindberg Strå- &amp; Filthatt-\n\nfabrik, Örebro.\n\nTillverkar dam- och barnhattar av strå\noch filt.\n\nHuvudkontor: Örebro. Telegr.-adr.:\nHattlindberg, Örebro. Telefon: 10467.\nPostgiro: 12606. Avd.-kontor: Stockholm,\nYasag. 15 o. 17, telefon: 114303;\nGöteborg, Drottningg. 30, telefon: 176460;\nMalmö, S. Förstadsg. 3, telefon: 14070.\n\nAkt.-kap.: 300,000 kr. Antal\nindustriarb.: 95. Tillv.-värde pr år: 1,000,000 kr.\n— Bolaget grundat 1913.\n\nStyrelse: disp. Levi Malm (ordf.), fru\nH. Béen, fru Lisa Lindberg.\n\nDisp.: Levi Malm.\n\nAvd.-chefer: i Stockholm: Josef\nDahlmark; i Göteborg: fröken Agda\nHögberg; i Malmö: Hugo Lundquist.\n\n* Lindbergs Tryckeri AB.,\n\nStockholm.\n\nBoktryckeri och bokbinderi. Utför bok-,\nillustrations-, broschyr- och\ntidskriftstryck, affärs- och blankettryck m. m.\n\nKontor: N. Smedjeg. 34. Telefon:\n232295. Postgiro: 52208. — Akt.-kap.:\n50,000 kr. Antal industriarb.: 73.\n\nFirman etabl. 1911, bolag 1921,\nomändrat 1935.\n\nStyrelse; bankdir. II. Axen (ordf.),\ndisp. I. Borg, disp. II. Söder.\n\nVerkst. direktörer: I. Borg o. H. Söder.\n\n*Cust. Lindberg, Värnamo\nByggnadssnickeri, Värnamo.\n\nSe Värnamo Byggnadssnickeri, Gust.\nLindberg, Värnamo.\n\n*Lindberg &amp; Co., Eiektrofirman\nAtermo, Göteborg.\n\nSe Eiektrofirman Atermo, Lindberg &amp;\nCo., Göteborg.\n\nLindbergs Mek. Verkstad, Storsjö.\n\nSe Bröderna Lindbergs Mek. Verkstad,\nStorsjö.\n\nH. Lindbergs Mek. Verkstad AB.,\n\nAlvesta.\n\nMek. verkstad och plåtslageri i Alvesta\n(Kronob. l.). Tillverkar smiden,\ntunnplåts- och massartiklar, rostfria arbeten\nför mejerier, bagerier och restauranter,\ndiskbänkar och tvättrännor, kylskåp,\nkyldiskar och kylrumsdörrar samt detaljer\ndärtill.\n\no*",
    "structured": {
        "firms": [
            {
                "name": "Ivar Linds Eftr. Sågbladsfabrik",
                "location": "Torshälla",
                "business": "Tillverkning av bandsågblad, handsågar, vedsågar, sticksågar, sicklingar och filklovar",
                "contact": {
                    "phone": [
                        "Eskilstuna 55144"
                    ],
                    "postgiro": "265335",
                    "factory_office": "Etablerad: 1930",
                    "owners": [
                        "fabr. Helmer Swärd",
                        "fabr. Vidar Andersson"
                    ]
                },
                "financials": {
                    "capital": "Ej tillgänglig",
                    "employees": {
                        "industriarb": 6
                    },
                    "annual_turnover": "100,000 kr",
                    "annual_production_value": "100,000 kr"
                },
                "foundation_year": 1930
            },
            {
                "name": "J. Linds Snickerifabriks AB.",
                "location": "Gimo",
                "business": "Tillverkning av byggnadssnickerier",
                "contact": {
                    "phone": [
                        "18"
                    ],
                    "postgiro": "13667",
                    "office": "Uppsala l.",
                    "board": [
                        {
                            "name": "fabr. Janne Lind",
                            "role": "ordf."
                        },
                        {
                            "name": "verkm. Ernst Thornberg",
                            "role": "kamrer"
                        },
                        {
                            "name": "kamrer Harald Thornberg",
                            "role": ""
                        }
                    ]
                },
                "financials": {
                    "capital": "45,000 kr",
                    "employees": {
                        "industriarb": 17
                    },
                    "annual_turnover": "175,000 kr",
                    "annual_production_value": "175,000 kr"
                },
                "foundation_year": 1927,
                "current_name_year": 1944
            },
            {
                "name": "AB. A. Lindahls Fabriker",
                "location": "Stockholm",
                "business": "Kemisk-teknisk fabrik",
                "contact": {
                    "phone": [
                        "670400"
                    ],
                    "postgiro": "4000",
                    "office": "Alifabolaget AB., JSTybrog. 27, Stockholm 5",
                    "board": [
                        {
                            "name": "ryttm. Erik Lindahl",
                            "role": "disp."
                        },
                        {
                            "name": "disp. Frithiof Lindahl",
                            "role": ""
                        },
                        {
                            "name": "",
                            "role": "frithiof Lindahl"
                        }
                    ],
                    "director": "Erik Lindahl",
                    "manager": "Erik Lindahl"
                },
                "financials": {
                    "capital": "200,000 kr",
                    "employees": {
                        "industriarb": 60
                    },
                    "annual_turnover": "Ej tillgänglig",
                    "annual_production_value": "Ej tillgänglig"
                },
                "foundation_year": 1902,
                "corporation_year": 1932
            },
            {
                "name": "Lindbacka AB.",
                "location": "Örebro",
                "business": "Tillverkning av gummi klackar och sulor samt gummiplattor",
                "contact": {
                    "phone": [
                        "19383"
                    ],
                    "postgiro": "161661",
                    "office": "Lindbacka, Örebro"
                },
                "financials": {
                    "capital": "80,000 kr",
                    "employees": {
                        "industriarb": 22
                    },
                    "annual_turnover": "Ej tillgänglig",
                    "annual_production_value": "Ej tillgänglig"
                },
                "foundation_year": 1938
            },
            {
                "name": "AB. Lindberg Strå- & Filthattfabrik",
                "location": "Örebro",
                "business": "Tillverkning av dam- och barnhattar av strå och filt",
                "contact": {
                    "phone": [
                        "10467"
                    ],
                    "postgiro": "12606",
                    "office": "Örebro",
                    "sales_offices": [
                        {
                            "location": "Stockholm",
                            "phone": "114303"
                        },
                        {
                            "location": "Göteborg",
                            "phone": "176460"
                        },
                        {
                            "location": "Malmö",
                            "phone": "14070"
                        }
                    ]
                },
                "financials": {
                    "capital": "300,000 kr",
                    "employees": {
                        "industriarb": 95
                    },
                    "annual_turnover": "1,000,000 kr",
                    "annual_production_value": "1,000,000 kr"
                },
                "foundation_year": 1913
            },
            {
                "name": "Lindbergs Tryckeri AB.",
                "location": "Stockholm",
                "business": "Boktryckeri och bokbinderi",
                "contact": {
                    "phone": [
                        "232295"
                    ],
                    "postgiro": "52208",
                    "office": "N. Smedjeg. 34"
                },
                "financials": {
                    "capital": "50,000 kr",
                    "employees": {
                        "industriarb": 73
                    }
                },
                "foundation_year": 1911,
                "corporation_year": 1921
            }
        ]
    }
}