{
    "original": "J önköping-\n\nr—J önsson\n\n^Jönköpings Vaddfabrik, C. Rydman\n\n&amp; Co., Jönköping.\n\nTillverkar täckvadd, limvadd och\nfönstervadd, förbandsvadd, tapetserarevadd,\naxelvadd, frisérbomull, tätningslist samt\ntäcken, madrasser och kuddar, flock och\ninläggssulor för skodon.\n\nTelefon: 226 o. 227. Postgiro: 10661.\n— Antal industriarb.: 40. Tillv.-värde pr\når: 550,000 kr. — Firman etabl. 1899.\n\nÄgare: fru I. Lindström o. fru I.\nLindstam.\n\nDisp.: Gunnar Landén.\n\n* Jönköpings och Vuicans\nTändsticksfabriks AB., Jönköping.\n\nTillverkar tändstickor, tomaskar och\ntändstickssplint vid fabriker i Jönköping,\nTidaholm, Västervik, Kalmar, Lidköping,\nMönsterås och Vetlanda.\n\nHuvudkontor: Jönköping.\nTelegr.-adr.: Matches, Jönköping. Telefon:\n»Tändsticksbolaget». Postgiro: 91399.\n\nEnsamförsäljare: för export: Svenska\nTändsticks AB., Jönköping; för Sverige:\nSvenska Tändsticksbolagets\nFörsäljnings-AB., Stockholm, V. Trädgårdsg. 15;\ntelefon: »Tändsticksbolaget».\n\nAkt.-kap.: 7,054,000 kr. Antal\nindustriarb.: 1,750.\n\nBolaget grundat 1903. Svenska\nTänd-sticks AB. äger bolagets samtliga\nstamaktier.\n\nStyrelse: f. d. riksantikvarie S. Ourman\n(ordf.), dir. Axel Brandin, dir. Torsten\nJung, civiling. F. G. Liljenroth, disp.\nVald. Lindahl.\n\nVerJcst. dir.: Torsten Jung.\n\nFabriksdisponenter: vid Jönköpings\nTändsticksfabrik: Torsten Jung; vid\nJönköpings Västra Tändsticksfabrik: Ernst\nA. Larsson; vid Vuicans\nTändsticksfabrik (Tidaholm): Vald. Lindahl; vid\nVästerviks Tändsticksfabrik: Eskil Ågren;\nvid Kalmar Tändsticksfabrik: E. Norén;\nvid Lidköpings Tändsticksfabrik: E. A.\nOlauson; vid Mönsterås\nTändsticksfabrik: Otto B. Olsson; vid Vetlanda\nTändsticksfabrik: Gösta Birgersson.\n\nJönköpings Vågfabriks AB.,\n\nJ önköping.\n\nTillverkar decimalvågar, taffel- och\nbalansvågar, skjutviktsvågar, barnvågar,\npersonvågar, paketvågar, gods- och\nbagagevågar, kranvågar, mejeri vågar,\nkreatursvågar, kör- och spårvågar m. fl.\n\nTelegr.-adr.. Vågar, Jönköping.\nTelefon: 1789. Postgiro: 11594. — Akt.-kap.:\n100,000 kr. Antal industriarb.: 20. —\nBolaget grundat 1918.\n\n21\n\nStyrelse: disp. Simon Larsson (ordf.),\nfru Margit Larsson.\n\nVerkst. dir..- Simon Larsson.\n\nJönsson &amp; Svensson, Skofabrik,\n\nFalkenberg.\n\nTillverkar sport- och arbetsskodon.\n\nTelefon: 377. Postgiro: 71882. —■\nAntal industriarb.: 60. — Firman etabl.\n1923.\n\nÄgare o. chef: fabr. Carl E. Jönsson.\n\n\"A. Jönsson &amp; Co., Trikå AB.,\n\nGöteborg.\n\nSe Ajco Trikåfabrik AB., Göteborg.\n\n\"And. Jönsson, Möbelfabrik,\n\nUlricehamn.\n\nTillverkar matrumsmöbler.\n\nTelefon: 110. Postgiro: 36565. —\nArb.-antal: 5. — Firman etabl. 1920.\n\nÄgare o. chef: fabr. Anders Jönsson.\n\nAB. Carl Jönsson, Tvål- &amp;\nParfymfabrik , Partille.\n\nKem. tekn. fabrik i Partille (Göteb. o.\nBohus l.). Tillverkar såpa, tvål och\ntvättpulver samt ljus. Varumärke: »Cejij».\n\nHuvudkontor: Partille. Telegr.-adr.:\nCeijipa, Partille. Telefon: 160 o. 310.\nPostgiro: 41284. Avd.-kontor: Göteborg,\nGötabergsg. 24, telefon: 167198.\n\nAkt.-kap.: 200,000 kr. Tillv.-värde pr\når: 1,000,000 kr. — Bolaget grundat 1936.\n\nVerkst. dir.: fröken R. Jönsson.\n\n*AB. Ernst O. Jönsson,\n\nHälsingborg.\n\nCykelfabrik. Tillverkar cyklar och\ndelar därtill. Märke: »Kärnan». Firman\n\ndriver även engroshandel med cykeldelar\nav främmande fabrikat.\n\nTelegr.-adr.: Ernsto, Hälsingborg.\nTelefon: 10727, 10737 o. 21287. Postgiro:\n14332.\n\nAkt.-kap.: 250,000 kr. Antal\nindustriarb.: 40. Tillv.-värde pr år: 1,250,000 kr.\n— Firman etabl. 1901, bolag 1922.\n\nStyrelse: dir. Ragnar Jönsson (ordf.),\nfil. dr E. K. Bruhn, fil. lic. Gunnar\nJönsson.\n\nVerJcst. dir.: Ragnar Jönsson.\nKontorschef: Gustav Larsson.\nFabrikschef: Gustav Johansson.\n\nL*",
    "structured": {
        "1": {
            "name": "Jönköpings Vaddfabrik, C. Rydman & Co.",
            "location": "Jönköping",
            "business": "Tillverkning av täckvadd, limvadd, fönstervadd, förbandsvadd, tapetserarevadd, axelvadd, frisérbomull, tätningslist samt tillverkning av täcken, madrasser och kuddar, flock och inläggssulor för skodon.",
            "products": "Produkter: täckvadd, limvadd, fönstervadd, förbandsvadd, tapetserarevadd, axelvadd, frisérbomull, tätningslist, täcken, madrasser och kuddar, flock, inläggssulor för skodon.",
            "contact": {
                "office": "Jönköping",
                "phone": [
                    "226",
                    "227"
                ],
                "postgiro": "10661",
                "head_office": "Jönköping",
                "telegraph": "",
                "factory_office": "",
                "factory_phone": ""
            },
            "financials": {
                "capital": "",
                "employees": {
                    "industriarb": 40
                },
                "annual_turnover": "550,000 kr",
                "annual_production_value": ""
            },
            "foundation_year": 1899,
            "owners": [
                "fru I. Lindström",
                "fru I. Lindstam"
            ],
            "director": ""
        },
        "2": {
            "name": "Jönköpings och Vuicans Tändsticksfabriks AB.",
            "location": "Jönköping",
            "business": "Tillverkning av tändstickor, tomaskar och tändstickssplint.",
            "products": "Produkter: tändstickor, tomaskar, tändstickssplint.",
            "contact": {
                "office": "Jönköping",
                "phone": [],
                "postgiro": "91399",
                "head_office": "Jönköping",
                "sales_offices": [
                    {
                        "location": "Sverige",
                        "phone": "Svenska Tändsticksbolagets Försäljnings-AB., Stockholm, V. Trädgårdsg. 15"
                    }
                ],
                "telegraph": "Matches",
                "factory_office": "",
                "factory_phone": ""
            },
            "financials": {
                "capital": "7,054,000 kr",
                "employees": {
                    "industriarb": 1750
                },
                "annual_turnover": "",
                "annual_production_value": ""
            },
            "corporation_year": 1903,
            "owners": [
                "Svenska Tändsticks AB."
            ],
            "board": [
                {
                    "name": "S. Ourman",
                    "role": "ordf."
                },
                {
                    "name": "Axel Brandin",
                    "role": "dir."
                },
                {
                    "name": "Torsten Jung",
                    "role": "dir."
                },
                {
                    "name": "F. G. Liljenroth",
                    "role": "civiling."
                },
                {
                    "name": "Vald. Lindahl",
                    "role": "disp."
                }
            ],
            "director": "Torsten Jung",
            "managing_director": "",
            "sales_manager": ""
        },
        "3": {
            "name": "Jönköpings Vågfabriks AB.",
            "location": "Jönköping",
            "business": "Tillverkning av decimalvågar, taffel- och balansvågar, skjutviktsvågar, barnvågar, personvågar, paketvågar, gods- och bagagevågar, kranvågar, mejeri vågar, kreatursvågar, kör- och spårvågar m. fl.",
            "contact": {
                "office": "Jönköping",
                "phone": [
                    "1789"
                ],
                "postgiro": "11594",
                "head_office": "Jönköping",
                "telegraph": "Vågar",
                "factory_office": "",
                "factory_phone": ""
            },
            "financials": {
                "capital": "100,000 kr",
                "employees": {
                    "industriarb": 20
                },
                "annual_turnover": "",
                "annual_production_value": ""
            },
            "foundation_year": 1918,
            "board": [
                {
                    "name": "Simon Larsson",
                    "role": "disp."
                },
                {
                    "name": "fru Margit Larsson",
                    "role": "ordf."
                }
            ],
            "director": "Simon Larsson"
        }
    }
}