{
    "original": "Elektriska—EleMrolux\n\n*\tElektriska Svetsnings AB. i\nStockholm, Stockholm.\n\nSe AB. Hammarbyverken, Stockholm.\n\n*AB. Elektro-Apparat, Göteborg.\n\nElektromek. verkstad i Alingsås.\nTillverkar elektr. värmeapparater, elektr.\nindustriugnar (märke: A.E.A.) för\nglödg-ning, ^ härdning, anlöpning, smältning,\ntorkning, lackering, emalj ering och\nvul-kanisering, elektr.\nstorköksvärmeappara-ter och bakugnar, manöverapparater för\nkraft och ljus, hög- och\nlågspänningsappa-rater, ljus- och scenregulatorer m. m.\n\nHuvudkontor: Göteborg, Kungsg. 56.\nTelegr.-adr.: Elektroapparat, Göteborg.\nTelefon: 133555. Postgiro: 40287.\nFabrikskontor: Alingsås, telefon: 366 o. 1230.\n\nAkt.-kap.: 200,000 kr. Antal\nindustriarb.: 75. Tillv.-värde pr år: 1,500,000 kr.\n— Bolaget, grundat 1916, övertog 1933\nBillman &amp; Co. AB., Partille.\n\nStyrelse: dir. Edvin Arnulf-Olsson,\ndir. Osvald Arnulf-Olsson.\n\nVerkst. dir.: E. Arnulf-Olsson.\n\nElektrodfabriken Kroma, Svenska,\n\nVänersborg.\n\nSe Svenska Elektrodfabriken Kroma,\nVänersborg.\n\n*\tElektrofirman A termo, Lindberg &amp;\nCo., Göteborg.\n\nTillverkar elektriska apparater såsom\nmotorskydd, nollspänningsbrytare,\nflottör-o. tryckströmbrytare, kontaktorer, aUtom.\nlikströmspådrag samt elstängsel.\nVarumärke: »Atermo».\n\nKontor: Postg. 30. Telefon: 111110 o.\n135992. Postgiro: 40312. Representanter:\nAB. Stohne-Verken, Stockholm,\nLind-tiagensg. 128, telefon: 520060; Kilian\nSvensson &amp; Son, Malmö, Erik\nDahl-bergsg. 26, telefon: 23850.\n\nAntal industriarb.: 26, — Firman etabl.\n1927.\n\nÄgare o. chef: ing. Per Lindberg.\n\nKamrer: Orvar Lindberg.\n\n*AB. Elektro-Cennel, Stockholm.\n\nElektromek. verkstad. Tillverkar elektr.\nvärmeapparater.\n\nKontor: Tunnelg. 19 A. Telegr.-adr.:\nElektrogennel, Stockholm. Telefon:\n112580 o. 100404. Postgiro: 19.\n\nAkt.-kap.: 150,000 kr. Antal\nindustriarb.: 20. — Bolaget, grundat 1942, har\n\növertagit Elektr. Industrifirman Ernst\nGennels rörelse, som etablerades 1920.\n\nStyrelse: bankdir. Herrman\nNachman-son (ordf.), greve G. A. Douglas, dir. Nils\nNachmanson,\n\nVerkst. dir.: Nils Nachmanson.\n\nAB. Elektrogjuteriet, Falkenberg.\n\nSe Gjuteribolaget Berggren &amp; Olsson,\nFalkenberg.\n\n*\tElektro-1 nvest, Stockholm.\n\nSe AB. Electro-Invest, Stockholm.\n\n*\tElektrokemiska AB., Boh us.\n\nElektrokemisk fabrik i Bohus (Älvsb. l.).\n\nTillverkar kaustikt kali och natron,\nsåväl kem. rent som tekniskt, flytande klor,\nvätgas, flytande kolsyra, saltsyra, såväl\nkem. ren som teknisk, järnklorid,\njärn-klorur, vätesuperoxid, natriumperborat,\nmetasilikat, ammoniumpersulfat, kiselgel\n(med och utan indikator), kristallsoda,\nkolsvavla, kopparoxidul, ferrum\nreduc-tum, svavelklorur, vattenglas (kali o.\nnatron), ren pottaska samt ett större antal\nkem. rena kemikalier,\nläkemedelskemikalier, konstvaxer, D.D.T.-produkter (medel\nmot skadeinsekter), alla för den\ngalva-niska industrien behövliga metall- och\ncyandubbelsalter m.m. Varumärke: EKA.\n\nTelegr.-adr.: Elektrokemiska, Göteborg.\nTelefon: Göteborg eller Surte,\n»Elektrokemiska». Postgiro: 8870. Avd.-kontor:\nStockholm, N. Mälarstrand 82, telefon:\n510349; Malmö, Lundav. 42, telefon:\n430400.\n\nAkt.-kap.: 1,700,000 kr. Antal\nindustriarb.: 525. Tillv.-värde pr år: 15,000,000\nkr. — Bolaget grundat 1895.\n\nStyrelse: dir. C. F. Tranchell (ordf.),\ndir. G. J. Fraenckel, dir. Per J.\nHemberg, adv. Torsten Setterberg, civiling.\nRyno Thelander.\n\nVerkst. dir.: R. Thelander.\n\növering.: Tage Nilsson.\n\nFörsäljn.- o. kontorschef: B. Rase.\n\n(Jfr annons före Varubenämningen.)\n\n*AB. Elektrolux, Stockholm.\n\nMek. verkstäder i Stockholm o. Motala.\n\nTillverkar: vid Stockholms fabriken :\ndammsugare, golvbonare, köksmaskiner,\naluminium- och zinkgjutgods, pressgods\nav formbara massor, elektriska\nsmåmoto-rer, omformare m. m.; vid\nMotalafabriken: kylapparater och kylskåp\n(helautomatiska), tunnplåtsarbeten såsom\nhyll-fack, skåp, bord och diskar,\narbetsbänkar, transport- och förrådslådor samt",
    "structured": {
        "1": {
            "name": "Elektriska Svetsnings AB. i Stockholm",
            "location": "Stockholm, Stockholm",
            "business": "Svetsning och elektriska apparater",
            "contact": {
                "office": "Göteborg, Kungsg. 56",
                "phone": [
                    "133555"
                ],
                "postgiro": "40287",
                "factory_office": "Alingsås",
                "factory_phone": "366 o. 1230"
            },
            "financials": {
                "capital": "200,000 kr",
                "employees": {
                    "industriarb": 75
                },
                "annual_turnover": "1,500,000 kr"
            },
            "foundation_year": 1916,
            "predecessor": "Billman & Co. AB., Partille",
            "board": [
                {
                    "name": "Edvin Arnulf-Olsson",
                    "role": "dir."
                },
                {
                    "name": "Osvald Arnulf-Olsson",
                    "role": "dir."
                }
            ]
        },
        "2": {
            "name": "Elektro-Apparat, Göteborg",
            "location": "Göteborg",
            "business": "Elektriska värmeapparater och fundament",
            "board": [
                {
                    "name": "Edvin Arnulf-Olsson",
                    "role": "dir."
                },
                {
                    "name": "Osvald Arnulf-Olsson",
                    "role": "dir."
                }
            ]
        },
        "3": {
            "name": "Elektromek. verkstad i Alingsås",
            "location": "Alingsås",
            "products": "elektr. värmeapparater, elektr. industriugnar (märke: A.E.A.) för glödg-ning, ^ härdning, anlöpning, smältning, torkning, lackering, emalj ering och vul-kanisering, elektr. storköksvärmeappara-ter och bakugnar, manöverapparater för kraft och ljus, hög- och lågspänningsappa-rater, ljus- och scenregulatorer m. m.",
            "contact": {
                "office": "Göteborg, Kungsg. 56",
                "phone": [
                    "133555"
                ],
                "postgiro": "40287",
                "factory_phone": "366 o. 1230"
            },
            "financials": {
                "capital": "200,000 kr",
                "employees": {
                    "industriarb": 75
                },
                "annual_turnover": "1,500,000 kr"
            },
            "foundation_year": 1916,
            "predecessor": "Billman & Co. AB., Partille",
            "board": [
                {
                    "name": "Edvin Arnulf-Olsson",
                    "role": "dir."
                },
                {
                    "name": "Osvald Arnulf-Olsson",
                    "role": "dir."
                }
            ]
        },
        "4": {
            "name": "Elektrofirman A termo, Lindberg & Co., Göteborg",
            "location": "Göteborg",
            "business": "Tillverkar elektriska apparater såsom motorskydd, nollspänningsbrytare, flottör-o. tryckströmbrytare, kontaktorer, aUtom. likströmspådrag samt elstängsel",
            "contact": {
                "office": "Postg. 30",
                "phone": [
                    "111110",
                    "135992"
                ],
                "postgiro": "40312"
            },
            "financials": {
                "employees": {
                    "industriarb": 26
                }
            },
            "current_name_year": 1927,
            "owners": [
                "ing. Per Lindberg"
            ]
        },
        "5": {
            "name": "AB. Elektro-Cennel, Stockholm",
            "location": "Stockholm",
            "business": "Elektromek. verkstad. Tillverkar elektr. värmeapparater",
            "contact": {
                "office": "Tunnelg. 19 A",
                "phone": [
                    "112580",
                    "100404"
                ],
                "postgiro": "19"
            },
            "financials": {
                "capital": "150,000 kr",
                "employees": {
                    "industriarb": 20
                }
            },
            "foundation_year": 1942,
            "predecessor": "Elektr. Industrifirman Ernst Gennels"
        },
        "6": {
            "name": "AB. Elektrogjuteriet, Falkenberg"
        },
        "7": {
            "name": "Elektrokemiska AB., Boh us",
            "location": "Bohus (Älvsb. l.)",
            "business": "Elektrokemisk fabrik. Tillverkar kemikalier och produkter för den galva-niska industrien",
            "contact": {
                "telegraph": "Elektrokemiska, Göteborg",
                "phone": "Göteborg eller Surte, »Elektrokemiska»",
                "postgiro": "8870"
            },
            "financials": {
                "capital": "1,700,000 kr",
                "employees": {
                    "industriarb": 525
                },
                "annual_turnover": "15,000,000 kr"
            },
            "foundation_year": 1895,
            "board": [
                {
                    "name": "C. F. Tranchell",
                    "role": "dir."
                },
                {
                    "name": "G. J. Fraenckel",
                    "role": "dir."
                }
            ],
            "director": "R. Thelander",
            "managing_director": "R. Thelander",
            "sales_manager": "Tage Nilsson",
            "manager": "B. Rase"
        },
        "8": {
            "name": "AB. Elektrolux, Stockholm",
            "location": "Stockholm, Motala",
            "business": "Mek. verkstäder. Tillverkar dammsugare, golvbonare, köksmaskiner, kylapparater, kylskåp, aluminium- och zinkgjutgods",
            "products": "omformare m. m.",
            "board": [
                {
                    "name": "Dir."
                }
            ]
        }
    }
}