{
    "original": "Göteborg\n\nStyrelse: dir.-assist. Carl-Axel\nLinde-löw, disp. Axel Lundell, fru V. Svahn.\n\nVerkst. dir.: Axel Lundell.\n\nKamrer: Joh. Bergqvist.\n\nDir.-assist.: Carl-Axel Lindelöw.\n\nGöteborgs Emballagefabrik, Martin\nFolkjern, Göteborg.\n\nLåd- och snickerifabrik. Tillverkar\nlåd-ämnen och lådor, byggnadssnickerier och\ninredningar.\n\nKontor: S:t Erikstorg 1. Telegr.-adr.:\nGötabox, Göteborg. Telefon: 118072 o.\n130815, Postgiro: 42941. — Antal\nindustriarb.: 27. Tillv.-värde pr är: 600,000\nkr. — Firman etabl. 1931.\n\nÄgare: ing. Martin Folkjerns sterbhus.\n\nGöteborgs Färg- &amp; Fernissfabrik,\n\nGöteborg.\n\nTillverkar lack-, olje-, cellulosa- och\nsyntetiska färger, fernissor,\ncellulosa-polerlack, rostskydds-, maskin- och\nredskapsfärger, spackelfärger, kitt m. m.\nVarumärken: »Cynol», »Kron»,\n»Kompassen» och »Rimsa».\n\nKontor: Hisingsbacka; postadr.: Box\n842, Göteborg 8. Telegr.-adr.:\nFärgfabriken, Göteborg. Telefon: 221414. Postgiro:\n42911. — Antal industriarb.: 45. —\nFirman etabl. 1900.\n\nÄgare o. chef: disp. Ragnar Lind.\n\nAB. Göteborgs\nGalvaniserings-fabrik, Göteborg,\n\nGalvaniseringsfabrik i Stillestorp,\nLundby (Göteb. o. Bohus l.). Tillverkar\nsåsom specialitet plåtkärl samt\ngalvani-serade, svetsade plåtarbeten; utför\ngalva-nisering av järneffekter på varm väg.\n\nKontor: Göteborg, Herkulesg. 1;\npostadr.: Göteborg 8. Telegr.-adr.: Galvan,\nGöteborg. Telefon: 220954.\n\nAkt.-kap.: 50,000 kr. Antal\nindustriarb.: 50. — Firman etabl. 1911, bolag\n1925. Bolaget äges av Stockholms\nGalvaniseringsfabrik AB., Liljeholmen.\n\nStyrelse: grossh. Erik Kistner (ordf.),\nfru Siri Collett, herr Åke Collett, dir.\nGustaf Sundberg, disp. Yngve Westberg.\n\nDisp.: Yngve Westberg (Sthlm).\n\nPlatschef: Nils Adner.\n\n*AB. Göteborgs Gamla\nTrätoffelfabrik, Göteborg.\n\nTillverkar trätofflor och\nträbotten-kängor.\n\nKontor: Brog. 3. Telefon: 137164.\nPostgiro: 25588. — Akt.-kap.: 10,000 kr.\nArb.-antal: 5. Tillv.-värde pr år: 70,000\nkr. — Firman etabl. 1887, bolag 1943.\n\nStyrelse o. disp.: Magnus Wiberg.\n\n*AB. Göteborgs Culdlistfabrik,\n\nGöteborg.\n\nTillverkar ram- och tapetlister samt\nspeglar vid fabrik i Göteborg, ävensom\nträlister vid listhyvleri i Gustafs\n(Kopparb. l.). Bolaget idkar jämväl handel\nmed papp, spegelglas, geringsmaskiner\noch sågar.\n\nHuvudkontor: Göteborg; postadr.:\nGöteborg 5. Telegr.-adr.: Guldlist, Göteborg.\nTelefon: 161839 o. 182557. Postgiro:\n40791. Avd.-kontor: Stockholm, Skepparg.\n37; telefon: 623695.\n\nAkt.-kap.: 150,000 kr. Antal\nindustriarb.: 50. — Firman etabl. 1897, bolag\n1905.\n\nStyrelse o. disp.: Hans Colberg.\n\n*AB. Göteborgs\nHartsoljefärg-Fabrik, Göteborg.\n\nKem.-tekn. fabrik och färgfabrik.\nTillverkar oljefärger, slamfärerer, fernissor,\nvagnssmörja, läderfett, insektsmedel, kitt,\nspecialoljor för bilar såsom\novansmörj-ning, rostolja, bromsvätska, polish,\nkaross-beck, chassilack m. m.\n\nKontor: Underåsbro, Sofierovägen.\nTelegr.-adr.: Hartsoljefärg, Göteborg.\nTelefon: 161790. Postgiro: 40696.\n\nAkt.-kap.: 140,000 kr. Arb.-antal: 10.\nTillv.-värde pr år: 400,000 kr. — Firman\netabl. 1888, bolag 1908.\n\nStyrelse o. verkst. dir.: ing. B. Werner.\n\nGöteborgs Hattfabrik, Göteborg.\n\nTillverkar damhattar och mössor.\n\nKontor: Friggag. 6 o. 8. Telefon:\n153465. Postgiro: 42522. — Antal\nindustriarb.: 24. Tillv.-värde pr år: 400,000\nkr. — Firman etabl. 1918.\n\nÄgare o. chef: fabr. David Johansson.\n\nDisp.: Rune Johansson.\n\nGöteborgs Kamgarnsspinnerl AB.,\n\nGöteborg.\n\nTillverkar strump-, stick- och\nväv-garner.\n\nKontor: Gårda. Telegr.-adr.:\nCarlströms, Göteborg. Telefon: 187155.\nPostgiro: 40484.\n\nAkt.-kap.: 2,700,000 kr. Antal\nindustriarb.: 280. Tillv.-värde pr år: 7,000,000 kr.\n— Bolaget grundat 1896.",
    "structured": {
        "firms": [
            {
                "name": "Göteborgs Emballagefabrik, Martin Folkjern",
                "location": "Göteborg",
                "business": "Låd- och snickerifabrik. Tillverkar låd-ämnen och lådor, byggnadssnickerier och inredningar.",
                "contact": {
                    "office": "S:t Erikstorg 1",
                    "phone": [
                        "118072",
                        "130815"
                    ],
                    "postgiro": "42941",
                    "telegraph": "Götabox, Göteborg"
                },
                "financials": {
                    "employees": {
                        "industriarb": 27
                    },
                    "annual_production_value": "600,000 kr"
                },
                "foundation_year": 1931,
                "owners": [
                    "ing. Martin Folkjerns sterbhus"
                ]
            },
            {
                "name": "Göteborgs Färg- & Fernissfabrik",
                "location": "Göteborg",
                "business": "Tillverkar lack-, olje-, cellulosa- och syntetiska färger, fernissor, cellulosa-polerlack, rostskydds-, maskin- och redskapsfärger, spackelfärger, kitt m. m.",
                "contact": {
                    "office": "Hisingsbacka",
                    "postgiro": "42911",
                    "telegraph": "Färgfabriken, Göteborg"
                },
                "financials": {
                    "employees": {
                        "industriarb": 45
                    }
                },
                "foundation_year": 1900,
                "owners": [
                    "disp. Ragnar Lind"
                ]
            },
            {
                "name": "AB. Göteborgs Galvaniserings-fabrik",
                "location": "Göteborg",
                "business": "Galvaniseringsfabrik i Stillestorp, Lundby (Göteb. o. Bohus l.). Tillverkar såsom specialitet plåtkärl samt galvani-serade, svetsade plåtarbeten; utför galva-nisering av järneffekter på varm väg.",
                "contact": {
                    "office": "Göteborg, Herkulesg. 1",
                    "postgiro": "42911",
                    "telegraph": "Galvan, Göteborg"
                },
                "financials": {
                    "capital": "50,000 kr",
                    "employees": {
                        "industriarb": 50
                    }
                },
                "foundation_year": 1911,
                "corporation_year": 1925,
                "owners": [
                    "Stockholms Galvaniseringsfabrik AB., Liljeholmen"
                ]
            },
            {
                "name": "AB. Göteborgs Gamla Trätoffelfabrik",
                "location": "Göteborg",
                "business": "Tillverkar trätofflor och träbotten-kängor.",
                "contact": {
                    "office": "Brog. 3",
                    "postgiro": "25588"
                },
                "financials": {
                    "capital": "10,000 kr",
                    "annual_turnover": "70,000 kr"
                },
                "foundation_year": 1887,
                "corporation_year": 1943,
                "owners": [
                    "Magnus Wiberg"
                ]
            },
            {
                "name": "AB. Göteborgs Culdlistfabrik",
                "location": "Göteborg",
                "business": "Tillverkar ram- och tapetlister samt speglar vid fabrik i Göteborg, ävensom trälister vid listhyvleri i Gustafs (Kopparb. l.). Bolaget idkar jämväl handel med papp, spegelglas, geringsmaskiner och sågar.",
                "contact": {
                    "office": "Göteborg",
                    "postgiro": "40791",
                    "additional_offices": [
                        {
                            "location": "Stockholm",
                            "phone": "623695"
                        }
                    ]
                },
                "financials": {
                    "capital": "150,000 kr",
                    "employees": {
                        "industriarb": 50
                    }
                },
                "foundation_year": 1897,
                "corporation_year": 1905,
                "owners": [
                    "Hans Colberg"
                ]
            },
            {
                "name": "AB. Göteborgs Hartsoljefärg-Fabrik",
                "location": "Göteborg",
                "business": "Kem.-tekn. fabrik och färgfabrik. Tillverkar oljefärger, slamfärerer, fernissor, vagnssmörja, läderfett, insektsmedel, kitt, specialoljor för bilar såsom ovansmörj-ning, rostolja, bromsvätska, polish, kaross-beck, chassilack m. m.",
                "contact": {
                    "office": "Underåsbro, Sofierovägen",
                    "postgiro": "40696"
                },
                "financials": {
                    "capital": "140,000 kr",
                    "employees": {
                        "industriarb": 10
                    },
                    "annual_production_value": "400,000 kr"
                },
                "foundation_year": 1888,
                "corporation_year": 1908,
                "owners": [
                    "ing. B. Werner"
                ]
            },
            {
                "name": "Göteborgs Hattfabrik",
                "location": "Göteborg",
                "business": "Tillverkar damhattar och mössor.",
                "contact": {
                    "office": "Friggag. 6 o. 8",
                    "postgiro": "42522"
                },
                "financials": {
                    "employees": {
                        "industriarb": 24
                    },
                    "annual_production_value": "400,000 kr"
                },
                "foundation_year": 1918,
                "owners": [
                    "fabr. David Johansson"
                ]
            },
            {
                "name": "Göteborgs Kamgarnsspinnerl AB.",
                "location": "Göteborg",
                "business": "Tillverkar strump-, stick- och väv-garner.",
                "contact": {
                    "office": "Gårda",
                    "telegraph": "Carlströms, Göteborg",
                    "postgiro": "40484"
                },
                "financials": {
                    "capital": "2,700,000 kr",
                    "employees": {
                        "industriarb": 280
                    },
                    "annual_production_value": "7,000,000 kr"
                },
                "foundation_year": 1896
            }
        ]
    }
}