{
    "original": "Uddevalla— Ulax\n\nUddevalla Gjuter! och Mek.\nVerkstads AB., Uddevalla.\n\nMek. verkstad, tackjärns- och\nmetailgjuteri. Tillverkar plåt- och\njärnkonstruktioner, maskinarbeten, pressmiden,\ntackjärnsgjutgods, kajpållare,\nkokillhär-dade roster samt metallgjutgods.\nSpecialiteter: styrmaskiner och rodersmiden för\nfiskefartyg.\n\nTelefon: 10068 o. 10168. Postgiro:\n132260.\n\nAkt.-kap.: 52,000 kr. Antal\nindustriarb.: 100. Tillv.-värde pr år: 700,000 kr.\n— Firman etabl. 1921, bolag 1936.\n\nVerkst. dir.: Ivar Thordén.\n\nV. verkst. dir.: ing. Georg R. Nilson.\n\nDriftsing.: Gunnar Wikström.\n\nKamrer: Eric Carlson.\n\n\"Uddevalla Nya Tunnfabrik AB.,\n\nUddevalla.\n\nTillverkar tunnor och laggkärl.\nSpecialitet: tunnor för sill och annan\nfiskförpackning.\n\nTelegr.-adr.: Tunnfabriken, Uddevalla.\nTelefon: 10055. Postgiro: 10255.\n\nAkt.-kap.: 50,000 kr. Antal\nindustriarb.: 50. Tillv.-värde pr år: 1,200,000 kr.\n\nBolaget grundat 1889 under namn\nUddevalla Tunnfabrik och Trävaru AB.,\nombildat med nuv. namn 1935.\n\nStyrelse: med. lic. Folke Malmquist,\nv. konsul Gösta Malmquist.\n\nVerkst. dir.: Gösta Malmquist.\n\n\"Uddevalla Snäckskalsbankar,\n\nUddevalla.\n\nSnäckskalsgruvor med förädlingsverk.\nBryter och förädlar snäckskal (kolsyrad\nkalk) till höns- och kycklingfoder.\n\nTelefon: 10705. Postgiro: 30035. —\nArb.-antal: 10. — Firman etabl. 1919.\n\nÄgare o. chef: fabr. Erik G. Norlin.\n\nUddevallavarvet AB., Uddevalla.\n\nSkeppsvarv och mek. verkstad. Utför\nnybyggnader och reparationer.\n\nTelegr.-adr. o. telefon:\n»Uddevallavarvet». Postgiro: 298264. — Akt.-kap.:\n5,000,000 kr. — Bolaget grundat 1945.\n\nStyrelse: bankdir. Halfdan Lugner\n(ordf.), grossh. Arvid Högström, typograf\nAxel Johansson, dir. Erik Norberg, dir.\nRobert Schwartzman, disp. Erland\nSjun-nesson, skeppsred. Gustaf Thordén.\n\nVerkst. dir.: Erik Norberg.\n\nTekn. dir.: Helge Hagelin.\n\nKamrer; Bengt Ryding.\n\nVarvsing.: Stellan Trollen.\n\nDriftsing.: Henning Westman.\n\nUddnäs Cjuteri &amp; Verkstads AB.,\n\nStockholm.\n\nMetall- och tackjärnsgjuteri i Staket\n(Stockholms l.). Tillverkar legerat\ngjnt-gods för höga temperatur- och\ntryckpå-känningar.\n\nKontor: Stockholm, Jutas Backe 1.\nTelefon: 119616. Postgiro: 155383.\n\nAkt.-kap.: 100,000 kr. Antal\nindustriarb.: 15. — Bolaget grundat 1916.\n\nStyrelse: e. o. hovrättsnot. R.\nSundblom (ordf.), fil. kand. C.-G. Gentele,\ning. Tom Lindberg.\n\nVerkst. dir..- Rafael Sundblom.\n\n\"AB. Uddnäs Kemiska Fabriker,\n\nStockholm.\n\nKem. tekn. fabrik i Norrköping.\nTillverkar natronvattenglas, kalivattenglas\nsamt vattenglas för syrafasta murningar.\n\nKontor: Stockholm, Jutas Backe 1.\nTelefon: 119616. Postgiro: 2075.\n\nAkt.-kap.: 50,000 kr. Arb.-antal: 5.\nTillv.-värde pr år: 200,000 kr. — Firman\netabl. 1892, bolag 1916.\n\nStyrelse: ing. Tom Lindberg, e. o.\nhovrättsnot. R. Sundblom.\n\nVerkst. dir.: Tom Lindberg.\n\n\"AB. Ugerups Tegelbruk,\n\nMalmö.\n\nTillverkar gult fasadtegel, lättegel och\nf lamtegel vid tegelbruk i Gärds Köp inge\n(Kristianst. l.).\n\nKontor o. ensamförsälj.: Malmö Grus\nAB., Malmö, Baltzarsg. 25. Telegr.-adr.:\nUgerupsbruk, Malmö. Telefon: 25234.\nPostgiro: 39597.\n\nAkt.-kap.: 42,000 kr. Antal\nindustriarb.: 24. Årstillv.: 2 milj. st. tegelvaror.\n— Tegelbruket anlagt under 1890-talet,\nbolag 1937.\n\nStyrelse o. verkst. dir.: disp. Sam.\nNilsson.\n\nTegelmäst.: Edvin Rundkvist.\n\n\"Uhr &amp; Son, Industri AB.,\n\nMotala.\n\nSe Industri AB. Uhr &amp; Son, Motala.\n\n\"AB. Ulax, Motala.\n\nMjölkfilterfabrik vid Ekön (Östergötl.\n1.). Tillverkar mjölkfilter av kem. renad\nbomull samt förbandsvadd.\n\nTelegr.-adr.: Ulax, Motala. Telefon:\n165. Postgiro: 11377.\n\nAkt.-kap.: 300,000 kr. Antal\nindustriarb.: 30. — Firman grundad 1902, bolag\n1911.\n\n735*",
    "structured": {
        "SwedishFirms": {
            "1": {
                "name": "Uddevalla Gjuter! och Mek. Verkstads AB.",
                "location": "Uddevalla",
                "business": "Mek. verkstad, tackjärns- och metailgjuteri. Tillverkar plåt- och järnkonstruktioner, maskinarbeten, pressmiden, tackjärnsgjutgods, kajpållare, kokillhär-dade roster samt metallgjutgods. Specialiteter: styrmaskiner och rodersmiden för fiskefartyg.",
                "contact": {
                    "phone": [
                        "10068",
                        "10168"
                    ],
                    "postgiro": "132260"
                },
                "financials": {
                    "capital": "52,000 kr",
                    "employees": {
                        "industriarb": 100
                    },
                    "annual_turnover": "700,000 kr"
                },
                "foundation_year": 1921,
                "corporation_year": 1936,
                "director": "Ivar Thordén",
                "managing_director": "Ing. Georg R. Nilson",
                "sales_manager": "Gunnar Wikström",
                "manager": "Eric Carlson"
            },
            "2": {
                "name": "Uddevalla Nya Tunnfabrik AB.",
                "location": "Uddevalla",
                "business": "Tillverkar tunnor och laggkärl. Specialitet: tunnor för sill och annan fiskförpackning.",
                "contact": {
                    "phone": "10055",
                    "postgiro": "10255"
                },
                "financials": {
                    "capital": "50,000 kr",
                    "employees": {
                        "industriarb": 50
                    },
                    "annual_turnover": "1,200,000 kr"
                },
                "foundation_year": 1889,
                "current_name_year": 1935,
                "board": [
                    {
                        "name": "Med. Lic. Folke Malmquist",
                        "role": null
                    },
                    {
                        "name": "V. Konsul Gösta Malmquist",
                        "role": null
                    }
                ],
                "director": "Gösta Malmquist"
            },
            "3": {
                "name": "Uddevalla Snäckskalsbankar",
                "location": "Uddevalla",
                "business": "Snäckskalsgruvor med förädlingsverk. Bryter och förädlar snäckskal (kolsyrad kalk) till höns- och kycklingfoder.",
                "contact": {
                    "phone": "10705",
                    "postgiro": "30035"
                },
                "employees": 10,
                "director": "Fabr. Erik G. Norlin"
            },
            "4": {
                "name": "Uddevallavarvet AB.",
                "location": "Uddevalla",
                "business": "Skeppsvarv och mek. verkstad. Utför nybyggnader och reparationer.",
                "contact": {
                    "phone": null,
                    "postgiro": "298264"
                },
                "financials": {
                    "capital": "5,000,000 kr"
                },
                "corporation_year": 1945,
                "board": [
                    {
                        "name": "Bankdir. Halfdan Lugner",
                        "role": "ordf."
                    },
                    {
                        "name": "Grossh. Arvid Högström",
                        "role": null
                    },
                    {
                        "name": "Typograf Axel Johansson",
                        "role": null
                    },
                    {
                        "name": "Dir. Erik Norberg",
                        "role": null
                    },
                    {
                        "name": "Dir. Robert Schwartzman",
                        "role": "disp."
                    },
                    {
                        "name": "Disp. Erland Sjunnesson",
                        "role": null
                    },
                    {
                        "name": "Skeppsred. Gustaf Thordén",
                        "role": null
                    }
                ],
                "director": "Erik Norberg",
                "manager": "Bengt Ryding",
                "sales_manager": "Stellan Trollen",
                "managing_director": "Henning Westman"
            },
            "5": {
                "name": "Uddnäs Gjuteri & Verkstads AB.",
                "location": "Stockholm",
                "business": "Metall- och tackjärnsgjuteri i Staket (Stockholms l.). Tillverkar legerat gjutgods för höga temperatur- och tryckpåkänningar.",
                "contact": {
                    "phone": "119616",
                    "postgiro": "155383"
                },
                "financials": {
                    "capital": "100,000 kr",
                    "employees": {
                        "industriarb": 15
                    }
                },
                "foundation_year": 1916,
                "board": [
                    {
                        "name": "E. o. Hovrättsnot. R. Sundblom",
                        "role": "ordf."
                    },
                    {
                        "name": "Fil. Kand. C.-G. Gentele",
                        "role": null
                    },
                    {
                        "name": "Ing. Tom Lindberg",
                        "role": null
                    }
                ],
                "director": "Rafael Sundblom"
            },
            "6": {
                "name": "AB. Uddnäs Kemiska Fabriker",
                "location": "Stockholm",
                "business": "Kem. tekn. fabrik i Norrköping. Tillverkar natronvattenglas, kalivattenglas samt vattenglas för syrafasta murningar.",
                "contact": {
                    "phone": "119616",
                    "postgiro": "2075"
                },
                "financials": {
                    "capital": "50,000 kr",
                    "employees": 5,
                    "annual_turnover": "200,000 kr"
                },
                "foundation_year": 1892,
                "corporation_year": 1916,
                "board": [
                    {
                        "name": "Ing. Tom Lindberg",
                        "role": null
                    },
                    {
                        "name": "E. o. Hovrättsnot. R. Sundblom",
                        "role": null
                    }
                ],
                "director": "Tom Lindberg"
            },
            "7": {
                "name": "AB. Ugerups Tegelbruk",
                "location": "Malmö",
                "business": "Tillverkar gult fasadtegel, lättegel och flamtegel vid tegelbruk i Gärds Köpinge (Kristianst. l.).",
                "contact": {
                    "phone": "25234",
                    "postgiro": "39597"
                },
                "financials": {
                    "capital": "42,000 kr",
                    "employees": {
                        "industriarb": 24
                    }
                },
                "annual_production_value": "2 milj. st. tegelvaror",
                "corporation_year": 1937,
                "director": "Disp. Sam. Nilsson",
                "sales_manager": "Edvin Rundkvist"
            },
            "8": {
                "name": "AB. Ulax",
                "location": "Motala",
                "business": "Mjölkfilterfabrik vid Ekön (Östergötl. l.). Tillverkar mjölkfilter av kem. renad bomull samt förbandsvadd.",
                "contact": {
                    "phone": "165",
                    "postgiro": "11377"
                },
                "financials": {
                    "capital": "300,000 kr",
                    "employees": 30
                },
                "foundation_year": 1902,
                "corporation_year": 1911
            }
        }
    }
}