{
    "original": "Gustafsfors—Gustafson\n\ndir. Hugo Edstam, dir. G. Osvald, dir.\nErnst Persson.\n\nVerkst. dir.: ing. Hjalmar Olson.\n\nKamrer: Arvid Ericson.\n\nFörsäljningen: hushållsporslin: R.\nSun-din; värme- o. sanitetstekn. avd.: H.\nWollrik, Karl Forslund o. Gunnar\nLindeberg.\n\nInköp: E. Bodelsson.\n\n*\tGust af stors Fabrikers AB.y\n\nBillingsfors.\n\nPappersbruk och sågverk vid\nSkåpafors samt kraftstation vid Krokfors\n(båda i Älvsb. l.). Tillverkar sulfat- och\nkraftpapper samt sågade trävaror.\n\nKontor: Billingsfors. Telegr.-adr.:\nGustfors, Vänersborg. Telefon:\nBengtsfors 170. Postgiro: 7843.\n\nAkt.-kap.: 1,500,000 kr. Antal\nindustriarb.: 230. Årstillv.: 9,000 ton\nkraftpapper, 1,600 stds sågade trävaror. —\nBolaget, grundat 1873, äges av AB.\nBillings-fors-Långed.\n\nStyrelse: disp. Gösta Ryding (ordf.),\ndir. Eric Collin, disp. Marcus Rosendahl.\n\nVerkst. dir.: Marcus Rosendahl.\n\nIntendent o. försäljn.-chef: Viking\nBlakstad.\n\nDriftschef i Skåpafors: förvalt. Paul\nNilsson.\n\nGustafsviks Torrdocka, Härnäsand.\n\nSe AB. Mohögs Mek. Verkstad,\nSköns-mon.\n\n*\tGustafsson &amp; Anderssons Varvs AB.,\n\nLidingö.\n\nVarv och mek. verkstad. Utför\nnybyggnader och reparationer av båtar upp\ntill 40 m:s längd samt tillverkar\nmarinmotorer upp till 130 hkr. Varumärke:\n»Bog-Båt».\n\nKontorsadr.: Lidingö 2. Telegr.-adr.:\nBogboat, Stockholm. Telefon:\nStockholm 655074 o. 655150. Postgiro: 131835.\n\nAkt.-kap.: 100,000 kr. Antal\nindustriarb.: 50. Tillv.-värde pr år: 600,000 kr.\n— Firman etabl. 1905, bolag 1942.\n\nStyrelse: fabr. Anders Gustafsson\n(ordf.), ing. Tage Boghammar, fru Signe\nHultman.\n\nVerkst. dir.: Tage Boghammar.\n\nKamrer: Eric Hultman.\n\n*\tGustafson &amp; Ljungqvist,\nPianofabriks AB., Norrköping.\n\nSe Pianofabriks AB. Gustafson &amp;\nLjungqvist, Norrköping.\n\nIB\n\nAB. Gustafsson &amp; Söners\nSkeppsvarv, Landskrona.\n\nUtför nybyggnader av träfartyg\nspeciellt fiskefartyg samt\nfartygsreparationer.\n\nTelegr.-adr.: Gustafssons varv,\nLandskrona. Telefon: 987 o. 2082.\n\nAkt.-kap.: 51,500 kr. Antal\nindustriarb.: 35. Prod.-värde pr år: 275,000 kr.\n— Firman etabl. 1922, bolag 1931.\n\nStyrelse: disp. Gustaf Gustafson (ordf.),\nänkefru H. Gustafsson, skeppsbyggm.\nMartin Gustafsson.\n\nVerkst. dir.: Gustaf Gustafson.\n\n*Ch. Gustafssons Skofabrik,\n\nMunkaljungby.\n\nTillverkar skodon vid fabrik i\nMunkaljungby (Kristianst. l.). Specialiteter:\nsportpjäxor och sandaler.\n\nTelefon: 105. Postgiro: 74752.\n\nAntal industriarb.: 35. Tillv.-värde pr\når: 450,000 kr. — Firman etabl. 1918.\n\nÄgare o. chef : fabr. Charles Gustafsson.\n\nE. Gustafsons Gravyranstalt &amp; Mek.\nVerkstad, Stockholm.\n\nUtför gravyr i stål, metall, guld,\nsilver m. m., maskingravyr och gradeTingar\nsamt tillverkar form-, stans- och\nbakelitverktyg.\n\nKontor: Bryggarg. 6 A. Telefon:\n213762 o. 106112. Postgiro: 4016. —\nAntal industriarb.: 15. Tillv.-värde pr år:\n170,000 kr. — Firman etabl. 1923.\n\nÄgare o. chef: fabr. Elof Gustafsson.\n\nKamrer: Åke Hedén.\n\nAB. Einar Gustafsson, Blyberg.\n\nSågverk, hyvleri och trähusfabrik i\nBlyberg (Kopparb. l.). Tillverkar sågade\noch hyvlade trävaror samt\nmonterings-färdiga trähus. Varumärke: »EGA-hus».\n\nTelegr.-adr.: Egahus, Blyberg.\nTelefon: 13 o. 14. Postgiro: 145088. —\nAkt.-kap.: 140,000 kr. Antal industriarb.: 75.\nÅrstillv.: 1,000 stds trävaror. — Firman\netabl. 1936, bolag 1944.\n\nVerkst. dir.: Gösta Gustafsson.\n\nKontorschef: Bertil Gustafsson.\n\nCideon Gustafson, Handen.\n\nTräemballagefabrik. Tillverkar\nemballage av björkplywood såsom varulådor\noch -korgar, tårtaskar och -skåp, tvätt-,\noch mangellådor m. m. samt skyltställ vid\n\nfabrik i Handen (Stockholms l.). .\n$*",
    "structured": {
        "1": {
            "name": "Gustafstors Fabrikers AB",
            "location": "Billingsfors",
            "business": "Pappersbruk och sågverk",
            "products": "Tillverkar sulfat- och kraftpapper samt sågade trävaror",
            "contact": {
                "office": "Billingsfors",
                "phone": [
                    "Bengtsfors 170"
                ],
                "telegraph": "Gustfors, Vänersborg",
                "postgiro": "7843"
            },
            "financials": {
                "capital": "1,500,000 kr",
                "employees": {
                    "industriarb": 230
                },
                "annual_turnover": "Not available",
                "annual_production_value": "9,000 ton kraftpapper, 1,600 stds sågade trävaror"
            },
            "foundation_year": 1873,
            "predecessor": "AB. Billingsfors-Långed",
            "board": [
                {
                    "name": "disp. Gösta Ryding",
                    "role": "ordf."
                },
                {
                    "name": "dir. Eric Collin",
                    "role": "Not available"
                },
                {
                    "name": "disp. Marcus Rosendahl",
                    "role": "Not available"
                }
            ],
            "owners": [
                "AB. Billings-fors-Långed"
            ],
            "director": "Marcus Rosendahl",
            "managing_director": "Not available",
            "sales_manager": "Viking Blakstad",
            "manager": "Paul Nilsson"
        },
        "2": {
            "name": "Gustafsson & Anderssons Varvs AB",
            "location": "Lidingö",
            "business": "Varv och mek. verkstad",
            "products": "Utför nybyggnader och reparationer av båtar samt tillverkar marinmotorer",
            "contact": {
                "office": "Lidingö 2",
                "phone": [
                    "Stockholm 655074",
                    "Stockholm 655150"
                ],
                "telegraph": "Bogboat, Stockholm",
                "postgiro": "131835"
            },
            "financials": {
                "capital": "100,000 kr",
                "employees": {
                    "industriarb": 50
                },
                "annual_turnover": "600,000 kr",
                "annual_production_value": "Not available"
            },
            "foundation_year": 1905,
            "corporation_year": 1942,
            "owner": "Not available",
            "manager": "Tage Boghammar",
            "board": [
                {
                    "name": "fabr. Anders Gustafsson",
                    "role": "ordf."
                },
                {
                    "name": "ing. Tage Boghammar",
                    "role": "Not available"
                },
                {
                    "name": "fru Signe Hultman",
                    "role": "Not available"
                }
            ]
        },
        "3": {
            "name": "Gustafson & Söners Skeppsvarv",
            "location": "Landskrona",
            "business": "Nybyggnader av träfartyg samt fartygsreparationer",
            "products": "Not available",
            "contact": {
                "telegraph": "Gustafssons varv, Landskrona",
                "phone": [
                    "987",
                    "2082"
                ],
                "postgiro": "Not available"
            },
            "financials": {
                "capital": "51,500 kr",
                "employees": {
                    "industriarb": 35
                },
                "annual_turnover": "275,000 kr",
                "annual_production_value": "Not available"
            },
            "foundation_year": 1922,
            "corporation_year": 1931,
            "board": [
                {
                    "name": "disp. Gustaf Gustafson",
                    "role": "ordf."
                },
                {
                    "name": "änkefru H. Gustafsson",
                    "role": "Not available"
                },
                {
                    "name": "skeppsbyggm. Martin Gustafsson",
                    "role": "Not available"
                }
            ],
            "manager": "Gustaf Gustafson"
        },
        "4": {
            "name": "Ch. Gustafssons Skofabrik",
            "location": "Munkaljungby",
            "business": "Tillverkar skodon",
            "products": "Sportpjäxor och sandaler",
            "contact": {
                "phone": [
                    "105"
                ],
                "postgiro": "74752"
            },
            "financials": {
                "annual_turnover": "450,000 kr",
                "annual_production_value": "Not available"
            },
            "foundation_year": 1918,
            "manager": "Charles Gustafsson"
        },
        "5": {
            "name": "E. Gustafsons Gravyranstalt & Mek. Verkstad",
            "location": "Stockholm",
            "business": "Utför gravyr i stål, metall, guld, silver m. m.",
            "products": "Maskingravyr, gradetingsar samt tillverkar form-, stans- och bakelitverktyg",
            "contact": {
                "office": "Bryggarg. 6 A",
                "phone": [
                    "213762",
                    "106112"
                ],
                "postgiro": "4016"
            },
            "financials": {
                "employees": {
                    "industriarb": 15
                },
                "annual_turnover": "170,000 kr",
                "annual_production_value": "Not available"
            },
            "foundation_year": 1923,
            "manager": "Elof Gustafsson",
            "contact_person": "Åke Hedén"
        },
        "6": {
            "name": "AB. Einar Gustafsson",
            "location": "Blyberg",
            "business": "Sågverk, hyvleri och trähusfabrik",
            "products": "Tillverkar sågade och hyvlade trävaror samt monterings-färdiga trähus",
            "contact": {
                "telegraph": "Egahus, Blyberg",
                "phone": [
                    "13",
                    "14"
                ],
                "postgiro": "145088"
            },
            "financials": {
                "capital": "140,000 kr",
                "employees": {
                    "industriarb": 75
                },
                "annual_turnover": "Not available",
                "annual_production_value": "1,000 stds trävaror"
            },
            "foundation_year": 1936,
            "corporation_year": 1944,
            "manager": "Gösta Gustafsson",
            "contact_person": "Bertil Gustafsson"
        },
        "7": {
            "name": "Cideon Gustafson",
            "location": "Handen",
            "business": "Träemballagefabrik",
            "products": "Tillverkar emballage av björkplywood såsom varulådor och -korgar, tårtaskar och -skåp",
            "contact": {
                "phone": [
                    "Not available"
                ],
                "postgiro": "74752"
            },
            "financials": {
                "annual_turnover": "Not available",
                "annual_production_value": "Not available"
            },
            "foundation_year": "Not available",
            "manager": "Not available",
            "contact_person": "Not available"
        }
    }
}