{
    "original": "O Ijeraffinaderi—O Isson\n\n\"Oljeraffinaderi AB. Zonen, Malmö.\n\nTillverkar färger, kitt, tjära samt kem.\ntekniska preparat. Bolaget driver jämväl\nengroshandel med smörjoljor, smörjfett,\ntorra färger, tran m. m.\n\nKontor: Industrihamnen. Telegr.-adr.:\nZonen, Malmö. Telefon: 71800. Postgiro:\n38179.\n\nAkt.-kap.: 260,000 kr. Antal\nindustriarb.: 15. — Firman grundad 1918.\n\nStyrelse: disp. A. J:son Ekholm\n(ordf.), prokurist Einar Eriksson,\nbygg-mäst. Olof Larsson.\n\nDisp.: A. J:son Ekholm.\n\nIvar Olausson &amp; Co., Hakefjordens\nKonservfabrik, Klädesholmen.\n\nSe Hakefjordens Konservfabrik, Ivar\nOlausson &amp; Co., Klädesholmen.\n\n*Oijeslagerl AB., Svenska, Göteborg.\nSe Svenska Oljeslageri AB., Göteborg.\n\n*AB. Olléns Tröskmaskinfabrik,\n\nFlen.\n\nMek. verkstad i Flen (Södermanl. l.).\nTillverkar självrensande tröskverk,\nklö-verfrönötare och sädesharpor.\n\nTelegr.-adr.: Tröskollén, Flen. Telefon:\n»Olléns». Postgiro: 143600.\n\nAkt.-kap.: 260,000 kr. Antal\nindustriarb.: 82. Tillv.-värde pr år: 1,450,000 kr.\n— Firman etabl. 1912, bolag 1924.\n\n*\tStyrelse: dir. Erik Gillberg (ordf.),\ndir. Gottfrid Asplund, disp. Sven\nWal-lenborg.\n\nVerkst. dir.: Sven Wallenborg.\n\n*\tO lotsson &amp; Nilsson, Nya Snickeri,\nfabriken, Laholm.\n\nSe Nya Snickerifabriken, Olofsson &amp;\nNilsson, Laholm.\n\n*Eric M. Olofsson, Möbelfabrik,\n\nKungsbacka.\n\nTillverkar kompletteringsmöbler.\nTelefon: 91. — Arb.-antal: 6. —\nFirman etabl. 1922.\n\nÄgare o. chef: fabr. Eric M. Olofsson.\n\n*\tOlof ströms Bruk, Olofström.\n\nSe Svenska Stålpressnings AB.\nOlof-ström, Olofström.\n\n*Olovsfors Bruk, Nordmaling.\n\nSe Nordmalings Ångsågs AB.,\nNordmaling.\n\n561*\n\nAB. Olo-verken, Hallsberg.\n\nMek. verkstad i Hallsberg (Örebro l.).\nTillverkar värmepannor.\n\nTelefon: 283. Postgiro: 175033. —\nAkt.-kap.: 105,500 kr. An tal industriarb.:\n25. Tillv.-värde pr år: 500,000 kr. —\nBolaget grundat 1941.\n\nVerkst. dir.: Oscar Ohlsson.\nDriftsing..- Bertil Ohlsson.\nKamrer: Bertil Hallberg.\n\n* Julius Oiséns Litografiska Anstalt,\n\nStockholm.\n\nUtför litografiskt tryck.\nKontor: Upplandsg. 17. Telefon:\n300872, 300379 o. 300879. Postgiro: 2914.\n— Antal industriarb.: 40. Tillv.-värde pr\når: 800,000 kr. — Firman etabl. 1918.\nÄgare o. chef: fabr. Julius Olsén.\n\n*T. Oisens Fabriks AB.,\n\nStockholm.\n\nKem.-teknisk fabrik. Tillverkar oljor\noch fettsmörjor för impregnering av läder\noch skodon, skokräm, textilkräm för\nputs-ning av tygskor samt bonvax,\nmetallputs-medel och smörjoljor. Varumärken:\n»Col-lan», »Glansing», »King», »Juvel» o.\n»Copin». Bolaget driver även handel med\nindustriförnödenheter och färger.\n\nKontor: Norrmalmstorg 4.\nTelegr.-adr.: Tolsen, Stockholm. Telefon: 208633.\nPostgiro: tekn. avd.: 2447; oljeavd.:\n156491. — Akt.-kap.: 50,000 kr.\nArb.-antal: 10. Omsättn.-värde pr år: 400,000\nkr.\n\nFirman etabl. 1880, bolag 1912 under\nnamn AB. Collan-Olje-Fabriken, T. Oisen,\nnuv. namn 1938.\n\nStyrelse o. verkst. dir.: Wolmar\nSjögren.\n\n*Qlsfors Trikåfabrik, Hultafors.\nSe AB. T. H. Lapidus, Borås.\n\nOlsson &amp; Co., Plåtförädlingsbolaget,\n\nVärnamo.\n\nSe Plåtförädlingsbolaget Olsson &amp; Co.,\nVärnamo.\n\n*AB. Olssons Mössfabrik, Boras.\n\nMöss- och pälsvarufabrik. Tillverkar\nherr-, dam- och barnmössor, pressade\nfilt-och strådamhattar, baskermössor samt\ndampälsar, pälsmössor och pälsbaretter.\nSpecialiteter: sportmössor och dampälsar.\nVarunamn: »Obo» o. »Borini». Bolaget\ndriver jämväl engrosförsäljning av\nherrhattar och pälsskinn.",
    "structured": {
        "firms": [
            {
                "name": "Oljeraffinaderi AB",
                "location": "Malmö",
                "business": "Tillverkar färger, kitt, tjära samt kem. tekniska preparat. Driver även engroshandel med smörjoljor, smörjfett, torra färger, tran m. m.",
                "contact": {
                    "office": "Industrihamnen",
                    "phone": [
                        "71800"
                    ],
                    "postgiro": "38179",
                    "telegraph": "Zonen, Malmö"
                },
                "financials": {
                    "capital": "260,000 kr",
                    "employees": {
                        "industriarb": 15
                    },
                    "annual_turnover": null,
                    "annual_production_value": null
                },
                "foundation_year": 1918,
                "board": [
                    {
                        "name": "A. J:son Ekholm",
                        "role": "ordf."
                    },
                    {
                        "name": "Einar Eriksson",
                        "role": "prokurist"
                    },
                    {
                        "name": "Olof Larsson",
                        "role": "bygg-mäst"
                    }
                ],
                "director": "A. J:son Ekholm"
            },
            {
                "name": "AB. Olléns Tröskmaskinfabrik",
                "location": "Flen",
                "business": "Mek. verkstad som tillverkar självrensande tröskverk, klöverfrönötare och sädesharpor.",
                "contact": {
                    "office": "Flen (Södermanl. l.)",
                    "phone": [
                        "Olléns"
                    ],
                    "postgiro": "143600",
                    "telegraph": "Tröskollén, Flen"
                },
                "financials": {
                    "capital": "260,000 kr",
                    "employees": {
                        "industriarb": 82
                    },
                    "annual_turnover": "1,450,000 kr",
                    "annual_production_value": null
                },
                "foundation_year": 1912,
                "corporation_year": 1924,
                "board": [
                    {
                        "name": "Erik Gillberg",
                        "role": "ordf."
                    },
                    {
                        "name": "Gottfrid Asplund",
                        "role": "dir."
                    },
                    {
                        "name": "Sven Wallenborg",
                        "role": "disp."
                    }
                ],
                "director": "Sven Wallenborg"
            },
            {
                "name": "Eric M. Olofsson, Möbelfabrik",
                "location": "Kungsbacka",
                "business": "Tillverkar kompletteringsmöbler.",
                "contact": {
                    "phone": [
                        "91"
                    ]
                },
                "financials": {
                    "employees": {
                        "arb.-antal": 6
                    }
                },
                "foundation_year": 1922,
                "director": "Eric M. Olofsson"
            },
            {
                "name": "AB. Olo-verken",
                "location": "Hallsberg",
                "business": "Mek. verkstad som tillverkar värmepannor.",
                "contact": {
                    "phone": [
                        "283"
                    ],
                    "postgiro": "175033"
                },
                "financials": {
                    "capital": "105,500 kr",
                    "employees": {
                        "industriarb": 25
                    },
                    "annual_turnover": "500,000 kr",
                    "annual_production_value": null
                },
                "foundation_year": 1941,
                "board": [
                    {
                        "name": "Oscar Ohlsson",
                        "role": "Verkst. dir."
                    },
                    {
                        "name": "Bertil Ohlsson",
                        "role": "Driftsing."
                    },
                    {
                        "name": "Bertil Hallberg",
                        "role": "Kamrer"
                    }
                ]
            },
            {
                "name": "Julius Oiséns Litografiska Anstalt",
                "location": "Stockholm",
                "business": "Utför litografiskt tryck.",
                "contact": {
                    "office": "Upplandsg. 17",
                    "phone": [
                        "300872",
                        "300379",
                        "300879"
                    ],
                    "postgiro": "2914"
                },
                "financials": {
                    "employees": {
                        "industriarb": 40
                    },
                    "annual_turnover": "800,000 kr",
                    "annual_production_value": null
                },
                "foundation_year": 1918,
                "director": "Julius Olsén"
            },
            {
                "name": "T. Oisens Fabriks AB.",
                "location": "Stockholm",
                "business": "Kem.-teknisk fabrik som tillverkar oljor och fettsmörjor för impregnering av läder och skodon, skokräm, textilkräm för putsning av tygskor samt bonvax, metallputs-medel och smörjoljor.",
                "contact": {
                    "office": "Norrmalmstorg 4",
                    "phone": [
                        "208633"
                    ],
                    "postgiro": "tekn. avd.: 2447; oljeavd.: 156491"
                },
                "financials": {
                    "capital": "50,000 kr",
                    "employees": {
                        "arb.-antal": 10
                    },
                    "annual_turnover": "400,000 kr",
                    "annual_production_value": null
                },
                "foundation_year": 1880,
                "corporation_year": 1912,
                "director": "Wolmar Sjögren"
            },
            {
                "name": "AB. Olssons Mössfabrik",
                "location": "Boras",
                "business": "Möss- och pälsvarufabrik som tillverkar herr-, dam- och barnmössor, pressade filt-och strådamhattar, baskermössor samt dampälsar, pälsmössor och pälsbaretter.",
                "contact": {
                    "phone": null
                },
                "director": null
            }
        ]
    }
}