{
    "original": "Mekaniska—Mercer\n\n*AB. Mekaniska Stickeriet I Malmö,\n\nMalmö.\n\nTrikåfabrik. Tillverkar dam-, herr-,\nbarn- och babytrikåvaror, blusar och\nsportskjortor, handskfoder, disk- och\nskurdukar, kaffepåsar m. m. Varumärke:\n»Mestic».\n\nKontor: Fabriksg. 10. Telegr.-adr.:\nMestic, Malmö. Telefon: 18500 o. 23468.\nPostgiro: 37943.\n\nAkt.-kap.: 60,000 kr. Antal\nindustriarb.: 75. Tillv.-värde pr år: 500,000 kr.\n— Firman etabl. 1913, bolag 1939.\n\nStyrelse: bankdir. August Nilsson\n(ordf.), adv. Eric Rappe, dir. Sten Sylvan.\n\nVerkst.- dir.: Sten Sylvan.\n\n*Mekano, Hälsingborg.\nSe Verkstads AB. Mekano, Hälsingborg.\n\nAB. A. Melins Börsfabrik,\n\nAnderstorp.\n\nTillverkar portmonnäer, plånböcker,\nsmålandsbörsar, portföljer och väskor,\nherr- och dambälten vid lädervarufabrik\ni Anderstorp (Jönköp. l.).\n\nTelefon: 55 o. 95. Postgiro: 70113. —\nAkt.-kap.: 20,000 kr. Antal industriarb.:\n40. — Firman etabl. 1886, bolag 1933.\n\nDisp.: Adolf Melin.\n\n*Melinders Skofabrik, Bröderna,\n\nMjällom.\n\nSe Bröderna Melinders Skofabrik,\nMjällom.\n\n\"Gustaf Melins AB., Göteborg.\n\nPartibokbinderi, album-, portfölj- och\nkontorsboksfabrik, bibel- och\npsalmboksförlag. Tillverkar album, biblar och\npsalmböcker, kontorsböcker,\nlösbladsböc-ker, samlingspärmar och kartonger;\nutför bindning i massupplagor.\n\nHuvudkontor: Göteborg, Lasarettsg. 4\no. 6. Telegr.-adr.: Albumfabriken,\nGöteborg. Telefon: »Esselte». Postgiro: 41207.\nAvd.-kontor: Stockholm, Drottningg. 20.\nTelefon: 104902 o. 104906.\n\nFirman etabl. 1886, bolag 1913.\nBolaget är anslutet till Esseltes\nGöteborgsindustrier AB., Göteborg.\n\nStyrelse o. verkst. dir.: disp. Nils J.\nÅhlund.\n\nAB. J. Melin &amp; Söner,\n\nÅkersberga.\n\nReseffektfabrik i Åkersberga (Sthlms\n1.). Tillverkar kappsäckar, portföljer och\nresväskor.\n\nKontor: Åkersberga. Telefon: 27.\nPostgiro: 9566. — Akt.-kap.: 75,000 kr.\nAntal industriarb.: 60. Tillv.-värde pr år: *\n700,000 kr. — Firman etabl. 1905, bolag\n1934.\n\nStyrelse: verkm. Alfred Lundqvist\n(ordf.), dir. Arvid Melin, fru Karin\nMelin,\n\nVerkst. dir.: Arvid Melin.\n\nMellersta Sveriges Linodlareförening\n\nu. p. a., Kristinehamn.\n\nSe Linberedningen, Kristinehamn.\n\nMerna, AB. Metallmanufaktur,\n\nLidköping.\n\nMetallfabrik och försilvringsverk.\nTillverkar servisbestick av nysilver och\nrostfritt stål, ävensom brickor, fat samt andra\ngalanterivaror i nysilver.\n\nTelegr.-adr.: Mema, Lidköping.\nTelefon: 22125. Postgiro: 32783.\n\nAkt.-kap.: 165,200 kr. Antal\nindustriarb.: 100. Tillv.-värde pr år: 1,300,000 kr.\n\n—\tBolaget grundat 1911, ombildat 1921.\n\nStyrelse: dir. Gunnar W. Anderson\n\n(ordf.), disp. Sven Ericsson, herr Åke\nRoslund.\n\nDisp.: Sven Ericsson.\n\nMepe, Holm &amp; Hoppe, Stockholm.\n\nMetallvarufabrik och mek. verkstad vid\nAspudden, Stockholm. Tillverkar\nbyggnadsbeslag, verktyg samt kinematografisk\nmateriel och pneumatiska apparater.\n\nTelegr.-adr.: Mepemetal, Stockholm.\nTelefon: 454664. Postgiro: 59194. —\nAntal industriarb.: 30. Tillv.-värde pr år:\n500,000 kr. — Firman etabl. 1930.\n\nÄgare o. chefer: ing. Hans Holm o.\ning. Nils Hoppe.\n\nAB. Mercer, Borås.\n\nTrikåfabrik. Tillverkar herrstrumpor.\nVarumärke: »Mercer».\n\nTelefon: 19069. Postgiro: 131545. Repr.\ni Norrköping: G. A. Gustafson, S:t\nOlofsg. 78 A, telefon: 27868.\n\nAkt.-kap.: 20,000 kr. Antal\nindustriarb.: 40. Tillv.-värde pr år: 500,000 kr.\n\n—\tFirman etabl. 1937.\n\nVerkst. dir.: Erik Ohlsson.\n\n",
    "structured": {
        "1": {
            "name": "Mekaniska—Mercer AB. Mekaniska Stickeriet I Malmö",
            "location": "Malmö",
            "business": "Trikåfabrik",
            "products": "Tillverkar dam-, herr-, barn- och babytrikåvaror, blusar och sportskjortor, handskfoder, disk- och skurdukar, kaffepåsar m. m. Varumärke: »Mestic».",
            "contact": {
                "office": "Fabriksg. 10",
                "phone": [
                    "18500",
                    "23468"
                ],
                "postgiro": "37943",
                "telegraph": "Mestic, Malmö",
                "factory_office": "N/A",
                "factory_phone": "N/A"
            },
            "financials": {
                "capital": "60,000 kr",
                "employees": {
                    "industriarb": 75
                },
                "annual_turnover": "500,000 kr",
                "annual_production_value": "N/A"
            },
            "foundation_year": 1913,
            "corporation_year": 1939,
            "board": [
                {
                    "name": "August Nilsson",
                    "role": "bankdir"
                },
                {
                    "name": "Eric Rappe",
                    "role": "adv"
                },
                {
                    "name": "Sten Sylvan",
                    "role": "dir"
                }
            ],
            "manager": "N/A"
        },
        "2": {
            "name": "AB. A. Melins Börsfabrik",
            "location": "Anderstorp",
            "business": "Tillverkar portmonnäer, plånböcker, smålandsbörsar, portföljer och väskor, herr- och dambälten vid lädervarufabrik",
            "products": "N/A",
            "contact": {
                "office": "N/A",
                "phone": [
                    "55",
                    "95"
                ],
                "postgiro": "70113",
                "telegraph": "N/A",
                "factory_office": "N/A",
                "factory_phone": "N/A"
            },
            "financials": {
                "capital": "20,000 kr",
                "employees": {
                    "industriarb": 40
                },
                "annual_turnover": "N/A",
                "annual_production_value": "N/A"
            },
            "foundation_year": 1886,
            "corporation_year": 1933,
            "board": [
                {
                    "name": "Adolf Melin",
                    "role": "disp"
                }
            ],
            "manager": "N/A"
        },
        "3": {
            "name": "Gustaf Melins AB.",
            "location": "Göteborg",
            "business": "Partibokbinderi, album-, portfölj- och kontorsboksfabrik, bibel- och psalmboksförlag",
            "products": "Tillverkar album, biblar och psalmböcker, kontorsböcker, lösbladsböcker, samlingspärmar och kartonger; utför bindning i massupplagor.",
            "contact": {
                "office": "Lasarettsg. 4 o. 6",
                "phone": [
                    "N/A"
                ],
                "postgiro": "41207",
                "telegraph": "Albumfabriken, Göteborg",
                "factory_office": "N/A",
                "factory_phone": "N/A"
            },
            "financials": {
                "capital": "N/A",
                "employees": {
                    "industriarb": "N/A"
                },
                "annual_turnover": "N/A",
                "annual_production_value": "N/A"
            },
            "foundation_year": 1886,
            "corporation_year": 1913,
            "board": [
                {
                    "name": "Nils J. Åhlund",
                    "role": "disp"
                }
            ],
            "manager": "N/A"
        },
        "4": {
            "name": "AB. J. Melin & Söner",
            "location": "Åkersberga",
            "business": "Reseffektfabrik",
            "products": "Tillverkar kappsäckar, portföljer och resväskor.",
            "contact": {
                "office": "Åkersberga",
                "phone": [
                    "27"
                ],
                "postgiro": "9566",
                "telegraph": "N/A",
                "factory_office": "N/A",
                "factory_phone": "N/A"
            },
            "financials": {
                "capital": "75,000 kr",
                "employees": {
                    "industriarb": 60
                },
                "annual_turnover": "700,000 kr",
                "annual_production_value": "N/A"
            },
            "foundation_year": 1905,
            "corporation_year": 1934,
            "board": [
                {
                    "name": "Alfred Lundqvist",
                    "role": "verkm"
                },
                {
                    "name": "Arvid Melin",
                    "role": "dir"
                },
                {
                    "name": "Karin Melin",
                    "role": "fru"
                }
            ],
            "manager": "N/A"
        },
        "5": {
            "name": "Merna, AB. Metallmanufaktur",
            "location": "Lidköping",
            "business": "Metallfabrik och försilvringsverk",
            "products": "Tillverkar servisbestick av nysilver och rostfritt stål, ävensom brickor, fat samt andra galanterivaror i nysilver.",
            "contact": {
                "office": "N/A",
                "phone": [
                    "22125"
                ],
                "postgiro": "32783",
                "telegraph": "Mema, Lidköping",
                "factory_office": "N/A",
                "factory_phone": "N/A"
            },
            "financials": {
                "capital": "165,200 kr",
                "employees": {
                    "industriarb": 100
                },
                "annual_turnover": "1,300,000 kr",
                "annual_production_value": "N/A"
            },
            "foundation_year": 1911,
            "corporation_year": 1921,
            "board": [
                {
                    "name": "Gunnar W. Anderson",
                    "role": "dir"
                },
                {
                    "name": "Sven Ericsson",
                    "role": "disp"
                },
                {
                    "name": "Åke Roslund",
                    "role": "herr"
                }
            ],
            "manager": "N/A"
        },
        "6": {
            "name": "Mepe, Holm & Hoppe",
            "location": "Stockholm",
            "business": "Metallvarufabrik och mek. verkstad",
            "products": "Tillverkar byggnadsbeslag, verktyg samt kinematografisk materiel och pneumatiska apparater.",
            "contact": {
                "office": "Aspudden, Stockholm",
                "phone": [
                    "454664"
                ],
                "postgiro": "59194",
                "telegraph": "Mepemetal, Stockholm",
                "factory_office": "N/A",
                "factory_phone": "N/A"
            },
            "financials": {
                "capital": "N/A",
                "employees": {
                    "industriarb": 30
                },
                "annual_turnover": "500,000 kr",
                "annual_production_value": "N/A"
            },
            "foundation_year": 1930,
            "corporation_year": "N/A",
            "board": [],
            "manager": "N/A"
        },
        "7": {
            "name": "AB. Mercer",
            "location": "Borås",
            "business": "Trikåfabrik",
            "products": "Tillverkar herrstrumpor. Varumärke: »Mercer».",
            "contact": {
                "office": "N/A",
                "phone": [
                    "19069"
                ],
                "postgiro": "131545",
                "telegraph": "N/A",
                "factory_office": "N/A",
                "factory_phone": "N/A"
            },
            "financials": {
                "capital": "20,000 kr",
                "employees": {
                    "industriarb": 40
                },
                "annual_turnover": "500,000 kr",
                "annual_production_value": "N/A"
            },
            "foundation_year": 1937,
            "corporation_year": "N/A",
            "board": [],
            "manager": "Erik Ohlsson"
        }
    }
}