{
    "original": "O rion—Orstadius\n\nHuvudkontor: Halmstad. Telefon: 235\no. 4235. Postgiro: 93479.\nFörsäljn.-kon-tor: Stockholm, Västerlångg. 40, telefon:\n107705.\n\nAntal industriarb.: 100. Tillv.-värde pr\når: 1,000,000 kr. — Firman etabl. 1935 i\nSmålandsstenar, nuv. adress 1941.\n\nÄgare o. chefer: fabr. Ebbe Johanson o.\ning. Sture Johansson.\n\nOrion, AB. Fabriken, Lindesberg.\n\nSe AB. Fabriken Orion, Lindesberg.\n\n*AB. Orrefors Glasbruk, Orrefors.\n\nGlasbruk i Orrefors och Hovmantorp\n(båda i Kronob. l.). Tillverkar\nkristall-och hushållsglas, konstglas,\nbelysningsarmatur samt flaskor och annat glas för\ntekniskt bruk.\n\nTelegr.-adr.: Orreglas, Orrefors.\nTelefon: 1, 2, 4, 6 och 112. Postgiro: 9220.\n\nAkt.-kap.: 1,000,000 kr. Antal\nindustriarb.: 300. Tillv.-värde pr år: 3,000,000 kr.\n— Firman etabl. 1726, bolaget grundat\n1937.\n\nStyrelse: grossh. Robert Ljunglöf (ordf.),\nkonsul Henning Beyer, konsulinnan S.\nBeyer, dir. Nils Johansson.\n\nVerkst. dir.: Nils Johansson.\n\nInköpschef: Torsten Hellner.\n\nAB. Orrefors Skogar, Orrefors.\n\nSågverk och hyvleri vid Orrefors\n(Kronobergs l.). Tillverkar sågade och hyvlade\nträvaror samt träull. Bolaget idkar även\njordbruk och skogshantering.\n\nTelegr.-adr.: Orreträ, Orrefors.\nTelefon: 7, 1 o. 5. Postgiro: 137117.\n\nAkt.-kap.: 1,200,000 kr. Antal\nindustriarb.: 115. Tillv.-värde pr år: 600,000 kr.\n\nBolaget grundat 1897 under namn\nOrrefors Bruks AB., nuv. namn 1938.\n\nStyrelse: f. d. justitierådet Joh.\nHellner (ordf.), konsul Henning Beyer,\nkonsul Carl Ekman, dir. Erik Hedberg,\növerste Folke Ramström.\n\nVerkst. dir.: Erik Hedberg.\n\nAB. Orresta Snickerifabrik,\n\nOrresta.\n\nSnickerifabrik vid Orresta (Västmanl.\nL). Tillverkar byggnadssnickerier såsom\nfönster, dörrar och inredningar samt\nparkettstav av ek. Specialitet: lamelldörrar.\n\nTelefon: 27 o. 24. Postgiro: 10621. —\nAkt.-kap.: 110,000 kr. Antal industriarb.:\n35. Tillv.-värde pr år: 450,000 kr. —\nFirman etabl. 1919, bolag 1928.\n\nDisp.: fabr. John Larsson.\n\nAB. Orresta Tegelbruk, Orresta.\n\nTegelbruk vid Orresta (Västmanl. l.).\nTillverkar taktegel och dräneringsrör.\n\nTelefon: 27 o. 30. Postgiro: 134306. —\nAkt.-kap.: 170,000 kr. Antal industriarb.:\n25. Årstillv.: 2 milj. st. tegelvaror. —\nBolaget grundat 1937.\n\nDisp.: fabr. John Larsson.\n\n*AB. Orrvikens Såg &amp;\nSnickerifabrik, Orrviken.\n\nSågverk och hyvleri i Fanbyn,\nGenvalla, och snickerifabrik i Orrviken\n(båda i Jämtl. l.). Tillverkar sågade och\nhyvlade trävaror, listverk, ^\nbyggnadssnickerier, möbler och inredningar samt\nmonteringsfärdiga trähus.\n\nKontor: Orrviken. Telefon: 7.\nPostgiro: 27030.\n\nAkt.-kap.: 60,000 kr. Antal\nindustriarb.: 25. Tillv.-värde pr år: 370,000 kr.\n\n—\tFirman etabl. 1916, bolag 1934. ^\n\nStyrelse: disp. Per Olov Viklund\n\n(ordf.), faktor Oskar Viklund.\n\nDisp.: Per Olov Viklund.\n\nOrsa Kättingfabrik, Birger Olsson,\n\nOrsa.\n\nSmidesfabrik i Orsa (Kopparb. l.).\nTillverkar kätting, flottningssmiden, ankare\noch draggar, smiden och kätting för\njärnvägsvagnar, skogsredskap,\njärnkonstruktioner m. m.\n\nTelegr.-adr.: Järnbirger, Orsa.\nTelefon: »Birger Olssons». Postgiro: 10459.\n\nAntal industriarb.: 40. Tillv.-värde pr\når: 700,000 kr. — Firman etabl. 1909.\n\nÄgare o. chef: dir. Birger Olsson.\n\n*AB. Orsa Sågbladsfabrik, Orsa.\n\nTillverkar vedsågblad, bandsågblad,\nsågbågar, timmersågar, stocksågar,\nhandsågar, sågfilklovar samt hjälp redskap för\nsågar vid fabrik i Orsa (Kopparb. l.).\nVarumärke: »Orsia».\n\nTelefon: 481. Ensamförsälj.: Firma\nBirger Olsson, Orsa, telefon: »Birger\nOlssons».\n\nAkt.-kap.: 75,000 kr. Antal\nindustriarb.: 45. Tillv.-värde pr år: 800,000 kr.\n\n—\tBolaget grundat 1927.\n\nStyrelse: dir. Birger Olsson, järnhandl.\nTuwe Olsson, ing. Gösta Timander.\n\nVerkst. dir.: Birger Olsson.\n\nOrstadius Boktryckeri AB.,\n\nGöteborg.\n\nUtför boktryck, affärs- och\nreklamtryck.\n\\*",
    "structured": {
        "1": {
            "name": "Orion",
            "location": "Halmstad",
            "business": "Okänd",
            "contact": {
                "office": "Huvudkontor: Halmstad",
                "phone": [
                    "235",
                    "4235"
                ],
                "postgiro": "93479",
                "head_office": "Lindesberg",
                "sales_offices": [
                    {
                        "location": "Stockholm, Västerlångg. 40",
                        "phone": "107705"
                    }
                ]
            },
            "financials": {
                "capital": "Okänd",
                "employees": {
                    "industriarb": 100
                },
                "annual_turnover": "Okänd",
                "annual_production_value": "1,000,000 kr"
            },
            "foundation_year": 1935,
            "owners": [
                "fabr. Ebbe Johanson",
                "ing. Sture Johansson"
            ]
        },
        "2": {
            "name": "Orrefors Glasbruk",
            "location": "Orrefors and Hovmantorp",
            "business": "Tillverkar kristall-och hushållsglas, konstglas, belysningsarmatur samt flaskor och annat glas för tekniskt bruk.",
            "contact": {
                "telegraph": "Orreglas, Orrefors",
                "phone": [
                    "1",
                    "2",
                    "4",
                    "6",
                    "112"
                ],
                "postgiro": "9220"
            },
            "financials": {
                "capital": "1,000,000 kr",
                "employees": {
                    "industriarb": 300
                },
                "annual_turnover": "Okänd",
                "annual_production_value": "3,000,000 kr"
            },
            "corporation_year": 1937,
            "board": [
                {
                    "name": "grossh. Robert Ljunglöf",
                    "role": "ordf."
                },
                {
                    "name": "konsul Henning Beyer",
                    "role": "Okänd"
                },
                {
                    "name": "konsulinnan S. Beyer",
                    "role": "Okänd"
                },
                {
                    "name": "dir. Nils Johansson",
                    "role": "Okänd"
                }
            ],
            "director": "Nils Johansson",
            "managing_director": "Okänd",
            "sales_manager": "Okänd"
        },
        "3": {
            "name": "Orrefors Skogar",
            "location": "Orrefors (Kronobergs l.)",
            "business": "Tillverkar sågade och hyvlade trävaror samt träull. Idkar även jordbruk och skogshantering.",
            "contact": {
                "telegraph": "Orreträ, Orrefors",
                "phone": [
                    "7",
                    "1",
                    "5"
                ],
                "postgiro": "137117"
            },
            "financials": {
                "capital": "1,200,000 kr",
                "employees": {
                    "industriarb": 115
                },
                "annual_turnover": "Okänd",
                "annual_production_value": "600,000 kr"
            },
            "corporation_year": 1938,
            "board": [
                {
                    "name": "f.d. justitierådet Joh. Hellner",
                    "role": "ordf."
                },
                {
                    "name": "konsul Henning Beyer",
                    "role": "Okänd"
                },
                {
                    "name": "konsul Carl Ekman",
                    "role": "Okänd"
                },
                {
                    "name": "dir. Erik Hedberg",
                    "role": "Okänd"
                },
                {
                    "name": "överste Folke Ramström",
                    "role": "Okänd"
                }
            ],
            "director": "Erik Hedberg",
            "managing_director": "Okänd",
            "sales_manager": "Okänd"
        },
        "4": {
            "name": "Orresta Snickerifabrik",
            "location": "Orresta (Västmanl)",
            "business": "Tillverkar byggnadssnickerier såsom fönster, dörrar och inredningar samt parkettstav av ek. Specialitet: lamelldörrar.",
            "contact": {
                "phone": [
                    "27",
                    "24"
                ],
                "postgiro": "10621"
            },
            "financials": {
                "capital": "110,000 kr",
                "employees": {
                    "industriarb": 35
                },
                "annual_turnover": "Okänd",
                "annual_production_value": "450,000 kr"
            },
            "corporation_year": 1928
        },
        "5": {
            "name": "Orresta Tegelbruk",
            "location": "Orresta (Västmanl l.)",
            "business": "Tillverkar taktegel och dräneringsrör.",
            "contact": {
                "phone": [
                    "27",
                    "30"
                ],
                "postgiro": "134306"
            },
            "financials": {
                "capital": "170,000 kr",
                "employees": {
                    "industriarb": 25
                },
                "annual_turnover": "Okänd",
                "annual_production_value": "Okänd"
            },
            "corporation_year": 1937
        },
        "6": {
            "name": "Orrvikens Såg & Snickerifabrik",
            "location": "Fanbyn and Orrviken (Jämtl. l.)",
            "business": "Tillverkar sågade och hyvlade trävaror, listverk, byggnadssnickerier, möbler och inredningar samt monteringsfärdiga trähus.",
            "contact": {
                "office": "Kontor: Orrviken",
                "phone": [
                    "7"
                ],
                "postgiro": "27030"
            },
            "financials": {
                "capital": "60,000 kr",
                "employees": {
                    "industriarb": 25
                },
                "annual_turnover": "Okänd",
                "annual_production_value": "370,000 kr"
            },
            "corporation_year": 1934
        },
        "7": {
            "name": "Orsa Kättingfabrik",
            "location": "Orsa (Kopparb. l.)",
            "business": "Tillverkar kätting, flottningssmiden, ankare och draggar, smiden och kätting för järnvägsvagnar, skogsredskap, järnkonstruktioner m. m.",
            "contact": {
                "telegraph": "Järnbirger, Orsa",
                "phone": [
                    "Birger Olssons"
                ],
                "postgiro": "10459"
            },
            "financials": {
                "capital": "Okänd",
                "employees": {
                    "industriarb": 40
                },
                "annual_turnover": "Okänd",
                "annual_production_value": "700,000 kr"
            },
            "foundation_year": 1909,
            "director": "dir. Birger Olsson"
        },
        "8": {
            "name": "Orsa Sågbladsfabrik",
            "location": "Orsa (Kopparb. l.)",
            "business": "Tillverkar vedsågblad, bandsågblad, sågbågar, timmersågar, stocksågar, handsågar, sågfilklovar samt hjälp redskap för sågar vid fabrik i Orsa (Kopparb. l.). Varumärke: »Orsia».",
            "contact": {
                "phone": [
                    "481"
                ],
                "postgiro": "Okänd"
            },
            "financials": {
                "capital": "75,000 kr",
                "employees": {
                    "industriarb": 45
                },
                "annual_turnover": "Okänd",
                "annual_production_value": "800,000 kr"
            },
            "corporation_year": 1927,
            "board": [
                {
                    "name": "järnhandl. Tuwe Olsson",
                    "role": "Okänd"
                },
                {
                    "name": "ing. Gösta Timander",
                    "role": "Okänd"
                }
            ],
            "director": "Birger Olsson"
        },
        "9": {
            "name": "Orstadius Boktryckeri AB.",
            "location": "Göteborg",
            "business": "Utför boktryck, affärs- och reklamtryck.",
            "contact": {
                "phone": "Okänd"
            }
        }
    }
}