{
    "original": "Boklund—Bolinder\n\n48. Tillv.-värde pr år: 1,700,000 kr. —\nFirman etabl. 1901, bolag 1923.\n\nVerkst. dir.: John Boklund.\n\nDisp.: Peder Bjurvik.\n\nAB. Boklund &amp; Son, Malmö.\n\nKniv- och verktygsfabrik. Tillverkar\nknivar och verktyg för kork-, handsk-,\nläder- och pälsvaruindustrierna m. fl.\nyrkesknivar.\n\nKontor: N. Vattenverksv. 44.\nTelegr.-adr.: Boklunds, Malmö. Telefon: 20616.\nPostgiro: 37597.\n\nAkt.-kap.: 40,000 kr. Arb.-antal: 12.\nTillv.-värde pr år: 200,000 kr. —\nFirman etabl. 1868, bolag 1934.\n\nVerkst. dir.: Thor Boklund.\n\n*F. A. Boklund AB., Stockholm.\n\nSnickerifabrik. Utför inredningar för\nboktryckerier och tidningssätterier.\n\nKontor: Roslagstull. Telegr.-adr.:\nBoktryckträ, Stockholm. Telefon: 337799.\nPostgiro: 52772.\n\nAkt.-kap.: 15,000 kr. Arb.-antal: 9.\nTillv.-värde pr år: 90,000 kr. — Firman\netabl. 1887, bolag 1942.\n\nStyrelse o. verkst. dir.: fabr. Carl W.\nBoklund.\n\nBoklövsfabriken i Magiehem AB.,\n\nKristianstad.\n\nPreparerar boklöv och ormbunk för\ndekorationsändamål vid fabrik i Magiehem,\nKristianstad.\n\nTelefon: 13867. Postgiro: 30259.\n\nAkt.-kap.: 30,000 kr. Arb.-antal: 8.\nTillv.-värde pr år: 125,000 kr. — Firman\netabl. 1920, bolag 1943.\n\nVerkst. dir.: järnhandl. Hjalmar\nHan-sen.\n\n*AB. Boksta Tegelbruk, Yittinge.\n\nTillverkar taktegel och dräneringsrör\nvid tegelbruk i Vittinge (Västmanl. l.).\n\nTelefon: 50. Postgiro: 75964. —\nAkt.-kap.: 100,000 kr. Antal industriarb.: 16.\nÅrstillv.: 1,1 milj. st. tegelvaror. —\nTegelbruket anlagt 1911, bolaget grundat\n1942.\n\nStyrelse o. verkst. dir.: J. Magnus\nPettersson.\n\n* Bolidens Cruv AB., Skelleftehamn.\n\nGruvdrift vid Boliden och\nKristineberg (båda i Västerb. l.) och vid Laisvall\n(Norrb. l.) m. fl. platser samt smältverk\nå Rönnskär, Skelleftehamn (Västerb. l.),\nvarest de erhållna malmprodukterna\nförädlas.\n\nHuvudkontor o. smältverk:\nSkelleftehamn. Telegr.-adr.: Smelter, Skellefteå.\nTelefon: Skellfteå 31500. Gruvförvaltn.:\nBoliden. Telegr.-adr.: Coppermine,\nSkellefteå. Telefon: »Gruvförvaltningen»,\nBoliden. Försäljn.-kontor: Stockholm,\nVästra Trädgårdsg. 17. Telegr.-adr.:\nBo-lidcomp., Stockholm. Telefon: 232620.\nCentrallaboratorium samt avdelningar\nför träimpregnering o. växtskyddssalter:\nStockholm, Bryggarg. 17, telefon: 232630.\n\nAkt.-kap.: 42,000,000 kr. Antal\nindustriarb.: 2,600. — Bolaget grundat 1925\nunder namn Västerbottens Gruv AB.,\nnuv. namn 1931.\n\nStyrelse: bankdir. Gustaf Söderlund\n(ordf.), bankdir. Åke Belfrage, dir. Erik\nJ. Bengtson, dir. Ragnar Blomquist, dir.\nOscar Falkman, bankdir. Ernst C:son\nHerslow, dir. Sven Schwartz.\n\nVerkst. dir.: Erik J. Bengtson.\n\nTekn. dir. för Rönnskärsverken: dir.\nOlov Herneryd.\n\nChef för gruvförvalt.: disp. Bertil\nNorén (Boliden).\n\nChef för försäljn.-avd.: dir. H. v.\nKnorring (Sthlm).\n\n(Jfr annons före Alfabet.\nVaruförteck-ning.)\n\n*AB. Bolinder—Munktell,\n\nEskilstuna.\n\nMek. verkstäder i Eskilstuna, mek.\nverkstad i Åstorp (Kristianst. l.).\n\nTillverkar i Eskilstuna: marina och\nstationära råolje- och dieselmotorer,\nflygmotorer, traktorer, väghyvlar och\nmotorvältar, tröskverk och skördetröskor,\nträbe-arbetningsmaskiner för sågverk, hyvlerier\noch lådfabriker samt verktygsmaskiner\nsåsom svarvar, pressar, hejare m. m. I\nÅstorp tillverkas halmfläktar och\nhalm-pressar samt utföras reparationer av\ntraktorer, skördetröskor och tröskverk.\n\nTelegr.-adr.: Munktells, Eskilstuna.\nTelefon: »Bolinder-Munktell». Postgiro:\n10704. Filialkontor o. reservlager:\nStockholm, N. Mälarstrand 30, telefon: 537304;\nGöteborg, Fiskhamnsg., telefon: 146419;\nÅstorp, telefon: »Bolinder-Munktell»;\nSkövde, telefon: 373; Linköping, telefon:\n21722; Kalmar: telefon: 1159.\n\nAkt.-kap.: 5,000,000 kr. Antal\nindustriarb.: 1,900. Tillv.-värde pr år: 32,000,000\nkr.\n\nBolaget bildades 1932 genom\nsammanslagning av Munktells Mekaniska\nVerkstads AB:s rörelse i Eskilstuna, grundad\n1832, och J. &amp; C. G. Bolinders Mek.\nVerkstads AB:s verkstadsrörelse i Stockholm,\ngrundad 1844. Bolaget äger följande\ndotterbolag: Munktells Mek. Verkstads\nAB., J. &amp; O. G. Bolinders Mek. Verkstads\n\nA\n\n58*",
    "structured": {
        "1": {
            "name": "AB. Boklund & Son",
            "location": "Malmö",
            "business": "Kniv- och verktygsfabrik",
            "products": "Tillverkar knivar och verktyg för kork-, handsk-, läder- och pälsvaruindustrierna m. fl. yrkesknivar",
            "contact": {
                "office": "N. Vattenverksv. 44",
                "phone": [
                    "20616"
                ],
                "telegraph": "Boklunds, Malmö",
                "postgiro": "37597"
            },
            "financials": {
                "capital": "40,000 kr",
                "employees": {
                    "total": 12
                },
                "annual_turnover": "200,000 kr"
            },
            "foundation_year": 1901,
            "board": [
                {
                    "name": "John Boklund",
                    "role": "Verkst. dir."
                },
                {
                    "name": "Peder Bjurvik",
                    "role": "Disp."
                }
            ],
            "director": "John Boklund"
        },
        "2": {
            "name": "F. A. Boklund AB.",
            "location": "Stockholm",
            "business": "Snickerifabrik",
            "products": "Utför inredningar för boktryckerier och tidningssätterier",
            "contact": {
                "office": "Roslagstull",
                "phone": [
                    "337799"
                ],
                "telegraph": "Boktryckträ, Stockholm",
                "postgiro": "52772"
            },
            "financials": {
                "capital": "15,000 kr",
                "employees": {
                    "total": 9
                },
                "annual_turnover": "90,000 kr"
            },
            "foundation_year": 1868,
            "board": [
                {
                    "name": "Thor Boklund",
                    "role": "Verkst. dir."
                }
            ],
            "director": "Thor Boklund"
        },
        "3": {
            "name": "Boklövsfabriken i Magiehem AB.",
            "location": "Kristianstad",
            "business": "Preparerar boklöv och ormbunk för dekorationsändamål vid fabrik i Magiehem",
            "contact": {
                "phone": [
                    "13867"
                ],
                "postgiro": "30259"
            },
            "financials": {
                "capital": "30,000 kr",
                "employees": {
                    "total": 8
                },
                "annual_turnover": "125,000 kr"
            },
            "foundation_year": 1887,
            "board": [
                {
                    "name": "fabr. Carl W. Boklund",
                    "role": "Styrelse o. verkst. dir."
                }
            ],
            "director": "fabr. Carl W. Boklund"
        },
        "4": {
            "name": "AB. Boksta Tegelbruk",
            "location": "Vittinge",
            "business": "Tillverkar taktegel och dräneringsrör",
            "contact": {
                "phone": "50",
                "postgiro": "75964"
            },
            "financials": {
                "capital": "100,000 kr",
                "employees": {
                    "total": 16
                },
                "annual_turnover": "1,100,000 kr"
            },
            "foundation_year": 1911,
            "corporation_year": 1942,
            "board": [
                {
                    "name": "J. Magnus Pettersson",
                    "role": "Styrelse o. verkst. dir."
                }
            ]
        },
        "5": {
            "name": "Bolidens Cruv AB.",
            "location": "Skelleftehamn",
            "business": "Gruvdrift och smältverk",
            "products": "Gruvdrift vid Boliden och Kristineberg (båda i Västerb. l.) och vid Laisvall (Norrb. l.) m. fl. platser samt smältverk å Rönnskär, Skelleftehamn (Västerb. l.)",
            "contact": {
                "office": "Skelleftehamn",
                "smältverk": "Rönnskär, Skelleftehamn (Västerb. l.)",
                "phone": "31500",
                "telegraph": "Smelter, Skellefteå"
            },
            "financials": {
                "capital": "42,000,000 kr",
                "employees": {
                    "total": 2,
                    "industriarb": 2,
                    "Centrallaboratorium": "Stockholm",
                    "Bryggarg": 17,
                    "telephone": 232630
                }
            },
            "foundation_year": 1925,
            "current_name_year": 1931,
            "predecessor": "Västerbottens Gruv AB.",
            "director": "Erik J. Bengtson"
        },
        "6": {
            "name": "AB. Bolinder—Munktell",
            "location": "Eskilstuna",
            "business": "Mek. verkstäder, tillverkar marina och stationära råolje- och dieselmotorer, traktorer, väghyvlar och motorvältar, tröskverk och skördetröskor, träbe-arbetningsmaskiner samt verktygsmaskiner",
            "products": "Tillverkar i Eskilstuna: marina och stationära råolje- och dieselmotorer, flygmotorer, traktorer, väghyvlar och motorvältar, tröskverk och skördetröskor, träbe-arbetningsmaskiner för sågverk, hyvlerier och lådfabriker samt verktygsmaskiner såsom svarvar, pressar, hejare m. m.",
            "contact": {
                "office": "Eskilstuna",
                "phone": "Bolinder-Munktell",
                "postgiro": "10704",
                "reservlager": {
                    "Stockholm": "N. Mälarstrand 30",
                    "Göteborg": "Fiskhamnsg.",
                    "Åstorp": "Bolinder-Munktell",
                    "Skövde": "373",
                    "Linköping": "21722",
                    "Kalmar": "1159"
                }
            },
            "financials": {
                "capital": "5,000,000 kr",
                "employees": {
                    "total": 1,
                    "industriarb": 1,
                    "2": "0 milj. st. tegelvaror"
                },
                "annual_turnover": "32,000,000 kr"
            }
        }
    }
}