{
    "original": "Sjöberg—Sjöstedt\n\nAB. Erik Sjöbergs\nFiskredskapsfabrik, Runnvika.\n\nTillverkar ryssjor, mjärdar, sjöfärdiga\nnät, håvar, kräftburar och kräfthåvar vid\nfabrik i Runnvika (Kopparb. l.).\n\nTelegr.-adr.: Fiskredskap, Runnvika.\nTelefon: 14. Postgiro: 24110. —\nAkt.-kap.: 90,000 kr. Tillv.-värde pr år:\n300,000 kr. — Firman etabl. 1907, bolag\n1945.\n\nVerkst. dir.: Erik Sjöberg.\n* Fritz Sjöbloms Trikåfabrik, Borås.\n\nTillverkar trikåvaror i bomull och\nsilke. Varumärken: »F. S. B. Boråstrikå»\no. »Sjöbloms».\n\nTelefon: 11717. Postgiro: 22111. —\nArb.-antal: 12. Tillv.-värde pr år: 200,000\nkr. — Firman etabl. 1909.\n\nÄgare o. chef: fabr. Fritz Sjöblom.\n\n*Sjöboverken AB., Sjöbo.\n\nSe Ankarsrums Skåne AB., Sjöbo.\n\nAB. Sjöexpress, Lidingö.\n\nBåtbyggeri och varv. Bygger och\nreparerar motorbåtar.\n\nTelegr.-adr.: Sjöexpress, Stockholm.\nTelefon: 656562. Postgiro: 23312. —\nAkt.-kap.: 150,000 kr. Tillv.-värde pr år:\n300,000 kr. — Firman etabl. 1898.\n\nStyrelse: dir. Henning Forslund\n(ordf.), fru Sigrid Forslund.\n\nVerkst. dir.: Henning Forslund.\n\nAB. P. A. Sjögren, Stockholm,.\n\nUtför gas-, vatten-, avlopps- och\nvärmeledningsanläggningar, bad- och\ntoalettrumsinredningar. Firman är gas- och\nvattenledningsentreprenör.\n\nKontor: Mästersamuelsg. 16; postadr.:\nStockholm 7. Telefon: »P. A. Sjögren».\nPostgiro: 1246.\n\nAkt.-kap.: 375,000 kr. — Firman etabl.\n1.888, bolag 1916.\n\nStyrélse: dir. Johan Sjögren (ordf.),\ning. Adolf Sjögren, fröken E. Sjögren,\nagronom Torsten Sjögren.\n\nVerkst. dir.: Torsten Sjögren.\n\nArvid Sjöquists Clasformfabrik &amp;\nMek. Verkstad, Nybro.\n\nTillverkar glasformar samt maskiner\noch verktyg för glasindustrin i Nybro\n(Kalmar l.).\n\nTelefon: 73. Postgiro: 20564.— Antal\nindustriarb.: 10. — Firman etabl. 1888.\n\nÄgare o. chef: fabr. Olof E. Sjöquist.\n\n47\n\n\"Helmer Sjökvist, Eskilstuna.\n\nMetallfabrik och mek. verkstad.\nTillverkar smörj sprutor och smörjnipplar för\nhögtryckssmör jning, beställningsarbeten\nsåsom armatur, maskindelar och svarvade\ndetaljer. Varumärke: »Lumatic».\n\nTelefon: 31555. Postgiro: 32846. —\nAntal industriarb.: 39. Tillv.-värde pr år:\n340,000 kr. — Firman etabl. 1924.\n\nÄgare o. chef: ing. Helmer Sjökvist.\n\nKamrer: Olle Sjökvist.\n\nVerkstads chef; ing. Sven Lundberg.\n\nAB. P. Sjökvists Skofabrik,\n\nLindesberg.\n\nSkofabrik i Lindesberg (Örebro L).\nTillverkar randsydda skodon.\n\nTelefon: 168. — Akt.-kap.: 75,000 kr.\nAntal industriarb.: 30. Tillv.-värde pr år:\n400,000 kr. — Bolaget grundat 1936, äges\nav Skofabriks AB. Kronan, Örebro.\n\nDirektörer: Arthur Larsson o. Håkan\nPerman.\n\n\"Sjölins Byggnads AB., Landskrona.\n\nByggnadsentreprenörfirma för\nbostads-och affärshus, industribyggnader m. m.\n\nTelefon: 825. Postgiro: 136644. —\nAkt.-kap.: 30,000 kr. Prod.-värde pr år:\n1,200,000 kr. — Bolaget grundat 1934.\n\nStyrelse: byggm. Sture Sjölin (ordf.),\nköpm. Harry Sjölin, revisor Ragnar\nSjölin.\n\nVerkst. dir.: Sture Sjölin.\n\nAB. Sjömarkens Skjortfabrik,\n\nBollebygd.\n\nSe AB. Yrkesuniformer, Bollebygd.\n\n\"Gustaf Sjöstedt &amp; Co., Handels- &amp;\nFabriks AB., Göteborg.\n\nFärg- och fernissfabrik samt\nlinolje-kokeri. Tillverkar linoleumfernissor,\nko-pal-, cellulosa- och spritfernissor, lack-,\nolje-, emulsions- och spritfärger,\nbrytningsfärger i tuber, spackelfärger, kokt\nlinolja och andra målaroljor, siccativer\nsamt färgborttagningsmedel. Varumärke:\n»Gusco». Firman driver även\nengroshandel med torra färger, penslar och övriga\nmåleriutensilier.\n\nHuvudkontor: Krokegårdsg. 5.\nTelegr.-adr.: Sjöstedts, Göteborg. Telefon: 222030.\nPostgiro: 43310. Avd.-kontor: Stockholm,\nWollmar Yxkullsg. 2, telefon: 410093—94.\n\nAkt.-kap.: 400,000 kr. Antal\nindustriarb.: 28. Tillv.-värde pr år: 2,100,000 kr.\n\nFirman etabl. 1889, bolag 1934.",
    "structured": {
        "1": {
            "name": "Erik Sjöbergs Fiskredskapsfabrik",
            "location": "Runnvika",
            "business": "Tillverkar ryssjor, mjärdar, sjöfärdiga nät, håvar, kräftburar och kräfthåvar vid fabrik i Runnvika (Kopparb. l.)",
            "contact": {
                "office": "Runnvika",
                "phone": [
                    "14"
                ],
                "postgiro": "24110",
                "telegraph": "Fiskredskap, Runnvika"
            },
            "financials": {
                "capital": "90,000 kr",
                "annual_turnover": "300,000 kr",
                "annual_production_value": "300,000 kr"
            },
            "foundation_year": 1907,
            "corporation_year": 1945,
            "director": "Erik Sjöberg"
        },
        "2": {
            "name": "Fritz Sjöbloms Trikåfabrik",
            "location": "Borås",
            "business": "Tillverkar trikåvaror i bomull och silke",
            "products": "Varumärken: »F. S. B. Boråstrikå» o. »Sjöbloms»",
            "contact": {
                "phone": [
                    "11717"
                ],
                "postgiro": "22111"
            },
            "financials": {
                "employees": {
                    "Arb.-antal": 12
                },
                "annual_production_value": "200,000 kr"
            },
            "foundation_year": 1909,
            "owner": "fabr. Fritz Sjöblom"
        },
        "3": {
            "name": "Sjöboverken AB.",
            "location": "Sjöbo",
            "predecessor": "Ankarsrums Skåne AB."
        },
        "4": {
            "name": "AB. Sjöexpress",
            "location": "Lidingö",
            "business": "Båtbyggeri och varv",
            "products": "Bygger och reparerar motorbåtar",
            "contact": {
                "office": "Stockholm",
                "phone": [
                    "656562"
                ],
                "postgiro": "23312"
            },
            "financials": {
                "capital": "150,000 kr",
                "annual_turnover": "300,000 kr"
            },
            "foundation_year": 1898,
            "board": [
                {
                    "name": "Henning Forslund",
                    "role": "ordf."
                },
                {
                    "name": "fru Sigrid Forslund"
                },
                {
                    "name": "Henning Forslund",
                    "role": "Verkst. dir."
                }
            ]
        },
        "5": {
            "name": "AB. P. A. Sjögren",
            "location": "Stockholm",
            "business": "Utför gas-, vatten-, avlopps- och värmeledningsanläggningar, bad- och toalettrumsinredningar",
            "contact": {
                "office": "Mästersamuelsg. 16",
                "phone": [
                    "P. A. Sjögren"
                ],
                "postgiro": "1246"
            },
            "financials": {
                "capital": "375,000 kr"
            },
            "foundation_year": 1888,
            "corporation_year": 1916,
            "board": [
                {
                    "name": "Johan Sjögren",
                    "role": "ordf."
                },
                {
                    "name": "ing. Adolf Sjögren"
                },
                {
                    "name": "fröken E. Sjögren"
                },
                {
                    "name": "agronom Torsten Sjögren",
                    "role": "Verkst. dir."
                }
            ]
        },
        "6": {
            "name": "Arvid Sjöquists Clasformfabrik & Mek. Verkstad",
            "location": "Nybro",
            "business": "Tillverkar glasformar samt maskiner och verktyg för glasindustrin i Nybro (Kalmar l.)",
            "contact": {
                "phone": [
                    "73"
                ],
                "postgiro": "20564"
            },
            "financials": {
                "employees": {
                    "Antal industriarb.": 10
                }
            },
            "foundation_year": 1888,
            "owner": "fabr. Olof E. Sjöquist"
        },
        "7": {
            "name": "Helmer Sjökvist",
            "location": "Eskilstuna",
            "business": "Metallfabrik och mek. verkstad",
            "products": "Tillverkar smörjsprutor och smörjnipplar för högtryckssmörjning, beställningsarbeten såsom armatur, maskindelar och svarvade detaljer",
            "contact": {
                "phone": [
                    "31555"
                ],
                "postgiro": "32846"
            },
            "financials": {
                "employees": {
                    "Antal industriarb.": 39
                },
                "annual_production_value": "340,000 kr"
            },
            "foundation_year": 1924,
            "owner": "ing. Helmer Sjökvist",
            "manager": "Olle Sjökvist",
            "sales_manager": "Sven Lundberg"
        },
        "8": {
            "name": "AB. P. Sjökvists Skofabrik",
            "location": "Lindesberg",
            "business": "Skofabrik i Lindesberg (Örebro L) tillverkar randsydda skodon",
            "contact": {
                "phone": [
                    "168"
                ]
            },
            "financials": {
                "capital": "75,000 kr"
            },
            "corporation_year": 1936,
            "owners": [
                "Skofabriks AB. Kronan, Örebro"
            ],
            "board": [
                {
                    "name": "Arthur Larsson"
                },
                {
                    "name": "Håkan Perman"
                }
            ]
        },
        "9": {
            "name": "Sjölins Byggnads AB.",
            "location": "Landskrona",
            "business": "Byggnadsentreprenörfirma för bostads-och affärshus, industribyggnader m. m.",
            "contact": {
                "phone": [
                    "825"
                ],
                "postgiro": "136644"
            },
            "financials": {
                "capital": "30,000 kr",
                "annual_production_value": "1,200,000 kr"
            },
            "foundation_year": 1934,
            "board": [
                {
                    "name": "byggm. Sture Sjölin",
                    "role": "ordf."
                },
                {
                    "name": "köpm. Harry Sjölin"
                },
                {
                    "name": "revisor Ragnar Sjölin",
                    "role": "Verkst. dir."
                }
            ]
        },
        "10": {
            "name": "AB. Sjömarkens Skjortfabrik",
            "location": "Bollebygd",
            "description": "Se AB. Yrkesuniformer, Bollebygd"
        },
        "11": {
            "name": "Gustaf Sjöstedt & Co., Handels- & Fabriks AB.",
            "location": "Göteborg",
            "business": "Färg- och fernissfabrik samt linolje-kokeri",
            "products": "Tillverkar linoleumfernissor, ko-pal-, cellulosa- och spritfernissor, lack-, olje-, emulsions- och spritfärger, brytningsfärger i tuber, spackelfärger, kokt linolja och andra målaroljor, siccativer samt färgborttagningsmedel. Firman driver även engroshandel med torra färger, penslar och övriga måleriutensilier",
            "contact": {
                "office": "Krokegårdsg. 5",
                "phone": [
                    "222030"
                ],
                "postgiro": "43310",
                "avd-kontor": "Stockholm, Wollmar Yxkullsg. 2",
                "avd-phone": [
                    "410093",
                    "94"
                ]
            },
            "financials": {
                "capital": "400,000 kr",
                "employees": {
                    "Antal industriarb.": 28
                },
                "annual_production_value": "2,100,000 kr"
            },
            "foundation_year": 1889,
            "corporation_year": 1934
        }
    }
}