{
    "original": "Flygverkstäder—Fors\n\nPostadr.: Orrefors. Telegr.-adr.:\nFlygs-forsglas, Orrefors. Telefon: Orrefors 57.\nPostgiro: 90544.\n\nAkt.-kap.: 120 000 kr. Antal\nindustriarb.: 200. Tillv.-värde pr år: 1,700,000 kr.\n\n—\tFirman etabl. 1930.\n\nStyrelse: disp. Oskar Rosander (ordf.),\narrendator Viktor Erlandson, dir. Emil\nFlytström, verkm. Gunnar Petersson,\nglasslipare Arne Rosander.\n\nVerkst. dir. o. di^v.: O^kar Rosander.\nDriftsing.: ing. Walter Granqvist.\nVerkm. f. armaturavd.: Gunnar\nPetersson\n\n(Jfr annons nr 85.)\n\nFlygverkstäder, AB. Förenade,\n\nLinköping.\n\nSe AB. Förenade Flygverkstäder,\nLinköping.\n\n*AB. Flyinge Tegelbruk, Flyinge.\n\nTillverkar murtegel och dräneringsrör\nvid tegelbruk i Flyinge (Malmöh. l.).\n\nTelefon: 21. Postgiro: 95624. —\nAkt.-kap.: 96,000 kr. Antal industriarb.: 15.\nÅrstillv.: 2 milj. st. tegelvaror. —\nBolaget grundat 1919.\n\nVerkst. dir.: Gustaf F. Swenson (Ystad).\nDisp.: Georg Nilsson.\n\n*Fläktfabriken, AB. Svenska,\n\nStockholm.\n\nSe AB. Svenska Fläktfabriken,\nStockholm.\n\nAB. Fläkt- &amp; Cyklonfabriken,\n\nMalmö.\n\nMek. verkstad. Tillverkar\nvarmvattenberedare och varmvattencisterner,\nhydroforer, luftklockor samt svetsade tunn- och\ngrovplå tsarbeten. Specialitet: vatten\nventil med ebonitkula.\n\nKontor: Friisg. 18—20. Telefon: 21514.\nPostsriro: 37595.\n\nAkt.-kap.: 30,000 kr. Antal\nindustriarb.: 20. Tillv.-värde pr år: 400,000 kr.\n\n—\tFirman etabl. 1924, bolag 1935.\nStyrelse: kassör Axel Ranby, konsul\n\nEdw. H. Thomée.\nDisp.: vakan t.\n\nFläkt- it Plåtsvetsning i Göteborg\nAB., Göteborg.\n\nSe örgryteverken AB., Göteborg.\n\n*AB. Fodervävnader, Alingsås.\n\nKonstsilkeväveri. Tillverkar\nkonstsilke-foder för herr- och damkonfektion.\n\nTelegr.-adr. o. telefon: Fodervävnader,\nAlingsås. Postgiro: 94048. Repr.: H. E„\nIlelm, Stockholm, Brunkebergstorg 15,.\ntelefon: 113791.\n\nAkt.-kap.: 600,000 kr. Antal\nindustriarb.: 160. Tillv.-värde pr år: 5,000,000\nkr. — Bolaget grundat 1933.\n\nStyrelse: jur. kand. Georg Boden\n(ordf.), köpm. H. E. Helm, disp. W.\nHösterey.\n\nDisp.: W. Hösterey.\n\n*AB. Fogelfors Bruk, Fågelfors.\n\nSnickerifabrik, trähusfabrik och\nsågverk med hyvleri vid Fågelfors (Kalmar\n1.). Tillverkar byggnadssnickerier, spec.\ndörrar och fönster, monteringsfärdiga\nträhus, sågade och hyvlade trävaror samt\nträkol. Bolaget idkar jämväl jordbruk\noch skogshantering.\n\nTelegr.-adr.: Fogelfors, Oskarshamn.\nTelefon: Fågelfors 2 o. 4. Postgiro:\n135113.\n\nAkt.-kap.: 500,000 kr. Antal\nindustriarb.: 180. Årstillv.: 1,500 stds sågade o.\nhyvlade trävaror. Tillv.-värde pr år för\nsnickerier o. trähus: 2,800,000 kr. —\nFirman grundades 1875, bolag 1916.\n\nStyrelse: bruksäg. Ivar Ekströmer^\nbruksäg. Thorsten Ekströmer, dir. Ad.\nFagerlund.\n\nVerkst. dir.: Thorsten Ekströmer.\n\nKassör: John Elf ström.\n\nKamrer: C. O. öjebeck.\n\nRitkontor sch ef: Gust. Hammare.\n\nFabriks för est.: Ernst Sonnerby.\n\n*Foglaviks Glasbruk, Fåglavik.\n\nSe AB. Fåglaviks Glasbruk, Göteborg.\n\n*Fohlströms Snickerifabrik,\nBröderna, Visby.\n\nSe Bröderna Fohlströms\nSnickerifabrik, Visby.\n\nFormalin AB., Svenska, Stockholm.\n\nSe Svenska Formalin AB., Stockholm.\n\n*Fors Bruk, Fors.\n\nSe Storviks Sulfit AB., Ockelbo.\n\n*AB. Fors Ullspinneri, Nyköping.\n\nUllspinneri och ylleväveri, färgeri och\nberedningsverk samt tvättanstalt för\nkemisk tvätt. Tillverkar ullgarn, hel- och\n\nhalvyllevävnader, filtar m. m.",
    "structured": {
        "1": {
            "name": "Flygverkstäder—Fors",
            "location": "Orrefors",
            "business": "Flygverkstäder",
            "contact": {
                "office": "Orrefors",
                "phone": [
                    "Orrefors 57"
                ],
                "postgiro": "90544"
            },
            "financials": {
                "capital": "120,000 kr",
                "employees": {
                    "industriarb": 200
                },
                "annual_turnover": "1,700,000 kr",
                "annual_production_value": "2 milj. st. tegelvaror"
            },
            "foundation_year": 1930,
            "board": [
                {
                    "name": "Oskar Rosander",
                    "role": "ordf."
                },
                {
                    "name": "Viktor Erlandson",
                    "role": "arrendator"
                },
                {
                    "name": "Emil Flytström",
                    "role": "dir."
                }
            ],
            "director": "O^kar Rosander",
            "managing_director": "Walter Granqvist",
            "sales_manager": "Gunnar Petersso",
            "manager": "Arne Rosander"
        },
        "2": {
            "name": "AB. Flyinge Tegelbruk, Flyinge",
            "location": "Flyinge",
            "business": "Tillverkar murtegel och dräneringsrör"
        },
        "3": {
            "name": "AB. Fläkt- &amp; Cyklonfabriken, Malmö",
            "location": "Malmö",
            "business": "Tillverkar varmvattenberedare och varmvattencisterner"
        },
        "4": {
            "name": "AB. Fodervävnader, Alingsås",
            "location": "Alingsås",
            "business": "Konstsilkeväveri"
        },
        "5": {
            "name": "AB. Fogelfors Bruk, Fågelfors",
            "location": "Fågelors",
            "business": "Snickerifabrik, trähusfabrik och sågverk"
        },
        "6": {
            "name": "Foglaviks Glasbruk, Fåglavik",
            "location": "Fåglavik"
        },
        "7": {
            "name": "Abb. Fors Ullspinneri, Nyköping",
            "location": "Nyköping",
            "business": "Ullspinneri och ylleväveri, färgeri och beredningsverk samt tvättanstalt"
        }
    }
}