{
    "original": "Munka—Munksund\n\nAkt-kap.: 950,000 kr. — Bolaget,\ngrundat 1924, äges av Mo och Domsjö AB.\nDriften kommer att under år 1947\nnedläggas.\n\nStyrelse: adv. Ernst Treffenberg (ordf.),\ndir. Carl Kempe, fil. dr Erik Kempe,\nciviling. Ragnar Kempe, dir. Ragnar\nLagergren.\n\nVerkst. dir.: Carl Kempe.\n\n*Munka Ljungby Snickeri AB.,\n\nMunkaljungby.\n\nTillverkar byggnadssnickerier,\nbutiksinredningar och som specialitet\nväxthusanläggningar vid fabrik i Munkaljungby\n(Kristianst. l.).\n\nTelefon: 6. Postgiro: 8,2247. —\nAkt.-kap.: 35,000 kr. Antal industriarb.: 20.\nTillv.-värde pr år: 300,000 kr. — Bolaget\ngrundat 1907.\n\nStyrelse: disp. Emil Persson (ordf.),\nverkm. Joel Karlsson, lantbr. Joel\nLarsson, byggm. August Persson, verkm. Folke\nPersson.\n\nVerkst. dir.: Emil Persson.\n\n* Munkedals AB., Munkedal.\n\nFinpappersbruk och pappfabrik med\nsulfitfabrik, träsliperi och spritfabrik vid\nMunkedal (Göteb. o. Bohus l.). Tillverkar\nträfria blekta papperssorter såsom\nskriv-och tryckpapper m. m., väggpapp,\nsulfitsprit samt för eget behov sulfitcellulosa\noch mek. trämassa.\n\nHuvudkontor: Munkedal. Telegr.-adr.:\nMunkedalsbruk, Munkedal. Telefon:\nMunkedal 3. Postgiro: 8630.\nFörsäljn.-kontor för Sverige: Munkedals\nStockholmskontor AB., Stockholm, Kungsg. 38.\nTelefon: 206015.\n\nAkt.-kap.: 3,000,000 kr. Antal\nindustriarb.: 600. Årstillv.: 12,000 ton papper o.\n2,500 ton papp. — Bolaget grundat 1871.\n\nStyrelse: skeppsred. H. Onstad (ordf.),\nbankdir. Henrik Skoog (v. ordf.), dir. B.\nLénberg, adv. Hugo Stenbeck.\n\nVerkst. dir.: H. Onstad.\n\nFörsäljn.-chef: Walter Lindeberg.\n\nDriftsing.: Paul Lund.\n\nKamrer: G. Sundman.\n\n*Munkeda!s Snickerifabrik AB.,\n\nMunkedal.\n\nTillverkar byggnadssnickerier och\nbutiksinredningar vid fabrik i Munkedal\n(Göteb. o. Bohus l.).\n\nTelefon: 2, 167 o. 182. Postgiro: 174890.\n— Akt.-kap.: 60,000 kr. Antal industri-\n\narb.: 25. Tillv.-värde pr år: 350,000 kr.\n— Firman etabl. 1939, bolag 1946.\n\nStyrelse o. verkst. dir.: disp. Hj.\nSohl-berg.\n\nKamrer: Eric Claezon.\n\n*AB. Munkens Konservfabriker,\n\nGravarne.\n\nSe AB. Bröderne Ameln, Stockholm.\n\n* Munkfors Järnverk, Munkfors.\n\nSe Uddeholms AB., Uddeholm.\n\n*Munksjö AB., Jönköping.\n\nPappersbruk och pappfabrik med\nsulfitfabrik vid Munksjö, Jönköping,\nsulfatfabrik vid Stödstorp, Vaggeryd,\nkartongfabrik vid Lindefors, Hok, elektr.\nvattenkraftstation vid Ebbes bruk (samtl. i\nJönköp. l.), sulfatfabrik och sågverk vid\nAspa (Örebro l.).\n\nTillverkar omslagspapper i kraft-,\nfi-déle- och sulfitkvalitet, spinnpapper,\nisoleringspapper och tändstickspapper,\ntakpapp, förhydningspapp, läder- och\nglanspapp, sulfatcellulosa och sågade trävaror\nävensom sulfitcellulosa och mek.\nträmassa för eget behov. Specialiteter:\nkabelisolerings-, spinn- och\ncementsäcks-papper, kraftpapperssäckar, handdukar,\nborddukar och servietter samt\npapperspåsar. Bolaget idkar jämväl\nskogshantering.\n\nBolaget äger Lagamilis AB. samt\nförsäljer detta bolags produkter.\n\nTelegr.-adr. o. telefon: »Munksjö»,\nJönköping. Postgiro: 14722. Lagerkontor\ni Stockholm, V. Trädgårdsg. 11 B,\ntelefon: 231640.\n\nAkt.-kap.: 15,000,000 kr. Antal\nindustriarb.: 885. Årstillv.: 40,000 ton papper\noch papp, 18,000 ton sulfatmassa för\nav-salu. — Bruket anlagt 1862, bolaget\ngrundat 1890.\n\nStyrelse: konsul Oscar Gullander\n(ordf.), dir. Nils G. Arvedson, bankdir.\nAnton Dahlin, adv. Emil Heijne, disp.\nOtto Heijne, disp. Werner Risberg.\n\nVerkst. dir.: Otto Heijne.\n\nKontors- o. försäljn.-chef: G. E.\nMalmström.\n\nDriftsingenjörer: i Munksjö: K.\nPer-Jönsson; i Stödstorp: Enok Nilsson; i\nAspa: Hj. Wallman.\n\nInköpschef: Carl Bergström.\n\n(Jfr annons nr 43.)\n\n*Munksunds AB., Luleå.\n\nSågverk, sulfatfabrik och snickerifabrik\nsamt kubbgolvsfabrik i Munksund,\nträmassefabrik invid Luleå (samtl. i Norr-",
    "structured": {
        "1": {
            "name": "Munka Ljungby Snickeri AB",
            "location": "Munkaljungby",
            "business": "Tillverkar byggnadssnickerier, butiksinredningar och som specialitet växthusanläggningar vid fabrik i Munkaljungby (Kristianst. l.)",
            "contact": {
                "phone": [
                    "6"
                ],
                "postgiro": "8,2247"
            },
            "financials": {
                "capital": "35,000 kr",
                "employees": {
                    "industriarb": 20
                },
                "annual_production_value": "300,000 kr"
            },
            "foundation_year": 1907
        },
        "2": {
            "name": "Munkedals AB",
            "location": "Munkedal",
            "business": "Finpappersbruk och pappfabrik med sulfitfabrik, träsliperi och spritfabrik vid Munkedal (Göteb. o. Bohus l.). Tillverkar träfria blekta papperssorter såsom skriv- och tryckpapper m. m., väggpapp, sulfitsprit samt för eget behov sulfitcellulosa och mek. trämassa",
            "contact": {
                "head_office": "Munkedal",
                "telegraph": "Munkedalsbruk, Munkedal",
                "phone": "Munkedal 3",
                "postgiro": "8630",
                "sales_offices": [
                    {
                        "location": "Stockholm, Kungsg. 38",
                        "phone": "206015"
                    }
                ]
            },
            "financials": {
                "capital": "3,000,000 kr",
                "employees": {
                    "industriarb": 600
                },
                "annual_turnover": "12,000 ton papper o. 2,500 ton papp"
            },
            "foundation_year": 1871
        },
        "3": {
            "name": "Munkedals Snickerifabrik AB",
            "location": "Munkedal",
            "business": "Tillverkar byggnadssnickerier och butiksinredningar"
        },
        "4": {
            "name": "Munkens Konservfabriker",
            "location": "Gravarne"
        },
        "5": {
            "name": "Munkfors Järnverk",
            "location": "Munkfors"
        },
        "6": {
            "name": "Munksjö AB",
            "location": "Jönköping",
            "business": "Pappersbruk och pappfabrik med sulfitfabrik vid Munksjö, Jönköping, sulfatfabrik vid Stödstorp, Vaggeryd, kartongfabrik vid Lindefors, Hok, elektr. vattenkraftstation vid Ebbes bruk (samtl. i Jönköp. l.). Tillverkar omslagspapper i kraft-, fi-déle- och sulfitkvalitet, spinnpapper, isoleringspapper och tändstickspapper, takpapp, förhydningspapp, läder- och glanspapp, sulfatcellulosa och sågade trävaror ävensom sulfitcellulosa och mek. trämassa för eget behov. Specialiteter: kabelisolerings-, spinn- och cementsäcks-papper, kraftpapperssäckar, handdukar, borddukar och servietter samt papperspåsar. Bolaget idkar jämväl skogshantering",
            "contact": {
                "telegraph": "Munksjö",
                "phone": "231640",
                "postgiro": "14722",
                "sales_offices": [
                    {
                        "location": "Stockholm, V. Trädgårdsg. 11 B",
                        "phone": "231640"
                    }
                ]
            },
            "financials": {
                "capital": "15,000,000 kr",
                "employees": {
                    "industriarb": 885
                },
                "annual_turnover": "40,000 ton papper och papp, 18,000 ton sulfatmassa för avsalu"
            },
            "foundation_year": 1890
        },
        "7": {
            "name": "Munksunds AB",
            "location": "Luleå",
            "business": "Sågverk, sulfatfabrik och snickerifabrik samt kubbgolvsfabrik i Munksund, trämassefabrik invid Luleå (samtl. i Norr-.)"
        }
    }
}