{
    "original": "Cehå—O entrala\n\nKontor: Stampgatan 24. Telegr.-adr.:\nCeder, Göteborg. Telefon: 152795.\nPostgiro: 40095,\n\nAkt.-kap.: 75,000 kr. Antal\nindustriarb.: 30. Tillv.-värde pr år: 250,000 kr.\n— Firman etabl. 1899, bolag 1920.\n\nStyrelse: fru Anna Cedervall, fabr.\nCarl Eric Cedervall.\n\nVerkst. dir.: C. E. Cedervall.\n\nAB. Cehå, Borlänge.\n\nTillverkar kolvpumpar,\ndjupbrunns-pumpar samt hydroforaggregat vid mek.\nverkstad i Töreboda (Skarab. l.).\nVarumärke: »Cehå».\n\nKontor: Borlänge. Telegr.-adr.: Cehå,\nBorlänge. Telefon: 10154. Postgiro:\n84371. — Akt.-kap.: 41,000 kr. Antal\nindustriarb.: 15. Tillv.-värde pr år: 275,000\nkr. — Bolaget grundat 1933.\n\nVerkst. dir.: fabr. Carl H. Swahn.\n\nCellufix AB., Stockholm.\n\nSe Svartviks AB., Sundsvall.\n\n*AB. CeElull, Vålherg.\n\nCellullfabrik vid Älvenäs, Vålberg\n(Värml. l.). Tillverkar fin- och grovull.\nVarumärke: »ABC».\n\nDirektörs- o. försäljn.-kontor:\nNorrköping, telefon: »Silkecellulosa».\nFabrikskontor: Vålberg, telegr.-adr.: Abecell,\nKarlstad, telefon: Karlstad 42100,\npostgiro: 192409.\n\nAkt.-kap.: 2,236,000 kr. Antal\nindustriarb..- 400. Årstillv.: 8,000 ton cellull. —\nBolaget, grundat 1941, drives i samarbete\nmed AB. Nordisk Silkecellulosa,\nNorrköping.\n\nStyrelse: dir. Albin Johansson (ordf.),\ndisp. Chr. v. Sydow (v. ordf.), civiling.\nGunnar Berg, dir. Hugo Edstam, dir.\nNils Engberg, dir. Ernst Persson.\n\nVerkst. dir.: C. Lindquist (Norrköp.).\n\nPlatschef: Olle Johansson.\n\nFörsäljn.-chef: Folke El änder (Norrköp.).\n\nKamrer: Fredrik Lindkvist (Norrköp.).\n\nKontorschef: Thorsten Johansson.\n\n*CeMuloidindustri, Svensk, Gislaved.\n\nSe Svensk Celluloidindustri AB.,\nGislaved.\n\n*Cementa, Svenska\nCementförsäljnings AB., Malmö.\n\nFörsäljningsorganisation för cement\nfrån\n\nSkånska Cement AB., Malmö, med\nfabriker i Limhamn, Hällekis och Köping,\nÖlands Cement AB.. Degerhamn,\nSlite Cement och Kalk AB., SI i te, och\nHidinge Kalkverk AB., Lannabruk.\n\nHuvudkontor: Malmö, Hans\nMichel-sensg. 1 B. Post-, telefon- o. telegr.-adr.:\nOementa, Malmö. Postgiro: 14152.\nKontor: Stockholm, Skeppsbron 18; post-,\ntelef on- o. telegr.-adr.: Cementa, Stockholm;\nGöteborg, östra Hamng. 52, post-,\ntelefon- o. telegr.-adr.: Cementa, Göteborg.\n\nAkt.-kap.: 27,600 kr. — Bolaget\ngrundat 1893.\n\nStyrelse: dir. Ernst Wehtje (ordf.),\ndir. Malte Ström (v. ordf.), dir. Arendt\nde Jounge, dr Fr. Killig, dir. Albin\nPersson, disp. H. Seb. Tham, övering.\nDonovan Werner.\n\nVerkst. dir.: Albin Persson.\n\nKontorschefer: i Stockholm: disp. I.\nStrömberg; i Göteborg: disp. H.\nSand-qvist.\n\n(Jfr annons å Bokmärket.)\n\n*Cementol, Isolerings AB., Göteborg.\n\nSe Isolerings AB. Cementol, Göteborg.\n\nAB. Cementrör, Tärnsjö.\n\nTillverkar betongrör, kulvertar,\nbrunnsringar, betonghålsten med och utan\nisoleringsplattor, cementtegel m. m. vid\nfabrik i Tärnsjö (Västmanl. l.).\n\nTelefon: 3. Postgiro: 33461. —\nAkt.-kap.: 45,000 kr. Arb.-antal: 9.\nTillv.-värde pr år: 70,000 kr. —Bolaget\ngrundat 1916.\n\nVerkst. dir.: grossh. Karl J. Norén.\nCenter Sport, Stockholm.\n\nTillverkar badmintonbollar.\nVarumärken: »Winett» o. »BMT».\n\nKontor: Beridarbansg. 21.\nTelegr.-adr.: Centersport, Stockholm. Telefon:\n209828 o. 110912. Postgiro: 151366. —\nArb.-antal: 20. — Firman etabl. 1933.\n\nÄgare o. chef: dir. Oscar C:son Swahn.\n\n*AB. Centrala Kartongfabriken,\n\nStockholm.\n\nFabrik i Ulvsunda, Stockholm, för\nförpackningar av papp, aromtät\nlivsmedelsförpackning, kartong och papper samt\noffsettryckeri. Förpackningsservice.\nVarumärken: »Ceka Ideal» o. »Ceka Lita».\n\nKontor: Ekbacksvägen 32—34,\nUlv-sunda. Telefon: 252690. Postgiro: 52696.\n\nAkt,-kap.: 80,400 kr. Antal\nindustriarb.: 65. Tillv.-värde pr år: 1,700,000 kr.\n— Firman etabl. 1916, bolag 1931.\n\nStyrelse: konsul Axel Christensson\n(ordf.), dir. Alf Christensson, disp.\nSverker Christensson.\n\nVerkst. dir.: Alf Christensson.\n\nDisp.: Sverker Christensson.\n\nKamrer: C. Alfr. Holm.",
    "structured": {
        "firms": [
            {
                "name": "Cehå",
                "location": "Stampgatan 24, Göteborg",
                "business": "Tillverkar kolvpumpar, djupbrunns-pumpar samt hydroforaggregat vid mek. verkstad i Töreboda (Skarab. l.)",
                "contact": {
                    "office": "Stampgatan 24",
                    "phone": [
                        "152795"
                    ],
                    "postgiro": "40095",
                    "head_office": "Stampgatan 24, Göteborg"
                },
                "financials": {
                    "capital": "75,000 kr",
                    "employees": {
                        "industriarb": 30
                    },
                    "annual_turnover": "250,000 kr"
                },
                "foundation_year": 1899,
                "corporation_year": 1920,
                "board": [
                    {
                        "name": "fru Anna Cedervall",
                        "role": "Styrelsemedlem"
                    },
                    {
                        "name": "fabr. Carl Eric Cedervall",
                        "role": "Styrelsemedlem"
                    }
                ],
                "director": "C. E. Cedervall"
            },
            {
                "name": "Cehå",
                "location": "Borlänge",
                "business": "Tillverkar kolvpumpar, djupbrunns-pumpar samt hydroforaggregat vid mek. verkstad i Töreboda (Skarab. l.)",
                "contact": {
                    "office": "Borlänge",
                    "phone": [
                        "10154"
                    ],
                    "postgiro": "84371"
                },
                "financials": {
                    "capital": "41,000 kr",
                    "employees": {
                        "industriarb": 15
                    },
                    "annual_turnover": "275,000 kr"
                },
                "foundation_year": 1933,
                "board": [
                    {
                        "name": "fabr. Carl H. Swahn",
                        "role": "Verkställande direktör"
                    }
                ],
                "director": "fabr. Carl H. Swahn"
            },
            {
                "name": "Cellufix AB.",
                "location": "Stockholm",
                "business": "Se Svartviks AB., Sundsvall.",
                "financials": {
                    "capital": "2,236,000 kr",
                    "employees": {
                        "industriarb": 400
                    },
                    "annual_turnover": "Not available"
                },
                "foundation_year": 1941,
                "board": [
                    {
                        "name": "dir. Albin Johansson",
                        "role": "Ordförande"
                    },
                    {
                        "name": "disp. Chr. v. Sydow",
                        "role": "Vice ordförande"
                    },
                    {
                        "name": "civiling. Gunnar Berg",
                        "role": "Styrelsemedlem"
                    },
                    {
                        "name": "dir. Hugo Edstam",
                        "role": "Styrelsemedlem"
                    },
                    {
                        "name": "dir. Nils Engberg",
                        "role": "Styrelsemedlem"
                    },
                    {
                        "name": "dir. Ernst Persson",
                        "role": "Styrelsemedlem"
                    }
                ],
                "director": "C. Lindquist (Norrköp.)",
                "manager": "C. Lindquist (Norrköp.)"
            },
            {
                "name": "CeMuloidindustri, Svensk",
                "location": "Gislaved",
                "business": "Se Svensk Celluloidindustri AB., Gislaved."
            },
            {
                "name": "Cementa, Svenska Cementförsäljnings AB.",
                "location": "Malmö",
                "business": "Försäljningsorganisation för cement från Skånska Cement AB., Malmö, med fabriker i Limhamn, Hällekis och Köping, Ölands Cement AB., Degerhamn, Slite Cement och Kalk AB., SI i te, och Hidinge Kalkverk AB., Lannabruk."
            },
            {
                "name": "Cementol, Isolerings AB.",
                "location": "Göteborg",
                "business": "Se Isolerings AB. Cementol, Göteborg."
            },
            {
                "name": "AB. Cementrör",
                "location": "Tärnsjö",
                "business": "Tillverkar betongrör, kulvertar, brunnsringar, betonghålsten med och utan isoleringsplattor, cementtegel m. m. vid fabrik i Tärnsjö (Västmanl. l.)",
                "contact": {
                    "office": "Tärnsjö",
                    "phone": [
                        "3"
                    ],
                    "postgiro": "33461"
                },
                "financials": {
                    "capital": "45,000 kr",
                    "employees": {
                        "industriarb": 9
                    },
                    "annual_turnover": "70,000 kr"
                },
                "foundation_year": 1916,
                "director": "grossh. Karl J. Norén"
            },
            {
                "name": "Center Sport",
                "location": "Stockholm",
                "business": "Tillverkar badmintonbollar.",
                "contact": {
                    "office": "Beridarbansg. 21, Stockholm",
                    "phone": [
                        "209828",
                        "110912"
                    ],
                    "postgiro": "151366"
                },
                "employees": 20,
                "manager": "dir. Oscar C:son Swahn"
            },
            {
                "name": "AB. Centrala Kartongfabriken",
                "location": "Stockholm",
                "business": "Fabrik i Ulvsunda, Stockholm, för förpackningar av papp, aromtät livsmedelsförpackning, kartong och papper samt offsettryckeri. Förpackningsservice.",
                "contact": {
                    "office": "Ekbacksvägen 32—34, Ulvsunda",
                    "phone": [
                        "252690"
                    ],
                    "postgiro": "52696"
                },
                "financials": {
                    "capital": "80,400 kr",
                    "employees": {
                        "industriarb": 65
                    },
                    "annual_turnover": "1,700,000 kr"
                },
                "foundation_year": 1916,
                "corporation_year": 1931,
                "board": [
                    {
                        "name": "konsul Axel Christensson",
                        "role": "Ordförande"
                    },
                    {
                        "name": "dir. Alf Christensson",
                        "role": "Styrelsemedlem"
                    }
                ],
                "director": "Alf Christensson",
                "manager": "Alf Christensson"
            }
        ]
    }
}