{
    "original": "Ilä ttvik—-Il örstrand\n\nkullans bröd» o. »Siljansbröd».\n\nTelefon: 83. Postgiro: 33782. —\nAkt.-kap.: 95,000 kr. Antal industriarb.: 35.\nTillv.-värde pr år: 525,000 kr. — Bolaget\ngrundat; 1928.\n\nVerkst. dir.: Karl J. Gustafsson.\n\nRättviks Textil, Rättvik.\n\nUllspinneri och trikåfabrik samt kem.\nt vättanstalt i Rättvik (Kopparb. l.).\nTillverkar filtar, raggsockor, toppmössor,\nvantar, herrtröjor, damjumpers m. m.;\nutför löngodsspinning och kem. tvätt.\nVarumärke: »R T».\n\nTelefon: »Rättviks Textil». Postgiro:\n162778. — Antal industriarb.: 60. —\nFirman etabl. 1939.\n\nÄgare o. chef: fabr. Gustaf Andersson.\n\n\"Röbo Tegelbruk, Uppsala.\n\nSe AB» Mälardalens Tegelbruk, Sthlm.\n\nAB. Rönnarps Makadamfabrik,\n\nTågarp. .\n\nTillverkar makadam och spar st en vid\nfabrik i Rönnarp, Tågarp (Malmöh. l.).\n\nTelefon: 33. Postgiro: 91823. —\nAkt.-kap.: 40,000 kr. Antal industriarb.: 20.\nProd.-värde pr år: 145,000 kr. — Bolaget\ngrundat 1935.\n\nVerkst. dir.: köpm. Thure Lundberg.\n\nAB. P. Rönning &amp; Cjerlöff,\n\nHälsingborg.\n\nKem.-tékn. fabrik. Tillverkar bläck,\ntusch, .stämpelfärger, radérvatten, klister,\ngummi, lim m. m. samt\ntakkonserveringsmedel, takfärger och träfärger.\n\nTelegr.-adr.: Gjerlöffs, Hälsingborg.\nTelefon: 11954. Postgiro: 10150. Repr. i\nStockholm: Otto Ekström AB.,\nSmå-landsg. 38, telefon: 105118.\n\nAkt.-kap.: 25,000 kr. Arb.-antal: 10.\nTillv.-värde pr år: 250,000 kr. —\nBolaget grundat 1911.\n\nDisp.: Einar Ekström.\n\nAB. Rönninge Handskfabrik,\n\nStockholm.\n\nTillverkar herr- och damhandskar vid\nfabrik i Rönninge (Sthlms l.).\nVarumärke: »Renola».\n\nKontor: Stockholm, Mästersamuelsg.\n63. Telefon: 213918. Postgiro: 156631.\n\nAkti-kap.: 30,000 kr. Antal\nindustriarb.: 60. —’ Bolaget grundat 1937.\n\nVerkst. dir.: Leon Lapidus.\n\n*Rönnqvist &amp; Söner AB., Örebro.\n\nMek. verkstad, metallvarufabrik och\nmodellsnickeri. Tillverkar spec. skedar,\ngafflar och knivar i nysilver och i\nrostfritt material samt excenterpressar med\n6—110 tons tryck och\nfriktionsskruv-pressar från 30 upp till 500 tons tryck.\n\nTelefon: 19175. Postgiro: 90222.\n\nAkt.-kap.: 300,000 kr. Antal\nindustriarb.: 70. Tillv.-värde pr år: 2,000,000 kr.\n— Firman etabl. 1894, bolag 1945.\n\nStyrelse: disp. Paul RÖnnqvist (ordf.),\nmajor John Cederblad, civiling. Georg\nNordberg.\n\nVerkst. dir.: Paul Rönnqvist.\n\n\"Rönnskärs Smältverk, Skelleftehamn,\n\nSe Bolidens Gruv AB., Skelleftehamn.\n\nRörklammerfabriken, Arvid Lindtte,\n\nEksjö.\n\nTillverkar skruv- och stamklammer,\nin-murningsklammer, stiftklammer,\nklam-svep, rörkrok, skarvrör, golvluckor m. m.\n\nTelefon: 885. Postgiro: 87775. —\nAntal industriarb.: 7. Tillv.-värde pr år:\n85,000 kr. — Firman etabl. 1931.\n\nÄgare o. chef: fabr. Arvid Lindhe.\n\n\"AB. Rörstrands Porslinsfabriker,\n\nLidköping.\n\nPorslinsfabrik i Lidköping.\n\nTillverkar husgeråds- och\nprydnadsartiklar i fältspatäkta porslin och i\nflintporslin samt porslin för tekniska\nändamål. Varumärke: »Rörstrand».\n\nHuvudkontor: Lidköping. Telegr.-adr.\no. telefon: Rörstrand, Lidköping.\nPostgiro: 8809. Försäljningskontor i\nStockholm, Drottningg. 18, telefon: 104461.\n\nAkt.-kap.: 4,000,000 kr. Tillv.-väfde, pr\når : 7,000,000 kr.\n\nBolaget har 1935 i sig upptagit AB.\nLidköpings Porslinsfabrik, Lidköping,\n\nDen sedan 1726 drivna porslinsfabriken\nvid Rörstrand i Stockholm överfördes\n1926 till Göteborg i och med övertagandet\nav Göteborgs Porslinsfabrik, anlagd år\n1900; AB. Lidköpings Porslinsfabrik\ninförlivades med Rörstrand 1928 och\nutbyggdes fabriken, som anlagts 1910,\ngenom nybyggnad 1936; år 1940 nedlades\ndriften vid Göteborgsfabriken och\növerfördes hela fabrikationen till\nLidköpings-fabrikerna.\n\nStyrelse: dir. Ernst Wehtje (ordf.),\nadv. Gösta Grönberg, dir. Kuno Möller,\növerstelöjtn. Carl O. A. Nyström» dir.\nFredrik Wehtje.\n\nVerkst. dir.: Fredrik Wehtje.\n\n46 3*",
    "structured": {
        "1": {
            "name": "Ilä ttvik—-Il örstrand",
            "location": "Rättvik",
            "business": "Ullspinneri och trikåfabrik samt kem. t vättanstalt",
            "products": "Tillverkar filtar, raggsockor, toppmössor, vantar, herrtröjor, damjumpers m. m.; utför löngodsspinning och kem. tvätt",
            "contact": {
                "office": "Rättviks Textil, Rättvik",
                "phone": [
                    "Rättviks Textil"
                ],
                "postgiro": "162778"
            },
            "financials": {
                "capital": "95,000 kr",
                "employees": {
                    "industriarb": 60
                },
                "annual_turnover": "525,000 kr",
                "annual_production_value": "525,000 kr"
            },
            "foundation_year": 1928,
            "director": "Karl J. Gustafsson"
        },
        "2": {
            "name": "AB. Röbo Tegelbruk",
            "location": "Uppsala",
            "business": "Tillverkar makadam och spar sten",
            "contact": {
                "office": "AB. Mälardalens Tegelbruk, Sthlm"
            },
            "financials": {
                "capital": "40,000 kr",
                "employees": {
                    "industriarb": 20
                },
                "annual_turnover": "145,000 kr",
                "annual_production_value": "145,000 kr"
            },
            "corporation_year": 1935,
            "director": "köpm. Thure Lundberg"
        },
        "3": {
            "name": "AB. Rönnarps Makadamfabrik",
            "location": "Tågarp",
            "business": "Kem.-tékn. fabrik",
            "products": "Tillverkar bläck, tusch, stämpelfärger, radérvatten, klister, gummi, lim m. m.; taktak konservingsmedel, takfärger och träfärger",
            "contact": {
                "office": "Gjerlöffs, Hälsingborg",
                "phone": "11954",
                "postgiro": "10150"
            },
            "financials": {
                "capital": "25,000 kr",
                "employees": {
                    "arb": 10
                },
                "annual_turnover": "250,000 kr"
            },
            "foundation_year": 1911,
            "board": [
                {
                    "name": "Einar Ekström",
                    "role": "Disp."
                }
            ]
        },
        "4": {
            "name": "AB. Rönninge Handskfabrik",
            "location": "Stockholm",
            "business": "Tillverkar herr- och damhandskar",
            "products": "Tillverkar herr- och damhandskar vid fabrik i Rönninge (Sthlms l.)",
            "contact": {
                "office": "Stockholm, Mästersamuelsg. 63",
                "phone": "213918",
                "postgiro": "156631"
            },
            "financials": {
                "capital": "30,000 kr",
                "employees": {
                    "industriarb": 60
                },
                "corporation_year": 1937
            },
            "manager": "Leon Lapidus"
        },
        "5": {
            "name": "Rönnqvist &amp; Söner AB.",
            "location": "Örebro",
            "business": "Mek. verkstad, metallvarufabrik och modellsnickeri",
            "products": "Tillverkar spec. skedar, gafflar och knivar i nysilver och i rostfritt material samt excenterpressar med 6—110 tons tryck och friktionsskruv-pressar from 30 upp till 500 tons tryck",
            "contact": {
                "office": "Rönnskärs Smältverk, Skelleftehamn",
                "phone": "19175",
                "postgiro": "90222"
            },
            "financials": {
                "capital": "300,000",
                "employees": {
                    "industriarb": 70
                },
                "annual_turnover": "2,000,000 kr"
            },
            "corporation_year": 1945,
            "board": [
                {
                    "name": "Paul Rönnqvist",
                    "role": "Disp."
                },
                {
                    "name": "John Cederblad",
                    "role": "Major"
                },
                {
                    "name": "Georg Nordberg",
                    "role": "Civiling."
                }
            ],
            "director": "Paul Rönnqvist"
        },
        "6": {
            "name": "Rörklammerfabriken, Arvid Lindtte",
            "location": "Eksjö",
            "business": "Tillverkar skruv- och stamklammer, inmurningsklammer, stiftklammer, klamsvep, rörkrok, skarvrör, golvluckor m. m.",
            "contact": {
                "office": "Arvid Lindhe",
                "phone": "885",
                "postgiro": "87775"
            },
            "financials": {
                "employees": {
                    "industriarb": 7
                },
                "annual_turnover": "85,000 kr"
            },
            "foundation_year": 1931,
            "manager": "Arvid Lindhe"
        },
        "7": {
            "name": "AB. Rörstrands Porslinsfabriker",
            "location": "Lidköping",
            "business": "Porslinsfabrik",
            "products": "Tillverkar husgeråds- och prydnadsartiklar i fältspatäkta porslin och i flintporslin samt porslin för tekniska ändamål",
            "contact": {
                "office": "Lidköping",
                "phone": "Rörstrand, Lidköping",
                "postgiro": "8809"
            },
            "financials": {
                "capital": "4,000,000 kr",
                "annual_production_value": "7,000,000 kr"
            },
            "board": [
                {
                    "name": "Ernst Wehtje",
                    "role": "Dir."
                },
                {
                    "name": "Gösta Grönberg",
                    "role": "Adv."
                },
                {
                    "name": "Kuno Möller",
                    "role": "Dir."
                },
                {
                    "name": "Carl O. A. Nyström",
                    "role": "Överstelöjtn."
                },
                {
                    "name": "Fredrik Wehtje",
                    "role": "Dir."
                }
            ],
            "director": "Fredrik Wehtje"
        }
    }
}