{
    "original": "Tollar e—Tornborg\n\nKontor: Kungsg. 15. Telegr.-adr.:\nByggtoll, Stockholm. Telefon: 231800,\n100798, 115468 o. 115478. Postgiro: 4830.\n\nAkt.-kap.: 1,000,000 kr.\nProduktionsvärde pr år: 9,000,000 kr. — Firman\ngrundad 1917.\n\nStyrelse: kanslirådet Axel Lekänder\n(ordf.), revisor Arne Henrikson, ing. Leo\nNordquist, civiling. Carl Gustaf Toll,\nkapten Gustav Vestin.\n\nVerkst. dir.: Carl Gustaf Toll.\n\nKamrer: Henning Löfstedt.\n\n\"AB. Tollare Pappersbruk,\n\nStockholm.\n\nPappersbruk med trämassefabrik vid\nTollare, Bo (Sthlms l.). Tillverkar\nomslagspapper och tryckpapper.\n\nPostadr.: Stockholm 15. Telegr.-adr.:\nTollare, Stockholm. Telefon: Stockholm\n150030. Postgiro: 52700.\n\nAkt.-kap.: 2,000,000 kr. Antal\nindustriarb.: 135. Årstillv.: 12.000 ton papper. —\nFabriken anlagd 1923, sliperiet 1927,\nbolag 1926.\n\nStyrelse: bankdir. H. Bexelius (ordf.),\nadv. Nils Berglund, fru Jane\nHedenström, disp. Sigurd Lind, dir. Gustaf B.\nSöderlund.\n\nVerkst. dir.: Sigurd Lind.\nDriftsing.: Bror Andersson.\n\n\"Tomelilla Konfektion, Tomelilla.\nSe Palms Konfektionsfabrik, Tomelilla.\n\n\"Tomten, Fabriken, Stockholm.\n\nSe Fabriken Tomten, Alex. Lagerman\nJ:r, AB., Stockholm.\n\nTomtens Kalkbruks AB.,\n\nTorbjörntorp.\n\nKalkbruk vid Torbjörntorp (Skarab. l.).\nTillverkar bränd, osläckt kalk för\njordbruks- och byggnadsändamål samt bränd\nsläckt kalk.\n\nTelefon: Falköping 611 o. Torbjörntorp\n34. Postgiro: 26826.\n\nAkt.-kap.: 112,000 kr. Antal\nindustriarb.: 100. Tillv.-värde pr år: 500,000 kr.\n— Bolaget grundat 1913.\n\nStyrelse: disp. John Torstensson\n(ordf.), ing. Bengt Torstensson, notarie\nÅke Thorstensson.\n\nDisp.: John Torstensson.\n\nAB. Torebo Cementgjuteri,\n\nUddevalla.\n\nTillverkar muff ror, väg- och kulvertrör,\ntrumögon, gatubrunnar, brunnsringar,\nväg- och trottoarplattor, kabelskydd,\npool-block m. m.\n\nHuvudkontor: Uddevalla. Telefon:\n11922. Postgiro: 161305.\n\nAkt.-kap.: 57,000 kr. Antal\nindustriarb.: 20. — Firman etabl. 1921, bolag\n1944.\n\nVerkst. dir.: Robert Hansson.\n\nAB. J. W. Torell, Linköping.\n\nTillverkar kylare till bilar, traktorer,\nvägmaskiner och stationära motorer m.\nm.; utför tunnplåtsarbeten.\n\nTelefon: 29935. Postgiro: 84022. —\nAkt.-kap.: 35,000 kr. Antal industriarb.:\n45. Tillv.-värde pr år: 450,000 kr. —\nFirman etabl. 1894.\n\nVerkst. dir.: fabr. Olof Torell.\n\nToréns Mek. Verkstads AB.,\n\nKarlshamn.\n\nMek. verkstad, metall gjuteri samt\nrör-läggeri för värme- och\nsanitetsanlägg-ningar. Tillverkar hjul för sjukhussängar,\nutomhusfrånskiljare för\nhögspännings-ledningar m. m. samt metallgjutgods.\n\nTelefon: 10. Postgiro: 96990. —\nAkt.-kap.: 65,000 kr. Antal industriarb.: 26.\n— Firman etabl. 1901.\n\nVerkst. dir.: fabr. Folke Torén.\n\nAB. Torkapparater, Stockholm.\n\nKonstruerar och låter vid olika\nverkstäder tillverka industriella\ntorkanläggningar och luftförvärmare.\n\nKontor: Sveavägen 28—30.\nTelegr.-adr.: Torkapparater, Stockholm. Telefon:\n104650 o. 104651. Postgiro: 152688.\n\nAkt.-kap.: 30,000 kr. Tillv.-värde pr år:\n500,000 kr. — Bolaget grundat 1937.\nStyrelse o. verJcst. dir.: ing. G. Bojner.\n\n\"Tornborg &amp; Lundberg AB.,\n\nStockholm.\n\nReparations- och serviceverkstad vid\nÅrstadalshamnen, Stockholm. Firman\ndriver såsom huvudrörelse försäljning av\nmaskiner och är försäljningsorganisation\nför Sala Maskinfabriks AB., Gullbergs\nMaskinfabriks AB. m. fl. verkstäder.\nSpecialiteter: maskiner och redskap för\nbyggnadsindustrien, för vägbyggnader och för\nträindustrien samt kätting och\nkätting-hjul.\n\n581*",
    "structured": {
        "1": {
            "name": "Tollar e—Tornborg",
            "location": "Stockholm",
            "business": "Fabrikation och försäljning av omslagspapper och tryckpapper",
            "contact": {
                "office": "Kungsg. 15",
                "phone": [
                    "231800",
                    "100798",
                    "115468",
                    "115478"
                ],
                "postgiro": "4830",
                "telegraph": "Byggtoll, Stockholm"
            },
            "financials": {
                "capital": "1,000,000 kr",
                "annual_production_value": "9,000,000 kr"
            },
            "foundation_year": 1917,
            "board": [
                {
                    "name": "kanslirådet Axel Lekänder",
                    "role": "ordf."
                },
                {
                    "name": "revisor Arne Henrikson",
                    "role": null
                },
                {
                    "name": "ing. Leo Nordquist",
                    "role": null
                },
                {
                    "name": "civiling. Carl Gustaf Toll",
                    "role": null
                },
                {
                    "name": "kapten Gustav Vestin",
                    "role": null
                }
            ],
            "director": "Carl Gustaf Toll"
        },
        "2": {
            "name": "AB. Tollare Pappersbruk",
            "location": "Tollare, Bo (Sthlms l.)",
            "business": "Tillverkning av omslagspapper och tryckpapper",
            "contact": {
                "office": null,
                "phone": [
                    "Stockholm 150030"
                ],
                "postgiro": "52700"
            },
            "financials": {
                "capital": "2,000,000 kr"
            },
            "foundation_year": 1923,
            "board": [
                {
                    "name": "bankdir. H. Bexelius",
                    "role": "ordf."
                },
                {
                    "name": "adv. Nils Berglund",
                    "role": null
                },
                {
                    "name": "fru Jane Hedenström",
                    "role": null
                },
                {
                    "name": "disp. Sigurd Lind",
                    "role": null
                },
                {
                    "name": "dir. Gustaf B. Söderlund",
                    "role": null
                }
            ],
            "director": "Sigurd Lind"
        },
        "3": {
            "name": "Tomtens Kalkbruks AB.",
            "location": "Torbjörntorp (Skarab. l.)",
            "business": "Tillverkning av bränd, osläckt kalk för jordbruks- och byggnadsändamål samt bränd släckt kalk",
            "contact": {
                "office": null,
                "phone": [
                    "Falköping 611",
                    "Torbjörntorp 34"
                ],
                "postgiro": "26826"
            },
            "financials": {
                "capital": "112,000 kr",
                "annual_production_value": "500,000 kr"
            },
            "foundation_year": 1913,
            "board": [
                {
                    "name": "disp. John Torstensson",
                    "role": "ordf."
                },
                {
                    "name": "ing. Bengt Torstensson",
                    "role": null
                },
                {
                    "name": "notarie Åke Thorstensson",
                    "role": null
                }
            ],
            "director": "disp. John Torstensson"
        },
        "4": {
            "name": "AB. Torebo Cementgjuteri",
            "location": "Uddevalla",
            "business": "Tillverkning av muff ror, väg- och kulvert-rör, trumögon, gatubrunnar, brunnsringar, väg- och trottoarplattor, kabelskydd, pool-block m. m.",
            "contact": {
                "office": null,
                "phone": [
                    "11922"
                ],
                "postgiro": "161305"
            },
            "financials": {
                "capital": "57,000 kr"
            },
            "foundation_year": 1921,
            "director": "Robert Hansson"
        },
        "5": {
            "name": "AB. J. W. Torell",
            "location": "Linköping",
            "business": "Tillverkning av kylare till bilar, traktorer, vägmaskiner och stationära motorer m. m.; utför tunnplåtsarbeten",
            "contact": {
                "office": null,
                "phone": [
                    "29935"
                ],
                "postgiro": "84022"
            },
            "financials": {
                "capital": "35,000 kr",
                "annual_production_value": "450,000 kr"
            },
            "foundation_year": 1894,
            "director": "fabr. Olof Torell"
        },
        "6": {
            "name": "Toréns Mek. Verkstads AB.",
            "location": "Karlshamn",
            "business": "Mek. verkstad, metall gjuteri samt rör-läggeri för värme- och sanitetsanläggningar",
            "contact": {
                "office": null,
                "phone": [
                    "10"
                ],
                "postgiro": "96990"
            },
            "financials": {
                "capital": "65,000 kr"
            },
            "foundation_year": 1901,
            "director": "fabr. Folke Torén"
        },
        "7": {
            "name": "AB. Torkapparater",
            "location": "Stockholm",
            "business": "Konstruktion av industriella torkanläggningar och luftförvärmare",
            "contact": {
                "office": "Sveavägen 28—30",
                "phone": [
                    "104650",
                    "104651"
                ],
                "postgiro": "152688",
                "telegraph": "Torkapparater, Stockholm"
            },
            "financials": {
                "capital": "30,000 kr",
                "annual_production_value": "500,000 kr"
            },
            "foundation_year": 1937,
            "director": "ing. G. Bojner"
        },
        "8": {
            "name": "Tornborg & Lundberg AB.",
            "location": "Stockholm",
            "business": "Reparations- och serviceverkstad samt försäljning av maskiner",
            "contact": {
                "office": "Årstadalshamnen, Stockholm",
                "phone": null,
                "telegraph": null
            },
            "foundation_year": null,
            "board": null,
            "director": null
        }
    }
}