{
    "original": "S tallberg—Sunds\n\nTelefon: 164. — Akt.-kap.: 150,000 kr.\nAntal industriarb.: 18. Årstillv.: 1,9\nmilj. st. tegelvaror. — Firman grundad\n1917.\n\nStyrelse: grossh. John Andersson\n(ordf.), häradsdom. Nils Andersson (v.\nordf.), disp. H. Markborn, ing. B. Sjö\nbron, köpm. Gösta Sjöström.\n\nVerkst. dir..- B. Sjöbron.\n\n*Ställhergs Grufve AB., Ludvika.\n\nGruvdrift vid Ställberg (Örebro l.)\nsamt vid Hillängsgruvan, Ludvika.\nBryter järnmalm med hög manganhalt (5 å\n11 %); försäljer jämväl fosforren\nblod-stensmalm och järnmalmsslig från Stripa\nGruv AB. (se detta bolag) samt järnmalm\nmed hög fosforhalt från Idkerbergets\nGruf AB.\n\nKontor: Ludvika. Telefon:\n»Ställ-bergsbolagen». Postgiro: 94183.\n\nAkt.-kap.: 2,100,000 kr. Antal\nindustriarb.: 125. — Bolaget, grundat 1880, äger\nIdkerbergets Gruf AB.\n\nStyrelse: hovstallmäst. frih. G. A.\nKlingspor (ordf.), kabinettskammarh.\nRobert v. Horn, kammarh. frih. B.\nKlingspor, hovjägm. frih. Wilh. Klingspor,\nadv. Hugo Stenbeck.\n\nVerkst. dir. o. disp.: B. Stein.\n\növering.: Sven Dalhammar.\n\nKamrer: Axel Frö vik.\n\n\"Ställdalens Bruk, Ställdalen.\n\nSe AB. S t jernf or s-Ställdalen,\nStälldalen.\n\n\"AB. Stängselfabriken, Göteborg.\nSe Nya AB. Stängselfabriken, Göteborg.\n\n\"AB. Stängselnät i Rydsgård,\n\nBydsgård.\n\nSe Nya AB. Stängselnät i Rydsgård,\nRydsgård.\n\n\"Stängselnäts AB., Svenska, Malmö.\nSe. Svenska Stängselnäts AB., Malmö.\n\n\"Stödstorps Sulfatfabrik, Vaggeryd.\nSe Munksjö AB., Jönköping.\n\n\"Suchard AB., Svenska, Lidköping.\nSe Svenska Suchard AB., Lidköping.\n\nSueciaverken Motor AB., Malmö.\n\nMeL verkstad i örkelljunga (Kristianst.\n1.). Tillverkar helautomatiska\noljeeldningsapparater, maskiner för\nlivsmedelsindustrin, ventilationsfläktar m. m.\nVarumärke: »Suecia».\n\nHuvudkontor: Malmö, Rundelsg. 14.\nTelegr.-adr.: Sueciaverken, Malmö. Telefon:\n14911. Postgiro: 24527. Fabrikskontor:\nörkelljunga. Telegr.-adr.: Sueciaverken,\nörkelljunga. Telefon: 175.\n\nAkt.-kap.: 60,000 kr. Antal\nindustriarb.: 40. — Bolaget grundat 1928.\n\nStyrelse: ryttm. Hugo Wehtje (ordf.),\nkamrer Nils Hagerström, disp. Thure\nJakobsson.\n\nVerkst. dir.: Hugo Wehtje.\n\nDisp.: Th. Jakobsson.\n\nFabrikschef: A. Helldov.\n\n\"Sulfit AB. Göta, Göta.\n\nSulfitfabrik och sulfitspritfabrik i\nGöta (Älvsb. l.). Tillverkar sulfitcellulosa,\nkvistmassa, ethylalkohol och indunstad\nsulfitlut samt cellulosa jäst. Bolaget idkar\njämväl jordbruk, skogshantering och\nrederirörelse.\n\nHuvudkontor: Göta. Telegr.-adr.: Göta,\nLilla Edet. Telefon: Lilla Edet 67.\nSkogskontor: Karlstad.\n\nAkt.-kap.: 1,625,000 kr. Antal\nindustriarb.: 275. Årstillv.: 75,000 ton 50 % våt,\nstark sulfitmassa, 2,500,000 ltr\nsulfitsprit. — Bolaget, grundat 1905, är\ndotterbolag till Uddeholms AB.\n\nStyrelse: disp. Nils Danielsen (ordf.),\ndir. Valdemar Hellgren, disp. Gösta\nRyding.\n\nVerkst. dir.: Gösta Ryding.\n\n\"Sulfit AB. Ljusnan, Vallvik.\n\nSe Marma—Långrörs AB., Söderhamn.\n\n\"Sund—Skön viks Verkstäder,\n\nSundsbruk.\n\nSe Sunds AB. o. Skönviks AB. samt\nSundsvallsbolagens Gemensamma\nFörvaltning AB., Sundsvall.\n\n\"Sunds AB., Sundsvall.\n\nSågverk, gjuteri och mek. verkstad samt\nslip i Sundsbruk, trähusfabrik i Nyvik,\nsulfitfabrik och sulfitspritfabrik i\nSör-åker (samtl. i Västernorrl. l.).\n\nTillverkar sågade trävaror,\nmonteringsfärdiga trähus, sulfitcellulosa och\nsulfitsprit samt ångmaskiner och ångpannor,\nbogserbåtar, sågverksmaskiner,\ngrovplåts-arbeten, tackjärnsgjutgods m. m. Bolaget\nidkar jämväl jordbruk och skogshantering.\n\n520*",
    "structured": {
        "1": {
            "name": "Ställbergs Grufve AB.",
            "foundation_year": 1880,
            "business": "Gruvdrift",
            "location": "Ludvika",
            "contact": {
                "office": "Ställberg, Ludvika",
                "phone": [
                    "Ställbergsbolagen"
                ],
                "postgiro": "94183"
            },
            "financials": {
                "capital": "2,100,000 kr",
                "employees": {
                    "total": 125
                }
            },
            "board": [
                {
                    "name": "hovstallmäst. frih. G. A. Klingspor",
                    "role": "ordf."
                },
                {
                    "name": "kabinettskammarh. Robert v. Horn",
                    "role": null
                },
                {
                    "name": "kammarh. frih. B. Klingspor",
                    "role": null
                },
                {
                    "name": "hovjägm. frih. Wilh. Klingspors",
                    "role": null
                },
                {
                    "name": "adv. Hugo Stenbeck",
                    "role": null
                }
            ],
            "director": "B. Stein",
            "managing_director": "Sven Dalhammar"
        },
        "2": {
            "name": "Sueciaverken Motor AB.",
            "foundation_year": 1928,
            "business": "Tillverkning av oljeeldningsapparater, maskiner för livsmedelsindustrin, ventilationsfläktar m. m.",
            "location": "Malmö",
            "contact": {
                "office": "Rundelsg. 14, Malmö",
                "phone": [
                    "14911"
                ],
                "postgiro": "24527",
                "factory_office": "Örkelljunga",
                "factory_phone": "175"
            },
            "financials": {
                "capital": "60,000 kr",
                "employees": {
                    "total": 40
                }
            },
            "board": [
                {
                    "name": "ryttm. Hugo Wehtje",
                    "role": "ordf."
                },
                {
                    "name": "kamrer Nils Hagerström",
                    "role": null
                },
                {
                    "name": "disp. Thure Jakobsson",
                    "role": null
                }
            ],
            "director": "Hugo Wehtje",
            "managing_director": null
        },
        "3": {
            "name": "Sulfit AB. Göta",
            "foundation_year": 1905,
            "business": "Sulfitfabrik och sulfitspritfabrik",
            "location": "Göta (Älvsb. l.)",
            "contact": {
                "office": "Göta",
                "phone": [
                    "Lilla Edet 67"
                ]
            },
            "financials": {
                "capital": "1,625,000 kr",
                "employees": {
                    "total": 275
                }
            },
            "board": [
                {
                    "name": "disp. Nils Danielsen",
                    "role": "ordf."
                },
                {
                    "name": "dir. Valdemar Hellgren",
                    "role": null
                },
                {
                    "name": "disp. Gösta Ryding",
                    "role": null
                }
            ],
            "director": "Gösta Ryding",
            "managing_director": null
        },
        "4": {
            "name": "Sunds AB.",
            "business": "Sågverk, gjuteri och mek. verkstad samt gulbricki i Sundsbruk, trähusfabrik i Nyvik, sulfitfabrik och sulfitspritfabrik i Sör-åker (samtl. i Västernorrl. l.)",
            "location": "Sundsbruk",
            "financials": {
                "employees": {
                    "total": 520
                }
            }
        }
    }
}