{
    "original": "Bråse—Bröderna\n\nHans Bråse &amp; Söner,\n\nKlädesholmen.\n\nKonservfabrik å Klädesholmen (Göteb.\no. Bohus l.). Tillverkar sillkonserver,\nspillånga och kabeljo samt kaf feklarmedel.\nVarumärke: »Sälen».\n\nTelefon: 36. Postgiro: 74830. — Antal\nindustriarb.: 25. Tillv.-värde pr år:\n250,000 kr. — Firman etabl. 1917.\n\nÄgare o. chef: fabr. Anders G. Bråse.\n\n*AB. Bräcke Trähusfabrik, BräcTce.\n\nTillverkar monteringsfärdiga trähus\nvid fabrik i Bräcke (Jämtl. l.).\n\nTelefon: 14. Postgiro: 287656.\n\nAkt.-kap.: 50,300 kr. Antal\nindustriarb.: 14. — Bolaget grundat 1944.\n\nStyrelse: handl. Adolf Ericson (ordf.),\ning. Petter Edling, disp. Stig Edling.\n\nVerkst. dir.: Adolf Ericson.\n\nAB. Bräcke Ångsåg, Bräcke.\n\nSågverk och hyvleri i Bräcke (Jämtl.\n1.). Tillverkar sågade och hyvlade\nträvaror, stav samt ribbtugg.\n\nTelegr.-adr.: Ångsågen, Bräcke.\nTelefon: 20. Postgiro: 22241. — Akt.-kap.:\n250,000 kr. Antal industriarb.: 40.\nÅrstillv.: 400 stds sågade och 1,400 stds\nhyvlade trävaror samt 100 stds övriga\nträvaror. — Sågverksrörelsen började 1879,\nnuv. bolag grundat 1938.\n\nDisp.: Stig Edling.\n\n*Brännlands Nya Träförädlings AB.,\n\nBrännland.\n\nSågverk, hyvleri och snickerifabrik i\nBrännland (Västerbott. l.) samt sågverk\noch hyvleri i Umeå. Tillverkar sågade och\nhyvlade trävaror samt byggnadssnickerier.\n\nTelegr.-adr.: Träförädlingen,\nBrännland. Telefon: 1. Postgiro: 62450.\n\nAkt.-kap.: 110,000 kr.\nAntal^industriarb.: 15. Årstillv.: 1,200 stds sågade och\n700 stds hyvlade trävaror. — Bolaget\ngrundat 1902, ombildat 1923.\n\nStyrelse: disp. J. Arv. Wiklund (ordf.),\ndir. Karl-Gustav Andersson, landstingsm.\nEric Emanuelsson.\n\nDisp.: J. Arv. Wiklund.\n\nKontorschef: G. Seeman.\n\nBrännströms Mek. Verkstad,\n\nSkellefteå.\n\nSe AB. Bröderna Brännströms Mek.\nVerkstad, Skellefteå.\n\n’Bröderna Alström, Fabriks AB-,\n\nBorås.\n\nSe Fabriks AB. Bröderna Alström,\nBorås.\n\n*AB. Bröderne Ameln, Stockholm.\n\nKonservfabriker i Gravarne (Göteb. o.\nBohus l.) och Göteborg. Tillverkar\nfisk-och sillkonserver. Varumärken: »Abba»,\n»Munken», »Bullen», »Makalös» m. fl.\nFirman driver jämväl engroshandel med\nsill, lax, torrfisk och salt.\n\nHuvudkontor: Stockholm, Värtan;\npost-adr.: Stockholm 7. Telegr.-adr.: Ameln,\nStockholm. Telefon: »Bröderne Ameln».\nPostgiro: 2210. Avd.-kontor: Göteborg,\nAmerikahuset, telefon: 170485;\nNorrköping, Slottsgatan 73, telefon: 29435;\nMalmö, Stora Kvarng. 36, telefon: 77625.\nTelegr.-adresser: Ameln, Göteborg,\nNorrköping och Malmö.\n\nAkt.-kap.: 1,000,000 kr. Antal\nindustri-arb.: 265.\n\nFirman etabl. såsom handelsfirma\n1838, bolag 1906, fabriksverksamheten\nbörjade 1928. Bolaget har i sig upptagit\nf. d. AB. Munkens Konservfabriker,\nGravarne.\n\nStyrelse: civiling. Bengt Ingeström\n(ordf.), dir. C. H. A. Ameln, civiling.\nRobert Ameln.\n\nVerkst. dir.: C. H. A. Ameln.\n\nKontorschef: Nils Anderson.\n\nChef för fabrikerna: ing. Stig Forssell.\n\nFabrikschefer: i Gravarne: disp.\nGunnar Stensby; i Göteborg: Stig Peterson.\n\nBröderna Andersons Farmfabrik,\n\nAlvesta.\n\nGjuteri och mek. verkstad i Alvesta\n(Kronob. l.). Tillverkar formar och\nmaskiner för glasindustrien samt\ngjutjärnsgods.\n\nTelefon: 94. Postgiro: 163348. —\nAntal industriarb.: 25. Tillv.-värde pr år:\n160,000 kr. — Firman etabl. 1919.\n\nÄgare o. chefer: fabr. Helge Anderson\no. fabr. Sten Anderson.\n\nAB. Bröderna Anderssons Gjuten,\n\nSTcurup.\n\nGjuteri, mek. verkstad och\nsnickerifabrik vid Skurup (Malmöh. l.). Tillverkar\nhalmpressar för tröskverk,\ntallriksskum-plogar, tallriksharvar (märke: »Canton»),\ntraktortallriksharvar, hästhackor\n(märken: »Skandia» o. »Hektor») samt\nsmi-desformar (märke: »Vesuvius»).",
    "structured": {
        "1": {
            "name": "Bråse—Bröderna",
            "location": "Klädesholmen",
            "business": "Konservfabrik",
            "products": "Tillverkar sillkonserver, spillånga och kabeljo samt kaf feklarmedel. Varumärke: »Sälen»",
            "contact": {
                "office": "Klädesholmen",
                "phone": [
                    "36"
                ],
                "postgiro": "74830",
                "head_office": "Klädesholmen"
            },
            "financials": {
                "capital": "N/A",
                "employees": {
                    "industrial_workers": 25
                },
                "annual_turnover": "250,000 kr",
                "annual_production_value": "N/A"
            },
            "foundation_year": 1917,
            "owners": [
                "fabr. Anders G. Bråse"
            ]
        },
        "2": {
            "name": "AB. Bräcke Trähusfabrik",
            "location": "Bräcke",
            "business": "Tillverkar monteringsfärdiga trähus",
            "contact": {
                "office": "Bräcke",
                "phone": [
                    "14"
                ],
                "postgiro": "287656"
            },
            "financials": {
                "capital": "50,300 kr",
                "employees": {
                    "industrial_workers": 14
                },
                "annual_turnover": "N/A",
                "annual_production_value": "N/A"
            },
            "foundation_year": 1944,
            "board": [
                {
                    "name": "handl. Adolf Ericson",
                    "role": "ordf."
                },
                {
                    "name": "ing. Petter Edling",
                    "role": "disp."
                },
                {
                    "name": "disp. Stig Edling",
                    "role": "N/A"
                }
            ],
            "director": "Adolf Ericson"
        },
        "3": {
            "name": "AB. Bräcke Ångsåg",
            "location": "Bräcke",
            "business": "Sågverk och hyvleri",
            "products": "Tillverkar sågade och hyvlade trävaror, stav samt ribbtugg",
            "contact": {
                "office": "Bräcke",
                "phone": [
                    "20"
                ],
                "postgiro": "22241"
            },
            "financials": {
                "capital": "250,000 kr",
                "employees": {
                    "industrial_workers": 40
                },
                "annual_turnover": "N/A",
                "annual_production_value": "400 stds sågade och 1,400 stds hyvlade trävaror samt 100 stds övriga trävaror"
            },
            "foundation_year": 1938,
            "board": [
                {
                    "name": "disp. Stig Edling",
                    "role": "N/A"
                }
            ]
        },
        "4": {
            "name": "Brännlands Nya Träförädlings AB.",
            "location": "Brännland",
            "business": "Sågverk, hyvleri och snickerifabrik",
            "products": "Tillverkar sågade och hyvlade trävaror samt byggnadssnickerier",
            "contact": {
                "office": "Brännland",
                "phone": [
                    "1"
                ],
                "postgiro": "62450"
            },
            "financials": {
                "capital": "110,000 kr",
                "employees": {
                    "industrial_workers": 15
                },
                "annual_turnover": "N/A",
                "annual_production_value": "1,200 stds sågade och 700 stds hyvlade trävaror"
            },
            "foundation_year": 1923,
            "board": [
                {
                    "name": "disp. J. Arv. Wiklund",
                    "role": "ordf."
                },
                {
                    "name": "dir. Karl-Gustav Andersson",
                    "role": "N/A"
                },
                {
                    "name": "landstingsm. Eric Emanuelsson",
                    "role": "N/A"
                }
            ],
            "manager": "G. Seeman"
        },
        "5": {
            "name": "AB. Bröderne Ameln",
            "location": "Stockholm",
            "business": "Konservfabriker",
            "products": "Tillverkar fisk-och sillkonserver. Varumärken: »Abba», »Munken», »Bullen», »Makalös» m. fl.",
            "contact": {
                "office": "Stockholm, Värtan",
                "phone": [
                    "N/A"
                ],
                "postgiro": "2210",
                "sales_offices": [
                    {
                        "location": "Göteborg",
                        "phone": "170485"
                    },
                    {
                        "location": "Norrköping",
                        "phone": "29435"
                    },
                    {
                        "location": "Malmö",
                        "phone": "77625"
                    }
                ]
            },
            "financials": {
                "capital": "1,000,000 kr",
                "employees": {
                    "industrial_workers": 265
                },
                "annual_turnover": "N/A",
                "annual_production_value": "N/A"
            },
            "foundation_year": 1928,
            "board": [
                {
                    "name": "civiling. Bengt Ingeström",
                    "role": "ordf."
                },
                {
                    "name": "dir. C. H. A. Ameln",
                    "role": "N/A"
                },
                {
                    "name": "civiling. Robert Ameln",
                    "role": "N/A"
                }
            ],
            "director": "C. H. A. Ameln",
            "manager": "Nils Anderson",
            "sales_manager": "Stig Peterson"
        },
        "6": {
            "name": "Bröderna Andersons Farmfabrik",
            "location": "Alvesta",
            "business": "Gjuteri och mek. verkstad",
            "products": "Tillverkar formar och maskiner för glasindustrien samt gjutjärnsgods",
            "contact": {
                "office": "Alvesta",
                "phone": [
                    "94"
                ],
                "postgiro": "163348"
            },
            "financials": {
                "capital": "N/A",
                "employees": {
                    "industrial_workers": 25
                },
                "annual_turnover": "160,000 kr",
                "annual_production_value": "N/A"
            },
            "foundation_year": 1919,
            "owners": [
                "fabr. Helge Anderson",
                "fabr. Sten Anderson"
            ]
        },
        "7": {
            "name": "AB. Bröderna Anderssons Gjuten",
            "location": "Skurup",
            "business": "Gjuteri, mek. verkstad och snickerifabrik",
            "products": "Tillverkar halmpressar för tröskverk, tallriksskum-plogar, tallriksharvar (märke: »Canton»), traktortallriksharvar, hästhackor (märken: »Skandia» o. »Hektor») samt smi-desformar (märke: »Vesuvius»)",
            "contact": {
                "office": "Skurup",
                "phone": [
                    "N/A"
                ],
                "postgiro": "N/A"
            },
            "financials": {
                "capital": "N/A",
                "employees": {
                    "industrial_workers": "N/A"
                },
                "annual_turnover": "N/A",
                "annual_production_value": "N/A"
            },
            "foundation_year": "N/A"
        }
    }
}