{
    "original": "Leo—Ijessebo\n\nStyrelse: bankdir. John Bergström\n(ordf.), akademifogde John Ericsson, fru\nStina Ericsson.\n\nVerkst. dir.: John Ericsson.\n\nDisp.: H. Annerman.\n\n\"AB. Leo, Hälsingborg.\n\nLäkemedelsfabrik. Tillverkar\nfarmaceu-tiska och kemiska produkter. Varumärke:\n»Leo».\n\nTelegr.-adr. o. telefon: Leo,\nHälsingborg. Postgiro: 171100. — Akt.-kap.:\n600,000 kr. Antal industriarb.: 145. —\nBolaget grundat 1914.\n\nStyrelse: ädv. Törsten Setterberg\n(ordf.), adv. Hans-Erik Bachmann,\nbankdir. C. D. Bilisten^ dir. Axel Hultman.\n\nVerkst. dir.; vakant.\n\nLerdals Sågverks AB., Rättvik.\n\nSågverk, hyvleri och kolningsverk vid\nLerdal, Rättvik (Kopparb. l.). Tillverkar\nsågade och hyvlade trävaror, träkol och\nträtjära.\n\nTelegr.-adr.: Rättsåg, Rättvik. Telefon:\n26 o. 326. Postgiro: 91654. — Akt.-kap.:\n100,000 kr. Antal industriarb.: 80.\nÅrstillv.: 3,000 stds trävaror. — Bolaget\ngrundat 1922.\n\nStyrelse; disp. Anders Hansson (ordf.),\ndisp. Karl J. Gustafsson.\n\nVerkst. dir.: Helge Wimark.\n\n\"Ler- &amp; Tegelindustri AB. Hercules\ni Christianstad, Kristianstad.\n\nTegelbruk vid Skånes Viby\n(Kristianst. l.). Tillverkar mur- och taktegel,\ndräneringsrör samt blomkrukor.\n\nHuvudkontor: Kristianstad. Telefon:\n13919. Postgiro: 98124.\n\nAkt.-kap.: 350,000 kr. Antal\nindustriarb.: 45. Årstillv.: 5 milj. st. tegelvaror.\n— Bolaget grundat 1899.\n\nStyrelse: med. lic. Ivar Borg, dir.\nHj. Oarlborn, dir. Bertil Ewe, fru Signe\nEwe, v. konsul öarl Nilsson.\n\nVerkst. dir.: Bertil Ewe.\n\nTegelm.: A. Liljekrantz.\n\nAB. Lerviks Konservfabrik,\n\nHögdals Nordby.\n\nTillverkar sardiner, herring, inkokt\nmakrill, fiskbullar m. m. vid fabrik i\nLervik, Strömstad (Göteborgs o. Bohus\n1.). Varumärken: »Queen Christina»,\n»Emblem» o. »Bohusfiskaren».\n\nPostadr.: Högdals Nordby.\nTelegr.-adr.: Jonas, Strömstad. Telefon:\nHog-dals-Nordby 3. Postgiro: 99777. Repre-\n\nsentanter: AB. O. Annerstedt, Stockholm,\nBrunkebergstorg 12, telefon: 202905;\nEmil W. Engleson. Malmö, Regementss.\n66, telefon: 25930; T. Winbergs AB.,\nGöteborg, Kungsportsav. 27, telefon: 165000.\n\nAkt.-kap.: 60,000 kr. Antal\nindustriarb.: 45. — Firman etabl. 1919, bolag\n1936.\n\nVerkst. dir. o. disp.: Knut J. Jonasson.\n\"Lesjöfors AB., Lesjöfors.\n\nJärnverk med valsverk, stållinefabrik,\ntråddrageri, manufaktursmedja,\nfjäderfabrik, gjuteri och mek. verkstad, såg och\nkolugnar# i Lesjöfors samt elektr.\nvattenkraftstationer vid Rämen, Lesjöfors och\nSt järnfors (samtl. i Värml. l.).\n\nTillverkar smitt och valsat stål,\njärn-och ståltråd, pianotråd, oljehärdad tråd,\nstållinor, hackor, släggor och, spett,\nbladfjädrar för järnvägsvagnar och\nautomo-biler samt spiralfjädrar av alla slag;\nlevererar sågade och hyvlade trävaror\noch ’snickerier, gengaskol, tjära och\nterpentin; distribuerar elektr. energi.\nBolaget idkar jämväl jordbruk och\nskogshantering.\n\nTelegr.-adr.: Lesjöfors, Filipstad.\nTelefon: »Lesjöfors Kontor». Postgiro: 11949.\nKontor i Stockholm: Lesjöfors\nFörsäljningskontor, V. Trädgårdsg. 4, telefon:\n105495.\n\nAkt.-kap.: 1,500.000 kr. Antal\nindustriarb.: 800. Tillv.-värde pr år: 9,000,000 kr.\n— Bolaget grundat 1867.\n\nStyrelse: frih. Gerard De Geer, disp.\nE. Hedendahl, dir. Kjell Ilägglöf.\n\nVerkst. dir.; frih. Gerard De Geer.\n\nFörsäljn.-chef: Birger Söderberg.\n\nKamrer: Knut Gustafsson.\n\n\"Lessebo AB., Klippan.\n\nPappersbruk med sulfitfabrik vid\nLessebo (Kronob. l.). Tillverkar hand- och\nmaskingjort post-, skriv- och filtrérpap-\n\nper, boktryckpapper, lito-, offset- och\ngravyrtryckpapper, brevkortskartong m.\nm., indunstad sulfitlut samt\nsulfitcellulosa huvudsakligen för eget behov.\nBolaget idkar jämväl jordbruk och\nskogshantering.\n\nHuvudkontor: Klippan. Telegr.-adr.\no. telefon: Pappersbruket, Klippan.\nFabrikskontor: Lessebo. Telegr.-adr.:\nLessebo, Växjö. Telefon: Växjö 2261.\n\nEnsamförsäljn. för Sverige:\nFinpappersbrukens Försäljnings AB., Stockholm,\nGöteborg och Malmö. Exportförsäljningen\nhandhaves av AB. Klippans\nFinpappers-bruk, Klippan.\n\nAkt.-kap.: 3,600,000 kr. Antal industri-",
    "structured": {
        "1": {
            "name": "AB. Leo",
            "location": "Hälsingborg",
            "business": "Läkemedelsfabrik",
            "products": "Tillverkar farmaceutiska och kemiska produkter. Varumärke: »Leo»",
            "contact": {
                "office": "Leo, Hälsingborg",
                "phone": [],
                "postgiro": "171100",
                "head_office": "",
                "sales_offices": [],
                "telegraph": "",
                "factory_office": "",
                "factory_phone": ""
            },
            "financials": {
                "capital": "600,000 kr",
                "employees": {
                    "industriarb.": 145
                },
                "annual_turnover": "",
                "annual_production_value": ""
            },
            "foundation_year": 1914,
            "current_name_year": null,
            "predecessor": "",
            "original_name": "",
            "corporation_year": null,
            "board": [
                {
                    "name": "ädv. Törsten Setterberg",
                    "role": "ordf."
                },
                {
                    "name": "adv. Hans-Erik Bachmann",
                    "role": ""
                },
                {
                    "name": "bankdir. C. D. Bilisten^ dir. Axel Hultman",
                    "role": ""
                }
            ],
            "owners": [],
            "director": "John Ericsson",
            "managing_director": "",
            "sales_manager": "",
            "manager": ""
        },
        "2": {
            "name": "Lerdals Sågverks AB.",
            "location": "Rättvik",
            "business": "Sågverk, hyvleri och kolningsverk",
            "products": "Tillverkar sågade och hyvlade trävaror, träkol och trätjära",
            "contact": {
                "office": "",
                "phone": [
                    "26",
                    "326"
                ],
                "postgiro": "91654",
                "head_office": "",
                "sales_offices": [],
                "telegraph": "Rättsåg, Rättvik",
                "factory_office": "",
                "factory_phone": ""
            },
            "financials": {
                "capital": "100,000 kr",
                "employees": {
                    "industriarb.": 80
                },
                "annual_turnover": "",
                "annual_production_value": ""
            },
            "foundation_year": 1922,
            "current_name_year": null,
            "predecessor": "",
            "original_name": "",
            "corporation_year": null,
            "board": [
                {
                    "name": "disp. Anders Hansson",
                    "role": "ordf."
                },
                {
                    "name": "disp. Karl J. Gustafsson",
                    "role": ""
                }
            ],
            "owners": [],
            "director": "",
            "managing_director": "Helge Wimark",
            "sales_manager": "",
            "manager": ""
        },
        "3": {
            "name": "Ler- & Tegelindustri AB. Hercules",
            "location": "Christianstad, Kristianstad",
            "business": "Tegelbruk",
            "products": "Tillverkar mur- och taktegel, dräneringsrör samt blomkrukor",
            "contact": {
                "office": "Kristianstad",
                "phone": [
                    "13919"
                ],
                "postgiro": "98124",
                "head_office": "",
                "sales_offices": [],
                "telegraph": "",
                "factory_office": "",
                "factory_phone": ""
            },
            "financials": {
                "capital": "350,000 kr",
                "employees": {
                    "industriarb.": 45
                },
                "annual_turnover": "",
                "annual_production_value": "5 milj. st. tegelvaror"
            },
            "foundation_year": 1899,
            "current_name_year": null,
            "predecessor": "",
            "original_name": "",
            "corporation_year": null,
            "board": [
                {
                    "name": "med. lic. Ivar Borg",
                    "role": ""
                },
                {
                    "name": "dir. Hj. Oarlborn",
                    "role": ""
                },
                {
                    "name": "dir. Bertil Ewe",
                    "role": ""
                },
                {
                    "name": "fru Signe Ewe",
                    "role": ""
                },
                {
                    "name": "v. konsul öarl Nilsson",
                    "role": ""
                }
            ],
            "owners": [],
            "director": "",
            "managing_director": "Bertil Ewe",
            "sales_manager": "",
            "manager": ""
        },
        "4": {
            "name": "AB. Lerviks Konservfabrik",
            "location": "Högdals Nordby",
            "business": "",
            "products": "Tillverkar sardiner, herring, inkokt makrill, fiskbullar m. m.",
            "contact": {
                "office": "",
                "phone": [
                    "Hog-dals-Nordby 3"
                ],
                "postgiro": "99777",
                "head_office": "",
                "sales_offices": [
                    {
                        "location": "Stockholm",
                        "phone": "202905"
                    },
                    {
                        "location": "Malmö",
                        "phone": "25930"
                    },
                    {
                        "location": "Göteborg",
                        "phone": "165000"
                    }
                ],
                "telegraph": "Jonas, Strömstad",
                "factory_office": "",
                "factory_phone": ""
            },
            "financials": {
                "capital": "60,000 kr",
                "employees": {
                    "industriarb.": 45
                },
                "annual_turnover": "",
                "annual_production_value": ""
            },
            "foundation_year": 1936,
            "current_name_year": 1919,
            "predecessor": "",
            "original_name": "",
            "corporation_year": null,
            "board": [],
            "owners": [],
            "director": "",
            "managing_director": "Knut J. Jonasson",
            "sales_manager": "",
            "manager": ""
        },
        "5": {
            "name": "Lesjöfors AB.",
            "location": "Lesjöfors",
            "business": "Järnverk med valsverk, stållinefabrik, tråddrageri",
            "products": "Tillverkar smitt och valsat stål, järn-och ståltråd, pianotråd, oljehärdad tråd, stållinor, hackor, släggor och, spett, bladfjädrar för järnvägsvagnar och automobiler samt spiralfjädrar av alla slag; levererar sågade och hyvlade trävaror och ’snickerier, gengaskol, tjära och terpentin; distribuerar elektr. energi. Bolaget idkar jämväl jordbruk och skogshantering.",
            "contact": {
                "office": "",
                "phone": [
                    "Lesjöfors Kontor"
                ],
                "postgiro": "11949",
                "head_office": "",
                "sales_offices": [
                    {
                        "location": "Stockholm",
                        "phone": "105495"
                    }
                ],
                "telegraph": "Lesjöfors, Filipstad",
                "factory_office": "",
                "factory_phone": ""
            },
            "financials": {
                "capital": "1,500,000 kr",
                "employees": {
                    "industriarb.": 800
                },
                "annual_turnover": "9,000,000 kr",
                "annual_production_value": ""
            },
            "foundation_year": 1867,
            "current_name_year": null,
            "predecessor": "",
            "original_name": "",
            "corporation_year": null,
            "board": [
                {
                    "name": "frih. Gerard De Geer",
                    "role": ""
                },
                {
                    "name": "disp. E. Hedendahl",
                    "role": ""
                },
                {
                    "name": "dir. Kjell Ilägglöf",
                    "role": ""
                }
            ],
            "owners": [],
            "director": "",
            "managing_director": "frih. Gerard De Geer",
            "sales_manager": "Birger Söderberg",
            "manager": "Knut Gustafsson"
        },
        "6": {
            "name": "Lessebo AB.",
            "location": "Klippan",
            "business": "Pappersbruk med sulfitfabrik",
            "products": "Tillverkar hand- och maskingjort post-, skriv- och filtrérpapper, boktryckpapper, lito-, offset- och gravyrtryckpapper, brevkortskartong m. m., indunstad sulfitlut samt sulfitcellulosa huvudsakligen för eget behov. Bolaget idkar jämväl jordbruk och skogshantering.",
            "contact": {
                "office": "Klippan",
                "phone": [],
                "postgiro": "",
                "head_office": "",
                "sales_offices": [],
                "telegraph": "",
                "factory_office": "Lessebo, Växjö",
                "factory_phone": "Växjö 2261"
            },
            "financials": {
                "capital": "3,600,000 kr",
                "employees": {},
                "annual_turnover": "",
                "annual_production_value": ""
            },
            "foundation_year": null,
            "current_name_year": null,
            "predecessor": "",
            "original_name": "",
            "corporation_year": null,
            "board": [],
            "owners": [],
            "director": "",
            "managing_director": "",
            "sales_manager": "",
            "manager": ""
        }
    }
}