{
    "original": "No rdpä Is—Nordström\n\nAkt.-kap. :o 5,400,000 kr. Antal\nindustriarb,: 455. Årstillv.: av sågade trävaror:\n€,000 stds; av masonite: 30,000 ton.\n\n—\tBolaget grundat 1861.\n\nStyrelse: f. d, landshövd. A. Unger\n(ordf.), jägmäst. Victor Fr. Ernberg,\n-grossh. Carl Wikström.\n\nVerkst. dir. o. disp.: f. d. borgm. Gustaf\nA. Johansson.\n\nAvd.-chefer: för sågverket: förv. F.\nTideman; för wallboardfabriken: ing. H.\nSköldkvist; för manufakturverket:\nkamrer K. F. Hörnström; för skogsegend.:\njägm. frih. A. C:son Leijonhufvud.\n\nAB. Nordpäls, Gävle.\n\nTillverkar dampälsar, pälsmössor,\nbaletter, caper m. m. Varumärke:\n»Nordpäls».\n\nTelegr.-adr.: Nordpäls, Gävle. Telefon:\n4827 o. 4829. Postgiro: 130907.\n\nAkt.-kap.: 56,000 kr. Antal\nindustriarb.: 28. Tillv.-värde pr år: 450,000 kr.\n\n—\tBolaget grundat 1937.\n\nStyrelse: dir. Gustaf Wöhrne (ordf.),\ndir. Anton Pettersson.\n\nVerkst. dir.: Gustaf Wöhrne.\n\n*\tNordstjernan, Bryggeri AB.,\n\nSundsvall.\n\nSe Bryggeri AB. Nordstjernan,\nSundsvall.\n\n*\tNordstjernan i Skövde AB.,\nBryggeriet, Skövde.\n\nSe Brve^geriet Nordstjernan i Skövde\nAB., Skövde.\n\nNordstjernans Knäckebröd AB.,\n\nTannefors.\n\nKnäckebrödsfabrik i Tannefors\n(Östergötl. l.). Tillverkar spis- och knäckebröd.\n\nTelegr.-adr.: Nordstjernan, Linköping.\nTelefon: Linköping 29390. Postgiro:\n11410.\n\nAkt.-kap.: 420,000 kr. xlntal\nindustriarb.: 102. Tillv.-värde pr år: 2,800,000 kr.\n\nFirman, etabl. 1906, bolag 1920, äger\nOskarshamns Knäckebröd AB.,\nOskarshamn. Bolaget äges av AB. Wasa\nSpis-hrödsfabrik, Filipstad.\n\nStyrelse: konsul K. E. Lundström\n(ordf.), dir. Ivar Hultkrantz,\ngeneralmajor Sig. Rahmqvist.\n\nDisp.: Fritz Nilsson.\n\nAB. Nordstjernans\nMineralvatten-fabrik, Stockholm.\n\nKontor: Norra Stationsg. 69. —\nAkt.-kap.: 2,300,000 kr.\n\n\"26\n\nBolaget, grundat 1899, är dotterbolag\ntill Apotekarnes Mineralvattens AB.*\nvilket äges av AB. Stockholms Bryggerier.\n\nStyrelse: dir. Sven Schwartz (ordf.),\ndir. Harald Engström, dir. Ivan\nNordgren.\n\nVerkst, dir.: Ivan Nordgren.\n\n* Nordström &amp; Go. AB., Tallåsens\nSnickerifabrik, Tallåsen.\n\nSe Tallåsens Snickerifabrik, Nordström\n&amp; Co. AB., Tallåsen.\n\nAB. Hugo Nordström, Lund.\n\nHandskfabrik. Tillverkar alla slags\nhandskar. Varumärken: »Nordren»,\n»Nordlav» o. »Nord Suéde».\n\nTelegr.-adr.: Nordströms, Lund.\nTelefon: 10140. Postgiro: 5057.\n\nAkt.-kap.: 150,000 kr. Antal\nindustriarb.: 155. Tillv.-värde pr år: 1,000,000 kr.\n\n—\tHandskfabriken anlagd 1876, bolag\n1941.\n\nStyrelse o. verkst. dir.: fabr. Walfrid\nNordström.\n\n*AB. Nordströms Carveri, Lund.\n\nTillverkar renskinn och kromgarvade\nskinn för handskar. Varumärken:\n»Nord-ren», »Nordlav» o. »Nord Suéde».\n\nTelegr.-adr.: Nordströms, Lund.\nTelefon: 14420. Postgiro: 176662.\n\nAkt.-kap.: 75,000 kr. Antal\nindustriarb.: 20. Tillv.-värde pr år: 400,000 kr.\n\n—\tGarveriet anlagt 1919, bolag 1941.\nStyrelse o. verkst. dir.: fabr. Walfrid\n\nNordström.\n\n*AB. Nordströms Linbanor,\n\nStockholm.\n\nMek, verkstäder i Enköping. Tillverkar\nlinbanor, hängbanor, kabelkranar,\nsläp-skopor, skophissar, rem-, stålbands- och\nkättingtransportörer, elevatorer, glid- och\nrullbanor, transportsnäckor,\nmatarappara-ter, lastnings- och lossningsapparater för\nfartyg, fackverksarbeten samt\nkontors-transportörer och rörpostanläggningar.\n\nHuvudkontor: Stockholm, Vasag. 16.\nTelegr.-adr.: Linbana, Stockholm.\nTelefon: 235590. Postgiro: 51789.\nVerkstadskontoret i Enköping: telefon: 16 o. 116.\n\nAkt.-kap.: 360,000 kr. Antal\nindustriarb.: 200. Tillv.-värde pr år: 6,000,000 kr.\n\n—\tFirman etabl. 1891, bolag 1911.\nStyrelse: disp. Th. Ekstrand, bergsing.\n\nRagnar Wahrgren, bankdir. Marcus\nWal-lenberg, civiling. Erik Widén.\nVerkst. dir.: Erik Widén.\nAvd.-ingenjör er i Stockholm: Henry\nHalle, Nils Appelkvist o. Olov R. Olsson.\nVerkstadsing.: Erik Eriksson.",
    "structured": {
        "firms": [
            {
                "name": "AB. Nordpäls",
                "location": "Gävle",
                "business": "Tillverkar dampälsar, pälsmössor, baletter, caper m. m.",
                "products": "Varumärke: »Nordpäls»",
                "contact": {
                    "office": "Nordpäls, Gävle",
                    "phone": [
                        "4827",
                        "4829"
                    ],
                    "postgiro": "130907",
                    "telegraph": "Nordpäls, Gävle"
                },
                "financials": {
                    "capital": "56,000 kr",
                    "employees": {
                        "industriarb": 28
                    },
                    "annual_production_value": "2,800,000 kr"
                },
                "foundation_year": 1937
            },
            {
                "name": "Nordstjernans Knäckebröd AB.",
                "location": "Tannefors",
                "business": "Knäckebrödsfabrik i Tannefors (Östergötl. l.). Tillverkar spis- och knäckebröd.",
                "contact": {
                    "telegraph": "Nordstjernan, Linköping",
                    "phone": "Linköping 29390",
                    "postgiro": "11410"
                },
                "financials": {
                    "capital": "420,000 kr",
                    "employees": {
                        "industriarb": 102
                    },
                    "annual_production_value": "2,800,000 kr"
                },
                "foundation_year": 1906
            },
            {
                "name": "AB. Nordstjernans Mineralvatten-fabrik",
                "location": "Stockholm",
                "business": null,
                "contact": {
                    "office": "Norra Stationsg. 69"
                },
                "financials": {
                    "capital": "2,300,000 kr"
                },
                "foundation_year": 1899
            },
            {
                "name": "AB. Hugo Nordström",
                "location": "Lund",
                "business": "Handskfabrik. Tillverkar alla slags handskar.",
                "products": "Varumärken: »Nordren», »Nordlav» o. »Nord Suéde»",
                "contact": {
                    "office": "Nordströms, Lund",
                    "phone": "10140",
                    "postgiro": "5057"
                },
                "financials": {
                    "capital": "150,000 kr",
                    "employees": {
                        "industriarb": 155
                    },
                    "annual_production_value": "1,000,000 kr"
                },
                "foundation_year": 1876
            },
            {
                "name": "AB. Nordströms Carveri",
                "location": "Lund",
                "business": "Tillverkar renskinn och kromgarvade skinn för handskar.",
                "products": "Varumärken: »Nord-ren», »Nordlav» o. »Nord Suéde»",
                "contact": {
                    "office": "Nordströms, Lund",
                    "phone": "14420",
                    "postgiro": "176662"
                },
                "financials": {
                    "capital": "75,000 kr",
                    "employees": {
                        "industriarb": 20
                    },
                    "annual_production_value": "400,000 kr"
                },
                "foundation_year": 1919
            },
            {
                "name": "AB. Nordströms Linbanor",
                "location": "Stockholm",
                "business": "Mek, verkstäder i Enköping. Tillverkar linbanor, hängbanor, kabelkranar, släp-skopor, skophissar, rem-, stålbands- och kättingtransportörer, elevatorer, glid- och rullbanor, transportsnäckor, matarappara-ter, lastnings- och lossningsapparater för fartyg, fackverksarbeten samt kontors-transportörer och rörpostanläggningar.",
                "contact": {
                    "office": "Stockholm, Vasag. 16",
                    "phone": "235590",
                    "postgiro": "51789"
                },
                "financials": {
                    "capital": "360,000 kr",
                    "employees": {
                        "industriarb": 200
                    },
                    "annual_production_value": "6,000,000 kr"
                },
                "foundation_year": 1891
            }
        ]
    }
}