{
    "original": "Färjestad—Förenade\n\n*\tFärjestads Bryggeri AB., Karlstad.\n\nTillverkar malt- och läskedrycker.\n\nTelefon: »Bryggeribolaget». Postgiro:\n71033. — Akt.-kap.: 200,000 kr.\n\nBolaget grundat 181)0. AB.\nWermlands-bryggerier, Karlstad, är huvudintressent\ni bolaget och driver i bolagets namn\nbryggerirörelsen enligt\nkommissionärs-avtal.\n\nVerkst. dir.: Sven Jansson.\n\n*\tFörberg-Film AB., Stockholm.\n\nProduktion av industri- och\npropagandafilmer samt stillfilmer för\nreklam-och försäljningsändamål.\n\nKontor: Kungsg. 27. Telegr.-adr.:\nFör-bergfilm, Stockholm. Telefon: 111655,\n101655 o. 118955. Postgiro: 57807.\n\nAkt.-kap.: 15,000 kr. Arb.-antal: 5.\nTillv.-värde pr år: 225,000 kr. —\nFirman etabl. 1934, bolag 1938.\n\nStyrelse: kapten Einar Förberg (ordf.),\ntandläkare Bo Förberg, fru Lily Förberg,\ndir. Eric Hallgren.\n\nVerkst. dir.: Einar Förberg.\n\n*AB. Förenade Bryggerierna i\nKarlskrona, Karlskrona.\n\nTillverkar maltdrycker, mineralvatten\noch läskedrycker.\n\nKontor: Karlskrona. Telegr.-adr.:\nBryggeribolaget, Karlskrona. Telefon: 108.\nPostgiro: 277979. — Akt.-kap.: 1,147,500\nkr. Antal industriarb.: 50. Tillv.-värde pr\når: 2,500,000 kr. — Bolaget grundat 1882.\n\nStyrelse: greve Axel Wachtmeister\n(ordf.), bankdir. T. Forsse, dir. O. H.\nJephson, konsul S. A. Liljevall, grossh.\nRobert Swenson.\n\nVerkst. dir.: O. H. Jephson.\n\nBryggmäst.: K. G. Palmaer.\n\nKontorschef: Reinhold Lundgren.\n\n*AB. Förenade Chokladfabrikerna,\n\nStockholm.\n\nChoklad- och konfektfabrik. Tillverkar\nkakao, choklad, karameller och\nkonfity-rer. Varumärken: »Thule Oacao» o.\n»Tulo»-tabletter.\n\nKontor: Fridhemsg. 53—55.\nTelegr.-adr.: Chokladthule, Stockholm. Telefon:\n»Chokladfabrikerna». Postgiro: 124.\n\nAkt.-kap.: 863.100 kr. Antal\nindustriarb.: 179. — Bolaget grundat 1910.\n\nStyrelse: dir. Sven G. Falk (ordf.),\nbankdir. Allan Carlsten, dir. Folke\nöfver-berg.\n\nVerkst. dir.: Folke öfverberg.\n\nKamrer: A. Åsbrink.\n\nInköpschef: Holger Mattsson.\n\nAB. Förenade Flygverkstäder,\n\nLinköping.\n\nBolaget grundat för forsknings- och\nkonstruktionsverksamhet inom\nflygteknikens område samt för försäljning av\nflygmaskiner. Verksamheten f. n. nedlagd.\n\nTelegr.-adr.: Volare, Linköping.\nTelefon: »Saab». — Akt.-kap.: 1,000,000 kr.\n— Bolaget grundat 1937.\n\nStyrelse: konsul Oscar Gullander, adv.\nWilhelm Moberg, dir. Ragnar Wahrgren.\n\nVerkst. dir.: Oscar Gullander.\n\n*AB. Förenade Cranitindustrier,\n\nKarlshamn.\n\nGranitbrott och stenhuggerier vid\nB räcke, Lahälla, Åker, Vrångebäck,\nHun-nebostrand, Ulebergshamn och Idefjorden\nm. fl. orter i Bohuslän; vid Vånga,\nOpp-manna och Immeln i Skåne; vid\nElfve-hult-Vånevik, Flivik, Hålvik,\nUtham-mar och Gamleby i Småland samt vid\nVätö, Norrtälje.\n\nTillverkar gat- och kantsten,\nbyggnadssten. kajsten samt råblock och gravvårdar.\n\nKontor: Karlshamn. Telegr.-adr.:\nGranitindustri, Karlshamn. Telefon: 671.\nPostgiro: 46530.\n\nAkt.-kap.: 500,000 kr. Antal\nindustriarb.: 300.\n\nBolaget, grundat 1917 under namn AB.\nNielsens Stenhuggerier, nuv. namn 1921.\näger Granit AB. Georg Luttensee,\nStrömstad. samt Brookes Granit Co., Ilälle.\n\nStyrelse: dir. Eric K. Fernström\n(ordf.), kamrer Einar Tillman, insp.\nEvald Werkström.\n\nVerkst. dir.: Eric K. Fernström.\n\nDisp.: Bertil Gustafsson.\n\n*\tFörenade Cummifabrikerna,\n\nHälsingborg.\n\nSe AB. Tretorn, Hälsingborg.\n\nFörenade Hattfabrikerna, Malmö.\n\nSe AB. Sveriges Förenade\nHattfabriker, Malmö.\n\n*\tFörenade Kaffeimportörers Rosteri\nAB. Triangeln, Göteborg.\n\nKafferosteri.\n\nHuvudkontor: Göteborg, Kvartersgat.\n3 B o. C. Telegr.-adr.: Triangeln,\nGöteborg. Telefon: 170260. Postgiro: 8295.\nAvd.-kontor: Malmö, S. Vallg. 5, telefon:\n28446, samt i Örebro, telefon: 11648.\n\nAkt.-kap.: 1,800,000 kr. Antal industri-",
    "structured": {
        "1": {
            "name": "Färjestads Bryggeri AB",
            "location": "Karlstad",
            "business": "Tillverkar malt- och läskedrycker",
            "contact": {
                "office": "Karlstad",
                "phone": [
                    "Bryggeribolaget"
                ],
                "postgiro": "71033",
                "head_office": "Karlstad",
                "factory_office": "Karlstad",
                "factory_phone": "Bryggeribolaget"
            },
            "financials": {
                "capital": "200,000 kr",
                "employees": {},
                "annual_turnover": "",
                "annual_production_value": ""
            },
            "foundation_year": 1810,
            "board": [
                {
                    "name": "Sven Jansson",
                    "role": "Verkst. dir."
                }
            ]
        },
        "2": {
            "name": "Förberg-Film AB",
            "location": "Stockholm",
            "business": "Produktion av industri- och propagandafilmer samt stillfilmer för reklam-och försäljningsändamål",
            "contact": {
                "office": "Kungsg. 27",
                "phone": [
                    "111655",
                    "101655",
                    "118955"
                ],
                "postgiro": "57807"
            },
            "financials": {
                "capital": "15,000 kr",
                "employees": {
                    "Arb.-antal": 5
                },
                "annual_turnover": "",
                "annual_production_value": "225,000 kr"
            },
            "foundation_year": 1934,
            "current_name_year": 1938,
            "board": [
                {
                    "name": "kapten Einar Förberg",
                    "role": "ordf."
                },
                {
                    "name": "tandläkare Bo Förberg",
                    "role": ""
                },
                {
                    "name": "fru Lily Förberg",
                    "role": ""
                },
                {
                    "name": "dir. Eric Hallgren",
                    "role": ""
                }
            ],
            "director": "Einar Förberg"
        },
        "3": {
            "name": "AB Förenade Bryggerierna",
            "location": "Karlskrona",
            "business": "Tillverkar maltdrycker, mineralvatten och läskedrycker",
            "contact": {
                "office": "Karlskrona",
                "phone": [
                    "108"
                ],
                "postgiro": "277979"
            },
            "financials": {
                "capital": "1,147,500 kr",
                "employees": {
                    "Antal industriarb.": 50
                },
                "annual_turnover": "",
                "annual_production_value": "2,500,000 kr"
            },
            "foundation_year": 1882,
            "board": [
                {
                    "name": "greve Axel Wachtmeister",
                    "role": "ordf."
                },
                {
                    "name": "bankdir. T. Forsse",
                    "role": ""
                },
                {
                    "name": "dir. O. H. Jephson",
                    "role": ""
                },
                {
                    "name": "konsul S. A. Liljevall",
                    "role": ""
                },
                {
                    "name": "grossh. Robert Swenson",
                    "role": ""
                }
            ],
            "director": "O. H. Jephson",
            "sales_manager": "Reinhold Lundgren"
        },
        "4": {
            "name": "AB Förenade Chokladfabrikerna",
            "location": "Stockholm",
            "business": "Choklad- och konfektfabrik. Tillverkar kakao, choklad, karameller och konfity-rer",
            "contact": {
                "office": "Fridhemsg. 53—55",
                "phone": [
                    "Chokladfabrikerna"
                ],
                "postgiro": "124"
            },
            "financials": {
                "capital": "863,100 kr",
                "employees": {
                    "Antal industriarb.": 179
                },
                "annual_turnover": "",
                "annual_production_value": ""
            },
            "foundation_year": 1910,
            "board": [
                {
                    "name": "dir. Sven G. Falk",
                    "role": "ordf."
                },
                {
                    "name": "bankdir. Allan Carlsten",
                    "role": ""
                },
                {
                    "name": "dir. Folke öfverberg",
                    "role": ""
                }
            ],
            "director": "Folke öfverberg",
            "manager": "A. Åsbrink",
            "sales_manager": "Holger Mattsson"
        },
        "5": {
            "name": "AB Förenade Flygverkstäder",
            "location": "Linköping",
            "business": "Forskning- och konstruktionsverksamhet inom flygteknikens område samt försäljning av flygmaskiner",
            "contact": {
                "office": "Linköping",
                "phone": [
                    "Saab"
                ],
                "postgiro": "",
                "head_office": "Linköping"
            },
            "financials": {
                "capital": "1,000,000 kr",
                "employees": {},
                "annual_turnover": "",
                "annual_production_value": ""
            },
            "foundation_year": 1937,
            "board": [
                {
                    "name": "konsul Oscar Gullander",
                    "role": ""
                },
                {
                    "name": "adv. Wilhelm Moberg",
                    "role": ""
                },
                {
                    "name": "dir. Ragnar Wahrgren",
                    "role": ""
                }
            ],
            "director": "Oscar Gullander"
        },
        "6": {
            "name": "AB Förenade Cranitindustrier",
            "location": "Karlshamn",
            "business": "Granitbrott och stenhuggerier",
            "contact": {
                "office": "Karlshamn",
                "phone": [
                    "671"
                ],
                "postgiro": "46530"
            },
            "financials": {
                "capital": "500,000 kr",
                "employees": {
                    "Antal industriarb.": 300
                },
                "annual_turnover": "",
                "annual_production_value": ""
            },
            "foundation_year": 1917,
            "current_name_year": 1921,
            "board": [
                {
                    "name": "dir. Eric K. Fernström",
                    "role": "ordf."
                },
                {
                    "name": "kamrer Einar Tillman",
                    "role": ""
                },
                {
                    "name": "insp. Evald Werkström",
                    "role": ""
                }
            ],
            "director": "Eric K. Fernström",
            "manager": "Bertil Gustafsson"
        },
        "7": {
            "name": "Förenade Kaffeimportörers Rosteri AB",
            "location": "Göteborg",
            "business": "Kafferosteri",
            "contact": {
                "office": "Göteborg, Kvartersgat. 3 B o. C",
                "phone": [
                    "170260"
                ],
                "postgiro": "8295"
            },
            "financials": {
                "capital": "1,800,000 kr",
                "employees": {},
                "annual_turnover": "",
                "annual_production_value": ""
            }
        }
    }
}