{
    "original": "Lana—Landsverk\n\nVerkst. dir.: Otto Heinrich Lammert.\n\nKamrer: Eric Casselblad.\n\nAvd.-chef i Sthlm: dr Robert Krahl.\n\nAB. Lana, Göteborg.\n\nKamgarnsspinneri i Mölndal.\nTillverkar strump-, stick- och vävgarner.\n\nHuvudkontor: Göteborg, S. Hamng.\n63. Telegr.-adr.: Lana, Göteborg.\nTelefon: 161936. Postgiro: 42350.\n\nAkt.-kap.: 1,200,000 kr. Antal\nindustriarb.: 150. — Fabriken anlagd 1889, nuv.\nbolag grundat 1893.\n\nStyrelse: dir. Gustaf Werner (ordf.),\njur. kand. Bengt Holming, disp. O. O.\nSmedmark.\n\nDisp.: John Ahlqvist.\n\n*Landhy &amp; Lundgrens Boktryckeri,\n\nMalmö.\n\nUtför trycksaker, speciellt illustrerade\nkataloger, bokverk, reklam- och färgtryck.\n\nKontor: Davidshallsg. 4. Telefon:\n21208 o. 23250. Postgiro: 37625. —\nAntal industriarb.: 50. Tillv.-värde pr år:\n850,000 kr, — Firman etabl. 1898.\n\nÄgare o. chef: boktr. Arvid Clarin.\n\n* Landsbro Tegelbruks AB.,\n\nStora Skedvi.\n\nTillverkar murtegel, lättmurtegel och\nhögporöst tegel vid tegelbruk i Stora\nSkedvi (Kopparb. l.).\n\nTelefon: 72. Postgiro: 34331. —\nAkt.-kap.: 40,000 ikr. Arb.-antal: 10. Årstillv.:\n2 milj. st. tegelvaror. — Bolaget grundat\n1940.\n\nStyrelse: disp. Karl Hedin (ordf.),\nfabr. Henning Hedin, fru Edit Hedin.\n\nVerkst. dir. o. disp.: Karl Hedin.\n\nLandskrona Kirurgiska Sliperi &amp;\nMetallvarufabrik, Landskrona.\n\nMetallvarufabrik med pressgjuteri.\nTillverkar sanitetsarmatur.\n\nTelefon: 1200. Postgiro: 82151. —\nAntal industriarb.: 30. Tillv.-värde pr år:\n300,000 kr. — Firman etabl. 1925.\n\nÄgare o. chefer: fabr. Helmer Jönsson\no. fabr. Einar Jönsson.\n\n^Landskrona Konstgödningsfabrik,\n\nLandskrona.\n\nSe AB. Förenade Superfosfatfabriker,\nHälsingborg.\n\nLandskrona Margarinfabrik AB.,\n\nLandskrona.\n\nTillverkar margarin och kokosfett.\n\nTelegr.-adr.: Palma, Landskrona.\nTelefon: 1933 o. 84. Postgiro: 72084. —\nAntal industriarb.: 15. — Bolaget grundat\n1934.\n\nDisp.: Stig Bernstone.\n\nLandskrona Nya Mek. Verkstads\n\nAB., Ijandskrona.\n\nSe AB. Landsverk, Landskrona.\n\n*\tLandskrona Spinneri AB.,\n\nLandskrona.\n\nUllspinneri, färgeri, trikå- och\nstrumpfabrik. Tillverkar ullgarn, trikåvaror och\nstrumpor.\n\nTelegr.-adr.: Ullgarn, Landskrona.\nTelefon: 22 o. 2530. Postgiro: 36314.\n\nAkt.-kap.: 210,000 kr. Antal\nindustriarb.: 55. Tillv.-värde pr år: 685,000 kr.\n— Bolaget grundat 1918.\n\nStyrelse: dir. Oscar C. Oliwers (ordf.),\nfru Karin Oliwers, dir.-assist. Lars\nOliwers.\n\nVerkst. dir.: Oscar C. Oliwers.\n\nDisp.: Eric Casslow.\n\n*\tLandskrona Valskvarn, Landskrona.\n\nSe AB. Mårten Pehrsons Valsqvarn,\nKristianstad.\n\n*AB. Landsverk, Landskrona.\n\nMek. verkstad och gjuteri.\n\nTillverkar järnvägsvagnar och annan\njärnvägsmateriel, järnvägs- och\nlandsvägsbroar, kranar och\ntransportanordningar, järnkonstruktioner, cisterner alla\nslag (spec. större oljecisterner),\nplåtarbeten, maskiner och apparater för\ncellulosa- och sockerindustrierna (spec.\nin-dustningsanläggningar, centrifuger och\nsnitselpressar), cement- och\ntegelbruks-maskiner, grävmaskiner,\nsopförbränningsanläggningar, gasklockor och\ngasverksapparater, centrifugalpumpar,\nsnabbgående ångmaskiner upp till 100 hkr,\nmotorfordon, gjutgods m. m.\n\nTelegr.-adr. o. telefon: Landsverk,\nLandskrona. Postgiro: 23222.\n\nAkt.-kap.: 2,170,000 kr. Antal\nindustriarb.: 800.\n\nFirman grundad 1872, bolag 1899\nunder namn Landskrona Nya Mek.\nVerkstads AB., nuv. namn 1928.\n\nStyrelse: bankdir. A. Riider (ordf.)r\ndir. Hermann Hennemann, dir. Arvid\n\n318*",
    "structured": {
        "firms": [
            {
                "name": "Lana—Landsverk",
                "location": "Göteborg",
                "business": "Kamgarnsspinneri i Mölndal",
                "products": "Tillverkar strump-, stick- och vävgarner",
                "contact": {
                    "office": "S. Hamng. 63",
                    "phone": [
                        "161936"
                    ],
                    "postgiro": "42350",
                    "head_office": "Göteborg, S. Hamng.",
                    "telegraph": "Lana, Göteborg",
                    "factory_office": "N/A",
                    "factory_phone": "N/A"
                },
                "financials": {
                    "capital": "1,200,000 kr",
                    "employees": {
                        "industriarb": 150
                    }
                },
                "foundation_year": 1893,
                "board": [
                    {
                        "name": "Gustaf Werner",
                        "role": "ordf."
                    },
                    {
                        "name": "Bengt Holming",
                        "role": "jur. kand."
                    },
                    {
                        "name": "O. O. Smedmark",
                        "role": "disp."
                    }
                ],
                "owners": [],
                "director": "Otto Heinrich Lammert",
                "managing_director": "N/A",
                "sales_manager": "N/A",
                "manager": "N/A"
            },
            {
                "name": "Landhy & Lundgrens Boktryckeri",
                "location": "Malmö",
                "business": "Utför trycksaker, speciellt illustrerade kataloger, bokverk, reklam- och färgtryck",
                "contact": {
                    "office": "Davidshallsg. 4",
                    "phone": [
                        "21208",
                        "23250"
                    ],
                    "postgiro": "37625",
                    "head_office": "N/A",
                    "telegraph": "N/A",
                    "factory_office": "N/A",
                    "factory_phone": "N/A"
                },
                "financials": {
                    "capital": "N/A",
                    "employees": {
                        "industriarb": 50
                    },
                    "annual_turnover": "850,000 kr"
                },
                "foundation_year": 1898,
                "board": [],
                "owners": [
                    "boktr. Arvid Clarin"
                ],
                "director": "N/A",
                "managing_director": "N/A",
                "sales_manager": "N/A",
                "manager": "N/A"
            },
            {
                "name": "Landsbro Tegelbruks AB.",
                "location": "Stora Skedvi",
                "business": "Tillverkar murtegel, lättmurtegel och högporöst tegel",
                "products": "N/A",
                "contact": {
                    "office": "N/A",
                    "phone": [
                        "72"
                    ],
                    "postgiro": "34331",
                    "head_office": "N/A",
                    "telegraph": "N/A",
                    "factory_office": "N/A",
                    "factory_phone": "N/A"
                },
                "financials": {
                    "capital": "40,000 ikr",
                    "employees": {
                        "industriarb": 10
                    }
                },
                "foundation_year": 1940,
                "board": [],
                "owners": [
                    "Karl Hedin",
                    "Henning Hedin",
                    "fru Edit Hedin"
                ],
                "director": "Karl Hedin",
                "managing_director": "N/A",
                "sales_manager": "N/A",
                "manager": "N/A"
            },
            {
                "name": "Landskrona Kirurgiska Sliperi & Metallvarufabrik",
                "location": "Landskrona",
                "business": "Metallvarufabrik med pressgjuteri",
                "products": "Tillverkar sanitetsarmatur",
                "contact": {
                    "office": "N/A",
                    "phone": [
                        "1200"
                    ],
                    "postgiro": "82151",
                    "head_office": "N/A",
                    "telegraph": "N/A",
                    "factory_office": "N/A",
                    "factory_phone": "N/A"
                },
                "financials": {
                    "capital": "N/A",
                    "employees": {
                        "industriarb": 30
                    },
                    "annual_turnover": "300,000 kr"
                },
                "foundation_year": 1925,
                "board": [],
                "owners": [
                    "fabr. Helmer Jönsson",
                    "fabr. Einar Jönsson"
                ],
                "director": "N/A",
                "managing_director": "N/A",
                "sales_manager": "N/A",
                "manager": "N/A"
            },
            {
                "name": "Landskrona Margarinfabrik AB.",
                "location": "Landskrona",
                "business": "Tillverkar margarin och kokosfett",
                "products": "N/A",
                "contact": {
                    "office": "N/A",
                    "phone": [
                        "1933",
                        "84"
                    ],
                    "postgiro": "72084",
                    "head_office": "N/A",
                    "telegraph": "Palma, Landskrona",
                    "factory_office": "N/A",
                    "factory_phone": "N/A"
                },
                "financials": {
                    "capital": "N/A",
                    "employees": {
                        "industriarb": 15
                    }
                },
                "foundation_year": 1934,
                "board": [],
                "owners": [],
                "director": "N/A",
                "managing_director": "N/A",
                "sales_manager": "N/A",
                "manager": "N/A"
            },
            {
                "name": "Landskrona Spinneri AB.",
                "location": "Landskrona",
                "business": "Ullspinneri, färgeri, trikå- och strumpfabrik",
                "products": "Tillverkar ullgarn, trikåvaror och strumpor",
                "contact": {
                    "office": "N/A",
                    "phone": [
                        "22",
                        "2530"
                    ],
                    "postgiro": "36314",
                    "head_office": "N/A",
                    "telegraph": "Ullgarn, Landskrona",
                    "factory_office": "N/A",
                    "factory_phone": "N/A"
                },
                "financials": {
                    "capital": "210,000 kr",
                    "employees": {
                        "industriarb": 55
                    },
                    "annual_turnover": "685,000 kr"
                },
                "foundation_year": 1918,
                "board": [],
                "owners": [
                    "dir. Oscar C. Oliwers",
                    "fru Karin Oliwers",
                    "dir.-assist. Lars Oliwers"
                ],
                "director": "Oscar C. Oliwers",
                "managing_director": "N/A",
                "sales_manager": "N/A",
                "manager": "N/A"
            },
            {
                "name": "AB. Landsverk",
                "location": "Landskrona",
                "business": "Mek. verkstad och gjuteri",
                "products": "Tillverkar järnvägsvagnar och annan järnvägsmateriel, järnvägs- och landsvägsbroar, kranar och transportanordningar, järnkonstruktioner, cisterner alla slag (spec. större oljecisterner), plåtarbeten, maskiner och apparater för cellulosa- och sockerindustrierna (spec. industningsanläggningar, centrifuger och snitselpressar), cement- och tegelbruksmaskiner, grävmaskiner, sopförbränningsanläggningar, gasklockor och gasverksapparater, centrifugalpumpar, snabbgående ångmaskiner upp till 100 hkr, motorfordon, gjutgods m. m.",
                "contact": {
                    "office": "N/A",
                    "phone": [
                        "N/A"
                    ],
                    "postgiro": "23222",
                    "head_office": "N/A",
                    "telegraph": "Landsverk, Landskrona",
                    "factory_office": "N/A",
                    "factory_phone": "N/A"
                },
                "financials": {
                    "capital": "2,170,000 kr",
                    "employees": {
                        "industriarb": 800
                    }
                },
                "foundation_year": 1899,
                "board": [
                    {
                        "name": "A. Riider",
                        "role": "bankdir."
                    },
                    {
                        "name": "Hermann Hennemann",
                        "role": "dir."
                    },
                    {
                        "name": "Arvid 318",
                        "role": "dir."
                    }
                ],
                "owners": [],
                "director": "N/A",
                "managing_director": "N/A",
                "sales_manager": "N/A",
                "manager": "N/A"
            }
        ]
    }
}