{
    "original": "Skruf-—Skyddskläder\n\nAkt.-kap.: 240,000 kr. Antal\nindustriarb.: 100. Tillv.-värde pr år: 600,000 kr.\n— Bolaget grundat 1910.\n\nStyrelse: disp. Harald Lindström\n(ordf.), disp. Ernst Karlson (v. ordf.),\nköpm. Per Hennel, konsul Seth Liljevall,\nkamrer Nils Widlund.\n\nVerkst. dir.: Ernst Karlson.\n\n\"Skrufs Ångbryggeri, Skruv.\n\nSe Ångbryggeriet Skruf, Skruv.\n\n\"Skruv AB. (i Uddeholm),\nEskilstuna.\n\nSkruvfabrik i Hagfors (Värml. l.).\nTillverkar träskruv och järngängad skruv\nav järn, mässing (rödmetall) och rostfritt\nstål samt ’roötfri nit.\n\nHuvudkontor: Eskilstuna.\nTelegr.-adr.: Screw, Eskilstuna. Telefon:\n»Skruvbolaget», Eskilstuna. Postgiro: 94308.\n\nAkt.-kap.: 2,000,000 kr. Antal\nindustriarb.: 250. Tillv.-värde pr år: 5,000,000 kr.\n\nSkruvfabrikationen, som sedan 1884\nbedrivits av Uddeholms AB., Övertogs\n1935 av nuv. bolag.\n\nStyrelse: bankdir. Ja,cob Wallenberg\n(ordf.), disp. Nore Nilsson, dir. Sixten\nV. Nilsson, disp. Sture Nilsson, kapten\nSten Rudberg.\n\nVerkst. dir.: Nore Nilsson\n(Eskilstuna).\n\nKontorschef: Gustaf Åkerblom\n(Eskilstuna).\n\nSkruvfabriks AB., Strängnäs.\n\nTillverkar blanka svarvade skruvar och\nmuttrar av järn och mässing samt\nko-niska pinnar.\n\nTelefon: 364. Postgiro: 9475. —\nAkt.-kap.: 80,000 kr. Antal industriarb.: 15.\nTillv.-värde pr år: 210,000 kr. — Bolaget\ngrundat 1919.\n\nVerkst. dir.: Olof Olsson.\n\nVerkstadschef: Agard Persson.\n\n\"Skultuna Bruk, Skultuna.\n\nSe AB. Svenska Metallverken, Västerås.\n\nSkumsläcknings AB., Svenska,\n\nStockholm.\n\nSe Svenska Skumsläcknings AB.,\nStockholm.\n\n\"Skurups Tegelbruk AB., Skurup.\n\nTegelbruk i Skurup och i Yddinge\n(båda i Malmöh. l.). Tillverkar murtegel,\nhål- och poröstegel, rött maskinhandsla-\n\nget och maskinpressat fasadtegel samt\ndränerings- och kopplingsrör.\n\nKontor: Skurup. Telefon: 286 o. 625.\n\nAkt.-kap.: 40,000 kr. Antal\nindustriarb.: 90. Årstillv.: 7 milj. st. tegelvaror.\n— Tegelbruken anlagda resp. 1899 och\n1893, nuv. bolag grundat 1939.\n\nStyrelse: dir. Kjell Beijer, dir. Bror\nMattson, dir. Edvin öhnner.\n\nVerkst. dir.: Bror Mattson.\n\nDisp.: Edvin öhnner.\n\n\"Skutskärs Fabriker, Skutskär.\n\nSulfit- och sulfatcellulosafabriker vid\nSkutskär (Uppsala l.). Tillverkar\nnatri-umbisulfit- och sulfatcellulosa,\nkvistpapper, sulfitsprit, terpentin, flytande harts\nsamt flytande klor, natronlut,\nsvavelsyr-lighet, butanol och butylacetat.\n\nPostadr.: Skutskär. Telefon: Härnäs\n500. — Försäljningen sker genom Stora\nKopparbergs Bergslags AB., Falun.\nTelefon: »Bergslaget», Falun.\n\nAntal industriarb.: 570. Årstillv.:\n30,000 ton sulfitcellulosa samt 50,000 ton\nblekt sulfatcellulosa av extra stark\nspecialkvalitet.\n\nSulfatfabriken anlades 1894 och\nombyggdes 1937, sulfitfabriken anlades 1900\noch ombyggdes 193i9—41, blekeriet och\nklorfabriken anlades 1931. Fabrikerna\nägas av Stora Kopparbergs Bergslags\nAB. (se detta bolag).\n\nPlatschef: dir. Ragnar Söderquist.\n\nFörsäljn.-chef er (Falun): för papper\noch cellulosa: dir. H. G. Gullander; för\nkemiska produkter: intendent Bo\nStenberg.\n\n\"Skutskärs Sågverk, Skutskär.\n\nSågyerk och hyvleri vid Skutskär\n(Uppsala l.). Tillverkar sågade och\nhyvlade trävaror.\n\nTelefon: Härnäs 500. — Försäljningen\nsker genom Stora Kopparbergs Bergslags\nAB., Falun. Telefon: »Bergslaget», Falun.\n\nAntal industriarb.: 300. Årstillv.:\n20,000 stds sågade och hyvlade trävaror.\n\nSågverket anlagt 1869, ombyggt 1943.\nVerket äges av Stora Kopparbergs\nBergslags AB. (se detta bolag).\n\nPlatschef: dir. Ragnar Söderquist.\n\nFörsäljn.-chef (Falun): dir. H. G.’\nGullander.\n\n\"AB. Skyddskläder, Fristad.\n\nKonfektionsfabrik i Fristad (Älvsb. l.).\nTillverkar overalls och arbetskläder,\nsportkostymer, vindtygs jackor, skjortor,\npoplin rockar m. m.\n\n48 O*",
    "structured": {
        "1": {
            "name": "Skruf Skyddskläder",
            "location": "Fristad",
            "business": "Konfektionsfabrik",
            "products": "Overalls och arbetskläder, sportkostymer, vindtygs jackor, skjortor, poplin rockar m.m.",
            "contact": {
                "postgiro": "",
                "head_office": "",
                "telegraph": "",
                "factory_office": "",
                "factory_phone": ""
            },
            "financials": {
                "capital": "240,000 kr",
                "employees": {
                    "industriarb": 100
                },
                "annual_turnover": "600,000 kr",
                "annual_production_value": ""
            },
            "foundation_year": 1910,
            "board": [
                {
                    "name": "disp. Harald Lindström",
                    "role": "ordf."
                },
                {
                    "name": "disp. Ernst Karlson",
                    "role": "v. ordf."
                },
                {
                    "name": "köpm. Per Hennel",
                    "role": ""
                },
                {
                    "name": "konsul Seth Liljevall",
                    "role": ""
                }
            ],
            "director": "Ernst Karlson",
            "managing_director": "",
            "sales_manager": "",
            "manager": ""
        },
        "2": {
            "name": "Skruv AB. (i Uddeholm)",
            "location": "Eskilstuna",
            "business": "Skruvfabrik",
            "products": "Tillverkar träskruv och järngängad skruv av järn, mässing (rödmetall) och rostfritt stål samt ’roötfri nit.",
            "contact": {
                "office": "",
                "phone": [
                    "Skruvbolaget",
                    "Eskilstuna"
                ],
                "postgiro": "94308",
                "head_office": "Eskilstuna",
                "telegraph": "Screw, Eskilstuna",
                "factory_office": "",
                "factory_phone": ""
            },
            "financials": {
                "capital": "2,000,000 kr",
                "employees": {
                    "industriarb": 250
                },
                "annual_turnover": "5,000,000 kr",
                "annual_production_value": ""
            },
            "foundation_year": "",
            "board": [
                {
                    "name": "bankdir. Jacob Wallenberg",
                    "role": "ordf."
                },
                {
                    "name": "disp. Nore Nilsson",
                    "role": ""
                },
                {
                    "name": "dir. Sixten V. Nilsson",
                    "role": ""
                },
                {
                    "name": "disp. Sture Nilsson",
                    "role": ""
                },
                {
                    "name": "kapten Sten Rudberg",
                    "role": ""
                }
            ],
            "director": "",
            "managing_director": "Nore Nilsson",
            "sales_manager": "",
            "manager": "Gustaf Åkerblom"
        },
        "3": {
            "name": "Skruvfabriks AB. Strängnäs",
            "location": "Strängnäs",
            "business": "Skruvfabrik",
            "products": "Tillverkar blanka svarvade skruvar och muttrar av järn och mässing samt korniska pinnar.",
            "contact": {
                "office": "",
                "phone": [
                    "364"
                ],
                "postgiro": "9475",
                "head_office": "",
                "telegraph": "",
                "factory_office": "",
                "factory_phone": ""
            },
            "financials": {
                "capital": "80,000 kr",
                "employees": {
                    "industriarb": 15
                },
                "annual_turnover": "210,000 kr",
                "annual_production_value": ""
            },
            "foundation_year": 1919,
            "board": [],
            "director": "Olof Olsson",
            "managing_director": "",
            "sales_manager": "",
            "manager": "Agard Persson"
        },
        "4": {
            "name": "Skutskärs Fabriker",
            "location": "Skutskär",
            "business": "Sulfit- och sulfatcellulosafabriker",
            "products": "Tillverkar natriumbisulfit- och sulfatcellulosa, kvistpapper, sulfitsprit, terpentin, flytande harts samt flytande klor, natronlut, svavelsyr-lighet, butanol och butylacetat.",
            "contact": {
                "office": "",
                "phone": [
                    "Härnäs 500"
                ],
                "postgiro": "",
                "head_office": "",
                "telegraph": "",
                "factory_office": "",
                "factory_phone": ""
            },
            "financials": {
                "capital": "",
                "employees": {
                    "industriarb": 570
                },
                "annual_turnover": "",
                "annual_production_value": "30,000 ton sulfitcellulosa samt 50,000 ton blekt sulfatcellulosa av extra stark specialkvalitet."
            },
            "foundation_year": "",
            "board": [],
            "director": "dir. Ragnar Söderquist",
            "managing_director": "",
            "sales_manager": "",
            "manager": ""
        },
        "5": {
            "name": "Skutskärs Sågverk",
            "location": "Skutskär",
            "business": "Sågverk och hyvleri",
            "products": "Tillverkar sågade och hyvlade trävaror.",
            "contact": {
                "office": "",
                "phone": [
                    "Härnäs 500"
                ],
                "postgiro": "",
                "head_office": "",
                "telegraph": "",
                "factory_office": "",
                "factory_phone": ""
            },
            "financials": {
                "capital": "",
                "employees": {
                    "industriarb": 300
                },
                "annual_turnover": "",
                "annual_production_value": "20,000 stds sågade och hyvlade trävaror."
            },
            "foundation_year": "",
            "board": [],
            "director": "dir. Ragnar Söderquist",
            "managing_director": "",
            "sales_manager": "",
            "manager": ""
        }
    }
}