{
    "original": "Linham—Linköping\n\nvärde pr år: 2,000,000 kr. — Bolaget\ngrundat 1917 under namn AB. Höglund\nk Co., nuv. naijtin 1942.\n\nVerkst. dir.: Carl Halvars.\n\nAB. Linham, Stockholm.\n\nMek. verkställ. Tillverkar\nspecialmaskiner för sköindustrien, smörjkoppar\nm. m. Varumärke: »Linham».\n\nKontor: Huvudstavägen 49.\nTelegr.-adr.: Linhamcup, Stockholm. Telefon:\n520300. Postgiro: 2728.\n\nAkt.-kap.: 32^,000 kr. Antgl\nindustriarb.: 155. Tillv.-värde pr år: 1,200,000 kr.\n— Bolaget grundat 1927.\n\nStyrelse: godsäg. Tli. Dieden (ordf.),\ndir.\" Oscar Almgren, jägm. Henrik\nDieden, fru M. Dieden.\n\nVerkst. dir.: Oscar Almgren.\n\n(Jfr annons nr 96.)\n\n*\tLinköpings Armatur- och\nMetallfabriks AB., Linköping.\n\nBolagets verksamhet består\nhuvudsakligen i försäljning av armatur av egna\nkonstruktioner för vatten och ånga,\nsyrafast armatur, mejeriarmatur, hydrauliska\nanläggningar och armatur för\ncellulosaindustrien, knutsilar och silplåtar,\nmetall- och lättmetallgjutgods, varmpressat\noch pressgjutet metall- och\nlättmetall-gods tillverkade av moderbolaget AB.\nNordiska Armaturfabrikerna, Linköping\n(se detta bolag).\n\nTelegr.-adr.: Armatur, Linköping.\nTelefon: »Armaturfabriken».\n\nAkt.-kap.: 600,000 kr. — Bolaget,\ngrundat 1915, är dotterbolag till AB. Nordiska\nArmaturfabrikerna.\n\nStyrelse: bruksdisp. Wiking Johnsson\n(ordf.), kommerserådet Axel F.\nEn-ström, dir. B. R. Gyllenram, dir. Kjell\nHäggiöf, dir. Helge Norlander,\ngeneralkonsul Ragnar Söderberg.\n\nVerkst. dir.: B. R. Gyllenram.\n\nDisp.: E. Stoije.\n\n*\tLinköpings Bryggeri, Linköping.\n\nSe AB. Nya Centralbryggeriet,\nLinköping.\n\n*AB. Linköpings Cjuteri &amp; Mek.\nVerkstad, Linköping.\n\nSe AB. Elge-Verken, Linköping.\n\n^Linköpings Linnefabriks AB.,\n\nLinköping.\n\nVitvarufabrik. Tillverkar kragar,\nmanschetter, skjortor, pyjamas och\ndamblusar.\n\nTelegr.-adr.: Linnefabriken, Linköping.\nTelefon: 29905. Postgiro: 6290.\n\nAkt.-kap.: 379,500 kr. Antal\nindustriarb.: 177. Tillv.-värde pr år: 1,750,000 kr.\n\n—\tBolaget grundat 1910.\n\nStyrelse: dir. Fredrik Béen (ordf.),\nf. d. förste postkontrollör Th. Béen,\nbankdir. G. Gyllensvard, konsul Ivar\nP:son Henning, kapten Th. Hög f eld t\n\nVerkst. dir.: Fredrik Béen.\n\nLinköpings Litografiska AB»,\n\nLinköping.\n\nUtför affärs- och reklamtryck i\nboktryck, litografiskt tryck, offset och\nståltryck; tillverkar kontorsböcker, kuvert,\npappers- och kartongemballage.\n\nTelefon: 20003. Postgiro: 5290. —\nBolaget, grundat 1884, är anslutet till AB.\nSveriges Litografiska Tryckerier,\nStockholm (se detta bölag).\tV-\n\nStyrelse: disp. C. O. Meurling.\n\nLinköpings Möbelindustri AB.,\n\nLinköping*\n\nTillverkar möbler.\n\nTelefon: 20419. Postgiro: 74668. —\nAkt.-kap.: 60,700 kr. Tillv.-värde pr år:\n350,000 kr. — Firman etabl. 1920.\n\nDisp.: Theodor Fridén.\n\n*AB. Linköpings Strumpfabrik,\n\nLinköping.\n\nTillverkar dam- och barnstrumpor,\nsportstrumpor m. m.\n\nTelefon: 20292. — Akt.-kap.: 225,000\nkr. Antal industriarb.: 65. Tillv.-värde pr\når: 800,000 kr.\n\nBolaget, grundat 1927, är dotterbolag\ntill AB. K. A. Ullholm, Linköping.\n\nStyrelse: v. konsul K. Albert Ullholm\n(ordf.), köpm. N. Beenard.\n\nVerkst. dir.: K. Albert Ullholm.\n\nLinköpings Strå- &amp; Filthattfabrik\nAB., Linköping.\n\nTillverkar spec. damhattar och\nmodevaror.\n\nHuvudkontor: Linköping. Telegr.-adr.:\nHattfabriken, Linköping. Telefon:\n»Linköpings Strå- o. Filthattfabrik».\nPostgiro: 84040. Försäljn.-kontor: Stockholm,\nKungsg. 39, telefon: 110565 o. 211142;\nGöteborg, ö. Hamng. 12, telefon: 134240\no. 134237.\n\nAkt.-kap.: 300,000 kr. Antal\nindustriarb.: 125. Tillv.-värde pr år: 1,250,000 kr.\n\n—\tBolaget grundat 1919.\n\nVerkst. dir.: fröken Ida Israelsson.\n\nKamrer: Eric Träff.\n\n336*",
    "structured": {
        "firms": [
            {
                "name": "Linham",
                "location": "Linköping",
                "business": "Tillverkar specialmaskiner för sköindustrien, smörjkoppar m. m.",
                "contact": {
                    "office": "Huvudstavägen 49",
                    "telegraph": "Linhamcup, Stockholm",
                    "phone": [
                        "520300"
                    ],
                    "postgiro": "2728"
                },
                "financials": {
                    "capital": "32,000 kr",
                    "employees": {
                        "industriarb": 155
                    },
                    "annual_turnover": "1,200,000 kr"
                },
                "foundation_year": 1917,
                "current_name_year": 1942,
                "director": "Carl Halvars"
            },
            {
                "name": "Linköpings Armatur- och Metallfabriks AB.",
                "location": "Linköping",
                "business": "Försäljning av armatur av egna konstruktioner för vatten och ånga, syrafast armatur, mejeriarmatur, hydrauliska anläggningar och armatur för cellulosaindustrien, knutsilar och silplåtar, metall- och lättmetallgjutgods samt varmpressat och pressgjutet metall- och lättmetall-gods.",
                "contact": {
                    "telegraph": "Armatur, Linköping"
                },
                "financials": {
                    "capital": "600,000 kr"
                },
                "foundation_year": 1915,
                "disp": "E. Stoije"
            },
            {
                "name": "Linköpings Linnefabriks AB.",
                "location": "Linköping",
                "business": "Tillverkar kragar, manschetter, skjortor, pyjamas och damblusar",
                "contact": {
                    "telegraph": "Linnefabriken, Linköping",
                    "phone": [
                        "29905"
                    ],
                    "postgiro": "6290"
                },
                "financials": {
                    "capital": "379,500 kr",
                    "employees": {
                        "industriarb": 177
                    },
                    "annual_turnover": "1,750,000 kr"
                },
                "foundation_year": 1910,
                "director": "Fredrik Béen"
            },
            {
                "name": "Linköpings Litografiska AB",
                "location": "Linköping",
                "business": "Utför affärs- och reklamtryck i boktryck, litografiskt tryck, offset och ståltryck; tillverkar kontorsböcker, kuvert, pappers- och kartongemballage",
                "contact": {
                    "phone": [
                        "20003"
                    ],
                    "postgiro": "5290"
                },
                "foundation_year": 1884,
                "description": "Är anslutet till AB. Sveriges Litografiska Tryckerier, Stockholm"
            },
            {
                "name": "Linköpings Möbelindustri AB",
                "location": "Linköping",
                "business": "Tillverkar möbler",
                "contact": {
                    "phone": [
                        "20419"
                    ],
                    "postgiro": "74668"
                },
                "financials": {
                    "capital": "60,700 kr",
                    "annual_turnover": "350,000 kr"
                },
                "foundation_year": 1920,
                "disp": "Theodor Fridén"
            },
            {
                "name": "AB. Linköpings Strumpfabrik",
                "location": "Linköping",
                "business": "Tillverkar dam- och barnstrumpor, sportstrumpor m. m.",
                "contact": {
                    "phone": [
                        "20292"
                    ]
                },
                "financials": {
                    "capital": "225,000 kr",
                    "employees": {
                        "industriarb": 65
                    },
                    "annual_turnover": "800,000 kr"
                },
                "foundation_year": 1927
            },
            {
                "name": "Linköpings Strå- & Filthattfabrik AB",
                "location": "Linköping",
                "business": "Tillverkar spec. damhattar och modevaror",
                "contact": {
                    "telegraph": "Hattfabriken, Linköping",
                    "phone": [
                        "Linköpings Strå- o. Filthattfabrik"
                    ],
                    "postgiro": "84040"
                },
                "financials": {
                    "capital": "300,000 kr",
                    "employees": {
                        "industriarb": 125
                    },
                    "annual_turnover": "1,250,000 kr"
                },
                "foundation_year": 1919,
                "director": "fröken Ida Israelsson",
                "kamrer": "Eric Träff"
            }
        ]
    }
}