{
    "original": "Lundgren—Lundin\n\n*AB. Dan. Lundgrens Läderfabrik,\n\nFalkenberg.\n\nTillverkar bottenläder, plattläder,\nres-effektläder och färgat läder.\n\nTelegr.-adr.: Läder, Falkenberg.\nTelefon: 975. Postgiro: 25879.\n\nAkt.-kap.: 700,000 kr. Antal\nindustriarb.: 70. Tillv.-värde pr år: 2,500,000 kr.\n— Firman etabl. 1835, bolag 1900.\n\nStyrelse: häradshövd. John A.\nSamuelson (ordf.), dir. A. P. Hallqvist, disp.\nÅke Hallqvist, lasarettssysslom. Arvid\nManzér, dir. Gustaf Nordström.\n\nVerkst. dir.: Gustaf Nordström.\n\n*C. Lundgrens Eftr. AB., Gustafs.\n\nTillverkar hyvlade trävaror, ramlister,\nramar och speglar vid guldlistfabrik i\nGustafs (Kopparb. l.).\n\nTelefon: Borlänge 40024. Postgiro:\n90300. — Akt.-kap.: 100,000 kr. Antal\nindustriarb.: 45. — Firman etabl. 1915,\nbolag 1945.\n\nStyrelse o. verkst. dir.: Clas Jakobsson.\n\n*AB. M. Lundgrens Cjuteri,\n\nHalmstad.\n\nGjuteri, mek. verkstad och\nemaljerings-verk. Tillverkar pumpar, ventiler, gjutna\nrördelar, sanitetsgjutgods, badkar och\nhandelsgjutgods. Varumärke: »ML».\n\nTelefon: 418, 449 o. 470. Postgiro:\n33299.\n\nAkt.-kap.: 300,000 kr. Antal\nindustriarb.: 185. Tillv.-värde pr år: 3,600,000 kr.\n—- Firman etabl. 1917, bolag 1932.\n\nStyrelse: ing. Hugo Lundgren, disp.\nJohn Lundgren, kamrer Gunnar\nLundgren.\n\nChefer: disp. John Lundgren o. ing.\nHugo Lundgren.\n\n*N. Lundgren, Gävle.\n\nTegelbruk i Uppsala (Uppsala Norra\nTegelbruk) och skorstensbyggnadsfirma i\nGävle. Tillverkar skorstenstegel; bygger\nskorstenar för fabriks- och andra\nändamål; utför ångpanne-, ugns- och andra\nindustriella inmurningar samt eld- och\nsyrafasta, alkalie-, salt- och oljefasta\nmureriarbeten.\n\nKontor: Gävle. Telegr.-adr.: Skorsten,\nGävle. Telefon: 151 o. 152. Postgiro:\n26178.\n\nAntal industriarb.: 58. Tillv.-värde pr\når: 850,000 kr. Årsprod. av tegelvaror:\n1,3 milj. st. — Firman etabl. 1869.\n\nÄgare: N. Lundgrens sterbhus.\n\nDisp.: ing. Ernst Ström.\n\nAvd.-chef i Uppsala: tegelmäst. Edvin\nÅsberg.\n\n(Jfr annons nr 19.)\n\n*AB. Lundholms Skomanufaktur,\n\nKumla.\n\nTillverkar rand-, vänd- och\nsandal-sydda skodon.\n\nTelefon: 70930. Postgiro: 20806.\n\nAkt.-kap.: 255,000 kr. Antal\nindustriarb.: 100. — Bolaget grundat 1919.\n\nStyrelse: dir. E. Ax. Lundholm (ordf.),\nadv. J. Frenander, disp. Sven Lundholm.\n\nVerkst. dir.: E. Ax. Lundholm.\n\n\"David Lundholm, Byggnads AB.,\n\nÖrebro.\n\nByggnadsentreprenörfirma för\nbostads-och affärshus, industribyggnader m. m.\n\nTelefon: 12615 o. 22195. Postgiro:\n161012. — Akt.-kap.: 50,000 kr.\nProd.-värde pr år: 1,000,000 kr. — Bolaget\ngrundat 1938.\n\nStyrelse: byggnadsing. Gunnar\nLundholm (ordf.), byggnadsing. Ewert\nBjörnestad (v. ordf.), fru Maj Björnestad, adv.\nJosef Frenander.\n\nVerkst. direktörer: Gunnar Lundholm\n\n0.\tEwert Björnestad.\n\n* Lundin &amp; Co., Råneå.\n\nGarveri och skofabrik i Råneå (Norrb.\n\n1.).\tTillverkar ovanläder och sulläder samt\npjäxor, vandrarskor och näbbskor.\nFirman driver även detaljhandel med\nskodon.\n\nTelefon: 163 o. 99. Postgiro: 60016.\n\nAntal industriarb.: 40. Tillv.-värde pr\når: för garveriet 200,000 kr., för\nskofabriken 500,000 kr. — Firman etabl.\n1883, bolag 1915.\n\nÄgare o. chefer: fabr. Hugo Lundin o.\nfabr. Ernst Lundin.\n\nAB. Lundin &amp; Johansson, Berga.\n\nSågverk och hyvleri i Berga (Kalmar\n1.). Tillverkar hyvlade trävaror, paneler\noch listverk m. m. Varumärke: »L. &amp; J.».\n\nTelegr.-adr.: Dörrar, Berga. Telefon: 6.\nPostgiro: 23761. — Akt.-kap.: 50,500 kr.\nArb.-antal: 8. Tillv.-värde pr år: 80,000\nkr. — Bolaget grundat 1924.\n\nStyrelse: disp. P. Lundin (ordf.), fru\nC. Lundin, fru D. Nyström.\n\nVerkst. dir. o. disp.: P. Lundin.\n\nKassör: C.-G. Lundin.\n\n*AB. Lundin &amp; Lindberg,\n\nEskilstuna.\n\nMetallvarufabrik. Tillverkar kokkärl,\ntennvaror, askurnor samt pressade,\ntryckta och svarvade delar i järn och\nmetall.",
    "structured": {
        "1": {
            "name": "AB. Dan. Lundgrens Läderfabrik",
            "location": "Falkenberg",
            "business": "Tillverkar bottenläder, plattläder, res-effektläder och färgat läder",
            "contact": {
                "telegraph": "Läder, Falkenberg",
                "phone": [
                    "975"
                ],
                "postgiro": "25879"
            },
            "financials": {
                "capital": "700,000 kr",
                "employees": {
                    "industriarb": 70
                },
                "annual_turnover": "2,500,000 kr",
                "annual_production_value": "2,500,000 kr"
            },
            "foundation_year": 1835,
            "corporation_year": 1900,
            "board": [
                {
                    "name": "häradshövd. John A. Samuelson",
                    "role": "ordf."
                },
                {
                    "name": "dir. A. P. Hallqvist",
                    "role": "disp."
                },
                {
                    "name": "Åke Hallqvist",
                    "role": "disp."
                },
                {
                    "name": "lasarettssysslom. Arvid Manzér",
                    "role": ""
                },
                {
                    "name": "dir. Gustaf Nordström",
                    "role": ""
                }
            ],
            "manager": "Gustaf Nordström"
        },
        "2": {
            "name": "C. Lundgrens Eftr. AB",
            "location": "Gustafs",
            "business": "Tillverkar hyvlade trävaror, ramlister, ramar och speglar vid guldlistfabrik i Gustafs (Kopparb. l.)",
            "contact": {
                "phone": [
                    "Borlänge 40024"
                ],
                "postgiro": "90300"
            },
            "financials": {
                "capital": "100,000 kr",
                "employees": {
                    "industriarb": 45
                }
            },
            "foundation_year": 1915,
            "corporation_year": 1945,
            "board": [
                {
                    "name": "Clas Jakobsson",
                    "role": ""
                }
            ],
            "manager": "Clas Jakobsson"
        },
        "3": {
            "name": "AB. M. Lundgrens Gjuteri",
            "location": "Halmstad",
            "business": "Gjuteri, mek. verkstad och emaljerings-verk. Tillverkar pumpar, ventiler, gjutna rördelar, sanitetsgjutgods, badkar och handelsgjutgods. Varumärke: »ML»",
            "contact": {
                "phone": [
                    "418",
                    "449",
                    "470"
                ],
                "postgiro": "33299"
            },
            "financials": {
                "capital": "300,000 kr",
                "employees": {
                    "industriarb": 185
                },
                "annual_turnover": "3,600,000 kr",
                "annual_production_value": "3,600,000 kr"
            },
            "foundation_year": 1917,
            "corporation_year": 1932,
            "board": [
                {
                    "name": "ing. Hugo Lundgren",
                    "role": "disp."
                },
                {
                    "name": "John Lundgren",
                    "role": "disp."
                },
                {
                    "name": "Gunnar Lundgren",
                    "role": "kamrer"
                }
            ],
            "director": "disp. John Lundgren",
            "managing_director": "ing. Hugo Lundgren"
        },
        "4": {
            "name": "N. Lundgren",
            "location": "Gävle",
            "business": "Tegelbruk i Uppsala (Uppsala Norra Tegelbruk) och skorstensbyggnadsfirma i Gävle. Tillverkar skorstenstegel; bygger skorstenar för fabriks- och andra ändamål; utför ångpanne-, ugns- och andra industriella inmurningar samt eld- och syrafasta, alkalie-, salt- och oljefasta mureriarbeten",
            "contact": {
                "office": "Gävle",
                "telegraph": "Skorsten, Gävle",
                "phone": [
                    "151",
                    "152"
                ],
                "postgiro": "26178"
            },
            "financials": {
                "employees": {
                    "industriarb": 58
                },
                "annual_turnover": "850,000 kr"
            },
            "foundation_year": 1869,
            "owners": [
                "N. Lundgrens sterbhus"
            ],
            "director": "disp. ing. Ernst Ström"
        },
        "5": {
            "name": "AB. Lundholms Skomanufaktur",
            "location": "Kumla",
            "business": "Tillverkar rand-, vänd- och sandal-sydda skodon",
            "contact": {
                "phone": [
                    "70930"
                ],
                "postgiro": "20806"
            },
            "financials": {
                "capital": "255,000 kr",
                "employees": {
                    "industriarb": 100
                }
            },
            "foundation_year": 1919,
            "board": [
                {
                    "name": "dir. E. Ax. Lundholm",
                    "role": "ordf."
                },
                {
                    "name": "adv. J. Frenander",
                    "role": ""
                },
                {
                    "name": "Sven Lundholm",
                    "role": "disp."
                }
            ],
            "manager": "E. Ax. Lundholm"
        },
        "6": {
            "name": "David Lundholm, Byggnads AB.",
            "location": "Örebro",
            "business": "Byggnadsentreprenörfirma för bostads-och affärshus, industribyggnader m. m",
            "contact": {
                "phone": [
                    "12615",
                    "22195"
                ],
                "postgiro": "161012"
            },
            "financials": {
                "capital": "50,000 kr",
                "annual_turnover": "1,000,000 kr"
            },
            "foundation_year": 1938,
            "board": [
                {
                    "name": "byggnadsing. Gunnar Lundholm",
                    "role": "ordf."
                },
                {
                    "name": "byggnadsing. Ewert Björnestad",
                    "role": "v.ordf."
                },
                {
                    "name": "fru Maj Björnestad",
                    "role": ""
                },
                {
                    "name": "adv. Josef Frenander",
                    "role": ""
                }
            ],
            "manager": "Gunnar Lundholm"
        },
        "7": {
            "name": "Lundin & Co.",
            "location": "Råneå",
            "business": "Garveri och skofabrik i Råneå (Norrb. l.). Tillverkar ovanläder och sulläder samt pjäxor, vandrarskor och näbbskor. Firman driver även detaljhandel med skodon",
            "contact": {
                "phone": [
                    "163",
                    "99"
                ],
                "postgiro": "60016"
            },
            "financials": {
                "employees": {
                    "industriarb": 40
                },
                "annual_turnover": "700,000 kr",
                "annual_production_value": "700,000 kr"
            },
            "foundation_year": 1883,
            "corporation_year": 1915,
            "owners": [
                "fabr. Hugo Lundin",
                "fabr. Ernst Lundin"
            ],
            "manager": "fabr. Hugo Lundin"
        },
        "8": {
            "name": "AB. Lundin & Johansson",
            "location": "Berga",
            "business": "Sågverk och hyvleri i Berga (Kalmar 1.). Tillverkar hyvlade trävaror, paneler och listverk m. m. Varumärke: »L. & J.»",
            "contact": {
                "telegraph": "Dörrar, Berga",
                "phone": [
                    "6"
                ],
                "postgiro": "23761"
            },
            "financials": {
                "capital": "50,500 kr",
                "employees": {
                    "industriarb": 8
                },
                "annual_turnover": "80,000 kr"
            },
            "foundation_year": 1924,
            "board": [
                {
                    "name": "disp. P. Lundin",
                    "role": "ordf."
                },
                {
                    "name": "fru C. Lundin",
                    "role": ""
                },
                {
                    "name": "fru D. Nyström",
                    "role": ""
                }
            ],
            "manager": "disp. P. Lundin",
            "sales_manager": "C.-G. Lundin"
        },
        "9": {
            "name": "AB. Lundin & Lindberg",
            "location": "Eskilstuna",
            "business": "Metallvarufabrik. Tillverkar kokkärl, tennvaror, askurnor samt pressade, tryckta och svarvade delar i järn och metall",
            "contact": {
                "phone": [
                    "***"
                ],
                "postgiro": "***"
            }
        }
    }
}