{
    "original": "BäcJclund—Bäckström\n\nAgenter i utlandet:\n\nEngland o. Eire: George Harrison,\nAgencies, Ltd, 22, tfpper Thames Street,\nLondon E. O. 4;\n\nBelgien: Le Duplex s. p. r. L, 37, Rue\nAuguste Denie, Bryssel;\n\nIndien: Shambhulal A. Shah &amp; Co.,\nPodar Chambers, Parsi Bazar St. Fort,\nBombay 1.\n\nAkt.-kap.: 350,000 kr. Antal\nindustriarb.: 140. Årstillv.: 18,000 ton papper o.\npapp.\n\nPappersbruket anlagt 1871, bolag 1894,\nnuv. namn 1946.\n\nStyrelse: civiling. Peder Thilén (ordf.),\ning. Bengt Ekholm, civiling. S. O.\nSandberg, ing. E. Sjögren, disp. Leif Thilén.\n\nVerkst. dir.: Peder Thilén.\n\nFabrikschefer: för sulfatfabriken: S.\nO. Sandberg; för pappersbruket: Bengt\nEkholm; för takpappfabriken: E.\nSjögren.\n\nKontorschef: Olle Falkfors.\n\nFörsäljn.-chef : Harry Eliström.\n\nV. Bäcklunds Metallvarufabrik,\n\nSkellefteå.\n\nTillverkar kokkärl och hushållskärl i\naluminium och koppar samt\nvarmvattenberedare.\n\nTelegr.-adr.: Bäcklundskärl, Skellefteå.\nTelefon: 10159 o. 11159. Postgiro: 29819.\n— Antal industriarb.: 18. — Firman\ngrundad 1860.\n\nÄgare o. chef: fabr. Viktor Bäcklund.\nDisp.: K. A. Bäcklund.\n\n*Vilh. Bäckman, Kvarnbyggerifirma,\n\nBjörköby.\n\nSe Kvarnbyggerifirman Vilh. Bäckman,\nBjörköby.\n\nSe även Beckman.\n\nBäckseda Möbelverkstad,\n\nBäckseda.\n\nSnickerifabrik i Bäckseda (Jönköp. l.).\nTillverkar radiolådor och -skåp,\ngrammofonlådor, urfodral m. m.\n\nTelefon: Vetlanda 867. Postgiro: 72422.\n— Antal industriarb.: 20. Tillv.-värde pr\når: 200,000 kr. — Firman etabl. 1909.\n\nÄgare o. chefer: fabr. Josef Svensson\no. fabr. Sam H. Svensson.\n\n*OsGar Bäcksins AB-, Göteborg.\n\nFärg- och fernissfabrik. Tillverkar\nlackfärger (»Mikadolack»), syntetiska\nlackfärger (»Synitlack»), cellulosalacker\nför möbler (»Etoxol») samt för bilar\n(»Etoxin»), emulsionsfärger (»Obematt»),\nmatta oljefärger (»Bäxoflat»), kopal- och\nspritfernissor, maskinfärger och glasyrer,\nsickativer, oljor m. m. Bolaget driver\njämväl engrosaffär samt detaljhandel genom\n10 minutaffärer.\n\nKontor o. lager: Postg. 17.\nTelegr.-adr.: Bäcksino, Göteborg. Telefon:\n»Oscar Bäcksins AB». Postgiro: 12016.\n\nAkt.-kap.: 500,000 kr. Antal\nindustriarb.: 40. Tillv.-värde pr år: 2,000,000 kr.\n\nBolaget grundat 1919, då det övertog\nden år 1901 av Oscar Bäcks in grundade\nfirman med samma namn. Bolaget äger\nAB. Bäxinol, Göteborg.\n\nStyrelse: dir. Bernhard Bäcksin, ing.\nH. Schalin, dir. Harald Treutiger.\n\nVerkst. dir.: Harald Treutiger.\n\nKontorschef: Nils Glanzelius.\n\nFörsäljn.-chef: Arne N. Elgquist.\n\n*\tBäckström &amp; Strömberg, Umeå.\n\nByggnadsentreprenörfirma i Teg\n(Västerb. l.). Entreprenör för bostads- och\naffärshus, industribyggnader samt\nkraftverksbyggnader.\n\nTelegr.-adr.: Byggnadsbolaget, TJmeå.\nTelefon: Umeå 570 o. 572. Postgiro:\n63033. — Prod.-värde pr år: 9,000,000 kr.\n— Firman etabl. 1909.\n\nChef: byggm. J. M. Bäckström.\n\nAvd.-chefer: byggm. J\\ Edvin\nBäckström o. byggm. Folke Bäckström.\n\nKamrer: Frans Lundström.\n\nA. Bäckströms Klichéanstalt,\n\nStockholm.\n\nTillverkar kemigrafiska arbeten i svart\noch färg.\n\nKontor: Tunnelg. 3. Telefon: 201404 o.\n201419. Postgiro: 58302. — Antal\nindustriarb.: 14. Tillv.-värde pr år: 230,000\nkr. — Firman etabl. 1926.\n\nÄgare o. chef: fabr. Allan Bäckström.\n\n*\tEinar Bäckström, Metallvarufabrik,\n\nMalmö.\n\nMetallvarufabrik. Tillverkar elektr.\nbelysningsarmatur. Ensamtillv. för Sverige\noch Norge av »Megaphos»-armatur.\n\nKontor: Föreningsg. 8. Telegr.-adr.:\nLampljus, Malmö. Telefon: 26954 o.\n17754. Postgiro: 14157. — Representant:",
    "structured": {
        "1": {
            "name": "BäcJclund—Bäckström",
            "location": "Skellefteå",
            "business": "Pappersbruk",
            "products": "18,000 ton papper och papp.",
            "contact": {
                "office": "Bäcklundskärl, Skellefteå",
                "phone": [
                    "10159",
                    "11159"
                ],
                "postgiro": "29819"
            },
            "financials": {
                "capital": "350,000 kr",
                "employees": {
                    "industriarb": 140
                },
                "annual_turnover": "Not available",
                "annual_production_value": "Not available"
            },
            "foundation_year": 1871,
            "current_name_year": 1946,
            "board": [
                {
                    "name": "civiling. Peder Thilén",
                    "role": "ordförande"
                },
                {
                    "name": "ing. Bengt Ekholm",
                    "role": "Not available"
                },
                {
                    "name": "civiling. S. O. Sandberg",
                    "role": "Not available"
                },
                {
                    "name": "ing. E. Sjögren",
                    "role": "Not available"
                },
                {
                    "name": "disp. Leif Thilén",
                    "role": "Not available"
                }
            ],
            "owners": [
                "fabr. Viktor Bäcklund"
            ],
            "director": "Not available",
            "managing_director": "Peder Thilén",
            "sales_manager": "Harry Eliström",
            "manager": "Not available"
        },
        "2": {
            "name": "V. Bäcklunds Metallvarufabrik",
            "location": "Skellefteå",
            "business": "Metallvarufabrik",
            "products": "Kokkärl, hushållskärl i aluminium och koppar, varmvattenberedare.",
            "contact": {
                "office": "Bäcklundskärl, Skellefteå",
                "phone": [
                    "10159",
                    "11159"
                ],
                "postgiro": "29819"
            },
            "financials": {
                "capital": "Not available",
                "employees": {
                    "industriarb": 18
                },
                "annual_turnover": "Not available",
                "annual_production_value": "Not available"
            },
            "foundation_year": 1860,
            "board": [
                {
                    "name": "Not available",
                    "role": "Not available"
                }
            ],
            "owners": [
                "fabr. Viktor Bäcklund"
            ],
            "director": "Not available",
            "managing_director": "Not available",
            "sales_manager": "Not available",
            "manager": "K. A. Bäcklund"
        },
        "3": {
            "name": "Bäckseda Möbelverkstad",
            "location": "Bäckseda",
            "business": "Snickerifabrik",
            "products": "Radiolådor, -skåp, grammofonlådor, urfodral m.m.",
            "contact": {
                "office": "Not available",
                "phone": [
                    "Vetlanda 867"
                ],
                "postgiro": "72422"
            },
            "financials": {
                "capital": "Not available",
                "employees": {
                    "industriarb": 20
                },
                "annual_turnover": "Not available",
                "annual_production_value": "200,000 kr"
            },
            "foundation_year": 1909,
            "board": [
                {
                    "name": "Not available",
                    "role": "Not available"
                }
            ],
            "owners": [
                "fabr. Josef Svensson",
                "fabr. Sam H. Svensson"
            ],
            "director": "Not available",
            "managing_director": "Not available",
            "sales_manager": "Not available",
            "manager": "Not available"
        },
        "4": {
            "name": "OsGar Bäcksins AB",
            "location": "Göteborg",
            "business": "Färg- och fernissfabrik",
            "products": "Lackfärger, syntetiska lackfärger, cellulosalacker för möbler, emulsionsfärger, oljefärger, kopal- och spritfernissor, maskinfärger, glasyrer, sickativer, oljor m.m.",
            "contact": {
                "office": "Postg. 17",
                "phone": [
                    "Oscar Bäcksins AB"
                ],
                "postgiro": "12016"
            },
            "financials": {
                "capital": "500,000 kr",
                "employees": {
                    "industriarb": 40
                },
                "annual_turnover": "2,000,000 kr",
                "annual_production_value": "Not available"
            },
            "foundation_year": 1919,
            "board": [
                {
                    "name": "dir. Bernhard Bäcksin",
                    "role": "Not available"
                },
                {
                    "name": "ing. H. Schalin",
                    "role": "Not available"
                },
                {
                    "name": "dir. Harald Treutiger",
                    "role": "Not available"
                }
            ],
            "owners": [
                "AB. Bäxinol, Göteborg"
            ],
            "director": "Not available",
            "managing_director": "Harald Treutiger",
            "sales_manager": "Arne N. Elgquist",
            "manager": "Not available"
        },
        "5": {
            "name": "Bäckström & Strömberg",
            "location": "Umeå",
            "business": "Byggnadsentreprenörfirma",
            "products": "Bostads- och affärshus, industribyggnader, kraftverksbyggnader.",
            "contact": {
                "office": "Byggnadsbolaget, Umeå",
                "phone": [
                    "Umeå 570",
                    "Umeå 572"
                ],
                "postgiro": "63033"
            },
            "financials": {
                "capital": "Not available",
                "employees": {
                    "industriarb": "Not available"
                },
                "annual_turnover": "9,000,000 kr",
                "annual_production_value": "Not available"
            },
            "foundation_year": 1909,
            "board": [
                {
                    "name": "Not available",
                    "role": "Not available"
                }
            ],
            "owners": [
                "Not available"
            ],
            "director": "Not available",
            "managing_director": "Not available",
            "sales_manager": "Not available",
            "manager": "byggm. J. M. Bäckström"
        },
        "6": {
            "name": "A. Bäckströms Klichéanstalt",
            "location": "Stockholm",
            "business": "Kemigrafiska arbeten",
            "products": "Kemigrafiska arbeten i svart och färg.",
            "contact": {
                "office": "Tunnelg. 3",
                "phone": [
                    "201404",
                    "201419"
                ],
                "postgiro": "58302"
            },
            "financials": {
                "capital": "Not available",
                "employees": {
                    "industriarb": 14
                },
                "annual_turnover": "Not available",
                "annual_production_value": "230,000 kr"
            },
            "foundation_year": 1926,
            "board": [
                {
                    "name": "Not available",
                    "role": "Not available"
                }
            ],
            "owners": [
                "fabr. Allan Bäckström"
            ],
            "director": "Not available",
            "managing_director": "Not available",
            "sales_manager": "Not available",
            "manager": "Not available"
        },
        "7": {
            "name": "Einar Bäckström",
            "location": "Malmö",
            "business": "Metallvarufabrik",
            "products": "Elektr. belysningsarmatur.",
            "contact": {
                "office": "Föreningsg. 8",
                "phone": [
                    "26954",
                    "17754"
                ],
                "postgiro": "14157"
            },
            "financials": {
                "capital": "Not available",
                "employees": {
                    "industriarb": "Not available"
                },
                "annual_turnover": "Not available",
                "annual_production_value": "Not available"
            },
            "foundation_year": "Not available",
            "board": [
                {
                    "name": "Not available",
                    "role": "Not available"
                }
            ],
            "owners": [
                "Not available"
            ],
            "director": "Not available",
            "managing_director": "Not available",
            "sales_manager": "Not available",
            "manager": "Not available"
        }
    }
}