{
    "original": "Gjuteri—Glimma\n\nAkt.-kap.: 200,000 kr. Antal\nindustriarb.: 125. Tillv.-värde pr år: 2,000,000 kr.\n\n—\tBolaget grundat 1927.\n\nStyrelse: adv. Sven Munck af\nRosen-sehöld, dir. J. E. Sande J:or, dir. Jean\nSilfving.\n\nVerkst. dir.: Jean Silfving.\nV. verkst. dir.: Sten Beite.\nDirassist. o. försäljn.-chef: Ragnar\nWi-sén.\n\nVerkstadschef: F. Hult.\n\nGjuter i AB. Normalrör,\n\nÄTeers styckebruk.\n\nTillverkar gjutna raka normalrör vid\ngjuteri i Eskilstuna. Varumärke: GN.\n\nKontor: Åkers styckebruk. Telefon:\nMariefred 55. Postgiro: 276907.\n\nAkt.-kap.: 30,000 kr. Antal\nindustriarb.: 180. Tillv.-värde pr år: 3,000,000 kr.\n\n—\tBolaget, grundat 1944, är dotterbolag\ntill AB. Åkers Styckebruk.\n\nStyrelse: bruksäg. Rutger v. Seth\n(ordf.), dir. Claes Gejrot, dir. Gunnar\nHult.\n\nVerkst. dir.: Rutger v. Seth.\nDriftsing.: Harry Eriksson.\n\n\"AB. Gjuterimaskiner, Halmstad.\n\nMek. verkstad och gjuteri. Tillverkar\ngjuterimaskiner och alla slags\nförnödenheter för gjuterier och modellverkstäder,\nvärmeledningsspisar och\nvärmeledningspannor, kokplattor, handpumpar,\ntackjärns- och metallgjutgods m. m. samt\nutför plåtarbeten och svetsning.\n\nTelegr.-adr.: Stans, Halmstad. Telefon:\n»Malcus». Postgiro: 77300.\n\nAkt.-kap.: 450,000 kr. Antal\nindustriarb.: 130. Tillv.-värde pr år: 1,550,000 kr.\n— Bolaget grundat 1913.\n\nStyrelse: dir. Edw. Berger (ordf.), ing.\nJohan G. Wendt (v. ordf.), disp. Carl\nMagnus Berger, v. konsul A. O. Hill.\n\nDisp.: ing. Nils Svensson.\n\nKamrer: Martin Ericson.\n\n\"AB. Glacéläderfabriken, Kävlinge.\n\nFårskinnsgarveri i Kävlinge (Malmöh.\n1.). Bereder får- och lammskinn för olika\nändamål.\n\nTelegr.-adr. o. telefon: Glacéläder,\nKävlinge. Postgiro: 30818.\n\nAkt.-kap.: 1,000,000 kr. Antal\nindustriarb.: 275. Tillv.-värde pr år: 12,000,000 kr.\n\nBolaget grundat 1898 under namn\nMalmö Handsk- &amp; Glacéläderfabriks AB.,\nnuv. namn 1929.\n\n1\n\nStyrelse: konsul Edw. H. Thomée\n(ordf.), dir. Frans Möller, amanuens\nMogens Möller.\n\nVerkst. dir.: Frans Möller.\n\nKontorschef: Albin Norrbring.\n\nAB. Clas &amp; Trä, Hovmantorp.\n\nSnickeri, glassliperi, folierings- oeii\nförgylleri verkstad i Hovmantorp\n(Kronob. l.). Tillverkar speglar, piedestaler,\nkompletteringsmöbler, badrumsskåp,\nserveringsbrickor, bordsdekorationer i glas\nm. m. Varumärke: »G. &amp; T.».\n\nTelegr.-adr.: Glasträ, Hovmantorp.\nTelefon: 1. o. 78. Postgiro: 275503. Repr. i\nMalmö: Möbel AB. Gustaf Lundgren.\nGust. Ad. torg 41, telefon: 14083.\n\nAkt.-kap.: 60,000 kr. Antal\nindustriarb.: 60. Tillv.-värde pr år: 800,000 kr.\n—- Bolaget grundat 1943.\n\nVerkst. dir.: disp. Gösta Franzén.\n\nCleisner &amp; Co.,\nKommanditbolaget, Älghultsby.\n\nSe Kommanditbolaget Gleisner &amp; Co.,\nÄlghultsby.\n\nAB. E. T. Cleitsmann, Trelleborg.\n\nTryckfärgsfabrik. Tillverkar svarta och\nkulörta tryckfärger, tryckfernissor,\nvalsmassa, torkpreparat, grafiska hjälpmedel\nm. m.\n\nTelefon: 1540. Postgiro: 23066. —\nAkt.-kap.: 200,000 kr. Antal industriarb.:\n40. — Bolaget grundat 1901.\n\nStyrelse: f. d. borgm. G. Rosencrantz\n(ordf.), övering. Hans Köhler, köpm. H.\nMaresch.\n\nVerkst. dir.: vakant.\n\növering.: Hans Köhler.\n\n\"Clemminge Tegelbruk, John\nGlem-ming, Glemmingebro.\n\nTillverkar murtegel och dräneringsrör\nvid tegelbruk i Glemmingebro\n(Kristian-st. l.).\n\nTelefon: 10. Postgiro: 72492.\n\nAntal industriarb.: 25. Årstillv.: 1,9\nmilj. st. tegel var or. — Tegelbruket anlagt\n1870, nuv. firma etabl. 1933.\n\nÄgare o. chef: disp. John Glemming.\n\nKamrer: A. E. Antonsson.\n\n\"Glimma Glasbruks AB.,\n\nGlimåkra.\n\nGlasbruk vid Glimåkra (Kristianst. l.).\nTillverkar hushålls- och restaurantglas,\n\ni*",
    "structured": {
        "1": {
            "name": "Gjuteri—Glimma",
            "financials": {
                "capital": "200,000 kr",
                "employees": {
                    "industriarb": 125
                },
                "annual_turnover": "2,000,000 kr"
            },
            "foundation_year": 1927,
            "board": [
                {
                    "name": "adv. Sven Munck af Rosen-sehöld",
                    "role": "Styrelse"
                },
                {
                    "name": "dir. J. E. Sande J:or",
                    "role": "Styrelse"
                },
                {
                    "name": "dir. Jean Silfving",
                    "role": "Styrelse"
                }
            ],
            "director": "Jean Silfving",
            "managing_director": "Sten Beite",
            "sales_manager": "Ragnar Wi-sén"
        },
        "2": {
            "name": "Gjuter i AB. Normalrör",
            "location": "Eskilstuna",
            "products": "Tillverkar gjutna raka normalrör vid gjuteri i Eskilstuna. Varumärke: GN.",
            "contact": {
                "office": "Åkers styckebruk",
                "phone": [
                    "Mariefred 55"
                ],
                "postgiro": "276907"
            },
            "financials": {
                "capital": "30,000 kr",
                "employees": {
                    "industriarb": 180
                },
                "annual_turnover": "3,000,000 kr"
            },
            "foundation_year": 1944,
            "predecessor": "AB. Åkers Styckebruk",
            "board": [
                {
                    "name": "bruksäg. Rutger v. Seth",
                    "role": "Styrelse"
                },
                {
                    "name": "dir. Claes Gejrot",
                    "role": "Styrelse"
                },
                {
                    "name": "dir. Gunnar Hult",
                    "role": "Styrelse"
                }
            ],
            "director": "Rutger v. Seth",
            "sales_manager": "Harry Eriksson"
        },
        "3": {
            "name": "AB. Gjuterimaskiner, Halmstad",
            "location": "Halmstad",
            "products": "Tillverkar gjuterimaskiner och alla slags förnödenheter för gjuterier och modellverkstäder, värmeledningsspisar och värmeledningspannor, kokplattor, handpumpar, tackjärns- och metallgjutgods m. m. samt utför plåtarbeten och svetsning.",
            "contact": {
                "telegraph": "Stans, Halmstad",
                "phone": "»Malcus»",
                "postgiro": "77300"
            },
            "financials": {
                "capital": "450,000 kr",
                "employees": {
                    "industriarb": 130
                },
                "annual_turnover": "1,550,000 kr"
            },
            "foundation_year": 1913,
            "board": [
                {
                    "name": "dir. Edw. Berger",
                    "role": "Styrelse"
                },
                {
                    "name": "ing. Johan G. Wendt",
                    "role": "Styrelse"
                },
                {
                    "name": "disp. Carl Magnus Berger",
                    "role": "Styrelse"
                },
                {
                    "name": "v. konsul A. O. Hill",
                    "role": "Styrelse"
                }
            ],
            "director": "disp. ing. Nils Svensson",
            "manager": "Martin Ericson"
        },
        "4": {
            "name": "AB. Glacéläderfabriken, Kävlinge",
            "location": "Kävlinge",
            "products": "Bereder får- och lammskinn för olika ändamål.",
            "contact": {
                "telegraph": "Glacéläder, Kävlinge",
                "phone": "Glacéläder, Kävlinge",
                "postgiro": "30818"
            },
            "financials": {
                "capital": "1,000,000 kr",
                "employees": {
                    "industriarb": 275
                },
                "annual_turnover": "12,000,000 kr"
            },
            "foundation_year": 1898,
            "current_name_year": 1929,
            "board": [
                {
                    "name": "konsul Edw. H. Thomée",
                    "role": "Styrelse"
                },
                {
                    "name": "dir. Frans Möller",
                    "role": "Styrelse"
                },
                {
                    "name": "amanuens Mogens Möller",
                    "role": "Styrelse"
                }
            ],
            "director": "Verkst. dir.: Frans Möller",
            "manager": "Albin Norrbring"
        },
        "5": {
            "name": "AB. Clas & Trä, Hovmantorp",
            "location": "Hovmantorp",
            "products": "Tillverkar speglar, piedestaler, kompletteringsmöbler, badrumsskåp, serveringsbrickor, bordsdekorationer i glas m. m.",
            "contact": {
                "telegraph": "Glasträ, Hovmantorp",
                "phone": "Möbel AB. Gustaf Lundgren",
                "postgiro": "275503"
            },
            "financials": {
                "capital": "60,000 kr",
                "employees": {
                    "industriarb": 60
                },
                "annual_turnover": "800,000 kr"
            },
            "foundation_year": 1943,
            "director": "Verkst. dir.: disp. Gösta Franzén"
        },
        "6": {
            "name": "AB. E. T. Cleitsmann, Trelleborg",
            "location": "Trelleborg",
            "products": "Tillverkar svarta och kulörta tryckfärger, tryckfernissor, valsmassa, torkpreparat, grafiska hjälpmedel m. m.",
            "contact": {
                "phone": "1540",
                "postgiro": "23066"
            },
            "financials": {
                "capital": "200,000 kr",
                "employees": {
                    "industriarb": 40
                }
            },
            "foundation_year": 1901,
            "board": [
                {
                    "name": "f. d. borgm. G. Rosencrantz",
                    "role": "Styrelse"
                },
                {
                    "name": "övering. Hans Köhler",
                    "role": "Styrelse"
                },
                {
                    "name": "köpm. H. Maresch",
                    "role": "Styrelse"
                }
            ],
            "manager": "övering.: Hans Köhler"
        },
        "7": {
            "name": "Clemminge Tegelbruk, John Glemming, Glemmingebro",
            "location": "Glemmingebro",
            "products": "Tillverkar murtegel och dräneringsrör vid tegelbruk i Glemmingebro.",
            "contact": {
                "phone": "10",
                "postgiro": "72492"
            },
            "financials": {
                "employees": {
                    "industriarb": 25
                },
                "annual_production_value": "1,900,000 st. tegel var or"
            },
            "original_name": "Tegelbruket anlagt 1870, nuv. firma etabl. 1933",
            "owners": "disp. John Glemming",
            "manager": "Kamrer: A. E. Antonsson"
        },
        "8": {
            "name": "Glimma Glasbruks AB., Glimåkra",
            "location": "Glimåkra",
            "products": "Tillverkar hushålls- och restaurantglas"
        }
    }
}