{
    "original": "Munchen—Månson\n\nStyrelse: se AB. O. Mustad &amp; Son,\nGöteborg.\n\nDisp.: Knut Aarsrud.\n\n*Miinchens Bryggeri, Stockholm.\n\nSe AB. Stockholms Bryggerier, Sthlm.\n\nMyggbo Såg AB., Västerås.\n\nSågverk och hyvleri i Västerås och\nOrresta (Västmanl. l.). Tillverkar sågade\noch hyvlade trävaror samt listverk.\nFirman driver även försäljning av plywood\noch träfiberplattor.\n\nTelefon: 30467. Postgiro: 26114. —\nAkt.-kap.: 55,000 kr. Antal industriarb.:\ni Västerås 25; i Orresta 10. Årstillv.:\n1,000 stds trävaror. — Firman etabl.\n1901, bolag 1932.\n\nVerkst. dir.: A. Rudolf Rudén.\n\nMyrbacka Sågverks AB.,\n\nDala-J ärna.\n\nSågverk, hyvleri och snickerifabrik i\nMyrbacka, Dala-Järna (Kopparb. l.).\nTillverkar sågade och hyvlade trävaror samt\nbyggnadssnickerier; utför dörrar och\nfönster av svensk standardtyp.\n\nTelefon: 8. Postgiro: 76287. —\nAkt.-kap.: 78,400 kr. Antal industriarb.: 34.\nTillv.-värde pr år: 350,000 kr. —\nBolaget grundat 1900.\n\nStyrelse: hemmansäg. Olof Andersson,\nhemmansäg. Anders Danielsson,\nhemmansäg. Alfr. Kristiansson, hemmansäg.\nJosef Larsson, skräddarmäst. Kristian\nLarsson.\n\nDisp.: Hugo Samuelsson.\n\nMyrens Mek. Verkstads AB.,\n\nStrömstad.\n\nBåtbyggeri, varv och mek. verkstad.\nTillverkar roddbåtar, segelbåtar,\nmotorbåtar och livbåtar. Specialitet:\n»Strömstads jollen».\n\nPostadr.: postfack 45, Strömstad.\nTelefon: 47 o. 275. Postgiro: 173320.\n\nAkt.-kap.: 35,000 kr. Antal\nindustriarb.: 22. Tillv.-värde pr år: 250,000 kr.\n— Firman etabl. 1915, bolag 1919.\n\nVerkst. dir.: Nils Ljungqvist.\n\nAB. Myresjö-Hus, Stockholm.\n\nTillverkar snickerier och annat\nträmaterial samt monteringsfärdiga bostadshus\noch baracker vid fabrik i Myresjö\n(Jönköp. l.).\n\nHuvudkontor: Stockholm, Kungsg. 2.\nTelefon: 230380. Fabrikskontor:\nMyresjö; telefon: »Myresjö-hus».\n\nöö\n\nAkt.-kap.: 300,000 kr. Antal\nindustriarb.: 150. Tillv.-värde pr år: 6,000,000 kr.\n\n—\tBolaget grundat 1932.\n\nStyrelse: dir. Gunnar Westholm (ordf.),\ndisp. Berth Järnland, disp. Guy\nNordlander, adv. Gösta Sandstedt, disp. Curt\nWestholm.\n\nVerkst. dir.: Gunnar Westholm.\n\nDisp.: Berth Järnland.\n\n\"Myrnäs AB., Sundsvall.\n\nSe Ankarsviks Ångsågs AB., Sundsvall.\n\nMåhl &amp; Normén, Gislaved.\n\nSe Be Ma, Måhl &amp; Normén, Gislaved.\n\n\"AB. Målerås Glasbruk, Målerås.\n\nGlasbruk i Målerås (Kronob. l.).\nTillverkar hushållsglas, servisglas och\npressglas i soda, halv-kristall och färgglas,\nhelkristall och konstglas samt\nlaboratorieglas.\n\nTelegr.-adr.: Måleråsglas, Målerås.\nTelefon: 4, 24 o. 25. Postgiro: 82113.\n\nAkt.-kap.: 90,000 kr. Antal\nindustriarb.: 175. Tillv.-värde pr år: 1,500,000 kr.\n\n—\tBolaget grundat 1923.\n\nStyrelse: disp. Oskar Rosander (ordf.),\nglasarb. Simon Erlandsson, dir. Emil\nFlytström, hyttmäst. Manfred Olmert.\n\nVerkst. dir. o. disp.: Knut Rosander.\n\nKamrer: Ove Andersson.\n\n\"AB. Mål i I la Mek. Verkstad,\n\nMålilla station.\n\nSe AB. Calmoverken, Målilla station.\n\n\"Målilla Möbelfabrik, Rosenfors.\n\nTillverkar möbler och stolar vid fabrik\ni Rosenfors (Kalmar l.).\n\nTelefon: Målilla 17. — Antal\nindustriarb.: 22. Tillv.-värde pr år: 200,000 kr.\n\n—\tFirman etabl. 1898.\n\nÄgare o. chef; fabr. Halward Haglund.\n\nMalte Månson AB., Linköping.\n\nMek. verkstäder. Tillverkar\nmotordelar, motorverktyg m. m.; utför såsom\nspecialitet motorrenoveringar.\n\nTelegr.-adr.: Motorverktyg, Linköping.\nTelefon: »Malte Månson». Postgiro: 23771.\n\nAkt.-kap.: 150.000 kr. Antal\nindustriarb.: 122. Tillv.-värde pr år: 2,000,000 kr.\n\n—\tFirman etabl. 1918, bolag 1942.\nVerkst. dir.: Malte Månson.\nDir.-assistent: Bert Månson.",
    "structured": {
        "1": {
            "name": "Myggbo Såg AB.",
            "location": "Västerås",
            "business": "Sågverk och hyvleri",
            "products": "Tillverkar sågade och hyvlade trävaror samt listverk. Försäljning av plywood och träfiberplattor.",
            "contact": {
                "office": "Västerås",
                "phone": [
                    "30467"
                ],
                "postgiro": "26114",
                "factory_office": "Orresta",
                "factory_phone": "Unknown"
            },
            "financials": {
                "capital": "55,000 kr",
                "employees": {
                    "Västerås": 25,
                    "Orresta": 10
                },
                "annual_turnover": "Unknown",
                "annual_production_value": "1,000 stds trävaror"
            },
            "foundation_year": 1901,
            "corporation_year": 1932,
            "board": {
                "1": {
                    "name": "A. Rudolf Rudén",
                    "role": "Verkst. dir."
                }
            }
        },
        "2": {
            "name": "Myrbacka Sågverks AB.",
            "location": "Dala-J ärna",
            "business": "Sågverk, hyvleri och snickerifabrik",
            "products": "Tillverkar sågade och hyvlade trävaror samt byggnadssnickerier. Dörrar och fönster av svensk standardtyp.",
            "contact": {
                "office": "Myrbacka, Dala-Järna",
                "phone": [
                    "8"
                ],
                "postgiro": "76287"
            },
            "financials": {
                "capital": "78,400 kr",
                "employees": 34,
                "annual_turnover": "Unknown",
                "annual_production_value": "350,000 kr"
            },
            "foundation_year": 1900,
            "board": {
                "1": {
                    "name": "Olof Andersson",
                    "role": "Styrelse"
                },
                "2": {
                    "name": "Anders Danielsson",
                    "role": "Styrelse"
                },
                "3": {
                    "name": "Alfr. Kristiansson",
                    "role": "Styrelse"
                },
                "4": {
                    "name": "Josef Larsson",
                    "role": "Styrelse"
                },
                "5": {
                    "name": "Kristian Larsson",
                    "role": "Skräddarmäst."
                },
                "6": {
                    "name": "Hugo Samuelsson",
                    "role": "Disp."
                }
            }
        },
        "3": {
            "name": "Myrens Mek. Verkstads AB.",
            "location": "Strömstad",
            "business": "Båtbyggeri, varv och mek. verkstad",
            "products": "Tillverkar roddbåtar, segelbåtar, motorbåtar och livbåtar. Specialitet: »Strömstads jollen».",
            "contact": {
                "office": "Unknown",
                "phone": [
                    "47",
                    "275"
                ],
                "postgiro": "173320"
            },
            "financials": {
                "capital": "35,000 kr",
                "employees": 22,
                "annual_turnover": "Unknown",
                "annual_production_value": "250,000 kr"
            },
            "foundation_year": 1915,
            "board": {
                "1": {
                    "name": "Nils Ljungqvist",
                    "role": "Verkst. dir."
                }
            }
        },
        "4": {
            "name": "AB. Myresjö-Hus",
            "location": "Stockholm",
            "business": "Tillverkar snickerier och annat trämaterial samt monteringsfärdiga bostadshus och baracker",
            "contact": {
                "office": "Stockholm, Kungsg. 2",
                "phone": [
                    "230380"
                ],
                "factory_office": "Myresjö",
                "factory_phone": "»Myresjö-hus»"
            },
            "financials": {
                "capital": "300,000 kr",
                "employees": 150,
                "annual_turnover": "6,000,000 kr",
                "annual_production_value": "Unknown"
            },
            "corporation_year": 1932,
            "board": {
                "1": {
                    "name": "Gunnar Westholm",
                    "role": "Styrelse"
                },
                "2": {
                    "name": "Berth Järnland",
                    "role": "Disp."
                },
                "3": {
                    "name": "Guy Nordlander",
                    "role": "Disp."
                },
                "4": {
                    "name": "Gösta Sandstedt",
                    "role": "Adv."
                },
                "5": {
                    "name": "Curt Westholm",
                    "role": "Disp."
                }
            }
        },
        "5": {
            "name": "AB. Mål i I la Mek. Verkstad",
            "location": "Målilla station",
            "contact": {
                "office": "Unknown",
                "phone": [
                    "Unknown"
                ]
            }
        },
        "6": {
            "name": "Målilla Möbelfabrik",
            "location": "Rosenfors",
            "business": "Tillverkar möbler och stolar",
            "products": "Tillverkar möbler och stolar.",
            "contact": {
                "phone": [
                    "Målilla 17"
                ]
            },
            "financials": {
                "employees": 22,
                "annual_production_value": "200,000 kr"
            },
            "foundation_year": 1898,
            "owner": "Halward Haglund"
        },
        "7": {
            "name": "Malte Månson AB.",
            "location": "Linköping",
            "business": "Mek. verkstäder",
            "products": "Tillverkar motordelar, motorverktyg m. m.; utför motorrenoveringar.",
            "contact": {
                "phone": [
                    "Unknown"
                ],
                "postgiro": "23771"
            },
            "financials": {
                "capital": "150,000 kr",
                "employees": 122,
                "annual_production_value": "2,000,000 kr"
            },
            "corporation_year": 1942,
            "director": "Malte Månson",
            "manager": "Bert Månson"
        }
    }
}