{
    "original": "B e i gg i ’&lt;e n—B er glimt/\n\nTelefon: 220. Postgiro: 75798. —\nAntal industriarb.: 25. — Firman etabl\n1930.\n\nÄgare o. chefer: fabr. Arvid Berggren\no. fabr. Evert V. Pettersson.\n\nBerggrens Stenhuggeri,\n\nStockholm.\n\nUtför arbeten av in- oeli utländsk\nmarmor samt av kalksten.\n\nKontor: Hornsg. 117. Telegr.-adr.:\nStenberggren, Stockholm. Telefon:\n400990. Postgiro: 52267.\n\nAntal industriarb.: 11. Prod.-värde pr\når: 150,000 kr. — Firman etabl. 1920.\n\nÄgare o. chef: fabr. Karl E. Berggren.\n\nBerghems Glasbruk, Älghultsby.\n\nSe Kommanditbolaget Gleisner &amp; Co.,\nÄlghultsby.\n\nAB. Bergkvara Träindustri,\n\nBergkvara.\n\nTunnbinderi i Bergkvara (Kalmar l.).\nTillverkar smördrittlar, sillfjärdingar,\ntunnor, såpfat m. m.\n\nTelegr.-adr.: Träindustri, Bergkvara.\nTelefon: 1. Postgiro: 76781. — Akt.-kap.:\n21,000 kr. Antal industriarb.: 25.\nTillv.-värde pr år: 200,000 kr. — Bolaget\ngrundat 1913.\n\nStyrelse: dir. Josef K. Karlberg (ordf.),\ngrossh. Fritz H. Alm, verkm. J. F.\nDacke, fru K. Karlberg, hovrättsfiskal\nPer Karlberg.\n\nVerkst. dir.: J. K. Karlberg.\n\nAxel Bergkvist AB., Insjön.\n\nSågverk och kolugnar i Insjön\n(Kopparb. l.). Tillverkar sågade trävaror samt\nträkol och tjära.\n\nTelegr.-adr.: Abi, Insjön. Telefon:\n40083. Postgiro: 29493.\n\nAkt.-kap.: 100,000 kr. Antal\nindustriarb.: 50. Årstillv.: 250,000 kbft trävaror,\n15,000 kbm träkol, 600 ton trätjära. —\nBolaget grundat 1935.\n\nStyrelse o. verkst. dir.: disp. Axel E.\nBergkvist.\n\nC. R. Bergqvist Fabriks AB.,\n\nHittar ed.\n\nKonfektionsfabrik i Hillared (Älvsb.\n1.). Tillverkar blåkläder,\nballongsiden-jackor, skidkläder, pyjamas, jackor,\nskjortor, byxor, badkappor m. m.\n\nTelefon: Borås 8231. Postgiro: 135878.\n— Akt.-kap.: 85,000 kr. Tillv.-värde pr\når: 270,000 kr. — Firman etabl. 1915,\nbolag 1946.\n\nVerkst. dir.: Carl R. Bergqvist.\n\nAB. K. S. Bergling &amp; Söner,\n\nStockholm.\n\nMek. verkstad, bilverkstad, vagnfabrik,\nsadelmakeri och tapetseriverkstad. Utför\nreparationer av bilar, motorer,\nbyggnads-och vägmaskiner samt\ntapetseriinredning-ar i fartyg och bilar; tillverkar\nkarosse-rier för person- och lastautomobiler,\nbilsläpvagnar, häståkdon, dragkärror och\ntransportvagnar, bagagehållare och\ncykel-hållare till aut omobiler samt kapell,\nsufletter, dynor etc. till bilar och\nbåtar-Kontor: N. Stationsg. 12. Telefon:\n335230 o. 332999. Postgiro: 3956. —\nAkt.-kan.: 25 000 kr. Antal industriarb.::\n25. — Bolaget grundat 1925.\n\nVerkst. dir. o. verkstadschef: ing. Nils\nBergling.\n\n* Berglund &amp; Söners Möbelfabrik,\n\nKvillsfors.\n\nTillverkar kontorsmöbler vid fabrik i\nKvillsfors (Jönköp. l.). Specialitet:\nskrivbord.\n\nTelefon: 18. — Antal industriarb.: 15.\nTillv.-värde pr år: 140,000 kr. — Firman\netabl. 1937.\n\nÄgare: fabr. Emil Berglund.\nFabrikschef: fabr. Gillis Berglund.\n\n*J. Em. Berglunds Eftr.\nMetallvaru-fabrik, Ockelbo.\n\nTillverkar kokkärl av aluminium samt\nandra hushållsartiklar av aluminium vid\nfabrik i Ockelbo (Gävleb. l.).\nVarumärken: »Jebo-kärl» o. »Ugglan».\n\nTelefon: 53. Postgiro: 24370. — Antal\nindustriarb.: 10. Tillv.-värde pr år:\n250,000 kr. — Firman etabl. 1905.\nÄgare o. chef: fabr. Karl-Emil Berglund.\n\n*AB. Karl Berglunds Eftr.\nSkofabrik, Lund.\n\nTillverkar randsydda, genomsydda och\nago-skodon. Varunamn: »K. B.-skodon».\n\nTelefon: 10439. Postgiro: 6639. —\nAkt.-kap.: 40,000 kr. Antal industriarb.:\n40. Tillv.-värde pr år: 500,000 kr. —\nFirman etabl. 1899, bolag 1930.\n\nStyrelse: dir. J. Alfred Persson.\nDisp.: Folke H, Bengtsson.\n\n40*",
    "structured": {
        "1": {
            "name": "Berggrens Stenhuggeri",
            "location": "Stockholm",
            "business": "Arbeten av in- oeli utländsk marmor samt av kalksten",
            "contact": {
                "office": "Hornsg. 117",
                "phone": [
                    "400990"
                ],
                "postgiro": "52267",
                "telegraph": "Stenberggren, Stockholm"
            },
            "financials": {
                "capital": "Not Available",
                "employees": {
                    "industriarb": 11
                },
                "annual_turnover": "150,000 kr"
            },
            "foundation_year": 1920,
            "owners": [
                "fabr. Karl E. Berggren"
            ]
        },
        "2": {
            "name": "AB. Bergkvara Träindustri",
            "location": "Bergkvara",
            "business": "Tunnbinderi i Bergkvara. Tillverkar smördrittlar, sillfjärdingar, tunnor, såpfat m. m.",
            "contact": {
                "phone": [
                    "1"
                ],
                "postgiro": "76781",
                "telegraph": "Träindustri, Bergkvara"
            },
            "financials": {
                "capital": "21,000 kr",
                "employees": {
                    "industriarb": 25
                },
                "annual_turnover": "200,000 kr"
            },
            "foundation_year": 1913,
            "board": [
                {
                    "name": "dir. Josef K. Karlberg",
                    "role": "ordf."
                },
                {
                    "name": "grossh. Fritz H. Alm",
                    "role": "Not Available"
                },
                {
                    "name": "verkm. J. F. Dacke",
                    "role": "Not Available"
                },
                {
                    "name": "fru K. Karlberg",
                    "role": "Not Available"
                },
                {
                    "name": "hovrättsfiskal Per Karlberg",
                    "role": "Not Available"
                }
            ],
            "director": "J. K. Karlberg"
        },
        "3": {
            "name": "Axel Bergkvist AB.",
            "location": "Insjön",
            "business": "Sågverk och kolugnar i Insjön. Tillverkar sågade trävaror samt träkol och tjära",
            "contact": {
                "phone": [
                    "40083"
                ],
                "postgiro": "29493",
                "telegraph": "Abi, Insjön"
            },
            "financials": {
                "capital": "100,000 kr",
                "employees": {
                    "industriarb": 50
                }
            },
            "foundation_year": 1935,
            "owner": "disp. Axel E. Bergkvist"
        },
        "4": {
            "name": "C. R. Bergqvist Fabriks AB.",
            "location": "Hittar ed",
            "business": "Konfektionsfabrik i Hillared. Tillverkar blåkläder, ballongsiden-jackor, skidkläder, pyjamas, jackor, skjortor, byxor, badkappor m. m.",
            "contact": {
                "phone": [
                    "Borås 8231"
                ],
                "postgiro": "135878"
            },
            "financials": {
                "capital": "85,000 kr",
                "annual_turnover": "270,000 kr"
            },
            "foundation_year": 1915,
            "corporation_year": 1946,
            "director": "Carl R. Bergqvist"
        },
        "5": {
            "name": "AB. K. S. Bergling & Söner",
            "location": "Stockholm",
            "business": "Mek. verkstad, bilverkstad, vagnfabrik, sadelmakeri och tapetseriverkstad",
            "contact": {
                "office": "N. Stationsg. 12",
                "phone": [
                    "335230",
                    "332999"
                ],
                "postgiro": "3956"
            },
            "financials": {
                "capital": "25,000 kr",
                "employees": {
                    "industriarb": 25
                }
            },
            "foundation_year": 1925,
            "director": "ing. Nils Bergling"
        },
        "6": {
            "name": "Berglund & Söners Möbelfabrik",
            "location": "Kvillsfors",
            "business": "Tillverkar kontorsmöbler vid fabrik i Kvillsfors. Specialitet: skrivbord",
            "contact": {
                "phone": [
                    "18"
                ]
            },
            "financials": {
                "annual_turnover": "140,000 kr"
            },
            "foundation_year": 1937,
            "owners": [
                "fabr. Emil Berglund"
            ],
            "director": "fabr. Gillis Berglund"
        },
        "7": {
            "name": "J. Em. Berglunds Eftr. Metallvaru-fabrik",
            "location": "Ockelbo",
            "business": "Tillverkar kokkärl av aluminium samt andra hushållsartiklar av aluminium",
            "contact": {
                "phone": [
                    "53"
                ],
                "postgiro": "24370"
            },
            "financials": {
                "employees": {
                    "industriarb": 10
                },
                "annual_turnover": "250,000 kr"
            },
            "foundation_year": 1905,
            "owner": "fabr. Karl-Emil Berglund"
        },
        "8": {
            "name": "AB. Karl Berglunds Eftr. Skofabrik",
            "location": "Lund",
            "business": "Tillverkar randsydda, genomsydda och ago-skodon",
            "contact": {
                "phone": [
                    "10439"
                ],
                "postgiro": "6639"
            },
            "financials": {
                "capital": "40,000 kr",
                "employees": {
                    "industriarb": 40
                },
                "annual_turnover": "500,000 kr"
            },
            "foundation_year": 1899,
            "corporation_year": 1930
        }
    }
}