{
    "original": "A ndrén—A nkursrum\n\nAkt.-kap.: 70,000 kr. Antal industriarb.:\n17. — Firman etabl. 1897, bolag 1938.\n\nStyrelse o. verkst. dir.: Bernhard\nAndrén.\n\nDisp.: Bertil Andrén.\n\nAB. Edwin Andrén &amp; Co.,\n\nGöteborg.\n\nTillverkar vid avd. Nord-Neon\n(Nordiska Neonrörfabriken AB.) neonrör och\nneonskyltar. Bolaget driver även elektr.\ninstallationsrörelse samt utför elektr.\nhissanläggningar.\n\nKontor: St. Badhusg. 20. Telegr.-adr.:\nAndrén, Göteborg. Telefon: 170010.\nPostgiro: 40146. — Akt.-kap.: 225,000 kr.\nAntal industriarb.: 30. Tillv.-värde pr år:\n500,000 kr. — Firman etabL 1872, bolag\n1908.\n\nVerkst. dir.: Arvid Carlsson.\n\nVictor Andrén, Mölndal.\n\nLädervarufabrik. Tillverkar\nportmonnäer, plånböcker, tobakspungar,\nlivremmar, portföljer och väskor. Specialitet:\nDamväskor.\n\nTelefon: 270487. Postgiro: 43173. —\nAntal industriarb.: 40. — Firman etabl.\n1925.\n\nÄgare o. chef: fabr. Rolf Andrén.\n*AB. Aneby Industrier, Aneby.\n\nTrähusfabrik, sågverk och hyvleri i\nAneby (Jönköp. l.). Tillverkar\nmonteringsfärdiga trähus (märke:\n»Aneby-hus») samt sågade och hyvlade trävaror.\n\nTelegr.-adr.: Anebyindustri, Aneby.\nTelefon: »Aneby Industrier». Postgiro:\n94697. — Akt.-kap.: 200,000 kr. Antal\nindustriarb.: 50. Tillv.-värde pr år för\nträhus: 2,000,000 kr. Årstillv. av\nträvaror.- 1,200 stds. — Bolaget grundat 1945.\n\nStyrelse: löjtn. Erling Andersson\n(ordf.), insp. David Andersson, civiling.\nGillis Andersson.\n\nVerkst. dir.: Erling Andersson.\n\nRitkontorschef: John Svegfors.\n\nFörsäljn.-chef: Sigge Oresjö.\n\nAB. Aneby Waddfabrik, Aneby.\n\nTillverkar täck- och madrassvadd samt\nlimvadd vid fabrik i Aneby (Jönköp. l.).\n\nTelefon: 70. — Akt.-kap.: 20,000 kr.\nAntal industriarb.: 4. — Bolaget\ngrundat 1937.\n\nVerkst. dir.: järnhandl. Albin\nJohanson.\n\n*A. J. Ängel AB., Hälsingborg.\n\nSe Täckfabriken A. J. Ängel AB.,\nHälsingborg.\n\n*AB. Ankarsrums Bruk, Ankarsrum.\n\nGjuteri, mek. verkstad, pressverk och\nemalj verk vid Ankarsrum (Kalmar l.).\nTillverkar svart och emaljerat\nhandels-gjutgods, elspisar, gasspisar, vedspisar,\nkaminer (märke: »Viking») och grytor,\nsanitetsgjutgods, emalj, badkar, gjutna\nrördelar, radiatorer av plåt, mejerikärl,\npressat plåtgods, svart, förtent och\nemaljerat, samt skyltar. Bolaget driver\njämväl jordbruk och sågverksrörelse.\n\nTelegr.-adr. o. telefon: Bruket,\nAnkarsrum. Postgiro: 13939.\n\nRepresentanter: i Stockholm: för\njärnhandelsgods: Carl Ström AB.,\nLästma-kareg. 14—16, telefon: 235400; för\nbadkar, radiatorer, sanitetsgjutgods, rördelar\nm. m.: AB. Ahlsell &amp; Bernström,\nMäster-samuelsg. 32, telefon: »Ahlsell &amp;\nBernström» ; i Göteborg: för järnhandelsgods:\nAnkarsrums Nederlag, Skeppsbroplatsen\n1, telefon: 176320; för badkar, radiatorer,\nsanitetsgods, rördelar m. m.: AB.\nSjöberg &amp; Bengtson, Första Långg.- 11 B,\ntelefon: » Sjöberg—Bengtson»; j - Malmö:\nför järnhandelsgods: Ånkarsnnpas\nNederlag, Djäkneg. 2, telefon: 27500.’; för\nbadkar, radiatorer, sanitetsgjutgods, jröJrd^lar\nm. m.: AB. Ahlsell &amp; Bernstaöm,\nRege-mentsg. 4, telefon: »Ahlsell å\nBern-ström».\t/ •\n\nAkt.-kap.: 1,800,000 kr. Antal. arK:\n700, varav 650 industriarb. Tillv.-värde\npr år: 9,000,000 kr. — Bruket grundlades\n1655, bolag 1882, nuv. bolagsordning\nantagen 1913. Bolaget äger Ankärsrunjs\nSkåne AB., Sjöbo.\n\nStyrelse: adv. Alarik Lindskog (ordf.),\ndir. Kjell Freden, dir. Jonas Spånberg. V\nVerkst. dir.: Jonas Spånberg.\nTekn. dir.: John Lagerman,,\nFörsäljn.chef: T. Schéle. ’ ,\t..\n\nInköpschef: H. Nanning.\nKamrer: Herman Samuelson.\n\n*Ankarsrums Skåne AB., Sjöbo.\n\nGjuteri och mek. verkstad i Sjöbo\n(Malmöh. l.). Tillverkar gjutna rördelar,\nbyggnadsgjutgods samt\nlossningsapparater.\n\nTelefon: 80 o. 100. Postgiro: 291930,\nFörsäljning av bolagets produkter sker\ngenom AB. Ankarsrums Bruk,\nAnkarsrum (se detta företag).\n\nAkt.-kap.: 50,000 kr. Antal\nindustriarb.: 50.\n\nBolaget, bildat 1945, efter\nÖvertagandet av f. d. Sjöboverken AB:s verkstäder*\när dotterbolag till AB. Ankarsrums Bruk\n(se detta bolag).\t-",
    "structured": {
        "firms": [
            {
                "name": "AB. Edwin Andrén & Co.",
                "location": "Göteborg",
                "business": "Tillverkar vid avd. Nord-Neon neonrör och neonskyltar. Bolaget driver även elektr. installationsrörelse samt utför elektr. hissanläggningar.",
                "contact": {
                    "office": "St. Badhusg. 20",
                    "phone": [
                        "170010"
                    ],
                    "postgiro": "40146"
                },
                "financials": {
                    "capital": "225,000 kr",
                    "employees": {
                        "industriarb": 30
                    }
                },
                "foundation_year": 1872,
                "board": [
                    {
                        "name": "Bernhard Andrén",
                        "role": "Styrelse o. verkst. dir."
                    }
                ]
            },
            {
                "name": "Victor Andrén",
                "location": "Mölndal",
                "business": "Lädervarufabrik. Tillverkar portmonnäer, plånböcker, tobakspungar, livremmar, portföljer och väskor. Specialitet: Damväskor.",
                "contact": {
                    "phone": [
                        "270487"
                    ],
                    "postgiro": "43173"
                },
                "financials": {
                    "employees": {
                        "industriarb": 40
                    }
                },
                "foundation_year": 1925,
                "owner": "Rolf Andrén"
            },
            {
                "name": "AB. Aneby Industrier",
                "location": "Aneby",
                "business": "Trähusfabrik, sågverk och hyvleri i Aneby (Jönköp. l.). Tillverkar monteringsfärdiga trähus (märke: »Aneby-hus») samt sågade och hyvlade trävaror.",
                "contact": {
                    "telegraph": "Anebyindustri, Aneby",
                    "phone": "»Aneby Industrier»",
                    "postgiro": "94697"
                },
                "financials": {
                    "capital": "200,000 kr",
                    "employees": {
                        "industriarb": 50
                    }
                },
                "foundation_year": 1945,
                "board": [
                    {
                        "name": "löjtn. Erling Andersson",
                        "role": "Styrelse"
                    },
                    {
                        "name": "insp. David Andersson",
                        "role": "Styrelse"
                    },
                    {
                        "name": "civiling. Gillis Andersson",
                        "role": "Styrelse"
                    }
                ]
            },
            {
                "name": "AB. Aneby Waddfabrik",
                "location": "Aneby",
                "business": "Tillverkar täck- och madrassvadd samt limvadd vid fabrik i Aneby (Jönköp. l.).",
                "contact": {
                    "phone": [
                        "70"
                    ],
                    "postgiro": "20,000 kr"
                },
                "financials": {
                    "employees": {
                        "industriarb": 4
                    }
                },
                "foundation_year": 1937,
                "director": "Albin Johanson"
            },
            {
                "name": "AB. Ankarsrums Bruk",
                "location": "Ankarsrum (Kalmar l.)",
                "business": "Gjuteri, mek. verkstad, pressverk och emalj verk. Tillverkar svart och emaljerat handels-gjutgods, elspisar, gasspisar, vedspisar, kaminer (märke: »Viking») och grytor, sanitetsgjutgods, emalj, badkar, gjutna rördelar, radiatorer av plåt, mejerikärl, pressat plåtgods, svart, förtent och emaljerat, samt skyltar. Bolaget driver jämväl jordbruk och sågverksrörelse.",
                "contact": {
                    "telegraph": "Bruket, Ankarsrum",
                    "phone": "Bruket, Ankarsrum",
                    "postgiro": "13939"
                },
                "financials": {
                    "capital": "1,800,000 kr",
                    "employees": {
                        "total": 700,
                        "industriarb": 650
                    }
                },
                "foundation_year": 1655,
                "corporation_year": 1882,
                "board": [
                    {
                        "name": "adv. Alarik Lindskog",
                        "role": "Styrelse"
                    },
                    {
                        "name": "dir. Kjell Freden",
                        "role": "Styrelse"
                    },
                    {
                        "name": "dir. Jonas Spånberg",
                        "role": "Styrelse"
                    }
                ],
                "director": "Jonas Spånberg"
            },
            {
                "name": "Ankarsrums Skåne AB.",
                "location": "Sjöbo (Malmöh. l.)",
                "business": "Gjuteri och mek. verkstad. Tillverkar gjutna rördelar, byggnadsgjutgods samt lossningsapparater.",
                "contact": {
                    "phone": [
                        "80",
                        "100"
                    ],
                    "postgiro": "291930"
                },
                "financials": {
                    "capital": "50,000 kr",
                    "employees": {
                        "industriarb": 50
                    }
                },
                "corporation_year": 1945
            }
        ]
    }
}