{
    "original": "Liljeholmen—Lilles\n\nFabriken, anlagd 1870, bolag 1901,\ntillhör Asea-koncernen.\n\nStyrelse: dir. Thorsten Ericson (ordf.),\ndir. Hugo Edström, dir. Albert Elfström.\n\nVerkst. dir.: Hugo Edström,\n\nTekn. chef: övering. Bror Hansson.\n\nFörsäljn.-chef: Nils Almgren.\n\nInköpschef: Göran Lybeck.\n\nKamrer: Fredrik Hesse.\n\n\"Liljeholmens Stearinfabriks AB.,\n\nStockholm.\n\nKem.-tekn. fabrik. Tillverkar stearin,\nstearinljus, kompositionsljus, paraf\nfinljus, vaxljus, glycerin, olein, stearinbeck,\netylabietat, zinkstearat m. m.\n\nKontor: Danviksg. 10; postadr.:\nStockholm 11. Telegr.-adr.: Stearinbolaget,\nStockholm. Telefon: 440140. Postgiro:\n2312\n\nAkt.-kap.: 4,000,000 kr. Antal\nindustriarb.: 140. Tillv.-värde pr år: 5,000,000 kr.\n\n—\tFirman etabl. 1839, bolag 1872.\n\nStyrelse: frih. Louis de Geer (ordf.),\n\ngrossh. Robert Ljunglöf, fil. dr Harald\nNordenson, disp. Nils Westerdahl, greve\nFabian Wrede.\n\nVerkst. dir.: Harald Nordenson.\n\nTekn. chef o. bitr. dir.: S. Gärdin.\n\nDir.-assist.: Lars Nordenson.\n\nKontorschef: Karl Sidenvall.\n\nDriftsingenjörer: Elon Olsson o. Göte\nHolm.\n\n(.Jfr annons nr 21.)\n\nLiljeholmens Ättiksfabrik AB.,\n\nStockholm,\n\nTillverkar ättiksprodukter, senap,\ngurkor, soya och såser. Varumärke:\n»Kocken».\n\nKontor: Barnängsg. 23. Telegr.-adr.:\nLiljeholmättika, Stockholm. Telefon:\n405312 o. 415858. Postgiro: 3941.\n\nAkt.-kap.: 70,000 kr. Antal\nindustriarb.: 19. Tillv.-värde pr år: 300,000 kr.\n\n—\tFirman etabl. 1859, bolag 1919,\n\nVerkst. dir. o. disp.: Bengt Melin.\n\n\"Liljeqvists Sågblads- &amp;\nRedskapsfabrik, Eskilstuna.\n\nSe Nya AB. Liljeqvists Sågblads- &amp;\nRedskapsfabrik, Eskilstuna.\n\nAB. P. M. Liljeqvist, Anderstorp.\n\nMek. verkstad i Anderstorp (Jönköp.\n1.). Tillverkar stålottomaner, hörnskydd,\nventilgaller, hjulcentrum för gummihjul\ntill skottkärror, skobeslag,\nplåtpressnings-arbeten m. m.\n\nTelefon: 44, 220 o. 101. Postgiro:\n\n26515. — Akt.-kap.: 90,000 kr. Antal\nindustriarb.: 35. Tillv.-värde pr år: 1,000,000\nkr. — Firman etabl. 1905, bolag 1936.\n\nStyrelse o. chefer: fabr. Peter M.\nLiljeqvist, fabr. Assar Liljeqvist o. fabr.\nJonatan Liljeqvist.\n\n\"Lilla Edets Pappersbruks AB.,\n\nLilla Edet.\n\nPappersbruk med träsliperi, påsfabrik,\ntryckeri och pappersförädling vid Lilla\nEdet (Älvsb. l.).\n\nTillverkar påspapper, kuvertpapper,\nomslagspapper, påsar, mönstertryckt\npapper samt handdukar, servetter,\ntoalettpapper (märke: »Edet-Kräpp») samt\nsjukhusartiklar av kräppat papper.\n\nHuvudkontor: Lilla Edet. Telegr.-adr.:\nHaeger, Lilla Edet. Telefon: 1, 121\n\n0.\t311. Postgiro: 8993. Försäljn.-bolag:\nGöteborg, postadr.: Box 60, telefon:\n192565; Stockholm, Atlasg. 5, telefon:\n321840; Malmö, Vinterg. 8, telefon:\n75427.\n\nAkt.-kap.: 1,000,000 kr. Antal\nindustriarb.: 425. Tillv.-värde pr år: 8,000,000 kr.\n\n—\tFirman etabl. 1880, bolag 1906.\nStyrelse: herr Ivan Haeger (ordf.),\n\nherr Gunnar Haeger, dir. K. Olle Haeger,\nfru G. Ligner.\n\nVerkst. dir.: K. Olle Haeger.\n\n\"AB. Lilla Harrie Redskapsverkstad,\n\nLilla Harrie.\n\nMek. verkstad i Lilla Harrie (Malmöh.\n\n1.).\tTillverkar lantbruksmaskiner och\nlantbruksredskap för häst- och\ntraktordrift.\n\nTelegr.-adr.: Redskapsverk, Lund.\nTelefon: Lund, »Lilla Harrie Redskap».\nPostgiro: 21412.\n\nAkt.-kap.: 225,000 kr. Antal\nindustriarb.: 80. Tillv.-värde pr år: 1,650,000 kr.\n\n—\tFirman etabl. 1903, bolag 1911.\nStyrelse: fabr. Carl Holmqvist (ordf.),\n\nfröken Elisabeth Holmqvist, ing. Gust.\nHolmqvist.\n\nVerkst. dir.: Carl Holmqvist.\nDispyt Gust, Holmqvist.\nKamrer: Ant. W. Nilsson.\n\n\"Lilles Konfektiöns AB., Borås.\n\nTillverkar dam-, herr- och gosskläder\nsåsom kostymer, byxor, trenchcoats,\ndräkter, blazers rn. m.\n\nTelefon: 16360 o. 19460. Postgiro:\n140681. — Akt.-kap.: 275,000 kr. Antal\nindustriarb.: 75. Tillv.-värde pr år:\n1,100,000 kr. — Firman etabl. 1938, bolag\n1939.\n\nChef: disp. Torsten Lillhage.",
    "structured": {
        "1": {
            "name": "Liljeholmens Stearinfabriks AB.",
            "location": "Stockholm",
            "business": "Kem.-tekn. fabrik",
            "products": "Tillverkar stearin, stearinljus, kompositionsljus, paraffinljus, vaxljus, glycerin, olein, stearinbeck, etylbietat, zinkstearat m. m.",
            "contact": {
                "office": "Danviksg. 10",
                "phone": [
                    "440140"
                ],
                "postgiro": "2312",
                "telegraph": "Stearinbolaget, Stockholm"
            },
            "financials": {
                "capital": "4,000,000 kr",
                "employees": {
                    "industriarb": 140
                },
                "annual_turnover": "5,000,000 kr",
                "annual_production_value": "5,000,000 kr"
            },
            "foundation_year": 1839,
            "corporation_year": 1872,
            "board": [
                {
                    "name": "frih. Louis de Geer",
                    "role": "ordf."
                },
                {
                    "name": "grossh. Robert Ljunglöf",
                    "role": "-"
                },
                {
                    "name": "fil. dr Harald Nordenson",
                    "role": "-"
                },
                {
                    "name": "disp. Nils Westerdahl",
                    "role": "-"
                },
                {
                    "name": "greve Fabian Wrede",
                    "role": "-"
                }
            ]
        },
        "2": {
            "name": "Liljeholmens Ättiksfabrik AB.",
            "location": "Stockholm",
            "business": "Tillverkar ättiksprodukter, senap, gurkor, soya och såser",
            "products": "Varumärke: 'Kocken'",
            "contact": {
                "office": "Barnängsg. 23",
                "phone": [
                    "405312",
                    "415858"
                ],
                "postgiro": "3941",
                "telegraph": "Liljeholmättika, Stockholm"
            },
            "financials": {
                "capital": "70,000 kr",
                "employees": {
                    "industriarb": 19
                },
                "annual_turnover": "300,000 kr"
            },
            "foundation_year": 1859,
            "corporation_year": 1919,
            "director": "Bengt Melin"
        },
        "3": {
            "name": "Lilla Edets Pappersbruks AB.",
            "location": "Lilla Edet",
            "business": "Pappersbruk med träsliperi, påsfabrik, tryckeri och pappersförädling",
            "products": "Tillverkar påspapper, kuvertpapper, omslagspapper, påsar, mönstertryckt papper samt handdukar, servetter, toalettpapper (märke: 'Edet-Kräpp') samt sjukhusartiklar av kräppat papper",
            "contact": {
                "office": "Lilla Edet",
                "phone": [
                    "1",
                    "121",
                    "311"
                ],
                "postgiro": "8993"
            },
            "financials": {
                "capital": "1,000,000 kr",
                "employees": {
                    "industriarb": 425
                },
                "annual_turnover": "8,000,000 kr"
            },
            "foundation_year": 1880,
            "corporation_year": 1906,
            "board": [
                {
                    "name": "herr Ivan Haeger",
                    "role": "ordf."
                },
                {
                    "name": "herr Gunnar Haeger",
                    "role": "-"
                },
                {
                    "name": "dir. K. Olle Haeger",
                    "role": "-"
                },
                {
                    "name": "fru G. Ligner",
                    "role": "-"
                }
            ]
        },
        "4": {
            "name": "AB. Lilla Harrie Redskapsverkstad",
            "location": "Lilla Harrie",
            "business": "Tillverkar lantbruksmaskiner och lantbruksredskap för häst- och traktordrift",
            "contact": {
                "telegraph": "Redskapsverk, Lund",
                "phone": [
                    "Lund, 'Lilla Harrie Redskap'"
                ],
                "postgiro": "21412"
            },
            "financials": {
                "capital": "225,000 kr",
                "employees": {
                    "industriarb": 80
                },
                "annual_turnover": "1,650,000 kr"
            },
            "foundation_year": 1903,
            "corporation_year": 1911,
            "board": [
                {
                    "name": "fabr. Carl Holmqvist",
                    "role": "ordf."
                },
                {
                    "name": "fröken Elisabeth Holmqvist",
                    "role": "-"
                },
                {
                    "name": "ing. Gust. Holmqvist",
                    "role": "-"
                }
            ]
        },
        "5": {
            "name": "Lilles Konfektiöns AB.",
            "location": "Borås",
            "business": "Tillverkar dam-, herr- och gosskläder såsom kostymer, byxor, trenchcoats, dräkter, blazers rn. m.",
            "contact": {
                "phone": [
                    "16360",
                    "19460"
                ],
                "postgiro": "140681"
            },
            "financials": {
                "capital": "275,000 kr",
                "employees": {
                    "industriarb": 75
                },
                "annual_turnover": "1,100,000 kr"
            },
            "foundation_year": 1938,
            "corporation_year": 1939,
            "manager": "disp. Torsten Lillhage"
        }
    }
}