{
    "original": "Handelsbolage t—Hansson\n\n*\tHandelsbolaget Segerdahls\nLäderfabrik, Linköping.\n\nTillverkar ko- och plattläder,\nremläder samt ränder.\n\nTelefon: 20095 o. 22154. Postgiro:\n71068. — Antal industriarb.: 15.\nTillv.-värde pr år: 675,000 kr. — Fabriken\nanlagd 1654, nuvarande firma grundad 1892.\n\nBolagsdelägare: ing. Sven Segerdahl,\nfabr. Sten Segerdahl, kamrer Gillis\nSegerdahl o. fru Ann-Marie Skiöldebrand.\n\nFirmatecknare: Sten Segerdahl.\n\n*\tHandöls Nya Täljstens och\nVattenkrafts AB., Stockholm.\n\nTälj stensbrott, stenförädling och\ntalk-verk vid Handöl (Jämtl. l.). Tillverkar\nkaminer och spisar av täljsten, tegel för\nsulfatfabriker, täljstensgryn och -mjöl\n(talk) m. m.\n\nHuvudkontor: Stockholm, Malmtorgsg.\n6. Telegr.-adr.: Handöls, Stockholm.\nTelefon: 232100. Postgiro: 2815.\nFabrikskontor: Handöl, Enafors. Ensamförsälj.:\nHöganäs-Billesholms AB., Höganäs.\n\nAkt.-kap.: 399,000 kr. Antal\nindustriarb.: 90. Tillv.-värde pr år: 800,000 kr.\n— Bolaget, grundat 1911, äges av\nHöganäs-Billesholms AB.\n\nStyrelse: dir. P. Eg. Gummeson (ordf.),\növering. Edvin V. Olsson, dir. M.\nSchwartz.\n\nVerkst. dir.: P. Eg. Gummeson\n(Höganäs).\n\nIngenjörer: K. I. E:son Rask o. T.\nNel-son (Handöl).\n\nHansson &amp; Andersson AB., Malmö.\n\nSe Kartongindustrin, Hansson &amp;\nAndersson AB., Malmö.\n\nHansson &amp; Pehrsson AB., Malmö.\n\nMek. verkstad. Tillverkar kassaskåp,\nvågar, skepps- och byggnadssmiden; utför\nsvarvningsarbeten samt reparationer av\ntryckerimaskiner.\n\nKontor: Jöns Filsg. 3—5. Telefon:\n24177. Postgiro: 147612.\n\nAkt.-kap.: 35,000 kr. Antal\nindustriarb.: 15. Omsättn.-värde pr år: 100,000\nkr. — Firman etabl. 1906, bolag 1917.\n\nVerkst. dir.: fabr. Gunnar Persgård.\n\nHanssons Handskfabriks AB.,\nBröderna, Malung.\n\nSe Bröderna Hanssons Handskfabriks\nAB., Mal ung.\n\n*AB. Alfr. Hanssons Skofabrik,\n\nBjursås.\n\nTillverkar pjäxor, arbets- och\nsportskodon samt randsydda herrskodon vid\nfabrik i Bjursås (Kopparb. l.).\n\nTelefon: 23. Postgiro: 24801. —\nAkt.-kap.: 100,000 kr. Antal industriarb.: 60.\nTillv.-värde pr år: 950,000 kr. — Firman\netabl. 1913, bolag 1943.\n\nStyrelse: fabr. Alfr. Hansson, fabr.\nBengt Hanson, fabr. Ernst Hanson.\n\nVerkst. dir.: Alfr. Hansson.\n\n*Aug. Hanssons Cjuteri, Halmstad.\n\nGjuteri och mek. verkstad. Tillverkar\npumpar, ventiler, rördelar, sanitetsgods,\nhandelsgjutgods m. m. Varumärke:\n»AI1G».\n\nTelegr.-adr.: Järnbolaget, Halmstad.\nTelefon: 410, 914 o. 1924. Postgiro:\n9518. — Antal industriarb.: 100.\n\nFirman, som grundades 1898, äges av\nHalmstads Järnvaru AB.\n\nStyrelse (för Halmstads Järnvaru AB.):\ndisp. Allan Boo, överstelöjtn. Evert\nCavalli, konsul Folke-Uno Folkow, dir.\nBirger Hultman, disp. Mauritz Persson,\nlöjtn. Lars Ågren.\n\nVerkst. dir.: Folke-Uno Folkow.\n\nFabrikschef: ing. Gustaf Oom.\n\nAB. E. Hansson &amp; C:o., Malmö.\n\nMetallvarufabrik. Tillverkar elektr.\nbelysningsarmatur, elektr, reklamskyltar\nsamt vattenarmatur.\n\nKontor: Industrig. 14—18.\nTelegr.-adr.: Armaturhansson, Malmö. Telefon:\n27448 o. 21488. Postgiro: 37629..—\nAkt.-kap.: 50,000 kr. Antal industriarb.: 35.\n— Bolaget grundat 1921.\n\nVerkst. dir.: Erik Hansson.\n\nNore L. Hansson, Hatt &amp;\nMössfabrik, Södertälje.\n\nTillverkar dam- och barnhattar samt\nmössor.\n\nTelegr.-adr.:. Norel, Södertälje.\nTelefon: 31824. Postgiro: 30313. — Antal\nindustriarb.: 35. Tillv.-värde pr år:\n200,000 kr. — Firman etabl. 1916.\n\nÄgare o. chef: körsnär Nore L. Hansson.\n\nSven Hansson &amp; Co. AB, Stockholm.\n\nPåsfabrik och pappersindustri.\nTillverkar påsar, toalettpapper, konvolut,\nbärkassar, konfektionsväskor samt blocknotes.\nVarumärken: »Sanigén» o. »Svenco».\n\nKontor: Hudiksvallsg. 4—6.\nTelegr.-adr.: Svenco, Stockholm. Telefon: 23049Ö.",
    "structured": {
        "firms": [
            {
                "name": "Handelsbolaget Segerdahls Läderfabrik",
                "location": "Linköping",
                "business": "Tillverkning av ko- och plattläder, remläder samt ränder",
                "products": "Tillverkar ko- och plattläder, remläder samt ränder",
                "contact": {
                    "office": "Läderfabrik, Linköping",
                    "phone": [
                        "20095",
                        "22154"
                    ],
                    "postgiro": "71068"
                },
                "financials": {
                    "capital": "Okänt",
                    "employees": {
                        "industriarb": 15
                    },
                    "annual_turnover": "675,000 kr",
                    "annual_production_value": "675,000 kr"
                },
                "foundation_year": 1892,
                "owners": [
                    "ing. Sven Segerdahl",
                    "fabr. Sten Segerdahl",
                    "kamrer Gillis Segerdahl",
                    "fru Ann-Marie Skiöldebrand"
                ],
                "director": "Sten Segerdahl"
            },
            {
                "name": "Handöls Nya Täljstens och Vattenkrafts AB.",
                "location": "Stockholm",
                "business": "Täljstensbrott, stenförädling och talk-verk",
                "products": "Tillverkar kaminer och spisar av täljsten, tegel för sulfatfabriker, täljstensgryn och -mjöl (talk) m. m.",
                "contact": {
                    "office": "Stockholm, Malmtorgsg. 6",
                    "phone": "232100",
                    "postgiro": "2815",
                    "sales_offices": [
                        {
                            "location": "Handöl",
                            "phone": "Okänt"
                        },
                        {
                            "location": "Enafors",
                            "phone": "Okänt"
                        }
                    ]
                },
                "financials": {
                    "capital": "399,000 kr",
                    "employees": {
                        "industriarb": 90
                    },
                    "annual_turnover": "800,000 kr",
                    "annual_production_value": "800,000 kr"
                },
                "foundation_year": 1911,
                "owners": [
                    "Höganäs-Billesholms AB"
                ],
                "board": [
                    {
                        "name": "P. Eg. Gummeson",
                        "role": "ordf."
                    },
                    {
                        "name": "Edvin V. Olsson",
                        "role": "övering."
                    },
                    {
                        "name": "M. Schwartz",
                        "role": "Okänt"
                    }
                ],
                "director": "P. Eg. Gummeson",
                "manager": "Okänt"
            },
            {
                "name": "Hansson &amp; Pehrsson AB.",
                "location": "Malmö",
                "business": "Mek. verkstad",
                "products": "Tillverkar kassaskåp, vågar, skepps- och byggnadssmiden; utför svarvningsarbeten samt reparationer av tryckerimaskiner",
                "contact": {
                    "office": "Jöns Filsg. 3—5",
                    "phone": "24177",
                    "postgiro": "147612"
                },
                "financials": {
                    "capital": "35,000 kr",
                    "employees": {
                        "industriarb": 15
                    },
                    "annual_turnover": "100,000 kr"
                },
                "foundation_year": 1917,
                "director": "Gunnar Persgård"
            },
            {
                "name": "AB. Alfr. Hanssons Skofabrik",
                "location": "Bjursås",
                "business": "Tillverkning av pjäxor, arbets- och sportskodon samt randsydda herrskodon",
                "products": "Tillverkar pjäxor, arbets- och sportskodon samt randsydda herrskodon vid fabrik i Bjursås (Kopparb. l.)",
                "contact": {
                    "phone": "23",
                    "postgiro": "24801"
                },
                "financials": {
                    "capital": "100,000 kr",
                    "employees": {
                        "industriarb": 60
                    },
                    "annual_turnover": "950,000 kr"
                },
                "foundation_year": 1943,
                "owners": [
                    "fabr. Alfr. Hansson",
                    "fabr. Bengt Hanson",
                    "fabr. Ernst Hanson"
                ],
                "director": "Alfr. Hansson"
            },
            {
                "name": "Aug. Hanssons Cjuteri",
                "location": "Halmstad",
                "business": "Gjuteri och mek. verkstad",
                "products": "Tillverkar pumpar, ventiler, rördelar, sanitetsgods, handelsgjutgods m. m.",
                "contact": {
                    "telegraph": "Järnbolaget, Halmstad",
                    "phone": [
                        "410",
                        "914",
                        "1924"
                    ],
                    "postgiro": "9518"
                },
                "financials": {
                    "employees": {
                        "industriarb": 100
                    }
                },
                "owners": [
                    "Halmstads Järnvaru AB"
                ],
                "board": [
                    {
                        "name": "disp. Allan Boo",
                        "role": "disp."
                    },
                    {
                        "name": "överstelöjtn. Evert Cavalli",
                        "role": "Okänt"
                    },
                    {
                        "name": "konsul Folke-Uno Folkow",
                        "role": "Okänt"
                    },
                    {
                        "name": "dir. Birger Hultman",
                        "role": "Okänt"
                    },
                    {
                        "name": "disp. Mauritz Persson",
                        "role": "Okänt"
                    },
                    {
                        "name": "löjtn. Lars Ågren",
                        "role": "Okänt"
                    }
                ],
                "director": "Folke-Uno Folkow",
                "factory_office": "Okänt",
                "factory_phone": "Okänt"
            },
            {
                "name": "AB. E. Hansson &amp; C:o.",
                "location": "Malmö",
                "business": "Metallvarufabrik",
                "products": "Tillverkar elektr. belysningsarmatur, elektr, reklamskyltar samt vattenarmatur",
                "contact": {
                    "office": "Industrig. 14—18",
                    "phone": [
                        "27448",
                        "21488"
                    ],
                    "postgiro": "37629"
                },
                "financials": {
                    "capital": "50,000 kr",
                    "employees": {
                        "industriarb": 35
                    }
                },
                "foundation_year": 1921,
                "director": "Erik Hansson"
            },
            {
                "name": "Nore L. Hansson, Hatt &amp; Mössfabrik",
                "location": "Södertälje",
                "business": "Tillverkning av dam- och barnhattar samt mössor",
                "products": "Tillverkar dam- och barnhattar samt mössor",
                "contact": {
                    "telegraph": "Norel, Södertälje",
                    "phone": "31824",
                    "postgiro": "30313"
                },
                "financials": {
                    "employees": {
                        "industriarb": 35
                    },
                    "annual_turnover": "200,000 kr"
                },
                "director": "körsnär Nore L. Hansson"
            },
            {
                "name": "Sven Hansson &amp; Co. AB",
                "location": "Stockholm",
                "business": "Påsfabrik och pappersindustri",
                "products": "Tillverkar påsar, toalettpapper, konvolut, bärkassar, konfektionsväskor samt blocknotes",
                "contact": {
                    "office": "Hudiksvallsg. 4—6",
                    "phone": "23049Ö"
                }
            }
        ]
    }
}