{
    "original": "W allenborg—Vansbro\n\nStyrelse: adv. S. Malmkvist (ordf.),\narkitekt Frans Borgström, konsul Hans\nEkman, kamrer Göte Wallenberg, fru Lisa\nWallenberg, fru B. Weiland.\n\nVerkst. dir.: Frans Borgström.\n\nDisp.; Gunnar Weiland.\n\n\"AB. C. A. Wallenborg &amp; Son,\n\nStockholm.\n\nFabrik för tillverkning av\nbyggnadsplattor av träull i östertälje (Stockholms\n1.). Varumärke: »Lignoma».\n\nKontor: Birger Järlsg. 73—75.\nTele-gr.-adr.: Grobnellaw, Stockholm. Telefon:\n235530.\n\nAkt.-kap.: 50,000 kr. Antal\nindustriarb.: 45. — Firman, etabl. 1904, bolag\n1945, äger Wallenborgs Motor AB.,\nStockholm.\n\nStyrelse: dir. Tore Wallenborg (ordf.),\ndisp. Harry Wallenborg.\n\nVerkst. dir.: Tore Wallenborg.\n\nAB. Vallevikens Cementfabrik,\n\nStockholm.\n\nSe AB. Ruteverken, Slite.\n\nWallins Konservfabrik, Göteborg.\n\nSe AB. Bröderna Wallins\nKonservfabrik, Göteborg.\n\nWallins Mek. Stenhuggeri, Älmhult.\n\nSe Bröderna Wallins Mek. Stenhuggeri,\nÄlmhult.\n\n\"Wallins Nysilverfabrik, Lidköping.\n\nSe Kommanditbolaget Bröderna\nWallins Nysilverfabrik, Lidköping.\n\nR. Wallins Piskfabrik, Norrköping.\n\nTillverkar piskor, ridspön och\npisk-slängar.\n\nTelefon: 24349. Postgiro: 30114. —\nAntal industriarb.: 4. Tillv.-värde pr år:\n25,000 kr. — Firman etabl. 1922.\n\nÄgare o. chef: fabr. Harry Wallin.\n\nW allnäs AB., Vallnäs.\n\nSågverk med hyvleri samt\ntorvströfabrik i Vallnäs (Jönköp. l.). Tillverkar\nsågade och hyvlade trävaror, stolpar samt\nbränntorv och torvströ. Specialitet:\nokantad snickerifuru och stolpar. Bolaget\ndriver även jordbruk och skogshantering.\n\nTelefon: Ingatorp 14. Postgiro: 6339.\n\n39\n\nAkt.-kap.: 900,000 kr. Antal\nindustriarb.: 50. Tillv.-värde pr år: 2,000,000 kr.\n\n—\tFirman etabl. 1896, bolag 1898.\nVerkst. dir.: civiling. Erik Fagerholm.\n\nWallsta Ångsågs AB., Vallsta.\n\nSågverk och hyvleri i Vallsta samt\nsågverk i Båtbacken, Järvsö (båda i Gävleb.\n1.). Tillverkar sågade och hyvlade\nträvaror, silltunnstav samt milkolade\nsågverkskol.\n\nTelegr.-adr.: Bergfors, Bollnäs.\nTelefon: Vallsta 65.\n\nAkt.-kap.: 100,000 kr. Antal\nindustriarb.: 60. Tillv.-värde pr år: 1,200,000 kr.\n\n—\tBolaget grundat 1928.\n\nVerkst. dir. o. disp.: Otto Sjöberg.\n\n\"Vallviks Sulfitfabrik, Vallvik.\nSe Marma-Långrörs AB., Söderhamn.\n\nWallåkra Stenkärlsfabrik, Vallåkra.\n\nTillverkar saltglaserade hushållskärl\nvid lergodsfabrik i Vallåkra (Malmöh. l.).\n\nTelefon: Hälsingborg 99031. — Antal\nindustriarb.: 6. Tillv.-värde pr år: 30,000\nkr. — Firman etabl. 1928.\n\nÄgare o. chef: fabr. Adolf Andersson.\n\n\"Valåsens Sågverk, Valåsen.\n\nSe AB. Statens Skogsindustrier,\nStockholm.\n\n\"AB. Vandenberghs Margarin,\n\nStockholm.\n\nMargarinfabrik i Mariehäll,\nSundbyberg. Tillverkar animaliskt och\nvegetabiliskt margarin samt cocostabletter.\n\nKontor: Stockholm, Norrmalmstorg 1.\nTelegr.-adr.: Vandenbergh, Stockholm.\nTelefon: 108509 o. 118509. Postgiro: 965.\nFörsäljningen sker genom\nMargarinbolaget AB., Stockholm, Vasag. 16, telefon:\n230960.\n\nAkt.-kap.: 2,500,000 kr. Antal\nindustriarb.: 26. Tillv.-värde pr år: 6,000,000\nkr. — Bolaget grundat 1920.\n\nStyrelse: adv. Dick Bergman, dir. J.\nH. Bruijn, adv. Tom Erik Forssner.\nVerkst. dir.: J. H. Bruijn.\növering.: dir. H. Ubbens.\nKontorschef: Louis Lekberg.\n\n\"Vansbro Sågverk o. Kolugnar,\n\nVansbro.\n\nSe AB. Träkol, Vansbro.",
    "structured": {
        "1": {
            "name": "C. A. Wallenborg & Son",
            "location": "Stockholm",
            "business": "Fabrik för tillverkning av byggnadsplattor av träull",
            "contact": {
                "office": "Birger Järlsg. 73—75",
                "phone": [
                    "235530"
                ],
                "telegraph": "Grobnellaw, Stockholm"
            },
            "financials": {
                "capital": "50,000 kr",
                "employees": {
                    "industriarb": 45
                },
                "annual_turnover": "Not available",
                "annual_production_value": "Not available"
            },
            "foundation_year": 1904,
            "current_name_year": 1945,
            "owners": [
                "Wallenborgs Motor AB"
            ]
        },
        "2": {
            "name": "Vallevikens Cementfabrik",
            "location": "Stockholm",
            "business": "Not available"
        },
        "3": {
            "name": "Wallins Konservfabrik",
            "location": "Göteborg",
            "business": "Not available"
        },
        "4": {
            "name": "Wallins Mek. Stenhuggeri",
            "location": "Älmhult",
            "business": "Not available"
        },
        "5": {
            "name": "Wallins Nysilverfabrik",
            "location": "Lidköping",
            "business": "Not available"
        },
        "6": {
            "name": "R. Wallins Piskfabrik",
            "location": "Norrköping",
            "business": "Tillverkar piskor, ridspön och pisk-slängar",
            "contact": {
                "phone": [
                    "24349"
                ],
                "postgiro": "30114"
            },
            "financials": {
                "employees": {
                    "industriarb": 4
                },
                "annual_turnover": "Not available",
                "annual_production_value": "25,000 kr"
            },
            "foundation_year": 1922
        },
        "7": {
            "name": "Wallnäs AB.",
            "location": "Vallnäs",
            "business": "Sågverk med hyvleri samt torvströfabrik",
            "contact": {
                "phone": [
                    "Ingatorp 14"
                ],
                "postgiro": "6339"
            },
            "financials": {
                "capital": "900,000 kr",
                "employees": {
                    "industriarb": 50
                },
                "annual_turnover": "2,000,000 kr",
                "annual_production_value": "Not available"
            },
            "foundation_year": 1896
        },
        "8": {
            "name": "Wallsta Ångsågs AB.",
            "location": "Vallsta",
            "business": "Sågverk och hyvleri",
            "contact": {
                "phone": [
                    "Vallsta 65"
                ]
            },
            "financials": {
                "capital": "100,000 kr",
                "employees": {
                    "industriarb": 60
                },
                "annual_turnover": "1,200,000 kr",
                "annual_production_value": "Not available"
            },
            "foundation_year": 1928
        },
        "9": {
            "name": "Vallviks Sulfitfabrik",
            "location": "Vallvik",
            "business": "Not available"
        },
        "10": {
            "name": "Wallåkra Stenkärlsfabrik",
            "location": "Vallåkra",
            "business": "Tillverkar saltglaserade hushållskärl vid lergodsfabrik",
            "contact": {
                "phone": [
                    "Hälsingborg 99031"
                ]
            },
            "financials": {
                "employees": {
                    "industriarb": 6
                },
                "annual_turnover": "Not available",
                "annual_production_value": "30,000 kr"
            },
            "foundation_year": 1928
        },
        "11": {
            "name": "Valåsens Sågverk",
            "location": "Valåsen",
            "business": "Not available"
        },
        "12": {
            "name": "Vandenberghs Margarin",
            "location": "Stockholm",
            "business": "Margarinfabrik",
            "contact": {
                "office": "Stockholm, Norrmalmstorg 1",
                "phone": [
                    "108509",
                    "118509"
                ],
                "telegraph": "Vandenbergh, Stockholm",
                "postgiro": "965"
            },
            "financials": {
                "capital": "2,500,000 kr",
                "employees": {
                    "industriarb": 26
                },
                "annual_turnover": "6,000,000 kr",
                "annual_production_value": "Not available"
            },
            "foundation_year": 1920
        },
        "13": {
            "name": "Vansbro Sågverk o. Kolugnar",
            "location": "Vansbro",
            "business": "Not available"
        }
    }
}