{
    "original": "Åry—Åskammar\n\nTelefon: Mariestad 78. Ensamförsäljare:\nför buteljer: Buteljglasbrukens\nFörsäljnings AB., Stockholm, Birger Jarlsg. 2,\ntelefon: 619920; för fönsterglas: Årnäs\nBruk, Försäljningskontoret, Stockholm,\nHovslagarg. 5 B, telefon: 200512.\n\nAntal industriarb.: 120. Tillv.-värde pr\når: för buteljer: 1,100,000 kr.; för\nfönsterglas: 1,000,000 kr. — Bruket anlagt 1802.\n\nÄgare: Fastighets AB. D. Carnegie &amp;\nCo., Göteborg.\n\nPlatschef: förvalt. Jonas Haggård.\n\nÅry Bruk, AB., Åryd.\n\nTillverkar träull vid fabrik i Åryd\n(Kronob. l.). Bolaget driver även\njordbruk och skogshantering.\n\nTelegr.-adr.: Årybruk, Växjö. Telefon:\nVäxjö 7440. Postgiro: 75573.\n\nAkt.-kap.: 600,000 kr. Antal\nindustriarb.: 10. Tillv.-värde pr år: 100,000 kr.\n\n—\tBolaget grundat 1918.\n\nVerkst. dir.: A. Edwin Ohlsson.\n\nV. verkst. dir.: major Hakon Gisle.\n\nKamrer: Carl-Uno Persson.\n\nAB. Åry Manufakturverk, Åryd.\n\nSågverk och lådfabrik i Åryd (Kronob.\n1.). Tillverkar sågade trävaror för\ntillverkning av lådämnen.\n\nTelegr.-adr.: Årybruk, Växjö. Telefon:\nVäxjö 7440. Postgiro: 82060.\n\nAkt.-kap.: 150,000 kr. Antal\nindustriarb.: 70. Tillv.-värde pr år: 600,000 kr.\n\n—\tBolaget grundat 1920.\n\nVerkst. dir.: major Hakon Gisle.\n\nKamrer: Carl-Uno Persson.\n\n*Åsbrohammar-Spångsholms Bruks\nNya AB., Sya.\n\nSe Spångsholms Bruks AB., Sya.\n\nÅsebyfors Ullspinneri &amp; Väveri,\n\nÅsebyfors.\n\nSpinneri och väveri i Åsebyfors\n(Värml. l.). Tillverkar garner, filtar och\nvadmal.\n\nTelefon: 9. Postgiro: 92128. — Antal\nindustriarb.: 5. Tillv.-värde pr år: 20,000\nkr. — Firman etabl. 1925.\n\nÄgare o. chef; fabr. Josef Claesson.\n\nAB. Åsedahus, Vetlanda.\n\nTillverkar monteringsfärdiga trähus\nvid fabrik i Åseda (Kronob. l.).\n\nKontor: Vetlanda. Telefon:\n»Åsedahus». Postgiro: 146951.\n\nAkt.-kap.: 150,000 kr. Antal industri-\n\narb.: 70. Tillv.-värde pr år: 2,300,000 kr.\n\n—\tBolaget grundat 1939.\nVerkst. dir.: Eric Allring.\nKamrer: Tage Alf redsson.\n\nAB. Åsedakläder, Åseda.\n\nTillverkar herr- och gosskonfektion vid\nfabrik i Åseda (Kronob. l.).\n\nTelefon: 91. Postgiro: 164265. —\nAkt.-kap.: 75,000 kr. Antal industriarb.: 50.\nTillv.-värde pr år: 500,000 kr. — Bolaget\ngrundat 1939.\n\nKontorschef: Sten Gustafsson.\nFörsäljn.-chef: Nils Larsson.\n\n* Åseda Sågverk, Åseda.\n\nSe AB. Böksholms Sulfitfabrik,\nKlippan.\n\n*Åsens Bruk, Upperud.\nSe Håfreströms AB., Håverud.\n\nAB. Åsens Syfabrik, Åsarp.\n\nTillverkar herrskjortor vid fabrik 1\nÅsarp (Älvsb. l.).\n\nTelefon: 3. Postgiro: 135894. —\nAkt.-kap.: 46,800 kr. Antal industriarb.: 25.\nTillv.-värde pr år: 400,000 kr. — Bolaget\ngrundat 1935.\n\nVerkst. dir.: bankkamrer J. Åseskog.\n\n*Åshammars Bultfabriks AB.,\n\nÅskammar.\n\nBultfabrik i Åshammar (Gävleb. l.).\nTillverkar bult, mutter och\nmutterbrickor, axelflänsmutter, nit, träskruvar,\nögleskruvar, rälsspik, rälsskarvbult,\niso-latorkrok, linlås, tröskverksstift, smiden\nför kraft- och telefonledningar m. m.\n\nTelegr.-adr.: Bultfabriken, Åshammar.\nTelefon: 3, 63 o. 93. Postgiro: 13033.\n\nAkt.-kap.: 540,000 kr. Antal\nindustriarb.: 95. Tillv.-värde pr år: 1,600,000 kr.\n\n—\tFirman etabl. 1899.\n\nStyrelse: disp. Oscar Jönsson (ordf.),\nbankkamrer Gösta Delin, trävaruhandl.\nAdolf Jönsson.\n\nVerkst. dir. o. disp.: Oscar Jönsson.\nKassör: B. B rusk.\nDriftsing.: Axel Adolfsson.\n\n*Åshammars Byggnadssnickeri AB.,\n\nLingked.\n\nTillverkar byggnadssnickerier och\ninredningar vid fabrik i Åshammar\n(Gävleb. l.).\n\nKontor: Linghed. Telefon: 18.\nPostgiro: 91280. — Akt.-kap.: 32,000 kr. An-",
    "structured": {
        "1": {
            "name": "Åry—Åskammar",
            "location": "Åryd",
            "business": "Glasbruk and träull",
            "products": "Buteljglas, fönsterglas, träull",
            "contact": {
                "office": "Åryd",
                "phone": [
                    "Mariestad 78",
                    "Växjö 7440"
                ],
                "postgiro": "75573",
                "head_office": "Växjö",
                "sales_offices": [
                    {
                        "location": "Stockholm",
                        "phone": "619920"
                    },
                    {
                        "location": "Stockholm",
                        "phone": "200512"
                    }
                ],
                "telegraph": "Årybruk, Växjö",
                "factory_office": "Åryd",
                "factory_phone": "Växjö 7440"
            },
            "financials": {
                "capital": "600,000 kr",
                "employees": {
                    "industriarb": 120
                },
                "annual_turnover": "1,100,000 kr",
                "annual_production_value": "1,000,000 kr"
            },
            "foundation_year": 1802,
            "board": [
                {
                    "name": "Jonas Haggård",
                    "role": "Platschef"
                },
                {
                    "name": "A. Edwin Ohlsson",
                    "role": "Verkst. dir."
                },
                {
                    "name": "major Hakon Gisle",
                    "role": "V. verkst. dir."
                },
                {
                    "name": "Carl-Uno Persson",
                    "role": "Kamrer"
                }
            ],
            "owners": [
                "Fastighets AB. D. Carnegie & Co., Göteborg"
            ],
            "manager": "Eric Allring"
        },
        "2": {
            "name": "Åry Manufakturverk",
            "location": "Åryd",
            "business": "Sågverk and lådfabrik",
            "products": "Sågade trävaror, lådämnen",
            "contact": {
                "office": "Åryd",
                "phone": "Växjö 7440",
                "postgiro": "82060"
            },
            "financials": {
                "capital": "150,000 kr",
                "employees": {
                    "industriarb": 70
                },
                "annual_turnover": "600,000 kr",
                "annual_production_value": "600,000 kr"
            },
            "foundation_year": 1920,
            "board": [
                {
                    "name": "major Hakon Gisle",
                    "role": "Verkst. dir."
                },
                {
                    "name": "Carl-Uno Persson",
                    "role": "Kamrer"
                }
            ]
        },
        "3": {
            "name": "Åsebyfors Ullspinneri & Väveri",
            "location": "Åsebyfors",
            "business": "Spinneri and väveri",
            "products": "Garner, filtar, vadmal",
            "contact": {
                "phone": "9",
                "postgiro": "92128"
            },
            "financials": {
                "employees": {
                    "industriarb": 5
                },
                "annual_turnover": "20,000 kr"
            },
            "foundation_year": 1925,
            "manager": "Josef Claesson"
        },
        "4": {
            "name": "Åsedahus",
            "location": "Åseda",
            "business": "Monteringsfärdiga trähus",
            "contact": {
                "office": "Åseda",
                "phone": "Vetlanda",
                "postgiro": "146951"
            },
            "financials": {
                "capital": "150,000 kr",
                "employees": {
                    "industriarb": 70
                },
                "annual_turnover": "2,300,000 kr"
            },
            "foundation_year": 1939,
            "manager": "Eric Allring",
            "director": "Eric Allring"
        },
        "5": {
            "name": "Åsedakläder",
            "location": "Åseda",
            "business": "Herr- and gosskonfektion",
            "contact": {
                "phone": "91",
                "postgiro": "164265"
            },
            "financials": {
                "capital": "75,000 kr",
                "employees": {
                    "industriarb": 50
                },
                "annual_turnover": "500,000 kr"
            },
            "foundation_year": 1939,
            "manager": "Sten Gustafsson",
            "sales_manager": "Nils Larsson"
        },
        "6": {
            "name": "Åshammars Bultfabriks",
            "location": "Åshammar",
            "business": "Bultfabrik",
            "products": "Bult, mutter and mutterbrickor, axelflänsmutter, nit, träskruvar, ögleskruvar, rälsspik, rälsskarvbult, iso-latorkrok, linlås, tröskverksstift",
            "contact": {
                "telegraph": "Bultfabriken, Åshammar",
                "phone": [
                    "3",
                    "63",
                    "93"
                ],
                "postgiro": "13033"
            },
            "financials": {
                "capital": "540,000 kr",
                "employees": {
                    "industriarb": 95
                },
                "annual_turnover": "1,600,000 kr"
            },
            "foundation_year": 1899,
            "board": [
                {
                    "name": "Oscar Jönsson",
                    "role": "Styrelse (ordf.)"
                },
                {
                    "name": "Gösta Delin",
                    "role": "Styrelse"
                },
                {
                    "name": "Adolf Jönsson",
                    "role": "Styrelse"
                }
            ]
        },
        "7": {
            "name": "Åshammars Byggnadssnickeri",
            "location": "Lingked",
            "business": "Byggnadssnickerier and inredningar",
            "contact": {
                "office": "Åshammar",
                "phone": "Linghed",
                "postgiro": "91280"
            },
            "financials": {
                "capital": "32,000 kr"
            }
        }
    }
}