{
    "original": "Malmberg—Malmsjö\n\nStyrelse: v. konsul Robert Carrick\n(ordf.), dir. Elof Malmberg, dir. E. L.\nSchullerqvist.\n\nVerkst. dir.: Elof Malmberg.\nFörsäljn.- o. inhöpschef: B. Thollin.\n\n*Karl Malmberg, Möbelfabrik,\n\nVimmerby.\n\nSe Möbelfabriken Ejdern, Vimmerby.\n\n*AB. Th. Malmbergs Tricotstickeri,\n\nBorås.\n\nTillverkar herrtrikåvaror. Specialitet:\nsportartiklar av trikå. Varumärken:\n»Idrott», »Embo» o. »Turken».\n\nTelefon: 17595. Postgiro: 34244. Repr.\ni Stockholm för sportartiklar: AB.\nArvid Forsberg &amp; Co., Sveavägen 52,\ntelefon: 200227.\n\nAkt.-kap.: 50,000 kr. Antal\nindustriarb.: 20. Tillv.-värde pr år: 500,000 kr.\n\n—\tFirman etabl. 1904, bolag 1937.\nStyrelse: kamrer Gunnar Malmberg,\n\ndisp. Åke Malmberg.\nDisp.: Åke Malmberg.\n\nAB. Malmbäcks Träindustri,\n\nMalmbäck.\n\nSe Industri AB. Mbk—WV, Malmbäck.\n\nMalmens Metallverkstad,\n\nHovmantorp.\n\nTillverkar pressade och svarvade\nmetallarbeten såsom beslag för\nbelysningsarmatur, kalottpendlar, takfattningar,\nnattduksbordslampor (kippstakar),\nsaxarmar m. m. vid metallverkstad i\nHovmantorp (Kronob. l.).\n\nTelefon: 89. Postgiro: 165792. —\nAntal industriarb.: 25. Tillv.-värde pr år:\n200,000 kr. — Firman etabl. 1937.\nÄgare o. chef: fabr. Thore Mattsson.\n\n* Malmgrens Skofabriks AB.,\n\nRamlösa.\n\nSkofabrik i Ramlösa (Malmöh. l.).\nTelegr.-adr.: Skofabriken, Ramlösa.\nTelefon: Hälsingborg 96252 o. 96253.\nPostgiro: 26040.\n\nAkt.-kap.: 700,000 kr. Antal\nindustriarb.: 135. Tillv.-värde pr år: 2,000,000 kr.\n\n—\tFirman etabl. 1895.\n\nStyrelse: dir. I. Ekblom, disp. Gösta\nGrönvall, med. dr Herman Grönvall, dir.\nSture Grönvall, f. assessor Henry\nLjunggren, disp. Erik Strömberg.\nVerkst. dir.: Sture Grönvall.\n\n*\tAlbert Malmgren &amp; Co., Göteborg~\n\nFärg- och fernissfabrik. Tillverkar\ntorra kemiska färger, jordfärger,\noljerivna färger samt fernissor. Varumärken:\n»AMCO», »NIT» o. »Skansen». Firman\ndriver jämväl engros- och detaljhandel\nmed färger, fernissor och kemikalier\nm. m.\n\nKontor: 2:dra Långg. 21; postadr.:\nGöteborg 7. Telegr.-adr.: Albmalmgren,\nGöteborg. Telefon: 170825. Postgiro:\n12073.\n\nAntal industriarb.: 18. Tillv.-värde pr\når: 2,000,000 kr. — Firman etabl. 1890.\n\nÄgare o. chefer: handl. Olof Malmgren\no. handl. Erik Malmgren.\n\nKontorschef: Johan Lindgren.\n\nMalmköpings Träförädling AB.,\n\nMalmköping.\n\nSågverk och snickerifabrik i\nMalmköping (Södermanl. l.). Tillverkar\nbyggnadssnickerier, inredningar, möbler,\nsågade och hyvlade trävaror.\n\nTelegr.-adr.: Träförädlingen,\nMalmköping. Telefon: 69 o. 332. Postgiro: 23748.\n\nAkt.-kap.: 100,000 kr. Antal\nindustriarb.: 30. Tillv.-värde pr år: 300,000 kr.\n\n—\tFirman etabl. 1904, bolag 1941.\n\nVerkst. dir.: Gustaf Hamrin.\n\nMalmletning, AB. Elektrisk,\n\nStockholm.\n\nSe AB. Elektrisk Malmletning,\nStockholm.\n\n*\tMalmquists Bryggeri, Malmö.\n\nSe AB. Malmö Förenade Bryggerier.,\nMalmö.\n\nJ. Malmqvist &amp; Son AB., Växjö.\n\nSmides- och mek. verkstad samt\nsnickerifabrik. Tillverkar sparkstöttingar,\nkälkar, järnkonstruktioner, helsvetsade\ncisterner och retortrar, tippvagnar och\ntransportvagnar m. m. samt pressade\nmassartiklar.\n\nTelefon: 2265 o. 2984. Postgiro: 84800.\n\n—\tAkt.-kap.: 100,000 kr. Antal\nindustriarb.: 80. Tillv.-värde pr år: 1,250,000 kr.\n\n—\tFirman etabl. 1881, bolag 1941.\n\nVerkst. dir.: Sune Malmqvist.\n\n*d. C. Malmsjö AB., Göteborg.\n\nPianofabrik. Tillverkar flyglar och\npianon.\n\nKontor: Sprängkullsg. 19 B.\nTelefon: 116709. Utställningar: Stockholm,",
    "structured": {
        "firms": [
            {
                "name": "AB. Th. Malmbergs Tricotstickeri",
                "location": "Borås",
                "business": "Tillverkar herrtrikåvaror. Specialitet: sportartiklar av trikå.",
                "contact": {
                    "phone": [
                        "17595"
                    ],
                    "postgiro": "34244",
                    "sales_offices": [
                        {
                            "location": "Stockholm",
                            "phone": "200227"
                        }
                    ]
                },
                "financials": {
                    "capital": "50,000 kr",
                    "employees": {
                        "industriarb": 20
                    },
                    "annual_turnover": "500,000 kr",
                    "annual_production_value": "500,000 kr"
                },
                "foundation_year": 1904,
                "corporation_year": 1937
            },
            {
                "name": "AB. Malmbäcks Träindustri",
                "location": "Malmbäck"
            },
            {
                "name": "Malmens Metallverkstad",
                "location": "Hovmantorp",
                "contact": {
                    "phone": "89",
                    "postgiro": "165792"
                },
                "financials": {
                    "employees": {
                        "industriarb": 25
                    },
                    "annual_production_value": "200,000 kr"
                },
                "foundation_year": 1937
            },
            {
                "name": "Malmgrens Skofabriks AB.",
                "location": "Ramlösa",
                "contact": {
                    "phone": [
                        "96252",
                        "96253"
                    ],
                    "postgiro": "26040"
                },
                "financials": {
                    "capital": "700,000 kr",
                    "employees": {
                        "industriarb": 135
                    },
                    "annual_turnover": "2,000,000 kr"
                },
                "foundation_year": 1895
            },
            {
                "name": "Albert Malmgren & Co.",
                "location": "Göteborg",
                "business": "Färg- och fernissfabrik. Tillverkar torra kemiska färger, jordfärger, oljerivna färger samt fernissor.",
                "contact": {
                    "phone": "170825",
                    "postgiro": "12073"
                },
                "financials": {
                    "employees": {
                        "industriarb": 18
                    },
                    "annual_production_value": "2,000,000 kr"
                },
                "foundation_year": 1890
            },
            {
                "name": "Malmköpings Träförädling AB.",
                "location": "Malmköping",
                "business": "Sågverk och snickerifabrik. Tillverkar byggnadssnickerier, inredningar, möbler, sågade och hyvlade trävaror.",
                "contact": {
                    "phone": [
                        "69",
                        "332"
                    ],
                    "postgiro": "23748"
                },
                "financials": {
                    "capital": "100,000 kr",
                    "employees": {
                        "industriarb": 30
                    },
                    "annual_turnover": "300,000 kr"
                },
                "foundation_year": 1904,
                "corporation_year": 1941
            },
            {
                "name": "Malmletning, AB. Elektrisk",
                "location": "Stockholm"
            },
            {
                "name": "J. Malmqvist & Son AB.",
                "location": "Växjö",
                "business": "Smides- och mek. verkstad samt snickerifabrik.",
                "contact": {
                    "phone": [
                        "2265",
                        "2984"
                    ],
                    "postgiro": "84800"
                },
                "financials": {
                    "capital": "100,000 kr",
                    "employees": {
                        "industriarb": 80
                    },
                    "annual_production_value": "1,250,000 kr"
                },
                "foundation_year": 1881,
                "corporation_year": 1941
            },
            {
                "name": "d. C. Malmsjö AB.",
                "location": "Göteborg",
                "business": "Pianofabrik. Tillverkar flyglar och pianon.",
                "contact": {
                    "office": "Sprängkullsg. 19 B",
                    "phone": "116709"
                }
            }
        ]
    }
}