{
    "original": "S venljunga—Svensk\n\nsamt valkfat och hasplar för garverier\nm. m. vid fabrik i Svenljunga (Älvsb. l.).\n\nTelefon: 1107. Postgiro: 143160. —\nArb.-antal: 8. Tillv.-värde pr år: 80,000\nkr. — Firman etabl. 1923.\n\nÄgare o. chef: fabr. Oscar Reinholds.\n\nAB. Svenljunga Syfabrik,\n\nSvenljunga.\n\nTillverkar herr- och damkonfektion,\narbetskläder samt herrskjortor vid fabrik\ni Svenljunga (Älvsb. l.). Varumärken:\n»Jibe» o. »Ätra».\n\nTelefon: 1002. Postgiro: 5274. —\nAkt.-kap.: 300,000 kr. Tillv.-värde pr år:\n1,500,000 kr. — Firman etabl. 1920, bolag\n1921.\n\nDisp.: John Blomquist.\n\nAB. Svenljunga Trikåfabrik,\n\nSvenljunga.\n\nTillverkar flick- och damunderkläder\nvid trikåfabrik i Svenljunga (Älvsb. l.).\n\nTelefon: 1071. Postgiro: 85831. Repr. i\nStockholm: Asperén &amp; Åkesson AB.,\nKungsg. 56, telefon: 101250.\n\nAkt.-kap.: 50,100 kr. Antal\nindustriarb.: 25. Tillv.-värde pr år: 500,000 kr. —\nFirman etabl. 1937, bolag 1940.\n\nDisp.: Nils Widén.\n\n\"Svensk Celluloidindustri AB.,\n\nGislaved.\n\nKem.-teknisk fabrik och mek. verkstad\ni Gislaved (Jönköp. l.). Tillverkar\ncel-luloidvaror såsom slanglösa\nvelocipedpumpar, velocipedhandtag, dörrskydd,\nledkort, etuier, skyltar, reklamartiklar\nsamt celluloid i plattor, massartiklar av\nkonstmassor såsom kammar, tub- och\nflaskförskruvningar samt pressade och\nsvarvade massartiklar av metall.\n\nTelegr.-adr. o. telefon: Celluloid,\nGislaved. Postgiro: 99562.\n\nAkt.-kap.: 45,000 kr. Antal\nindustriarb.: 90. Tillv.-värde pr år: 1,900,000 kr.\n— Firman grundad 1920, bolag 1944.\n\nStyrelse o. verkst. dir.: Thure\nMårtenson.\n\n(Jfr annons nr 36.)\n\n\"AB. Svensk-Engelska\nHerrkonfek-tionsfabriken Hjelm, Örkelljunga.\n\nSe AB. Fabriken Hjelm, örkelljunga.\n\nAB. Svensk Filmindustri,\n\nStockholm.\n\nFilminspelningsateljéer och\nlaboratorier i Råsunda (Sthlms l.). Bolaget ut-\n\nför inspelning, framkallning och\nkopiering av biograf- och beställningsfilmer;\nuthyr och försäljer biograffilm i Sverige\noch utlandet samt driver biografrörelse\noch skolfilmverksamhet.\n\nKontor: Centrum. Telegr.-adr.:\nFilmindustri, Stockholm. Telefon: »Svensk\nFilmindustri». Postgiro: 630. —\nAkt.-kap.: 8,000,010 kr.\n\nFirman etabl. 1919 genom\nsammanslagning av AB. Svenska Biograf teatern,\nbildat 1907, och Filmindustri AB.\nSkan-dia, bildat 1918.\n\nStyrelse: häradshövd. G. Siljeström\n(ordf.), dir. Olof Andersson, jur. dr E.\nBroms, bankdir. P. Brundell, fil. lic. C.\nA. Dymling, dir. Hugo B. Hintze, dir.\nAxel Lindberg, adv. J. Listander.\n\nVerkst. dir.: C. A. Dymling.\n\n\"Svensk Fjäder- &amp; Dunindustri AB.,\n\nS tallarholmen.\n\nFörädlar fjäder och dun samt\ntillverkar stoppningsmaterial och sängkläder vid\nfabrik i Stallarholmen (Södermanl. !.).\nVarumärke: »Sana».\n\nTelegr.-adr.: Sanadun, Stallarholmen.\nTelefon: 10. Postgiro: 57661.\n\nAkt.-kap.: 60,000 kr. Antal\nindustriarb.: 20. — Bolaget grundat 1933.\n\nStyrelse: disp. Karl Jönsson, dir. A.\nKreibom, fru Elsa Seidel.\n\nDisp.: Karl Jönsson.\n\nAB. Svensk Grammofonindustri,\n\nStockholm.\n\nTillverkar grammofonskivemassa och\nmatriser samt utför pressning av\ngrammofonskivor vid fabrik i Bro (Uppsala\n1.). Varumärke: »Toni».\n\nKontor: Stockholm, Vasag. 26.\nTelefon: 106367 o. 211007. Postgiro: 39941.\n\nAkt.-kap.: 120,000 kr. Antal\nindustriarb.: 30. Tillv.-värde pr år: 625,000 kr. —\nBolaget grundat 1937.\n\nDir.: Emil Pettersson.\n\nDisp..- Tage Andersson.\n\nKamrer: Harry Svalfors.\n\n\"AB. Svensk Knappindustri,\n\nSträngnäs.\n\nTillverkar stennötsknappar.\n\nTelegr.-adr.: Knappindustri,\nSträngnäs. Telefon: 309. Postgiro: 88890.\n\nAkt.-kap.: 50,000 kr. Antal\nindustriarb.: 60. — Firman etabl. 1934, bolag\n1941.\n\nStyrelse o. verkst. dir.: Gustav B.\nLarson.\n\n528*",
    "structured": {
        "1": {
            "name": "Svensk samt valkfattare och hasplar för garverier m. m.",
            "location": "Svenljunga",
            "business": "Valkfattare och hasplar för garverier",
            "products": "Svenljunga (Älvsb. l.)",
            "contact": {
                "office": "Ej tillgängligt",
                "phone": [
                    "1107"
                ],
                "postgiro": "143160",
                "telegraph": "Ej tillgängligt",
                "factory_office": "Ej tillgängligt",
                "factory_phone": "Ej tillgängligt"
            },
            "financials": {
                "capital": "Ej tillgängligt",
                "employees": {
                    "arb.-antal": 8
                },
                "annual_turnover": "80,000 kr",
                "annual_production_value": "80,000 kr"
            },
            "foundation_year": 1923,
            "owners": [
                "Oscar Reinholds"
            ]
        },
        "2": {
            "name": "AB. Svenljunga Syfabrik",
            "location": "Svenljunga",
            "business": "Herr- och damkonfektion, arbetskläder samt herrskjortor",
            "products": "Svenljunga (Älvsb. l.)",
            "contact": {
                "phone": [
                    "1002"
                ],
                "postgiro": "5274"
            },
            "financials": {
                "capital": "300,000 kr",
                "annual_turnover": "1,500,000 kr"
            },
            "foundation_year": 1920,
            "corporation_year": 1921,
            "director": "John Blomquist"
        },
        "3": {
            "name": "AB. Svenljunga Trikåfabrik",
            "location": "Svenljunga",
            "business": "Flick- och damunderkläder",
            "products": "Svenljunga (Älvsb. l.)",
            "contact": {
                "phone": [
                    "1071"
                ],
                "postgiro": "85831"
            },
            "financials": {
                "capital": "50,100 kr",
                "employees": {
                    "antal industriarb.": 25
                },
                "annual_turnover": "500,000 kr"
            },
            "foundation_year": 1937,
            "corporation_year": 1940,
            "director": "Nils Widén"
        },
        "4": {
            "name": "Svensk Celluloidindustri AB.",
            "location": "Gislaved",
            "business": "Kem.-teknisk fabrik och mek. verkstad",
            "products": "Gislaved (Jönköp. l.)",
            "contact": {
                "phone": [
                    "Ej tillgängligt"
                ],
                "postgiro": "99562",
                "telegraph": "Celluloid, Gislaved"
            },
            "financials": {
                "capital": "45,000 kr",
                "employees": {
                    "antal industriarb.": 90
                },
                "annual_turnover": "1,900,000 kr"
            },
            "foundation_year": 1920,
            "corporation_year": 1944,
            "director": "Thure Mårtenson"
        },
        "5": {
            "name": "AB. Svensk Filmindustri",
            "location": "Stockholm",
            "business": "Filminspelningsateljéer och laboratorier",
            "products": "Råsunda (Sthlms l.)",
            "contact": {
                "office": "Centrum",
                "phone": [
                    "Ej tillgängligt"
                ],
                "postgiro": "630"
            },
            "financials": {
                "capital": "8,000,010 kr"
            },
            "foundation_year": 1919,
            "board": [
                {
                    "name": "häradshövd. G. Siljeström",
                    "role": "ordf."
                },
                {
                    "name": "dir. Olof Andersson",
                    "role": "Ej tillgängligt"
                },
                {
                    "name": "jur. dr E. Broms",
                    "role": "Ej tillgängligt"
                },
                {
                    "name": "bankdir. P. Brundell",
                    "role": "Ej tillgängligt"
                },
                {
                    "name": "fil. lic. C. A. Dymling",
                    "role": "Ej tillgängligt"
                },
                {
                    "name": "dir. Hugo B. Hintze",
                    "role": "Ej tillgängligt"
                },
                {
                    "name": "dir. Axel Lindberg",
                    "role": "Ej tillgängligt"
                },
                {
                    "name": "adv. J. Listander",
                    "role": "Ej tillgängligt"
                }
            ],
            "managing_director": "C. A. Dymling"
        },
        "6": {
            "name": "Svensk Fjäder- & Dunindustri AB.",
            "location": "Stallarholmen",
            "business": "Förädlar fjäder och dun samt tillverkar stoppningsmaterial och sängkläder",
            "products": "Stallarholmen (Södermanl. l.)",
            "contact": {
                "phone": [
                    "10"
                ],
                "postgiro": "57661",
                "telegraph": "Sanadun, Stallarholmen"
            },
            "financials": {
                "capital": "60,000 kr",
                "employees": {
                    "antal industriarb.": 20
                }
            },
            "foundation_year": 1933,
            "board": [
                {
                    "name": "disp. Karl Jönsson",
                    "role": "Ej tillgängligt"
                },
                {
                    "name": "dir. A. Kreibom",
                    "role": "Ej tillgängligt"
                },
                {
                    "name": "fru Elsa Seidel",
                    "role": "Ej tillgängligt"
                }
            ],
            "director": "Karl Jönsson"
        },
        "7": {
            "name": "AB. Svensk Grammofonindustri",
            "location": "Stockholm",
            "business": "Tillverkar grammofonskivemassa och matriser samt utför pressning av grammofonskivor",
            "products": "Bro (Uppsala 1.)",
            "contact": {
                "office": "Stockholm, Vasag. 26",
                "phone": [
                    "106367",
                    "211007"
                ],
                "postgiro": "39941"
            },
            "financials": {
                "capital": "120,000 kr",
                "employees": {
                    "antal industriarb.": 30
                },
                "annual_turnover": "625,000 kr"
            },
            "foundation_year": 1937,
            "director": "Emil Pettersson"
        },
        "8": {
            "name": "AB. Svensk Knappindustri",
            "location": "Strängnäs",
            "business": "Tillverkar stennötsknappar",
            "products": "Ej tillgängligt",
            "contact": {
                "phone": [
                    "309"
                ],
                "postgiro": "88890",
                "telegraph": "Knappindustri, Strängnäs"
            },
            "financials": {
                "capital": "50,000 kr",
                "employees": {
                    "antal industriarb.": 60
                }
            },
            "foundation_year": 1934,
            "corporation_year": 1941,
            "director": "Gustav B. Larson"
        }
    }
}