{
    "original": "Trelleborg—Trikå\n\nAkt.-kap.: 4,200,000 kr. Antal\nindustriarb.: 1,600. — Bolaget grundat 1905.\n\nStyrelse: disp. Henry Dunker (ordf.),\nf. d. medicinalrådet Magnus Herrlin,\nborgm. C. J. Reventberg, dir. H.\nStåhlbrandt, bankdir. Ivar Åkerman.\n\nVerkst. direktörer: Henry Dunker o.\nH. Ståhlbrandt.\n\növering.: Folke Rosén.\n\nKontorschef: Arthur Lindquist.\n\nDir.-assist.: Åke Ståhlbrandt.\n\nKamrer: Adolf Borgström.\n\nFörsäljn.-chef er: Bengt Johanson, J.\nHerrström, A. Hellberg, Fredrik\nBergström o. A. Thelin.\n\n(Jfr annons nr 37.)\n\n\"AB. Trelleborgs Linoleumindustri,\n\nStockholm.\n\nTillverkar golvmattor vid fabrik i\nTrelleborg. Varumärke: »Trelinum».\n\nHuvudkontor: Stockholm, Hamng. 10;\npostadr.: Box 7138. Telegr.-adr.:\nTrelinum, Stockholm. Telefon: 233015.\nPostgiro: 59353. Fabrikskontor: Trelleborg.\nTelefon: 1435 o. 1760.\n\nAkt.-kap.: 600,000 kr. Antal\nindustriarb.: 50. Tillv.-värde pr år: 2,000,000 kr.\n— Bolaget grundat 1935.\n\nStyrelse: dir. Kr. Huldt (ordf.), disp.\nG. Gunnarsson, ing. Erik Huldt.\n\nVerkst. dir.: Erik Huldt.\n\nV. verkst. dir.: G. Gunnarsson.\n\nFabrikschef: Hans Starck.\n\nAB. Trelleborgs Velocipedfabrik,\n\nTrelleborg.\n\nTillverkar velocipeder. Specialiteter:\nramar och gafflar för velocipeder.\n\nTelegr.-adr.: Velofabrik, Trelleborg.\nTelefon: 1174. Postgiro: 30468.\n\nAkt.-kap.: 65,000 kr. Antal\nindustriarb.: 45.\n\nFirman etabl. 1923, bolag 1940.\n\nChefer: fabr. O. G. Liljeberg o.\nkontorschef Gunnar Liljeberg.\n\n\"AB. Tretorn, Hälsingborg.\n\nTillverkar galoscher, snowboots och\ngymnastikskor vid fabrik i Malmö\n(för-utv. Ryska Gummifabriks AB.).\n\nHuvudkontor: Hälsingborg.\nFabrikskontor: Malmö, Barkg. 10. Telegr.-adr.:\nGummifabriken, Malmö. Telefon: Malmö\n71045.\n\nAkt.-kap.: 12,478,800 kr. Antal\nindustriarb.: 300. — Fabriken anlagd 1899.\n\nStyrelse: bankdir. Åke Belfrage\n(ordf.), disp. Henry Dunker, dir. Clas\nErikson, generalkonsul Ragnar Hedberg,\n\nryttm. Ulf Olsson, ryttm. Gösta v. Plåten,\ndisp. Artur Stibe.\n\nVerkst. direktörer: disp. Henry\nDunker o. disp. Artur Stibe.\n\nPlatschef i Malmö: dir. N. Liljemark.\n\n\"Triangeln, Fören. Kaffeimportörers\nRosteri AB., Göteborg.\n\nSe Förenade Kaffeimportörers Rosteri\nAB. Triangeln, Göteborg.\n\nTriangeln, Kem. Tekn. Fabriken,\n\nMalmö.\n\nSe Kem. Tekn. Fabriken Triangeln\nAB., Malmö.\n\n\"AB. Tricotkonfektion, Stockholm.\nSe AB. Kantex, Stockholm.\n\n\"AB. Trikåfabriken Elit, Borås.\n\nTillverkar trikåunderkläder i bomull,\nsilke och silkebomull. Specialitet:\ninter-lockvaror.\n\nTelefon: 10369 o. 15369. Postgiro:\n84940. — Akt.-kap:: 125,000 kr. Antal\nindustriarb.: 35. — Firman etabl. 1927,\nbolag 1940.\n\nStyrelse o. verkst. dir.: Oscar\nSegelmark.\n\nFörsäljn.-chef: Karl Gustav Karlqvist.\n\n\"AB. Trikåfabriken Essve,\n\nStockholm.\n\nTillverkar underkläder och * damblusar\nhuvudsakligen av charmeuse och siden.\nVarumärke: »Essve».\n\nKontor: Nordenflychtsvägen 64.\nTelefon: 511211 o. 511260. Postgiro: 4528.\n\nAkt.-kap.: 40,000 kr. Antal\nindustriarb.: 20. Tillv.-värde pr år: 300,000 kr.\n— Bolaget grundat 1928.\n\nStyrelse: dir. Josef Söderberg, köpm.\nArne Villard, dir. Fritz Villard.\n\nVerkst. direktörer: Josef Söderberg o.\nFritz Villard.\n\n\"Trikåfabriken Svea, Borås.\n\nTillverkar trikåunderkläder.\nTelefon: 11541. — Antal industriarb.:\n4. — Firman etabl. 1916.\n\nÄgare o. chef: fabr. Arthur Andersson\n\n\"Trikåfabriker, Sveriges Förenade,\n\nBorås.\n\nSe AB. Sveriges Förenade\nTrikåfabriker, Borås.",
    "structured": {
        "1": {
            "name": "AB. Trelleborgs Linoleumindustri",
            "location": "Trelleborg",
            "business": "Tillverkar golvmattor vid fabrik",
            "products": "Golvmattor",
            "contact": {
                "office": "Stockholm, Hamng. 10; postadr.: Box 7138",
                "phone": [
                    "233015"
                ],
                "postgiro": "59353",
                "head_office": "Stockholm, Hamng. 10",
                "sales_offices": [
                    {
                        "location": "Trelleborg",
                        "phone": "1435 o. 1760"
                    }
                ],
                "telegraph": "Trelinum, Stockholm",
                "factory_office": "Trelleborg",
                "factory_phone": "1435 o. 1760"
            },
            "financials": {
                "capital": "600,000 kr",
                "employees": {
                    "industriarb": 50
                },
                "annual_production_value": "2,000,000 kr"
            },
            "foundation_year": 1935
        },
        "2": {
            "name": "AB. Trelleborgs Velocipedfabrik",
            "location": "Trelleborg",
            "business": "Tillverkar velocipeder",
            "products": "Ramar och gafflar för velocipeder",
            "contact": {
                "telegraph": "Velofabrik, Trelleborg",
                "phone": "1174",
                "postgiro": "30468"
            },
            "financials": {
                "capital": "65,000 kr",
                "employees": {
                    "industriarb": 45
                }
            },
            "foundation_year": 1940
        },
        "3": {
            "name": "AB. Tretorn",
            "location": "Hälsingborg",
            "business": "Tillverkar galoscher, snowboots och gymnastikskor vid fabrik",
            "products": "Galoscher, snowboots och gymnastikskor",
            "contact": {
                "head_office": "Hälsingborg",
                "factory_office": "Malmö, Barkg. 10",
                "phone": [
                    "Malmö 71045"
                ],
                "telegraph": "Gummifabriken, Malmö",
                "postgiro": "12,478,800 kr"
            },
            "financials": {
                "capital": "12,478,800 kr",
                "employees": {
                    "industriarb": 300
                }
            },
            "foundation_year": 1899
        },
        "4": {
            "name": "AB. Trikåfabriken Elit",
            "location": "Borås",
            "business": "Tillverkar trikåunderkläder i bomull, silke och silkebomull",
            "products": "Trikåunderkläder i bomull, silke och silkebomull",
            "contact": {
                "phone": [
                    "10369",
                    "15369"
                ],
                "postgiro": "84940"
            },
            "financials": {
                "capital": "125,000 kr",
                "employees": {
                    "industriarb": 35
                }
            },
            "foundation_year": 1940
        },
        "5": {
            "name": "AB. Trikåfabriken Essve",
            "location": "Stockholm",
            "business": "Tillverkar underkläder och damblusar huvudsakligen av charmeuse och siden",
            "products": "Underkläder och damblusar",
            "contact": {
                "office": "Nordenflychtsvägen 64",
                "phone": [
                    "511211",
                    "511260"
                ],
                "postgiro": "4528"
            },
            "financials": {
                "capital": "40,000 kr",
                "employees": {
                    "industriarb": 20
                },
                "annual_production_value": "300,000 kr"
            },
            "foundation_year": 1928
        },
        "6": {
            "name": "Trikåfabriken Svea",
            "location": "Borås",
            "business": "Tillverkar trikåunderkläder",
            "products": "Trikåunderkläder",
            "contact": {
                "phone": [
                    "11541"
                ]
            },
            "financials": {
                "employees": {
                    "industriarb": 4
                }
            },
            "foundation_year": 1916
        }
    }
}