{
    "original": "Emmaboda—Enfors\n\n*AB. Emmaboda Snickerifabrik,\n\nEmmaboda.\n\nSnickerifabrik i Emmaboda (Kalmar\n1.). Tillverkar byggnadssnickerier,\ninredningar och möbler.\n\nTelefon: 39. Postgiro: 75307.\n\nAkt.-kap.: 175,000 kr. Antal\nindustriarb.: 40. Tillv.-värde pr år: 400,000 kr.\n— Fabriken anlagd 1901, nuv. bolag\ngrundat 1925.\n\nStyrelse: v. konsul Th. Annerstedt\n(ordf.), konditor Frans E. Holmgren,\nbankdir. G. Larsen.\n\nVerkst. dir.: Th. Annerstedt.\n\nDisp.: K. G. Annerstedt.\n\n*Emmaboda Tapetfabrik,\nKommanditbolag, Emmaboda.\n\nTapetfabrik i Emmaboda (Kalmar l.).\nTillverkar tapeter och bårder.\n\nTelegr.-adr.: Emmabodatapet,\nEmmaboda. Telefon: 52. Postgiro: 80950. —\nAntal industriarb.: 26. —- Firman etabl.\n1920.\n\nDisp.: Henry Carlsson.\n\nEmmaljunga Barnvagnsfabrik,\n\nEmmaljunga.\n\nMek. verkstad och barnvagnsfabrik i\nEmmaljunga (Kristianst. l.). Tillverkar\nbarnvagnar och dockvagnar m. m.\n\nTelegr.-adr.: Barnvagnar, Emmaljunga.\nTelefon: Emmaljunga 9 o. 56. Postgiro:\n31622. — Antal industriarb.: 100. —\nFirman etabl. 1925.\n\nÄgare o. chef: fabr. Henry L. Persson.\n\n*Carl Emond AB., Landskrona.\n\nTextilfabrik. Tillverkar hängslen,\nstrumpeband, ärmhållare, herrstrumpor,\nbadkappor samt halsdukar och bälten.\nVarumärke: »Emond».\n\nTelefon: »Carl Emonds». Postgiro:\n9663. Avd.-kontor: Stockholm,\nNorr-landsg. 31—33, telefon: 111458.\n\nAkt.-kap.: 425,000 kr. Antal\nindustriarb.: 100. — Bolaget grundat 1923.\n\nStyrelse: dir. Carl Emond, ing. Stig\nEmond.\n\nVerkst. dir.: Carl Emond.\n\n*Emil Emond AB., Landskrona.\n\nTrikå- och konfektionsfabrik.\nTillverkar damunderkläder och klänningar.\nVarumärke: »Solblomman».\n\nTelefon: »Emil Emonds». Postgiro:\n6815. Avd.-kontor: Stockholm,\nSveavägen 29, telefon: 208272; Göteborg,\nKungsg. 10 B, telefon: 134203.\n\nAkt.-kap.: 600,000 kr. Antal\nindustriarb.: 500. — Firman etabl. 1921.\n\nStyrelse: grossh. Albert Emond, dir.\nEmil Emond, disp. Fabian Emond,\nkonstnär Martin Emond.\n\nVerkst. dir.: Emil Emond.\n\n*AB. Emsfors Bruk, Påskallavik.\n\nPappersbruk med^ sulfitfabrik i\nEmsfors (Kalmar l.). Tillverkar omslags- och\npåspapper, fruktomslags- och\nbuteljomslagspapper samt sulfitcellulosa. Bolaget\ndriver jämväl jordbruk och\nskogshantering.\n\nTelegr.-adr.: Emsfors, Oskarshamn.\nTelefon: 4, 24 o. 55. Postgiro: 95393.\n\nAkt.-kap.: 1,000,000 kr. Årstillv.: 12,000\nton sulfitpapper o. 3,000 ton\nsulfitcellulosa (för försäljn.). — Firman etabl.\n1867, nuv. bolag grundat 1914.\n\nStyrelse: civiling. frih. Tage\nFleet-wood, konsul Tag*e Hedborg, dir. Arvid\nörn, dir. Bertil örn, disp. Ragnar örn.\n\nDisp.: Ragnar örn.\n\nFörsäljn.-chef: Folke Enderlein.\n\n\"Emtiverken, Eskilstuna.\n\nMetall- och försilvringsfabrik.\nTillverkar tenn- och nysilverartiklar, utför\nför-silvring samt rostskyddsbehandling av\njärn och stål (fosfatering). Specialitet:\nmotivpräglade turistartiklar.\n\nTelefon: 32340. Postgiro: 27094. —\nArb.-antal: 9. — Firman etabl. 1925\nunder namn Eskilstuna Metall- &amp;\nTermosindustri, nuv. namn 1930.\n\nÄgare o. chef: ing. O. F. Flodeli.\n\nAB. Eneroth &amp; Co., Stockholm.\n\nKem. tekn. fabrik. Tillverkar såpa,\ntvättpulver (»Gummans» tvättpulver),\nkristallsoda m. m.\n\nKontor: Alvik, Stockholm; postadr.:\nStockholm 12. Telegr.-adr. o. telefon:\n»Kemabolagen», Stockholm.\n\nAkt.-kap..: 1,000,000 kr. — Fabriken\nanlagd 1812 i Göteborg, nuv. bolag\ngrundat 1897. Bolaget äges av Fabriken\nTomten, Alex. Lagerman J:r AB., Stockholm,\noch ingår i Kema-Bolagen.\n\nStyrelse: grossh. Robert Ljunglöf\n(ordf.), fil. dr Harald Nordenson, disp.\nNils Westerdahl.\n\nVerkst. dir.: Tor Olsson.\n\n*Thure Enfors, Stockholm.\n\nByggnadsentreprenörfirma för\nbostads-och affärshus, industribyggnader m. m.\n\nKontor: Florag. 20. Telefon: 109030\no. 109535. Postgiro: 156684. — Firman\netabl. 1926.\n\nÄgare o. chef: ing. Thure Enfors.",
    "structured": {
        "1": {
            "name": "AB. Emmaboda Snickerifabrik",
            "location": "Emmaboda",
            "business": "Snickerifabrik i Emmaboda.",
            "products": "Tillverkar byggnadssnickerier, inredningar och möbler.",
            "contact": {
                "office": "Emmaboda",
                "phone": [
                    "39"
                ],
                "postgiro": "75307"
            },
            "financials": {
                "capital": "175,000 kr",
                "employees": {
                    "industriarb": 40
                },
                "annual_turnover": "400,000 kr",
                "annual_production_value": "400,000 kr"
            },
            "foundation_year": 1901,
            "current_name_year": 1925,
            "board": [
                {
                    "name": "v. konsul Th. Annerstedt",
                    "role": "ordf."
                },
                {
                    "name": "konditor Frans E. Holmgren",
                    "role": ""
                },
                {
                    "name": "bankdir. G. Larsen",
                    "role": ""
                }
            ],
            "director": "Th. Annerstedt",
            "managing_director": "Th. Annerstedt"
        },
        "2": {
            "name": "Emmaboda Tapetfabrik",
            "location": "Emmaboda",
            "business": "Tapetfabrik i Emmaboda.",
            "products": "Tillverkar tapeter och bårder.",
            "contact": {
                "postgiro": "80950"
            },
            "board": [
                {
                    "name": "",
                    "role": ""
                }
            ],
            "director": "",
            "managing_director": "",
            "manager": ""
        },
        "3": {
            "name": "Emmaljunga Barnvagnsfabrik",
            "location": "Emmaljunga",
            "business": "Mek. verkstad och barnvagnsfabrik i Emmaljunga.",
            "products": "Tillverkar barnvagnar och dockvagnar m. m.",
            "contact": {
                "phone": [
                    "Emmaljunga 9",
                    "56"
                ],
                "postgiro": "31622"
            },
            "financials": {
                "employees": {
                    "industriarb": 100
                }
            },
            "director": "",
            "managing_director": "",
            "manager": "fabr. Henry L. Persson"
        },
        "4": {
            "name": "Carl Emond AB.",
            "location": "Landskrona",
            "business": "Textilfabrik.",
            "products": "Tillverkar hängslen, strumpeband, ärmhållare, herrstrumpor, badkappor samt halsdukar och bälten.",
            "contact": {
                "phone": [
                    "Norr-landsg. 31—33",
                    "111458"
                ],
                "postgiro": "9663"
            },
            "financials": {
                "capital": "425,000 kr",
                "employees": {
                    "industriarb": 100
                }
            },
            "foundation_year": 1923,
            "board": [
                {
                    "name": "dir. Carl Emond",
                    "role": ""
                },
                {
                    "name": "ing. Stig Emond",
                    "role": ""
                }
            ],
            "director": "Carl Emond",
            "sales_manager": ""
        },
        "5": {
            "name": "Emil Emond AB.",
            "location": "Landskrona",
            "business": "Trikå- och konfektionsfabrik.",
            "products": "Tillverkar damunderkläder och klänningar.",
            "contact": {
                "phone": [
                    "Sveavägen 29",
                    "208272",
                    "Kungsg. 10 B",
                    "134203"
                ],
                "postgiro": "6815"
            },
            "financials": {
                "capital": "600,000 kr",
                "employees": {
                    "industriarb": 500
                }
            },
            "foundation_year": 1921,
            "board": [
                {
                    "name": "grossh. Albert Emond",
                    "role": ""
                },
                {
                    "name": "dir. Emil Emond",
                    "role": ""
                },
                {
                    "name": "disp. Fabian Emond",
                    "role": ""
                },
                {
                    "name": "konstnär Martin Emond",
                    "role": ""
                }
            ],
            "director": "Emil Emond"
        },
        "6": {
            "name": "AB. Emsfors Bruk",
            "location": "Påskallavik",
            "business": "Pappersbruk med^ sulfitfabrik i Emsfors.",
            "products": "Tillverkar omslags- och påspapper, fruktomslags- och buteljomslagspapper samt sulfitcellulosa.",
            "financials": {
                "capital": "1,000,000 kr",
                "annual_turnover": "12,000 ton sulfitpapper o. 3,000 ton sulfitcellulosa (för försäljn.)"
            },
            "foundation_year": 1867,
            "current_name_year": 1914,
            "board": [
                {
                    "name": "civiling. frih. Tage Fleet-wood",
                    "role": ""
                },
                {
                    "name": "konsul Tag*e Hedborg",
                    "role": ""
                },
                {
                    "name": "dir. Arvid örn",
                    "role": ""
                },
                {
                    "name": "dir. Bertil örn",
                    "role": ""
                },
                {
                    "name": "disp. Ragnar örn",
                    "role": ""
                }
            ],
            "director": "",
            "sales_manager": "Folke Enderlein"
        },
        "7": {
            "name": "Emtiverken",
            "location": "Eskilstuna",
            "business": "Metall- och försilvringsfabrik.",
            "products": "Tillverkar tenn- och nysilverartiklar, utför för-silvring samt rostskyddsbehandling av järn och stål (fosfatering).",
            "contact": {
                "phone": [
                    "32340"
                ],
                "postgiro": "27094"
            },
            "financials": {
                "employees": {
                    "arb.-antal": 9
                }
            },
            "current_name_year": 1930,
            "owner": "ing. O. F. Flodeli"
        },
        "8": {
            "name": "AB. Eneroth & Co.",
            "location": "Stockholm",
            "business": "Kem. tekn. fabrik.",
            "products": "Tillverkar såpa, tvättpulver (»Gummans» tvättpulver), kristallsoda m. m.",
            "contact": {
                "office": "Alvik, Stockholm",
                "postgiro": "Stockholm 12"
            },
            "financials": {
                "capital": "1,000,000 kr"
            },
            "foundation_year": 1897,
            "board": [
                {
                    "name": "grossh. Robert Ljunglöf",
                    "role": "ordf."
                },
                {
                    "name": "fil. dr Harald Nordenson",
                    "role": ""
                },
                {
                    "name": "disp. Nils Westerdahl",
                    "role": ""
                }
            ],
            "director": "Tor Olsson"
        },
        "9": {
            "name": "Thure Enfors",
            "location": "Stockholm",
            "business": "Byggnadsentreprenörfirma för bostads-och affärshus, industribyggnader m. m.",
            "contact": {
                "office": "Florag. 20",
                "phone": [
                    "109030",
                    "109535"
                ],
                "postgiro": "156684"
            },
            "foundation_year": 1926,
            "owner": "ing. Thure Enfors"
        }
    }
}