{
    "original": "Kungsskogen—Kvarn\n\nStyrelse: rådman Gustaf Veländer\n(ordf.), överstelöjtn. Arne Francke, dir.\nTSTils Francke, herr Didrik Reuterskiöld,\ndir. Ragnar Sundfeldt.\n\nVerkst. dir.: Nils Francke.\n\nSlcogschef: Lars Falck.\n\n*\tKungsskogens Sågverk, Ölme.\n\nSe AB. Statens Skogsindustrier,\nStockholm.\n\n\"Kungsörs Armaturfabrik, Kungsör.\n\nSe AB. Nordiska Armaturfabrikerna,\nLinköping.\n\n*\tAB. Kungsörs Bleckkärlsfabrik,\n\nKungsör.\n\nBleckkärls- och metallvarufabrik i\nKungsör (Västmanl. l.). Tillverkar\nhushållskärl av aluminium- och bleckplåt,\nin-kokningsapparater, lackerade artiklar,\ngasmätare och stormlyktor samt utför på\nbeställning alla slags arbeten i tunnplåt,\npressade, svetsade och lackerade.\n\nTelegr.-adr. o. telefon: Bleckkärl,\nKungsör. Postgiro: 9231. Avd.-kontor:\nStockholm, Stureg. 10, telefon: 674167.\n\nAntal industriarb.: 250. Tillv.-värde pr\når: 3,000,000 kr.\n\nBolaget grundades 1897.\n\nStyrelse: civiling. Arvid Hamrin\n(ordf.), disp. Anton Hamrin.\n\nVerkst. dir.: Arvid Hamrin.\n\nDisp.: Anton Hamrin.\n\nFörsäljn.-chef i Stockholm: disp. Allan\nHamrin.\n\n*\tKungsörs Sågverks AB., Kungsör.\n\nTillverkar sågade och hyvlade trävaror\nvid sågverk med hyvleri i Kungsör\n(Västmanl. l.). Bolaget driver även\nhandel med byggnadsmateriel.\n\nTelefon: »Sågbolaget». Postgiro: 266765.\n— Akt.-kap.: 70,000 kr. Antal\nindustriarb.: 21. Årsproduktion: 1,200 stds\nträvaror. — Bolaget grundat 1943.\n\nStyrelse: disp. George Andersson\n(ordf.), disp. Elis V. Ericsson,\nsågverks-äg. David Israelsson.\n\nDisponenter: George Andersson o. Elis\nV. Ericsson.\n\n*AB. Kungsörs Träförädling,\n\nKungsör.\n\nTillverkar dörrar och fönster samt\nköksinredningar vid fabrik i Kungsör\n(Västmanl. l.).\n\n447*\n\nTelefon: 182. Postgiro: 73468. —\nAkt.-kap.: 12,000 kr. Arb.-antal: 7.\nTillv.-värde pr år: 90,000 kr. — Firman etabl.\n1926, bolag 1927.\n\nStyrelse: fabr. Karl A. Lundgren\n(ordf.), fabr. Oarl O. Johansson, fabr.\nKarl Kvick, fabr. Arthur Lindholm, fabr.\nOskar Olsson.\n\nChefer: Karl A. Lundgren, Arthur\nLindholm o. Carl O. Johansson.\n\n\"Kungsörs Träindustri, Axel\nAndersson &amp; Co. AB., Kungsör.\n\nTräförädlingsfabrik i Kungsör\n(Västmanl. l.). Tillverkar som specialitet\ntvätt-klämmor samt trämjöl.\n\nTelegr.-adr.: Springpeg, Kungsör.\nTelefon: 38 o. 388. Postgiro: 13779. -\nAkt.-kap.: 75,000 kr. Antal industriarb.: 21.\nTillv.-värde pr år: 490,000 kr. — Firman\netabl. 1927.\n\nStyrelse o. verkst. dir.: disp. Tage\nAndersson.\n\n\"Kungälvs Glasbruks AB., Kungälv.\n\nSe AB. Surte Glasbruk, Surte.\n\n\"Kungälvs Kexfabrik, Kungälv.\n\nSe Göteborgs Kexfabriks AB., Kungälv.\n\n\"AB. Kungälvs Sko- &amp; Sportindustri,\n\nKungälv.\n\nTillverkar skodon.\n\nTelefon: 284. Ensamförsälj.: L.\nSterner &amp; Co., Göteborg, Korsg. 9, telefon:\n138466. — Akt.-kap.: 30,000 kr. Antal\nindustriarb.: 28. Tillv.-värde pr år:\n350,000 kr. — Bolaget grundat 1937.\n\nStyrelse: dir. Herbert Sterner (ordf.),\ndisp. Max Löwengart, fru C. Sterner.\n\nVerkst. dir.: Herbert Sterner\n(Göteborg).\n\n\"Kvarn AB. J. C. S., Norrköping.\n\nTillverkar mjöl, gryn, kli och gröpe\nvid elektr. kvarn å Djurön i Bråviken\n(Östergötl. l.).\n\nKontor: Norrköping. Telegr.-adr.:\nValskvarn, Norrköping. Telefon: »J. G.\nSwartz».\n\nAkt.-kap.: 2,400,000 kr. Antal\nindustriarb.: 65. Prod.-värde pr år: 10,000,000 kr.\n— Firman etabl. 1844, bolag 1914.\n\nStyrelse: greve G. Falkenberg (ordf.),\ndir. Daniel Arfwidsson, kapten Helmer\nLöfgreen, överstelöjtn. J. M. Palmaer.\n\nVerkst. dir.: Daniel Arfwidsson.\n\nKamrer: E. Runemark.\n\n",
    "structured": {
        "1": {
            "name": "Kungsskogens Sågverk",
            "location": "Ölme",
            "business": "Tillverkar sågade och hyvlade trävaror",
            "products": null,
            "contact": {
                "office": null,
                "phone": null,
                "postgiro": null,
                "head_office": null,
                "sales_offices": null,
                "telegraph": null,
                "factory_office": null,
                "factory_phone": null
            },
            "financials": {
                "capital": null,
                "employees": null,
                "annual_turnover": null,
                "annual_production_value": "3,000,000 kr"
            },
            "foundation_year": 1943,
            "current_name_year": null,
            "predecessor": null,
            "original_name": null,
            "corporation_year": null,
            "board": [
                {
                    "name": "disp. George Andersson",
                    "role": "ordf."
                },
                {
                    "name": "disp. Elis V. Ericsson",
                    "role": null
                },
                {
                    "name": "sågverks-äg. David Israelsson",
                    "role": null
                }
            ],
            "owners": null,
            "director": null,
            "managing_director": null,
            "sales_manager": null,
            "manager": null
        },
        "2": {
            "name": "Kungsörs Bleckkärlsfabrik",
            "location": "Kungsör",
            "business": "Tillverkar hushållskärl av aluminium- och bleckplåt",
            "products": "in-kokningsapparater, lackerade artiklar, gasmätare och stormlyktor samt utför på beställning alla slags arbeten i tunnplåt, pressade, svetsade och lackerade.",
            "contact": {
                "office": null,
                "phone": [
                    "Bleckkärl, Kungsör"
                ],
                "postgiro": "9231",
                "head_office": null,
                "sales_offices": [
                    {
                        "location": "Stockholm",
                        "phone": "674167"
                    }
                ],
                "telegraph": null,
                "factory_office": null,
                "factory_phone": null
            },
            "financials": {
                "capital": null,
                "employees": 250,
                "annual_turnover": null,
                "annual_production_value": "3,000,000 kr"
            },
            "foundation_year": 1897,
            "current_name_year": null,
            "predecessor": null,
            "original_name": null,
            "corporation_year": null,
            "board": [
                {
                    "name": "civiling. Arvid Hamrin",
                    "role": "ordf."
                },
                {
                    "name": "disp. Anton Hamrin",
                    "role": null
                }
            ],
            "owners": null,
            "director": null,
            "managing_director": null,
            "sales_manager": null,
            "manager": null
        },
        "3": {
            "name": "Kungsörs Sågverks AB.",
            "location": "Kungsör",
            "business": "Tillverkar sågade och hyvlade trävaror vid sågverk med hyvleri",
            "products": null,
            "contact": {
                "office": null,
                "phone": [
                    "Sågbolaget"
                ],
                "postgiro": "266765",
                "head_office": null,
                "sales_offices": null,
                "telegraph": null,
                "factory_office": null,
                "factory_phone": null
            },
            "financials": {
                "capital": "70,000 kr",
                "employees": 21,
                "annual_turnover": null,
                "annual_production_value": "1,200 stds trävaror"
            },
            "foundation_year": 1943,
            "current_name_year": null,
            "predecessor": null,
            "original_name": null,
            "corporation_year": null,
            "board": [
                {
                    "name": "disp. George Andersson",
                    "role": "ordf."
                },
                {
                    "name": "disp. Elis V. Ericsson",
                    "role": null
                },
                {
                    "name": "sågverks-äg. David Israelsson",
                    "role": null
                }
            ],
            "owners": null,
            "director": null,
            "managing_director": null,
            "sales_manager": null,
            "manager": null
        },
        "4": {
            "name": "Kungsörs Träförädling",
            "location": "Kungsör",
            "business": "Tillverkar dörrar och fönster samt köksinredningar",
            "products": null,
            "contact": {
                "office": null,
                "phone": [
                    "182"
                ],
                "postgiro": "73468",
                "head_office": null,
                "sales_offices": null,
                "telegraph": null,
                "factory_office": null,
                "factory_phone": null
            },
            "financials": {
                "capital": "12,000 kr",
                "employees": 7,
                "annual_turnover": null,
                "annual_production_value": "90,000 kr"
            },
            "foundation_year": 1926,
            "current_name_year": null,
            "predecessor": null,
            "original_name": null,
            "corporation_year": null,
            "board": [
                {
                    "name": "fabr. Karl A. Lundgren",
                    "role": "ordf."
                }
            ],
            "owners": null,
            "director": null,
            "managing_director": null,
            "sales_manager": null,
            "manager": null
        },
        "5": {
            "name": "Kungälvs Sko- & Sportindustri",
            "location": "Kungälv",
            "business": "Tillverkar skodon",
            "products": null,
            "contact": {
                "office": null,
                "phone": [
                    "284"
                ],
                "postgiro": null,
                "head_office": null,
                "sales_offices": [
                    {
                        "location": "Göteborg",
                        "phone": "138466"
                    }
                ],
                "telegraph": null,
                "factory_office": null,
                "factory_phone": null
            },
            "financials": {
                "capital": "30,000 kr",
                "employees": 28,
                "annual_turnover": null,
                "annual_production_value": "350,000 kr"
            },
            "foundation_year": 1937,
            "current_name_year": null,
            "predecessor": null,
            "original_name": null,
            "corporation_year": null,
            "board": [
                {
                    "name": "dir. Herbert Sterner",
                    "role": "ordf."
                },
                {
                    "name": "disp. Max Löwengart",
                    "role": null
                }
            ],
            "owners": null,
            "director": null,
            "managing_director": "Herbert Sterner",
            "sales_manager": null,
            "manager": null
        },
        "6": {
            "name": "Kvarn AB. J. C. S.",
            "location": "Norrköping",
            "business": "Tillverkar mjöl, gryn, kli och gröpe vid elektr. kvarn",
            "products": null,
            "contact": {
                "office": null,
                "phone": [
                    "«J. G. Swartz»"
                ],
                "postgiro": null,
                "head_office": null,
                "sales_offices": null,
                "telegraph": null,
                "factory_office": null,
                "factory_phone": null
            },
            "financials": {
                "capital": "2,400,000 kr",
                "employees": 65,
                "annual_turnover": null,
                "annual_production_value": "10,000,000 kr"
            },
            "foundation_year": 1914,
            "current_name_year": null,
            "predecessor": null,
            "original_name": null,
            "corporation_year": null,
            "board": [
                {
                    "name": "greve G. Falkenberg",
                    "role": "ordf."
                },
                {
                    "name": "dir. Daniel Arfwidsson",
                    "role": null
                }
            ],
            "owners": null,
            "director": null,
            "managing_director": null,
            "sales_manager": null,
            "manager": null
        }
    }
}