{
    "original": "Rior—R ockhammar\n\nTelefon: 48. Postgirö: 74403. Repr.:\nByggnadsmaterial AB. Törnell &amp; Co.,\nNorrköping, telefon: 20143.\n\nAntal industriarb.: 23. Årstillv.: 1,5\nmilj. st. tegelvaror. — Firman etabl.\n1929.\n\nÄgare o. chef: fabr. C. R. Lundin.\n\nRior, Maskin AB., Stockholm.\n\nSe Maskin AB. Rior, Stockholm.\n\n*AB. Risingsbo Ångbryggeri,\n\nM or gårdshammar.\n\nTillverkar maltdrycker vid bryggeri i\nMorgårdshammar (Kopparb. l.).\n\nTelefon: Smedjebacken 35. —\nAkt.-kap.: 100,000 kr. Arb.-antal: 12.\nTillv.-värde pr år: 300,000 kr. — Firman etabl.\n1856, bolag 1920.\n\nStyrelse: disp. Gunnar Westlund (ordf.),\nkamrer Emil Hultgren, fru Sigrid\nWest-lund.\n\nDisp.: Gunnar Westlund.\nRisängs Tegelbruk, Kinna.\n\nTillverkar murtegel, fasad- och\nrevete-ringstegel vid tegelbruk i Risäng, Kinna\n(Älvsb. l.).\n\nTelefon: 10434. — Antal arb.: 5.\nÅrstillv.: 0,4 milj. st. tegelvaror. — Firman\netabl. 1937.\n\nÄgare o. chef: fabr. Albert Peterson.\n\n*Robby, Konfektions AB., Borås.\n\nSe Konfektions AB. Robiby, Borås.\n\n*AB. Roberts, Örebro.\n\nEssensfabrik. Tillverkar aromer och\nex trakter för läskedrycks-, karamell- och\nkonfektfabrikation samt för bagerier och\nkonditorier, kräm- och glacemjöl,\nvanil-linsocker, jästmjöl, hushållsaromer m. m.\nBolaget driver även handel med kem.\nrena salter för mineralvattenfabrikation.\n\nTelegr.-adr.: Roberts, Örebro. Telefon:\n12156 o. 10556. Postgiro: 20744. —\nAkt.-kap.: 180,000 kr. Antal industriarb.: 15.\n— Bolaget grundat 1910.\n\nStyrelse: dir. Harry Roberts (ordf.),\ndisp. Lennart Roberts, fru Maria Roberts.\n\nVerkst. dir.: Harry Roberts.\n\nKontorschef: Henric Johanson.\n\n*ÄB. Robertsfors, Stockholm och\nHärnösand.\n\nSulfitfabrik, sulfitspritfabrik, mindre\nmek. verkstad och gjuteri samt elektr.\n\nkraftstationer i Robertsfors,\nhamnahlägg-ningar i Sikeå (båda i Väéterbött. l.).\nTillverkar sulfitcellulosä och sulfitsprit.\nBolaget idkar jämväl jordbruk och\nskogshantering.\n\nHuvudkontor: Stockholm, Strandvägen\n1 (okt.—maj), telefon: 601275 o. 601260;\nHärnösand (juni—sept.), telefon: 2122.\nTelegr.-adr.: Sethkempe, Stockholm o.\nHärnösand. Brukskontor: Robertsfors.\nFörsäljningen av cellulosa handhaves av\nAB. Nordsvenska Bruk, Stockholm,\nStrandvägen 1, telegr.-adr.: Nordmilis,\nStockholm, telefon: 670050.\n\nAkt.-kap.: 4,000,000 kr. Antal\nindustriarb.: 110. Årskapacitet: 30,000 ton torr\nsulfitcellulosa, 1,5 milj. liter 95 % sprit.\n\n—\tBolaget grundat 1899.\n\nStyrelse: generallöjtn. T. Friis (Ordf.),\nfil. dr Erik Kempe, civiling. Ragnar\nKempe.\n\nVerkst. dir.: Erik Kempe.\nShogschef: O. W. Zetterberg.\nIng. vid sulfitfabr.: I. Frölander.\n\n*AB. Davy Robertsons Maskinfabrik,\n\nGöteborg.\n\nMek. verkstad och gjuteri. Tillverkar\nkolvringar, kolv- och slidstångspackningar\nav gjutjärn samt gjutgods. Varumärke:\n»Daros».\n\nKontor: Stampg. 30. Telegr.-adr.:\nDaros, Göteborg. Telefon: 170085.\nPostgiro: 40480.\n\nAkt.-kap.: 600,000 kr. Antal\nindustriarb.: 250. Tillv.-värde pr år: 3,000^000 kr.\n\n—\tFabriken grundad 1851, bolag 1899.\nStyrelse: dir. S. Forster (ordf.), ing.\n\nRolf Sörman (v. ordf.), dir. Karl-Erik\nJacobson, t ing. Tage Mädsen, ing. H.\nSchalin.\n\nVerkst. dir.: Tage Madsen.\nFörsäljn.-chef: ing. H. Åberg.\nVerkstadschef: ing. Nils Ekstein.\n\n\"Rockhammars Bruks AB.,\n\nSällinge.\n\nTräsliperi, wallboardfabrik, sågverk och\nhyvleri vid Rockhammar, Sällinge\n(Örebro l.). Tillverkar mek. trämassa, porös\nwallboard samt sågade och hyvlade\nträvaror. Bolaget idkar jämväl jordbruk och\nskogshantering.\n\nKontor: Sällinge. Telegr.-adr.:\nRockhammar, Lindesberg. Telefon: Sällinge\n12 o. 14. Postgiro: 75910.\n\nAkt.-kap.: 750,000 kr. Antal\nindustriarb.: 100. Årstillv.: 30,000 ton våt vit\nmek. trämassa, varav 15,000 ton för eget\nbehov, 7,000 ton porös wallboard, 500 stds\nträvaror. — Bolaget grundat 1895.\n\nStyrelse: disp. Carl Persson (ordf.),",
    "structured": {
        "1": {
            "name": "Byggnadsmaterial AB. Törnell & Co.",
            "location": "Norrköping",
            "business": "Byggnadsmaterial",
            "contact": {
                "office": "N/A",
                "phone": [
                    "48"
                ],
                "postgiro": "74403",
                "head_office": "N/A",
                "sales_offices": [],
                "factory_office": "N/A",
                "factory_phone": "N/A"
            },
            "foundation_year": 1929,
            "owners": [],
            "director": "fabr. C. R. Lundin"
        },
        "2": {
            "name": "AB. Risingsbo Ångbryggeri",
            "location": "Morgårdshammar",
            "business": "Maltdrycker",
            "contact": {
                "office": "N/A",
                "phone": [
                    "Smedjebacken 35"
                ],
                "postgiro": "N/A",
                "head_office": "N/A",
                "sales_offices": [],
                "factory_office": "N/A",
                "factory_phone": "N/A"
            },
            "foundation_year": 1856,
            "owners": [
                "disp. Gunnar Westlund",
                "kamrer Emil Hultgren",
                "fru Sigrid Westlund"
            ],
            "director": "disp. Gunnar Westlund"
        },
        "3": {
            "name": "Risängs Tegelbruk",
            "location": "Kinna",
            "business": "Murtegel, fasad- och reverteringstegel",
            "contact": {
                "office": "N/A",
                "phone": [
                    "10434"
                ],
                "postgiro": "N/A",
                "head_office": "N/A",
                "sales_offices": [],
                "factory_office": "N/A",
                "factory_phone": "N/A"
            },
            "foundation_year": 1937,
            "owners": [
                "fabr. Albert Peterson"
            ],
            "director": "fabr. Albert Peterson"
        },
        "4": {
            "name": "AB. Roberts",
            "location": "Örebro",
            "business": "Essensfabrik, aromer och extrakter",
            "contact": {
                "office": "N/A",
                "phone": [
                    "12156",
                    "10556"
                ],
                "postgiro": "20744",
                "head_office": "N/A",
                "sales_offices": [],
                "factory_office": "N/A",
                "factory_phone": "N/A"
            },
            "foundation_year": 1910,
            "owners": [
                "dir. Harry Roberts",
                "disp. Lennart Roberts",
                "fru Maria Roberts"
            ],
            "director": "dir. Harry Roberts",
            "manager": "Henric Johanson"
        },
        "5": {
            "name": "ÄB. Robertsfors",
            "location": "Stockholm och Härnösand",
            "business": "Sulfitcellulosa och sulfitsprit",
            "contact": {
                "office": "N/A",
                "phone": [
                    "601275",
                    "601260",
                    "2122"
                ],
                "postgiro": "N/A",
                "head_office": "Strandvägen 1 (okt.—maj), Härnösand (juni—sept.)",
                "sales_offices": [],
                "factory_office": "Robertsfors",
                "factory_phone": "N/A"
            },
            "foundation_year": 1899,
            "owners": [
                "generallöjtn. T. Friis",
                "fil. dr Erik Kempe",
                "civiling. Ragnar Kempe"
            ],
            "director": "fil. dr Erik Kempe",
            "sales_manager": "O. W. Zetterberg",
            "manager": "I. Frölander"
        },
        "6": {
            "name": "AB. Davy Robertsons Maskinfabrik",
            "location": "Göteborg",
            "business": "Mek. verkstad och gjuteri",
            "contact": {
                "office": "Stampg. 30",
                "phone": [
                    "170085"
                ],
                "postgiro": "40480",
                "head_office": "N/A",
                "sales_offices": [],
                "factory_office": "N/A",
                "factory_phone": "N/A"
            },
            "foundation_year": 1899,
            "owner": [
                "dir. S. Forster",
                "ing. Rolf Sörman",
                "dir. Karl-Erik Jacobson",
                "t ing. Tage Mädsen",
                "ing. H. Schalin"
            ],
            "director": "ing. Rolf Sörman",
            "sales_manager": "ing. H. Åberg",
            "manager": "ing. Nils Ekstein"
        },
        "7": {
            "name": "Rockhammars Bruks AB.",
            "location": "Sällinge",
            "business": "Träsliperi, wallboardfabrik, sågverk och hyvleri",
            "contact": {
                "office": "N/A",
                "phone": [
                    "Sällinge 12",
                    "14"
                ],
                "postgiro": "75910",
                "head_office": "N/A",
                "sales_offices": [],
                "factory_office": "N/A",
                "factory_phone": "N/A"
            },
            "foundation_year": 1895,
            "owners": [
                "disp. Carl Persson"
            ],
            "director": "disp. Carl Persson"
        }
    }
}