{
    "original": "Brusafors—Bruzaholm\n\n*AB. Brusafors-Hällefors,\n\nSilverdalen.\n\nPappersbruk och träsliperi i Hällefors\n(Kalmar l.), sulfitfabrik i Brusafors,\nMariannelund (Jönköp. l.), sågverk och\nhyvleri (Skogstorps och Framnäs\nångsågar) samt träsliperi i Sävsjöström\n(Kronob. l.).\n\nTillverkar tryck-, skriv- och\nomslagspapper, mek. trämassa, sulfitcellulosa,\nsågade och hyvlade trävaror samt\nbyggnadssnickerier. Bolaget äger elektr.\nvattenkraftstationer vid Hällefors,\nSävsjöström och Emån samt driver jämväl\njord-och skogsbruk.\n\nHuvudkontor: Silverdalen.\nTelegr.-adr.: Hälleforsbruken, Hultsfred.\nTelefon: Hultsfred 110. Postgiro: 15115.\nAvd.-kontor: Mariannelund och\nSävsjöström.\n\nRepresentant i Stockholm: Svenskt\nPapper AB., Sveav. 98, telefon: 231120.\n\nAkt.-kap.: 5,000,000 kr. Antal\nindustriarb.: 480. Årstillv.: 8,000 ton\nsulfitcellulosa, 8,000 ton mek. trämassa, 17,000 ton\npapper, 1,000 stds sågade och hyvlade\nträvaror. — Bolaget grundat 1903.\n\nStyrelse: disp. Sven Esmarch, dir. Nils\nKläning, kamrer K. Wigander.\n\nVerTcst. dir.: vakant.\n\nAvd.-chefer: i Mariannelund: ing. H.\nKjellberg; i Sävsjöström: disp. Sven\nEsmarch; för pappersbruket i Hällefors:\ndir. Nils Kläning.\n\n*AB. Fredr. Brusewitz, Limmareds\nBruk, Limmar ed.\n\nGlasbruk med sliperi och glasmåleri\nsamt sågverk och hyvleri i Limmared\n(Älvsb. l.).\n\nTillverkar apoteks-, laboratorie- och\nmedicinskt glas, kemiskt- och tekniskt\nglas, mjölkflaskor m. m. samt sågade och\nhyvlade trävaror. Bolaget idkar jämväl\njordbruk och skogshantering.\n\nTelegr.-adr.: Brusewitz, Limmared.\nTelefon: Svenljunga 71002, 71013, 71026\no. 71041. Postgiro: 30160.\n\nAkt.-kap.: 460,500 kr. Antal\nindustriarb.: 300, varav vid glasbruket 285.\nTillv.-värde pr år: 2,700,000 kr. — Glasbruket\nanlagt 1740, bolaget grundat 1900.\n\nStyrelse: lektor Carl Munthe (ordf.),\nforstmäst. Henrik Munthe, kapten Walter\nH. Ohlsson, civiling. Gösta östlund.\n\nDisp.: Gösta östlund.\n\n*HugO Brusewitz AB., Göteborg.\n\nLitografiskt tryckeri, boktryckeri och\nkartongfabrik. Tillverkar som specialitet\n\netiketter, festmärken, litogr. emballage\nsamt utför reklamtryck. Firman driver\näven bokförlagsrörelse.\n\nKontor: Lasarettsg. 4—6. Telegr.-adr.:\nBrus, Göteborg. Telefon: »Esselte».\nPostgiro: 12386. Avd.-kontor: Stockholm,\nBrunnsg. 21 A, telefon: 109240—41. —\nFirman, som grundades år 1903, är\nansluten till Esseltes Göteborgsindustrier AB.\n\nStyrelse o. verkst. dir.: Nils J. Åhlund.\n\n*AB. Hugo Brusewitz Bleckvaru-\n\nfabrik, Göteborg.\n\nSe AB. Plåtmanufaktur,\nGöteborgsfabrikerna, Göteborg.\n\n*Hakon A. Bruun AB., Hallsberg.\n\nMössfabrik i Hallsberg (Örebro l.).\nTillverkar tygmössor samt tyg- och filthattar.\nFirman idkar även engroshandel med\nfilt- och stråhattar samt pälsvaror m. m.\n\nTelegr.-adr.: Hakon, Hallsberg.\nTelefon: 360 o. 560. Postgiro: 2688.\n\nAkt.-kap.: 150,700 kr. Antal\nindustriarb.: 35. Tillv.-värde pr år: 600,000 kr.\n— Firman etabl. 1886, bolag 1929.\n\nStyrelse: v. häradshövd. E. J.\nNathorst-Böös, dir. Charles W. Sande, konsul\nJohan Sande J:or.\n\nVerkst. dir.: Charles W. Sande.\n\n*AB. Bruzaholms Bruk,\n\nBruzaholm.\n\nMek. verkstad, gjuteri, pressnings- och\nsvetsningsverkstad, sågverk och elektr.\nvattenkraftstation vid Bruzaholm\n(Jönköp. l.).\n\nTillverkar plåtradiatorer,\nvärmeledningspannor, kokspisar, vädurar,\ngjut-gods samt diskmaskiner.\n\nTelegr.-adr.: Bruzabruk, Eksjö.\nTelefon: »Bruzaholms Bruk», Bruzaholm.\nPostgiro: 6836.\n\nRepresentanter: i Hälsingborg: Ernst\nBörjesson, telefon: 10251; i Göteborg:\nEd v. Eriksson, österlyckan 22, telefon:\nGöteborg 261167; i Stockholm: Zacco &amp;\nCo. Eftr., Dalag. 4, telefon: 106292.\n\nAkt.-kap.: 280,000 kr. Antal\nindustriarb.: 80. Tillv.-värde pr år: 1,000,000 kr.\n— Bruket grundlades 1630, nuv. firma\netabl. 1931, bolag 1937.\n\nStyrelse: disp. Gustaf Alm (ordf.),\ndisp. Erik Alm, ing. Holger Alm.\n\nDisp.: Gustaf Alm.\n\nDriftsing.: Holger Alm.",
    "structured": {
        "1": {
            "name": "AB. Brusafors-Hällefors",
            "location": "Silverdalen",
            "business": "Pappersbruk och träsliperi",
            "products": "tryck-, skriv- och omslagspapper, mek. trämassa, sulfitcellulosa, sågade och hyvlade trävaror samt byggnadssnickerier",
            "contact": {
                "office": "Silverdalen",
                "phone": [
                    "Hultsfred 110"
                ],
                "postgiro": "15115",
                "head_office": "Silverdalen",
                "sales_offices": [
                    {
                        "location": "Mariannelund",
                        "phone": "N/A"
                    },
                    {
                        "location": "Sävsjöström",
                        "phone": "N/A"
                    }
                ],
                "telegraph": "Hälleforsbruken, Hultsfred",
                "factory_office": "N/A",
                "factory_phone": "N/A"
            },
            "financials": {
                "capital": "5,000,000 kr",
                "employees": {
                    "industriarb.": 480
                },
                "annual_turnover": "N/A",
                "annual_production_value": "N/A"
            },
            "foundation_year": 1903,
            "board": [
                {
                    "name": "disp. Sven Esmarch",
                    "role": "N/A"
                },
                {
                    "name": "dir. Nils Kläning",
                    "role": "N/A"
                },
                {
                    "name": "kamrer K. Wigander",
                    "role": "N/A"
                }
            ]
        },
        "2": {
            "name": "AB. Fredr. Brusewitz",
            "location": "Limmareds Bruk, Limmar ed",
            "business": "Glasbruk med sliperi och glasmåleri samt sågverk och hyvleri",
            "products": "apoteks-, laboratorie- och medicinskt glas, kemiskt- och tekniskt glas, mjölkflaskor m. m.",
            "contact": {
                "telegraph": "Brusewitz, Limmared",
                "phone": [
                    "Svenljunga 71002",
                    "71013",
                    "71026",
                    "71041"
                ],
                "postgiro": "30160"
            },
            "financials": {
                "capital": "460,500 kr",
                "employees": {
                    "industriarb.": 300
                },
                "annual_turnover": "N/A",
                "annual_production_value": "2,700,000 kr"
            },
            "foundation_year": 1900,
            "board": [
                {
                    "name": "lektor Carl Munthe",
                    "role": "ordf."
                },
                {
                    "name": "forstmäst. Henrik Munthe",
                    "role": "N/A"
                },
                {
                    "name": "kapten Walter H. Ohlsson",
                    "role": "N/A"
                },
                {
                    "name": "civiling. Gösta östlund",
                    "role": "N/A"
                }
            ]
        },
        "3": {
            "name": "HugO Brusewitz AB.",
            "location": "Göteborg",
            "business": "Litografiskt tryckeri, boktryckeri och kartongfabrik",
            "products": "etiketter, festmärken, litogr. emballage samt utför reklamtryck",
            "contact": {
                "office": "Lasarettsg. 4—6",
                "phone": [
                    "N/A"
                ],
                "postgiro": "12386",
                "sales_offices": [
                    {
                        "location": "Stockholm",
                        "phone": "N/A"
                    }
                ],
                "telegraph": "Brus, Göteborg"
            },
            "foundation_year": 1903,
            "board": [
                {
                    "name": "Nils J. Åhlund",
                    "role": "verkst. dir."
                }
            ]
        },
        "4": {
            "name": "AB. Hugo Brusewitz Bleckvaru-fabrik",
            "location": "Göteborg",
            "business": "N/A",
            "contact": {
                "telegraph": "N/A",
                "phone": [
                    "N/A"
                ],
                "postgiro": "N/A"
            }
        },
        "5": {
            "name": "Hakon A. Bruun AB.",
            "location": "Hallsberg",
            "business": "Mössfabrik",
            "products": "tygmössor samt tyg- och filthattar, engroshandel med filt- och stråhattar samt pälsvaror m. m.",
            "contact": {
                "telegraph": "Hakon, Hallsberg",
                "phone": [
                    "360",
                    "560"
                ],
                "postgiro": "2688"
            },
            "financials": {
                "capital": "150,700 kr",
                "employees": {
                    "industriarb.": 35
                },
                "annual_turnover": "600,000 kr",
                "annual_production_value": "N/A"
            },
            "foundation_year": 1886,
            "board": [
                {
                    "name": "v. häradshövd. E. J. Nathorst-Böös",
                    "role": "N/A"
                },
                {
                    "name": "dir. Charles W. Sande",
                    "role": "N/A"
                },
                {
                    "name": "konsul Johan Sande J:or",
                    "role": "N/A"
                }
            ]
        },
        "6": {
            "name": "AB. Bruzaholms Bruk",
            "location": "Bruzaholm",
            "business": "Mek. verkstad, gjuteri, pressnings- och svetsningsverkstad, sågverk och elektr. vattenkraftstation",
            "products": "plåtradiatorer, värmeledningspannor, kokspisar, vädurar, gjut-gods samt diskmaskiner",
            "contact": {
                "telegraph": "Bruzabruk, Eksjö",
                "phone": [
                    "Bruzaholms Bruk",
                    "Bruzaholm"
                ],
                "postgiro": "6836"
            },
            "financials": {
                "capital": "280,000 kr",
                "employees": {
                    "industriarb.": 80
                },
                "annual_turnover": "N/A",
                "annual_production_value": "1,000,000 kr"
            },
            "foundation_year": 1931,
            "board": [
                {
                    "name": "disp. Gustaf Alm",
                    "role": "ordf."
                },
                {
                    "name": "disp. Erik Alm",
                    "role": "N/A"
                },
                {
                    "name": "ing. Holger Alm",
                    "role": "N/A"
                }
            ],
            "director": "N/A",
            "managing_director": "N/A",
            "sales_manager": "N/A",
            "manager": "N/A"
        }
    }
}