{
    "original": "Ljunggren—Ljungström\n\nLjunggren &amp; Co., Göteborg.\n\nMek. verkstad. Tillverkar pressade och\nsvarvade massartiklar, bl. a. för elektriska\nändamål samt pressverktyg.\n\nKontor: Artillerig. 29. Telefon: 159200.\nPostgiro: 45534. — Antal industriarb.:\n30. Tillv.-värde pr år: 400,000 kr. —\nFirman etabl. 1938.\n\nÄgare o. chef: Elof Rönnqvist.\n\nDisp.: Torsten Thonfors.\n\n*Ljunglids Snickeriverkstad,\n\nHyssna.\n\nTillverkar byggnadssnickerier och\nmöbler vid fabrik i Hyssna (Älvsb. l.).\nSpecialitet: fåtölj stommar.\n\nTelefon: Kinna 39025. Postgiro:\n275320. — Antal industriarb.: 5.\nTillv.-värde pr år: 30,000 kr. — Firman etabl.\n1943.\n\nÄgare o. chefer: snickarmäst. Karl\nKarlsson o. snickarmäst. Gunnar\nEriksson.\n\nLjunglöfs Litografiska AB.,\n\nStockholm.\n\nOffsettryckeri, kartongfabrik samt\nblecktryckeri. Utför offsettryck,\nreklamtrycksaker, tryck å celluloid och\nmetallplåt samt tillverkar bleckskyltar och\nkar-tonnage.\n\nKontor: Igeldammsg. 22. Telefon:\n520280. Postgiro: 156813.\n\nAkt.-kap.: 169,000 kr. Antal\nindustriarb.: 70. Tillv.-värde pr år: 900,000 kr.\n\n—\tFirman etabl. 1896, bolag 1931.\n\nStyrelse: kungl. boktryckare Simon\n\nSöderstam (ordf.), kand. Bengt\nSöderstam, disp. Gösta Söderstam.\n\nDisp.: Carl Björkland.\n\n*AB. Ljungmans Verkstäder, Malmö.\n\nMek. verkstad och gjuteri. Tillverkar\nmätare och apparater för förvaring och\ndistribution av eldfarliga oljor och\nsmörjoljor, hydrauliska billyftare,\nsmörjverktyg samt klaffpumpar.\n\nHuvudkontor: Malmö, Limhamnsvägen.\nTelegr.-adr.: Ljungmanis, Malmö.\nTelefon: »Ljungmans verkstäder». Postgiro:\n37610. Avd.-kontor: Stockholm,\nNybrokajen 7, telefon: 232035.\nUtställningslokal : Göteborg, Konserthuset.\n\nAkt.-kap.: 1,000,000 kr. Antal\nindustriarb.: 340. Tillv.-värde pr år: 5,000,000 kr.\n\n—\tBolaget grundat 1924.\n\nStyrelse o. verkst. dir.: Erik Eklund.\n\növering.: Ivar Eklund.\n\nInköpschef: Sam Rosén.\n\nLjungquist, Bröderna, Jönköping.\nSe Bröderna Ljungquist, Jönköping.\n\n*AB. Ljungqvists Tapetfabrik,\n\nNorrköping.\n\nTillverkar tapeter och bårder.\nTelefon: 21774 o. 22153. Postgiro: 8997.\n\n—\tAkt.-kap.: 125,000 kr. Antal\nindustriarb.: 40. — Bolaget grundat 1905,\nombildat 1924.\n\nStyrelse: disp. Einar Engblad, disp.\nKnut Pettersson, disp. Hans Rasmussen.\nVerkst. dir.: Einar Engblad.\n\n*J. F. Ljungqvist, Svensk Pälsskinns*\nberedning, Tranås.\n\nSe Svensk Pälsskinnsberedning, J. F.\nLjungqvist, Tranås.\n\n*AB. S. Ljungqvists Möbelfabrik,\n\nHabo.\n\nTillverkar möbler (speciellt bord) vid\nfabrik i Habo (Skarab. l.).\n\nTelefon: 93 o. 143. Postgiro: 91813.\n\n—\tAkt.-kap.: 75,000 kr. Antal\nindustriarb.: 35. Tillv.-värde pr år: 575,000 kr.\n\n—\tFirman etabl. 1926,_ bolag 1945.\nStyrelse o. verkst. dir.: Sigfrid\nLjungqvist.\n\n* Ljungströms Turbinfabrik,\n\nFinspång.\n\nSe Svenska Turbinfabriks AB.\nLjungström, Finspång.\n\nLjungströms i Göteborg Verkstads\n\nAB., Göteborg.\n\nMek. verkstäder i Göteborg och\nHäl-lingsjö, Härryda (Göteb. o. Bohus L).\nTillverkar mek. detaljer, verktyg och\ntillbehör för bilar samt vågar.\n\nKontor: Göteborg, Friggag. 12.\nTelefon: 156873. Postgiro: 42420. —\nAkt.-kap.: 10,000 kr. Antal industriarb.: 60,\nvarav i Göteborg 20. Tillv.-värde pr år:\n600,000 kr. — Firman etabl. 1931, bolag\n1939.\n\nStyrelse o. verkst. dir.: fabr. Hans\nLjungström.\n\nAB. Ljungströms Konfektionsfabrik,\n\nVingåker.\n\nTillverkar herrkläder vid fabriker i\nKatrineholm och Vingåker (Södermanl.\n1.). Varumärke: »Ljungströms Sir\nKläder».",
    "structured": {
        "firms": [
            {
                "name": "Ljunggren—Ljungström",
                "location": "Göteborg",
                "business": "Mek. verkstad",
                "products": "Tillverkar pressade och svarvade massartiklar, bl. a. för elektriska ändamål samt pressverktyg",
                "contact": {
                    "office": "Artillerig. 29",
                    "phone": [
                        "159200"
                    ],
                    "postgiro": "45534"
                },
                "financials": {
                    "capital": "N/A",
                    "employees": {
                        "industriarb": 30
                    },
                    "annual_turnover": "400,000 kr",
                    "annual_production_value": "N/A"
                },
                "foundation_year": 1938,
                "owner": "Elof Rönnqvist",
                "director": "N/A",
                "managing_director": "N/A",
                "sales_manager": "N/A",
                "manager": "N/A"
            },
            {
                "name": "Ljunglids Snickeriverkstad",
                "location": "Hyssna",
                "business": "Tillverkar byggnadssnickerier och möbler",
                "products": "Specialitet: fåtölj stommar",
                "contact": {
                    "phone": [
                        "Kinna 39025"
                    ],
                    "postgiro": "275320"
                },
                "financials": {
                    "capital": "N/A",
                    "employees": {
                        "industriarb": 5
                    },
                    "annual_turnover": "30,000 kr",
                    "annual_production_value": "N/A"
                },
                "foundation_year": 1943,
                "owners": [
                    "snickarmäst. Karl Karlsson",
                    "snickarmäst. Gunnar Eriksson"
                ],
                "director": "N/A",
                "managing_director": "N/A",
                "sales_manager": "N/A",
                "manager": "N/A"
            },
            {
                "name": "Ljunglöfs Litografiska AB.",
                "location": "Stockholm",
                "business": "Offsettryckeri, kartongfabrik samt blecktryckeri",
                "products": "Utför offsettryck, reklamtrycksaker, tryck å celluloid och metallplåt samt tillverkar bleckskyltar och kar-tonnage.",
                "contact": {
                    "office": "Igeldammsg. 22",
                    "phone": [
                        "520280"
                    ],
                    "postgiro": "156813"
                },
                "financials": {
                    "capital": "169,000 kr",
                    "employees": {
                        "industriarb": 70
                    },
                    "annual_turnover": "900,000 kr",
                    "annual_production_value": "N/A"
                },
                "foundation_year": 1896,
                "corporation_year": 1931,
                "board": [
                    {
                        "name": "kungl. boktryckare Simon Söderstam",
                        "role": "ordf."
                    },
                    {
                        "name": "kand. Bengt Söderstam",
                        "role": "N/A"
                    },
                    {
                        "name": "disp. Gösta Söderstam",
                        "role": "N/A"
                    }
                ],
                "director": "N/A",
                "managing_director": "N/A",
                "sales_manager": "N/A",
                "manager": "N/A"
            },
            {
                "name": "AB. Ljungmans Verkstäder",
                "location": "Malmö",
                "business": "Mek. verkstad och gjuteri",
                "products": "Tillverkar mätare och apparater för förvaring och distribution av eldfarliga oljor och smörjoljor, hydrauliska billyftare, smörjverktyg samt klaffpumpar",
                "contact": {
                    "office": "Malmö, Limhamnsvägen",
                    "phone": [
                        "N/A"
                    ],
                    "postgiro": "37610",
                    "sales_offices": [
                        {
                            "location": "Stockholm",
                            "phone": "232035"
                        }
                    ]
                },
                "financials": {
                    "capital": "1,000,000 kr",
                    "employees": {
                        "industriarb": 340
                    },
                    "annual_turnover": "5,000,000 kr",
                    "annual_production_value": "N/A"
                },
                "foundation_year": 1924,
                "owner": "N/A",
                "director": "N/A",
                "managing_director": "N/A",
                "sales_manager": "N/A",
                "manager": "N/A"
            },
            {
                "name": "AB. Ljungqvists Tapetfabrik",
                "location": "Norrköping",
                "business": "Tillverkar tapeter och bårder",
                "contact": {
                    "phone": [
                        "21774",
                        "22153"
                    ],
                    "postgiro": "8997"
                },
                "financials": {
                    "capital": "125,000 kr",
                    "employees": {
                        "industriarb": 40
                    },
                    "annual_turnover": "N/A",
                    "annual_production_value": "N/A"
                },
                "foundation_year": 1905,
                "corporation_year": 1924,
                "board": [
                    {
                        "name": "disp. Einar Engblad",
                        "role": "N/A"
                    },
                    {
                        "name": "disp. Knut Pettersson",
                        "role": "N/A"
                    },
                    {
                        "name": "disp. Hans Rasmussen",
                        "role": "N/A"
                    }
                ],
                "director": "Einar Engblad",
                "managing_director": "Einar Engblad",
                "sales_manager": "N/A",
                "manager": "N/A"
            },
            {
                "name": "AB. S. Ljungqvists Möbelfabrik",
                "location": "Habo",
                "business": "Tillverkar möbler",
                "products": "Speciellt bord",
                "contact": {
                    "phone": [
                        "93",
                        "143"
                    ],
                    "postgiro": "91813"
                },
                "financials": {
                    "capital": "75,000 kr",
                    "employees": {
                        "industriarb": 35
                    },
                    "annual_turnover": "575,000 kr",
                    "annual_production_value": "N/A"
                },
                "foundation_year": 1926,
                "corporation_year": 1945,
                "board": [],
                "director": "N/A",
                "managing_director": "Sigfrid Ljungqvist",
                "sales_manager": "N/A",
                "manager": "N/A"
            },
            {
                "name": "Ljungströms i Göteborg Verkstads AB",
                "location": "Göteborg",
                "business": "Mek. verkstäder",
                "products": "Tillverkar mek. detaljer, verktyg och tillbehör för bilar samt vågar",
                "contact": {
                    "office": "Göteborg, Friggag. 12",
                    "phone": [
                        "156873"
                    ],
                    "postgiro": "42420"
                },
                "financials": {
                    "capital": "10,000 kr",
                    "employees": {
                        "industriarb": 60
                    },
                    "annual_turnover": "600,000 kr",
                    "annual_production_value": "N/A"
                },
                "foundation_year": 1931,
                "corporation_year": 1939,
                "board": [],
                "director": "N/A",
                "managing_director": "fabr. Hans Ljungström",
                "sales_manager": "N/A",
                "manager": "N/A"
            },
            {
                "name": "AB. Ljungströms Konfektionsfabrik",
                "location": "Vingåker",
                "business": "Tillverkar herrkläder",
                "products": "Varumärke: »Ljungströms Sir Kläder»",
                "contact": {
                    "phone": [
                        "N/A"
                    ],
                    "postgiro": "N/A"
                },
                "financials": {
                    "capital": "N/A",
                    "employees": {
                        "industriarb": 0
                    },
                    "annual_turnover": "N/A",
                    "annual_production_value": "N/A"
                },
                "foundation_year": "N/A",
                "board": [],
                "director": "N/A",
                "managing_director": "N/A",
                "sales_manager": "N/A",
                "manager": "N/A"
            }
        ]
    }
}