{
    "original": "Rummens—By d\n\nadr.: Rulles. Stockholm. Telefon: 314747\no. 314749. Postgiro: 3046. Repr. för\nGöteborg o. Malmö: Kurt Eckerström AB.,\nGöteborg, Köpmansg. 40, telefon: 172975.\n\nAkt.-kap.: 103.000 kr. Arb.-antal: 10.\n— Firman etabL 1908, bolag 1920.\n\nStyrelse: fru C. Engström (ordf.), disp.\nC. G. Jäderblom.\n\nDisp.: C. G. Jäderblom.\n\nAB. Rummens Möbelindustri,\n\nGamléby.\n\nTillverkar kontors- och bostadsmöbler,\nbank- och affärsinredningar vid\nmöbelfabrik i Gamlehy (Kalmar l.).\n\nTelefon: 259 C. — Akt.-kap.: 40,100 kr.\nAntal industriarb.: 20. Tillv.-värde pr år:\n200,000 kr. — Bolaget grundat 1937.\n\nVerkst. dir. o. disp.: Gunnar Tydén.\n\nRuna, Skofabriks AB., Örebro.\n\nSe Skofabriks AB. Runa, Örebro.\n\n*Karl Rundgren, Borås.\n\nVäveri. Tillverkar överkast,\ndraperity-ger och gardiner samt borddukar.\n\nTelefon: 12265. Postgiro: 36066. —\nAntal industriarb;: 301 Tillv.-Värde pr år:\n900,000 kr. — Firman etabl. 1927.\n\nÄgare o. chefer: fabr. Erik Rundgren\no. fabr. Karl Rundgren.\n\nFörsäljn.-chef: Otto Linder.\n\n*Edvin Rundlöf, Stockholm,\n\nByggnadsentreprenörfirma för\nbostads-och affärshus, industribyggnader m. m.\n\nKontor: Triewaldsgränd 2. Telefon:\n116852 o. 205365. Postgiro: 57813. —\nFirman etabl. 1929.\n\nÄgare o. chef: byggm. EiJvin Ruiidlöf.\n\n* Rundviks Ångsåg, Lögdeå.\n\nSe Nördmalings Ångsågs AB.,\nNordmaling. :\n\nRunemo Sågverks AB., Bunemo.\n\nSågverk och hyvleri i Runemo (Gävleb.\nL). Tillverkar sågade och hyvlade\nträvaror.\n\nTelegr.-adr.: Runemosåg, Bollnäs.\nTelefon: Alf ta 4.\n\nAkt.-kap.: 234,250 kr. Autftl\nincju^tri-arb.: 75. Årstillv.: 3,500 stds sågade o.\nhyvlade trävaror. — Bolaget, grundat\n1900, äges av AB. Iggesunds Bruk.\n\nStyrelse: dir. Carl Trygger (ordf.), dr\nGunnar Sundblad, jur. kand. Hans\nWest-berg, skogschef Rolf Ålund.\n\nVerJcst. dir.: Gunnar Sundblad.\n\n*Rurik, Fabriken, Karlshamn.\n\nSe Fabriken Rurik, Karlshamn,\n\n*Nils Ruthérs Möbelfabrik, Nässjö.\n\nTillverkar komoletteringsmöbler Vid\nfabrik i Nässjö (Jönköp. l.).\n\nTelefon: 997. Postgiro: 164652. -^\nAntal industriarb.: 16. Tillv.-värde pr. år:\n180,000 kr. — Firman etabl. 1937 Hinder\nnamn Husinredningar, nuv. namn 1,945.\n\nÄgare o. chef: fabr. Nils Ruthér- , V\n\nAB. RuteverkenSlite.\n\nTillverkar trottoarplattor,\nbyggnadsmaterial av lättbetong (»Siporex»)r samt\nkalkstensmjöl vid fabrik i Rute (GofcL l.).\n\nHuvudkontor: Slite. Telefon:\n»Slitecement» . Försäljningskontor: Stockholm,\nNorrlandsg. 7—9, telefon: 234780.\nPostgiro: 37503. Telegr.-adresser:\nRutéver-ken, Stockholm och Slite.\n\nAkt.-kap.: 500,000 kr. Antal\nindustriarb.: 90. Tillv.-värde pr år: 1,200,000 kr.\n\nBolaget grundat 1933 efter övertagande\nav en del av den tidigare vid f. d.\nVallevikens Cementfabrik bedrivna rörelsen.\n\nStyrelse: dir. Ernst Wehtje (ordf.),\ndir. Arendt de Jounge, dir. Malte Ström.\n\nVerkst. dir.: Arendt de Jounge.\n\nAB. Ruuthsbo Konservfabriker,\n\nYstad,\n\nTillverkar konserver av ärter, sparris,\nchampinjoner, frukt m. m. Bolaget har\negna grönsaksodlingar.\n\nTelegr.-adr.: Ark, Ystad. Telefon: 948.\nPostgiro: 12962. Representanter: i\nStockholm: Herbert Bjursten, Roslagsg. 29,\ntelefon: 318794; i : Göteborg:- öftvid\nThorsson. Kristinehöjdsg. 9, telefon:\n181268. ’\n\nAkt.-kap.: 177,000 kr. Antal\nindustriarb. : 30. Tillv.-värde pr år: 650,000-kr.\n— Firman etabl. 1918. bolag 1921. &gt;’•.;\n\nStyrelse: grossh. Oscar Möller, disp.\nBror Tibell, disp. S.-Å. Åkeson.\n\nVerkst. dir. o. disp.: Bror Tibellv\n\nKamrer: J. G. Malmborg.\n\nRyd, Rydh.\n\nRydhs Fabriks AB., Virserum.\n\nMek. verkstad i Virserum (Kalmar l.).\nTillverkar semitrailer, släpvagnar,\nbog-gieaxlar för lastbilar, släpvagns- och\nhäst-vagnsaxlar samt plåthjul och\npressnings-arbeten.\n\nTelefon: »Rydhs AB.». Postgiro:\n164717. — Akt.-kap.: 40,000 kr. Antal",
    "structured": {
        "1": {
            "name": "Rummens Möbelindustri",
            "location": "Gamléby",
            "business": "Tillverkar kontors- och bostadsmöbler, bank- och affärsinredningar vid möbelfabrik i Gamleby (Kalmar l.)",
            "contact": {
                "office": "Gamléby",
                "phone": [
                    "259 C"
                ],
                "postgiro": "3046"
            },
            "financials": {
                "capital": "103.000 kr",
                "employees": {
                    "total": 10
                },
                "annual_production_value": "200,000 kr"
            },
            "foundation_year": 1908,
            "corporation_year": 1920,
            "board": [
                {
                    "name": "fru C. Engström",
                    "role": "ordförande"
                },
                {
                    "name": "C. G. Jäderblom",
                    "role": "disp."
                }
            ]
        },
        "2": {
            "name": "Runa, Skofabriks AB.",
            "location": "Örebro",
            "business": "Se Skofabriks AB. Runa, Örebro"
        },
        "3": {
            "name": "Karl Rundgren",
            "location": "Borås",
            "business": "Väveri. Tillverkar överkast, draperityger och gardiner samt borddukar"
        },
        "4": {
            "name": "Edvin Rundlöf",
            "location": "Stockholm",
            "business": "Byggnadsentreprenörfirma för bostads-och affärshus, industribyggnader m.m.",
            "contact": {
                "office": "Triewaldsgränd 2",
                "phone": [
                    "116852",
                    "205365"
                ],
                "postgiro": "57813"
            },
            "foundation_year": 1929,
            "owner": "byggm. Edvin Rundlöf"
        },
        "5": {
            "name": "Rundviks Ångsåg",
            "location": "Lögdeå",
            "business": "Se Nördmalings Ångsågs AB., Nordmaling."
        },
        "6": {
            "name": "Runemo Sågverks AB.",
            "location": "Bunemo",
            "business": "Sågverk och hyvleri i Runemo (Gävleb. L). Tillverkar sågade och hyvlade trävaror",
            "contact": {
                "telegraph": "Runemosåg, Bollnäs",
                "phone": "Alfta 4"
            },
            "financials": {
                "capital": "234,250 kr",
                "employees": {
                    "total": 75
                },
                "annual_turnover": "3,500 stds sågade och hyvlade trävaror",
                "corporation_year": 1900
            },
            "board": [
                {
                    "name": "dir. Carl Trygger",
                    "role": "ordf."
                },
                {
                    "name": "dr Gunnar Sundblad",
                    "role": null
                },
                {
                    "name": "jur. kand. Hans Westberg",
                    "role": null
                },
                {
                    "name": "skogschef Rolf Ålund",
                    "role": null
                }
            ],
            "managing_director": "Gunnar Sundblad"
        },
        "7": {
            "name": "Fabriken Rurik",
            "location": "Karlshamn"
        },
        "8": {
            "name": "Nils Ruthérs Möbelfabrik",
            "location": "Nässjö",
            "business": "Tillverkar kompletteringsmöbler vid fabrik i Nässjö (Jönköp. l.)",
            "contact": {
                "phone": "997",
                "postgiro": "164652"
            },
            "financials": {
                "employees": {
                    "total": 16
                },
                "annual_production_value": "180,000 kr"
            },
            "foundation_year": 1937,
            "original_name": "Husinredningar",
            "current_name_year": 1945,
            "owner": "fabr. Nils Ruthér"
        },
        "9": {
            "name": "AB. Ruteverken",
            "location": "Slite",
            "business": "Tillverkar trottoarplattor, byggnadsmaterial av lättbetong (»Siporex»), samt kalkstensmjöl vid fabrik i Rute (GofcL l.)",
            "contact": {
                "head_office": "Slite",
                "phone": "Slitecement",
                "sales_offices": [
                    {
                        "location": "Stockholm",
                        "phone": "234780"
                    }
                ],
                "postgiro": "37503"
            },
            "financials": {
                "capital": "500,000 kr",
                "employees": {
                    "total": 90
                },
                "annual_production_value": "1,200,000 kr"
            },
            "foundation_year": 1933,
            "predecessor": "Vallevikens Cementfabrik",
            "board": [
                {
                    "name": "dir. Ernst Wehtje",
                    "role": "ordf."
                },
                {
                    "name": "dir. Arendt de Jounge",
                    "role": null
                },
                {
                    "name": "dir. Malte Ström",
                    "role": null
                }
            ],
            "managing_director": "Arendt de Jounge"
        },
        "10": {
            "name": "AB. Ruuthsbo Konservfabriker",
            "location": "Ystad",
            "business": "Tillverkar konserver av ärter, sparris, champinjoner, frukt m.m. Bolaget har egna grönsaksodlingar",
            "contact": {
                "telegraph": "Ark, Ystad",
                "phone": "948",
                "postgiro": "12962"
            },
            "financials": {
                "capital": "177,000 kr",
                "employees": {
                    "total": 30
                },
                "annual_production_value": "650,000 kr"
            },
            "foundation_year": 1918,
            "corporation_year": 1921,
            "board": [
                {
                    "name": "grossh. Oscar Möller",
                    "role": null
                },
                {
                    "name": "disp. Bror Tibell",
                    "role": null
                },
                {
                    "name": "disp. S.-Å. Åkeson",
                    "role": null
                }
            ],
            "managing_director": "Bror Tibell",
            "sales_manager": "Otto Linder"
        },
        "11": {
            "name": "Rydhs Fabriks AB.",
            "location": "Virserum",
            "business": "Mek. verkstad i Virserum (Kalmar l.). Tillverkar semitrailer, släpvagnar, boggieaxlar för lastbilar, släpvagns- och hästvagnsaxlar samt plåthjul och pressningsarbeten",
            "contact": {
                "phone": "Rydhs AB.",
                "postgiro": "164717"
            },
            "financials": {
                "capital": "40,000 kr"
            }
        }
    }
}