{
    "original": "Carl—Carlsson\n\nCarl, AB. Fabriken, Malmö.\n\nSe AB. Fabriken Carl, Malmö.\nCarlanders Väveri, Skiätorp.\n\nTillverkar handvävda mattor vid väveri\ni Skultorp (Skarab. l.). Telefon: 74.\nPostgiro: 166091. — Antal arb.: 13.\nTillv.-varde pr år: 100,000 kr. — Firman etabl.\n1935.,\n\nÄgare o. chefer: fabr. Carl-David\nCar-lander o. fröken Rakel Carlander.\n\n*Carlfors AB., Huskvarna.\n\nFärgfabrik vid Karlfors, Huskvarna.\nTillverkar torra aluminiumfärger och\nbronspulver för målning, för litografiskt\ntryck, för offset- och tapettryck m. m.,\naluminiumpulver för gasbetong och\npyro-tekniska ändamål, ävensom\naluminium-griess och atomiserat aluminiumpulver\nför termit, värmekompresser och\nmetallurgisk^ ändamål m. m. Bolaget driver\njämväl jordbruk.\n\nTelegr.-adr.: Carlfors, Huskvarna.\nTelefon: 22 o. 255. Postgiro: 51051.\n\nAkt.-kap.: 90,000 kr. Antal\nindustriarb.: 30. Tillv.-värde pr år: 1,500,000 kr.\n— Firman etabl. 1874, bolag 1898.\n\nStyrelse: dir. G. Eckerbom (ordf.),\nfru E. Björklund, kammarrättsrådet Kurt\nBjörklund.\n\nVerkst. dir.: fru E. Björklund.\n\nFörsäljn^chef: kamrer Nils Lindquist.\n\nDriftsing.: Gustaf Winqvist.\n\n*AB. P. A. Carlmark, Älvängen.\n\nSisalspinneri, repslageri och\nbindgarns-fabrik i Älvängen (Älvsb. l.). Tillverkar\ntågvirke, skördegarn, bindgarn,\nrepslageri-varor, sadelgjordsväv, sisalmattor,\npappersgarn m. m.\n\nTelegr.-adr.: Carlmark, Göteborg.\nTelefon: »PA Carlmark», Älvängen. Postgiro:\n70134.\n\nAvd.-kontor: Stockholm: Packhusgränd\n6, telefon: 105381 o. 106381; Malmö: N.\nLånggatan 1, telefon: 25286.\n\nAkt.-kap.: 600,000 kr. Antal\nindustriarb.: 250. — Firman etabl. 1848 i Åmål,\nflyttade 1918 till Älvängen vid Göta älv,\nbolag 1932.\n\nStyrelse: fru Anneliese Carlmark, fru\nIngeborg Carlmark, kontorschef Nils\nCarlmark, disp. Per Carlmark.\n\nDisp.: Per Carlmark.\n\nDriftsing.: Kurt Israel.\n\n*P. H. Carlséns Söner, Stolfabrik,\n\nSkirö.\n\nTillverkar sargstolar och stilstolar vid\nfabrik i Skirö (Jönköp. l.).\n\nTelefon: Skirö 36. Järnvägsadr.:\nÄdel-fors. — Antal industriarb.: 15.\nTillv.-värde pr år: 90,000 kr. — Firman etabl.\n1903, nuv. namn 1945.\n\nÄgare: fabr. Lennart Carlsén, fabr. Olof\nCarlsén, maskinsnickare Herbert Carlsén,\nbildhuggare Arne Carlsén o. stud. Hans\nCarlsén.\n\nChef: Lennart Carlsén.\n\n*Carlshamns Bryggeri AB.,\n\nKarlshamn.\n\nBryggeri och läskedrycksfabrik\n(Källans vattenfabrik). Tillverkar\nmaltdrycker, mineralvatten och läskedrycker.\n\nTelegr.-adr.: Bryggeribolaget,\nKarlshamn. Telefon: 33 o. 304. Postgiro:\n170598. — Akt.-kap.: 194,200 kr. Antal\nindustriarb.: 32. — Bolaget, grundat 1883,\näger AB. Kalmar Miner al vattenfabrik.\n\nStyrelse: dir. Harald Engström (ordf.),\ndisp. K. A. Hagen, disp. Inge Sjövall.\n\nDisp.: Inge Sjövall.\n\nKontorschef: Hildur Olsson.\n\nBryggmäst.: Harald Andersson.\n\nCarlshamns Mek. Stensliperi,\n\nKarlshamn.\n\nStenhuggeri och -sliperi i Karlshamn,\nstenbrott i Kyrkhult (Blekinge l.).\nTillverkar alla slags granitarbeten.\nSpecialiteter: gravvårdar samt sågad och slipad\nbyggnadssten.\n\nTelegr.-adr.: Stensliperiet, Karlshamn.\nTelefon: 281. Postgiro: 81566. — Antal\nindustriarb.: 30. — Firman etabl. 1897.\n\nÄgare o. chef: fabr. Hugo Nilsson.\n\nSe även Karlshamn.\n\nCarlson, Carlsson.\n\nCarlsson &amp; Anderssons AB.,\nBröderna, Eskilstuna.\n\nSe Bröderna Carlsson &amp; Anderssons\nAB., Eskilstuna.\n\n*Carlsson, Carlqvist &amp; C:o, Buda.\n\nMöbelfabrik i Ruda (Kalm. l.).\nTillverkar stolar och fåtöljer.\n\nTelefon: 10 o. 23. Postgiro: 23752. —\nAntal industriarb.: 18. Tillv.-värde pr år:\n140.000 kr. — Firman etabl. 1923.\n\nÄgare: fabr. G. Emanuel Carlsson,\nfabr. K. Axel J. Karlqvist, fabr. Carl A.\nCarlqvist, fabr. Axel E. Sundqvist,\n\nDisp.: G. Em. Carlsson.\n\n92*",
    "structured": {
        "1": {
            "name": "Carl AB. Fabriken",
            "location": "Malmö",
            "business": "Tillverkar handvävda mattor vid väveri i Skultorp (Skarab. l.)",
            "contact": {
                "office": "AB. Fabriken Carl, Malmö",
                "phone": [
                    "74"
                ],
                "postgiro": "166091",
                "factory_office": "Fabrik",
                "factory_phone": "Skultorp (Skarab. l.)"
            },
            "financials": {
                "capital": "Okänt",
                "employees": {
                    "Antal arb.": 13
                },
                "annual_turnover": "100,000 kr",
                "annual_production_value": "Okänt"
            },
            "foundation_year": 1935,
            "owners": [
                "fabr. Carl-David Carlander",
                "fröken Rakel Carlander"
            ]
        },
        "2": {
            "name": "Carlfors AB.",
            "location": "Huskvarna",
            "business": "Färgfabrik vid Karlfors, Huskvarna",
            "products": "Tillverkar torra aluminiumfärger och bronspulver för målning, för litografiskt tryck, för offset- och tapettryck m. m.",
            "contact": {
                "telegraph": "Carlfors, Huskvarna",
                "phone": [
                    "22",
                    "255"
                ],
                "postgiro": "51051"
            },
            "financials": {
                "capital": "90,000 kr",
                "employees": {
                    "industriarb.": 30
                },
                "annual_turnover": "1,500,000 kr",
                "annual_production_value": "Okänt"
            },
            "foundation_year": 1874,
            "corporation_year": 1898,
            "board": [
                {
                    "name": "dir. G. Eckerbom",
                    "role": "ordf."
                },
                {
                    "name": "fru E. Björklund",
                    "role": "Okänt"
                },
                {
                    "name": "kammarrättsrådet Kurt Björklund",
                    "role": "Okänt"
                }
            ],
            "owners": [
                "Okänt"
            ],
            "director": "Okänt",
            "managing_director": "fru E. Björklund",
            "sales_manager": "kamrer Nils Lindquist",
            "manager": "Gustaf Winqvist"
        },
        "3": {
            "name": "AB. P. A. Carlmark",
            "location": "Älvängen",
            "business": "Sisalspinneri, repslageri och bindgarns-fabrik i Älvängen (Älvsb. l.)",
            "products": "Tillverkar tågvirke, skördegarn, bindgarn, repslageri-varor, sadelgjordsväv, sisalmattor, pappersgarn m. m.",
            "contact": {
                "office": "Stockholm: Packhusgränd 6, telefon: 105381 o. 106381; Malmö: N. Långgatan 1, telefon: 25286",
                "telegraph": "Carlmark, Göteborg",
                "phone": [
                    "Okänt"
                ],
                "postgiro": "70134"
            },
            "financials": {
                "capital": "600,000 kr",
                "employees": {
                    "industriarb.": 250
                },
                "annual_turnover": "Okänt",
                "annual_production_value": "Okänt"
            },
            "foundation_year": 1848,
            "corporation_year": 1932,
            "owners": [
                "fru Anneliese Carlmark",
                "fru Ingeborg Carlmark",
                "kontorschef Nils Carlmark",
                "disp. Per Carlmark"
            ],
            "director": "Okänt",
            "managing_director": "Okänt",
            "sales_manager": "Okänt"
        },
        "4": {
            "name": "P. H. Carlséns Söner",
            "location": "Skirö",
            "business": "Tillverkar sargstolar och stilstolar vid fabrik i Skirö (Jönköp. l.)",
            "contact": {
                "phone": [
                    "Skirö 36"
                ],
                "postgiro": "Okänt"
            },
            "financials": {
                "capital": "Okänt",
                "employees": {
                    "Antal industriarb.": 15
                },
                "annual_turnover": "90,000 kr",
                "annual_production_value": "Okänt"
            },
            "foundation_year": 1903,
            "original_name": "Okänt",
            "predecessor": "Okänt",
            "owners": [
                "fabr. Lennart Carlsén",
                "fabr. Olof Carlsén",
                "maskinsnickare Herbert Carlsén",
                "bildhuggare Arne Carlsén",
                "stud. Hans Carlsén"
            ],
            "manager": "Lennart Carlsén"
        },
        "5": {
            "name": "Carlshamns Bryggeri AB.",
            "location": "Karlshamn",
            "business": "Bryggeri och läskedrycksfabrik",
            "products": "Tillverkar maltdrycker, mineralvatten och läskedrycker",
            "contact": {
                "telegraph": "Bryggeribolaget, Karlshamn",
                "phone": [
                    "33",
                    "304"
                ],
                "postgiro": "170598"
            },
            "financials": {
                "capital": "194,200 kr",
                "employees": {
                    "industriarb.": 32
                },
                "annual_turnover": "Okänt",
                "annual_production_value": "Okänt"
            },
            "foundation_year": 1883,
            "corporation_year": "Okänt",
            "owners": [
                "Okänt"
            ],
            "director": "dir. Harald Engström",
            "managing_director": "Okänt",
            "sales_manager": "Okänt",
            "manager": "Okänt"
        },
        "6": {
            "name": "Carlshamns Mek. Stensliperi",
            "location": "Karlshamn",
            "business": "Stenhuggeri och -sliperi",
            "products": "Tillverkar alla slags granitarbeten",
            "specialities": "Specialiteter: gravvårdar samt sågad och slipad byggnadssten",
            "contact": {
                "telegraph": "Stensliperiet, Karlshamn",
                "phone": [
                    "281"
                ],
                "postgiro": "81566"
            },
            "financials": {
                "capital": "Okänt",
                "employees": {
                    "industriarb.": 30
                },
                "annual_turnover": "Okänt",
                "annual_production_value": "Okänt"
            },
            "foundation_year": 1897,
            "owners": [
                "fabr. Hugo Nilsson"
            ],
            "manager": "fabr. Hugo Nilsson"
        },
        "7": {
            "name": "Carlsson AB. Bröderna",
            "location": "Eskilstuna",
            "business": "Se Bröderna Carlsson & Anderssons AB., Eskilstuna"
        },
        "8": {
            "name": "Carlsson, Carlqvist & C:o",
            "location": "Buda",
            "business": "Möbelfabrik i Ruda (Kalm. l.)",
            "products": "Tillverkar stolar och fåtöljer",
            "contact": {
                "phone": [
                    "10",
                    "23"
                ],
                "postgiro": "23752"
            },
            "financials": {
                "capital": "Okänt",
                "employees": {
                    "Antal industriarb.": 18
                },
                "annual_turnover": "140.000 kr",
                "annual_production_value": "Okänt"
            },
            "foundation_year": 1923,
            "owners": [
                "fabr. G. Emanuel Carlsson",
                "fabr. K. Axel J. Karlqvist",
                "fabr. Carl A. Carlqvist",
                "fabr. Axel E. Sundqvist"
            ],
            "director": "Okänt",
            "managing_director": "Okänt",
            "sales_manager": "Okänt"
        }
    }
}