{
    "original": "Weibidl-—Wennberg\n\n*Weibul!s Carvämnesfabrik,\n\nLandskrona.\n\nSe Garvämnes AB. Weibull,\nLandskrona.\n\nAB. Fritz Weist &amp; Co-, Stockholm.\n\nTillverkar vid dotterbolaget, AB.\nFotomekano, Stockholm, fotografiska\noch optiska instrument såsom\nseriefotokameror (märke: »Fotomat»),\nförstoringsapparater, stillbildsprojektorer m. m.\nsamt tillbehör. Bolaget driver även\nhandel med instrument av utländsk\ntillverkning samt engroshandel med fotografiska\nartiklar.\n\nKontor: Regeringsg. 32. Telegr.-adr.:\nWeist Stockholm. Telefon: 108747—48 o.\n101443. Postgiro: 2564.\n\nAkt.-kap.: 164,000 kr. — Firman etabl.\n1921, bolag 1939. — Bolaget äger AB.\nFotomekano, Stockholm (se detta bolag).\n\nStyrelse o. verkst. dir.: Fritz Weist.\n\n*AB. Claes Welander, Ulricehamn.\n\nTrikåfabrik. Tillverkar damkoftor,\njumpers, sporttröjor, pullovers, västar,\nmössor, vantar och skidsockor m. m. i ylle.\n\nTelefon: 128. Postgiro: 83400. —\nAkt.-kap.: 200,000 kr. Antal industriarb.: 50.\nTillv.-värde pr år: 700,000 kr. — Firman\netabl. 1913, bolag 1922.\n\nStyrelse o. verkst. dir.: fabr. Claes\nWelander.\n\n*lvar Welander, Norrköping.\n\nYlleväveri. Tillverkar yllevävnader.\nSpecialitet: paletåtyger och tyger av\nsvenskull. Varunamn för\nsvenskullsty-gerna: »IW 100 % svenskull».\n\nTelegr.-adr.: Iwelander, Norrköping.\nTelefon: 20360. Postgiro: 29414. —\nArb.-antal: 10. Tillv.-värde pr år: 150,000 kr.\n— Firman etabl. 1912.\n\nÄgare o. chef : fabr. Ivar Welander.\n\nAB. Weldex, Vadstena,\n\nMek. verkstad. Tillverkar\nvarmvattenberedare, badkaminer, askhinkar samt\nshuntventiler. Varumärke: »Luko».\n\nTelefon: 31. Postgiro: 144063. —\nAkt.-kap.: 25,000 kr. Tillv.-värde pr år:\n400,000 kr. — Firman etabl. 1938.\n\nStyrelse: disp. Sven Lundstedt (ordf.),\nfru Mary Lundstedt.\n\nDisp.: Sven Lundstedt.\n\nKamrer: Gunnar Palmkvist.\n\n* Vellinge Vagn- &amp; Karosserlverkstad,\n\nVellinge.\n\nSnickeri, plåt- och smidesverkstäder i\nVellinge (Malmöh. l.).\n\nTillverkar karosserier, förråds-,\nmanskaps- och campingvagnar,\ntransportvagnar, hytter för traktorer samt\nsäckeleva-torer.\n\nTelefon: 222. Postgiro: 160659. —\nAntal industriarb.: 15. Tillv.-värde pr år:\n130,000 kr. — Firman etabl. 1933.\n\nÄgare o. chef: fabr. Artur Sjöö.\n\nWellpappfabriken, AB. Svenska,\n\nKinnahult.\n\nSe AB. Svenska Wellpappfabriken,\nKinnahult.\n\n*Wellpappfabriken, Gamla,\n\nStockholm.\n\nSe Gamla Wellpappfabriken AB.,\nStockholm.\n\n\"Welting, AB. Läderfabriken,\n\nRonneby.\n\nSe AB. Läderfabriken Welting,\nRonneby.\n\n*C. Wendahls Möbelfabrik, Bodafors.\n\nTillverkar möbler vid fabrik i Bodafors\n(Jönköp. l.).\n\nTelefon: 46. Postgiro: 144749. —\nArb.-antal: 10. Tillv.-värde pr år: 100,000 kr.\n— Firman etabl. 1909.\n\nÄgare o. chef: fabr. Gustaf Wendahl.\n\n*AB. C. J. Wennbergs Mekaniska\nVerkstad, Karlstad.\n\nMek. verkstad med gjuteri och\nplåtslageri. Tillverkar maskiner och\nutrustningar för cellulosa- och\npappersindustrien samt dammluckor och hydrauliska\npressar. Varumärke: »WEVERK».\n\nTelefon: »Weverk». Postgiro: 34300.\n\nAkt.-kap.: 500,000 kr. Antal\nindustriarb.: 110. Tillv.-värde pr år: 1,400,000 kr.\n-— Verkstaden anlades 1875, bolag 1906.\n\nStyrelse: disp. Simon Wennberg (ordf.) ,\nkonsul Curt Wennberg, övering. Olov\nWennberg.\n\nVerkst. dir.: Curt Wennberg.\n\növering&gt;: Olov Wennberg.\n\n(Jfr annons nr 94.)",
    "structured": {
        "1": {
            "name": "AB. Fritz Weist & Co-",
            "location": "Stockholm",
            "business": "Tillverkar vid dotterbolaget, AB. Fotomekano, Stockholm, fotografiska och optiska instrument såsom seriefotokameror (märke: »Fotomat»), förstoringsapparater, stillbildsprojektorer m. m. samt tillbehör. Bolaget driver även handel med instrument av utländsk tillverkning samt engroshandel med fotografiska artiklar.",
            "contact": {
                "office": "Regeringsg. 32",
                "phone": [
                    "108747—48",
                    "101443"
                ],
                "postgiro": "2564",
                "telegraph": "Weist Stockholm"
            },
            "financials": {
                "capital": "164,000 kr",
                "foundation_year": 1921,
                "corporation_year": 1939
            },
            "board": [
                {
                    "name": "Fritz Weist",
                    "role": "Styrelse o. verkst. dir."
                }
            ]
        },
        "2": {
            "name": "AB. Claes Welander",
            "location": "Ulricehamn",
            "business": "Trikåfabrik. Tillverkar damkoftor, jumpers, sporttröjor, pullovers, västar, mössor, vantar och skidsockor m. m. i ylle.",
            "contact": {
                "phone": "128",
                "postgiro": "83400"
            },
            "financials": {
                "capital": "200,000 kr",
                "employees": {
                    "industriarb": 50
                },
                "annual_turnover": "700,000 kr",
                "foundation_year": 1913,
                "corporation_year": 1922
            },
            "board": [
                {
                    "name": "fabr. Claes Welander",
                    "role": "Styrelse o. verkst. dir."
                }
            ]
        },
        "3": {
            "name": "Alvar Welander",
            "location": "Norrköping",
            "business": "Ylleväveri. Tillverkar yllevävnader. Specialitet: paletåtyger och tyger av svenskull.",
            "contact": {
                "phone": "20360",
                "postgiro": "29414"
            },
            "financials": {
                "employees": {
                    "arb": 10
                },
                "annual_production_value": "150,000 kr",
                "foundation_year": 1912
            },
            "owner": "fabr. Ivar Welander"
        },
        "4": {
            "name": "AB. Weldex",
            "location": "Vadstena",
            "business": "Mek. verkstad. Tillverkar varmvattenberedare, badkaminer, askhinkar samt shuntventiler.",
            "contact": {
                "phone": "31",
                "postgiro": "144063"
            },
            "financials": {
                "capital": "25,000 kr",
                "annual_production_value": "400,000 kr",
                "foundation_year": 1938
            },
            "board": [
                {
                    "name": "disp. Sven Lundstedt",
                    "role": "Styrelse"
                },
                {
                    "name": "fru Mary Lundstedt",
                    "role": "Styrelse"
                }
            ]
        },
        "5": {
            "name": "Vellinge Vagn- & Karosserlverkstad",
            "location": "Vellinge",
            "business": "Snickeri, plåt- och smidesverkstäder i Vellinge (Malmöh. l.). Tillverkar karosserier, förråds-, manskaps- och campingvagnar, transportvagnar, hytter för traktorer samt säckeleva-torer.",
            "contact": {
                "phone": "222",
                "postgiro": "160659"
            },
            "financials": {
                "employees": {
                    "industriarb": 15
                },
                "annual_production_value": "130,000 kr",
                "foundation_year": 1933
            },
            "owner": "fabr. Artur Sjöö"
        },
        "6": {
            "name": "AB. C. J. Wennbergs Mekaniska Verkstad",
            "location": "Karlstad",
            "business": "Mek. verkstad med gjuteri och plåtslageri. Tillverkar maskiner och utrustningar för cellulosa- och pappersindustrien samt dammluckor och hydrauliska pressar.",
            "contact": {
                "phone": "Weverk",
                "postgiro": "34300"
            },
            "financials": {
                "capital": "500,000 kr",
                "employees": {
                    "industriarb": 110
                },
                "annual_production_value": "1,400,000 kr",
                "foundation_year": 1875,
                "corporation_year": 1906
            },
            "board": [
                {
                    "name": "disp. Simon Wennberg",
                    "role": "Styrelse"
                },
                {
                    "name": "konsul Curt Wennberg",
                    "role": "Styrelse"
                },
                {
                    "name": "övering. Olov Wennberg",
                    "role": "Styrelse"
                }
            ]
        }
    }
}