{
    "original": "Heby—Hedemora\n\nStockholm: O. Haux, Sysslomansg. 28,\ntelefon: 503806.\n\nAkt.-kap.: 50,000 kr. Antal\nindustriarb.: 25. — Firman etabl. 1907, bolag\n1924, ombildat 1931.\n\nStyrelse: fabr. Carl August Haux\n(ordf.), fabr. W. Kaesen, grossh. G. Oscar\nSvensson.\n\nVerkst. dir.: Carl August Haux.\n\n*AB. Heby Tegelverk, Heby.\n\nTegelbruk i Heby (Heby Norra o.\nHeby Nya Tegelbruk samt Tegelbruket\nFunkis) och i Hårsbäck (samtl. i\nVästmanl. l.). Tillverkar taktegel,\ndräneringsrör och blomkrukor. Specialitet: taktegel.\nBolaget driver även sågverksrörelse.\nVarumärke: »Original Heby Tegel».\n\nHuvudkontor: Heby. Telegr.-adr.:\nHeby tegel, Heby. Telefon: »Heby\nTegelverk». Postgiro: 33651. Avd.-kontor:\nStockholm, Kungsg. 44, telefon: 118155.\nEnsamförsälj. för västra Sverige:\nLarsson, Seaton &amp; Co. AB., Göteborg,\nMarie-holmsg. 36, telefon: »Larsson-Seaton».\n\nAkt.-kap.: 800,000 kr. Antal\nindustriarb.: 190. Årstillv.: 10,5 milj. taktegel, 2\nmilj. dräneringsrör, 1,5 milj. blomkrukor.\n\nBolaget grundat 1918. Tegelbruken\narrenderas av firman Heby Tegelverk,\nSköldberg &amp; Co., Kommanditbolag.\n\nStyrelse: direktör Gustaf Settergren\n(ordf.), civiling. Nils Blomqvist, adv.\nHarald Håkansson, akademiesekr. C. O.\nHäggquist, adv. Carl. v. Plomgren.\n\nVerkst. dir. o. disp.: J. Fab. Janson.\n\nHedbergs Verkstäder, Osby.\n\nMek. verkstad, förnicklings- och\nfor-kromningsverkstad samt grovplåtslageri\ni Osby (Kristianst. l.). Tillverkar\nfackverkskonstruktioner, vinschar, hissar och\nkranar, pressar, tankar m. m.\n\nTelefon: 382. Postgiro: 143537. —\nAntal industriarb.: 40. Tillv.-värde pr år:\n400,000 kr. — Firman etabl. 1898.\n\nÄgare o. chef: ing. Axel Hedberg.\n\nCust. Hedberg, Stockholm.\n\nBokbinderi. Tillverkar biblioteksband\noch lyxband ävensom adresser och\nalbum avsedda till hedersgåvor.\n\nKontor: Regeringsg. 26. Telefon:\n106105. — Arb.-antal: 10. Tillv.-värde pr\når: 200,000 kr. — Firman etabl. 1886.\n\nÄgare o. chef: hovbokb. Arvid Hedberg.\n\n*J. A. Hedberg &amp; Co. Industri AB»,\n\nStockholm.\n\nPappersförädlingsfabrik vid\nHenriks-dal, Stockholm. Tillverkar carbon- och\nkalkérpapper, stenciler, skrivmaskinsband\noch dupliceringsfärg. Varumärke:\n»Stjärnan».\n\nKontor: Henriksdal, postadr.:\nStockholm 4. Telegr.-adr.: Kvarnpaper,\nStockholm. Telefon: 439855—56—57. Postgiro:\n3598.\n\nAkt.-kap.: 100,000 kr. Antal\nindustriarb.: 25. — Firman etabl. 1921, bolag\n1926.\n\nStyrelse o. verkst. dir.: civiling. Olof\nHirsch.\n\nHedbloms Möbel- &amp; Biljardfabrik,\n\nHudiksvall.\n\nTillverkar möbler och biljarder.\n\nTelefon: 66. — Arb.-antal: 6.\nTillv.-värde pr år: 75,000 kr. — Firman etabl.\n1878.\n\nÄgare o. chef: snickaremäst. Karl\nHedblom.\n\n*Ä. G. Hedbrandh Trikåfabrik AB.,\n\nHälsingborg.\n\nTillverkar herr- och damunderkläder.\n\nTelefon: 15344. Postgiro: 32141. —\nAkt.-kap.: 250,300 kr. Antal industriarb.:\n75. Tillv.-värde pr år: 900,000 kr. —\nFirman etabl. 1930, bolag 1941.\n\nStyrelse: ing. Eric Hedbrandh, disp.\nÅke G. Hedbrandh, kontorschef Harry\nLindén.\n\nVerkst. dir.: k. G. Hedbrandh.\n\nDriftsing.: E. Hedbrandh.\n\nKontorschef: Harry Lindén.\n\nHede Bandfabrik, Sjömarken.\n\nTillverkar bastband, flätade\nbomullsband, resårband, indiaband, kyprade band,\nrullgardinssnören m. m. samt bindgarn\noch mattvarp vid fabrik i Sjömarken\n(Älvsb. l.).\n\nKontor: Sjömarken. Telefon: Borås\n54023. Postgiro: 74725. — Antal\nindustriarb.: 5. Tillv.-värde pr år-.100,000 kr.\n— Firman etabl. 1931.\n\nÄgare o. chef: fabr. David Johansson.\n\nInlcöps- o. försäljn.-chef: kontorschef\nTorsten Johansson.\n\n*AB. Hedemora Verkstäder,\n\nHedemora.\n\nMek. verkstad, grovplåtslageri och\nradiatorfabrik. Tillverkar maskiner och\napparater för cellulosafabriker, pappers-",
    "structured": {
        "1": {
            "name": "AB. Heby Tegelverk",
            "location": "Heby",
            "business": "Tegelbruk",
            "products": "Tillverkar taktegel, dräneringsrör och blomkrukor. Specialitet: taktegel. Bolaget driver även sågverksrörelse. Varumärke: »Original Heby Tegel».",
            "contact": {
                "office": "Heby",
                "phone": [
                    "Heby Tegelverk"
                ],
                "postgiro": "33651",
                "head_office": "Heby",
                "sales_offices": [
                    {
                        "location": "Stockholm",
                        "phone": "118155"
                    }
                ]
            },
            "financials": {
                "capital": "800,000 kr",
                "employees": {
                    "industriarb": 190
                },
                "annual_turnover": "10.5 milj. taktegel, 2 milj. dräneringsrör, 1.5 milj. blomkrukor"
            },
            "foundation_year": 1918,
            "board": [
                {
                    "name": "direktör Gustaf Settergren",
                    "role": "ordf."
                },
                {
                    "name": "civiling. Nils Blomqvist",
                    "role": "adv."
                },
                {
                    "name": "adv. Harald Håkansson",
                    "role": "akademiesekr."
                },
                {
                    "name": "C. O. Häggquist",
                    "role": "adv."
                },
                {
                    "name": "adv. Carl. v. Plomgren",
                    "role": ""
                }
            ]
        },
        "2": {
            "name": "Hedbergs Verkstäder",
            "location": "Osby",
            "business": "Mek. verkstad",
            "products": "Tillverkar fackverkskonstruktioner, vinschar, hissar och kranar, pressar, tankar m. m.",
            "contact": {
                "phone": "382",
                "postgiro": "143537"
            },
            "financials": {
                "employees": {
                    "industriarb": 40
                },
                "annual_production_value": "400,000 kr"
            },
            "foundation_year": 1898
        },
        "3": {
            "name": "Cust. Hedberg",
            "location": "Stockholm",
            "business": "Bokbinderi",
            "products": "Tillverkar biblioteksband och lyxband ävensom adresser och album avsedda till hedersgåvor.",
            "contact": {
                "office": "Regeringsg. 26",
                "phone": [
                    "106105"
                ]
            },
            "financials": {
                "employees": {
                    "arb": 10
                },
                "annual_production_value": "200,000 kr"
            },
            "foundation_year": 1886
        },
        "4": {
            "name": "*J. A. Hedberg & Co. Industri AB»",
            "location": "Stockholm",
            "business": "Pappersförädlingsfabrik",
            "products": "Tillverkar carbon- och kalkérpapper, stenciler, skrivmaskinsband och dupliceringsfärg. Varumärke: »Stjärnan».",
            "contact": {
                "office": "Henriksdal"
            },
            "financials": {
                "capital": "100,000 kr",
                "employees": {
                    "industriarb": 25
                }
            },
            "foundation_year": 1921
        },
        "5": {
            "name": "Hedbloms Möbel- & Biljardfabrik",
            "location": "Hudiksvall",
            "business": "Möbel- & Biljardfabrik",
            "products": "Tillverkar möbler och biljarder.",
            "contact": {
                "phone": "66"
            },
            "financials": {
                "employees": {
                    "arb": 6
                },
                "annual_production_value": "75,000 kr"
            },
            "foundation_year": 1878
        },
        "6": {
            "name": "*Ä. G. Hedbrandh Trikåfabrik AB.,",
            "location": "Hälsingborg",
            "business": "Trikåfabrik",
            "products": "Tillverkar herr- och damunderkläder.",
            "contact": {
                "phone": "15344",
                "postgiro": "32141"
            },
            "financials": {
                "capital": "250,300 kr",
                "employees": {
                    "industriarb": 75
                },
                "annual_production_value": "900,000 kr"
            },
            "foundation_year": 1930
        },
        "7": {
            "name": "Hede Bandfabrik",
            "location": "Sjömarken",
            "business": "Bandfabrik",
            "products": "Tillverkar bastband, flätade bomullsband, resårband, indiaband, kyprade band, rullgardinssnören m. m. samt bindgarn och mattvarp vid fabrik i Sjömarken (Älvsb. l.).",
            "contact": {
                "office": "Sjömarken",
                "phone": [
                    "Borås 54023"
                ],
                "postgiro": "74725"
            },
            "financials": {
                "employees": {
                    "industriarb": 5
                },
                "annual_production_value": "100,000 kr"
            },
            "foundation_year": 1931
        },
        "8": {
            "name": "*AB. Hedemora Verkstäder",
            "location": "Hedemora",
            "business": "Mek. verkstad",
            "products": "Tillverkar maskiner och apparater för cellulosafabriker, pappers-.",
            "contact": {
                "office": "Hedemora",
                "phone": [
                    "Hedemora Verkstäder"
                ],
                "postgiro": "3598"
            },
            "financials": {
                "employees": {
                    "industriarb": 25
                }
            },
            "foundation_year": 1921
        }
    }
}