{
    "original": "Pulverkemi—Pythagoras\n\nAB, Pulverkemi, Stockholm.\n\nPulveriseringsanläggning vid\nLiljeholmen och mek. verkstad vid Jakobsdal\n(båda i Stockholm). Tillverkar\nmetallpulver och apparater för\nsintermetalltillverkning.\n\nKontor: Tuleg. 15. Telegr.-adr.:\nPulverkemi, Stockholm. Telefon: 320068.\nPostgiro: 192466.\n\nAkt.-kap.: 100,000 kr. Antal\nindustriarb.: 11. Tillv.-värde pr år: 200,000 kr.\n\n—\tBolaget grundat 1942.\n\nVerkst. dir.: fil. dr Josef Heuberger.\n\n*AB. Pumpindustri, Göteborg.\n\nMek. verkstad och metallgjuteri i\nKrokslätt, Mölndal. Tillverkar centrifugal-,\nkolv- och kugghjulspumpar, motorsprutor,\nbrandkårsutrustningar samt\nmetallgjut-gods m. m. Varumärke: »API».\n\nHuvudkontor: Krokslätt; postadr.:\nGöteborg 5. Telegr.-adr.: Pumpindustri,\nGöteborg. Telefon: 187130. Postgiro: 41382.\nAvd.-kontor: Stockholm, Malmskillnadsg.\n39, telefon: 11117$ o. 202064.\n\nAkt.-kap.: 300,000 kr. Antal\nindustriarb.: 110. Tillv.-värde pr år: 2,000,000 kr.\n\n—\tBolaget grundat 1918.\n\nStyrelse: dir. Walter Edström (ordf.),\ndir. Olof Jahn, dir. Gustaf Larson,\nbankdir. Ebbe Lundberg.\n\nVerkst. dir.: Olof Jahn.\n\nEhonomichef: Rolf Deinoff.\n\nAB. Pump-Separator, Stockholm.\n\nTillverkar mjölkseparatorer och\nsmörkärnor. Varumärken: »Diabolo»,\n»Viking» o. »Velox».\n\nKontor: Flemingg. 8. Telegr.-adr.:\nPumpsep, Stockholm. Telefon: 532304.\n—* Akt.-kap.: 10,000,000 kr.\n\nBolaget, grundat 1903, äger AB.\nPump-Separators Gjuterier, Katrineholm, AB.\nBomhus Lådfabrik, Bomhus, samt ett\nflertal utländska försäljningsbolag. AB.\nSeparator är huvudintressent i bolaget.\n\nStyrelse: fil. dr Karl Hildebrand\n(ordf.), dir. E. Brändström, dir. Nils E.\nEricsson, dir. Folke Hellstedt, dir. Axel\nWästfelt.\n\nVerkst. dir.: Nils E. Ericsson.\n\n*AB. Pump-Separators Cjuterier,\n\nKatrineholm.\n\nGjuteri, mek. verkstad, smedja,\nsnickeriverkstad och emaljeringsverk.\n\nTillverkar tackjärnsgjutgods,\nhejarsmi-de, trä-, järn- och metallmodeller samt\nutför emaljering av gjutgods och plåt för\n\nfrämmande beställare, handelsgjutgods\nsåsom spisar (bl. a. »Serva»-spisar);\nvedkaminer, hushållsmanglar, pannor, ventiler,\ngjutna rör och rördelar, byggnadsplattor,\ndrickeshoar, kakelugnsinsatser (»Serva»)a\ngräsklippare, smörältare, cylinderkannor\nm. m. Varumärke: »P. S. G.».\n\nTelegr.-adr.: Gjuterierna, Katrineholm.\nTelefon: 347. Postgiro: 13089.\n\nRepresentanter: i Stockholm:\nPump-Separators Svenska Avd. AB., Flemingg.\n8, telefon: 532304; Serva Järnvaru-AB.,\nFlemingg. 8, telefon: 532479, samt AB.\nSeparator (avd. Pressbolaget), Bergsg. 23,\ntelefon: »Separator»; i Göteborg: Olbert\n&amp; Co. AB., St, Nygatan 31, telefon:\n117582.\n\nAkt.-kap.: 1,000,000 kr. Antal\nindustriarb.: 300. Tillv.-värde pr år: 5,000,000 kr.\n\n—\tBolaget grundat 1916.\n\nStyrelse: dir. Axel Wästfelt (ordf.),\ndir. E. Brändström, dir. Nils E. Ericsson,\ndir. Folke Hellstedt, disp. Herman\nMagnusson.\n\nVerkst. dir.: Herman Magnusson.\n\nKamrer: Axel Hernblom.\n\n(Jfr annons nr 95.)\n\nAB. Punker, Eskilstuna.\n\nTillverkar spritgaskök och -element\n(märke: »Punker»), motorvärmare,\nkarbidlampor, förgasare för gengasbilar,\nfönsterbeslag (»Pivåfönsterbeslag») samt\nskruvstycken och mjölkningsmaskiner.\n\nTelegr.-adr.: Punker, Eskilstuna.\nTelefon: 31020 o. 32520. Postgiro: 170017.\n\nAkt.-kap.: 175,000 kr. Antal\nindustriarb.: 75. Tillv.-värde pr år: 800,000 kr.\n\n—\tBolaget grundat 1940.\n\nStyrelse: dir. John F. Claeson (ordf.),\ndir. Nath. Hall.\n\nVerkst. dir.: John F. Claeson.\n\n*Pyrotekniska AB. C. R. Hansson &amp;\nSöner, Göteborg.\n\nTillverkar fyrverkeriartiklar m. m.\n\nKontor: Askim; postadr.: Göteborg 11,\nTelegr.-adr.: Pyrofabrik, Göteborg.\nTelefon: 282000. Postgiro: 42422.\n\nAkt.-kap.: 50,000 kr. Antal\nindustriarb.: 100.\n\nBolaget, grundat 1934, äger\nSprängämnesfabriken Trionyl, Ängelholm.\n\nStyrelse: dir. Gösta Hansson, dir.\nStellan Hansson, häradsskrivare Gustaf\nPalm.\n\nVerkst. dir..- Gösta Hansson.\n\n\"Pythagoras, Motor AB., Norrtälje.\n\nSe Motor AB. Pythagoras, Norrtälje.",
    "structured": {
        "1": {
            "name": "Pulverkemi—Pythagoras AB",
            "location": "Stockholm",
            "business": "Tillverkar metallpulver och apparater för sintermetalltillverkning",
            "contact": {
                "office": "Tuleg. 15",
                "phone": [
                    "320068"
                ],
                "postgiro": "192466",
                "telegraph": "Pulverkemi, Stockholm"
            },
            "financials": {
                "capital": "100,000 kr",
                "employees": {
                    "industriarb": 11
                },
                "annual_turnover": "200,000 kr",
                "annual_production_value": "200,000 kr"
            },
            "foundation_year": 1942,
            "director": "fil. dr Josef Heuberger"
        },
        "2": {
            "name": "AB. Pumpindustri",
            "location": "Göteborg",
            "business": "Tillverkar centrifugal-, kolv- och kugghjulspumpar, motorsprutor, brandkårsutrustningar samt metallgjut-gods",
            "contact": {
                "office": "Krokslätt",
                "phone": [
                    "187130"
                ],
                "postgiro": "41382",
                "sales_offices": [
                    {
                        "location": "Stockholm",
                        "phone": "11117$ o. 202064"
                    }
                ]
            },
            "financials": {
                "capital": "300,000 kr",
                "employees": {
                    "industriarb": 110
                },
                "annual_turnover": "2,000,000 kr",
                "annual_production_value": "2,000,000 kr"
            },
            "foundation_year": 1918,
            "board": [
                {
                    "name": "dir. Walter Edström",
                    "role": "ordf."
                },
                {
                    "name": "dir. Olof Jahn",
                    "role": ""
                },
                {
                    "name": "dir. Gustaf Larson",
                    "role": ""
                },
                {
                    "name": "bankdir. Ebbe Lundberg",
                    "role": ""
                }
            ],
            "director": "Olof Jahn",
            "sales_manager": "Rolf Deinoff"
        },
        "3": {
            "name": "AB. Pump-Separator",
            "location": "Stockholm",
            "business": "Tillverkar mjölkseparatorer och smörkärnor",
            "contact": {
                "office": "Flemingg. 8",
                "phone": [
                    "532304"
                ],
                "postgiro": "10,000,000 kr"
            },
            "original_name": "AB. Pump-Separators Gjuterier, Katrineholm, AB. Bomhus Lådfabrik, Bomhus",
            "foundation_year": 1903,
            "board": [
                {
                    "name": "fil. dr Karl Hildebrand",
                    "role": "ordf."
                },
                {
                    "name": "dir. E. Brändström",
                    "role": ""
                },
                {
                    "name": "dir. Nils E. Ericsson",
                    "role": ""
                },
                {
                    "name": "dir. Folke Hellstedt",
                    "role": ""
                },
                {
                    "name": "dir. Axel Wästfelt",
                    "role": ""
                }
            ],
            "director": "Nils E. Ericsson"
        },
        "4": {
            "name": "AB. Pump-Separators Cjuterier",
            "location": "Katrineholm",
            "business": "Tillverkar tackjärnsgjutgods, hejarsmi-de, trä-, järn- och metallmodeller samt utför emaljering av gjutgods och plåt för främmande beställare",
            "contact": {
                "telegraph": "Gjuterierna, Katrineholm",
                "phone": "347",
                "postgiro": "13089"
            },
            "foundation_year": 1916,
            "board": [
                {
                    "name": "dir. Axel Wästfelt",
                    "role": "ordf."
                },
                {
                    "name": "dir. E. Brändström",
                    "role": ""
                },
                {
                    "name": "dir. Nils E. Ericsson",
                    "role": ""
                },
                {
                    "name": "dir. Folke Hellstedt",
                    "role": ""
                },
                {
                    "name": "disp. Herman Magnusson",
                    "role": ""
                }
            ],
            "director": "Herman Magnusson"
        },
        "5": {
            "name": "AB. Punker",
            "location": "Eskilstuna",
            "business": "Tillverkar spritgaskök och -element (märke: »Punker»), motorvärmare, karbidlampor, förgasare för gengasbilar, fönsterbeslag (»Pivåfönsterbeslag») samt skruvstycken och mjölkningsmaskiner",
            "contact": {
                "telegraph": "Punker, Eskilstuna",
                "phone": [
                    "31020 o. 32520"
                ],
                "postgiro": "170017"
            },
            "financials": {
                "capital": "175,000 kr",
                "employees": {
                    "industriarb": 75
                },
                "annual_turnover": "800,000 kr",
                "annual_production_value": "800,000 kr"
            },
            "foundation_year": 1940,
            "board": [
                {
                    "name": "dir. John F. Claeson",
                    "role": "ordf."
                },
                {
                    "name": "dir. Nath. Hall",
                    "role": ""
                }
            ],
            "director": "John F. Claeson"
        },
        "6": {
            "name": "Pyrotekniska AB. C. R. Hansson & Söner",
            "location": "Göteborg",
            "business": "Tillverkar fyrverkeriartiklar m. m.",
            "contact": {
                "office": "Askim",
                "phone": [
                    "282000"
                ],
                "postgiro": "42422"
            },
            "original_name": "Sprängämnesfabriken Trionyl, Ängelholm",
            "foundation_year": 1934,
            "board": [
                {
                    "name": "dir. Gösta Hansson",
                    "role": ""
                },
                {
                    "name": "dir. Stellan Hansson",
                    "role": ""
                },
                {
                    "name": "häradsskrivare Gustaf Palm",
                    "role": ""
                }
            ],
            "director": "Gösta Hansson"
        }
    }
}