{
    "original": "Ankarsvik—Apotekarne\n\nStyrelse: dir. Jonas Spånberg (ordf.)»\ndir. John Lagerman, disp. Bengt\nSpånberg.\n\nDisp.: Bengt Spånberg.\n\nKassör: Nils Lithander.\n\n*Ankarsviks Ångsågs AB., Sundsvall.\n\nSågverk, hvvleri, trähus-, snickeri- och\nwallboardfabriker vid Johannedal,\nsågverk vid Karlsvik och Hofvid samt\nhyvleri och lamellgolvfabrik vid Myrnäs\n(samtl. i Västernorrl. l.).\n\nTillverkar sågade och hyvlade trävaror,\nträfiberplattor (varunamn:\n»Ankar-board»), trähus, lamellgolv, snickerier\nm. m.\n\nKontor: Sundsvall. Telegr.-adr.:\nAnkarsvik, Sundsvall. Telefon: 55540.\nPostgiro: 72567. Repr. för monteringsfärdiga\nträhus: AB. Svenska Trähus, Stockholm,\nBirger Jarisg. 27, telefon: »Svenska\nTrähus».\n\nAkt.-kap.: 2,000,000 kr. Antal\nindustriarb. : 900. Årstillv.: 10,000 stds sågade\nOjch 8,000 stds hyvlade trävaror samt\n2*0; 000 ton wallboard.\n\nAgenter i utlandet: England: Thomas\nSimson &amp; Co., Ltd. 6, Great Winchester\nStreet, London E. C. 2; Danmark:\nHan-sen &amp; Co., Köpenhamn; Belgien: Bulow,\nBennet &amp; Cie., Bruxelles; Spanien:\nSimpler &amp; Blidberg, S. A., Tolosa;\nFrankrike: Sofetra, Paris.\n\nBolaget, som grundades 1891, äger\nHofvids Trävaru AB., Myrnäs AB.,\nJo-hannedals Trävaru AB., Alviks\nTräförädlings AB., AB. Ytterfjärden och Böle\nSkogs AB., Sundsvall.\n\nStyrelse: konsul Hugo Nordgren\n(ordf.), disp. Wilhelm Lindgren, bankdir.\nIvar Wallmark.\n\nVerkst. dir. o. disp.: Wilhelm Lindgren.\n\nFörsäljningschefer: för trävaruavd.:\nGustaf Pousette; för wallboard- o.\nlåd-avd.: Hjalmar Jansson.\n\növering. vid wallboardfabriken: Sten\nRasch.\n\nSkogschef: Hugo Backström.\n\nSägverksförvalt.: Gustaf Engström.\n\nDriftsing. vid trähusfabr.: J. Viktor\nOlsson.\n\nKamrer: B. Ryländer.\n\n*AB. Annetorps Tegelbruk, Lund.\n\nTillverkar flamtegel, hårdbränt tegel,\nbrunntegel samt dräneringsrör vid\ntegelbruk i Lund. Bolaget driver även\njordbruk.\n\nTelefon: 10356. Postgiro: 176595. —\nAkt.-kap.: 90,000 kr. Antal industriarb.:\n25. Årstillv.: 2 milj. st. tegelvaror. —\nFirman etabl. 1874, bolag 1904.\n\nStyrelse: intendent Gertrud\nSerner-Petrén (ordf.), civiling. John Frostberg,\nfru Ellen Hydner.\n\nDisp.: vakant.\n\nAB. John Antonsons Boktryckeri,\n\nGöteborg.\n\nBoktryckeri och bokbinderi. Utför\nboktryck, litografi, teckningar, klichéer och\nretuscharbeten för reproduktionsändamål\nsamt bokbinderi arbeten. Specialitet:\nil-lustr. reklamtryck å olika språk, däribland\nryska, tjeckiska och polska.\n\nKontor: Kronhusg. 2 F. Telegr.-adr.:\nAntonsontryck,Göteborg. Telefon: 170210.\nPostgiro: 40638.\n\nAkt.-kap.: 105 000 kr. Antal\nindustriarb.: 50. — Firman etabl. 1894, bolag\n1916.\n\nStyrelse o. verkst. dir.: Thorsten\nAntonson.\n\nAnundsjö Sko- &amp; Läderfabrik,\nCelinder &amp; Co., Bredbyn.\n\nSkofabrik med garveri i Bredbyn\n(Västernorrl. l.). Tillverkar pjäxor, skidskor,\nsamt arbetsskor och vandrarskor.\n\nTelefon: 49. — Antal industriarb.: 30.\nTillv.-värde pr år: 300,000 kr. —\nFirman etabl. 1926.\n\nChef: Nils Selinder.\n\n*AB. Apotekarnes Förenade\nVattenfabriker i Göteborg, Göteborg.\n\nTillverkar mineralvatten, läskvatten\n\noch söta läskedrycker.\n\nKontor: Åvägen 24. Telefon: 167200\n—04. Postgiro: 42042.\n\nAkt.-kap.: 2,456.000 kr. Antal\nindustriarb.: 150. Tillv.-värde pr år: 4,200,000 kr.\n— Bolaget grundat 1907.\n\nStyrelse: civiling. Erik Olson (ordf.),\nmed. lic. E. Belfrage, tandläk. V. Heijde,\ndisp. Lars Loberg, över läk. Albert\nWal-lin.\n\nVerkst. dir.: Lars Loberg.\nDriftsing.: Olle Olsson.\n\n*Apotekarnes Kemiska Fabriker,\n\nSödertälje.\n\nSe AB. Astra, Apotekarnes Kemiska\nFabriker, Södertälje.",
    "structured": {
        "1": {
            "name": "Ankarsviks Ångsågs AB.",
            "location": "Sundsvall",
            "business": "Sågverk, trähus-, snickeri- och wallboardfabriker",
            "products": "sågade och hyvlade trävaror, träfiberplattor, trähus, lamellgolv, snickerier",
            "contact": {
                "office": "Sundsvall",
                "phone": [
                    "55540"
                ],
                "postgiro": "72567",
                "head_office": "Johannedal",
                "sales_offices": [
                    {
                        "location": "Stockholm",
                        "phone": "Svenska Trähus"
                    }
                ],
                "telegraph": "Ankarsvik, Sundsvall",
                "factory_office": "Myrnäs",
                "factory_phone": "N/A"
            },
            "financials": {
                "capital": "2,000,000 kr",
                "employees": {
                    "sågade": 900,
                    "hyvlade": 900,
                    "wallboard": 0
                },
                "annual_turnover": "N/A"
            },
            "foundation_year": 1891,
            "current_name_year": "N/A",
            "predecessor": "N/A",
            "original_name": "N/A",
            "corporation_year": "N/A",
            "board": [
                {
                    "name": "Hugo Nordgren",
                    "role": "ordf."
                },
                {
                    "name": "Wilhelm Lindgren",
                    "role": "verkst. dir."
                }
            ],
            "owners": [
                "N/A"
            ],
            "director": "Wilhelm Lindgren",
            "managing_director": "N/A",
            "sales_manager": "N/A",
            "manager": "N/A"
        },
        "2": {
            "name": "AB. Annetorps Tegelbruk",
            "location": "Lund",
            "business": "Tillverkar flamtegel, hårdbränt tegel, brunntegel samt dräneringsrör",
            "products": "tegelvaror, dräneringsrör",
            "contact": {
                "office": "Lund",
                "phone": [
                    "10356"
                ],
                "postgiro": "176595",
                "head_office": "N/A",
                "sales_offices": [],
                "telegraph": "N/A",
                "factory_office": "N/A",
                "factory_phone": "N/A"
            },
            "financials": {
                "capital": "90,000 kr",
                "employees": {
                    "total": 25
                },
                "annual_turnover": "N/A"
            },
            "foundation_year": 1874,
            "current_name_year": 1904,
            "predecessor": "N/A",
            "original_name": "N/A",
            "corporation_year": "N/A",
            "board": [
                {
                    "name": "Gertrud Serner-Petrén",
                    "role": "ordf."
                },
                {
                    "name": "John Frostberg",
                    "role": "civiling."
                }
            ],
            "owners": [
                "N/A"
            ],
            "director": "N/A",
            "managing_director": "N/A",
            "sales_manager": "N/A",
            "manager": "N/A"
        },
        "3": {
            "name": "AB. John Antonsons Boktryckeri",
            "location": "Göteborg",
            "business": "Boktryckeri och bokbinderi",
            "products": "boktryck, litografi, teckningar, klichéer, illustr. reklamtryck, bokbinderi arbeten",
            "contact": {
                "office": "Göteborg",
                "phone": [
                    "170210"
                ],
                "postgiro": "40638",
                "head_office": "N/A",
                "sales_offices": [],
                "telegraph": "Antonsontryck,Göteborg",
                "factory_office": "N/A",
                "factory_phone": "N/A"
            },
            "financials": {
                "capital": "105,000 kr",
                "employees": {
                    "total": 50
                },
                "annual_turnover": "N/A"
            },
            "foundation_year": 1894,
            "current_name_year": 1916,
            "predecessor": "N/A",
            "original_name": "N/A",
            "corporation_year": "N/A",
            "board": [
                {
                    "name": "Thorsten Antonson",
                    "role": "verkst. dir."
                }
            ],
            "owners": [
                "N/A"
            ],
            "director": "N/A",
            "managing_director": "N/A",
            "sales_manager": "N/A",
            "manager": "N/A"
        },
        "4": {
            "name": "Anundsjö Sko- &amp; Läderfabrik, Celinder &amp; Co.",
            "location": "Bredbyn",
            "business": "Skofabrik med garveri",
            "products": "pjäxor, skidskor, arbetsskor, vandrarskor",
            "contact": {
                "office": "Bredbyn",
                "phone": [
                    "49"
                ],
                "postgiro": "N/A",
                "head_office": "N/A",
                "sales_offices": [],
                "telegraph": "N/A",
                "factory_office": "N/A",
                "factory_phone": "N/A"
            },
            "financials": {
                "capital": "N/A",
                "employees": {
                    "total": 30
                },
                "annual_turnover": "300,000 kr"
            },
            "foundation_year": 1926,
            "current_name_year": "N/A",
            "predecessor": "N/A",
            "original_name": "N/A",
            "corporation_year": "N/A",
            "board": [
                {
                    "name": "Nils Selinder",
                    "role": "chef"
                }
            ],
            "owners": [
                "N/A"
            ],
            "director": "N/A",
            "managing_director": "N/A",
            "sales_manager": "N/A",
            "manager": "N/A"
        },
        "5": {
            "name": "AB. Apotekarnes Förenade Vattenfabriker",
            "location": "Göteborg",
            "business": "Tillverkar mineralvatten, läskvatten och söta läskedrycker",
            "products": "mineralvatten, läskvatten, söta läskedrycker",
            "contact": {
                "office": "Åvägen 24",
                "phone": [
                    "167200-04"
                ],
                "postgiro": "42042",
                "head_office": "N/A",
                "sales_offices": [],
                "telegraph": "N/A",
                "factory_office": "N/A",
                "factory_phone": "N/A"
            },
            "financials": {
                "capital": "2,456,000 kr",
                "employees": {
                    "total": 150
                },
                "annual_turnover": "4,200,000 kr"
            },
            "foundation_year": 1907,
            "current_name_year": "N/A",
            "predecessor": "N/A",
            "original_name": "N/A",
            "corporation_year": "N/A",
            "board": [
                {
                    "name": "Erik Olson",
                    "role": "ordf."
                },
                {
                    "name": "Lars Loberg",
                    "role": "disp."
                }
            ],
            "owners": [
                "N/A"
            ],
            "director": "Lars Loberg",
            "managing_director": "N/A",
            "sales_manager": "N/A",
            "manager": "N/A"
        },
        "6": {
            "name": "AB. Apotekarnes Kemiska Fabriker",
            "location": "Södertälje",
            "business": "Se AB. Astra, Apotekarnes Kemiska Fabriker, Södertälje..",
            "products": "N/A",
            "contact": {
                "office": "N/A",
                "phone": [
                    "N/A"
                ],
                "postgiro": "N/A",
                "head_office": "N/A",
                "sales_offices": [],
                "telegraph": "N/A",
                "factory_office": "N/A",
                "factory_phone": "N/A"
            },
            "financials": {
                "capital": "N/A",
                "employees": {
                    "total": "N/A"
                },
                "annual_turnover": "N/A"
            },
            "foundation_year": "N/A",
            "current_name_year": "N/A",
            "predecessor": "N/A",
            "original_name": "N/A",
            "corporation_year": "N/A",
            "board": [],
            "owners": [
                "N/A"
            ],
            "director": "N/A",
            "managing_director": "N/A",
            "sales_manager": "N/A",
            "manager": "N/A"
        }
    }
}