{
    "original": "G af vet orp— Gällstad\n\n\"Gåfvetorps Tegelbruk, Gåvetorp.\n\nTillverkar murtegel, poröst och\nhög-poröst murtegel, beklädnadstegel samt\ndräneringsrör vid tegelbruk i Gåvetorp\n(Kronob. l.).\n\nTelefon: Gåvetorp 26. Postgiro: 22142.\n—- Antal industriarb.: 35. Årstillv.: 2\nmilj. st. tegel var or. — Bruket anlagt i\nbörjan av 1800-talet.\n\nÄ’.gare o. chef: dr Arvid Aaby-Eriesson.\n\n\"Gåragöls Stärkelse- &amp; Sagofabrik,\n\nHemsjö.\n\nTillverkar potatismjöl, potatisgryn och\nsagogryn vid fabrik i Gåragöl, Hemsjö\n(Blekinge l.).\n\nTelegr.-adr.: Amylum, Karlshamn.\nTelefon: Hemsjö 1. — Antal industriarb.:\n10. Tillv.-värde pr år: 185,000 kr. —\nFabriken anlagd 1879.\n\nChef: fabr. Jöns Nilsson.\n\nCårda Fabrikers AB., Göteborg.\n\nTrikå- och strumpfabrik, bandfabrik,\nullfärgeri samt briljantblekeri.\nTillverkar trikåvaror och strumpor i ylle,\nbomull samt konst- och natursilke, vävda och\nflätade ylle-, bomulls- och konstsilkeband\nsamt resårband. Utför färgning och\nbriljantblekning av ull och ullgarn samt\nfärgning av annat löst textilmaterial.\n\nHuvudkontor: Göteborg. Telegr.-adr.:\nGårdabolag, Göteborg. Telefon: 192560.\nPostgiro: 41075. Avd.-kontor: Stockholm,\nKungsg. 29, telefon: 209926.\n\nAkt.-kap.: 2,130,000 kr. Antal\nindustriarb.: 577. — Firman, grundad 1880,\nom-bildad till bolag 1893, äger Spinneri AB.\nHermann Kurzel, Göteborg.\n\nStyrelse: dir. Gustaf Werner (ordf.),\ndir. Åke Arvidius, dir. Frans H. Nilsson.\n\nVerkst. dir. o. disp.: Åke Arvidius.\n\nKamrer: S. Brankell.\n\nKontorschef: Hugo Kjellmer.\n\nDriftsing.: Bo Byfors.\n\n\"Cårda Stärkelsefabrik, Göteborg.\n\nSe Gegerfelt &amp; Weijdling AB.,\nGöteborg.\n\nAB. Gåsöfjordens Konservfabrik,\n\nGrundsund.\n\n•Tillverkar sill- och makrillkonserver,\nansjovis samt kaviar vid fabrik i\nGrundsund (Göteb. o. Bohus l.).\n\nTplpsrr.-adr.: Gå^öfiorden, Gruudsrmd.\nTelefon: 6. Postgiro: 9856. — Akt.-kap.:\n65,000 kr. Antal industriarb.: 20. —\nFirman etabl. 1925, bolag 1946.\n\nVerkst. dir.: Johan G. Petersson.\n\n\"AB. Gäddeglo Tegelbruk,\n\nVästervik.\n\nTillverkar mur- och taktegel samt\ndräneringsrör vid tegelbruk i Gäddeglo,\nVästervik.\n\nPostadr.: Västervik. Telegr.-adr.:\nGäddeglo, Västervik. Telefon: Västervik\n232. — Akt.-kap.: 80,000 kr. Antal\nindustriarb.: 35. Årstillv.: 1,5 milj. st.\ntegelvaror. — Firman etabl. 1904.\n\nVerkst. dir.: fru Hildur Holmström.\n\nDisp.: Axel Holmström.\n\n\"Cäddvikens Superfosfatfabrik,\n\nStockholm.\n\nSe Kooperativa Superfosfatfabriks AB.,\nStockholm.\n\nGällaryds Möbel- &amp; Träindustri AB.,\n\nSmål. Gällaryd.\n\nTillverkar möbler vid fabrik i\nSmålands Gällaryd (Jönköp. l.).\n\nTelefon: Gällaryd 43. Postgiro: 283004.\n—i-, Akt.-kap.: 51,000 kr. Antal\nindustriarb.: 17. — Bolaget grundat 1943.\n\nDisp.: verkm. Bernadotte Peterson.\n\n\"Gällivare Malmfält, Gällivare.\n\nSe Luossavaara-Kiirunavaara AB.,\nStockholm.\n\n\"Gällivare Bryggeri Kommanditbol»,\nE. Wåhlin &amp; Co., Gällivare.\n\nTillverkar malt- och läskedrycker samt\nmineralvatten vid skattepliktigt bryggeri\ni Gällivare (Norrb. l.).\n\nTelefon: 33 o. 333. Postgiro: 60844. —\nKommanditkai).: 10,000 kr. Antal\nindustriarb.: 20. Tillv.-värde pr år: 500,000\nkr. — Bryggeriet anlagt 1898.\n\nStyrelse: förste prov. läkare Olof\nWåhlin (ordf.), fröken G. Jansson, fru Elin\nWåhlin.\n\nVerkst. dir.: fru Elin Wåhlin.\n\nDisp.: Alvar Lydén.\n\nKamrer: fröken A.-S. Berglund.\n\nGällstads Hemindustri AB.,\n\nGällstad.\n\nTillverkar yllevaror såsom sockor,\nstrumpor, vantar, tröjor, slipovers, västar\noch bluskoftor vid trikåfabrik i Gällstad\n(Älvsb. l.).\n\nTelefon: 49. — Akt.-kap.: 70;000 kr.\nAntal industriarb.: 24 samt 232\nhemarbetare. Tillv.-värde pr år: 320,000 kr.\n— Firman etabl. 1930, bolag 1943.\n\nVerkst. dir.: fabr. Eric Höglund.\n\nK*",
    "structured": {
        "firms": [
            {
                "name": "Gåfvetorps Tegelbruk",
                "location": "Gåvetorp",
                "business": "Tillverkar murtegel, poröst och hög-poröst murtegel, beklädnadstegel samt dräneringsrör vid tegelbruk.",
                "contact": {
                    "phone": [
                        "Gåvetorp 26"
                    ],
                    "postgiro": "22142"
                },
                "financials": {
                    "employees": {
                        "industriarb": 35
                    },
                    "annual_turnover": "2 milj. st. tegel var or",
                    "foundation_year": 1800
                },
                "directors": {
                    "owner_and_ceo": "dr Arvid Aaby-Eriesson"
                }
            },
            {
                "name": "Gåragöls Stärkelse- & Sagofabrik",
                "location": "Hemsjö",
                "business": "Tillverkar potatismjöl, potatisgryn och sagogryn vid fabrik.",
                "contact": {
                    "phone": [
                        "Hemsjö 1"
                    ],
                    "telegraph": "Amylum, Karlshamn"
                },
                "financials": {
                    "employees": {
                        "industriarb": 10
                    },
                    "annual_production_value": "185,000 kr",
                    "foundation_year": 1879
                },
                "director": "fabr. Jöns Nilsson"
            },
            {
                "name": "Cårda Fabrikers AB.",
                "location": "Göteborg",
                "business": "Trikå- och strumpfabrik, bandfabrik, ullfärgeri samt briljantblekeri.",
                "products": "Tillverkar trikåvaror och strumpor i ylle, bomull samt konst- och natursilke, vävda och flätade ylle-, bomulls- och konstsilkeband samt resårband. Utför färgning och briljantblekning av ull och ullgarn samt färgning av annat löst textilmaterial.",
                "contact": {
                    "phone": "192560",
                    "postgiro": "41075",
                    "sales_offices": [
                        {
                            "location": "Stockholm",
                            "phone": "209926"
                        }
                    ]
                },
                "financials": {
                    "capital": "2,130,000 kr",
                    "employees": {
                        "industriarb": 577
                    },
                    "foundation_year": 1880,
                    "corporation_year": 1893
                },
                "board": [
                    {
                        "name": "Gustaf Werner",
                        "role": "ordf."
                    },
                    {
                        "name": "Åke Arvidius",
                        "role": "dir."
                    },
                    {
                        "name": "Frans H. Nilsson",
                        "role": "dir."
                    }
                ],
                "managing_director": "Åke Arvidius",
                "manager": "Hugo Kjellmer"
            },
            {
                "name": "AB. Gåsöfjordens Konservfabrik",
                "location": "Grundsund",
                "business": "Tillverkar sill- och makrillkonserver, ansjovis samt kaviar vid fabrik.",
                "contact": {
                    "phone": "6",
                    "postgiro": "9856"
                },
                "financials": {
                    "capital": "65,000 kr",
                    "employees": {
                        "industriarb": 20
                    },
                    "foundation_year": 1925,
                    "corporation_year": 1946
                },
                "managing_director": "Johan G. Petersson"
            },
            {
                "name": "AB. Gäddeglo Tegelbruk",
                "location": "Västervik",
                "business": "Tillverkar mur- och taktegel samt dräneringsrör vid tegelbruk.",
                "contact": {
                    "phone": "Västervik 232"
                },
                "financials": {
                    "capital": "80,000 kr",
                    "employees": {
                        "industriarb": 35
                    },
                    "annual_turnover": "1,5 milj. st. tegelvaror",
                    "foundation_year": 1904
                },
                "directors": {
                    "owner": "fru Hildur Holmström",
                    "manager": "Axel Holmström"
                }
            },
            {
                "name": "Cäddvikens Superfosfatfabrik",
                "location": "Stockholm",
                "business": "Se Kooperativa Superfosfatfabriks AB."
            },
            {
                "name": "Gällaryds Möbel- & Träindustri AB.",
                "location": "Smål. Gällaryd",
                "business": "Tillverkar möbler vid fabrik.",
                "contact": {
                    "phone": "Gällaryd 43",
                    "postgiro": "283004"
                },
                "financials": {
                    "capital": "51,000 kr",
                    "employees": {
                        "industriarb": 17
                    },
                    "foundation_year": 1943
                },
                "manager": "verkm. Bernadotte Peterson"
            },
            {
                "name": "Gällivare Bryggeri Kommanditbol»",
                "location": "Gällivare",
                "business": "Tillverkar malt- och läskedrycker samt mineralvatten vid skattepliktigt bryggeri.",
                "contact": {
                    "phone": [
                        "33",
                        "333"
                    ],
                    "postgiro": "60844"
                },
                "financials": {
                    "capital": "10,000 kr",
                    "employees": {
                        "industriarb": 20
                    },
                    "annual_production_value": "500,000 kr",
                    "foundation_year": 1898
                },
                "board": [
                    {
                        "name": "Olof Wåhlin",
                        "role": "ordf."
                    },
                    {
                        "name": "G. Jansson",
                        "role": "fröken"
                    },
                    {
                        "name": "Elin Wåhlin",
                        "role": "fru"
                    }
                ],
                "managing_director": "fru Elin Wåhlin"
            },
            {
                "name": "Gällstads Hemindustri AB.",
                "location": "Gällstad",
                "business": "Tillverkar yllevaror såsom sockor, strumpor, vantar, tröjor, slipovers, västar och bluskoftor vid trikåfabrik.",
                "contact": {
                    "phone": "49",
                    "postgiro": "70000 kr"
                },
                "financials": {
                    "capital": "70,000 kr",
                    "employees": {
                        "industriarb": 24,
                        "hemarbetare": 232
                    },
                    "annual_production_value": "320,000 kr",
                    "foundation_year": 1930
                },
                "managing_director": "fabr. Eric Höglund"
            }
        ]
    }
}