{
    "original": "Ranten—Record\n\nlefon: 234720. Postgiro: 57815.\nFabrikskontor: Falköping. Telegr.-adr.:\nRan-tenshatt, Falköping. Telefon: 156 o. 556.\nAvd.-kontor: Malmö, Söderg. 19.\n\nAkt.-kap.: 300,000 kr. Antal\nindustriarb.: 80. Tillv.-värde pr år: 1,500,000 kr.\n\nFirman etabl. 1916, bolag 1917 under\nnamn AB. Rantens Strå- &amp;\nFilthattfabrik, nuv. namn 1935.\n\nStyrelse: dir. Erik Thorssell (ordf.),\ndisp. Sten A. Andersson, köpm. R.\nKarlberg, adv. Linus Lindberg.\n\nVerkst. dir.: Erik Thorssell.\n\nKamrer: N. Wigzell (Stockholm).\n\nDisp. i Falköping: Sten A. Andersson.\n\nFörest, i Malmö: Allan Tullberg.\n\nAB. Rantens Saft- &amp; Vattenfabrik,\n\nFalköping.\n\nTillverkar läskedrycker, mineralvatten,\nsaft och sylt.\n\nTelefon: Falköping 55 o. 56. Postgiro:\nkap.: 27,000 kr. Arb.-antal: 8.\nTillv.-värde pr år: 45.000 kr. — Fabriken\nanlagd 1904, bolag 1937.\n\nChef: fröken Signe Holmen.\n\n*AB. Rantens Snickerifabrik,\n\nFalköping.\n\nTillverkar byggnadssnickerier och\ninredningar samt dörrar enligt\npatentskyddad konstruktion.\n\nTelefon: Falköping 55 o. 56. Postgiro:\n10066. — Akt.-kap.: 75,000 kr.\nArb.-antal: 15. Tillv.-värde pr år: 300,000 kr.\n— Fabriken anlagd 1885, bolag 1911.\n\nStyrelse o. disp.: Bengt Karmert.\n\n* Rantens Trikåindustri, Falköping.\n\nTillverkar dam- och herrunderkläder.\n\nTelefon: 739. Postgiro: 133154.\nRepresentant: Sam Millner, Stockholm,\nTeg-nérg. 35, telefon: 116192.\n\nAntal industriarb.: 10. Tillv.-värde pr\når: 150,000 kr. — Firman etabl. 1935.\n\nÄgare o. chef: fabr. Fredrik\nAllers-meier.\n\n*Rantzows Gymnast i kmaterlel,\n\nHjärnarp.\n\nSnickerifabrik i Hjärnarp (Kristianst.\n1.). Tillverkar såsom specialitet\ngymnastikredskap.\n\nTelefon: 47 o. 147. Repr.: Skånes\nGymnastikförbund, Kristianstad, telefon:\n1018. — Antal industriarb.: 20.\nTillv.-värde pr år: 200,000 kr. — Firman etabl.\n1925.\n\nÄgare o. chef: fabr. Fritiof Rantzow.\n\n*Ranå Tegelbruk, Ransäter.\n\nTillverkar murtegel vid tegelbruk i\nRansäter (Värml. l.).\n\nTelefon: 45. Postgiro: 274169. — Antal\nindustriarb.: 13. Årstillv.: 1,6 milj. st.\nmurtegel. — Tegelbruket anlagt är.’1906,\nnuv. ägare sedan 1937.\n\nÄgare: bruksäg. Gottfrid Sand walls\nsterbhus (Söderköping).\n\nPlatschef : tegelmäst. Lars O. Jönsson.\n\n* Albin Rapp, Konfektionsfabrik,\n\nÖrebro.\n\nKonfektionsfabriker i Örebro, Arboga,\nHallsberg och Strängnäs. Tillverkar\nkostymer och överrockar, popliiirockar,\ntrenchcoats, damkappor och -dräkter.\nVarumärke: »Rappson».\n\nHuvudkontor o. expedition: Örebro.\nTelefon: »Albin Rapp». Postgiro: 20733.\n— Antal industriarb.: 550. — Firman\ngrundad 1921.\n\nÄgare o. chef: fabr. Albin Rapp.\n\nAB. Rasco, Malmö.\n\nPappersförädlingsfabrik. Tillverkar\ngummerade förseglingsremsor, gummerat\npapper i ark och rullar, perforerade\netiketter i rullar, räknemaskins- och\nkassa-kvittorullar, reklamartiklar m. m.\nVarumärke: »Rasco». Bolaget driver även\nengroshandel med transparent papper\nm. m.\n\nKontor: Hjulhamnsg. 4. Telegr.-adr.:\nRäscobolaget, Malmö. Telefon: 72360.\nPostgiro: 14162. Försäljn.-kontor:\nGöteborg, Friggag. 4. Avd.-kontor:\nStockholm, Drottningg. 30.\n\nAkt.-kap.: 100,000 kr. Antal\nindustriarb.: 50. — Firman etabl. 1927 under\nnamn Rasch &amp; Arnesen AB., nuv. namn\n1938.\n\nVerkst. dir.: Carl Arnesen.\nRaus Stenkärlsfabrik, Råns.\n\nTillverkar saltglaserade stenkärl vid\nfabrik i Raus (Malmöh. l.).\n\nTelefon: Hälsingborg 90130. Antal\nindustriarb. 7. Tillv.-värde pr år: 46,000\nkr. — Firman etabl. 1911, står vid\nkalenderns tryckning under ombildände till\nbolag.\n\nÄgare: L. A. Johnssons sterbhus.\n\nRecord, Mek. Verkstaden, AB.,\n\nStockholm.\n\nSe Mek. Verkstaden Record AB.,\nStockholm.",
    "structured": {
        "1": {
            "name": "AB. Rantens Strå- & Filthattfabrik",
            "location": "Falköping",
            "business": "Tillverkning av hattar och filtar",
            "contact": {
                "office": "Rantenshatt, Falköping",
                "phone": [
                    "156",
                    "556"
                ],
                "postgiro": "57815",
                "factory_office": "Falköping",
                "factory_phone": "55"
            },
            "financials": {
                "capital": "300,000 kr",
                "employees": {
                    "Industriarb": 80
                },
                "annual_turnover": "1,500,000 kr"
            },
            "foundation_year": 1916,
            "corporation_year": 1917,
            "current_name_year": 1935,
            "board": [
                {
                    "name": "Erik Thorssell",
                    "role": "ordf."
                },
                {
                    "name": "Sten A. Andersson",
                    "role": "disp."
                },
                {
                    "name": "R. Karlberg",
                    "role": "köpm."
                },
                {
                    "name": "Linus Lindberg",
                    "role": "adv."
                }
            ],
            "manager": "Erik Thorssell"
        },
        "2": {
            "name": "AB. Rantens Saft- & Vattenfabrik",
            "location": "Falköping",
            "business": "Tillverkning av läskedrycker, mineralvatten, saft och sylt",
            "contact": {
                "phone": [
                    "55",
                    "56"
                ],
                "postgiro": "27,000 kr"
            },
            "financials": {
                "capital": "27,000 kr",
                "employees": {
                    "Arb.-antal": 8
                },
                "annual_turnover": "45,000 kr"
            },
            "foundation_year": 1904,
            "corporation_year": 1937,
            "manager": "fröken Signe Holmen"
        },
        "3": {
            "name": "AB. Rantens Snickerifabrik",
            "location": "Falköping",
            "business": "Tillverkning av byggnadssnickerier och inredningar samt dörrar",
            "contact": {
                "phone": [
                    "55",
                    "56"
                ],
                "postgiro": "10066"
            },
            "financials": {
                "capital": "75,000 kr",
                "employees": {
                    "Arb.-antal": 15
                },
                "annual_turnover": "300,000 kr"
            },
            "foundation_year": 1885,
            "corporation_year": 1911,
            "manager": "Bengt Karmert"
        },
        "4": {
            "name": "Rantens Trikåindustri",
            "location": "Falköping",
            "business": "Tillverkning av dam- och herrunderkläder",
            "contact": {
                "phone": "739",
                "postgiro": "133154"
            },
            "financials": {
                "employees": {
                    "Antal industriarb.": 10
                },
                "annual_turnover": "150,000 kr"
            },
            "foundation_year": 1935,
            "manager": "fabr. Fredrik Allers-meier"
        },
        "5": {
            "name": "Rantzows Gymnastikredskap",
            "location": "Hjärnarp",
            "business": "Tillverkning av gymnastikredskap",
            "contact": {
                "phone": [
                    "47",
                    "147"
                ]
            },
            "financials": {
                "employees": {
                    "Antal industriarb.": 20
                },
                "annual_turnover": "200,000 kr"
            },
            "foundation_year": 1925,
            "manager": "fabr. Fritiof Rantzow"
        },
        "6": {
            "name": "Ranå Tegelbruk",
            "location": "Ransäter",
            "business": "Tillverkning av murtegel",
            "contact": {
                "phone": "45",
                "postgiro": "274169"
            },
            "financials": {
                "employees": {
                    "Antal industriarb.": 13
                },
                "annual_production_value": "1,600,000 st. murtegel"
            },
            "foundation_year": 1906,
            "current_name_year": 1937,
            "owner": "bruksäg. Gottfrid Sand walls sterbhus",
            "manager": "tegelmäst. Lars O. Jönsson"
        },
        "7": {
            "name": "Albin Rapp, Konfektionsfabrik",
            "location": "Örebro",
            "business": "Tillverkning av kostymer, överrockar, poplinrockar, trenchcoats, damkappor och -dräkter",
            "contact": {
                "office": "Örebro"
            },
            "financials": {
                "employees": {
                    "Antal industriarb.": 550
                },
                "foundation_year": 1921,
                "manager": "fabr. Albin Rapp"
            }
        },
        "8": {
            "name": "AB. Rasco",
            "location": "Malmö",
            "business": "Pappersförädlingsfabrik",
            "contact": {
                "office": "Hjulhamnsg. 4",
                "postgiro": "14162",
                "sales_offices": [
                    {
                        "location": "Göteborg",
                        "phone": "Friggag. 4"
                    },
                    {
                        "location": "Stockholm",
                        "phone": "Drottningg. 30"
                    }
                ]
            },
            "financials": {
                "capital": "100,000 kr",
                "employees": {
                    "Antal industriarb.": 50
                }
            },
            "foundation_year": 1927,
            "current_name_year": 1938,
            "manager": "Carl Arnesen"
        },
        "9": {
            "name": "Raus Stenkärlsfabrik",
            "location": "Råns",
            "business": "Tillverkning av saltglaserade stenkärl",
            "contact": {
                "phone": "Hälsingborg 90130"
            },
            "financials": {
                "employees": {
                    "Antal industriarb.": 7
                },
                "annual_turnover": "46,000 kr"
            },
            "foundation_year": 1911,
            "owner": "L. A. Johnssons sterbhus"
        }
    }
}