{
    "original": "Olsson\n\nAkt.-kap.: 300,000 kr. Antal\nindustriarb.: 65. Tillv.-värde pr år: 1,050,000 kr.\n— Firman etabl. 1862, bolag 1937.\n\nStyrelse: boktr. Håkan Theodor\nOhlsson, boktr. Per-Håkan Ohlsson, fil. kand.\nSven Håkan Ohlsson.\n\nVerkst. dir.: Per-Håkan Ohlsson.\n\n*AB. Joh:s Olssons Skofabrik,\n\nÖrebro.\n\nTillverkar genomsydda, randsydda och\npliggade skodon. Specialiteter: pjäxor och\narbetskängor. Varumärken: »Jio» o.\n»Ed-lings».\n\nTelefon: 11334. Postgiro: 13999.\nEnsamförsälj.: AB. Carlsson &amp; Åqvist,\nÖrebro, telefon: »Carlssonåqvist».\n\nAkt.-kap.: 100,000 kr. Antal\nindustriarb.: 65. Tillv.-värde pr år: 1,200,000 kr.\n\nFabriken anlagd 1912, bolaget grundat\n1920.\n\nStyrelse: dir. Torsten Åqvist (ordf.),\n«disp. Erik Johansson, kontorschef\nHerbert Johnson.\n\nDisp.: Erik Johansson.\n\n*AB. Joh. Ohlssons Tekniska Fabrik,\n\nStockholm.\n\nTjärdestilleringsverk samt asfalt- och\ntjärpappfabriker vid Ulvsunda,\nStockholm. Tillverkar stenkolstjärprodukter\noch asfaltprodukter, impregneringsmedel,\ndesinfektionsmedel samt byggnadspapp.\nVarumärken: Anhydrol, Carlinum,\nKop-ralin, Hydropal, Lysterolit, Mammut,\n-Jotef, Uco, Carbosol och Antivermin.\n\nPostadr.: Stockholm 1. Telegr.-adr.:\nOhlssonfabrik, Stockholm. Telefon: 256881\n—86.\n\nAkt.-kap.: 530,200 kr. Antal\nindustriarb. : 30. Årstillv.: 6,000 ton. — Firman\ngrundad 1859, bolag 1899.\n\n# Styrelse: övering. Otto Stålhane (ordf.),\nfil. lic. Guy S:son Frey, civiling. Holger\nOhlsson, civiling. Torsten Ohlsson, fil.\nlic. Bertil Stålhane.\n\nVerkst. dir.: Torsten Ohlsson.\n\nKamrer: Algot Sandberg.\n\nFörsäljn.-chef: Erik Egander.\n\nChef f. exp.: Bengt Bengtson.\n\nDriftschef: Guy S:son Frey.\n\nDriftsing.: Holger Ohlsson.\n\nM. &amp; E. Ohlssons Klockgjuteri &amp;\nArmaturfabrik, Ystad.\n\nTillverkar kyrkklockor, klockspel,\nsignalklockor, metallgjutgods, askurnor»\nmekaniska och elektriska ringmaskiner\noch upphängningsarmatur för klockor,\njärnklockstolar samt belysningsarmatur.\n\nTelefon: 973 o. 1163. — Arb.-antal: 8.\nTillv.-värde pr ar: 150,000 kr. — Firman\netabl. 1805.\n\nÄgare o. chef: ing. Erland\nBröchner-Ohlsson.\n\n*0scar Ohlson, Byggnads AB.,\n\nBorås.\n\nSe Byggnads AB. Oscar Ohlson,\nBorås.\n\nOtto Olssons Rörformfabrik,\n\nBorrby.\n\nMek. verkstad och plåtslageri i Borrby\n(Kristianst. l.). Tillverkar\nbetongrörformar för brunnsringar, kulvertrör och\nmuffrör för gatubrunnar, cementtegel,\ncementhålsten och vägrör samt\nbetong-varumaskiner såsom vibrationsrörpressar\noch rörstampningsmaskiner.\n\nTelefon: 130. Postgiro: 169891. Repr. i\nNorge: A/S Betongprodukter, Oslo. —\nAntal industriarb.: 23. Tillv.-värde pr år:\n350,000 kr. — Firman etabl. 1908 under\nnamn Otto Olssons Smidesverkstad, nuv.\nnamn 1931.\n\nÄgare o. chef; fabr. Otto Olsson.\n\nDriftschef: Georg Olsson.\n\n0. J. Olsson &amp; Comp., Korkfabrik,\n\nHälsingborg.\n\nTillverkar flaskkork, spec. medicinkork.\n\nTelefon: 10138. Postgiro: 70748. —\nArb.-antal: 4. Tillv.-värde pr år: 120,000\nkr. — Firman grundad 1884.\n\nÄgare o. chef : ing. Reinhard Svensson.\n\nAB. 0. W. Olssons Såg- &amp; Hyvleri,\n\nBengtsfors.\n\nTillverkar sågade och hyvlade trävaror\nsamt listverk vid sågverk i Bengtsfors\n(Älvsb. l.).\n\nTelefon: 36. Postgiro: 70292. —\nAkt.-kap.: 100,000 kr. Antal industriarb.: 23.\nTillv.-värde pr år.: 175,000 kr. Årstillv.:\n600 stds trävaror. — Bolaget grundat\n1923.\n\nVerkst, dir.: disp. Ivar Olsson.\n\n*AB. P. Olsson &amp; Co., Hälsingborg.\n\nTegelbruk i Sennan (Hallands l.) samt\ntegelbruk i Rögle (Malmöh. l.).\nTillverkar fasad- och murtegel samt\ndräneringsrör. Specialitet: rött handslaget\nfasad-tegel. Firman driver även engroshandel\nmed byggnadsvaror.",
    "structured": {
        "1": {
            "name": "AB. Joh:s Olssons Skofabrik",
            "location": "Örebro",
            "business": "Tillverkning av skodon",
            "products": "Genomsydda, randsydda och pliggade skodon, specialiteter: pjäxor och arbetskängor, varumärken: Jio och Ed-lings",
            "contact": {
                "office": "Örebro",
                "phone": [
                    "11334"
                ],
                "postgiro": "13999",
                "sales_offices": [
                    {
                        "location": "AB. Carlsson & Åqvist, Örebro",
                        "phone": "Carlssonåqvist"
                    }
                ]
            },
            "financials": {
                "capital": "300,000 kr",
                "employees": {
                    "industriarb": 65
                },
                "annual_production_value": "1,050,000 kr"
            },
            "foundation_year": 1862,
            "corporation_year": 1937,
            "board": [
                {
                    "name": "Håkan Theodor Ohlsson",
                    "role": "Boktr"
                },
                {
                    "name": "Per-Håkan Ohlsson",
                    "role": "Boktr"
                },
                {
                    "name": "Sven Håkan Ohlsson",
                    "role": "Fil. kand."
                }
            ],
            "director": "Per-Håkan Ohlsson"
        },
        "2": {
            "name": "AB. Joh. Ohlssons Tekniska Fabrik",
            "location": "Stockholm",
            "business": "Tjärdestillering och tillverkning av stenkolstjärprodukter",
            "products": "Stenkolstjärprodukter, asfaltprodukter, impregneringsmedel, desinfektionsmedel, byggnadspapp",
            "contact": {
                "office": "Stockholm 1",
                "telegraph": "Ohlssonfabrik, Stockholm",
                "phone": "256881-86",
                "postgiro": "N/A"
            },
            "financials": {
                "capital": "530,200 kr",
                "employees": {
                    "industriarb": 30
                },
                "annual_turnover": "N/A",
                "annual_production_value": "6,000 ton"
            },
            "foundation_year": 1859,
            "corporation_year": 1899,
            "board": [
                {
                    "name": "Torsten Åqvist",
                    "role": "Dir."
                },
                {
                    "name": "Erik Johansson",
                    "role": "Disp."
                },
                {
                    "name": "Herbert Johnson",
                    "role": "Kontorschef"
                }
            ],
            "director": "Torsten Ohlsson"
        },
        "3": {
            "name": "M. & E. Ohlssons Klockgjuteri & Armaturfabrik",
            "location": "Ystad",
            "business": "Tillverkning av klockor, klockspel, metallgjutgods, elektriska ringmaskiner och belysningsarmatur",
            "products": "Kyrkklockor, klockspel, signalklockor, metallgjutgods, askurnor, järnklockstolar, belysningsarmatur",
            "contact": {
                "office": "Ystad",
                "phone": [
                    "973",
                    "1163"
                ],
                "postgiro": "N/A"
            },
            "financials": {
                "capital": "N/A",
                "employees": {
                    "arb": 8
                },
                "annual_production_value": "150,000 kr"
            },
            "foundation_year": 1805,
            "board": [
                {
                    "name": "Otto Stålhane",
                    "role": "Övering."
                },
                {
                    "name": "Guy S:son Frey",
                    "role": "Fil. lic."
                },
                {
                    "name": "Holger Ohlsson",
                    "role": "Civiling."
                },
                {
                    "name": "Torsten Ohlsson",
                    "role": "Civiling."
                },
                {
                    "name": "Bertil Stålhane",
                    "role": "Fil. lic."
                }
            ],
            "owner": "Ing. Erland Bröchner-Ohlsson"
        },
        "4": {
            "name": "Otto Olssons Rörformfabrik",
            "location": "Borrby",
            "business": "Mekanisk verkstad och plåtslageri",
            "products": "Betongrörformar, brunnsringar, kulvertrör, gatubrunnar, cementtegel, cementhålsten, vägrör, betong-varumaskiner",
            "contact": {
                "office": "Borrby",
                "phone": [
                    "130"
                ],
                "postgiro": "169891",
                "sales_offices": [
                    {
                        "location": "A/S Betongprodukter, Oslo",
                        "phone": "N/A"
                    }
                ]
            },
            "financials": {
                "capital": "N/A",
                "employees": {
                    "industriarb": 23
                },
                "annual_production_value": "350,000 kr"
            },
            "foundation_year": 1908,
            "board": [
                {
                    "name": "Otto Olsson",
                    "role": "Fabr."
                },
                {
                    "name": "Georg Olsson",
                    "role": "Driftschef"
                }
            ]
        },
        "5": {
            "name": "O. J. Olsson & Comp., Korkfabrik",
            "location": "Hälsingborg",
            "business": "Tillverkning av flaskkork",
            "products": "Medicinkork",
            "contact": {
                "office": "Hälsingborg",
                "phone": "10138",
                "postgiro": "70748"
            },
            "financials": {
                "capital": "N/A",
                "employees": {
                    "arb": 4
                },
                "annual_production_value": "120,000 kr"
            },
            "foundation_year": 1884,
            "owner": "Ing. Reinhard Svensson"
        },
        "6": {
            "name": "AB. 0. W. Olssons Såg- & Hyvleri",
            "location": "Bengtsfors",
            "business": "Tillverkning av sågade och hyvlade trävaror",
            "contact": {
                "office": "Bengtsfors",
                "phone": [
                    "36"
                ],
                "postgiro": "70292"
            },
            "financials": {
                "capital": "100,000 kr",
                "employees": {
                    "industriarb": 23
                },
                "annual_production_value": "175,000 kr",
                "annual_turnover": "600 stds trävaror"
            },
            "corporation_year": 1923,
            "director": "Ivar Olsson"
        }
    }
}