{
    "original": "Hagberg—Hagström\n\nStyrelse: landsfiskal E. M. Almgren\n(ordf.), ing. Hilding Jehander, disp.\nArvid Lyckman.\n\nVerJcst. dir.: Arvid Lyckman.\n\nTegelmäst.: Bengt Lyckman.\n\n\"Knut Hagberg, Fabriks AB.,\n\nNorrköping.\n\nUllspinneri och väveri. Tillverkar\nhelylletyger såsom kommiss, satin och\ndiagonal, foulé, drapé, eskimå, paletå,\nserge, kamgarnstyger m. m. samt\nullgarner för eget behov. Varumärke:\n»Domino».\n\nTelegr.-adr.: Knut, Norrköping.\nTelefon: 20090. Postgiro: 11090. Repr. i\nStockholm: John André, Skönviksvägen\n243, Stureby. Telefon: 495853.\n\nAkt.-kap.: 300.000 kr. Antal\nindustriarb.: 45. Tillv.-värde pr år: 800,000 kr.\n— Firman etabl. 1850, nuvarande bolag\n1918.\n\nStyrelse: fabr. Birger K:son Hagberg,\nfru Karin Hagberg, dir. Knut-Fredrik\nK:son Hagberg.\n\nVerkst. dir.: K.-F. K:son Hagberg.\n\nIvar Hageberg, Metall AB.,\n\nHillerstorp.\n\nSe Metall AB. Ivar Hageberg,\nHillerstorp.\n\n’ HagelIn &amp; Larsson, Ingenjörsfirman,\n\nGöteborg.\n\nSe Ingenjörsfirman Hagelin &amp; Larsson,\nGöteborg.\n\nHageltorns, Bror Hageltorn,\n\nHälsingborg.\n\nSe Fabriks AB. Hageltorns,\nHälsingborg.\n\n\"Hagfors Järnverk, Hagfors.\n\nSe Uddeholms AB., Uddeholm.\n\n\"Haggårdens Kalkbruk, Kinnemalma.\n\nSe AB. Västergötlands Förenade\nKalkindustrier, Falköping.\n\n\"Haglund &amp; Söner AB., Falköping.\n\nRullgardinsfabrik och knappfabrik.\nTillverkar rullgardiner och\nrullgardinskäppar av trä och metall med tillhörande\nbeslag, även för automobiler, bussar och\njärnvägsvagnar samt knappformar, knapp-\n\nslagningsmaskiner och knappar.\nVarumärken: »Eclipse», »Alliance», »Mercur»\no. »Hagex».\n\nTelegr.-adr.: Haglunds, Falköping.\nTelefon: 14. Postgiro: 10478.\n\nAkt.-kap.: 805,000 kr. Antal\nindustriarb.: 120. Tillv.-värde pr år: 1,400,000\nkr. — Firman etabl. 1885, bolag 1908.\n\nStyrelse: ing. Ernst Haglund, dir.\nJosef Haglund, disp. Titus Haglund.\n\nVerJcst. dir.: Josef Haglund.\n\n\"L. Haglund &amp; Co., Gävle.\n\nHatt-, möss- och pälsvarufabrik.\nTillverkar damhattar, felbhattar, tyg- och\npälsmössor samt pälskappor.\n\nTelegr.-adr.: Elhå, Gävle. Telefon:\n5780—82. Postgiro: 22366.\n\nAntal industriarb.: 150. Tillv.-värde pr\når: 1,000,000 kr. — Firman etabl. 1872.\n\nÄgare: fabr. Sven Haglund o. fabr.\nBror Haglund.\n\nDisp.: Bengt Haglund.\n\nFörsäljn.-chef: Lars Haglund.\n\n\"AB. Albin Hagström, Älvdalen.\n\nMusikinstrumentfabrik i Älvdalen\n(Kopparb. l.). Tillverkar dragspel och\ngrammofoner. Varumärken för dragspel:\n»Hagström», »Excellent», »Castello»,\n»Granesso», »Skandia» o. »Accordia».\n\nTelegr.-adr.: Hagstrombolag, Älvdalen.\nTelefon: »Hagströmbolaget». Postgiro:\n7781. Butiker: i Stockholm: St. Nyg. 32,\ntelefon: 106282; i Göteborg: S. Larmg.\n4, telefon: 114711; i Malmö, Davidshallsg.\n27, telefon: 31160.\n\nAkt.-kap.: 700,000 kr. Antal\nindustriarb.: 200. Tillv.-värde pr år: 2,000,000 kr.\n\n—\tFirman, etabl. 1924, bolag 1936, äger\nAlbin Hagströms Musikaffär i Stockholm\nAB. (se detta bolag).\n\nStyrelse: fru Agnes Hagström, dir,\nAlbin Hagström.\n\nVerJcst. dir.: Albin Hagström.\n\nAlbin Hagströms Musikaffär i\nStockholm AB., Stockholm.\n\nTillverkar dragspel vid fabrik i Solna\n(Sthlms l.). Varumärke: »Accordia».\n\nHuvudkontor: Stockholm, Drottningg.\n57, telefon: 118433. Postgiro: 54788.\nFabrikskontor: Solna, telefon: Stockholm\n274520.\n\nAkt.-kap.: 10,000 kr. Antal\nindustriarb.: 50. Tillv.-värde pr år: 400,000 kr.\n\n—\tBolaget, grundat 1938, är dotterbolag\ntill AB. Albin Hagström, Älvdalen.\n\nStyrelse o. verJcst. dir.: Albin\nHagström.\n\nFörsäljn.-chef: Nils Ånghammar.\n\nFabriks förest.: Bele Olsson.\n\n206*",
    "structured": {
        "1": {
            "name": "Knut Hagberg, Fabriks AB.",
            "location": "Norrköping",
            "business": "Ullspinneri och väveri",
            "products": "Tillverkar helylletyger såsom kommiss, satin och diagonal, foulé, drapé, eskimå, paletå, serge, kamgarnstyger m.m. samt ullgarner för eget behov.",
            "contact": {
                "office": "",
                "phone": [
                    "20090"
                ],
                "postgiro": "11090",
                "head_office": "",
                "sales_offices": [
                    {
                        "location": "Stockholm",
                        "phone": "495853"
                    }
                ],
                "telegraph": "Knut, Norrköping"
            },
            "financials": {
                "capital": "300,000 kr",
                "annual_turnover": "800,000 kr",
                "annual_production_value": "800,000 kr"
            },
            "foundation_year": 1850,
            "current_name_year": 1918
        },
        "2": {
            "name": "Ivar Hageberg, Metall AB.",
            "location": "Hillerstorp",
            "business": "Se Metall AB. Ivar Hageberg"
        },
        "3": {
            "name": "HagelIn & Larsson, Ingenjörsfirman",
            "location": "Göteborg",
            "business": "Se Ingenjörsfirman Hagelin & Larsson, Göteborg"
        },
        "4": {
            "name": "Hageltorns, Bror Hageltorn",
            "location": "Hälsingborg",
            "business": "Se Fabriks AB. Hageltorns, Hälsingborg"
        },
        "5": {
            "name": "Hagfors Järnverk",
            "location": "Hagfors",
            "business": "Se Uddeholms AB., Uddeholm"
        },
        "6": {
            "name": "Haggårdens Kalkbruk",
            "location": "Kinnemalma",
            "business": "Se AB. Västergötlands Förenade Kalkindustrier, Falköping"
        },
        "7": {
            "name": "Haglund & Söner AB.",
            "location": "Falköping",
            "business": "Rullgardinsfabrik och knappfabrik. Tillverkar rullgardiner och rullgardinskäppar av trä och metall med tillhörande beslag, även för automobiler, bussar och järnvägsvagnar samt knappformar, knappslagningsmaskiner och knappar."
        },
        "8": {
            "name": "L. Haglund & Co.",
            "location": "Gävle",
            "business": "Hatt-, möss- och pälsvarufabrik. Tillverkar damhattar, felbhattar, tyg- och pälsmössor samt pälskappor."
        },
        "9": {
            "name": "AB. Albin Hagström",
            "location": "Älvdalen",
            "business": "Musikinstrumentfabrik i Älvdalen (Kopparb. 1.). Tillverkar dragspel och grammofoner."
        },
        "10": {
            "name": "Albin Hagströms Musikaffär i Stockholm AB.",
            "location": "Stockholm",
            "business": "Tillverkar dragspel vid fabrik i Solna (Sthlms l.)."
        }
    }
}