{
    "original": "Forsa—Forserum\n\nTelegr.-adr.: Fors, Nyköping. Telefon:\n6. Postgiro: 30115.\n\nAkt.-kap.: 600,000 kr. Antal\nindustriarb.: 285. Tillv.-värde pr år: 4,500,000 kr.\n— Bolaget grundat 1886. Svenska\nYllekoncernen AB. är huvudintressent i\nbolaget.\n\nStyrelse: disp. C. G. Lundberg,\nbankdir. E. Löwenhard, dir. Gösta Åhlén.\n\nVerkst. dir.: C. G. Lundberg.\n\nPlatschef: H. Herbst.\n\n* Forsa Linspinneri, Sörforsa.\n\nSe Holma-Helsinglands Linspinneri- &amp;\nVäfveri AB., Sörforsa och Madängsholm.\n\n* Forsbacka Jernverks AB.,\n\nForsbacka.\n\nJärnverk med masugnar, bessemer- och\nmartinverk, göt-, medium-, fin- och\nrörvalsverk, manufaktursmedja, gjuteri och\nmek. verkstad vid Forsbacka (Gävleb. l.).\n\nBolagets verk och anläggningar\narrenderas av Fagersta Bruks AB. Betr.\ntillverkning och försäljning, se sistnämnda\nbolag.\n\nTelegr.-adr.: Forsbacka, Gävle.\nTelefon: Forsbacka 180—182. — Akt.-kap.:\n1,000,000 kr. — Bruket anlades på\n1500-talet.\n\nStyrelse: disp. Hj. Åselius (ordf.),\ndir. Nils Elfström, övering. Einar\nSjögren.\n\nPlatschef: Einar Sjögren.\n\nAlfr. Forsberg, Matfors.\n\nSmides- och kättingfabrik i Matfors\n(Västernorrl. l.). Tillverkar kätting och\nf lottn i ngssmiden.\n\nTelefon: 2. Postgiro: 144025. —\nFör-säljn.: Kättingfabrikernas\nFörsäljningskontor, Stockholm, Hamner. 22; telefon:\n207535. — Antal industriarb.: 25.\nÅrstillv.: 500 ton kätting o. smiden. —\nFirman etabl. 1888.\n\nÄgare o. chef: ing. Bertil Forsberg.\n\n*Axel Forsberg, Choklad- &amp;\nKonfektfabrik AB., Göteborg.\n\nTillverkar choklad, karameller,\nkonfi-tyrer, lakrits, marmelad och safter.\nVarumärke: »Lidol».\n\nKontor: Carl Johansg. 104—106.\nTelegr.-adr.: Lidol, Göteborg. Telefon:\n170675—78. Postgiro: 40263.\n\nAkt.-kap.: 200,000 kr. Antal industri-\n\narb.: 75. Tillv.-värde pr år: 1,400,000 kr,\n\n—\tFirman etabl. 1876, bolag 1933.\nStyrelse: disp. Alf Forsberg, fabr. Axel\n\nForsberg.\n\nVerkst. dir.: Axel Forsberg.\nDisp.: Alf Forsberg.\n\nFr. Forsbergs Borstfabrik,\n\nBodafors.\n\nTillverkar borstar och penslar vid\nfabrik i Bodafors (Jönköp. l.).\n\nTelefon: »Forsbergs borst». Postgiro:\n32579. — Antal industriarb.: 54.\nTillv.-värde pr år: 795,000 kr. — Firman etabl,\n1910.\n\nÄgare o. chef: fabr. Frans Forsbergs\nsterbhus.\n\nDisp.: Rich. Forsberg.\n\nForsbo Yllefabrik, Arbrå.\n\nSpinneri, väveri och färgeri i Arbrå\n(Gävleb. l.).\n\nTillverkar sängfiltar och handelsgarn,\nvadmal, sporttyger, hästfiltar och vadd.\nUtför kemisk tvätt, färgning samt\nlön-spinning.\n\nTelefon: 32. Postgiro: 173418. —\nAntal industriarb.: 40. Tillv.-värde pr år:\n600 000 kr. — Fabriken anlagd 1879.\n\nÄgare o. chefer: fabr. Rune Rydahl o.\nfabr. Gunnar Rydahl.\n\nForserums Mek. Verkstads AB.,\n\nForserum.\n\nMek. verkstad i Forserum (Jönköp, l.).\nTillverkar hushållsvågar, brevvågar,\ndecimal- och skjutviktsvågar, taffelvågar,\nanalysvågar samt besman.\n\nTelefon: Forsernm 15. — Akt.-kap.:\n32,000 kr. Antal industriarb.: 80. —\nBolaget grundat 1899.\n\nStyrelse: civiling. Rob. Lindeli (ordf.),\nherr David Lindeli, herr Olof Lindell.\nVerkst. dir.: Rob. Lindell.\nPlatschef: David Lindell.\n\nForserums Säng. &amp; Svarverifabrik,\n\nForserum.\n\nTillverkar barn- och turistsängar vid\nfabrik i Forserum (Jönköp. l.).\n\nTelefon: 67, 107 o. 137. Antal\nindustriarb.: 68. Tillv.-värde pr år: 900,000 kr.\n\n—\tFirman etabl. 1932.\n\nÄgare o. chef: fabr. Werner Karlsson.\n\n* Forserums Yxfabrik, AB.,\n\nStockholm.\n\nSmidesfabrik i Forserum (Jönköp. l.).\nTillverkar yxor och bilor.",
    "structured": {
        "1": {
            "name": "Forsa—Forserum",
            "location": "Fors, Nyköping",
            "business": "Yllekoncernen",
            "contact": {
                "telegraph": "Fors, Nyköping",
                "postgiro": "30115",
                "head_office": "Fors, Nyköping"
            },
            "financials": {
                "capital": "600,000 kr",
                "employees": {
                    "industriarb": 285
                },
                "annual_turnover": "4,500,000 kr",
                "annual_production_value": "4,500,000 kr"
            },
            "foundation_year": 1886,
            "board": [
                {
                    "name": "C. G. Lundberg",
                    "role": "disp."
                },
                {
                    "name": "E. Löwenhard",
                    "role": "bankdir."
                },
                {
                    "name": "Gösta Åhlén",
                    "role": "dir."
                }
            ],
            "owners": [
                "Svenska Yllekoncernen AB"
            ],
            "director": "C. G. Lundberg",
            "managing_director": "C. G. Lundberg",
            "sales_manager": "H. Herbst"
        },
        "2": {
            "name": "Forsbacka Jernverks AB.",
            "location": "Forsbacka, Gävle",
            "business": "Järnverk",
            "contact": {
                "telegraph": "Forsbacka, Gävle",
                "phone": "Forsbacka 180—182",
                "postgiro": "Not available",
                "office": "Forsbacka, Gävle"
            },
            "financials": {
                "capital": "1,000,000 kr"
            },
            "corporation_year": 1500,
            "board": [
                {
                    "name": "Hj. Åselius",
                    "role": "disp."
                },
                {
                    "name": "Nils Elfström",
                    "role": "dir."
                },
                {
                    "name": "Einar Sjögren",
                    "role": "övering."
                }
            ],
            "owners": [
                "Fagersta Bruks AB"
            ],
            "director": "Einar Sjögren"
        },
        "3": {
            "name": "Alfr. Forsberg, Matfors",
            "business": "Smides- och kättingfabrik",
            "location": "Matfors, Västernorrl",
            "contact": {
                "phone": "2",
                "postgiro": "144025"
            },
            "financials": {
                "employees": {
                    "industriarb": 25
                },
                "annual_production_value": "500 ton"
            },
            "foundation_year": 1888,
            "owner": "ing. Bertil Forsberg"
        },
        "4": {
            "name": "Axel Forsberg, Choklad- & Konfektfabrik AB.",
            "business": "Choklad- & Konfektfabrik",
            "location": "Göteborg",
            "contact": {
                "office": "Carl Johansg. 104—106",
                "telegraph": "Lidol, Göteborg",
                "phone": "170675—78",
                "postgiro": "40263"
            },
            "financials": {
                "capital": "200,000 kr",
                "employees": {
                    "industriarb": 75
                },
                "annual_production_value": "1,400,000 kr"
            },
            "foundation_year": 1876,
            "corporation_year": 1933,
            "board": [
                {
                    "name": "Alf Forsberg",
                    "role": "disp."
                },
                {
                    "name": "Axel Forsberg",
                    "role": "fabr."
                }
            ],
            "director": "Axel Forsberg",
            "managing_director": "Axel Forsberg"
        },
        "5": {
            "name": "Fr. Forsbergs Borstfabrik, Bodafors",
            "business": "Borstar och penslar",
            "location": "Bodafors, Jönköp",
            "contact": {
                "phone": "Forsbergs borst",
                "postgiro": "32579"
            },
            "financials": {
                "employees": {
                    "industriarb": 54
                },
                "annual_production_value": "795,000 kr"
            },
            "foundation_year": 1910,
            "owner": "fabr. Frans Forsbergs sterbhus",
            "director": "Rich. Forsberg"
        },
        "6": {
            "name": "Forsbo Yllefabrik, Arbrå",
            "business": "Spinneri, väveri och färgeri",
            "location": "Arbrå, Gävleb",
            "contact": {
                "phone": "32",
                "postgiro": "173418"
            },
            "financials": {
                "employees": {
                    "industriarb": 40
                },
                "annual_production_value": "600,000 kr"
            },
            "foundation_year": 1879,
            "owners": [
                "fabr. Rune Rydahl",
                "fabr. Gunnar Rydahl"
            ]
        },
        "7": {
            "name": "Forserums Mek. Verkstads AB.",
            "business": "Mek. verkstad",
            "location": "Forserum, Jönköp",
            "contact": {
                "phone": "Forserum 15"
            },
            "financials": {
                "capital": "32,000 kr",
                "employees": {
                    "industriarb": 80
                }
            },
            "foundation_year": 1899,
            "board": [
                {
                    "name": "civiling. Rob. Lindeli",
                    "role": "ordf."
                },
                {
                    "name": "David Lindeli",
                    "role": "herr"
                },
                {
                    "name": "Olof Lindell",
                    "role": "herr"
                }
            ],
            "director": "Rob. Lindell",
            "managing_director": "Rob. Lindell",
            "sales_manager": "David Lindell"
        },
        "8": {
            "name": "Forserums Säng. & Svarverifabrik",
            "business": "Tillverkar barn- och turistsängar",
            "location": "Forserum, Jönköp",
            "contact": {
                "phone": "67, 107, 137"
            },
            "financials": {
                "employees": {
                    "industriarb": 68
                },
                "annual_production_value": "900,000 kr"
            },
            "foundation_year": 1932,
            "owner": "fabr. Werner Karlsson"
        },
        "9": {
            "name": "Forserums Yxfabrik, AB.",
            "business": "Smidesfabrik",
            "location": "Forserum, Jönköp",
            "contact": {
                "office": "Stockholm"
            },
            "financials": {
                "capital": "Not available"
            },
            "foundation_year": "Not available"
        }
    }
}