{
    "original": "T ornva 11—Torsvik\n\nHuvudkontor: Förmansvägen 19,\nÅr-stadalshamnen; postadr.: Stockholm 9.\nTelegr.-adr.: Tornborgs, Stockholm.\nTelefon: »Törnborg &amp; Lundberg». Postgiro:\n51240. Avd.-kontor: Göteborg,\nSkeppsbro-huset, telefon: 133072; Malmö:\nSkeppsbron 7, telefon: 11170.\n\nAkt.-kap.: 825,000 kr. Antal\nindustriarb.: 43. — Firman etabl. 1882, bolag\n1907.\n\nStyrelse: ing. Walter Hesselman\n(ordf.), ing. Gottfrid Mattsson.\n\nVerkst. dir.: W. Hesselman.\n\nTornvalls Konfektlons AB.,\n\nSödertälje.\n\nTillverkar herrkläder samt damdräkter.\nVarumärken: »Tornkläder» o. »Tornman».\n\nTelegr.-adr. o. telefon: Tornkläder,\nSödertälje. Postgiro: 11089.\n\nAkt.-kap.: 410,000 kr. Antal\nindustriarb.: 160. Tillv.-värde pr år: 2,500,000 kr.\n\nFirman etabl. 1919 i Norrköping under\nnamn Konfektions AB. Herrkläder,\nnamnförändring och överflyttning till\nSödertälje 1933.\n\nStyrelse: dir. Eric Tornvall (ordf.),\nlagerchef R. Börjesson, kamrer Gustaf\nÅlund.\n\nVerkst. dir.: Eric Tornvall.\n\n*Torpa Tegelbruks AB-, Göteborg.\n\nTegelbruk vid Torpa, Skrehall (Älvsb.\n1.). Tillverkar murtegel och dräneringsrör.\n\nKontor: Göteborg, Kj^rkog. 4. Telefon:\n131328.\n\nAkt.-kap.; 20,000 kr. Antal\nindustriarb.: 25. Årstillv.: 3 milj. st. tegel. —\nBolaget grundat 1928.\n\nStyrelse: kapten*Hilding Ström (ordf.),\ndisp. R. Nymansson, bruksäg. Gunnar\nWulf.\n\nDisp.: R. Nymansson.\n\nAB. Torpa Trikåfabrik, Laxå.\n\nTillverkar herrunderkläder vid fabrik\ni Laxå samt damunderkläder, jumpers\noch sportartiklar vid fabrik i Vretstorp\n(båda i Örebro l.).\n\nHuvudkontor: Laxå. Telefon: 211.\nPostgiro: 30382. Avd.-kontor: Vretstorp.\nTelefon: 68.\n\nAkt.-kap.: 150,000 kr. Antal\nindustri-»rb.: 25. Tillv.-värde pr år: 200,000 kr.\n- Bolaget grundat 1922.\nVerkst. dir.: And. Andersson.\n\"Disp.: Göran Tärby.\n\nAB. Torps Mek. Verkstäder,\n\nTorpsbruk.\n\nGjuteri och mek. verkstad med\nsnickerifabrik vid Torpsbruk (Kronob. l.).\nTillverkar enkel- och dubbelrensande\ntröskverk, råoljemotorer, lokomobiler,\nångpannor samt automatiska bobinmaskiner,\nsågmaskiner m. m. Bolaget driver jämväl\nkvarn- och sågverksrörelse.\n\nTelegr.-adr.: Brukskontoret, Torpsbruk.\nTelefon: 1 o. 9. Postgiro: 13768.\n\nAkt.-kap.: 100,000 kr. Antal\nindustriarb.: 80. Tillv.-värde pr år: 550,000 kr.\n— Bolaget grundat 1858, ombildat 1933.\n\nDisp.: Manfred Johansson.\n\n\"Torsby Kraftstation, Torsby.\n\nSe Billeruds AB., Säffle.\n\nAB. Torshaga Strumpfabrik,\n\nBorås.\n\nTillverkar damstrumpor.\n\nTelefon: 12557. Postgiro: 135558.\n\nAkt.-kap.: 30,000 kr. Arb.-antal: 5.\nTillv.-värde pr år: 35,000 kr. — Bolaget\ngrundat 1926.\n\nVerkst. dir.: civilekonom Gunnar\nLindahl.\n\n\"Torshags Bomullsspinneri, Åby.\n\nSe Stockholms Bomullsspinneri och\nVäfveri AB., Stockholm.\n\nTorshälla Sågbladsfabrik,\n\nTorshälla.\n\nTillverkar cirkelsågar för trä- och\nmetallbearbetning, stock- och issågar,\nkedjesågar, ram- och bandsågblad, rälssågblad\nm. fl. sågblad samt hugg- och\nbarkmaskin-knivar för trämassefabriker,\nmaskinhyvel-järn, cirkelknivar och\nhackelsemaskinkni-var, trä- och metallfräsar, skiftnycklar\nsamt excenter- och hävstångsplåtsaxar\nm. m. Firman driver jämväl\nbetongvaru-fabrik vid Folkesta (Södermanl. l.) med\nförsäljning av gjut- och kärnsand.\n\nTelegr.-adr.: Sågfabriken, Torshälla.\nTelefon: Eskilstuna 55005. Postgiro:\n140505. — Tillv.-värde pr år: 150,000 kr.\n— Firman etabl. 1881.\n\nÄgare o. chef: ing. Rune Alison.\n\n\"Torsviks AB., Norrahammar.\nSe Thorsviks AB., Norrahammar.",
    "structured": {
        "firms": [
            {
                "name": "Tornva 11—Torsvik",
                "location": "Södertälje",
                "contact": {
                    "office": "Förmansvägen 19",
                    "telegraph": "Tornborgs, Stockholm",
                    "postgiro": "51240",
                    "head_office": "Förmansvägen 19, År-stadalshamnen, Stockholm 9",
                    "sales_offices": [
                        {
                            "location": "Göteborg",
                            "phone": "133072"
                        },
                        {
                            "location": "Malmö",
                            "phone": "11170"
                        }
                    ]
                },
                "financials": {
                    "capital": "825,000 kr",
                    "employees": {
                        "industriarb": 43
                    },
                    "annual_turnover": "N/A",
                    "annual_production_value": "N/A"
                },
                "foundation_year": 1882,
                "corporation_year": 1907,
                "board": [
                    {
                        "name": "ing. Walter Hesselman",
                        "role": "ordförande"
                    },
                    {
                        "name": "ing. Gottfrid Mattsson",
                        "role": "N/A"
                    }
                ],
                "director": "W. Hesselman"
            },
            {
                "name": "Tornvalls Konfektlons AB.",
                "location": "Södertälje",
                "products": "Tillverkar herrkläder samt damdräkter. Varumärken: »Tornkläder» o. »Tornman».",
                "contact": {
                    "office": "N/A",
                    "telegraph": "Tornkläder, Södertälje",
                    "postgiro": "11089"
                },
                "financials": {
                    "capital": "410,000 kr",
                    "employees": {
                        "industriarb": 160
                    },
                    "annual_turnover": "2,500,000 kr",
                    "annual_production_value": "N/A"
                },
                "foundation_year": 1919,
                "board": [
                    {
                        "name": "dir. Eric Tornvall",
                        "role": "ordförande"
                    },
                    {
                        "name": "lagerchef R. Börjesson",
                        "role": "N/A"
                    },
                    {
                        "name": "kamrer Gustaf Ålund",
                        "role": "N/A"
                    }
                ],
                "director": "Eric Tornvall"
            },
            {
                "name": "Torpa Tegelbruks AB",
                "location": "Göteborg",
                "business": "Tillverkar murtegel och dräneringsrör.",
                "contact": {
                    "office": "Kj^rkog. 4",
                    "postgiro": "N/A"
                },
                "financials": {
                    "capital": "20,000 kr",
                    "employees": {
                        "industriarb": 25
                    },
                    "annual_turnover": "N/A",
                    "annual_production_value": "3 milj. st. tegel"
                },
                "corporation_year": 1928,
                "board": [
                    {
                        "name": "kapten*Hilding Ström",
                        "role": "ordförande"
                    },
                    {
                        "name": "disp. R. Nymansson",
                        "role": "N/A"
                    },
                    {
                        "name": "bruksäg. Gunnar Wulf",
                        "role": "N/A"
                    }
                ],
                "director": "N/A"
            },
            {
                "name": "AB. Torpa Trikåfabrik",
                "location": "Laxå",
                "products": "Tillverkar herrunderkläder samt damunderkläder, jumpers och sportartiklar.",
                "board": [
                    {
                        "name": "N/A",
                        "role": "ordförande"
                    }
                ],
                "director": "And. Andersson"
            },
            {
                "name": "AB. Torps Mek. Verkstäder",
                "location": "Torpsbruk",
                "business": "Gjuteri och mek. verkstad med snickerifabrik vid Torpsbruk (Kronob. l.). Tillverkar enkel- och dubbelrensande tröskverk, råoljemotorer, lokomobiler, ångpannor samt automatiska bobinmaskiner, sågmaskiner m. m.",
                "contact": {
                    "office": "Brukskontoret, Torpsbruk",
                    "postgiro": "13768"
                },
                "financials": {
                    "capital": "100,000 kr",
                    "employees": {
                        "industriarb": 80
                    },
                    "annual_turnover": "N/A",
                    "annual_production_value": "550,000 kr"
                },
                "corporation_year": 1933,
                "board": [
                    {
                        "name": "N/A",
                        "role": "ordförande"
                    }
                ],
                "director": "N/A"
            },
            {
                "name": "AB. Torshaga Strumpfabrik",
                "location": "Borås",
                "products": "Tillverkar damstrumpor.",
                "contact": {
                    "phone": "12557",
                    "postgiro": "135558"
                },
                "financials": {
                    "capital": "30,000 kr",
                    "employees": {
                        "arb": 5
                    },
                    "annual_turnover": "N/A",
                    "annual_production_value": "35,000 kr"
                },
                "board": [
                    {
                        "name": "N/A",
                        "role": "ordförande"
                    }
                ],
                "director": "civilekonom Gunnar Lindahl"
            },
            {
                "name": "Torshälla Sågbladsfabrik",
                "location": "Torshälla",
                "business": "Tillverkar cirkelsågar för trä- och metallbearbetning, stock- och issågar, kedjesågar, ram- och bandsågblad, rälssågblad m. fl. sågblad samt hugg- och barkmaskin-knivar för trämassefabriker, maskinhyvel-järn, cirkelknivar och hackelsemaskinkni-var, trä- och metallfräsar, skiftnycklar samt excenter- och hävstångsplåtsaxar m. m.",
                "contact": {
                    "telegraph": "Sågfabriken, Torshälla",
                    "phone": "Eskilstuna 55005",
                    "postgiro": "140505"
                },
                "financials": {
                    "employees": {
                        "industriarb": "N/A"
                    },
                    "annual_turnover": "N/A",
                    "annual_production_value": "150,000 kr"
                },
                "board": [
                    {
                        "name": "N/A",
                        "role": "N/A"
                    }
                ],
                "owners": [
                    "ing. Rune Alison"
                ],
                "managing_director": "N/A",
                "sales_manager": "N/A",
                "manager": "N/A"
            }
        ]
    }
}