{
    "original": "Bakelit—Baltisk\n\nKontor: Kalendeg. 9. Telegr.-adr.:\nBadkläder, Malmö. Telefon: 27185. Postgiro:\n38271.\n\nAkt.-kap.: 35,000 kr. Antal\nindustriarb.: 10 (exel. hemarbetare). Tillv.-värde\npr år: 220,000 kr. — Firman etabl. 1907,\nbolag 1921.\n\nStyrelse o. verkst. dir.: disp. Gunnar\n-Johanson.\n\nBakelit-Eklund &amp; Co., Gislaved.\n\nTillverkar bakelitprodukter såsom\nrak-liyvlar, proppar till diskbänkar m. m. vid\nfabrik i Gislaved (Jönköp. l.).\n\nTelefon: 517. Postgiro: 293330. —\nAntal industriarb.: 4. Tillv.-värde pr år:\n75,000 kr. — Firman etabl. 1945.\n\nChef: fabr. Lage Eklund.\n\nBakelitfabriken Ambo, Gislaved.\n\nTillverkar elektr. installationstillbehör\nsåsom tryckknappströmbrytare,\nvipp-strömbrytare, ringledningskontakter samt\nbilelektriska artiklar vid fabrik i\nGislaved (Jönköp. l.).\n\nTelefon: 35. Postgiro: 266654. —\nAntal industriarb.: 25. Tillv.-värde pr år:\n350,000 kr. — Firman etabl. 1943.\n\nÄgare o. chef: fabr. Carl Bolin.\n\n*AB. Balatum, Göteborg.\n\nFabriker för tillverkning av golvmattor\n(inreg. märke: »Balatum») och\nimpreg-nering av papp i Hisingsbacka (Göteb.\no. Bohus l.).\n\nPostadr.: Göteborg, postfack 165.\nTelefon: 222613, 222649 o. 220649. Postgiro:\n150160.\n\nAkt.-kap.: 600,000 kr. Antal\nindustriarb.: 30. Tillv.-värde pr år: 2,500,000 kr.\n— Bolaget grundat 1936.\n\nStyrelse: adv. Olof Södermark (ordf.),\ndir. S. Nolte, adv. Sten Södermark, dir.\nö. Georg Theorin.\n\nVerkst. dir.: C. G. Theorin.\n\nBalder, AB. Möbelfabriken,\n\nVaggeryd.\n\nSe AB. Möbelfabriken Balder,\nVaggeryd.\n\nAB. Ballingslövs Träförädling,\n\nBallingslöv.\n\nSnickerifabrik i Ballingslöv (Kristianst.\n1). Tillverkar fönster, dörrar, trappor\noch inredningar.\n\nTelefon: 49. Postgiro: 145135. —\nAkt.-kap.: 42,500 kr. Antal industriarb.: 22.\nTillv.-värde pr år: 250,000 kr. — Bolaget\ngrundat 1929.\n\nVerkst. dir. o. disp.: H. Albin Svensson.\n\nAB. Balsamolfabriken, Mjölby.\n\nKaramell- och konfektyrfabrik i\nMjölby (Östergötl. l.). Tillverkar kola*\nkarameller, tabletter och gelésaker.\n\nTelefon: 875. Postgiro: 164548. —\nAkt.-kap.: 25,000 kr. Antal industriarb.:\n15. Tillv.-värde pr år: 350,000 kr. —\nFirman etabl. 1939, bolag 1944.\n\nVerkst. dir.: disp. Bror Printzell.\n\nAB. Balsviks Kalkbruk,\n\nKristianstad.\n\nTillverkar jordbrukskalk och murkalk\nvid kalkbruk i Balsvik, Kristianstad.\n\nTelefon: 10188. Postgiro: 277959.\nEn-samförsälj.: Calcium, Svenska\nKalkförsäljnings AB., Malmö, Hans Mickelsensg.\n1, telefon: 71420.\n\nAkt.-kap.: 60,000 kr. Antal\nindustriarb.: 10. Tillv.-värde pr år: 87,000 kr. —\nBolaget grundat 1904.\n\nVerkst. dir.: Bertil Ewe.\n\nKamrer: Swen Nilsson.\n\n*AB. Baltic, Södertälje.\n\nMek. verkstad. Tillverkar\nspecialmaskiner och -verktyg, skjutmått,\nmaskindelar samt pressade detaljer i tunnplåt.\n\nTelegr.-adr.: Baltic, Södertälje.\nTelefon: 32530. Postgiro: 195045.\n\nAkt.-kap.: 1,000,000 kr. Antal\nindustriarb.: 350. — Bolaget, grundat 1904,\nom-bildat 1928, äges av AB. Separator\nStockholm.\n\nStyrelse: dir. Axel Wästfelt (ordf.),\ndir. Folke Bergman, dir. Erik\nBrändström, dir. Nils Ericsson, dir. Folke\nHellstedt.\n\nVerkst. dir.: Folke Bergman.\n\n*Baltic Radio AB.,\nStockholm-Lidingö.\n\nSe Aga-Baltic AB., Stockholm-Lidingö.\n\n*AB. Baltisk Möbelindustri, Bjärnum.\n\nTillverkar möbler vid fabrik i\nBjärnum (Kristianst. l.).\n\nTelefon: 4. Postgiro: 84576. —\nAkt.-kap.: 49,000 kr. Antal industriarb.: 50.\nTillv.-värde pr år: 500,000 kr. — Bolaget\ngrundat 1933.\n\nStyrelse: disp. Carl A. Petersson, fru\nClara P. Petersson.\n\nDisp.: Carl A. Petersson.",
    "structured": {
        "1": {
            "name": "Bakelit—Baltisk",
            "location": "Malmö",
            "business": "Badkläder",
            "contact": {
                "office": "Kalendeg. 9",
                "phone": [
                    "27185"
                ],
                "postgiro": "38271",
                "telegraph": ""
            },
            "financials": {
                "capital": "35,000 kr",
                "employees": {
                    "industriarb": 10
                }
            },
            "foundation_year": 1907,
            "corporation_year": 1921,
            "board": [
                {
                    "name": "disp. Gunnar -Johanson",
                    "role": ""
                }
            ]
        },
        "2": {
            "name": "Bakelit-Eklund & Co.",
            "location": "Gislaved",
            "business": "Tillverkar bakelitprodukter",
            "contact": {
                "phone": [
                    "517"
                ],
                "postgiro": "293330"
            },
            "financials": {
                "employees": {
                    "industriarb": 4
                }
            },
            "foundation_year": 1945,
            "board": [],
            "director": "",
            "managing_director": "",
            "sales_manager": "",
            "manager": ""
        },
        "3": {
            "name": "Bakelitfabriken Ambo",
            "location": "Gislaved",
            "business": "Tillverkar elektr. installationstillbehör",
            "contact": {
                "phone": [
                    "35"
                ],
                "postgiro": "266654"
            },
            "financials": {
                "employees": {
                    "industriarb": 25
                }
            },
            "foundation_year": 1943
        },
        "4": {
            "name": "AB. Balatum",
            "location": "Göteborg",
            "business": "Fabriker för tillverkning av golvmattor",
            "contact": {
                "postadr": "Göteborg, postfack 165",
                "phone": [
                    "222613",
                    "222649",
                    "220649"
                ],
                "postgiro": "150160"
            },
            "financials": {
                "capital": "600,000 kr",
                "employees": {
                    "industriarb": 30
                }
            },
            "corporation_year": 1936,
            "board": [
                {
                    "name": "adv. Olof Södermark",
                    "role": "ordf."
                },
                {
                    "name": "dir. S. Nolte",
                    "role": ""
                },
                {
                    "name": "adv. Sten Södermark",
                    "role": ""
                },
                {
                    "name": "dir. ö. Georg Theorin",
                    "role": ""
                }
            ],
            "managing_director": "C. G. Theorin"
        },
        "5": {
            "name": "AB. Ballingslövs Träförädling",
            "location": "Ballingslöv",
            "business": "Snickerifabrik",
            "contact": {
                "phone": [
                    "49"
                ],
                "postgiro": "145135"
            },
            "financials": {
                "capital": "42,500 kr",
                "employees": {
                    "industriarb": 22
                }
            },
            "foundation_year": 1929,
            "board": [],
            "director": "",
            "managing_director": "",
            "sales_manager": "H. Albin Svensson",
            "manager": ""
        },
        "6": {
            "name": "AB. Balsamolfabriken",
            "location": "Mjölby",
            "business": "Karamell- och konfektyrfabrik",
            "contact": {
                "phone": [
                    "875"
                ],
                "postgiro": "164548"
            },
            "financials": {
                "capital": "25,000 kr",
                "employees": {
                    "industriarb": 15
                }
            },
            "foundation_year": 1939,
            "corporation_year": 1944,
            "director": "disp. Bror Printzell",
            "managing_director": "",
            "sales_manager": "",
            "manager": ""
        },
        "7": {
            "name": "AB. Balsviks Kalkbruk",
            "location": "Kristianstad",
            "business": "Tillverkar jordbrukskalk och murkalk",
            "contact": {
                "phone": [
                    "10188"
                ],
                "postgiro": "277959"
            },
            "financials": {
                "capital": "60,000 kr",
                "employees": {
                    "industriarb": 10
                }
            },
            "foundation_year": 1904,
            "board": [],
            "director": "",
            "managing_director": "",
            "sales_manager": "",
            "manager": "Bertil Ewe",
            "corporation_year": 1904
        },
        "8": {
            "name": "AB. Baltic",
            "location": "Södertälje",
            "business": "Mek. verkstad",
            "contact": {
                "telegraph": "Baltic, Södertälje",
                "phone": [
                    "32530"
                ],
                "postgiro": "195045"
            },
            "financials": {
                "capital": "1,000,000 kr",
                "employees": {
                    "industriarb": 350
                }
            },
            "foundation_year": 1904,
            "corporation_year": 1928,
            "board": [
                {
                    "name": "dir. Axel Wästfelt",
                    "role": "ordf."
                },
                {
                    "name": "dir. Folke Bergman",
                    "role": ""
                },
                {
                    "name": "dir. Erik Brändström",
                    "role": ""
                },
                {
                    "name": "dir. Nils Ericsson",
                    "role": ""
                },
                {
                    "name": "dir. Folke Hellstedt",
                    "role": ""
                }
            ],
            "managing_director": "Folke Bergman"
        },
        "9": {
            "name": "Baltic Radio AB.",
            "location": "Stockholm-Lidingö",
            "contact": {
                "telegraph": "Aga-Baltic AB., Stockholm-Lidingö"
            }
        },
        "10": {
            "name": "AB. Baltisk Möbelindustri",
            "location": "Bjärnum",
            "business": "Tillverkar möbler",
            "contact": {
                "phone": [
                    "4"
                ],
                "postgiro": "84576"
            },
            "financials": {
                "capital": "49,000 kr",
                "employees": {
                    "industriarb": 50
                }
            },
            "foundation_year": 1933,
            "board": [
                {
                    "name": "disp. Carl A. Petersson",
                    "role": ""
                }
            ]
        }
    }
}