{
    "original": "Gotthard t—Graham\n\n*AB* Herman Gotthardty Malmö.\n\nTågvirkes-, bindgarn- och mattfabrik\nsamt mek. fläteri i Arlöv (Malmöh. l.)\nävensom flaggfabrik och\npresenningsfabrik i Malmö.\n\nTillverkar tågvirke, flagglinor,\nbindgarn, dörrmattor och gångmattor av\nko-kos och papper, flaggor, presenningar,\nlivbojar, livbälten m. m. Bolaget driver\njämväl engroshandel med\nskeppsutrust-ningsartiklar.\n\nKontor: Malmö, Jörgen Kocksg. 4,\ntelegr.-adr.: Gotthardt, Malmö, telefon:\n71275, postgiro: 14060; Stockholm,\nStadsgården 14—16, telefon: 440170, postgiro:\n249972; Göteborg, Brog. 3, telefon:\n133268 o. 138569.\n\nAkt.-kap.: 525.000 kr. Antal\nindustriarb.: 95. Tillv.-värde pr år: 1,750,000 kr.\n\n—\tBolaget grundat 1916.\n\nStyrelse: dir. Herman Gotthardt\n(ordf.), konsul Magnus Wiberg, dir. Åke\nWiberg.\n\nVerkst. dir.: Herman Gotthardt.\n\nDisp.: Torsten Tellbo.\n\nA B. Oscar Gottlow* Knappfabrik,\n\nEslöv.\n\nTillverkar massartiklar av konsthorn\noch konstharts samt knappar och\nspännen huvudsakligen för damkonfektion.\n\nTelegr.-adr.: Gottlow, Eslöv. Telefon:\n594. Postgiro: 6177.\n\nAkt.-kap.: 10,000 kr. Arb.-antal: 5.\nTillv.-värde pr år: 50,000 kr. — Efter\ninköp av AB. Konsthorn-Industri\netablerades firman 1923 under namn Eslövs\nKamfabrik, bolag under nuv. namn 1939.\n\nVerkst. dir.: fabr. Oscar Gottlow.\n\n*AB. Gracilsko, Örebro.\n\nSkofabrik. Tillverkar lättare\ndamskodon. Varumärke: »Graeilsko».\n\nTelefon: 15111. Postgiro: 87614.\nRepresentanter: för Stockholm: Fritz\nSjöberg, Sveav. 25—27, telefon: 200199; för\nsödra Sverige: Adolf Schult, Malmö,\nRe-gementsg. 80, telefon: 28081.\n\nAkt.-kap.: 21,800 kr. Antal\nindustriarb.: 33. Tillv.-värde pr år: 500,000 kr.\n\n—\tFirman etabl. 1933.\n\nStyrelse: fabr. Georg Johansson (ordf.),\nmodellör Iron Bliime, verkm. Karl Ohberg.\n\nVerkst. dir.: fabr. Georg Johanson.\n\nGrafiska AB. Hofving &amp; Myrberg,\n\nStockholm.\n\nUtför klichéer, stereotypier och matriser.\n\nKontor: Luntmakarg. 25. Telefon:\n112188 o. 118131. Postgiro: 51242.\n\nAkt.-kap.: 27,500 kr. Antal\nindustriarb.: 32. Tillv.-värde pr år: 400,000 kr.\n— Firman etabl. 1919.\n\nStyrelse: kungl. boktryckare Simon\nSöderstam (ordf.), disp. K. F. Scherman,\nkamrer Gustaf Söderstam.\n\nVerkst. dir.: Gustaf Söderstam.\n\nDisp.: K. F. Scherman.\n\n* Grafiska Maskin AB., Stockholm.\n\nMek. verkstad. Konstruerar och\ntillverkar tryckpressar. Varumärke: »GMA».\n\nKontor: Norra Stationsg. t&gt;9.\nTelegr.-adr.: Gemapress, Stockholm. Telefon:\n331170—71 o. 331191. Postgiro: 199487.\n\nAkt.-kap.: 600,000 kr. Antal\nindustriarb.: 30. — Bolaget grundat 1944.\n\nStyrelse: dir. Gustaf Ekholm (ordf.),\ndir. Bruno Alm, dir. Folke Fessé, ing.\nRagnar Isberg, dir. E. A. Pehrsson.\n\nVerkst. dir.: Bruno Alm.\n\nAB. Grafit, Göteborg.\n\nGrafitgruva och anrikningsverk i\nHå-tuna, Bro (Uppsala l.). Tillverkar\nspår-vägsgrafit, gjuterisrrafit samt annan\nindustriell grafit. Varumärken:\n»Sveagra-fit» o. »Håtunagrafit».\n\nKontor: Göteborg, Magasinsg. 3.\nTelefon: 172950. Postgiro: 46455. —\nAkt.-kap.: 100,000 kr. Antal industriarb.: 16.\n— Firman grundades 1939.\n\nStyrelse: civiling. Gunnar Bergendahl\n(ordf.), civiling. Gunnar Höckert.\n\nVerkst. dir.; Gunnar Bergendahl.\n\n*Crafitindustri, Skandinaviska,\n\nTrollhättan.\n\nSe Skandinaviska Grafitindustri AB.,\nTrollhättan.\n\n*Graham Brothers AB., Stockholm.\n\nMek. verkstad med snickerifabrik vid\nLilla Ursvik, Ulriksdal (Sthlms l.).\nTillverkar hissar, allformatorer (elektr.\nkon-taktströmriktare), neonskyltar,\nlysämnes-armaturer och laboratorieglas.\n\nKontor: Brunkebergstorg 12.\nTelegr.-adr.: Grahams, Stockholm. Telefon:\n»Gra-ham Brothers». Postgiro: 1865.\n\nAkt.-kap.: 1,000,000 kr. Antal\nindustriarb.: 140. Tillv.-värde pr år: 3,500,000 kr.\n\nBolaget, grundat 1917, har i sig\nupptagit f. d. AB. Elevator, Stockholm.\nHuvudintressent i bolaget ar Svenska\nElektromekaniska Industri AB.,\nHälsingborg, som tillhör L. M. Ericsson-gruppen.",
    "structured": {
        "firms": [
            {
                "name": "AB Herman Gotthardt",
                "location": "Malmö",
                "business": "Tågvirkes-, bindgarn- och mattfabrik",
                "products": "Tillverkar tågvirke, flagglinor, bindgarn, dörrmattor och gångmattor av kokos och papper, flaggor, presenningar, livbojar, livbälten m.m. Bolaget driver jämväl engroshandel med skeppsutrustningsartiklar.",
                "contact": {
                    "office": "Malmö, Jörgen Kocksg. 4",
                    "telegraph": "Gotthardt, Malmö",
                    "phone": [
                        "71275"
                    ],
                    "postgiro": "14060",
                    "head_office": "Stockholm, Stadsgården 14-16",
                    "sales_offices": [
                        {
                            "location": "Stockholm",
                            "phone": "440170"
                        },
                        {
                            "location": "Göteborg",
                            "phone": "133268,138569"
                        }
                    ]
                },
                "financials": {
                    "capital": "525.000 kr.",
                    "employees": {
                        "industriarb": 95
                    },
                    "annual_turnover": "1,750,000 kr.",
                    "annual_production_value": "1,750,000 kr."
                },
                "foundation_year": 1916,
                "board": [
                    {
                        "name": "Herman Gotthardt",
                        "role": "dir."
                    },
                    {
                        "name": "Magnus Wiberg",
                        "role": "konsul"
                    },
                    {
                        "name": "Åke Wiberg",
                        "role": "dir."
                    }
                ],
                "director": "Herman Gotthardt",
                "managing_director": "Herman Gotthardt"
            },
            {
                "name": "AB Oscar Gottlow Knappfabrik",
                "location": "Eslöv",
                "business": "Tillverkar massartiklar av konsthorn och konstharts samt knappar och spännen huvudsakligen för damkonfektion.",
                "contact": {
                    "office": "Eslöv",
                    "telegraph": "Gottlow, Eslöv",
                    "phone": [
                        "594"
                    ],
                    "postgiro": "6177"
                },
                "financials": {
                    "capital": "10,000 kr.",
                    "employees": {
                        "industriarb": 5
                    },
                    "annual_turnover": "50,000 kr."
                },
                "original_name": "Eslövs Kamfabrik",
                "corporation_year": 1939,
                "director": "fabr. Oscar Gottlow"
            },
            {
                "name": "AB Gracilsko",
                "location": "Örebro",
                "business": "Skofabrik",
                "products": "Tillverkar lättare damskodon.",
                "contact": {
                    "phone": "15111",
                    "postgiro": "87614"
                },
                "financials": {
                    "capital": "21,800 kr.",
                    "employees": {
                        "industriarb": 33
                    },
                    "annual_turnover": "500,000 kr."
                },
                "foundation_year": 1933,
                "board": [
                    {
                        "name": "fabr. Georg Johansson",
                        "role": "ordf."
                    },
                    {
                        "name": "modellör Iron Blume",
                        "role": "modellör"
                    },
                    {
                        "name": "verkm. Karl Ohberg",
                        "role": "verkm."
                    }
                ],
                "director": "fabr. Georg Johanson"
            },
            {
                "name": "Grafiska AB. Hofving & Myrberg",
                "location": "Stockholm",
                "business": "Utför klichéer, stereotypier och matriser.",
                "contact": {
                    "office": "Luntmakarg. 25",
                    "phone": [
                        "112188,118131"
                    ],
                    "postgiro": "51242"
                },
                "financials": {
                    "capital": "27,500 kr.",
                    "employees": {
                        "industriarb": 32
                    },
                    "annual_turnover": "400,000 kr."
                },
                "foundation_year": 1919,
                "board": [
                    {
                        "name": "kungl. boktryckare Simon Söderstam",
                        "role": "ordf."
                    },
                    {
                        "name": "disp. K. F. Scherman",
                        "role": "disp."
                    },
                    {
                        "name": "kamrer Gustaf Söderstam",
                        "role": "kamrer"
                    }
                ],
                "director": "Gustaf Söderstam",
                "managing_director": "Gustaf Söderstam",
                "sales_manager": "K. F. Scherman"
            },
            {
                "name": "Grafiska Maskin AB.",
                "location": "Stockholm",
                "business": "Mek. verkstad",
                "products": "Konstruerar och tillverkar tryckpressar.",
                "contact": {
                    "office": "Norra Stationsg. 9",
                    "telegraph": "Gemapress, Stockholm",
                    "phone": [
                        "331170-71,331191"
                    ],
                    "postgiro": "199487"
                },
                "financials": {
                    "capital": "600,000 kr.",
                    "employees": {
                        "industriarb": 30
                    }
                },
                "corporation_year": 1944,
                "board": [
                    {
                        "name": "dir. Gustaf Ekholm",
                        "role": "ordf."
                    },
                    {
                        "name": "dir. Bruno Alm",
                        "role": "dir."
                    },
                    {
                        "name": "dir. Folke Fessé",
                        "role": "dir."
                    },
                    {
                        "name": "ing. Ragnar Isberg",
                        "role": "ing."
                    },
                    {
                        "name": "dir. E. A. Pehrsson",
                        "role": "dir."
                    }
                ],
                "director": "Bruno Alm"
            },
            {
                "name": "AB. Grafit",
                "location": "Göteborg",
                "business": "Grafitgruva och anrikningsverk i Håtuna, Bro (Uppsala l.).",
                "products": "Tillverkar spårvägsgrafit, gjuterisgrafit samt annan industriell grafir.",
                "contact": {
                    "office": "Göteborg, Magasinsg. 3",
                    "phone": [
                        "172950"
                    ],
                    "postgiro": "46455"
                },
                "financials": {
                    "capital": "100,000 kr.",
                    "employees": {
                        "industriarb": 16
                    }
                },
                "foundation_year": 1939,
                "board": [
                    {
                        "name": "civiling. Gunnar Bergendahl",
                        "role": "ordf."
                    },
                    {
                        "name": "civiling. Gunnar Höckert",
                        "role": "civiling."
                    }
                ],
                "director": "Gunnar Bergendahl"
            },
            {
                "name": "Graham Brothers AB.",
                "location": "Stockholm",
                "business": "Mek. verkstad med snickerifabrik vid Lilla Ursvik, Ulriksdal (Sthlms l.).",
                "products": "Tillverkar hissar, allformatorer (elektr. kontaktströmriktare), neonskyltar, lysämnesarmaturer och laboratorieglas.",
                "contact": {
                    "office": "Brunkebergstorg 12",
                    "telegraph": "Grahams, Stockholm",
                    "phone": "Graham Brothers",
                    "postgiro": "1865"
                },
                "financials": {
                    "capital": "1,000,000 kr.",
                    "employees": {
                        "industriarb": 140
                    },
                    "annual_turnover": "3,500,000 kr."
                }
            }
        ]
    }
}