{
    "original": "Ahlberg-—.\n\nAhremark\n\narb.: 70. Tillv.-värde pr\nFirman etabl. 1894, bolag 1908.\n\nStyrelse o. verkst. -dit.’: ’Stén’ Bengtsson.\n\nKontorschef: Oscar J. Andersson.\n\nDriftsingenjörer: för elektr. avd.: ing.\nRagnar Nilsson; föé fänéie^jo. sanitära\navd.: ing. John Almqvist.\n\n* AhlbergA Ohlssons Instrument AB.,\n\nStockholm.\n\nTillverkar mässingsblåsinstrument,\njakt- och signalhorn, trummor m. m.\nBolaget idkar jämväl handel med\nmusika-lier och träblåsinstrument av utländsk\ntillverkning.\n\nKontor: Sibylleg. 10, Telefon: 621581.\nPostgiro: 717.\n\nAkt.-kap.: 50,000 kr. Arb.-antal: 10.\nTillv.-värde pr år: 100,000 kr. — Firman\netabl. 1850,. bolag 1904.\n\nStyrelse: grossh. -Harry L. Ohlsson\n(ordf.), fröken Gerda Johansson, fru\nDindi Ohlsson.\n\nVerkst. dir.: SärTy L. Öhlssoh.\n\n*F„ Ahlgrens Tekn. Fabrik AB.,\n\nGävle.\n\nTillverkning av brösttabletter\n(»Läke-rol»), konfityrer, dragéer\n(Wiener-Lin-ser), lakritsvaror m. m.; kem.-tekn. fabrik\nmed tillverkning av skoputsmedel\n(»Nobless»), antitranspirationsmedel\n(»Torofin»), metallputsmedél (»Silverglans»),\nbonvax (»Golvglans») samt andra\ntekniska preparat.\n\nTelegr.-adr.: Läkerol, Gävle. Telefon:\n252, 1165, 2100 o. 4138. Postgiro: 5123.\nAvd.-kontor: Göteborg,\nKungsportsave-nyen 1, telefon: 116472; Malmö, Erik\nDahlbergsg. 24 O, telefon: 18159.\n\nAkt.-kap.: 800,000 kr. Antal\nindustri-arb.: 77. Tillv.-värde pr år: 3,000,000 kr.\n— Firman etabl. 1885, bolag 1933.\n\nStyrelse: ad v. A. Hemming-Sjöberg\n(ordf.), dir. Adolf F. Ahlgren, konsul\nBengt Ahlgren, dir. Sven Alilgren, disp.\nGust. Melin.\n\nVerkst. dir,: Adolf F. Ahlgren,\n\nVice verkst. dir.: Bengt Ahlgren.\n\nDisp.: Gust. Melin.\n\nReklamchef: Sven Ahlgren;\n\nKamrer: Fritz Hedberg.\n\nThor Ahlgren, Skillingaryd.\n\nMek. verkstad i Skillingaryd (Jönköp.\n1.). Tillverkar skohakar och märlor,\nkar-tongklammer, nit- och mutter brickor,\nlimknektar- och tvingar,\nturistsäng-beslag, skidspännare m. m.\n\nTelefon: 75. Postgiro: 29238. — Antal\nindustriarb.: 18. Tillv.-värde pr år:\n230,000 kr. — Firman etabl. 1918.\n\nÄgare o. chef: fabr. Thor Ahlgren.\n\n*Ahlsnickerier, A. €mi §M$Uppsåta*\n\nTillverkar möbler och inredningar.\n\nTelefon: 30947. Postgiro: 270485. —\nAntal industriarb.: 5. —Firman etabl.\n1943.\n\nÄgare o. chef: fabr. A. Emanuel Ahl.\n\n*Ahlsta Kvarn &amp; Tegelbruks AB.,\n\nÖrsundsbro.\n\n. Tillverkar murtegel och tegelrör vid\ntegelbruk i Örsundsbro (Uppsala.,1.)-\nfirman driver även kvarnrörelse.\n\nTelefon: Nysätra 4 A. — Akt.-kap.:\n107,000 kr. Antal industriarb.: 25.\nTillv.-värde pr år: 100,000 kr. — Bolaget\ngrundat 1925.\n\nStyrelse o. verkst. dir.: Per Anderson.\n\n*K. S. Ahlstedt, Kristinehamn.\n\nOhokladfabrik samt soda- och\nvattén-glasfabrik. Tillverkar chokladpraliner,\nmarmelad och konfityrer samt\nkristall-soda och vattenglas.\n\nTelefon: 10755, 10917 o. 10087. Post*\ngiro: 31092.\n\nAntal industriarb.: 28, varav vid\nchokladfabriken 24. —^; Firman, etabl. 4J23,\näger Gefle Karamell AB.\n\nÄgare o. chef: fabr. K. S. Ahlstedt.\n\nDisp.: Gunnar Wallin.\n\n*And. &lt;1. Ahlström, Byggnadsfirma,\n\nHälsingborg.\n\nByggnadsentreprenörfirma för\nbostads-och affärshus, offentliga byggnader,\nindustribyggnader m. m.\n\nTelefon: 10008. — Firman etabl, 1898.\n\nÄgare o. chefer: byggnadsing. Herbert\nAhlström o. byggnadsing. Gustaf\nAhlström.\n\nSe även Alström.\n\n*Ahremarks Konfektions AB.,\n\nBorås.\n\nTillverkar goss- och ynglingakläder,\ntrenchcoats, barn-, flick- och\nbackfisch-kappor. Varumärke: »Ahremarks».\n\nTelefon: 17135. Postgiro: 72925.\n\nAkt.-kap.: 300,000 kr. Antal\nindustriarb.: 100 samt 15 hemarbetare.\nTillv.-värde pr år: 2,100,000 kr. — Firman\netabl. 1901, bolag 1931.\n\nStyrelse: dir. Olof Ahremark (ordf.),\nfru E. Ahremark.\n\nVerkst. dir.: Olof Ahremark.",
    "structured": {
        "name": "Ahlberg-",
        "location": "",
        "business": "",
        "products": null,
        "contact": {
            "office": null,
            "phone": null,
            "postgiro": null,
            "head_office": null,
            "sales_offices": null,
            "telegraph": null,
            "factory_office": null,
            "factory_phone": null
        },
        "financials": {
            "capital": null,
            "employees": null,
            "annual_turnover": null,
            "annual_production_value": null
        },
        "foundation_year": 1894,
        "current_name_year": 1908,
        "predecessor": null,
        "original_name": "Firman etabl. 1894, bolag 1908",
        "corporation_year": null,
        "board": [
            {
                "name": "'Stén' Bengtsson",
                "role": null
            }
        ],
        "owners": null,
        "director": "Oscar J. Andersson",
        "managing_director": null,
        "sales_manager": null,
        "brands": null,
        "manager": null,
        "reference": null
    }
}