{
    "original": "Petit—Pettersson\n\nStyrelse: grossh. öarl Persson (ordf.),\ndisp; Oohrad Raihle, disp. Harry Raihle,\ndisp. Ossian Raihle, dir. William Raihle.\n\nVerkst. dir.: William Raihle.\n\nDisponenter: Harry Raihle o. Ossian\nRaihle,\n\nKamrer: Orvar Raihle.\n\nChefsassist.: Åke Raihle.\n\nReklamchef: Carl Eskil Sjöstedt.\n\nFabrikschef: Algot Bard.\n\nFrltr Persson, Mosås.\n\nSmides-, och mek. verkstad i Mosås\n(Örebro l.). Tillverkar lastbilsflak samt\nsläpvagnar för bilar och traktorer.\n\nTelefon: 75068. Postgiro: 166701. —\nAntal industriarb.: 13. Tillv.-värde pr år:\n180 000 kr. — Firman etabl. 1925.\n\nÄgare o. chef: fabr. Fritz Persson,\n\n*Cust. Perssons Läderfabriks AB.,\n\nUddevalla.\n\nSe AB. Vargläderfabriken, Uddevalla.\n\nAB. Henning Persson, Göteborg.\n\nFärg- och fernissfabrik i Säve (Göteb.\no. Bohus l.) samt asfaltkokeri och\nkem.-teknisk fabrik i Göteborg. Tillverkar\nolje- och lackfärger, fernissor och läcker,\nslamfärger, asfaltprodukter,\nisolerings-och impregneringsmedel samt skur-,\ndisk-oeh rengöringsmedel, putsmedel, bonvax\nm. m. Bolaget driver även engroshandel\nmed kemikalier.\n\nKontor: Göteborg, ö. Hamng. 12.\nTelefon: 172925. Postgiro: 47871.\n\nAkt.-kap.: 45,000 kr. Antal\nindustriarb.: 40. Tillv.-värde pr år: 2,000,000 kr.\n— Bolaget, grundat 1942, har i sig\nupptagit f. d. AB. Hemper, Göteborg.\n\nVerkst. dir.: Henning Persson.\n\nKontorschef: Roland Arvidsson.\n\n*lvan B. Person, Stockholm.\n\nByggnadsentreprenörfirma för\nbostads-och affärshus, industribyggnader m. m.\n\nKontor: Drottningg. 4. Telefon:\n230930. Postgiro: 157766. — Firman\netabl. 1910.\n\nÄgare o. chef: ing. Ivan B. Person.\n\n*AB. J. Pehrson &amp; Comp., Örebro.\n\nTillverkar skodon. Varumärken:\n»Ingeborg» och »Engelbrekt». Bolaget idkar\njämväl engroshandel med skodon, läder\noch galoscher m. m.\n\nTelegr.-adr.: Pehrson, Örebro. Telefon:\n»Pehrson &lt;&amp; Comp». Postgiro: 5148.\n\nAkt.-kap.: 1,500,000 kr. Antal\nindustriarb.: 235. Tillv.-värde pr år: 3,500,000 kr.\n\n—\tBolaget grundat 1901.\n\nStyrelse: dir. Reinhold Berglund (ördf.),\ndisp. Gustaf Berglund, disp. Torsten\nBerglund, fru Ingegerd Carolsson.\n\nVerkst. dir.; Reinhold Berglund.\n\nAB. Johan Perssons Byggnadsvaror,\n\nLönsboda.\n\nSågverk och hyvleri i Lönsboda\n(Kristianst. l.). Tillverkar sågade och\nhyvlade trävaror, listverk tia. m. Bolaget\ndriver även handel med byggnadsvaror\nsåsom fönster och dörrar, plywood m. m.\n\nTelefon: 42. Postgiro: 74865. ~\nAkt.-kap.: 262,000 kr. Antal industriarb.: 12.\nTillv.-värde pr år: 120,000 kr.\n\nBolaget bildat 1940 efter\nsammanslagning av firmorna Johan Perssons\nByggnadsvaror och Lönsboda Träförädling,\nPella Persson.\n\nDisp.: N. E. Rönbeck.\n\nK. J. Persson, Handskfabrik,\n\nMalung.\n\nTillverkar promenadhandskar,\nsport-och arbetshandskar vid fabrik i Malung\n(Kopparb. l.).\n\nTelefon: 110. Postgiro: 130378. Antal\nindustriarb. : 32. — Firman etabl, 1924. ,\n\nÄgare och chefer: fabr. Johan Persson\no. disp. Sven Persson.\n\n*Leander Pehrson Möbler,\n\nSimrishamn.\n\nTillverkar möbler.\n\nTelefon: 150 o. 151. Postgiro: 27872.\n\n—\tAntal industriarb.: 10. —- Firman\netabl. 1912, ombildad 1945,\n\nÄgare o. chefer: fabr. Leander Pehrson\no. försäljn.-chef Börje Pehrson.\n\n*AB. Mårten Pehrsons Valsqvarn,\n\nKristianstad.\n\nKvarnar i Kristianstad och\nLandskrona. Tillverkar mjöl och kli av vete och\nråg.\n\nTelegr.-adr.: Kvarnbolaget,\nKristianstad o. Landskronakvarn, Landskrona.\nTelefon: »Kvarnbolaget», Kristianstad,\nsamt 25, 157, 775 o. 1157, Landskrona.\nPostgiro: 6827 (Kristianstad).\n\nAkt.-kap.: 6,000,000 kr. Antal\nindustriarb.: 135. — Bolaget grundat 1898.\n\nStyrelse: v. konsul Carl Nilsson\n(ordf.), landshövd. Joh. Nilsson (v. ordf.),\ngrossh. Anders Andersson, dir. Hj. Oarl-\n\n573*",
    "structured": {
        "1": {
            "name": "Frltr Persson",
            "location": "Mosås (Örebro l.)",
            "business": "Smides-, och mek. verkstad",
            "products": "Tillverkar lastbilsflak samt släpvagnar för bilar och traktorer.",
            "contact": {
                "office": "Mosås (Örebro l.)",
                "phone": [
                    "75068"
                ],
                "postgiro": "166701"
            },
            "financials": {
                "employees": {
                    "industriarb.": 13
                },
                "annual_turnover": "180 000 kr",
                "annual_production_value": "180 000 kr"
            },
            "foundation_year": 1925,
            "owners": [
                "fabr. Fritz Persson"
            ]
        },
        "2": {
            "name": "AB. Henning Persson",
            "location": "Göteborg, Säve (Göteb. o. Bohus l.)",
            "business": "Färg- och fernissfabrik",
            "products": "Tillverkar olje- och lackfärger, fernissor och läcker, slamfärger, asfaltprodukter, isolerings-och impregneringsmedel samt skur-, disk-oeh rengöringsmedel, putsmedel, bonvax m. m. Bolaget driver även engroshandel med kemikalier.",
            "contact": {
                "office": "Göteborg, ö. Hamng. 12",
                "phone": [
                    "172925"
                ],
                "postgiro": "47871"
            },
            "financials": {
                "capital": "45,000 kr",
                "employees": {
                    "industriarb.": 40
                },
                "annual_turnover": "2,000,000 kr",
                "annual_production_value": "2,000,000 kr"
            },
            "foundation_year": 1942,
            "predecessor": "f.d. AB. Hemper, Göteborg",
            "owners": [
                "Verkst. dir.: Henning Persson"
            ],
            "board": [
                {
                    "name": "dir. Reinhold Berglund",
                    "role": "ördf."
                },
                {
                    "name": "disp. Gustaf Berglund",
                    "role": ""
                },
                {
                    "name": "disp. Torsten Berglund",
                    "role": ""
                },
                {
                    "name": "fru Ingegerd Carolsson",
                    "role": ""
                }
            ]
        },
        "3": {
            "name": "Ivan B. Person",
            "location": "Stockholm",
            "business": "Byggnadsentreprenörfirma",
            "products": "Bostads-och affärshus, industribyggnader m. m.",
            "contact": {
                "office": "Drottningg. 4",
                "phone": [
                    "230930"
                ],
                "postgiro": "157766"
            },
            "foundation_year": 1910,
            "owners": [
                "ing. Ivan B. Person"
            ]
        },
        "4": {
            "name": "AB. J. Pehrson &amp; Comp.",
            "location": "Örebro",
            "business": "Tillverkar skodon",
            "products": "Varumärken: »Ingeborg» och »Engelbrekt». Bolaget idkar jämväl engroshandel med skodon, läder och galoscher m. m.",
            "contact": {
                "telegraph": "Pehrson, Örebro",
                "phone": [
                    "Pehrson &amp; Comp"
                ],
                "postgiro": "5148"
            },
            "financials": {
                "capital": "1,500,000 kr",
                "employees": {
                    "industriarb.": 235
                },
                "annual_turnover": "3,500,000 kr"
            },
            "foundation_year": 1901,
            "board": [
                {
                    "name": "dir. Reinhold Berglund",
                    "role": "ördf."
                },
                {
                    "name": "disp. Gustaf Berglund",
                    "role": ""
                },
                {
                    "name": "disp. Torsten Berglund",
                    "role": ""
                },
                {
                    "name": "fru Ingegerd Carolsson",
                    "role": ""
                }
            ]
        },
        "5": {
            "name": "AB. Johan Perssons Byggnadsvaror",
            "location": "Lönsboda (Kristianst. l.)",
            "business": "Sågverk och hyvleri",
            "products": "Tillverkar sågade och hyvlade trävaror, listverk tia. m. Bolaget driver även handel med byggnadsvaror såsom fönster och dörrar, plywood m. m.",
            "contact": {
                "office": "Lönsboda (Kristianst. l.)",
                "phone": [
                    "42"
                ],
                "postgiro": "74865"
            },
            "financials": {
                "capital": "262,000 kr",
                "employees": {
                    "industriarb.": 12
                },
                "annual_turnover": "120,000 kr"
            },
            "foundation_year": 1940,
            "predecessor": "Johan Perssons Byggnadsvaror, Lönsboda Träförädling, Pella Persson",
            "directors": [
                "Disp.: N. E. Rönbeck"
            ]
        },
        "6": {
            "name": "K. J. Persson, Handskfabrik",
            "location": "Malung (Kopparb. l.)",
            "business": "Tillverkar promenadhandskar, sport-och arbetshandskar",
            "contact": {
                "office": "Malung (Kopparb. l.)",
                "phone": [
                    "110"
                ],
                "postgiro": "130378"
            },
            "financials": {
                "employees": {
                    "industriarb.": 32
                }
            },
            "foundation_year": 1924,
            "owners": [
                "fabr. Johan Persson"
            ]
        },
        "7": {
            "name": "Leander Pehrson Möbler",
            "location": "Simrishamn",
            "business": "Tillverkar möbler",
            "contact": {
                "phone": [
                    "150",
                    "151"
                ],
                "postgiro": "27872"
            },
            "financials": {
                "employees": {
                    "industriarb.": 10
                }
            },
            "foundation_year": 1912,
            "owners": [
                "fabr. Leander Pehrson",
                "försäljn.-chef Börje Pehrson"
            ]
        },
        "8": {
            "name": "AB. Mårten Pehrsons Valsqvarn",
            "location": "Kristianstad",
            "business": "Kvarnar",
            "products": "Tillverkar mjöl och kli av vete och råg.",
            "contact": {
                "telegraph": "Kvarnbolaget, Kristianstad o. Landskronakvarn, Landskrona",
                "phone": [
                    "Kvarnbolaget",
                    "Kristianstad",
                    "25",
                    "157",
                    "775",
                    "1157"
                ],
                "postgiro": "6827 (Kristianstad)"
            },
            "financials": {
                "capital": "6,000,000 kr",
                "employees": {
                    "industriarb.": 135
                }
            },
            "foundation_year": 1898,
            "board": [
                {
                    "name": "v. konsul Carl Nilsson",
                    "role": "ordf."
                },
                {
                    "name": "landshövd. Joh. Nilsson",
                    "role": "v. ordf."
                },
                {
                    "name": "grossh. Anders Andersson",
                    "role": ""
                },
                {
                    "name": "dir. Hj. Oarl-573*",
                    "role": ""
                }
            ]
        }
    }
}