{
    "original": "Häftstiftsfabrikenr—H äggådalen\n\nAkt.-kap.: 400,000 kr. Antal\nindustriarb.: 60. Tillv.-värde pr år: 1,358,000 kr.\n\nBruket anlagt 1682, nuv. bolag grundat\n1899.\n\nStyrelse: kammarherre Fredrik v.\nMecklenburg (ordf.), ing. W.\nSchull-ström (v. ordf,), disp. Em. Ljungström.\n\nVerkst dir. o. disp.: Em. Ljungström.\n\n’Häftstiftsfabriken, AB. Svenska,\n\nÖrebro.\n\nSe AB. Svenska Häftstiftsfabriken,\nÖrebro.\n\nErik Hägg, Grimsås.\n\nSe Grimsås Syfabrik, Erik H ägg,\nGrimsås.\n\n*AB. Hägglund &amp; Söner,\n\nÖrnsköldsvik.\n\nKarosserifabrik med mekanisk och\nelek-tromekanisk avdelning. Tillverkar\nomni-buskarosserier, spårvagnar, rälsbussar,\nelektriska svetsmaskiner, skolbänkar och\nbastuaggregat.\n\nTelefon: 1440. Postgiro: 28950.\n\nAkt.-kap.: 693,000 kr. Antal\nindustriarb.: 800. Tillv.-värde pr år: 12,000,000\nkr.\n\nFirman, grundad 1899, bolag 1922, äger\nAB. Splitkein, Örnsköldsvik, med\ntillverkning av lamellskidor.\n\nStyrelse: dir. Per Evert Hägglund\n(ordf.), disp. Gösta E. Hägglund (v.\nordf.), fabr. Gustaf Hägglund.\n\nVerkst. dir.: P. E. Hägglund.\n\nDisp.: Gösta E. Hägglund.\n\nFörsäljn.-chef: Georg Skogsberg.\n\nInköpschef: John Lundblad.\n\nAB. Joh. Hägglund,\n\nÖrnsköldsvik.\n\nSko- och handskfabrik. Tillverkar\nsportskodon, norrlandspjäxor, arbetshandskar\noch raggsockor. Firman bedriver även\nhud- och skinnexport.\n\nTelegr.-adr.: Hägglundarna,\nÖrnsköldsvik. Telefon: 2402. Postgiro: 28943.\n\nAkt.-kap.: 208,000 kr. Antal\nindustriarb.: 100. Tillv.-värde pr år: 1,450,000 kr.\n— Bolaget grundat 1920.\n\nStyrelse: dir. John Hägglund (ordf.),\ndir. Hjalmar Hägglund, fabr. Karl H.\nHägglund.\n\nVerkst. dir.: Hjalmar Hägglund.\n\nHäggström, Haeggström.\n\nFritz Haeggström AB., Stockholm.\n\nFiskkonservfabrik. Tillverkar ansjovis,\nsill- och kaviarinläggningar. Varumärke:\n»Fyrväpplingen». Bolaget driver även\nengroshandel i kolonialvaror.\n\nKontor: Malmgårdsvägen 63.\nTelegr.-adr.: Merchants, Stockholm. Telefon:\n440500. Postgiro: 3937. — Akt-kap.:\n75,000 kr. Antal industriarb: 50.\nTillv.-värde pr år: 1,000,000 kr, — Firman\netabl. 1919, bolag 1930.\n\nVerkst. dir.: Fritz Haeggström.\n\nKamrer: Sven Baarsen.\n\n’Ivar Haeggströms Boktryckeri &amp;\nBokförlags AB., Stockholm.\n\nBoktryckeri, ståltryckeri och\nlitogra-fisk anstalt.\n\nKontor: G:la Brog. 26. Telefon: »Ivar\nHaeggströms». Postgiro: 3430. —\nAkt.-kap.: 800,000 kr. Antal industriarb.: 129.\n\nFirman etabl. 1813, nuv. bolag grundat\n1899. Bolaget äges av Almqvist &amp;\nWick-sells Boktryckeri AB., Uppsala.\n\nStyrelse: dir. H. W. Söderman (ordf.),\ndisp. H. Engstrand, dir. Göran Z.\nHaeggström.\n\nVerkst. dir.: Göran Z. Haeggström.\n\nDisp.: H. Engstrand.\n\nFörest.: för boktryckeriavd.: William\nPeterson; för litogr. avd.: R. O. Drewitz.\n\nKamrer: Hj. Arloff.\n\n*AB. Torsten Häggström, Borås.\n\nTrikåfabrik. Tillverkar jumpers, ^\nkoftor, stickade . barnkläder, babyartiklar,\nherrvästar, slipovers m. m. Specialitet:\njumpers. Varumärke: »Tehå».\n\nKontor: Wiskabergs Fabriker, Borås.\nTelefon: 13428. Postgiro: 71601.\n\nAkt.-kap.: 100,000 kr. Antal\nindustriarb.: 32, hemarbetare 150. Tillv.-värde\npr år: 900,000 kr. — Tillverkningen\nstartades 1905, bolaget grundat 1934.\n\nStyrelse: fabr. Torsten Häggström\n(ordf.), dir. Erik Häggström.\n\nVerkst. dir.: Torsten Häggström.\n\nKamrer: Holger Häggström.\n\n’Häggådalens Mek. Linneväfveriers\n\nAB., Kinna.\n\nLinneväveri, blekeri och\nappreterings-verk i Kinna (Älvsb. l.). Tillverkar\nduktyger, servietter och handdukar i damast,\njacquard och dräll.\n\nTelegr.-adr.: Linne, Kinna. Telefon:\n10027 o. 10207. Postgiro: 7998.\n\nAkt.-kap.: 250,000 kr. Antal\nindustriarb.: 211. Tillv.-värde pr år: 6,000,000 kr.\n\n375*",
    "structured": {
        "1": {
            "name": "Häftstiftsfabrikenr—H äggådalen",
            "location": "Örebro",
            "business": "Häftstiftsproduktion",
            "financials": {
                "capital": "400,000 kr",
                "employees": {
                    "industriarb": 60
                },
                "annual_turnover": "1,358,000 kr"
            },
            "foundation_year": 1682,
            "corporation_year": 1899,
            "board": [
                {
                    "name": "kammarherre Fredrik v. Mecklenburg",
                    "role": "ordf."
                },
                {
                    "name": "ing. W. Schull-ström",
                    "role": "v. ordf."
                },
                {
                    "name": "disp. Em. Ljungström",
                    "role": "disp."
                }
            ],
            "director": "Em. Ljungström"
        },
        "2": {
            "name": "AB. Hägglund & Söner",
            "location": "Örnsköldsvik",
            "business": "Karosseri- och mekanisk tillverkning",
            "products": "Omnibusskarosserier, spårvagnar, rälsbussar, elektriska svetsmaskiner, skolbänkar, bastuaggregat, lamellskidor",
            "contact": {
                "phone": [
                    "1440"
                ],
                "postgiro": "28950"
            },
            "financials": {
                "capital": "693,000 kr",
                "employees": {
                    "industriarb": 800
                },
                "annual_turnover": "12,000,000 kr"
            },
            "foundation_year": 1899,
            "corporation_year": 1922,
            "board": [
                {
                    "name": "dir. Per Evert Hägglund",
                    "role": "ordf."
                },
                {
                    "name": "disp. Gösta E. Hägglund",
                    "role": "v. ordf."
                },
                {
                    "name": "fabr. Gustaf Hägglund",
                    "role": "fabr."
                }
            ],
            "director": "P. E. Hägglund",
            "sales_manager": "Georg Skogsberg",
            "manager": "John Lundblad"
        },
        "3": {
            "name": "AB. Joh. Hägglund",
            "location": "Örnsköldsvik",
            "business": "Sko- och handsktillverkning samt hud- och skinnexport",
            "products": "Sportskodon, norrlandspjäxor, arbetshandskar, raggsockor",
            "contact": {
                "telegraph": "Hägglundarna",
                "phone": "2402",
                "postgiro": "28943"
            },
            "financials": {
                "capital": "208,000 kr",
                "employees": {
                    "industriarb": 100
                },
                "annual_turnover": "1,450,000 kr"
            },
            "corporation_year": 1920,
            "board": [
                {
                    "name": "dir. John Hägglund",
                    "role": "ordf."
                },
                {
                    "name": "dir. Hjalmar Hägglund",
                    "role": "dir."
                },
                {
                    "name": "fabr. Karl H. Hägglund",
                    "role": "fabr."
                }
            ],
            "director": "Hjalmar Hägglund"
        },
        "4": {
            "name": "Fritz Haeggström AB.",
            "location": "Stockholm",
            "business": "Fiskkonservfabrik och engroshandel i kolonialvaror",
            "products": "Ansjovis, sill- och kaviarinläggningar",
            "contact": {
                "office": "Malmgårdsvägen 63",
                "telegraph": "Merchants",
                "phone": "440500",
                "postgiro": "3937"
            },
            "financials": {
                "capital": "75,000 kr",
                "employees": {
                    "industriarb": 50
                },
                "annual_turnover": "1,000,000 kr"
            },
            "corporation_year": 1930,
            "board": [
                {
                    "name": "Verkst. dir. Fritz Haeggström",
                    "role": "Verkst. dir."
                }
            ]
        },
        "5": {
            "name": "Ivar Haeggströms Boktryckeri & Bokförlags AB.",
            "location": "Stockholm",
            "business": "Boktryckeri, ståltryckeri och litografisk anstalt",
            "contact": {
                "office": "G:la Brog. 26",
                "phone": "Ivar Haeggströms",
                "postgiro": "3430"
            },
            "financials": {
                "capital": "800,000 kr",
                "employees": {
                    "industriarb": 129
                }
            },
            "corporation_year": 1899,
            "board": [
                {
                    "name": "disp. H. Engstrand",
                    "role": "disp."
                },
                {
                    "name": "dir. Göran Z. Haeggström",
                    "role": "dir."
                }
            ],
            "director": "Göran Z. Haeggström"
        },
        "6": {
            "name": "AB. Torsten Häggström",
            "location": "Borås",
            "business": "Trikåfabrik",
            "products": "Jumpers, koftor, stickade barnkläder, babyartiklar, herrvästar, slipovers",
            "contact": {
                "office": "Wiskabergs Fabriker",
                "phone": "13428",
                "postgiro": "71601"
            },
            "financials": {
                "capital": "100,000 kr",
                "employees": {
                    "industriarb": 32,
                    "hemarbetare": 150
                },
                "annual_turnover": "900,000 kr"
            },
            "corporation_year": 1934,
            "board": [
                {
                    "name": "dir. Erik Häggström",
                    "role": "dir."
                }
            ],
            "director": "Torsten Häggström"
        },
        "7": {
            "name": "Häggådalens Mek. Linneväfveriers AB.",
            "location": "Kinna",
            "business": "Linneväveri, blekeri och appreteringsverk",
            "products": "Duktyger, servietter, handdukar i damast, jacquard, dräll",
            "contact": {
                "telegraph": "Linne",
                "phone": "10027 o. 10207",
                "postgiro": "7998"
            },
            "financials": {
                "capital": "250,000 kr",
                "employees": {
                    "industriarb": 211
                },
                "annual_turnover": "6,000,000 kr"
            }
        }
    }
}