{
    "original": "Olsson\n\nTelegr.-adr. o. telefon: Abom, Borås.\nPostgiro: 10440. - Akt.-kap.: 440,000 kr.\nAntal industriarb.: 115, ävensom 30\nhemarbetare. — Firman grundad 1904, bolag\n1924.\n\nStyrelse: dir. Joel Olsson (ordf.),\nförsäljn.-chef Gösta Olsson, dir. Harry\nOlsson.\n\nVerkst. direktörer: J. Olsson o. H.\nOlsson.\n\n\"AB. Olsson &amp; Roséns Skofabrik,\n\nKumla.\n\nSkofabrik i Kumla (Örebro l.).\nTillverkar randsydda damskodon.\n\nTelefon: 71001—02. Postgiro; 28235.\n— Akt.-kap.: 50,000 kr. — Antal\nindustriarb.: 70. Tillv.-värde pr år: 855,000\nkr. — Firman etabl. 1923, bolag 1946.\n\nStyrelse o. verkst. direktörer: fabr.\nFolke Olsson o. fabr. Otto Rosén,\n\n\"Olsson &amp; Rosenlunds AB.,\n\nStockholm.\n\nBrädgård vid Hägersten, Stockholm,\nbrädgård i Sundbyberg, sågverk vid öster\nLedinge och Alby (Sthlms l.), sågverk,\nsnickerifabrik och tegelbruk vid Heby,\nbrädgård i Västerås, sågverk vid Kroksbo\n(Västmanl. l.) samt snickeri- och\nträhusfabrik i Västervik (Kalmar l.).\n\nTillverkar sågade och hyvlade trävaror,\nmonteringsfärdiga hus,\nbyggnadssnickerier, tak- och murtegel, dräneringsrör,\nglaserade lerrör samt form- och\ngolvplattor. Bolaget idkar jämväl jordbruk\noch skogshantering.\n\nHuvudkontor: Stockholm, Dalag. 1 C.\nTelegr.-adr.: Orab, Stockholm. Telefon:\n233710. Postgiro: 2726.\n\nAkt.-kap.: 4,350,000 kr. Antal\nindustriarb.: 350. — Firman etabl. 1882, bolag\n1916.\n\nStyrelse: dir. Fritz H. Eriksson, dir.\nL. Gösta Olsson, disp. A. Sigge\nRosenlund, dir. Ingvar Rosenlund, godsäg.\nErik-Lorentz SÖderhielm.\n\nVerkst. direktörer: L. Gösta Olsson o.\nA. Sigge Rosenlund.\n\n\"AB. Olssons Textilfabriker,\n\nHalmstad.\n\nVäveri, trikå- och konfektionsfabrik.\nTillverkar vävnader, sydda artiklar samt\ntrikåvaror.\n\nTelefon: »Olssons textil». Postgiro:\n140750. — Akt.-kap.: 150,000 kr. Antal\nindustriarb.: 90. Tillv.-värde pr år:\n3,000,000 kr.\n\nFirman etabl. 1935 i Värnamo under\nnamn AB. Wibom &amp; Co., nuv. namn och\nadress 1945.\n\nStyrelse: jur. dr Karl Hillgård (ordf.),\ndir. Helge Olsson, fröken Nanny Olsson.\n\nVerkst, dir.: Helge Olsson.\n\n\"A. Edv. Olsons Stålstämpelfabrik,\n\nEskilstuna.\n\nSe Stålstämpelfabriken, A. Edv. Olson,\nEskilstuna.\n\nBirger Olsson, Orsa Kättingfabrik,\n\nOr sa.\n\nSe Orsa Kättingfabrik, Birger Olsson,\nOrsa.\n\nAB. Daniel Olssons Pälsvarufabrik,\n\nTranås.\n\nTillverkar herr- och dampälsar,\npälsmössor och baretter. Varumärke:\n»Leopard».\n\nTelegr.-adr.: Pälsolsson, Tranås.\nTelefon: 2427. Postgiro: 29443.\n\nAkt.-kap.: 85,000 kr. Antal\nindustriarb.: 45. Tillv.-värde pr år: 700,000 kr.\n— Firman etabl. 1919, bolag 1927.\n\nDisp.: Torbjörn Olsson.\n\n\"Emil Olssons Fickkniv Fabriks AB.,\n\nEskilstuna.\n\nSmidesverkstad. Tillverkar fick- och\npennknivar, etsade och förgyllda\nstålarbeten samt stålskalor och skjutmått.\n\nTelefon: 30013 o. 34588. Postgiro:\n13713. — Akt.-kap.: 75,000 kr.\nTillv.-värde pr år: 300,000 kr. — Firman etabl.\n1896, bolag 1928.\n\nStyrelse: bankkassör Bror Olsson, fabr.\nEinar Olsson, ing. Harry Olsson, kamrer\nRuben Olsson.\n\nProkurist: Ruben Olsson.\n\n\"F. Olssons Skofabrik, Nya Varvet.\n\nSe Bröderna Olssons Skofabrik, Nya\nVarvet.\n\n\"AB. Håkan Ohlssons Boktryckeri,\n\nhund.\n\nBoktryckeri med bokbinderi och\nblankettförlag. Utför affärstryck och\nboktryck, spec. akademiska avhandlingar,\nvetenskapliga verk samt kataloger.\n\nKontor: S:t Anneg. 4. Telegr.-adr.:\nHåkanohlsson, Lund. Telefon: »Håkan\nOhlsson» eller 17040. Postgiro: 6928.",
    "structured": {
        "1": {
            "name": "AB. Olsson & Roséns Skofabrik",
            "location": "Kumla",
            "business": "Skofabrik",
            "products": "Tillverkar randsydda damskodon",
            "contact": {
                "office": "Kumla, Örebro l.",
                "phone": [
                    "71001—02"
                ],
                "postgiro": "28235"
            },
            "financials": {
                "capital": "50,000 kr",
                "annual_turnover": "855,000 kr",
                "annual_production_value": "855,000 kr"
            },
            "foundation_year": 1923,
            "board": [
                {
                    "name": "fabr. Folke Olsson",
                    "role": "Styrelse"
                },
                {
                    "name": "fabr. Otto Rosén",
                    "role": "Styrelse"
                }
            ],
            "managing_director": "J. Olsson",
            "sales_manager": "H. Olsson"
        },
        "2": {
            "name": "Olsson & Rosenlunds AB.",
            "location": "Stockholm",
            "business": "Brädgård, sågverk, snickerifabrik, tegelbruk",
            "products": "Sågade och hyvlade trävaror, monteringsfärdiga hus, byggnadssnickerier, tak- och murtegel, dräneringsrör, glaserade lerrör, form- och golvplattor",
            "contact": {
                "office": "Stockholm, brädgård vid Hägersten",
                "phone": [
                    "233710"
                ],
                "postgiro": "2726"
            },
            "financials": {
                "capital": "4,350,000 kr",
                "annual_turnover": "Not available",
                "annual_production_value": "Not available"
            },
            "foundation_year": 1882,
            "board": [
                {
                    "name": "dir. Fritz H. Eriksson",
                    "role": "Styrelse"
                },
                {
                    "name": "L. Gösta Olsson",
                    "role": "Styrelse"
                },
                {
                    "name": "A. Sigge Rosenlund",
                    "role": "Disposition"
                },
                {
                    "name": "Ingvar Rosenlund",
                    "role": "Styrelse"
                },
                {
                    "name": "godsäg. Erik-Lorentz Söderhielm",
                    "role": "Styrelse"
                }
            ],
            "managing_director": "L. Gösta Olsson",
            "sales_manager": "A. Sigge Rosenlund"
        },
        "3": {
            "name": "AB. Olssons Textilfabriker",
            "location": "Halmstad",
            "business": "Väveri, trikå- och konfektionsfabrik",
            "products": "Vävnader, sydda artiklar, trikåvaror",
            "contact": {
                "office": "Halmstad",
                "phone": [
                    "Olssons textil"
                ],
                "postgiro": "140750"
            },
            "financials": {
                "capital": "150,000 kr",
                "annual_turnover": "3,000,000 kr",
                "annual_production_value": "3,000,000 kr"
            },
            "foundation_year": 1935,
            "board": [
                {
                    "name": "jur. dr Karl Hillgård",
                    "role": "Styrelse"
                },
                {
                    "name": "Helge Olsson",
                    "role": "Styrelse"
                }
            ],
            "managing_director": "Helge Olsson"
        },
        "4": {
            "name": "AB. Daniel Olssons Pälsvarufabrik",
            "location": "Tranås",
            "business": "Pälsvarufabrik",
            "products": "Herr- och dampälsar, pälsmössor, baretter",
            "contact": {
                "office": "Tranås",
                "phone": [
                    "2427"
                ],
                "postgiro": "29443"
            },
            "financials": {
                "capital": "85,000 kr",
                "annual_turnover": "700,000 kr",
                "annual_production_value": "700,000 kr"
            },
            "foundation_year": 1919,
            "board": [
                {
                    "name": "Torbjörn Olsson",
                    "role": "Disposition"
                }
            ]
        },
        "5": {
            "name": "Emil Olssons Fickkniv Fabriks AB.",
            "location": "Eskilstuna",
            "business": "Smidesverkstad",
            "products": "Fick- och pennknivar, etsade och förgyllda stålarbeten, stålskalor, skjutmått",
            "contact": {
                "office": "Eskilstuna",
                "phone": [
                    "30013",
                    "34588"
                ],
                "postgiro": "13713"
            },
            "financials": {
                "capital": "75,000 kr",
                "annual_turnover": "300,000 kr",
                "annual_production_value": "300,000 kr"
            },
            "foundation_year": 1896,
            "board": [
                {
                    "name": "bankkassör Bror Olsson",
                    "role": "Styrelse"
                },
                {
                    "name": "fabr. Einar Olsson",
                    "role": "Styrelse"
                },
                {
                    "name": "ing. Harry Olsson",
                    "role": "Styrelse"
                }
            ],
            "manager": "Ruben Olsson"
        },
        "6": {
            "name": "AB. Håkan Ohlssons Boktryckeri",
            "location": "Lund",
            "business": "Boktryckeri med bokbinderi och blankettförlag",
            "products": "Affärstryck, boktryck, akademiska avhandlingar, vetenskapliga verk, kataloger",
            "contact": {
                "office": "Lund",
                "phone": [
                    "Håkan Ohlsson",
                    "17040"
                ],
                "postgiro": "6928"
            }
        }
    }
}