{
    "original": "Börtzell—Gardell\n\narb.: 80. Tillv.-värde pr år: 700,000 kr.\nÅrstillv.: 2,250 stds trävaror. — Bolaget\ngrundat 1942.\n\nStyrelse o. verkst. dir.: Per Börser.\n\n*A. Börtzells Tryckeri AB.,\n\nStockholm.\n\nTryckeri och kemigrafisk anstalt.\nUtför heliogravyr, koppar-, ljus-, djup-,\nlitografiskt och offsettryck, klichéer för\nsvart- och flerfärgstryck, fotolitografi\noch fotografiska reproduktioner, skiop-\n\ntikonbilder i svart och i färger\n(uva-chrommetoden) samt färgfotografi med\npapperskopior.\n\nKontor: Vasag. 16. Telefon:\n»Stabs-litografen». Postgiro: 488.\n\nBolaget, som grundades 1886, innehar\nGeneralstabens Litografiska Anstalt och\när anslutet till AB. Sveriges Litografiska\nTryckerier, Stockholm. (Se detta bolag.)\n\nStyrelse: disp. Gustaf Dahlbäck,\ngeneralkonsul R. Söderberg, ryttm. Åke G.\nWickman, dir. Knut Östberg.\n\nVerkst. dir.: Åke G. Wickman.\n\n* utmärker till Sveriges Industriförbund anslutna företag.\n\n*Cacao- &amp; Chokladfabriken Stella,\n\nAB., Stockholm.\n\nSe Stella AB. Cacao- &amp; Chokladfabrik,\nStockholm.\n\n*AB. Calmoverken, Målilla station.\n\nMek. verkstad och gjuteri i Målilla\n(Kalmar l.). Tillverkar råolje- och\ndieselmotorer, sågverksmaskiner, kompressorer\noch fläktar.\n\nTelegr.-adr. o. telefon: Calmoverken,\nMålilla station. Postgiro: 6066.\n\nAkt.-kap.: 110,000 kr. Antal\nindustriarb.: 25- Tillv.-värde pr år: 390,000 kr.\n— Firman etabl. 1907, bolag 1937 under\nnamn AB. Målilla Mek. Verkstad, nuv.\nnamn 1944.\n\nStyrelse: disp. Erik Alm (ordf.),\nverkstadschef Axel Alm, disp. Gustaf Alm.\n\nVerkst. dir.: Erik Alm.\n\nVerkstadschef: Axel Alm.\n\n*Calor, Värmelednings AB.,\n\nStockholm.\n\nSe Värmelednings AB. Galor,\nStockholm.\n\n*AB. Calvert &amp; Co., Göteborg.\n\nSe AB. Flobvverken, Göteborg.\n\nAB. Canos, Påarp.\n\nMaskinpackningsfabrik i Påarp\n(Malmöh. l.). Tillverkar packningar för\nångmaskiner, ångpannor, pumpar m. m.\nVarumärke: »Canos».\n\nTelefon: Hälsingborg 97045 o. 97042.\n\nPostgiro: 94385. — Akt.-kap.: 30,000 kr.\nAntal industriarb.: 30. — Bolaget\ngrundat 1935.\n\nVerkst. dir.: Carl A. Nordström.\n\nDisp.: Sven A. Nordström, ....,\n\n*Cap Chokladfabrik AB., Göteborg.\n\nTillverkar choklad, kola, karameller,\n\nkonfekt och dragéer.\n\nKontor: ö. Hamng. 17. Telegr.-adr.:\nCap, Göteborg. Telefon: »Capchoklad».\nPostgiro: 12101. Avd.-kohtor: i\n’Stockholm: Scheeleg. 24, telefon: 501323 o.\n501373, postgiro: 4650; i Malmö:\nMalm-borgsg. 7, telefon: 18575, postgiro:\n149011.\n\nAkt.-kap.: 875,000 kr. Antal\nindustriarb.: 160. — Firman etabl. 1895, bolag\n1916.\n\nStyrelse: dir. J. Elis Lindell (ordf.),\ndir.-assist. Claes A. Palmers, dir. Oscar\nPalmers.\n\nVerkst. dir.: Oscar Palmers.\n\nFabrikschef: disp. Regis Palmers.\n\nCarbidkontoret, AB. Svenska,\n\nGöteborg.\n\nSe AB. Svenska Carbidkontoret,\nGöteborg.\n\nE. Cardell Portfölj varufabri k,\n\nMalmö,\n\nTillverkar portföljer, portmonnäer,\nplånböcker och damväskor.\n\nKontor: S:t Tomasg. IB. Telefon:\n27096 o. 18996. Postgiro: 38109. — Antal\nindustriarb.: 50. — Firman etabl. 1925,\n\nÄgare o. chef: fabr. E. Cardell.\n\n91’",
    "structured": {
        "1": {
            "name": "Börtzells Tryckeri AB.",
            "location": "Stockholm",
            "business": "Tryckeri och kemigrafisk anstalt",
            "products": "Utför heliogravyr, koppar-, ljus-, djup-, litografiskt och offsettryck, klichéer för svart- och flerfärgstryck, fotolitografi och fotografiska reproduktioner, skiop- tikonbilder i svart och i färger (uva-chrommetoden) samt färgfotografi med papperskopior.",
            "contact": {
                "office": "Vasag. 16",
                "phone": [
                    "Stabs-litografen"
                ],
                "postgiro": "488"
            },
            "financials": {
                "capital": "Okänt",
                "employees": {
                    "Okänt": null
                },
                "annual_turnover": "Okänt",
                "annual_production_value": "Okänt"
            },
            "foundation_year": 1886,
            "board": [
                {
                    "name": "disp. Gustaf Dahlbäck",
                    "role": "Okänt"
                },
                {
                    "name": "generalkonsul R. Söderberg",
                    "role": "Okänt"
                },
                {
                    "name": "ryttm. Åke G. Wickman",
                    "role": "Okänt"
                },
                {
                    "name": "dir. Knut Östberg",
                    "role": "Okänt"
                }
            ],
            "director": "Per Börser"
        },
        "2": {
            "name": "Cacao- & Chokladfabriken Stella, AB.",
            "location": "Stockholm",
            "contact": {
                "phone": [
                    "Okänt"
                ],
                "postgiro": "Okänt"
            },
            "original_name": "Stella AB. Cacao- & Chokladfabrik",
            "foundation_year": 1945
        },
        "3": {
            "name": "AB. Calmoverken",
            "location": "Målilla station",
            "business": "Mek. verkstad och gjuteri",
            "products": "Tillverkar råolje- och dieselmotorer, sågverksmaskiner, kompressorer och fläktar.",
            "contact": {
                "office": "Okänt",
                "phone": [
                    "Calmoverken, Målilla station"
                ],
                "postgiro": "6066"
            },
            "financials": {
                "capital": "110000 kr",
                "employees": {
                    "Industriarb.": 25
                },
                "annual_turnover": "390000 kr",
                "annual_production_value": "Okänt"
            },
            "foundation_year": 1907,
            "current_name_year": 1944,
            "board": [
                {
                    "name": "disp. Erik Alm",
                    "role": "ordf."
                },
                {
                    "name": "verkstadschef Axel Alm",
                    "role": "Okänt"
                },
                {
                    "name": "disp. Gustaf Alm",
                    "role": "Okänt"
                }
            ],
            "director": "Erik Alm",
            "managing_director": "Okänt"
        },
        "4": {
            "name": "Calor, Värmelednings AB.",
            "location": "Stockholm",
            "original_name": "Värmelednings AB. Galor",
            "foundation_year": 1945
        },
        "5": {
            "name": "AB. Calvert & Co.",
            "location": "Göteborg",
            "original_name": "AB. Flobvverken"
        },
        "6": {
            "name": "AB. Canos",
            "location": "Påarp",
            "business": "Maskinpackningsfabrik",
            "products": "Tillverkar packningar för ångmaskiner, ångpannor, pumpar m. m. Varumärke: »Canos».",
            "contact": {
                "phone": [
                    "Hälsingborg 97045",
                    "Hälsingborg 97042"
                ],
                "postgiro": "94385"
            },
            "financials": {
                "capital": "30000 kr",
                "employees": {
                    "Industriarb.": 30
                },
                "annual_turnover": "Okänt",
                "annual_production_value": "Okänt"
            },
            "foundation_year": 1935,
            "board": [
                {
                    "name": "Carl A. Nordström",
                    "role": "Okänt"
                }
            ],
            "director": "Carl A. Nordström",
            "original_name": "Okänt"
        },
        "7": {
            "name": "Cap Chokladfabrik AB.",
            "location": "Göteborg",
            "business": "Tillverkar choklad, kola, karameller, konfekt och dragéer",
            "products": "Okänt",
            "contact": {
                "office": "ö. Hamng. 17",
                "phone": [
                    "Capchoklad"
                ],
                "postgiro": "12101"
            },
            "financials": {
                "capital": "875000 kr",
                "employees": {
                    "Industriarb.": 160
                },
                "annual_turnover": "Okänt",
                "annual_production_value": "Okänt"
            },
            "foundation_year": 1916,
            "board": [
                {
                    "name": "dir. J. Elis Lindell",
                    "role": "ordf."
                },
                {
                    "name": "dir.-assist. Claes A. Palmers",
                    "role": "Okänt"
                },
                {
                    "name": "dir. Oscar Palmers",
                    "role": "Okänt"
                }
            ],
            "director": "Oscar Palmers",
            "original_name": "Okänt",
            "managing_director": "disp. Regis Palmers"
        },
        "8": {
            "name": "Carbidkontoret, AB. Svenska",
            "location": "Göteborg",
            "original_name": "AB. Svenska Carbidkontoret"
        },
        "9": {
            "name": "E. Cardell Portfölj varufabri k",
            "location": "Malmö",
            "business": "Tillverkar portföljer, portmonnäer, plånböcker och damväskor",
            "contact": {
                "office": "S:t Tomasg. IB",
                "phone": [
                    "27096",
                    "18996"
                ],
                "postgiro": "38109"
            },
            "financials": {
                "employees": {
                    "Industriarb.": 50
                }
            },
            "foundation_year": 1925,
            "manager": "fabr. E. Cardell"
        }
    }
}