{
    "original": "Anders—Andersson\n\n* Anders Siden väveri AB.,\n\nNorrköping.\n\nTillverkar sidentyger av konstsilke\nsåsom satin fleur, crepe satin, crepe de\nchine m. fl. modebetonade\nklännings-tyger.\n\nTelegr.-adr.: Andersiden, Norrköping.\nTelefon: 30134. Postgiro: 272392.\n\nAkt.-kap.: 63,000 kr. Antal\nindustri-arb.: 15. — Bolaget grundat 1944.\n\nStyrelse: bankdir. Albert Änder (ordf.),\ning. Lennart Änder, provinsialläkare\nIvan Wildner.\n\nVerkst. dir.: Lennart Änder.\n\nAndersson &amp; Son, Ljungby.\n\nSe Ljungby Snickerifabrik, Andersson\n&amp; Son, Ljungby.\n\nAndersons Formfabrik, Bröderna,\n\nAlvesta.\n\nSe Bröderna Andersons Formfabrik,\nAlvesta.\n\nAnderssons Cjuteri, AB. Bröderna,\n\nSkurup.\n\nSe AB. Bröderna Anderssons Gjuteri,\nSkurup.\n\nAB. Andersson &lt;&amp; Hjalmarson,\n\nUlricehamn.\n\nTrikåfabrik. Tillverkar bluskoftor,\nbäddjackor och damjumper samt\nherrtröjor.\n\ntelefon: 744. Postgiro: 131844. —\nAkt.-kap.: 20,000 kr. Antal industriarb’.:\n10. Tillv.-värde pr år: 200,000 kr. —\nFirman etabl. 1934, bolag 1939.\n\nChef: fabr. Jonas Hjalmarson.\n\nAndersson &amp; Johansson, Höganäs.\n\nTillverkar konstkeramik, eldfast\nhushållsgods samt blomkrukor vid keramisk\nverkstad i Höganäs (Malmöh. l.).\n\nTelefon: 294. Postgiro: 30487. —\nAntal industriarb.: 50. Tillv.-värde pr år:\n250,000 kr. — Firman etabl. 1909.\n\nÄgare o. chefer: fabr. Karl A.\nAndersson o. fabr. Sigfrid Johansson.\n\nAndersson &amp; Liberg,\nKassaskåpsfabrik, Hagalund.\n\nTillverkar kassaskåp, brandisolerade\nståldörrar, kassavalvsdörrar,\ndepositions-fack, dörrar för hisschakt och kylrum,\narkivinredningar, flyttbara bibliotekshyl-\n\nlor m. m. samt elektr. instrumenttavlor\noch ställverk.\n\nKontor: Industrivägen 25, Hagalund.\nTelefon: Stockholm 274353 o. 273687.\nPostgiro: 50864.\n\nAntal industriarb.: 50. Tillv.-värde pr\når: 500,000 kr. — Firman etabl. 1917.\nÄgare o. chef: fabr. K. M. Liberg.\n\n*\tAndersson &amp; Lundgren, Malmö.\n\nMetallvarufabrik. Tillverkar elektr.\nbelysningsarmatur.\n\nKontor: Djäkneg. 21. Telegr.-adr.:\nAndlund, Malmö. Telefon: 21804.\nPostgiro: 24476. — Antal industriarb.: 11. -—\nFirman etabl. 1901.\n\nÄgare o. chef: fabr. John B.\nAnders-&gt; son.\n\n—Andersson &amp; Nilsander, Lydde\nTegelbruk, Kinna.\n\nSe Lydde Tegelbruk, Andersson &amp;\nNilsander, Kinna»\n\n*\tAndersson &amp; Sahlström, Skara\nSnickeri &amp; Trävaruaffär, Skara.\n\nSe Skara Snickeri &amp; Trävaruaffär,\nAndersson &amp; Sahlström, Skara.\n\nAndersson &amp; Sundberg,\nBåtbyggeri-bolag, Söderköping.\n\nSe Båtbyggeribolaget Andersson &amp;\nSundberg, Söderköping.\n\n^Anderssons Velociped- &amp;\nRadio-fabrik AB., Bröderna, Göteborg.\n\nSe Bröderna Anderssons Velociped- dt\nRadiofabrik AB., Göteborg.\n\n*Axel Andersson &amp; Co. AB.,\n\nKungsör.\n\nSe Kungsörs Träindustri, Axel\nAndersson &amp; Co. AB., Kungsör.\n\n*A. C. Anderssons AB., Kumla.\n\nSkofabrik i Kumla. Tillverkar\nrand-sydda, sandalsydda och durksydda\nskodon, sport- och militärkängor.\n\nTelefon: Örebro 70001 o. 70026. —\nAkt.-kap.: 400,800 kr. Antal industriarb.:\n200. Tillv.-värde pr år: 3,000,000 kr. —\nFirman etabl. 1880, bolag 1928.\n\nStyrelse: disp. Harry Andersson, disp.\nHelmer Andersson-Age, dir. Reinhold\nBerglund.\n\nVerkst. dir.: vakant.",
    "structured": {
        "1": {
            "name": "Anders Siden väveri AB.",
            "location": "Norrköping",
            "business": "Sidentyger av konstsilke",
            "products": "Satin fleur, crepe satin, crepe de chine m. fl. modebetonade klännings-tyger",
            "contact": {
                "office": "Andersiden, Norrköping",
                "phone": [
                    "30134"
                ],
                "postgiro": "272392",
                "head_office": null,
                "sales_offices": null,
                "telegraph": "Andersiden, Norrköping",
                "factory_office": null,
                "factory_phone": null
            },
            "financials": {
                "capital": "63,000 kr",
                "employees": {
                    "industri-arb": 15
                },
                "annual_turnover": null
            },
            "foundation_year": 1944,
            "current_name_year": null,
            "predecessor": null,
            "original_name": null,
            "corporation_year": null,
            "board": [
                {
                    "name": "Albert Änder",
                    "role": "bankdir."
                },
                {
                    "name": "Lennart Änder",
                    "role": "ing."
                },
                {
                    "name": "Ivan Wildner",
                    "role": "provinsialläkare"
                }
            ],
            "owners": null,
            "director": null,
            "managing_director": "Lennart Änder",
            "sales_manager": null,
            "manager": null
        },
        "2": {
            "name": "Andersson & Son, Ljungby",
            "location": "Ljungby",
            "business": "Snickerifabrik",
            "products": null,
            "contact": {
                "office": null,
                "phone": null,
                "postgiro": null,
                "head_office": null,
                "sales_offices": null,
                "telegraph": null,
                "factory_office": null,
                "factory_phone": null
            },
            "financials": {
                "capital": null,
                "employees": null,
                "annual_turnover": null
            },
            "foundation_year": null,
            "current_name_year": null,
            "predecessor": null,
            "original_name": null,
            "corporation_year": null,
            "board": null,
            "owners": null,
            "director": null,
            "managing_director": null,
            "sales_manager": null,
            "manager": null
        },
        "3": {
            "name": "Andersons Formfabrik, Bröderna",
            "location": "Alvesta",
            "business": "Formfabrik",
            "products": null,
            "contact": {
                "office": null,
                "phone": null,
                "postgiro": null,
                "head_office": null,
                "sales_offices": null,
                "telegraph": null,
                "factory_office": null,
                "factory_phone": null
            },
            "financials": {
                "capital": null,
                "employees": null,
                "annual_turnover": null
            },
            "foundation_year": null,
            "current_name_year": null,
            "predecessor": null,
            "original_name": null,
            "corporation_year": null,
            "board": null,
            "owners": null,
            "director": null,
            "managing_director": null,
            "sales_manager": null,
            "manager": null
        },
        "4": {
            "name": "Anderssons Cjuteri, AB. Bröderna",
            "location": "Skurup",
            "business": "AB. Bröderna Anderssons Gjuteri",
            "products": null,
            "contact": {
                "office": null,
                "phone": null,
                "postgiro": null,
                "head_office": null,
                "sales_offices": null,
                "telegraph": null,
                "factory_office": null,
                "factory_phone": null
            },
            "financials": {
                "capital": null,
                "employees": null,
                "annual_turnover": null
            },
            "foundation_year": null,
            "current_name_year": null,
            "predecessor": null,
            "original_name": null,
            "corporation_year": null,
            "board": null,
            "owners": null,
            "director": null,
            "managing_director": null,
            "sales_manager": null,
            "manager": null
        },
        "5": {
            "name": "AB. Andersson & Hjalmarson",
            "location": "Ulricehamn",
            "business": "Trikåfabrik",
            "products": "Bluskoftor, bäddjackor, damjumper, herrtröjor",
            "contact": {
                "office": null,
                "phone": [
                    "744"
                ],
                "postgiro": "131844",
                "head_office": null,
                "sales_offices": null,
                "telegraph": null,
                "factory_office": null,
                "factory_phone": null
            },
            "financials": {
                "capital": "20,000 kr",
                "employees": {
                    "industriarb": 10
                },
                "annual_turnover": "200,000 kr"
            },
            "foundation_year": 1939,
            "current_name_year": null,
            "predecessor": null,
            "original_name": null,
            "corporation_year": null,
            "board": null,
            "owners": null,
            "director": null,
            "managing_director": "Jonas Hjalmarson",
            "sales_manager": null,
            "manager": null
        },
        "6": {
            "name": "Andersson & Johansson",
            "location": "Höganäs",
            "business": "Konstkeramik, eldfast hushållsgods, blomkrukor",
            "products": null,
            "contact": {
                "office": null,
                "phone": [
                    "294"
                ],
                "postgiro": "30487",
                "head_office": null,
                "sales_offices": null,
                "telegraph": null,
                "factory_office": null,
                "factory_phone": null
            },
            "financials": {
                "capital": null,
                "employees": {
                    "industriarb": 50
                },
                "annual_turnover": "250,000 kr"
            },
            "foundation_year": 1909,
            "current_name_year": null,
            "predecessor": null,
            "original_name": null,
            "corporation_year": null,
            "board": null,
            "owners": [
                "Karl A. Andersson",
                "Sigfrid Johansson"
            ],
            "director": null,
            "managing_director": null,
            "sales_manager": null,
            "manager": null
        },
        "7": {
            "name": "Andersson & Liberg, Kassaskåpsfabrik",
            "location": "Hagalund",
            "business": "Kassaskåp, brandisolerade ståldörrar, kassavalvsdörrar",
            "products": "Depositions-fack, dörrar för hisschakt, kylrum, arkivinredningar, flyttbara bibliotekshyllor, elektr. instrumenttavlor, ställverk",
            "contact": {
                "office": "Industrivägen 25, Hagalund",
                "phone": [
                    "Stockholm 274353",
                    "Stockholm 273687"
                ],
                "postgiro": "50864",
                "head_office": null,
                "sales_offices": null,
                "telegraph": null,
                "factory_office": null,
                "factory_phone": null
            },
            "financials": {
                "capital": null,
                "employees": {
                    "industriarb": 50
                },
                "annual_turnover": "500,000 kr"
            },
            "foundation_year": 1917,
            "current_name_year": null,
            "predecessor": null,
            "original_name": null,
            "corporation_year": null,
            "board": null,
            "owners": [
                "Fabr. K. M. Liberg"
            ],
            "director": null,
            "managing_director": null,
            "sales_manager": null,
            "manager": null
        },
        "8": {
            "name": "Andersson & Lundgren",
            "location": "Malmö",
            "business": "Metallvarufabrik",
            "products": "Elektr. belysningsarmatur",
            "contact": {
                "office": "Djäkneg. 21",
                "phone": [
                    "21804"
                ],
                "postgiro": "24476",
                "head_office": null,
                "sales_offices": null,
                "telegraph": null,
                "factory_office": null,
                "factory_phone": null
            },
            "financials": {
                "capital": null,
                "employees": {
                    "industriarb": 11
                },
                "annual_turnover": null
            },
            "foundation_year": 1901,
            "current_name_year": null,
            "predecessor": null,
            "original_name": null,
            "corporation_year": null,
            "board": null,
            "owners": [
                "Fabr. John B. Andersson"
            ],
            "director": null,
            "managing_director": null,
            "sales_manager": null,
            "manager": null
        },
        "9": {
            "name": "Andersson & Nilsander, Lydde Tegelbruk",
            "location": "Kinna",
            "business": "Tegelbruk",
            "products": null,
            "contact": {
                "office": null,
                "phone": null,
                "postgiro": null,
                "head_office": null,
                "sales_offices": null,
                "telegraph": null,
                "factory_office": null,
                "factory_phone": null
            },
            "financials": {
                "capital": null,
                "employees": null,
                "annual_turnover": null
            },
            "foundation_year": null,
            "current_name_year": null,
            "predecessor": null,
            "original_name": null,
            "corporation_year": null,
            "board": null,
            "owners": null,
            "director": null,
            "managing_director": null,
            "sales_manager": null,
            "manager": null
        },
        "10": {
            "name": "Andersson & Sahlström, Skara Snickeri & Trävaruaffär",
            "location": "Skara",
            "business": "Trävaruaffär",
            "products": null,
            "contact": {
                "office": null,
                "phone": null,
                "postgiro": null,
                "head_office": null,
                "sales_offices": null,
                "telegraph": null,
                "factory_office": null,
                "factory_phone": null
            },
            "financials": {
                "capital": null,
                "employees": null,
                "annual_turnover": null
            },
            "foundation_year": null,
            "current_name_year": null,
            "predecessor": null,
            "original_name": null,
            "corporation_year": null,
            "board": null,
            "owners": null,
            "director": null,
            "managing_director": null,
            "sales_manager": null,
            "manager": null
        },
        "11": {
            "name": "Andersson & Sundberg, Båtbyggeri-bolag",
            "location": "Söderköping",
            "business": "Båtbyggeri-bolag",
            "products": null,
            "contact": {
                "office": null,
                "phone": null,
                "postgiro": null,
                "head_office": null,
                "sales_offices": null,
                "telegraph": null,
                "factory_office": null,
                "factory_phone": null
            },
            "financials": {
                "capital": null,
                "employees": null,
                "annual_turnover": null
            },
            "foundation_year": null,
            "current_name_year": null,
            "predecessor": null,
            "original_name": null,
            "corporation_year": null,
            "board": null,
            "owners": null,
            "director": null,
            "managing_director": null,
            "sales_manager": null,
            "manager": null
        },
        "12": {
            "name": "Anderssons Velociped- & Radio-fabrik AB., Bröderna",
            "location": "Göteborg",
            "business": "Bröderna Anderssons Velociped- dt Radiofabrik AB.",
            "products": null,
            "contact": {
                "office": null,
                "phone": null,
                "postgiro": null,
                "head_office": null,
                "sales_offices": null,
                "telegraph": null,
                "factory_office": null,
                "factory_phone": null
            },
            "financials": {
                "capital": null,
                "employees": null,
                "annual_turnover": null
            },
            "foundation_year": null,
            "current_name_year": null,
            "predecessor": null,
            "original_name": null,
            "corporation_year": null,
            "board": null,
            "owners": null,
            "director": null,
            "managing_director": null,
            "sales_manager": null,
            "manager": null
        },
        "13": {
            "name": "Axel Andersson & Co. AB.",
            "location": "Kungsör",
            "business": "Kungsörs Träindustri",
            "products": null,
            "contact": {
                "office": null,
                "phone": null,
                "postgiro": null,
                "head_office": null,
                "sales_offices": null,
                "telegraph": null,
                "factory_office": null,
                "factory_phone": null
            },
            "financials": {
                "capital": null,
                "employees": null,
                "annual_turnover": null
            },
            "foundation_year": null,
            "current_name_year": null,
            "predecessor": null,
            "original_name": null,
            "corporation_year": null,
            "board": null,
            "owners": null,
            "director": null,
            "managing_director": null,
            "sales_manager": null,
            "manager": null
        },
        "14": {
            "name": "A. C. Anderssons AB.",
            "location": "Kumla",
            "business": "Skofabrik",
            "products": "Rand-sydda, sandalsydda, durksydda skodon, sport- och militärkängor",
            "contact": {
                "office": null,
                "phone": [
                    "Örebro 70001",
                    "Örebro 70026"
                ],
                "postgiro": null,
                "head_office": null,
                "sales_offices": null,
                "telegraph": null,
                "factory_office": null,
                "factory_phone": null
            },
            "financials": {
                "capital": "400,800 kr",
                "employees": {
                    "industriarb": 200
                },
                "annual_turnover": "3,000,000 kr"
            },
            "foundation_year": 1928,
            "current_name_year": null,
            "predecessor": null,
            "original_name": null,
            "corporation_year": null,
            "board": null,
            "owners": [
                "Disp. Harry Andersson",
                "Disp. Helmer Andersson-Age",
                "Dir. Reinhold Berglund"
            ],
            "director": null,
            "managing_director": null,
            "sales_manager": null,
            "manager": null
        }
    }
}