{
    "original": "Konstgödning—Kopia\n\n\"Konstgödnings &amp;\nSvavelsyrefabrikerna! Svenska, Malmö.\n\nSe^ AB. Förenade Superfosfatfabriker,\nHälsingborg.\n\n\"Konsthantverk, Tyringe.\n\nMetallvarufabrik i Tyringe (Kristianst.\n1.). Tillverkar elektr. belysningsarmatur\nsamt utför metallpressningar,\nbutiksinredningar m. m.\n\nTelefon: 116. Postgiro: 23558. —\nAntal industriarb.: 20. Tillv.-värde pr år:\n200,000 kr. — Firman etabl. 1921.\n\nÄgare o. chefer: fabr. Frans Oscar\nJohansson o. verkm. Carl-Emil Johansson.\n\nAB. Konst harts, Trelleborg.\n\nBakelitpressverk. Tillverkar detaljer av\nfenol- och karbamidpressmassor samt av\ntermoplastiska material.\n\nTelefon: 1720. Postgiro: 281815. —\nAkt.-kap.: 100,000 kr. Antal industriarb.:\n130. — Bolaget grundat 1934.\n\nStyrelse o. verJcst. dir.; fil. dr B.\nStein-hoff.\n\nKonsthartz-Industri, Svensk, Gemla.\n\nSe Svensk Konsthartz-Industri, Gemla.\n\n\"Konstruktör, Byggnads AB., Gävle.\nSe Byggnads AB. Konstruktör, Gävle.\n\n\"Konstsilke, AB. Svenskt, Borås.\nSe AB. Svenskt Konstsilke, Borås.\n\nAB. Kontrollinstrument, Stockholm.\n\nInstrument- och finmekanisk verkstad.\nTillverkar manometrar och termometrar,\nfinmekaniska instrument samt\nspecialverktyg. Varumärke: »AKI».\n\nKontor: Kungstensg. 18. Telegr.-adr.:\nAkimätare, Stockholm. Telefon: 327432\n\n—\t33. Postgiro: 192610.\n\nAkt.-kap.: 100,000 kr. Antal\nindustriarb.: 70. Tillv.-värde pr år: 1,000,000 kr.\n\n—\tBolaget grundat 1941.\nVerkst. dir.: ing. Erik Hysing.\nFörsäljn.-dir.: Nils Järte.\n\n\"Kontrollregister, AB. Svenskt,\n\nStockholm.\n\nSe AB. Svenskt Kontrollregister,\nStockholm.\n\n\"Kooperativa Förbundets Kem.\nTekn. Fabrik, Malmö.\n\nTillverkar kem. tekniska preparat;\nutför målning samt paketering av kryddor\noch te.\n\nKontor: St. Trädgårdsg. 4. Telefon:\n28743 o. 28789. Huvudkontor: Stockholm,\nStadsgården 6. Telegr.-adr. o. telefon:\nKooperativa, Stockholm.\n\nAntal industriarb.: 65. Tillv.-värde pr\når: 3,000,000 kr.\n\nÄgare: Kooperativa Förbundet.\n\nDisp.: Gunnar Petterson.\n\nKamrer: Harry Ohlsson.\n\n\"Kooperativa Förbundet\nMargarinfabriken AB., Norrköping.\n\nTillverkar margarin.\n\nTelegr.-adr.: Margarinf abrik,\nNorrköping. Telefon: 29460.\n\nAkt.-kap.: 3,000,000 kr. Antal\nindustriarb.: 55. Tillv.-värde pr år: 26,000,000 kr.\n— Fabriken anlagd 1920.\n\nStyrelse: dir. Albin Johansson (ordf.)*\nfil. lic. Mauritz Bonow, dir. Hj.\nDeger-stedt, dir. Hugo Edstam, dir. G. Osvaldy\ndir. Ernst Persson, konsul S. H.\nSörensen.\n\nVerkst. dir.: S. H. Sörensen.\n\n\"Kooperativa Förbundets Mek.\nVerkstad, Stockholm.\n\nSe AB. Svenskt Kontrollregister,\nStockholm.\n\n\"Kooperativa Superfosfatfabriks AB.»\n\nStockholm.\n\nSuperfosfatf abrik vid Gädd viken\n(Sthlms l.). — Akt.-kap.: 3,000.000 kr.\n\nFabriken är intill den 1 juli 1947\nutarrenderad till AB. Förenade\nSuperfosfatfabriker, Hälsingborg (se vidare under\ndetta bolag).\n\nStyrelse: dir. Albin Johansson (ordf.),»\nfil. lic. Mauritz Bonow, dir. Hj.\nDeger-stedt, dir. Hugo Edstam, dir. G. Osvald,,\ndir. Ernst Persson.\n\n\"AB. Kopia, Stockholm.\n\nReproduktionsatelier och litografiskt\ntryckeri. Utför rokotryck av ritningar,,\nkartor, tabeller, kartreproduktioner såsom\nskogskartor och stadsplanekartor,\nlitografiskt tryck såsom aktiebrev, brevpapper,,\netiketter, offsetttryck såsom affischer,\nreklamplakat m. m.\n\nKontor: David Bagaresg. 7.\nTelegr.-adr.: Kopia, Stockholm. Telefon: 232240.\nPostgiro: 50657.",
    "structured": {
        "1": {
            "name": "Konstgödnings & Svavelsyrefabrikerna",
            "location": "Svenska, Malmö",
            "business": "Konstgödning",
            "contact": {
                "office": "Not available",
                "phone": [
                    "Not available"
                ],
                "postgiro": "Not available",
                "head_office": "Not available",
                "sales_offices": [],
                "telegraph": "Not available",
                "factory_office": "Not available",
                "factory_phone": "Not available"
            },
            "financials": {
                "capital": "Not available",
                "employees": {
                    "industriarb": 20
                },
                "annual_turnover": "200,000 kr",
                "annual_production_value": "200,000 kr"
            },
            "foundation_year": 1921,
            "owners": [
                "fabr. Frans Oscar Johansson",
                "verkm. Carl-Emil Johansson"
            ],
            "board": []
        },
        "2": {
            "name": "AB. Konst harts",
            "location": "Trelleborg",
            "business": "Bakelitpressverk",
            "contact": {
                "office": "Not available",
                "phone": [
                    "1720"
                ],
                "postgiro": "281815",
                "head_office": "Not available",
                "sales_offices": [],
                "telegraph": "Not available",
                "factory_office": "Not available",
                "factory_phone": "Not available"
            },
            "financials": {
                "capital": "100,000 kr",
                "employees": {
                    "industriarb": 130
                },
                "annual_turnover": "Not available",
                "annual_production_value": "Not available"
            },
            "foundation_year": 1934,
            "owners": [],
            "board": [
                {
                    "name": "fil. dr B. Stein-hoff",
                    "role": "Not available"
                }
            ]
        },
        "3": {
            "name": "AB. Kontrollinstrument",
            "location": "Stockholm",
            "business": "Instrument- och finmekanisk verkstad",
            "contact": {
                "office": "Kungstensg. 18",
                "phone": [
                    "327432-33"
                ],
                "postgiro": "192610",
                "head_office": "Not available",
                "sales_offices": [],
                "telegraph": "Akimätare, Stockholm",
                "factory_office": "Not available",
                "factory_phone": "Not available"
            },
            "financials": {
                "capital": "100,000 kr",
                "employees": {
                    "industriarb": 70
                },
                "annual_turnover": "1,000,000 kr",
                "annual_production_value": "1,000,000 kr"
            },
            "foundation_year": 1941,
            "owners": [],
            "board": [
                {
                    "name": "ing. Erik Hysing",
                    "role": "Verkst. dir."
                },
                {
                    "name": "Nils Järte",
                    "role": "Försäljn.-dir."
                }
            ]
        },
        "4": {
            "name": "Kooperativa Förbundets Kem. Tekn. Fabrik",
            "location": "Malmö",
            "business": "Tillverkar kem. tekniska preparat; utför målning samt paketering av kryddor och te",
            "contact": {
                "office": "St. Trädgårdsg. 4",
                "phone": [
                    "28743",
                    "28789"
                ],
                "postgiro": "Not available",
                "head_office": "Stockholm, Stadsgården 6",
                "sales_offices": [],
                "telegraph": "Kooperativa, Stockholm",
                "factory_office": "Not available",
                "factory_phone": "Not available"
            },
            "financials": {
                "capital": "Not available",
                "employees": {
                    "industriarb": 65
                },
                "annual_turnover": "3,000,000 kr",
                "annual_production_value": "Not available"
            },
            "foundation_year": "Not available",
            "owners": [
                "Kooperativa Förbundet"
            ],
            "board": [
                {
                    "name": "Gunnar Petterson",
                    "role": "Disp."
                },
                {
                    "name": "Harry Ohlsson",
                    "role": "Kamrer"
                }
            ]
        },
        "5": {
            "name": "Kooperativa Förbundet Margarinfabriken AB.",
            "location": "Norrköping",
            "business": "Tillverkar margarin",
            "contact": {
                "office": "Not available",
                "phone": [
                    "29460"
                ],
                "postgiro": "Not available",
                "head_office": "Not available",
                "sales_offices": [],
                "telegraph": "Margarinfabrik, Norrköping",
                "factory_office": "Not available",
                "factory_phone": "Not available"
            },
            "financials": {
                "capital": "3,000,000 kr",
                "employees": {
                    "industriarb": 55
                },
                "annual_turnover": "26,000,000 kr",
                "annual_production_value": "Not available"
            },
            "foundation_year": 1920,
            "owners": [],
            "board": [
                {
                    "name": "dir. Albin Johansson (ordf.)",
                    "role": "Not available"
                },
                {
                    "name": "fil. lic. Mauritz Bonow",
                    "role": "Not available"
                },
                {
                    "name": "dir. Hj. Deger-stedt",
                    "role": "Not available"
                },
                {
                    "name": "dir. Hugo Edstam",
                    "role": "Not available"
                },
                {
                    "name": "dir. G. Osvaldy",
                    "role": "Not available"
                },
                {
                    "name": "dir. Ernst Persson",
                    "role": "Not available"
                },
                {
                    "name": "konsul S. H. Sörensen",
                    "role": "Not available"
                }
            ]
        },
        "6": {
            "name": "AB. Kopia",
            "location": "Stockholm",
            "business": "Reproduktionsatelier och litografiskt tryckeri",
            "contact": {
                "office": "David Bagaresg. 7",
                "phone": [
                    "232240"
                ],
                "postgiro": "50657",
                "head_office": "Not available",
                "sales_offices": [],
                "telegraph": "Kopia, Stockholm",
                "factory_office": "Not available",
                "factory_phone": "Not available"
            },
            "financials": {
                "capital": "Not available",
                "employees": {
                    "industriarb": "Not available"
                },
                "annual_turnover": "Not available",
                "annual_production_value": "Not available"
            },
            "foundation_year": "Not available",
            "owners": [],
            "board": []
        }
    }
}