{
    "original": "Lidan—LidJcö ping\n\ni bomull för herr, dam och barn, koftor,\njumpers, pullovers, slipovers,\nflickklän-ningar och gosskostymer, vantar,\nstrumpor och raggsockor. Varumärke: »Libo».\n\nTelegr.-adr. o. telefon: Libo, Borås.\nPostgiro: 81004.\n\nAkt.-kap.: 450,000 kr. Antal\nindustriarb.-. 450 samt 350 hemarbetare.\nTillv.-värde pr år: 8,000,000 kr.\n\nBolaget grundat 1932 under namn Nya\nLinneindustri AB., nuv. namn 1943.\n\nStyrelse: dir. Gustaf Wadstein (ordf.),\nherr Sven Dahlberg, ing. Björn Johanson,\ndir. Carl Gust. Johanson, disp. Per\nJohanson.\n\nVerkst. dir.: Carl Gust. Johanson.\n\nAB. Lidans Motor verkst ad,\n\nLidköping.\n\nTillverkar motorvinschar, ankarspel,\nm. m. Varumärke: »Lidan».\n\nTelegr.-adr.: Lidan, Lidköping.\nTelefon: 20259. Postgiro: 26853.\n\nAkt.-kap.: 50,000 kr. Antal\nindustriarb.: 35. Tillv.-värde pr år: 415,000 kr.\n— Firman etabl. 1910, bolag 1918.\n\nStyrelse o. disp.: disp. Carl Friman.\n\nLidboholms AB., Braås.\n\nSågverk och hyvleri, elektr.\nkraftstation och kvarn i Braås (Kronob. l.).\nTillverkar sågade och hyvlade trävaror samt\nspjäl- och snöstaket; distribuerar elektr.\nenergi.\n\nTelefon: 7. Postgiro: 73847. —\nAkt.-kap.: 200,000 kr. Antal industriarb.: 38.\nÅrstillv. av trävaror: 1,000 stds.\nTillv.-värde pr år: 600,000 kr. — Bolaget\ngrundat 1930.\n\nDisp.: Sven Varde.\n\n\"Lidingö Nya Warv &amp; Werkstäder,\n\nLidingö.\n\nSlip och mek. verkstad samt\ngrovplåtslageri. Utför fartygsnybyggnader och\nreparationer samt tillverkar\njärnkonstruktioner och cisterner.\n\nPostadr.: Lidingö 3. Telegr.-adr.:\nÅbergvarv, Stockholm. Telefon: 652555.\nPostgiro: 157840.\n\nAntal industriarb.: 125. Tillv.-värde pr\når: 1,500,000 kr. — Firman etabl. 1939.\n\nÄgare o. chef: disp. Joh. Abr. Åberg.\n\nVarvsing.: K.-E. Christianson.\n\n\"Lidköpings Bryggeri AB.,\n\nLidköping.\n\nTillverkar malt- och läskedrycker.\n\n■Telegr.-adr.: Bryggeribolaget,\nLidköping. Telefon: 22005. Postgiro: 21026.\n\nAkt.-kap.: 1,000,000 kr. Antal\nindustriarb.: 25. Tillv.-värde pr år: 900,000 kr.\n— Bryggeriet anlagt 1829, bolaget\ngrundat 1866.\n\nStyrelse: hovrättsassessor Bo\nNilson-Dag (ordf.), fältläkare P. G. Lundgren,\ndisp. Wilhelm Nilson-Dag.\n\nVerkst. dir.: W. Nilson-Dag.\n\nBryggm.: Henrik Björkman.\n\nAB. Lidköpings Konfektyr Industri,\n\nLidköping.\n\nTillverkar konfektyrer, choklad, kola,\nkarameller, marmelad, tabletter och\npastiller vid fabrik i Alingsås. Varumärke:\n»LK».\n\nHuvud- o. kassakontor: Lidköping.\nTelegr.-adr.: Lidkonfekt, Lidköping.\nTelefon: »Kinnevik». Fabriks- o.\nförsäljningskontor: Alingsås. Telefon: »Suchard o.\nLK». Avd.-kontor: Stockholm, Sveavägen\n48, telefon: 233920; Göteborg, Östra\nHamngatan 52, telefon: 132090.\n\nAkt.-kap.: 400,000 kr. —- Bolaget,\ngrundat 1932, arbetar under gemensam\nförvaltning med Svenska Suchard AB.,\nLidköping.\n\nStyrelse: hovjägm. frih. W. Klingspor\n(ordf.), adv. Hugo Stenbeck (v. ordf.),\ndir. Clarence T. Brockman, bankdir.\nHelmer Sten, dir. Folke Stenbeck.\n\nVerkst. dir.: Clarence T. Brockman\n(Alingsås).\n\nDir. för kassakontoret: H. Björkeroth.\n\n\"Lidköpings Mekaniska Verkstads\nAB., Lidköping.\n\nMek. verkstad och gjuteri i Lidköping\nsamt mek. verkstad i Midsommarkransen,\nStockholm. Tillverkar verktygsmaskiner\nsåsom centerless rundslipmaskiner,\nplan-slipmaskiner, verktygsslipmaskiner,\nrevolversvarvar, maskiner för tillverkning\noch reparation av rullande\njärnvägsmate-riel m. m.\n\nTelegr.-adr.: Verkstaden, Lidköping.\nTelefon: 22130 o. »Lidköpings\nMekaniska». Postgiro: 29575. Avd.-kontor:\nVästberga, Midsommarkransen, telefon:\nStockholm 452790.\n\nAkt.-kap.: 1,500,000 kr. Antal\nindustriarb.: 700. Verkstaden anlagd 1874.\nBolaget äges av AB. Svenska\nKullagerfabriken, Göteborg.\n\nStyrelse: tekn. dr Hilding\nTörnebohm (ordf.), dir. Gustaf Ekholm, disp.\nIvar Eliasson, ekonomichef Elon\nJacobsson.\n\nVerkst. dir.: Gustaf Ekholm.\n\nChef för fabriken i\nMidsommarkransen: disp. Ivar Eliasson.\n\n(Jfr annons nr 78.)\n\n326*",
    "structured": {
        "firms": [
            {
                "name": "Lidan",
                "location": "Borås",
                "business": "Bomullsfabrik för herr, dam och barnkläder, koftor, jumpers, pullovers, och accessoarer.",
                "products": "Varumärke: »Libo».",
                "contact": {
                    "office": "AB. Lidans Motor verkstad, Lidköping",
                    "phone": [
                        "20259"
                    ],
                    "postgiro": "26853",
                    "telegraph": "Lidan, Lidköping",
                    "factory_office": "AB. Lidans Motor verkstad, Lidköping",
                    "factory_phone": "20259"
                },
                "financials": {
                    "capital": "450,000 kr",
                    "employees": {
                        "industriarb": 450,
                        "hemarbetare": 350
                    },
                    "annual_turnover": "8,000,000 kr",
                    "annual_production_value": "8,000,000 kr"
                },
                "foundation_year": 1932,
                "current_name_year": 1943,
                "board": [
                    {
                        "name": "Gustaf Wadstein",
                        "role": "ordförande"
                    },
                    {
                        "name": "Sven Dahlberg",
                        "role": null
                    },
                    {
                        "name": "Björn Johanson",
                        "role": "ingenjör"
                    },
                    {
                        "name": "Carl Gust. Johanson",
                        "role": "direktör"
                    },
                    {
                        "name": "Per Johanson",
                        "role": "disponent"
                    }
                ]
            },
            {
                "name": "AB. Lidans Motor verkstad",
                "location": "Lidköping",
                "business": "Tillverkning av motorvinschar, ankarspel, m. m.",
                "contact": {
                    "office": "Lidan, Lidköping",
                    "phone": [
                        "20259"
                    ],
                    "postgiro": "26853",
                    "telegraph": "Lidan, Lidköping"
                },
                "financials": {
                    "capital": "50,000 kr",
                    "employees": {
                        "industriarb": 35
                    },
                    "annual_turnover": "415,000 kr",
                    "annual_production_value": "415,000 kr"
                },
                "corporation_year": 1918
            },
            {
                "name": "Lidboholms AB.",
                "location": "Braås",
                "business": "Sågverk, hyvleri, elektr. kraftstation och kvarn",
                "products": "Tillverkar trävaror, spjäl- och snöstaket, distribuerar elektr. energi.",
                "contact": {
                    "phone": [
                        "7"
                    ],
                    "postgiro": "73847"
                },
                "financials": {
                    "capital": "200,000 kr",
                    "employees": {
                        "industriarb": 38
                    },
                    "annual_production_value": "600,000 kr"
                },
                "foundation_year": 1930,
                "board": [
                    {
                        "name": "Sven Varde",
                        "role": "disp."
                    }
                ]
            },
            {
                "name": "Lidingö Nya Warv & Werkstäder",
                "location": "Lidingö",
                "business": "Slip- och mekanisk verkstad samt grovplåtslageri",
                "products": "Utför fartygsnybyggnader och reparationer samt tillverkar järnkonstruktioner och cisterner.",
                "contact": {
                    "office": "Lidingö 3",
                    "phone": [
                        "652555"
                    ],
                    "postgiro": "157840",
                    "telegraph": "Åbergvarv, Stockholm"
                },
                "financials": {
                    "annual_production_value": "1,500,000 kr"
                },
                "predecessor": "Firman etabl. 1939",
                "owners": [
                    "disp. Joh. Abr. Åberg"
                ],
                "director": "K.-E. Christianson"
            },
            {
                "name": "Lidköpings Bryggeri AB.",
                "location": "Lidköping",
                "business": "Tillverkar malt- och läskedrycker",
                "contact": {
                    "phone": [
                        "22005"
                    ],
                    "postgiro": "21026",
                    "telegraph": "Bryggeribolaget, Lidköping"
                },
                "financials": {
                    "capital": "1,000,000 kr",
                    "employees": {
                        "industriarb": 25
                    },
                    "annual_production_value": "900,000 kr"
                },
                "foundation_year": 1866,
                "board": [
                    {
                        "name": "Bo Nilson-Dag",
                        "role": "hovrättsassessor"
                    },
                    {
                        "name": "P. G. Lundgren",
                        "role": "fältläkare"
                    },
                    {
                        "name": "Wilhelm Nilson-Dag",
                        "role": "disp."
                    }
                ],
                "director": "W. Nilson-Dag",
                "managing_director": "W. Nilson-Dag",
                "sales_manager": "Henrik Björkman"
            },
            {
                "name": "AB. Lidköpings Konfektyr Industri",
                "location": "Alingsås",
                "business": "Tillverkning av konfektyrer, choklad, kola, karameller, marmelad, tabletter och pastiller.",
                "products": "Varumärke: »LK».",
                "contact": {
                    "office": "Huvud- och kassakontor, Lidköping",
                    "phone": [
                        "Kinnevik"
                    ],
                    "factory_office": "Fabrik i Alingsås",
                    "factory_phone": "Suchard o. LK",
                    "postgiro": null
                },
                "financials": {
                    "capital": "400,000 kr"
                },
                "board": [
                    {
                        "name": "W. Klingspor",
                        "role": "hovjägm."
                    },
                    {
                        "name": "Hugo Stenbeck",
                        "role": "adv."
                    },
                    {
                        "name": "Clarence T. Brockman",
                        "role": "dir."
                    },
                    {
                        "name": "Helmer Sten",
                        "role": "bankdir."
                    },
                    {
                        "name": "Folke Stenbeck",
                        "role": "dir."
                    }
                ],
                "director": "Clarence T. Brockman",
                "manager": "H. Björkeroth"
            },
            {
                "name": "Lidköpings Mekaniska Verkstads AB.",
                "location": "Lidköping",
                "business": "Mek. verkstad och gjuteri",
                "products": "Tillverkar verktygsmaskiner, rullande järnvägsmateriel m. m.",
                "contact": {
                    "office": "Verkstaden, Lidköping",
                    "phone": [
                        "22130",
                        "Lidköpings Mekaniska"
                    ],
                    "postgiro": "29575"
                },
                "financials": {
                    "capital": "1,500,000 kr",
                    "employees": {
                        "industriarb": 700
                    }
                },
                "board": [
                    {
                        "name": "Hilding Törnebohm",
                        "role": "tekn. dr"
                    },
                    {
                        "name": "Gustaf Ekholm",
                        "role": "dir."
                    },
                    {
                        "name": "Ivar Eliasson",
                        "role": "disp."
                    },
                    {
                        "name": "Elon Jacobsson",
                        "role": "ekonomichef"
                    }
                ],
                "director": "Gustaf Ekholm",
                "manager": "Ivar Eliasson"
            }
        ]
    }
}