{
    "original": "Breven—Brofjorden\n\n».Kohinoor»-putscreme, » Spectrol»\n-fläck-vatten, »Cross»-lim m. fl.\n\nKontor: Brunkebergsg. 4. Telefon:\n230330. Postgiro: 3127.\n\nAkt.-kap.: 50,000 kr. Antal\nindustriarb.: 15. Tillv.-värde pr år: 500,000 kr.\n— Bolaget grundat 1912.\n\nStyrelse: grossh. John F. Åkerblom\n(ordf.), assessor Knut Ljungberg, grossh.\nDavid Niklason.\n\nVerkst. direktörer: David Niklason o.\nJohn F. Åkerblom.\n\nBrevens Bruk, Carl Cripenstedt,\n\nKilsmo.\n\nMek. verkstad, gjuteri,\nmanufaktursmedja och plåtslageriverkstad vid\nBrevens bruk, sågverk med hyvleri i\nKilsmo (båda i Örebro l.).\n\nTillverkar vattenturbiner och\nturbin-regulatorer, maskiner för gruv-, sten-,\nbetong-, såg-, trämasse- och\ncellulosaindustrier, gjutgods, sågade och hyvlade\nträvaror. Vid bruket drives jämväl\nkvarnrörelse, jordbruk o. skogshantering.\n\nTelegr.-adr.: Brevensbruk, Örebro.\nTelefon: Kilsmo 5. Postgiro: 23363.\n\nAntal industriarb.: 150. Tillv.-värde pr\når: 2,000,000 kr. Årstillv. av sågade och\nhyvlade trävaror: 2,500 stds. — Bruket\nanlagt på 1600-talet.\n\nÄgare o. chef: frih. Carl Gripenstedt.\n\nKassör: Carl Hellström.\n\nVerkstadsing.: Viktor Sundström.\n\nSdgverhsinsp.: Hugo Carlsson.\n\nShogsförvalt.: Gustaf Norstedt.\n\nBrio-Konfektion AB., Göteborg.\n\nTillverkar hängslen, strumpeband och\närmhållare samt badrockar och\nfrackvästar i piké och siden. Varumärke:\n»Briostjärnan».\n\nKontor: 3:e Långg. 38—40.\nTelegr.-adr.: Merkur, Göteborg. Telefon: 145011.\nPostgiro: 42232.\n\nAkt.-kap.: 5,000 kr. Antal industriarb.:\n20. Tillv.-värde pr år: 400,000 kr. —\nBolaget grundat 1931.\n\nVerkst. dir.: disp. Folke Ellioth.\n\nKontorschef: Gösta Johnson.\n\nBritanniafabriks AB-, Stenkullen.\n\nMetallgjuteri och stansverk i\nStenkullen (Älvsb. l.). Tillverkar bordbestick\noch husgerådsartiklar av britanniametall,\naluminium och rostfritt stål samt i\nnysilver, råvaror för nysilverfabriker,\ngjutna galanterivaror i svenskt tenn samt\narmatur.\n\nTelegr.-adr.: Britannia, Göteborg.\nTelefon: Stenkullen 75. — Akt.-kap.:\n90,000 kr. Antal industriarb.: 45. —\nFirman etabl. 1891, bolag 1903.\nVerkst. dir.: Carl CJolsman.\n\n*Bro Ångsågs AB., Vansbro.\n\nSågverk, hyvleri och kolugnar i\nVansbro (Kopparb. l.). Tillverkar sågade och\nhyvlade trävaror, lådbräder och laths\nsamt träkol, träsprit, trät j ära och\nrå-terpentin.\n\nTelegr.-adr.: Brosågen, Vansbro.\nTelefon: 87. Postgiro: 75200.\n\nAkt.-kap.: 330,000 kr. Antal\nindustriarb.: 90. Årstillv.: 3,000 stds trävaror,\n9,000 läster träkol, 400 ton trätjära och\n50 ton träsprit. — Bolaget grundat 1909.\n\nStyrelse: disp. Filip Sjöberg, kassör\nOlof Sjöberg, ing. Åke Sjöberg.\nVerkst. dir.: Filip Sjöberg.\n\n*Broby Mek. Verkstads AB-, Broby.\n\nTillverkar hästskor och vagnsaxlar vid\nverkstad i Broby (Kristianst. l.).\n\nTelegr.-adr.: Verkstaden, Broby.\nTelefon: 37. Ensamförsälj.: AB. J. H. Dieden\nJ:or, Malmö, telefon: 20827.\n\nAkt.-kap.: 20,500 kr. Antal\nindustriarb.: 25. Tillv.-värde pr år: 250,000 kr.\n— Bolaget grundat 1907.\n\nStyrelse: fru Hulda Holmberg, dir.\nSwante H. Holmberg, fru Gunvor Widell.\nVerkst dir.: S. H. Holmberg.\n\n*\tBroby Tegelbruk, Ekskogen.\n\nSe AB. Mälardalens Tegelbruk,\nStockholm.\n\n*\tNestor Brodin, Flöda.\n\nGarveri vid Flöda (Älvsb. l.).\nTillverkar beklädnadsskinn, handskskinn,\nskoskinn, foderskinn, bokbinderiskinn och\nreseffektskinn.\n\nTelegr.-adr.: Brodin, Flöda. Telefon:\nFlöda 4. Postgiro: 166820. — Antal\nindustriarb.: 50. Tillv.-värde pr år:\n2,000,000 kr. — Firman etabl. 1898.\nÄgare o. chef: disp. Lars Brodin.\n\nAB. Brofjordens Konservfabrik,\n\nGöteborg.\n\nTillverkar ansjovis, sillkonserver,\nkaviar samt konserver av skaldjur, svamp,\nfrukt och grönsaker vid konservfabrik i\nSjöbol, Lyse (Göteb. o. Bohus l.).\n\nKontor: Göteborg, Fisktorget 3.\nTelegr.-adr.: Brofjorden, Göteborg. Telefon:\n\n114909. Postgiro: 43427.\n*",
    "structured": {
        "1": {
            "name": "Breven—Brofjorden",
            "location": "Kilsmo",
            "business": "Mek. verkstad, gjuteri",
            "products": "vattenturbiner, turbin-regulatorer, maskiner för gruv-, sten-, betong-, såg-, trämasse- och cellulosaindustrier, gjutgods, sågade och hyvlade trävaror, kvarnrörelse, jordbruk o. skogshantering",
            "contact": {
                "office": "Brunkebergsg. 4",
                "phone": [
                    "230330"
                ],
                "postgiro": "3127",
                "head_office": "Brevens bruk, Örebro",
                "telegraph": "Brevensbruk, Örebro",
                "factory_office": "Kilsmo",
                "factory_phone": "5"
            },
            "financials": {
                "capital": "50,000 kr",
                "employees": {
                    "industriarb": 15
                },
                "annual_turnover": "500,000 kr",
                "annual_production_value": "2,500 stds"
            },
            "foundation_year": 1912,
            "board": [
                {
                    "name": "grossh. John F. Åkerblom",
                    "role": "ordf."
                },
                {
                    "name": "assessor Knut Ljungberg",
                    "role": null
                },
                {
                    "name": "grossh. David Niklason",
                    "role": null
                }
            ],
            "director": "David Niklason",
            "managing_director": "John F. Åkerblom"
        },
        "2": {
            "name": "Brevens Bruk",
            "location": "Carl Cripenstedt, Kilsmo",
            "business": "Mek. verkstad, gjuteri, manufaktursmedja, plåtslageriverkstad",
            "products": "vattenturbiner, turbin-regulatorer, maskiner för gruv-, sten-, betong-, såg-, trämasse- och cellulosaindustrier, gjutgods, sågade och hyvlade trävaror",
            "contact": {
                "office": null,
                "phone": [
                    "Kilsmo 5"
                ],
                "postgiro": "23363",
                "telegraph": "Brevensbruk, Örebro"
            },
            "financials": {
                "employees": {
                    "industriarb": 150
                },
                "annual_turnover": "2,000,000 kr",
                "annual_production_value": null
            },
            "foundation_year": "1600-talet",
            "owners": [
                "frih. Carl Gripenstedt"
            ],
            "manager": "frih. Carl Gripenstedt",
            "managerial_roles": {
                "kassör": "Carl Hellström",
                "verkstadsing.": "Viktor Sundström",
                "sdgverhsinsp.": "Hugo Carlsson",
                "shogsförvalt.": "Gustaf Norstedt"
            }
        },
        "3": {
            "name": "Brio-Konfektion AB.",
            "location": "Göteborg",
            "business": "Tillverkar hängslen, strumpeband och ärmhållare samt badrockar och frackvästar i piké och siden",
            "products": null,
            "contact": {
                "office": "3:e Långg. 38—40",
                "phone": [
                    "145011"
                ],
                "postgiro": "42232",
                "telegraph": "Merkur, Göteborg"
            },
            "financials": {
                "capital": "5,000 kr",
                "employees": {
                    "industriarb": 20
                },
                "annual_turnover": "400,000 kr",
                "annual_production_value": null
            },
            "foundation_year": 1931,
            "director": "disp. Folke Ellioth",
            "manager": "Gösta Johnson"
        },
        "4": {
            "name": "Britanniafabriks AB-",
            "location": "Stenkullen",
            "business": "Metallgjuteri och stansverk",
            "products": "bordbestick, husgerådsartiklar av britanniametall, aluminium och rostfritt stål, nysilver, gjutna galanterivaror i svenskt tenn samt armatur",
            "contact": {
                "phone": [
                    "Stenkullen 75"
                ],
                "telegraph": "Britannia, Göteborg"
            },
            "financials": {
                "capital": "90,000 kr",
                "employees": {
                    "industriarb": 45
                }
            },
            "foundation_year": 1891,
            "director": "Carl CJolsman"
        },
        "5": {
            "name": "Bro Ångsågs AB.",
            "location": "Vansbro",
            "business": "Sågverk, hyvleri och kolugnar",
            "products": "sågade och hyvlade trävaror, lådbräder och laths, träkol, träsprit, trätjära och rå-terpentin",
            "contact": {
                "phone": [
                    "87"
                ],
                "postgiro": "75200",
                "telegraph": "Brosågen, Vansbro"
            },
            "financials": {
                "capital": "330,000 kr",
                "employees": {
                    "industriarb": 90
                },
                "annual_production_value": "3,000 stds trävaror, 9,000 läster träkol, 400 ton trätjära och 50 ton träsprit"
            },
            "foundation_year": 1909,
            "board": [
                {
                    "name": "disp. Filip Sjöberg",
                    "role": null
                },
                {
                    "name": "kassör Olof Sjöberg",
                    "role": null
                },
                {
                    "name": "ing. Åke Sjöberg",
                    "role": null
                }
            ],
            "director": "Filip Sjöberg"
        },
        "6": {
            "name": "Broby Mek. Verkstads AB",
            "location": "Broby",
            "business": "Tillverkar hästskor och vagnsaxlar",
            "products": null,
            "contact": {
                "phone": [
                    "37"
                ],
                "telegraph": "Verkstaden, Broby"
            },
            "financials": {
                "capital": "20,500 kr",
                "employees": {
                    "industriarb": 25
                },
                "annual_production_value": "250,000 kr"
            },
            "foundation_year": 1907,
            "board": [
                {
                    "name": "fru Hulda Holmberg",
                    "role": null
                },
                {
                    "name": "dir. Swante H. Holmberg",
                    "role": null
                },
                {
                    "name": "fru Gunvor Widell",
                    "role": null
                }
            ],
            "director": "S. H. Holmberg"
        },
        "7": {
            "name": "Nestor Brodin",
            "location": "Flöda",
            "business": "Garveri",
            "products": "beklädnadsskinn, handskskinn, skoskinn, foderskinn, bokbinderiskinn och reseffektskinn",
            "contact": {
                "phone": [
                    "Flöda 4"
                ],
                "postgiro": "166820",
                "telegraph": "Brodin, Flöda"
            },
            "financials": {
                "employees": {
                    "industriarb": 50
                },
                "annual_production_value": "2,000,000 kr"
            },
            "foundation_year": 1898,
            "director": "disp. Lars Brodin"
        },
        "8": {
            "name": "AB. Brofjordens Konservfabrik",
            "location": "Göteborg, Fisktorget 3",
            "business": "Tillverkar ansjovis, sillkonserver, kaviar samt konserver av skaldjur, svamp, frukt och grönsaker",
            "products": null,
            "contact": {
                "phone": [
                    "114909"
                ],
                "postgiro": "43427",
                "telegraph": "Brofjorden, Göteborg"
            }
        }
    }
}