{
    "original": "Elektriska\n\nElektr. Apparatfabriken Glory,\n\nMariefred.\n\nTillverkar elektr. värmedynor samt\nelektromed. värmelampor. Varumärke:\n»Glory».\n\nTelegr.-adr.: Glory, Mariefred.\nTelefon: 39. Postgiro: 21308. — Antal\nindustriarb.: 7. Tillv.-värde pr år: 90,000 kr.\n\n—\tFirman etabl. 1925.\n\nÄgare: fröken Kerstin Johansson o. fru\nAnna Strandmark.\n\nChef: Kerstin Johansson.\n\n\"Elektriska AB. Chr. Bergh &amp; Co.,\n(Cebe), Svalöv.\n\nSe Cebe AB., Svalöv.\n\"Elektriska AB. Ergo, Västerås.\n\nTillverkar elektriska värmeapparater\nsåsom värmeplattor, kokskåp,\nvattenvär-mare, värmeelement för kyrkor,\nradiatorer, värmebatterier för pressluft,\ncirkulationsapparater för vatten, olja o. d.,\nvärmeanläggningar med automatisk\ntemperaturreglering m. m.\n\nTelefon: 39010—12. Postgiro: 8702.\n\nAkt.-kap.: 60,000 kr. Antal\nindustriarb.: 40. Tillv.-värde pr år: 700,000 kr.\n\n—\tFirman etabl. 1922, bolag 1929.\n\nStyrelse: ing. Johan A. Carlberg\n\n(ordf.), verkm. Erik O. Larsson, ing. G.\nE. Schnell.\n\nVerkst. dir.: Johan A. Carlberg.\n\nKontorschef: G. E. Schnell.\n\n* Elektriska Fabriken Jonsson &amp;\nLarsson, Arboga.\n\nSe AB. Arbogamaskiner, Arboga.\n\n\"Elektriska AB. Helios, Stockholm.\n\nElektromek. verkstad. Tillverkar\nelvärmeapparater såsom spisar, kaminer,\nkokkärl, strykjärn, värmeplattor,\nvärmeskåp, bakugnar, vattenvärmare m. m. samt\nelvärmeutrustningar för stor kök,\nrestauranger, bagerier, industrier, laboratorier\netc.\n\nKontor: Heliosv. 12. Telegr.-adr. o.\ntelefon: Elektrohelios, Stockholm.\nPostgiro: 2804.\n\nAkt.-kap.: 500,000 kr. Antal\nindustriarb.: 740. — Bolaget, grundat 1919,\ntillhör Asea-koncernen.\n\nStyrelse: dir. Hugo Edström, dir. Alb.\nElfström, dir. Thorsten Ericson, kamrer\nTore Lindén.\n\nVerkst dir.: Hugo Edström.\n\nKommersiell chef: Tore Lindén.\n\nTeknisk chef: N. Wollart.\n\n1*\n\nElektriska Industri AB.y\n\nStockholm.\n\nElektromek. verkstad. Tillverkar\nradio-materiel och radioapparater. —\nVarumärke: »EIA».\n\nKontor: Hudiksvallsg. 6. Telegr.-adr.:\nEj a, Stockholm. Telefon: 232140.\nPostgiro: 1339 o. 58449. Utställningslokal:\nDrottningg. 85.\n\nAkt.-kap.: 50,000 kr. Antal\nindustriarb.: 60. Tillv.-värde pr år: 1,800,000 kr.\n— Bolaget grundat 1916, ombildat 1926.\n\nStyrelse: ing. W. Berling, civiling.\nHåkan Kjörling, kamrer E. Westin.\n\nVerkst. dir.: Håkan Kjörling.\n\n\"Elektr. Industrifirman Ernst\nGennel, Stockholm.\nSe AB. Elektro-Gennel, Stockholm.\n\n\"Elektriska AB. Järnh, Stockholm.\nSe Järnhs Elektriska AB., Stockholm.\n\nElektriska AB. Käwe, Sundbyberg.\n\nElektromek. verkstad i Sundbyberg\n(Sthlms l.). Tillverkar\nhårtorkningsappa-rater, permanentapparater samt\nlänkrullar.\n\nTelefon: 281266. Postgiro: 162141. —\nAkt.-kap.: 8,000 kr. Antal industriarb.:\n13. Tillv.-värde pr år: 300,000 kr. —\nBolaget grundat 1934.\n\nVerkst. dir.: Karl Andersson.\n\n\"Elektriska AB. Lindström &amp; Andeli,\n\nGöteborg.\n\nElektromek. verkstad i Göteborg samt\ntransformatorfabrik i Ugglum, Göteborg.\nTillverkar transformatorer och elektr.\nstartapparater samt utför reparationer\noch omlindningar av elektr. motorer,\ngeneratorer, transformatorer m. m. Bolaget\ndriver även försäljning och uthyrning av\nsåväl nya som begagnade elektr. maskiner.\n\nHuvudkontor: Göteborg, Odinsplatsen\n2 B. Telegr.-adr.: Elektroandell,\nGöteborg. Telefon: 172730. Postgiro: 12280.\nAvd.-kontor: Stockholm, Styrmansg. 39,\ntelefon: 672041 o. 672044.\n\nAkt.-kap.: 150,000 kr. Antal\nindustriarb.: 84. — Firman etabl. 1918, bolag\n1934.\n\nStyrelse o. verkst. dir.: Albin Andeli.",
    "structured": {
        "1": {
            "name": "Elektriska Apparatfabriken Glory",
            "location": "Mariefred",
            "business": "Tillverkar elektr. värmedynor samt elektromed. värmelampor",
            "products": "Varumärke: »Glory»",
            "contact": {
                "office": "Glory, Mariefred",
                "phone": [
                    "39"
                ],
                "postgiro": "21308",
                "telegraph": "Glory, Mariefred"
            },
            "financials": {
                "capital": "N/A",
                "employees": {
                    "total": 7
                },
                "annual_turnover": "90,000 kr",
                "annual_production_value": "N/A"
            },
            "foundation_year": 1925,
            "owners": [
                "fröken Kerstin Johansson",
                "fru Anna Strandmark"
            ],
            "director": "Kerstin Johansson"
        },
        "2": {
            "name": "Elektriska AB. Ergo",
            "location": "Västerås",
            "business": "Tillverkar elektriska värmeapparater",
            "products": "såsom värmeplattor, kokskåp, vattenvär-mare, värmeelement för kyrkor, radiatorer, värmebatterier för pressluft, cirkulationsapparater för vatten, olja o. d., värmeanläggningar med automatisk temperaturreglering m. m.",
            "contact": {
                "phone": "39010—12",
                "postgiro": "8702"
            },
            "financials": {
                "capital": "60,000 kr",
                "employees": {
                    "total": 40
                },
                "annual_turnover": "700,000 kr",
                "annual_production_value": "N/A"
            },
            "foundation_year": 1922,
            "corporation_year": 1929,
            "board": [
                {
                    "name": "ing. Johan A. Carlberg",
                    "role": "ordf."
                },
                {
                    "name": "verkm. Erik O. Larsson"
                },
                {
                    "name": "ing. G. E. Schnell"
                }
            ],
            "director": "Johan A. Carlberg",
            "sales_manager": "G. E. Schnell"
        },
        "3": {
            "name": "Elektriska AB. Helios",
            "location": "Stockholm",
            "business": "Elektromek. verkstad",
            "products": "Tillverkar elvärmeapparater såsom spisar, kaminer, kokkärl, strykjärn, värmeplattor, värmeskåp, bakugnar, vattenvärmare m. m. samt elvärmeutrustningar för stor kök, restauranger, bagerier, industrier, laboratorier etc.",
            "contact": {
                "office": "Heliosv. 12",
                "phone": [
                    "Elektrohelios, Stockholm"
                ],
                "postgiro": "2804"
            },
            "financials": {
                "capital": "500,000 kr",
                "employees": {
                    "total": 740
                },
                "annual_turnover": "N/A",
                "annual_production_value": "N/A"
            },
            "foundation_year": 1919,
            "board": [
                {
                    "name": "dir. Hugo Edström"
                },
                {
                    "name": "dir. Alb. Elfström"
                },
                {
                    "name": "dir. Thorsten Ericson"
                },
                {
                    "name": "kamrer Tore Lindén"
                }
            ],
            "director": "Hugo Edström",
            "sales_manager": "Tore Lindén",
            "manager": "N. Wollart"
        },
        "4": {
            "name": "Elektriska Industri AB.y",
            "location": "Stockholm",
            "business": "Elektromek. verkstad",
            "products": "Tillverkar radiomateriel och radioapparater",
            "contact": {
                "office": "Hudiksvallsg. 6",
                "phone": [
                    "232140"
                ],
                "postgiro": [
                    "1339",
                    "58449"
                ],
                "exhibition": "Drottningg. 85"
            },
            "financials": {
                "capital": "50,000 kr",
                "employees": {
                    "total": 60
                },
                "annual_turnover": "1,800,000 kr",
                "annual_production_value": "N/A"
            },
            "foundation_year": 1916,
            "corporation_year": 1926,
            "board": [
                {
                    "name": "ing. W. Berling"
                },
                {
                    "name": "civiling. Håkan Kjörling"
                },
                {
                    "name": "kamrer E. Westin"
                }
            ],
            "manager": "Håkan Kjörling"
        },
        "5": {
            "name": "Elektriska AB. Käwe",
            "location": "Sundbyberg",
            "business": "Elektromek. verkstad",
            "products": "Tillverkar hårtorkningsapparater, permanentapparater samt länkrullar",
            "contact": {
                "phone": [
                    "281266"
                ],
                "postgiro": "162141"
            },
            "financials": {
                "capital": "8,000 kr",
                "employees": {
                    "total": 13
                },
                "annual_turnover": "300,000 kr",
                "annual_production_value": "N/A"
            },
            "foundation_year": 1934,
            "director": "Karl Andersson"
        },
        "6": {
            "name": "Elektriska AB. Lindström & Andeli",
            "location": "Göteborg",
            "business": "Elektromek. verkstad",
            "products": "Tillverkar transformatorer och elektr. startapparater samt utför reparationer och omlindningar av elektr. motorer, generatorer, transformatorer m. m.",
            "contact": {
                "office": "Göteborg, Odinsplatsen 2 B",
                "phone": [
                    "172730"
                ],
                "postgiro": "12280",
                "branch_office": {
                    "location": "Stockholm",
                    "phone": [
                        "672041",
                        "672044"
                    ]
                }
            },
            "financials": {
                "capital": "150,000 kr",
                "employees": {
                    "total": 84
                },
                "annual_turnover": "N/A",
                "annual_production_value": "N/A"
            },
            "foundation_year": 1918,
            "corporation_year": 1934,
            "director": "Albin Andeli"
        }
    }
}