{
    "original": "Kinna—Kinofa\n\nBolaget grundat 1930.\n\nStyrelse: dir. Edvin Leffler (ordf.),\nkamrer A. Wilhelm Anderson, adv. Erik\nGrenfors, konsul Erland Skantze.\n\nVerkst. dir.: kamrer A. Wilhelm\nAnderson (Borås).\n\nKamrer: Artur Barrholm.\n\nKinna Cardinfabrik, Kinna.\n\nSe Framnäs Väveri AB., Kinna.\n\nKinna Wäveri, Bröderna Nilsson,\n\nKinna.\n\nTillverkar gardin-, draperi- och\nmöbeltyger samt konstsilkevävnader vid väveri\ni Kinna (Älvsb. l.).\n\nTelefon: 10292. Postgiro: 81750. —\nAntal industriarb.: 20. Tillv.-värde pr\når: 400,000 kr. — Firman etabl. 1931.\n\nÄgare o. chefer: fabr. Erik W. Nilsson\n\n0.\tfabr. Josef Nilson.\n\n\"Kinna Yllefabrik, Kinna.\n\nVäveri, färgeri, trikå- och\nkonfektionsfabrik i Kinna (Älvsb. l.). Tillverkar\nbad-kappstyger och badkappor i velour och\nfrotté, möbeltyger, smärting m. m. samt\nklänningar i jersey.\n\nTelefon: 10143 o. 10053. Postgiro:\n12732.\n\nAntal industriarb.: 50. — Fabriken\nanlagd 1914, nuv. firma etabl. 1926.\n\nÄgare o. chef: dir. Verner Werner gren.\n\nKinnahults Trikåfabrik, Kinnahult.\n\nTillverkar herr- och damunderkläder\nvid fabrik i Kinnahult (Älvsb. l.).\n\nTelefon: Kinna 10288. Postgiro:\n162299. — Antal industriarb.: 10.\nTillv.-värde pr år: 100,000 kr. — Firman etabl.\n1934.\n\nÄgare o. chef: fabr. Sigfrid Johansson.\n\nKinnahults Väfveri, Kinnahult.\n\nTillverkar gardiner, draperi- och\nmöbeltyger vid väveri i Kinnahult (Älvsb.\n\n1.).\n\nTelefon: Kinna 10043. Postgiro: 9346.\n— Antal industriarb.: 55. Tillv.-värde pr\når: 800,000 kr. — Firman etabl. 1917.\n\nDisp.: Axel Markow.\n\nÄgare o. chef: fabr. Erik Eliason.\n\n\"Kinnamarks Mek. Väveri, Kinna.\n\nSe AB. Ludvig Svensson, Kinna.\n\nAB. Kinnareds Textil, Halmstad.\n\nTillverkar gardin- och draperityger vid\nväveri i Kinnared (Hallands l.).\n\nKontor: Halmstad. Telefon: »Olssons\nTextil». Postgiro: 171500.\n\nAkt.-kap.: 80,000 kr. Antal\nindustriarb.: 32. Tillv.-värde pr år: 500,000 kr.\n\n—\tFirman etabl. 1934, bolag 1941.\n\nVerkst. dir.: Helge Olsson.\n\nFabrihschef i Kinnared: John Alsin.\n\n\"Kinnasands Mek. Väveri, Kinna.\n\nSe AB. Claes Håkansson, Kinna.\n\n\"Kinnaströms Väfveri AB., Kinna.\n\nBomulls väveri, färgeri, blekeri och\nappreturverk vid Kinnaström, Kinna\n(Älvsb. l.). Tillverkar bomulls-, silke- och\nhalvyllevävnader samt jaequardbolster.\n\nTelegr.-adr. o. telefon: »Kinnaström»,\nKinna. Postgiro: 73660.\n\nAkt.-kap.: 1,760,000 kr. Antal\nindustriarb.: 335. Tillv.-värde pr år: 6,000,000 kr.\n\n—\tFirman etabl. 1885, bolag 1895.\n\nStyrelse: dir. Clas Erikson (ordf.), dir.\n\nEdvin Leffler (v. ordf.), dir. John O.\nErikson.\n\nVerkst. dir.: Edvin Leffler.\n\nDisp.: Ragnar Erikson.\n\nDir.-assist.: Uno Mårtensson.\n\nKassör: Charles öfverberg.\n\nDriftsin g.: Ulf Leffler.\n\nVäverichef: Sven Ad. Svensson.\n\nAB. Kinnekulle Kalk, Lidköping.\n\nTillverkar jordbruks- och\nmurbruks-kalk vid fabrik i Kinnemalma (Skarab.\n1.). Bolaget driver jämväl jordbruk.\n\nTelefon: Lidköping 20340. Postgiro:\n25915. — Akt.-kap.: 45,000 kr. Antal\nindustriarb.: 20. Tillv.-värde pr år: 70,000\nkr. — Bolaget grundat 1928.\n\nStyrelse: dir. Knut Karlsson (ordf.),\nfru J. Beckman, disp. Erik Danielsson.\n\nDisp.: Erik Danielsson.\n\nAB. Kinofa, Stockholm.\n\nFabrik för tillverkning av\nbiografapparater såsom filmprojektorer,\nljudfilman-läggningar, likriktare samt båglampor\noch tillbehör för biografmaskiner m. m.\nVarumärke: »Kinofa».\n\nKontor: Hammarbyvägen 9—11;\npostadr.: Stockholm 20. Telegr.-adr.: Kinofa,\nStockholm. Telefon: 441415—16.\nPostgiro: 2562.\n\nAkt.-kap.: 150,000 kr. Antal\nindustriarb.: 40. Tillv.-värde pr år: 500,000 kr.\n\nFirman, etabl. 1913, erhöll 1916\nnamnet Skandinaviska Kinematograffabriken,\nnuv. bolag 1935.\n\nVerkst. dir.: Stig Sundgren.",
    "structured": {
        "1": {
            "name": "Kinna Cardinfabrik",
            "location": "Kinna",
            "business": "Tillverkar gardin-, draperi- och möbeltyger samt konstsilkevävnader vid väveri",
            "contact": {
                "office": "Kinna",
                "phone": [
                    "10292"
                ],
                "postgiro": "81750"
            },
            "financials": {
                "employees": {
                    "industriarb": 20
                },
                "annual_turnover": "400,000 kr",
                "annual_production_value": "400,000 kr"
            },
            "foundation_year": 1931,
            "owners": [
                "fabr. Erik W. Nilsson",
                "fabr. Josef Nilson"
            ]
        },
        "2": {
            "name": "Kinna Yllefabrik",
            "location": "Kinna",
            "business": "Väveri, färgeri, trikå- och konfektionsfabrik i Kinna",
            "contact": {
                "office": "Kinna",
                "phone": [
                    "10143",
                    "10053"
                ],
                "postgiro": "12732"
            },
            "financials": {
                "employees": {
                    "industriarb": 50
                },
                "annual_turnover": "N/A",
                "annual_production_value": "N/A"
            },
            "foundation_year": 1926,
            "owner": "dir. Verner Werner gren"
        },
        "3": {
            "name": "Kinnahults Trikåfabrik",
            "location": "Kinnahult",
            "business": "Tillverkar herr- och damunderkläder",
            "contact": {
                "office": "Kinnahult",
                "phone": "Kinna 10288",
                "postgiro": "162299"
            },
            "financials": {
                "employees": {
                    "industriarb": 10
                },
                "annual_production_value": "100,000 kr"
            },
            "foundation_year": 1934,
            "owner": "fabr. Sigfrid Johansson"
        },
        "4": {
            "name": "Kinnahults Väfveri",
            "location": "Kinnahult",
            "business": "Tillverkar gardiner, draperi- och möbeltyger",
            "contact": {
                "office": "Kinnahult",
                "phone": "Kinna 10043",
                "postgiro": "9346"
            },
            "financials": {
                "employees": {
                    "industriarb": 55
                },
                "annual_production_value": "800,000 kr"
            },
            "foundation_year": 1917,
            "owner": "fabr. Erik Eliason"
        },
        "5": {
            "name": "AB. Kinnareds Textil",
            "location": "Halmstad",
            "business": "Tillverkar gardin- och draperityger vid väveri i Kinnared",
            "contact": {
                "office": "Halmstad",
                "phone": "N/A",
                "postgiro": "171500"
            },
            "financials": {
                "employees": {
                    "industriarb": 32
                },
                "annual_production_value": "500,000 kr"
            },
            "foundation_year": 1934,
            "corporation_year": 1941,
            "director": "John Alsin"
        },
        "6": {
            "name": "Kinnaströms Väfveri AB.",
            "location": "Kinnaström, Kinna",
            "business": "Bomulls väveri, färgeri, blekeri och appreturverk",
            "contact": {
                "office": "Kinnaström, Kinna",
                "phone": "Kinna 10043",
                "postgiro": "9346"
            },
            "financials": {
                "employees": {
                    "industriarb": 55
                },
                "annual_production_value": "6,000,000 kr"
            },
            "foundation_year": 1885,
            "corporation_year": 1895,
            "owners": [
                "dir. Clas Erikson",
                "dir. Edvin Leffler",
                "dir. John O. Erikson"
            ]
        },
        "7": {
            "name": "AB. Kinnekulle Kalk",
            "location": "Kinnemalma",
            "business": "Tillverkar jordbruks- och murbruks-kalk vid fabrik i Kinnemalma",
            "contact": {
                "office": "Kinnemalma",
                "phone": "Lidköping 20340",
                "postgiro": "25915"
            },
            "financials": {
                "employees": {
                    "industriarb": 20
                },
                "annual_production_value": "70,000 kr"
            },
            "foundation_year": 1928,
            "owners": [
                "dir. Knut Karlsson",
                "fru J. Beckman"
            ],
            "director": "Erik Danielsson"
        },
        "8": {
            "name": "AB. Kinofa",
            "location": "Stockholm",
            "business": "Fabrik för tillverkning av biografapparater",
            "contact": {
                "office": "Hammarbyvägen 9-11",
                "phone": [
                    "441415",
                    "441416"
                ],
                "postgiro": "2562"
            },
            "financials": {
                "employees": {
                    "industriarb": 40
                },
                "annual_production_value": "500,000 kr"
            },
            "foundation_year": 1913,
            "corporation_year": 1935,
            "director": "Stig Sundgren"
        }
    }
}