{
    "original": "Mono po l—Morgärdshammar\n\n\"Monopol-Fabriken, Borås.\n\nSe AB. Kemiska Fabriken Monopol,\nBorås.\n\nMonsun AB., Landskrona.\n\nFläktfabrik. Tillverkar fläktar,\nvärmebatterier, torkapparater och\nventilationsradiatorer. Specialiteter: fläkthjul,\nutblåsningsgaller och plåtkåpor.\n\nTelegr.-adr. o. telefon: Monsunbolaget,\nLandskrona. Postgiro: 249930.\n\nAkt.-kap.: 100,000 kr. Antal\nindustriarb.: 43. Tillv.-värde pr år: 700,000 kr.\n— Bolaget grundat 1939 i Vänersborg,\növerflyttat till Landskrona 1944.\n\nVerkst. dir. o. disp.: ing. Arne v.\nSnei-dern.\n\nMontanindustri AB., Skandinaviska,\n\nHedemora.\n\nSe Skandinaviska Gruv AB., Hedemora.\nAB. Lars Montén, Stockholm.\n\nKem.-tekn. fabrik. Tillverkar såpa.\n\nKontor: Alvik, Stockholm. Telegr.-adr.\no. telefon: »Kemabolagen», Stockholm. —\nAkt.-kap.: 5,000 kr.\n\nSåpfabriken anlagd 1823, bolaget\ngrundat 1929. Bolaget ingår i\n»Kema-Bola-gen», Stockholm.\n\nStyrelse: grossh. Robert Ljunglöf\n(ordf.), avd. Bo Hedberg, disp. Nils\nWes-terdahl.\n\nVerkst. dir.: Tor Olsson.\n\n\"Hugo Montgomery AB.,\nCivilingenjör, Stockholm.\n\nKonstruerar och låter vid olika\nverkstäder tillverka lyftkranar och andra\ntransportanordningar samt elektr.\nljus-bågsugnar; utför servisarbeten vid egen\nverkstad. Varumärke: »Huge». Bolaget\ndriver såsom huvudrörelse handel med\ntelfrar, truckar, gjuterimaskiner och\n-förnödenheter.\n\nKontor: Nybrog. 42. Telegr.-adr.:\nDe-inater, Stockholm. Telefon: 679050.\nPostgiro: 52493. — Akt.-kap.: 100,000 kr.\nAntal arb.: 15. — Firman grundad 1918,\nbolag 1943.\n\nStyrelse o. verkst. dir.: civiling. Hugo\nMontgomery.\n\nMora Armaturfabrik AB., Mora.\n\nGjuteri och metallverkstad i östnor,\nMora (Kopparb. l.). Tillverkar\nsanitets-armatur\n\nPostadr.: Box 33, Mora. Telegr.-adr.:\nMoraarmatur, Mora. Telefon: 320 o. 620.\nPostgiro: 99874.\n\nAkt.-kap.: 60,000 kr. Antal\nindustriarb.: 100. Tillv.-värde pr år: 1,300,000 kr.\n\n—\tFirman etabl. 1927, bolag 1938.\nStyrelse o. verkst. dir.: Folke Mattsson.\n\n\"Mora Bryggeri AB., Mora.\n\nBryggerier i Mora och Malung,\nsvag-dricksbryggerier i Rättvik och Leksand\n(samtl. i Kopparb. l.). Tillverkar\nmaltdrycker, läskedrycker och kolsyrade\nmineralvatten.\n\nTelegr.-adr.: Bryggeribolaget, Mora.\nTelefon: »Bryggeriet». Postgiro: 85475.\n\nAkt.-kap.: 1,000,000 kr. Antal\nindustriarb.: 85. Tillv.-värde pr år: 1,900,000 kr.\n\n—\tFirman, grundad 1872, är delägare i\nAB. Falu Ångbryggeri, Falun.\n\nStyrelse: dir. Nils G. Arvedson (ordf.),\ndisp. Erik Löfgren, disp. John Löfgren.\nDisp.: Erik Löfgren.\n\nAB. Moraindustri, Mora.\n\nArmaturfabrik i Mora (Kopparb. l.).\nTillverkar sanitetsarmatur.\n\nTelefon: 332. Postgiro: 144714. —\nAkt.-kap.: 40,000 kr. Antal industriarb.:\n46. Tillv.-värde pr år: 600,000 kr. —\nBolaget grundat 1936.\n\nVerkst. dir.: Johan Eriksson.\n\n\"Morén, Elektr. AB., Partille.\nSe Elektr. AB. Morén, Partille.\n\n\"AB. Moresco, Malmö.\n\nKapp- och pälsvarufabrik. Tillverkar\ndam- och barnkappor samt pälsvaror.\n\nKontor: Gustaf Adolfs Torg 12 A.\nTelegr.-adr.: Moresco, Malmö. Telefon:\n71010. Postgiro: 38456.\n\nAkt.-kap.: 750,000 kr. Antal\nindustriarb.: 300. — Bolaget grundat 1892.\n\nStyrelse: bankdir. William Lindahl\n(ordf.), dir. J. Moresco, adv. Rolf\nNor-denstedt.\n\nVerkst. dir.: Arvid Thulin.\n\n\"Morgårdshammars Mek. Verkstads\nAB., Morgärdshammar.\n\nMek. verkstad och elektr.\nvattenkraftstation vid Morgärdshammar (Kopparb.\n1.). Tillverkar maskiner för gruvor,\njärn-och stålverk m. m. Bolaget idkar jämväl\njordbruk samt sågverks- och kvarnrörelse.\n\nTelegr.-adr. o. telefon:\nMorgärdshammar, Smedjebacken. Postgiro: 72287.\n\n379*",
    "structured": {
        "1": {
            "name": "Monsun AB.",
            "location": "Landskrona",
            "business": "Fläktfabrik",
            "products": "Tillverkar fläktar, värmebatterier, torkapparater och ventilationsradiatorer. Specialiteter: fläkthjul, utblåsningsgaller och plåtkåpor.",
            "contact": {
                "office": null,
                "phone": [
                    "Monsunbolaget, Landskrona"
                ],
                "postgiro": "249930",
                "head_office": null,
                "sales_offices": null,
                "telegraph": null,
                "factory_office": null,
                "factory_phone": null
            },
            "financials": {
                "capital": "100,000 kr",
                "employees": {
                    "industriarb": 43
                },
                "annual_turnover": "700,000 kr",
                "annual_production_value": "700,000 kr"
            },
            "foundation_year": 1939,
            "current_name_year": 1944,
            "corporation_year": null,
            "board": null,
            "owners": null,
            "director": "ing. Arne v. Snei-dern",
            "managing_director": null,
            "sales_manager": null,
            "manager": null
        },
        "2": {
            "name": "AB. Lars Montén",
            "location": "Stockholm",
            "business": "Kem.-tekn. fabrik",
            "products": "Tillverkar såpa.",
            "contact": {
                "office": "Alvik, Stockholm",
                "phone": [
                    "Kemabolagen, Stockholm"
                ],
                "postgiro": null,
                "head_office": null,
                "sales_offices": null,
                "telegraph": null,
                "factory_office": null,
                "factory_phone": null
            },
            "financials": {
                "capital": "5,000 kr",
                "employees": null,
                "annual_turnover": null,
                "annual_production_value": null
            },
            "foundation_year": 1929,
            "current_name_year": null,
            "corporation_year": null,
            "board": {
                "name": "grossh. Robert Ljunglöf",
                "role": "ordf."
            },
            "owners": null,
            "director": null,
            "managing_director": null,
            "sales_manager": null,
            "manager": null
        },
        "3": {
            "name": "Hugo Montgomery AB.",
            "location": "Stockholm",
            "business": "Konstruerar och låter vid olika verkstäder tillverka lyftkranar och andra transportanordningar samt elektr. ljusbågsugnar; utför servisarbeten vid egen verkstad. Varumärke: »Huge». Bolaget driver såsom huvudrörelse handel med telfrar, truckar, gjuterimaskiner och förnödenheter.",
            "products": null,
            "contact": {
                "office": "Nybrog. 42",
                "phone": [
                    "679050"
                ],
                "postgiro": "52493",
                "head_office": null,
                "sales_offices": null,
                "telegraph": "De-inater, Stockholm",
                "factory_office": null,
                "factory_phone": null
            },
            "financials": {
                "capital": "100,000 kr",
                "employees": null,
                "annual_turnover": null,
                "annual_production_value": null
            },
            "foundation_year": 1918,
            "current_name_year": 1943,
            "corporation_year": null,
            "board": null,
            "owners": null,
            "director": "civiling. Hugo Montgomery",
            "managing_director": null,
            "sales_manager": null,
            "manager": "civiling. Hugo Montgomery"
        },
        "4": {
            "name": "Mora Armaturfabrik AB.",
            "location": "Mora",
            "business": "Gjuteri och metallverkstad",
            "products": "Tillverkar sanitetsarmatur",
            "contact": {
                "office": null,
                "phone": [
                    "320",
                    "620"
                ],
                "postgiro": "99874",
                "head_office": null,
                "sales_offices": null,
                "telegraph": "Moraarmatur, Mora",
                "factory_office": null,
                "factory_phone": null
            },
            "financials": {
                "capital": "60,000 kr",
                "employees": {
                    "industriarb": 100
                },
                "annual_turnover": "1,300,000 kr",
                "annual_production_value": "1,300,000 kr"
            },
            "foundation_year": 1927,
            "current_name_year": 1938,
            "corporation_year": null,
            "board": null,
            "owners": null,
            "director": null,
            "managing_director": null,
            "sales_manager": null,
            "manager": null
        },
        "5": {
            "name": "Mora Bryggeri AB.",
            "location": "Mora",
            "business": "Bryggerier",
            "products": "Tillverkar maltdrycker, läskedrycker och kolsyrade mineralvatten.",
            "contact": {
                "office": null,
                "phone": [
                    "Bryggeriet"
                ],
                "postgiro": "85475",
                "head_office": null,
                "sales_offices": null,
                "telegraph": "Bryggeribolaget, Mora",
                "factory_office": null,
                "factory_phone": null
            },
            "financials": {
                "capital": "1,000,000 kr",
                "employees": {
                    "industriarb": 85
                },
                "annual_turnover": "1,900,000 kr",
                "annual_production_value": "1,900,000 kr"
            },
            "foundation_year": 1872,
            "current_name_year": null,
            "corporation_year": null,
            "board": {
                "name": "dir. Nils G. Arvedson",
                "role": "ordf."
            },
            "owners": null,
            "director": null,
            "managing_director": null,
            "sales_manager": null,
            "manager": null
        },
        "6": {
            "name": "AB. Moraindustri",
            "location": "Mora",
            "business": "Armaturfabrik",
            "products": "Tillverkar sanitetsarmatur.",
            "contact": {
                "office": null,
                "phone": [
                    "332"
                ],
                "postgiro": "144714",
                "head_office": null,
                "sales_offices": null,
                "telegraph": null,
                "factory_office": null,
                "factory_phone": null
            },
            "financials": {
                "capital": "40,000 kr",
                "employees": {
                    "industriarb": 46
                },
                "annual_turnover": "600,000 kr",
                "annual_production_value": "600,000 kr"
            },
            "foundation_year": 1936,
            "current_name_year": null,
            "corporation_year": null,
            "board": null,
            "owners": null,
            "director": null,
            "managing_director": null,
            "sales_manager": null,
            "manager": null
        },
        "7": {
            "name": "AB. Moresco",
            "location": "Malmö",
            "business": "Kapp- och pälsvarufabrik",
            "products": "Tillverkar dam- och barnkappor samt pälsvaror.",
            "contact": {
                "office": "Gustaf Adolfs Torg 12 A",
                "phone": [
                    "71010"
                ],
                "postgiro": "38456",
                "head_office": null,
                "sales_offices": null,
                "telegraph": "Moresco, Malmö",
                "factory_office": null,
                "factory_phone": null
            },
            "financials": {
                "capital": "750,000 kr",
                "employees": {
                    "industriarb": 300
                },
                "annual_turnover": null,
                "annual_production_value": null
            },
            "foundation_year": 1892,
            "current_name_year": null,
            "corporation_year": null,
            "board": {
                "name": "bankdir. William Lindahl",
                "role": "ordf."
            },
            "owners": null,
            "director": null,
            "managing_director": null,
            "sales_manager": null,
            "manager": null
        },
        "8": {
            "name": "Morgårdshammars Mek. Verkstads AB.",
            "location": "Morgärdshammar",
            "business": "Mek. verkstad och elektr. vattenkraftstation",
            "products": "Tillverkar maskiner för gruvor, järn-och stålverk m. m. Bolaget idkar jämväl jordbruk samt sågverks- och kvarnrörelse.",
            "contact": {
                "office": null,
                "phone": [
                    "Morgärdshammar, Smedjebacken"
                ],
                "postgiro": "72287",
                "head_office": null,
                "sales_offices": null,
                "telegraph": null,
                "factory_office": null,
                "factory_phone": null
            },
            "financials": {
                "capital": null,
                "employees": null,
                "annual_turnover": null,
                "annual_production_value": null
            },
            "foundation_year": null,
            "current_name_year": null,
            "corporation_year": null,
            "board": null,
            "owners": null,
            "director": null,
            "managing_director": null,
            "sales_manager": null,
            "manager": null
        }
    }
}