{
    "original": "Centralbolaget—Choklad fabriken\n\n*\tCentra I bolaget för Kemiska\nIndustrier AB., Stockholm.\n\nBolaget har till syfte att förmedla och\nutvidga kommersiellt och tekniskt\nsamarbete på den kemiska industriens\nområde, att stå i kontakt med in- och utländsk\nforsknings- och försöksverksamhet samt\natt inom sin intressentkrets verka för ett\nrationellt utbyte av såväl vetenskapliga\nsom tekniska iakttagelser och\nerfarenheter.\n\nIntressenter i bolaget äro: AB. Bofors,\nBolidens Gruv AB., Höganäs-Billesholms\nAB., AB. Kerna, Liljeholmens\nStearinfabriks AB., Reymersholms Gamla\nIndustri AB., AB. Stille-Werner, AB.\nStockholms Bryggerier, Stockholms\nSuperfosfat Fabriks AB., Svenska\nSockerfabriks AB., Uddeholms AB. och AB.\nWilh. Beeker.\n\nHuvudkontor: Sveavägen 48.\nTelegr.-adr.: Kemindu^tri, Stockholm. Telefon:\n233530. Postgiro: 193104.\nKonstruktionsbyrå: Uppsala, telefon: 40579 o.\n30542. — Akt.-kap.: 480,000 kr. —\nBolaget grundat 1940.\n\nStyrelse: grossh. Robert Ljunglöf\n(ordf.), dir. Sverre R:son Sohlman (v.\nordf.), dir. Erik 3*. Bengtson, dir. Gösta\nBrowall, dir. P. Eg. Gummeson, dir. W.\nHellgren, dir. Sven E. Lundberg, dir. ISf.\nW. Lundblad, fil. dr Harald Nordenson,\ndir. Ii. Rydin, dir. Sven Schwartz, disp.\nNils Westerdahi.\n\nVerkst. dir.: tekn. dr R. Winbladh.\n\nAvd.-ehefer: för\nproduktionsplanerings-avcl.: civiling. S. Telenius; för\nförsäljn.-avd.: för Sverige: ing. C. A. Nilson; för\nutlandet: civiling. G. Renius; för\nkonstruktionsbyrån: civiling. G. Philipson.\n\nKontorschef: G. Orneman.\n\n(Jfr annons nr 18.)\n\n*\tCentralbryggeriet, Linköping.\n\nSe AB, Nya Centralbryggeriet,\nLinköping.\n\n*AB. Centraltryckeriet I Stockholm,\n\nStockholm.\n\nBok-, stål- och djuptryckeri, litografisk\noch klichéanstalt, notstickeri och\nmusikalietryckeri, bokbinderi och stämpelfabrik.\n\nKontor: Vasag. 16. Telegr.-adr.:\nCentraltryck, Stockholm. Telefon:\n»Centraltryckeriet». Postgiro: 35.\n\nFirman etabl. 1873. Bolaget är anslutet\ntill AB. Sveriges Litografiska Tryckerier,\nStockholm (se detta bolag).\n\nStyrelse o. verkst. dir.: Gösta Smith.\n\n7\n\n*Centrlfug AB., Svenska, Stockholm.\n\nSe Svenska Centrifug AB., Stockholm.\n\n*Centrum, Radiofabriken, Stockholm.\n\nSe AB. Gylling &amp; Co., Stockholm.\n\nCeres, AB. Oljeraffinaderiet, Malmö.\n\nSe AB. Oljeraffinaderiet Ceres, Malmö.\n\nCertus, Ingenjörsfirman, Stockholm.\n\nSe Ingenjörsfirman Certus, Stockholm.\n\n*AB. Cewo-Kappor, Malmö.\n\nTillverkar dräkter, dam- och\nflickkap-por samt riddräkter. Varumärke:\n»College-stilen».\n\nKontor: Norbergsg. 11. Telegr.-adr.:\nCewo, Malmö. Telefon: 71575. Postgiro:\n147431. — Akt.-kap.: 100,000 kr. Antal\nindustriarb.: 200. — Firman etabl. 19.36,\nbolag 1945.\n\nStyrelse o. verkst. dir.: fru S. Thånell.\n\n*AB. Chamberts Möbelfabrik,\n\nNorrköping.\n\nTillverkar möbler och inredningar.\n\nTelefon: 27244. Postgiro: 95235. —\nAkt.-kap.: 70,000 kr. Antal industriarb.:\n15. — Firman.etabl. 1883, bolag 192$.\n\nStyfélse o. verkst. dir.: Axel Chambert.\n\nDisp.: Otto Chambert.\n\n*Charlottenbergs Kraftverk,\n\nCharlottenberg.\n\nSe Billeruds AB., Säffle.\n\nCharlottenbergs Tegelbruk,\n\nCharlottenberg.\n\nTillverkar mur- och taktegel vid\ntegelbruk i Charlottenberg (Värml. l.).\n\nTelefon: 4. Postgiro: 142845. —\nAntal industriarb.: 16. Årstillv.: 120,000 st.\ntaktegel, 250,000 st. murtegel. —\nTegelbruket grundlagt 1907, övertogs av nuv.\nägare 1937.\n\nÄgare o. chef: fabr. Henry Högsäter.\n\nChenillefabriken, Ängelholm.\n\nSe Svenska Chenillefabriken,\nÄngelholm.\n\n*AB. Chokladfabriken Coralli,\n\nHälsingborg.\n\nTillverkar kakao, choklad och\nkonfi-tyrer.",
    "structured": {
        "firms": [
            {
                "name": "Centralbolaget—Choklad fabriken",
                "location": "Stockholm",
                "business": "Förmedla och utvidga kommersiellt och tekniskt samarbete på den kemiska industriens område",
                "contact": {
                    "office": "Sveavägen 48",
                    "phone": [
                        "233530"
                    ],
                    "postgiro": "193104",
                    "telegraph": "Kemindustri, Stockholm"
                },
                "financials": {
                    "capital": "480,000 kr"
                },
                "foundation_year": 1940,
                "board": [
                    {
                        "name": "grossh. Robert Ljunglöf",
                        "role": "ordf."
                    },
                    {
                        "name": "dir. Sverre R:son Sohlman",
                        "role": "v. ordf."
                    },
                    {
                        "name": "dir. Erik 3*. Bengtson",
                        "role": null
                    },
                    {
                        "name": "dir. Gösta Browall",
                        "role": null
                    },
                    {
                        "name": "dir. P. Eg. Gummeson",
                        "role": null
                    },
                    {
                        "name": "dir. W. Hellgren",
                        "role": null
                    },
                    {
                        "name": "dir. Sven E. Lundberg",
                        "role": null
                    },
                    {
                        "name": "dir. ISf. W. Lundblad",
                        "role": null
                    },
                    {
                        "name": "fil. dr Harald Nordenson",
                        "role": null
                    },
                    {
                        "name": "dir. Ii. Rydin",
                        "role": null
                    },
                    {
                        "name": "dir. Sven Schwartz",
                        "role": null
                    },
                    {
                        "name": "disp. Nils Westerdahi",
                        "role": null
                    }
                ],
                "director": "tekn. dr R. Winbladh"
            },
            {
                "name": "AB. Centraltryckeriet I Stockholm",
                "location": "Stockholm",
                "business": "Bok-, stål- och djuptryckeri, litografisk och klichéanstalt, notstickeri och musikalietryckeri, bokbinderi och stämpelfabrik",
                "contact": {
                    "office": "Vasag. 16",
                    "phone": null,
                    "postgiro": "35",
                    "telegraph": "Centraltryck, Stockholm"
                },
                "financials": null,
                "foundation_year": 1873,
                "board": [
                    {
                        "name": "Gösta Smith",
                        "role": "verkst. dir."
                    }
                ]
            },
            {
                "name": "AB. Cewo-Kappor",
                "location": "Malmö",
                "business": "Tillverkar dräkter, dam- och flickkappor samt riddräkter",
                "contact": {
                    "office": "Norbergsg. 11",
                    "phone": [
                        "71575"
                    ],
                    "postgiro": "147431"
                },
                "financials": {
                    "capital": "100,000 kr"
                },
                "foundation_year": 1936,
                "board": [
                    {
                        "name": "fru S. Thånell",
                        "role": "verkst. dir."
                    }
                ]
            },
            {
                "name": "AB. Chamberts Möbelfabrik",
                "location": "Norrköping",
                "business": "Tillverkar möbler och inredningar",
                "contact": {
                    "phone": "27244",
                    "postgiro": "95235"
                },
                "financials": {
                    "capital": "70,000 kr"
                },
                "foundation_year": 1923,
                "board": [
                    {
                        "name": "Axel Chambert",
                        "role": "verkst. dir."
                    },
                    {
                        "name": "Otto Chambert",
                        "role": "Disp."
                    }
                ]
            },
            {
                "name": "AB. Chokladfabriken Coralli",
                "location": "Hälsingborg",
                "business": "Tillverkar kakao, choklad och konfityrer",
                "contact": {
                    "phone": null,
                    "postgiro": "147431"
                },
                "financials": null,
                "foundation_year": null
            }
        ]
    }
}