{
    "original": "Falu—Faxe\n\nFalu Spisbrödsfabrik, Vald.\nJohansson, Falun.\n\nTillverkar spisbröd. Varunamn: »Falu\nRutbröd».\n\nTelefon: 750. Postgiro: 160013. —\nAntal industriarb.: 20. Tillv.-värde pr år:\n300,000 kr. — Firman etabl. 1939.\n\nÄgare o. chef: fabr. Vald. Johansson.\n\n\"Falu Tegelverks AB., Falun,\n\nTegelbruk samt sågverk (Gethällens\nsåg). Tillverkar murtegel och\ntäckdikes-rör samt sågade trävaror.\n\nTelegr.-adr.: Tegelverk, Falun.\nTelefon: 228 o. 224. Postgiro: 31188.\n\nAkt.-kap.: 212,500 kr. Antal\nindustriarb.: 30. Årstillv.: 1,000 stds trävaror, o.\n1,8 milj. st. tegelvaror. — Bolaget\ngrundat 1899.\n\nVerkst. dir.: Carl Hellberg.\n\n*Falu Yllefabriks AB., Sågmyra.\n\nUllspinneri och ylleväveri, stamp- och\nberedningsverk, färgeri, schoddyfabrik,\nvaddfabrik och kemisk tvättänstalt i\nSågmyra (Kopparb. l.). Tillverkar filtar,\nhel- och halvyllevävnader, ullgarn och\nvadd samt bedriver löngodsrörelse.\nVarumärke: »Tidstrand».\n\nTelefon: Falun 138. Postgiro: 8468.\nFörsäljn.-kontor: Stockholm: Falu Ylles\nFörsäljningskontor, Sveavägen 25—27,\ntelefon: 116228.\n\nAkt.-kap.: 2,250,000 kr. Antal\nindustriarb.: 650. Tillv.-värde pr år: 8,000,000 kr.\n— Firman etabl. 1896, bolag 1916.\n\nStyrelse: fabr. Axel L. Tidstrand\n(ordf.), dir. Ragnar Tidstrand, disp. Sven\nTidstrand.\n\nVerkst. dir.: A. L. Tidstrand.\n\nDisp.: Sven Tidstrand.\n\nKamrer: Th. Nordahl.\n\n*AB. Falu Ångbryggeri, Falun.\n\nTillverkar malt- och läskedrycker samt\nmineralvatten.\n\nTelegr.-adr. o. telefon: Ångbryggeriet,\nFalun. Postgiro: 23925. — Akt.-kap.:\n450,000 kr. Antal industriarb.: 26.\nTillv.-värde pr år: 800,000 kr. — Bryggeriet\nanlagt 1869, nuv. bolag grundat 1910.\n\nStyrelse: disp. John Löfgren (ordf.),\ndir. Nils G. Arvedson, dir. A. Bäcklund.\n\nDisp.: John Löfgren.\n\n*AB. Fanérfabriken i Forserum,\n\nForserum.\n\nTillverkar enkelskuret fanér för\nmöbeltillverkning vid fabrik i Forserum\n(Jönköp. l.).\n\nTelegr.-adr.: Fanérfabriken, Forserum.\nTelefon: 61. Postgiro: 98777.\n\nAkt.-kap.: 10,000 kr. Arb.-antal: 8.\nTillv.-värde pr år: 125,000 kr. —\nBolaget grundat 1923.\n\nStyrelse: disp. Eric Lagerquist (ordf.),\nverkm. Georg Lagerquist, trävaruhandl.\nHilding Lagerquist, fru Idalia\nLagerquist, fru Sigrid Lagerquist^\n\nVerkst. dir.: Eric Lagerquist.\n\nKamrer: Gösta Ryländer.\n\nAB. Fargo, Malmö.\n\nMek. verkstad. Tillverkar lastvagnar å\ngummihjul, hydrauliska tippapparater\nsamt ogrässprutor.\n\nKontor: Bothildenborgsv., postadr,:,\nMalmö 13. Telefon: 12576. Postgiro:\n39648. — Akt.-kap.: 20,000 kr. Antal\nindustriarb.: 10. Tillv.-värde pr år: 200,000\nkr. — Bolaget grundat 1936.\n\nStyrelse o. verkst. dir.: Herman Twede.\n\nDisp.: Thure Twede.\t. ;\n\n. . , . . i\n\n*AB. Fasilko, Göteborg,\n\nSidenväveri, trikåväveri och\ndamkonfektionsfabrik. ^ Tillverkar sidentyger,,\ncharmeuse och jersey samt klänningar och.\ndamunderkläder.\n\nKontor: 3:e Långgat. 13 B.\nTelegr.-adr.: Fasilko, Göteborg. Telefon: 17064Q.\nPostgiro: 40033.\n\nAkt.-kap.: 200,000 kr. Antal\nindustriarb.: 160. — Bolaget grundat 1927.\n\nStyrelse: dir. J. Henning Wenander\n(ordf.), disp. Sven Nielsen, ing. Nils WeJ\nnander.\n\nVerkst. dir.: J. H. Wenander;\n\nV. verkst. dir.: Nils Wenander.\t•\n\nKamrer: Kristian Boberg.\n\nFast, Fabriks AB. Stålformar, M\n\nLimhamn.\n\nMek. verkstad i Malmö. Tillverkar\npress- och stansverktyg samt pneumatiska\nmaskin- och bänkskruvstycken.\nVarumärke: »Fast».\n\nKontor: Limhamn. Telefon: Malmö\n50630 o. 50730. — Akt.-kap.: 20,000 kr.\nAntal industriarb.: 12. Tillv-värde pr år:\n200,000 kr. — Bolaget, grundat 1944, är\ndotterbolag till Svenska Elfabriks AB.,\nSELFA, Limhamn (se detta bolag).\n\nVerkst. dir.: Olof Edman (Sthlm).\n\n*G. C. Faxe AB., Malmö.\n\nAckumulatorfabrik (Nordiska\nAckumulator Fabriken) samt syrgasfabrik (Syr^\ngasfabriken Flytande Luft). Tillverkar\nblyackumulatorer (märke: »Noack») fÖB\n\n",
    "structured": {
        "1": {
            "name": "Falu Spisbrödsfabrik",
            "location": "Falu, Falun",
            "business": "Tillverkar spisbröd. Varunamn: »Falu Rutbröd»",
            "contact": {
                "phone": [
                    "750"
                ],
                "postgiro": "160013"
            },
            "financials": {
                "employees": {
                    "industriarb": 20
                },
                "annual_turnover": "300,000 kr"
            },
            "foundation_year": 1939,
            "owner": "Vald. Johansson"
        },
        "2": {
            "name": "Falu Tegelverks AB",
            "location": "Falun",
            "business": "Tegelbruk samt sågverk (Gethällens såg). Tillverkar murtegel och täckdikes-rör samt sågade trävaror",
            "contact": {
                "phone": [
                    "228",
                    "224"
                ],
                "postgiro": "31188"
            },
            "financials": {
                "capital": "212,500 kr",
                "employees": {
                    "industriarb": 30
                },
                "annual_turnover": "1,000 stds trävaror, o. 1,8 milj. st. tegelvaror"
            },
            "board": [
                {
                    "name": "Carl Hellberg",
                    "role": "Verkst. dir."
                }
            ],
            "foundation_year": 1899
        },
        "3": {
            "name": "Falu Yllefabriks AB",
            "location": "Sågmyra",
            "business": "Ullspinneri och ylleväveri, stamp- och beredningsverk, färgeri, schoddyfabrik, vaddfabrik och kemisk tvättänstalt",
            "contact": {
                "phone": "Falun 138",
                "postgiro": "8468"
            },
            "financials": {
                "capital": "2,250,000 kr",
                "employees": {
                    "industriarb": 650
                },
                "annual_turnover": "8,000,000 kr"
            },
            "foundation_year": 1896,
            "current_name_year": 1916,
            "board": [
                {
                    "name": "Axel L. Tidstrand",
                    "role": "Ordf."
                },
                {
                    "name": "Ragnar Tidstrand",
                    "role": "Dir."
                },
                {
                    "name": "Sven Tidstrand",
                    "role": "Disp."
                }
            ],
            "owner": "fabr. Axel L. Tidstrand"
        },
        "4": {
            "name": "AB. Falu Ångbryggeri",
            "location": "Falun",
            "business": "Tillverkar malt- och läskedrycker samt mineralvatten",
            "contact": {
                "phone": "Ångbryggeriet, Falun",
                "postgiro": "23925"
            },
            "financials": {
                "capital": "450,000 kr",
                "employees": {
                    "industriarb": 26
                },
                "annual_turnover": "800,000 kr"
            },
            "foundation_year": 1910,
            "predecessor": "Bryggeriet anlagt 1869"
        },
        "5": {
            "name": "AB. Fanérfabriken i Forserum",
            "location": "Forserum",
            "business": "Tillverkar enkelskuret fanér för möbeltillverkning vid fabrik i Forserum",
            "contact": {
                "phone": "61",
                "postgiro": "98777"
            },
            "financials": {
                "capital": "10,000 kr",
                "employees": {
                    "arbetare": 8
                },
                "annual_turnover": "125,000 kr"
            },
            "foundation_year": 1923,
            "board": [
                {
                    "name": "Eric Lagerquist",
                    "role": "Ordf."
                },
                {
                    "name": "Georg Lagerquist",
                    "role": "Verkm."
                },
                {
                    "name": "Hilding Lagerquist",
                    "role": "Trävaruhandl."
                },
                {
                    "name": "Idalia Lagerquist",
                    "role": "Fru"
                },
                {
                    "name": "Sigrid Lagerquist",
                    "role": "Fru"
                }
            ]
        },
        "6": {
            "name": "AB. Fargo",
            "location": "Malmö",
            "business": "Mek. verkstad. Tillverkar lastvagnar å gummihjul, hydrauliska tippapparater samt ogrässprutor",
            "contact": {
                "phone": "12576",
                "postgiro": "39648"
            },
            "financials": {
                "capital": "20,000 kr",
                "employees": {
                    "industriarb": 10
                },
                "annual_turnover": "200,000 kr"
            },
            "foundation_year": 1936,
            "board": [
                {
                    "name": "Herman Twede",
                    "role": "Styrelse o. verkst. dir."
                }
            ]
        },
        "7": {
            "name": "AB. Fasilko",
            "location": "Göteborg",
            "business": "Sidenväveri, trikåväveri och damkonfektionsfabrik",
            "contact": {
                "phone": "170640",
                "postgiro": "40033"
            },
            "financials": {
                "capital": "200,000 kr",
                "employees": {
                    "industriarb": 160
                }
            },
            "foundation_year": 1927,
            "board": [
                {
                    "name": "J. Henning Wenander",
                    "role": "Ordf."
                },
                {
                    "name": "Sven Nielsen",
                    "role": "Disp."
                },
                {
                    "name": "Nils Wenander",
                    "role": "Ing."
                }
            ]
        },
        "8": {
            "name": "Fabriks AB. Stålformar",
            "location": "Limhamn",
            "business": "Mek. verkstad. Tillverkar press- och stansverktyg samt pneumatiska maskin- och bänkskruvstycken",
            "contact": {
                "phone": "Malmö 50630 o. 50730"
            },
            "financials": {
                "capital": "20,000 kr",
                "employees": {
                    "industriarb": 12
                },
                "annual_turnover": "200,000 kr"
            },
            "board": [
                {
                    "name": "Olof Edman",
                    "role": "Verkst. dir."
                }
            ],
            "corporation_year": 1944
        },
        "9": {
            "name": "G. C. Faxe AB.",
            "location": "Malmö",
            "business": "Ackumulatorfabrik (Nordiska Ackumulator Fabriken) samt syrgasfabrik (Syrgasfabriken Flytande Luft). Tillverkar blyackumulatorer (märke: 'Noack') fÖB",
            "contact": {
                "phone": "",
                "postgiro": ""
            }
        }
    }
}