{
    "original": "Fougstedt—Fredfors\n\nAkt.-kap.: 20,000 kr. Antal industriarb.:\n60. Tillv.-värde pr år: 600,000 kr. —\nFirman etabl. 1942, bolag 1944.\n\nDisp.: Göt^ Johansson.\n\n*Fougstedts Klädes- &amp; Konfektions\nAB., Malmö.\n\nTillverkar damkappor. Bolaget driver\näven engroshandel med tyger samt egen\nminuthandel med kappor oeh tyger.\n\nKontor: Stortorget 6. Telegr.-adr.:\nFougstedts, Malmö. Telefon: 72060.\nPostgiro: 37675.\n\nAkt.-kap.: 600,000 kr. Antal\nindustriarb.: 205. Tillv.-värde pr år: 3,000,000\nkr. — Firman etabl. 1857, bolag 1926.\n\nStyrelse: dir. Bror O. Jeppsson (ordf.),\nlänsassessor Sigurd Dahlrup, dir. Erik\nEmil Eriksson, dir. Nils P. Lundh, dir.\nKjell Nilsson.\n\nVerkst. dir.: Bror O. Jeppsson.\n\nKontorschef: Olga Olsson.\n\n*\tFougstedts Pälsvarufabrik, Nya AB.,\n\nMalmö.\n\nSe Nya AB. Fougstedts Pälsvarufabrik,\nMalmö.\n\nFramnäs Väveri AB., Kinna.\n\nGardinfabrik i Kinna (Älvsb. l.).\nTillverkar såsom specialitet gardiner,\nmöbel-och draperi tyger av konstsilke och bomull.\n\nTelegr.-adr.: Framnäs, Kinna. Telefon:\n10089. Postgiro: 82260.\n\nAkt.-kap.: 200,000 kr. Antal\nindustriarb.: 50. Tillv.-värde pr år: 1,000,000 kr.\n— Firman etabl. 1900, bolag 1923.\n\nStyrelse: dir. Arne Sundqvist, ing.\nGunnar Sundqvist.\n\nVerkst. dir.: Arne Sundqvist.\n\n*\tFramnäs Ångsåg, Sävsjöström.\n\nSe AB. Brusafors-Hällefors,\nSilverdalen.\n\n^Framtiden, Tryckeri AB., Malmö.\n\nSe Tryckeri AB. Framtiden, Malmö.\n\n*AB. Carl Franckes Läder &amp; Sko-\n\nfabrik, Halmstad.\n\nTillverkar koläder, kruponger,\nrand-sydda, agoskodon oeh genomsydda\nskodon, filt- och skinntofflor. Varumärke:\n»Franckes».\n\nTelegr.-adr.: Francke, Halmstad.\nTelefon: 175, 507 o. 1875. Postgiro: 36254.\n\nAkt.-kap.: 1,200,000 kr. Antal\nindustriarb.: 175. Tillv.-värde pr år: 3,000,000 kr.\n— Firman etabl. 1888, bolag 1929.\n\nStyrelse: dir. Curt Francke (ordf.),\nkontorschef Hugo Nilsson, bankkamrer\nIvar Nyberg, disp. Axel Persson, fru E.\nPersson.\n\nVerkst. dir.: Curt Francke.\nKontorschef: H. Nilsson.\n\nL. E. Franksson, Sågverk &amp; Hyvleri,\n\nOckelbo.\n\nSågverk med hyvleri (Fredriksro\nsågverk) samt kolugnar vid Ockelbo (Gävleb.\n1.). Tillverkar sågade och hyvlade\nträvaror, list verk, telegrafstolpar samt\nträkol, gengaskol, trätjära och tjärolja.\nFirman driver även jordbruk och\nskogshantering:.\n\nTelegr.-adr.: Franksson, Ockelbo.\nTelefon: 2 o. 92. Postgiro: 287643. — Antal\nindustriarb.: 75. Årstillv.: 2,500 stds\nträvaror. — Sågverket anlagt 1916, nuv.\nfirma etabl. 1934.\n\nÄgare o. chef: disp. L. E. Franksson.\n\n*Erik Franssons Fabriker, Tenhult.\n\nMöbelfabrik i Tenhult (Jönköp. l.).\nTillverkar byråar.\n\nTelefon: 127 o. 40. Postgiro: 139858.—\nAntal industriarb.: 35. Tillv.-värde pr år:\n650,000 kr. — Firman etabl. 1936.\n\nÄgare o. chef: fabr. Erik Fransson.\n\nFranzéns Trävaru AB., Näsbykulla.\n\nTillverkar sågade och hyvlade trävaror\nvid sågverk med hyvleri i Näsbykulla\n(Kronob. l.). Varumärke: »F. R. N.».\n\nTelefon: 12. Postgiro: 166742. —\nAkt.-kap.: 120,000 kr. Antal industriarb.: 25.\nTillv.-värde pr år: 500,000 kr. — Bolaget\ngrundat 1929.\n\nDisp.: Ragnar Franzén.\n\nFredfors Fabriks AB., Ulvsunda.\n\nRem- och presenningsfabrik i\nUlvsunda, Stockholm. Tillverkar remmar av\nläder och bomull, presenningar m. m.\nBolaget driver jämväl engroshandel med\nremmar, tekn. gummivaror,\nmaskinförnödenheter, brandredskap samt maskiner och\nverktyg m. m. Varumärke: »Fredmar».\n\nKontor: Ulvsundavägen 180.\nTelegr.-adr.: Fredfors, Stockholm. Telefon:\n282500. Postgiro: 57900. — Akt.-kap.:\n100,000 kr. Antal industriarb.: 10.—\nBolaget grundat 1887, ombildat 1934.",
    "structured": {
        "firms": [
            {
                "name": "Fougstedt—Fredfors",
                "location": "Malmö",
                "business": "Klädes- & Konfektionstillverkning",
                "products": "Tillverkar damkappor och driver engroshandel med tyger samt egen minuthandel med kappor och tyger.",
                "contact": {
                    "office": "Stortorget 6, Malmö",
                    "phone": [
                        "72060"
                    ],
                    "telegraph": "Fougstedts, Malmö",
                    "postgiro": "37675"
                },
                "financials": {
                    "capital": "20,000 kr",
                    "employees": {
                        "industriarb": 60
                    },
                    "annual_turnover": "600,000 kr"
                },
                "foundation_year": 1942
            },
            {
                "name": "Fougstedts Klädes- & Konfektions AB.",
                "location": "Malmö",
                "business": "Klädes- & Konfektionstillverkning",
                "products": "Tillverkar damkappor och driver engroshandel med tyger samt egen minuthandel med kappor och tyger.",
                "contact": {
                    "office": "Stortorget 6, Malmö",
                    "phone": [
                        "72060"
                    ],
                    "telegraph": "Fougstedts, Malmö",
                    "postgiro": "37675"
                },
                "financials": {
                    "capital": "600,000 kr",
                    "employees": {
                        "industriarb": 205
                    },
                    "annual_turnover": "3,000,000 kr"
                },
                "foundation_year": 1857
            },
            {
                "name": "Fougstedts Pälsvarufabrik, Nya AB.",
                "location": "Malmö",
                "products": "Se Nya AB. Fougstedts Pälsvarufabrik, Malmö."
            },
            {
                "name": "Framnäs Väveri AB.",
                "location": "Kinna",
                "business": "Gardinfabrik",
                "products": "Tillverkar gardiner, möbel- och drapertyger av konstsilke och bomull.",
                "contact": {
                    "telegraph": "Framnäs, Kinna",
                    "phone": "10089",
                    "postgiro": "82260"
                },
                "financials": {
                    "capital": "200,000 kr",
                    "employees": {
                        "industriarb": 50
                    },
                    "annual_turnover": "1,000,000 kr"
                },
                "foundation_year": 1900
            },
            {
                "name": "Framnäs Ångsåg, Sävsjöström",
                "products": "Se AB. Brusafors-Hällefors, Silverdalen."
            },
            {
                "name": "Framtiden, Tryckeri AB.",
                "location": "Malmö",
                "products": "Se Tryckeri AB. Framtiden, Malmö."
            },
            {
                "name": "AB. Carl Franckes Läder & Skofabrik",
                "location": "Halmstad",
                "business": "Tillverkning av skor och lädervaror",
                "products": "Tillverkar koläder, kruponger, rand-sydda, agoskodon och genomsydda skodon, samt filt- och skinntofflor.",
                "contact": {
                    "telegraph": "Francke, Halmstad",
                    "phone": [
                        "175",
                        "507",
                        "1875"
                    ],
                    "postgiro": "36254"
                },
                "financials": {
                    "capital": "1,200,000 kr",
                    "employees": {
                        "industriarb": 175
                    },
                    "annual_turnover": "3,000,000 kr"
                },
                "foundation_year": 1888
            },
            {
                "name": "L. E. Franksson, Sågverk & Hyvleri",
                "location": "Ockelbo",
                "products": "Sågade och hyvlade trävaror, listverk, telegrafstolpar samt träkol, gengaskol, trätjära och tjärolja."
            },
            {
                "name": "Erik Franssons Fabriker",
                "location": "Tenhult",
                "business": "Tillverkning av möbler",
                "products": "Tillverkar byråar.",
                "contact": {
                    "phone": [
                        "127",
                        "40"
                    ],
                    "postgiro": "139858"
                },
                "financials": {
                    "employees": {
                        "industriarb": 35
                    },
                    "annual_turnover": "650,000 kr"
                },
                "foundation_year": 1936
            },
            {
                "name": "Franzéns Trävaru AB.",
                "location": "Näsbykulla",
                "products": "Sågade och hyvlade trävaror.",
                "contact": {
                    "phone": "12",
                    "postgiro": "166742"
                },
                "financials": {
                    "capital": "120,000 kr",
                    "employees": {
                        "industriarb": 25
                    },
                    "annual_turnover": "500,000 kr"
                },
                "foundation_year": 1929
            },
            {
                "name": "Fredfors Fabriks AB.",
                "location": "Ulvsunda, Stockholm",
                "business": "Rem- och presenningstillverkning",
                "products": "Tillverkar remmar av läder och bomull, presenningar m.m. Driver också engroshandel med tekniska gummivaror, maskinförnödenheter, brandredskap samt maskiner och verktyg m.m.",
                "contact": {
                    "office": "Ulvsundavägen 180, Stockholm",
                    "phone": [
                        "282500"
                    ],
                    "telegraph": "Fredfors, Stockholm",
                    "postgiro": "57900"
                },
                "financials": {
                    "capital": "100,000 kr",
                    "employees": {
                        "industriarb": 10
                    }
                },
                "foundation_year": 1887,
                "corporation_year": 1934
            }
        ]
    }
}