{
    "original": "HöganäsJeeramile—Högfors\n\nFörsäljn.-chefer: int. Bo Malmström\n(keram. prod.); int. Helge Rickman\n(spe-cialprod.); kamrer Josef Wrahme\n(stenkol).\n\növeringenjörer: vid gruvavd.:\nbergsing. Mauritz Ahlstrand; vid keramiska\navd.: E. Tuschhoff o. Edvin V. Olsson.\n\n(Jfr annons nr 71.)\n\nHöganäskeramik, Holm &amp; Bjurestig,\n\nHöganäs.\n\nTillverkar eldfast hushållsgods samt\nprydnadssaker av keramik.\n\nTelefon: 401. Postgiro: 320953. —\nArb.-antal: 45. Tillv.-värde pr år: 40,000\nkr. — Firman etabl. 1930.\n\nÄgare o. chefer: herr Sture Holm o.\nherr Äke Bjurestig.\n\nHögbergs Kemisk-Tekniska Industri,\n\nStockholm.\n\nTillverkar förbandsartiklar,\nfarmaceu-tiska preparat, klister m. m. Firman\ndriver även engroshandel med kemiska\nprodukter av främmande fabrikat.\nVarumärken: Z-plast, Z-gasbinda m. fl.\n\nKontor: Flemingg. 15. Telefon: 510962\no. 533500. — Antal industriarb.: 32.\nTillv.-värde pr år: 825,000 kr. — Firman\netabl. 1938.\n\nÄgare o. chef: disp. H. J. Johnen.\n\nChefskemiker: dr Bruno Lövenberg.\n\n*AB. Högberg &amp; Hultners\nSnickerifabrik, Mjölby:\n\nTillverkar fodral till grammofonlådor\noch -skåp, radiolådor och -skåp,\nsymaskinsbord, urfoder samt\nkompletterings-möbler.\n\nTelegr.-adr.: Hultner, Mjölby. Telefon:\n49 o. 879. Postgiro: 11686. — Akt.-kap.:\n100,000 kr. Antal industriarb.: 150. —\nFirman etabl. 1901, bolag 1932.\n\nStyrelse: disp. Einar Wissing (ordf.),\ndir. Axel Hultner, herr Gösta Hultner.\n\nVerkst. dir.: Axel Hultner.\n\nDisp.: Einar Wissing.\n\nKontorschef: Gillis Wissing.\n\nHögboholms Mek. Verkstad,\n\nTorpsbruk.\n\nTillverkar bänksvarvar, pressade\nmassartiklar, chuckar samt dejsar och stål för\ntoftmaskiner vid verkstad i Torpsbruk\n(Kronob. l.).\n\nTelefon: 7. Postgiro: 274846. —\nArb.-antal: 10. Tillv-.värde pr år: 55,000 kr. —\nFirman etabl. 1941.\n\nÄgare o. chef: fabr. Yngve Cornfors.\n\n\"Högfors AB., Högforsbruk.\n\nJärnmalmsgruvor och sintringsverk,\n\nmasugn samt mek. verkstad och gjuteri\nvid Högfors bruk (Örebro l.). Tillverkar\ntackjärn och sinter samt\nkupolugnsgjut-gods.\n\nTelegr.-adr.: Högforsab, Kopparberg.\nTelefon: Högforsbruk 11 o. 23. Postgiro:\n83230.\n\nAkt.-kap.: 400.000 kr. Antal\nindustriarb.: 100. Prod.-värde pr år: 2,500,000 kr.\n— Bruket anlagt på 1760-talet, nuv.\nbolag grundat 1897.\n\nStyrelse: disp. Karl Hedin, herr Lars\nHedin, disp. Olof Hedin, adv. Helmer\nLindh.\nDisp.: Olof Hedin.\n\nHögfors Cjuteri &amp; Mek. Verkstad,\n\nHögforsbruk.\n\nSe AB. Walldén-Verken, Köping.\n\n\"Högfors och Persbo AB.,\n\nStockholm.\n\nMasugnar och gjuteri vid Högfors\n(Västmanl. l.). Tillverkar tackjärn och\ngjutgods. Bolaget idkar jämväl jordbruk\noch skogshantering.\n\nHuvudkontor och ensamförsälj.: A.\nJohnson &amp; Co., Stockholm, Stureplan 3.\nTelefon: »Johnsons». Brukskontor:\nHögfors. Telegr.-adr.: Högfors, Norberg.\nTelefon: Norberg 26.\n\nAkt.-kap.: 1,000,000 kr. Antal\nindustriarb.: 200.\n\nBolaget, grundat 1880, äges av Avesta\nJernverks AB.\n\nStyrelse: generalkonsul Axel Ax:son\nJohnson (ordf.), dir. Vilhelm Björkman,\ning. Filip Eriksson, disp. Walfrid\nEriksson, bergsing. Axel Ax:son Johnson J:or.\n\nVerkst. dir.: Axel Ax:son Johnson.\n\nPlatschef: ing. H. Montgomery.\n\nAB. Högfors Träsliperi,\n\nHäggenås.\n\nTräsliperi vid Högfors, Häggenås\n(Jämtl. l.). Tillverkar torr mek. trämassa.\n\nTelefon: Häggenås 6, 52 o. 73. —\nAkt.-kap.: 150,000 kr. Antal industriarb.: 45.\nÅrstillv.: 30,000 ton mek. trämassa\n(våt-beräkn.). — Bolaget grundat 1935.\n\nStyrelse: dir. G. Bertil örn (ordf.),\nciviling. frih. Tage Fleetwood, ing. Erik\nHedborg.\n\nVerkst. dir.: G. B. Örn.\n\nKamrer: Olof Hagson.",
    "structured": {
        "1": {
            "name": "Höganäskeramik, Holm & Bjurestig",
            "location": "Höganäs",
            "business": "Tillverkar eldfast hushållsgods samt prydnadssaker av keramik",
            "contact": {
                "phone": [
                    "401"
                ],
                "postgiro": "320953"
            },
            "financials": {
                "employees": {
                    "Arb.-antal": 45
                },
                "annual_turnover": "40,000 kr",
                "annual_production_value": "40,000 kr"
            },
            "foundation_year": 1930,
            "owners": [
                "herr Sture Holm",
                "herr Äke Bjurestig"
            ]
        },
        "2": {
            "name": "Högbergs Kemisk-Tekniska Industri",
            "location": "Stockholm",
            "business": "Tillverkar förbandsartiklar, farmaceutiska preparat, klister m. m.",
            "contact": {
                "office": "Flemingg. 15",
                "phone": [
                    "510962",
                    "533500"
                ],
                "postgiro": "Not provided"
            },
            "financials": {
                "employees": {
                    "Antal industriarb.": 32
                },
                "annual_turnover": "825,000 kr"
            },
            "foundation_year": 1938,
            "owner": "disp. H. J. Johnen",
            "board": [
                "disp. H. J. Johnen (chef)",
                "dr Bruno Lövenberg (chefer"
            ]
        },
        "3": {
            "name": "AB. Högberg & Hultners Snickerifabrik",
            "location": "Mjölby",
            "business": "Tillverkar fodral till grammofonlådor och -skåp, radiolådor och -skåp, symaskinsbord, urfoder samt kompletteringsmöbler.",
            "contact": {
                "telegraph": "Hultner, Mjölby",
                "phone": [
                    "49",
                    "879"
                ],
                "postgiro": "11686"
            },
            "financials": {
                "capital": "100,000 kr",
                "employees": {
                    "Antal industriarb.": 150
                }
            },
            "foundation_year": 1901,
            "corporation_year": 1932,
            "owners": [
                "Einar Wissing",
                "Axel Hultner",
                "Gösta Hultner"
            ],
            "director": "Axel Hultner",
            "manager": "Gillis Wissing"
        },
        "4": {
            "name": "Högboholms Mek. Verkstad",
            "location": "Torpsbruk",
            "business": "Tillverkar bänksvarvar, pressade massartiklar, chuckar samt dejsar och stål för toftmaskiner vid verkstad i Torpsbruk (Kronob. l.).",
            "contact": {
                "phone": [
                    "7"
                ],
                "postgiro": "274846"
            },
            "financials": {
                "employees": {
                    "Arb.-antal": 10
                },
                "annual_production_value": "55,000 kr"
            },
            "foundation_year": 1941,
            "owner": "fabr. Yngve Cornfors",
            "managing_director": "Yngve Cornfors"
        },
        "5": {
            "name": "Högfors AB., Högforsbruk",
            "business": "Järnmalmsgruvor och sintringsverk, masugn samt mek. verkstad och gjuteri vid Högfors bruk (Örebro l.). Tillverkar tackjärn och sinter samt kupolugnsgjutgods.",
            "contact": {
                "telegraph": "Högforsab, Kopparberg",
                "phone": [
                    "Högforsbruk 11",
                    "Högforsbruk 23"
                ],
                "postgiro": "83230"
            },
            "financials": {
                "capital": "400,000 kr",
                "employees": {
                    "Antal industriarb.": 100
                },
                "annual_turnover": "2,500,000 kr"
            },
            "corporation_year": 1897,
            "board": [
                "disp. Karl Hedin",
                "Lars Hedin",
                "Olof Hedin",
                "adv. Helmer Lindh"
            ]
        },
        "6": {
            "name": "Högfors Cjuteri & Mek. Verkstad",
            "location": "Högforsbruk",
            "business": "See AB. Walldén-Verken, Köping",
            "contact": {
                "telegraph": "Not provided",
                "phone": [
                    "Not provided"
                ]
            },
            "original_name": "AB. Walldén-Verken, Köping"
        },
        "7": {
            "name": "Högfors och Persbo AB.",
            "location": "Stockholm",
            "business": "Masugnar och gjuteri vid Högfors (Västmanl. l.). Tillverkar tackjärn och gjutgods. Bolaget idkar jämväl jordbruk och skogshantering.",
            "contact": {
                "office": "Stureplan 3",
                "phone": [
                    "Not provided"
                ],
                "postgiro": "Not provided"
            },
            "financials": {
                "capital": "1,000,000 kr",
                "employees": {
                    "Antal industriarb.": 200
                }
            },
            "board": [
                "generalkonsul Axel Ax:son Johnson",
                "Vilhelm Björkman",
                "Filip Eriksson",
                "Walfrid Eriksson",
                "Axel Ax:son Johnson J:or"
            ]
        },
        "8": {
            "name": "AB. Högfors Träsliperi",
            "location": "Häggenås",
            "business": "Träsliperi vid Högfors, Häggenås (Jämtl. l.). Tillverkar torr mek. trämassa.",
            "contact": {
                "phone": [
                    "Häggenås 6",
                    "Häggenås 52",
                    "Häggenås 73"
                ],
                "postgiro": "Not provided"
            },
            "financials": {
                "capital": "150,000 kr",
                "employees": {
                    "Antal industriarb.": 45
                }
            },
            "board": [
                "dir. G. Bertil örn",
                "Tage Fleetwood",
                "Erik Hedborg"
            ]
        }
    }
}