{
    "original": "Gröndal—Guldvaru\n\nTelegr.-adr.: Bruket, Bergsjö. Telefon:\n28 o. 49. Postgiro: 30389.\nKonsignations-lager i Stockholm: G. M. Flink &amp; Co.\nAB., N. Mälarstrand 28, telefon: 520910.\n\nAkt.-kap.: 56,200 kr. Antal\nindustriarb.: 35. Tillv.-värde pr år: 400,000 kr.\n— Bolaget grundat 1902.\n\nStyrelse: grossh. Olof Eriksson (ordf.),\nkontorschef Axel Bäckström, verkm. A.\nWennerström.\n\nVerkst. dir.: Olof Eriksson.\n\n* Gröndals Grufve AB., K ärrgruvan.\n\nSe Norbergs Grufförvaltning,\nKärrgruvan.\n\n*Crönkwists Mek. Verkstad,\n\nKatrineholm.\n\nSe AB. Svenska Kullagerfabriken,\nKatrineholmsverken, Katrineholm.\n\n*Crönskogs Bryggeri, Nybro.\n\nSe Bryggeriet Grönskog, Nybro.\n\n*Crönwalls Bryggeri, Stockholm.\n\nSe AB. Stockholms Bryggerier,\nStockholm.\n\nAB. Wilh. Grönvalls Läderfabrik,\n\nÄngelholm.\n\nTillverkar sulläder och bindsulläder,\ndiamantläder, kruponger, vändläder,\nsmorläder, plattläder, toffel- och\nsandalläder, portföljläder samt handskläder och\nspalt.\n\nTelegr.-adr.: Grönvall, Ängelholm.\nTelefon: »Grönvalls Läderfabrik». Postgiro:\n73550.\n\nAkt.-kap.: 3,000,000 kr. Antal\nindustriarb.: 200. — Firman etabl. 1858, nuv.\nbolag grundat 1911.\n\nStyrelse: dir. Sture Grönvall (ordf.),\ndr Herman Grönvall (v. ordf.), dir. I.\nEkblom.\n\nVerkst. dir.: Sture Grönvall.\n\nDisp.: Gösta Grönvall.\n\n*Cui1laumes Verkstäder, Kopparberg.\n\nSe AB. Berglöfs Verkstäder,\nKopparberg.\n\n*Cu1dl1stfabriken, AB. Svenska,\n\nKarlstad.\n\nSe AB. Svenska Guldlistfabriken,\nKarlstad.\n\n*\tGuldsmeds AB. i Stockholm, C. A. B.,\n\nStockholm.\n\nSilver-, nysilver-, tenn- och\nbronsvaru-fabrik med smält- och valsverk, mek.\nverkstad samt verkstäder för pressning,\nslip-ning, försilvring, förgyllning etc.\n\nTillverkar bords-, kyrk-, prydnads-,\nskriv- och rökbordsartiklar, spec.\nmatsilver av silver och nysilver; anoder,\nmot-ståndstråd, stålstansar och stämplar,\nskyltar och plaketter m. m. samt utför\nförgyllning, försilvring, gravering, ciselering\noch plätering t. ex. guld på silver, silver\npå koppar, silver på järn etc. samt\nkontaktmaterial.\n\nKontor: Svedenborgsg. 50. Telegr.-adr.:\nGabis, Stockholm. Telefon: »G. A. B.».\nPostgiro: 3383.\n\nAkt.-kap.: 2,000,000 kr. Antal\nanställda: 350, varav 140 industriarb.\nTillv.-värde pr år: 5,000,000 kr. — Bolaget\ngrundat 1867.\n\nStyrelse: jur. dr Axel Roos (ordf.),\nkamrer Gert Arnold, fröken G. Holm,\nfru G. Nyström, dir. Carl-Sigvard Roos,\nfru G. Roos.\n\nVerkst. dir.: A. Roos.\n\nV. verkst. dir.: Carl-Sigvard Roos.\n\nKamrer: G. Arnold.\n\n*Culdsmedshytte AB.,\n\nGuldsmedshyttan.\n\nJärnverk med gruvor, anriknings- och\nsintringsverk, masugnar, gjuteri och mek.\nverkstad, valssvarvningsverkstad samt\nsågverk och elektr. vattenkraftstation vid\nGuldsmedshyttan (Örebro l.).\n\nBryter och anrikar järnmalm,\ntillverkar järnmalmsslig och sinter, tackjärn,\ngjutgods, slitgods, valsverks- och\nkvarnvalsar, valsar för gummi- och\npappersfabriker, plåtarbeten, nitade och svetsade\njärnkonstruktioner samt sågade trävaror.\n\nHuvudkontor: Guldsmedshyttan.\nTelegr.-adr.: Guldsmedshyttan, Lindesberg.\nTelefon: Guldsmedshyttan 44. Postgiro:\n6910.\n\nAkt.-kap.: 600,000 kr. Antal\nindustriarb.: 400. — Bolaget grundat 1868.\n\nStyrelse: dir. Bertil Ahrenbeck (ordf.),\ndisp. Sven Ekelund, adv. Thure Essén.\n\nVerkst. dir. o. disp.: Sven Ekelund.\n\n(Jfr annons nr 34.)\n\n*\tGuldvaru AB. C. Dahlgren &amp; Co.,\n\nMalmö.\n\nTillverkar alla slags smycken i guld,\nplatina och silver.\n\nHuvudkontor: Malmö, Engelbrektsg. 7.\nTelegr.-adr.: Guldvarubolaget, Malmö.\nTelefon: 24195. Postgiro: 14094.\nAvd.-kontor: Stockholm, Norrmalmstorg 1 (Ci-",
    "structured": {
        "1": {
            "name": "Gröndal—Guldvaru",
            "location": "Bruket, Bergsjö",
            "business": "Guldvaror",
            "contact": {
                "telegraph": "Bruket, Bergsjö",
                "phone": [
                    "28",
                    "49"
                ],
                "postgiro": "30389"
            },
            "financials": {
                "capital": "56,200 kr",
                "employees": {
                    "industriarb": 35
                },
                "annual_turnover": "400,000 kr"
            },
            "foundation_year": 1902,
            "board": [
                {
                    "name": "grossh. Olof Eriksson",
                    "role": "ordf."
                },
                {
                    "name": "kontorschef Axel Bäckström",
                    "role": null
                },
                {
                    "name": "verkm. A. Wennerström",
                    "role": null
                }
            ],
            "director": "Olof Eriksson"
        },
        "2": {
            "name": "AB. Wilh. Grönvalls Läderfabrik",
            "location": "Ängelholm",
            "business": "Tillverkar sulläder och bindsulläder, diamantläder, kruponger, vändläder, smorläder, plattläder, toffel- och sandalläder, portföljläder samt handskläder och spalt.",
            "contact": {
                "telegraph": "Grönvall, Ängelholm",
                "phone": "Grönvalls Läderfabrik",
                "postgiro": "73550"
            },
            "financials": {
                "capital": "3,000,000 kr",
                "employees": {
                    "industriarb": 200
                }
            },
            "foundation_year": 1858,
            "current_name_year": 1911,
            "board": [
                {
                    "name": "dir. Sture Grönvall",
                    "role": "ordf."
                },
                {
                    "name": "dr Herman Grönvall",
                    "role": "v. ordf."
                },
                {
                    "name": "dir. I. Ekblom",
                    "role": null
                }
            ],
            "director": "Sture Grönvall"
        },
        "3": {
            "name": "Guldsmeds AB. i Stockholm, C. A. B.",
            "location": "Stockholm",
            "business": "Silver-, nysilver-, tenn- och bronsvaru-fabrik",
            "contact": {
                "office": "Svedenborgsg. 50",
                "telegraph": "Gabis, Stockholm",
                "phone": "G. A. B.",
                "postgiro": "3383"
            },
            "financials": {
                "capital": "2,000,000 kr",
                "employees": {
                    "total": 350,
                    "industriarb": 140
                },
                "annual_turnover": "5,000,000 kr"
            },
            "foundation_year": 1867,
            "board": [
                {
                    "name": "jur. dr Axel Roos",
                    "role": "ordf."
                },
                {
                    "name": "kamrer Gert Arnold",
                    "role": null
                },
                {
                    "name": "fröken G. Holm",
                    "role": null
                },
                {
                    "name": "fru G. Nyström",
                    "role": null
                },
                {
                    "name": "dir. Carl-Sigvard Roos",
                    "role": null
                }
            ],
            "director": "A. Roos"
        },
        "4": {
            "name": "Guldvaru AB. C. Dahlgren & Co.",
            "location": "Malmö",
            "business": "Tillverkar alla slags smycken i guld, platina och silver",
            "contact": {
                "telegraph": "Guldvarubolaget, Malmö",
                "phone": "24195",
                "postgiro": "14094"
            },
            "foundation_year": null
        }
    }
}