{
    "original": "Marabou—Margarin\n\nsamt såsom specialtillverkning\ngängmaskiner och verktyg. Varumärke: »Manus».\n\nTelegr.-adr. o. telefon: Manus,\nNorrköping. Postgiro: 26492.\n\nAkt.-kap.: 311,500 kr. Antal\nindustriarb.: 200. Tillv.-värde pr år: 3,000,000 kr.\n— Bolaget grundat 1911.\n\nStyrelse: adv. Axel Hemmar (ordf.),\nbankdir. Alb. Änder, lantbrukare Bertil\nÄnder, disp. Elis Ellison, apot. Lennart\nEllison.\n\nVerkst. dir.: Elis Ellison.\n\nV. verkst. dir.: Lennart Ellison.\n\n*Marabou Chokladfabrik,\n\nSundbyberg.\n\nSe AB. Chokladfabriken Marabou,\nSundbyberg.\n\n*Marbodals Snickerifabrik AB.,\n\nTidaholm.\n\nTillverkar köksinredningar.\n\nTelefon: 410 o. 710. — Akt.-kap.:\n40,000 kr. Antal industriarb.: 50.\nTillv.-värde pr år: 800,000 kr. — Firman etabl.\n1933, bolag 1938.\n\nStyrelse o. chefer: disp. John Holmvik,\nverkm. Bror Holmvik, verkm. Ernst\nHolmvik, kamrer Ivar Holmvik,\nmaskin-förm. Gunnar Holmvik.\n\nAB. Marboväveriet, Fritsla.\nSe AB. Fritsla Gardinfabrik, Fritsla.\n\n*Marattifabriken, AB. Svenska,\n\nStockholm.\n\nSe AB. Svenska Marattifabriken,\nStockholm.\n\n*Marbäcks Fabriks AB., Marbäck.\n\nPappfabrik med träsliperi vid Marbäck\n(Hallands l.). Tillverkar glättad, oglättad\noch mönstrad brun papp, färgad kartong\nsamt skoindustripapp ävensom mek.\nträmassa för eget behov.\n\nTelegr.-adr.: Leatherboard, Halmstad.\nTelefon: Halmstad 420 o. 320. Postgiro:\n34776.\n\nAkt.-kap.: 150,000 kr. Antal\nindustriarb.: 50. Årstillv.: 2,000 ton papp. —\nBolaget grundat 1911.\n\nStyrelse: disp. Håkan Böhn, övering.\nNils Enock Nilsson.\n\nVerkst. dir.: N. E. Nilsson.\n\n. Kontorschef: Erik H. Eriksson.\n\nIsaac Marcus’ Boktryckeri AB.,\n\nStockholm.\n\nUtför boktryck och bokbinderiarbeten.\n\nKontor: Tryckerigatan 2. — Firman,\ngrundad 1849, bolag 1873, är ansluten till\nAB. P. A. Norstedt &amp; Söner. (Se detta\nbolag.)\n\nVerkst. dir.: fd. hovrättsrådet J.\nNordenfalk.\n\nDisp.: Napoleon Holm.\n\nS. Marcussons Transportvagnfabrik,\n\nÄngelholm.\n\nMek. verkstad. Tillverkar\ntransportanordningar, spec. skyffelvagnar.\nVarumärke: »Marco».\n\nTelegr.-adr. o. telefon: Marco,\nÄngelholm. Postgiro: 82715. — Antal\nindustriarb.: 50. Tillv.-värde pr år: 1,500,000 kr.\n\n—\tFirman etabl. 1936.\n\nÄgare o. chef: fabr. Sven Marcusson.\n\nFörsäljn.-chef; Eric Franck.\n\nMargarin AB. Alba, Dalby.\n\nSe Alba Fabrikers AB., Dalby.\n\n*Margarin AB. Svea, Kalmar.\n\nOljefabrik, raffinaderi och\nmargarin-fabrik. Tillverkar raffinerade och\ntekniska oljor såsom kokosolja, jordnötsolja,\nsojaolja, cottonolja m. fl., margarin,\n\nkonstister, kokossmör, kokosflott, speciella\nfettämnen för kexfabriker, choklad- och\nkonfektfabriker samt specialkvaliteter i\nkokos för tvålindustrien.\n\nTelefon: »Margarinbolaget». Postgiro:\n6094. Margarinförsäljningen sker genom\nMargarinbolaget AB. (se detta bolag).\n\nAkt.-kap.: 2,000,000 kr. Antal\nindustriarb.: 135. Tillv.-värde pr år: 20,000,000\nkr. -— Bolaget grundat 1906.\n\nStyrelse: adv. Dick Bergman (ordf.),\nkonsul Gösta J eansson, dir. Ragnar\nJeansson, dir. René de Vries.\n\nVerkst. dir.: Ragnar Jeansson.\n\nDisp.: Gösta Jeansson.\n\n^Margarin AB. Zenith, Malmö.\n\nMargarinfabrik. Tillverkar margarin,\nkonstister och kokossmör.\n\nKontor: Sallerupsvägen. Telegr.-adr.:\nZenith, Malmö. Telefon:\n»Margarinbolaget». Postgiro: 38075. Försäljningen sker\ngenom Margarinbolaget AB. (se detta\nbolag).\n\nAkt.-kap.: 4,000,000 kr. Antal\nindustriarb.: 50. Tillv.-värde pr år: 7,000,000 kr.\n\n—\tBolaget grundat 1898.",
    "structured": {
        "1": {
            "name": "Marabou—Margarin",
            "location": "Norrköping",
            "business": "särskild tillverkning gängmaskiner och verktyg",
            "contact": {
                "telegraph": "Manus",
                "phone": [
                    "Telefon: Manus"
                ],
                "postgiro": "26492"
            },
            "financials": {
                "capital": "311,500 kr",
                "employees": {
                    "industriarb": 200
                },
                "annual_turnover": "3,000,000 kr"
            },
            "foundation_year": 1911,
            "board": [
                {
                    "name": "adv. Axel Hemmar",
                    "role": "ordf."
                },
                {
                    "name": "bankdir. Alb. Änder",
                    "role": null
                },
                {
                    "name": "lantbrukare Bertil Änder",
                    "role": null
                },
                {
                    "name": "disp. Elis Ellison",
                    "role": null
                },
                {
                    "name": "apot. Lennart Ellison",
                    "role": null
                }
            ],
            "director": "Elis Ellison",
            "managing_director": "Lennart Ellison"
        },
        "2": {
            "name": "Marbodals Snickerifabrik AB.",
            "location": "Tidaholm",
            "business": "Tillverkar köksinredningar",
            "contact": {
                "phone": [
                    "Telefon: 410",
                    "Telefon: 710"
                ],
                "postgiro": null
            },
            "financials": {
                "capital": "40,000 kr",
                "employees": {
                    "industriarb": 50
                },
                "annual_turnover": "800,000 kr"
            },
            "foundation_year": 1933,
            "board": [
                {
                    "name": "disp. John Holmvik",
                    "role": null
                },
                {
                    "name": "verkm. Bror Holmvik",
                    "role": null
                },
                {
                    "name": "verkm. Ernst Holmvik",
                    "role": null
                },
                {
                    "name": "kamrer Ivar Holmvik",
                    "role": null
                },
                {
                    "name": "maskin-förm. Gunnar Holmvik",
                    "role": null
                }
            ]
        },
        "3": {
            "name": "Marbäcks Fabriks AB.",
            "location": "Marbäck",
            "business": "Pappfabrik med träsliperi",
            "contact": {
                "telegraph": "Leatherboard, Halmstad",
                "phone": [
                    "Telefon: Halmstad 420",
                    "Telefon: 320"
                ],
                "postgiro": "34776"
            },
            "financials": {
                "capital": "150,000 kr",
                "employees": {
                    "industriarb": 50
                },
                "annual_production_value": "2,000 ton papp"
            },
            "foundation_year": 1911,
            "board": [
                {
                    "name": "disp. Håkan Böhn",
                    "role": null
                },
                {
                    "name": "övering. Nils Enock Nilsson",
                    "role": null
                }
            ],
            "director": "N. E. Nilsson",
            "manager": "Erik H. Eriksson"
        },
        "4": {
            "name": "Isaac Marcus’ Boktryckeri AB.",
            "location": "Stockholm",
            "business": "Utför boktryck och bokbinderiarbeten",
            "contact": {
                "office": "Tryckerigatan 2"
            },
            "foundation_year": 1849,
            "corporation_year": 1873,
            "director": "fd. hovrättsrådet J. Nordenfalk",
            "manager": "Napoleon Holm"
        },
        "5": {
            "name": "S. Marcussons Transportvagnfabrik",
            "location": "Ängelholm",
            "business": "Mek. verkstad. Tillverkar transportanordningar",
            "contact": {
                "telegraph": "Marco, Ängelholm",
                "phone": [
                    "Telefon: Marco"
                ],
                "postgiro": "82715"
            },
            "financials": {
                "employees": {
                    "industriarb": 50
                },
                "annual_production_value": "1,500,000 kr"
            },
            "foundation_year": 1936,
            "owners": [
                "fabr. Sven Marcusson"
            ],
            "sales_manager": "Eric Franck"
        },
        "6": {
            "name": "Margarin AB. Svea",
            "location": "Kalmar",
            "business": "Oljefabrik, raffinaderi och margarin-fabrik",
            "contact": {
                "phone": [
                    "Telefon: \"Margarinbolaget\""
                ],
                "postgiro": "6094"
            },
            "financials": {
                "capital": "2,000,000 kr",
                "employees": {
                    "industriarb": 135
                },
                "annual_turnover": "20,000,000 kr"
            },
            "foundation_year": 1906,
            "board": [
                {
                    "name": "adv. Dick Bergman",
                    "role": "ordf."
                },
                {
                    "name": "konsul Gösta J eansson",
                    "role": null
                },
                {
                    "name": "dir. Ragnar Jeansson",
                    "role": null
                },
                {
                    "name": "dir. René de Vries",
                    "role": null
                }
            ],
            "director": "Ragnar Jeansson",
            "manager": "Gösta Jeansson"
        },
        "7": {
            "name": "Margarin AB. Zenith",
            "location": "Malmö",
            "business": "Margarinfabrik",
            "contact": {
                "office": "Sallerupsvägen",
                "telegraph": "Zenith, Malmö",
                "phone": [
                    "Telefon: \"Margarinbolaget\""
                ],
                "postgiro": "38075"
            },
            "financials": {
                "capital": "4,000,000 kr",
                "employees": {
                    "industriarb": 50
                },
                "annual_turnover": "7,000,000 kr"
            },
            "foundation_year": 1898
        }
    }
}