{
    "original": "Holm—Holten\n\n*AB. Holms Skeppsvarv, Båå.\n\nBygger träfartyg för fraktfart,\nfiskefartyg och andra båtar vid varv i Råå,\nHälsingborg.\n\nTelefon: Hälsingborg 90140. Postgiro:\n13951. — Akt.-kap.: 125,000 kr. Antal\nindustriarb.: 20. Tillv.-värde pr år: 200,000\nkr. — Firman etabl. 1899, bolag 1902,\nnuv. namn 1920.\n\nStyrelse: konsul Anton Hof vendahl\n(ordf.), järnhandl. John Holm, disp. Åke\nHolm.\n\nVerkst. dir.: Åke Holm.\n\n*J. A. Holms AB., Halmstad.\n\nSkofabrik. Tillverkar ago damskodon.\nTelefon: 1327. Postgiro: 75675.\nAkt.-kap.: 30,200 kr. Antal\nindustriarb.: 35. Tillv.-värde pr år: 450,000 kr.\n\n—\tFirman etabl. 1926 under namn AB.\nPalmqvist &amp; Holm, nuv. namn 1942.\n\nStyrelse o. verkst. dir.: fabr. John A.\nHolm.\n\n*Karl Holm Möbelfabrik AB.,\n\nVirserum.\n\nTillverkar bäddmöbler, speciellt\nbäddsoffor och dyschateller vid möbelfabrik i\nVirserum samt stolar vid fabrik i Målilla\n(båda i Kalmar l.).\n\nKontor: Virserum. Telefon: 94 o. 314.\nPostgiro: 163503. — Akt.-kap.: 55,000 kr.\nAntal industriarb.: 70. Tillv.-värde pr\når: 900,000 kr. — Firman etabl. 1918,\nbolag 1945.\n\nStyrelse: verkm. Althon Holm, disp.\nHelmer Holm, fabr. Karl Holm.\nVerkst. dir.: Karl Holm.\nDisp.: Helmer Holm.\nKamrer: David Ingvarsson.\nPlatschef i Målilla: Althon Holm.\n\n*AB. Tore Holms Yachtvarv,\n\nGamleby.\n\nBåtvarv i Gamleby (Kalmar l.).\nTillverkar och reparerar segel- och motoryachter,\nfiskefartyg m. m.\n\nTelefon: 140. Postgiro: 266345.\nAkt.-kap.: 40,000 kr. Antal\nindustriarb.: 27. Tillv.-värde pr år: 400,000 kr.\n\n—\tVarvet anlagt 1905, bolaget grundat\n1936.\n\nStyrelse: snickare Severin Carlsson,\nträvaruhandl. Helge Ericsson, civiling.\nTore Holm, bankdir. Herrman\nNachman-ison.\n\nVerkst. dir.: Tore Holm.\n\n\"Holmsunds AB., Holmsund.\n\nSågverk och hyvleri samt\nträföräd-lingsfabriker i Holmsund, sågverk,\nsnickeri- och trähusfabrik i Sandvik,\nsulfatfabrik i Obbola samt elektr.\nvattenkraftstation vid Baggböle (samtL i Västerb. l.).\n\nTillverkar: i Holmsund: sågade och\nhyvlade trävaror, lamellgolv, -dörrar och\n-plattor, parkettstav samt svarvat och\nplanskuret faner; i Sandvik:\nmonteringsfärdiga trähus och byggnadssnickerier; i\nObbola: sulfatcellulosa, terpentin och\nflytande harts.\n\nHuvudkontor: Holmsund. Telegr.-adr.:\nHolmos, Holmsund. Telefon: »Holmsunds\nbolag». Postgiro: 64067. Fabr.-kontor:\nObbola. Skogsförvaltn. i Holmsund med\ndistriktskontor i Lycksele, Vindeln och\nGargnäs.\n\nEnsamförsälj.: för cellulosa, terpentin\no. harts: Svenska Cellulosa AB.,\nStockholm, V. Trädgårdsg. 15, telefon:\n»Cellulosabolaget»; för trähus: AB. Svenska\nTrähus, Stockholm, Birger Jarlsg. 27,\ntelefon: »Svenska Trähus»; för\nlamellträ-produkter: Lamellgolv AB., Stockholm,\nKungsg. 18, telefon: 233465; övriga\nprodukter säljas genom huvudkontoret.\n\nAkt.-kap.: 6,000.000 kr. Antal\nindustriarb.: 1,100. Årstillv.: 16,000 stds sågade\nträvaror, varav 3.000 stds hyvlade, 30,000\nton sulfatcellulosa.\n\nBolaget grundat 1896. Aktierna i\nbolaget innehavas av Svenska Cellulosa AB.\n\nStyrelse: dir. Torsten Hérnod (ordf.),\ndisp. Ax. Enström, dir. K. Erik Nyberg,\ndir. Gust. J. Sahlin, bankdir. Per Wåhlin.\n\nVerkst. dir.: Ax. Enström.\n\nHols’ Skinnindustri AB., Malung.\n\nTillverkar handskar och\nskinnbeklädnader vid fabrik i Malung (Kopparb. l.).\n\nTelefon: 330. Postgiro: 173381. —\nAkt.-kap.: 50,000 kr. Antal industriarb.:\n27. — Bolaget grundat 1941.\n\nStyrelse o. verkst. dir.: fabr. Johan\nE:son Hols.\n\nCarl Holten AB., Hässleholm.\n\nHerrkonfektionsfabrik.\tTillverkar\n\nfrack-, smoking- och kavajkostymer,\nuniformer samt ulstrar, paletåer och\ntrench-coats.\n\nTelefon: 950 o. 951. Postgiro: 38910.\n— Akt.-kap.: 80,000 kr. Antal\nindustriarb.: 75. — Bolaget grundat 1939.\n\nStyrelse o. verkst. dir.: Carl G.\nHolten-man.\n\n230*",
    "structured": {
        "firms": [
            {
                "name": "AB. Holms Skeppsvarv",
                "location": "Råå, Hälsingborg",
                "business": "Bygger träfartyg för fraktfart, fiskefartyg och andra båtar",
                "contact": {
                    "office": "Hälsingborg",
                    "phone": [
                        "90140"
                    ],
                    "postgiro": "13951"
                },
                "financials": {
                    "capital": "125,000 kr",
                    "employees": {
                        "industriarb": 20
                    },
                    "annual_turnover": "200,000 kr",
                    "annual_production_value": "200,000 kr"
                },
                "foundation_year": 1899,
                "corporation_year": 1902,
                "current_name_year": 1920,
                "board": [
                    {
                        "name": "konsul Anton Hof vendahl",
                        "role": "ordf."
                    },
                    {
                        "name": "järnhandl. John Holm",
                        "role": "disp."
                    },
                    {
                        "name": "disp. Åke Holm",
                        "role": "disp."
                    }
                ],
                "director": "Åke Holm"
            },
            {
                "name": "J. A. Holms AB.",
                "location": "Halmstad",
                "business": "Skofabrik",
                "contact": {
                    "office": "Halmstad",
                    "phone": [
                        "1327"
                    ],
                    "postgiro": "75675"
                },
                "financials": {
                    "capital": "30,200 kr",
                    "employees": {
                        "industriarb": 35
                    },
                    "annual_turnover": "450,000 kr"
                },
                "foundation_year": 1926,
                "current_name_year": 1942,
                "board": [
                    {
                        "name": "fabr. John A. Holm",
                        "role": "Styrelse o. verkst. dir."
                    }
                ]
            },
            {
                "name": "Karl Holm Möbelfabrik AB.",
                "location": "Virserum",
                "business": "Tillverkar bäddmöbler, speciellt bäddsoffor och dyschateller",
                "products": "stolar vid fabrik i Målilla (båda i Kalmar l.)",
                "contact": {
                    "office": "Virserum",
                    "phone": [
                        "94",
                        "314"
                    ],
                    "postgiro": "163503"
                },
                "financials": {
                    "capital": "55,000 kr",
                    "employees": {
                        "industriarb": 70
                    },
                    "annual_turnover": "900,000 kr"
                },
                "foundation_year": 1918,
                "corporation_year": 1945,
                "board": [
                    {
                        "name": "verkm. Althon Holm",
                        "role": "Styrelse"
                    },
                    {
                        "name": "disp. Helmer Holm",
                        "role": "Disp."
                    },
                    {
                        "name": "fabr. Karl Holm",
                        "role": "Styrelse"
                    }
                ],
                "director": "Karl Holm"
            },
            {
                "name": "AB. Tore Holms Yachtvarv",
                "location": "Gamleby",
                "business": "Båtvarv",
                "products": "Tillverkar och reparerar segel- och motoryachter, fiskefartyg m. m.",
                "contact": {
                    "office": "Gamleby",
                    "phone": [
                        "140"
                    ],
                    "postgiro": "266345"
                },
                "financials": {
                    "capital": "40,000 kr",
                    "employees": {
                        "industriarb": 27
                    },
                    "annual_turnover": "400,000 kr"
                },
                "foundation_year": 1905,
                "corporation_year": 1936,
                "board": [
                    {
                        "name": "snickare Severin Carlsson",
                        "role": "Styrelse"
                    },
                    {
                        "name": "trävaruhandl. Helge Ericsson",
                        "role": "Styrelse"
                    },
                    {
                        "name": "civiling. Tore Holm",
                        "role": "Styrelse"
                    }
                ],
                "director": "Tore Holm"
            },
            {
                "name": "Holmsunds AB.",
                "location": "Holmsund",
                "business": "Sågverk och hyvleri samt träförädlingsfabriker",
                "products": "Tillverkar: i Holmsund: sågade och hyvlade trävaror, lamellgolv, -dörrar och -plattor, parkettstav samt svarvat och planskuret faner; i Sandvik: monteringsfärdiga trähus och byggnadssnickerier; i Obbola: sulfatcellulosa, terpentin och flytande harts.",
                "contact": {
                    "office": "Holmsund",
                    "telegraph": "Holmos, Holmsund",
                    "phone": [
                        "Holmsunds bolag"
                    ],
                    "postgiro": "64067",
                    "factory_office": "Obbola"
                },
                "financials": {
                    "capital": "6,000,000 kr",
                    "employees": {
                        "industriarb": 1100
                    },
                    "annual_turnover": "16,000 stds sågade trävaror, varav 3,000 stds hyvlade, 30,000 ton sulfatcellulosa"
                },
                "corporation_year": 1896,
                "board": [
                    {
                        "name": "dir. Torsten Hérnod",
                        "role": "ordf."
                    },
                    {
                        "name": "disp. Ax. Enström",
                        "role": "Disp."
                    },
                    {
                        "name": "dir. K. Erik Nyberg",
                        "role": "Styrelse"
                    }
                ],
                "director": "Ax. Enström",
                "owners": [
                    "Svenska Cellulosa AB"
                ],
                "platschef_i": "Målilla: Althon Holm"
            },
            {
                "name": "Hols’ Skinnindustri AB.",
                "location": "Malung",
                "business": "Tillverkar handskar och skinnbeklädnader",
                "contact": {
                    "office": "Malung",
                    "phone": [
                        "330"
                    ],
                    "postgiro": "173381"
                },
                "financials": {
                    "capital": "50,000 kr",
                    "employees": {
                        "industriarb": 27
                    }
                },
                "foundation_year": 1941,
                "board": [
                    {
                        "name": "fabr. Johan E:son Hols",
                        "role": "Styrelse o. verkst. dir."
                    }
                ]
            },
            {
                "name": "Carl Holten AB.",
                "location": "Hässleholm",
                "business": "Herrkonfektionsfabrik",
                "products": "Tillverkar frack-, smoking- och kavajkostymer, uniformer samt ulstrar, paletåer och trench-coats",
                "contact": {
                    "office": "Hässleholm",
                    "phone": [
                        "950",
                        "951"
                    ],
                    "postgiro": "38910"
                },
                "financials": {
                    "capital": "80,000 kr",
                    "employees": {
                        "industriarb": 75
                    }
                },
                "foundation_year": 1939,
                "board": [
                    {
                        "name": "Carl G. Holten-man",
                        "role": "Styrelse o. verkst. dir."
                    }
                ]
            }
        ]
    }
}