{
    "original": "Bröderna\n\nTelegr.-adr.: Bröderna, Skurup.\nTelefon: 67 o. 287. Postgiro: 9178. —\nAkt.-kap.: 180,000 kr. Antal industriarb.: 70.\nTillv.-värde pr år: 800,000 kr. — Firman\ngrundad 1903, bolag 1918.\n\nVerkst. direktörer: A. Olof Andersson\no. Emil Andersson.\n\nKamrer: Lars M. Hansson.\n\n*Bröderna Anderssons Velociped- &amp;\nRadiofabrik AB., Göteborg.\n\nTillverkar velocipeder och\nradioapparater. Varumärken: »Kungs-Radio»,\n»Kungsvelocipeden», »B.A.V.» o. »Velux».\n\nKontor: Kungsg. 18. Telegr.-adr.:\nRadiocykel, Göteborg. Telefon:\n»Kungsradio». Postgiro: 12207.\n\nAkt.-kap.: 600,000 kr. Antal\nindustriarb.: 140. — Firman etabl. 1903, nuv.\nnamn 1932, bolag 1941.\n\nStyrelse: dir. Albin Andersson, dir.\nArne Andersson, fru Gunhild Andersson.\n\nVerkst. direktörer: Albin Andersson o.\nArne Andersson.\n\n^Bröderna Andrée, Ruda\nSnickeri-&amp; Möbelfabrik, Ruda.\n\nSe Ruda Snickeri- &amp; Möbelfabrik,\nBröderna Andrée, Ruda.\n\n*AB. Bröderna Arnerot, Stockholm.\n\nSnickerifabrik. Tillverkar\nbyggnadssnickerier samt inredningar för banker,\nbiografer, affärslokaler och laboratorier.\n\nKontor: Norra Stationsg. 63. Telefon:\n339563. Postgiro: 3554.\n\nAkt.-kap.: 30,000 kr. Antal\nindustriarb.: 27. Tillv.-värde pr år: 330,000 kr.\n— Firman etabl. 1917, bolag 1940.\n\nStyrelse: fabr. Elias Arnerot (ordf.),\nfabr. Erik Arnerot, vaktmäst. Bror\nEma-nuelz.\n\nVerkst. direktörer: Elias Arnerot o.\nErik Arnerot.\n\n* Bröderna Bengtsson, Falkenberg.\n\nByggnadsentreprenörfirma för\nbostads-och affärshus, industribyggnader m. m.\n\nTelefon: 202. Postgiro: 77814. —\nProd.-värde pr år: 1,250,000 kr. —\nFirman etabl. 1920.\n\nÄgare: byggm. Gustaf Bengtsson,\nbyggm. Hugo Bengtsson, fru Signe\nBengtsson.\n\nLedare o. inköpschef: Gustaf\nBengtsson.\n\n^Bröderna Bergbäck, Byggnads AB.,\n\nLinköping.\n\nSe Byggnads AB. Bröderna Bergbäck,\nLinköping.\n\n*\tBröderna Bringholtz’ Möbelfabrik,\n\nRuda.\n\nTillverkar stolar och fåtöljer vid fabrik\ni Ruda (Kalmar l.).\n\nTelefon: 21. — Arb.-antal: 20.\nTillv.-värde pr år: 250,000 kr. — Firman etabl.\n1926.\n\nÄgare o. chefer: fabr. Linder\nBringholtz o. fabr. Erik Bringholtz.\n\n*\tBröderna Bruce, Seffle\nMotorverkstad, Säffle.\n\nSe AB. Seffle Motorverkstad, Bröderna\nBruce, Säffle.\n\nAB. Bröderna Brännströms Mek.\nVerkstad, Skellefteå.\n\nTillverkar sågverksmaskiner,\nångvin-schar, hissar, transmissioner och\nmaskinelement m. m.\n\nTelegr.-adr.: Maskiner, Skellefteå.\nTelefon: 10218 o. 11718. Postgiro: 61446.\n\n—\tAkt.-kap.: 25,000 kr. Antal\nindustriarb.: 35. Tillv.-värde pr år: 400,000 kr.\n\n—\tFirman etabl. 1913, bolag 1933.\nChef: dir. Karl A. Eriksson.\n\nBröderna Carlsson &amp; Anderssons\n\nAB., Eskilstuna.\n\nMetallgjuteri och metallvarufabrik.\nTillverkar gjutgods i mässing, rödgods,\nlagermetall m. m. samt spiselräck,\nbatterikabelskor, bilbeslag m. m.\n\nTelefon: 31851. Postgiro: 27782. —\nAkt.-kap.: 30,000 kr. Arb.-antal: 12.\nTillv.-värde pr år: 175,000 kr. — Firman\netabl. år 1919, bolag 1942.\n\nVerkst. dir.: fabr. O. Arvid Carlsson.\n\n*AB. Bröderna Carlssons\nMöbelfabrik, Virserum.\n\nTillverkar matsalsmöbler samt\nbokhyllor, bord och stolar vid fabrik i Virserum\n(Kalmar l.).\n\nTelefon: 50 o. 26. Postgiro: 130780. —\nAkt.-kap.: 36,000 kr. Antal industriarb.:\n10. Tillv.-värde pr år: 190,000 kr. —\nBolaget grundat 1922.\n\nStyrelse o. chefer: fabr. Gust. Carlsson\n(ordf.), fabr. Johan Andersson, fabr.\nArvid Carlsson o. fabr. Fabian Carlsson.\n\n72*",
    "structured": {
        "1": {
            "name": "Bröderna",
            "location": "Skurup",
            "contact": {
                "telegraph": "Bröderna, Skurup",
                "phone": [
                    "67",
                    "287"
                ],
                "postgiro": "9178"
            },
            "financials": {
                "capital": "180,000 kr",
                "employees": {
                    "industriarb": 70
                },
                "annual_production_value": "800,000 kr"
            },
            "foundation_year": 1903,
            "corporation_year": 1918,
            "board": [
                {
                    "name": "A. Olof Andersson",
                    "role": "Verkst. direktör"
                },
                {
                    "name": "Emil Andersson",
                    "role": "Verkst. direktör"
                },
                {
                    "name": "Lars M. Hansson",
                    "role": "Kamrer"
                }
            ]
        },
        "2": {
            "name": "Bröderna Anderssons Velociped- & Radiofabrik AB.",
            "location": "Göteborg",
            "business": "Tillverkar velocipeder och radioapparater",
            "products": "Varumärken: »Kungs-Radio», »Kungsvelocipeden», »B.A.V.» o. »Velux».",
            "contact": {
                "office": "Kungsg. 18",
                "telegraph": "Radiocykel, Göteborg",
                "phone": "»Kungsradio»",
                "postgiro": "12207"
            },
            "financials": {
                "capital": "600,000 kr",
                "employees": {
                    "industriarb": 140
                }
            },
            "foundation_year": 1903,
            "current_name_year": 1932,
            "corporation_year": 1941,
            "board": [
                {
                    "name": "Albin Andersson",
                    "role": "dir."
                },
                {
                    "name": "Arne Andersson",
                    "role": "dir."
                },
                {
                    "name": "Gunhild Andersson",
                    "role": "fru"
                }
            ]
        },
        "3": {
            "name": "Bröderna Arnerot",
            "location": "Stockholm",
            "business": "Snickerifabrik",
            "products": "Tillverkar byggnadssnickerier samt inredningar för banker, biografer, affärslokaler och laboratorier.",
            "contact": {
                "office": "Norra Stationsg. 63",
                "phone": "339563",
                "postgiro": "3554"
            },
            "financials": {
                "capital": "30,000 kr",
                "employees": {
                    "industriarb": 27
                },
                "annual_production_value": "330,000 kr"
            },
            "foundation_year": 1917,
            "corporation_year": 1940,
            "board": [
                {
                    "name": "Elias Arnerot",
                    "role": "fabr."
                },
                {
                    "name": "Erik Arnerot",
                    "role": "fabr."
                },
                {
                    "name": "Bror Ema-nuelz",
                    "role": "vaktmäst."
                }
            ]
        },
        "4": {
            "name": "Bröderna Bengtsson",
            "location": "Falkenberg",
            "business": "Byggnadsentreprenörfirma",
            "products": "För bostads-och affärshus, industribyggnader m. m.",
            "contact": {
                "phone": "202",
                "postgiro": "77814"
            },
            "financials": {
                "annual_production_value": "1,250,000 kr"
            },
            "foundation_year": 1920,
            "owners": [
                "byggm. Gustaf Bengtsson",
                "byggm. Hugo Bengtsson",
                "fru Signe Bengtsson"
            ],
            "manager": "Gustaf Bengtsson"
        },
        "5": {
            "name": "Bröderna Bringholtz’ Möbelfabrik",
            "location": "Ruda",
            "business": "Tillverkar stolar och fåtöljer",
            "products": "Vid fabrik i Ruda (Kalmar l.)",
            "contact": {
                "phone": "21"
            },
            "financials": {
                "annual_production_value": "250,000 kr"
            },
            "foundation_year": 1926,
            "owners": [
                "fabr. Linder Bringholtz",
                "fabr. Erik Bringholtz"
            ]
        },
        "6": {
            "name": "Bröderna Bruce, Seffle Motorverkstad",
            "location": "Säffle",
            "business": "Seffle Motorverkstad",
            "contact": {
                "telegraph": "AB. Seffle Motorverkstad, Bröderna Bruce, Säffle"
            }
        },
        "7": {
            "name": "AB. Bröderna Brännströms Mek. Verkstad",
            "location": "Skellefteå",
            "business": "Tillverkar sågverksmaskiner, ångvin-schar, hissar, transmissioner och maskinelement m. m.",
            "contact": {
                "telegraph": "Maskiner, Skellefteå",
                "phone": [
                    "10218",
                    "11718"
                ],
                "postgiro": "61446"
            },
            "financials": {
                "capital": "25,000 kr",
                "employees": {
                    "industriarb": 35
                },
                "annual_production_value": "400,000 kr"
            },
            "foundation_year": 1913,
            "corporation_year": 1933,
            "director": "Karl A. Eriksson"
        },
        "8": {
            "name": "Bröderna Carlsson & Anderssons AB.",
            "location": "Eskilstuna",
            "business": "Metallgjuteri och metallvarufabrik",
            "products": "Tillverkar gjutgods i mässing, rödgods, lagermetall m. m. samt spiselräck, batterikabelskor, bilbeslag m. m.",
            "contact": {
                "phone": "31851",
                "postgiro": "27782"
            },
            "financials": {
                "capital": "30,000 kr",
                "employees": {
                    "industriarb": 12
                },
                "annual_production_value": "175,000 kr"
            },
            "foundation_year": 1919,
            "corporation_year": 1942,
            "director": "O. Arvid Carlsson"
        },
        "9": {
            "name": "AB. Bröderna Carlssons Möbelfabrik",
            "location": "Virserum",
            "business": "Tillverkar matsalsmöbler samt bokhyllor, bord och stolar",
            "products": "Vid fabrik i Virserum (Kalmar l.)",
            "contact": {
                "phone": [
                    "50",
                    "26"
                ],
                "postgiro": "130780"
            },
            "financials": {
                "capital": "36,000 kr",
                "employees": {
                    "industriarb": 10
                },
                "annual_production_value": "190,000 kr"
            },
            "corporation_year": 1922,
            "board": [
                {
                    "name": "Gust. Carlsson",
                    "role": "fabr."
                },
                {
                    "name": "Johan Andersson",
                    "role": "fabr."
                },
                {
                    "name": "Arvid Carlsson",
                    "role": "fabr."
                },
                {
                    "name": "Fabian Carlsson",
                    "role": "fabr."
                }
            ]
        }
    }
}