{
    "original": "Borås\n\n* Borås Band- &amp; Hängslefabriks AB.,\n\nBorås.\n\nVäveri och färgeri. Tillverkar vävda\noeh flätade band, hängslen, ärm- och\nstrumphållare; utför färgning av ull-,\nbomulls- och konstsilkegarn samt\nstyck-färgning av rundtrikå.\n\nTelegr.-adr.: Ilängslefabriken, Borås.\nTelefon: 17095. Postgiro: 14945. -\nAkt.-kap.: 675,000 kr. Antal industriarb.: 150.\nTillv.-värde pr år: 2,500,000 kr. —\nBolaget grundat 1898.\n\nStyrelse: adv. E. Grenfors, kamrer G.\nHedelin, ing. Rolf Lindström.\n\nDisp.: Nils-Håkan Klaening.\n\n*AB. Borås Draperi- &amp; Cardinfabrik,\n\nBorås.\n\nTillverkar gardiner, draperityger,\nta-pisserivävnader, möbeltyger och\ndivantäc-ken. Varumärke: »Stjärnmärket».\n\nTelegr.-adr.: Gardinfabriken, Borås.\nTelefon: 10673. Postgiro: 88000.\n\nAkt.-kap.: 225,000 kr. Antal\nindustriarb.: 31. Tillv.-värde pr år: 600,000 kr.\n— Bolaget grundat 1907.\n\nStyrelse: ing. Helge Björkman (ordf.),\nfru Hallvi Björkman, fru Ingrid\nBjörkman, ing. Ivar Björkman, verkm. Arne\nSjölander, disp. S. E. Wiede.\n\nDisp.: Oscar Åring.\n\n*AB. Borås Jacquardväfveri, Borås.\n\nTillverkar möbel- och draperityger\nsamt frottévävnader. Varumärke: B. J. V.\n\nTelegr.-adr.: Jacquard, Borås.\nTelefon: 10919. Postgiro: 20633. —\nAkt.-kap.: 300,000 kr. Antal industriarb.: 40.\nTillv.-värde pr år: 1,200,000 kr. —\nBolaget grundat 1913.\n\nStyrelse: ing. Axel L. Wallgren (ordf.),\nfru A. Wallgren, kapten Bernt A.\nWallgren.\n\nVerJcst. dir.: A. L. Wallgren.\n\nBorås Kliché &amp; Litografiska AB.,\n\nBorås.\n\nKlichéanstalt, offset- och litografiskt\ntryckeri. Tillverkar klichéer och utför\ntrycksaker i en eller flera färger.\n\nTelefon: 12637 o. 12685. Postgiro:\n134048. — Akt.-kap.: 8,200 kr. Antal\nindustriarb.: 70. Tillv.-värde pr år: 720,000\nkr. — Bolaget grundat 1926, ombildat\nmed nuv. namn 1933.\n\nStyrelse o. verkst. direktörer:’ Ivar K.\nFäldt (ordf.) o. Sten A. Bussqvist.\n\n*AB. Borås Klädningstygsfabrik,\n\nBorås.\n\nYlleväveri med färgeri och\nappretur-verk. Tillverkar helylletyger.\n\nPost- o. telegr.-adr.: Klädningstyg,\nBorås. Telefon: 10235. Postgiro: 24990.\n— Akt.-kap.: 1,200,000 kr. Antal\nindustriarb.: 125. Tillv.-värde pr år: 3,600,000\nkr. — Bolaget grundat 1898. Kilsunds\nAB., Borås, är huvudintressent i bolaget.\n\nStyrelse: dir. Arthur Anderson, dir.\nC. E. Edlund, dir. Carl Eiserman, dir.\nNils Hörstadius.\n\nVerkst. dir.: C. E. Edlund.\n\n*AB. Borås Konfektionsfabrik, Borås.\n\nSe Magni AB., Borås.\n\n*AB. Borås Mattväveri, Borås.\n\nMattväveri i Källbäcksryd, Borås.\nTillverkar gångmattor och avpassade mattor\ni jute-, bomulls- och hårgarner.\n\nPostadr.: Källbäcksryd, Borås. Telefon:\n48120. — Akt.-kap.: 100,000 kr. Antal\nindustriarb.: 10. Tillv.-värde pr år:\n400,000 kr. — Firman etabl. 1935, bolag\n1946.\n\nStyrelse o. verkst. direktörer: Walter\nBranzell o. Gösta Persson.\n\n*AB. Borås Mekaniska\nCummi-väfveri, Borås.\n\nGummibandsväveri och korsettfabrik.\nTillverkar gummi band, hängslen, bälten\noch skärp, strumpeband samt korsetter.\nVarumärke: »Alligator».\n\nTelegr.-adr.: Gummiväfveriet, Borås.\nTelefon: 17355. Postgiro: 34478. —\nAkt.-kap.: 385,000 kr. Antal industriarb.:\n235. — Bolaget grundat 1895.\n\nStyrelse: disp. Åke Rydin (ordf.),\ndisp. Bror Bökmark, kamrer Helge Rydin.\n\nDisp.: Å. Rydin.\n\n* Borås Mek. Verkstads AB., Borås.\n\nMek. verkstad och gjuteri. Tillverkar\nhydrauliska pressanläggningar,\nkugg-hjulsfräsmaskiner, färgeri- och\nappretur-maskiner, järnkonstruktioner, broar,\nångpannor m. m.\n\nTelegr.-adr.: Verkstaden, Borås.\nTelefon: 10016 o. 10216. Postgiro: 76800. —\nAkt.-kap.: 300,000 kr. Antal industriarb.:\n100. — Firman etabl. 1888.\n\nStyrelse: civiling. Axel Nyländer (ordf.),\nmajor Erik W:son Änder, övering. Carl\nBredin.\n\nVerkst. dir. o. disp.: A. Nyländer.\n\nKamrer: Eric G. Anderson.",
    "structured": {
        "1": {
            "name": "Borås Band- & Hängslefabriks AB.",
            "location": "Borås",
            "business": "Väveri och färgeri. Tillverkar vävda oeh flätade band, hängslen, ärm- och strumphållare; utför färgning av ull-, bomulls- och konstsilkegarn samt styck-färgning av rundtrikå.",
            "contact": {
                "office": "Not available",
                "phone": [
                    "17095"
                ],
                "postgiro": "14945",
                "sales_offices": [
                    {
                        "location": "Not available",
                        "phone": "Not available"
                    }
                ],
                "telegraph": "Ilängslefabriken, Borås",
                "factory_office": "Not available",
                "factory_phone": "Not available"
            },
            "financials": {
                "capital": "675,000 kr",
                "employees": {
                    "industriarb.": 150
                },
                "annual_turnover": "2,500,000 kr",
                "annual_production_value": "Not available"
            },
            "foundation_year": 1898,
            "current_name_year": "Not available",
            "predecessor": "Not available",
            "original_name": "Not available",
            "corporation_year": "Not available",
            "board": [
                {
                    "name": "adv. E. Grenfors",
                    "role": "Not available"
                },
                {
                    "name": "kamrer G. Hedelin",
                    "role": "Not available"
                },
                {
                    "name": "ing. Rolf Lindström",
                    "role": "Not available"
                }
            ],
            "owners": [
                "Not available"
            ],
            "director": "Nils-Håkan Klaening",
            "managing_director": "Not available",
            "sales_manager": "Not available",
            "manager": "Not available"
        },
        "2": {
            "name": "AB. Borås Draperi- & Cardinfabrik",
            "location": "Borås",
            "business": "Tillverkar gardiner, draperityger, ta-pisserivävnader, möbeltyger och divantäc-ken. Varumärke: »Stjärnmärket».",
            "contact": {
                "office": "Not available",
                "phone": [
                    "10673"
                ],
                "postgiro": "88000",
                "sales_offices": [
                    {
                        "location": "Not available",
                        "phone": "Not available"
                    }
                ],
                "telegraph": "Gardinfabriken, Borås",
                "factory_office": "Not available",
                "factory_phone": "Not available"
            },
            "financials": {
                "capital": "225,000 kr",
                "employees": {
                    "industriarb.": 31
                },
                "annual_turnover": "600,000 kr",
                "annual_production_value": "Not available"
            },
            "foundation_year": 1907,
            "current_name_year": "Not available",
            "predecessor": "Not available",
            "original_name": "Not available",
            "corporation_year": "Not available",
            "board": [
                {
                    "name": "ing. Helge Björkman",
                    "role": "ordf."
                },
                {
                    "name": "fru Hallvi Björkman",
                    "role": "Not available"
                },
                {
                    "name": "fru Ingrid Björkman",
                    "role": "Not available"
                },
                {
                    "name": "ing. Ivar Björkman",
                    "role": "Not available"
                },
                {
                    "name": "verkm. Arne Sjölander",
                    "role": "Not available"
                },
                {
                    "name": "disp. S. E. Wiede",
                    "role": "Not available"
                }
            ],
            "owners": [
                "Not available"
            ],
            "director": "Oscar Åring",
            "managing_director": "Not available",
            "sales_manager": "Not available",
            "manager": "Not available"
        },
        "3": {
            "name": "AB. Borås Jacquardväfveri",
            "location": "Borås",
            "business": "Tillverkar möbel- och draperityger samt frottévävnader. Varumärke: B. J. V.",
            "contact": {
                "office": "Not available",
                "phone": [
                    "10919"
                ],
                "postgiro": "20633",
                "sales_offices": [
                    {
                        "location": "Not available",
                        "phone": "Not available"
                    }
                ],
                "telegraph": "Jacquard, Borås",
                "factory_office": "Not available",
                "factory_phone": "Not available"
            },
            "financials": {
                "capital": "300,000 kr",
                "employees": {
                    "industriarb.": 40
                },
                "annual_turnover": "1,200,000 kr",
                "annual_production_value": "Not available"
            },
            "foundation_year": 1913,
            "current_name_year": "Not available",
            "predecessor": "Not available",
            "original_name": "Not available",
            "corporation_year": "Not available",
            "board": [
                {
                    "name": "ing. Axel L. Wallgren",
                    "role": "ordf."
                },
                {
                    "name": "fru A. Wallgren",
                    "role": "Not available"
                },
                {
                    "name": "kapten Bernt A. Wallgren",
                    "role": "Not available"
                }
            ],
            "owners": [
                "Not available"
            ],
            "director": "A. L. Wallgren",
            "managing_director": "Not available",
            "sales_manager": "Not available",
            "manager": "Not available"
        },
        "4": {
            "name": "Borås Kliché & Litografiska AB.",
            "location": "Borås",
            "business": "Klichéanstalt, offset- och litografiskt tryckeri. Tillverkar klichéer och utför trycksaker i en eller flera färger.",
            "contact": {
                "office": "Not available",
                "phone": [
                    "12637",
                    "12685"
                ],
                "postgiro": "134048",
                "sales_offices": [
                    {
                        "location": "Not available",
                        "phone": "Not available"
                    }
                ],
                "telegraph": "Not available",
                "factory_office": "Not available",
                "factory_phone": "Not available"
            },
            "financials": {
                "capital": "8,200 kr",
                "employees": {
                    "industriarb.": 70
                },
                "annual_turnover": "720,000 kr",
                "annual_production_value": "Not available"
            },
            "foundation_year": 1926,
            "current_name_year": 1933,
            "predecessor": "Not available",
            "original_name": "Not available",
            "corporation_year": "Not available",
            "board": [
                {
                    "name": "Ivar K. Fäldt",
                    "role": "ordf."
                },
                {
                    "name": "Sten A. Bussqvist",
                    "role": "Not available"
                }
            ],
            "owners": [
                "Not available"
            ],
            "director": "Not available",
            "managing_director": "Not available",
            "sales_manager": "Not available",
            "manager": "Not available"
        },
        "5": {
            "name": "AB. Borås Klädningstygsfabrik",
            "location": "Borås",
            "business": "Ylleväveri med färgeri och appretur-verk. Tillverkar helylletyger.",
            "contact": {
                "office": "Not available",
                "phone": [
                    "10235"
                ],
                "postgiro": "24990",
                "sales_offices": [
                    {
                        "location": "Not available",
                        "phone": "Not available"
                    }
                ],
                "telegraph": "Klädningstyg, Borås",
                "factory_office": "Not available",
                "factory_phone": "Not available"
            },
            "financials": {
                "capital": "1,200,000 kr",
                "employees": {
                    "industriarb.": 125
                },
                "annual_turnover": "3,600,000 kr",
                "annual_production_value": "Not available"
            },
            "foundation_year": 1898,
            "current_name_year": "Not available",
            "predecessor": "Not available",
            "original_name": "Not available",
            "corporation_year": "Not available",
            "board": [
                {
                    "name": "dir. Arthur Anderson",
                    "role": "Not available"
                },
                {
                    "name": "dir. C. E. Edlund",
                    "role": "Not available"
                },
                {
                    "name": "dir. Carl Eiserman",
                    "role": "Not available"
                },
                {
                    "name": "dir. Nils Hörstadius",
                    "role": "Not available"
                }
            ],
            "owners": [
                "Kilsunds AB., Borås"
            ],
            "director": "C. E. Edlund",
            "managing_director": "Not available",
            "sales_manager": "Not available",
            "manager": "Not available"
        },
        "6": {
            "name": "AB. Borås Konfektionsfabrik",
            "location": "Borås",
            "business": "Not available",
            "contact": {
                "office": "Not available",
                "phone": [
                    "Not available"
                ],
                "postgiro": "Not available",
                "sales_offices": [
                    {
                        "location": "Not available",
                        "phone": "Not available"
                    }
                ],
                "telegraph": "Not available",
                "factory_office": "Not available",
                "factory_phone": "Not available"
            },
            "financials": {
                "capital": "Not available",
                "employees": {
                    "industriarb.": "Not available"
                },
                "annual_turnover": "Not available",
                "annual_production_value": "Not available"
            },
            "foundation_year": "Not available",
            "current_name_year": "Not available",
            "predecessor": "Not available",
            "original_name": "Not available",
            "corporation_year": "Not available",
            "board": [
                {
                    "name": "Not available",
                    "role": "Not available"
                }
            ],
            "owners": [
                "Not available"
            ],
            "director": "Not available",
            "managing_director": "Not available",
            "sales_manager": "Not available",
            "manager": "Not available"
        },
        "7": {
            "name": "AB. Borås Mattväveri",
            "location": "Borås",
            "business": "Mattväveri i Källbäcksryd, Borås. Tillverkar gångmattor och avpassade mattor i jute-, bomulls- och hårgarner.",
            "contact": {
                "office": "Not available",
                "phone": [
                    "48120"
                ],
                "postgiro": "Not available",
                "sales_offices": [
                    {
                        "location": "Not available",
                        "phone": "Not available"
                    }
                ],
                "telegraph": "Not available",
                "factory_office": "Källbäcksryd, Borås",
                "factory_phone": "Not available"
            },
            "financials": {
                "capital": "100,000 kr",
                "employees": {
                    "industriarb.": 10
                },
                "annual_turnover": "400,000 kr",
                "annual_production_value": "Not available"
            },
            "foundation_year": 1935,
            "current_name_year": "1946",
            "predecessor": "Not available",
            "original_name": "Not available",
            "corporation_year": "Not available",
            "board": [
                {
                    "name": "Walter Branzell",
                    "role": "ordf."
                },
                {
                    "name": "Gösta Persson",
                    "role": "Not available"
                }
            ],
            "owners": [
                "Not available"
            ],
            "director": "Not available",
            "managing_director": "Not available",
            "sales_manager": "Not available",
            "manager": "Not available"
        },
        "8": {
            "name": "AB. Borås Mekaniska Cummi-väfveri",
            "location": "Borås",
            "business": "Gummibandsväveri och korsettfabrik. Tillverkar gummi band, hängslen, bälten och skärp, strumpeband samt korsetter. Varumärke: »Alligator».",
            "contact": {
                "office": "Not available",
                "phone": [
                    "17355"
                ],
                "postgiro": "34478",
                "sales_offices": [
                    {
                        "location": "Not available",
                        "phone": "Not available"
                    }
                ],
                "telegraph": "Gummiväfveriet, Borås",
                "factory_office": "Not available",
                "factory_phone": "Not available"
            },
            "financials": {
                "capital": "385,000 kr",
                "employees": {
                    "industriarb.": 235
                },
                "annual_turnover": "Not available",
                "annual_production_value": "Not available"
            },
            "foundation_year": 1895,
            "current_name_year": "Not available",
            "predecessor": "Not available",
            "original_name": "Not available",
            "corporation_year": "Not available",
            "board": [
                {
                    "name": "disp. Åke Rydin",
                    "role": "ordf."
                },
                {
                    "name": "disp. Bror Bökmark",
                    "role": "Not available"
                },
                {
                    "name": "kamrer Helge Rydin",
                    "role": "Not available"
                }
            ],
            "owners": [
                "Not available"
            ],
            "director": "Not available",
            "managing_director": "Not available",
            "sales_manager": "Not available",
            "manager": "Not available"
        },
        "9": {
            "name": "Borås Mek. Verkstads AB.",
            "location": "Borås",
            "business": "Mek. verkstad och gjuteri. Tillverkar hydrauliska pressanläggningar, kugg-hjulsfräsmaskiner, färgeri- och appretur-maskiner, järnkonstruktioner, broar, ångpannor m. m.",
            "contact": {
                "office": "Not available",
                "phone": [
                    "10016",
                    "10216"
                ],
                "postgiro": "76800",
                "sales_offices": [
                    {
                        "location": "Not available",
                        "phone": "Not available"
                    }
                ],
                "telegraph": "Verkstaden, Borås",
                "factory_office": "Not available",
                "factory_phone": "Not available"
            },
            "financials": {
                "capital": "300,000 kr",
                "employees": {
                    "industriarb.": 100
                },
                "annual_turnover": "Not available",
                "annual_production_value": "Not available"
            },
            "foundation_year": 1888,
            "current_name_year": "Not available",
            "predecessor": "Not available",
            "original_name": "Not available",
            "corporation_year": "Not available",
            "board": [
                {
                    "name": "civiling. Axel Nyländer",
                    "role": "ordf."
                },
                {
                    "name": "major Erik W:son Änder",
                    "role": "Not available"
                },
                {
                    "name": "övering. Carl Bredin",
                    "role": "Not available"
                }
            ],
            "owners": [
                "Not available"
            ],
            "director": "Not available",
            "managing_director": "A. Nyländer",
            "sales_manager": "Not available",
            "manager": "Not available"
        }
    }
}