{
    "original": "Sand b e rg—Sandin\n\nSandberg, Bröderna, Hallabro.\nSe Bröderna Sandberg, Hallabro.\n\nSandbergs Mek. Verkstad, Bröderna,\n\nKumla.\n\nSe Bröderna Sandberg, Mek. Verkstad,\nKumla.\n\n*Rob. L. Sandberg, Stockholm.\n\nSnickerifabrik. Tillverkar möbler samt\nsnickerier såsom butiks-, kontors- och\nlagerinredningar.\n\nKontor: Riddarg. 40. Telefon: 624128.\nPostgiro: 151737. — Arb.-antal: 3. —\nFirman etabl. 1921.\n\nÄgare o. chef: snickarmast. Rob. L.\nSandberg.\n\n*Sandblom &amp; Stohne Verkstads AB.,\n\nStockholm.\n\nSe AB. Stohne-Ver ken, Stockholm.\n\nAB. Sandby maskiner,\n\nSödra Sandby.\n\nGjuter i och mek. verkstad i Södra\nSandby (Malmöh. l.). Tillverkar\nmaskiner för lantbruk och byggnadsindustri\nsåsom halmpressar, gröpkvarnar och\nsä-deskrossar samt byggnads- och\nmagasinshissar, betong- och murbruksblandare,\nkranarmar, bränntorvmaskiner och\ntorv-utsättningsvagnar, torvbärgningsvagnar,\nutsättningslinbanor, gjutna fönster,\ngjutgods m. m.\n\nTelegr.-adr.: Gjuteriet, Södra Sandby.\nTelefon: 1 o. 3. Postgiro: 36614. —\nAkt.-kap.: 100,000 kr. Antal industriarb.: 40.\nTillv.-värde pr år: 500,000 kr. — Firman\netabl. 1886 under namn Martin Jönssons\nMek. Verkstad, nuv. namn o. bolag 1946.\n\nVerkst. dir.: disp. Gunnar W.\nWahlbeck.\n\nKamrer o. försäljn.-chef: Harald\nHansson.\n\n*Sandbäck AB., Bröderna, Ljusdal.\nSe Bröderna Sandbäck AB., Ljusdal.\n\n*AB. Sandéns Mek. Verkstad,\n\nVärnamo.\n\nMek. verkstad. Tillverkar kombinerade\nsnickerimaskiner, snabbkallsågar,\nplan-fräsmaskiner, universalfräsmaskiner,\ndelningsapparater samt trådrefflingsverk för\nspiktråd. Varumärke: »Sajo».\n\nTelefon: 10155, 10755 o. 10995. Postgiro:\n22260. — Akt.-kap.: 90,000 kr. Antal\n\nindustriarb.: 90. Tillv.-värde pr år:\n2,000,000 kr. — Firman etabl. 1916, bolag\n1942.\n\nStyrelse o. verkst. dir.: Oscar Sandén.\n\nAlfr. Sandersons Maskinfabrik,\n\nLinköping.\n\nMek. verkstad. Tillverkar maskiner för\nden grafiska industrien såsom\nlinjerings-maskiner, linjerrullar och linjerpennor,\nanlimningsmaskiner, perforermaskiner,\nperforerkammar och perforerlinjer,\nstanslinjer, rillmaskiner,\nMlstansningsmaski-ner samt elektriska blinkljusapparater och\nringklockor för järnvägar,\ngatutrafik-fyrar m. m.\n\nTelegr.-adr.: Sanderson, Linköping.\nTelefon: 20004. Postgiro: 8144.\n\nAntal industriarb.: 50. — Firman\netabl. 1892 under namn Alfr. Sandersons\nLinjeringsmaskinfabrik, nuv. namn 1929.\n\nÄgare o. chefer: fabr. Bror Sanderson\no. civiling. Harald Sanderson.\n\n*Sandhems Nya Trävaru AB.,\n\nSandhem.\n\nSågverk, hyvleri och snickerifabrik i\nSandhem (Skarab. l.). Tillverkar sågade\noch hyvlade trävaror, byggnadssnickerier,\nlamelldörrar samt dörrar för export.\nBolaget driver även försäljning av\nfiberplattor och byggnadsmaterialier.\n\nTelefon: 5 o. 20. Postgiro: 88080. —\nAkt.-kap.: 70,000 kr. Antal industriarb.:\n55. — Bolaget grundat 1895, ombildat\n1933.\n\nStyrelse: vägbyggm. Joh. M. Grahn\n(ordf.), godsäg. Carl Andersson,\nmeje-riäg. E. Kruus.\n\nVerkst. dir.: Joh. M. Grahn.\n\nDisp.: Bengt Blomberg.\n\nKamrer: John Ekenius.\n\nAB. Sandins Metallfabrik,\n\nSundbyberg.\n\nMetallvarufabrik i Nya Mariehäll,\nSundbyberg (Sthlms l.). Tillverkar\nfönsterkarmar och dörrar av metall och rostfritt\nstål, trappräck och ledstänger, skyltskåp,\nmontrar och brevinkast samt\nfastighetsregister och tidtabellstavlor av metall med\nutbytbara typer; utför tunnplåtsarbeten,\npressning, svetsning och trycksvarvning.\n\nTelegr.-adr.: Samefa, Stockholm.\nTelefon: Stockholm 282670. Postgiro: 150785.\n\nAkt.-kap.: 5,000 kr. Antal\nindustriarb.: 80. Tillv.-värde pr år: 800,000 kr.\n— Firman etabl. 1934, bolag 1935, äges\nav Industri AB. Svenska Automatvapen.",
    "structured": {
        "1": {
            "name": "Rob. L. Sandberg",
            "location": "Stockholm",
            "business": "Snickerifabrik",
            "products": "Tillverkar möbler samt snickerier såsom butiks-, kontors- och lagerinredningar.",
            "contact": {
                "office": "Riddarg. 40",
                "phone": [
                    "624128"
                ],
                "postgiro": "151737"
            },
            "financials": {
                "capital": "N/A",
                "employees": {
                    "arbetsantal": 3
                },
                "annual_turnover": "N/A",
                "annual_production_value": "N/A"
            },
            "foundation_year": 1921,
            "owners": [
                "Rob. L. Sandberg"
            ],
            "director": "Rob. L. Sandberg"
        },
        "2": {
            "name": "Sandblom & Stohne Verkstads AB.",
            "location": "Stockholm",
            "business": "N/A",
            "products": "N/A",
            "contact": {
                "office": "N/A",
                "phone": [],
                "postgiro": "N/A"
            },
            "financials": {
                "capital": "N/A",
                "employees": {
                    "industriarb": 40
                },
                "annual_turnover": "500,000 kr",
                "annual_production_value": "N/A"
            },
            "foundation_year": 1886,
            "owners": [
                "N/A"
            ],
            "director": "disp. Gunnar W. Wahlbeck"
        },
        "3": {
            "name": "Sandby maskiner",
            "location": "Södra Sandby",
            "business": "Gjuteri i och mek. verkstad",
            "products": "Tillverkar maskiner för lantbruk och byggnadsindustri såsom halmpressar, gröpkvarnar och sä-deskrossar samt byggnads- och magasinshissar, betong- och murbruksblandare, kranarmar, bränntorvmaskiner och torv-utsättningsvagnar, torvbärgningsvagnar, utsättningslinbanor, gjutna fönster, gjutgods m. m.",
            "contact": {
                "office": "N/A",
                "phone": [
                    "1",
                    "3"
                ],
                "postgiro": "36614"
            },
            "financials": {
                "capital": "100,000 kr",
                "employees": {
                    "industriarb": 40
                },
                "annual_turnover": "500,000 kr",
                "annual_production_value": "N/A"
            },
            "foundation_year": 1886,
            "original_name": "Martin Jönssons Mek. Verkstad",
            "corporation_year": 1946,
            "director": "disp. Gunnar W. Wahlbeck"
        },
        "4": {
            "name": "Sandbäck AB.",
            "location": "Ljusdal",
            "business": "N/A",
            "products": "N/A",
            "contact": {
                "office": "N/A",
                "phone": [],
                "postgiro": "N/A"
            },
            "financials": {
                "capital": "N/A",
                "employees": {
                    "N/A": "N/A"
                },
                "annual_turnove": "N/A",
                "annual_production_value": "N/A"
            },
            "foundation_year": "N/A",
            "owners": [
                "N/A"
            ],
            "director": "N/A"
        },
        "5": {
            "name": "AB. Sandéns Mek. Verkstad",
            "location": "Värnamo",
            "business": "Mek. verkstad",
            "products": "Tillverkar kombinerade snickerimaskiner, snabbkallsågar, plan-fräsmaskiner, universalfräsmaskiner, delningsapparater samt trådrefflingsverk för spiktråd. Varumärke: »Sajo».",
            "contact": {
                "office": "N/A",
                "phone": [
                    "10155",
                    "10755",
                    "10995"
                ],
                "postgiro": "22260"
            },
            "financials": {
                "capital": "90,000 kr",
                "employees": {
                    "industriarb": 90
                },
                "annual_turnover": "2,000,000 kr",
                "annual_production_value": "N/A"
            },
            "foundation_year": 1916,
            "original_name": "N/A",
            "corporation_year": 1942,
            "director": "Oscar Sandén"
        },
        "6": {
            "name": "Alfr. Sandersons Maskinfabrik",
            "location": "Linköping",
            "business": "Mek. verkstad",
            "products": "Tillverkar maskiner för den grafiska industrien såsom linjerings-maskiner, linjerrullar och linjerpennor, anlimningsmaskiner, perforermaskiner, perforerkammar och perforerlinjer, stanslinjer, rillmaskiner, Mlstansningsmaski-ner samt elektriska blinkljusapparater och ringklockor för järnvägar, gatutrafik-fyrar m. m.",
            "contact": {
                "office": "N/A",
                "phone": [
                    "20004"
                ],
                "postgiro": "8144"
            },
            "financials": {
                "capital": "N/A",
                "employees": {
                    "industriarb": 50
                },
                "annual_turnover": "N/A",
                "annual_production_value": "N/A"
            },
            "foundation_year": 1892,
            "original_name": "Alfr. Sandersons Linjeringsmaskinfabrik",
            "corporation_year": 1929,
            "director": "N/A"
        },
        "7": {
            "name": "Sandhems Nya Trävaru AB.",
            "location": "Sandhem",
            "business": "Sågverk, hyvleri och snickerifabrik",
            "products": "Tillverkar sågade och hyvlade trävaror, byggnadssnickerier, lamelldörrar samt dörrar för export.",
            "contact": {
                "office": "N/A",
                "phone": [
                    "5",
                    "20"
                ],
                "postgiro": "88080"
            },
            "financials": {
                "capital": "70,000 kr",
                "employees": {
                    "industriarb": 55
                },
                "annual_turnover": "N/A",
                "annual_production_value": "N/A"
            },
            "foundation_year": 1895,
            "original_name": "N/A",
            "corporation_year": 1933,
            "director": "Joh. M. Grahn"
        },
        "8": {
            "name": "AB. Sandins Metallfabrik",
            "location": "Sundbyberg",
            "business": "Metallvarufabrik",
            "products": "Tillverkar fönsterkarmar och dörrar av metall och rostfritt stål, trappräck och ledstänger, skyltskåp, montrar och brevinkast samt fastighetsregister och tidtabellstavlor av metall med utbytbara typer; utför tunnplåtsarbeten, pressning, svetsning och trycksvarvning.",
            "contact": {
                "office": "Nya Mariehäll, Sundbyberg",
                "phone": [
                    "Stockholm 282670"
                ],
                "postgiro": "150785"
            },
            "financials": {
                "capital": "5,000 kr",
                "employees": {
                    "industriarb": 80
                },
                "annual_turnover": "800,000 kr",
                "annual_production_value": "N/A"
            },
            "foundation_year": 1934,
            "original_name": "N/A",
            "corporation_year": 1935,
            "director": "N/A"
        }
    }
}