{
    "original": "Gry cksb o—Gränsf o rs\n\n*Grycksbo Pappersbruk AB.,\n\nGrycksbo.\n\nPappersbruk med cellulosafabriker i\nGrycksbo (Kopparb. l.). Tillverkar\nskrivpapper, tryckpapper, kraftpapper,\nrit-papper, filtrerpapper m. m., samt\nkartonger (märke: »Perga»).\n\nTelegr.-adr.: Munktell, Grycksbo.\nTelefon: »Grycksbo Pappersbruk», Falun.\nPostgiro: 72424. ^ Ensamförsälj. för\nfinpapper för Sverige: Finpappersbrukens\nFörsäljnings AB., Stockholm, telefon:\n»Finbruken»; Göteborg, telefon: 136896;\nMalmö, telefon: 72045.\n\nAkt.-kap.: 4,500,000 kr. Antal\nindustriarb.: 800. Årstillv.: 18,000 ton papper.\n\nBruket anlagt 1740, bolag 1887 under\nnamn J. H. Munktells Pappersfabriks\nAB., nuv. namn 1939.\n\nStyrelse: disp. H. Hanngren, ing. A.\nM. Munktell, prof. Henrik Munktell,\nkapten William Nisser.\n\nVerkst. dir.: William Nisser.\n\növering.: E. Mide.\n\nDriftsingenjörer: G. Kull, F. Krug, P.\nGranath o. Sven Miintzing.\n\nFörsäljn.- o. inhöpschef: A. Goliath.\n\nKamrer: A. Sandgren.\n\n*AB. Gryts Bruk, Hjortkvarn.\n\nTråddrageri och galvaniseringsverk i\nBjörnhammar samt trådspikfabrik i Gryt\n(båda i Örebro l.). Tillverkar blank,\nför-kopprad, galvaniserad och glödgad\njärntråd samt trådspik.\n\nKontor: Björnhammar, Hjortkvarn.\nTelegr.-adr.: Gryts Bruk, Örebro.\nTelefon: Hjortkvarn 16. Postgiro: 80656.\nEnsamförsälj.: Söderberg &amp; Haak AB.,\nStockholm, Drottningg. 2. Telefon:\n»Söderberg &amp; Haak». Postgiro: 501.\n\nAkt.-kap.: 1,000,000 kr. Antal\nindustriarb.: 80. Tillv.-värde pr år: 2,500,000 kr.\n—- Bolaget grundat 1905.\n\nStyrelse: generalkonsul Ragnar\nSöderberg (ordf.), disp. Gust. Kihlgren,\ngeneralkonsul Torsten O. Söderberg.\n\nVerkst. dir. o. disp.: Gust. Kihlgren.\n\nKamrer: Nils Larsson.\n\n*Crytgöls Bruks AB., Grytgöl\n\nTråddrageri-, spik- och\nstängselnät-fabrik samt järnmanufakturverk vid\nGrytgöl (Östergötl. l.).\n\nTillverkar blank, förkopprad, glödgad,\nförzinkad och förtent järntråd, häfttråd,\nstängselnät, trådspik, krampor samt\nstålmöbler och järnmanufakturvaror.\nBolaget driver jämväl sågverksrörelse samt\njord- och skogsbruk.\n\nTeleffr.-adr.: Grytgöl, Grytgöl.\nTelefon: Grytgöl # 36—41. Postgiro: 6617.\nGodsadr.: Ljusf allshammar. Repr. i\nStockholm: Carl Bursell, Kaptensg. 14,\ntelefon: 605501 o. 628549.\n\nAkt.-kap.: 325,000 kr. Antal\nindustriarb.: 130. Tillv.-värde pr år: 2,300,000 kr.\n\nTråddrageriet anlagt på 1880-talet,\nombyggt 1918, bolaget grundat 1893.\n\nStyrelse: kapten Arv. Buren (ordf.),\ndisp. C. D. Buren, överstelöjtn. Torsten\nHagstedt.\n\nVerkst. dir.: Arv. Buren.\n\nV. verkst. dir..- Torsten Hagstedt.\n\nKamrer: Ivar Ringdahl.\n\nDriftsing.: Olof Buren.\n\nFörsäljn.-chef: C. Georg Carlsson.\n\n*AB. Crythytte Skifferverk,\n\nGrythyttan.\n\nSkifferverk vid Grvthyttan (Örebro l.).\nBryter svart urlerskiffer samt tillverkar\ntakskiffer, skifferhällar till\ngårdsbeläggning och sockelbeklädnad, hyvlade och\nslipade skifferplattor för elektriska och\nbyggnadsändamål m. m. samt\nmöbelplattor. Utför genom egna resetäckare\ntaktäckningar med skiffer samt med\nimpregnerade furuspån.\n\nTelegr.-adr.: Skifferverket, Grythyttan.\nTelefon: 1 o. 69. Postgiro: 33470.\n\nAkt.-kap.: 100.000 kr. Antal\nindustriarb.: 80. Tillv.-värde pr år: 500,000 kr.\n\nSkifferfyndigheterna bearbetas sedan\n1790-talet, aktiebolaget grundat 1917.\n\nStyrelse: bruksäg. Carl E. Carlsson\n(ordf.), dir. P. Eg. Gummeson, civiling.\nVincent Spak.\n\nDisp.: Vincent Spak.\n\n*Grängesbergsbolaget, Stockholm.\n\nSe Trafik AB. Grängesberg-Oxelösund,\nStockholm.\n\n*\tGrängesbergs Bryggeri,\n\nGrängesberg.\n\nSkattepliktigt bryggeri i Grängesberg\n(Kopparb. l.). Tillverkar maltdrycker.\n\nTelefon: 33. — Arb.-antal: 12.\nTillv.-värde pr år: 300,000 kr. — Bryggeriet\nan la ert 1898.\n\nÄgare: bryggm. Louis Spendrup.\n\nBryggeriförest.: Edvin Jakobsson.\n\n*\tGränsf ors Bruks A B., Bergsjö.\n\nManufaktursmedja vid Bergsjö (Gävleb.\n1.). Tillverkar yxor, bilor och barkspadar\nsamt svartsmiden såsom flåhackor,\njord-hackor, timmerredskap och hakgångjärn\nm. m.",
    "structured": {
        "1": {
            "name": "Grycksbo Pappersbruk AB.",
            "location": "Grycksbo",
            "business": "Pappersbruk med cellulosafabriker",
            "products": "skrivpapper, tryckpapper, kraftpapper, rit-papper, filtrerpapper, kartonger",
            "contact": {
                "office": "Munktell, Grycksbo",
                "phone": [
                    "Grycksbo Pappersbruk, Falun"
                ],
                "postgiro": "72424"
            },
            "financials": {
                "capital": "4,500,000 kr",
                "employees": {
                    "industriarb.": 800
                },
                "annual_turnover": "18,000 ton papper"
            },
            "foundation_year": 1740,
            "current_name_year": 1939,
            "board": [
                {
                    "name": "disp. H. Hanngren",
                    "role": ""
                },
                {
                    "name": "ing. A. M. Munktell",
                    "role": ""
                },
                {
                    "name": "prof. Henrik Munktell",
                    "role": ""
                },
                {
                    "name": "kapten William Nisser",
                    "role": ""
                }
            ],
            "director": "William Nisser",
            "managing_director": "E. Mide",
            "sales_manager": "A. Goliath"
        },
        "2": {
            "name": "AB. Gryts Bruk",
            "location": "Hjortkvarn",
            "business": "Tråddrageri och galvaniseringsverk",
            "products": "blank, för-kopprad, galvaniserad och glödgad järntråd, trådspik",
            "contact": {
                "office": "Björnhammar, Hjortkvarn",
                "phone": [
                    "Hjortkvarn 16"
                ],
                "postgiro": "80656"
            },
            "financials": {
                "capital": "1,000,000 kr",
                "employees": {
                    "industriarb.": 80
                },
                "annual_turnover": "2,500,000 kr"
            },
            "foundation_year": 1905,
            "board": [
                {
                    "name": "generalkonsul Ragnar Söderberg",
                    "role": "ordf."
                },
                {
                    "name": "disp. Gust. Kihlgren",
                    "role": ""
                },
                {
                    "name": "generalkonsul Torsten O. Söderberg",
                    "role": ""
                }
            ],
            "director": "Gust. Kihlgren",
            "manager": "Nils Larsson"
        },
        "3": {
            "name": "AB. Grytgöls Bruks AB.",
            "location": "Grytgöl",
            "business": "Tråddrageri-, spik- och stängselnät-fabrik",
            "products": "blank, förkopprad, glödgad, förzinkad och förtent järntråd, häfttråd, stängselnät, trådspik, krampor, stålmöbler, järnmanufakturvaror",
            "contact": {
                "office": "Grytgöl, Grytgöl",
                "phone": [
                    "Grytgöl # 36—41"
                ],
                "postgiro": "6617"
            },
            "financials": {
                "capital": "325,000 kr",
                "employees": {
                    "industriarb.": 130
                },
                "annual_turnover": "2,300,000 kr"
            },
            "board": [
                {
                    "name": "kapten Arv. Buren",
                    "role": "ordf."
                },
                {
                    "name": "disp. C. D. Buren",
                    "role": ""
                },
                {
                    "name": "överstelöjtn. Torsten Hagstedt",
                    "role": ""
                }
            ],
            "director": "Arv. Buren",
            "manager": "Ivar Ringdahl"
        },
        "4": {
            "name": "AB. Crythytte Skifferverk",
            "location": "Grythyttan",
            "business": "Skifferverk",
            "products": "takskiffer, skifferhällar, skifferplattor för elektriska och byggnadsändamål, möbelplattor",
            "contact": {
                "office": "Skifferverket, Grythyttan",
                "phone": [
                    "1",
                    "69"
                ],
                "postgiro": "33470"
            },
            "financials": {
                "capital": "100,000 kr",
                "employees": {
                    "industriarb.": 80
                },
                "annual_turnover": "500,000 kr"
            },
            "board": [
                {
                    "name": "bruksäg. Carl E. Carlsson",
                    "role": "ordf."
                },
                {
                    "name": "dir. P. Eg. Gummeson",
                    "role": ""
                },
                {
                    "name": "civiling. Vincent Spak",
                    "role": ""
                }
            ],
            "director": "",
            "managing_director": "",
            "manager": ""
        },
        "5": {
            "name": "Grängesbergs Bryggeri",
            "location": "Grängesberg",
            "business": "Bryggeri",
            "products": "maltdrycker",
            "contact": {
                "phone": [
                    "33"
                ],
                "postgiro": ""
            },
            "financials": {
                "employees": {
                    "Arb.-antal": 12
                },
                "annual_turnover": "300,000 kr"
            },
            "foundation_year": 1898,
            "owners": [
                "bryggm. Louis Spendrup"
            ],
            "director": "",
            "manager": "Edvin Jakobsson"
        },
        "6": {
            "name": "Gränsfors Bruks A B.",
            "location": "Bergsjö",
            "business": "Manufaktursmedja",
            "products": "yxor, bilor och barkspadar, svartsmiden såsom flåhackor, jord-hackor, timmerredskap, hakgångjärn",
            "contact": {
                "office": "",
                "phone": [],
                "postgiro": ""
            },
            "financials": {
                "employees": {},
                "annual_turnover": ""
            },
            "board": [],
            "director": "",
            "manager": ""
        }
    }
}