{
    "original": "Trané—(Transport emballage\n\nKontor: Stockholm, Gustaf Adolfs\nTorg- 18. Telegr.-adresser: Trafikbola^et.\nMalmexport o. Malmfartyg, Stockholm.\nTelefon: »Grängesbergsbolaget».\nPostgiro: 3141.\n\nAkt.-kap.: 119,000,000 kr.\n\nBolaget, som grundades 1896, äger\nhälften (alla stamaktierna) i\nLuossavaara-Kiirunavaara AB., Stockholm.\n\nStyrelse: f. d. justitierådet Rudolf\nEklund (ordf.), överståthållare Torsten\nNo-thin (statens ombud), bankdir. Ernst\nC:son Herslow, fil. dr Erik Kempe. fil.\ndr Sigurd Nauckhoff, dir. Martin\nWaldenström, dir. P. O. Westerberg.\n\nVerkst. dir.: Martin Waldenström.\n\nDirektörer: B. Forsgrén o. P. O.\nWick-man.\n\nGruvdir.: Hugo Gårde.\n\nRederidir.: H. Hoogland.\n\nKamrerare: Gottfr. Hesselgren, A. F.\nMoberg o. Hugo Åberg.\n\n\"AB. Trané, Stockholm.\n\nMössfabrik. Tillverkar mössor,\nspeciellt sport- och skidmössor. Varumärke:\n»Trané».\n\nKontor: Götg. 24. Telefon: 419220.\nPostgiro: 2226. — Akt.-kap.: 15,000 kr.\nAntal industriarb.: 15. — Bolaget\ngrundat 1928.\n\nStyrelse o. verkst. dir.: fabr. Eskil\nTrané.\n\n*Tranemo Cementvaru AB.,\n\nTranemo.\n\nBetongvarufabrik i Tranemo (Älvsb. l.).\nTillverkar avloppsrör, vägtrummor,\nbrunnsringar, trottoarplattor,\nbyggnadssten, trappsteg m. m.\n\nTelefon: Svenliunga 70150. Postgiro:\n81450. — Akt.-kap.: 100,000 kr. Antal\nindustriarb.: 35. Tillv.-värde pr år: 600,000\nkr. — Bolaget grundat 1919, ombildat\n1923.\n\nStyrelse: disp. Waldemar Hermanson\n(ordf.), fru Anna Hermanson, arkitekt\nFolke Hermanson, verkm. Per Anders\nHermanson.\n\nVerkst. dir.: Waldemar Hermanson.\n\nTranemo Textil AB.,\n\nTranemo.\n\nTillverkar arbetskläder och\nsportdräkter vid fabrik i Tranemo (Älvsb. l.).\n\nTelefon: Svenljunga 70066. Postgiro:\n88336. — Akt.-kap.: 35,200 kr. Antal\nindustriarb.: 70. — Bolaget grundat 1934.\n\nDisp.: Gustav Kjöllerström.\n\n\"Tranemo Trikåindustri AB.,\n\nTranemo.\n\nTillverkar stickade artiklar såsom\njumpers, koftor, slipovers, fingervantar,\nmud-dar m. m. vid trikåfabrik i Tranemo\n(Älvsb. l.).\n\nKontor: Tranemo. Telefon: Svenljunga\n70191. Postgiro: 77000. — Akt.-kap.:\n15,000 kr. Antal industriarb.: 10. —\nFirman etabl. 1945, bolag 1946.\n\nStyrelse: fabr. Carl-Gustaf Blåberg\n(ordf.), verkm. Gilbert Bringle.\n\nVerkst. dir.: Carl-Gustaf Blåberg.\n\n\"Tranemo Yllefabriks AB.,\n\nTranemo.\n\nTillverkar sport- och barnkläder samt\nstickade ytterplagg vid fabriker i\nTranemo (Älvsb. l.) och Smålands Burseryd\n(Jönköp. l.).\n\nKontor: Tranemo. Telefon: Svenljunga\n70140. Postgiro: 94111.\n\nAkt.-kap.: 250,000 kr. Antal\nindustriarb.: 135 (ävensom 250 hemarbetare).\nTillv.-värde pr år: 2,800,000 kr. —\nBolaget grundat 1935.\n\nStyrelse: dir. Knut Palmquist (ordf.),\nfru S. Palmquist.\n\nVerkst. dir.: Knut- Palmquist.\n\nDisp.: Carl Eric Löfquist.\n\nKamrer: Bror Axel Löfquist.\n\n\"Transformatorfabriken, Svenska,\n\nLinköping.\n\nSe AB. Svenska Transformatorfabriken,\nLinköping.\n\nTransjö Glasbruk, R. 0. Brauer &amp;\nCo., Kosta.\n\nGlasbruk vid Transjö, Kosta (Kronob.\n1.). Tillverkar hushållsglas, servisglas,\n\nprydnadsglas och tekn. glas.\n\nTelefon: Kosta 7. Postgiro: 32423. —\nAntal industriarb.: 50. — Firman etabl.\n1870.\n\nÄgare o. chefer: disp. Bengt Brauer o.\ning. Magnus Brauer.\n\nTransportbolaget, Stockholm.\n\nSe Stockholms Transport- o. Bogserings\nAB., Stockholm.\n\nAB. Transportembaliage, Örebro.\n\nWellpappfabrik. Tillverkar\nwellpappkartonger och wellpapp i rullar.\n\nPostadr.: Örebro 3. Telefon: 15820 o.\n21240. Postgiro: 170422.\n\n584*",
    "structured": {
        "1": {
            "name": "AB. Trané",
            "location": "Stockholm",
            "business": "Malmexport o. Malmfartyg",
            "contact": {
                "office": "Gustaf Adolfs Torg-18",
                "phone": [
                    "Grängesbergsbolaget"
                ],
                "postgiro": "3141"
            },
            "financials": {
                "capital": "119,000,000 kr"
            },
            "foundation_year": 1896,
            "board": [
                {
                    "name": "Rudolf Eklund",
                    "role": "ordförande"
                },
                {
                    "name": "Torsten Nothin",
                    "role": "statens ombud"
                },
                {
                    "name": "Ernst C:son Herslow",
                    "role": "bankdirektör"
                },
                {
                    "name": "Erik Kempe",
                    "role": "fil dr"
                },
                {
                    "name": "Sigurd Nauckhoff",
                    "role": "fil dr"
                },
                {
                    "name": "Martin Waldenström",
                    "role": "direktör"
                },
                {
                    "name": "P. O. Westerberg",
                    "role": "direktör"
                }
            ],
            "owners": [
                "Luossavaara-Kiirunavaara AB."
            ],
            "director": "B. Forsgrén",
            "managing_director": "P. O. Wickman",
            "sales_manager": "Hugo Gårde"
        },
        "2": {
            "name": "AB. Trané",
            "location": "Stockholm",
            "business": "Mössfabrik",
            "products": "Tillverkar mössor, speciellt sport- och skidmössor. Varumärke: »Trané»",
            "contact": {
                "office": "Götgatan 24",
                "phone": [
                    "419220"
                ],
                "postgiro": "2226"
            },
            "financials": {
                "capital": "15,000 kr"
            },
            "foundation_year": 1928,
            "board": [
                {
                    "name": "Eskil Trané",
                    "role": "styrelse o. verkst. dir."
                }
            ]
        },
        "3": {
            "name": "Tranemo Cementvaru AB.",
            "location": "Tranemo",
            "business": "Betongvarufabrik",
            "products": "Tillverkar avloppsrör, vägtrummor, brunnsringar, trottoarplattor, byggnadssten, trappsteg m. m.",
            "contact": {
                "phone": [
                    "Svenliunga 70150"
                ],
                "postgiro": "81450"
            },
            "financials": {
                "capital": "100,000 kr",
                "annual_turnover": "600,000 kr"
            },
            "foundation_year": 1919,
            "corporation_year": 1923,
            "board": [
                {
                    "name": "Waldemar Hermanson",
                    "role": "disp."
                },
                {
                    "name": "Anna Hermanson",
                    "role": "styrelse"
                },
                {
                    "name": "Folke Hermanson",
                    "role": "arkitekt"
                },
                {
                    "name": "Per Anders Hermanson",
                    "role": "verkm."
                }
            ],
            "director": "Waldemar Hermanson"
        },
        "4": {
            "name": "Tranemo Textil AB.",
            "location": "Tranemo",
            "business": "Tillverkar arbetskläder och sportdräkter",
            "contact": {
                "phone": [
                    "Svenljunga 70066"
                ],
                "postgiro": "88336"
            },
            "financials": {
                "capital": "35,200 kr"
            },
            "foundation_year": 1934,
            "board": [
                {
                    "name": "Gustav Kjöllerström",
                    "role": "disp."
                }
            ]
        },
        "5": {
            "name": "Tranemo Trikåindustri AB.",
            "location": "Tranemo",
            "business": "Tillverkar stickade artiklar",
            "products": "Jumpers, koftor, slipovers, fingervantar, muddar m. m.",
            "contact": {
                "office": "Tranemo",
                "phone": [
                    "Svenljunga 70191"
                ],
                "postgiro": "77000"
            },
            "financials": {
                "capital": "15,000 kr"
            },
            "foundation_year": 1945,
            "corporation_year": 1946,
            "board": [
                {
                    "name": "Carl-Gustaf Blåberg",
                    "role": "styrelse o. verkst. dir."
                },
                {
                    "name": "Gilbert Bringle",
                    "role": "verkm."
                }
            ]
        },
        "6": {
            "name": "Tranemo Yllefabriks AB.",
            "location": "Tranemo",
            "business": "Tillverkar sport- och barnkläder samt stickade ytterplagg",
            "products": "Sportkläder, barnkläder, stickade ytterplagg",
            "contact": {
                "office": "Tranemo",
                "phone": [
                    "Svenljunga 70140"
                ],
                "postgiro": "94111"
            },
            "financials": {
                "capital": "250,000 kr",
                "annual_production_value": "2,800,000 kr"
            },
            "foundation_year": 1935,
            "board": [
                {
                    "name": "Knut Palmquist",
                    "role": "dir."
                },
                {
                    "name": "S. Palmquist",
                    "role": "fru"
                }
            ]
        },
        "7": {
            "name": "Transformatorfabriken, Svenska",
            "location": "Linköping"
        },
        "8": {
            "name": "Transjö Glasbruk",
            "location": "Kosta",
            "products": "Hushållsglas, servisglas, prydnadsglas och tekn. glas",
            "contact": {
                "phone": [
                    "Kosta 7"
                ],
                "postgiro": "32423"
            },
            "foundation_year": 1870,
            "owners": [
                "R. 0. Brauer & Co."
            ],
            "director": "disp. Bengt Brauer",
            "manager": "ing. Magnus Brauer"
        },
        "9": {
            "name": "Transportbolaget",
            "location": "Stockholm"
        },
        "10": {
            "name": "AB. Transportembaliage",
            "location": "Örebro",
            "business": "Wellpappfabrik",
            "products": "Tillverkar wellpappkartonger och wellpapp i rullar",
            "contact": {
                "postadr": "Örebro 3",
                "phone": [
                    "15820",
                    "21240"
                ],
                "postgiro": "170422"
            }
        }
    }
}