{
    "original": "Örgry teverken—Österby\n\nÖrgryteverken AB., Göteborg.\n\nPlåtslageri och mek. verkstad.\nTillverkar fläktar för ventilations- och\nindustriella ändamål, lamellbatterier,\noljeavskil-jare, textilmaskiner och\ntorvkolnings-ugnar (system: »Pilo»); utför svetsade\nplåtarbeten och järnkonstruktioner.\n\nKontor: Elisedal 7. Telegr.-adr.:\nTox-verk, Göteborg. Telefon: 183345. —\nAkt.-kap.: 135,000 kr. Antal industriarb.: 100.\n\n—\tBolaget grundat 1940 under namn\nFläkt- &amp; Plåtsvetsning i Göteborg AB.,\nnuv. namn 1944.\n\nVerkst. dir.: ing. Tom O. Biéth.\n\n\"Örnen, Nya Skofabriks AB., Örebro.\n\nSe Nya Skofabriks AB. örnen, Örebro.\n\nAB. Örnmaskiner, Storebro.\n\nTillverkar snabbsvarvar och\nmed-bringare vid mek. verkstad i Storebro\n(Kalmar l.).\n\nTelefon: 22 o. 23. Postgiro: 95420. —\nAkt.-kap.: 75,000 kr. Ailtal industriarb.:\n75. Tillv.-värde pr år: 1,200,000 kr. —\nFirman etabl. 1933, bolag 1945.\n\nVerkst. dir.: disp. Ivar Gustafsson.\n\nÖrnäs Produkter AB., Kungsängen.\n\nKonservfabrik i Kungsängen\n(Uppsala l.). Tillverkar sylt, syltade frukter,\nmarmelader, safter och fruktkonserver.\n\nKontor: Kungsängen. Telefon: 70.\nPostgiro: 293853. Försäljn.-kontor:\nStockholm, Birger Jarlsg. 32, telefon: 200778.\n\n—\tAkt.-kap.: 60,000 kr. Antal\nindustriarb.: 17. Tillv.-värde pr år: 1,140,000 kr.\n\n—\tFirman etabl. 1935.\n\nDisp.: Richard Bodén.\n\n\"Östansjö Skoindustri, Östansjö.\n\nTillverkar herr- och damskodon vid\nfabrik i Östansjö (Örebro l.).\n\nTelefon: 21. Postgiro: 167915. —\nAntal industriarb.: 60. Tillv.-värde pr år:\n600,000 kr. — Firman etabl. 1930.\n\nÄgare o. chefer: fabr. John Knutsson\no. fabr. Einar Andersson.\n\n\"Östanå Fabriks ABGlimminge.\n\nSågverk och elektr. kraftverk i östanå,\nGlimminge (Kristianst. l.). Tillverkar\nsågade trävaror samt distribuerar elektr.\nenergi.\n\nTelefon: östanåbruk 3 o. Osby 4.\nPostgiro: 23789.\n\nAkt.-kap.: 215,000 kr. Arb.-antal: 10.\n\n—\tBolaget grundat 1885.\n\nStyrelse: bergsing, Gustaf Ekman, disp.\nJohan Ekman, godsäg. Folke Sederholm.\n\nDisp.: Johan Ekman.\n\nAB. Östanå Pappersbruk, Lund.\n\nTillverkar finpapper såsom post-,»\nskriv-, tryck- och offsetpapper m. m. vid\npappersbruk i östanå, Glimminge\n(Kristianst. l.).\n\nKontor: Lund. Telegr.-adr.:\nöstanå-papper, Lund. Telefon: »Åkerlund &amp;\nRau-sing». Postgiro: 270256.\n\nAkt.-kap.: 300,000 kr. Antal\nindustriarb.: 75. Årstillv.: 4,000 ton papper. —\nPappersbruket anlagt 1904, nuv. bolag,,\ngrundat 1943, är anslutet till AB.\nÅkerlund &amp; Rausing, Lund.\n\nStyrelse: dir. Ruben Rausing (ordf.)*\ndir. Holger Crafoord, bankdir. Göte\nEng-fors, adv. Cecil Rausing.\n\nVerkst. dir.: Holger Crafoord.\n\nFörsäljn.-chef: Ebbe Nihlberg.\n\nDisp.: ing. Fritiof Svensson.\n\nÖstanåsågen, Nya AB., Ovanåker.\n\nSe Nya AB. östanåsågen, Ovanåker.\n\nÖstblads Skridskofabrik, Järna.\n\nTillverkar rör skridskor samt\nskålslip-ningsmaskiner för skridskor vid fabrik i\nJärna (Sthlms l.).\n\nTelefon: 93. Postgiro: 31619. — Antal\nindustriarb.: 24. Tillv.-värde pr år:\n200,000 kr. — Firman etabl. 1926.\n\nÄgare o. chef: fabr. Johan östblad.\n\n\"AB. Aug. österberg, Örebro.\n\nKartong- och emballagefabrik.\nTillverkar kartonger, burkar helt av papp eller\nmed lock och botten av plåt samt\nimpregnerade pappaskar.\n\nTelefon: 10111 o. 11111. Postgiro:\n20788.\n\nAkt.-kap.: 60,000 kr. Antal\nindustriarb.: 60. Tillv.-värde pr år: 900,000 kr.\n— Firman etabl. 1871, bolag 1912.\n\nStyrelse: disp. Arvid österberg (ordf.),\nfabr. Erik österberg, järnhandl. Robert\nösterberg.\n\nDisp.: Arvid österberg.\n\nDisp.-assist..- Ragnar Dahl.\n\n\"Österby Jernverks AB.,\n\nÖsterbybruk.\n\nMasugnar vid Gimo, masugn,\nmartin-och elektrostålugnar, stålsmedja, valsverk,\nmaskinknivverkstad, wallonsmedja,\nstålgjuteri och mek. verkstad i österby (båda\ni Uppsala l.).\n\n652*",
    "structured": {
        "1": {
            "name": "Örgryteverken AB.",
            "location": "Göteborg",
            "business": "Plåtslageri och mek. verkstad",
            "products": "Tillverkar fläktar för ventilations- och industriella ändamål, lamellbatterier, oljeavskil-jare, textilmaskiner och torvkolnings-ugnar (system: »Pilo»); utför svetsade plåtarbeten och järnkonstruktioner.",
            "contact": {
                "office": "Elisedal 7",
                "telegraph": "Tox-verk, Göteborg",
                "phone": [
                    "183345"
                ]
            },
            "financials": {
                "capital": "135,000 kr",
                "employees": {
                    "industriarb": 100
                }
            },
            "foundation_year": 1940,
            "current_name_year": 1944,
            "director": "ing. Tom O. Biéth"
        },
        "2": {
            "name": "Örnäs Produkter AB.",
            "location": "Kungsängen",
            "business": "Konservfabrik",
            "products": "Tillverkar sylt, syltade frukter, marmelader, safter och fruktkonserver.",
            "contact": {
                "office": "Kungsängen",
                "phone": [
                    "70"
                ],
                "postgiro": "293853",
                "sales_offices": [
                    {
                        "location": "Stockholm",
                        "phone": "200778"
                    }
                ]
            },
            "financials": {
                "capital": "60,000 kr",
                "employees": {
                    "industriarb": 17
                }
            },
            "foundation_year": 1935,
            "director": "Richard Bodén"
        },
        "3": {
            "name": "Örnen, Nya Skofabriks AB.",
            "location": "Örebro",
            "predecessor": "Nya Skofabriks AB. örnen"
        },
        "4": {
            "name": "AB. Örnmaskiner",
            "location": "Storebro",
            "business": "Tillverkar snabbsvarvar och med-bringare vid mek. verkstad",
            "contact": {
                "phone": "22 o. 23",
                "postgiro": "95420"
            },
            "financials": {
                "capital": "75,000 kr",
                "employees": {
                    "industriarb": 75
                },
                "annual_production_value": "1,200,000 kr"
            },
            "foundation_year": 1933,
            "corporation_year": 1945,
            "director": "disp. Ivar Gustafsson"
        },
        "5": {
            "name": "Östansjö Skoindustri",
            "location": "Östansjö",
            "business": "Tillverkar herr- och damskodon",
            "contact": {
                "phone": "21",
                "postgiro": "167915"
            },
            "financials": {
                "employees": {
                    "industriarb": 60
                },
                "annual_production_value": "600,000 kr"
            },
            "foundation_year": 1930,
            "owners": [
                "fabr. John Knutsson",
                "fabr. Einar Andersson"
            ]
        },
        "6": {
            "name": "Östanå Fabriks AB",
            "location": "Glimminge",
            "business": "Sågverk och elektr. kraftverk",
            "products": "Tillverkar sågade trävaror samt distribuerar elektr. energi",
            "contact": {
                "phone": "östanåbruk 3 o. Osby 4",
                "postgiro": "23789"
            },
            "financials": {
                "capital": "215,000 kr",
                "employees": {
                    "Arb.-antal": 10
                }
            },
            "foundation_year": 1885,
            "board": [
                {
                    "name": "bergsing",
                    "role": "Gustaf Ekman"
                },
                {
                    "name": "disp. Johan Ekman",
                    "role": "godsäg. Folke Sederholm"
                }
            ],
            "director": "Johan Ekman"
        },
        "7": {
            "name": "AB. Östanå Pappersbruk",
            "location": "Lund",
            "business": "Tillverkar finpapper såsom post-, skriv-, tryck- och offsetpapper m. m. vid pappersbruk",
            "contact": {
                "office": "Lund",
                "telegraph": "östanå-papper, Lund",
                "phone": "Åkerlund & Rau-sing",
                "postgiro": "270256"
            },
            "financials": {
                "capital": "300,000 kr",
                "employees": {
                    "industriarb": 75
                },
                "annual_turnover": "4,000 ton papper"
            },
            "board": [
                {
                    "name": "dir. Ruben Rausing",
                    "role": "ordf."
                },
                {
                    "name": "dir. Holger Crafoord",
                    "role": "bankdir. Göte Eng-fors"
                }
            ],
            "director": "Holger Crafoord",
            "sales_manager": "Ebbe Nihlberg"
        },
        "8": {
            "name": "Östanåsågen, Nya AB.",
            "location": "Ovanåker"
        },
        "9": {
            "name": "Östblads Skridskofabrik",
            "location": "Järna",
            "business": "Tillverkar rör skridskor samt skålslip-ningsmaskiner för skridskor"
        },
        "10": {
            "name": "AB. Aug. österberg",
            "location": "Örebro",
            "business": "Kartong- och emballagefabrik",
            "products": "Tillverkar kartonger, burkar helt av papp eller med lock och botten av plåt samt impregnerade pappaskar",
            "contact": {
                "phone": "10111 o. 11111",
                "postgiro": "20788"
            },
            "financials": {
                "capital": "60,000 kr",
                "employees": {
                    "industriarb": 60
                },
                "annual_production_value": "900,000 kr"
            }
        },
        "11": {
            "name": "Österby Jernverks AB.",
            "location": "Österbybruk",
            "business": "Masugnar",
            "products": "Masugnar, martin-och elektrostålugnar, stålsmedja, valsverk, maskinknivverkstad, wallonsmedja, stålgjuteri och mek. verkstad"
        }
    }
}