{
    "original": "Dalsjöfors—-Danhult\n\nAB. Dalsjöfors Konfektionsfabrik,\n\nDalsjöfors.\n\nTillverkar herr- och gosskostymer,\nbyxor, ytterrockar m. m. vid fabrik i\nDalsjöfors (Älvsb. l.). Varumärke:\n»Da-Ko».\n\nTelefon: Borås 70206 o. 70032.\nPostgiro: 175881. — Akt.-kap.: 62,400 kr.\nAntal industriarb.: 40. Tillv.-värde pr år:\n600,000 kr. — Firman etabl. 1917, bolag\n1941.\n\nVerkst. dir.: John Svenningson.\n\n’Dalsjöfors Väveri, Dalsjöfors.\n\nSe Almedahl-Dalsjöfors AB., Göteborg.\n\nDalskogs Ångsåg &amp; Träförädlings\n\nAB., Dalskog.\n\nSågverk, hyvleri och snickerifabrik i\nDalskog (Älvsb. l.). Tillverkar\nbyggnadssnickerier och inredningar. Firman\ndriver även försäljning av byggnadsmateriel\nsåsom wallboard, plywood, cement, tegel\noch dräneringsrör.\n\nHuvudkontor: Dalskog. Telefon: 43 o.\n46. Postgiro: 80268. Avd.-kontor:\nBäckefors o. Mellerud. — Akt.-kap.: 212,000\nkr. Antal industriarb.: 40. — Firman\netabl. 1907, bolag 1927.\n\nStyrelse: dir. J. Niklas Jonasson\n(ordf.), kontorschef S. Balder, disp. Carl\nO. Jonasson.\n\nVerkst. dir.: J. Niklas Jonasson.\n\nDisp.: Carl O. Jonasson.\n\nKontorschef: S. Balder.\n\nDalslands Byggnadssnickeri AB.,\n\nÅmål.\n\nTillverkar fönster, dörrar och\nköksinredningar vid snickerifabrik i Åmål\n(Älvsb. l.).\n\nTelefon: 845. — Akt.-kap.: 30,000 kr.\nAntal industriarb.: 22. Tillv.-värde pr\når: 245,000 kr. — Bolaget grundat 1943.\n\nVerkst. dir. o. disp.: Erik Abrahamson.\n\nDamaskfabriken, AB. Svenska,\n\nStockholm.\n\nSe AB. Svenska Damaskfabriken,\nStockholm.\n\n*Dama-Verken, AB. Damm- &amp;\nSpårs-ledningar, Malmö.\n\nMek. verkstad. Tillverkar\ncentrifugal-f läktar, axialfläktar, varmluftsbatterier\noch varmluftstemprar; utför kompletta\n\npneumatiska transport-,\ndammsugnings-och ventilationsanläggningar samt\ntorkan-läggningar och\nluftkonditioneringsanläggningar, förråds- och arkivinredningar\nav stål. Varumärke: »Dama».\n\nKontor: Lantmannagat. 28—30.\nTelegr.-adr.: Ventilator, Malmö. Telefon:\n25924, 22954 o. 19954. Postgiro: 149393.\n— Akt.-kap.: 90,000 kr. Antal\nindustriarb.: 60. — Bolaget grundat 1909.\n\nStyrelse: civiling. O. Winkler (ordf.),\ning. F. Juhlin, avd.-chef A. Norén.\n\nVerkst. dir.: O. Winkler.\n\nKamrer: Carl B. Andersson.\n\nIngenjörer: Frans E. Juhlin, Allan J.\nOlsson o. Sven E. Ransmark.\n\n(Jfr annons nr 75.)\n\n*AB. Damkappor, Kristianstad.\n\nTillverkar damkappor och damdräkter.\n\nTelegr.-adr.: Distingo, Kristianstad.\nTelefon: 11297. Postgiro: 8760.\n\nAkt.-kap.: 1,250,000 kr. Antal\nindustriarb.: 280. — Bolaget grundat 1923.\n\nStyrelse: disp. David Kristensson, dir.\nBengt Lithander, dir. Georg Lithander.\n\nVerkst. dir.,- Georg Lithander.\n\nDisp.: Erik Nilsson.\n\nKontorschef: Alfhild Ringdahl.\n\nAB. Damklädningar, Borås.\n\nKonfektionsfabrik. Tillverkar\ndam-och flickklänningar, dräkter och jumpers.\nVarumärke: »Eiser».\n\nTelegr.-adr. o. telefon: Eiser, Borås.\n\nAkt.-kap.: 5,000 kr. Antal industriarb.:\n30. Tillv.-värde pr år: 200,000 kr. —\nBolaget, grundat 1940, äges av AB. Sveriges\nFörenade Trikåfabriker.\n\nStyrelse o. verkst. dir.: Carl Eiser man.\n\nDisp.: Axel Lindstedt.\n\n’AB. Damm- &amp; Spånledningar,\n\nMalmö.\n\nSe Dama-Verken, AB. Damm- &amp;\nSpånledningar, Malmö.\n\n’Danhults Tegelbruks AB.,\n\nHälsingborg.\n\nTillverkar murtegel och dräneringsrör\nvid tegelbruk i Ingelsträde (Malmöh. l.).\n\nKontor: Hälsingborg. Telefon: 10970.\nPostgiro: 14468. — Akt.:kap.: 35,300 kr.\nAntal industriarb.: 30. Årstillv.: 2 milj.\nst. tegelvaror. — Bolaget grundat 1890.\n\nVerkst. dir.: ing. Thore Lindberg.",
    "structured": {
        "1": {
            "name": "Dalsjöfors Konfektionsfabrik",
            "location": "Dalsjöfors",
            "business": "Tillverkar herr- och gosskostymer, byxor, ytterrockar m. m.",
            "products": "Varumärke: »Da-Ko»",
            "contact": {
                "office": "Dalsjöfors",
                "phone": [
                    "Borås 70206",
                    "Borås 70032"
                ],
                "postgiro": "175881",
                "head_office": "Dalsjöfors"
            },
            "financials": {
                "capital": "62,400 kr",
                "employees": {
                    "industriarb": 40
                },
                "annual_turnover": "600,000 kr",
                "annual_production_value": "600,000 kr"
            },
            "foundation_year": 1917,
            "corporation_year": 1941,
            "board": [
                {
                    "name": "John Svenningson",
                    "role": "Verkst. dir."
                }
            ]
        },
        "2": {
            "name": "Dalskogs Ångsåg & Träförädlings AB.",
            "location": "Dalskog",
            "business": "Sågverk, hyvleri och snickerifabrik",
            "products": "Tillverkar byggnadssnickerier och inredningar.",
            "contact": {
                "office": "Dalskog",
                "phone": [
                    "43",
                    "46"
                ],
                "postgiro": "80268",
                "sales_offices": [
                    {
                        "location": "Bäckefors",
                        "phone": "XX"
                    },
                    {
                        "location": "Mellerud",
                        "phone": "XX"
                    }
                ]
            },
            "financials": {
                "capital": "212,000 kr",
                "employees": {
                    "industriarb": 40
                },
                "corporation_year": 1927
            },
            "board": [
                {
                    "name": "J. Niklas Jonasson",
                    "role": "ordf."
                },
                {
                    "name": "S. Balder",
                    "role": "kontorschef"
                },
                {
                    "name": "Carl O. Jonasson",
                    "role": "disp."
                }
            ],
            "director": "J. Niklas Jonasson"
        },
        "3": {
            "name": "Dalslands Byggnadssnickeri AB.",
            "location": "Åmål",
            "business": "Tillverkar fönster, dörrar och köksinredningar"
        },
        "4": {
            "name": "Dama-Verken, AB. Damm- & Spårs-ledningar",
            "location": "Malmö",
            "business": "Mek. verkstad",
            "products": "Tillverkar centrifugal-fläktar, axialfläktar, varmluftsbatterier och varmluftstemprar",
            "contact": {
                "office": "Malmö",
                "phone": [
                    "25924",
                    "22954",
                    "19954"
                ],
                "telegraph": "Ventilator, Malmö",
                "postgiro": "149393"
            },
            "financials": {
                "capital": "90,000 kr",
                "employees": {
                    "industriarb": 60
                }
            },
            "board": [
                {
                    "name": "civiling. O. Winkler",
                    "role": "ordf."
                },
                {
                    "name": "ing. F. Juhlin",
                    "role": "ing. F. Juhlin"
                },
                {
                    "name": "avd.-chef A. Norén",
                    "role": "avd.-chef"
                }
            ],
            "director": "O. Winkler",
            "managing_director": "O. Winkler"
        },
        "5": {
            "name": "AB. Damkappor",
            "location": "Kristianstad",
            "business": "Tillverkar damkappor och damdräkter",
            "contact": {
                "office": "Kristianstad",
                "phone": "11297",
                "postgiro": "8760"
            },
            "financials": {
                "capital": "1,250,000 kr",
                "employees": {
                    "industriarb": 280
                }
            },
            "board": [
                {
                    "name": "disp. David Kristensson",
                    "role": "disp."
                },
                {
                    "name": "dir. Bengt Lithander",
                    "role": "dir."
                },
                {
                    "name": "dir. Georg Lithander",
                    "role": "dir."
                }
            ],
            "director": "Georg Lithander"
        },
        "6": {
            "name": "AB. Damklädningar",
            "location": "Borås",
            "business": "Konfektionsfabrik",
            "products": "Tillverkar dam-och flickklänningar, dräkter och jumpers.",
            "contact": {
                "office": "Borås",
                "phone": "Eiser, Borås"
            },
            "financials": {
                "capital": "5,000 kr",
                "employees": {
                    "industriarb": 30
                },
                "annual_turnover": "200,000 kr"
            },
            "board": [
                {
                    "name": "Carl Eiser man",
                    "role": "Styrelse o. verkst. dir."
                },
                {
                    "name": "Axel Lindstedt",
                    "role": "disp."
                }
            ]
        },
        "7": {
            "name": "Danhults Tegelbruks AB.",
            "location": "Hälsingborg",
            "business": "Tillverkar murtegel och dräneringsrör",
            "products": "Årstillv.: 2 milj. st. tegelvaror.",
            "contact": {
                "office": "Hälsingborg",
                "phone": "10970",
                "postgiro": "14468"
            },
            "financials": {
                "capital": "35,300 kr",
                "employees": {
                    "industriarb": 30
                }
            },
            "corporation_year": 1890,
            "board": [
                {
                    "name": "ing. Thore Lindberg",
                    "role": "Verkst. dir."
                }
            ]
        }
    }
}