{
    "original": "Lydde—Lång ed\n\nTelefon: 49 o. 258. Postgiro: 21488. —\nÅntal industriarb.: 25. Tillv.-värde pr år:\n300,000 kr — Firman etabl. 1919.\n\nÄgare o. chef: fabr. Erik P. Lindblom.\n\n* Lydde Tegelbruk, Anderson &amp;\nNilsander, Kinna.\n\nTegelbruk vid Lydde, Kinna (Älvsb. l.).\nTillverkar murtegel, gult och rött\nfasad-tegel, högporöst och lättegel, plattor,\ntak- och reveteringstegel, block-,\nmellanväggstegel, månghålstegel samt\ndräneringsrör.\n\nTelefon: Kinna 10024. Postgiro: 72899.\n\n—\tAntal industriarb.: 46. Årstillv.: 4\nmilj. st. tegelvaror. — Tegelbruket anlagt\n1879, nuv. firma etabl. 1915.\n\nÄgare o. chef: fabr. J. Nilsander.\n\n\"AB. Lysekils Emballagefabrik,\n\nLysekil.\n\nBleckemballagef abrik och\nbleckplåtstryckeri. Tillverkar som specialiteter\nkonservemballage och konservnycklar.\n\nTelefon: »Plåtmanufaktur». Postgiro:\n132955. Huvudkontor: AB.\nPlåtmanufaktur, Stockholm, Biblioteksg. 26,\ntelefon: 235700.\n\nAkt.-kap.: 100,000 kr. Antal\nindustriarb.: 130. — Firman, etabl. 1937, är\nansluten till AB. Plåtmanufaktur (se detta\nbolag).\t’\n\nStyrelse: disp. Gunnar Flodin, dir.\nKnut Laurin, dir. Börje Svenby, adv.\nClas Östberg.\n\nVerkst. dir.: Knut Laurin (Stockholm).\nDisp.: Gunnar Flodin.\n\nAB. Lysekils Konservfabrik,\n\nLysekil.\n\nTillverkar ansjovis, sillinläggningar,\nkaviar samt fiskkonserver, musslor m. m.\nVarumärken: »Ocean», »Monark» o.\n»Pirat».\n\nTelegr.-adr.: Oceankonserv, Lysekil.\nTelefon: 72. Postgiro: 70115.\n\nAkt.-kap.: 45,000 kr. Antal\nindustriarb.: 25. Tillv.-värde pr år: 500,000 kr.\n\n—\tFirman etabl. 1898, bolag 1937.\nVerkst. dir.: disp. Ivar Havstam.\n\nAB. Lysekils Stenindustri,\n\nStrömstad.\n\nGranitbrott och stenhuggerier på flera\nplatser i Bohuslän. Tillverkar gat-,\nkaj-och kantsten, byggnadssten, råblock m. m.\n\nTelefon: 11. Postgiro: 172210. —\nAkt.-kap.: 200,000 kr. Antal industriarb.: 40.\n\n—\tBolaget grundat 1917.\nVerkst. dir.: Y. Septus-Larsen.\n\nLyths Instrumentfabrik, Stockholm.\nSe Instrumentfabr. AB. Lyth, Stockholm.\n\n\"Lyxmöbelfabriken, Blikstorp.\n\nSe Svenska Lyxmöbelfabriken,\nBlikstorp.\n\n\"AB. Långasjönäs Pappersbruk,\n\nKisa.\n\nPappersbruk vid Forså, Kisa (Östergötl.\n1.). Tillverkar cellulosavadd, handgjort\nfiltrer- och karduspapper, filtermassa för\nbryggerier, oljefiltrerpapper,\ngrålump-papper, toalettpapper, M. G. sulfit- och\nM. G. Cappapper, mösspapp, papp till\nslip- och polérskivor m. m.\n\nTelegr.-adr.: Långasjönäs, Kisa.\nTelefon: 119. Postgiro: 8015.\n\nAgenter för utlandet: Ekmans Export\nAB., Packhusplatsen 2, Göteborg o. George\nHarrison Agencies Ltd., 22 Upper Thames\nStreet, London E. C. 4.\n\nAkt.-kap.: 225,000 kr. Antal\nindustriarb.: 45. Årstillv.: 1,800 ton\ncellulosavadd, 2,500 ton M. G.-papper samt 400\nton handgjort papper och papp.\n\nFirman etabl. 1800, bolag 1935.\n\nStyrelse: ing. Kurt V:son Sandberg,\ning. Victor Sandberg, fru I. öman.\n\nDisp.: Kurt V:son Sandberg.\n\n\"Långbans Cruvbolag, Långban.\nSe Grufve AB. Långban, Långban.\n\nAB. Långebro Mek. Werkstad,\n\nLångebro.\n\nMek. verkstad, gjuteri och\nkopparsla-geri i Långebro (Kristianst. l.).\nTillverkar apparater, redskap och utrustningar\nför brännerier, stärkelsefabriker,\nmuste-rier och fruktkonservfabriker,\nångpannor och andra kärl under tryck, pumpar,\nhissar, transportanordningar,\npackningsmaskiner m. m.; utför elsvetsning och\nmetallisering.\n\nTelefon: Kristianstad 10409. Postgiro:\n80744. — Akt.-kap. 70,000 kr. Antal\nindustriarb.: 50. Tillv.-värde pr år:\n350,000 kr. — Bolaget grundat 1903.\n\nVerkst. dir.: Carl Björklund.\n\n\"Långeds Pappersbruk, Lång ed.\n\nSe AB. Billingsfors-Långed, Billings-\n\nfors.\n\n*",
    "structured": {
        "1": {
            "name": "Lydde Tegelbruk, Anderson & Nilsander",
            "location": "Kinna (Älvsb. l.)",
            "business": "Tegeltillverkning",
            "products": "Murtegel, gult och rött fasad-tegel, högporöst och lättegel, plattor, tak- och reveteringstegel, block-, mellanväggstegel, månghålstegel samt dräneringsrör.",
            "contact": {
                "phone": [
                    "Kinna 10024"
                ],
                "postgiro": "72899"
            },
            "financials": {
                "employees": {
                    "industriarb": 46
                },
                "annual_turnover": "4 milj. kr",
                "annual_production_value": "4 milj. st. tegelvaror"
            },
            "foundation_year": 1915,
            "predecessor": "Tegelbruket anlagt 1879",
            "director": "fabr. J. Nilsander"
        },
        "2": {
            "name": "AB. Lysekils Emballagefabrik",
            "location": "Lysekil",
            "business": "Bleckemballagef abrik och bleckplåtstryckeri",
            "products": "Konservemballage och konservnycklar",
            "contact": {
                "telegraph": "Plåtmanufaktur, Stockholm",
                "postgiro": "132955",
                "head_office": "AB. Plåtmanufaktur, Stockholm, Biblioteksg. 26, telefon: 235700"
            },
            "financials": {
                "capital": "100,000 kr",
                "employees": {
                    "industriarb": 130
                }
            },
            "foundation_year": 1937,
            "board": [
                {
                    "name": "disp. Gunnar Flodin",
                    "role": null
                },
                {
                    "name": "dir. Knut Laurin",
                    "role": null
                },
                {
                    "name": "dir. Börje Svenby",
                    "role": null
                },
                {
                    "name": "adv. Clas Östberg",
                    "role": null
                }
            ],
            "director": "Knut Laurin",
            "managing_director": "Gunnar Flodin"
        },
        "3": {
            "name": "AB. Lysekils Konservfabrik",
            "location": "Lysekil",
            "business": "Fiskkonservering",
            "products": "Ansjovis, sillinläggningar, kaviar samt fiskkonserver, musslor m.m.",
            "contact": {
                "telegraph": "Oceankonserv, Lysekil",
                "phone": [
                    "72"
                ],
                "postgiro": "70115"
            },
            "financials": {
                "capital": "45,000 kr",
                "employees": {
                    "industriarb": 25
                },
                "annual_turnover": "500,000 kr"
            },
            "foundation_year": 1937,
            "director": "disp. Ivar Havstam"
        },
        "4": {
            "name": "AB. Lysekils Stenindustri",
            "location": "Strömstad",
            "business": "Granitbrott och stenhuggerier",
            "products": "Gat-, kaj-och kantsten, byggnadssten, råblock m.m.",
            "contact": {
                "phone": [
                    "11"
                ],
                "postgiro": "172210"
            },
            "financials": {
                "capital": "200,000 kr",
                "employees": {
                    "industriarb": 40
                }
            },
            "foundation_year": 1917,
            "director": "Y. Septus-Larsen"
        },
        "5": {
            "name": "Lyths Instrumentfabrik",
            "location": "Stockholm",
            "director": null
        },
        "6": {
            "name": "AB. Långasjönäs Pappersbruk",
            "location": "Kisa",
            "business": "Pappersbruk",
            "products": "Cellulosavadd, handgjort filter- och karduspapper, filtermassa för bryggerier, oljefiltrerpapper, grålump-papper, toalettpapper, M. G. sulfit- och M. G. Cappapper, mösspapp, papp till slip- och polérskivor m.m.",
            "contact": {
                "telegraph": "Långasjönäs, Kisa",
                "phone": [
                    "119"
                ],
                "postgiro": "8015"
            },
            "financials": {
                "capital": "225,000 kr",
                "employees": {
                    "industriarb": 45
                },
                "annual_turnover": null
            },
            "foundation_year": 1935,
            "board": [
                {
                    "name": "ing. Kurt V:son Sandberg",
                    "role": null
                },
                {
                    "name": "ing. Victor Sandberg",
                    "role": null
                },
                {
                    "name": "fru I. öman",
                    "role": null
                }
            ],
            "director": "Kurt V:son Sandberg"
        },
        "7": {
            "name": "AB. Långebro Mek. Werkstad",
            "location": "Långebro (Kristianst. l.)",
            "business": "Mek. verkstad, gjuteri och koppar-sla-geri",
            "products": "Apparater, redskap, utrustningar, ångpannor, pumpar, hissar, transportanordningar, packningsmaskiner m.m.; utför elsvetsning och metallisering",
            "contact": {
                "phone": [
                    "Kristianstad 10409"
                ],
                "postgiro": "80744"
            },
            "financials": {
                "capital": "70,000 kr",
                "employees": {
                    "industriarb": 50
                },
                "annual_turnover": "350,000 kr"
            },
            "foundation_year": 1903,
            "director": "Carl Björklund"
        },
        "8": {
            "name": "AB. Långeds Pappersbruk",
            "location": "Långed",
            "director": null
        }
    }
}