{
    "original": "Finne—-\n\n-Fintling\n\n*Finnés Snickerifabriks AB.,\n\nLingbo.\n\nSågverk, hyvleri och snickerifabrik i\nLingbo (Gävleb. l.). Tillverkar sågade\noch hyvlade trävaror, byggnadssnickerier,\nträkol och gengaskol.\n\nTelefon: 11. Postgiro: 73654.\n—Akt.-kap.: 406,000 kr. Antal industriarb.: 90.\nTillv.-värde pr år: 1,500,000 kr. —\nFirman etabl. 1894, bolag 1928.\n\nStyrelse: ing. Walo Finne (ordf.),\ndisp. Helmer Finne, kamrer J. B.\nForsblom.\n\nDisp.: Helmer Finne.\n\n*Finnmosse Crufbolag, Persberg.\nSe Uddeholms AB., Uddeholm.\n\n*AB. C. E. Finquists Verkstäder,\n\nÄlvsjö.\n\nMek. verkstad i Älvsjö, Stockholm.\nTillverkar snack- och\nprecisionskuggväx-lar, kuggväxelmotorer, kugghjul,\nkätting-hjul samt elastiska kopplingar.\n\nTelefon: 472540—43. Postgiro: 25158.\nAkt.-kap.: 100,000 kr. Antal\nindustriarb.: 55. Tillv.-värde pr år: 950,000 kr.\n\n—\tFirman etabl. 1922, bolag 1931.\nStyrelse: ing. Clifford W. Finquist\n\n(ordf.), fröken F. J. Finquist, fru H. J.\nFinquist.\n\nVerkst. dir.: Clifford W. Finquist.\n\n*AB. Finshyttans Bruk, Finnshyttan.\n\nGjuteri och mek. verkstad vid\nFinnshyttan (Värml. l.). Tillverkar\nvattenturbiner och turbinregulatorer, pumpar,\nmaskiner för cellulosa- och\npappersindustrien, gruvspel och uppfordringsverk,\nmaskiner för järnbruk,\nreningsanläggningar för dricksvatten och kloakvatten samt\ngjutgods. Firman har egna kraftstationer\nsamt husbehovssåg.\n\nTelegr.-adr.: Finshyttebruk, Filipstad.\nTelefon: Filipstad 5, 9, 335, 337, 395 o.\n542. Postgiro: 90090.\n\nAkt.-kap.: 150,000 kr. Antal\nindustriarb.: 165. Tillv.-värde pr år: 2,200,000kr.\n\n—\tVerkstaden anlagd 1872, bolag 1903,\nnuv. bolag grundat 1940.\n\nStyrelse: jur. kand. Gillis Fahlbeck,\nkamrer J. Alfr. Larsson, disp. Rudolf\nWallertz.\n\nVerkst. dir. o. disp.: R. Wallertz.\nKamrer: J. Alfr. Larsson.\nRitlcontorschef: ing. E. Fredriksson.\nVerkstadsing.: Börje Sjögren.\n\n289*\n\nFinsjö Kraft AB., Malmö.\n\nElektr. vattenkraftverk vid Finsjö\nm. fl. platser i Kalmar län. Distribuerar\nelektr. energi.\n\nKontor: Malmö, Stora Ny g. 52. Tele-^\ngr.-adr.: Kraftfinsjö, Malmö. Telefon:\n»Sydkraft». Postgiro: 24600.\n\nAkt.-kap.: 654,000 kr. Distrib.-värde\npr år.: 3,000,000 kr. — Bolaget, som\ngrundades 1909, äges av Sydsvenska Kraft\nAB., Malmö.\n\nVerkst. dir.: Jonte Hultkrantz.\n\n*AB. Finsjö Pappersbruk, Finsjö.\n\nPappfabrik i Finsjö (Kalmar l.).\nTillverkar papp och kartong, konstläderpapp,\njacquardpapp, omslagspapp m. m.\n\nTelegr.-adr.: Pappersbruket, Finsjö.\nTelefon: Fliseryd 10. Postgiro: 131880.\n\nAkt.-kap.: 270,000 kr. Antal industri,\narb.: 65. Årstillv.: 2,500 ton papp och\nkartong. — Fabriken anlagd 1860, bolaget\ngrundat 1916.\n\nStyrelse o. verkst. dir.: disp. Oskar E.\nHalle.\n\n*AB. Finspongs Hästskor, Stockholm.\n\nHästskofabrik i Motala. Tillverkar\nhästskor. Varumärke: »Banco».\n\nTelefon: Motala 8. Huvudkontor o.\nen-samförsälj.: AB. Odelberg &amp; Olson,\nStockholm, Kungsg. 4 A. Telegr.-adr. o.\ntelefon: Odelbergolson, Stockholm. Postgiro:\n1408.\n\nAkt.-kap.: 100,000 kr. Antal\nindustriarb.: 25. Tillv.-värde pr år: 400,000 kn\n— Bolaget grundat 1913, ombildat 1922.\n\nStyrelse: disp. Olof Hjorth, adv. L.\nLevy, dir. Sven Ponsbach, dir. Karl-Erik\nTiblom, ing. Olof Tiblom.\n\nVerkst. dir.: S. Ponsbach.\n\nPlatschef i Motala: K.-Th. Härse.\n\n’Finspongs Metallverks AB.,\n\nStockholm.\n\nSe AB. Svenska Metallverken,\nVästerås.\n\n’AB. Fintlings Nickel- &amp; Nysilver-\n\nfabrik, Stockholm,.\n\nElektrogalvanisk fabrik. Utför\nförgyllning, försilvring, förkromning,\nförnick-ling, förmässing, förzinkning,\nhårdför-kromning, oxidering m. m.\n\nKontor: Roslagsg. 33. Telegr.-adr.:\nNickelfint, Stockholm. Telefon: 230280.\nPostgiro: 2744.",
    "structured": {
        "1": {
            "name": "Finnés Snickerifabriks AB",
            "location": "Lingbo",
            "business": "Sågverk, hyvleri och snickerifabrik",
            "products": "Tillverkar sågade och hyvlade trävaror, byggnadssnickerier, träkol och gengaskol",
            "contact": {
                "office": "Lingbo",
                "phone": [
                    "11"
                ],
                "postgiro": "73654"
            },
            "financials": {
                "capital": "406,000 kr",
                "employees": {
                    "industriarb": 90
                },
                "annual_turnover": "1,500,000 kr",
                "annual_production_value": "1,500,000 kr"
            },
            "foundation_year": 1894,
            "corporation_year": 1928,
            "board": [
                {
                    "name": "ing. Walo Finne",
                    "role": "ordf."
                },
                {
                    "name": "disp. Helmer Finne",
                    "role": ""
                },
                {
                    "name": "kamrer J. B. Forsblom",
                    "role": ""
                }
            ]
        },
        "2": {
            "name": "AB. C. E. Finquists Verkstäder",
            "location": "Älvsjö",
            "business": "Mek. verkstad",
            "products": "Tillverkar snack- och precisionskuggväxlar, kuggväxelmotorer, kugghjul, kättinghjul samt elastiska kopplingar",
            "contact": {
                "office": "Älvsjö, Stockholm",
                "phone": [
                    "472540-43"
                ],
                "postgiro": "25158"
            },
            "financials": {
                "capital": "100,000 kr",
                "employees": {
                    "industriarb": 55
                },
                "annual_turnover": "950,000 kr",
                "annual_production_value": "950,000 kr"
            },
            "foundation_year": 1922,
            "corporation_year": 1931,
            "board": [
                {
                    "name": "ing. Clifford W. Finquist",
                    "role": "ordf."
                },
                {
                    "name": "fröken F. J. Finquist",
                    "role": ""
                },
                {
                    "name": "fru H. J. Finquist",
                    "role": ""
                }
            ],
            "director": "Clifford W. Finquist"
        },
        "3": {
            "name": "AB. Finshyttans Bruk",
            "location": "Finnshyttan",
            "business": "Gjuteri och mek. verkstad",
            "products": "Tillverkar vattenturbiner och turbinregulatorer, pumpar, maskiner för cellulosa- och pappersindustrien, gruvspel och uppfordringsverk, maskiner för järnbruk, reningsanläggningar för dricksvatten och kloakvatten samt gjutgods",
            "contact": {
                "office": "Finnshyttan (Värml. l.)",
                "phone": [
                    "Filipstad 5",
                    "9",
                    "335",
                    "337",
                    "395",
                    "542"
                ],
                "postgiro": "90090"
            },
            "financials": {
                "capital": "150,000 kr",
                "employees": {
                    "industriarb": 165
                },
                "annual_turnover": "2,200,000 kr",
                "annual_production_value": "2,200,000 kr"
            },
            "corporation_year": 1903,
            "board": [
                {
                    "name": "jur. kand. Gillis Fahlbeck",
                    "role": ""
                },
                {
                    "name": "kamrer J. Alfr. Larsson",
                    "role": ""
                },
                {
                    "name": "disp. Rudolf Wallertz",
                    "role": ""
                }
            ],
            "director": "R. Wallertz",
            "manager": "Börje Sjögren"
        },
        "4": {
            "name": "Finsjö Kraft AB",
            "location": "Malmö",
            "business": "Elektr. vattenkraftverk",
            "products": "Distribuerar elektr. energi",
            "contact": {
                "office": "Malmö, Stora Ny g. 52",
                "telegraph": "Kraftfinsjö, Malmö",
                "phone": "Sydkraft",
                "postgiro": "24600"
            },
            "financials": {
                "capital": "654,000 kr",
                "annual_turnover": "3,000,000 kr"
            },
            "corporation_year": 1909,
            "owners": [
                "Sydsvenska Kraft AB., Malmö"
            ],
            "director": "Jonte Hultkrantz"
        },
        "5": {
            "name": "AB. Finsjö Pappersbruk",
            "location": "Finsjö",
            "business": "Pappfabrik",
            "products": "Tillverkar papp och kartong, konstläderpapp, jacquardpapp, omslagspapp m. m.",
            "contact": {
                "office": "Finsjö (Kalmar l.)",
                "phone": [
                    "Fliseryd 10"
                ],
                "postgiro": "131880"
            },
            "financials": {
                "capital": "270,000 kr",
                "employees": {
                    "industriarb": 65
                },
                "annual_production_value": "2,500 ton papp och kartong"
            },
            "corporation_year": 1916,
            "director": "disp. Oskar E. Halle"
        },
        "6": {
            "name": "AB. Finspongs Hästskor",
            "location": "Stockholm",
            "business": "Hästskofabrik",
            "products": "Tillverkar hästskor",
            "contact": {
                "office": "Motala",
                "phone": [
                    "Motala 8"
                ],
                "postgiro": "1408"
            },
            "financials": {
                "capital": "100,000 kr",
                "employees": {
                    "industriarb": 25
                },
                "annual_turnover": "400,000 kr"
            },
            "corporation_year": 1922,
            "board": [
                {
                    "name": "disp. Olof Hjorth",
                    "role": ""
                },
                {
                    "name": "adv. L. Levy",
                    "role": ""
                },
                {
                    "name": "dir. Sven Ponsbach",
                    "role": ""
                },
                {
                    "name": "dir. Karl-Erik Tiblom",
                    "role": ""
                },
                {
                    "name": "ing. Olof Tiblom",
                    "role": ""
                }
            ],
            "director": "S. Ponsbach",
            "manager": "K.-Th. Härse"
        },
        "7": {
            "name": "AB. Fintlings Nickel- & Nysilverfabrik",
            "location": "Stockholm",
            "business": "Elektrogalvanisk fabrik",
            "products": "Utför förgyllning, försilvring, förkromning, förnickling, förmässing, förzinkning, hårdkromning, oxidering m. m.",
            "contact": {
                "office": "Roslagsg. 33",
                "telegraph": "Nickelfint, Stockholm",
                "phone": [
                    "230280"
                ],
                "postgiro": "2744"
            }
        }
    }
}