{
    "original": "C ontractor—C ryptoteknik\n\n(linoleumfernissa), »Sylacol» (synt.\nfärger o. fernissor), »Covelack» (éellul.\nfärger o. fernissor), »Condorlack»\n(lackfärger), »Gambrinol» (bryggerilacker),\nSea-bird (båtlack o. bottenfärg).\n\nKontor: Hertzia. Telefon: 111673 o.\n136673. Postgiro: 40388. — Akt.-kap.:\n115,000 kr. Antal industriarb.: 15.\nTillv.-värde pr år: 700,000 kr. — Bolaget\ngrundat 1929.\n\nStyrelse: dir. Enar Nilbo (ordf.),\nkamrer Algot Ericson, adv. G. Sundberg.\n\nVerkst. dir.: Enar Nilbo.\n\n*Gontractor, Stockholm.\n\nSe Byggnads AB. Contractor,\nStockholm.\n\nAB» Corda, Trollhättan.\n\nMek. verkstad. Tillverkar tillbehör för\nautomobiler och motorcyklar såsom\ngasreglerings- o. frikopplingshandtag,\nluft-och tändningsreglage, backspeglar,\nbaklyktor, signalhorn m. m. samt\nspecialmaskiner och pressverktyg. Varumärke:\n»Corda».\n\nTelegr.-adr.: Corda, Trollhättan.\nTelefon: 10691’. Postgiro: 131462. —\nAkt.-kap.: 13,300 kr. Antal industriarb.: 25.\nTillv.-värde pr år: 200,000 kr. — Bolaget\ngrundat 1938.\n\nDisp.: Folke Johnsson.\n\nKamrer: Henry Johnsson.\n\nAB. Cornérs Konservfabrik,\n\nLysekil.\n\nTillverkar ansjovis och sillkonserver.\nVarumärke: »örnen».\n\nTelefon: 106. Postgiro: 84582. —\nAkt.-kap.: 50,000 kr. Antal industriarb.: 40.\n— Firman etabl. 1895, bolag 1933.\n\nVerkst. dir.: Helge Cornér.\n\nAB. Corona Belysningskultur,\n\nO. Gronwin, Stockholm.\n\nArmaturfabrik. Tillverkar\nbelysningsarmatur och lampskärmar. Varumärke:\n»Corona».\n\nKontor: Artillerig. 51. Telefon: 604114.\nPostgiro: 50881. — Akt.-kap.: 30,000 kr.\nAntal industriarb.: 28. — Firman etabl.\n1927, bolag 1943.\n\nVerkst. dir.: Gunnar Cronwin.\n\nFörsäljn.-chef: ing. Harry Borg.\n\n*Coronaverken AB-, Göteborg.\n\nMek. verkstad och gjuteri. Tillverkar\nkokapparater, kokvagnar, kokskåp,\nvärme-skåp, torkapparater, diskmaskiner, desin-\n\nfektionsapparater, steriliseringsapparater\nför sjukhus, tvättmaskiner, centrifuger,\nångmanglar, värmeledningsmateriel,\nträns-missionsgjutgods, axelkopplingar,\nremskivor, fläktar och tempers (varumärke:\n»VE VE»), maskingjutgods etc.\n\nKontor: Hisingen. Telegr.-adr.:\nCo-ronaverken, Göteborg. Telefon: 222240.\nPostgiro: 41516. — Akt.-kap.: 400,000 kr.\nAntal industriarb.: 65.\n\nBolaget, grundat 1918, äger AB.\nVul-canverken, Göteborg, samt driver dess\nverksamhet och försäljning.\n\nStyrelse: grossh. Sigurd Larsson (ordf.),\ndisp. Franz Hartmann, ing. Reinh.\nHjorth.\n\nVerkst. dir.: Reinh. Hjorth.\n\nAB. Corsettindustri, Borås.\n\nTillverkar strumphållare, höfthållare,\nkorsetter och korseletter samt bysthållare.\nVarumärke: »Abc».\n\nTelegr.-adr.: Abc-korsetten, Borås.\nTelefon: »Abckorsett». Postgiro: 81318. —\nAkt.-kap.: 200,000 kr. Antal industriarb.:\n150. — Firman etabl. 1932.\n\nVerkst. dir.: disp. Joel Åkerlund.\n\nAB. Cottonstrumpor, Göteborg.\n\nTillverkar damstrumpor.\n\nKontor: ö. Spannmålsg. 6.\nTelegr.-adr.: Cottonstrumpor, Göteborg. Telefon:\n113103. Postgiro: 42940.\n\nAkt.-kap.: 100,000 kr. Antal\nindustriarb.: 150. Tillv.-värde pr år: 1,500,000\nkr. — Bolaget grundat 1931.\n\nStyrelse o. verkst. dir.: Eric O.\nMagnuson.\n\nDir.-assist.: Åke Magnuson.\n\n*AB. Cryptoteknik, Stockholm.\n\nFinmek. verkstad. Tillverkar\nchiffre-ringsmaskiner (»Cryptografer», system\n\nHagelin&gt;. \"\n\nKontor: Nordenflychtsvägen 62;\npost-adr.: Stockholm 30. Telegr.-adr.: Crypto,\nStockholm. Telefon: 520390. Postgiro:\n154072.\n\nAkt.-kap.: 400,000 kr. Antal\nindustriarb.: 65. Tillv.-värde pr år: 1,000,000 kr.\n— Bolaget grundat 1938.\n\nStyrelse: dir. Anders Ekdal (ordf.),\ndir. Henrik W. Bechshöft, civiling. Boris\nHagelin, civiling. Wilhelm’ Qvarnström,.\nciviling. S. T. Åberg.\n\nVerkst. dir.: W. Qvarnström.\n\nFörsäljn.-chef: H. W. Bechshöft.\n\nTekn. chef: civiling. Vigo W.\nLind-stein.\n\nKamrer: Stig Fraser.\n\nDriftsing.: Gösta Holmström.\n\n101*",
    "structured": {
        "1": {
            "name": "Contractor—Cryptoteknik",
            "location": "Stockholm",
            "business": "Finmek. verkstad",
            "products": "chiffreringsmaskiner (»Cryptografer», system Hagelin&gt;)",
            "contact": {
                "office": "Nordenflychtsvägen 62",
                "phone": [
                    "520390"
                ],
                "postgiro": "154072"
            },
            "financials": {
                "capital": "400,000 kr",
                "employees": {
                    "industrial": 65
                },
                "annual_turnover": "1,000,000 kr",
                "foundation_year": 1938
            },
            "board": [
                {
                    "name": "Anders Ekdal",
                    "role": "ordf."
                },
                {
                    "name": "Henrik W. Bechshöft",
                    "role": "dir."
                },
                {
                    "name": "Boris Hagelin",
                    "role": "civiling."
                },
                {
                    "name": "Wilhelm’ Qvarnström",
                    "role": "civiling."
                },
                {
                    "name": "S. T. Åberg",
                    "role": "civiling."
                }
            ],
            "manager": "W. Qvarnström",
            "sales_manager": "H. W. Bechshöft",
            "description": "Akt.-kap.: 400,000 kr. Antal industriarb.: 65. Tillv.-värde pr år: 1,000,000 kr. — Bolaget grundat 1938."
        },
        "2": {
            "name": "Corda",
            "location": "Trollhättan",
            "business": "Mek. verkstad",
            "products": "gasreglerings- o. frikopplingshandtag, luft-och tändningsreglage, backspeglar, baklyktor, signalhorn m. m. samt specialmaskiner och pressverktyg",
            "contact": {
                "office": "N/A",
                "phone": [
                    "10691"
                ],
                "postgiro": "131462"
            },
            "financials": {
                "capital": "13,300 kr",
                "employees": {
                    "industrial": 25
                },
                "annual_turnover": "200,000 kr",
                "foundation_year": 1938
            },
            "manager": "Folke Johnsson",
            "contact_description": "Akt.-kap.: 13,300 kr. Antal industriarb.: 25. Tillv.-värde pr år: 200,000 kr. — Bolaget grundat 1938."
        },
        "3": {
            "name": "Cornérs Konservfabrik",
            "location": "Lysekil",
            "business": "Tillverkar ansjovis och sillkonserver",
            "contact": {
                "office": "N/A",
                "phone": [
                    "106"
                ],
                "postgiro": "84582"
            },
            "financials": {
                "capital": "50,000 kr",
                "employees": {
                    "industrial": 40
                },
                "incorporation_year": 1933
            },
            "manager": "Helge Cornér",
            "contact_description": "Akt.-kap.: 50,000 kr. Antal industriarb.: 40. — Firman etabl. 1895, bolag 1933."
        },
        "4": {
            "name": "Corona Belysningskultur",
            "location": "O. Gronwin, Stockholm",
            "business": "Armaturfabrik",
            "products": "belysningsarmatur och lampskärmar",
            "contact": {
                "office": "Artillerig. 51",
                "phone": [
                    "604114"
                ],
                "postgiro": "50881"
            },
            "financials": {
                "capital": "30,000 kr",
                "employees": {
                    "industrial": 28
                },
                "incorporation_year": 1943
            },
            "manager": "Gunnar Cronwin",
            "sales_manager": "ing. Harry Borg",
            "contact_description": "Akt.-kap.: 30,000 kr. Antal industriarb.: 28. — Firman etabl. 1927, bolag 1943."
        },
        "5": {
            "name": "Coronaverken AB",
            "location": "Göteborg",
            "business": "Mek. verkstad och gjuteri",
            "products": "kokapparater, kokvagnar, kokskåp, värme-skåp, torkapparater, diskmaskiner, desinfektionsapparater, steriliseringsapparater för sjukhus, tvättmaskiner, centrifuger, ångmanglar, värmeledningsmateriel, tränsmi sionsgjutgods, axelkopplingar, remskivor, fläktar och tempers (varumärke: »VE VE»), maskingjutgods etc.",
            "contact": {
                "office": "Hisingen",
                "phone": [
                    "222240"
                ],
                "postgiro": "41516"
            },
            "financials": {
                "capital": "400,000 kr",
                "employees": {
                    "industrial": 65
                },
                "contact_description": "Bolaget, grundat 1918, äger AB. Vulcanverken, Göteborg, samt driver dess verksamhet och försäljning."
            },
            "board": [
                {
                    "name": "Sigurd Larsson",
                    "role": "ordf."
                },
                {
                    "name": "Franz Hartmann",
                    "role": "disp."
                },
                {
                    "name": "Reinh. Hjorth",
                    "role": "ing."
                }
            ],
            "manager": "Reinh. Hjorth"
        },
        "6": {
            "name": "Corsettindustri",
            "location": "Borås",
            "business": "Tillverkar strumphållare, höfthållare, korsetter och korseletter samt bysthållare",
            "products": "Varumärke: »Abc»",
            "contact": {
                "office": "N/A",
                "phone": [
                    "N/A"
                ],
                "postgiro": "81318"
            },
            "financials": {
                "capital": "200,000 kr",
                "employees": {
                    "industrial": 150
                },
                "foundation_year": 1932
            },
            "manager": "Joel Åkerlund",
            "contact_description": "Akt.-kap.: 200,000 kr. Antal industriarb.: 150. — Firman etabl. 1932."
        },
        "7": {
            "name": "Cottonstrumpor",
            "location": "Göteborg",
            "business": "Tillverkar damstrumpor",
            "contact": {
                "office": "ö. Spannmålsg. 6",
                "phone": [
                    "113103"
                ],
                "postgiro": "42940"
            },
            "financials": {
                "capital": "100,000 kr",
                "employees": {
                    "industrial": 150
                },
                "annual_turnover": "1,500,000 kr",
                "foundation_year": 1931
            },
            "board": [
                {
                    "name": "Eric O. Magnuson",
                    "role": "ordf."
                }
            ],
            "manager": "Eric O. Magnuson",
            "contact_description": "Akt.-kap.: 100,000 kr. Antal industriarb.: 150. Tillv.-värde pr år: 1,500,000 kr. — Bolaget grundat 1931."
        }
    }
}