{
    "original": "Ulvsunda—Upperud\n\n* Ulvsunda Verkstäder AB.,\n\nTJlv sunda.\n\nMek. verkstad i Ulvsunda, Stockholm.\nTillverkar hålslipmaskiner, slipspindlar,\nmassartiklar, verktyg, jiggar, fixturer\nm. m. Varumärke: »UVA».\n\nKontor: Johannesf redsvägen 15—17,\nUlvsunda. Telefon: 252510. Postgiro:\n53803.\n\nAkt.-kap.: 4,000,000 kr. Antal\nindustriarb.: 250. — Bolaget grundat 1928 under\nnamn AB. Nomy, nuv. namn 1940.\n\nStyrelse; dir. Assar Gabrielsson\n(ordf.), dir. Nils Frenne, dir. Gustaf\nLarson.\n\nVerkst. dir.: Carl Gustaf Janson.\n\növering.: Martin Björklind.\n\nVerkstadschef: ing. Arthur Hellsten.\n\nKamrer: Harry Sandberg.\n\nFörsäljn.-chef: civiling. Lennart\nOd-qvist.\n\n’Ulvviks AB., Kramfors.\n\nTräsliperi vid Ulf vik (Västernorrl. l.).\nTillverkar mek. trämassa.\n\nHuvudkontor: Kramfors. Telegr.-adr.:\nUlvviksbolag, Kramfors. Telefon:\nKramfors 2000. Fabrikskontor: Älandsbro.\nTelefon: Älandsbro 61. Ensamförsälj.:\nSvenska Cellulosa AB., Stockholm, V:a\nTrädgårdsg. 15. Telefon: »Cellulosabolaget».\n\nAkt.-kap.: o 1,000,000 kr. Årskapacitet:\n36,000 ton våt, vit mek. trämassa. —\nBolaget, grundat 1923, äges av Kramfors\nAB., som arrenderar och driver bolagets\nträsliperi.\n\nStyrelse: dir. K. E. Nyberg, dir. A.\nOrrmell.\n\nVerkst. dir.: A. Orrmell.\n\nDisp.: R. Frölander.\n\növering.: U. Fryklund.\n\nDriftsing.; John Söderlind.\n\nShogschef: H. Swan.\n\nKontorschef: G. Granquist.\n\n’Umeå Klichéanstalt, Umeå.\n\nTillverkar klichéer.\n\nTelefon: 989 o. 1078. Postgiro: 62499.\n\n— Arb.-antal: 2. Tillv.-värde pr år:\n24,000 kr. — Firman etabl. 1924.\n\nÄgare o. chef: köpm. Carl Jansson.\n\n’Umeå Tegelbruk, Bäckström &amp; Co.,\n\nTeg.\n\nTillverkar murtegel och högporöst\ntegel vid tegelbruk i Sofiehem, Umeå.\n\nKontor: Teg. Telefon: Umeå 570.\nPostgiro: 63034. —^ Antal industriarb.: 27.\nÅrstillv.: 1 milj. st. tegelvaror. ■—\nFirman etabl. 1920.\n\nÄgare o. chef: byggmäst. J. M.\nBäckström.\n\nTegelmäst.: Helge Johansson.\n\nKamrer: Frans Lundström.\n\n’AB. Umeå Trämassefabriker,\n\nUmeå.\n\nTräsliperier i Umeå och i Sofiehem,\nUmeå. Tillverkar våt mek. trämassa.\n\nTelegr.-adr.: Pulpmills, Umeå. Telefon:\n2100. Postgiro: 62513.\n\nAkt.-kap.: 2,000,000 kr. Antal\nindustriarb.: 300. Årskapacitet: 130,000 ton våt\nträmassa.\n\nBolaget bildades 1937 efter inköp av\nfabrikerna från AB. Scharins Söner,\nKle-mensnäs.\n\nStyrelse: adv. Sune Wetter (ordf.),\nmr Stanley Bell, dir. J. W. R.\nLillie-stråle, konsul Arne Unander-Scharin.\n\nVerkst. dir.: Arne Unander-Scharin.\n\n’Umeå Ångbryggeri,\nKommanditbolag, Umeå.\n\nTillverkar maltdrycker och\nläskedrycker.\n\nTelegr.-adr. o. telefon: Ångbryggeriet,\nUmeå. Postgiro: 29326. — Antal\nindustriarb.: 51. Tillv.-värde pr år: 1,800,000 kr.\n\nStyrelse: flottningsehef Robert\nCarlsson, grosshandl. Emil Lundmark, dir. K.\nSohlgren.\n\nVerkst. dir. o. disp.: Gunnar Sandell.\n\nBryggmäst.: E. Lindeman.\n\n’Adolf Ungers Industri AB.,\n\nSöderhamn.\n\nSe Marma—Långrörs AB., Söderhamn.\n\nAB. Uplandsprodukter, Uppsala,\n\nTillverkar saltströmming, jböckling,\nsardiner, fiskfärs, sillinläggningar m. m.\nVarumärke: »Rospiggen».\n\nTelegr.-adr. o. telefon: Uplandsfisk,\nUppsala. Postgiro: 161203. — Akt.-kap.:\n500,000 kr. Antal industriarb.: 100.\nTillv.-värde pr år: 2,500,000 kr. —\nBolaget grundat 1939 under namn AB.\nStrömmingskonserver, nuv. namn 1946.\n\nDisp.: Sune Eriksson.\n\nInhöps- o. försäljn.-chef: Åke Levin.\n\nAB. Upperuds Trämassefabrik,\n\nUpperud.\n\nTillverkar mek. trämassa vid fabrik i\nUpperud (Älvsb. l.).\n\nTelegr.-adr.: Upperudsfabrik,\nVänersborg. Telefon: Åsensbruk 1. Postgiro:\n137632.",
    "structured": {
        "1": {
            "name": "Ulvsunda Verkstäder AB.",
            "location": "Ulvsunda, Stockholm",
            "business": "Mekanisk verkstad",
            "products": "Tillverkar hålslipmaskiner, slipspindlar, massartiklar, verktyg, jiggar, fixturer m.m",
            "contact": {
                "office": "Johannesfredsvägen 15-17, Ulvsunda",
                "phone": [
                    "252510"
                ],
                "postgiro": "53803"
            },
            "financials": {
                "capital": "4,000,000 kr",
                "employees": {
                    "industriarb": 250
                },
                "annual_turnover": "N/A",
                "annual_production_value": "N/A"
            },
            "foundation_year": 1928,
            "current_name_year": 1940,
            "board": [
                {
                    "name": "Assar Gabrielsson",
                    "role": "ordförande"
                },
                {
                    "name": "Nils Frenne",
                    "role": "direktör"
                },
                {
                    "name": "Gustaf Larson",
                    "role": "direktör"
                }
            ],
            "director": "Carl Gustaf Janson",
            "managing_director": "N/A",
            "sales_manager": "Lennart Odqvist",
            "manager": "N/A"
        },
        "2": {
            "name": "Ulvviks AB.",
            "location": "Kramfors",
            "business": "Träsliperi",
            "products": "Tillverkar mekanisk trämassa",
            "contact": {
                "head_office": "Kramfors",
                "telegraph": "Ulvviksbolag, Kramfors",
                "sales_offices": [
                    {
                        "location": "Älandsbro",
                        "phone": "Älandsbro 61"
                    }
                ]
            },
            "financials": {
                "capital": "1,000,000 kr",
                "employees": {
                    "N/A": 0
                },
                "annual_turnover": "N/A",
                "annual_production_value": "36,000 ton våt, vit mekanisk trämassa"
            },
            "foundation_year": 1923,
            "board": [
                {
                    "name": "K. E. Nyberg",
                    "role": "direktör"
                },
                {
                    "name": "A. Orrmell",
                    "role": "direktör"
                }
            ],
            "manager": "R. Frölander"
        },
        "3": {
            "name": "Umeå Klichéanstalt",
            "location": "Umeå",
            "business": "Tillverkning av klichéer",
            "contact": {
                "phone": [
                    "989",
                    "1078"
                ],
                "postgiro": "62499"
            },
            "financials": {
                "employees": {
                    "N/A": 2
                },
                "annual_turnover": "24,000 kr",
                "annual_production_value": "N/A"
            },
            "foundation_year": 1924,
            "director": "Carl Jansson"
        },
        "4": {
            "name": "Umeå Tegelbruk, Bäckström & Co.",
            "location": "Sofiehem, Umeå",
            "business": "Tillverkning av murtegel och högporöst tegel",
            "contact": {
                "office": "Teg",
                "phone": [
                    "Umeå 570"
                ],
                "postgiro": "63034"
            },
            "financials": {
                "employees": {
                    "N/A": 27
                },
                "annual_turnover": "N/A",
                "annual_production_value": "1 milj. st. tegelvaror"
            },
            "foundation_year": 1920,
            "manager": "J. M. Bäckström"
        },
        "5": {
            "name": "AB. Umeå Trämassefabriker",
            "location": "Umeå & Sofiehem, Umeå",
            "business": "Tillverkning av våt mekanisk trämassa",
            "contact": {
                "telegraph": "Pulpmills, Umeå",
                "phone": [
                    "2100"
                ],
                "postgiro": "62513"
            },
            "financials": {
                "capital": "2,000,000 kr",
                "employees": {
                    "industriarb": 300
                },
                "annual_turnover": "N/A",
                "annual_production_value": "130,000 ton våt trämassa"
            },
            "foundation_year": 1937,
            "board": [
                {
                    "name": "Sune Wetter",
                    "role": "ordförande"
                },
                {
                    "name": "Stanley Bell",
                    "role": "direktör"
                },
                {
                    "name": "J. W. R. Lilliestråle",
                    "role": "direktör"
                },
                {
                    "name": "Arne Unander-Scharin",
                    "role": "konsul"
                }
            ],
            "manager": "Arne Unander-Scharin"
        },
        "6": {
            "name": "Umeå Ångbryggeri, Kommanditbolag",
            "location": "Umeå",
            "business": "Tillverkning av maltdrycker och läskedrycker",
            "contact": {
                "telegraph": "Ångbryggeriet, Umeå",
                "phone": [
                    "N/A"
                ],
                "postgiro": "29326"
            },
            "financials": {
                "employees": {
                    "N/A": 51
                },
                "annual_turnover": "N/A",
                "annual_production_value": "1,800,000 kr"
            },
            "board": [
                {
                    "name": "Robert Carlsson",
                    "role": "flottningschef"
                },
                {
                    "name": "Emil Lundmark",
                    "role": "grosshandlare"
                },
                {
                    "name": "K. Sohlgren",
                    "role": "direktör"
                }
            ],
            "director": "Gunnar Sandell",
            "manager": "N/A"
        },
        "7": {
            "name": "Adolf Ungers Industri AB.",
            "location": "Söderhamn",
            "business": ""
        },
        "8": {
            "name": "AB. Uplandsprodukter",
            "location": "Uppsala",
            "business": "Tillverkning av fiskprodukter"
        },
        "9": {
            "name": "AB. Upperuds Trämassefabrik",
            "location": "Upperud (Älvsb. l.)",
            "business": "Tillverkning av mekanisk trämassa",
            "contact": {
                "telegraph": "Upperudsfabrik, Vänersborg",
                "phone": [
                    "Åsensbruk 1"
                ],
                "postgiro": "137632"
            }
        }
    }
}