{
    "original": "Blomström—Bob er g\n\nTelegr.-adr.: Möbelfabriken,\nBlomster-måla. Telefon: 1. Postgiro: 71530.\n\nAkt.-kap.: 90,000 kr. Antal\nindustriarb.: 41. Tillv.-värde pr år: 400,000 kr.\n— Firman etabl. 1900, bolag 1920.\n\nStyrelse: arkitekt Per Persson (ordf.),\nbildhuggare Gustaf Nilsson, kamrer\nSigurd Persson.\n\nDisp.: Per Persson.\n\nBlomström &amp; Hel Isberg, Eskilstuna.\n\nVerktygsfabrik och mek. verkstad.\nTillverkar stans- och pressverktyg,\nmaskin-hyvelstål och kuttrar.\n\nTelefon: 32881. Postgiro: 92160. —\nArb.-antal: 12. Tillv.-värde pr år: 75,000\nkr. — Firman etabl. 1931.\n\nÄgare o. chef: fabr. Arvid Helisberg.\n\n* Blusexperten, Stockholm.\n\nDamkonfektion. Tillverkar blusar i\nsiden och konstsiden.\n\nKontor: Döbelnsg. 34 G. Telegr.-adr.:\nBlusexperten, Stockholm. Telefon: 312237.\nPostgiro: 159602. — Antal industriarb.:\n30. Tillv.-värde pr år: 500,000 kr. —\nFirman etabl. 1919.\n\nÄgare o. chef: grossh. Abraham\nHirsch-feldt.\n\n*Blus- &amp; Klänningskonfektions AB.,\n\nStockholm.\n\nTillverkar blusar och klänningar.\n\nKontor: Flemingg. 17. Telefon:\n510601 o. 500677. Postgiro: 159020.\n\nAkt.-kap.: 45,000 kr. Antal\nindustriarb.: 50. — Firman etabl. 1934, bolag\n1940.\n\nStyrelse: adv. Mauritz Griinberger\n(ordf.), disp. Richard Cassel, dir. Ruben\nGliickman.\n\nVerkst. dir.: Ruben Gliickman.\n\nDisp.: Richard Oassel.\n\nAB. T. Bluchers Pappersindustri,\n\nKvidinge.\n\nPapperspås- och kuvertfabrik i\nKvidinge (Kristianst. l.). Tillverkar påsar\noch kuvert, toalettpapper m. m. samt\nutför såsom specialitet anilintrycksaker.\nBolaget driver även engrosförsäljning av\nomslagspapper, tårtpapper, kartonger och\nbindgarn.\n\nTelegr.-adr.: Bluchers, Kvidinge.\nTelefon: 123 o. 70. Postgiro: 8831. —\nAkt.-kap.: 300,000 kr. Antal industriarb.: 35.\n— Firman etabl. 1915, bolag 1931.\nBolaget äger Sörstafors Pappersbruks AB.,\nKolbäck (se detta bolag).\n\nStyrelse: disp. S. E. Ahnfors, fotograf\nHarald Bliieher, dir. Tage Bliicher, adv.\nO. H. Ljunggren.\n\nVerkst. dir.: Tage Bliicher.\n\nBlyaccumulator AB., Norrköping.\n\nTillverkar startbatterier\n(blyaccumula-torer). Varumärke: »ATO».\n\nTelefon: 27270. Postgiro: 88800. —\nAkt.-kap.: 25,000 kr. Antal industriarb.:\n7. Tillv.-värde pr år: 124,000 kr. —\nFirman etabl. 1934 under namn Svensk\nBlyaccumulator, B. G. Lindström AB., nuv.\nbolag 1945.\n\nStyrelse o. verkst. dir.: ing. Bror\nLindström.\n\n* Blyertsfabriken Viking AB.,\n\nStockholm.\n\nBlyertsfabrik i Växjö. Tillverkar\nblyertspennor, kopiepennor,\ntimmermanspennor, pennskaft, färgkritor m. m.\nVarumärke: »Viking».\n\nKontor: Stockholm, Drottningg. 71 C.\nTelefon: 203440 o. 112151. Postgiro:\n56440. — Akt.-kap.: 50,000 kr. Antal\nindustriarb.: 25. — Bolaget grundat 1933.\n\nStyrelse: dir. Wictor Lindström, dir.\nF. Preisler, adv. Carl Axel Sandberg.\nVerkst. dir.: Wictor Lindström.\n\nBlå Pilen AB., Insjön.\n\nKravattfabrik, trikåfabrik och\nhand-väveri i Insjön (Kopparb. l.). Tillverkar\nhalsdukar, scarves, stickade mössor samt\nsport jackor. Varumärke: »Blå Pilen».\nTelefon: 40230—31. Postgiro: 96595.\n\n—\tAkt.-kap.: 50,000 kr. Antal\nindustriarb.: 25. Tillv.-värde pr år: 500,000 kr.\n\n—\tFirman etabl. 1936, bolag 1945.\nDisp.: Erik Niling.\n\n* Blötbergets Gruvor, Blötberget.\nSe Bergverks AB. Vulcanus, Blötberget.\n\nBobergs Fajansfabrik AB., Gävle.\n\nFajansfabrik. Tillverkar hushållskärl,\nblomkrukor samt handdekorerade\nhushålls- och prydnadsfajanser. Varumärke:\n»Bo-fajans».\n\nTelegr.-adr.: Bobergs, Gävle. Telefon:\n5836 o. 236. Postgiro: 26168. —\nAkt.-kap.: 225,600 kr. Antal industriarb.: 70.\n—- Firman etabl. 1874, bolag 1921.\n\nStyrelse: disp. John Boberg (ordf.),\nherr Erik Boberg, fröken H. Boberg,\nkamrer Nils A. Boberg.\n\nVerkst. dir. o. disp.: John Boberg.",
    "structured": {
        "1": {
            "name": "Blomström—Bob er g",
            "location": "Möbelfabriken, Blomster-måla",
            "contact": {
                "telegraph": "Möbelfabriken, Blomster-måla",
                "phone": [
                    "1"
                ],
                "postgiro": "71530"
            },
            "financials": {
                "capital": "90,000 kr",
                "employees": {
                    "industriarb": 41
                },
                "annual_turnover": "400,000 kr",
                "annual_production_value": "400,000 kr"
            },
            "foundation_year": 1900,
            "corporation_year": 1920,
            "board": [
                {
                    "name": "Per Persson",
                    "role": "ordf."
                },
                {
                    "name": "Gustaf Nilsson",
                    "role": "bildhuggare"
                },
                {
                    "name": "Sigurd Persson",
                    "role": "kamrer"
                }
            ],
            "director": "Per Persson"
        },
        "2": {
            "name": "Blomström & Hel Isberg",
            "location": "Eskilstuna",
            "business": "Verktygsfabrik och mek. verkstad",
            "contact": {
                "phone": "32881",
                "postgiro": "92160"
            },
            "financials": {
                "employees": {
                    "industriarb": 12
                },
                "annual_production_value": "75,000 kr"
            },
            "foundation_year": 1931,
            "owner": "Arvid Helisberg"
        },
        "3": {
            "name": "Blusexperten",
            "location": "Stockholm",
            "business": "Damkonfektion",
            "contact": {
                "office": "Döbelnsg. 34 G",
                "telegraph": "Blusexperten, Stockholm",
                "phone": [
                    "312237"
                ],
                "postgiro": "159602"
            },
            "financials": {
                "employees": {
                    "industriarb": 30
                },
                "annual_production_value": "500,000 kr"
            },
            "foundation_year": 1919,
            "owner": "Abraham Hirsch-feldt"
        },
        "4": {
            "name": "Blus- & Klänningskonfektions AB.",
            "location": "Stockholm",
            "business": "Tillverkar blusar och klänningar",
            "contact": {
                "office": "Flemingg. 17",
                "phone": [
                    "510601",
                    "500677"
                ],
                "postgiro": "159020"
            },
            "financials": {
                "capital": "45,000 kr",
                "employees": {
                    "industriarb": 50
                }
            },
            "foundation_year": 1934,
            "corporation_year": 1940,
            "board": [
                {
                    "name": "Mauritz Griinberger",
                    "role": "ordf."
                },
                {
                    "name": "Richard Cassel",
                    "role": "disp."
                },
                {
                    "name": "Ruben Gliickman",
                    "role": "dir."
                }
            ],
            "director": "Ruben Gliickman"
        },
        "5": {
            "name": "AB. T. Bluchers Pappersindustri",
            "location": "Kvidinge",
            "business": "Papperspås- och kuvertfabrik",
            "contact": {
                "telegraph": "Bluchers, Kvidinge",
                "phone": [
                    "123",
                    "70"
                ],
                "postgiro": "8831"
            },
            "financials": {
                "capital": "300,000 kr",
                "employees": {
                    "industriarb": 35
                }
            },
            "foundation_year": 1915,
            "corporation_year": 1931,
            "board": [
                {
                    "name": "S. E. Ahnfors",
                    "role": "disp."
                },
                {
                    "name": "Harald Bliieher",
                    "role": "fotograf"
                },
                {
                    "name": "Tage Bliicher",
                    "role": "dir."
                },
                {
                    "name": "O. H. Ljunggren",
                    "role": "adv."
                }
            ],
            "director": "Tage Bliicher"
        },
        "6": {
            "name": "Blyaccumulator AB.",
            "location": "Norrköping",
            "business": "Tillverkar startbatterier",
            "contact": {
                "phone": "27270",
                "postgiro": "88800"
            },
            "financials": {
                "capital": "25,000 kr",
                "employees": {
                    "industriarb": 7
                },
                "annual_turnover": "124,000 kr"
            },
            "foundation_year": 1934,
            "owner": "Svensk Blyaccumulator, B. G. Lindström AB",
            "director": "Bror Lindström"
        },
        "7": {
            "name": "Blyertsfabriken Viking AB.",
            "location": "Växjö",
            "business": "Tillverkar blyertspennor",
            "contact": {
                "office": "Drottningg. 71 C",
                "phone": [
                    "203440",
                    "112151"
                ],
                "postgiro": "56440"
            },
            "financials": {
                "capital": "50,000 kr",
                "employees": {
                    "industriarb": 25
                }
            },
            "foundation_year": 1933,
            "board": [
                {
                    "name": "Wictor Lindström",
                    "role": "dir."
                },
                {
                    "name": "F. Preisler",
                    "role": "dir."
                },
                {
                    "name": "Carl Axel Sandberg",
                    "role": "adv."
                }
            ],
            "director": "Wictor Lindström"
        },
        "8": {
            "name": "Blå Pilen AB.",
            "location": "Insjön",
            "business": "Kravattfabrik, trikåfabrik och handväveri",
            "contact": {
                "phone": "40230—31",
                "postgiro": "96595"
            },
            "financials": {
                "capital": "50,000 kr",
                "employees": {
                    "industriarb": 25
                },
                "annual_production_value": "500,000 kr"
            },
            "foundation_year": 1936,
            "corporation_year": 1945,
            "director": "Erik Niling"
        },
        "9": {
            "name": "Bobergs Fajansfabrik AB.",
            "location": "Gävle",
            "business": "Fajansfabrik",
            "contact": {
                "telegraph": "Bobergs, Gävle",
                "phone": [
                    "5836",
                    "236"
                ],
                "postgiro": "26168"
            },
            "financials": {
                "capital": "225,600 kr",
                "employees": {
                    "industriarb": 70
                }
            },
            "foundation_year": 1874,
            "corporation_year": 1921,
            "board": [
                {
                    "name": "John Boberg",
                    "role": "disp."
                },
                {
                    "name": "Erik Boberg",
                    "role": "herr"
                },
                {
                    "name": "H. Boberg",
                    "role": "fröken"
                },
                {
                    "name": "Nils A. Boberg",
                    "role": "kamrer"
                }
            ],
            "director": "John Boberg"
        }
    }
}