{
    "original": "Tullberg—Tunelius\n\n*AB. Hasse W. Tullberg, Stockholm.\n\nBoktryckeri, stål- och djup tryckeri,\nklichéanstalt, bokbinderi, bok- och\nblankettförlag.\n\nKontor: Vasag. 16. Telegr.-adr.: Hasse,\nStockholm. Telefon: »Hasse W.\nTullberg». Postgiro: 507. Bokförlag:\nDrottninggatan 20. Blankettförlag: Klara V.\nKyrkogata 15.\n\nFirman etabl. 1871, bolag 1905.\nBolaget är anslutet till AB. Sveriges\nLitogra-fiska Tryckerier, Stockholm. (Se detta\nbolag.)\n\nStyrelse o. verkst. dir.: disp, Gösta\nSmith.\n\nBeställningskontoret: faktor Axel\nWestberg.\n\nAB. R. S. Tullberg, Klippan.\n\nBok- och offsettryckeri samt\nkontors-bokfabrik i Klippan (Kristianst. l.).\n\nTelegr.-adr.: Tullberg, Klippan.\nTelefon: 82 o. 486. Postgiro: 10199.\nAvd.-kontor: Stockholm, Kungsholmstorg 16;\ntelefon: 534424.\n\nAkt.-kap.: 200,000 kr. Antal\nindustriarb.: 60. — Firman etabl. 1909, bolag\n1925.\n\nDisp.: Gösta Tullberg.\n\nTullgarns Cjuteri och Mek.\nVerkstads AB., TJppsala.\n\nMek. verkstad med gjuteri i Uppsala.\nTillverkar kylanläggningar, mek. grindar\nsamt gjutgods av järn, metall och\naluminium såväl maskin- som handformat.\n\nTelegr.-adr.: Tullgarns, Uppsala.\nTelefon: 39470. Postgiro: 32848.\n\nAkt.-kap.: 230,500 kr. Antal\nindustriarb.: 100. Tillv.-värde pr år: 1,500,000 kr.\n— Bolaget grundat 1898.\n\nStyrelse: överstelöjtn. Fritz Ploman\n(ordf.), adv. Olof Chrysander, ing. Sven\nE, Nilsson.\n\nVerkst. dir.: Sven E. Nilsson.\n\nKontorschef: Georg Sundberg.\n\nDriftsing.: C. Thorwid.\n\n(Jfr annons nr 31.)\n\nTunabergs Trävaru AB.,\n\nKoppartorp.\n\nSågverk och snickerifabrik vid\nMarsviken (Södermanl. l.). Tillverkar sågade\nträvaror, laths, props och massaved,\nträkol samt byggnadssnickerier och\nmonteringsfärdiga trähus.\n\nTelegr.-adr.: Skogsbruk, Nyköping.\nTelefon: Koppartorp 42 o. 43 samt\nNyköping 30 a. Postgiro: 90220. Ensamför-\n\nsälj. för export: Träyaru AB.\nNorrköpings Exporthyfleri, Norrköping.\n\nAkt.-kap.: 1,000,000 kr. Antal\nindustriarb.: 180. Årstillv.: 7,000 stds trävaror.\n\n—\tFirman grundad 1901, nuv. bolag 1923.\n\nStyrelse: godsäg. Henning Danielsson,\n\ndisp. Emrik Danielsson, löjtn. Nils-Olof\nDanielsson, disp. Olof Danielsson,\njäg-mäst. Gunnar Norén.\n\nDisp.: Olof Danielsson.\n\nAB. Tunabröd, Stora Tuna.\n\nKvarn och spisbrödsfabrik i Stora\nTuna (Kopparb. l.). Tillverkar mjöl och\nspisbröd.\n\nTelefon: 33101 o. 33065. Postgiro:\n25966.\n\nAkt.-kap.: 150,000 kr. Antal\nindustriarb.: 35. Prod.-värde pr år: 1,000,000 kr.\n\nFirman etabl. 1923 i Korsnäs,\növerflyttades 1932 till Stora Tuna, nuv. bolag\n1939 efter övertagandet av Stora Tuna\nValskvarn.\n\nDisp.: Karl Andersson.\n\nKamrer: Hjalmar Andersson.\n\n*AB. Tuna-Möbler, Matfors.\n\nTillverkar kompletteringsmöbler samt\nstoppade möbler vid fabrik i Matfors\n(Västernorrl. l.).\n\nTelefon: 265. Postgiro: 282171. —\nAkt.-kap.: 25,000 kr. Antal industriarb.:\n15. — Bolaget grundat 1944.\n\nStyrelse: heminredn.-ark. Nils\nLindholm (ordf.), fröken Maria Berglund, fru\nE. Lindholm, fru I. Lindholm,\nheminredn.-ark. Sven Lindholm.\n\nVerkst. dir.: Nils Lindholm.\n\n*Tunafors Fabriker, Eskilstuna.\n\nSe Eskilstuna Jernmanufaktur AB.,\nEskilstuna.\n\nAB. C. E. Tunelius Borst- &amp;\nPenselfabrik, Tierp.\n\nBorst- och penselfabrik med\nsadelma-keri och snickerifabrik i Tierp (Uppsala\n1.). Tillverkar borstar och penslar,\nbutiksinredningar, skolbänkar samt\nsadel-makerivaror.\n\nTelegr.-adr.: Tunelius, Tierp. Telefon:\n20 o. 140. Postgiro: 9021.\n\nAkt.-kap.: 150,000 kr. Antal\nindustriarb.: 100. Tillv.-värde pr år: 1,100,000 kr.\n\n—\tFirman etabl. 1899, bolag, 1915.\n\nStyrelse: fabr. G. E. Tunelius (ordf.),\n\ndir. C. W. Lundhammar, fröken A.\nTunelius.\n\nVerkst. dir.: G. E. Tunelius.\n\nKamrer: Tuve Johansson.",
    "structured": {
        "1": {
            "name": "Tullberg—Tunelius AB.",
            "location": "Stockholm",
            "business": "Boktryckeri, stål- och djup tryckeri, klichéanstalt, bokbinderi, bok- och blankettförlag.",
            "contact": {
                "office": "Vasag. 16",
                "phone": [
                    "Hasse W. Tullberg"
                ],
                "postgiro": "507",
                "head_office": "Drottninggatan 20",
                "sales_offices": [
                    {
                        "location": "Klara V. Kyrkogata 15",
                        "phone": "Kungsholmstorg 16; telefon: 534424"
                    }
                ],
                "telegraph": "Hasse, Stockholm",
                "factory_office": "Not provided",
                "factory_phone": "Not provided"
            },
            "financials": {
                "capital": "Not provided",
                "employees": {
                    "bolaget": 1905
                },
                "annual_turnover": "Not provided",
                "annual_production_value": "Not provided"
            },
            "foundation_year": 1871,
            "corporation_year": 1905,
            "board": [
                {
                    "name": "disp, Gösta Smith",
                    "role": "Not provided"
                }
            ],
            "original_name": "Not provided"
        },
        "2": {
            "name": "AB. R. S. Tullberg",
            "location": "Klippan",
            "business": "Bok- och offsettryckeri samt kontors-bokfabrik.",
            "contact": {
                "office": "Not provided",
                "phone": [
                    "82",
                    "486"
                ],
                "postgiro": "10199",
                "head_office": "Not provided",
                "sales_offices": [
                    {
                        "location": "Stockholm",
                        "phone": "534424"
                    }
                ],
                "telegraph": "Tullberg, Klippan",
                "factory_office": "Not provided",
                "factory_phone": "Not provided"
            },
            "financials": {
                "capital": "200,000 kr",
                "employees": {
                    "Antal industriarb.": 60
                },
                "annual_turnover": "Not provided",
                "annual_production_value": "Not provided"
            },
            "foundation_year": 1909,
            "corporation_year": 1925,
            "board": [
                {
                    "name": "disp., Gösta Tullberg",
                    "role": "Not provided"
                }
            ],
            "original_name": "Not provided"
        },
        "3": {
            "name": "Tullgarns Cjuteri och Mek. Verkstads AB.",
            "location": "Uppsala",
            "business": "Mek. verkstad med gjuteri.",
            "contact": {
                "office": "Not provided",
                "phone": [
                    "39470"
                ],
                "postgiro": "32848",
                "head_office": "Not provided",
                "sales_offices": [],
                "telegraph": "Tullgarns, Uppsala",
                "factory_office": "Not provided",
                "factory_phone": "Not provided"
            },
            "financials": {
                "capital": "230,500 kr",
                "employees": {
                    "Antal industriarb.": 100
                },
                "annual_turnover": "Not provided",
                "annual_production_value": "1,500,000 kr"
            },
            "foundation_year": 1898,
            "corporation_year": "Not provided",
            "board": [
                {
                    "name": "överstelöjtn. Fritz Ploman",
                    "role": "ordf."
                },
                {
                    "name": "adv. Olof Chrysander",
                    "role": "Not provided"
                },
                {
                    "name": "ing. Sven E, Nilsson",
                    "role": "Not provided"
                }
            ],
            "original_name": "Not provided"
        },
        "4": {
            "name": "Tunabergs Trävaru AB.",
            "location": "Koppartorp",
            "business": "Sågverk och snickerifabrik.",
            "contact": {
                "office": "Not provided",
                "phone": [
                    "Koppartorp 42",
                    "43",
                    "Nyköping 30 a"
                ],
                "postgiro": "90220",
                "telegraph": "Skogsbruk, Nyköping",
                "factory_office": "Not provided",
                "factory_phone": "Not provided"
            },
            "financials": {
                "capital": "1,000,000 kr",
                "employees": {
                    "Antal industriarb.": 180
                },
                "annual_turnover": "Not provided",
                "annual_production_value": "7,000 stds trävaror"
            },
            "foundation_year": 1901,
            "corporation_year": 1923,
            "board": [
                {
                    "name": "godsäg. Henning Danielsson",
                    "role": "Not provided"
                },
                {
                    "name": "disp. Emrik Danielsson",
                    "role": "Not provided"
                },
                {
                    "name": "löjtn. Nils-Olof Danielsson",
                    "role": "Not provided"
                },
                {
                    "name": "disp. Olof Danielsson",
                    "role": "Not provided"
                },
                {
                    "name": "jäg-mäst. Gunnar Norén",
                    "role": "Not provided"
                }
            ],
            "original_name": "Not provided"
        },
        "5": {
            "name": "AB. Tunabröd",
            "location": "Stora Tuna",
            "business": "Kvarn och spisbrödsfabrik.",
            "contact": {
                "office": "Not provided",
                "phone": [
                    "33101",
                    "33065"
                ],
                "postgiro": "25966",
                "head_office": "Not provided",
                "sales_offices": [],
                "telegraph": "Not provided",
                "factory_office": "Not provided",
                "factory_phone": "Not provided"
            },
            "financials": {
                "capital": "150,000 kr",
                "employees": {
                    "Antal industriarb.": 35
                },
                "annual_turnover": "Not provided",
                "annual_production_value": "1,000,000 kr"
            },
            "foundation_year": 1923,
            "corporation_year": 1939,
            "board": [
                {
                    "name": "Not provided",
                    "role": "Not provided"
                }
            ],
            "original_name": "Not provided"
        },
        "6": {
            "name": "AB. Tuna-Möbler",
            "location": "Matfors",
            "business": "Tillverkar kompletteringsmöbler samt stoppade möbler vid fabrik.",
            "contact": {
                "office": "Not provided",
                "phone": [
                    "265"
                ],
                "postgiro": "282171",
                "head_office": "Not provided",
                "sales_offices": [],
                "telegraph": "Not provided",
                "factory_office": "Not provided",
                "factory_phone": "Not provided"
            },
            "financials": {
                "capital": "25,000 kr",
                "employees": {
                    "Antal industriarb.": 15
                },
                "annual_turnover": "Not provided",
                "annual_production_value": "Not provided"
            },
            "foundation_year": 1944,
            "corporation_year": "Not provided",
            "board": [
                {
                    "name": "heminredn.-ark. Nils Lindholm",
                    "role": "ordf."
                },
                {
                    "name": "fröken Maria Berglund",
                    "role": "Not provided"
                },
                {
                    "name": "fru E. Lindholm",
                    "role": "Not provided"
                },
                {
                    "name": "fru I. Lindholm",
                    "role": "Not provided"
                },
                {
                    "name": "heminredn.-ark. Sven Lindholm",
                    "role": "Not provided"
                }
            ],
            "original_name": "Not provided"
        },
        "7": {
            "name": "AB. C. E. Tunelius Borst- & Penselfabrik",
            "location": "Tierp",
            "business": "Borst- och penselfabrik med sadelmakeri och snickerifabrik.",
            "contact": {
                "office": "Not provided",
                "phone": [
                    "20",
                    "140"
                ],
                "postgiro": "9021",
                "head_office": "Not provided",
                "sales_offices": [],
                "telegraph": "Tunelius, Tierp",
                "factory_office": "Not provided",
                "factory_phone": "Not provided"
            },
            "financials": {
                "capital": "150,000 kr",
                "employees": {
                    "Antal industriarb.": 100
                },
                "annual_turnover": "Not provided",
                "annual_production_value": "1,100,000 kr"
            },
            "foundation_year": 1899,
            "corporation_year": 1915,
            "board": [
                {
                    "name": "fabr. G. E. Tunelius",
                    "role": "ordf."
                },
                {
                    "name": "dir. C. W. Lundhammar",
                    "role": "Not provided"
                },
                {
                    "name": "fröken A. Tunelius",
                    "role": "Not provided"
                }
            ],
            "original_name": "Not provided"
        }
    }
}