{
    "original": "S kandinaviska—-S kam\n\nriet, Stockholm. Telefon: »Skånska\nCementgjuter i et». Postgiro: 2650.\n\nAkt.-kap.: 30,000 kr. — Bolaget\ngrundat 1897.\n\nStyrelse: dir. Agne Sandberg (ordf.),\ning. Hugo Åsberg.\n\nVerkst. dir.: Agne Sandberg.\n\nDriftsledare: Hugo Åsberg.\n\n*AB. Skandinaviska\nSängresår-fabriken, Skattkärr.\n\nSängresår- och snickerifabriker i\nSkattkärr (Värml. l.) och i Karlstad.\nTillverkar resårmadrasser (märke:\n»Spring-madr assen»), bil-, buss- och spår\nvagnsdynor samt sängar, duchateller, soffor,\nsäng järn, vinkel järnsramar m. m.\n\nHuvudkontor: Skattkärr. Telefon: 133.\nPostgiro: 34022. Verkstadskontor:\nKarlstad, telefon: 10344. Avd.-kontor i\nStockholm, Drottningg. 73 C, telefon: 235775.\n\nAkt.-kap.: 125,000 kr. Antal\nindustriarb.: 106. — Firman etabl. 1900, bolag\n1943.\n\nStyrelse: ing. Lennart Ullberg (ordf.),\nfru Gerda Petersson, fru Eva Ullberg.\n\nVerkst. dir. o. disp.: Lennart Ullberg.\n\nKamrer: Theodor Ericson.\n\nVerkstadsing.: Per-Olov östergren.\n\n*AB. Skandinaviska\nTrådgardinfabriken, Tången, Stockholm.\n\nSe Tångens Gardinfabrik AB., Sthlm.\n\nSkandinaviska Träimport AB.,\n\nStockholm.\n\nTrä- och fanérlager, sågverk och\nång-torkar i Stockholm, trä- och fanérlager,\nfanérfabrik, sågverk, ångtorkar samt\nämnes-sågeri i Norrköping, trä- och\nfanérlager samt sågverk i Malmö. Bolaget\ndriver även handel med in- och utländska\nträvaror, fanér, plywood, lamellplattor\noch parkettstav.\n\nKontor: Stockholm, Värtahamnen.\nTelegr.-adr.: Träimport, Stockholm.\nTelefon: 670410. Avd.-kontor: Norrköping,\ntelefon: 23707 o. 23784; Malmö, S.\nNep-tunig. 6, telefon: 20137 o. 28127.\n\nAkt.-kap.: 1,200,000 kr. Antal\nindustriarb.: 65. — Firman etabl. 1901.\n\nStyrelse: dir. Hans Th. Holm (ordf.),\nbankdir. Frithiof Ahrén, dir. Hans Bruu,\nadv. Knut Littorin, försäljn.-chef Ragnar\nWinberg.\n\nVerkst. dir.: Hans Bruu.\n\n^Skandinaviska Verktygsfabriks\n\nAB., Tyringe.\n\nVerktygsfabrik i Tyringe (Kristianst.\n1.). Tillverkar gängverktyg, fräsar,\nbrot-schar m. m. samt chuckar och backskivor.\nVarumärke: S.V.A.\n\nTelefon: »Verktygsfabriken». Postgiro:\n7736.\n\nAkt.-kap.: 1,000,000 kr. Antal\nindustriarb.: 425. Tillv.-värde pr år: 5,000,000 kr.\n\n—\tBolaget grundat 1896.\n\nStyrelse.- dir. Carl Björk (ordf.), ing.\nGunnar Anderson, disp. Harry E.\nAnderson, rektor Emil Johansson, ing. G.\nStrandqvist.\n\nVerkst. dir.: Carl Björk.\nDisp.: Harry E. Anderson.\nKontorschef: Malte Niles.\n\n\"Skara Bryggeri AB., Skara.\n\nTillverkar maltdrycker och\nläskedrycker.\n\nTelegr.-adr.: Bryggeribolaget, Skara.\nTelefon: 105 o. 200. Postgiro: 74445.\n\nAkt.-kap.: 200,000 kr. Antal\nindustriarb.: 10. Tillv.-värde pr år: 200,000 kr.\n\n—\tBolaget grundat 1901.\n\nStyrelse: disp. Erik Petré (ordf.), dir.\nOskar Ahlström, ing. Henry Andersson,\nhovrättsassessor Bo Nilsson-Dag, disp.\nWilhelm Nilsson-Dag.\n\nVerkst. dir.: Henry Andersson.\nDisp.: Wilhelm Nilsson-Dag.\n\nAB. Skara Karosserifabrik, Skara.\n\nTillverkar förarhytter och lastflak,\nbrandbils-, likvagns- och\nskåpvagnskaros-serier m. m.\n\nTelefon: »J. Johansson &amp; Co.»\nPostgiro: 92987. - Akt.-kap.: 54,000 kr.\nAntal industriarb.: 25. — Bolaget grundat\n1929.\n\nDisp.: Egon Johansson.\n\n*Skara Skofabriks AB., Skara.\nSe AB. J. Bryntesson &amp; C:o, Skara.\n\n*Skara Snickeri &amp; Trävaruaffär,\nAndersson &amp; Sahiström, Skara.\n\nTillverkar ^ dörrar och fönster samt\nbutiksinredningar. Firman driver även\nhandel med trävaror.\n\nTelefon: 121. Postgiro: 164106. —\nArb.-antal: 7. Tillv.-värde pr år: 100,000 kr.\n\n—\tFirman etabl. 1910.\n\nÄgare o. chefer: trävaruhandl. Nils\nSahiström, trävaruhandl. Olof Sahiström\no. fabr. Johan L. Andersson.\n\n482*",
    "structured": {
        "1": {
            "name": "Skandinaviska Sängresår-fabriken",
            "location": "Skattkärr",
            "business": "Sängresår- och snickerifabriker",
            "products": "Tillverkar resårmadrasser (märke: »Spring-madr assen»), bil-, buss- och spårvagnsdynor samt sängar, duchateller, soffor, sängjärn, vinkeljärnsramar m. m.",
            "contact": {
                "office": "Skattkärr",
                "phone": [
                    "133"
                ],
                "postgiro": "34022",
                "head_office": "Skattkärr",
                "sales_offices": [
                    {
                        "location": "Karlstad",
                        "phone": "10344"
                    },
                    {
                        "location": "Stockholm, Drottningg. 73 C",
                        "phone": "235775"
                    }
                ]
            },
            "financials": {
                "capital": "125,000 kr",
                "employees": {
                    "industriarb": 106
                },
                "annual_turnover": "Not available",
                "annual_production_value": "Not available"
            },
            "foundation_year": 1900,
            "corporation_year": 1943,
            "board": [
                {
                    "name": "ing. Lennart Ullberg",
                    "role": "ordf."
                },
                {
                    "name": "fru Gerda Petersson",
                    "role": ""
                },
                {
                    "name": "fru Eva Ullberg",
                    "role": ""
                }
            ]
        },
        "2": {
            "name": "Skandinaviska Träimport AB.",
            "location": "Stockholm",
            "business": "Trä- och fanérlager, sågverk och ångtorkar",
            "products": "Not available",
            "contact": {
                "office": "Stockholm, Värtahamnen",
                "phone": "670410",
                "postgiro": "Not available",
                "sales_offices": [
                    {
                        "location": "Norrköping",
                        "phone": "23707 o. 23784"
                    },
                    {
                        "location": "Malmö, S. Nep-tunig. 6",
                        "phone": "20137 o. 28127"
                    }
                ]
            },
            "financials": {
                "capital": "1,200,000 kr",
                "employees": {
                    "industriarb": 65
                },
                "annual_turnover": "Not available",
                "annual_production_value": "Not available"
            },
            "foundation_year": 1901,
            "corporation_year": "Not available",
            "board": [
                {
                    "name": "dir. Hans Th. Holm",
                    "role": "ordf."
                },
                {
                    "name": "bankdir. Frithiof Ahrén",
                    "role": ""
                },
                {
                    "name": "dir. Hans Bruu",
                    "role": ""
                },
                {
                    "name": "adv. Knut Littorin",
                    "role": ""
                },
                {
                    "name": "försäljn.-chef Ragnar Winberg",
                    "role": ""
                }
            ]
        },
        "3": {
            "name": "Skandinaviska Verktygsfabriks AB.",
            "location": "Tyringe",
            "business": "Verktygsfabrik",
            "products": "Tillverkar gängverktyg, fräsar, brotschar m. m. samt chuckar och backskivor. Varumärke: S.V.A.",
            "contact": {
                "office": "Tyringe (Kristianst. l.)",
                "phone": "Not available",
                "postgiro": "7736",
                "head_office": "Tyringe",
                "sales_offices": []
            },
            "financials": {
                "capital": "1,000,000 kr",
                "employees": {
                    "industriarb": 425
                },
                "annual_turnover": "5,000,000 kr",
                "annual_production_value": "Not available"
            },
            "foundation_year": 1896,
            "corporation_year": "Not available",
            "board": [
                {
                    "name": "dir. Carl Björk",
                    "role": "ordf."
                },
                {
                    "name": "ing. Gunnar Anderson",
                    "role": ""
                },
                {
                    "name": "disp. Harry E. Anderson",
                    "role": ""
                },
                {
                    "name": "rektor Emil Johansson",
                    "role": ""
                },
                {
                    "name": "ing. G. Strandqvist",
                    "role": ""
                }
            ]
        },
        "4": {
            "name": "Skara Bryggeri AB.",
            "location": "Skara",
            "business": "Tillverkar maltdrycker och läskedrycker.",
            "products": "Not available",
            "contact": {
                "office": "Skara",
                "phone": [
                    "105",
                    "200"
                ],
                "postgiro": "74445",
                "head_office": "Skara",
                "sales_offices": []
            },
            "financials": {
                "capital": "200,000 kr",
                "employees": {
                    "industriarb": 10
                },
                "annual_turnover": "200,000 kr",
                "annual_production_value": "Not available"
            },
            "foundation_year": 1901,
            "corporation_year": "Not available",
            "board": [
                {
                    "name": "disp. Erik Petré",
                    "role": "ordf."
                },
                {
                    "name": "dir. Oskar Ahlström",
                    "role": ""
                },
                {
                    "name": "ing. Henry Andersson",
                    "role": ""
                },
                {
                    "name": "hovrättsassessor Bo Nilsson-Dag",
                    "role": ""
                },
                {
                    "name": "disp. Wilhelm Nilsson-Dag",
                    "role": ""
                }
            ]
        },
        "5": {
            "name": "Skara Karosserifabrik",
            "location": "Skara",
            "business": "Tillverkar förarhytter och lastflak, brandbils-, likvagns- och skåpvagnskarosserier m. m.",
            "products": "Not available",
            "contact": {
                "office": "Skara",
                "phone": [
                    "92987"
                ],
                "postgiro": "Not available",
                "head_office": "Skara",
                "sales_offices": []
            },
            "financials": {
                "capital": "54,000 kr",
                "employees": {
                    "industriarb": 25
                },
                "annual_turnover": "Not available",
                "annual_production_value": "Not available"
            },
            "foundation_year": 1929,
            "corporation_year": "Not available",
            "board": [
                {
                    "name": "Not available",
                    "role": ""
                }
            ]
        },
        "6": {
            "name": "Skara Snickeri & Trävaruaffär",
            "location": "Skara",
            "business": "Tillverkar dörrar och fönster samt butiksinredningar. Firman driver även handel med trävaror.",
            "products": "Not available",
            "contact": {
                "office": "Skara",
                "phone": [
                    "121"
                ],
                "postgiro": "164106",
                "head_office": "Skara",
                "sales_offices": []
            },
            "financials": {
                "capital": "Not available",
                "employees": {
                    "arb": 7
                },
                "annual_turnover": "100,000 kr",
                "annual_production_value": "Not available"
            },
            "foundation_year": 1910,
            "corporation_year": "Not available",
            "board": [
                {
                    "name": "Not available",
                    "role": ""
                }
            ],
            "owners": [
                "trävaruhandl. Nils Sahiström",
                "trävaruhandl. Olof Sahiström",
                "fabr. Johan L. Andersson"
            ]
        }
    }
}