{
    "original": "Korp—Kosta\n\nPostadr.: Umeå. Telefon: Umeå 908\no. 1380. Postgiro: 62797. — Akt.-kap.:\n33,400 kr. Antal industriarb.: 15.\nTillv.-värde pr år: 250,000 kr. — Bolaget\ngrundat 1933.\n\nVerkst. dir.: disp. Algot Schäder.\n\nKorp &amp; Söners Verkstäder,\n\nVänersborg.\n\nTillverkar betongblandare, järn- och\nplåtsaxar, bockningsmaskiner,\nmurbruksmaskiner, sandelevatorer,\nkalksläcknings-maskiner, kalkvispar, friktionsspel,\nstansmaskiner, skruvstycken, dörrar och luckor\nav järn och stål, järnkonstruktioner för\nhus- och brobyggnader samt\ngrovplåts-arbeten\n\nTelefon: 1869. Postgiro: 281730. —\nAntal industriarb.: 100. Tillv.-värde pr\når: 1,500,000 kr. — Firman etabl. 1921.\n\nChef: fabr. Helge E. Korp.\n\n*Korsberga Tegelbruks AB.,\n\nVärnamo.\n\n^ Tillverkar mur-, fasad- och\nrevete-ringstegel, taktegel samt dräneringsrör\nvid tegelbruk i Korsberga (Skarab. l.).\nSpecialiteter: rör och fasadtegel.\n\nKontor: Värnamo. Telefon: 10098 o.\n10638. Postgiro: 92911. Repr.:\nTegelförsäljningskontoret, Skövde, telefon: 873, o.\nJönköping, telefon: 4197.\n\nAkt.-kap.: 160,000 kr. Antal\nindustriarb.: 40. Årstillv.: 4 milj. st. tegel varor.\n\n—\tBolaget grundat 1936.\n\nVerkst. dir. o. disp.: Gunnar Thilén.\n\nKamrer: Lage Thilén.\n\nTegelmäst.: Karl Sundström.\n\nKorsettfabriken Spirella AB.,\n\nMalmö.\n\nTillverkar gördlar, korsetter samt\nbysthållare efter mått. Varunamn: »Spirella».\n\nKontor: Davidshallsg. 18. Telegr.-adr.:\nSpirella, Malmö. Telefon: 72395.\nPostgiro: 37720.\n\nAkt.-kap.: 800,000 kr. Antal\nindustriarb.: 100. Tillv.-värde pr år: 2,000,000 kr.\n\n—\tFirman etabl. 1916, bolag 1920.\n\nStyrelse: disp. Carl J. Bergh (ordf.),\n\nkonsul Thorsten C. Bergh, adv. Rolf\nNor-denstedt, dir. John W. Stewart.\n\nVerkst. dir.: Arthur C. Stewart.\n\nAB. Korsnäs Koppartråd &amp;\nKabelfabrik, Korsnäs.\n\nTråddrageri i Korsnäs (Kopparb. l.).\nTillverkar hård och glödgad koppartråd,\nkopparlinor.\n\nTelegr.-adr.: Korsnäskoppar, Korsnäs.\nTelefon: 36. Postgiro: 24015. —\nAkt.-kap.: 50,000 kr. Arb.-antal: 10. Årstillv.:\n2,000 ton. — Bolaget grundat 1922.\n\nStyrelse: fru A. Westman (ordf.), jur.\nstud. Hans Lindblad, grossh. Tore\nWestman.\n\nVerkst. led.: fru A. Westman.\n\nDriftschef: förvalt. J. Gellström.\n\n\"Korsnäs Sågverks AB., Gävle.\n\nSågverk, hyvleri och trähusfabrik,\nsulfit-, sulfat- och spritfabriker samt\npappersbruk vid Korsnäsverken, Gävle.\n\nTillverkar sågade och hyvlade trävaror,\nmonteringsfärdiga trähus, blekt ^ och\noblekt sulfit- och sulfatcellulosa,\nsilke-cellulosa, M. G. och ogl. sulf at (kraft)\npapper i oblekt och blekt utförande,\nsäckpapper, spinnpapper, kraftpapperssäckar,\nkraftliner, sulfitsprit, flytande harts,\nterpentin samt driver skogs- och jordbruk.\n\nHuvudkontor: Gävle 2. Telegr.-adr.:\nKorsnäs, Gävle. Telefon:\n»Korsnäsver-ken». Postgiro: 13001.\n\nAkt.-kap.: 21,000,000 kr. Antal\nindustriarb.: 1,150. Årstillv.: 30,000 stds\nsågade och hyvlade trävaror, 65,000 ton\nsulfitcellulosa, 38,000 ton sulfatcellulosa,\n12,000 ton papper, 3,000,000 ltr\nsulfitsprit.\n\nBolaget, grundat 1855, äger Trävaru\nAB. Dalarne, Vansbro, o. Gimo AB.,\nGimo.\n\nStyrelse: kabinettskammarh. Robert v.\nHorn (ordf.), dir. Sven V. Engwall, dir.\nErik W. Eriksson, frih. Wilh. Klingspor,\nf. d. överfyring. F. Lundeberg, överste\nGunnar Salander, adv. Hugo Stenbeck.\n\nVerkst. dir.: Erik W. Eriksson.\n\nTekn. dir.: civiling. John Spangenberg.\n\nSkogschef: C. E. Barth.\n\nEkonomichef: C. R. Andersson.\n\nFörsäljn.-chef er: för cellulosa: disp.\nGösta Hall; för trävaror: disp. Erik\nHellman; för papper: Carl Otto Dahlén.\n\n\"AB. Kosta Glasbruk, Kosta.\n\nGlasbruk i Kosta (Kronob. l.).\nTillverkar konstglas, slipat och graverat\nprydnadsglas, servisglas och hushållsglas,\nkonserv- och hushållsburkar. Bolaget idkar\njämväl jordbruk.\n\nTelegr.-adr.: Kostabolaget, Växjö.\nTelefon: 1—3. Postgiro: 84630.\nFörsäljn.-kontor i Stockholm: AB. De Svenska\nKristallglasbruken, Klarabergsg. 56; telefon:\n103755.\n\nAkt.-kap.: 800,000 kr. Antal\nindustriarb.: 350. Tillv.-värde pr år: 3,000,000 kr.\n\nGlasbruket anlagt 1742, nuv. bolag\ngrundat 1894, ny bolagsordning 1904.",
    "structured": {
        "1": {
            "name": "Korp—Kosta",
            "location": "Umeå",
            "contact": {
                "phone": [
                    "Umeå 908",
                    "1380"
                ],
                "postgiro": "62797"
            },
            "financials": {
                "capital": "33,400 kr",
                "employees": {
                    "industriarb": 15
                },
                "annual_turnover": "250,000 kr"
            },
            "foundation_year": 1933,
            "board": [
                {
                    "name": "Algot Schäder",
                    "role": "disp."
                }
            ]
        },
        "2": {
            "name": "Korp & Söners Verkstäder",
            "location": "Vänersborg",
            "products": "Tillverkar betongblandare, järn- och plåtsaxar, bockningsmaskiner, murbruksmaskiner, sandelevatorer, kalksläcknings-maskiner, kalkvispar, friktionsspel, stansmaskiner, skruvstycken, dörrar och luckor av järn och stål, järnkonstruktioner för hus- och brobyggnader samt grovplåts-arbeten",
            "contact": {
                "phone": "1869",
                "postgiro": "281730"
            },
            "financials": {
                "capital": "N/A",
                "employees": {
                    "industriarb": 100
                },
                "annual_turnover": "1,500,000 kr"
            },
            "foundation_year": 1921,
            "director": "Helge E. Korp"
        },
        "3": {
            "name": "Korsberga Tegelbruks AB.",
            "location": "Värnamo",
            "products": "Tillverkar mur-, fasad- och revere-ringstegel, taktegel samt dräneringsrör vid tegelbruk i Korsberga (Skarab. l.). Specialiteter: rör och fasadtegel",
            "contact": {
                "phone": [
                    "10098",
                    "10638"
                ],
                "postgiro": "92911"
            },
            "financials": {
                "capital": "160,000 kr",
                "employees": {
                    "industriarb": 40
                },
                "annual_turnover": "4 milj. st. tegel varor"
            },
            "foundation_year": 1936,
            "board": [
                {
                    "name": "Gunnar Thilén",
                    "role": "Verkst. dir. o. disp."
                },
                {
                    "name": "Karl Sundström",
                    "role": "Tegelmäst."
                }
            ]
        },
        "4": {
            "name": "Korsettfabriken Spirella AB.",
            "location": "Malmö",
            "products": "Tillverkar gördlar, korsetter samt bysthållare efter mått. Varunamn: »Spirella»",
            "contact": {
                "office": "Davidshallsg. 18",
                "telegraph": "Spirella, Malmö",
                "phone": "72395",
                "postgiro": "37720"
            },
            "financials": {
                "capital": "800,000 kr",
                "employees": {
                    "industriarb": 100
                },
                "annual_turnover": "2,000,000 kr"
            },
            "foundation_year": 1916,
            "current_name_year": 1920,
            "board": [
                {
                    "name": "Carl J. Bergh",
                    "role": "disp."
                },
                {
                    "name": "Thorsten C. Bergh",
                    "role": "konsul"
                },
                {
                    "name": "Rolf Nordenstedt",
                    "role": "adv."
                },
                {
                    "name": "John W. Stewart",
                    "role": "dir."
                }
            ],
            "managing_director": "Arthur C. Stewart"
        },
        "5": {
            "name": "AB. Korsnäs Koppartråd & Kabelfabrik",
            "location": "Korsnäs",
            "products": "Tillverkar hård och glödgad koppartråd, kopparlinor",
            "contact": {
                "telegraph": "Korsnäskoppar, Korsnäs",
                "phone": "36",
                "postgiro": "24015"
            },
            "financials": {
                "capital": "50,000 kr",
                "employees": {
                    "antal": 10
                },
                "annual_production_value": "2,000 ton"
            },
            "corporation_year": 1922,
            "board": [
                {
                    "name": "fru A. Westman",
                    "role": "Styrelse"
                },
                {
                    "name": "Hans Lindblad",
                    "role": "jur. stud."
                },
                {
                    "name": "Tore Westman",
                    "role": "grossh."
                }
            ],
            "director": "fru A. Westman",
            "factory_office": "Korsnäs (Kopparb. l.)"
        },
        "6": {
            "name": "Korsnäs Sågverks AB.",
            "location": "Gävle",
            "products": "Tillverkar sågade och hyvlade trävaror, monteringsfärdiga trähus, blekt ^ och oblekt sulfit- och sulfatcellulosa, silke-cellulosa, M. G. och ogl. sulfat (kraft) papper i oblekt och blekt utförande, säckpapper, spinnpapper, kraftpapperssäckar, kraftliner, sulfitsprit, flytande harts, terpentin samt driver skogs- och jordbruk",
            "contact": {
                "head_office": "Gävle 2",
                "telegraph": "Korsnäs, Gävle",
                "phone": "»Korsnäsver-ken»",
                "postgiro": "13001"
            },
            "financials": {
                "capital": "21,000,000 kr",
                "employees": {
                    "industriarb": 1,
                    "sågade och hyvlade trävaror": 350,
                    "sulfitcellulosa": 65,
                    "sulfatcellulosa": 38,
                    "papper": 12,
                    "sulfitsprit": 3
                }
            }
        },
        "7": {
            "name": "AB. Kosta Glasbruk",
            "location": "Kosta (Kronob. l.)",
            "products": "Tillverkar konstglas, slipat och graverat prydnadsglas, servisglas och hushållsglas, konserv- och hushållsburkar",
            "contact": {
                "telegraph": "Kostabolaget, Växjö",
                "phone": "1—3",
                "postgiro": "84630"
            },
            "financials": {
                "capital": "800,000 kr",
                "employees": {
                    "industriarb": 350
                },
                "annual_turnover": "3,000,000 kr"
            }
        }
    }
}