{
    "original": "Trävaru—Tuf vasson\n\ntaf Johansson, grossh. M. Markussen,\nträ-varuhandl. Gustaf A. Nilsson, godsäg.\nBirger Skogström.\n\nDisp.: Arvid Fälth.\n\nKamrer: Thorsten Nilsson.\n\n*Trävaru AB. Norrköpings Export-\n\nhyfleri, Norrköping.\n\nSågverk och hyvleri i Blankaholm\n(Kalmar l.), hyvleri och trähusfabrik i\nNorrköping. Tillverkar sågade och\nhyvlade trävaror, laths, kvastkäppämnen och\nlådbräder samt byggnadssnickerier och\nmonteringsfärdiga trähus.\n\nTelegr.-adr.: Hyfleriet, Norrköping.\nTelefon: 22907. Postgiro: 137824.\n\nAkt.-kap.: 525,000 kr. Antal\nindustriarb.: 175. Årstillv.: 18,000 stds sågade o.\nhyvlade trävaror. — Bolaget grundades\n1903, ombildat 1929.\n\nStyrelse: disp. Emrik Danielsson,\ngods-äg. Henning Danielsson, disp. Olof\nDanielsson, disp. Åke Danielsson.\n\nVerkst. dir. o. disp.: Åke Danielsson.\n\n\"Trävara AB. Svartvik, Sundsvall.\n\nSe Svartviks AB., Sundsvall.\n\nTrönninge Cummifabriks AB.,\n\nT rönninge.\n\nTillverkar tekniska gummi varor såsom\npackningar, formartiklar, slangar m. m.\nvid fabrik i Trönninge (Hallands l.).\n\nTelefon: »Gummifabriken». —\nAkt.-kap.: 75,000 kr. Antal industriarb.: 40.\nTillv.-värde pr år: 500,000 kr. — Bolaget\ngrundat 1941.\n\nVerkst. dir.: G. Rossel.\n\nFabrikschef: Allan Ekelund.\n\n\"Trönninge Tegelbruks AB.,\n\nTrönninge.\n\nTillverkar fasad- och murtegel samt\ndräneringsrör vid tegelbruk i Trönninge\n(Hallands l.). Specialiteter:\nbjälklags-tegel, högporösa tegel samt\nmellanväggsplattor.\n\nTelefon: 6. Postgiro: 99486. Repr.:\nSöderberg &amp; Haak AB., Göteborg, telefon:\n»Söderberg-Haak».\n\nAkt.-kap.: 100,000 kr. Antal\nindustriarb.: 30. Årstillv.: 3,7 milj. st. tegelvaror.\n— Bolaget grundat 1898.\n\nVerkst. dir.: Axel Andersson.\n\nTubus, Svenska AB., Uddevalla.\n\nSe Svenska AB. Tubus, Uddevalla.\n\n\"AB. Tudor, Stockholm.\n\nAckumulatorfabrik vid Nol (Älvsb. l.),\ntorrelementfabrik (Pertrixverken) vid\nMariehäll, Sundbyberg.\n\nTillverkar elektr. ackumulatorer,\nalkaliska och blyackumulatorer för stationära\noch transportabla ändamål samt förelbilar,\nstartbatterier, radiobatterier,\nackumulatorer för signaländamål, torrelement,\nlikrik-tare och laddningsanordningar, elektr.\nmotstånd, vindgeneratorer, ansiktsskydd\nför svetsning m. m. samt blymönja,\nbly-glete, ackumulatorsyra och destillerat\nvatten. Varumärke »Tudor» för\nstationära, traktionära, start-, belysnings- och\nradioackumulatorer samt för likriktare,\nelektr. installationsmateriel (B-rör) och\nelektr. strålkaminer.\n\nBolaget driver jämväl försäljning av\nvattendestillationsapparater.\n\nHuvudkontor och utställning:\nStockholm, Birger Ja*lsg. 55. Telegr.-adr.:\nAcumulator, Stockholm. Telefon:\n»Tu-dorbatterier». Postgiro: 562.\nReparationsverkstäder och laddningsstationer:\nStockholm, Birger Jarlsg. 55; Göteborg,\nKungs-höjdsg. 3, telefon: 172960; Malmö,\nExer-cisg. 12, telefon: 71370.\n\nAkt.-kap.: 2,500,000 kr. Antal\nindustriarb.: 870. — Bolaget grundat 1914, under\nnamn Ackumulator-Fabriks AB. Tudor;\nnuv. namn 1946.\n\nStyrelse: f. riksmarskalk Axel\nVenner-sten (ordf.), f. generaldir. greve A.\nHa-milton, övering. W. F. Kugelberg,\növerintendent H. W. Lettström, f. bankdir.\nM. Philipson, kommendörkapten Erik\nSundblad, konteramiral Nils Wijkmark.\n\nVerkst. dir.: Erik Sundblad.\n\nTekn. dir.: H. Y. Wikander.\n\nÖvering.: Nils Sterner.\n\nFörsäljn.-chef: Ernst Ek.\n\nKamrer: A. Bothorp.\n\nKassör: Gustaf Holmgren.\n\nPlatschefer: i Nol: övering. Erik\nSundberg; i Sundbyberg: ing. Ture Jacobson.\n\nFilialchefer: i Göteborg: Douglas\nOlsson; i Malmö för transportabla batterier:\ning. Kjell Sandberg, o. för stationära o.\nelbilsbatterier: ing. R. Stålskog.\n\nTuf vassons Transformatorfabrik\n\nAB., Sigtuna.\n\nTillverkar transformatorer.\nTelefon: 101. Postgiro: 143360. —\nAkt.-kap.: 30,400 kr. Antal industriarb.:\n20. Tillv.-värde pr år: 720,000 kr. —\nBolaget grundat 1938.\n\nVerkst. dir.: ing. Birger Tuf vasson.",
    "structured": {
        "1": {
            "name": "Trävaru AB",
            "location": "Norrköping",
            "business": "Tillverkar sågade och hyvlade trävaror, laths, kvastkäppämnen och lådbräder samt byggnadssnickerier och monteringsfärdiga trähus.",
            "contact": {
                "office": "Norrköpings Export-hyfleri, Norrköping",
                "phone": [
                    "22907"
                ],
                "postgiro": "137824",
                "telegraph": "Hyfleriet, Norrköping"
            },
            "financials": {
                "capital": "525,000 kr",
                "employees": {
                    "industriarb": 175
                },
                "annual_turnover": "18,000 stds sågade o. hyvlade trävaror",
                "annual_production_value": "18,000 stds sågade o. hyvlade trävaror"
            },
            "foundation_year": 1903,
            "current_name_year": 1929,
            "board": [
                {
                    "name": "Emrik Danielsson",
                    "role": "disp."
                },
                {
                    "name": "Henning Danielsson",
                    "role": "gods-äg."
                },
                {
                    "name": "Olof Danielsson",
                    "role": "disp."
                },
                {
                    "name": "Åke Danielsson",
                    "role": "disp., Verkst. dir."
                }
            ]
        },
        "2": {
            "name": "Trönninge Cummifabriks AB",
            "location": "Trönninge",
            "business": "Tillverkar tekniska gummi varor såsom packningar, formartiklar, slangar m. m.",
            "contact": {
                "office": "Trönninge (Hallands l.)",
                "phone": [
                    "Gummifabriken"
                ]
            },
            "financials": {
                "capital": "75,000 kr",
                "employees": {
                    "industriarb": 40
                },
                "annual_production_value": "500,000 kr"
            },
            "foundation_year": 1941,
            "director": "G. Rossel",
            "manager": "Allan Ekelund"
        },
        "3": {
            "name": "Trönninge Tegelbruks AB",
            "location": "Trönninge",
            "business": "Tillverkar fasad- och murtegel samt dräneringsrör",
            "contact": {
                "office": "Trönninge (Hallands l.)",
                "phone": [
                    "6"
                ],
                "postgiro": "99486"
            },
            "financials": {
                "capital": "100,000 kr",
                "employees": {
                    "industriarb": 30
                },
                "annual_production_value": "3,7 milj. st. tegelvaror"
            },
            "foundation_year": 1898,
            "director": "Axel Andersson"
        },
        "4": {
            "name": "AB. Tudor",
            "location": "Stockholm",
            "business": "Ackumulatorfabrik vid Nol (Älvsb. l.), torrelementfabrik (Pertrixverken) vid Mariehäll, Sundbyberg.",
            "contact": {
                "head_office": "Stockholm, Birger Ja*lsg. 55",
                "phone": [
                    "Tu-dorbatterier"
                ],
                "postgiro": "562",
                "sales_offices": [
                    {
                        "location": "Göteborg",
                        "phone": "172960"
                    },
                    {
                        "location": "Malmö",
                        "phone": "71370"
                    }
                ]
            },
            "financials": {
                "capital": "2,500,000 kr",
                "employees": {
                    "industriarb": 870
                }
            },
            "foundation_year": 1914,
            "corporation_year": 1946,
            "board": [
                {
                    "name": "Axel Venner-sten",
                    "role": "ordf."
                },
                {
                    "name": "A. Ha-milton",
                    "role": "f. generaldir."
                },
                {
                    "name": "W. F. Kugelberg",
                    "role": "övering."
                },
                {
                    "name": "H. W. Lettström",
                    "role": "överintendent"
                },
                {
                    "name": "M. Philipson",
                    "role": "f. bankdir."
                },
                {
                    "name": "Erik Sundblad",
                    "role": "kommendörkapten"
                },
                {
                    "name": "Nils Wijkmark",
                    "role": "konteramiral"
                }
            ],
            "director": "Erik Sundblad"
        },
        "5": {
            "name": "Tuf vassons Transformatorfabrik AB",
            "location": "Sigtuna",
            "business": "Tillverkar transformatorer.",
            "contact": {
                "office": "Sigtuna",
                "phone": [
                    "101"
                ],
                "postgiro": "143360"
            },
            "financials": {
                "capital": "30,400 kr",
                "employees": {
                    "industriarb": 20
                },
                "annual_production_value": "720,000 kr"
            },
            "foundation_year": 1938,
            "director": "ing. Birger Tuf vasson"
        }
    }
}