{
    "original": "Skånska—Skästra\n\nFirman etabl. 1917, bolag 1921, äges av\nAB. Wasa Spisbrödsfabrik, Filipstad.\n\nStyrelse: konsul Karl Lundström\n(ordf.), disp. Sven Lindquist, fru G.\nLundström.\n\nVerkst. dir.: Karl Lundström (Sthlm).\n\nDisp.: Sven Lindquist.\n\n\"Skånska Svavelsyrefabrikerna,\n\nHälsingborg.\n\nSe Reymersholms Gamla Industri AB.,\nHälsingborg.\n\n\"Skånska Takpappfabriken,\nBönne-lyche &amp; Thuröe AB., Malmö.\n\nTillverkar takpapp, tjära,\nisoleringsmattor, oljor och färger,\nimpregnerings-medel samt besprutningsmedel för\nfruktträd. Varumärken: »Astral», »Astralit»,\n»Rex», »Cuprinol» o. »Bisol». Firman\ndriver även engroshandel med\nbyggnadsmaterial.\n\nKontor: österg. 3. Telegr.-adr.:\nBön-nelyche, Malmö. Telefon,: »Bönnelyche\n&amp;’ Thuröe». Postgiro: 38538.\n\nAkt.-kap.: 600,000 kr. Antal\nindustriarb.: 40. Tillv.-värde pr år: 2,000,000 kr.\n— Fabriken grundad 1889, bolag 1939.\n\nStyrelse: konsul K. Bönnelyche,\nassessor Hans Falck, disp. Gustaf Hjort,\ntand-läk. G. Köhler, frih. Gösta Rappe,\ngene-rallöjtn. E. Testrup, ing. E. Thuröe.\n\nVerkst. dir.: K. Bönnelyche.\n\nKontorschef: A. Hofverberg.\n\n\"AB. Skånska Yllefabriken,\n\nKristianstad.\n\nYlleväveri, ull- och kamgarnsspinneri\nsamt färgeri. Tillverkar kamgarner samt\nyllevävnader såsom kommiss, kläden,\npa-letå-, ulster-, kostym- och dräkttyger.\n\nTelefon: »Skånska Yllefabriken».\nPostgiro: 80375.\n\nAkt.-kap.: 1,701,000 kr. Antal\nindustriarb.: 600. — Bolaget grundat 1898.#\n\nStyrelse: v. konsul Carl Nilsson\n(ordf.), dir. Hjalmar Carlborn, dir. Nils\nEngberg, v. konsul P. G. Laveson,\nborgarrådet Harald Mårtens, adv. Thorsten\nPersson, grossh. Thure Persson.\n\nVerkst. dir.: Nils Engberg.\n\nDir.-assist.: civiling. Kaj Engberg.\n\nFabrikschef: ing. Bertil Melin.\n\nKamrer; civilekonom Knut Rönneman.\n\n\"Skånska Ättikfabriken, AB.,\n\nPerstorp.\n\nKolugnar med destillationsverk,\nättiksyrafabrik, formalinfabrik, lösningsme-\n\ndelsfabrik, konsthartsfabrik, sågverk,\nparkettfabrik, möbelfabrik samt\narmatur-fabrik i Perstorp (Kristianst. l.),\n\nTillverkar bokträkol, boktjära,\nkarboli-neum, bokbeek, kreosot, metylalkohol,\nbu-tylalkohol, amylalkohol, etylacetat,\nbutyl-acetat, amylacetat, aceton m. fl.\nlösningsmedel, isättika, ättiksyra,\nmonoklorättik-syra, formalin, paraformalin,\nhexametyl-entetramin, natriumacetat,\nkonstharts-(Isolit-)produkter, plank och sågade\nämnen av lövträ, möbler, radiolådor, parkett\nsamt elektrisk belysningsarmatur.\n\nTelegr.-adr. o. telefon: Ättikfabriken,\nPerstorp. Postgiro: 37000. Avd.-kontor: i\nStockholm: Kungsg. 48, telefon: 233085;\ni Göteborg: S. Larmg. 6, telefon: 116617\no. 116618.\n\nAkt.-kap.: 2,000,000 kr. Antalet\nanställda: 945, varav 715 industriarb. —\nFirman etabl. 1883, bolag 1925.\n\nStyrelse: civiling. J. Olof Nauclér, fru\nMargareta Näs, civiling. Guy Wendt,\nciviling. Harold Wendt, fröken Maria\nWendt, fru Minna Wendt, civiling. Otto\nWendt.\n\nVerkst. dir.: Otto Wendt.\n\nChef för Stockholmskontoret: dir. Érik\nKillander.\n\nSkåpafors Pappersbruk, Skåpafars.\n\nSe Gustafsfors Fabrikers AB.,\nBil-lingsfors.\n\n*Skärblacka Pappersbruk,\n\nSkäi*blacka.\n\nSe Fiskeby Fabriks AB., Norrköping.\nGunnar Skärfve, Anderstorp.\n\nTillverkar piprensare, cykelrockskydd,\nvindskydd samt motorglasögon vid fabrik\ni Anderstorp (Jönköp. l.).\n\nTelefon: 97. Postgiro: 97788. — Antal\narb.: 9. Tillv.-värdé pr år: 100,000 kr. —\nFirman etabl. 1935.\n\nÄgare o. chef: fabr. Gunnar Skärfve.\n\nSkästra Ångsågs AB., Skästra.\n\nSågverk, hyvleri och^ tegelbruk vid\nSkästra (Gävleb. !.). Tillverkar sågade\noch hyvlade trävaror samt murtegel.\n\nTelegr.-adr.: Skästrasåg, Ljusdal.\nTelefon: Ljusdal 3211. Postgiro: 131344.\n\nAkt.-kap.: 346,000 kr. Antal\nindustriarb.: 53. Årstillv.: 1,500 stds trävaror,\n175,000 st. tegel. — Firman etabl. 1897.\n\nStyrelse: dir. Jonas Hanson (ordf.),\nlantbr. M. Mårtensson, lantbr. Olof Ols-\n\n5*",
    "structured": {
        "1": {
            "name": "Skånska Svavelsyrefabrikerna",
            "location": "Hälsingborg",
            "business": "Tillverkning av svavelsyra och relaterade kemiska produkter.",
            "contact": {
                "office": "Se Reymersholms Gamla Industri AB., Hälsingborg",
                "telegraph": "",
                "factory_office": "",
                "factory_phone": "",
                "sales_offices": []
            },
            "financials": {
                "capital": "",
                "employees": {},
                "annual_turnover": "",
                "annual_production_value": ""
            },
            "foundation_year": 0,
            "board": [],
            "owners": [],
            "director": ""
        },
        "2": {
            "name": "Skånska Takpappfabriken",
            "location": "Malmö",
            "business": "Tillverkning av takpapp, tjära, isoleringsmattor, oljor och färger.",
            "products": "Varumärken: »Astral», »Astralit», »Rex», »Cuprinol» och »Bisol». Firman driver även engroshandel med byggnadsmaterial.",
            "contact": {
                "office": "österg. 3",
                "telegraph": "Bön-nelyche, Malmö",
                "postgiro": "38538",
                "phone": [
                    "»Bönnelyche &’ Thuröe»"
                ]
            },
            "financials": {
                "capital": "600,000 kr",
                "employees": {
                    "industriarb": 40
                },
                "annual_turnover": "2,000,000 kr",
                "annual_production_value": ""
            },
            "foundation_year": 1889,
            "board": [
                {
                    "name": "K. Bönnelyche",
                    "role": "konsul"
                },
                {
                    "name": "Hans Falck",
                    "role": "assessor"
                },
                {
                    "name": "Gustaf Hjort",
                    "role": "disp."
                },
                {
                    "name": "G. Köhler",
                    "role": "tandläk."
                },
                {
                    "name": "Gösta Rappe",
                    "role": "frih."
                },
                {
                    "name": "E. Testrup",
                    "role": "generallöjtn."
                },
                {
                    "name": "E. Thuröe",
                    "role": "ing."
                }
            ],
            "owners": [],
            "director": ""
        },
        "3": {
            "name": "AB. Skånska Yllefabriken",
            "location": "Kristianstad",
            "business": "Ylleväveri, ull- och kamgarnsspinneri samt färgeri.",
            "products": "Tillverkar kamgarner samt yllevävnader såsom kommiss, kläden, paletå-, ulster-, kostym- och dräkttyger.",
            "contact": {
                "office": "",
                "telegraph": "",
                "postgiro": "80375",
                "phone": [
                    "Skånska Yllefabriken"
                ]
            },
            "financials": {
                "capital": "1,701,000 kr",
                "employees": {
                    "industriarb": 600
                },
                "annual_turnover": "",
                "annual_production_value": ""
            },
            "foundation_year": 1898,
            "board": [
                {
                    "name": "Carl Nilsson",
                    "role": "v. konsul"
                },
                {
                    "name": "Hjalmar Carlborn",
                    "role": "dir."
                },
                {
                    "name": "Nils Engberg",
                    "role": "dir."
                },
                {
                    "name": "P. G. Laveson",
                    "role": "v. konsul"
                },
                {
                    "name": "Harald Mårtens",
                    "role": "borgarrådet"
                },
                {
                    "name": "Thorsten Persson",
                    "role": "adv."
                },
                {
                    "name": "Thure Persson",
                    "role": "grossh."
                }
            ],
            "owners": [],
            "director": "Nils Engberg"
        },
        "4": {
            "name": "Skånska Ättikfabriken, AB.",
            "location": "Perstorp",
            "business": "Tillverkning av ättiksyra, formalin, konsthartsprodukter, sågade trävaror, möbler och elektrisk belysningsarmatur.",
            "products": "Tillverkar bokträkol, boktjära, karbolin, bokbeek, kreosot, lösningsmedel, isättika, ättiksyra, monoklorättiksyra, formalin, paraformalin, hexametylentetramin, natriumacetat.",
            "contact": {
                "office": "",
                "telegraph": "Ättikfabriken, Perstorp",
                "postgiro": "37000",
                "phone": []
            },
            "financials": {
                "capital": "2,000,000 kr",
                "employees": {
                    "total": 945,
                    "industriarb": 715
                },
                "annual_turnover": "",
                "annual_production_value": ""
            },
            "foundation_year": 1883,
            "board": [
                {
                    "name": "J. Olof Nauclér",
                    "role": "civiling."
                },
                {
                    "name": "Guy Wendt",
                    "role": "civiling."
                },
                {
                    "name": "Harold Wendt",
                    "role": "civiling."
                },
                {
                    "name": "Maria Wendt",
                    "role": "fröken"
                },
                {
                    "name": "Margareta Näs",
                    "role": "fru"
                },
                {
                    "name": "Minna Wendt",
                    "role": "fru"
                },
                {
                    "name": "Otto Wendt",
                    "role": "civiling."
                }
            ],
            "owners": [],
            "director": "Otto Wendt"
        },
        "5": {
            "name": "Skästra Ångsågs AB.",
            "location": "Skästra",
            "business": "Sågverk, hyvleri och tegelbruk.",
            "products": "Tillverkar sågade och hyvlade trävaror samt murtegel.",
            "contact": {
                "office": "",
                "telegraph": "Skästrasåg, Ljusdal",
                "postgiro": "131344",
                "phone": [
                    "Ljusdal 3211"
                ]
            },
            "financials": {
                "capital": "346,000 kr",
                "employees": {
                    "industriarb": 53
                },
                "annual_turnover": "",
                "annual_production_value": "1,500 stds trävaror, 175,000 st. tegel"
            },
            "foundation_year": 1897,
            "board": [
                {
                    "name": "Jonas Hanson",
                    "role": "dir."
                },
                {
                    "name": "M. Mårtensson",
                    "role": "lantbr."
                },
                {
                    "name": "Olof Ols",
                    "role": "lantbr."
                }
            ],
            "owners": [],
            "director": ""
        }
    }
}