{
    "original": "Holmlund—Holm\n\nHolmlunds Kameraverkstad,\n\nStockholm.\n\nSnickerifabrik i Josefsdal, Sala, samt\nmonteringsverkstad i Stockholm.\n\nTillverkar reproduktionskameror,\nteckningskameror och vertilkalkameror samt\nkopieringsramar.\n\nKontor: Stockholm, Holländarg. 5.\nTelefon: 213022. Postgiro: 193609. —\nAntal industriarb.: 8. Tillv.-värde pr år:\n100,000 kr. — Firman etabl. 1899.\n\nÄgare o. chef: fabr. Ernst Adamson.\n\nDisp.: Elof Johansson.\n\nAllan Holmqvist AB., Stockholm.\n\nMek. verkstad. Tillverkar ugnar,\nmaskiner, inredningar och utensilier för\nbagerier och konditorier, restauranger\noch storkök. Varumärke: »AHAB».\nBolaget driver jämväl engroshandel med\nfrämmande fabrikat.\n\nKontor: Malmskillnadsg. 39.\nTelegr.-adr.: Elholmqvist, Stockholm. Telefon:\n233800. Postgiro: 130647.\n\nAkt.-kap.: 250,000 kr. Antal\nindustriarb.: 25. — Firman etabl. 1943, bolag\n1944.\n\nVerkst. dir. o. disp.: Allan Holmqvist.\n\n*C. R. Holmqvists Boktryckeri AB.,\n\nGöteborg.\n\nUtför tryckalster såsom böcker,\nkataloger, tidskrifter, reklamtryck, blanketter,\nfraktsedlar m. m.\n\nKontor: Magasinsg. 3. Telefon: 130607\no. 139614. Postgiro: 42908.\n\nAkt.-kap.: 50,000 kr. Antal\nindustriarb.: 24. — Firman etabl. 1886, bolag\n1922.\n\nStyrelse: ing. J. Ewald Holmqvist\n(ordf.), dir. Otto R. Holmqvist, fru E.\nKarlberg.\n\nVerkst. dir.: Otto R. Holmqvist.\n\n*AB. Malcus Holmquist, Halmstad.\n\nMek. verkstäder med gjuterier,\nverktygs- och spiralborrfabrik samt\nfiltfabrik.\n\nBolaget tillverkar:\n\nlyftverktyg av alla slag såsom block,\ntelfers, traverser och kranar för hand-,\nång- och elektr. kraft ävensom\npneuma-tiska lyftanordningar;\n\nmaskiner, utrustningar och\nförnödenheter för gjuterier samt utför förslag till\nny- och ombyggnader av gjuterier;\n\nspiralborr av kolstål och snabbstål\nsamt verktyg;\n\nslipmaskiner såsom centerless\nrund-slipmaskiner och planslipmaskiner;\n\nvärmeledningsspisen och -pannan\n»Malcus», oljebrännaren »Malcus»,\nsnabblyf-tande domkraften »Malcus» m. m.;\n\nfilt för tekniskt bruk såsom#\nfiltpoler-skivor, underlagsfilt, filtpackningar, filt\nför isolationsändamål etc.\n\nTelegr.-adr. o. telefon: Malcus,\nHalmstad. Postgiro: 14707. — Akt.-kap.:\n1,800,000 kr. Antal industriarb.: 800. —\nFirman etabl. 1889. Bolaget äger\nHalmstads Nya Verkstads AB., Halmstad.\n\nStyrelse: dir. Edw. Berger (ordf.), disp.\nCarl Magnus Berger, disp. Kurt Berger,\nv. konsul A. O. Hill, civiling. Johan\nWendt.\n\nVerkst. dir.: Edw. Berger.\n\nAvd.-chefer å affärskontoret: för\ngju-teri- samt allm. maskinavdelningen:\nkontorschef J. B. Thorbjörnsson; för\nlyft-verktygsavd.: ing. O. Nordqvist; för\nfilt-avd.: E. Ammilon; för borravd.: A.\nPaulson; för slipmaskiner: ing. M. Brofelth;\nför värmetekniska avd.: Ernst Andersson;\nför patent- och litterära avd.: ing. M.\nBrofelth.\n\n(Jfr annonser nr 65 o. efter Förordet.)\n\nHolmsbruks Gjuter! AB., Motala.\n\nSe Prestoverken i Motala AB., Motala.\n\n\"Holms Industri AB., Motala.\n\nManufakturverk vid Holmsbruk,\nMotala. Tillverkar såsom specialiteter:\nhästskor och plogdelar, hejar- och pressmiden,\nspadar och skyfflar samt utför\nplåtpress-ningsarbeten och svetsning.\n\nTelefon: 1011, 591 o. 292. Postgiro:\n30327.\n\nAkt.-kap.: 225,000 kr. Antal\nindustriarb.: 90. Tillv.-värde pr år: 1,400,000 kr.\n(inkl. Hultgrens Spad- &amp; Skyffelfabrik).\n— Bolaget etabl. 1927.\n\nStyrelse: disp. Karl Ström (ordf.),\ning. Lars Dahlström, schaktm. R.\nPettersson, disp. Edvin Sandström.\n\nDisp.: Edvin Sandström.\n\nHolms Maskinfabrik AB., Södertälje.\n\nTillverkar verktygsmaskiner och\nkopplingar. Specialiteter: profilslipmaskiner\no. lamellkopplingar.\n\nTelefon: 34010. Postgiro: 176814. —\nAkt.-kap.: 25,000 kr. Antal industriarb.:\n45. Tillv.-värde pr år: 600,000 kr. —\nFirman etabl. 1940, bolag 1943.\n\nVerkst. dir.: ing. Sven Holm.\n\nVerkstadsing.: Tore Holm.\n\nKamrer: Bengt Gunnermark.",
    "structured": {
        "firms": [
            {
                "name": "Holmlunds Kameraverkstad",
                "location": "Stockholm",
                "business": "Tillverkar reproduktionskameror, teckningskameror och vertilkalkameror samt kopieringsramar",
                "contact": {
                    "office": "Holländarg. 5",
                    "phone": [
                        "213022"
                    ],
                    "postgiro": "193609"
                },
                "financials": {
                    "capital": "okänt",
                    "employees": {
                        "industriarb": 8
                    },
                    "annual_turnover": "okänt",
                    "annual_production_value": "100,000 kr"
                },
                "foundation_year": 1899,
                "owner_and_manager": {
                    "owner": "Ernst Adamson",
                    "director": "Elof Johansson"
                }
            },
            {
                "name": "Allan Holmqvist AB",
                "location": "Stockholm",
                "business": "Mek. verkstad. Tillverkar ugnar, maskiner, inredningar och utensilier för bagerier och konditorier, restauranger och storkök",
                "contact": {
                    "office": "Malmskillnadsg. 39",
                    "telegraph": "Elholmqvist, Stockholm",
                    "phone": "233800",
                    "postgiro": "130647"
                },
                "financials": {
                    "capital": "250,000 kr",
                    "employees": {
                        "industriarb": 25
                    }
                },
                "foundation_year": 1943,
                "owner_and_manager": {
                    "director_and_disp": "Allan Holmqvist"
                }
            },
            {
                "name": "C. R. Holmqvists Boktryckeri AB",
                "location": "Göteborg",
                "business": "Utför tryckalster såsom böcker, kataloger, tidskrifter, reklamtryck, blanketter, fraktsedlar m. m.",
                "contact": {
                    "office": "Magasinsg. 3",
                    "phone": [
                        "130607",
                        "139614"
                    ],
                    "postgiro": "42908"
                },
                "financials": {
                    "capital": "50,000 kr",
                    "employees": {
                        "industriarb": 24
                    }
                },
                "foundation_year": 1886,
                "owner_and_manager": {
                    "board": [
                        {
                            "name": "ing. J. Ewald Holmqvist",
                            "role": "ordf"
                        },
                        {
                            "name": "dir. Otto R. Holmqvist",
                            "role": "ing. J. Ewald Holmqvist"
                        },
                        {
                            "name": "fru E. Karlberg",
                            "role": "dir. Otto R. Holmqvist"
                        }
                    ],
                    "director": "Otto R. Holmqvist"
                }
            },
            {
                "name": "AB. Malcus Holmquist",
                "location": "Halmstad",
                "business": "Mek. verkstäder med gjuterier, verktygs- och spiralborrfabrik samt filtfabrik",
                "contact": {
                    "telegraph": "Malcus, Halmstad",
                    "phone": "okänt",
                    "postgiro": "14707"
                },
                "financials": {
                    "capital": "1,800,000 kr",
                    "employees": {
                        "industriarb": 800
                    }
                },
                "foundation_year": 1889,
                "owner_and_manager": {
                    "board": [
                        {
                            "name": "dir. Edw. Berger",
                            "role": "ordf"
                        },
                        {
                            "name": "disp. Carl Magnus Berger",
                            "role": "dir. Edw. Berger"
                        },
                        {
                            "name": "disp. Kurt Berger",
                            "role": "v. konsul A. O. Hill"
                        },
                        {
                            "name": "civiling. Johan Wendt",
                            "role": "disp. Kurt Berger"
                        }
                    ],
                    "director": "Edw. Berger",
                    "department_managers": [
                        {
                            "department": "gjuteri- samt allm. maskinavdelningen",
                            "manager": "kontorschef J. B. Thorbjörnsson"
                        },
                        {
                            "department": "lyftverktygsavd.",
                            "manager": "ing. O. Nordqvist"
                        },
                        {
                            "department": "filtavd.",
                            "manager": "E. Ammilon"
                        },
                        {
                            "department": "borravd.",
                            "manager": "A. Paulson"
                        },
                        {
                            "department": "slipmaskiner",
                            "manager": "ing. M. Brofelth"
                        },
                        {
                            "department": "värmetekniska avd.",
                            "manager": "Ernst Andersson"
                        },
                        {
                            "department": "patent- och litterära avd.",
                            "manager": "ing. M. Brofelth"
                        }
                    ]
                }
            },
            {
                "name": "Holms Industri AB.",
                "location": "Motala",
                "business": "Manufakturverk vid Holmsbruk, Motala. Tillverkar såsom specialiteter: hästskor och plogdelar, hejar- och pressmiden, spadar och skyfflar samt utför plåtpressningsarbeten och svetsning",
                "contact": {
                    "telegraph": "okänt",
                    "phone": [
                        "1011",
                        "591",
                        "292"
                    ],
                    "postgiro": "30327"
                },
                "financials": {
                    "capital": "225,000 kr",
                    "employees": {
                        "industriarb": 90
                    },
                    "annual_turnover": "okänt",
                    "annual_production_value": "1,400,000 kr"
                },
                "foundation_year": 1927,
                "owner_and_manager": {
                    "board": [
                        {
                            "name": "disp. Karl Ström",
                            "role": "ordf"
                        },
                        {
                            "name": "ing. Lars Dahlström",
                            "role": "disp. Karl Ström"
                        },
                        {
                            "name": "schaktm. R. Pettersson",
                            "role": "ing. Lars Dahlström"
                        },
                        {
                            "name": "disp. Edvin Sandström",
                            "role": "schaktm. R. Pettersson"
                        }
                    ],
                    "director": "Edvin Sandström"
                }
            },
            {
                "name": "Holms Maskinfabrik AB.",
                "location": "Södertälje",
                "business": "Tillverkar verktygsmaskiner och kopplingar. Specialiteter: profilslipmaskiner o. lamellkopplingar",
                "contact": {
                    "phone": "34010",
                    "postgiro": "176814"
                },
                "financials": {
                    "capital": "25,000 kr",
                    "employees": {
                        "industriarb": 45
                    },
                    "annual_turnover": "okänt",
                    "annual_production_value": "600,000 kr"
                },
                "foundation_year": 1940,
                "owner_and_manager": {
                    "director": "ing. Sven Holm",
                    "workshop_engineer": "Tore Holm",
                    "accountant": "Bengt Gunnermark"
                }
            }
        ]
    }
}