{
    "original": "Kamyr—Kappfabriken\n\nTelegr.-adr. o. telefon: Kampenhof,\nUddevalla. Postgiro: 15188.\nRepresentant i Stockholm: Knut Åkerlundh, L.\nNygatan 19; telefon: 203529.\n\nAkt.-kap.: 900,000 kr. Antal\nindustriarb.: 380. Tillv.-värde pr år: 5,500,000 kr.\n\n—\tBolaget grundat 1856.\n\nStyrelse: f. överste Axel M. Koch\n(ordf.), disp. Nils Dreijer, f. major G.\nLönner, konsul J. H. Sanne, disp. David\nThorburn.\n\nVerkst. dir. o. disp.: Nils Dreijer.\n\nAB. Kamyr, Karlstad.\n\nBolaget försäljer patenterade maskiner\nför trämasse- och cellulosatillverkning\nsåsom högtryckspressar,\nupptagningsmaskiner, slipverk, barktrummor,\nblekerimaski-ner m. fl., vilka maskiner tillverkas av\nAB. Karlstads Mek. Werkstad, Karlstad.\n\nKontor: Karlstad. Telefon: »KMW».\nTelegr.-adr.: Kamyr, Karlstad. —\nAkt.-kap.: 363,000 kr. — Bolaget grundat 1919.\n\nStyrelse: grossh. F. Anker, dir.\nGunnar Brolin, dir. G. Raabe.\n\nVerkst. dir.: Knud Dahl.\n\nKanex Konfektions AB., Borås.\n\nTillverkar kostymer, rockar, tr^nchcoats,\nkappor, blazers och byxor.\n\nTelefon: 12524. Postgiro: 263843.\n\nAkt.-kap.: 50,000 kr. Antal industriarb.:\n40. Tillv.-värde pr år: 700,000 kr. —\nFirman etabl. 1943, bolag 1944.\n\nVerkst. dir.: Karl Axel Larson.\n\n*AB. Kaniks Tegelfabrik, Flädie.\n\nTegelbruk i Kanik, Flädie (Malmöh.\n1.). Tillverkar murtegel, lättegel och\ndräneringsrör. Specialiteter: gul, gulgrön o.\nröd hand- och maskinslagen fasadtegel\njämväl i refflad kvalitet.\n\nTelegr.-adr.: Kanikstegel, Lund.\nTelefon: Lund 47024. Postgiro: 275016.\n\nAkt.-kap.: 210,000 kr. Antal\nindustriarb.: 40. Årstillv.: 5 milj. st. tegelvaror.\n\n—\tBolaget grundat 1909.\n\nStyrelse: dir. Lars Swenson (ordf.),\ning. Arwid Swenson, fru E.\nSönne-Swenson, fröken A. Trydegård, teknolog Lars\nIngvar Trydegård.\n\nVerkst. dir.: Lars Swenson.\n\n*Kanolds Chokladfabrik, Göteborg.\n\nSe Bröderna Kanold AB., Göteborg.\n\n*AB. Kantex, Stockholm.\n\nTrikåfabrik. Tillverkar dam- och\nherrunderkläder, spec. av natursilke.\nVarumärke: »Kantex».\n\nKontor: Svarvareg. 11. Telegr.-adr.:\nKantex, Stockholm. Telefon: 536801—02.\nPostgiro: 3931.\n\nAkt.-kap.: 150,000 kr. Antal\nindustriarb.: 30. — Firman etabl. 1924 under\nnamn AB. Tricotkonfektion, nuv. namn\n1938.\n\nStyrelse o. verkst. dir.: C. Kahn.\n\n*AB. Kant hal, Hallstahammar.\n\nElektr. stålgjuteri, smältverk,\nkallvalsverk och dragerier i Hallstahammar\n(Västmanl. l.). Tillverkar elektr.\nmot-ståndsmateriel, bimetall,\ntermoelement-tråd, elektrostålgjutgods, även rostfritt,\nsyrafast och eldhärdigt samt\nhögeldhär-diga stållegeringar. Varumärke:\n»Kan-thal».\n\nTelegr.-adr. o. telefon: Kanthal,\nHallstahammar. Postgiro: 73633.\n\nAkt.-kap.: 4,500,000 kr. Antal\nindustriarb.: 400. Tillv.-värde pr år: 8,000,000 kr.\n\nBolaget, grundat 1931, äges av\nBult-fabriks AB., Hallstahammar.\n\nStyrelse: ing. Bengt Ingeström (ordf.),\ndisp. Hans v. Kantzow (v. ordf.), greve\nGöran Kalling, generalkonsul Ragnar\nSöderberg.\n\nVerkst. dir. o. disp.: Hans v. Kantzow.\nÖvering.: Gösta Rehnqvist.\nFörsäljn.-chef er: Alfred Rapp o. Åke\nLindblad.\n\n*Kantorps Malmfält, Sköldinge.\nSe Boxholms AB., Boxholm.\n\n*AB. M. Kaplans Konfektionsfabrik,\n\nStockholm.\n\nTillverkar herrkläder samt damkappor\noch -dräkter. Varumärke: »Kap’s».\n\nKontor: Igeldammsg. 22. Telegr.-adr.:\nKonfektion, Stockholm. Telefon:\n»Kaplans Konfektionsfabrik». Postgiro: 52549.\n\nAkt.-kap.: 487,500 kr. Antal\nindustriarb.: 260. Tillv.-värde pr år: 3,300,000 kr.\n— Bolaget grundat 1927.\n\nStyrelse: adv. L. Levy (ordf.), dir.\nMarcus Kaplan, disp. Oscar Kaplan.\nVerkst. dir.: M. Kaplan.\nDisp.: O. Kaplan.\nKontorschef: Samuel Gerov.\n\n*Kapokfabriken, Svenska, Stockholm.\n\nSe Svenska Kapokfabriken AB.,\nStockholm.\n\n*Kappfabriken, Svenska, Malmö.\nSe AB. Svenska Kappfabriken, Malmö.\n\n",
    "structured": {
        "1": {
            "name": "Kamyr—Kappfabriken",
            "location": "Uddevalla",
            "business": "Tillverkning av trämasse- och cellulosatillverkning",
            "contact": {
                "office": "Kampenhof, Uddevalla",
                "phone": [
                    "203529"
                ],
                "postgiro": "15188",
                "telegraph": "Kamyr, Karlstad",
                "factory_office": "AB. Karlstads Mek. Werkstad, Karlstad"
            },
            "financials": {
                "capital": "900,000 kr",
                "employees": {
                    "industriarb": 380
                },
                "annual_turnover": "5,500,000 kr",
                "annual_production_value": "5,500,000 kr"
            },
            "foundation_year": 1856,
            "board": [
                {
                    "name": "Axel M. Koch",
                    "role": "ordförande"
                },
                {
                    "name": "Nils Dreijer",
                    "role": "disp."
                },
                {
                    "name": "G. Lönner",
                    "role": "f. major"
                },
                {
                    "name": "J. H. Sanne",
                    "role": "konsul"
                },
                {
                    "name": "David Thorburn",
                    "role": "disp."
                }
            ]
        },
        "2": {
            "name": "AB. Kamyr",
            "location": "Karlstad",
            "business": "Försäljning av patenterade maskiner för trämasse- och cellulosatillverkning",
            "contact": {
                "office": "Karlstad",
                "phone": [],
                "postgiro": "",
                "telegraph": "KMW",
                "head_office": "Karlstad"
            },
            "financials": {
                "capital": "363,000 kr"
            },
            "foundation_year": 1919,
            "board": [
                {
                    "name": "F. Anker",
                    "role": "grosshandlare"
                },
                {
                    "name": "Gunnar Brolin",
                    "role": "dir."
                },
                {
                    "name": "G. Raabe",
                    "role": "dir."
                }
            ],
            "director": "Knud Dahl"
        },
        "3": {
            "name": "Kanex Konfektions AB.",
            "location": "Borås",
            "business": "Tillverkning av kostymer, rockar, trenchcoats, kappor, blazers och byxor",
            "contact": {
                "phone": [
                    "12524"
                ],
                "postgiro": "263843"
            },
            "financials": {
                "capital": "50,000 kr",
                "employees": {
                    "industriarb": 40
                },
                "annual_turnover": "700,000 kr"
            },
            "foundation_year": 1944,
            "manager": "Karl Axel Larson"
        },
        "4": {
            "name": "AB. Kaniks Tegelfabrik",
            "location": "Flädie",
            "business": "Tillverkning av murtegel, lättegel och dräneringsrör",
            "contact": {
                "phone": [
                    "Lund 47024"
                ],
                "postgiro": "275016",
                "telegraph": "Kanikstegel, Lund"
            },
            "financials": {
                "capital": "210,000 kr",
                "employees": {
                    "industriarb": 40
                }
            },
            "foundation_year": 1909,
            "board": [
                {
                    "name": "Lars Swenson",
                    "role": "dir."
                },
                {
                    "name": "Arwid Swenson",
                    "role": "ing."
                },
                {
                    "name": "E. Sönne-Swenson",
                    "role": "fru"
                },
                {
                    "name": "A. Trydegård",
                    "role": "fröken"
                },
                {
                    "name": "Lars Ingvar Trydegård",
                    "role": "teknolog"
                }
            ],
            "director": "Lars Swenson"
        },
        "5": {
            "name": "AB. Kantex",
            "location": "Stockholm",
            "business": "Tillverkning av dam- och herrunderkläder, speciellt av natursilke",
            "contact": {
                "office": "Svarvareg. 11, Stockholm",
                "phone": [
                    "536801—02"
                ],
                "postgiro": "3931"
            },
            "financials": {
                "capital": "150,000 kr",
                "employees": {
                    "industriarb": 30
                }
            },
            "foundation_year": 1938,
            "manager": "C. Kahn"
        },
        "6": {
            "name": "AB. Kant hal",
            "location": "Hallstahammar",
            "business": "Tillverkning av elektr. stålgjuteri, smältverk, kallvalsverk och dragerier",
            "contact": {
                "office": "Hallstahammar",
                "phone": [
                    "Kanthal"
                ],
                "postgiro": "73633"
            },
            "financials": {
                "capital": "4,500,000 kr",
                "employees": {
                    "industriarb": 400
                },
                "annual_turnover": "8,000,000 kr"
            },
            "foundation_year": 1931,
            "board": [
                {
                    "name": "Bengt Ingeström",
                    "role": "ing."
                },
                {
                    "name": "Hans v. Kantzow",
                    "role": "disp."
                },
                {
                    "name": "Göran Kalling",
                    "role": "greve"
                },
                {
                    "name": "Ragnar Söderberg",
                    "role": "generalkonsul"
                }
            ]
        },
        "7": {
            "name": "AB. M. Kaplans Konfektionsfabrik",
            "location": "Stockholm",
            "business": "Tillverkning av herrkläder samt damkappor och -dräkter",
            "contact": {
                "office": "Igeldammsg. 22, Stockholm",
                "phone": [
                    "Kaplans Konfektionsfabrik"
                ],
                "postgiro": "52549"
            },
            "financials": {
                "capital": "487,500 kr",
                "employees": {
                    "industriarb": 260
                },
                "annual_turnover": "3,300,000 kr"
            },
            "foundation_year": 1927,
            "board": [
                {
                    "name": "L. Levy",
                    "role": "adv."
                },
                {
                    "name": "Marcus Kaplan",
                    "role": "dir."
                },
                {
                    "name": "Oscar Kaplan",
                    "role": "disp."
                }
            ],
            "director": "M. Kaplan",
            "managing_director": "M. Kaplan",
            "sales_manager": "O. Kaplan",
            "manager": "Samuel Gerov"
        }
    }
}