{
    "original": "Bohman—Boklund\n\nmåla. Telefon: 2, 22 o. 52. Postgiro:\n29502.\n\nAkt.-kap.: 170,000 kr. Antal\nindustriarb.: 110. Tillv.-värde pr år: 4,000,000 kr.\n\n—\tFirman etabl. 1897, bolag 1904.\nStyrelse: dir. Sven J. Larsson, köpm.\n\nÅke Larson, disp. Wald. Person.\nDisp.: Wald. Person.\n\nJ. Bohmans Fabriks AB., Jönköping.\n\nMek. verkstad, träförädlingsfabrik och\nelektricitetsverk i Lovsjö, Jönköoing.\nTillverkar tvättbräden, diskställ,\ntrappstegar, krocketspel, manglar med\npatentvalsar av bakelit, barncyklar, cykel- och\nbarnkärror, spjälvagnar m. m.\n\nTelegr.-adr.: Bohmans, Jönköping.\nTelefon: Lovsjö 6 o. 26. Postgiro: 23417. —\nAkt.-kap.: 100,000 kr. Tillv.-värde pr år:\n500,000 kr. — Firman etabl. 1889, bolag\n1944.\n\nVerkst. dir.: John Bohman.\n\n*Knut Bomans Mössfabrik AB.,\n\nGöteborg.\n\nTillverkar herr-, dam- och barnmössor.\nVarumärke: »Kåbe».\n\nKontor: Ö. Hamng. 12. Telefon: 137568.\nPostgiro: 40532.\n\nAkt.-kap.: 60,000 kr. Antal\nindustriarb.: 30. Tillv.-värde pr år: 400,000 kr.\n\n—\tFirman etabl. 1906, bolag 1934.\nStyrelse o. disp.: Gustaf Ryhre.\n\n*Bohus Mek. Verkstads AB.,\n\nGöteborg.\n\nMek. verkstad, plåtslageri och gjuteri.\nTillverkar tvättmaskiner, centrifuger,\nvarmmanglar, strykpressar, torkmaskiner,\nfärgerimaskiner samt gjutgods.\n\nKontor: Getebergsäng; postadr.:\nGöteborg 5. Telegr.-adr.: Bohus, Göteborg.\nTelefon: 187020. Postgiro: 40796.\n\nAkt.-kap.: 445,000 kr. Antal\nindustriarb.: 225. Tillv.-värde pr år: 5,000,000\nkr. — Verkstaden grundad 1876, bolag\n1882.\n\nStyrelse: dir. Gust. J. Sahlin (ordf.),\ndir. Axel O. Engberg, civiling. Gunnar\nJuhlin.\n\nVerTcst. dir.: Gunnar Juhlin.\nKamrer: Arvid Anderson.\n\nBohus Varv, Knut Tiderman,\n\nBohus.\n\nUtför nybyggnader och reparationer av\njärn- och träfartyg såsom kanalbåtar,\nfiskefartyg och pråmar vid varv i Bohus\n(Älvsb. l.).\n\nTelefon: Surte 3 o. 144. Postgiro:\n145621. — Antal industriarb.: 60. —\nFirman etabl. 1907.\n\nÄgare o. chef: Knut Tiderman.\n\nAB. Bohusläns Stenförädling,\n\nHunne b ostrand.\n\nStenhuggeri och sliperi vid\nHunnebo-strand och Bovallstrand (Göteb. o. Bohus\n1.). Tillverkar gat- och kantsten,\nbyggnadssten, gravvårdar samt sågad och\nslipad granit.\n\nTelefon: 111. Postgiro: 133876. —\nAkt.-kap.: 50,000 kr. Antal industriarb.: 100.\nProd.-värde pr år: 500,000 kr. — Bolaget\ngrundat 1937.\n\nStyrelse o. chefer: fabr. Axel R.\nBäckman (ordf.), disp. Hj. Höij.\n\nAB. Bohuslänska Granit-Kompaniet,\n\nStrömstad.\n\nStenhuggerier å olika platser i norra\nBohuslän. Tillverkar gat- och kantsten,\nbyggnadssten samt råblock.\n\nKontor: Strömstad. Telegr.-adr.:\nHes-sel, Strömstad. Telefon: 77.\nEnsamför-sälj. för utlandet: Sveriges\nGranitindustris Exportförening m. b. p. a., Göteborg,\nAvenyen 1, telefon: 138553 o. 131772.\n\nAkt.-kap.: 60,000 kr. Antal\nindustriarb.: 65. Prod.-värde pr år: 150,000 kr.\n\n—\tBolaget grundat 1908.\n\nStyrelse o. verkst. dir.: konsul Arthur\nHessel.\n\n* Bokenäs Tegelbruks AB.,\n\nGöteborg.\n\nTillverkar mur- och taktegel samt\ndräneringsrör vid tegelbruk i Bokenäs\n(Göteb. o. Bohus l.).\n\nKontor: Göteborg, Kyrkog. 4.\nTelefon: 131328. Postgiro: 41856.\n\nAkt.-kap.: 85,000 kr. Antal\nindustriarb.: 60. Årstillv.: 3,3 milj. st. tegelvaror.\n\n—\tFirman etabl. 1937.\n\nStyrelse: bruksäg. Gunnar Wulf (ordf.),\ndisp. Ragnar Nymansson, kapten Hilding\nStröm, disp. Joel Svensson.\n\nDisp.: R. Nymansson.\n\nTegelmäst.: Harald Olsson.\n\nAB. Boklund &amp; Davidson,\n\nLinköping.\n\nMöbelfabrik. Tillverkar bäddsoffor och\nottomaner.\n\nTelefon: 22730. Postgiro: 95788. —\nAkt.-kap.: 125,000 kr. Antal industriarb.:",
    "structured": {
        "1": {
            "name": "J. Bohmans Fabriks AB.",
            "location": "Jönköping",
            "business": "Mek. verkstad, träförädlingsfabrik och elektricitetsverk",
            "contact": {
                "office": "Lovsjö, Jönköping",
                "phone": [
                    "6",
                    "26"
                ],
                "postgiro": "23417",
                "telegraph": "Bohmans, Jönköping"
            },
            "financials": {
                "capital": "100 000 kr",
                "employees": {
                    "industriarb": 110
                },
                "annual_production_value": "500 000 kr"
            },
            "foundation_year": 1889,
            "corporation_year": 1944,
            "board": [
                {
                    "name": "Sven J. Larsson",
                    "role": "dir."
                },
                {
                    "name": "Åke Larson",
                    "role": "disp."
                },
                {
                    "name": "Wald. Person",
                    "role": "disp."
                }
            ],
            "director": "John Bohman"
        },
        "2": {
            "name": "Knut Bomans Mössfabrik AB.",
            "location": "Göteborg",
            "business": "Tillverkar herr-, dam- och barnmössor",
            "contact": {
                "office": "Ö. Hamng. 12",
                "phone": [
                    "137568"
                ],
                "postgiro": "40532"
            },
            "financials": {
                "capital": "60 000 kr",
                "employees": {
                    "industriarb": 30
                },
                "annual_production_value": "400 000 kr"
            },
            "foundation_year": 1906,
            "corporation_year": 1934,
            "board": [
                {
                    "name": "Gustaf Ryhre",
                    "role": "Styrelse o. disp."
                }
            ]
        },
        "3": {
            "name": "Bohus Mek. Verkstads AB.",
            "location": "Göteborg",
            "business": "Mek. verkstad, plåtslageri och gjuteri",
            "contact": {
                "office": "Getebergsäng, postadr.: Göteborg 5",
                "telegraph": "Bohus, Göteborg",
                "phone": "187020",
                "postgiro": "40796"
            },
            "financials": {
                "capital": "445 000 kr",
                "employees": {
                    "industriarb": 225
                },
                "annual_production_value": "5 000 000 kr"
            },
            "foundation_year": 1876,
            "corporation_year": 1882,
            "board": [
                {
                    "name": "Gust. J. Sahlin",
                    "role": "dir. (ordf.)"
                },
                {
                    "name": "Axel O. Engberg",
                    "role": "dir."
                },
                {
                    "name": "Gunnar Juhlin",
                    "role": "civiling., verkst. dir."
                }
            ],
            "director": "Gunnar Juhlin",
            "manager": "Arvid Anderson"
        },
        "4": {
            "name": "Bohus Varv, Knut Tiderman",
            "location": "Bohus",
            "business": "Utför nybyggnader och reparationer av järn- och träfartyg",
            "contact": {
                "phone": [
                    "3",
                    "144"
                ],
                "postgiro": "145621"
            },
            "employees": {
                "industriarb": 60
            },
            "foundation_year": 1907,
            "manager": "Knut Tiderman"
        },
        "5": {
            "name": "AB. Bohusläns Stenförädling",
            "location": "Hunnebostrand",
            "business": "Stenhuggeri och sliperi",
            "contact": {
                "phone": "111",
                "postgiro": "133876"
            },
            "financials": {
                "capital": "50 000 kr",
                "employees": {
                    "industriarb": 100
                },
                "annual_production_value": "500 000 kr"
            },
            "foundation_year": 1937,
            "board": [
                {
                    "name": "Axel R. Bäckman",
                    "role": "fabr. (ordf.)"
                },
                {
                    "name": "Hj. Höij",
                    "role": "disp."
                }
            ]
        },
        "6": {
            "name": "AB. Bohuslänska Granit-Kompaniet",
            "location": "Strömstad",
            "business": "Stenhuggerier å olika platser i norra Bohuslän",
            "contact": {
                "office": "Strömstad",
                "phone": "77",
                "telegraph": "Hessel, Strömstad"
            },
            "financials": {
                "capital": "60 000 kr",
                "employees": {
                    "industriarb": 65
                },
                "annual_production_value": "150 000 kr"
            },
            "foundation_year": 1908,
            "director": "Arthur Hessel"
        },
        "7": {
            "name": "Bokenäs Tegelbruks AB.",
            "location": "Göteborg",
            "business": "Tillverkar mur- och taktegel samt dräneringsrör",
            "contact": {
                "office": "Göteborg, Kyrkog. 4",
                "phone": "131328",
                "postgiro": "41856"
            },
            "financials": {
                "capital": "85 000 kr",
                "employees": {
                    "industriarb": 60
                }
            },
            "foundation_year": 1937,
            "board": [
                {
                    "name": "Gunnar Wulf",
                    "role": "bruksäg. (ordf.)"
                },
                {
                    "name": "Ragnar Nymansson",
                    "role": "disp."
                },
                {
                    "name": "Hilding Ström",
                    "role": "kapten"
                },
                {
                    "name": "Joel Svensson",
                    "role": "disp."
                }
            ],
            "manager": "Harald Olsson"
        },
        "8": {
            "name": "AB. Boklund & Davidson",
            "location": "Linköping",
            "business": "Möbelfabrik. Tillverkar bäddsoffor och ottomaner",
            "contact": {
                "phone": "22730",
                "postgiro": "95788"
            },
            "financials": {
                "capital": "125 000 kr",
                "employees": {
                    "industriarb": "N/A"
                }
            }
        }
    }
}