{
    "original": "J akobsson—Jansson\n\nAB; Carl Jakobssons Bleck kär Is-\n\nfabrik, Odensbacken.\n\nTillverkar bleckemballage för\nfärgfabriker, tekn. fabriker m. fl.,\nkonserv-emballage, plåtkaminer samt utför\nplåtslageri arbeten vid fabrik i Odensbacken\n(Örebro l.).\n\nTelefon: 44. Postgiro: 24888. —\nAkt.-kap.: 55,000 kr. Antal industriarb.: 40.\nTillv.-värde pr år: 675,000 kr. — Firman\netabl. 1895, bolag 1926.\n\nVerkst. dir.: fabr. Nils Jakobsson.\n\n\"Oscar Jacobson AB., Borås.\n\nHerrkonfektionsfabrik. Tillverkar\nkostymer, gosskläder, ulstrar, överrockar,\ntrenchcoats, byxor samt skjortor och\narbetskläder. Varumärken: »Klimax» o.\n»Ojac».\n\nTelefon: »Jacobsons bolag». Postgiro:\n71282.\n\nAkt.-kap.: 1,680,000 kr. Antal\nindustriarb.: 290. Tillv.-värde pr år: 6,000,000 kr.\n— Firman etabl. 1929, bolag 1935.\n\nStyrelse: dir. Oscar Jacobson (ordf.),\nkamrer N. H. Edberg.\n\nVerkst. dir.: Oscar Jacobson.\n\nKontorschef: N. H. Edberg.\n\nJannebergs Tegelbruk, Karlshamn.\n\nTegelbruk och elektr. kraftstation vid\nJanneberg, Karlshamn (Blekinge l.).\nTillverkar tegel och dräneringsrör. Firman\ndriver även bränner i- och kvarnrörelse\nsamt skogshantering.\n\nKontor: Karlshamn. Telefon: 887.\nPostgiro: 97961. Antal industriarb.: 40.\nÅrstillv.: 3 milj. st. tegelvaror. —\nTegelbruket anlagt på 1890-talet.\n\nÄgare o. chef: civiling. Nils Santesson.\n\nJansson &amp; Co., Stockholm.\n\nSe AB. Svenska Korsettfabriken,\nJansson &amp; Co., Stockholm.\n\nAB. Jansson &amp; Sjögrens Eftr.,\n\nVästerås.\n\nKaramellfabrik, bageri och\nspisbröds-fabrik. Tillverkar konfektyrer, choklad,\nmarmelad och karameller (specialitet:\nbrända mandlar), bageri- och\nkonditorivaror samt spisbröd.\n\nTelefon: 30215, 35015 o. 31182.\nPostgiro: 22847.\n\nAkt.-kap.: 50,000 kr. Antal\nindustriarb. : 40, varav i karamellfabriken 20.\nTillv.-värde pr år: 600,000 kr. — Firman\netabl. 1889, bolag 1942.\n\nVerkst. dir.: kapten John Jahn.\n\nDisp.: Ture J. Bengtson.\n\nAB. Ax. G. Jansson, Smides- &amp; Mek.\nVerkstad, Stockholm.\n\nUtför järnkonstruktioner, räckarbeten\ni järn, rostfritt och metall samt\nbygg-nadssmide.\n\nKontor: Katarina Bangata 77. Telefon:\n440595. Postgiro: 54139.\n\nAkt.-kap.: 225,000 kr. Antal\nindustriarb.: 120. Tillv.-värde pr år: 1,764,000 kr.\n\n—\tFirman etabl. 1912, bolag 1937.\nVerkst. dir.: Axel G. Jansson.\nVerkstadsing.: David E. Johansson.\nKamrer: Gösta Gardbeck.\n\nAB. J. Janssons Kalkbruk,\n\nKälvene.\n\nTillverkar bränd kalk vid kalkbruk i\nKälvene (Skarab. l.).\n\nTelefon: 5. Postgiro: 77871. —\nAkt.-kap.: 90,000 kr. Antal industriarb.: 30.\nTillv.-värde pr år: 150,000 kr. — Bolaget\ngrundat 1918.\n\nDisp.: Erik Jansson.\n\n\"AB. J. Axel Janssons Nysilverfabrik,\n\nLidköping.\n\nMetallvarufabrik och försilvringsverk.\nTillverkar bordsartiklar i nysilver och\nrostfritt stål, potatisskalare samt\nslip-och polermaskiner för branschen.\n\nTelegr.-adr.: Janssonssilver, Lidköping.\nTelefon: 20069. Postgiro: 10321.^\n\nAkt.-kap.: 50,000 kr. Antal\nindustriarb.: 55. Tillv.-värde pr år: 900,000 kr.\n\n—\tFirman etabl. 1925, bolag 1939.\nStyrelse o. verkst. dir.: J. Axel Jansson.\nVerk stads chef: disp. Helge Jansson.\n\n\"AB. Otto Janssons Skofabrik,\n\nJ önköping.\n\nTillverkar rand- och sandalsydda\nherr-och barnskodon. Varumärken: »J:son\nskodon», »Lunkentus» o. »Aristokrat».\n\nTelefon: 23. Postgiro: 30218. —\nAkt.-kap.: 150,000 kr. Antal industriarb.: 140.\nTillv.-värde pr år: 2,200,000 kr. –\nFirman etabl. 1925, bolag 1929.\n\nStyrelse o. disp.: Eilert Jansson.\n\nSigfrid Janssons Metallfabrik,\n\nMariefred.\n\nMetallvarufabrik och gjuteri.\nTillverkar byggnads- och båtbeslag.\n\nTelefon: 64. Postgiro: 30613. —\nAntal industriarb.: 16. Tillv.-värde pr år:\n150,000 kr. — Firman etabl. 1900.\nÄgare o. chef: fru E. Jansson.",
    "structured": {
        "1": {
            "name": "Carl Jakobssons Bleck kär Isfabrik",
            "location": "Odensbacken",
            "business": "Tillverkar bleckemballage för färgfabriker, tekn. fabriker m. fl., konserv-emballage, plåtkaminer samt utför plåtslageriarbeten vid fabrik i Odensbacken (Örebro l.)",
            "contact": {
                "office": "Odensbacken",
                "phone": [
                    "44"
                ],
                "postgiro": "24888"
            },
            "financials": {
                "capital": "55,000 kr",
                "employees": {
                    "industriarb": 40
                },
                "annual_turnover": "675,000 kr",
                "annual_production_value": "3 milj. st. tegelvaror"
            },
            "foundation_year": 1895,
            "corporation_year": 1926,
            "director": "Nils Jakobsson"
        },
        "2": {
            "name": "Oscar Jacobson AB.",
            "location": "Borås",
            "business": "Herrkonfektionsfabrik. Tillverkar kostymer, gosskläder, ulstrar, överrockar, trenchcoats, byxor samt skjortor och arbetskläder.",
            "contact": {
                "phone": [
                    "Jacobsons bolag"
                ],
                "postgiro": "71282"
            },
            "financials": {
                "capital": "1,680,000 kr",
                "employees": {
                    "industriarb": 290
                },
                "annual_turnover": "6,000,000 kr"
            },
            "foundation_year": 1929,
            "corporation_year": 1935,
            "board": [
                {
                    "name": "Oscar Jacobson",
                    "role": "ordf."
                },
                {
                    "name": "N. H. Edberg",
                    "role": "kamrer"
                }
            ],
            "director": "Oscar Jacobson",
            "sales_manager": "N. H. Edberg"
        },
        "3": {
            "name": "Jannebergs Tegelbruk",
            "location": "Karlshamn",
            "business": "Tegelbruk och elektr. kraftstation vid Janneberg, Karlshamn (Blekinge l.). Tillverkar tegel och dräneringsrör. Firman driver även bränner i- och kvarnrörelse samt skogshantering.",
            "contact": {
                "office": "Karlshamn",
                "phone": [
                    "887"
                ],
                "postgiro": "97961"
            },
            "financials": {
                "employees": {
                    "industriarb": 40
                },
                "annual_production_value": "150,000 kr"
            },
            "owner": "civiling. Nils Santesson"
        },
        "4": {
            "name": "Jansson & Co.",
            "location": "Stockholm",
            "description": "Se AB. Svenska Korsettfabriken, Jansson & Co., Stockholm."
        },
        "5": {
            "name": "AB. Jansson & Sjögrens Eftr.",
            "location": "Västerås",
            "business": "Karamellfabrik, bageri och spisbröds-fabrik. Tillverkar konfektyrer, choklad, marmelad och karameller (specialitet: brända mandlar), bageri- och konditorivaror samt spisbröd.",
            "contact": {
                "phone": [
                    "30215",
                    "35015",
                    "31182"
                ],
                "postgiro": "22847"
            },
            "financials": {
                "capital": "50,000 kr",
                "employees": {
                    "industriarb": 40
                },
                "annual_turnover": "600,000 kr"
            },
            "foundation_year": 1889,
            "corporation_year": 1942,
            "director": "kapten John Jahn",
            "sales_manager": "Ture J. Bengtson"
        },
        "6": {
            "name": "AB. Ax. G. Jansson, Smides- & Mek. Verkstad",
            "location": "Stockholm",
            "business": "Utför järnkonstruktioner, räckarbeten i järn, rostfritt och metall samt byggnadssmide.",
            "contact": {
                "office": "Katarina Bangata 77",
                "phone": [
                    "440595"
                ],
                "postgiro": "54139"
            },
            "financials": {
                "capital": "225,000 kr",
                "employees": {
                    "industriarb": 120
                },
                "annual_turnover": "1,764,000 kr"
            },
            "foundation_year": 1912,
            "corporation_year": 1937,
            "director": "Axel G. Jansson",
            "managing_director": "David E. Johansson",
            "sales_manager": "Gösta Gardbeck"
        },
        "7": {
            "name": "AB. J. Janssons Kalkbruk",
            "location": "Kälvene",
            "business": "Tillverkar bränd kalk vid kalkbruk i Kälvene (Skarab. l.)",
            "contact": {
                "phone": [
                    "5"
                ],
                "postgiro": "77871"
            },
            "financials": {
                "capital": "90,000 kr",
                "employees": {
                    "industriarb": 30
                },
                "annual_turnover": "150,000 kr"
            },
            "corporation_year": 1918,
            "director": "Erik Jansson"
        },
        "8": {
            "name": "AB. J. Axel Janssons Nysilverfabrik",
            "location": "Lidköping",
            "business": "Metallvarufabrik och försilvringsverk. Tillverkar bordsartiklar i nysilver och rostfritt stål, potatisskalare samt slip-och polermaskiner för branschen.",
            "contact": {
                "telegraph": "Janssonssilver, Lidköping",
                "phone": [
                    "20069"
                ],
                "postgiro": "10321"
            },
            "financials": {
                "capital": "50,000 kr",
                "employees": {
                    "industriarb": 55
                },
                "annual_turnover": "900,000 kr"
            },
            "corporation_year": 1939,
            "director": "J. Axel Jansson",
            "factory_manager": "Helge Jansson"
        },
        "9": {
            "name": "AB. Otto Janssons Skofabrik",
            "location": "Jönköping",
            "business": "Tillverkar rand- och sandalsydda herr-och barnskodon.",
            "contact": {
                "phone": [
                    "23"
                ],
                "postgiro": "30218"
            },
            "financials": {
                "capital": "150,000 kr",
                "employees": {
                    "industriarb": 140
                },
                "annual_turnover": "2,200,000 kr"
            },
            "corporation_year": 1929,
            "director": "Eilert Jansson"
        },
        "10": {
            "name": "Sigfrid Janssons Metallfabrik",
            "location": "Mariefred",
            "business": "Metallvarufabrik och gjuteri. Tillverkar byggnads- och båtbeslag.",
            "contact": {
                "phone": [
                    "64"
                ],
                "postgiro": "30613"
            },
            "financials": {
                "employees": {
                    "industriarb": 16
                },
                "annual_turnover": "150,000 kr"
            },
            "owner": "fru E. Jansson"
        }
    }
}