{
    "original": "Ludvika—Lundh\n\nkontor: Timmernabben, Borgholm,\nFärjestaden och Degerhamn. — Antal\nindustriarb.: 45. Årstillv.: 7,500 stds trävaror.\n\n—\tFirman etabl. 1895.\n\nÄgare: grossh. Emil Th. Ludvigsson\n(Förlösa).\n\nDisp.: Nils Westerberg (Kalmar).\n\n\"Ludvika Bryggeri, Ludvika.\n\nSe AB. Sveabryggerier, Filipstad.\n\n\"AB. Ludvika Ångsåg, Ludvika.\n\nSågverk och hyvleri i Ludvika.\nTillverkar sågade och hyvlade trävaror.\n\nTelegr.-adr.: Ångsågen, Ludvika.\nTelefon: 1357 o. 260. Postgiro: 75709.\n\nAkt.-kap.: 400,000 kr. Antal\nindustriarb.: 50. Årstillv.: 3,000 stds sågade\nträvaror, varav 1,000 stds hyvlade. — Sågen\nanlagd 1900, nuv. bolag stiftat 1918.\n\nBolaget äges av Billeruds AB., Säffle,\nvarigenom inköp och försäljningar med\nundantag för platsförsäljningen ske. (Se\ndetta bolag.)\n\nStyrelse: disp. Chr. Storjohann (ordf.),\ndir. H. Dyster-Aas, dir. E. Vermcrantz.\n\nVerkst. dir.: Chr. Storjohann.\n\nVice verkst. dir.: H. Dyster-Aas.\n\nPlatschef: forstm. Gust. K. Åsryd.\n\n\"Lugnviks Ångsåg, Björkåbruk.\n\nSe Björkå AB., Björkåbruk.\n\n\"AB. Luleå Bryggeri, Luleå.\n\nTillverkar malt, maltdrycker och\nläskedrycker.\n\nTelegr.-adr.: Bryggeribolaget, Luleå.\nTelefon: »Luleå bryggeri». Postgiro:\n23265.\n\nAkt.-kap.: 450,000 kr. Antal\nindustriarb.: 45. Tillv.-värde pr år: 1,000,000 kr.\n\n—\tBolaget, grundat 1908, äger Piteå\nBryggeri AB., Piteå.\n\nStyrelse: marinöverkommissarie Arthur\nWirström (ordf.), dir. Folke Burström,\ntandl. Hugo Burström, generalkonsul\nCurt Wirström.\n\nVerkst. dir. o. disp.: Folke Burström.\n\nKassör: Carl F. Eriksson.\n\nBryggm.: G. Sandgren.\n\nLuleå Järnverk, Luleå.\n\nSe Norrbottens Järnverk AB., Luleå.\n\n\"Luleå Tegelbruks AB., Luleå.\n\nTillverkar murtegel samt\nträullsplat-tor vid Mariebergs Tegelbruk, Södra\nSunderbyn (Norrb. l.).\n\nKontor: Luleå. Telefon: 4620.\nPostgiro: 67723.\n\nAkt.-kap.: 135,000 kr. Antal\nindustriarb.: 50. Årstillv.: 1,8 milj. st. tegel. —\nBolaget, grundat 1902, äges av AB. Luleå\nKol &amp; Materialaffär.\n\nStyrelse: bankdir. Gunnar Dahlgren\n(ordf.), dir. K. Beijer, adv. Thure Essen,\ndir. Harald Lönnegårdh, dir. Oscar\nNyländer.\n\nVerkst. dir.: Oscar Nyländer.\n\n\"Luleå Trämassefabrik, Luleå.\n\nSe Munksunds AB., Luleå.\n\nLuleå Varv &amp; Verkstäder, Luleå.\n\nSe Nya AB. Luleå Varv &amp; Verkstäder,\nLuleå.\n\n\"Lumalampan AB., Stockholm.\n\nGlödlampfabrik. Tillverkar elektr.\nlampor såsom belysningslampor,\nspeciallampor, billampor, dvärglampor,\nkvicksilver-ånglampor, lysämneslampor, glimlampor,\nlikriktarrör, elektriska\njulgransbelysningar och terapilampor, elektr.\nkontakter, elektroder, neonelektroder,\nvolfram-tråd, molybdentråd, hårdmetall,\ndragskivor, ställbara dragmatriser, dragdornar\noch andra dragverktyg. natriumvolframat,\nnatriummolybdat, ammoniumfluorid,\nam-moniummolybdat, fosforvolframsyra,\nlys-pulver, ävensom gjutmassor och cement\nför elektrotekniska ändamål.\nVarumärken: »Luma» o. »Lumant».\n\nKontor: Lumavägen 6; post.-adr.:\nStockholm 20. Telegr.-adr. o. telefon:\n»Lumalampan», Stockholm. Postgiro:\n156690.\n\nAkt.-kap.: 2,000,000 kr. Antal\nindustriarb.: 1,000. — Bolaget, grundat 1930\nunder namn AB. Hammarbylampan, nuv.\nnamn 1942, äges av Kooperativa\nFörbundet.\n\nStyrelse: dir. Albin Johansson (ordf.),\nfil. lic. Mauritz Bonow, dir. Hj.\nDeger-stedt, dir. Hugo Edstam, dir. G. Osvald,\ndir. Ernst Persson, ing. H. Schlott.\n\nVerkst. dir.: H. Schlott.\n\nDir.-assist.: civiling. M. Hyström.\n\nKontorschef: kamrer E. Edblad.\n\nLaboratoriechef: dr phil. G. Siljeholm.\n\n(Jfr annons efter Branschregistret.)\n\n\"Aug. Lundhs Metallfabrik,\n\nEskilstuna.\n\nTillverkar kokkärl och andra\nhushållsartiklar av aluminium.\n\nTelefon: 31817. — Antal industriarb.:\n12. Tillv.-värde pr år: 215,000 kr. —\nFirman etabl. 1920.\n\nÄgare o. chef: fabr. Tore Lundh.",
    "structured": {
        "1": {
            "name": "AB. Ludvika Ångsåg",
            "location": "Ludvika",
            "business": "Sågverk och hyvleri",
            "products": "Tillverkar sågade och hyvlade trävaror.",
            "contact": {
                "office": "Ångsågen, Ludvika",
                "phone": [
                    "1357",
                    "260"
                ],
                "postgiro": "75709"
            },
            "financials": {
                "capital": "400,000 kr",
                "employees": {
                    "industriarb": 50
                },
                "annual_turnover": "3,000 stds sågade trävaror, varav 1,000 stds hyvlade",
                "annual_production_value": "Sågen anlagd 1900, nuv. bolag stiftat 1918"
            },
            "foundation_year": 1895,
            "board": [
                {
                    "name": "Chr. Storjohann",
                    "role": "ordf."
                },
                {
                    "name": "H. Dyster-Aas",
                    "role": "dir."
                },
                {
                    "name": "E. Vermcrantz",
                    "role": null
                }
            ]
        },
        "2": {
            "name": "AB. Luleå Bryggeri",
            "location": "Luleå",
            "business": "Tillverkar malt, maltdrycker och läskedrycker.",
            "contact": {
                "telegraph": "Bryggeribolaget, Luleå",
                "phone": "Luleå bryggeri",
                "postgiro": "23265"
            },
            "financials": {
                "capital": "450,000 kr",
                "employees": {
                    "industriarb": 45
                },
                "annual_turnover": "1,000,000 kr"
            },
            "foundation_year": 1908,
            "board": [
                {
                    "name": "Arthur Wirström",
                    "role": "ordf."
                },
                {
                    "name": "Folke Burström",
                    "role": "dir."
                },
                {
                    "name": "Hugo Burström",
                    "role": null
                },
                {
                    "name": "Curt Wirström",
                    "role": "generalkonsul"
                }
            ],
            "director": "Folke Burström",
            "bryggm": "G. Sandgren"
        },
        "3": {
            "name": "Lumalampan AB.",
            "location": "Stockholm",
            "business": "Glödlampfabrik",
            "products": "Tillverkar elektr. lampor såsom belysningslampor, speciallampor, billampor, dvärglampor, kvicksilver-ånglampor, lysämneslampor, glimlampor, likriktarrör, elektriska julgransbelysningar och terapilampor, elektr. kontakter, elektroder, neonelektroder, volfram-tråd, molybdentråd, hårdmetall, dragskivor, ställbara dragmatriser, dragdornar och andra dragverktyg.",
            "contact": {
                "office": "Lumavägen 6",
                "telegraph": "Lumalampan",
                "phone": "Lumalampan",
                "postgiro": "156690"
            },
            "financials": {
                "capital": "2,000,000 kr",
                "employees": {
                    "industriarb": 1000
                }
            },
            "foundation_year": 1930,
            "board": [
                {
                    "name": "Albin Johansson",
                    "role": "ordf."
                },
                {
                    "name": "Mauritz Bonow",
                    "role": null
                },
                {
                    "name": "Hj. Degerstedt",
                    "role": "dir."
                },
                {
                    "name": "Hugo Edstam",
                    "role": "dir."
                },
                {
                    "name": "G. Osvald",
                    "role": "dir."
                },
                {
                    "name": "Ernst Persson",
                    "role": "dir."
                }
            ],
            "verkst. dir": "H. Schlott",
            "dir.-assist": "M. Hyström",
            "kontorschef": "E. Edblad",
            "laboratoriechef": "G. Siljeholm"
        },
        "4": {
            "name": "Aug. Lundhs Metallfabrik",
            "location": "Eskilstuna",
            "business": "Tillverkar kokkärl och andra hushållsartiklar av aluminium",
            "contact": {
                "phone": "31817"
            },
            "financials": {
                "employees": {
                    "industriarb": 12
                },
                "annual_production_value": "215,000 kr"
            },
            "foundation_year": 1920,
            "manager": "fabr. Tore Lundh"
        }
    }
}