{
    "original": "Svenska\n\nAkt.-kap.: 200,000 kr. Prod.-värde pr\når: 7,000,000 kr. — Bolaget grundat\n1945.\n\nStyrelse: civiling. Carl Pålsson (ordf.),\nciviling. Håkan Birke, ing. Alvar Bylund,\ning. Sven Dahlberg, civiling. Bo Jondal.\n\nVerkst. dir.: Sven Dahlberg.\n\n\"Svenska Invarit AB., Köping.\n\nTillverkar asbestcementplattor för\ntaktäckning och väggbeklädnad samt\nevakueringstrummor m. m. Varumärke:\n»Invarit» .\n\nHuvudkontor: Köping. Telegr.-adr.:\nInvarit, Köping. Telefon:\n»Invaritbola-l?et». Postgiro: 268373. Försäljn.-kontor:\nStockholm, Kungsg. 32, telefon: 231650;\nGöteborg, V. Hamng. 24, telefon: 113527\n—28.\n\nAkt.-kap.: 100,000 kr. Antal\nindustriarb.: 130. — Bolaget grundat 1940,\nfabriken anlagd 1943.\n\nStyrelse: dir. Ernst Wehtje (ordf.),\ndir. Malte Ström, övering. Donovan\nWerner.\n\nDriftsing.: Karl G. Fieber.\n\n(Jfr annons nr 16.)\n\nAB. Svenska\nIsoleringsflask-f abr i ken, Jönköping.\n\nSe AB. Termoverken, Jönköping.\n\n*AB. Svenska Järnvägsverkstäderna,\n\nLinköping.\n\nMek. verkstäder och gjuterier i\nLinköping, Falun (Vagn- och Maskinfabriken i\nFalun) och Arlöv (Waggonfabriken i\nAr-löv).\n\nTillverkar lokomotiv, järnvägsvagnar,\nspårvagnar, rälsbussar,\nomnibuskarosse-rier, arméfordon, värmetekniska\napparater (system: »Parca») såsom kol- och\nvedeldade värmeledningspannor,\nstoker-pannor och stokerapparater för flis och\nstenkol, generatorpannor,\nindustrigeneratorer, industriugnar, varmvattenberedare\noch motströmsapparater samt gjutgods etc.\n\nHuvudkontor: Linköping. Telegr.-adr.:\nSvenska, Linköping. Telefon:\n»Verkstäderna». Postgiro: 11430. Avd.-kontor:\nFalun och Arlöv.\n\nAkt.-kap.: 12,249,000 kr. Antal\nanställda: 1,650.\n\nBolaget grundat 1907.\n\nStyrelse: konsul Oscar Gullander\n*(ordf.), bankdir. Rolf Calissendorff,\nbergsing. Tryggve Holm, civiling. F. G.\nlaljenroth.\n\nVerkst. dir.: Tryggve Holm.\n\nPlatschef i Falun: övering. John\nMalmkvist.\n\n(Jfr annons efter Alfabet.\nVaruför-teckning.)\n\n\"Svenska Jästfabriks AB.,\n\nStockholm.\n\nJästfabriker i Rotebro (Sthlms l.),\nMölndal (Göteb. o. Bohus. L), Nässjö\n(Jönköp. l.)l och Tomelilla (Kristianst. l.) ;\nstärkelsefabriker i Tomelilla, Långebro,\nLinderöd, Tjörnarp och Vallabäcken\n(samtl. i Kristianst. l.) samt Backaryd\n(Blekinge l.); potatisbränneri i Tomelilla;\nlantgårdar i Sollentunaholm, Nässjö och\nTomelilla.\n\nTillverkar pressjäst, torr jäst, ^\njäst-extrakt, potatismjöl och potatissprit.\n\nHuvudkontor: Stockholm, Kammakarg.\n62. Telegr.-adr.: Zymos, Stockholm.\nTelefon: »Jästbolaget». Postgiro: 839.\n\nAkt.-kap.: 16,000,000 kr. Antal\nindustriarb.: 160.\n\nBolaget grundat 1919. Resp. fabriker\nanlagda: Rotebro 1893, Mölndal 1874,\nNässjö 1890 och Tomelilla 1894.\n\nStyrelse: dir. Fritiof Söderbäck (ordf.),\nciviling. Sten Westerberg (v. ordf.),\növering. Henry Brahmer, civiling. C.-G. Piehl,\ndir. Otto Ramstedt, fabr. Carl Schröder,\ndir. Richard Wennberg.\n\nVerkst. dir.: Sten Westerberg.\nV. verkst. dir. o. övering.: Henry\nBrahmer.\n\nDisponenter: i Stockholm: I. Westin;\ni Göteborg: Alb. Cewers; i Nässjö:\nWilhelm Johanson; i Tomelilla: N. R.\nNor-mander.\n\n(Jfr annons nr 99.)\n\n*Svenska Kamgarnsspinneri AB.,\n\nBorås.\n\nTillverkar vid fabrik i Norrköping\nkamgarner för AB. Borås\nKlädningstygs-fabriks behov.\n\nTelegr.-adr.: Tops, Borås. Telefon:\n10056.\n\nAkt.-kap.: 200,000 kr. Antal\nindustriarb.: 45. Tillv.-värde pr år: 515,000 kr.\n— Bolaget grundat 1915.\n\nStyrelse: dir. Arthur Anderson, dir.\nC. E. Edlund.\n\nVerkst. dir.: C. E. Edlund.\n\n*Svenska Kapokfabriken AB.,\n\nStockholm.\n\nTillverkar kapok, vadd, täcken,\nmadrasser och kuddar samt sovsäckar vid fabrik\ni Rosersberg (Sthlms l.) samt\nmorgonrockar, bädd jackor och damkonfektion",
    "structured": {
        "0": {
            "name": "Svenska Invarit AB.",
            "location": "Köping",
            "business": "Tillverkar asbestcementplattor för taktäckning och väggbeklädnad samt evakueringstrummor m. m.",
            "products": "Varumärke: Invarit",
            "contact": {
                "office": "Köping",
                "phone": [
                    "Invaritbola-l?et"
                ],
                "postgiro": "268373",
                "head_office": "Köping",
                "sales_offices": [
                    {
                        "location": "Stockholm",
                        "phone": "231650"
                    },
                    {
                        "location": "Göteborg",
                        "phone": "113527—28"
                    }
                ],
                "telegraph": "Invarit, Köping"
            },
            "financials": {
                "capital": "200,000 kr",
                "annual_production_value": "7,000,000 kr"
            },
            "foundation_year": 1945,
            "board": [
                {
                    "name": "civiling. Carl Pålsson",
                    "role": "ordf."
                },
                {
                    "name": "civiling. Håkan Birke",
                    "role": ""
                },
                {
                    "name": "ing. Alvar Bylund",
                    "role": ""
                },
                {
                    "name": "ing. Sven Dahlberg",
                    "role": ""
                },
                {
                    "name": "civiling. Bo Jondal",
                    "role": ""
                }
            ],
            "director": "Sven Dahlberg"
        },
        "1": {
            "name": "AB. Svenska Isoleringsflaskfabriken",
            "location": "Jönköping",
            "business": "Se AB. Termoverken, Jönköping.",
            "products": null,
            "contact": {
                "office": null,
                "phone": null,
                "postgiro": null,
                "head_office": null,
                "sales_offices": null,
                "telegraph": null
            },
            "financials": {
                "capital": "100,000 kr"
            },
            "foundation_year": 1940,
            "board": [
                {
                    "name": "dir. Ernst Wehtje",
                    "role": "ordf."
                },
                {
                    "name": "dir. Malte Ström",
                    "role": ""
                },
                {
                    "name": "övering. Donovan Werner",
                    "role": ""
                }
            ],
            "director": "Karl G. Fieber"
        },
        "2": {
            "name": "AB. Svenska Järnvägsverkstäderna",
            "location": "Linköping",
            "business": "Mek. verkstäder och gjuterier",
            "products": "Tillverkar lokomotiv, järnvägsvagnar, spårvagnar, rälsbussar, omnibuskarosserier, arméfordon, värmetekniska apparater (system: Parca) såsom kol- och vedeldade värmeledningspannor, stokerpannor och stokerapparater för flis och stenkol, generatorpannor, industriugnar, varmvattenberedare och motströmsapparater samt gjutgods etc.",
            "contact": {
                "office": "Linköping",
                "phone": [
                    "Verkstäderna"
                ],
                "postgiro": "11430",
                "head_office": "Linköping",
                "sales_offices": [
                    {
                        "location": "Falun",
                        "phone": null
                    },
                    {
                        "location": "Arlöv",
                        "phone": null
                    }
                ],
                "telegraph": "Svenska, Linköping"
            },
            "financials": {
                "capital": "12,249,000 kr",
                "employees": {
                    "industriarb.": 130
                }
            },
            "foundation_year": 1907,
            "board": [
                {
                    "name": "konsul Oscar Gullander",
                    "role": "ordf."
                },
                {
                    "name": "bankdir. Rolf Calissendorff",
                    "role": ""
                },
                {
                    "name": "bergsing. Tryggve Holm",
                    "role": ""
                },
                {
                    "name": "civiling. F. G. laljenroth",
                    "role": ""
                }
            ],
            "director": "Tryggve Holm"
        },
        "3": {
            "name": "Svenska Jästfabriks AB.",
            "location": "Stockholm",
            "business": "Jästfabriker och stärkelsefabriker",
            "products": "Tillverkar pressjäst, torr jäst, jäst-extrakt, potatismjöl och potatissprit.",
            "contact": {
                "office": "Stockholm",
                "phone": [
                    "Jästbolaget"
                ],
                "postgiro": "839",
                "head_office": "Stockholm",
                "sales_offices": null,
                "telegraph": "Zymos, Stockholm"
            },
            "financials": {
                "capital": "16,000,000 kr",
                "employees": {
                    "industriarb.": 160
                }
            },
            "foundation_year": 1919,
            "board": [
                {
                    "name": "dir. Fritiof Söderbäck",
                    "role": "ordf."
                },
                {
                    "name": "civiling. Sten Westerberg",
                    "role": "v. ordf."
                },
                {
                    "name": "övering. Henry Brahmer",
                    "role": ""
                },
                {
                    "name": "civiling. C.-G. Piehl",
                    "role": ""
                },
                {
                    "name": "dir. Otto Ramstedt",
                    "role": ""
                },
                {
                    "name": "fabr. Carl Schröder",
                    "role": ""
                },
                {
                    "name": "dir. Richard Wennberg",
                    "role": ""
                }
            ],
            "director": "Sten Westerberg"
        },
        "4": {
            "name": "Svenska Kamgarnsspinneri AB.",
            "location": "Borås",
            "business": "Tillverkar vid fabrik i Norrköping kamgarner för AB. Borås Klädningstygsfabriks behov.",
            "products": null,
            "contact": {
                "office": null,
                "phone": null,
                "postgiro": null,
                "head_office": null,
                "sales_offices": null,
                "telegraph": "Tops, Borås"
            },
            "financials": {
                "capital": "200,000 kr"
            },
            "foundation_year": 1915,
            "board": [
                {
                    "name": "dir. Arthur Anderson",
                    "role": ""
                },
                {
                    "name": "dir. C. E. Edlund",
                    "role": "ordf."
                }
            ],
            "director": "C. E. Edlund"
        },
        "5": {
            "name": "Svenska Kapokfabriken AB.",
            "location": "Stockholm",
            "business": "Tillverkar kapok, vadd, täcken, madrasser, kuddar samt sovsäckar och morgonrockar, bäddjackor och damkonfektion",
            "products": null,
            "contact": {
                "office": null,
                "phone": null,
                "postgiro": null,
                "head_office": null,
                "sales_offices": null,
                "telegraph": null
            },
            "financials": {
                "capital": "unknown"
            },
            "foundation_year": null,
            "board": [
                {
                    "name": "unknown"
                }
            ]
        }
    }
}