{
    "original": "Industri\n\nAkt.-kap.: 30,000 kr. Antal\nindustriarb.: 20. Tillv.-värde pr år: 500,000 kr.\n— Bolaget grundat 1938.\n\nDisp.: Gust. Månson.\n\nKamrer: Ragnar Svensson.\n\nDriftsing.: Hjalmar Carlbring.\n\nIndustri AB. Mbk-W.,\n\nMalmbäck.\n\nTillverkar fåtölj- och matbord, rökbord,\nbarbord, sybord, hopfällbara spelbord,\nbrickbord, tevagnar m. m. samt möbellås\noch beslag i järn och metall vid fabrik i\nMalmbäck (Jönköp. l.).\n\nTelefon: 6 o. 20. Postgiro: 77123. —\nAkt.-kap.: 80,000 kr. Antal industriarb.:\n15. — Bolaget grundat 1943 efter\növertagandet av AB. Bröderna Malmqvists\nMöbelfabrik och AB. Malmbäcks\nTräindustri, båda i Malmbäck.\n\nVerkst. dir.: Carl Wigell.\n\nIndustri AB. Svenska Automatvapen,\n\nStockholm,.\n\nFörsäljn.-bolag för AB. Sandins\nMetallfabrik, Sundbyberg (se detta bolag).\n\nKontor: Stockholm, Arsenalsg. 2.\nTelefon: 231270.\n\nAkt.-kap.: 200,000 kr. — Bolaget\ngrundat 1940.\n\nStyrelse: övering. Patrik Rydbeck\n(ordf.), dir. Gustaf Kahm, major Torsten\nLindfors, ing. Erik Lindholm, civiling.\nErik Lindström.\n\nVerkst. dir.: Gustaf Kahm.\n\nDisp. o. försäljn.-chef: Sten Hasselberg.\n\n\"Industri AB. Sylva, Landskrona.\n\nKem.-teknisk fabrik. Tillverkar såpa,\ntvål, tvättmedel, parfymer och kosmetiska\npreparat. Varunamn: Resia, Za-Za, Aina,\nVeronica, Oryalis, Tsardas o. Vibadont.\n\nTelefon: »Sylva». Postgiro: 278089. —\nAkt.-kap.: 3,000,000 kr. Antal\nindustriarb.: 130. — Bolaget grundat 1916.\n\nStyrelse: dir. Gunnar Andersson\n(ordf.), bankdir. frih. Sven Raab.\n\nVerkst. dir.: Sven Green.\n\nBitr. dir.: Kaj Simonsen.\n\n\"Industri AB. Uhr &amp; Son, Skänninge.\n\nTillverkar möbler, spad- och\nskyffelskaft vid fabrik i Skänninge\n(Östergötl. l.).\n\nTelefon: 390. Försäljn.-kontor: Äng.\nTelefon: 60. Postgiro: 99353.\n\nAkt.-kap.: 80,000 kr. Arb.-antal: 25.\nTillv.-värde pr år: 300,000 kr. — Bolaget\n\ngrundat 1931 under namn AB.\nVätter-vikens Skaftfabrik, nuv. namn 1945.\n\nVerkst. dir.: Ivar V. Uhr.\n\nFörsäljn.-chef: Ingemar Uhr.\n\nPlatschef: C. A. Fridlund.\n\n\"Industri-AB. Viking, Örebro.\n\nKem.-teknisk fabrik med glasbruk,\nbleckemballage- och kartongfabrik.\nTillverkar »Viking»-skokräm,\n»Viking»-lädersmörja och »Viking»-ugnsvärta.\n\nTelegr.-adr.: Viking, Örebro. Telefon:\n10120 o. 11614. Postgiro: 10241.\n\nAkt.-kap.: 550,000 kr. Antal\nindustriarb.: 50. Tillv.-värde pr år: 3,400,000 kr.\n\nFirman grundades 1901 och ombildades\n1907 till aktiebolag.\n\nStyrelse: fil. mag. Ruben Hellerstad,\nfru Emma Pehrson, herr Karl-Erik\nPehr-son.\n\nVerkst. dir.: Ruben Hellerstad.\n\nKamrer: Gösta Palmgren.\n\nIndustri AB. Ölandssten, Kalmar.\n\nStenhuggeri vid Persnäs på Öland\n(Kalmar l.). Tillverkar byggnads- och\nträdgårdssten samt gravvårdar av\nkalksten.\n\nKontor: Kalmar. Telegr.-adr.: Mikael,\nKalmar. Telefon: 3785. Postgiro: 277960.\n— Akt.-kap.: 42,000 kr. Antal\nindustriarb.: 31. Prod.-värde pr år: 125,000 kr. —\nBolaget grundat 1944.\n\nVerkst. dir.: löjtn. Göte Mikaelsson.\n\nIndustrifirman Skandia, Anderstorp.\n\nTillverkar rostfria kuvertartiklar, fat\noch husgerådsartiklar vid mek. verkstad i\nAnderstorp (Jönköp. l.).\n\nTelefon: 175. Postgiro: 163311. —\nAntal industriarb.: 10. Tillv.-värde pr år:\n400,000 kr. — Firman etabl. 1939.\n\nÄgare o. chef: fabr. Oscar Gustafsson.\n\nKamrer: Arvid Olsson.\n\nAB. Industrifärger, Lidingö.\n\nFärg- och fernissfabrik. Tillverkar\nolje- och spritlacker, lack- och oljefärger,\ncellulosalacker samt syntetiska läcker;\nspecialiteter: rostskydds- och\nindustrifärger. Varumärken: »Ifanol»,\n»Plasto-lac», »Ifalit», »Ferrokrom» o. »Syntolin».\n\nTelegr.-adr.: Industrifärger, Lidingö.\nTelefon: 652580. Postgiro: 6622.\n\nAkt.-kap.: 25,000 kr. Arb.-antal: 20.\nTillv.-värde pr år: 1,500,000 kr. —\nFirman etabl. 1931 i Göteborg, överflyttades\ntill Lidingö 1937.\n\nDisp.: civiling. Alfred Kaufmann.\n\nKontorschef: kamrer S. Å. Rhodin.\n\nFörsäljn.-chef; W. Odhammar.",
    "structured": {
        "firms": [
            {
                "name": "Industri AB. Mbk-W.",
                "location": "Malmbäck",
                "business": "Tillverkar fåtölj- och matbord, rökbord, barbord, sybord, hopfällbara spelbord, brickbord, tevagnar m. m. samt möbellås och beslag i järn och metall vid fabrik i Malmbäck (Jönköp. l.)",
                "contact": {
                    "phone": [
                        "6",
                        "20"
                    ],
                    "postgiro": "77123"
                },
                "financials": {
                    "capital": "30,000 kr",
                    "employees": {
                        "industriarb": 20
                    },
                    "annual_turnover": "500,000 kr"
                },
                "foundation_year": 1938,
                "director": "Gust. Månson",
                "manager": "Hjalmar Carlbring"
            },
            {
                "name": "Industri AB. Mbk-W.",
                "location": "Malmbäck",
                "business": "Bolaget grundat 1943 efter övertagandet av AB. Bröderna Malmqvists Möbelfabrik och AB. Malmbäcks Träindustri, båda i Malmbäck.",
                "contact": {
                    "phone": [
                        "6",
                        "20"
                    ],
                    "postgiro": "77123"
                },
                "financials": {
                    "capital": "80,000 kr",
                    "employees": {
                        "industriarb": 15
                    }
                },
                "foundation_year": 1943,
                "director": "Carl Wigell"
            },
            {
                "name": "Industri AB. Svenska Automatvapen",
                "location": "Stockholm",
                "business": "Försäljn.-bolag för AB. Sandins Metallfabrik, Sundbyberg (se detta bolag).",
                "contact": {
                    "phone": "231270"
                },
                "financials": {
                    "capital": "200,000 kr"
                },
                "foundation_year": 1940,
                "board": [
                    {
                        "name": "Patrik Rydbeck",
                        "role": "övering"
                    },
                    {
                        "name": "Gustaf Kahm",
                        "role": "dir."
                    },
                    {
                        "name": "Torsten Lindfors",
                        "role": "major"
                    },
                    {
                        "name": "Erik Lindholm",
                        "role": "ing."
                    },
                    {
                        "name": "Erik Lindström",
                        "role": "civiling."
                    }
                ],
                "director": "Gustaf Kahm",
                "sales_manager": "Sten Hasselberg"
            },
            {
                "name": "Industri AB. Sylva",
                "location": "Landskrona",
                "business": "Kem.-teknisk fabrik. Tillverkar såpa, tvål, tvättmedel, parfymer och kosmetiska preparat.",
                "contact": {
                    "telegraph": "Sylva",
                    "postgiro": "278089"
                },
                "financials": {
                    "capital": "3,000,000 kr",
                    "employees": {
                        "industriarb": 130
                    }
                },
                "foundation_year": 1916,
                "board": [
                    {
                        "name": "Gunnar Andersson",
                        "role": "dir."
                    },
                    {
                        "name": "Sven Raab",
                        "role": "bankdir. frih."
                    }
                ],
                "director": "Sven Green",
                "sales_manager": "Kaj Simonsen"
            },
            {
                "name": "Industri AB. Uhr & Son",
                "location": "Skänninge",
                "business": "Tillverkar möbler, spad- och skyffelskaft vid fabrik i Skänninge (Östergötl. l.)",
                "contact": {
                    "phone": "390",
                    "factory_phone": "60",
                    "postgiro": "99353"
                },
                "financials": {
                    "capital": "80,000 kr",
                    "employees": {
                        "arb.-antal": 25
                    },
                    "annual_turnover": "300,000 kr"
                },
                "foundation_year": 1931,
                "current_name_year": 1945,
                "director": "Ivar V. Uhr",
                "sales_manager": "Ingemar Uhr",
                "manager": "C. A. Fridlund"
            },
            {
                "name": "Industri-AB. Viking",
                "location": "Örebro",
                "business": "Kem.-teknisk fabrik med glasbruk, bleckemballage- och kartongfabrik. Tillverkar »Viking»-skokräm, »Viking»-lädersmörja och »Viking»-ugnsvärta.",
                "contact": {
                    "telegraph": "Viking",
                    "phone": [
                        "10120",
                        "11614"
                    ],
                    "postgiro": "10241"
                },
                "financials": {
                    "capital": "550,000 kr",
                    "employees": {
                        "industriarb": 50
                    },
                    "annual_turnover": "3,400,000 kr"
                },
                "corporation_year": 1907,
                "board": [
                    {
                        "name": "Ruben Hellerstad",
                        "role": "fil. mag."
                    },
                    {
                        "name": "Emma Pehrson",
                        "role": "fru"
                    },
                    {
                        "name": "Karl-Erik Pehrson",
                        "role": "herr"
                    }
                ],
                "director": "Ruben Hellerstad",
                "kamrer": "Gösta Palmgren"
            },
            {
                "name": "Industri AB. Ölandssten",
                "location": "Kalmar",
                "business": "Stenhuggeri vid Persnäs på Öland (Kalmar l.). Tillverkar byggnads- och trädgårdssten samt gravvårdar av kalksten.",
                "contact": {
                    "telegraph": "Mikael",
                    "phone": "3785",
                    "postgiro": "277960"
                },
                "financials": {
                    "capital": "42,000 kr",
                    "employees": {
                        "industriarb": 31
                    },
                    "annual_production_value": "125,000 kr"
                },
                "foundation_year": 1944,
                "director": "löjtn. Göte Mikaelsson"
            },
            {
                "name": "Industrifirman Skandia",
                "location": "Anderstorp",
                "business": "Tillverkar rostfria kuvertartiklar, fat och husgerådsartiklar vid mek. verkstad i Anderstorp (Jönköp. l.)",
                "contact": {
                    "phone": "175",
                    "postgiro": "163311"
                },
                "financials": {
                    "employees": {
                        "industriarb": 10
                    },
                    "annual_production_value": "400,000 kr"
                },
                "foundation_year": 1939,
                "manager": "Oscar Gustafsson",
                "kamrer": "Arvid Olsson"
            },
            {
                "name": "AB. Industrifärger",
                "location": "Lidingö",
                "business": "Färg- och fernissfabrik. Tillverkar olje- och spritlacker, lack- och oljefärger, cellulosalacker samt syntetiska läcker; specialiteter: rostskydds- och industrifärger.",
                "contact": {
                    "telegraph": "Industrifärger",
                    "phone": "652580",
                    "postgiro": "6622"
                },
                "financials": {
                    "capital": "25,000 kr",
                    "employees": {
                        "arb.-antal": 20
                    },
                    "annual_production_value": "1,500,000 kr"
                },
                "foundation_year": 1931,
                "current_name_year": 1937,
                "director": "civiling. Alfred Kaufmann",
                "managing_director": "kamrer S. Å. Rhodin",
                "sales_manager": "W. Odhammar"
            }
        ]
    }
}