{
    "original": "Wikström—Wingqvist\n\nTelefon: 10456. Postgiro: 13711. —\nAkt.-kap.: 24,000 kr. Antal industriarb.:\n15. — Firman etabl. 1908, bolag 1936.\n\nVerkst. dir. o. disp.: fabr. Erik Nord.\n\n*AB. Carl Wikström, Göteborg.\n\nMössfabrik. Tillverkar mössor, spec.\nsportmössor. Varumärken: »Carwic»,\n»Triumf» o. »AB. C. W. G.». Firman\ndriver jämväl engroshandel med herrhattar,\ntrikåvaror, skjortor, handskar m. m.\n\nKontor: Wallg. 38. Telegr.-adr.:\nCarl-wik, Göteborg. Telefon: 111275, 130125\no. 138275. Postgiro: 12140.\n\nAkt.-kap.: 227,000 kr. Antal\nindustriarb.: 35. Tillv.-värde pr år: 400,000 kr.\n\n—\tFirman etabl. 1891, bolag 1917.\n\nStyrelse: dir. Nils Göransson, dir.\nRudolf Köhler, fröken A. Pehrson.\n\nFabrikationen: Nils Göransson.\n\nKontorschef: fröken A. Pehrson.\n\nHj. Wikström , Stockholm.\n\nMöbelfabrik. Tillverkar möbler samt\nbåt- oeh andra inredningar.\n\nKontor: Banérg. 25. Telefon: 614825.\n\n-\tArb.-antal: 4. — Firman etabl. 1902.\n\nÄgare o. chef: Hjalmar Wikström.\n\n\"Vilans Mek. Verkstads AB.,\n\nKristianstad.\n\nSe Hvilans Mek. Verkstads AB.,\nKristianstad.\n\n*Vimmerby Bryggeri, Vimmerby.\n\nSe AB. Nya Centralbryggeriet,\nLinköping.\n\nAB. Vimmerby Byggnadssnickerier,\n\nVimmerby.\n\nTillverkar byggnadssnickerier såsom\ndörrar, fönster, trappor och inredningar.\n\nTelefon: 291. Postgiro: 132070. Repr.\ni Stockholm: Olof S. Lindell, S:t\nEriks-plan 2, telefon: 320130.\n\nAkt.-kap.: 208,800 kr. Antal\nindustriarb.: 50. Tillv.-värde pr år: 900,000 kr. —\nBolaget grundat 1935.\n\nVerkst. dir.: Tore Isberg.\n\n* Vimmerby Läderfabriks AB.,\n\nVimmerby.\n\nTillverkar kromovanläder,\nkombina-tionsgarvat ovanläder, plattläder och\ntof-felläder.\n\nTelegr.-adr.: Läder fabriken, Vimmerby.\nTelefon: 172. Postgiro: 70200.\n\nAkt.-kap.: 70,500 kr. Antal\nindustriarb.: 40. Tillv.-värde pr år: 1,000,000 kr.\n— Firman etabl. 1881, bolag 1918.\n\nStyrelse: civiling. Robert Karlberg\n(ordf.), disp. Erik Karlberg.\n\nDisp.: Erik Karlberg.\n\n*AB. Vimmerby Träförädiingsfabrik,\n\nVimmerby.\n\nTillverkar byggnadssnickerier, hyvlade\nträvaror samt listverk.\n\nTelefon: 73. — Akt.-kap.: 225,200 kr.\nAntal industriarb.: 27. Tillv.-värde pr år:\n325,000 kr. — Firman grundad 1892,\nbolag 1929.\n\nStyrelse: fabr. Arvid Hallberg, disp.\nEric Hallberg, fabr. Gustaf Hallberg,\ndir. Ture Törnell.\n\nVerkst. dir.: T. Törnell.\n\nDisp.: Eric Hallberg.\n\n*AB. Th. Winborg &amp; Co., Stockholm,\n\nKem.-tekn. fabrik i Saltsjö-Järla\n(Sthlms l.). Tillverkar ättika, senap,\nsoja, såser, safter, konserver m. m. samt\nfruktviner.\n\nPostadr.: Stockholm 11. Telegr.-adr.:\nWinborgs, Stockholm. ^ Telefon:\n»Win-borgs Fabriker». Postgiro: 870.\n\nAkt.-kap.: 2,100,000 kr. Antal\nindustriarb.: 150. Tillv.-värde pr år: 7,000,000\nkr. — Firman etabl. 1861, bolag 1900.\n\nStyrelse: dir. Boris Meyerson (ordf.),\ning. Gunnar Meyerson.\n\nVerkst. dir.: B. Meyerson.\n\nV. verkst. dir.: Gunnar Meyerson.\n\nFörsäljn.-chef: Ralph Berglund.\n\nKamrer: Olof Agell.\n\n*AB. P. Winckler &amp; Comp., Malmö.\n\nSnickeri- och möbelfabrik. Tillverkar\nmöbler och butiksinredningar samt\nkommersiella kylskåp.\n\nKontor: Norreg. 4. Telefon: 22390.\nPostgiro: 245623. — Akt.-kap.: 18,000 kr.\nAntal industriarb.: 7. Tillv.-värde pr år:\n125,000 kr. — Firman etabl. 1906, bolag\n1946.\n\nStyrelse: snickarmäst. Einar Andersson\n(ordf.), snickare Nils Larsson, verkm.\nTage Nordqvist.\n\nVerkst. dir.: Einar Andersson.\n\n*L. J. Wingqvist, Fritsla Mekaniska\nVäfveri &amp; Spinnerier, Fritsla.\n\nVäveri, färgeri, blekeri och\nappretur-verk, bomulls- och ullspinnerier i Fritsla\n(Älvsb. l.).",
    "structured": {
        "1": {
            "name": "AB. Carl Wikström",
            "location": "Göteborg",
            "business": "Mössfabrik",
            "contact": {
                "office": "Wallg. 38",
                "phone": [
                    "111275",
                    "130125",
                    "138275"
                ],
                "postgiro": "12140",
                "telegraph": "Carl-wik, Göteborg"
            },
            "financials": {
                "capital": "24,000 kr",
                "employees": {
                    "industriarb": 15
                },
                "foundation_year": 1908,
                "corporation_year": 1936
            },
            "board": [
                {
                    "name": "Nils Göransson",
                    "role": "dir."
                },
                {
                    "name": "Rudolf Köhler",
                    "role": "dir."
                },
                {
                    "name": "fröken A. Pehrson",
                    "role": "Kontorschef"
                }
            ],
            "owners": [
                "Erik Nord"
            ]
        },
        "2": {
            "name": "Hj. Wikström",
            "location": "Stockholm",
            "business": "Möbelfabrik",
            "contact": {
                "office": "Banérg. 25",
                "phone": "614825"
            },
            "financials": {
                "employees": {
                    "Arb.-antal": 4
                },
                "foundation_year": 1902
            },
            "owners": [
                "Hjalmar Wikström"
            ]
        },
        "3": {
            "name": "Vimmerby Bryggeri",
            "location": "Vimmerby",
            "description": "Se AB. Nya Centralbryggeriet, Linköping"
        },
        "4": {
            "name": "AB. Vimmerby Byggnadssnickerier",
            "location": "Vimmerby",
            "business": "Tillverkar byggnadssnickerier",
            "contact": {
                "phone": "291",
                "postgiro": "132070",
                "sales_offices": [
                    {
                        "location": "Stockholm",
                        "phone": "320130"
                    }
                ]
            },
            "financials": {
                "capital": "208,800 kr",
                "employees": {
                    "industriarb": 50
                },
                "annual_production_value": "900,000 kr"
            },
            "foundation_year": 1935,
            "director": "Tore Isberg"
        },
        "5": {
            "name": "Vimmerby Läderfabriks AB.",
            "location": "Vimmerby",
            "business": "Tillverkar kromovanläder, kombinationstärdat ovanläder, plattläder och toffelläder",
            "contact": {
                "telegraph": "Läder fabriken, Vimmerby",
                "phone": "172",
                "postgiro": "70200"
            },
            "financials": {
                "capital": "70,500 kr",
                "employees": {
                    "industriarb": 40
                },
                "annual_production_value": "1,000,000 kr"
            },
            "foundation_year": 1881
        },
        "6": {
            "name": "AB. Vimmerby Träförädingsfabrik",
            "location": "Vimmerby",
            "business": "Tillverkar byggnadssnickerier, hyvlade trävaror samt listverk",
            "contact": {
                "phone": "73"
            },
            "financials": {
                "capital": "225,200 kr",
                "employees": {
                    "industriarb": 27
                },
                "annual_production_value": "325,000 kr"
            },
            "foundation_year": 1892
        },
        "7": {
            "name": "AB. Th. Winborg & Co.",
            "location": "Stockholm",
            "business": "Kem-teknisk fabrik",
            "contact": {
                "postaddr": "Stockholm 11",
                "telegraph": "Winborgs, Stockholm",
                "phone": "»Win-borgs Fabriker»",
                "postgiro": "870"
            },
            "financials": {
                "capital": "2,100,000 kr",
                "employees": {
                    "industriarb": 150
                },
                "annual_production_value": "7,000,000 kr"
            },
            "foundation_year": 1861,
            "board": [
                {
                    "name": "Boris Meyerson",
                    "role": "dir."
                },
                {
                    "name": "Gunnar Meyerson",
                    "role": "ing."
                }
            ],
            "owners": [
                "B. Meyerson",
                "Gunnar Meyerson"
            ]
        },
        "8": {
            "name": "AB. P. Winckler & Comp.",
            "location": "Malmö",
            "business": "Snickeri- och möbelfabrik",
            "contact": {
                "office": "Norreg. 4",
                "phone": "22390",
                "postgiro": "245623"
            },
            "financials": {
                "capital": "18,000 kr",
                "employees": {
                    "industriarb": 7
                },
                "annual_production_value": "125,000 kr"
            },
            "foundation_year": 1906,
            "board": [
                {
                    "name": "Einar Andersson",
                    "role": "snickarmäst."
                },
                {
                    "name": "Nils Larsson",
                    "role": "snickare"
                },
                {
                    "name": "Tage Nordqvist",
                    "role": "verkm."
                }
            ]
        },
        "9": {
            "name": "L. J. Wingqvist, Fritsla Mekaniska Väfveri & Spinnerier",
            "location": "Fritsla",
            "business": "Väveri, färgeri, blekeri och appreturverk, bomulls- och ullspinnerier",
            "description": "i Fritsla (Älvsb. l.)"
        }
    }
}