{
    "original": "Hellefors—Hellman\n\neller elektrostålkvalitet i form av göt,\nbillets, band, tråd samt stångstål i\nvarmvalsat draget eller slipat utförande;\nle-gerat eller olegerat stål levereras i en\nmängd specialkvaliteter såsom\nverktygsstål, kullagersstål, knivstål, filstål, ihåligt\noch solitt bergborrstål, konstruktionsstål,\nfjäderstål; centerlesslipat axelstål,\nsilverstål; alla slag av valstråd såsom\nstål-valstråd, lintråd, pianotråd, mjuk\nvalstråd för emballage, spik etc., sömjärn,\nledningstråd, nittråd, svetstråd etc.,\ndraget järn och stål; gjutgods,\nverkstadsarbeten; sågade och hyvlade trävaror, lådor\noch lådämnen samt byggnadssnickerier;\ndistribuerar elektrisk energi.\n\nSikfors Bruk o. gruvavd.,Sikfors.\nMasugn, anriknings- och sintringsverk samt\nkolningsverk i Sikfors, järnmalmsgruvor\nvid SirsjÖbergs gruvfält, kalkbrott i\nHasselhöjden och Skatviken (samtl. i Örebro\nL). Bryter järnmalm och kalksten,\nframställer slig, sinter och tackjärn, tjära och\nråmetanol.\n\nBängbroverken, Bångbro. Kallvalsverk.\nTillverkar kallvalsat bandjärn och\nbandstål i härdat och ohärdat utförande,\nsåsom ur- och grammofonfjäderstål, stål för\nträ- och metallbandsågar, bågfilstål,\nmått-bandstål, rakbladstål, bandstål för\ndiverse delar i textilmaskiner.\n\nStållinefabriken, Kristinehamn.\nTråd-drageri och linslageri. Tillverkar\nståltrådslinor av alla slag, dragen ståltråd\noch järntråd samt svetsningstråd.\n\n^ Fredriksbergsverken, Fredriksberg.\nSulfit-, sulfat- och pappfabriker. Tillverkar\nsulfit- och sulfatcellulosa samt sulfatpapp.\n\nBolaget idkar jämväl jordbruk,\nskogshantering och kvarnrörelse, äger ett\n20-tal elektriska vattenkraftstationer vid\nSvartälven med biflöden samt trafikerar\nHällefors—Fredriksbergs järnvägar och\nHällefors bruksbana.\n\nHuvudkontor: Hällefors.\nTelegr.-adr.: Trävaror o. cellulosa:\nHellefors-wood; stållinor: Lina, i övrigt: Hellefors,\nFilipstad. Telefon: Hällefors,\n»Brukskontoret». Postgiro: 80675.\nAvdelningskontor i Sikfors,\nFredriksberg, Bångbro och Kristinehamn.\nFörsäljningskontor: Stockholm,\nStu-replan 19, telefon: 110766, 200766 o.\n200770; Malmö, Carlsg. 52, telefon: 75910,\n759*30 o. 76910.\n\nAkt.-kap.: 10,000,000 kr. Sammanlagt\nantal arbetare c:a 3,500, varav\nindustriarbetare c:a 2,000. Årstillv.: 40,000 ton\njärn och stål samt produkter därav,\n10,000 stds sågade och hyvlade trävaror,\n5,000 stds lådämnen och lådor, 14,000\nton sulfitmassa, 10,000 ton sulfatmassa\noch 12,000 ton kraftpapp.\n\nFöretaget grundat 1639, aktiebolag\n1864, senast ombildat 1935. Bolaget har\ni sig upptagit f. d. AB. Hellefors\nManufakturverk, Bångbro, samt AB. Svenska\nStållinor, Kristinehamn.\n\nStyrelse: bankdir. Gustaf Söder lund\n(ordf.), bankdir. P. Brundell, bankdir.\nErnst C:son Herslow, adv. Alf Lindahl,\ndir. Ernst Wehtje, dir. P. O. Westerberg,\ndisp. Th. Wigelius.\n\nVerkst. dir. o. disp.: Thorsten Wigelius.\n\nV. verkst. dir.: Sven L. Wahlström.\n\nKamrer.- Ed v. Jarnulf.\n\nOmbudsman: jur. kand. Folke Arkling.\n\nFörsäljn.-chef er: för järn o. stål:\nbergs-ing. Johan Paues; för trävaror o.\ncellulosa: G. Uhlén.\n\nInköpschef: E. Breitenau.\n\nSkogschef: Wilhelm Blom.\n\nDriftschefer: i Hällefors: för\njärn-o. stålverken: övering. H. Kihlander; för\nsågverk o. lådfabrik: förv. R. Fogelberg;\nfor kraft-, byggnads- o. transportavd.:\nkapten Åke Blomberg; i Sikfors:\nbergs-ing. Ingvar Janelid; i Fredriksberg:\növering. Nils Wegner; i Bångbro:\növering. Erik G. Pernstål; i Kristinehamn:\nbergsing. Folke Koraen.\n\n\"AB. Hellefors Manufakturverk,\n\nHällefors.\n\nSe Hellefors Bruks AB., Hällefors.\n\n* Hellefors Pappersbruk, Lönneberga.\n\nSe AB. Brusafors-Hällefors,\nSilverdalen.\n\n\"Hellekis Cementfabrik, Hellekis.\n\nSe Skånska Cement AB., Malmö.\n\nHellman &amp; Co. AB., Stockholm.\n\nFärg- och fernissfabrik. Tillverkar\nindustrilackfärger, skeppsfärger, fernissor,\ndekorationsfärger, specialoljor samt kem.\ntekniska artiklar. Varumärken: »Somos»,\n»Gallion», »Hellmans Snabblack»,\n»Oci-oco», »Dekora» o. »Tätabol».\n\nHuvudkontor: Lövholmsvägen 49;\npost-adr.: Stockholm 9. Telegr.-adr.: Cresta,\nStockholm. Telefon: 452670. Postgiro:\n848. Avd.-kontor: Göteborg, S. Vägen 69,\ntelefon, 164393; Malmö: Jerusalemsg. 14,\ntelefon: 33880.\n\nAkt.-kap.: 100,000 kr. Antal\nindustriarb.: 24. — Firman etabl. 1878, bolag\n1919.\n\nVerkst. dir.: ing. Sven Fagerberg.\n\nFörsäljn.-chef: Arne Sörensen-Ringi.\n\n355*",
    "structured": {
        "1": {
            "name": "Hellefors",
            "location": "Hällefors",
            "business": "Ståltillverkning och distribuering av elektrisk energi",
            "products": "Stålprodukter, sågade och hyvlade trävaror, lådor och lådämnen samt byggnadssnickerier",
            "contact": {
                "office": "Hällefors",
                "telegraph": "Trävaror o. cellulosa: Hellefors-wood; stållinor: Lina, i övrigt: Hellefors, Filipstad",
                "postgiro": "80675",
                "sales_offices": [
                    {
                        "location": "Sikfors",
                        "phone": ""
                    },
                    {
                        "location": "Fredriksberg",
                        "phone": ""
                    },
                    {
                        "location": "Bångbro",
                        "phone": ""
                    },
                    {
                        "location": "Kristinehamn",
                        "phone": ""
                    }
                ]
            },
            "financials": {
                "capital": "10,000,000 kr",
                "employees": {
                    "industriarbetare": 2000
                },
                "annual_turnover": "40,000 ton järn och stål samt produkter därav, 10,000 stds sågade och hyvlade trävaror, 5,000 stds lådämnen och lådor, 14,000 ton sulfitmassa, 10,000 ton sulfatmassa och 12,000 ton kraftpapp"
            },
            "foundation_year": 1639,
            "corporation_year": 1864,
            "board": [
                {
                    "name": "Gustaf Söderlund",
                    "role": "ordförande"
                },
                {
                    "name": "P. Brundell",
                    "role": "bankdirektör"
                },
                {
                    "name": "Ernst C:son Herslow",
                    "role": "bankdirektör"
                },
                {
                    "name": "Alf Lindahl",
                    "role": "advokat"
                },
                {
                    "name": "Ernst Wehtje",
                    "role": "direktör"
                },
                {
                    "name": "P. O. Westerberg",
                    "role": "direktör"
                },
                {
                    "name": "Th. Wigelius",
                    "role": "disp."
                }
            ],
            "owners": [],
            "director": "Thorsten Wigelius",
            "managing_director": "Sven L. Wahlström",
            "sales_manager": "Johan Paues",
            "manager": "Ed v. Jarnulf"
        },
        "2": {
            "name": "Sikfors Bruk o. gruvavd.",
            "location": "Sikfors",
            "business": "Masugn, anriknings- och sintringsverk samt kolkning",
            "products": "Järnmalmsgruvor, kalksten och kolprodukter",
            "contact": {},
            "financials": {},
            "foundation_year": null
        },
        "3": {
            "name": "Bängbroverken",
            "location": "Bångbro",
            "business": "Tillverkning av kallvalsat bandjärn och bandstål",
            "products": "Bland annat ur- och grammofonfjäderstål, stål för trä- och metallbandsågar, bågfilstål, mått-bandstål, rakbladstål",
            "contact": {},
            "financials": {},
            "foundation_year": null
        },
        "4": {
            "name": "Stållinefabriken",
            "location": "Kristinehamn",
            "business": "Tillverkning av ståltrådslinor och dragen ståltråd samt svetsningstråd",
            "products": "",
            "contact": {},
            "financials": {},
            "foundation_year": null
        },
        "5": {
            "name": "Fredriksbergsverken",
            "location": "Fredriksberg",
            "business": "Tillverkning av sulfit-, sulfat- och pappmassa",
            "products": "Sulfit- och sulfatcellulosa samt sulfatpapp",
            "contact": {},
            "financials": {},
            "foundation_year": null
        },
        "6": {
            "name": "Hellman & Co. AB.",
            "location": "Stockholm",
            "business": "Färg- och fernissfabrik",
            "products": "Industrilackfärger, skeppsfärger, fernissor, dekorationsfärger, specialoljor samt kem. tekniska artiklar",
            "contact": {
                "office": "Lövholmsvägen 49, Stockholm 9",
                "telegraph": "Cresta, Stockholm",
                "postgiro": "848",
                "sales_offices": [
                    {
                        "location": "Göteborg",
                        "phone": "164393"
                    },
                    {
                        "location": "Malmö",
                        "phone": "33880"
                    }
                ]
            },
            "financials": {
                "capital": "100,000 kr",
                "employees": {
                    "industriarb": 24
                }
            },
            "foundation_year": 1878,
            "corporation_year": 1919,
            "director": "ing. Sven Fagerberg",
            "sales_manager": "Arne Sörensen-Ringi"
        }
    }
}