{
    "original": "Burseryd—Byggnad\n\n*ABi Burseryds Tråd- &amp; Spikfabrik,\n\nSmålands Burseryd.\n\nTråddrageri, spikfabrik och lådfabrik i\nSmålands Burseryd (Jönköp. l.).\nTillverkar blank, förkopprad, förtent,\ngalva-niserad och glödgad järntråd, häfttråd,\ntaggtråd, trådspik, staglinor, galvaniserat\nvarm- och kallvalsat band järn,\nsängbot-tenkätting, ovaler, spiraler samt sågade\nlådämnen. Bolaget äger elektr.\nkraftstation.\n\nTelegr.-adr.: Tråddrageriet, Smålands\nBurseryd. Telefon: 83. Postgiro: 22588.\n\nAkt.-kap.: 90,000 kr. Antal\nindustriarb.: 27. Tillv.-värde pr år: ’950,000 kr. —\nFirman etabl. 1913, bolag 1943.\n\nStyrelse: disp. Carl-Evert Josefsson\n(ordf.), bokh. Kristina Josefsson, ing.\nRagnar Josefsson.\n\nVerkst. dir. o. disp.: Carl-Evert\nJosefsson.\n\n*AB. Burseryds Träindustri,\n\nSmålands Burseryd.\n\nParkettfabrik i Smålands Burseryd\n(Jönköp. l.). Tillverkar parkettstav och\nutför inläggning av parkettgolv.\n\nTelefon: 51. Postgiro: 94045.\nRepresentanter: AB. Axel Assmundson,\nStockholm, Nybrokajen 7, o. Göteborg,\nSkeppsbron 2; AB. Welinder &amp; Co, Malmö,\nDjäknear. 17; A. Jansson, Parkettgolv,\nNorrköping; AB. Matti &amp; Ehrnebo,\nEskilstuna.\n\nAkt.-kap.: 52,000 kr. Antal\nindustriarb.: 47. Tillv.-värde pr år: 900,000 kr.\n— Bolaget grundat 1935.\n\nStyrelse: nämndeman Martin Larsson\n(ordf.), fabr. Lars Davidsson, disp. John\nJohansson, fabr. Walfrid Sanden,\njärn-handl. Emil Willstedt.\n\nVerkst. dir.: John Johansson.\n\nBustorps Tegelbruk, Nättrabyhamn.\n\nTillverkar mur- och fasad tegel,\nhög-poröst- och lättegel, taktegel samt\ndräneringsrör vid tegelbruk vid Ronneby.\nFirman driver även jordbruk.\n\nKontor: Nättrabyhamn. Telefon:\nNätt-raby 1 o. 211. Postgiro: 5476. — Antal\nindustriarb.: 35. Årstillv.: 2,5 milj. st.\ntegel varor. — Tegelbruket anlagt\nomkring 1860.\n\nÄgare o. chef: fabr. Eric Mattelin.\n\nButeljglasbrukens Försäljnings AB-,\n\nStockholm.\n\nBolaget är ensamförsäljare för\nföljande glasbruk: Hammars Glasbruks AB.,\n\nAskersund, Kongelf s Glasbruks, AB.,\nKungälv, AB. Surte Giasbruk, Surte, och\nÅrnäs Bruk, österäng. Säljer buteljer,\nvattenflaskor, damejeanner,\nsvagdricks-flaskor, mjölkflaskor, kem. tekn. glas,\nkonserveringsglas, burkar m. m.\n\nKontor: Birger Jarlsg. 2. Telegr.-adr.:\nButeljglas, Stockholm. Telefon: 619920—\n23. Postgiro: 1601.\n\nAkt.-kap.: 70,000 kr. Antal\nindustriarb. vid de anslutna glasbruken: 900.\nSammanlagt tillv.-värde pr år: 12,000,000\nkr. — Bolaget grundat 1914.\n\nStyrelse: dir. Harald Engström (ordf.),\ndir. Gustaf Bergendal, dir. K.-H.\nFahl-ström, dir. Per J. Hemberg, frih. C.-G.\nLangenskiöld.\n\nVerkst. dir.: S. Emanuelson.\n\n*Buttorps Såg, Sexdrega.\n\nSe Bark &amp; Warburgs AB., Göteborg.\n\n*\tByggnads AB. Bröderna Bergbäck,\n\nLinköping.\n\nByggnadsentreprenörfirma för\nbostads-och affärshus, industribyggnader m. m.\n\nTelefon: 23731 och 26390. Postgiro:\n131618.\n\nAkt.-kap.: 40,000 kr. Prod.-värde pr år:\n1,200,000 kr. — Firman etabl. 1905, bolag\n1938 under namn Byggnads AB. Axel\nJohanson, nuv. namn 1945.\n\nStyrelse: byggnadsing. Ragnar\nBergbäck (ordf.), byggnadsing. Bror Bergbäck,\nkamrer Martin Bergbäck.\n\nVerkst. dir.: R. Bergbäck.\n\nArbetschef: B. Bergbäck.\n\nKamrer: M. Bergbäck.\n\n*\tByggnads AB. Contractor,\n\nStockholm.\n\nByggnadsentreprenadfirma med\nvarvsanläggning i Nyköping (Brandholmens\nvarv). Utför kaj-, bro-, kraftstations-,\nindustri- och bostadsbyggnader,\ngrundläggnings- och sprängningsarbeten,\nfördjupnings- och sandfyllningsarbeten med\nsandsugningsfartyg. Tillverkar kasuner,\npontoner, pråmar, färjor m. m. av\narmerad betong.\n\nKontor: Kungsg. 28. Telegr.-adr.:\nContractor, Stockholm. Telefon: 231605.\nPostgiro: 50653. — Akt.-kap.: 900,000\nkr. Omsättningsvärde pr år: 10,000,000\nkr. — Bolaget grundat 1910.\n\nStyrelse: disp. Erik Lenander (ordf.),\nciviling. Einar Almström, dir. Hans",
    "structured": {
        "1": {
            "name": "ABi Burseryds Tråd- & Spikfabrik",
            "location": "Smålands Burseryd",
            "business": "Tråddrageri, spikfabrik och lådfabrik",
            "products": "Tillverkar blank, förkopprad, förtent, galvaniserad och glödgad järntråd, häfttråd, taggtråd, trådspik, staglinor, galvaniserat varm- och kallvalsat band järn, sängbot-tenkätting, ovaler, spiraler samt sågade lådämnen",
            "contact": {
                "office": "Elektr. kraftstation",
                "phone": [
                    "83"
                ],
                "postgiro": "22588",
                "telegraph": "Tråddrageriet, Smålands Burseryd"
            },
            "financials": {
                "capital": "90,000 kr",
                "employees": {
                    "industriarb": 27
                },
                "annual_turnover": "950,000 kr",
                "annual_production_value": null
            },
            "foundation_year": 1913,
            "corporation_year": 1943,
            "board": [
                {
                    "name": "Carl-Evert Josefsson",
                    "role": "disp."
                },
                {
                    "name": "Kristina Josefsson",
                    "role": "bokh."
                }
            ],
            "director": "Carl-Evert Josefsson"
        },
        "2": {
            "name": "AB. Burseryds Träindustri",
            "location": "Smålands Burseryd",
            "business": "Parkettfabrik",
            "products": "Tillverkar parkettstav och utför inläggning av parkettgolv",
            "contact": {
                "phone": "51",
                "postgiro": "94045"
            },
            "financials": {
                "capital": "52,000 kr",
                "employees": {
                    "industriarb": 47
                },
                "annual_turnover": "900,000 kr",
                "annual_production_value": null
            },
            "foundation_year": 1935,
            "board": [
                {
                    "name": "Martin Larsson",
                    "role": "nämndeman"
                },
                {
                    "name": "Lars Davidsson",
                    "role": "fabr."
                }
            ],
            "director": "John Johansson"
        },
        "3": {
            "name": "Bustorps Tegelbruk",
            "location": "Nättrabyhamn",
            "business": "Tillverkar mur- och fasad tegel, hög-poröst- och lättegel, taktegel samt dräneringsrör vid tegelbruk vid Ronneby. Firman driver även jordbruk",
            "contact": {
                "office": "Nättrabyhamn",
                "phone": [
                    "Nättraby 1",
                    "211"
                ],
                "postgiro": "5476"
            },
            "financials": {
                "employees": {
                    "industriarb": 35
                },
                "annual_production_value": "2,5 milj. st. tegel varor"
            },
            "owner": "fabr. Eric Mattelin"
        },
        "4": {
            "name": "Buteljglasbrukens Försäljnings AB",
            "location": "Stockholm",
            "business": "Bolaget är ensamförsäljare för följande glasbruk",
            "products": "Säljer buteljer, vattenflaskor, damejeanner, svagdricks-flaskor, mjölkflaskor, kem. tekn. glas, konserveringsglas, burkar m. m.",
            "contact": {
                "office": "Birger Jarlsg. 2",
                "phone": [
                    "619920—23"
                ],
                "postgiro": "1601"
            },
            "financials": {
                "capital": "70,000 kr",
                "annual_production_value": "12,000,000 kr"
            },
            "foundation_year": 1914,
            "board": [
                {
                    "name": "Harald Engström",
                    "role": "dir."
                }
            ],
            "managing_director": "S. Emanuelson"
        },
        "5": {
            "name": "Byggnads AB. Bröderna Bergbäck",
            "location": "Linköping",
            "business": "Byggnadsentreprenörfirma för bostads-och affärshus, industribyggnader m. m.",
            "contact": {
                "phone": [
                    "23731",
                    "26390"
                ],
                "postgiro": "131618"
            },
            "financials": {
                "capital": "40,000 kr",
                "annual_production_value": "1,200,000 kr"
            },
            "foundation_year": 1905,
            "corporation_year": 1938,
            "original_name": "Byggnads AB. Axel Johanson",
            "board": [
                {
                    "name": "Ragnar Bergbäck",
                    "role": "byggnadsing."
                }
            ],
            "director": "R. Bergbäck"
        },
        "6": {
            "name": "Byggnads AB. Contractor",
            "location": "Stockholm",
            "business": "Byggnadsentreprenadfirma med varvsanläggning i Nyköping (Brandholmens varv)",
            "products": "Utför kaj-, bro-, kraftstations-, industri- och bostadsbyggnader, grundläggnings- och sprängningsarbeten, fördjupnings- och sandfyllningsarbeten med sandsugningsfartyg. Tillverkar kasuner, pontoner, pråmar, färjor m. m. av armerad betong",
            "contact": {
                "office": "Kungsg. 28",
                "phone": [
                    "231605"
                ],
                "postgiro": "50653"
            },
            "financials": {
                "capital": "900,000 kr",
                "annual_turnover": "10,000,000 kr"
            },
            "foundation_year": 1910,
            "board": [
                {
                    "name": "Erik Lenander",
                    "role": "disp."
                }
            ]
        }
    }
}