{
    "original": "Textilverken—Thorburn\n\nTextS Iver ken, AB. Svenska,\n\nG ene vad.\n\nSe AB. Svenska Textilverken, Genevad.\n\n\"The General Trading Company AB.,\n\nStockholm.\n\nMetallmanufakturverk. Tillverkar\nfiltermaterial för bil-, fläkt- och\nkompressorindustri samt vävda diskbollar av stål.\n\nKontor: Mästersamuelsg. 3.\nTelegr.-adr.: Getraco, Stockholm. Telefon: 202926\no. 202944. Postgiro: 190013.\n\nAkt.-kap.: 5,000 kr. Antal industriarb.:\n7. — Bolaget grundat 1940.\n\nVerkst. dir.: Richard W. Gefeldt.\n\nFörsäljn.-chef: disp. B. Wahlström.\n\n\"AB. Joh. Thermaenius &amp; Son,\n\nHallsberg.\n\nMek. verkstad i Hallsberg (Örebro l.).\nTillverkar tröskverk. klöverfrönötare.\nrensnings- och sorteringsmaskiner samt\nhalmfläktar och höinjektorer.\n\nTelefon: »Thermaenius». Postgiro:\n77951. Ensamförsälj. för Sverige:\nKullberg &amp; Co. AB., Katrineholm, telefon:\n»Kullbergs», Katrineholm; för utlandet:\nAB. Arvika-Verken, Arvika.\n\nAkt.-kap.: 500.000 kr. Antal\nindustriarb.: 235. Tillv.-värde pr år: 3,000,000 kr.\n— Bolaget, som grundades 1897, äges av\nAB. Arvika-Verken, Arvika.\n\nStyrelse: dir. Mauritz Carlson (ordf.),\ndir. Sven Alwerud, dir. Carl Kihlgren,\ndisp. A. Thermaenius.\n\nVerkst. dir.: Carl Kihlgren.\n\nV erlcstadschef: Enar Finlöw.\n\nKamrer: Gunnar Bjernerup.\n\n\"AB. Thermia-Verken, Arvika.\n\nMek. verkstad och gjuteri. Tillverkar\nvärmeledningspannor,\nvärmeledningsspisar. plåt radiatorer, varmvattenberedare,\nlågtryckspannor samt kokspisar m. m.\nVarumärke: »Thermia».\n\nTelegr.-adr.: Thermiaverken, Arvika.\nTelefon: »Thermia». Postgiro: 9852.\n\nAkt.-kap.: 250,000 kr. Antal\nindustriarb.: 154. Tillv.-värde pr år: 2,500,000 kr.\n— Bolaget grundat 1923.\n\nStyrelse: disp. Gösta Schotte (ordf.),\nkonstnär Tor Hörlin, bankdir. Arne\nJosefson, dir. Sven Kihlberg, dir. A. H.\nTinglöf.\n\nVerkst. dir.: A. H. Tinglöf.\n\n\"Thomsens Fabrikers AB.,\n\nGöteborg.\n\nTillverkar makaroner, sago- och\npotatisgryn samt dextrin, lim och\ntextilhjälpmedel; utför röstning av kaffe.\n\nKontor: A vägen 7 o. 8. Telegr.-adr.:\nThomsen, Göteborg. Telefon: 152372 o.\n159192. Postgiro: 41950.\n\nAkt.-kap.: 150,000 kr. Antal\nindustriarb.: 20. — Firman etabl. 1888, bolag\n1909.\n\nStyrelse: dir. Ewald Thomsen,\nbankdir. Ivar Thomsen, fru S. Thomsen.\nVerkst. dir.: Ewald Thomsen.\n\n\"AB. Thors Kemiska Fabriker,\n\nUlvsunda.\n\nKem.-tekn. fabrik i Ulvsunda,\nStockholm. Tillverkar specialtvättmedel för\nmaskintvätt, kemiska preparat för\ntextilindustrien, tvålflingor, diskpulver,\nrengöringsmedel, bad-, tvätt- och skurtvål\nsamt borr olja. Varunamn: »Pertor an»,\n»Sorol», »Tvätt-Thor», »Thoril» o.\n»Thoralin».\n\nPostadr.: Ulvsunda 1. Telefon: 256808.\nPostgiro: 1397.\n\nAkt.-kap.: 135,000 kr. Arb.-antal: 7.\nTillv.-värde pr år: 800,000 kr. — Bolaget\ngrundat 1921.\n\nStyrelse: disp. Oskar Ekroth (ordf.),\ndir. Ivar Ekroth, dir. C. L. Rydh.\nVerkst. dir.: Ivar Ekroth.\nDisp.: Oskar Ekroth.\n\n\"Thors Konfektions AB., Malmö.\n\nTillverkar damkappor och dräkter.\nKontor: Friisg. 6. Telefon: 18415 o.\n30188. Postgiro: 38343.\n\nAkt.-kap.: 15,000 kr. Antal\nindustriarb.: 80. Tillv.-värde pr år: 1,000 000 kr.\n\n—\tFirman etabl. 1934, bolag 1937.\nStyrelse o. verkst. dir.: Gunnar Thor.\n\nThor, AB. Tekniska Fabriken,\n\nNässjö.\n\nSe AB. Tekniska Fabriken Thor,\nNässjö.\n\nThorburns Söners AB., Uddevalla.\n\nOljeslageri vid Badö, Uddevalla.\nTillverkar kokt och rå linolja, linfrökakor\nm. m.\n\nTelegr.-adr.: Thorburns, Uddevalla.\nTelefon: 10004. Postgiro: 25627.\nAkt.-kap.: 500,000 kr. Arb.-antal: 9.\n\n—\tFirman etabl. 1825, bolag 1886.",
    "structured": {
        "1": {
            "name": "TextS Iver ken, AB. Svenska",
            "location": "Genevad",
            "business": "Metallmanufakturverk",
            "products": "Tillverkar filtermaterial för bil-, fläkt- och kompressorindustri samt vävda diskbollar av stål.",
            "contact": {
                "office": "Mästersamuelsg. 3",
                "phone": [
                    "202926",
                    "202944"
                ],
                "postgiro": "190013"
            },
            "financials": {
                "capital": "5,000 kr",
                "employees": {
                    "industriarb": 7
                },
                "annual_turnover": "Not available",
                "annual_production_value": "Not available"
            },
            "foundation_year": 1940,
            "board": [
                {
                    "name": "Richard W. Gefeldt",
                    "role": "Verkst. dir."
                },
                {
                    "name": "disp. B. Wahlström",
                    "role": "Försäljn.-chef"
                }
            ]
        },
        "2": {
            "name": "AB. Joh. Thermaenius & Son",
            "location": "Hallsberg",
            "business": "Mek. verkstad",
            "products": "Tillverkar tröskverk, klöverfrönötare, rensnings- och sorteringsmaskiner samt halmfläktar och höinjektorer.",
            "contact": {
                "phone": "Thermaenius",
                "postgiro": "77951"
            },
            "financials": {
                "capital": "500,000 kr",
                "employees": {
                    "industriarb": 235
                },
                "annual_turnover": "3,000,000 kr",
                "annual_production_value": "Not available"
            },
            "foundation_year": 1897,
            "owners": [
                "AB. Arvika-Verken, Arvika"
            ],
            "board": [
                {
                    "name": "Mauritz Carlson",
                    "role": "Styrelse: dir."
                },
                {
                    "name": "Sven Alwerud",
                    "role": "Styrelse: dir."
                },
                {
                    "name": "Carl Kihlgren",
                    "role": "Styrelse: dir."
                },
                {
                    "name": "A. Thermaenius",
                    "role": "disp."
                }
            ]
        },
        "3": {
            "name": "AB. Thermia-Verken",
            "location": "Arvika",
            "business": "Mek. verkstad och gjuteri",
            "products": "Tillverkar värmeledningspannor, värmeledningsspisar, plåt radiatorer, varmvattenberedare, lågtryckspannor samt kokspisar m. m.",
            "contact": {
                "telegraph": "Thermiaverken, Arvika",
                "phone": "Thermia",
                "postgiro": "9852"
            },
            "financials": {
                "capital": "250,000 kr",
                "employees": {
                    "industriarb": 154
                },
                "annual_turnover": "2,500,000 kr",
                "annual_production_value": "Not available"
            },
            "foundation_year": 1923,
            "board": [
                {
                    "name": "Gösta Schotte",
                    "role": "Styrelse: disp."
                },
                {
                    "name": "Tor Hörlin",
                    "role": "konstnär"
                },
                {
                    "name": "Arne Josefson",
                    "role": "bankdir."
                },
                {
                    "name": "Sven Kihlberg",
                    "role": "Styrelse: dir."
                },
                {
                    "name": "A. H. Tinglöf",
                    "role": "disp."
                }
            ]
        },
        "4": {
            "name": "Thomsens Fabrikers AB.",
            "location": "Göteborg",
            "business": "Tillverkar makaroner, sago- och potatisgryn samt dextrin, lim och textilhjälpmedel; utför röstning av kaffe.",
            "contact": {
                "office": "A vägen 7 o. 8",
                "telegraph": "Thomsen, Göteborg",
                "phone": [
                    "152372",
                    "159192"
                ],
                "postgiro": "41950"
            },
            "financials": {
                "capital": "150,000 kr",
                "employees": {
                    "industriarb": 20
                },
                "annual_turnover": "Not available",
                "annual_production_value": "Not available"
            },
            "foundation_year": 1888,
            "corporation_year": 1909,
            "board": [
                {
                    "name": "Ewald Thomsen",
                    "role": "Styrelse: dir."
                },
                {
                    "name": "Ivar Thomsen",
                    "role": "bankdir."
                },
                {
                    "name": "S. Thomsen",
                    "role": "Other"
                }
            ]
        },
        "5": {
            "name": "AB. Thors Kemiska Fabriker",
            "location": "Ulvsunda",
            "business": "Kem.-tekn. fabrik",
            "products": "Tillverkar specialtvättmedel för maskintvätt, kemiska preparat för textilindustrien, tvålflingor, diskpulver, rengöringsmedel, bad-, tvätt- och skurtvål samt borr olja.",
            "contact": {
                "postadr": "Ulvsunda 1",
                "phone": "256808",
                "postgiro": "1397"
            },
            "financials": {
                "capital": "135,000 kr",
                "employees": {
                    "industriarb": 7
                },
                "annual_turnover": "800,000 kr",
                "annual_production_value": "Not available"
            },
            "foundation_year": 1921,
            "board": [
                {
                    "name": "Oskar Ekroth",
                    "role": "Styrelse: disp."
                },
                {
                    "name": "Ivar Ekroth",
                    "role": "Verkst. dir."
                },
                {
                    "name": "C. L. Rydh",
                    "role": "Styrelse: dir."
                }
            ]
        },
        "6": {
            "name": "Thors Konfektions AB.",
            "location": "Malmö",
            "business": "Tillverkar damkappor och dräkter",
            "contact": {
                "office": "Friisg. 6",
                "phone": [
                    "18415",
                    "30188"
                ],
                "postgiro": "38343"
            },
            "financials": {
                "capital": "15,000 kr",
                "employees": {
                    "industriarb": 80
                },
                "annual_turnover": "1,000,000 kr",
                "annual_production_value": "Not available"
            },
            "foundation_year": 1934,
            "corporation_year": 1937,
            "director": "Gunnar Thor",
            "managing_director": "Gunnar Thor"
        },
        "7": {
            "name": "Thorburns Söners AB.",
            "location": "Uddevalla",
            "business": "Oljeslageri",
            "products": "Tillverkar kokt och rå linolja, linfrökakor m. m.",
            "contact": {
                "telegraph": "Thorburns, Uddevalla",
                "phone": "10004",
                "postgiro": "25627"
            },
            "financials": {
                "capital": "500,000 kr",
                "employees": {
                    "industriarb": 9
                },
                "annual_turnover": "Not available",
                "annual_production_value": "Not available"
            },
            "foundation_year": 1825,
            "corporation_year": 1886
        }
    }
}