{
    "original": "Vato—Wazo\n\nFirman, etabl. 1904 under namn\nFilipstads Bageri A.-B., nuv. bolag 1934, äges\nav AB. Skellefteå Spisbrödsfabrik.\nBolaget äger AB. Skånska Spisbrödsfabriken,\nKristianstad, AB. Öhmanska Bageriet,\nAB. Kronbröd och AB. A. U. Bergmans\nEnka, samtliga i Stockholm,\nNordstjer-nans Knäckebröd AB., Tannefors,\nOskarshamns Knäckebröd AB., Oskarshamn,\nf. d. AB. Spis- och Knäckebrödsfabriken\nKronan, Sundbyberg, samt AB.\nHärnö-Hoting, Iloting.\n\nStyrelse: konsul Karl Lundström\n(ordf.), dir. Ivar Hultkrantz, fru G.\nLundström.\n\nVerkst. dir.: Karl Lundström\n(Stockholm).\n\nV. verkst. dir. o. disp.: Ivar Hultkrantz.\n\nKamrer: F. Brännström.\n\nInköpschef: G. Waldegren.\n\nÖvering.: D. Karp.\n\nAvd.-ingenjör er: Henry Jaensson o.\nStig Söderquist.\n\nChef f. försäljningscentralen i\nStockholm: dir. Sven Ehrén.\n\nChef f. avd.-kontoret i Ulvsunda:\nkamrer Gunnar öhlin.\n\n\"Vato, Svenska AB., Halmstad.\n\nSe Svenska AB. Vato, Halmstad.\n\nAB. Vattentät Cement, Göteborg.\n\nTillverkar träullsplattor (märke:\n»Ser-ponit») och fasadputs (märke:\n»Serpo-nit-Fasadputs») samt utför förmalning\nav mineralprodukter vid mek. verkstad\noch plattfabrik i Snäcke, Ånimskog\n(Älvsb. l.).\n\nKontor o. ensamförsälj.: Ernström &amp;\nCo. AB., Göteborg, St, Badhusg. 20.\nTelefon: 114648.\n\nAkt.-kap.: 25,000 kr. Antal\nindustriarb.: 80. Tillv.-värde pr år: 900,000 kr.\n— Bolaget grundat 1928.\n\nVerkst. dir.: Albert Hobohm.\n\nFabrikschef: Felix Karlsson.\n\n*AB. Vatten värmare-Kompaniet,\n\nOsby.\n\nTillverkar lågtrycksångpannor\n(märken: »Osby-Pannan», »Osby» o. »Davo»),\nelektriska tvättmaskiner och\nvattenvär-mare vid grov- och tunnplåtslageri i Osby\n(Kristianst. l.).\n\nTelefon: »Osby pannan». Postgiro:\n99553. — Akt.-kap.: 168,200 kr. Antal\nindustriarb.: 45. Tillv.-värde pr år:\n3,000,000 kr. — Firman etabl. 1935, bolag\n1938.\n\nStyrelse: dir. Gösta Darlin,\nförsäljn.-chef John Darlin, ing. Nils Lithner.\n\nVerkst. dir.: Gösta Darlin.\n\n*Wattholma Bruks AB., Stockholm.\n\nMek. verkstad, gjuteri, snickerifabrik\noch såg vid Vattholma (Uppsala l.).\n\nTillverkar brandredskap, brandbilar,\ngymnastikinredningar, värmevagnar,\nfackverkskonstruktioner, spiraltrappor,\ngjut-gods, skottkärror, drickeshoar samt sågade\nträvaror.\n\nHuvudkontor: Stockholm, Schéeleg. 28,\ntelefon: 532258—59 o. 516551.\nFabrikskontor: Vattholma. Telefon: 1. Postgiro:\n90760.\n\nAkt.-kap.: 100,000 kr. Antal\nindustriarb.: 50. Tillv.-värde pr år: 500,000 kr.\n\nBruket anlagt på 1300-talet, nuv. bolag\ngrundat 1941.\n\nStyrelse: ing. Edwin Bergström (ordf.),\nciviling. Erik Bergström, civiling. Knut\nBergström.\n\nVerkst. dir.: Edwin Bergström.\n\nDriftschef: i. d. kapten F. W. Kylberg.\n\nVerkstadsing.: S. Spångberg.\n\n\"Reinh. Watz Eftr., Stockholm.\n\nSnickerifabrik. Tillverkar möbler och\ninredningar.\n\nKontor: Slöjdg. 1. Telefon: 101082.\nPostgiro: 152340. — Antal industriarb.:\n8. Tillv.-värde pr år: 100,000 kr. —\nFirman etabl. 1919.\n\nÄgare o. chef: fabr. Aug. Anderson.\n\nVaxduks AB., Svenska,\n\nSmålands Anneberg.\n\nSe Svenska Vaxduks AB., Smålands\nAnneberg.\n\nAB. Vaxpapper &amp; LIto, Göteborg.\n\nVaxpappers-, pås- och kartongfabrik\nsamt offset-, bok- och litografiskt\ntryckeri. Tillverkar choklad-, karamell- och\nbrödomslag samt utför trycksaker.\n\nKontor: Jakobsdal; postadr.: Göteborg\n5. Telefon: 171080. Postgiro: 41110.\n\nAkt.-kap.: 180,000 kr. Antal\nindustriarb.: 40. Tillv.-värde pr år: 400,000 kr.\n— Firman, etabl. 1910, nuv. bolag 1930.\näges av Bröderna Kanold AB.\n\nVerkst. dir.: Fred. G. Kanold.\n\nDisp.: Raymond Kanold.\n\nWazo-Ver ken AB., Göteborg.\n\nMetallvaru- och bultfabrik. Tillverkar\nsvarvade småartiklar, pressade detaljer,\nverktyg, arbetslampor (märke; »Ledu»)\nsamt symaskinsbelysningar (märke:\n»Wazo 126»).",
    "structured": {
        "1": {
            "name": "Filipstads Bageri A.-B.",
            "location": "Stockholm",
            "business": "Spis- och Knäckebrödsfabrik",
            "contact": {
                "office": "Stockholm",
                "phone": [],
                "postgiro": "",
                "head_office": "",
                "sales_offices": [],
                "telegraph": "",
                "factory_office": "",
                "factory_phone": ""
            },
            "financials": {
                "capital": "",
                "employees": {},
                "annual_turnover": "",
                "annual_production_value": ""
            },
            "foundation_year": 1904,
            "current_name_year": 1934,
            "predecessor": "",
            "original_name": "Filipstads Bageri A.-B.",
            "corporation_year": 1934,
            "board": [
                {
                    "name": "konsul Karl Lundström",
                    "role": "ordförande"
                },
                {
                    "name": "dir. Ivar Hultkrantz",
                    "role": ""
                },
                {
                    "name": "fru G. Lundström",
                    "role": ""
                }
            ],
            "owners": [],
            "director": "Karl Lundström",
            "managing_director": "",
            "sales_manager": "",
            "manager": ""
        },
        "2": {
            "name": "AB. Vato",
            "location": "Halmstad",
            "business": "Träullsplattor och fasadputs",
            "contact": {
                "office": "",
                "phone": [],
                "postgiro": "",
                "head_office": "",
                "sales_offices": [],
                "telegraph": "",
                "factory_office": "",
                "factory_phone": ""
            },
            "financials": {
                "capital": "25,000 kr",
                "employees": {
                    "industriarb": 80
                },
                "annual_turnover": "",
                "annual_production_value": "900,000 kr"
            },
            "foundation_year": 1928,
            "current_name_year": 0,
            "predecessor": "",
            "original_name": "AB. Vato",
            "corporation_year": 0,
            "board": [],
            "owners": [],
            "director": "Albert Hobohm",
            "managing_director": "",
            "sales_manager": "",
            "manager": ""
        },
        "3": {
            "name": "AB. Vattentät Cement",
            "location": "Göteborg",
            "business": "Tillverkning av träullsplattor och fasadputs",
            "contact": {
                "office": "",
                "phone": [],
                "postgiro": "99553",
                "head_office": "",
                "sales_offices": [],
                "telegraph": "",
                "factory_office": "",
                "factory_phone": ""
            },
            "financials": {
                "capital": "168,200 kr",
                "employees": {
                    "industriarb": 45
                },
                "annual_turnover": "",
                "annual_production_value": "3,000,000 kr"
            },
            "foundation_year": 1935,
            "current_name_year": 1938,
            "predecessor": "",
            "original_name": "AB. Vattentät Cement",
            "corporation_year": 1938,
            "board": [
                {
                    "name": "dir. Gösta Darlin",
                    "role": ""
                },
                {
                    "name": "försäljn.-chef John Darlin",
                    "role": ""
                },
                {
                    "name": "ing. Nils Lithner",
                    "role": ""
                }
            ],
            "owners": [],
            "director": "Gösta Darlin",
            "managing_director": "",
            "sales_manager": "",
            "manager": ""
        },
        "4": {
            "name": "Wattholma Bruks AB.",
            "location": "Stockholm",
            "business": "Mekanisk verkstadsindustri",
            "contact": {
                "office": "Stockholm, Schéeleg. 28",
                "phone": [
                    "532258-59",
                    "516551"
                ],
                "postgiro": "90760",
                "head_office": "",
                "sales_offices": [
                    {
                        "location": "Vattholma",
                        "phone": "1"
                    }
                ],
                "telegraph": "",
                "factory_office": "",
                "factory_phone": ""
            },
            "financials": {
                "capital": "100,000 kr",
                "employees": {
                    "industriarb": 50
                },
                "annual_turnover": "",
                "annual_production_value": "500,000 kr"
            },
            "foundation_year": 1941,
            "current_name_year": 0,
            "predecessor": "",
            "original_name": "Wattholma Bruks AB.",
            "corporation_year": 1941,
            "board": [
                {
                    "name": "ing. Edwin Bergström",
                    "role": "ordförande"
                },
                {
                    "name": "civiling. Erik Bergström",
                    "role": ""
                },
                {
                    "name": "civiling. Knut Bergström",
                    "role": ""
                }
            ],
            "owners": [],
            "director": "Edwin Bergström",
            "managing_director": "",
            "sales_manager": "",
            "manager": ""
        },
        "5": {
            "name": "Reinh. Watz Eftr.",
            "location": "Stockholm",
            "business": "Möbeltillverkning och snickeri",
            "contact": {
                "office": "Stockholm, Slöjdg. 1",
                "phone": [
                    "101082"
                ],
                "postgiro": "152340",
                "head_office": "",
                "sales_offices": [],
                "telegraph": "",
                "factory_office": "",
                "factory_phone": ""
            },
            "financials": {
                "capital": "",
                "employees": {
                    "industriarb": 8
                },
                "annual_turnover": "",
                "annual_production_value": "100,000 kr"
            },
            "foundation_year": 1919,
            "current_name_year": 0,
            "predecessor": "",
            "original_name": "Reinh. Watz Eftr.",
            "corporation_year": 0,
            "board": [],
            "owners": [],
            "director": "Aug. Anderson",
            "managing_director": "",
            "sales_manager": "",
            "manager": ""
        },
        "6": {
            "name": "Vaxpapper & LIto",
            "location": "Göteborg",
            "business": "Pappers- och tryckindustri",
            "contact": {
                "office": "Jakobsdal, Göteborg 5",
                "phone": [
                    "171080"
                ],
                "postgiro": "41110",
                "head_office": "",
                "sales_offices": [],
                "telegraph": "",
                "factory_office": "",
                "factory_phone": ""
            },
            "financials": {
                "capital": "180,000 kr",
                "employees": {
                    "industriarb": 40
                },
                "annual_turnover": "",
                "annual_production_value": "400,000 kr"
            },
            "foundation_year": 1910,
            "current_name_year": 1930,
            "predecessor": "",
            "original_name": "Vaxpapper & LIto",
            "corporation_year": 1930,
            "board": [],
            "owners": [],
            "director": "Fred. G. Kanold",
            "managing_director": "",
            "sales_manager": "",
            "manager": ""
        },
        "7": {
            "name": "Wazo-Verken AB.",
            "location": "Göteborg",
            "business": "Metallvaru- och bultfabrik",
            "contact": {
                "office": "",
                "phone": [],
                "postgiro": "",
                "head_office": "",
                "sales_offices": [],
                "telegraph": "",
                "factory_office": "",
                "factory_phone": ""
            },
            "financials": {
                "capital": "",
                "employees": {},
                "annual_turnover": "",
                "annual_production_value": ""
            },
            "foundation_year": 0,
            "current_name_year": 0,
            "predecessor": "",
            "original_name": "Wazo-Verken AB.",
            "corporation_year": 0,
            "board": [],
            "owners": [],
            "director": "",
            "managing_director": "",
            "sales_manager": "",
            "manager": ""
        }
    }
}