{
    "original": "Nordström—Norlin\n\nNordströms Plåtindustri,\n\nHälsingborg.\n\nTillverkar plåtemballage och rostfria\nplåtarbeten.\n\nTelefon: 13872 o. 17272. Postgiro:\n84390. — Antal industriarb.: 25.\nTillv.-värde pr år: 350,000 kr. — Firman etabl.\n1920.\n\nÄgare o. chef er: fabr. Elmer Nordstrom\no. fabr. Nils Nordström.\n\nNordsvensk Reklamservice,\n\nMalung.\n\nSe Norema Industrier, Nordsvensk\nReklamservice, Malung.\n\nAB. Nordsvenska Bruk,\n\nStockholm.\n\nBolaget är försäljnings-,\nbefraktnings-och inköpskontor för Mo och Domsjö AB.,\nStockholm, AB. Robertsfors, Stockholm,\noch AB. Moälvens Träsliperi,\nÖrnsköldsvik.\n\nKontor: Strandvägen 1. Telegr.-adr.:\nNordmills, Stockholm. Telefon: 670050.\nPostgiro: 153964. — Akt.-kap.: 25,000 kr.\n— Bolaget grundat 1931.\n\nStyrelse: dir. Carl Kempe, fil. dr Erik\nKempe, dir. Ragnar Lagergren.\n\nVerkst. dir.: R. Lagergren.\n\n\"Nordsvenska Ventil- &amp; Armatur AB.,\n\nNorrtälje.\n\nSe Armaturfabriken Svecia AB.,\nNorrtälje.\n\nA. K. Nordwall, Göteborg.\n\nKonfektionsfabrik. Tillverkar\ndamunderkläder av charmeuse.\n\nKontor: N. Larmg. 5. Telefon: 135881.\nPostgiro: 42234. Representanter i\nStockholm: H. Frohde, Vasag. 44, telefon:\n119799; A. Kallenberg, Tunnelg. 19 b,\ntelefon: 212224.\n\nAntal industriarb.: 25. Tillv.-värde pr\når: 500,000 kr. — Firman etabl. 1929.\n\nDelägare o. chef: fru Elsa Nordwall.\n\n\"AB. W. H. Nordvall &amp; Co., Sjöbo.\n\nTillverkar trycksaker, kontorsböcker\noch apoteksemballage vid tryckeri och\nbokbinderi i Sjöbo (Malmöh. l.).\n\nTelefon: »Nordvall &amp; Co.». Postgiro:\n6623. —Akt.-kap.: 150,000 kr. Antal\nindustriarb.: 25. Tillv.-värde pr år: 334,000\nkr. — Firman etabl. 1908, bolag 1920.\n\nStyrelse: dir. Albin Nordvall (ordf.)^\ndisp. Olof Johansson, fru Ruth\nJohansson.\n\nVerkst. dir.: Albin Nordvall.\n\nDisp.: Olof Johansson.\n\n\"AB. Nordverk, Skattkärr.\n\nSnickerifabrik och mek. verkstad i\nSkattkärr (Värml. l.). Tillverkar sängary\nschäslonger, ottomaner och dyschateller,\nsoffor samt vägsladdar och\nbeställningsarbeten i järn, stål och plåt.\n\nTelegr.-adr.: Nordverk, Karlstad.\nTelefon: »Nordverk», Skattkärr. Postgiro:\n299556. — Akt.-kap.: 50,000 kr. Antal\nindustriarb.: 80. — Bolaget grundat 1945.\n\nStyrelse; disp. Lennart Ullberg (ordf.),\nfru Gerda Petersson, fru Eva Ullberg.\n\nVerkst. dir. o. disp.: Lennart Ullberg.\n\nKamrer: Theodor Ericson.\n\nVerkstadsing.: Per-Olof östergren.\n\nNorema Industrier, Nordsvensk\nReklamservice, Malung.\n\nSkyltfabrik och mek. verkstad i\nMalung (Kopparb. l.). Tillverkar ljus- och’\naffärsskyltar, bagageräck och -bryggor\nför bilar, verktygslådor, montörvagnar,\nverkstadsbord, -skåp och -stolar,\nklädskåp, backspeglar, skottkärror,\nmagasinskärror, transportvagnar, cykelställ och\n-garage samt motor-, rodd- och segelbåtar.\n\nTelefon: 201. Postgiro: 83892. —\nAntal industriarb.: 35. Tillv.-värde pr år:\n600,000 kr. — Firman etabl. 1932.\n\nÄgare o. chef: fabr. Eric Larsson.\n\n\"Norlings Bryggeri AB., Örebro.\n\nTillverkar maltdrycker, läskedrycker\noch vichyvatten.\n\nTelefon: »Norlings bryggeri». Postgiro:\n75168. — Akt.-kap.: 400,000 kr. Antal\nindustriarb.: 35. Tillv.-värde pr år: 900,006\nkr. — Firman etabl. 1868, bolag 1897.\n\nStyrelse: adv. Per Westling (ordf.),\nfröken Anna Cederborg, disp. Erland\nSkantze.\n\nVerkst. dir.: Erland Skantze.\n\nIvar E. Norlins Skofabrik,\n\nMjällom.\n\nTillverkar arbets- och sportskodon vid\nfabrik i Mjällom, Nordingrå\n(Västernorrl. l.).\n\nTelefon: Nordingrå 42. Postgiro: 96222.\n— Antal industriarb.: 60. Tillv.-värde pr\når: 1,200,000 kr. — Firman etabl. 1932.\n\nÄgare o. chef: fabr. Ivar Norlin.",
    "structured": {
        "firms": [
            {
                "name": "Nordströms Plåtindustri",
                "location": "Hälsingborg",
                "business": "Tillverkar plåtemballage och rostfria plåtarbeten.",
                "contact": {
                    "phone": [
                        "13872",
                        "17272"
                    ],
                    "postgiro": "84390"
                },
                "financials": {
                    "employees": {
                        "industriarb": 25
                    },
                    "annual_turnover": "350,000 kr"
                },
                "foundation_year": 1920,
                "owners": [
                    "fabr. Elmer Nordstrom",
                    "fabr. Nils Nordström"
                ]
            },
            {
                "name": "AB. Nordsvenska Bruk",
                "location": "Stockholm",
                "business": "Försäljnings-, befraktnings- och inköpskontor för Mo och Domsjö AB., Stockholm, AB. Robertsfors, Stockholm, och AB. Moälvens Träsliperi, Örnsköldsvik.",
                "contact": {
                    "office": "Strandvägen 1",
                    "phone": "670050",
                    "telegraph": "Nordmills, Stockholm",
                    "postgiro": "153964"
                },
                "financials": {
                    "capital": "25,000 kr"
                },
                "foundation_year": 1931,
                "board": [
                    {
                        "name": "dir. Carl Kempe",
                        "role": ""
                    },
                    {
                        "name": "fil. dr Erik Kempe",
                        "role": ""
                    },
                    {
                        "name": "dir. Ragnar Lagergren",
                        "role": ""
                    }
                ],
                "manager": "R. Lagergren"
            },
            {
                "name": "AB. W. H. Nordvall & Co.",
                "location": "Sjöbo",
                "business": "Tillverkar trycksaker, kontorsböcker och apoteksemballage vid tryckeri och bokbinderi i Sjöbo (Malmöh. l.).",
                "contact": {
                    "postgiro": "6623"
                },
                "financials": {
                    "capital": "150,000 kr",
                    "employees": {
                        "industriarb": 25
                    },
                    "annual_turnover": "334,000 kr"
                },
                "foundation_year": 1920,
                "owners": [
                    "dir. Albin Nordvall",
                    "disp. Olof Johansson",
                    "fru Ruth Johansson"
                ],
                "manager": "Albin Nordvall",
                "board": [
                    {
                        "name": "disp. Olof Johansson",
                        "role": ""
                    }
                ]
            },
            {
                "name": "AB. Nordverk",
                "location": "Skattkärr",
                "business": "Snickerifabrik och mek. verkstad i Skattkärr (Värml. l.). Tillverkar sängar, schäslonger, ottomaner och dyschateller, soffor samt vägsladdar och beställningsarbeten i järn, stål och plåt.",
                "contact": {
                    "telegraph": "Nordverk, Karlstad",
                    "phone": "Skattkärr",
                    "postgiro": "299556"
                },
                "financials": {
                    "capital": "50,000 kr",
                    "employees": {
                        "industriarb": 80
                    }
                },
                "foundation_year": 1945,
                "board": [
                    {
                        "name": "disp. Lennart Ullberg",
                        "role": "ordf."
                    },
                    {
                        "name": "fru Gerda Petersson",
                        "role": ""
                    },
                    {
                        "name": "fru Eva Ullberg",
                        "role": ""
                    }
                ],
                "manager": "Lennart Ullberg",
                "director": "Per-Olof östergren"
            },
            {
                "name": "AB. Norema Industrier",
                "location": "Malung",
                "business": "Skyltfabrik och mek. verkstad i Malung (Kopparb. l.). Tillverkar ljus- och affärsskyltar, bagageräck och -bryggor för bilar, verktygslådor, montörvagnar, verkstadsbord, -skåp och -stolar, klädskåp, backspeglar, skottkärror, magasinskärror, transportvagnar, cykelställ och -garage samt motor-, rodd- och segelbåtar.",
                "contact": {
                    "phone": "201",
                    "postgiro": "83892"
                },
                "financials": {
                    "employees": {
                        "industriarb": 35
                    },
                    "annual_turnover": "600,000 kr"
                },
                "foundation_year": 1932,
                "owner": "fabr. Eric Larsson"
            },
            {
                "name": "AB. Norlings Bryggeri",
                "location": "Örebro",
                "business": "Tillverkar maltdrycker, läskedrycker och vichyvatten.",
                "contact": {
                    "phone": "Norlings bryggeri",
                    "postgiro": "75168"
                },
                "financials": {
                    "capital": "400,000 kr",
                    "employees": {
                        "industriarb": 35
                    },
                    "annual_turnover": "900,006 kr"
                },
                "foundation_year": 1897,
                "board": [
                    {
                        "name": "adv. Per Westling",
                        "role": "ordf."
                    },
                    {
                        "name": "fröken Anna Cederborg",
                        "role": ""
                    }
                ],
                "manager": "Erland Skantze"
            },
            {
                "name": "Ivar E. Norlins Skofabrik",
                "location": "Mjällom",
                "business": "Tillverkar arbets- och sportskodon vid fabrik i Mjällom, Nordingrå (Västernorrl. l.).",
                "contact": {
                    "phone": "Nordingrå 42",
                    "postgiro": "96222"
                },
                "financials": {
                    "employees": {
                        "industriarb": 60
                    },
                    "annual_turnover": "1,200,000 kr"
                },
                "foundation_year": 1932,
                "owner": "fabr. Ivar Norlin"
            }
        ]
    }
}