{
    "original": "Wästlund-\n\nl—Växlar\n\nAB. Wästlunds Trä, Earlstad.\n\nSågverk och hyvleri i Skattkärr (Värml.\nL) samt hyvleri i Karlstad. Tillverkar\nsågade och hyvlade trävaror. Bolaget\ndriver även handel med byggnadsmateriel.\n\nTelegr.-adr.: Träwästlund, Karlstad.\nTelefon: 15435. Postgiro: 70278.\n\nAkt.-kap.: 100,000 kr. Antal\nindustriarb.: 30. Årstillv.: 800 stds trävaror. —\nFirman etabl. 1907, bolag 1938.\n\nVerkst. dir.: byggm. Olof Wästlund.\n\n\"Västra Klagstorps Snickerifabrik,\n\nVästra Klagstorp.\n\nTillverkar fönster, dörrar, trappor och\nköksinredningar vid fabrik i Västra\nKlagstorp (Malmöh. l.).\n\nTelefon: Malmö 66141. Postgiro:\n12992. — Arb.-antal: 7. Tillv.-värde pr\når: 55,000 kr. — Firman etabl. 1925.\n\nÄgare o. chef: fabr. Orvar Berggren.\n\n\"Vestra Sverige, Beton AB.,\n\nGöteborg.\n\nSe Beton AB. Vestra Sverige,\nGöteborg.\n\n\"Västra Sveriges Textilfabrik AB.,\n\nBorås.\n\nVäveri. Tillverkar gardiner och\ndraperityger samt såsom specialitet\nklänningstyger i konstsilke.\n\nTelegr.-adr.: Västsverige, Borås.\nTelefon: 12238 o. 12256. Postgiro: 90653.\nBepresentant: F. Victorin, Stockholm,\nSvartmang. 6, telefon: 209707.\n\nAkt.-kap.: 100,000 kr. Antal\nindustriarb.: 75. Tillv.-värde pr år: 1,000,000 kr.\n— Firman etabl. 1922, bolag 1923.\n\nStyrelse: fru A. Weber, disp. E. W.\nWeber.\n\nVerkst. dir.: E. W. Weber.\n\nVästsvenska Fläkt AB.,\n\nGöteborg.\n\nMek. verkstad. Tillverkar fläktar och\nventilationsanläggningar,\nvarmluftsbat-terier, luftfilter m. m. Varumärke:\n»VSF».\n\nKontor: Barnhusgatan 16. Telefon:\n192505. Postgiro: 47545. — Akt.-kap.:\n60,000 kr. Antal industriarb.: 34. —\nFirman etabl. 1925, bolag 1938 under namn\nSävedalens Fläkt- &amp; Svetsningsverkstad\nAB., nuv. namn 1943.\n\nDisp.: Per Björk.\n\n63\n\n\"Västsvenska Kylhus AB., Göteborg.\n\nTillverkar konst-is samt utför\ninfrys-ning och lagring av livsmedel m. m.\n\nKontor: Andréeg. Telegr.-adr.:\nCoo-ling, Göteborg. Telefon: 128420 o. 129040.\nPostgiro: 48093.\n\nAkt.-kap.: 1,000,000 kr. Antal\nindustriarb.: 20. — Firman etabl. 1941.\n\nStyrelse: adv. J. Ramberg (ordf.),\nskeppsm. G. Blidberg, dir. I. Busck,\nbankkamrer Ernst Holmberg,\nhöjesteretssag-förer Ejvind Möller, dir. J. O. Möller.\n\nVerkst. dir.: Otis Hanson.\n\n\"AB. Vättervikens Skaftfabrik,\n\nSkänninge.\n\nSe Industri AB. Uhr &amp; Son, Skänninge.\n\n\"Väveri AB. Egnell &amp; C:o.,\n\nNorrköping.\n\nYlleväveri. Tillverkar kostymtyger,\npa-letå- och kapptyger.\n\nTelefon: 27847. Postgiro: 141155.\n\nAkt.-kap.: 25,000 kr. Arb.-antal: 10.\nTillv.-värde pr år: 200,000 kr. — Firman\netabl. 1936, bolag 1937.\n\nStyrelse: fabr. Einar Egnell (ordf.),\nfru M. Egnell, kamrer Ernst Svenson.\n\nVerkst. dir.: Ernst Svenson.\n\nVäxiö, se Wexiö.\n\n\"AB. Växlar och Signaler (Avos),\n\nÖrebro.\n\nMek. verkstad och gjuteri. Tillverkar\nspårväxlar, mekaniska och elektriska\nväg-bommar, ljussignaler, varningsmärken,\nvändskivor, gjutgods m. m.; utför\nväxel-och signalsäkerhetsanläggningar för\njärnvägar samt reparationer av bilar.\nVarumärke: »Avos».\n\nTelegr.-adr.: Avos, Örebro. Telefon:\n19285. Postgiro: 13789.\n\nAkt.-kap.: 400,000 kr. Antal\nindustriarb.: 150. Tillv.-värde pr år: 2,400,000 kr.\n\nBolaget grundat 1915, nuv. namn 1921.\n\nStyrelse: grossh. Mårten E. Liander\n(ordf.), herr Olof Andrén, tullfiskal\nThure Eksandh, disp. Carl-Axel Ericsson,\nmajor Hugo Håkansson, trafikchef\nVilhelm Lindström.\n\nVerkst. dir.: Mårten E.Liander (Sthlm).\n\nDisp.: Carl-Axel Ericsson.\n\nÖvering.: Oskar Hägglund.\n\nKamrer o. inköpschef: Ivar Carlsson.\n\nKassör: Gust. M. Almén.",
    "structured": {
        "1": {
            "name": "Wästlund-l—Växlar AB",
            "location": "Earlstad",
            "business": "Sågverk och hyvleri.",
            "products": "Tillverkar sågade och hyvlade trävaror och driver handel med byggnadsmateriel.",
            "contact": {
                "office": "Skattkärr (Värml. l.) samt hyvleri i Karlstad",
                "phone": [
                    "15435"
                ],
                "postgiro": "70278",
                "head_office": "Träwästlund, Karlstad",
                "telegraph": "Träwästlund, Karlstad"
            },
            "financials": {
                "capital": "100,000 kr",
                "employees": {
                    "industriarb": 30
                },
                "annual_turnover": "800 stds trävaror",
                "foundation_year": 1907,
                "corporation_year": 1938
            },
            "board": [
                {
                    "name": "Olof Wästlund",
                    "role": "Verkst. dir."
                }
            ]
        },
        "2": {
            "name": "Västra Klagstorps Snickerifabrik",
            "location": "Västra Klagstorp",
            "business": "Tillverkar fönster, dörrar, trappor och köksinredningar.",
            "contact": {
                "phone": [
                    "Malmö 66141"
                ],
                "postgiro": "12992"
            },
            "financials": {
                "employees": {
                    "arb.-antal": 7
                },
                "annual_production_value": "55,000 kr",
                "foundation_year": 1925
            },
            "owners": [
                "fabr. Orvar Berggren"
            ]
        },
        "3": {
            "name": "Västra Sveriges Textilfabrik AB.",
            "location": "Borås",
            "business": "Väveri.",
            "products": "Tillverkar gardiner och draperityger samt klänningstyger i konstsilke.",
            "contact": {
                "phone": [
                    "12238",
                    "12256"
                ],
                "postgiro": "90653",
                "sales_offices": [
                    {
                        "location": "Stockholm",
                        "phone": "209707"
                    }
                ]
            },
            "financials": {
                "capital": "100,000 kr",
                "employees": {
                    "industriarb": 75
                },
                "annual_production_value": "1,000,000 kr",
                "foundation_year": 1922,
                "corporation_year": 1923
            },
            "board": [
                {
                    "name": "fru A. Weber",
                    "role": "Styrelse"
                },
                {
                    "name": "disp. E. W. Weber",
                    "role": "Styrelse"
                }
            ],
            "director": "E. W. Weber"
        },
        "4": {
            "name": "Västsvenska Fläkt AB.",
            "location": "Göteborg",
            "business": "Mek. verkstad.",
            "products": "Tillverkar fläktar, ventilationsanläggningar, varmluftsbat-terier, luftfilter m. m.",
            "contact": {
                "office": "Barnhusgatan 16",
                "phone": [
                    "192505"
                ],
                "postgiro": "47545"
            },
            "financials": {
                "capital": "60,000 kr",
                "employees": {
                    "industriarb": 34
                },
                "foundation_year": 1925,
                "corporation_year": 1938
            },
            "managing_director": "Per Björk"
        },
        "5": {
            "name": "Västsvenska Kylhus AB.",
            "location": "Göteborg",
            "business": "Tillverkar konst-is samt utför infrysning och lagring av livsmedel m. m.",
            "contact": {
                "office": "Andréeg",
                "phone": [
                    "128420",
                    "129040"
                ],
                "postgiro": "48093"
            },
            "financials": {
                "capital": "1,000,000 kr",
                "employees": {
                    "industriarb": 20
                },
                "foundation_year": 1941
            },
            "board": [
                {
                    "name": "adv. J. Ramberg",
                    "role": "Styrelse"
                },
                {
                    "name": "skeppsm. G. Blidberg",
                    "role": "Styrelse"
                },
                {
                    "name": "dir. I. Busck",
                    "role": "Styrelse"
                },
                {
                    "name": "bankkamrer Ernst Holmberg",
                    "role": "Styrelse"
                },
                {
                    "name": "höjesteretssagförer Ejvind Möller",
                    "role": "Styrelse"
                },
                {
                    "name": "dir. J. O. Möller",
                    "role": "Styrelse"
                }
            ],
            "director": "Otis Hanson"
        },
        "6": {
            "name": "AB. Vättervikens Skaftfabrik",
            "location": "Skänninge",
            "predecessor": "Industri AB. Uhr & Son",
            "original_name": "Vättervikens Skaftfabrik",
            "foundation_year": 1923
        },
        "7": {
            "name": "Väveri AB. Egnell & C:o.",
            "location": "Norrköping",
            "business": "Ylleväveri.",
            "products": "Tillverkar kostymtyger, paletå- och kapptyger.",
            "contact": {
                "phone": [
                    "27847"
                ],
                "postgiro": "141155"
            },
            "financials": {
                "capital": "25,000 kr",
                "employees": {
                    "arb.-antal": 10
                },
                "annual_production_value": "200,000 kr",
                "foundation_year": 1936,
                "corporation_year": 1937
            },
            "board": [
                {
                    "name": "fabr. Einar Egnell",
                    "role": "Styrelse"
                },
                {
                    "name": "fru M. Egnell",
                    "role": "Styrelse"
                },
                {
                    "name": "kamrer Ernst Svenson",
                    "role": "Styrelse"
                }
            ],
            "director": "Ernst Svenson"
        },
        "8": {
            "name": "AB. Växlar och Signaler (Avos)",
            "location": "Örebro",
            "business": "Mek. verkstad och gjuteri.",
            "products": "Tillverkar spårväxlar, mekaniska och elektriska väg-bommar, ljussignaler, varningsmärken, vändskivor och gjutgods samt utför växel- och signalsäkerhetsanläggningar för järnvägar samt reparationer av bilar.",
            "contact": {
                "phone": [
                    "19285"
                ],
                "postgiro": "13789"
            },
            "financials": {
                "capital": "400,000 kr",
                "employees": {
                    "industriarb": 150
                },
                "annual_production_value": "2,400,000 kr",
                "foundation_year": 1915,
                "corporation_year": 1921
            },
            "board": [
                {
                    "name": "grossh. Mårten E. Liander",
                    "role": "Styrelse"
                },
                {
                    "name": "herr Olof Andrén",
                    "role": "Styrelse"
                },
                {
                    "name": "tullfiskal Thure Eksandh",
                    "role": "Styrelse"
                },
                {
                    "name": "disp. Carl-Axel Ericsson",
                    "role": "Styrelse"
                },
                {
                    "name": "major Hugo Håkansson",
                    "role": "Styrelse"
                },
                {
                    "name": "trafikchef Vilhelm Lindström",
                    "role": "Styrelse"
                }
            ],
            "director": "Mårten E.Liander (Sthlm)",
            "managing_director": "Carl-Axel Ericsson",
            "sales_manager": "Oskar Hägglund",
            "manager": "Ivar Carlsson",
            "cashier": "Gust. M. Almén"
        }
    }
}