{
    "original": "Bandage/fabriken—Barnstrumpor\n\nBandagefabriken, AB. Svenska,\n\nStockholm.\n\nSe AB. Svenska Bandagefabriken,\nStockholm.\n\n*AB. Bandindustri, Kumla.\n\nTillverkar kängsnören, skoband,\ntät-ningslister, vävda konstsilkeband samt\nresårband. Varumärken: »Elita» ocli\n»Svecia».\n\nTelefon: 70820—21. Postgiro: 144754.\nEnsamförsälj.: AB. Lindmark &amp; Nilsson,\nÖrebro, telefon: »Lindmark &amp; Nilsson».\n— Akt.-kap.: 50,000 kr. Antal\nindustriarb.: 110. — Bolaget grundat 1938.\n\nStyrelse: dir. Ivar Lindmark (ordf.),\ndisp. Birger Lindmark, adv. Axel T.\nNilsson.\n\nFabrikschef: Alfred Ortweiler.\n\n*Bara Tegelbruks- &amp; Sågverks AB.,\n\nKlågerup.\n\nTegelbruk i Bara samt sågverk i Torup\n(båda i Malmöh. l.). Tillverkar murtegel,\nbrunntegel, dräneringsrör samt sågade\nträvaror.\n\nKontor: Klågerup. Telefon: 22.\nPostgiro: 88180. — Akt.-kap.: 80,000 kr.\nAntal industriarb.: 22, varav vid tegelbruket\n20. Årstillv. av tegel varor: 2,7 milj. st.\n— Bolaget grundat 1932.\n\nStyrelse o. disp.: Axel Nyberg.\n\n*Bark &amp; Warburgs AB., Göteborg.\n\nBolaget äger Esereds ångsåg, Ätran\n(Hallands l.) samt Buttorps såg,\nSex-drega och Sunnanå såg, Mellerud (båda i\nÄlvsb. l.).\n\nTillverkar sågade och hyvlade trävaror,\nbyggnadssnickerier. lister och lådämnen.\n\nTelegr.-adr.: Barkwaburg, Göteborg.\nTelefon: 222190. Postgiro: 42166. —\nAkt.-kap.: 600,000 kr.\n\nBolaget, grundat 1888, samarbetar med\nAB. Strömman &amp; Larsson, Göteborg (se\ndetta bolag).\n\nStyrelse: dir. R. Hamberg (ordf.),\navd.-chef I. Hamberg, generalkonsul Folke\nJ onsson.\n\nVerkst. dir.: R. Hamberg.\n\n* Barkens Sågverks AB., Vad.\n\nSågverk, hyvleri, trähusfabrik,\nkolugnar och impregneringsverk vid Vad.\nsågverk^ vid Saxehammar, Söderbärke\n(båda i Kopparb. l.) samt sågverk i\nEngelsberg (Västmanl. l.). Tillverkar så-\n\n3\n\ngade och hyvlade trävaror, pappersved^,\nprops och träkol samt monteringsfärdiga;\nträhus. — Bolaget driver även skogsbruk\noch jordbruk samt brädgårdsrörelse i\nStockholm.\n\nKontor: Vad. Telegr.-adr.: Barkens,\nVad. Telefon: Söderbärke, »Barkens\nsågverk». Postgiro: 9678. Ensamförsäljare\nav trähus: AB. Svenska Trähus,\nStockholm, Birger Jarlsg. 27, telefon:\n»Svenska Trähus» (se detta bolag).\n\nAkt.-kap.: 4,000,000 kr. Antal\nindustriarb.: 230. Årstillv.: 8,000 stds sågade o.\n2,000 stds hyvlade trävaror, 5,000 läster\nträkol, 19,000 kbm pappersved o. props\nm. m. — Bolaget grundat 1907.\n\nStyrelse: t. f. revisionssekr. Åke\nThorell (ordf.), disp.-assist. Rolf v.\nHeiden-stam, dir. K.-I. Hising, disp. Axel\nWik-lund.\n\nVerkst. dir.: K.-I. Hising.\n\nDisp.: Axel Wiklund.\n\n*AB. S. Barnekows Tekn. Kem.\nLaboratorium, Malmö.\n\nTillverkar mejeri- och näringspreparat\nsåsom ostlopeextrakt, ostlöpepulver,\nost-löpetabletter, ostmålning, ost-, smör- och\nmargarinfärger, syreväckare,\nschweizer-ostbakterier, roquefortmögel,\njunkettab-letter m. m.\n\nKontor: Industrig. Telegr.-adr.:\nBarne-kow, Malmö. Telefon: 20612, 26993, 22574.\nPostgiro: 14048.\n\nAkt.-kap.: 200,000 kr. Arb.-antal: 5.\nTillv.-värde pr år: 600,000 kr. — Firman\netabl. 1878, bolag 1913.\n\nStyrelse: veterinärdir. Erik\nOsberg-(ordf.), fru G. Fornander, fröken E.\nHallberg, fröken I. Hallberg, fil. lic. C.\nHorn-merberg.\n\nVerkst. dir.: fröken E. Hallberg.\n\nKontorschef: Axel Furustam.\n\nLab.-chef: Knut Häggström.\n\nAB. Barnstrumpor, Malmö.\n\nTillverkar dam-, barn- och herrmössor\nsamt pälsvaror.\n\nKontor: Kärleksg. 1. Telefon: 11513.\nPostgiro: 37795.\n\nAkt.-kap.: 35,000 kr. Antal\nindustriarb.: 24. Tillv.-värde pr år: 350,000 kr.\n— Bolaget grundat 1935.\n\nStyrelse o. verkst. dir.: fabr. Anders.\nBarning.\n\nAB. Barnstrumpor, Malmö.\n\nTillverkar barnstrumpor.\n\nKontor o. ensamförsälj.: AB. Malmö»\nStrumpfabrik, Trelleborgs vägen. Telefon:;\n»Malmö Strumpfabrik».\n\n-K-",
    "structured": {
        "1": {
            "name": "AB. Bandagefabriken",
            "location": "Stockholm",
            "business": "Manufacturing",
            "products": "Kängsnören, skoband, tät-ningslister, vävda konstsilkeband, resårband",
            "contact": {
                "office": "Stockholm",
                "phone": [
                    "70820",
                    "70821"
                ],
                "postgiro": "144754"
            },
            "financials": {
                "capital": "50,000 kr",
                "employees": {
                    "industriarb": 110
                },
                "annual_turnover": "Not available"
            },
            "foundation_year": 1938,
            "board": [
                {
                    "name": "Ivar Lindmark",
                    "role": "Chairman"
                },
                {
                    "name": "Birger Lindmark",
                    "role": "Managing Director"
                },
                {
                    "name": "Axel T. Nilsson",
                    "role": "Advisor"
                }
            ]
        },
        "2": {
            "name": "Bara Tegelbruks- & Sågverks AB.",
            "location": "Klågerup",
            "business": "Manufacturing",
            "products": "Murtegel, brunntegel, dräneringsrör, sågade trävaror",
            "contact": {
                "office": "Klågerup",
                "phone": [
                    "22"
                ],
                "postgiro": "88180"
            },
            "financials": {
                "capital": "80,000 kr",
                "employees": {
                    "industriarb": 22,
                    "tegelbruket": 20
                },
                "annual_turnover": "Not available"
            },
            "foundation_year": 1932,
            "board": [
                {
                    "name": "Axel Nyberg",
                    "role": "Director"
                }
            ]
        },
        "3": {
            "name": "Bark & Warburgs AB.",
            "location": "Göteborg",
            "business": "Manufacturing",
            "products": "Sågade/hyvlade trävaror, byggnadssnickerier, lister, lådämnen",
            "contact": {
                "office": "Göteborg",
                "phone": "222190",
                "postgiro": "42166"
            },
            "financials": {
                "capital": "600,000 kr",
                "employees": {
                    "Not available": 0
                },
                "annual_turnover": "Not available"
            },
            "foundation_year": 1888,
            "board": [
                {
                    "name": "R. Hamberg",
                    "role": "Chairman"
                },
                {
                    "name": "I. Hamberg",
                    "role": "Department Manager"
                },
                {
                    "name": "Folke Jonsson",
                    "role": "Honorary Consul"
                }
            ],
            "director": "R. Hamberg"
        },
        "4": {
            "name": "Barkens Sågverks AB.",
            "location": "Vad",
            "business": "Manufacturing",
            "products": "Sågade/hyvlade trävaror, trähus, träkol, monteringsfärdiga trähus",
            "contact": {
                "office": "Vad",
                "phone": "Not available",
                "postgiro": "9678"
            },
            "financials": {
                "capital": "4,000,000 kr",
                "employees": {
                    "Not available": 230
                },
                "annual_turnover": "Not available"
            },
            "foundation_year": 1907,
            "board": [
                {
                    "name": "Åke Thorell",
                    "role": "Secretary"
                },
                {
                    "name": "Rolf v. Heidenstam",
                    "role": "Assistant Manager"
                },
                {
                    "name": "K.-I. Hising",
                    "role": "Director"
                },
                {
                    "name": "Axel Wiklund",
                    "role": "Manager"
                }
            ],
            "managing_director": "K.-I. Hising"
        },
        "5": {
            "name": "AB. S. Barnekows Tekn. Kem. Laboratorium",
            "location": "Malmö",
            "business": "Manufacturing",
            "products": "Mejeri- and näringspreparat",
            "contact": {
                "office": "Malmö",
                "phone": [
                    "20612",
                    "26993",
                    "22574"
                ],
                "postgiro": "14048"
            },
            "financials": {
                "capital": "200,000 kr",
                "employees": {
                    "Not available": 5
                },
                "annual_turnover": "600,000 kr"
            },
            "foundation_year": 1913,
            "board": [
                {
                    "name": "Erik Osberg",
                    "role": "Veterinary Director"
                },
                {
                    "name": "G. Fornander",
                    "role": "Member"
                },
                {
                    "name": "E. Hallberg",
                    "role": "Member"
                },
                {
                    "name": "I. Hallberg",
                    "role": "Member"
                },
                {
                    "name": "C. Hornmerberg",
                    "role": "Member"
                }
            ],
            "manager": "Axel Furustam",
            "director": "E. Hallberg"
        },
        "6": {
            "name": "AB. Barnstrumpor",
            "location": "Malmö",
            "business": "Manufacturing",
            "products": "Dam-, barn- and herrmössor, pälsvaror",
            "contact": {
                "office": "Malmö",
                "phone": "11513",
                "postgiro": "37795"
            },
            "financials": {
                "capital": "35,000 kr",
                "employees": {
                    "Not available": 24
                },
                "annual_turnover": "350,000 kr"
            },
            "foundation_year": 1935,
            "manager": "Anders Barning"
        }
    }
}