{
    "original": "Luth—Lycksele\n\nAkt.-kap.: 110,000,000 kr. — Bolaget\ngrundat 1890.\n\nSvenska staten och Trafik AB.\nGrängesberg-Oxelösund, Stockholm, äro\nhuvudintressenter i bolaget.\n\nStyrelse: f. d. justitierådet R. Eklund\n(ordf.), generaldir. W. Borgquist, f. d.\nlandshövd. Bernhard Eriksson, fil. dr\nErik Kempe, fil. dr S. Nauckhoff, dir.\nKnut Norlin, överståthållare Torsten\nNothin, dir. Martin Waldenström.\n\nVerkst. dir.: Martin Waldenström.\n\nDirektörer: B. Forsgrén o. P. O.\nWickman.\n\nOruvdir.: Hugo Gårde.\n\nDisponenter: i Kiruna: W.\nFreden-berg; i Malmberget: T. Ekstam; i Luleå:\nF. Westerberg; i Narvik: J. Hoel.\n\n*Luth &amp; Roséns Elektriska AB.y\n\nEskilstuna.\n\nMek. verkstäder i Eskilstuna.\nTillverkar radiatorer och kamrör samt pressade\noch svetsade plåtarbeten.\n\nTelegr.-adr.: Luth, Eskilstuna.\nTelefon: »Luth &amp; Rosén». Postgiro: 3111.\n\nAkt.-kap.: 2,037,500 kr. Antal\nindustriarb.: 165. Tillv.-värde pr år: 3,500,000 kr.\n\nFirman etabl. 1885, bolag 1892,\nombil-dat 1926. Allm. Svenska Elektr. AB.,\nVästerås, är huvudintressent i bolaget.\n\nStyrelse: dir. J. S. Edström (ordf.),\ndir. Thorsten Ericson, dir. Fritz\nLillie-creutz, dir. Hilding Sandberg.\n\nVerkst. dir.: Hilding Sandberg.\n\nVerkstadschef: Eskil Hallin.\n\nInköpschef: Thure Bruneli.\n\nKamrer: Börje Ramqvist.\n\n*AB. Lux, Stockholm.\n\nSe AB. Elektrolux, Stockholm.\n\nLuxor Radio AB., Motala.\n\nTillverkar elektr. grammofoner,\nradioapparater, högtalare och ljudförstärkare\nmed tillbehör samt apparater för elektr.\nstängsel. Varumärken: »Luxor»,\n»Luxor-Radio» o. »Luxor-Briljant».\n\nTelegr.-adr.: Luxor, Motala. Telefon:\n685 o. 1242. Postgiro: 92670. — Akt.-kap.:\n125,400 kr. Antal industriarb.: 300. —\nFirman etabl. 1918, bolag 1934.\n\nStyrelse: verkstadschef Karl\nHolstens-son, försäljn.-chef Lars Holstenson,\ninköpschef Erik Rosenström.\n\nVerkst. dir. o. exportchef: Ernst Hjelm.\n\nFörsäljn.-chef: Lars Holstenson.\n\nInköpschef: Erik Rosenström.\n\nVerkstadschef: Karl Holstensson.\n\n*\tGeorg Luttensee, Göteborg.\n\nSe AB. Förenade Granitindustrier,\nGöteborg.\n\nAB. Lyckes Söners Konserv»\nfabriker, Fiskebäckskil.\n\nKonservfabriker vid Fiskebäckskil\n(Göteb. o. Bohus l.). Tillverkar ansjovis och\nsillkonserver. Varunamn: »Rex-ansjovis»,\n\n»Elless-ansjovis», »Rio-ansjovis» o.\n»Rex-sill».\n\nTelegr.-adr.: Lyckes, Fiskebäckskil.\nTelefon: 15. Postgiro: 31155.\nRepresentanter: i Stockholm: Henning Melin,\nöstermalmstorg 5, telefon: 606725; i\nGöteborg: Uno Lycke, Storängsg. 9, telefon:\n175430.\n\nAkt.-kap.: 210,000 kr. Antal\nindustriarb.: 45. Tillv.-värde pr år: 1,200,000 kr.\n\n—\tFirman etabl. 1878, bolag 1931.\n\nVerkst. dir.: G. Lycke.\n\nKamrer: B. Tambo.\n\n*Lyckeåborgs Bruk, Torskors.\n\nSe Nyby Bruks AB., Nybybruk.\n\n*J. W. Lyckholm &amp; Co., Göteborg.\n\nSe AB. Pripp &amp; Lyckholm, Göteborg.\n\nLycksele Industri AB., Lycksele.\n\nKolningsverk i Lycksele (Västerb. l.).\nTillverkar träkol, kolstyhb, retorttjära av\nbjörk, tjärolja, motorbränsle, metanol,\nacetaldehyd, aceton, etylacetat och div.\nlösningsmedel.\n\nTelegr.-adr.: Träkemi, Lycksele.\nTelefon: 12. Postgiro: 63843.\n\nAkt.-kap.: 500.000 kr. Antal\nindustriarb.: 110. Tillv.-värde pr år: 2,100,000 kr.\n\n—\tBolaget, grundat 1941, äges av\nKooperativa Förbundet.\n\nStyrelse: dir. Albin Johansson (ordf.),\nfil. lic. Mauritz Bonow, dir. Hj.\nDeger-stedt, dir. Hugo Edstam, ing. G. Osvald,\ndir. Ernst Persson.\n\nVerkst. dir. o. platschef: civiling. J. P.\nTrolle.\n\nKamrer: F. J. Creutzer.\n\n*\tLycksele Snickerifabrik, Lycksele.\n\nSnickerifabrik, såg och hyvleri i\nLycksele (Västerb. l.).\n\nTillverkar byggnadssnickerier,\nbutiks-och köksinredningar samt sågade och\nhyvlade trävaror. Firman driver även\nengroshandel med byggnadsmateriel såsom\nträfiberplattor, fanér, glas m. m.\n&gt;*",
    "structured": {
        "1": {
            "name": "Luth—Lycksele",
            "location": "Stockholm",
            "business": "Företagets huvudsakliga verksamhet är ej specificerad",
            "financials": {
                "capital": "110,000,000 kr",
                "employees": {
                    "industriarb.": 0
                }
            },
            "foundation_year": 1890,
            "board": [
                {
                    "name": "f. d. justitierådet R. Eklund",
                    "role": "ordförande"
                },
                {
                    "name": "generaldir. W. Borgquist",
                    "role": null
                },
                {
                    "name": "f. d. landshövd. Bernhard Eriksson",
                    "role": null
                },
                {
                    "name": "fil. dr Erik Kempe",
                    "role": null
                },
                {
                    "name": "fil. dr S. Nauckhoff",
                    "role": null
                },
                {
                    "name": "dir. Knut Norlin",
                    "role": null
                },
                {
                    "name": "överståthållare Torsten Nothin",
                    "role": null
                },
                {
                    "name": "dir. Martin Waldenström",
                    "role": null
                }
            ],
            "owners": [
                "Svenska staten",
                "Trafik AB",
                "Grängesberg-Oxelösund"
            ],
            "director": "Martin Waldenström",
            "managing_director": null,
            "sales_manager": null,
            "manager": null
        },
        "2": {
            "name": "Luth & Roséns Elektriska AB.",
            "location": "Eskilstuna",
            "business": "Tillverkar radiatorer och kamrör samt pressade och svetsade plåtarbeten",
            "contact": {
                "telegraph": "Luth, Eskilstuna",
                "office": null,
                "phone": [
                    "Luth & Rosén"
                ],
                "postgiro": "3111",
                "head_office": null,
                "factory_office": null,
                "factory_phone": null,
                "sales_offices": null
            },
            "financials": {
                "capital": "2,037,500 kr",
                "employees": {
                    "industriarb.": 165
                },
                "annual_turnover": "3,500,000 kr",
                "annual_production_value": "3,500,000 kr"
            },
            "foundation_year": 1885,
            "board": [
                {
                    "name": "dir. J. S. Edström",
                    "role": "ordförande"
                },
                {
                    "name": "dir. Thorsten Ericson",
                    "role": null
                },
                {
                    "name": "dir. Fritz Lilliecreutz",
                    "role": null
                },
                {
                    "name": "dir. Hilding Sandberg",
                    "role": null
                }
            ],
            "owners": [
                "Allm. Svenska Elektr. AB",
                "Västerås"
            ],
            "director": "Hilding Sandberg",
            "managing_director": null,
            "sales_manager": null,
            "manager": null
        },
        "3": {
            "name": "AB. Lux",
            "location": "Stockholm",
            "business": "Se AB. Elektrolux, Stockholm"
        },
        "4": {
            "name": "Luxor Radio AB.",
            "location": "Motala",
            "business": "Tillverkar elektr. grammofoner, radioapparater, högtalare och ljudförstärkare med tillbehör samt apparater för elektr. stängsel",
            "contact": {
                "telegraph": "Luxor, Motala",
                "phone": [
                    "685",
                    "1242"
                ],
                "postgiro": "92670",
                "office": null,
                "factory_office": null,
                "factory_phone": null,
                "head_office": null,
                "sales_offices": null
            },
            "financials": {
                "capital": "125,400 kr",
                "employees": {
                    "industriarb.": 300
                }
            },
            "foundation_year": 1918,
            "board": [
                {
                    "name": "verkstadschef Karl Holstensson",
                    "role": null
                },
                {
                    "name": "försäljn.-chef Lars Holstenson",
                    "role": null
                },
                {
                    "name": "inköpschef Erik Rosenström",
                    "role": null
                }
            ],
            "owners": null,
            "director": null,
            "managing_director": null,
            "sales_manager": null,
            "manager": null
        },
        "5": {
            "name": "AB. Lyckes Söners Konservfabriker",
            "location": "Fiskebäckskil",
            "business": "Tillverkar ansjovis och sillkonserver"
        },
        "6": {
            "name": "Lycksele Industri AB.",
            "location": "Lycksele",
            "business": "Tillverkar träkol, kolstyhb, retorttjära av björk, tjärolja, motorbränsle, metanol, acetaldehyd, aceton, etylacetat och div. lösningsmedel",
            "contact": {
                "telegraph": "Träkemi, Lycksele",
                "phone": [
                    "12"
                ],
                "postgiro": "63843",
                "office": null,
                "factory_office": null,
                "factory_phone": null,
                "head_office": null,
                "sales_offices": null
            },
            "financials": {
                "capital": "500,000 kr",
                "employees": {
                    "industriarb.": 110
                },
                "annual_turnover": "2,100,000 kr",
                "annual_production_value": "2,100,000 kr"
            },
            "foundation_year": 1941,
            "board": [
                {
                    "name": "dir. Albin Johansson",
                    "role": "ordförande"
                },
                {
                    "name": "fil. lic. Mauritz Bonow",
                    "role": null
                },
                {
                    "name": "dir. Hj. Degerstedt",
                    "role": null
                },
                {
                    "name": "dir. Hugo Edstam",
                    "role": null
                },
                {
                    "name": "ing. G. Osvald",
                    "role": null
                },
                {
                    "name": "dir. Ernst Persson",
                    "role": null
                }
            ],
            "owners": [
                "Kooperativa Förbundet"
            ],
            "director": "civiling. J. P. Trolle",
            "managing_director": null,
            "sales_manager": null,
            "manager": null
        },
        "7": {
            "name": "Lycksele Snickerifabrik",
            "location": "Lycksele",
            "business": "Snickerifabrik, såg och hyvleri i Lycksele (Västerb. l.). Tillverkar byggnadssnickerier, butiks-och köksinredningar samt sågade och hyvlade trävaror. Firman driver även engroshandel med byggnadsmateriel såsom träfiberplattor, fanér, glas m. m."
        }
    }
}