{
    "original": "Ljungström—Ljussigna ler\n\nTelefon: 96 o. 396. Postgiro: 73348. —\nAkt-kap.: 100,000 kr. Antal industriarb.:\n100. Tillv.-värde pr år: 1,500,000 kr. —\nFirman etabl. 1925, bolag 1934.\n\nVerkst. dir.: Valter Ljungström.\n\n\"Ljungströms Urfodralfabrik,\n\nTöreboda.\n\nSnickerifabrik i Götene (Skarab. l.).\nTillverkar urfodral samt finare etuier och\nlådor, soffbord, radiobord och -skåp m. m.\n\nFörsäljn.-kontor: Töreboda. Telefon:\n369. Postgiro: 85043. — Antal\nindustriarb.: 20. — Firman etabl. 1924.\n\nÄgare: disp. Ruben Westerstrand o.\ning. James Westerstrand.\n\nChef: James Westerstrand.\n\n\"AB. Ljungströms Angturbin,\n\nStockholm.\n\nExploaterar patent å ångturbiner,\nluft-förvärmare, ångturbinlokomotiv,\ngasturbiner, hydrauliska växlar, kompressorer\nsamt gasrenare.\n\nKontor: Kungsg. 32; postadr.:\nStockholm 3. Telegr.-adr.: Ljungturbin,\nStockholm. Telefon: 231810. Postgiro: 151546.\n\n—\tAkt.-kap.: 1,500,000 kr. — Bolaget\ngrundat 1908.\n\nStyrelse: bankdir. P. Brundell (ordf.),\nbankir Tage Cervin, dir. Gunnar Dalen,\ndir. Carl Kihlgren, civiling. Manne T.\nLindhagen.\n\nVerkst. dir.: Manne T. Lindhagen.\n\n\"Evald Ljungström, Möbelfabrik,\n\nTibro.\n\nTillverkar matsalsmöbler vid fabrik i\nTibro (Skarab. l.).\n\nTelefon: 144. Postgiro: 143367. —\nAntal industriarb.: 11. Tillv.-värde pr år:\n140,000 kr. — Firman etabl. 1921.\n\nÄgare o. chef: fabr. Evald Ljungström.\n\n\"AB. Ljusdals Nya Angbryggeri,\n\nLjusdal.\n\nTillverkar maltdrycker av klass I och\nII samt läskedrycker och mineralvatten\nvid bryggeri i Ljusdal (Gävleb. l.).\n\nTelefon: 1058 o. 1665. Postgiro: 80087.\n\nAkt.-kap.: 200,000 kr. Antal\nindustriarb.: 15. Tillv.-värde pr år: 225,000 kr.\n\n—\tBryggeriet anlagt 1906.\n\nStyrelse: disp. Olof Molin (ordf.), fru\nEllen Molin, kamrer Martin Svensson.\n\nVerkst. dir.: Olof Molin.\n\nKamrer: Martin Svensson.\n\nLjusfallshammars Verkstads AB.,\n\nLjusfallshammar.\n\nTillverkar träbearbetnings- och\nverktygsmaskiner, raka och spiralskurna\nkugghjul samt utför hyvlingsarbeten vid\nmek. verkstad i Ljusfallshammar\n(Östergötl. l.).\n\nTelegr.-adr.: Mekaniska,\nLjusfallshammar. Telefon: 1. Postgiro: 33630. —\nAkt.-kap.: 40,000 kr. Antal industriarb.: 35.\nTillv.-värde pr år: 410,000 kr. —\nVerkstaden anlagd 1896, nuv. bolag grundat\n1940.\n\nVerkst. dir.: ing. Bernh. Stenberg.\n\nDriftsing.: Alf Olsson.\n\nKamrer: Karl-Erik Orrblad.\n\n\"Ljusfors Pappersbruk, Ljusfors.\n\nSe Fiskeby Fabriks AB., Norrköping.\n\n\"Ljusne—Woxna AB., Ljusne.\n\nSågverk, hyvleri, fabrik för\nmonteringsfärdiga trähus, plywood- och\nwall-boardfabriker samt gjuteri, mek.\nverkstad, manufaktursmedja och kättingfabrik\ni Ljusne (Gävleb. l.).\n\nTillverkar sågade och hyvlade trävaror,\nmonteringsfärdiga trähus, plywood,\nwallboard, träkol m. m. samt kätting.\nBolaget idkar jämväl jordbruk och\nskogshantering samt äger elektr.\nvattenkraftstationer i Ljusne och Voxna.\n\nHuvudkontor: Ljusne. Telegr.-adr.:\nEllwiron, Söderhamn. Telefon: Ljusne,\n»Ljusne-Woxna». Postgiro: 28080.\n\nAkt.-kap.: 6,000,000 kr. Antal\nindustriarb.: 1,000. Tillv.-värde pr år: 18,000,000\nkr. Årstillv.: 10,000 stds sågade o.\nhyvlade trävaror, 8,000 ton plywood, 20,000\nton wallboard o. 1,500 ton kätting.\n\nBolaget grundades 1881. Ströms Bruks\nAB. är huvudintressent i bolaget.\n\nStyrelse: vice amiral Fabian Tamm\n(ordf.), disp. Fabian Lundquist, dir.\nC. J. Robbert, disp. C. G. Rothelius.\n\nVerkst. dir. o. disp.: C. G. Rothelius.\n\nFörsäljn.-chef er: för wallboard o.\nplywood: Nils H. Rabenius; export: Bengt\nHamrén; för trävaror: Bertil Hansson.\n\nInköpschef: Helge Lundquist.\n\n(Jfr annons nr 12.)\n\n\"AB. Ljussignaler, Malmö.\n\nElektromek. verkstad. Tillverkar -\ncentralinstrument för fjärrmanövrerad\ndriftkontroll, personsökaranläggningar, reläer,\nmätur, helautomatiska\nbrandalarmanlägg-ningar samt lokaltelefon-, signal- och\ntid-uranläggningar, flygalarmaggregat m. m.\nUtför installationer av neonljusanlägg-",
    "structured": {
        "1": {
            "name": "Ljungströms Urfodralfabrik",
            "location": "Töreboda",
            "business": "Tillverkar urfodral samt finare etuier och lådor, soffbord, radiobord och -skåp m. m.",
            "contact": {
                "office": "Töreboda",
                "phone": [
                    "369"
                ],
                "postgiro": "85043"
            },
            "financials": {
                "capital": "100,000 kr",
                "employees": {
                    "industriarb": 20
                },
                "annual_turnover": "1,500,000 kr"
            },
            "foundation_year": 1924,
            "owner": [
                "disp. Ruben Westerstrand",
                "ing. James Westerstrand"
            ],
            "manager": "James Westerstrand"
        },
        "2": {
            "name": "AB. Ljungströms Angturbin",
            "location": "Stockholm",
            "business": "Exploaterar patent å ångturbiner, luft-förvärmare, ångturbinlokomotiv, gasturbiner, hydrauliska växlar, kompressorer samt gasrenare.",
            "contact": {
                "office": "Kungsg. 32",
                "phone": "231810",
                "postgiro": "151546"
            },
            "financials": {
                "capital": "1,500,000 kr"
            },
            "corporation_year": 1908,
            "board": [
                {
                    "name": "bankdir. P. Brundell",
                    "role": "ordf."
                },
                {
                    "name": "bankir Tage Cervin",
                    "role": ""
                },
                {
                    "name": "dir. Gunnar Dalen",
                    "role": ""
                },
                {
                    "name": "dir. Carl Kihlgren",
                    "role": ""
                },
                {
                    "name": "civiling. Manne T. Lindhagen",
                    "role": ""
                }
            ],
            "director": "Manne T. Lindhagen"
        },
        "3": {
            "name": "Evald Ljungström, Möbelfabrik",
            "location": "Tibro",
            "business": "Tillverkar matsalsmöbler vid fabrik i Tibro (Skarab. l.)",
            "contact": {
                "office": "Tibro",
                "phone": [
                    "144"
                ],
                "postgiro": "143367"
            },
            "financials": {
                "employees": {
                    "industriarb": 11
                },
                "annual_turnover": "140,000 kr"
            },
            "foundation_year": 1921,
            "owner": "fabr. Evald Ljungström",
            "manager": "Evald Ljungström"
        },
        "4": {
            "name": "AB. Ljusdals Nya Angbryggeri",
            "location": "Ljusdal",
            "business": "Tillverkar maltdrycker av klass I och II samt läskedrycker och mineralvatten vid bryggeri i Ljusdal (Gävleb. l.)",
            "contact": {
                "phone": [
                    "1058",
                    "1665"
                ],
                "postgiro": "80087"
            },
            "financials": {
                "capital": "200,000 kr",
                "employees": {
                    "industriarb": 15
                },
                "annual_turnover": "225,000 kr"
            }
        },
        "5": {
            "name": "Ljusfallshammars Verkstads AB.",
            "location": "Ljusfallshammar",
            "business": "Tillverkar träbearbetnings- och verktygsmaskiner, raka och spiralskurna kugghjul samt utför hyvlingsarbeten vid mek. verkstad i Ljusfallshammar (Östergötl. l.)",
            "contact": {
                "telegraph": "Mekaniska, Ljusfallshammar",
                "phone": "1",
                "postgiro": "33630"
            },
            "financials": {
                "capital": "40,000 kr",
                "employees": {
                    "industriarb": 35
                },
                "annual_turnover": "410,000 kr"
            },
            "corporation_year": 1940
        },
        "6": {
            "name": "Ljusne—Woxna AB.",
            "location": "Ljusne",
            "business": "Sågverk, hyvleri, fabrik för monteringsfärdiga trähus, plywood- och wall-boardfabriker samt gjuteri, mek. verkstad, manufaktursmedja och kättingfabrik i Ljusne (Gävleb. l.)",
            "contact": {
                "head_office": "Ljusne",
                "telegraph": "Ellwiron, Söderhamn",
                "phone": "Ljusne, \"Ljusne-Woxna\"",
                "postgiro": "28080"
            },
            "financials": {
                "capital": "6,000,000 kr",
                "employees": {
                    "industriarb": 1000
                },
                "annual_turnover": "18,000,000 kr"
            },
            "corporation_year": 1881,
            "board": [
                {
                    "name": "vice amiral Fabian Tamm",
                    "role": "ordf."
                },
                {
                    "name": "disp. Fabian Lundquist",
                    "role": ""
                },
                {
                    "name": "dir. C. J. Robbert",
                    "role": ""
                },
                {
                    "name": "disp. C. G. Rothelius",
                    "role": ""
                }
            ],
            "director": "C. G. Rothelius",
            "managers": [
                {
                    "role": "wallboard o. plywood",
                    "name": "Nils H. Rabenius"
                },
                {
                    "role": "export",
                    "name": "Bengt Hamrén"
                },
                {
                    "role": "trävaror",
                    "name": "Bertil Hansson"
                }
            ],
            "purchasing_manager": "Helge Lundquist"
        },
        "7": {
            "name": "AB. Ljussignaler",
            "location": "Malmö",
            "business": "Elektromek. verkstad. Tillverkar - centralinstrument för fjärrmanövrerad driftkontroll, personsökaranläggningar, reläer, mätur, helautomatiska brandalarmanläggningar samt lokaltelefon-, signal- och tid-uranläggningar, flygalarmaggregat m. m. Utför installationer av neonljusanlägg-."
        }
    }
}