{
    "original": "Kav e l torp—Ke micano\n\n*Kaveltorps Malmfält, Kopparberg.\n\nSe AB. Svenska Metallverken, Västerås.\n\n*0. Kavli AB., Stockholm.\n\nOst- och konservfabrik. Tillverkar\nmjukost, kaviar, majonnäs, sallader,\nmarmelad och konserver. Varumärken:\n»Pri-mula», »Kavli-ost», »Convalli»,\n»Mayon-na»-majonäs, »Tångkaviar» m. fl.\n\nHuvudkontor: Stockholm,\nBergsundsstrand 31, telegr.-adr.: Kavlikontoret,\nStockholm, telefon: 440655, postgiro:\n157188. Avd.-kontor: Göteborg,\nWahl-bergsg. 2, telefon: 194489; Malmö,\nMalmg. 10, telefon: 21232.\n\nAkt.-kap.: 100,000 kr. Antal\nindustriarb.: 45. Tillv.-värde pr år: 2,000,000 kr.\n\n—\tFabriken anlagd 1940.\n\nStyrelse: fru K. Kavli, dir. O.\nTern-ström.\n\nAdministr.-dir.: dir. Knut Kavli.\n\nVerkst. dir.: C. Ternström.\n\nDisp.: L. Iversen.\n\nKamrer: S. Rosén.\n\nFörsäljn.-chef: P. Broén.\n\nAvd.-chefer: Göteborg: Eric Svensson;\nMalmö: B. Thorell.\n\n*Albert Keifer Strumpfabrik AB.,\n\nMalmö.\n\nTillverkar damstrumpor. Varumärke:\nKeifer.\n\nKontor: Lundavägen 17. Telegr.-adr.:\nStrumpkeifer, Malmö. Telefon: 17135.\nPostgiro: 38592. Representanter i\nStockholm: G. Hellman, Nybrokajen 7,\ntelefon: 203974, o. Lars G. Bohman, Rindög.\n17, telefon: 619422.\n\nAkt.-kap.: 150,000 kr. Antal\nindustriarb.: 70. Tillv.-värde pr år: 1,000,000 kr.\n\n—\tFirman grundad 1934, bolag 1941.\n\nStyrelse o. verkst. dir.: Albert Keifer.\n\nAB. Carl Keijser &amp; Co., Västerås.\n\nMetallvarufabrik. Tillverkar div.\nmetallartiklar samt utför tryckningar och\npressningar i järn, mässing, aluminium,\nkoppar, nysilver och rostfritt stål, ävensom\nförnicklingar; tillverkar snus- och\ntobaksdosor, mjölkmätare (märke: »EOK»),\ntvålskumsapparater (märke: »Aros»)\nm. m.\n\nTelegr.-adr.: Keijsers, Västerås.\nTelefon: 30036. Postgiro: 30058.\n\nAkt.-kap.: 90,000 kr. Antal\nindustriarb.: 30. Tillv.-värde pr år: 250,000 kr.\n\n—\tFirman etabl. 1882, bolag 1914.\n\nVerkst. dir.: Robert Keijser.\n\nKamrer: Edward Keijser.\n\n*AB. Kerna, Stockholm.\n\nBolaget driver kemisk-teknisk\nfabrikation ävensom tillverkning av vissa\nlivsmedel genom Kema-Bolagen\n(Barnängens Tekniska Fabrikers AB., AB. Lars\nMontén, Fruit Products AB., Fabriken\nTomten Alex. Lagerman J:or AB. o. AB.\nEneroth &amp; Co.).\n\nKontor: Sveavägen 42. Telegr.-adr. r\nKemab, Stockholm. Telefon: 112809,\n112826 o. 112848. — Akt.-kap.: 5,500,000\nkr. Sammanlagt antal industriarb. vid\ntill koncernen anslutna industriföretag:\n250. — Bolaget grundat 1929.\n\nStyrelse: fil. dr Harald NordensoB\n(ordf.), disp. Sverre Bröholdt, frih. Louis\nde Geer, grossh. Rob. Ljunglöf, dir. Sven\nSchwartz, disp. Nils Westerdahl.\n\nVerkst. dir.: Rob. Ljunglöf.\n\nKamrer: Hugo Lager.\n\nOmbudsman: jur. kand. Bo Hedberg.\n\n*Kembels Skofabriks AB.,\n\nStockholm.\n\nTillverkar lyx- och promenadskodon»\nSpecialitet: Kembels handmetod. Bolaget\ndriver även ^ detaljhandel genom en egen\nminutaffär i Stockholm.\n\nKontor: Magnus Ladulåsg. 11.\nTelegr.-adr.: Kembels, Stockholm. Telefon:\n411015. Postgiro: 53675.\n\nAkt.-kap.: 1,000,000 kr. Antal\nindustriarb.: 95. Tillv.-värde pr år: 1,500,000 kr.\n\n—\tBolaget, grundat 1906, äges av\nKooperativa Förbundet.\n\nStyrelse: dir. Albin Johansson (ordf.)r\nfil. lic. Mauritz Bonow, dir. Hj.\nDeger-stedt, dir. Hugo Edstam, dir. G. Osvald,,\ndir. Ernst Persson.\n\nDisp.: Mauritz Peterson.\n\n*AB. Kemicano, Stockholm.\n\nKem. tekn. fabriker i Henriksdal\n(Sthlms l.) och i Stjärnhov (SödermanL\n1.). Framställer salter, färger, ytoljor\noch konc. badlösningar för\nrostskyddsändamål, levererar anläggningar för\nrostskydds- och ytbehandlingar samt utför\nytbehandlingar såsom fosfatering och?\nmålning. Bolaget driver även försäljning\nav kemikalier.\n\nKontor: Henriksdal; postadr.:\nStockholm 4. Telefon: 425000 o. 435000.\nPostgiro: 273590.\n\nAkt.-kap.: 75,000 kr. Antal\nindustriarb.: 15. Tillv.-värde pr år: 375,000 kr.\n\n—\tFirman grundad 1932 under namns\nRostskyddsbolaget Lidén &amp; Co., nuv.\nbolag 1943.\n\nStyrelse: civiling. C. F. Lidén, ing. Per\nLidén.\n\nVerkst. dir.: C. F. Lidén",
    "structured": {
        "firms": [
            {
                "name": "Kaveltorps Malmfält, Kopparberg",
                "location": "Västerås",
                "business": "Svenska Metallverken",
                "products": "mjukost, kaviar, majonnäs, sallader, marmelad och konserver",
                "contact": {
                    "office": "Bergsundsstrand 31, Stockholm",
                    "phone": [
                        "440655"
                    ],
                    "postgiro": "157188",
                    "head_office": "Stockholm",
                    "sales_offices": [
                        {
                            "location": "Göteborg",
                            "phone": "194489"
                        },
                        {
                            "location": "Malmö",
                            "phone": "21232"
                        }
                    ]
                },
                "financials": {
                    "capital": "100,000 kr",
                    "employees": {
                        "industriarb": 45
                    },
                    "annual_turnover": "2,000,000 kr",
                    "annual_production_value": "2,000,000 kr"
                },
                "foundation_year": 1940,
                "board": [
                    {
                        "name": "fru K. Kavli",
                        "role": "Styrelse"
                    },
                    {
                        "name": "dir. O. Tern-ström",
                        "role": "Styrelse"
                    }
                ],
                "owner": "Knut Kavli",
                "director": "Knut Kavli",
                "sales_manager": "P. Broén"
            },
            {
                "name": "Albert Keifer Strumpfabrik AB",
                "location": "Malmö",
                "business": "Strumpfabrik",
                "products": "damstrumpor",
                "contact": {
                    "office": "Lundavägen 17",
                    "phone": [
                        "17135"
                    ],
                    "postgiro": "38592"
                },
                "financials": {
                    "capital": "150,000 kr",
                    "employees": {
                        "industriarb": 70
                    },
                    "annual_turnover": "1,000,000 kr",
                    "annual_production_value": "1,000,000 kr"
                },
                "foundation_year": 1934,
                "corporation_year": 1941,
                "board": [
                    {
                        "name": "Albert Keifer",
                        "role": "Styrelse o. verkst. dir."
                    }
                ]
            },
            {
                "name": "AB. Carl Keijser & Co.",
                "location": "Västerås",
                "business": "Metallvarufabrik",
                "contact": {
                    "office": "Västerås",
                    "phone": "30036",
                    "postgiro": "30058"
                },
                "financials": {
                    "capital": "90,000 kr",
                    "employees": {
                        "industriarb": 30
                    },
                    "annual_turnover": "250,000 kr",
                    "annual_production_value": "250,000 kr"
                },
                "foundation_year": 1882,
                "corporation_year": 1914,
                "director": "Robert Keijser",
                "manager": "Edward Keijser"
            },
            {
                "name": "AB. Kerna",
                "location": "Stockholm",
                "business": "kemisk-teknisk fabrikation",
                "contact": {
                    "office": "Sveavägen 42",
                    "phone": [
                        "112809",
                        "112826",
                        "112848"
                    ]
                },
                "financials": {
                    "capital": "5,500,000 kr",
                    "employees": {
                        "total_industriarb": 250
                    }
                },
                "foundation_year": 1929,
                "board": [
                    {
                        "name": "fil. dr Harald NordensoB",
                        "role": "Styrelse"
                    },
                    {
                        "name": "disp. Sverre Bröholdt",
                        "role": "Styrelse"
                    }
                ],
                "director": "Rob. Ljunglöf"
            },
            {
                "name": "Kembels Skofabriks AB",
                "location": "Stockholm",
                "business": "Skofabrik",
                "products": "lyx- och promenadskor",
                "contact": {
                    "office": "Magnus Ladulåsg. 11",
                    "phone": [
                        "411015"
                    ],
                    "postgiro": "53675"
                },
                "financials": {
                    "capital": "1,000,000 kr",
                    "employees": {
                        "industriarb": 95
                    },
                    "annual_turnover": "1,500,000 kr",
                    "annual_production_value": "1,500,000 kr"
                },
                "foundation_year": 1906,
                "owner": "Kooperativa Förbundet"
            },
            {
                "name": "AB. Kemicano",
                "location": "Stockholm",
                "business": "Kem. tekn. fabriker",
                "products": "salter, färger, ytoljor och konc. badlösningar för rostskyddsändamål",
                "contact": {
                    "office": "Henriksdal",
                    "phone": [
                        "425000",
                        "435000"
                    ],
                    "postgiro": "273590"
                },
                "financials": {
                    "capital": "75,000 kr",
                    "employees": {
                        "industriarb": 15
                    },
                    "annual_turnover": "375,000 kr",
                    "annual_production_value": "375,000 kr"
                },
                "foundation_year": 1932,
                "original_name": "Rostskyddsbolaget Lidén & Co.",
                "board": [
                    {
                        "name": "civiling. C. F. Lidén",
                        "role": "Styrelse"
                    },
                    {
                        "name": "ing. Per Lidén",
                        "role": "Verkst. dir."
                    }
                ]
            }
        ]
    }
}