{
    "original": "Ny gcirde—Nykvarn\n\nStyrelse: disp. Evert Wijkander (ordf.),\ndir. Einar Glimstedt, adv. Fred.\nHolmgren, dir. Manfred Kjellander,\nkonter-amiral Erik P:son Wetter.\n\nVerTcst. dir.: M. Kjellander.\n\nEkonomichef: kamrer Gösta Månsson.\n\nFörsäljn.-chef: övering. Bengt Sjölin.\n\n*Nygärde Tegelbruks AB., Kalmar.\n\nTegelbruk i Smedby (Kalmar l.).\nTillverkar murtegel, skorstenstegel samt\ndräneringsrör.\n\nHuvudkontor: Kalmar. Telegr.-adr.:\nNy gärde, Kalmar. Telefon: 452 o. 1204.\nBrukskontor: Smedby, telefon: 15.\n\nAkt.-kap.: 300,000 kr. Antal\nindustriarb.: 45. Årstillv.: 5,5 milj. st. tegelvaror.\n\nFirman, etabl. 1889, är huvudintressent\ni AB. Berga Tegelbruk, Kalmar.\n\nStyrelse: dir. Allan Jeansson (ordf.),\ntegelmäst. Björn Jeansson, kassör Sigfrid\nJeansson.\n\nVerkst. dir.: Allan Jeansson.\n\nTegelmäst.: Björn Jeansson.\n\n*AB. Nyhammars Bruk,\n\nNyhammar.\n\nJärnverk med mekanisk verkstad och\ngjuteri, manufaktursmedje, elektromek.\nverkstad, sågverk och snickeriverkstad vid\nNyhammar (Kopparb. l.).\n\n_ Tillverkar maskiner för gruvor och\nanrikningsverk, plåtarbeten,\nfackverkskonstruktioner, gjutgods, elektriska\ntrefasmotorer samt sågade och hyvlade\nträvaror. Bolaget idkar jämväl jord- och\nskogsbruk.\n\nTelegr.-adr.: Nyhammarsbruk,\nLudvika. Telefon: Grangärde 1 o. 35.\nPostgiro: 24621.\n\nAkt.-kap.: 300,000 kr. Antal\nindustriarb.: 100. Tillv.-värde pr år: 1,350,000 kr.\n— Bruket anlagt på 1680-talet, nuv.\nbolag 1929.\n\nStyrelse: disp. J. Kempe (ordf.), disp.\nAtle Lundström, disp. Anton P. Ohlson.\n\nVerkst. dir.: Anton P. Ohlson.\n\nIng.: H. Wåhlstrand.\n\n(Jfr annons nr 52.)\n\nNyhammars Träullsfabriks AB.,\n\nTuna Hästberg.\n\nTillverkar träull vid fabrik i\nNyhammar (Kopparb. l.).\n\nKontor: Tuna Hästberg. Telefon: 4.\nPostgiro: 177875. — Akt.-kap.: 20,000 kr.\nAntal industriarb.: 14. Tillv.-värde pr år:\n240,000 kr. — Bolaget grundat 1931.\n\nDisp.: Helmer Hellander.\n\n*Nyhamns AB., Sundsvall.\n\nSulfitfabrik och sulfitspritfabrik vid\nNyhamn, Essvik (Västernorrl. l.). Driftem\nf. n. nedlagd.\n\nHuvudkontor: Sundsvall (se\nSundsvallsbolagen).\n\nAkt.-kap.: 2,502,500 kr. — Bolaget\ngrundat 1907 under namn Nyhamns\nCellulosa AB., nuv. namn 1939.\nAktiemajoriteten i bolaget innehaves av Svenska\nCellulosa AB.\n\nStyrelse: dir. Torsten Hérnod (ordf.)»\ndir. Gust. Göranson, dir. Gust. J. Sahlin,,\nbankdir. P. F. Wåhlin.\n\nVerkst. dir.: Gust. Göranson.\n\nDriftsing.: L. B. Schibbye.\n\nAB. Ny hems Mek. Verkstad,\n\nHalmstad.\n\nTillverkar velocipeddetaljer såsom\nkedjeskydd, styrstänger och styrstammar,\nsadelstolpar, packningshållare, barnsadlar\nm. m.; utför förnickling och förtkromning.-\n\nTelegr.-adr.: Erex, Halmstad. Telefon:\n1270—71 o. 1063. Postgiro: 30534.\n\nAkt.-kap.: 53,000 kr. Antal\nindustriarb.: 100. Tillv.-värde pr år: 1,600,000 kr.\n— Firman etabl. 1919, bolag 1934.\n\nStyrelse o. verkst. dir.: fru A. Rex.\n\nDisp.: Stig Rex.\n\nDriftsing.: Sam Thurén.\n\n* Adolf Nyhlén AB., Karlstad.\n\nSe Karlstads Tagelspinneri, Adolf\nNyhlén AB., Karlstad.\n\n*Nykroppa Järnverk, Nykroppa.\n\nSe Uddeholms AB., Uddeholm.\n\n*AB. Nykvarns Bruk, Nykvarn.\n\nPappersbruk och kartongfabrik i\nNykvarn (Sthlms l.). Tillverkar tryck-,,\nskriv- och omslagspapper, tapetpapper,\nkartong m. m.\n\nTelegr.-adr.: Nykvarn,\nSödertälje-Telefon: Turinge 1, 2 o. 20. Postgiro:\n15284. Nederlagskontor: Stockholm,.\nTegnérg. 15, telefon: 231420.\n\nAkt.-kap.: 800,000 kr. Antal\nindustriarb.: 200. Årstillv.: 18,000 ton papper o.\nkartong. — Bruket anlagt 1847, nuv.\nbolag grundat 1924.\n\nStyrelse: godsäg. Anders Bergengren\n(ordf.), dir. Gösta Du Rietz, civiling. G.\nEckerbom, civiling. S. Lindahl,\nbank-ombudsm. Eric Paulson.\n\nVerkst. dir.: G. Eckerbom (Sthlm).\n\nDisp.: civiling. E. A. Ernstler.\n\nFörsäljn.-chef: Einar österberg.",
    "structured": {
        "firms": [
            {
                "name": "Ny gcirde—Nykvarn",
                "location": "Nykvarn",
                "products": "Pappersbruk och kartongfabrik i Nykvarn (Sthlms l.). Tillverkar tryck-, skriv- och omslagspapper, tapetpapper, kartong m. m.",
                "contact": {
                    "telegraph": "Nykvarn, Södertälje",
                    "phone": [
                        "Turinge 1",
                        "2",
                        "20"
                    ],
                    "postgiro": "15284",
                    "head_office": "Stockholm, Tegnérg. 15",
                    "sales_offices": [
                        {
                            "location": "Stockholm",
                            "phone": "231420"
                        }
                    ]
                },
                "financials": {
                    "capital": "800,000 kr",
                    "employees": {
                        "industriarb": 200
                    }
                },
                "foundation_year": 1924,
                "board": [
                    {
                        "name": "godsäg. Anders Bergengren",
                        "role": "ordf."
                    },
                    {
                        "name": "dir. Gösta Du Rietz",
                        "role": null
                    },
                    {
                        "name": "civiling. G. Eckerbom",
                        "role": null
                    },
                    {
                        "name": "civiling. S. Lindahl",
                        "role": null
                    },
                    {
                        "name": "bank-ombudsm. Eric Paulson",
                        "role": null
                    }
                ]
            },
            {
                "name": "Nyhammars Bruk",
                "location": "Nyhammar",
                "products": "Järnverk med mekanisk verkstad och gjuteri, manufaktursmedje, elektromek. verkstad, sågverk och snickeriverkstad vid Nyhammar (Kopparb. l.). Tillverkar maskiner för gruvor och anrikningsverk, plåtarbeten, fackverkskonstruktioner, gjutgods, elektriska trefasmotorer samt sågade och hyvlade trävaror.",
                "contact": {
                    "telegraph": "Nyhammarsbruk, Ludvika",
                    "phone": [
                        "Grangärde 1",
                        "35"
                    ],
                    "postgiro": "24621"
                },
                "financials": {
                    "capital": "300,000 kr",
                    "employees": {
                        "industriarb": 100
                    }
                },
                "corporation_year": 1929,
                "board": [
                    {
                        "name": "disp. J. Kempe",
                        "role": "ordf."
                    },
                    {
                        "name": "disp. Atle Lundström",
                        "role": null
                    },
                    {
                        "name": "disp. Anton P. Ohlson",
                        "role": null
                    }
                ]
            },
            {
                "name": "Nyhammars Träullsfabriks AB",
                "location": "Tuna Hästberg",
                "products": "Tillverkar träull vid fabrik i Nyhammar (Kopparb. l.)",
                "contact": {
                    "phone": "4",
                    "postgiro": "177875"
                },
                "financials": {
                    "capital": "20,000 kr",
                    "employees": {
                        "industriarb": 14
                    }
                },
                "foundation_year": 1931,
                "board": [
                    {
                        "name": "Disp. Helmer Hellander",
                        "role": null
                    }
                ]
            },
            {
                "name": "Nyhamns AB.",
                "location": "Sundsvall",
                "products": "Sulfitfabrik och sulfitspritfabrik vid Nyhamn, Essvik (Västernorrl. l.). Driftem f. n. nedlagd.",
                "contact": {
                    "head_office": "Sundsvall",
                    "phone": null
                },
                "financials": {
                    "capital": "2,502,500 kr"
                },
                "corporation_year": 1939,
                "board": [
                    {
                        "name": "dir. Torsten Hérnod",
                        "role": "ordf."
                    },
                    {
                        "name": "dir. Gust. Göranson",
                        "role": null
                    },
                    {
                        "name": "dir. Gust. J. Sahlin",
                        "role": null
                    },
                    {
                        "name": "bankdir. P. F. Wåhlin",
                        "role": null
                    }
                ]
            },
            {
                "name": "Ny hems Mek. Verkstad",
                "location": "Halmstad",
                "products": "Tillverkar velocipeddetaljer såsom kedjeskydd, styrstänger och styrstammar, sadelstolpar, packningshållare, barnsadlar m. m.; utför förnickling och förtkromning.",
                "contact": {
                    "telegraph": "Erex, Halmstad",
                    "phone": [
                        "1270—71",
                        "1063"
                    ],
                    "postgiro": "30534"
                },
                "financials": {
                    "capital": "53,000 kr",
                    "employees": {
                        "industriarb": 100
                    }
                },
                "corporation_year": 1934,
                "board": [
                    {
                        "name": "fru A. Rex",
                        "role": "verkst. dir."
                    },
                    {
                        "name": "Stig Rex",
                        "role": "disp."
                    },
                    {
                        "name": "Sam Thurén",
                        "role": "driftsing."
                    }
                ]
            }
        ]
    }
}