{
    "original": "Globus—Gnosjö\n\npressglas, mjölkflaskor, flaskor och\nkonservburkar, sylt-, honungs- och\nkaramellburkar, slipat servisglas och kristallglas\nm. m. Varumärke: »Glimma».\n\nTelegr.-adr.: Glimmaglas, Glimåkra.\nTelefon: 64, 6 o. 106. Postgiro: 36192.\nRepr. i Stockholm: AB. Gustaf Landin,\nKarlbergsvägen 42, telefon: 335534.\n\nAkt.-kap.: 125,000 kr. Antal\nindustriarb.: 100. Tillv.-värde pr år: 800,000 kr.\n— Bolaget grundat 1918.\n\nStyrelse: dir. Oscar Carlström (ordf.),\nhyttm. Olof Carlström, driftschef Sten\nCarlström, rektor Alb. E. Christiansson,\njuvelerare N. C. Christiansson.\n\nVerkst. dir. o. disp.: Oscar Carlström.\n\nDriftschef: Sten Carlström.\n\n*Globusy AB. Svenska\nKonservfabriken, Stockholm.\n\nSe AB. Svenska Konservfabriken\nGlo-bus, Stockholm.\n\nClory, Elektr. Apparatfabriken,\n\nMariefred.\n\nSe Elektr. Apparatfabriken Glory,\nMariefred.\n\n*Glumslövs Tegelbruks AB.,\n\nGlumslöv.\n\nTillverkar murtegel och månghålstegel\nvid tegelbruk i Glumslöv samt fasadtegel\nvid tegelbruk i Tjustorp, Skabersjö (båda\ni Malmöh. l.).\n\nTelefon: Glumslöv 70 o. Malmö 447094\no. 447114. Postgiro: 85083.\nEnsamför-sälj.: Bröderna Edstrand AB., Malmö,\nIndustrihamnen, telefon: »Bröderna\nEd-strand».\n\nAkt.-kap.: 500,000 kr. Antal\nindustriarb.: 50. Årstillv.: 13 milj. st. tegel. —\nBolaget grundat 1930 efter övertagandet\nav Sundviks Tegelbruk.\n\nStyrelse: konsul Knut Edstrand\n(ordf.), bruksdisp. Carl Gustav Edstrand,\nbergsing. Gunnar Edstrand.\n\nDisp.: Anders Sintring.\n\nClödlampfabriken Birka AB.,\n\nStockholm.\n\nTillverkar glödlampor.\nKontor: Odeng. 71. Telegr.-adr.:\nBirka-lampan, Stockholm. Telefon: 335185.\nPostgiro: 3715.\n\nAkt.-kap.: 80,000 kr. Antal\nindustriarb.: 20. Tillv.-värde pr år: 165,000 kr.\n— Firman etabl. 1909, bolag 1926.\n\n1\n\nStyrelse: fil, dr Axel O. Appelberg\n(ordf.), kamrer G. Remigius.\n\nVerkst. dir.: A. O. Appelberg.\n\nKamrer: G. Remigius.\n\n*Cnesta Bryggeri AB., Gnesta.\n\nTillverkar maltdryker av klass I och\nII samt kol sy rade läskedrycker och\nmineralvatten vid bryggeri i Gnesta\n(Södermanl. l.).\n\nTelefon: 34. Postgiro: 25152. —\nAkt.-kap.: 150,000 kr. Arb.-antal: 12. —\nFirman etabl. 1898, bolag 1935.\n\nStyrelse: disp. Sten 0:son Berggren\n(ordf.), fru A. L. Berggren, fru I.\nKjel-lin, apot. Ingvar Kjellin.\n\nVerkst. dir. o. disp.: S. O:son\nBerggren.\n\nGnosjö Armaturfabrik, Gnosjö.\n\nTillverkar värmelednings- och annan\narmatur av järn och metall vid fabrik i\nGnosjö (Jönköp. l.).\n\nTelefon: 114. Postgiro: 173823. —\nArb.-antal: 10. Tillv.-värde pr år: 65,000\nkr. — Firman etabl. 1932.\n\nÄgare o. chefer: fabr. Bror Hyltén o.\nfabr. Bertil Hyltén.\n\nGnosjö Celbgjuteri, A. Jacobson A\nCo., Gnosjö.\n\nMetallvarufabrik och förnicklingsverk i\nGnosjö (Jönköp. l.). Tillverkar\nbyggnadsbeslag m m.\n\nTelefon: 14. Postgiro: 72104.\n—Arb.-antal: 10. Tillv.-värde pr år: 60,000 kr.\n— Firman etabl. 1906.\n\nÄgare: fru W. Jacobson, fabr. August\nPettersson o. fabr. Johannes Pettersson.\n\nChef: Carl Jacobson.\n\nGnosjö Portföljfabrik, Paul Svensson\n&amp; Co., Gnosjö.\n\nTillverkar portmonnäer och plånböcker\nav skinn vid fabrik i Gnosjö (Jönköp. l.).\n\nTelefon: 47. Postgiro: 37201. —\nAntal industriarb.: 15. Tillv.-värde pr år:\n150,000 kr. — Firman, etabl. 1924, äger\nGnosjö Läderindustri.\n\nDisp.: Paul Svensson.\n\nGnosjö Trämanufaktur, Gnosjö.\n\nTillverkar rockhängare vid fabrik i\nGnosjö (Jönköp. l.).\n\nTelefon: 55 o. 78. Antal industriarb.:\n12. — Firman etabl. 1925 under namn\nFingal Anderssons Träförädlingsfabrik,\nnuv. namn 1946.\n\nÄgare o. chef: fabr. Fingal Sigblad.\n\n■fr",
    "structured": {
        "1": {
            "name": "Globus—Gnosjö",
            "location": "Gnosjö",
            "business": "pressglas, mjölkflaskor, flaskor och konservburkar, sylt-, honungs- och karamellburkar, slipat servisglas och kristallglas m. m.",
            "products": "Varumärke: »Glimma».",
            "contact": {
                "office": "Glimmaglas, Glimåkra",
                "phone": [
                    "64",
                    "6",
                    "106"
                ],
                "postgiro": "36192",
                "head_office": "AB. Gustaf Landin, Karlbergsvägen 42",
                "sales_offices": [
                    {
                        "location": "Stockholm",
                        "phone": "335534"
                    }
                ]
            },
            "financials": {
                "capital": "125,000 kr",
                "employees": {
                    "industriarb": 100
                },
                "annual_turnover": "800,000 kr",
                "annual_production_value": "800,000 kr"
            },
            "foundation_year": 1918,
            "board": [
                {
                    "name": "Oscar Carlström",
                    "role": "dir. (ordf.)"
                },
                {
                    "name": "Olof Carlström",
                    "role": "hyttm."
                },
                {
                    "name": "Sten Carlström",
                    "role": "driftschef"
                },
                {
                    "name": "Alb. E. Christiansson",
                    "role": "rektor"
                },
                {
                    "name": "N. C. Christiansson",
                    "role": "juvelerare"
                }
            ],
            "director": "Oscar Carlström",
            "manager": "Oscar Carlström",
            "sales_manager": "Sten Carlström"
        },
        "2": {
            "name": "Glumslövs Tegelbruks AB.",
            "location": "Glumslöv",
            "business": "Tillverkar murtegel och månghålstegel vid tegelbruk i Glumslöv samt fasadtegel vid tegelbruk i Tjustorp, Skabersjö (båda i Malmöh. l.).",
            "contact": {
                "phone": [
                    "Glumslöv 70",
                    "Malmö 447094",
                    "Malmö 447114"
                ],
                "postgiro": "85083",
                "sales_offices": [
                    {
                        "location": "Malmö",
                        "phone": "Bröderna Edstrand AB., Industrihamnen"
                    }
                ]
            },
            "financials": {
                "capital": "500,000 kr",
                "employees": {
                    "industriarb": 50
                },
                "annual_production_value": "13 milj. st. tegel"
            },
            "foundation_year": 1930,
            "board": [
                {
                    "name": "Knut Edstrand",
                    "role": "konsul (ordf.)"
                },
                {
                    "name": "Carl Gustav Edstrand",
                    "role": "bruksdisp."
                },
                {
                    "name": "Gunnar Edstrand",
                    "role": "bergsing."
                },
                {
                    "name": "Anders Sintring",
                    "role": "Disp."
                }
            ]
        },
        "3": {
            "name": "Clory, Elektr. Apparatfabriken",
            "location": "Mariefred",
            "business": "Se Elektr. Apparatfabriken Glory, Mariefred."
        },
        "4": {
            "name": "Clödlampfabriken Birka AB.",
            "location": "Stockholm",
            "business": "Tillverkar glödlampor."
        },
        "5": {
            "name": "Cnesta Bryggeri AB.",
            "location": "Gnesta",
            "business": "Tillverkar maltdryker av klass I och II samt kol sy rade läskedrycker och mineralvatten vid bryggeri i Gnesta (Södermanl. l.).",
            "contact": {
                "phone": [
                    "34"
                ],
                "postgiro": "25152"
            },
            "financials": {
                "capital": "150,000 kr",
                "employees": {
                    "Arb.-antal": 12
                }
            },
            "foundation_year": 1898
        },
        "6": {
            "name": "Gnosjö Armaturfabrik",
            "location": "Gnosjö",
            "business": "Tillverkar värmelednings- och annan armatur av järn och metall vid fabrik i Gnosjö (Jönköp. l.).",
            "contact": {
                "phone": [
                    "114"
                ],
                "postgiro": "173823"
            },
            "financials": {
                "employees": {
                    "Arb.-antal": 10
                },
                "annual_production_value": "65,000 kr"
            },
            "foundation_year": 1932
        },
        "7": {
            "name": "Gnosjö Celbgjuteri, A. Jacobson A Co.",
            "location": "Gnosjö",
            "business": "Metallvarufabrik och förnicklingsverk i Gnosjö.",
            "contact": {
                "phone": [
                    "14"
                ],
                "postgiro": "72104"
            },
            "financials": {
                "employees": {
                    "Arb.-antal": 10
                },
                "annual_production_value": "60,000 kr"
            },
            "foundation_year": 1906
        },
        "8": {
            "name": "Gnosjö Portföljfabrik, Paul Svensson & Co.",
            "location": "Gnosjö",
            "business": "Tillverkar portmonnäer och plånböcker av skinn vid fabrik i Gnosjö (Jönköp. l.).",
            "contact": {
                "phone": [
                    "47"
                ],
                "postgiro": "37201"
            },
            "financials": {
                "employees": {
                    "Antal industriarb.": 15
                },
                "annual_production_value": "150,000 kr"
            },
            "foundation_year": 1924
        },
        "9": {
            "name": "Gnosjö Trämanufaktur",
            "location": "Gnosjö",
            "business": "Tillverkar rockhängare vid fabrik i Gnosjö (Jönköp. l.).",
            "contact": {
                "phone": [
                    "55",
                    "78"
                ]
            },
            "financials": {
                "employees": {
                    "Antal industriarb.": 12
                }
            },
            "foundation_year": 1925
        }
    }
}