{
    "original": "Waplan— Wardell\n\nWaplans Mekaniska Verkstads AB.,\n\nNälden.\n\nMek. verkstad och gjuteri i Vaplan,\nNälden (Jämtl. l.). Tillverkar\nvattenturbiner med regulatorer, maskiner för\nträ-sliperier och cellulosafabriker,\nbyggnadsmaskiner m. m. Specialiteter:\nbarktrum-me-, barkapparat-, barkpress- och\nbark-torkanläggningar.\n\nTelegr.-adr.: Verkstaden, Nälden.\nTelefon: 10 o. 51. Postgiro: 95555.\n\nAkt.-kap.: 285,000 kr. Antal\nindustriarb.: 80. Tillv.-värde pr år: 1,500,000 kr.\n\n—\tFirman etabl. 1883, bolag 1909.\nStyrelse: disp. Axel G. Johansson\n\n(ordf.), dir. Sten Bergström, disp. A.\nGunnarsson, lantbr. Eskil Olsson, ing.\nThure Waplan.\n\nDisp.: Axel G. Johansson.\nOfferting.: Thure Waplan.\nVerkstadsing.: civiling. Thord Waplan.\nRitkontors chef: civiling. L. Wassvik.\nInköpschef: kamrer P. Trollsås.\n\n’AB. Vara Tegelbruk, Vara.\n\nTillverkar mur- och taktegel samt\ndräneringsrör vid tegelbruk i Vara\n(Skarab. l.).\n\nTelegr.-adr.: Tegelbruket, Vara.\nTelefon: 32 o. 150. Postgiro: 22266.\n\nAkt.-kap.: 200,000 kr. Antal\nindustriarb.: 26. Årstillv.: 4 milj. st. tegelvaror.\n\n—\tBolaget grundat 1904.\n\nStyrelse: handl. Ludvig Båth, handl.\nAron Karlsson, disp. Karl Paulsson, disp.\nLennart Paulsson, kontorschef Olof\nSvensson.\n\nDisp.: Lennart Paulsson.\nKamrer: Evald Eldh.\n\n’Vara Valskvarn AB., Vara.\n\nTillverkar vetemjöl, rågmjöl samt kli\nvid kvarn i Vara (Skarab. l.).\nVarumärke : » Väs ter gyllen ».\n\nTelefon: 215. Postgiro: 8107. —\nAkt.-kap.: 500,000 kr. Antal industriarb.: 12.\nProd.-värde pr år: 1,300,000 kr. —\nFirman etabl. 1923, bolag 1927.\n\nStyrelse: dir. Sven Malmberg (ordf.),\ndir. Hj. Carlborn, disp. Knut I.\nSvensson.\n\nDisp.: Knut I. Svensson.\n\nVarbergs Betongvaru AB., Varberg.\n\nSe Betongbolaget, Varbergs\nBetongvaru AB., Varberg.\n\nVarbergs Schackelfabrik, Varberg.\n\nSmidesfabrik och mek. verkstad i\nVarberg (Hallands l.). Tillverkar\nskepps-smiden såsom schackels, vantskruv,\nlastkrokar, fiskebåtsankare, fartygsblock\nm. m.\n\nTelefon: 994. Postgiro: 268405. —\nAntal industriarb.: 25. Tillv.-värde pr år:\n250,000 kr. — Firman etabl. 1941.\n\nÄgare o. chef: fabr. Gottfrid Carlsson\no. fabr. Erik Svensson.\n\n’Varbergs Skofabrik, Varberg.\n\nTillverkar randsydda, durksydda och\nsandalsydda skodon. Varumärke:\n»Varbergs».\n\nTelefon: 430 o. 1450. Postgiro: 80803.\n\n—\tAntal industriarb.: 85. — Firman\netabl. 1921.\n\nÄgare o. chef: fabr. Erik G. Larsson.\n\n’Varbergs Spinneri, Varberg.\n\nSe Malmö Yllefabriks AB., Malmö.\n\n’Varbergs Trikåfabrik, Varberg.\n\nTillverkar dam-, barn- och\nherrkonfek-tion i trikå. Specialitet: baddräkter.\n\nTelegr.-adr.: Trikåfabriken, Varberg.\nTelefon: 592. Postgiro: 85900. — Antal\nindustriarb.: 40. Tillv.-värde pr år:\n700,000 kr. — Fabriken anlagd 1922.\n\nÄgare o. chef: dir. Tage Montalvo.\n\n’Varbergs Träförädling, Andersson &amp;\nNilsson, Varberg.\n\nTillverkar byggnadssnickerier,\nbutiksinredningar m. m.\n\nTelefon: 267 o. 1067. Postgiro: 36917.\n\n—\tAntal industriarb.: 50. Tillv.-värde pr\når: 300,000 kr. — Firman etabl. 1933.\n\nÄgare o. chefer: fabr. Gottfrid\nAndersson, fabr. Karl J. Nilsson o. grossh. Noak\nA. Johansson.\n\nAB. Axel Wardells Pälsvarufabrik,\n\nKristianstad.\n\nPälsvarufabrik. Tillverkar pälskappor\noch -kragar. Firman driver även\nförsäljning av lösa skinn.\n\nTelefon: 10296. Postgiro: 30385.\nFör-säljn.-kontor: Stockholm, Smålandsg. 17,\ntelefon: 106696 o. 105858; Göteborg,\nCentrum, telefon: 114296; Malmö, S.\nFörstadsg. 2, telefon: 23296.\n\nAkt.-kap.: 350,000 kr. Antal\nindustriarb.: 40. Tillv.-värde pr år: 1,500,000 kr.\n\n—\tFirman etabl. 1908, bolag 1940.\n\nVerkst. dir.: fabr. Axel Wardell.\n\nDisp.: Göte Wardell.",
    "structured": {
        "1": {
            "name": "Waplans Mekaniska Verkstads AB",
            "location": "Nälden",
            "business": "Mek. verkstad och gjuteri",
            "products": "Tillverkar vattenturbiner med regulatorer, maskiner för trä-sliperier och cellulosafabriker, byggnadsmaskiner m.m. Specialiteter: barktrumme, barkapparat, barkpress och bark-torkanläggningar",
            "contact": {
                "office": "",
                "phone": [
                    "10",
                    "51"
                ],
                "postgiro": "95555",
                "head_office": "",
                "sales_offices": [],
                "telegraph": "Verkstaden, Nälden",
                "factory_office": "",
                "factory_phone": ""
            },
            "financials": {
                "capital": "285 000 kr",
                "employees": {
                    "industriarb": 80
                },
                "annual_turnover": "1 500 000 kr",
                "annual_production_value": "1 500 000 kr"
            },
            "foundation_year": 1883,
            "corporation_year": 1909,
            "board": [
                {
                    "name": "disp. Axel G. Johansson",
                    "role": "ordf."
                },
                {
                    "name": "dir. Sten Bergström",
                    "role": ""
                },
                {
                    "name": "disp. A. Gunnarsson",
                    "role": ""
                },
                {
                    "name": "lantbr. Eskil Olsson",
                    "role": ""
                },
                {
                    "name": "ing. Thure Waplan",
                    "role": ""
                }
            ],
            "original_name": "",
            "owners": [],
            "director": "",
            "managing_director": "",
            "sales_manager": "",
            "manager": ""
        },
        "2": {
            "name": "AB. Vara Tegelbruk",
            "location": "Vara",
            "business": "Tillverkar mur- och taktegel samt dräneringsrör",
            "products": "",
            "contact": {
                "office": "",
                "phone": [
                    "32",
                    "150"
                ],
                "postgiro": "22266",
                "head_office": "",
                "sales_offices": [],
                "telegraph": "Tegelbruket, Vara",
                "factory_office": "",
                "factory_phone": ""
            },
            "financials": {
                "capital": "200 000 kr",
                "employees": {
                    "industriarb": 26
                },
                "annual_turnover": "",
                "annual_production_value": "4 milj. st. tegelvaror"
            },
            "foundation_year": 1904,
            "corporation_year": 0,
            "board": [
                {
                    "name": "handl. Ludvig Båth",
                    "role": ""
                },
                {
                    "name": "handl. Aron Karlsson",
                    "role": ""
                },
                {
                    "name": "disp. Karl Paulsson",
                    "role": ""
                },
                {
                    "name": "disp. Lennart Paulsson",
                    "role": ""
                },
                {
                    "name": "kontorschef Olof Svensson",
                    "role": ""
                }
            ],
            "original_name": "",
            "owners": [],
            "director": "",
            "managing_director": "",
            "sales_manager": "",
            "manager": ""
        },
        "3": {
            "name": "Vara Valskvarn AB.",
            "location": "Vara",
            "business": "Tillverkar vetemjöl, rågmjöl samt kli",
            "products": "",
            "contact": {
                "office": "",
                "phone": [
                    "215"
                ],
                "postgiro": "8107",
                "head_office": "",
                "sales_offices": [],
                "telegraph": "",
                "factory_office": "",
                "factory_phone": ""
            },
            "financials": {
                "capital": "500 000 kr",
                "employees": {
                    "industriarb": 12
                },
                "annual_turnover": "",
                "annual_production_value": "1 300 000 kr"
            },
            "foundation_year": 1923,
            "corporation_year": 1927,
            "board": [
                {
                    "name": "dir. Sven Malmberg",
                    "role": "ordf."
                },
                {
                    "name": "dir. Hj. Carlborn",
                    "role": ""
                },
                {
                    "name": "disp. Knut I. Svensson",
                    "role": ""
                }
            ],
            "original_name": "",
            "owners": [],
            "director": "",
            "managing_director": "",
            "sales_manager": "",
            "manager": ""
        },
        "4": {
            "name": "Varbergs Betongvaru AB.",
            "location": "Varberg",
            "business": "",
            "products": "",
            "contact": {
                "office": "",
                "phone": [
                    "994"
                ],
                "postgiro": "268405",
                "head_office": "",
                "sales_offices": [],
                "telegraph": "",
                "factory_office": "",
                "factory_phone": ""
            },
            "financials": {
                "capital": "",
                "employees": {
                    "industriarb": 25
                },
                "annual_turnover": "",
                "annual_production_value": "250 000 kr"
            },
            "foundation_year": 1941,
            "corporation_year": 0,
            "board": [],
            "original_name": "",
            "owners": [],
            "director": "",
            "managing_director": "",
            "sales_manager": "",
            "manager": ""
        },
        "5": {
            "name": "Varbergs Schackelfabrik",
            "location": "Varberg",
            "business": "Smidesfabrik och mek. verkstad",
            "products": "Tillverkar skepps-smiden såsom schackels, vantskruv, lastkrokar, fiskebåtsankare, fartygsblock mm",
            "contact": {
                "office": "",
                "phone": [
                    "994"
                ],
                "postgiro": "268405",
                "head_office": "",
                "sales_offices": [],
                "telegraph": "",
                "factory_office": "",
                "factory_phone": ""
            },
            "financials": {
                "capital": "",
                "employees": {
                    "industriarb": 25
                },
                "annual_turnover": "",
                "annual_production_value": "250 000 kr"
            },
            "foundation_year": 1941,
            "corporation_year": 0,
            "board": [],
            "original_name": "",
            "owners": [],
            "director": "",
            "managing_director": "",
            "sales_manager": "",
            "manager": ""
        },
        "6": {
            "name": "Varbergs Skofabrik",
            "location": "Varberg",
            "business": "Tillverkar randsydda, durksydda och sandalsydda skodon",
            "products": "",
            "contact": {
                "office": "",
                "phone": [
                    "430",
                    "1450"
                ],
                "postgiro": "80803",
                "head_office": "",
                "sales_offices": [],
                "telegraph": "",
                "factory_office": "",
                "factory_phone": ""
            },
            "financials": {
                "capital": "",
                "employees": {
                    "industriarb": 85
                },
                "annual_turnover": "",
                "annual_production_value": ""
            },
            "foundation_year": 1921,
            "corporation_year": 0,
            "board": [],
            "original_name": "",
            "owners": [],
            "director": "",
            "managing_director": "",
            "sales_manager": "",
            "manager": ""
        },
        "7": {
            "name": "Varbergs Spinneri",
            "location": "Varberg",
            "business": "Se Malmö Yllefabriks AB",
            "products": "",
            "contact": {
                "office": "",
                "phone": [
                    "",
                    ""
                ],
                "postgiro": "0",
                "head_office": "",
                "sales_offices": [],
                "telegraph": "",
                "factory_office": "",
                "factory_phone": ""
            },
            "financials": {
                "capital": "",
                "employees": {
                    "industriarb": 0
                },
                "annual_turnover": "",
                "annual_production_value": ""
            },
            "foundation_year": 0,
            "corporation_year": 0,
            "board": [],
            "original_name": "",
            "owners": [],
            "director": "",
            "managing_director": "",
            "sales_manager": "",
            "manager": ""
        },
        "8": {
            "name": "Varbergs Trikåfabrik",
            "location": "Varberg",
            "business": "Tillverkar dam-, barn- och herrkonfektion i trikå",
            "products": "Specialitet: baddräkter",
            "contact": {
                "office": "",
                "phone": [
                    "592"
                ],
                "postgiro": "85900",
                "head_office": "",
                "sales_offices": [],
                "telegraph": "Trikåfabriken, Varberg",
                "factory_office": "",
                "factory_phone": ""
            },
            "financials": {
                "capital": "",
                "employees": {
                    "industriarb": 40
                },
                "annual_turnover": "",
                "annual_production_value": "700 000 kr"
            },
            "foundation_year": 1922,
            "corporation_year": 0,
            "board": [],
            "original_name": "",
            "owners": [],
            "director": "",
            "managing_director": "",
            "sales_manager": "",
            "manager": ""
        },
        "9": {
            "name": "Varbergs Träförädling, Andersson & Nilsson",
            "location": "Varberg",
            "business": "Tillverkar byggnadssnickerier, butiksinredningar m.m.",
            "products": "",
            "contact": {
                "office": "",
                "phone": [
                    "267",
                    "1067"
                ],
                "postgiro": "36917",
                "head_office": "",
                "sales_offices": [],
                "telegraph": "",
                "factory_office": "",
                "factory_phone": ""
            },
            "financials": {
                "capital": "",
                "employees": {
                    "industriarb": 50
                },
                "annual_turnover": "",
                "annual_production_value": "300 000 kr"
            },
            "foundation_year": 1933,
            "corporation_year": 0,
            "board": [],
            "original_name": "",
            "owners": [],
            "director": "",
            "managing_director": "",
            "sales_manager": "",
            "manager": ""
        },
        "10": {
            "name": "AB. Axel Wardells Pälsvarufabrik",
            "location": "Kristianstad",
            "business": "Pälsvarufabrik",
            "products": "Tillverkar pälskappor och -kragar",
            "contact": {
                "office": "Stockholm, Smålandsg. 17",
                "phone": [
                    "106696",
                    "105858"
                ],
                "postgiro": "30385",
                "head_office": "",
                "sales_offices": [
                    {
                        "location": "Göteborg",
                        "phone": "114296"
                    },
                    {
                        "location": "Malmö",
                        "phone": "23296"
                    }
                ],
                "telegraph": "",
                "factory_office": "",
                "factory_phone": ""
            },
            "financials": {
                "capital": "350 000 kr",
                "employees": {
                    "industriarb": 40
                },
                "annual_turnover": "",
                "annual_production_value": "1 500 000 kr"
            },
            "foundation_year": 1908,
            "corporation_year": 1940,
            "board": [],
            "original_name": "",
            "owners": [],
            "director": "",
            "managing_director": "fabr. Axel Wardell",
            "sales_manager": "",
            "manager": ""
        }
    }
}