{
    "original": "Reinebo1 q—R( stu\n\nAB. Reinoborg &amp; Lind, Bpdafors\n\nDamväskf abrik i Bodafors (Jönköp.’!.).\nTillverkar damyäskor i skinn ock plastic\nsamt shoppingväskor. Varumärke:\n»Reven ue».\n\nKontor: Bodafors. Telegr.-adr.: Abereli,\nBodafors. Telefon: 6 o. 26. Postgiro:\n196019. Avd.-kontor: Stockholm, Birger\nJarlsg. 62, telefon: 112629.\n\nAkt.-kap.: 40,000 kr. Antal\nindustriarb.; 20. Tillv.-värde pr år: 200,000 kr.\n\n—\tBolaget grundat 1944.\nDisponenter: Sigvard Reineborg o. Erik\n\nBertil Lind.\n\n*Reiners industri AB., Mjölby.\n\nMöbelfabrik. Tillverkar möbler och\nsilverschatull.\n\nTelegr.-adr.: Reiner, Mjölby. Telefon:\n191 o. 59L Postgiro: 9356. — Akt.-kap.:\n50,000 kr. Antal industriarb.: 59. —\nFirman etabl. 1915, bolag 1926.\n\nStyrelse o. verkst. dir.: fru Maria\nReiner.\n\ntteklambarid, Svenska Reklamband*\nfabriken Nya AB., Linköping.\n\nTillverkar reklamband.\nTelegr.-ädr.: Reklamband, Linköping.\nTelefon: 21597. Postgiro: 30109.\nAvd.-kontor: Stockholm, Regeringsg. 51,\ntelefon: 113108.\n\nAkt.-kap.: 60,000 kr. Antal industriarb.:\n17. Tillv.-värde pr år: 430,000 kr. —\nBolaget grundat 1915.\n\nVerkst. dir.: fru A. Zaar.\nAyd.~c.hefi i Sthlm: Eric Zaar. *\n\nRepsiageriet Holmlund &amp; Co.,\nKommanditbolaget, Örnsköldsvik.\n\nSe Kommanditbolaget Repsiageriet\nIlölmlund &amp; Co., Örnsköldsvik.\n\nReppe Stärkelsefabriks AB.,\n\nRäppe.\n\nTillverkar potatismjöl, glykos, dextrin.\nsago- och potatisgryn m. m. vid fabrik i\nRäppe (Kmvob.,1.).\n\nTelegr.-adr.: Stärkelsefabriken, Växjö.\nTelefon: Växjö 6017. Postgiro: 146070.\n\n—\tAkt.-kap.; 1-50,000 kr. Antal\nindustriarb.: 20. — Bolaget grundat 1876.\n\nStyrelse: disp. Hj. Svenfelt, kapten\nSven Svenfelt, dir. F. öfverberg.\nVerkst. dir.: Cuno Nyblom.\n\n*Reo, Skofabriken, Örebro.\n\nSe sSkofabriken Reo, Örebro,.\n\nReservearpennfabriken, AB»\nSvenska, Strömstad.\n\nSe AB. Svenska Reservoarpennfabriken,\nStrömstad.\n\n*AB. Resexo, Stockholm.\n\nFirman driver konsulterande\nverksamhet rörande produkter av konstharts.\n\nKontor: Birger Jarlsg. 55. Telegr.-adr.:\nPolvmer, Stockholm. Telefon: 118178.\nPostgiro: 251238.\n\nAkt.-kap.: 10,000 kr. — Bolaget\ngrundat 1945.\n\nStyrelse: dir. Gunnar Rooth, di,sp.\nGunnar WtlnäMäd-. * ä 1 ’ v : - ’\nVerkst. dir.: Gunnar Sandblad:\n\n: Resinit, Nya AB., Västervik* :\nSe Nya AB. Resinit, Västervik.\n\nAB. Resteröds Hemindustri,\n\nLjungskile.\t/\n\nTillverkar herr-, dam- och\nbarnunderkläder vicl trikåfabrik i Ljungskile\n(Göteb. o. Bohus l.).\t. •\n\nTelefon: 194 o. 102. Postgiro: 37487.\nRepresentanter: Otto Haux, Stockholm,\nSysslomansg. 28, telefon: 503806; Erik\nWidbom, Göteborg, Haga kyrkog. 26,\ntelefon: 115232.\n\nAkt.-kap.: 150,000 kr. Antal\nindustriarb.: 24. Tillv.-värde pr år: 400,000 kr.\n\n—\tFirman etabl. 1930, bolag 19351\nVerkst. dir.: Karl-August Mattsson.\n\nAB. Result, Stockholm.\n\nMek. verkstad. Tillverkar hydrauliska\npressar upp till 100 ton,\nsmalfilmspro-jektorer (märke: »Svepro-16»),\nautomatiska vågar samt verktyg.\n\nKontor: Björngårdsg. 3. Telegr.-adr.:\nAbr.es, Stockholm. Telefon: 422526 o.\n409784. Postgiro: 192517.\nEnsamförsälj. för pressar: A. Karlson, Metall- och\nMaskin AB., Stockholm, Birger Jarlsg.\n13; telefon: 232445.\n\nAkt.-kap.: 500,000 kr. Antal\nindustriarb.: 40. Tillv.-värde pr år: 490,000 kr.\n\n—\tBolaget grundat 1936.\t. j\nStyrelse: bokförL Kaj Böhnier (Ördf.),\n\nbokförl. Gerard Bonnier, bokförl. Åke\nBonnier, ing. Lars-Erik Svensson/.\nVerkst. dir.: Lars-Erik Svenssöii. . .\n\n* A B. Resår, Karlstad. ;\n\nResår- och sängfabrik. Tillverkar\nstål-resårmadrasser, resårstommar för bi lr och\n\n452*",
    "structured": {
        "firms": [
            {
                "name": "AB. Reinoborg & Lind",
                "location": "Bodafors",
                "business": "Damväskfabrik",
                "products": "Tillverkar damväskor i skinn och plast samt shoppingväskor. Varumärke: 'Revenue'.",
                "contact": {
                    "office": "Bodafors",
                    "phone": [
                        "6",
                        "26"
                    ],
                    "postgiro": "196019",
                    "sales_offices": [
                        {
                            "location": "Stockholm",
                            "phone": "112629"
                        }
                    ],
                    "telegraph": "Abereli, Bodafors"
                },
                "financials": {
                    "capital": "40,000 kr",
                    "employees": {
                        "industriarb": 20
                    },
                    "annual_turnover": "200,000 kr",
                    "annual_production_value": "200,000 kr"
                },
                "foundation_year": 1944,
                "board": [
                    {
                        "name": "Sigvard Reineborg",
                        "role": "Disponent"
                    },
                    {
                        "name": "Erik Bertil Lind",
                        "role": "-"
                    }
                ]
            },
            {
                "name": "Reiners Industri AB.",
                "location": "Mjölby",
                "business": "Möbelfabrik",
                "products": "Tillverkar möbler och silverschatull.",
                "contact": {
                    "office": "Mjölby",
                    "phone": [
                        "191",
                        "59"
                    ],
                    "postgiro": "9356"
                },
                "financials": {
                    "capital": "50,000 kr",
                    "employees": {
                        "industriarb": 59
                    }
                },
                "foundation_year": 1944,
                "board": [
                    {
                        "name": "fru Maria Reiner",
                        "role": "Styrelse o. verkst. dir."
                    }
                ]
            },
            {
                "name": "Svenska Reklambandfabriken Nya AB.",
                "location": "Linköping",
                "business": "Tillverkar reklamband",
                "contact": {
                    "office": "Linköping",
                    "phone": "21597",
                    "postgiro": "30109",
                    "sales_offices": [
                        {
                            "location": "Stockholm",
                            "phone": "113108"
                        }
                    ],
                    "telegraph": "Reklamband, Linköping"
                },
                "financials": {
                    "capital": "60,000 kr",
                    "employees": {
                        "industriarb": 17
                    },
                    "annual_turnover": "430,000 kr"
                },
                "foundation_year": 1915,
                "board": [
                    {
                        "name": "fru A. Zaar",
                        "role": "Verkst. dir."
                    },
                    {
                        "name": "Eric Zaar",
                        "role": "Avd.-chef i Sthlm"
                    }
                ]
            },
            {
                "name": "Reppe Stärkelsefabriks AB.",
                "location": "Räppe",
                "business": "Tillverkar potatismjöl, glykos, dextrin, sago- och potatisgryn m. m.",
                "contact": {
                    "office": "Räppe",
                    "phone": "Växjö 6017",
                    "postgiro": "146070",
                    "telegraph": "Stärkelsefabriken, Växjö"
                },
                "financials": {
                    "capital": "1-50,000 kr",
                    "employees": {
                        "industriarb": 20
                    }
                },
                "foundation_year": 1876,
                "board": [
                    {
                        "name": "disp. Hj. Svenfelt",
                        "role": "Styrelse"
                    },
                    {
                        "name": "kapten Sven Svenfelt",
                        "role": "-"
                    },
                    {
                        "name": "dir. F. öfverberg",
                        "role": "Verkst. dir."
                    }
                ]
            },
            {
                "name": "AB. Resexo",
                "location": "Stockholm",
                "business": "Konsulterande verksamhet rörande produkter av konstharts",
                "contact": {
                    "office": "Birger Jarlsg. 55",
                    "phone": "118178",
                    "postgiro": "251238"
                },
                "financials": {
                    "capital": "10,000 kr"
                },
                "foundation_year": 1945,
                "board": [
                    {
                        "name": "dir. Gunnar Rooth",
                        "role": "Styrelse"
                    },
                    {
                        "name": "disp. Gunnar WtlnäMäd-",
                        "role": "-"
                    },
                    {
                        "name": "Gunnar Sandblad",
                        "role": "Verkst. dir."
                    }
                ]
            },
            {
                "name": "AB. Result",
                "location": "Stockholm",
                "business": "Mek. verkstad",
                "products": "Tillverkar hydrauliska pressar upp till 100 ton, smalfilmsprojektorer (märke: 'Svepro-16'), automatiska vågar samt verktyg.",
                "contact": {
                    "office": "Björngårdsg. 3",
                    "phone": [
                        "422526",
                        "409784"
                    ],
                    "postgiro": "192517"
                },
                "financials": {
                    "capital": "500,000 kr",
                    "employees": {
                        "industriarb": 40
                    },
                    "annual_turnover": "490,000 kr"
                },
                "foundation_year": 1936,
                "board": [
                    {
                        "name": "bokförL Kaj Böhnier (Ördf.)",
                        "role": "Styrelse"
                    },
                    {
                        "name": "bokförl. Gerard Bonnier",
                        "role": "-"
                    },
                    {
                        "name": "bokförl. Åke Bonnier",
                        "role": "-"
                    },
                    {
                        "name": "ing. Lars-Erik Svensson",
                        "role": "Verkst. dir."
                    }
                ]
            },
            {
                "name": "AB. Resår",
                "location": "Karlstad",
                "business": "Resår- och sängfabrik",
                "products": "Tillverkar stålresårmadrasser, resårstommar för bäddar och 452."
            },
            {
                "name": "AB. Resteröds Hemindustri",
                "location": "Ljungskile",
                "business": "Tillverkar herr-, dam- och barnunderkläder"
            }
        ]
    }
}