{
    "original": "Pe rsson—Pe ter se n\n\nbom*, v. konsul Thure Carlsson, dir. C. W.\nÖländer, grossh. Thure Persson.\n\nVerkst. dir.: Hj. Carlborn.\n\nJourh. dir.: Carl Nilsson.\n\nVice verkst. dir.: O. W. Öländer.\n\n*Oscar Persson, Modell- &amp; Snickeri,\nverkstad, Lund.\n\nTillverkar gjuterimodeller samt\nmöbler, inredningar, trappor och trappräck,\npaneler m. m.\n\nTelefon: 12067. Postgiro: 84945. —\nAntal industriarb.: 15. Tillv.-värde pr\når: 135,000 kr. — Firman etabl. 1924.\n\nÄgare o. chef: snickaremäst. Oscar\nPersson.\n\n* Oscar Persson, Möbeltillverkning,\n\nMalmö.\n\nTillverkar möbler.\n\nKontor: Djäkneg. 17. Telefon: 21472.\nArb.-antal: 1. — Firman etabl. 1900.\n\nÄgare: snickaremäst. Oscar Persson.\n\n*AB. Per Perssons Väf- och\nStick-maskin, Ulvsunda,\n\nMek, verkstad vid Ulvsunda\n(Stockholm). Tillverkar stickmaskiner av olika\ntyper för tillverkning av trikå samt\nkardanaxlar ; utför konstruktionsarbeten,\nverktygsarbeten, pressningar,\nmaskinbearbetning, planslipningar m. m.\nVarumärke: »Perssons».\n\nKontor: Ulvsunda. Telegr.-adr.:\nStickmaskin, Stockholm. Telefon: Stockholm\n262500. Postgiro: 196.\n\nAkt.-kap.: 1,000,000 kr. Antal\nindustriarb.: 200. Tillv.-värde pr år: 3,000,000 kr.\n— Bolaget grundat 1894.\n\nStyrelse: adv. Ivar Morssing (ordf.),\nmarining. Carl Asker, f. d. justitierådet\nAlgot Bagge, prof. Gösta Bagge, civiling.\nSeth Bernström.\n\nVerkst. dir.: Carl Asker.\n\n*AB. P. M. Pehrsson, Halmstad.\n\nGlacéläderfabrik, skinnfärgeri och\nhandskfabrik. Tillverkar handskar av\nolika slag samt finläder för handsk- och\nbeklädnadsindustrien, för mössfabriker,\nsköfabriker, bandage- och kirurgiska\ninstrumentfabriker, orgel- och\npianofabriker etc. Specialiteter: damhandskar,\nfoder- och sporthandskar. Varumärken:\n»PMP» o. »Glovex».\n\nTelegr.-adr.: Handskfabriken,\nHalmstad. Telefon: 561 o. 161. Postgiro:\n24225.\n\nAkt.-kap.: 200,000 kr. Antal\nindustriarb.: 200. Tillv.-värde pr år: 2,500,000 kr.\n\n—\tFirman etabl. 1880, bolag 1909.\nStyrelse: dir. Tage Pehrsson (ordf.),\n\nnämndem. Nils Pehrsson, dir. Adolf\nSvensson.\n\nVerkst. dir.: T. Pehrsson.\n\n*AB. S. P. Persson, Malung.\n\nSkinn-, handsk- och pälsvarufabrik i\nMalung (Kopparb. l.). Tillverkar\nhandskar, pälsar och skinntröjor m. m.\nFirman äger Elingeåns Elektricitetsverk,\nvarifrån distribueras elektr. energi inom\nsamhällena Malung och Yttermalung.\nBolaget driver även elektr.\ninstallationsverksamhet samt handel med\nbyggnadsmaterial, järn och specerier.\n\nHuvudkontor: Malung. Telefon: 13,150\no. 400. Postgiro: 32752. Repr. i\nStockholm: S. P. Perssons Stockholms AB.,\nVästerlånggatan 38. Telefon: 102710 o.\n102701.\n\nAkt.-kap.: 602,000 kr. Antal\nindustriarb.: 100 samt 125 hemarb. Tillv.-värde\npr år: 3,000,000 kr. — Firman etabl.\n1888, bolag 1916.\n\nStyrelse: dir. P. Danils (ordf.), dir.\nSimon Jansson, dir. Emanuel Persson,\nfru Rut Persson, fru E. Tobieson.\nVerkst. dir.: Emanuel Jansson.\nChef för Stockholmsbolaget: Josef\nJonsson.\n\n*Perstorps Armaturfabrik, Perstorp.\n\nSe Skånska Ättikfabriken, AB.,\nPerstorp.\n\n*Perstorps Ättikfabrik, Perstorp.\n\nSe Skånska Ättikfabriken, AB.,\nPerstorp.\n\n&lt;J. C. Petersens Mekaniska\nVerkstads AB-, Trelleborg.\n\nGrovplåtslageri, mek. verkstad och\ngjuteri. Tillverkar broar och\njärnkonstruktioner, plåtcisterner, däcksmaskiner för\nfartyg, metallborrmaskiner, spårväxlar\nsamt tackjärnsgjutgods.\n\nTelegr.-adr.: Gjuteriet, Trelleborg.\nTelefon: 68 o. 166. Postgiro: 287630.\n\nAkt.-kap.: 500,000 kr. Antal\nindustriarb.: 215. Tillv.-värde pr år: 3,100,000 kr.\n\n—\tVerkstaden anlagd 1867, bolag 1921.\nDisp.: Oskar Kjellberg.\n\nKamrer: Ruben Lindkvist.\nFörsäljn.-chef: Erik Lammer.\nVerkstadsing.: Axel Andersson.\n\n•K-",
    "structured": {
        "1": {
            "name": "Oscar Persson Modell- & Snickeri verkstad",
            "location": "Lund",
            "business": "Tillverkar gjuterimodeller samt möbler, inredningar, trappor och trappräck, paneler m. m.",
            "contact": {
                "office": "Not available",
                "phone": [
                    "12067"
                ],
                "postgiro": "84945",
                "head_office": "Not available",
                "telegraph": "Not available",
                "factory_office": "Not available",
                "factory_phone": "Not available"
            },
            "financials": {
                "employees": {
                    "industriarb": 15
                },
                "annual_turnover": "Not available",
                "annual_production_value": "135,000 kr"
            },
            "foundation_year": 1924,
            "owner": "Oscar Persson"
        },
        "2": {
            "name": "Oscar Persson Möbeltillverkning",
            "location": "Malmö",
            "business": "Tillverkar möbler",
            "contact": {
                "office": "Djäkneg. 17",
                "phone": [
                    "21472"
                ],
                "postgiro": "Not available",
                "head_office": "Not available",
                "telegraph": "Not available",
                "factory_office": "Not available",
                "factory_phone": "Not available"
            },
            "financials": {
                "employees": {
                    "arb-antal": 1
                },
                "annual_turnover": "Not available",
                "annual_production_value": "Not available"
            },
            "foundation_year": 1900,
            "owner": "Oscar Persson"
        },
        "3": {
            "name": "AB. Per Perssons Väf- och Stick-maskin",
            "location": "Ulvsunda",
            "business": "Tillverkar stickmaskiner av olika typer för tillverkning av trikå samt kardanaxlar",
            "contact": {
                "office": "Ulvsunda",
                "phone": [
                    "Stockholm 262500"
                ],
                "postgiro": "196",
                "head_office": "Not available",
                "telegraph": "Stickmaskin, Stockholm",
                "factory_office": "Not available",
                "factory_phone": "Not available"
            },
            "financials": {
                "capital": "1,000,000 kr",
                "employees": {
                    "industriarb": 200
                },
                "annual_turnover": "3,000,000 kr",
                "annual_production_value": "Not available"
            },
            "foundation_year": 1894,
            "board": [
                {
                    "name": "adv. Ivar Morssing",
                    "role": "ordf."
                },
                {
                    "name": "marining. Carl Asker",
                    "role": "Not available"
                },
                {
                    "name": "f. d. justitierådet Algot Bagge",
                    "role": "Not available"
                },
                {
                    "name": "prof. Gösta Bagge",
                    "role": "Not available"
                },
                {
                    "name": "civiling. Seth Bernström",
                    "role": "Not available"
                }
            ]
        },
        "4": {
            "name": "AB. P. M. Pehrsson",
            "location": "Halmstad",
            "business": "Glacéläderfabrik, skinnfärgeri och handskfabrik",
            "contact": {
                "office": "Not available",
                "phone": [
                    "561",
                    "161"
                ],
                "postgiro": "24225",
                "head_office": "Not available",
                "telegraph": "Handskfabriken, Halmstad",
                "factory_office": "Not available",
                "factory_phone": "Not available"
            },
            "financials": {
                "capital": "200,000 kr",
                "employees": {
                    "industriarb": 200
                },
                "annual_turnover": "2,500,000 kr",
                "annual_production_value": "Not available"
            },
            "foundation_year": 1880,
            "board": [
                {
                    "name": "dir. Tage Pehrsson",
                    "role": "ordf."
                },
                {
                    "name": "nämndem. Nils Pehrsson",
                    "role": "Not available"
                },
                {
                    "name": "dir. Adolf Svensson",
                    "role": "Not available"
                }
            ]
        },
        "5": {
            "name": "AB. S. P. Persson",
            "location": "Malung",
            "business": "Skinn-, handsk- och pälsvarufabrik i Malung (Kopparb. l.). Tillverkar handskar, pälsar och skinntröjor m. m.",
            "contact": {
                "office": "Malung",
                "phone": [
                    "13150",
                    "400"
                ],
                "postgiro": "32752",
                "head_office": "Not available",
                "telegraph": "Not available",
                "factory_office": "Not available",
                "factory_phone": "Not available"
            },
            "financials": {
                "capital": "602,000 kr",
                "employees": {
                    "industriarb": 100,
                    "hemarb": 125
                },
                "annual_turnover": "3,000,000 kr",
                "annual_production_value": "Not available"
            },
            "foundation_year": 1888,
            "board": [
                {
                    "name": "dir. P. Danils",
                    "role": "ordf."
                },
                {
                    "name": "dir. Simon Jansson",
                    "role": "Not available"
                },
                {
                    "name": "dir. Emanuel Persson",
                    "role": "Not available"
                },
                {
                    "name": "fru Rut Persson",
                    "role": "Not available"
                },
                {
                    "name": "fru E. Tobieson",
                    "role": "Not available"
                }
            ]
        },
        "6": {
            "name": "J. C. Petersens Mekaniska Verkstads AB",
            "location": "Trelleborg",
            "business": "Grovplåtslageri, mek. verkstad och gjuteri. Tillverkar broar och järnkonstruktioner, plåtcisterner, däcksmaskiner för fartyg, metallborrmaskiner, spårväxlar samt tackjärnsgjutgods.",
            "contact": {
                "office": "Not available",
                "phone": [
                    "68",
                    "166"
                ],
                "postgiro": "287630",
                "head_office": "Not available",
                "telegraph": "Gjuteriet, Trelleborg",
                "factory_office": "Not available",
                "factory_phone": "Not available"
            },
            "financials": {
                "capital": "500,000 kr",
                "employees": {
                    "industriarb": 215
                },
                "annual_turnover": "3,100,000 kr",
                "annual_production_value": "Not available"
            },
            "foundation_year": 1867,
            "board": [
                {
                    "name": "Disp. Oskar Kjellberg",
                    "role": "Not available"
                }
            ]
        }
    }
}