{
    "original": "Bergvik—\n\n—Berner\n\nBolaget grundades 1888. Bolaget äger\nBergviks Hartsprodukter AB.,\nHerjeda-lens Skogs AB. och Landaforsens Kraft\nAB.\n\nStyrelse: bankdir. Helmer Sten (ordf.),\nciviling. H. Francke, dir. K. E. Nyberg,\ndir. Ragnar Sundfeldt, bankdir. Per F.\nWåhlin.\n\nVerkst. dir.: Ragnar Sundfeldt.\n\nArbetschefer: vid Bergviks\nsulfitfabrik: övering. Gerhard Rohdin; vid\nSandarne sulfatfabrik: övering. I. Göthner;\nvid Ala sågverk: förvalt. Erland\nWahlberg; vid Bergviks kraftförvaltn.:\növering. Werner Ivermark.\n\ntikogschef: H. Schröder.\n\nHuvudkamrer: E. Johannesson.\n\nFörsäljn.-chef: Ragnar öhlander.\n\nBergviks Hartsprodukter AB.,\n\nSöderhamn.\n\nDestillationsverk vid Sandarne\n(Gäv-leb. l.). Tillverkar tallolja, hartsbeck,\nharts i stvcken, hartskristaller\n(abietin-syra), kokillolja och kärnolja samt\ntall-oljealkyder, fenolmodifierade liartser,\nesterhartser m. fl. konsthartsprodukter.\n\nKontor: Söderhamn. Telegr.-adr.:\nBergvik, Söderhamn. Telefon: 1490.\nPostgiro: 31769.\n\nAkt.-kap.: 100,000 kr. Tillv.-värde pr\når: 6,000,000 kr. — Bolaget grundat 1940.\n\nStyrelse: dir. Ragnar Sundfeldt (ordf.),\növering. I. Göthner, dir. K. E. Nyberg,\ndir. A. Orrmell.\n\nVerkst. dir.: Ragnar Sundfeldt.\n\nAvd.-chef: civiling. Tage Sunnberg.\n\n:Bergå Färgeri &amp; Ullspinneri AB.,\n\nStora Sked vi.\n\nUllspinneri, färgeri och kemisk\ntvättanstalt i Stora Skedvi (Kopparb. l.) samt\nkem. tvättanstalt i Avesta. Tillverkar\nliemslöjdsgarner samt utför beredning av\nhemvävda tyger m. m.\n\nTelefon: Arkhyttan 12 o. 52. Postgiro:\n26749.\n\nAkt.-kap.: 52,000 kr. Antal\nindustriarb.: 30. — Firman etabl. 1856, bolag\n1936.\n\nStyrelse: dir. Josef Bergeå (ordf.),\niantbr. Johan Bergeå, fabrikschef Sven\nBergeå, korrespondent Joel Johnsson,\nspinnmäst. Gustav Nord.\n\nVerkst. dir.: Josef Bergeå.\n\nFabrikschef: Sven Bergeå.\n\n*M. Berlin &amp; Co. AB., Värnamo.\n\nVelocipedfabrik. Tillverkar\nvelocipeder och velocipeddetaljer. Varumärke:\n\n&gt;Apol!o».\n\nTelegr.-adr.: Cykelberlin, Värnamo.\nTelefon: »Berlin &amp; Co.». Postgiro:\n89855. Filialkontor: Stockholm, Götg. 90,\ntelefon: 408848 o. 400948; Uppsala,\ntelefon: 819 o. 4913.\n\nAkt.-kap.: 400,000 kr. Antal\nindustriarb.: 71. Tillv.-värde pr år: 2,000,000 kr.\n— Bolaget grundat 1934.\n\nStyrelse: adv. Axel T. Nilsson (ordf.),\ndisp. Göran Berlin, dir. Mauritz Berlin,\ngeneralkonsul C. G. Gislow.\n\nVerkst. dir.: M. Berlin.\n\nBerlingska Boktryckeri &amp;\nStil-gjuteri AB., Lund.\n\nTillverkar boktryckstilar,\nstereotypklichéer, lågmaterial och mässingslinjer\nsamt utför boktryck.\n\nTelegr.-adr. o. telefon: Berlings, Lund.\nPostgiro: 30490. — Akt.-kap.: 600,000\nkr. Antal industriarb.: 70. Tillv.-värde\npr år: 600,000 kr. — Firman etabl. 1666,\növertogs av C. G. Berling 1745, ombildad\ntill bolag 1888.\n\nStyrelse: fil. dr Algot Werin (ordf.),\nboktr. Per-Håkan Ohlsson, adv. B.\nWiek-inan.\n\nVerkst. dir. o. disp.: P.-H. Ohlsson.\n\nBerner &amp; Zetterström AB.,\n\nGöteborg.\n\nKem. teknisk fabrik. Tillverkar\ninsekts-medel, råttutrotningsmedel samt\ninläggssulor in. m. Varumärken: »Dunex»,\n»Mo-tafly», »Råttut», »Kilbits» o. »Ziwa».\nBolaget driver även engroshandel med\nkorta varor, sjukvårdsartiklar,\npappersvaror m. ni.\n\nKontor: Drottningg. 53. Telegr.-adr.:\nBernzett, Göteborg. Telefon: 110506.\nPostgiro: 12331.\n\nAkt.-kap.: 125,000 kr. Antal\nindustriarb.: 15. — Firman etabl. 1908, bolag\n1929.\n\nVerkst. dir.: Carl Berner.\n\nBerners AB., Borås.\n\nBlekeri, färgeri, merceriserings- och\nappreturverk. Utför beredning av\nbomullsvävnader och bomullsgarn.\nVarumärke: »Berners».\n\nTelegr.-adr.: Berner, Borås. Telefon:\n11579, 11179 o. 11240. Postgiro: 20601.\n\n—\tAkt.-kap.: 400,000 kr. Antal\nindustriarb.: 30. Prod.-värde pr år: 2,500,000 kr.\n\n—\tFirman etabl. 1916, bolag 1937.\nStyrelse o. verkst. dir.: fabr. Aron\n\nBerner.",
    "structured": {
        "1": {
            "name": "Bergviks Hartsprodukter AB.",
            "location": "Söderhamn",
            "foundation_year": 1940,
            "board": [
                {
                    "name": "Ragnar Sundfeldt",
                    "role": "ordf."
                },
                {
                    "name": "I. Göthner",
                    "role": ""
                },
                {
                    "name": "K. E. Nyberg",
                    "role": "dir."
                },
                {
                    "name": "A. Orrmell",
                    "role": "dir."
                }
            ],
            "financials": {
                "capital": "100,000 kr",
                "annual_production_value": "6,000,000 kr"
            },
            "products": "Tillverkar tallolja, hartsbeck, harts i stvcken, hartskristaller (abietin-syra), kokillolja och kärnolja samt tall-oljealkyder, fenolmodifierade liartser, esterhartser m. fl. konsthartsprodukter.",
            "contact": {
                "office": "Söderhamn",
                "phone": [
                    "1490"
                ],
                "postgiro": "31769",
                "telegraph": "Bergvik, Söderhamn"
            }
        },
        "2": {
            "name": "Bergå Färgeri & Ullspinneri AB.",
            "location": "Stora Skedvi",
            "foundation_year": 1936,
            "board": [
                {
                    "name": "Josef Bergeå",
                    "role": "ordf."
                },
                {
                    "name": "Johan Bergeå",
                    "role": "fantbr."
                },
                {
                    "name": "Sven Bergeå",
                    "role": "fabrikschef"
                },
                {
                    "name": "Joel Johnsson",
                    "role": "korrespondent"
                },
                {
                    "name": "Gustav Nord",
                    "role": "spinnmäst."
                }
            ],
            "financials": {
                "capital": "52,000 kr",
                "employees": {
                    "industriarb.": 30
                }
            },
            "products": "Tillverkar liemslöjdsgarner samt utför beredning av hemvävda tyger m. m.",
            "contact": {
                "phone": [
                    "12",
                    "52"
                ],
                "postgiro": "26749"
            }
        },
        "3": {
            "name": "M. Berlin & Co. AB.",
            "location": "Värnamo",
            "foundation_year": 1934,
            "board": [
                {
                    "name": "Axel T. Nilsson",
                    "role": "adv."
                },
                {
                    "name": "Göran Berlin",
                    "role": "disp."
                },
                {
                    "name": "Mauritz Berlin",
                    "role": "dir."
                },
                {
                    "name": "C. G. Gislow",
                    "role": "generalkonsul"
                }
            ],
            "financials": {
                "capital": "400,000 kr",
                "employees": {
                    "industriarb.": 71
                },
                "annual_turnover": "2,000,000 kr"
            },
            "products": "Tillverkar velocipeder och velocipeddetaljer.",
            "contact": {
                "phone": [
                    "Cykelberlin, Värnamo"
                ],
                "postgiro": "89855",
                "sales_offices": [
                    {
                        "location": "Stockholm",
                        "phone": "408848 o. 400948"
                    },
                    {
                        "location": "Uppsala",
                        "phone": "819 o. 4913"
                    }
                ]
            }
        },
        "4": {
            "name": "Berlingska Boktryckeri & Stilgjuteri AB.",
            "location": "Lund",
            "foundation_year": 1888,
            "board": [
                {
                    "name": "Algot Werin",
                    "role": "fil. dr"
                },
                {
                    "name": "Per-Håkan Ohlsson",
                    "role": "boktr."
                },
                {
                    "name": "B. Wiekman",
                    "role": "adv."
                }
            ],
            "financials": {
                "capital": "600,000 kr",
                "employees": {
                    "industriarb.": 70
                },
                "annual_turnover": "600,000 kr"
            },
            "products": "Tillverkar boktryckstilar, stereotypklichéer, lågmaterial och mässingslinjer samt utför boktryck.",
            "contact": {
                "phone": [
                    "Berlings, Lund"
                ],
                "postgiro": "30490"
            }
        },
        "5": {
            "name": "Berner & Zetterström AB.",
            "location": "Göteborg",
            "foundation_year": 1929,
            "board": [],
            "financials": {
                "capital": "125,000 kr",
                "employees": {
                    "industriarb.": 15
                }
            },
            "products": "Tillverkar insektsmedel, råttutrotningsmedel samt inläggssulor in. m.",
            "contact": {
                "office": "Drottningg. 53",
                "phone": [
                    "110506"
                ],
                "postgiro": "12331",
                "telegraph": "Bernzett, Göteborg"
            },
            "managing_director": "Carl Berner"
        },
        "6": {
            "name": "Berners AB.",
            "location": "Borås",
            "foundation_year": 1937,
            "board": [
                {
                    "name": "Aron Berner",
                    "role": "fabr."
                }
            ],
            "financials": {
                "capital": "400,000 kr",
                "employees": {
                    "industriarb.": 30
                },
                "annual_production_value": "2,500,000 kr"
            },
            "products": "Utför beredning av bomullsvävnader och bomullsgarn.",
            "contact": {
                "phone": [
                    "11579",
                    "11179",
                    "11240"
                ],
                "postgiro": "20601"
            }
        }
    }
}