{
    "original": "Sundb er g—Sundsvall\n\nHuvudkontor: Sundsvall (se\nSundsvallsbolagen). Ensamförsälj. för\ncellulosa: Sveaska Cellulosa AB., Stockholm,\nV. Trädgårdsg. 15, telefon:\n»Cellulosabolaget».\n\nAkt.-kap.: 9,420,000 kr. Antal\nindustriarb.: 500. Årskapacitet: 9,000 stds sågade\nträvaror, 36,000 ton torr stark\nsulfitcellulosa, 3 milj. liter sulfitsprit.\n\nBolaget grundat 1856. Aktiemajoriteten\ni bolaget innehaves av Svenska Cellulosa\nAB.. Stockholm.\n\nStyrelse: dir. Torsten Hérnod (ordf.),\ndir. Gust. Göranson, dir. Gust. J. Sahlin,\nbankdir. P. F. Wåhlin.\n\nVerkst. dir.: Gust. Göranson.\n\nDriftsing. i Söråker: Rolf de Jounge.\n\nVerkstadschef i Sundsbruk: G. Gidlöf.\n\nSågverhsförvalt.: S. Stigenberg.\n\nAB. Erik Sundberg, Tureberg.\n\nTransformatorfabrik i Tureberg (Sthlms\n1.). Tillverkar transformatorer, drosslar\noch pressarbeten.\n\nTelegr.-adr.: Suntrans, Stockholm.\nTelefon: Stockholm 351681. Postgiro: 81741.\n\n—\tAkt.-kap.: 60,000 kr. Antal\nindustriarb.: 45.Tillv.-värde pr år: 500,000 kr. —\nFirman etabl. 1921 i Sigtuna, bolag 1928,\nflyttad 1943.\n\nVerkst. dir.: fru R. Hoffner-Björklund.\n\nFabrihschef: ing. E. A. Sundberg.\n\nKamrer: fröken M. Karlsson.\n\n(Jfr annons nr 26.)\n\n\"Sundby Tegelbruks AB.,\n\nStockholm.\n\nTillverkar murtegel vid tegelbruk i\nSundby, Stallarholmen (Södermanl. l.).\n\nKontor: Stockholm, V. Trädgårdsg.\n11 A. Telefon: 107223 o. 107208. Postgiro:\n2018.\n\nAkt.-kap.: 150.000 kr. Antal\nindustriarb.: 30. Årsprod.: 3,5 milj. st. tegelvaror.\n\n—\tBolaget grundat 1916.\n\nVerkst. dir.: Gustaf Thornstedt.\n\n\"Sundby Verkstäder, Uppsala.\n\nSnickeri-, plåtslageri- och\nmåleriverkstäder. Tillverkar byggnadssnickerier,\nköks- och butiksinredningar samt utför\nplåtslageriarbeten. Specialiteter: kyl- och\nisskåpsstommar samt kylrumsdörrar.\n\nTelefon: 31295. Postgiro: 270861. —\nArb.-antal: 12. — Firman etabl. 1943.\n\nÄgare o. chef: fabr. Sten Johansson.\n\nSundelins AB., Domsjöverken.\n\nPäls- och damkonfektionsfabrik i\nDom-sjöverken (Västernorrl. l.). Tillverkar\ndam- och barnpälsar, dräkter och kappor.\n\nTelefon: Örnsköldsvik 5202, 5252 o.\n5452. Postgiro: 6687.\n\nAkt.-kap.: 50,000 kr. Antal\nindustriarb.: 62. Tillv.-värde pr år: 850,000 kr. —\nFirman etabl. 1912, bolag 1942.\nVerkst. dir.: Alfred Sundelin.\nDisp.: Åke Sundelin.\n\n\"Sundins Fabriker, Hudiksvall.\n\nSnickerifabrik. Tillverkar skidor.\nFirman driver jämväl engroshandel med\nskidtillbehör.\n\nTelefon: 851 o. 856. Postgiro: 77416.\n— Antal industriarb.: 70. Tillv.-värde pr\når: 700,000 kr. — Firman etabl. 1927.\nÄgare o. chef: fabr. Eric Sundin.\n\n\"A. E. Sundkvist Skofabrik, Tierp.\n\nTillverkar arbetskängor, sportskodon,\nvandrarskor, sandaler och skidpjäxor vid\nskofabrik i Tierp (Uppsala l.).\nVarumärke: »Vargen».\n\nTelefon: 374. Postgiro: 99205. —\nAntal industriarb.: 30. Tillv.-värde pr år:\n500,000 kr. — Firman etabl. 1916 i\nSöderfors, flyttad till Tierp 1942.\n\nÄgare o. chef: fabr. Arvid Sundkvist.\n\n\"Sundströms Skofabrik, Kumla.\n\nTillverkar barn- och damskodon vid\nfabrik i Kumla (Örebro l.).\n\nTelefon: Örebro 70117. Ensamförsälj.:\nAB. Carlsson &amp; Åqvist, Örebro, telefon:\nCarlssonåqvist. — Antal industriarb.: 30.\nTillv.-värde pr år: 320,000 kr. — Firman\netabl. 1910.\n\nÄgare o. chef: fabr. Henry Sundström.\n\n\"Sundsvallsbolagens Gemensamma\nFörvaltning AB., Sundsvall.\n\nBolaget administrerar bl. a. följande\ntill Svenska Cellulosa AB. anslutna\nföretag:\n\nCellufix AB.,\nEssviks AB.,\nNyhamns AB.,\nSkönviks AB.,\nSund-Skönviks Verkstäder,\nSunds AB.,\n\nSundsvalls Perspektivfönster AB.,\nSvartviks AB.,\nTorpshammars AB.,\nAB. östrands Sulfatfabrik m. fl. (se\näven dessa bolag).\n\nHuvudkontor: Sundsvall. Postadr.:\nSundsvallsbolagen, Sundsvall.\nTelegr.-adr.: Koncernbolag, Sundsvall. Telefon:\n»Cellulosakoncernen», Sundsvall.\nPostgiro: 11502.\n\n",
    "structured": {
        "1": {
            "name": "Sundb erg—Sundsvall",
            "location": "Sundsvall",
            "business": "cellulosa",
            "contact": {
                "office": "V. Trädgårdsg. 15",
                "phone": [
                    "»Cellulosabolaget»"
                ],
                "postgiro": "81741"
            },
            "financials": {
                "capital": "9,420,000 kr",
                "employees": {
                    "industriarb": 500
                }
            },
            "foundation_year": 1856,
            "board": [
                {
                    "name": "Torsten Hérnod",
                    "role": "ordf."
                },
                {
                    "name": "Gust. Göranson",
                    "role": "dir."
                },
                {
                    "name": "Gust. J. Sahlin",
                    "role": "dir."
                },
                {
                    "name": "P. F. Wåhlin",
                    "role": "bankdir."
                }
            ],
            "owners": [
                "Svenska Cellulosa AB.. Stockholm"
            ],
            "director": "Gust. Göranson",
            "managing_director": "Gust. Göranson",
            "sales_manager": "Rolf de Jounge"
        },
        "2": {
            "name": "AB. Erik Sundberg",
            "location": "Tureberg (Sthlms 1.)",
            "business": "transformatorer, drosslar och pressarbeten",
            "contact": {
                "telegraph": "Suntrans, Stockholm",
                "phone": "Stockholm 351681",
                "postgiro": "81741"
            },
            "financials": {
                "capital": "60,000 kr",
                "employees": {
                    "industriarb": 45
                }
            },
            "foundation_year": 1921,
            "director": "fru R. Hoffner-Björklund",
            "managing_director": "ing. E. A. Sundberg",
            "manager": "fröken M. Karlsson"
        },
        "3": {
            "name": "Sundby Tegelbruks AB.,",
            "location": "Stallarholmen (Södermanl. l.)",
            "business": "murtegel",
            "contact": {
                "office": "Stockholm, V. Trädgårdsg. 11 A",
                "phone": [
                    "107223",
                    "107208"
                ],
                "postgiro": "2018"
            },
            "financials": {
                "capital": "150,000 kr",
                "employees": {
                    "industriarb": 30
                }
            },
            "foundation_year": 1916,
            "managing_director": "Gustaf Thornstedt"
        },
        "4": {
            "name": "Sundby Verkstäder, Uppsala",
            "location": "Uppsala",
            "business": "snickeri-, plåtslageri- och måleriverkstäder",
            "contact": {
                "phone": "31295",
                "postgiro": "270861"
            },
            "financials": {
                "employees": {
                    "antal": 12
                }
            },
            "foundation_year": 1943,
            "owner": "fabr. Sten Johansson"
        },
        "5": {
            "name": "Sundelins AB., Domsjöverken",
            "location": "Domsjöverken (Västernorrl. l.)",
            "business": "Päls- och damkonfektionsfabrik",
            "contact": {
                "phone": [
                    "Örnsköldsvik 5202",
                    "5252",
                    "5452"
                ],
                "postgiro": "6687"
            },
            "financials": {
                "capital": "50,000 kr",
                "employees": {
                    "industriarb": 62
                }
            },
            "foundation_year": 1912,
            "director": "Alfred Sundelin",
            "disp": "Åke Sundelin"
        },
        "6": {
            "name": "Sundins Fabriker, Hudiksvall",
            "location": "Hudiksvall",
            "business": "Snickerifabrik",
            "contact": {
                "phone": [
                    "851",
                    "856"
                ],
                "postgiro": "77416"
            },
            "financials": {
                "employees": {
                    "antal": 70
                }
            },
            "foundation_year": 1927,
            "owner": "fabr. Eric Sundin"
        },
        "7": {
            "name": "A. E. Sundkvist Skofabrik, Tierp",
            "location": "Tierp (Uppsala l.)",
            "business": "arbetskängor, sportskodon, vandrarskor, sandaler och skidpjäxor",
            "contact": {
                "phone": "374",
                "postgiro": "99205"
            },
            "financials": {
                "employees": {
                    "antal": 30
                }
            },
            "foundation_year": 1916,
            "owner": "fabr. Arvid Sundkvist"
        },
        "8": {
            "name": "Sundströms Skofabrik, Kumla",
            "location": "Kumla (Örebro l.)",
            "business": "barn- och damskodon",
            "contact": {
                "phone": "Örebro 70117",
                "sales_office": {
                    "location": "AB. Carlsson & Åqvist, Örebro",
                    "phone": "Carlssonåqvist"
                }
            },
            "financials": {
                "employees": {
                    "antal": 30
                }
            },
            "foundation_year": 1910,
            "owner": "fabr. Henry Sundström"
        },
        "9": {
            "name": "Sundsvallsbolagens Gemensamma Förvaltning AB., Sundsvall",
            "location": "Sundsvall",
            "business": "administrerar bl. a. följande till Svenska Cellulosa AB. anslutna företag",
            "contact": {
                "postgiro": "11502"
            }
        }
    }
}