{
    "original": "Fredlund—Fribärande\n\nStyrelse: dir. Åke Nyberg (ordf.), dir.\nGunnar Arnbrink, disp. 0. David Berg,\nherr N. Lindoff, civiling. Sten Tiberg.\nVerkst. dir.: Åke Nyberg.\n\n*AB. J. C. Fredlund &amp; C:o, Alunda.\n\nSnickerifabrik i Alunda (Uppsala l.).\nTillverkar byggnadssnickerier;\nspecialitet: W-trälamelldörrar. Firman driver\näven försäljning av plywood och\nträfiberplattor.\n\nTelefon: 136. Postgiro: 94933.\nRepresentanter i Stockholm: Martin Lindell,\nHagag. 20, telefon: 318821 o. Olof S.\nLindell, S:t Eriksplan 2, telefon: 320130.\n\nAkt.-kap.: 105,000 kr. Antal\nindustriarb.: 40, Tillv.-värde pr år: 450,000 kr.\n— Firman etabl. 1918, bolag 1943.\n\nStyrelse: fabr. Gottfrid Fredlund\n(ordf.), ver km. *Ebbe Fredlund, ing.\nMartin Lindell, kamrer Erik Sundell.\nVerkst. dir.: Gottfrid Fredlund.\n\n* Fredriksbergsverken, Fredriksberg.\nSe Hellefors Bruks AB., Hällefors.\n\nFredriksro Sågverk, Ockelbo.\n\nSe L. E. Franksson, Sågverk &amp; Hyvleri,\nOckelbo.\n\n*AB. B. Fredriksons Snickeri,\n\nStockholm.\n\nUtför snickeriarbeten, företrädesvis\nfuruarbeten och reparationer.\n\nKontor: Gamla Brogatan 36. Telefon:\n116699 o. 119868. Postgiro: 52608. —\nAkt.-kap.: 60,000 kr. Arb.-antal: 10. —\nFirman etabl. 1918, bolag 1939.\n\nStyrelse o. verkst. dir.: Birger\nFredrikson.\n\n*AB. Freese &amp; Bruno, Åby.\n\nUllspinneri, väveri, färgeri och\nappre-turverk vid Åby (Östergötl. l.).\nTillverkar finare kamgarner, yllevävnader för\nherr- och damkläder, kulört boj,\nsvensk-ulls-tweed och »stormcord» samt\nmöbel-och draperityg av cellull. Varumärken:\n»Cell an a» o. »Febex».\n\nTelegr.-adr.: Ylleåby, Åby. Telefon:\nNorrköping 50274. Postgiro: 11107.\n\nAkt.-kap.: 150,000 kr. Antal\nindustriarb.: 100. — Firman etabl. 1899, bolag\n1908, ombildat 1928.\n\nStyrelse: disp. G. Mathias Bruno\n(ordf.), dir. Hans Bruno, arkitekt J. E.\nBernhard*\n\nVerkst. dir.: Hans Bruno.\nKamrer: Åke Zetterström.\nFabrikschef o. dessinatör: Per M.\nBruno.\n\nFreiberger &amp; Andrae, Stockholm.\n\nInstrumentfabrik. Tillverkar\ntermometrar, areometrar samt glasinstrument och\napparater för industri- och\nlaboratoriebruk. Specialiteter: Termometrar o.\nkvicksilverströmbrytare.\n\nKontor: Flemingg. 9, Telegr.-adr.:\nGlasterm, Stockholm. Telefon: 535402 o.\n510310. Postgiro: 55378.\n\nAntal industriarb.: 40. Tillv.-värde pr\når: 300,000 kr. — Firman etabl. 1932.\n\nÄgare o. chefer: fabr. Ernst Andrae o.\nfabr. Josef Freiberger.\n\n*Freja, Bergverks AB-, Stockholm.\nSe Bergverks AB. Freja, Stockholm.\n\n*\tFreja, AB. Choklad- &amp;\nKonfekt-fabriken, Oävle.\n\nSe AB. Choklad- &amp; Konfektfabriken\nFreja, Gävle.\n\n*\tFriberg &amp; Co. AB., Ingenjörsfirman,\n\nGöteborg.\n\nSe Ingeniörsfirman Friberg &amp; Co. AB.,\nGöteborg.\n\n*AB. Harald Friberg, Töreboda.\nMöbelfabrik i Töreboda (Skarab. l.).\nTillverkar turistsängar, soffor,\nschäslonger och ottomaner med vävda\nståltrådsbottnar samt barnkammarmÖbler,\nkontors- och köksinredningar.\n\nTelefon: 330. Postgiro: 71905. —\nAkt.-kap.: 75,000 kr. Antal industriarb.: 30.\nTillv.-värde pr år: 400,000 kr.\n\nFabriken anlagd i Borås 1910, bolag\n1932, verksamheten flyttad till Töreboda\n1944.\n\nStyrelse: ing. Harald Friberg (ordf.),\ndisp. Anders Friberg, möbelhandl. Bror\nLindgren.\n\nDisp.: Anders Friberg.\n\n*AB. Fribärande Träkonstruktioner,\n\nTöreboda.\n\nSnickerifabrik, hyvleri och\nmonteringshall i Töreboda (Skarab. l.). Tillverkar\nfribärande träkonstruktioner till tak och\nbroar enligt system: »Töreboda» och\n»Kreiiger», spannmålssilo av trä samt\nglastak.\n\nTelegr.-adr.: Träkonstruktioner,\nTöreboda. Telefon: 102. Postgiro: 172400.\nRepresentant i Stockholm: Byggnadsfirma\nBjörkman &amp; Hebel&gt; Birger Jarlsg. 18»\ntelefon: 611760—61.\n\n164*",
    "structured": {
        "1": {
            "name": "AB. J. C. Fredlund & C:o",
            "location": "Alunda (Uppsala l.)",
            "business": "Snickerifabrik",
            "products": "Tillverkar byggnadssnickerier; specialitet: W-trälamelldörrar. Driver även försäljning av plywood och träfiberplattor.",
            "contact": {
                "office": "Alunda",
                "phone": [
                    "136"
                ],
                "postgiro": "94933",
                "sales_offices": [
                    {
                        "location": "Stockholm",
                        "phone": "318821"
                    },
                    {
                        "location": "Stockholm",
                        "phone": "320130"
                    }
                ]
            },
            "financials": {
                "capital": "105,000 kr",
                "employees": {
                    "industriarb": 40
                },
                "annual_turnover": "450,000 kr",
                "annual_production_value": "450,000 kr"
            },
            "foundation_year": 1918,
            "corporation_year": 1943,
            "board": [
                {
                    "name": "Åke Nyberg",
                    "role": "Verkst. dir."
                },
                {
                    "name": "Gunnar Arnbrink",
                    "role": "Styrelse"
                },
                {
                    "name": "David Berg",
                    "role": "disp."
                },
                {
                    "name": "N. Lindoff",
                    "role": "herr"
                },
                {
                    "name": "Sten Tiberg",
                    "role": "civiling."
                }
            ]
        },
        "2": {
            "name": "AB. B. Fredriksons Snickeri",
            "location": "Stockholm",
            "business": "Snickeriarbeten",
            "products": "Utför snickeriarbeten, företrädesvis furuarbeten och reparationer",
            "contact": {
                "office": "Gamla Brogatan 36",
                "phone": [
                    "116699",
                    "119868"
                ],
                "postgiro": "52608"
            },
            "financials": {
                "capital": "60,000 kr",
                "employees": {
                    "arb-antal": 10
                },
                "corporation_year": 1939
            },
            "foundation_year": 1918
        },
        "3": {
            "name": "AB. Freese & Bruno",
            "location": "Åby (Östergötl. l.)",
            "business": "Ullspinneri, väveri, färgeri och appreturverk",
            "products": "Tillverkar finare kamgarner, yllevävnader för herr- och damkläder, kulört boj, svensk-ulls-tweed och »stormcord» samt möbel-och draperityg av cellull",
            "contact": {
                "telegraph": "Ylleåby, Åby",
                "phone": "Norrköping 50274",
                "postgiro": "11107"
            },
            "financials": {
                "capital": "150,000 kr",
                "employees": {
                    "industriarb": 100
                },
                "corporation_year": 1908
            },
            "foundation_year": 1899
        },
        "4": {
            "name": "Freiberger & Andrae",
            "location": "Stockholm",
            "business": "Instrumentfabrik",
            "products": "Tillverkar termometrar, areometrar samt glasinstrument och apparater för industri- och laboratoriebruk",
            "specialities": "Specialiteter: Termometrar o. kvicksilverströmbrytare",
            "contact": {
                "office": "Flemingg. 9",
                "telegraph": "Glasterm, Stockholm",
                "phone": [
                    "535402",
                    "510310"
                ],
                "postgiro": "55378"
            },
            "financials": {
                "employees": {
                    "industriarb": 40
                },
                "annual_turnover": "300,000 kr"
            },
            "foundation_year": 1932
        },
        "5": {
            "name": "AB. Harald Friberg",
            "location": "Töreboda (Skarab. l.)",
            "business": "Möbelfabrik",
            "products": "Tillverkar turistsängar, soffor, schäslonger och ottomaner med vävda ståltrådsbottnar samt barnkammarmöbler, kontors- och köksinredningar",
            "contact": {
                "phone": "330",
                "postgiro": "71905"
            },
            "financials": {
                "capital": "75,000 kr",
                "employees": {
                    "industriarb": 30
                },
                "annual_production_value": "400,000 kr"
            },
            "foundation_year": 1910,
            "corporation_year": 1932
        },
        "6": {
            "name": "AB. Fribärande Träkonstruktioner",
            "location": "Töreboda (Skarab. l.)",
            "business": "Snickerifabrik, hyvleri och monteringshall",
            "products": "Tillverkar fribärande träkonstruktioner till tak och broar enligt system: »Töreboda» och »Kreiiger», spannmålssilo av trä samt glastak",
            "contact": {
                "telegraph": "Träkonstruktioner, Töreboda",
                "phone": "102",
                "postgiro": "172400",
                "sales_offices": [
                    {
                        "location": "Stockholm",
                        "phone": "611760-61"
                    }
                ]
            },
            "board": [
                {
                    "name": "Verkst. dir.: Gottfrid Fredlund",
                    "role": "Styrelse"
                },
                {
                    "name": "fabr. Gottfrid Fredlund",
                    "role": "ordf."
                },
                {
                    "name": "ver km. *Ebbe Fredlund",
                    "role": "Styrelse"
                },
                {
                    "name": "ing. Martin Lindell",
                    "role": "Styrelse"
                }
            ]
        }
    }
}