{
    "original": "A rnb er g—A rvika\n\nAvd.-chef er: i Stockholm: civiling. Bo\nEkelund; i Göteborg: civiling. Sven B.\nAskling; i Norrköping: ing. I. Rustner;\ni Örebro: ing. J. S. Ekhem; i Skövde:\ning. G. Alvemo.\n\nArnbergs Fabriks AB., Höganäs.\n\nDamkonfektionsfabrik och\nkonstsilke-väveri i Höganäs (Malmöh. l.).\nTillverkar korsetter, bysthållare m. m.\n\nTelefon: 2 o. 250. Postgiro: 8597. —\nAkt.-kap.: 300,000 kr. Tillv.-värde pr år:\n3,500,000 kr. — Firman etabl. 1894, bolag\n1941.\n\nVerkst. dir.: konsul Olof Arnberg.\n\nDisp.: Max O. Arnberg.\n\n*Arnerot, AB. Bröderna, Stockholm.\n\nSe AB. Bröderna Arnerot, Stockholm.\n\nAB. Arno, Malmö.\n\nMek. verkstad. Tillverkar maskiner för\ngarverier, lädervarufabriker och\npäls-skinnsberederier samt olika slags\nspecialmaskiner. Bolaget driver även\nengroshan-&lt;iel med tillbehör för garveriindustrin.\n\nKontor: Carlsg. 5. Telegr.-adr.: Arno,\nMalmö. Telefon: 72220. Postgiro: 148734.\n\nAkt.-kap.: 10,000 kr. Antal\nindustriarb.: 20. Tillv.-värde pr år: 500,000 kr.\n— Firman etabl. 1942.\n\nVerkst. dir.: ing. Gösta Mårtensson.\n\n*Aroma, Kolafabriken, Stockholm.\n\nSe Kolafabriken Aroma, Stockholm.\n\nAronsdals Färgeri, H. Crauers,\n\nPartille.\n\nFärgar och bleker bomull, ylle, silke,\njute, lin och hampa i korsrullar, hank,\nbommar och väv vid fabrik i Partille\n(Göteb. o. Bohus l.).\n\nTelefon: Göteborg 174083 o. Partille 26.\nPostgiro: 30129. — Antal industriarb.:\n30. Prod.-värde pr år: 750,000 kr. —\nFirman etabl. 1869.\n\nChef: disp. Bertil Grauers.\n\nA. K. Aronzons Bokbinderi,\n\nStockholm.\n\nUtför bokbinderiarbeten samt tillverkar\nkartonger.\n\nKontor: Bryggarg. 17. Telefon: 110453\n\n—54. Postgiro: 151052. — Antal\nindustriarb.: 73. Tillv.-värde pr år: 716,000 kr. —\nFirman etabl. 1888.\n\nÄgare o. chef: fabr. Henrik Ljunggren.\n\nAB. Arosverken, Västerås.\n\nMek. verkstad. Tillverkar\nverktygsmaskiner och utför maskinrenoveringar.\n\nTelefon: 34226. Postgiro: 177449. —\nAkt.-kap.: 30,000 kr. Antal industriarb.:\n50. Tillv.-värde pr år: 500,000 kr. —\nBolaget grundat 1940.\n\nStyrelse o. verkst. dir.: fabr. E. Edvin\nEriksson.\n\n*Arvika Bryggeri AB., Arvika.\n\nTillverkar malt- och läskedrycker samt\nmineralvatten.\n\nTelefon: 5 o. 1075. Postgiro: 31823.\n\n—\tAkt.-kap.: 200,000 kr. Antal\nindustriarb.: 21. Tillv.-värde pr år: 140,000 kr.\n\n—\tBryggeriet anlagt 1856, bolag 1906.\nStyrelse: disp. E. G. Riilcker (ordf.),\n\nrevisor Yngve Holmgren, kamrer Artur\nRiilcker.\n\nDisp.: E. G. Riilcker.\nKamrer: Artur Riilcker.\nBryggm.: Ivar Lydén.\n\nArvika Metallfabrik, Arvika.\n\nTillverkar metallgjutgods och armatur\nsamt utför värmelednings- och\nsanitets-tekniska anläggningar.\n\nTelegr.-adr.: Metallfabriken, Arvika.\nTelefon: 218. Postgiro: 262831. —\nArb.-antal: 28. Omsättningsvärde pr år:\n300,000 kr. — Firman etabl. 1910.\n\nÄgare o, chef: ing. Harry Nilsson.\n\n*AB. Arvika Redskapsfabrik,\n\nEskilstuna.\n\nStål- och järnmanufakturverk i Arvika.\nTillverkar handredskap såsom högafflar,\ngrepar, hackor, spadar och skyfflar,\nskogs-kulturredskap, trädgårdsredskap, yxor\noch bilor (märken: »Thor», »Diamond»\nm. fl.), svartsmiden m. m. samt skaft för\nhandredskap och yxor, vevhandtag för\nseparatorer och köttkvarnar m. m. Utför\npå beställning alla slags handredskap och\nyxor samt fasonsmide. Varumärke:\n»Ar fa».\n\nHuvudkontor: Eskilstuna. Telegr.-adr.:\nSpade, Eskilstuna. Telefon: 37440.\nPostgiro: 83183. Fabrikskontor: Arvika.\nTelegr.-adr.: Spade, Arvika. Telefon: 270.\n\nAkt.-kap.: 150,000 kr. Antal\nindustriarb.: 70. Tillv.-värde pr år: 700,000 kr.\n— Bolaget grundat 1923.\n\nStyrelse: kapten Peter A.\nSchollin-Borg (ordf.), dir. Eric Benson, löjtn.\nAlexis Gyllenberg, disp. Arvid H.\nNilsson, med. lic. I. Ryott-Iohnson, bergsing.\nAllan Schollin-Borg, civiling. Gunnar\n\n■Jr",
    "structured": {
        "1": {
            "name": "Arnbergs Fabriks AB.",
            "location": "Höganäs",
            "business": "Damkonfektionsfabrik och konstsilke-väveri",
            "products": "Tillverkar korsetter, bysthållare m. m.",
            "contact": {
                "office": "Höganäs",
                "phone": [
                    "2",
                    "250"
                ],
                "postgiro": "8597"
            },
            "financials": {
                "capital": "300,000 kr",
                "annual_turnover": "3,500,000 kr"
            },
            "foundation_year": 1894,
            "corporation_year": 1941,
            "director": "konsul Olof Arnberg",
            "managing_director": "Max O. Arnberg"
        },
        "2": {
            "name": "Arno, Malmö",
            "business": "Mek. verkstad",
            "products": "Tillverkar maskiner för garverier, lädervarufabriker och päls-skinnsberederier samt olika slags specialmaskiner",
            "contact": {
                "office": "Carlsg. 5",
                "telegraph": "Arno, Malmö",
                "phone": "72220",
                "postgiro": "148734"
            },
            "financials": {
                "capital": "10,000 kr",
                "annual_turnover": "500,000 kr"
            },
            "foundation_year": 1942,
            "director": "ing. Gösta Mårtensson"
        },
        "3": {
            "name": "Aronsdals Färgeri, H. Crauers",
            "location": "Partille",
            "business": "Färgar och bleker bomull, ylle, silke, jute, lin och hampa",
            "contact": {
                "office": "Partille",
                "phone": [
                    "174083",
                    "26"
                ],
                "postgiro": "30129"
            },
            "financials": {
                "employees": {
                    "industriarb": 30
                },
                "annual_turnover": "750,000 kr"
            },
            "foundation_year": 1869,
            "director": "disp. Bertil Crauers"
        },
        "4": {
            "name": "A. K. Aronzons Bokbinderi",
            "location": "Stockholm",
            "business": "Utför bokbinderiarbeten samt tillverkar kartonger",
            "contact": {
                "office": "Bryggarg. 17",
                "phone": "110453-54",
                "postgiro": "151052"
            },
            "financials": {
                "employees": {
                    "industriarb": 73
                },
                "annual_turnover": "716,000 kr"
            },
            "foundation_year": 1888,
            "owner": "fabr. Henrik Ljunggren"
        },
        "5": {
            "name": "AB. Arosverken",
            "location": "Västerås",
            "business": "Mek. verkstad",
            "products": "Tillverkar verktygsmaskiner och utför maskinrenoveringar",
            "contact": {
                "phone": "34226",
                "postgiro": "177449"
            },
            "financials": {
                "capital": "30,000 kr",
                "employees": {
                    "industriarb": 50
                },
                "annual_turnover": "500,000 kr"
            },
            "corporation_year": 1940,
            "director": "fabr. E. Edvin Eriksson"
        },
        "6": {
            "name": "Arvika Bryggeri AB.",
            "location": "Arvika",
            "business": "Tillverkar malt- och läskedrycker samt mineralvatten",
            "contact": {
                "phone": [
                    "5",
                    "1075"
                ],
                "postgiro": "31823"
            },
            "financials": {
                "capital": "200,000 kr",
                "employees": {
                    "industriarb": 21
                },
                "annual_turnover": "140,000 kr"
            },
            "corporation_year": 1906,
            "board": [
                {
                    "name": "disp. E. G. Riilcker",
                    "role": "ordf."
                },
                {
                    "name": "revisor Yngve Holmgren",
                    "role": "revisor"
                },
                {
                    "name": "kamrer Artur Riilcker",
                    "role": "kamrer"
                }
            ],
            "director": "disp. E. G. Riilcker",
            "manager": "Ivar Lydén"
        },
        "7": {
            "name": "Arvika Metallfabrik",
            "location": "Arvika",
            "business": "Tillverkar metallgjutgods och armatur samt utför värmelednings- och sanitetstekniska anläggningar",
            "contact": {
                "telegraph": "Metallfabriken, Arvika",
                "phone": "218",
                "postgiro": "262831"
            },
            "financials": {
                "employees": {
                    "Arb.-antal": 28
                },
                "annual_turnover": "300,000 kr"
            },
            "foundation_year": 1910,
            "director": "ing. Harry Nilsson"
        },
        "8": {
            "name": "AB. Arvika Redskapsfabrik",
            "location": "Eskilstuna",
            "business": "Stål- och järnmanufakturverk",
            "products": "Tillverkar handredskap",
            "contact": {
                "office": "Eskilstuna",
                "telegraph": "Spade, Eskilstuna",
                "phone": "37440",
                "postgiro": "83183",
                "factory_office": "Arvika",
                "factory_phone": "270"
            },
            "financials": {
                "capital": "150,000 kr",
                "employees": {
                    "industriarb": 70
                },
                "annual_turnover": "700,000 kr"
            },
            "corporation_year": 1923,
            "board": [
                {
                    "name": "kapten Peter A. Schollin-Borg",
                    "role": "ordf."
                },
                {
                    "name": "dir. Eric Benson",
                    "role": "direktör"
                },
                {
                    "name": "löjtn. Alexis Gyllenberg",
                    "role": "löjtnant"
                },
                {
                    "name": "disp. Arvid H. Nilsson",
                    "role": "disp."
                },
                {
                    "name": "med. lic. I. Ryott-Iohnson",
                    "role": "medicinsk licentiat"
                },
                {
                    "name": "bergsing. Allan Schollin-Borg",
                    "role": "bergsingenjör"
                },
                {
                    "name": "civiling. Gunnar",
                    "role": "civilingenjör"
                }
            ]
        }
    }
}