{
    "original": "Tenggrenstorp—Termoverken\n\nAkt.-kap.: 70,581,910 kr. Antal\nindustriarb.: 4,000.\n\nBolaget utgör en år 1918 genomförd\nsammanslutning av det år 1876 grundade\nfabriksföretag, vilket efter 1896 bar\nnamnet AB. L. M. Ericsson &amp; Co., samt\nStockholms Allmänna Telefon AB., grundat\n1883, till vilka 1922 anslöts Allmänna\nIndustri AB. H. T. Cedergren, grundat\n1907 under namnet AB.\nStockholmstelefon.\n\nTill Ericsson-gruppen äro följande\nsvenska företag anslutna:\n\nTelefon AB. L. M. Ericsson, Stockholm\n32,\n\nMexikanska Telefon AB. Ericsson,\n\nStockholm 32,\nL M Ericssons Försäljnings AB.,\n\nStockholm 3,\nL M Ericssons Driftkontroll AB.,\n\n(Sthlm 21),\nAB. Ermex, (Sthlm 21),\nL M Ericssons Mätinstrument AB.\n\n(Ermi), Ulvsunda 1, (Sthlm),\nL M Ericssons Signal AB.\n(Signalbolaget, Stockholm 32,\nSvenska Radio AB., Stockholm 12,\nAB. Rifa, Stockholm 19,\nMax Sieverts Fabriks AB. (Sieverts\n\nKabelverk), Sundbyberg,\nAB.Alpha, Sundbyberg, och\nAB. Svenska Elektronrör, Stockholm 20.\nStyrelse: generaldir. W. Borgquist\n(ordf.), bankdir. Marcus Wallenberg (v.\n(ordf.), bankdir. Ernfrid Browaldh, dir.\nHelge Ericson, dir. Hemming Johansson,\nadv. Sven Salmonson, dir. C.-A.\nWican-der, prof. Ragnar Woxén.\n\nVerkst. dir.: Helge Ericson.\nV. verkst. dir.: Nils A. Sterner.\növering.; Hans Thorelli.\nChefer: för telefonfabriken: ing.\nAnders Tobiasson; för kabelverket: dir.\nGeorg Olsson.\n\n\"Tenggrenstorps Tegelbruk,\n\nVänersborg.\n\nSe Wulf &amp; Co. AB., Vänersborg.\n\n*AB. Tengwall, Hälsingborg.\n\nFabrik för tillverkning av\nsamlingspärmar. Varumärke: »Triopärmen».\n\nTelegr.-adr.: Tengwalls, Hälsingborg.\nTelefon: 10213. Postgiro: 6274.\n\nFirman, etabl. 1883, övertogs 1925 av\nAB. Sveriges Litografiska Tryckerier,\nStockholm (se detta bolag). Rörelsen\nbe-drives i anslutning till Johnsons\nPappersindustri AB., Hälsingborg.\n\nStyrelse o. verkst. dir.: disp. Hj.\nMagnuson.\n\n\"Albert Terberger AB., Stockholm.\n\nTrikåfabrik. Tillverkar ylle-, silke- och\nbomullsvaror. Varumärke: »ALTEA».\n\nKontor: Fabriks v. 19, Hammarby\nIndustriområde. Telegr.-adr.: Terberger,.\nStockholm. Telefon: 440250. Postgiro:\n53730.\n\nAkt.-kap.: 600,000 kr. Antal\nindustriarb.: 205. Tillv.-värde pr år: 3,100,000 kr.\n— Firman etabl. 1894, bolag 1922.\n\nStyrelse: dir. Tore Grönwall (ordf.),\nkapten Ernst Wahlquist.\n\nVerkst. dir.: E. Wahlquist.\n\nFabrikschef: P. Perey.\n\nFörsäljn.-chef: Holge Pettersson.\n\nAB. Gustaf Terling, Göteborg.\n\nMek. verkstad. Tillverkar pumpar.\nBolaget driver även reparationsverkstad för\npumpar, fläktar, kompressorer,\noljebrän-nare, bensinmotorer m. m. samt\nengroshandel med maskiner av främmande\nfabrikat.\n\nKontor: St. Badhusg. 18. Telegr.-adr.:\nTerlingab, Göteborg. Telefon: 170,440.\nPostgiro: 12360. Avd.-kontor: Stockholm,\nSkulptörvägen 30—32, telefon: 494613—\n14; Malmö: Västerg. 22, telefon: 33400.\n\nAkt.-kap.: 75,000 kr. Antal\nindustriarb.: 35. Tillv.-värde pr år (egen tillv. av\npumpar): 50,000 kr. — Firman etabl.\n1924, bolag 1937.\n\nVerkst. dir.: Gustaf Terling.\n\nAB. Termosindustri, Kalmar.\n\nGlasförädlingsindustri. Tillverkar\nter-mosflaskkolvar, elektrodrör för\nhögfre-kvensapparater och laboratorieglas.\n\nTelefon: 4020. Postgiro: 164200. —\nAkt.-kap.: 25,000 kr. Antal industriarb.:\n16. Tillv.-värde pr år: 350,000 kr. —\nBolaget grundat 1945.\n\nVerkst. dir.: disp. Arnold Glave.\n\nAB. Termo ver ken, Jönköping.\n\nTillverkar termosflaskor. Varumärke:\n»Kokhett».\n\nTelegr.-adr.: Termoverken, Jönköping.\nTelefon: 6470. — Akt.-kap.: 45,000 kr.\nAntal industriarb.: 90. Tillv.-värde pr år:\n1,450,000 kr.\n\nBolaget grundat 1915, under namn AB.\nSvenska Isoleringsflaskfabriken, nuv.\nnamn 1941.\n\nStyrelse: disp. H. Sjöbeck (ordf.), dir.\nA. E. Albons, dir. A. Schierenbeck.\n\nVerkst. direktörer: A. E. Albons o. A.\nSchierenbeck.\n\n574*",
    "structured": {
        "1": {
            "name": "Tenggrenstorp—Termoverken",
            "foundation_year": 1918,
            "corporation_year": 1876,
            "predecessor": "AB. L. M. Ericsson & Co.",
            "original_name": "Stockholms Allmänna Telefon AB",
            "business": "Tillverkning av telekom- och elektronikprodukter",
            "financials": {
                "capital": "70,581,910 kr",
                "employees": {
                    "industriarb": 4000
                }
            },
            "board": [
                {
                    "name": "W. Borgquist",
                    "role": "generaldirektör"
                },
                {
                    "name": "Marcus Wallenberg",
                    "role": "bankdirektör"
                },
                {
                    "name": "Ernfrid Browaldh",
                    "role": "bankdirektör"
                },
                {
                    "name": "Helge Ericson",
                    "role": "direktör"
                },
                {
                    "name": "Hemming Johansson",
                    "role": "direktör"
                },
                {
                    "name": "Sven Salmonson",
                    "role": "advokat"
                },
                {
                    "name": "C.-A. Wicander",
                    "role": "direktör"
                },
                {
                    "name": "Ragnar Woxén",
                    "role": "professor"
                }
            ],
            "director": "Helge Ericson",
            "managing_director": "Nils A. Sterner",
            "sales_manager": "Hans Thorelli",
            "contact": {
                "office": "Tenggrenstorp—Termoverken, Jönköping",
                "postgiro": "6274",
                "telegraph": "Termoverken, Jönköping"
            }
        },
        "2": {
            "name": "AB. Tengwall",
            "location": "Hälsingborg",
            "business": "Tillverkning av samlingspärmar",
            "foundation_year": 1883,
            "current_name_year": 1925,
            "owners": [
                "AB. Sveriges Litografiska Tryckerier"
            ],
            "contact": {
                "office": "AB. Tengwall, Hälsingborg",
                "phone": [
                    "10213"
                ],
                "postgiro": "6274",
                "telegraph": "Tengwalls, Hälsingborg"
            }
        },
        "3": {
            "name": "Albert Terberger AB.",
            "location": "Stockholm",
            "business": "Tillverkning av trikåvaror",
            "foundation_year": 1894,
            "financials": {
                "capital": "600,000 kr",
                "employees": {
                    "industriarb": 205
                },
                "annual_turnover": "3,100,000 kr"
            },
            "board": [
                {
                    "name": "Tore Grönwall",
                    "role": "direktör"
                },
                {
                    "name": "Ernst Wahlquist",
                    "role": "kapten"
                }
            ],
            "director": "E. Wahlquist",
            "contact": {
                "office": "Fabriks v. 19, Hammarby Industriområde, Stockholm",
                "phone": [
                    "440250"
                ],
                "postgiro": "53730",
                "telegraph": "Terberger, Stockholm"
            }
        },
        "4": {
            "name": "AB. Gustaf Terling",
            "location": "Göteborg",
            "business": "Mekanisk verkstad och maskinhandel",
            "foundation_year": 1924,
            "financials": {
                "capital": "75,000 kr",
                "employees": {
                    "industriarb": 35
                },
                "annual_production_value": "50,000 kr"
            },
            "contact": {
                "office": "St. Badhusg. 18, Göteborg",
                "phone": [
                    "170440"
                ],
                "postgiro": "12360"
            }
        },
        "5": {
            "name": "AB. Termosindustri",
            "location": "Kalmar",
            "business": "Tillverkning av glasförädlingsprodukter",
            "foundation_year": 1945,
            "financials": {
                "capital": "25,000 kr",
                "employees": {
                    "industriarb": 16
                },
                "annual_production_value": "350,000 kr"
            },
            "contact": {
                "phone": [
                    "4020"
                ],
                "postgiro": "164200"
            },
            "director": "Arnold Glave"
        },
        "6": {
            "name": "AB. Termoverken",
            "location": "Jönköping",
            "business": "Tillverkning av termosflaskor",
            "foundation_year": 1915,
            "current_name_year": 1941,
            "financials": {
                "capital": "45,000 kr",
                "employees": {
                    "industriarb": 90
                },
                "annual_production_value": "1,450,000 kr"
            },
            "board": [
                {
                    "name": "H. Sjöbeck",
                    "role": "disp."
                },
                {
                    "name": "A. E. Albons",
                    "role": "direktör"
                },
                {
                    "name": "A. Schierenbeck",
                    "role": "direktör"
                }
            ],
            "managing_director": "A. E. Albons",
            "contact": {
                "telegraph": "Termoverken, Jönköping",
                "phone": [
                    "6470"
                ]
            }
        }
    }
}