{
    "original": "Vidus—Wii\n\nTelefon: 28. Postgiro: 74596. —\nAkt.-kap,: 700,000 kr. Antal industriarb.: 20.\nÅrstillv.: 1,5 milj. st. tegel, 1,500 kbm\nträvaror. — Bolaget grundat 1915.\n\nVerkst. dir.: Rolf-Henning\nStjärn-swärcL\n\n*AB. Vidus, Arvika.\n\nMöbelfabrik. Tillverkar\nkompletteringsmöbler och inredningar samt elektr.\nbelysningsarmatur.\n\nTelegr.-adr.: Vidus, Arvika. Telefon:\n130. Postgiro: 31080. Repr. i Stockholm:\nHerold &amp; Warring, Kungsg. 37; telefon:\n206190.\n\nAkt.-kap.: 75,000 kr. Antal\nindustriarb.: 35. Tillv.-värde pr år: 235,000 kr.\n— Firman etabl. 1918.\n\nStyrelse o. disp.: Anders Lehander.\n\n\"Vieille Montagne, Åmmeberg.\n\nZink- och blygruvor samt\nanrikningsverk vid Åmmebergs- och Isåsafälten (i\nÖrebro o. Östergötl. l.). Bryter och\nanrikar zink- och blymalm.\n\nHuvudkontor: Åmmeberg. Telegr.-adr.:\nVieilmont, Askersund. Telefon:\nÅmmeberg 21. Postgiro: 6573. Avd.-kontor:\nZinkgruvan.\n\nAntal industriarb.: 250. Prod.-värde pr\när: 4,000,000 kr.\n\nÄgare: La Société des mines et\nfon-deries de zinc de la Vieille Montagne,\nAngleur, Belgien.\n\nDirektör: civiling. Sven Torell.\n\nKontorschef o. sehr.: V. Davignon.\n\nKassör: Reinhold Jonsson.\n\nDriftsingenjörer: i Åmmeberg: Harry\nHolm; i Zinkgruvan: E. Mueller o. Algot\nPersson.\n\n*Wifstavarfs AB., Vivstavarv.\n\nSågverk, hyvleri, wallboardfabrik och\nsulfatfabrik vid Vivstavarv, sulfit- och\nsulfitspritfabrik samt pappfabrik vid\nFagervik (båda i Västernorrl. l.).\n\nTillverkar sågade och hyvlade trävaror,\nsulfat- och sulfitcellulosa, sulfitsprit,\nwallboard, papp, terpentin, flytande harts\nm. m. Bolaget idkar jämväl\nskogshantering.\n\nTelegr.-adr.: Wifsta, Sundsvall.\nTelefon: Sundsvall 74400.\n\nAkt.-kap.: 14,500,000 kr. Antal\nindustriarb.: 600. Tillv.-värde pr år:\n20,000,000 kr. Årskapacitet: 20,000 stds\nsågade o. 4,000 stds hyvlade trävaror,\n30,000 ton sulfatcellulosa, 75,000 ton\nsulfitcellulosa, 8 milj. ltr sulfitsprit, 10,000\nton wallboard.\n\nFirman grundad 1798, ombildad till\naktiebolag 1896.\n\nStyrelse: envoyé Axel Wallenberg\n(ordf.), bankdir. Erik Berggren, dir. J.\nW. R. Lilliestråle, frih. Oscar af Ugglas,\nbankdir. Marcus Wallenberg.\n\nVerkst. dir.: J. W. R. Lilliestråle.\n\nDisp.: Wilhelm Lilliestråle.\n\nFörsäljn.-chef: Gustaf I. Johnson.\n\nKontorschef: Folke Nilsson.\n\növering.: H. Wadell.\n\nDriftsing.: Gustav Pettersson.\n\n*Wigells Stolfabrik, Malmbäck.\n\nSe AB. Bröderna Wigells Stolfabrik,\nMalmbäck.\n\n*AB. Oscar Wigén, Tranås.\n\nPäls- och mössfabrik.\n\nTelegr.-adr.: Wigén, Tranås. Telefon:\n4195. Postgiro: 11698. Representanter: i\nStockholm: Arvid Rundquist o. Manfred\nLebenberg, Vasagatan 15—17, telefon:\n110435 o. 118406; i Göteborg: Erik\nCarlson, Friggag. 11 B, telefon: 152650.\n\nAkt.-kap.: 648,000 kr. Antal\nindustriarb.: 150. Tillv.-värde pr år: 3,500,000 kr.\n— Mössfabriken anlagd 1898,\npälsfabriken 1899, bolag 1911.\n\nStyrelse: bankdir. Carl Annerfeldt, disp.\nManfred Lebenberg, disp. H. Ode, dir.\nGunnar Perlind, herr Erik Rosén.\n\nVerkst. dir.: Gunnar Perlind.\n\n*Wiggmans Möbelfabrik, Krylbo.\n\nSe Bröderna Wiggmans Möbelfabrik,\nKrylbo.\n\nAB. Vigär, Hälsingborg.\n\nKem.-teknisk fabrik. Tillverkar\nvitamin jästtabletter. Varumärke: »Vigär».\n\nKontor: Karl Krooksg. 65. Telefon:\n14701. Postgiro: 92088. Representant:\nEneqvist, Holme &amp; Co., AB., Stockholm,\nHolländarg. 12; telefon: 230645.\n\nAkt.-kap.: 58,100 kr. Tillv.-värde pr år:\n100,000 kr. — Firman etabl. 1937, bolag\n1938.\n\nVerkst. dir.: frih. Hans Henric M.\nRamel.\n\nWii Elektriska AB., Sundsvall.\n\nElektr. vattenkraftstation vid Viiforsen\n(Västernorrl. l.). Distribuerar elektr.\nenergi till Sundsvalls stad samt en del\nstorindustrier i Sundsvallsdistriktet.\n\nTelefon: 55585. — Akt.-kap.: 600,000\nkr.\n\nBolaget grundat 1898. Aktiemajoriteten",
    "structured": {
        "firms": [
            {
                "name": "Vidus-Wii",
                "location": "Arvika",
                "business": "Möbelfabrik",
                "products": "Tillverkar kompletteringsmöbler och inredningar samt elektr. belysningsarmatur.",
                "contact": {
                    "office": "Vidus, Arvika",
                    "phone": [
                        "130"
                    ],
                    "postgiro": "31080",
                    "head_office": "Vidus, Arvika",
                    "sales_offices": [
                        {
                            "location": "Stockholm",
                            "phone": "206190"
                        }
                    ]
                },
                "financials": {
                    "capital": "700,000 kr",
                    "employees": {
                        "industriarb": 20
                    },
                    "annual_turnover": "1,500 kbm trävaror",
                    "annual_production_value": "1,5 milj. st. tegel"
                },
                "foundation_year": 1915,
                "director": "Rolf-Henning Stjärn-swärcL"
            },
            {
                "name": "Vieille Montagne",
                "location": "Åmmeberg",
                "business": "Zink- och blygruvor samt anrikningsverk",
                "products": "Bryter och anrikar zink- och blymalm.",
                "contact": {
                    "office": "Åmmeberg",
                    "phone": [
                        "Åmmeberg 21"
                    ],
                    "telegraph": "Vieilmont, Askersund",
                    "sales_offices": [
                        {
                            "location": "Zinkgruvan",
                            "phone": ""
                        }
                    ]
                },
                "financials": {
                    "employees": {
                        "industriarb": 250
                    },
                    "annual_turnover": "4,000,000 kr",
                    "annual_production_value": ""
                },
                "foundation_year": "",
                "owners": "La Société des mines et fonderies de zinc de la Vieille Montagne, Angleur, Belgien",
                "director": "civiling. Sven Torell",
                "manager": "V. Davignon",
                "treasurer": "Reinhold Jonsson",
                "engineering_managers": [
                    "Harry Holm",
                    "E. Mueller",
                    "Algot Persson"
                ]
            },
            {
                "name": "Wifstavarfs AB",
                "location": "Vivstavarv",
                "business": "Sågverk, hyvleri, wallboardfabrik och sulfatfabrik",
                "products": "Tillverkar sågade och hyvlade trävaror, sulfat- och sulfitcellulosa, sulfitsprit, wallboard, papp, terpentin, flytande harts m. m.",
                "contact": {
                    "office": "Wifsta, Sundsvall",
                    "phone": [
                        "Sundsvall 74400"
                    ]
                }
            },
            {
                "name": "AB. Oscar Wigén",
                "location": "Tranås",
                "business": "Päls- och mössfabrik",
                "contact": {
                    "office": "Wigén, Tranås",
                    "phone": [
                        "4195"
                    ],
                    "postgiro": "11698",
                    "sales_offices": [
                        {
                            "location": "Stockholm",
                            "phone": "110435, 118406"
                        },
                        {
                            "location": "Göteborg",
                            "phone": "152650"
                        }
                    ]
                },
                "financials": {
                    "capital": "648,000 kr",
                    "employees": {
                        "industriarb": 150
                    },
                    "annual_turnover": "3,500,000 kr"
                },
                "foundation_year": 1911,
                "board": [
                    {
                        "name": "Carl Annerfeldt",
                        "role": "bankdir"
                    },
                    {
                        "name": "Manfred Lebenberg",
                        "role": "disp"
                    },
                    {
                        "name": "H. Ode",
                        "role": "disp"
                    },
                    {
                        "name": "Gunnar Perlind",
                        "role": "dir"
                    },
                    {
                        "name": "Erik Rosén",
                        "role": "herr"
                    }
                ],
                "director": "Gunnar Perlind"
            },
            {
                "name": "AB. Vigär",
                "location": "Hälsingborg",
                "business": "Kem.-teknisk fabrik",
                "products": "Tillverkar vitamin jästtabletter.",
                "contact": {
                    "office": "Karl Krooksg. 65",
                    "phone": [
                        "14701"
                    ],
                    "postgiro": "92088",
                    "sales_offices": [
                        {
                            "location": "Stockholm",
                            "phone": "230645"
                        }
                    ]
                },
                "financials": {
                    "capital": "58,100 kr",
                    "employees": {
                        "industriarb": null
                    },
                    "annual_turnover": "100,000 kr"
                },
                "foundation_year": 1938,
                "director": "frih. Hans Henric M. Ramel"
            },
            {
                "name": "Wii Elektriska AB",
                "location": "Sundsvall",
                "business": "Elektr. vattenkraftstation",
                "products": "Distribuerar elektr. energi till Sundsvalls stad samt en del storindustrier i Sundsvallsdistriktet.",
                "contact": {
                    "phone": [
                        "55585"
                    ]
                },
                "financials": {
                    "capital": "600,000 kr",
                    "foundation_year": 1898
                }
            }
        ]
    }
}