{
    "original": "Eriksson—Emlid\n\nStyrelse: byggm. N. M. Eriksson\n*(ordf.), konsul Allan Börjesson,\nskepps-xed. Hans Lundgren.\n\nVerkst. dir.: N. M. Eriksson.\n\n*Oskar &amp; Georg Erikssons Mek.\nSnickeriverkstad, Örebro.\n\nTillverkar butiksinredningar samt\nstans-Émbbar.\n\nTelefon: 11459. — Arb.-antal: 10.\nTillv.-värde pr år: 90,000 kr. — Firman\netabl. 1914.\n\nÄgare o. chef: fabr. Oskar Eriksson.\n\nAB. P. Ericsson &amp; Co., Göteborg.\n\nPresennings-, markis-, tält- och\npersiennefabrik. Tillverkar presenningar,\nmarkiser, tält, persienner, rullgardiner\noch flaggor, presennings-, smerting-,\nmar-kis-, tält- och segelduk samt band och\nflätade linor.\n\nHuvudkontor: Göteborg, Odinsplatsen\n3. Telegr.-adr.: Pericsson, Göteborg.\nTelefon: 151193. Postgiro: 25511.\nAvd.-kontor: Stockholm, Kl. V. Kyrkog. 10,\ntelefon: 102531.\n\nAkt.-kap.: 200,000 kr. Antal\nindustriarb.: 50. Tillv.-värde pr år: 1,000,000 kr.\n\n—\tFirman etabl. 1850, bolagsform 1910.\nStyrelse: ing. G. Appelqvist, dir. John\n\nJLindström, disp. Ivar Wendt.\nVerkst. dir.: John Lindström.\n\n*Hull Hans Eriksson Snickeri AB.,\n\nMora.\n\nTillverkar dörrar, fönster,\nköksinred-mingar, paneler och listverk vid\nsnickerifabrik i Mora (Kopparb. l.).\n\nTelefon: Vinäs 12. Postgiro: 82246.\nAkt.-kap.: 14,400 kr. Antal\nindustriarb.: 20. Tillv.-värde pr år: 240,000 kr.\n\n—\tFirman etabl. 1932, bolag 1937.\nStyrelse: dir. Hull Erik Hansson\n\n{ordf.), verkm. Joel Hansson, verkm. Nils\nMansson.\n\nVerkst. dir.: Hull Erik Hansson.\n\nAB. W. Erikson &amp; Co., Osby.\n\nTryckeri, kuvert- och kontorsbokfabrik\ni. Osby (Kristianst. l.). Tillverkar\nkon-ifcorsartiklar, album och skrivunderlägg,\nkuvert, blanketter, jul- och\ngratulationskort samt reklamartiklar. Firman driver\näven engroshandel med pappersvaror.\n\nTelegr.-adr.: Erikson, Osby. Telefon:\n22 o. 222. Postgiro: 10820. — Akt.-kap.:\n150,000 kr. Antal industriarb.: 75.\nTillv.-värde pr år: 1,250,000 kr. — Firman\n«atabL 1398, bolag 1940.\n\nStyrelse o. verkst. dir.: Willy Erikson.\n\n*Erlabolaget, Borås.\n\nSe AB. Erikson &amp; Larson, Borås.\n\n* Erlandsons Fårull, Östanbäcks\n\nSpinneri, Norra Valbo.\n\nUllspinneri och färgeri i N. Valbo\n(Gävleb. l.). Tillverkar yllekardgarn för\nhandstickning och vävning samt utför\nlöngodsspinning av hemslöjdsgarner.\nFirman äger vattenkraftverk för eget behov.\n\nTelefon: Valbo 32 o. 41. Postgiro:\n23287. — Antal industriarb.: 25.\nTillv.-värde pr år: 400,000 kr. — Firman etabl.\n1865 under namn östanbäcks Fabriks AB.,\nnuv. namn 1942.\n\nÄgare o. chefer: fröken Alfhild\nErlandson o. fröken Elna Erlandson.\n\n*Ervalla Torvströfabrik, Järle.\n\nSe Jerle Torf AB., Järle.\n\n*Esereds Ångsåg, Ätran.\n\nSe Bark &amp; Warburgs AB., Göteborg.\n\nErnest Modellkonfektion AB.,\n\nStockholm.\n\nDamkonfektionsfabrik. Tillverkar\nkappor, dräkter och klänningar. Varumärke:\nErnest Modes.\n\nKontor: Igeldammsg. 24. Telegr.-adr.:\nErnestfab, Stockholm. Telefon: 500188 o.\n524588. Postgiro: 159204.\n\nAkt.-kap.: 75,000 kr. Antal\nindustriarb.: 60. Tillv.-värde pr år: 800,000 kr.\n\n—\tFirman etabl. 1932.\n\nVerkst. dir.: Gunnar Ericsson.\nDisp.: Garl Johan Gille.\n\n*Ernlids Träförädling AB., Lidhult.\n\nSågverk, hyvleri och snickerifabrik i\nLidhult (Kronob. l.). Tillverkar ^ sågade\noch hyvlade trävaror, byggnadssnickerier\noch inredningar samt småartiklar i trä.\n\nHuvudkontor: Lidhult. Telefon: 10 o.\n110. Postgiro: 283279. Kassakontor:\nHalmstad. Telefon:\n»Skogsägareföreningen».\n\nAkt.-kap.: 250,000 kr. Antal\nindustriarb.: 55. Tillv.-värde pr år: 850,000 kr.\n\n—\tFirman etabl. 1926, bolag 1944.\nStyrelse: frih. Carl Magnus Hermelin\n\n(ordf.), landstingsm. J. E. Bjersér,\nlands-tingsm. Ernst Brånalt.\nDisp.: Enock Ernlid.\nKamrer: Sven Dymell.\n\n;*",
    "structured": {
        "1": {
            "name": "Oskar & Georg Erikssons Mek. Snickeriverkstad",
            "location": "Örebro",
            "business": "Tillverkar butiksinredningar samt stans-Émbbar.",
            "contact": {
                "office": "Örebro",
                "phone": [
                    "11459"
                ],
                "telegraph": "",
                "factory_office": "",
                "factory_phone": ""
            },
            "financials": {
                "capital": "",
                "employees": {
                    "total": 10
                },
                "annual_turnover": "90,000 kr",
                "annual_production_value": ""
            },
            "foundation_year": 1914,
            "current_name_year": "",
            "predecessor": "",
            "original_name": "",
            "corporation_year": "",
            "board": "",
            "owners": "",
            "director": "",
            "managing_director": "Oskar Eriksson",
            "sales_manager": "",
            "manager": ""
        },
        "2": {
            "name": "AB. P. Ericsson & Co.",
            "location": "Göteborg",
            "business": "Presennings-, markis-, tält- och persiennefabrik. Tillverkar presenningar, markiser, tält, persienner, rullgardiner och flaggor, presennings-, smerting-, markis-, tält- och segelduk samt band och flätade linor.",
            "contact": {
                "office": "Göteborg, Odinsplatsen 3",
                "phone": [
                    "151193"
                ],
                "telegraph": "Pericsson, Göteborg",
                "factory_office": "",
                "factory_phone": ""
            },
            "financials": {
                "capital": "200,000 kr",
                "employees": {
                    "total": 50
                },
                "annual_turnover": "1,000,000 kr",
                "annual_production_value": ""
            },
            "foundation_year": 1850,
            "current_name_year": 1910,
            "predecessor": "",
            "original_name": "",
            "corporation_year": "",
            "board": {
                "1": {
                    "name": "ing. G. Appelqvist",
                    "role": ""
                },
                "2": {
                    "name": "dir. John Lindström",
                    "role": ""
                },
                "3": {
                    "name": "disp. Ivar Wendt",
                    "role": ""
                }
            },
            "owners": "",
            "director": "",
            "managing_director": "",
            "sales_manager": "",
            "manager": ""
        },
        "3": {
            "name": "Hull Hans Eriksson Snickeri AB.",
            "location": "Mora",
            "business": "Tillverkar dörrar, fönster, köksinred-mingar, paneler och listverk vid snickerifabrik i Mora (Kopparb. l.).",
            "contact": {
                "office": "Mora",
                "phone": [
                    "Vinas 12"
                ],
                "telegraph": "",
                "factory_office": "",
                "factory_phone": ""
            },
            "financials": {
                "capital": "14,400 kr",
                "employees": {
                    "total": 20
                },
                "annual_turnover": "240,000 kr",
                "annual_production_value": ""
            },
            "foundation_year": 1932,
            "current_name_year": 1937,
            "predecessor": "",
            "original_name": "",
            "corporation_year": "",
            "board": {
                "1": {
                    "name": "dir. Hull Erik Hansson",
                    "role": ""
                },
                "2": {
                    "name": "verkm. Joel Hansson",
                    "role": ""
                },
                "3": {
                    "name": "verkm. Nils Mansson",
                    "role": ""
                }
            },
            "owners": "",
            "director": "",
            "managing_director": "",
            "sales_manager": "",
            "manager": ""
        },
        "4": {
            "name": "AB. W. Erikson & Co.",
            "location": "Osby",
            "business": "Tryckeri, kuvert- och kontorsbokfabrik i Osby (Kristianst. l.). Tillverkar kon-ifcorsartiklar, album och skrivunderlägg, kuvert, blanketter, jul- och gratulationskort samt reklamartiklar. Firman driver även engroshandel med pappersvaror.",
            "contact": {
                "office": "Osby (Kristianst. l.)",
                "phone": [
                    "22",
                    "222"
                ],
                "telegraph": "Erikson, Osby",
                "factory_office": "",
                "factory_phone": ""
            },
            "financials": {
                "capital": "150,000 kr",
                "employees": {
                    "total": 75
                },
                "annual_turnover": "1,250,000 kr",
                "annual_production_value": ""
            },
            "foundation_year": 1398,
            "current_name_year": 1940,
            "predecessor": "",
            "original_name": "",
            "corporation_year": "",
            "board": {
                "1": {
                    "name": "",
                    "role": ""
                }
            },
            "owners": "",
            "director": "",
            "managing_director": "Willy Erikson",
            "sales_manager": "",
            "manager": ""
        },
        "5": {
            "name": "Erlandsons Fårull, Östanbäcks Spinneri",
            "location": "Norra Valbo (Gävleb. l.)",
            "business": "Ullspinneri och färgeri i N. Valbo (Gävleb. l.). Tillverkar yllekardgarn för handstickning och vävning samt utför löngodsspinning av hemslöjdsgarner. Firman äger vattenkraftverk för eget behov.",
            "contact": {
                "office": "N. Valbo (Gävleb. l.)",
                "phone": [
                    "Valbo 32",
                    "Valbo 41"
                ],
                "telegraph": "",
                "factory_office": "",
                "factory_phone": ""
            },
            "financials": {
                "capital": "",
                "employees": {
                    "total": 25
                },
                "annual_turnover": "400,000 kr",
                "annual_production_value": ""
            },
            "foundation_year": 1865,
            "current_name_year": 1942,
            "predecessor": "östl collaboratefabriks AB.",
            "original_name": "",
            "corporation_year": "",
            "board": "",
            "owners": [
                "fröken Alfhild Erlandson",
                "fröken Elna Erlandson"
            ],
            "director": "",
            "managing_director": "",
            "sales_manager": "",
            "manager": ""
        },
        "6": {
            "name": "Ernest Modellkonfektion AB.",
            "location": "Stockholm",
            "business": "Damkonfektionsfabrik. Tillverkar kappor, dräkter och klänningar. Varumärke: Ernest Modes.",
            "contact": {
                "office": "Igeldammsg. 24",
                "phone": [
                    "500188",
                    "524588"
                ],
                "telegraph": "Ernestfab, Stockholm",
                "factory_office": "",
                "factory_phone": ""
            },
            "financials": {
                "capital": "75,000 kr",
                "employees": {
                    "total": 60
                },
                "annual_turnover": "800,000 kr",
                "annual_production_value": ""
            },
            "foundation_year": 1932,
            "current_name_year": "",
            "predecessor": "",
            "original_name": "",
            "corporation_year": "",
            "board": "",
            "owners": "",
            "director": "",
            "managing_director": "Gunnar Ericsson",
            "sales_manager": "",
            "manager": ""
        },
        "7": {
            "name": "Ernlids Träförädling AB.",
            "location": "Lidhult (Kronob. l.)",
            "business": "Sågverk, hyvleri och snickerifabrik i Lidhult (Kronob. l.). Tillverkar ^ sågade och hyvlade trävaror, byggnadssnickerier och inredningar samt småartiklar i trä.",
            "contact": {
                "office": "Lidhult",
                "phone": [
                    "10",
                    "110"
                ],
                "telegraph": "",
                "factory_office": "",
                "factory_phone": ""
            },
            "financials": {
                "capital": "250,000 kr",
                "employees": {
                    "total": 55
                },
                "annual_turnover": "850,000 kr",
                "annual_production_value": ""
            },
            "foundation_year": 1926,
            "current_name_year": 1944,
            "predecessor": "",
            "original_name": "",
            "corporation_year": "",
            "board": {
                "1": {
                    "name": "frih. Carl Magnus Hermelin",
                    "role": ""
                },
                "2": {
                    "name": "landstingsm. J. E. Bjersér",
                    "role": ""
                },
                "3": {
                    "name": "lands-tingsm. Ernst Brånalt",
                    "role": ""
                }
            },
            "owners": "",
            "director": "",
            "managing_director": "",
            "sales_manager": "",
            "manager": ""
        }
    }
}