{
    "original": "Upsala\n\nAB. Upsala Margarinfabrik,\n\nUppsala.\n\nTillverkar margarin.\n\nTelegr.-adr. o. telefon:\nUpsalamarga-rin, Uppsala. Postgiro: 25225.\n\nAkt.-kap.: 500,000 kr. Antal\nindustriarb.: 12. Tillv.-värde pr år: 3,000,000kr.\n—– Bolaget grundat 1927.\n\nStyrelse: dir. Martin Edlund (ordf.),\nbankdir. G. E. Didner.\n\nDisp.: G. Swärdson.\n\nKontorschef: Ragnar Larsheden.\n\nUpsala Mek. Verkstads AB.,\n\nUppsala.\n\nUtför gas-, vatten-, avlopps- och\nvärmeledningsanläggningar.\n\nTelefon: »Wolrath &amp; Co.» Postgiro:\n7633.\n\nAkt.-kap.: 150,000 kr. Antal\nindustriarb.: 35. Tillv.-värde pr år: 750,000 kr.\n\nFirman etabl. 1868, bolag 1902,\nnamnändring 1931.\n\nStyrelse: dir. Eric Wolrath (ordf.),\ndir. Gunnar Hedman, dir. Folke Wolrath.\n\nVerkst. dir.: Gunnar Hedman.\n\n\"Upsala Möblerings AB., Uppsala.\n\nSnickeri- och möbelfabrik. Tillverkar\nmöbler och butiksinredningar.\n\nTelefon: 31842. Postgiro: 92909.\n\nAkt.-kap.: 170,000 kr. Antal\nindustriarb.: 20. Tillv.-värde pr år: 200,000 kr.\n\n—\tFirman etabl. 1910.\n\nStyrelse: disp. Carl W. Svensson (ordf.),\nverkm. Edwin Borgestedt, kamrer Carl\nGustaf Gustafsson, ritm. Amlitz Loven,\njusterare Simeon Lundgren.\n\nDisp.: Carl W. Svensson.\n\n\"Uppsala Norra Tegelbruk, Uppsala.\n\nSe N. Lundgren, Gävle.\n\n\"AB. Uppsala Optiska Industri,\n\nUppsala.\n\nTillverkar glasögonglas, glasögon,\nskytteglasögon samt skyddsglasögon mot\nsolen och för industrien. Firman driver\näven engroshandel med optiska\ninstrument.\n\nPostadr.: Box 73, Uppsala.\nTelegr.-adr.: Optik, Uppsala. Telefon: 38680,\nPostgiro: 90755.\n\nxlkt.-kap.: 25,000 kr. Antal\nindustriarb.: 40. Tillv.-värde pr år: 500,000 kr.\n\n—\tFirman etabl. 1937, bolag 1939.\n\nStyrelse: ing. Bruno Knebel (ordf.),\n\nadv. Olof Chrysander, dir. Willi Drömer.\n\nVerkst. dir.: Willi Drömer.\n\n\"Upsata Separator AB., Norrköping.\n\nTillverkar handdrivna\nmjölkseparatorer och smörkärnor. Varumärken: »Tor»,\n»Optima», »Rex», »Favorite», »Rune» o.\n»Vera».\n\nKontor: Norrköping. Telegr.-adr.:\nManusseparator, Norrköping. Telefon: 29405.\nPostgiro: 25147.\n\nRepresentanter i utlandet: Franhrihe:\nC. O. Bergman, Paris, 85 Rue Lafontaine;\nBrasilien: Fausto Soarés &amp; Cia Ltda, Rio\nde Janeiro, Rua Mayrink Veiga 18 A;\nChile: K. Herud y Cia Ltda, Santiago,\nCasilla 2211.\n\nAkt.-kap.: 10,000 kr. — Bolaget,\ngrundat 1898, är dotterbolag till AB. Manus,\nNorrköping.\n\nStyrelse: adv. Axel Hemmar (ordf.),\ndisp. Elis Ellison, apot. Lennart Ellison.\n\nVerkst. dir.: Elis Ellison.\n\n\"AB. Upsala Sidenväverier, Uppsala.\n\nTillverkar konstsilketyger samt\nylle-och helsilketyger.\n\nTelegr.-adr.: Upsalasiden, Uppsala.\nTelefon: 39730. Postgiro: 23716.\n\nAkt.-kap.: 1,000,000 kr. Antal\nindustriarb.: 200. Tillv.-värde pr år: 4,000,000 kr.\n— Bolaget grundat 1936.\n\nStyrelse: dir. Martin Edlund (ordf.),\nbyggnadsing. A. Diös, disp. Folke\nEdlund, intendent Tore Edlund, disp.\nRagnar Åkerblom.\n\nVerkst. dir.: Folke Edlund.\n\nDisp.: V. Nordlund.\n\nKontorschef: G. Modin.\n\n\"AB. Upsala Sportartikelfabrik,\n\nStockholm.\n\nTräförädlingsfabrik i Uppsala.\nTillverkar tennis-, badminton- och\nsquash-rackets, bandy- och ishockeyklubbor samt\ngolfklubbor.\n\nKontor: Stockholm, Sveavägen 52.\nTelefon: 200227, 200237 o. 200239.\nPostgiro: 141230. Ensamförsälj.: AB. Arvid\nForsberg &amp; Co., Stockholm, Sveavägen 52.\n\nAkt.-kap.: 65,000 kr. Antal\nindustriarb.: 18.\n\nFirman etabl. 1928 under namn\nSvenska Racketfabriken, nuv. namn 1945.\n\nStyrelse o. verkst. dir.: Gösta Forsberg.\n\nUppsala—Stockholms Läns\nLinodlareförening u. p. a., Gimo.\n\nTillverkar lintåga, linblånor och\nlin-kortfiber vid linberedningsverk i Gimo\n(Uppsala l.).",
    "structured": {
        "1": {
            "name": "AB. Upsala Margarinfabrik",
            "location": "Uppsala",
            "business": "Tillverkar margarin",
            "contact": {
                "telegraph": "Upsalamarga-rin, Uppsala",
                "phone": [],
                "postgiro": "25225"
            },
            "financials": {
                "capital": "500,000 kr",
                "employees": {
                    "industriarb": 12
                },
                "annual_turnover": "3,000,000kr",
                "annual_production_value": "3,000,000kr"
            },
            "foundation_year": 1927,
            "board": [
                {
                    "name": "dir. Martin Edlund",
                    "role": "ordf."
                },
                {
                    "name": "bankdir. G. E. Didner",
                    "role": "unknown"
                }
            ],
            "director": "unknown",
            "managing_director": "G. Swärdson",
            "sales_manager": "unknown",
            "manager": "Ragnar Larsheden"
        },
        "2": {
            "name": "Upsala Mek. Verkstads AB.",
            "location": "Uppsala",
            "business": "Utför gas-, vatten-, avlopps- och värmeledningsanläggningar",
            "contact": {
                "phone": [
                    "Wolrath & Co."
                ],
                "postgiro": "7633"
            },
            "financials": {
                "capital": "150,000 kr",
                "employees": {
                    "industriarb": 35
                },
                "annual_production_value": "750,000 kr"
            },
            "corporation_year": 1902,
            "board": [
                {
                    "name": "dir. Eric Wolrath",
                    "role": "ordf."
                },
                {
                    "name": "dir. Gunnar Hedman",
                    "role": "unknown"
                },
                {
                    "name": "dir. Folke Wolrath",
                    "role": "unknown"
                }
            ],
            "director": "Gunnar Hedman"
        },
        "3": {
            "name": "Upsala Möblerings AB.",
            "location": "Uppsala",
            "business": "Snickeri- och möbelfabrik. Tillverkar möbler och butiksinredningar",
            "contact": {
                "phone": [
                    "31842"
                ],
                "postgiro": "92909"
            },
            "financials": {
                "capital": "170,000 kr",
                "employees": {
                    "industriarb": 20
                },
                "annual_production_value": "200,000 kr"
            },
            "foundation_year": 1910,
            "board": [
                {
                    "name": "disp. Carl W. Svensson",
                    "role": "ordf."
                },
                {
                    "name": "verkm. Edwin Borgestedt",
                    "role": "unknown"
                },
                {
                    "name": "kamrer Carl Gustaf Gustafsson",
                    "role": "unknown"
                },
                {
                    "name": "ritm. Amlitz Loven",
                    "role": "unknown"
                },
                {
                    "name": "justerare Simeon Lundgren",
                    "role": "unknown"
                }
            ],
            "director": "Carl W. Svensson"
        },
        "4": {
            "name": "AB. Uppsala Optiska Industri",
            "location": "Uppsala",
            "business": "Tillverkar glasögonglas, glasögon, skytteglasögon samt skyddsglasögon mot solen och för industrien. Driver även engroshandel med optiska instrument",
            "contact": {
                "telegraph": "Optik, Uppsala",
                "phone": [
                    "38680"
                ],
                "postgiro": "90755"
            },
            "financials": {
                "capital": "25,000 kr",
                "employees": {
                    "industriarb": 40
                },
                "annual_turnover": "500,000 kr"
            },
            "corporation_year": 1939,
            "board": [
                {
                    "name": "ing. Bruno Knebel",
                    "role": "ordf."
                },
                {
                    "name": "adv. Olof Chrysander",
                    "role": "unknown"
                },
                {
                    "name": "dir. Willi Drömer",
                    "role": "unknown"
                }
            ],
            "director": "Willi Drömer"
        },
        "5": {
            "name": "Upsata Separator AB.",
            "location": "Norrköping",
            "business": "Tillverkar handdrivna mjölkseparatorer och smörkärnor. Varumärken: »Tor», »Optima», »Rex», »Favorite», »Rune» o. »Vera».",
            "contact": {
                "telegraph": "Manusseparator, Norrköping",
                "phone": [
                    "29405"
                ],
                "postgiro": "25147"
            },
            "financials": {
                "capital": "10,000 kr"
            },
            "predecessor": "AB. Manus, Norrköping",
            "board": [
                {
                    "name": "adv. Axel Hemmar",
                    "role": "ordf."
                },
                {
                    "name": "disp. Elis Ellison",
                    "role": "unknown"
                },
                {
                    "name": "apot. Lennart Ellison",
                    "role": "unknown"
                }
            ],
            "director": "Elis Ellison"
        },
        "6": {
            "name": "AB. Upsala Sidenväverier",
            "location": "Uppsala",
            "business": "Tillverkar konstsilketyger samt ylle-och helsilketyger",
            "contact": {
                "telegraph": "Upsalasiden, Uppsala",
                "phone": [
                    "39730"
                ],
                "postgiro": "23716"
            },
            "financials": {
                "capital": "1,000,000 kr",
                "employees": {
                    "industriarb": 200
                },
                "annual_turnover": "4,000,000 kr"
            },
            "foundation_year": 1936,
            "board": [
                {
                    "name": "dir. Martin Edlund",
                    "role": "ordf."
                },
                {
                    "name": "byggnadsing. A. Diös",
                    "role": "unknown"
                },
                {
                    "name": "disp. Folke Edlund",
                    "role": "unknown"
                },
                {
                    "name": "intendent Tore Edlund",
                    "role": "unknown"
                },
                {
                    "name": "disp. Ragnar Åkerblom",
                    "role": "unknown"
                }
            ],
            "director": "Folke Edlund"
        },
        "7": {
            "name": "AB. Upsala Sportartikelfabrik",
            "location": "Stockholm",
            "business": "Tillverkar tennis-, badminton- och squash-rackets, bandy- och ishockeyklubbor samt golfklubbor",
            "contact": {
                "phone": [
                    "200227",
                    "200237",
                    "200239"
                ],
                "postgiro": "141230"
            },
            "financials": {
                "capital": "65,000 kr",
                "employees": {
                    "industriarb": 18
                }
            },
            "current_name_year": 1945,
            "board": [
                {
                    "name": "Gösta Forsberg",
                    "role": "unknown"
                }
            ]
        }
    }
}