{
    "original": "Svenska\n\nSvensk Konsthartz industri, Gemla.\n\nBakelitpresseri i Gemla (Kronob. l.).\nTillverkar artiklar av pressat konstharts\nsåsom skruvlock, kapsyler, etuier, kulor,\nknappar m. m. samt specialdetaljer för\nolika industriändamål.\n\nTelefon: Växjö 67127. Postgiro: 97280.\n\n—\tAntal industriarb.: 50. Tillv.-värde pr\når: 350,000 kr. — Firman etabl. 1935.\n\nDelägare o. chef: fabr. Hugo Helmert.\nTehn. chef: Hans Wiillrich.\n\n*AB. Svensk Läderkonst,\n\nSollebrunn.\n\nMöbelfabrik i Sollebrunn (Älvsb. l.).\nTillverkar fåtöljer ocb soffor i skinn och\ntyg. Specialitet: Skinnmöbler.\n\nTelefon: 54 o. 74. Postgiro: 83151.\nAkt.-kap.: 35,000 kr. Antal\nindustriarb.: 60. Tillv.-värde pr år: 500,000 kr.\n\n—\tBolaget grundat 1932.\nDisponenter: Erik Danielson o. Karl\n\nEriksson.\n\nSvensk Metallförädfing AB.,\n\nSundbyberg.\n\nTillverkar rostfria kärl såsom kokkärl,\nbunkar, karotter, skopor m. m.\nVarumärke: »Svemab».\n\nTelefon: 284525 o. 281865. Postgiro:\n143886. — Akt.-kap.: 25,000 kr. Antal\nindustriarb.: 50. Tillv.-värde pr år:\n1,000,000 kr. — Bolaget grundat 1937.\nVerkst. dir.: Åke O. Lindblom.\n\nSvensk Pappersindustri, Järnfors &amp;\nHall AB., Sandared. .\n\nPappersförädlingsfabrik i Sandared\n(Älvsb. l.). Tillverkar papperstuber,\nspol-pipor, flänsrullar, skyddshylsor,\npappburkar samt formpressade artiklar såsom\ndockansikten, påskägg m. m.\n\nTelefon: Borås 55150. Postgiro: 170167.\n\n—\tAkt.-kap.: 50,000 kr. Antal\nindustriarb.: 60. Tillv.-värde pr år: 600,000 kr.\n\n—\tFirman etabl. 1935, bolag 1942.\nVerkst. dir.:, Sven Järnfors (Borås).\nDisp.: Albert Hall.\n\nDriftsing.: Gösta Järnfors.\n\n’Svensk Pälsskinnsberedning, J. F.\n\nLjungqvist, Tranås.\n\nBereder och färgar pälsskinn samt\ntillverkar dampälsar^ skinnhuvor, capes,\nskinnkragar och skinnpåsar.\n\nTelegr.-adr.: Pälsberedningen, Tranås.\nTelefon: 2134. Postgiro: 11664. — An-\n\n665*\n\ntal industriarb.: 50. — Firman etabl.\n1915.\n\nÄgare o. chef: fabr. J. F. Ljungqvist.\n\nKontorschef: Ragnar Ljungqvist.\n\n’AB. Svensk Rakklinga,\n\nSandviken.\n\nSe Swing Ltd. AB., Sandviken.\n\nAB. Svensk Skruv, Eskilstuna.\n\nTillverkar träskruv vid fabrik i Gnosjö\n(Jönköp. l.).\n\nKontor: Eskilstuna. Telefon: 30054.\nPostgiro: 13058.\n\nAkt.-kap.: 600,000 kr. Antal\nindustriarb.: 10. — Bolaget grundat 1943.\n\nStyrelse: fabr. David Bauréus, fru V.\nBauréus, disp. Eric Stålberg, dir. Gunnar\nStålberg.\n\nVerkst. dir.: Gunnar Stålberg.\n\nFörsäljn.-chef: kamrer Bernhard\nSöderström.\n\n*AB. Svensk Sprit, Stockholm.\n\nBolaget driver försäljning och\ndistribution av sulfitsprit.\n\nKontor: Wahrendorffsg. 6.\nTelegr.-adr.: Svensksprit, Stockholm. Telefon:\n232780. Postgiro: 1822. — Akt.-kap.:\n900.000 kr.\n\nBolaget grundat 1918 under namn\nFörsäljnings AB. Sulfitsprit, nuv. namn\n1922.\n\nStyrelse: dr Gunnar Sundblad (ordf.),\ndir. Gust. Göranson (v. ordf.), civiling.\nTore Bergström, dir. H. Dyster-Aas, dir.\nErik W. Eriksson, fil. dr Erik Kempe,\ndir. J. W. R. Lilliestråle, disp. Fabian\nLundquist, dir. Ragnar Sundfeldt.\n\nVerkst. dir.: Arthur Hellström.\n\n’Svensk Stålull AB., Stockholm.\n\nTillverkar stålull för industri,\nhantverk, lantbruk och hushåll vid fabrik i\nAneby (Jönköp. l.). Varumärke:\n»Kron-ull».\n\nKontor: Stockholm, Mäster Samuelsg.\n3. Telegr.-adr.: Kronull, Stockholm.\nTelefon: 202926 o. 202944. Postgiro: 191221.\n\nAkt.-kap.: 200,000 kr. Antal\nindustriarb.: 20. — Bolaget grundat 1941.\n\nStyrelse: kommerserådet S. Erik\nösterberg (ordf.), disp. Richard W. Gefeldt,\narkitekt Nils Malmborg, skeppsred. Ole\nSchröder.\n\nVerkst. dir.: Richard W. Gefeldt.\n\nFörsäljn.-chef: disp. Bernt Wahlström.",
    "structured": {
        "firms": [
            {
                "name": "Svensk Konsthartz industri",
                "location": "Gemla",
                "business": "Tillverkning av artiklar av pressat konstharts",
                "products": "Skruvlock, kapsyler, etuier, kulor, knappar m.m.",
                "contact": {
                    "phone": [
                        "Växjö 67127"
                    ],
                    "postgiro": "97280"
                },
                "financials": {
                    "capital": "Okänt",
                    "employees": {
                        "industriarb": 50
                    },
                    "annual_turnover": "350,000 kr",
                    "annual_production_value": "Okänt"
                },
                "foundation_year": 1935,
                "current_name_year": "Okänt",
                "director": "Hugo Helmert",
                "manager": "Hans Wiillrich"
            },
            {
                "name": "AB. Svensk Läderkonst",
                "location": "Sollebrunn",
                "business": "Tillverkning av möbler i skinn och tyg",
                "products": "Fåtöljer och soffor",
                "contact": {
                    "phone": [
                        "54",
                        "74"
                    ],
                    "postgiro": "83151"
                },
                "financials": {
                    "capital": "35,000 kr",
                    "employees": {
                        "industriarb": 60
                    },
                    "annual_turnover": "500,000 kr",
                    "annual_production_value": "Okänt"
                },
                "foundation_year": 1932,
                "current_name_year": "Okänt",
                "directors": [
                    "Erik Danielson",
                    "Karl Eriksson"
                ]
            },
            {
                "name": "Svensk Metallförädfing AB.",
                "location": "Sundbyberg",
                "business": "Tillverkning av rostfria kärl",
                "products": "Kokkärl, bunkar, karotter, skopor m.m.",
                "contact": {
                    "phone": [
                        "284525",
                        "281865"
                    ],
                    "postgiro": "143886"
                },
                "financials": {
                    "capital": "25,000 kr",
                    "employees": {
                        "industriarb": 50
                    },
                    "annual_turnover": "1,000,000 kr",
                    "annual_production_value": "Okänt"
                },
                "foundation_year": 1937,
                "current_name_year": "Okänt",
                "director": "Åke O. Lindblom"
            },
            {
                "name": "Svensk Pappersindustri, Järnfors & Hall AB.",
                "location": "Sandared",
                "business": "Tillverkning av papperstuber och andra papperförädlingsprodukter",
                "products": "Papperstuber, spol-pipor, flänsrullar, skyddshylsor, pappburkar, dockansikten, påskägg m.m.",
                "contact": {
                    "phone": [
                        "Borås 55150"
                    ],
                    "postgiro": "170167"
                },
                "financials": {
                    "capital": "50,000 kr",
                    "employees": {
                        "industriarb": 60
                    },
                    "annual_turnover": "600,000 kr",
                    "annual_production_value": "Okänt"
                },
                "foundation_year": 1935,
                "corporation_year": 1942,
                "director": "Sven Järnfors",
                "managing_director": "Albert Hall",
                "sales_manager": "Gösta Järnfors"
            },
            {
                "name": "Svensk Pälsskinnsberedning, J. F. Ljungqvist",
                "location": "Tranås",
                "business": "Bereder och färgar pälsskinn samt tillverkar dampälsar^ skinnhuvor, capes, skinnkragar och skinnpåsar",
                "products": "Dampälsar, skinnhuvor, capes, skinnkragar, skinnpåsar",
                "contact": {
                    "phone": [
                        "2134"
                    ],
                    "postgiro": "11664"
                },
                "financials": {
                    "capital": "Okänt",
                    "employees": {
                        "industriarb": 50
                    },
                    "annual_turnover": "Okänt",
                    "annual_production_value": "Okänt"
                },
                "foundation_year": 1915,
                "director": "J. F. Ljungqvist",
                "manager": "Ragnar Ljungqvist"
            },
            {
                "name": "AB. Svensk Skruv",
                "location": "Eskilstuna",
                "business": "Tillverkning av träskruvar",
                "contact": {
                    "phone": [
                        "30054"
                    ],
                    "postgiro": "13058"
                },
                "financials": {
                    "capital": "600,000 kr",
                    "employees": {
                        "industriarb": 10
                    },
                    "annual_turnover": "Okänt",
                    "annual_production_value": "Okänt"
                },
                "corporation_year": 1943,
                "board": [
                    {
                        "name": "David Bauréus",
                        "role": "Fabrikör"
                    },
                    {
                        "name": "V. Bauréus",
                        "role": "Okänt"
                    },
                    {
                        "name": "Eric Stålberg",
                        "role": "Disp."
                    },
                    {
                        "name": "Gunnar Stålberg",
                        "role": "Verkst. dir."
                    }
                ],
                "sales_manager": "Bernhard Söderström"
            },
            {
                "name": "AB. Svensk Sprit",
                "location": "Stockholm",
                "business": "Försäljning och distribution av sulfitsprit",
                "contact": {
                    "office": "Wahrendorffsg. 6",
                    "phone": [
                        "232780"
                    ],
                    "postgiro": "1822"
                },
                "financials": {
                    "capital": "900,000 kr",
                    "employees": "Okänt",
                    "annual_turnover": "Okänt",
                    "annual_production_value": "Okänt"
                },
                "corporation_year": 1922,
                "board": [
                    {
                        "name": "dr Gunnar Sundblad",
                        "role": "Ordf."
                    },
                    {
                        "name": "Gust. Göranson",
                        "role": "V. ordf."
                    },
                    {
                        "name": "Tore Bergström",
                        "role": "Civiling."
                    },
                    {
                        "name": "H. Dyster-Aas",
                        "role": "Dir."
                    },
                    {
                        "name": "Erik W. Eriksson",
                        "role": "Dir."
                    },
                    {
                        "name": "Erik Kempe",
                        "role": "Fil. dr"
                    },
                    {
                        "name": "J. W. R. Lilliestråle",
                        "role": "Disp."
                    },
                    {
                        "name": "Fabian Lundquist",
                        "role": "Dir."
                    },
                    {
                        "name": "Ragnar Sundfeldt",
                        "role": "Dir."
                    }
                ],
                "director": "Arthur Hellström"
            },
            {
                "name": "Svensk Stålull AB.",
                "location": "Stockholm",
                "business": "Tillverkning av stålull för industri, hantverk, lantbruk och hushåll",
                "products": "Stålull",
                "contact": {
                    "office": "Mäster Samuelsg. 3",
                    "phone": [
                        "202926",
                        "202944"
                    ],
                    "postgiro": "191221"
                },
                "financials": {
                    "capital": "200,000 kr",
                    "employees": {
                        "industriarb": 20
                    },
                    "annual_turnover": "Okänt",
                    "annual_production_value": "Okänt"
                },
                "corporation_year": 1941,
                "board": [
                    {
                        "name": "S. Erik österberg",
                        "role": "Kommerseråd"
                    },
                    {
                        "name": "Richard W. Gefeldt",
                        "role": "Disp."
                    },
                    {
                        "name": "Nils Malmborg",
                        "role": "Arkitekt"
                    },
                    {
                        "name": "Ole Schröder",
                        "role": "Skeppsred."
                    }
                ],
                "sales_manager": "Bernt Wahlström"
            }
        ]
    }
}