{
    "original": "Silfors—Silve r\n\nAkt.-kap.: 400,000 kr. Antal\nindustriarb.: 180. — Bolaget grundat 1938.\n\nStyrelse: adv. Stig Wiberg (ordf.), dir.\nJohn Löfström, dir. Eugen Weiss.\nVerkst. dir.: E. Weiss.\n\nSilfors Sågverks AB., Alfta.\n\nSågverk oeh hyvleri vid Silfors, Alfta\n(Gävleb. l.). Tillverkar sågade och\nhyvlade trävaror.\n\nTelegr.-adr.: Silfors, Bollnäs. Telefon:\nLånghed 10. Postgiro: 80486.\n\nAkt.-kap.: 35,000 kr. Antal\nindustriarb.: 65. Årstillv.: 1,500 stds hyvlade o.\n300 stds ohyvlade trävaror. — Bolaget\ngrundat 1909.\n\nVerkst. dir. o. disp.: C. Oscar Nyberg.\n\n*Warner Silfversparres Grafiska AB.,\n\nStockholm,\n\nKlichéanstalt och stämpelfabrik.\nTillverkar klichéer och kautschukstämplar.\nVarumärke: Fransk lilja.\n\nKontor: Herkulesgatan 22. Telefon:\n231330. Postgiro: 2667.\n\nAkt.-kap.: 80,000 kr. Antal\nindustriarb.: 23. Tillv.-värde pr år: 300,000 kr.\n\n—\tFirman etabl. 1885, bolag 1893.\nStyrelse: dir. Nils Lilja (ordf.), fröken\n\nG. Lilja.\n\nVerkst. dir.: N. Lilja.\n\nSiljans Sågverks AB.,\n\nMora Noret.\n\nSågverk, hyvleri och kolugn vid Mora\nNoret (Kopparb. l.). Tillverkar sågade\noch hyvlade trävaror samt träkol och\nträtjära.\n\nTelegr.-adr.: Siljanssågen, Mora.\nTelefon: Mora 55 o. 248. Postgiro: 6000.\n\nAkt.-kap.: 215,500 kr. Antal\nindustriarb.: 115. Årstillv. av trävaror: 3,000 stds.\n\n—\tBolaget grundat 1896, ombildat 1935.\nDisp.: Carl Ericsson.\n\n*Silkecellulosa, AB. Nordisk,\n\nNorrköping.\n\nSe AB. Nordisk Silkeeellulosa,\nNorrköping.\n\n^Silkefabriks AB. Astra, Smålands\nAnnéberg.\n\nKonstsilkeväveri och konfektionsfabrik\ni Smålands Anneberg samt\nkonstsidenvä-veri och konfektionsfabrik i Vetlanda\n(båda i Jönköp. l.). Tillverkar herr- och\ndamunderkläder, klänningar, blusar av\nkonstsilke-charmeuse och siden samt herr-\n\n611*\n\noch gosskjortor av konstsilke-charmeuse.\nSpecialiteter: damunderkläder o. blusar.\n\nHuvudkontor: Smålands Anneberg.\nTe-legr.-adr.: Silkastra, Nässjö. Telefon:\nNässjö 611 o. Smålands Anneberg 20.\nPostgiro: 97455. Avd.-kontor: Vetlanda;\ntelefon: 586.\n\nAkt.-kap.: 35,000 kr. Antal\nindustriarb.: 110. Tillv.-värde pr år: 1,800,000 kr\n\nBolaget grundat 1931 med\nverksamheten förlagd i Mölndal, överflyttades 1936\ntill Smålands Anneberg; fabriken i\nVetlanda startad 1943. Bolaget äges av\nJönköpings och Vulcans Tändsticksfabriks\nAB.\n\nStyrelse o. verkst. dir.: disp. Gösta\nBirgersson.\n\nFabrihsförest.: Erland Engdahl.\n\nAB. Siikemanufaktur, Stockholm.\n\nSilkeväveri och konfektionsfabrik.\nTillverkar damunderkläder.\n\nEontor: Igeldammsg. 24. Telefon:\n508537. Postgiro: 520.26.\n\nAkt.-kap.: 25,000 kr. Antal\nindustriarb.: 20. Tillv.-värde pr år: 300,000 kr.\n— Firman etabl. 1929, bolag 1930.\n\nVerkst. dir.: disp. Arvid Gustafson.\n\n*Sillbo Tegelbruk, Huddungeby.\n\nTillverkar tak- och murtegel samt\ndräneringsrör vid tegelbruk i Huddunge\n(Västmanl. l.).\n\nTelefon: Huddungeby 7.\nJärnvägsadress: Heby. — Antal industriarb.: 20.\nÅrstillv.: 1 milj. st. tegelvaror. —\nBruket grundat 1889.\n\nÄgare: Olsson &amp; Rosenlunds AB., Heby.\n\nTegelmästE. Bleckert.\n\nAB. Sillkungens Konservfabriker,\n\nSkärhamn.\n\nTillverkar ansjovis, gaffelbitar och\nkaviar vid fabrik i Skärhamn (Göteb. o.\nBohus l.). Varumärke: »Sikko».\n\nHuvudkontor: Lysekil. Fabrikskontor:\nSkärhamn; telefon: 73; telegr.-adr.:\nSillkungen, Skärhamn; postgiro: 85735;\n\nAntal industriarb.: 25. — Firman\netabl. 1933, bolag 1938.\n\nVerkst. dir.: E. Luckey.\n\nFabrihschef: Ivar Ohlsson.\n\n*Silver- &amp; Nysilver AB. Skandia,\n\nStockholm.\n\nUtför försilvring och polering av\nskedar, knivar, gafflar, skålar, fat m. m.\nVarumärke: »Skandia Silver Alpacca».\n\n/ä *\n)\"",
    "structured": {
        "1": {
            "name": "Silfors Sågverks AB.",
            "location": "Alfta",
            "business": "Tillverkar sågade och hyvlade trävaror",
            "contact": {
                "telegraph": "Silfors, Bollnäs",
                "phone": [
                    "Långhed 10"
                ],
                "postgiro": "80486"
            },
            "financials": {
                "capital": "400,000 kr",
                "employees": {
                    "industriarb": 180
                },
                "foundation_year": 1938
            }
        },
        "2": {
            "name": "Warner Silfversparres Grafiska AB.",
            "location": "Stockholm",
            "business": "Tillverkar klichéer och kautschukstämplar",
            "contact": {
                "office": "Herkulesgatan 22",
                "phone": [
                    "231330"
                ],
                "postgiro": "2667"
            },
            "financials": {
                "capital": "80,000 kr",
                "employees": {
                    "industriarb": 23
                },
                "annual_turnover": "300,000 kr"
            }
        },
        "3": {
            "name": "Siljans Sågverks AB.",
            "location": "Mora Noret",
            "business": "Tillverkar sågade och hyvlade trävaror samt träkol och trätjära",
            "contact": {
                "telegraph": "Siljanssågen, Mora",
                "phone": [
                    "Mora 55",
                    "248"
                ],
                "postgiro": "6000"
            },
            "financials": {
                "capital": "215,500 kr",
                "employees": {
                    "industriarb": 115
                },
                "annual_production_value": "3,000 stds"
            }
        },
        "4": {
            "name": "Silkefabriks AB. Astra",
            "location": "Smålands Annéberg",
            "business": "Konstsilkeväveri och konfektionsfabrik",
            "contact": {
                "telegraph": "Silkastra, Nässjö",
                "phone": [
                    "Nässjö 611",
                    "Smålands Anneberg 20"
                ],
                "postgiro": "97455",
                "sales_offices": [
                    {
                        "location": "Vetlanda",
                        "phone": "586"
                    }
                ]
            },
            "financials": {
                "capital": "35,000 kr",
                "employees": {
                    "industriarb": 110
                },
                "annual_production_value": "1,800,000 kr"
            }
        },
        "5": {
            "name": "AB. Siikemanufaktur",
            "location": "Stockholm",
            "business": "Silkeväveri och konfektionsfabrik",
            "contact": {
                "office": "Igeldammsg. 24",
                "phone": "508537",
                "postgiro": "520.26"
            },
            "financials": {
                "capital": "25,000 kr",
                "employees": {
                    "industriarb": 20
                },
                "annual_production_value": "300,000 kr"
            }
        },
        "6": {
            "name": "Sillbo Tegelbruk",
            "location": "Huddungeby",
            "business": "Tillverkar tak- och murtegel samt dräneringsrör",
            "contact": {
                "phone": "Huddungeby 7"
            },
            "financials": {
                "employees": {
                    "industriarb": 20
                }
            }
        },
        "7": {
            "name": "AB. Sillkungens Konservfabriker",
            "location": "Skärhamn",
            "business": "Tillverkar ansjovis, gaffelbitar och kaviar",
            "contact": {
                "office": "Lysekil",
                "fabrikskontor": "Skärhamn",
                "phone": "73",
                "postgiro": "85735"
            },
            "financials": {
                "employees": {
                    "industriarb": 25
                }
            }
        },
        "8": {
            "name": "Silver- & Nysilver AB. Skandia",
            "location": "Stockholm",
            "business": "Utför försilvring och polering av skedar, knivar, gafflar, skålar, fat m. m."
        }
    }
}