{
    "original": "Iföverken—Iggesund\n\n*AB. Iföverken, Bromölla.\n\nKaolinbrott och kaolinsl ammeri på\nIvö, chamottefabrik, porslinsfabrik och\ngolvplattfabrik i Bromölla (båda i\nKristianst. l.).\n\nBryter kaolin, eldfasta leror samt\nkvartsit; tillverkar elektrotekniskt\nporslin, säkringsproppar, kuhlodosor,\ndosinsatser, sanitetsporslin, eldfast tegel och\nmurbruk samt sintrade golvplattor;\nutför kompletta ugnsanläggningar för\ngasverk, kalkbruk, glasbruk m. fl. industrier\nsamt kremationsugnar.\n\nHuvudkontor: Bromölla; postadr.:\nBromölla 2. Telegr.-adr.: Iföverken,\nSölvesborg. Telefon: Sölvesborg 27250.\nPostgiro: 15100.\n\nRepresentanter: för eldfast tegel\noch murbruk i Stockholm: AB.\nKarta &amp; Oaxens Kalkbruk, Norr Mälarstrand\n22; telefon: »Karta-Oaxen»; för\nsanitetsporslin för mellersta och norra\nSverige: AB. Iföverken, Stockholm,\nDö-belnsg. 1, telefon: 110510; för\ngolvplattor: i Stockholm: Svenska\nPlattförsäljnings AB., Döbelnsg. 1, telefon:\n104726; för norra Sverige: Upsala-Ekeby\nAB., Ekebybruk.\n\nAkt.-kap.: 20,000,000 kr. Antal\nindustriarb.: 1,900. Tillv.-värde pr år:\n21,000,000 kr.\n\nBolaget, grundat 1927, utgör en\nsammanslagning av Ifö Cementfabriks AB.,\noch AB. Ifö Chamotte- &amp; Kaolinverk,\nbåda grundade 1909.\n\nStyrelse: majoren greve W. A. H.\nHa-milton (ordf.), disp. Nils Danielsen,\ngeneralkonsul G. M. I. Fagraeus,\nhovjäg-mäst. frih. W. Klingspor, dir. Carl\nJohan Malmros, generallöjtn. Bengt\nNordenskiöld, överstelöjtn. Carl O. A.\nNyström, dir. Ernst Wehtje.\n\nVerkst. dir.: Ernst Wehtje.\n\nVice dir.: Ernst J. Ydrén.\n\növering.: Olof Lund.\n\nFörsäljn.-chef er: för eldfast tegel: ing.\nÅ. Esbjörnsson; för elporslin: ing. O.\nMiöen; för sanitetsporslin o. golvplattor:\nE. Gard.\n\nInköpschef: Jacob Jacobsson.\n\n*lgelfors Bruks AB., Stockholm.\n\nManufaktur smed ja vid Igelfors\n(Östergötl. l.). Tillverkar liar, skäror,\nbandknivar och röjningsknivar. Varumärken:\n»Kron» o. »Banko». Bolaget idkar jämväl\njordbruk och skogshantering.\n\nKontor o. ensamförsälj.: AB. Odelberg\n&amp; Olson, Stockholm, Kungsg. 4 A.\nTelefon: »Odelbergolson». Postgiro: 1408.\n\nAkt.-kap.: 300,000 kr. Antal\nindustriarb.: 53. Tillv.-värde pr år: 500,000 kr.\n\n—\tBolaget grundat 1891.\n\nStyrelse: bruksdisp. Olof Hjorth (ordf.),\nadv. L. Levy, dir. Sven Ponsbach, dir.\nKarl Erik Tiblom, ing. Olof Tiblom.\n\nVerkst. dir.: S. Ponsbach.\n\nDisp. i Igelfors: Georg Holmquist.\n\nIgelsta Trävaru AB., Östertälje.\n\nSågverk och hyvleri, ångtork,\nsnickerifabrik samt träimpregneringsverk i\nIgelsta, östertälje (Sthlms l.). Tillverkar\nohyvlade och hyvlade trävaror samt\nträkol, snickerier och träull; utför\nimpreg-neringar av stolpar och sågat virke.\nVarumärke: IT A.\n\nTelegr.-adr. o. telefon: Igelsta trä,\nSödertälje. Postgiro: 92800.\n\nAkt.-kap.: 500,000 kr. Antal\nindustriarb.: 115. Årstillv.: 5,000 stds trävaror.\n\n—\tBolaget grundat 1928, ombildat 1936.\n\nStyrelse: bankdir. Marcus Wallenberg\n\n(ordf.), disp. Lars Amundsen, envoyén\nE. C:son Boheman, disp. Erik Bolin, disp.\nSten E. Holgersson, dir. Walter Wehtje.\n\nDisp.: Erik Bolin.\n\nInköpschef: forstmäst. G. Tiderman.\n\n’AB. Iggesunds Bruk, Iggesund.\n\nJärnverk med masugnar, bessemerverk,\nlancashiresmedja, valsverk,\nånghammarsmedja, sågbladsfabrik, gjuteri och mek.\nverkstad; sulfat- och sulfitfabriker,\nsulfitspritfabrik, träsliperi samt fartygsslip,\nallt vid Iggesund; masugn och\nwallon-smedja vid Strömbacka; sågverk med\nhyvleri, lådfabrik, golvparkettfabrik samt\nträmjöls-, trähus- och snickerifabrik vid\nHåstaholmen, Hudiksvall (samtl. verk i\nGävleb. l.).\n\nTillverkar tackjärn, bessemergöt, smitt\noch valsat järn och stål, wallonjärn,\nramsågblad, cirkelsågar, fällningssågar,\nma-skinhyveljärn och maskinknivar,\nsulfat-och sulfitcellulosa, sulfitsprit, jäst, harts\noch terpentin, mek. trämassa, sågade och\nhyvlade trävaror, golvparkett, lådämnen,\nmonteringsfärdiga trähus, snickerier,\nträmjöl m. m. Bolaget idkar jämväl\njordbruk och skogshantering samt äger\nandelar i Dannemora, Vigelsbo, Tuolluvaara\noch Kolningsbergs m. fl. gruvor.\n\nHuvudkontor: Iggesund. Telegr.-adr.:\nIggesund, Hudiksvall; för trävaror:\nTrävarubolaget, Hudiksvall. Postgiro: 76700.\nFörsälj, för monteringsfärdiga trähus:\nAB. Svenska Trähus, Stockholm, Birger\nJarlsg. 27, telefon: »Svenska Trähus».\n\nAkt.-kap.: 18,000,000 kr. Antal\nindustriarb.: 1,250. Årstillv.: 28,000 stds sågade\nträvaror och lådämnen, varav 10,000 stds",
    "structured": {
        "1": {
            "name": "Iföverken",
            "location": "Bromölla",
            "business": "Kaolinbrott och kaolinsl ammeri på Ivö, chamottefabrik, porslinsfabrik och golvplattfabrik i Bromölla (båda i Kristianst. l.)",
            "products": "Bryter kaolin, eldfasta leror samt kvartsit; tillverkar elektrotekniskt porslin, säkringsproppar, kuhlodosor, dosinsatser, sanitetsporslin, eldfast tegel och murbruk samt sintrade golvplattor; utför kompletta ugnsanläggningar för gasverk, kalkbruk, glasbruk m. fl. industrier samt kremationsugnar.",
            "contact": {
                "office": "Bromölla",
                "phone": [
                    "Sölvesborg 27250"
                ],
                "postgiro": "15100",
                "head_office": "Bromölla; postadr. Bromölla 2",
                "telegraph": "Iföverken, Sölvesborg"
            },
            "financials": {
                "capital": "20,000,000 kr",
                "employees": {
                    "Antal industriarb.": 1900
                },
                "annual_turnover": "21,000,000 kr",
                "annual_production_value": "21,000,000 kr"
            },
            "foundation_year": 1927,
            "original_name": "AB. Ifö Cementfabriks AB., och AB. Ifö Chamotte- & Kaolinverk"
        },
        "2": {
            "name": "Igelfors Bruks AB.",
            "location": "Stockholm",
            "business": "Manufactursmedja vid Igelfors (Östergötl. l.).",
            "products": "Tillverkar liar, skäror, bandknivar och röjningsknivar. Varumärken: »Kron» o. »Banko». Bolaget idkar jämväl jordbruk och skogshantering.",
            "contact": {
                "office": "AB. Odelberg & Olson, Stockholm, Kungsg. 4 A",
                "phone": [
                    "Odelbergolson"
                ],
                "postgiro": "1408"
            },
            "financials": {
                "capital": "300,000 kr",
                "employees": {
                    "Antal industriarb.": 53
                },
                "annual_turnover": "500,000 kr"
            },
            "foundation_year": 1891
        },
        "3": {
            "name": "Igelsta Trävaru AB.",
            "location": "Östertälje",
            "business": "Sågverk och hyvleri, ångtork, snickerifabrik samt träimpregneringsverk i Igelsta, östertälje (Sthlms l.).",
            "products": "Tillverkar ohyvlade och hyvlade trävaror samt träkol, snickerier och träull; utför impregneringar av stolpar och sågat virke. Varumärke: IT A.",
            "contact": {
                "office": "Igelsta, Södertälje",
                "phone": [
                    "Igelsta trä"
                ],
                "postgiro": "92800"
            },
            "financials": {
                "capital": "500,000 kr",
                "employees": {
                    "Antal industriarb.": 115
                },
                "annual_production_value": "5,000 stds trävaror"
            },
            "foundation_year": 1928
        },
        "4": {
            "name": "AB. Iggesunds Bruk",
            "location": "Iggesund",
            "business": "Järnverk med masugnar, bessemerverk, lancashiresmedja, valsverk, ånghammarsmedja, sågbladsfabrik, gjuteri och mek. verkstad; sulfat- och sulfitfabriker, sulfitspritfabrik, träsliperi samt fartygsslip, allt vid Iggesund; masugn och wallonsmedja vid Strömbacka; sågverk med hyvleri, lådfabrik, golvparkettfabrik samt trä!"
        }
    }
}