{
    "original": "Träkons truktio ner—Trä varu\n\nTelegr.-adr.: Träkol, Vansbro. Telefon:\n55, 255 o. 175. Postgiro: 8772.\n\nAkt.-kap.: 750,000 kr. Antal\nindustriarb.: 150. Tillv.-värde pr år: 2,500,000 kr.\n\n—\tBolaget grundat 1889.\n\nStyrelse: skogschef G. Wesslén (ordf.),\ndisp. Bengt Carleson, dir. A. Wahlsteen.\n\nVerkst. dir. o. disp.: Folke Lunell.\n\n\"Träkonstruktioner, AB. Fribärande,\n\nTöreboda.\n\nSe AB. Fribärande Träkonstruktioner,\nTöreboda.\n\nTrälleborg, se Treileborg.\n\nAB. Trämanufaktur, Värnamo.\n\nSe E. Bergwall, Värnamo.\n\n\"Träspecialen, David Johansson,\n\nSmålandsstenar.\n\nSnickerifabrik i Smålandsstenar\n(Jönköp. l.). Tillverkar fällbara bord med\nmasoniteskiva (märke: »Fix»).\n\nTelefon: 66. Postgiro: 86457. Repr. i\nStockholm: Åke Gille, Stockholm,\nKam-makarg. 54, telefon: 105933. — Antal\nindustriarb.: 14. Tillv.-värde pr år:\n200,000 kr. — Firman etabl. 1934, nuv.\nnamn 1940.\n\nÄgare o. chef: fru Carin Johansson.\n\nTräullit, AB., Köping.\n\nTillverkar träullsplattor för\nbyggnadsändamål. Varumärke: »Träullit».\nSpecialitet : armerade träullsplattor.\n\nTelegr.-adr.: Träullit, Köping. Telefon:\n1313 o. 1350. Postgiro :q 251690.\nFörsäljn.-kontor: Stockholm, Rådmansg. 56,\ntelefon: 232575.\n\nAkt.-kap.: 150,000 kr. Antal\nindustriarb.: 80. Tillv.-värde pr år: 1,500,000 kr.\n\n—\tBolaget grundat 1943.\n\nStyrelse o. verkst. direktörer: disp.\nViggo Hanzon o. ing. Henrik Mattsson.\n\nDriftsing.: Henry Wallestam.\n\nKamrer: Bertil Bengtsson.\n\n\"Träullsbolaget Export, Forserum.\n\nTillverkar träull vid fabrik i Forserum\n(Jönköp. l.).\n\nTelefon: 52. Postgiro: 137170. —\nAntal industriarb.: 6. Tillv.-värde pr år:\n120,000 kr. — Firman etabl. 1928.\n\nÄgare o. chef: fabr. Albert Blomkvist.\n\n\"Trävaru AB. Braås, Braås.\n\nSe AB. Böksholms Sulfitfabrik,\nKlippan,\n\n\"Trävaru AB. Dalarne, Vansbro.\n\nElektrisk kraftstation vid Eldforsen,\nTretjärn (Kopparb. l.). Distribuerar\nelektr. energi.\n\nTelegr.-adr.: Dalarne, Vansbro.\nTelefon: 61. Postgiro: 85188.\n\nAkt.-kap.: 2,500,000 kr.\nDistributionskapacitet pr år: 19,000,000 kWh.\n\nBolaget, grundat 1892, äges av Korsnäs\nSågverks AB., Gävle.\n\nStyrelse: kabinettskammarh. Robert v.\nHorn (ordf.), dir. Sven Engwall, dir.\nErik W. Eriksson, f. d. överfyring. Folke\nLundeberg, adv. Hugo Stenbeck.\n\nFörvalt.: Ernst Tingdal.\n\n\"Trävaruindustrin, B. Johansson,\n\nSmålandsstenar.\n\nTillverkar turistsängar och balkongbord\nvid snickerifabrik i Smålandsstenar\n(Jönköp. l.).\n\nTelefon: 214. Postgiro: 281951. —\nAntal industriarb.: 12. Tillv.-värde pr år:\n200,000 kr. — Firman etabl. 1944.\n\nÄgare o. chef: fabr. Bertil Johansson.\n\n\"Trävaru AB. N. Chr. Jensen,\n\nKarlstad.\n\nSågverk vid Bergholmen, hyvleri och\nlådfabrik vid Orrholmen (båda i Värml.\n1.). Tillverkar sågade och hyvlade\nträvaror, lådbräder samt monteringsfärdiga\nträhus.\n\nTelegr.-adr.: Jensen, Karlstad.\nTelefon: 10475, 10833 o. 10021. Postgiro:\n73316.\n\nAkt.-kap.: 400,000 kr. Antal\nindustriarb.: 100. Årstillv.: 8,000 stds trävaror.\n\n—\tFirman grundad 1905.\n\nStyrelse: hemmansäg. Daniel\nDanielson, dir. Per Danils, v. konsul N. Chr.\nJensen, disp. Sven Karlsson, jägm. Sven\nPersson.\n\nVerkst. dir.: Sven Karlsson.\n\n\"Trävaru AB. Kronoberg, Räppe.\n\nLådfabrik och hyvleri vid Räppe\n(Kronob. l.). Tillverkar lådämnen och\nhyvlade trävaror, bryggerilådor,\npacklådor, fatbottnar och halvfabrikat för\nleksaksindustrien.\n\nTelegr.-adr.: Krono, Växjö. Telefon:\nVäxjö 6040. Postgiro: 34876.\n\nAkt.-kap.: 200,000 kr. Antal\nindustriarb.: 50. Årstillv.: 3,000 stds trävaror.\n\n—\tBolaget grundat 1922.\n\nStyrelse: grossh. Adolf Johansson\n(ordf.), trävaruhandl. Johan Andersson,\nträvaruhandl. Aug. Danielsson,\nträvaruhandl. Joh. Fransson, trävaruhandl. Gus-",
    "structured": {
        "1": {
            "name": "Träkons truktio ner—Trä varu",
            "location": "Vansbro",
            "business": "Trävaru",
            "contact": {
                "telegraph": "Träkol, Vansbro",
                "phone": [
                    "55",
                    "255",
                    "175"
                ],
                "postgiro": "8772"
            },
            "financials": {
                "capital": "750,000 kr",
                "employees": {
                    "industrial": 150
                },
                "annual_turnover": "2,500,000 kr",
                "annual_production_value": "2,500,000 kr"
            },
            "foundation_year": 1889,
            "board": [
                {
                    "name": "G. Wesslén",
                    "role": "skogschef (ordf.)"
                },
                {
                    "name": "Bengt Carleson",
                    "role": "disp."
                },
                {
                    "name": "A. Wahlsteen",
                    "role": "dir."
                }
            ],
            "director": "Folke Lunell"
        },
        "2": {
            "name": "Träkonstruktioner, AB. Fribärande",
            "location": "Töreboda",
            "business": "Fribärande Träkonstruktioner"
        },
        "3": {
            "name": "Trämanufaktur, Värnamo",
            "location": "Värnamo",
            "business": "E. Bergwall"
        },
        "4": {
            "name": "Träspecialen, David Johansson",
            "location": "Smålandsstenar",
            "business": "Snickerifabrik",
            "products": "fällbara bord med masoniteskiva (märke: »Fix»)",
            "contact": {
                "phone": "66",
                "postgiro": "86457"
            },
            "financials": {
                "employees": {
                    "industrial": 14
                },
                "annual_turnover": "200,000 kr"
            },
            "foundation_year": 1934,
            "current_name_year": 1940,
            "owners": [
                "fru Carin Johansson"
            ]
        },
        "5": {
            "name": "Träullit, AB.",
            "location": "Köping",
            "business": "Träullsplattor",
            "products": "armerade träullsplattor",
            "contact": {
                "telegraph": "Träullit, Köping",
                "phone": [
                    "1313",
                    "1350"
                ],
                "postgiro": "251690"
            },
            "financials": {
                "capital": "150,000 kr",
                "employees": {
                    "industrial": 80
                },
                "annual_turnover": "1,500,000 kr"
            },
            "foundation_year": 1943,
            "board": [
                {
                    "name": "Viggo Hanzon",
                    "role": "disp."
                },
                {
                    "name": "Henrik Mattsson",
                    "role": "ing."
                }
            ],
            "director": "Henry Wallestam"
        },
        "6": {
            "name": "Träullsbolaget Export, Forserum",
            "location": "Forserum",
            "business": "Träull"
        },
        "7": {
            "name": "Trävaru AB. Braås",
            "location": "Braås",
            "business": "AB. Böksholms Sulfitfabrik"
        },
        "8": {
            "name": "Trävaru AB. Dalarne",
            "location": "Vansbro",
            "business": "Elektrisk kraftstation",
            "products": "distribuerar elektr. energi",
            "contact": {
                "telegraph": "Dalarne, Vansbro",
                "phone": "61",
                "postgiro": "85188"
            },
            "financials": {
                "capital": "2,500,000 kr",
                "annual_turnover": "19,000,000 kWh"
            },
            "foundation_year": 1892,
            "owners": [
                "Korsnäs Sågverks AB., Gävle"
            ]
        },
        "9": {
            "name": "Trävaruindustrin, B. Johansson",
            "location": "Smålandsstenar",
            "business": "Snickerifabrik",
            "products": "turistsängar, balkongbord",
            "contact": {
                "phone": "214",
                "postgiro": "281951"
            },
            "financials": {
                "employees": {
                    "industrial": 12
                },
                "annual_turnover": "200,000 kr"
            },
            "foundation_year": 1944,
            "owners": [
                "fabr. Bertil Johansson"
            ]
        },
        "10": {
            "name": "Trävaru AB. N. Chr. Jensen",
            "location": "Karlstad",
            "business": "Sågverk, hyvleri, lådfabrik, trähus"
        },
        "11": {
            "name": "Trävaru AB. Kronoberg",
            "location": "Räppe",
            "business": "Lådfabrik, hyvleri",
            "products": "lådämnen, bryggerilådor, packlådor, fatbottnar"
        }
    }
}