{
    "original": "Klichéanstalten—Klippan\n\nAkt.-kap.: 18,000 kr. Arb.-antal: 15.\nTillv.-värde pr år: 230,000 kr. — Firman\netabl. 1921, bolag 1941.\n\nStyrelse: fabr. Gustav Ahlstedt, fabr.\nAxel Johanson, fabr. Einar Ohlson.\nVerkst. dir.: Axel Johanson.\n\nAB. Klichéanstalten Petit,\n\nGöteborg.\n\nUtför klichéer, retuscher och\nteckningar.\n\nKontor: Odinsg. 2. Telefon: 152262—\n63. Postgiro: 40475. — Akt.-kap.: 25,000\nkr. Antal industriarb.: 24. Tillv.-värde\npr år: 295,000 kr. — Bolaget grundat\n1926.\n\nVerkst. dir.: John Andersson.\n\nKlichécentralen, Stockholm.\n\nTillverkar klichéer och retuscher.\nKontor: Kl. S. Kyrkog. 11. Telefon:\n102480 o. 118757. Postgiro: 54858. —\nAntal industriarb.: 25. Tillv.-värde pr år:\n200,000 kr. — Firman etabl. 1921.\nÄgare o. chef: fabr. Erik Olauson.\n\n\"Klint, Bernhardt &amp; Co. AB.,\n\nStockholm.\n\nFärg- och fernissfabrik.\n\nTillverkar kopal- och spritfernissor\n(»Klintlack» o. »Industrilack»),\nzapon-lack, kokt linolja, faktorolja, lack- och\noljefärger (»Svealack»),\nskeppsbotten-och pansarfärg, cellulosalacker och\n-färger (»Bernolin», »Mero»),\nklorkautschuk-lack (»Cautex»), syntetisk lackfärg\n(»Bernax»), syntetiska emulsionsfärger\n(»Kåbecit» o. »Kåbelin»), kitt,\ntorkpre-parater, spackelfärg, artistfärger,\nfärg-borttagningsmedel (»Solventol»), löd\nvätska (»Acidol»), rostborttagningsmedel\n(»Puritol») m. m. samt\nimpregnerings-medel för wallboard.\n\nFirman driver jämväl engroshandel\nmed torra färger, kemikalier, oljor,\nkem.-tekn. artiklar samt detaljhandel genom\nåtta egna minutaffärer i Stockholm.\n\nKontor: Saltmätarg. 19 A; postadr.:\nStockholm 3. Telegr.-adr. o. telefon:\nKlintbernhardt, Stockholm. Postgiro: 33.\n\nAkt.-kap.: 1,000,000 kr. Antal\nindustriarb.: 94. Tillv.-värde pr år: 5,000,000 kr.\n— Firman etabl. 1873, bolag 1944.\n\nStyrelse: dir. John A. Klint (ordf.),\nadv. Adolf Körner, dir. Gunnar Malmvik.\n\nVerkst. direktörer: John A. Klint o.\nGunnar Malmvik.\n\nFabrikschefer: ing. B. Heijmer o. tekn.\nlic. Ivar Huss.\n\nAB. Klintebys Konservfabrik,\n\nKlintehamn.\n\nKonservfabrik i Klintehamn (Gotl. l.).\nTillverkar frukt- och grönsakskonserver.\nSpecialiteter: sparris och\ndelikatessgurkor. Varumärke: »Hansa».\n\nTelegr.-adr.: Klintekonserv, Visby.\nTelefon: Klintehamn 25. Postgiro: 80849.\nRepr. i Stockholm: Riksost, Vasag. 16,\ntelefon: »Riksost».\n\nAkt.-kap.: 78,200 kr. Antal\nindustriarb.: -54. Tillv.-värde pr år: 1,300,000 kr.\n— Firman etabl. 1915, nuv. namn o.\nbolag 1932.\n\nDisp. o. verkst. dir.: Melcher Paulsson.\nKamrer: E. F. Allard.\n\n\"Klippans Bryggeri, Klippan.\n\nSe AB. Skånebryggerier, Hälsingborg.\n\n\"AB. Klippans Finpappersbruk,\n\nKlippan.\n\nPappersbruk, kartongfabrik och\npappersförädling i Klippan (Kristianst. l.).\nTillverkar tryck-, dokument-, post- och\nskrivpapper, kopiepapper,\ngenomslagspapper, luftpostpapper, silkespapper,\nkräpp- och vaxpapper, papeterier,\npap-persservietter, kartong m. m.\n\nTelegr.-adr. o. telefon: Pappersbruket,\nKlippan. Postgiro: 80041. Ensamförsäljn.\nför Sverige: Finpappersbrukens\nFörsäljnings AB., Stockholm, Göteborg och\nMalmö. Exportförsäljning direkt från\nhuvudkontoret i Klippan.\n\nAkt.-kap.: 7,000,000 kr. Antal\nindustriarb.: 625. Årstillv.: 6,500 ton papper o.\nkartong.\n\nPappersbruket anlagt år 1573,\naktiebolag 1870.\n\nAB. Klippans Finpappersbruk äger\näven Lessebo AB., AB. Lessebo Skogar,\nAB. Böksholms Sulfitfabrik och Konga\nAB. Arb.-antal vid hela koncernen:\n1.400. Årstill verkning vid koncernen:\n18,000 ton papper o. kartong, 18,000 ton\nsulfitcellulosa, huvudsakligen för eget\nbehov, 6,000 stds trävaror, 12,000 ton\nindunstad sulfitlut.\n\nStyrelse: bankir Tage Cervin (ordf.),\nbankdir. Allan Alexanderson, dir. P. Eg.\nGummeson, f. d. baakdir. H. K.\nLaurit-zen, dir. Carl Joh. Malmros.\n\nVerkst. dir. o. disp.: Carl Joh.\nMalmros.\n\nDir .-assistenter: Josef Larson o. Gustaf\nWetterling.\n\nKontorschef: Josef Larson.\n\növering.: Gustaf Wetterling.",
    "structured": {
        "firms": [
            {
                "name": "Klichéanstalten—Klippan",
                "location": "Klippan",
                "business": "Klichéer, retuscher och teckningar",
                "contact": {
                    "office": "Odinsg. 2",
                    "phone": [
                        "152262",
                        "63"
                    ],
                    "postgiro": "40475"
                },
                "financials": {
                    "capital": "18,000 kr",
                    "employees": {
                        "total": 15
                    },
                    "annual_turnover": "230,000 kr"
                },
                "foundation_year": 1921,
                "corporation_year": 1941,
                "board": [
                    {
                        "name": "fabr. Gustav Ahlstedt",
                        "role": "Styrelseledamot"
                    },
                    {
                        "name": "fabr. Axel Johanson",
                        "role": "Styrelseledamot"
                    },
                    {
                        "name": "fabr. Einar Ohlson",
                        "role": "Styrelseledamot"
                    }
                ],
                "director": "Axel Johanson"
            },
            {
                "name": "AB. Klichéanstalten Petit",
                "location": "Göteborg",
                "business": "Klichéer, retuscher och teckningar",
                "contact": {
                    "office": "Unknown",
                    "phone": [
                        "152262",
                        "63"
                    ],
                    "postgiro": "40475"
                },
                "financials": {
                    "capital": "25,000 kr",
                    "employees": {
                        "total": 24
                    },
                    "annual_turnover": "295,000 kr"
                },
                "foundation_year": 1926,
                "board": [
                    {
                        "name": "John Andersson",
                        "role": "Verkst. dir."
                    }
                ]
            },
            {
                "name": "Klichécentralen",
                "location": "Stockholm",
                "business": "Klichéer och retuscher",
                "contact": {
                    "office": "Kl. S. Kyrkog. 11",
                    "phone": [
                        "102480",
                        "118757"
                    ],
                    "postgiro": "54858"
                },
                "financials": {
                    "employees": {
                        "total": 25
                    },
                    "annual_turnover": "200,000 kr"
                },
                "foundation_year": 1921,
                "owner": "fabr. Erik Olauson"
            },
            {
                "name": "Klint, Bernhardt & Co. AB.",
                "location": "Stockholm",
                "business": "Färg- och fernissfabrik",
                "contact": {
                    "office": "Saltmätarg. 19 A",
                    "postgiro": "33"
                },
                "financials": {
                    "capital": "1,000,000 kr",
                    "employees": {
                        "total": 94
                    },
                    "annual_turnover": "5,000,000 kr"
                },
                "foundation_year": 1873,
                "corporation_year": 1944,
                "board": [
                    {
                        "name": "dir. John A. Klint",
                        "role": "Styrelseordförande"
                    },
                    {
                        "name": "adv. Adolf Körner",
                        "role": "Styrelseledamot"
                    },
                    {
                        "name": "dir. Gunnar Malmvik",
                        "role": "Styrelseledamot"
                    }
                ],
                "managing_director": "John A. Klint",
                "factory_managers": [
                    "ing. B. Heijmer",
                    "tekn. lic. Ivar Huss"
                ]
            },
            {
                "name": "AB. Klintebys Konservfabrik",
                "location": "Klintehamn",
                "business": "Konservfabrik",
                "contact": {
                    "phone": "Klintehamn 25",
                    "postgiro": "80849"
                },
                "financials": {
                    "capital": "78,200 kr",
                    "employees": {
                        "total": 54
                    },
                    "annual_turnover": "1,300,000 kr"
                },
                "foundation_year": 1915,
                "corporation_year": 1932,
                "director": "Melcher Paulsson",
                "finance_manager": "E. F. Allard"
            },
            {
                "name": "AB. Klippans Finpappersbruk",
                "location": "Klippan",
                "business": "Pappersbruk, kartongfabrik och pappersförädling",
                "contact": {
                    "office": "Unknown",
                    "postgiro": "80041"
                },
                "financials": {
                    "capital": "7,000,000 kr",
                    "employees": {
                        "total": 625
                    },
                    "annual_production_value": "6,500 ton papper o. kartong"
                },
                "foundation_year": 1573
            }
        ]
    }
}