{
    "original": "Betong-—Billerud\n\n*AB. Betong och Järn, Stockholm.\n\nByggnadsentreprenörfirma för\nväg-och vattenbyggnadsarbeten,\nindustribyggnader m. m.\n\nKontor: Norrlandsg. 16. Telegr.-adr.:\nBetojär, Stockholm. Telefon: 105028 o.\n201958.\n\nAkt.-kap.: 22,000 kr. Prod.-värde pr\når: 1,000,000 kr. — Bolaget grundat 1928.\n\nStyrelse o. verkst. dir.: civiling.\nHarald Linde.\n\nArbetschef: ing. Axel Rosenblom.\n\nAB. Betongklinker, Stockholm.\n\nSe Stavsborgs AB., Stockholm.\n\nBeus &amp; Mattson AB., Mora.\n\nTillverkar skogsinstrument såsom\ntillväxtborrar, tumklovar m. m., torvborrar\nsamt biljettkontrolltänger för järnvägar\nm. m. vid mek. verkstad i Mora\n(Kopparb. l.).\n\nTelefon: 32. Postgiro: 28578. —\nAkt.-kap.: 15,000 kr. Tillv.-värde pr år: 80,000\nkr. — Firman etabl. 1895, bolag 1938.\n\nVerkst. dir.: ing. Johannes\nMattson-Djos.\n\n*AB. Béve &amp; C:nis Kappfabrik,\n\nStockholm.\n\nTillverkar damkappor och damdräkter.\n\nKontor: N:a Stationsg. 79—81.\nTelegr.-adr.: Bevecompani, Stockholm. Telefon:\n234020. Postgiro: 152534.\n\nAkt.-kap.: 300,000 kr. Antal\nindustriarb.: 300. Tillv.-värde pr år: 5,000,000\nkr. — Firman grundad 1855, bolag 1901.\n\nStyrelse: bankdir. Ando Wikström\n(ordf.), dir. Nils Kärrlander, ad v. Sven\nMunck af Rosenschöld, fru Elsa öhman,\ndir. Erik öhman.\n\nVerkst. dir.: Erik öhman.\n\nV. verkst. dir.: Bertil Falk.\n\nBeyronds AB., Malmö.\n\nPartibokbinderi och boktryckeri.\nTillverkar amatöralbum, skrivunderlägg,\nportföljer, bok-, telegram- och\nadresspärmar, dag- och gästböcker, spelschatull,\nTädergalanterivaror, reklamartiklar m. m.\n\nKontor: Nya Vatten verksvägen 1.\nTelegr.-adr.: Bokbeyrond, Malmö. Telefon:\n72170. Postgiro: 37592.\n\nAkt.-kap.: 90,000 kr. Tillv.-värde pr år:\n1,500,000 kr. — Firman etabl. 1916,\nbolag 1929.\n\nStyrelse o. verkst. dir.: Gösta Beyrond.\n\nBiideve i Munkaljungby AB.,\n\nMunkaljungby.\n\nMek. verkstad i Munkaljungby (Kris-’\ntianst. l.). Tillverkar hydrauliska\nlyftredskap och verktyg för bilservice,\nindustri och andra ändamål.\n\nTelefon: 49 o. 209. Postgiro: 167394.\n\n—\tAkt.-kap.: 100,000 kr. Antal\nindustriarb.: 37. Tillv.-värde pr år: 500,000 kr.\n\n—\tVerkstaden anlagd 1920, nuv. bolag\ngrundat 1943.\n\nVerkst. dir.: Nils Viebke.\n\nBilindustri, Blidsberg.\n\nTillverkar hydrauliska tippanordningar\nför lastbilar, bilflak, släpvagnar och andra\nlastbilsbyggnationer vid mek. verkstad\ni Blidsberg (Älvsb. l.).\n\nTelefon: 19. Postgiro: 145516. —\nAndelskapital: 150,000 kr. Antal\nindustriarb.: 50. Tillv.-värde pr år: 800,000 kr.\n— Firman etabl. 1938.\n\nDelägare: fabr. Gustaf L. Andersson,\nfabr. A. Verner Andersson o. fabr. Alrik\nJ. Nyström.\n\n*Billeruds AB., Säffle.\n\nSulfitfabriker vid Billerud, Kyrkebyn,\nSlottsbron och Jössefors, sulfatfabrik\nmed reningsverk vid Gruvön,\npappersbruk vid Billerud, Gruvön och Jössefors\nsamt papperssäckfabrik vid Gruvön,\nsågverk med hyvleri och lådfabrik vid\nGruvön och Hillringsberg samt\nsulfitspritfabriker vid Billerud, Slottsbron och\nJössefors (samti. i Värml. l.).\n\nTillverkar torr blekt sulfitcellulosa för\nsåväl pappers- som konstsilketillverkning,\nädelcellulosa, blekt och oblekt våt\nsulfitmassa, stark sulfatmassa, blekt och\noblekt greaseproofpapper, pergamyn,\npa-raffinerat papper, M. G.- och oglättat\nkraftpapper, såväl blekt som oblekt,\nklistrade, sydda och nitade\nkraftpapperssäc-kar, M. G.-sulfitpapper (rent och\nslip-blandat), sulfitsprit, råterpentin,\nflytande harts (sulfatharts), sågade och hyvlade\nträvaror, lådämnen m. m.\n\n^ Bolaget äger elektriska\nvattenkraftstationer vid Borgvik, Hillringsberg,\nJössefors, Brättne, Charlottenberg, Torsby och\nRämen. Från Charlottenbergs och\nTors-by kraftstationer distribueras elektrisk\nenergi till resp. Charlottenbergs och\nTorsby samhällen. — Bolaget idkar\njämväl skogshantering, jordbruk och\nrederirörelse.\n\nHuvudkontor (varigenom alla inköp och\n\nförsäljningar ske): Säffle. Telegr.-adr. o.",
    "structured": {
        "firms": [
            {
                "name": "AB. Betong och Järn",
                "location": "Stockholm",
                "business": "Byggnadsentreprenörfirma för väg-och vattenbyggnadsarbeten, industribyggnader m. m.",
                "contact": {
                    "office": "Norrlandsg. 16",
                    "telegraph": "Betojär, Stockholm",
                    "phone": [
                        "105028",
                        "201958"
                    ]
                },
                "financials": {
                    "capital": "22,000 kr",
                    "annual_production_value": "1,000,000 kr"
                },
                "foundation_year": 1928,
                "board": [
                    {
                        "name": "civiling. Harald Linde",
                        "role": "Styrelse o. verkst. dir."
                    }
                ],
                "director": "civiling. Harald Linde",
                "managing_director": "ing. Axel Rosenblom"
            },
            {
                "name": "AB. Betongklinker",
                "location": "Stockholm",
                "business": "Tillverkar skogsinstrument såsom tillväxtborrar, tumklovar m. m., torvborrar samt biljettkontrolltänger för järnvägar m. m.",
                "phone": "32",
                "postgiro": "28578",
                "financials": {
                    "capital": "15,000 kr",
                    "annual_production_value": "80,000 kr"
                },
                "foundation_year": 1895,
                "corporation_year": 1938,
                "director": "ing. Johannes Mattson-Djos"
            },
            {
                "name": "AB. Béve & C:nis Kappfabrik",
                "location": "Stockholm",
                "business": "Tillverkar damkappor och damdräkter.",
                "contact": {
                    "office": "N:a Stationsg. 79—81",
                    "telegraph": "Bevecompani, Stockholm",
                    "phone": "234020",
                    "postgiro": "152534"
                },
                "financials": {
                    "capital": "300,000 kr",
                    "employees": {
                        "Antal industriarb.": 300
                    },
                    "annual_production_value": "5,000,000 kr"
                },
                "foundation_year": 1855,
                "corporation_year": 1901,
                "board": [
                    {
                        "name": "bankdir. Ando Wikström",
                        "role": "Styrelse"
                    },
                    {
                        "name": "dir. Erik öhman",
                        "role": "Verkst. dir."
                    },
                    {
                        "name": "Bertil Falk",
                        "role": "V. verkst. dir."
                    }
                ]
            },
            {
                "name": "Beyronds AB.",
                "location": "Malmö",
                "business": "Partibokbinderi och boktryckeri. Tillverkar amatöralbum, skrivunderlägg, portföljer, bok-, telegram- och adresspärmar, dag- och gästböcker, spelschatull, Tädergalanterivaror, reklamartiklar m. m.",
                "contact": {
                    "office": "Nya Vattenverksvägen 1",
                    "telegraph": "Bokbeyrond, Malmö",
                    "phone": "72170",
                    "postgiro": "37592"
                },
                "financials": {
                    "capital": "90,000 kr",
                    "annual_production_value": "1,500,000 kr"
                },
                "foundation_year": 1916,
                "corporation_year": 1929,
                "director": "Gösta Beyrond"
            },
            {
                "name": "Biideve i Munkaljungby AB.",
                "location": "Munkaljungby",
                "business": "Mek. verkstad i Munkaljungby (Kristianst. l.). Tillverkar hydrauliska lyftredskap och verktyg för bilservice, industri och andra ändamål.",
                "phone": [
                    "49",
                    "209"
                ],
                "postgiro": "167394",
                "financials": {
                    "capital": "100,000 kr",
                    "employees": {
                        "Antal industriarb.": 37
                    },
                    "annual_production_value": "500,000 kr"
                },
                "corporation_year": 1943,
                "director": "Nils Viebke"
            },
            {
                "name": "Bilindustri",
                "location": "Blidsberg",
                "business": "Tillverkar hydrauliska tippanordningar för lastbilar, bilflak, släpvagnar och andra lastbilsbyggnationer vid mek. verkstad i Blidsberg (Älvsb. l.).",
                "phone": "19",
                "postgiro": "145516",
                "financials": {
                    "capital": "150,000 kr",
                    "employees": {
                        "Antal industriarb.": 50
                    },
                    "annual_production_value": "800,000 kr"
                },
                "foundation_year": 1938,
                "owners": [
                    "fabr. Gustaf L. Andersson",
                    "fabr. A. Verner Andersson",
                    "fabr. Alrik J. Nyström"
                ]
            },
            {
                "name": "Billeruds AB.",
                "location": "Säffle",
                "business": "Sulfitfabriker, sulfatfabrik, pappersbruk, papperssäckfabrik, sågverk, sulfitspritfabriker, torr blekt sulfitcellulosa, ädelcellulosa, papper, trävaror, skogshantering, jordbruk, rederirörelse, elektriska vattenkraftstationer.",
                "contact": {
                    "office": "Säffle"
                },
                "financials": {
                    "annual_turnover": "not disclosed"
                }
            }
        ]
    }
}