{
    "original": "Oxelösund—Palm\n\n^Oxelösunds Järnverks AB.,\n\nOxelösund.\n\nJärnverk med sintringsverk och\nkoksmasugn, koksverk med biproduktsverk\nsamt fönsterglasverk i Oxelösund\n(Södermanl. l.).\n\nTillverkar sinter, kokstackjärn alla slag,\nkoks samt tjära, ammoniumsulfat, bensol,\nsolventnafta, toluol, xylol m. fl.\ndestillationsprodukter ävensom maskindraget\nfönsterglas. Varumärke: »OJA».\n\nTelegr.-adr. o. telefon: Järnverket,\nOxelösund. Postgiro: 71560.\nEnsamförsälj. för koksverksbiprodukter: Gas- o.\nKoksverkens Ekonomiska Förening u. p. a.,\nStockholm, Florag. 14, telefon: 238565.\n\nAkt.-kap.: 6,170,000 kr. Antal\nindustriarb.: 550. — Bolaget grundat 1913.\n\nStyrelse; bankdir. Gustaf Söderlund\n(ordf.), bankdir. Petrus Brundell, dir.\nGunnar Jacobsson, dir. Ivar Kull, dir.\nHildor Medin.\n\nVerkst. dir.: Ivar Kull.\n\növering.: N. Bönthron.\n\nKontorschef: Gunnar Nyström.\n\nAvd.-ingenjörer: järnverket: G.\nPou-sette; glasverket: T. Medin; koks verket:\nO. Hage; mek. verkst.: Th. Fridh;\nlaboratoriet: E. Braaten; ritkontoret: E.\nStenström.\n\nOxelösunds Träindustri AB.,\n\nOxelösund.\n\nTillverkar gardinbräder och\ngardinkor-nischer i trä vid fabrik i Oxelösund\n(Södermanl. l.). Varumärke: »Ota».\n\nKontor: Nyköping. Telefon: 109.\n—-Akt.-kap.: 75,000 kr. Antal industriarb.:\n25. Tillv.-värde pr år: 400,000 kr. —\nBolaget grundat 1938.\n\nDisp.: Knut Irving.\n\nKamrer: Birger Bergquist.\n\n*AB. Oxygenol, Stockholm.\n\nKem.-tekn. fabrik. Tillverkar\nkosmetiska och antiseptiska medel, syrgasbad\nsamt farmaceutiska preparater.\nVarunamn: »Oxygenol», »Amarant»,\n»Trans-pirol», »Cremsol», »Handolén»,\n»Lavi-fleur» o. »Aqua Vera».\n\nKontor: Lindhagensg. 122. Telegr.-adr.:\nOxygenol, Stockholm. Telefon: 520235.\nPostgiro: 1370.\n\nAkt.-kap.: 604,200 kr. Antal\nindustriarb.: 40. — Bolaget grundat 1908.\n\nStyrelse: disp. Einar Eklund (ordf.),\nadv. Gösta Grönberg, arkitekt Dag Melin,\ning. Ingvar Röing, apot. Ivar Röing.\n\nVerkst. dir. o. tehn. chef: Ivar Röing.\n\nKamrer: Hans Unell.\n\n* utmärker till Sveriges Industriförbund anslutna företag.\n\n*AB. Packningsindustri, Råa.\n\nMaskinpackningsfabrik i Råå (Malmöh.\n1.). Tillverkar boxpackningar av asbest,\nbomull, lingarn, hampa, jute och läder\nsamt bromsband och lamellbelägg.\nVarumärken: »Pi», »Pal-pi», »Hecopi»,\n»Tor-pi», »Dragon», »Aspi» o. »Ze-pi».\n\nTelegr.-adr.: Pi, Hälsingborg. Telefon:\n90190—91. Postgiro: 34372. — Akt.-kap.:\n108,000 kr. Antal industriarb.: 35. —\nBolaget grundat 1918.\n\nStyrelse: dir. Bernh. Nordström (ordf.),\ndisp. Oscar Nordström, maskininsp.\nFranklin Rebensdorff, dir. E. K.\nThorsson, skeppsred. Morgan Wedlin.\n\nVerkst. dir.: Bernh. Nordström.\n\nDisp.: Oscar Nordström.\n\nPahnes Textil, Halmstad.\n\nStrumpfabrik. Tillverkar sport- och\nherrstrumpor.\n\nTelefon: 4750. Postgiro: 178213. —\nAntal industriarb.: 20. Tillv.-värde pr\når: 250,000 kr. — Firman etabl. 1940.\n\nÄgare o. chef: fabr. Eric Pahne.\n\n*Palms Konfektionsfabrik,\n\nTomelilla,\n\nTillverkar herr- och gosskläder vid\nfabrik i Tomelilla (Kristianst. l.).\n\nTelefon: »Palms fabriker». Postgiro:\n11148. — Antal industriarb.: 90. —\nFirman etabl. 1943 under manm Tomelilla\nKonfektion, nuv. namn 1946.\n\nÄgare o. chef: fabr. Gösta Palm.\n\nDisp.: Otto Björklund.\n\n*Palms Mössfabrik, Tomelilla.\n\nMössfabrik i Tomelilla (Kristianst. l.).\nTillverkar sportmössor, skol- och klädes-\n\n432*",
    "structured": {
        "1": {
            "name": "Oxelösunds Järnverks AB.",
            "location": "Oxelösund",
            "business": "Järnverk med sintringsverk och koksmasugn, koksverk med biproduktsverk samt fönsterglasverk i Oxelösund (Södermanl. l.)",
            "products": "Tillverkar sinter, kokstackjärn alla slag, koks samt tjära, ammoniumsulfat, bensol, solventnafta, toluol, xylol m. fl. destillationsprodukter ävensom maskindraget fönsterglas. Varumärke: »OJA».",
            "contact": {
                "office": "Järnverket, Oxelösund",
                "phone": [
                    "Telefonnummer 1"
                ],
                "postgiro": "71560",
                "head_office": "Head office address",
                "sales_offices": [
                    {
                        "location": "Sales office 1",
                        "phone": "Phone number 1"
                    },
                    {
                        "location": "Sales office 2",
                        "phone": "Phone number 2"
                    }
                ],
                "telegraph": "Telegraph address",
                "factory_office": "Factory office address",
                "factory_phone": "Factory phone number"
            },
            "financials": {
                "capital": "6,170,000 kr",
                "employees": {
                    "industriarb.": 550
                },
                "annual_turnover": "Annual turnover value",
                "annual_production_value": "Annual production value"
            },
            "foundation_year": 1913,
            "board": [
                {
                    "name": "Gustaf Söderlund",
                    "role": "ordf."
                },
                {
                    "name": "Petrus Brundell",
                    "role": "dir."
                },
                {
                    "name": "Gunnar Jacobsson",
                    "role": "dir."
                },
                {
                    "name": "Ivar Kull",
                    "role": "dir."
                },
                {
                    "name": "Hildor Medin",
                    "role": "dir."
                }
            ]
        },
        "2": {
            "name": "Oxelösunds Träindustri AB.",
            "location": "Oxelösund",
            "business": "Tillverkar gardinbräder och gardinkor-nischer i trä vid fabrik i Oxelösund (Södermanl. l.)",
            "products": "Varumärke: »Ota».",
            "contact": {
                "office": "Nyköping",
                "phone": [
                    "109"
                ]
            },
            "financials": {
                "capital": "75,000 kr",
                "employees": {
                    "industriarb.": 25
                },
                "annual_production_value": "400,000 kr"
            },
            "foundation_year": 1938
        },
        "3": {
            "name": "AB. Oxygenol, Stockholm",
            "business": "Kem.-tekn. fabrik. Tillverkar kosmetiska och antiseptiska medel, syrgasbad samt farmaceutiska preparater.",
            "products": "Varunamn: »Oxygenol», »Amarant», »Trans-pirol», »Cremsol», »Handolén», »Lavi-fleur» o. »Aqua Vera».",
            "contact": {
                "office": "Lindhagensg. 122",
                "phone": [
                    "520235"
                ],
                "postgiro": "1370"
            },
            "financials": {
                "capital": "604,200 kr",
                "employees": {
                    "industriarb.": 40
                }
            },
            "foundation_year": 1908
        },
        "4": {
            "name": "AB. Packningsindustri, Råa",
            "business": "Maskinpackningsfabrik i Råå (Malmöh. 1.)",
            "products": "Tillverkar boxpackningar av asbest, bomull, lingarn, hampa, jute och läder samt bromsband och lamellbelägg. Varumärken: »Pi», »Pal-pi», »Hecopi», »Tor-pi», »Dragon», »Aspi» o. »Ze-pi».",
            "contact": {
                "office": "Pi, Hälsingborg",
                "phone": [
                    "90190",
                    "91"
                ],
                "postgiro": "34372"
            },
            "financials": {
                "capital": "108,000 kr",
                "employees": {
                    "industriarb.": 35
                }
            },
            "foundation_year": 1918
        },
        "5": {
            "name": "Pahnes Textil, Halmstad",
            "business": "Strumpfabrik",
            "products": "Tillverkar sport- och herrstrumpor",
            "contact": {
                "phone": [
                    "4750"
                ],
                "postgiro": "178213"
            },
            "financials": {
                "annual_production_value": "250,000 kr"
            },
            "foundation_year": 1940
        },
        "6": {
            "name": "Palms Konfektionsfabrik, Tomelilla",
            "business": "Tillverkar herr- och gosskläder vid fabrik i Tomelilla (Kristianst. l.)",
            "contact": {
                "phone": "»Palms fabriker»",
                "postgiro": "11148"
            },
            "financials": {
                "employees": {
                    "industriarb.": 90
                }
            },
            "current_name_year": 1946,
            "predecessor": "Tomelilla Konfektion"
        },
        "7": {
            "name": "Palms Mössfabrik, Tomelilla",
            "business": "Mössfabrik i Tomelilla (Kristianst. l.). Tillverkar sportmössor, skol- och klädes- 432*.",
            "financials": {
                "annual_production_value": "250,000 kr"
            },
            "current_name_year": 1946,
            "predecessor": "Tomelilla Konfektion"
        }
    }
}