{
    "original": "Skinnskattebergsverken—Skofabriken\n\n\"Skinnskattebergsverken,\n\nSkinnskatt eb er g.\n\nSe AB. Statens Skogsindustrier,\nStockholm.\n\nSkjortfabriken Bore AB.,\n\nTrollhättan.\n\nTillverkar vita och kulörta\nherrskjor-tor samt pyjamas m. m.\n\nTelefon: 10284 o. 18109. Postgiro:\n14620. — Akt.-kap.: 60,000 kr. Antal\nindustriarb.: 60. Tillv.-värde pr år: 700,000\nkr. — Fabriken anlagd 1918, bolag 1934.\nVerkst. dir.: disp. G. Öberg.\n\nAB. Skjutfönster, Malmö.\n\nTillverkar vertikala skjutfönster av trä,\njärn och metall vid fabrik i Malmö.\nVarumärke: »Futurum».\n\nTelefon: 71475. Postgiro: 147429. —\nAkt.-kap.: 25,000 kr. Antal industriarb.:\n4. — Bolaget grundat 1934.\n\nVerkst. dir.: civiling. Franz Peterzén.\n\n*AB. Sko-Cement, Malmö.\n\nKem.-tekn. fabrik. Tillverkar\nkem.-tekniska artiklar för skofabriker.\n\nKontor: Celsiusg. 37. Telegr.-adr.:\nSko-cement, Malmö. Telefon: 24860.\nPostgiro: 39421. — Akt.-kap.: 100,000 kr.\nArb.-antal: 10. — Bolaget grundat 1912.\n\nStyrelse o. verkst. dir.: ing. H.\nUldall-Jörgensen.\n\n\"Skofabriken Eyra, Håkansson &amp;\nPersson, Kävlinge.\n\nSkofabrik i Kävlinge (Malmöh. l.).\nTillverkar ago damskor. Varumärke:\n»Eyra-skodon».\n\nTelefon: 300. Postgiro: 26602. —\nAntal industriarb.: 25. Tillv.-värde pr år:\n300,000 kr. — Firman etabl. 1920,\nom-bildad 1924 o. 1945; * •\n\nÄgare ö. chefer: fabr. Hilding\nHåkansson o. fabr. Jöns Persson.\n\n\"Skofabriken Hebe AB., Göteborg.\n\nTillverkar damskodon. Varumärke:\n»Hebe».\n\nKontor: Malmsjög. 14. Telefon: 157990.\nPostgiro: 40890.\n\nAkt.-kap.: 50,000 kr. Antal\nindustriarb.: 40. Tillv.-värde pr år: 440,000 kr.\n— Firman etabl. 1919, bolag 1938.\n\nStyrelse: fabr. Ejnar Sjöqvist (ordf.),\nköpm. Eric Olofson, herr Per Sjöqvist.\nVerkst. dir.: Ejnar Sjöqvist.\n\n48*\n\nAB. Skofabriken Iris, Almby.\n\nTillverkar sandalsydda och ago skodon\nvid fabrik i Almby (Örebro L).\n\nTelefon: 13282. — Akt.-kap.: 24,000 kr.\nAntal industriarb.: 40. Tillv.-värde pr år:\n400,000 kr. — Firman etabl. 1924, bolag\n1931.\n\nVerkst. dir.: fabr. Eskil Fredriksson.\n\n\"Skofabriken Johansson &amp; Söner,\n\nFalkenberg.\n\nTillverkar rand- och becksömsydda\npjäxor och lågskor, sandalsydda\nbarn-och mansskor samt klamrade pjäxor.\n\nTelefon: 637. Postgiro: 71857. —\nAntal industriarb.: 15. Tillv.-värde pr år:\n300,000 kr. — Firman etabl. 1916, nuv.\nfirmanamn 1930.\n\nÄgare o. chefer: fabr. Erik Johansson,\nfabr. Gunnar Johansson, fabr. Henrik\nJohansson o. fabr. Gösta Johansson.\n\n\"Skofabriken Ree, Qrébro.\n\nTillverkar veltsydda skodon.\n\nTelefon: 15695. Postgiro: 135191. —\nAntal industriarb.: 30. Tillv.-värde pr.år:\n300,000 kr. — Firman etabl. 1931.\n\nÄgare o. chefer: fabr. John Eriksson o.\nköpman Bertil Pettersson.\n\n\"AB. Skofabriken Rex, Örebro.\n\nTillverkar skodon. Specialitet:\ndamskodon. Varumärke: »Rex».\n\nTelegr.-adr.: Rex, Örebro. Telefon:\n19470. Postgiro: 96940. Ensamförsäljare:\nAB. Carlsson &amp; Åqvist, Örebro. Telefon:\n»Carlssonåqvist». Representant i\nStockholm: Nils Olsson, Vasag. 16. Telefon:\n1001fc9.\n\nAkt.-kap.: 600,000 kr. Antal\nindustriarb.: 150. — Bolaget grundat 1913.\n\nStyrelse: grossh. Erik Åqvist (ordf.),\nkontorschef Herbert Johnson, disp.\nArvid Sterner, dir. Torsten Åqvist.\n\nVerkst. dir.: Torsten Åqvist.\n\nDisponenter: Arvid Sterner o. Erik\nJohansson.\n\nKontorschef: Herbert Johnson.\n\nSkofabriks AB. Runa, Örebro.\n\nTillverkar damskodon.\n\nTelefon: 12777. Postgiro: 28145. —\nAkt.-kap.: 20,000 kr. Tillv.-värde pr år:\n100,000 kr. Bolaget grundat 1931.\n\nVerkst. dir.: fabr. Adolf Carlsson,\n\n\"AB. Skofabriken Skändia, Örebro.\n\nTillverkar skodon och tofflor.\n\nTelefon: 19205. Postgiro: 21464. En-",
    "structured": {
        "1": {
            "name": "Skinnskattebergsverken—Skofabriken",
            "location": "Skinnskatt eb er g",
            "business": "Skofabrik",
            "contact": {
                "office": "Skinnskattebergsverken, Skinnskatt eb er g, Stockholm",
                "phone": [
                    "10284",
                    "18109"
                ],
                "postgiro": "14620",
                "manager": "disp. G. Öberg"
            },
            "financials": {
                "capital": "60,000 kr",
                "employees": {
                    "industriarb": 60
                },
                "annual_turnover": "700,000 kr",
                "annual_production_value": "700,000 kr"
            },
            "foundation_year": 1918,
            "corporation_year": 1934
        },
        "2": {
            "name": "AB. Skjutfönster",
            "location": "Malmö",
            "business": "Tillverkare av vertikala skjutfönster",
            "products": "Vertikala skjutfönster av trä, järn och metall",
            "contact": {
                "office": "Malmö",
                "phone": "71475",
                "postgiro": "147429",
                "contact": {
                    "location": "Malmö",
                    "phone": "71475"
                }
            },
            "financials": {
                "capital": "25,000 kr",
                "employees": {
                    "industriarb": 4
                },
                "corporation_year": 1934
            }
        },
        "3": {
            "name": "AB. Sko-Cement",
            "location": "Malmö",
            "business": "Kemisk-teknisk fabrik",
            "products": "Tillverkning av kemisk-tekniska artiklar för skofabriker",
            "contact": {
                "office": "Celsiusg. 37, Malmö",
                "phone": "24860",
                "postgiro": "39421",
                "factory_office": "Celsiusg. 37",
                "factory_phone": "24860"
            },
            "financials": {
                "capital": "100,000 kr",
                "employees": {
                    "arb-antal": 10
                },
                "foundation_year": 1912
            }
        },
        "4": {
            "name": "Skofabriken Eyra",
            "location": "Kävlinge",
            "business": "Skofabrik",
            "products": "Tillverkar ago damskor",
            "contact": {
                "office": "Kävlinge",
                "phone": "300",
                "postgiro": "26602"
            },
            "financials": {
                "employees": {
                    "industriarb": 25
                },
                "annual_turnover": "300,000 kr",
                "corporation_year": 1945
            },
            "foundation_year": 1920
        },
        "5": {
            "name": "Skofabriken Hebe AB.",
            "location": "Göteborg",
            "business": "Tillverkare av damskodon",
            "products": "Tillverkar damskodon, varumärke: »Hebe»",
            "contact": {
                "office": "Malmsjög. 14, Göteborg",
                "phone": "157990",
                "postgiro": "40890"
            },
            "financials": {
                "capital": "50,000 kr",
                "employees": {
                    "industriarb": 40
                },
                "annual_turnover": "440,000 kr",
                "corporation_year": 1938
            },
            "foundation_year": 1919
        },
        "6": {
            "name": "AB. Skofabriken Iris",
            "location": "Almby",
            "business": "Tillverkar sandalsydda och ago skodon",
            "products": "Sandal-sydda och ago skodon",
            "contact": {
                "office": "Almby",
                "phone": "13282",
                "postgiro": "24,000 kr"
            },
            "financials": {
                "employees": {
                    "industriarb": 40
                },
                "annual_turnover": "400,000 kr",
                "foundation_year": 1924,
                "corporation_year": 1931
            }
        },
        "7": {
            "name": "Skofabriken Johansson &amp; Söner",
            "location": "Falkenberg",
            "business": "Tillverkare av skor",
            "products": "Tillverkar rand- och becksömsydda pjäxor och lågskor, sandalsydda barn-och mansskor samt klamrade pjäxor",
            "contact": {
                "office": "Falkenberg",
                "phone": "637",
                "postgiro": "71857"
            },
            "financials": {
                "employees": {
                    "industriarb": 15
                },
                "annual_turnover": "300,000 kr"
            },
            "foundation_year": 1916,
            "corporation_year": 1930
        },
        "8": {
            "name": "Skofabriken Ree",
            "location": "Örebro",
            "business": "Tillverkar veltsydda skodon",
            "contact": {
                "office": "Örebro",
                "phone": "15695",
                "postgiro": "135191"
            },
            "financials": {
                "employees": {
                    "industriarb": 30
                },
                "annual_turnover": "300,000 kr",
                "foundation_year": 1931
            }
        },
        "9": {
            "name": "AB. Skofabriken Rex",
            "location": "Örebro",
            "business": "Tillverkar skodon",
            "products": "Specialitet dams-kodon, varumärke: »Rex»",
            "contact": {
                "office": "Örebro",
                "phone": "19470",
                "postgiro": "96940"
            },
            "financials": {
                "capital": "600,000 kr",
                "employees": {
                    "industriarb": 150
                },
                "corporation_year": 1913
            }
        },
        "10": {
            "name": "Skofabriks AB. Runa",
            "location": "Örebro",
            "business": "Tillverkar damskodon",
            "contact": {
                "office": "Örebro",
                "phone": "12777",
                "postgiro": "28145"
            },
            "financials": {
                "capital": "20,000 kr",
                "annual_turnover": "100,000 kr",
                "corporation_year": 1931
            }
        },
        "11": {
            "name": "AB. Skofabriken Skändia",
            "location": "Örebro",
            "business": "Tillverkar skodon och tofflor",
            "contact": {
                "office": "Örebro",
                "phone": "19205",
                "postgiro": "21464"
            }
        }
    }
}