{
    "original": "Elsvets—Enmiab oda\n\n*AB. El- och Cassvetsning, Göteborg.\n\nTillverkar apparater och tillbehör för\nsåväl gas- som elektr. svetsning,\nelektroder för elektr. ljusbågssvetsning och\nmetallarmatur för svetsning samt\nframställer syrgas.\n\nKontor: Frigången. Telegr.-adr.:\nEl-gasvets, Göteborg. Telefon: »Elgasvets».\nPostgiro: 44915. Avd.-kontor:\nStockholm, Torsg. 41, telefon: 328275; Malmö:\nStortorget 17, telefon: 79345; Sundsvall,\ntelefon: 58100.\n\nAkt.-kap.: 250,000 kr. Antal\nindustriarb.: 110. Tillv.-värde pr år: 2,500,000 kr.\n\n—\tBolaget grundat 1938.\n\nStyrelse: dir. Carl Alfredson (ordf.),\nkamrer H. Benjaminson, avd.-chef Rolf\nOlsson, verkm. Yngve Åsberg.\n\nVerkst. dir.: Carl Alfredson.\n\nKamrer: H. Benjaminson.\n\nFörsäljn.-chef: B.-H. Berndtsson.\n\nDriftsing.: Ture Rehn.\n\nAB. El tron, Stockholm.\n\nElektromek. verkstad. Tillverkar elektr.\nmotstånd, potentiometrar, mätinstrument,\nelektr. materiel samt bakelitdetaljer.\nVarumärke: »Eltron». Bolaget driver\näven engroshandel med radiomateriel.\n\nHuvudkontor: Stockholm, Kronobergsg.\n19. Telegr.-adr.: Eltron, Stockholm.\nTelefon: 507993—94. Postgiro: 57325.\nAvd.-kontor: Göteborg, Tegnérsg. 12, telefon:\n186718.\n\nAkt.-kap.: 100,000 kr. Antal\nindustriarb.: 35. Tillv.-värde pr år: 250,000 kr.\n\n—\tFirman etabl. 1934.\n\nVerkst. dir.: Paul Richter.\n\nKamrer: Wilh. Wernersson.\n\nElvärme AB., Stockholm.\n\nElektromek. verkstad i Ulvsunda.\nTillverkar elektr. värmeapparater såsom\nspisar, kokplattor, kokhällar, kaminer,\ntermostater och strykjärn samt värmeskåp.\nVarumärke: »Elva».\n\nHuvudkontor o. ensamförsäljn.:\nBröderna Engströms Elektr. AB., Stockholm,\nTunnelg. 28 B. Telefon: 280101. —\nAkt.-kap.: 50,000 kr. Antal industriarb.: 50.\n\n—\tBolaget grundat 1938.\n\nStyrelse: dir. Ernst Engström (ordf.),\ning. Gösta Burvik, dir. Nils Engström.\n\nVerkst. dir.: Ernst Engström.\n\nAB. Emaljskyltfabriken Svea,\n\nFritsla.\n\nTillverkar emaljerade plåtskyltar och\nemaljerade kopparbokstäver vid fabrik i\nFritsla (Älvsb. l.).\n\nTelefon; Kinna 70059. Postgiro: 30390.\n\n—\tAkt.-kap.: 15,000 kr. Antal\nindustriarb.: 10. — Firman etabl. 1910, bolag\n1935.\n\nVerkst. direktörer: Arvid Nohlström o.\nCarl J. Johansson.\n\n\"Eminentverktyg, Brandstad &amp;\nMon-teen, Torshälla.\n\nJärn- och metallmanufakturfabrik.\nTillverkar verktyg såsom vinklar,\nborrsvängar, bågfilsställningar, ställbara\nhak-nycklar, drillapparater, skiftnycklar,\nskruvstycken, ventilslipapparater,\navlopp srensare, slangklämmor m. fl. samt\nhushållsartiklar såsom julgransfötter,\nkonservöppnare, osthyvlar,\npotatisskala-re m. m. Varumärken: »EV» o.\n»Eminent» (verktyg).\n\nTelefon: 55111 o. 55211. Postgiro:\n84626. Antal industriarb.: 96.\nTillv.-värde pr år: 1,000,000 kr. — Firman\netabl. 1933.\n\nÄgare o. chefer: ing. M. Brandstad o.\ning. Morris Monteen.\n\nAB. Emmaboda Clasverk,\n\nEmmaboda.\n\nFönsterglasverk i Emmaboda (Kalmar\n1.). Tillverkar maskindraget fönsterglas.\n\nTelegr.-adr.: Glasverket, Emmaboda.\nTelefon: 40 o. 200. Postgiro: 87345.\n\nAkt.-kap.: 315,000 kr. Antal\nindustriarb.: 250. Tillv.-värde pr år: 6,000,000 kr.\n\n—\tFirman etabl. 1919, nuv. namn och\nbolag 1933.\n\nStyrelse: dir. Eric Åfors (ordf.), teol.\ndr Herbert Johansson, fru Greta Åfors.\n\nVerkst. dir.: Eric Åfors.\n\nAB. Emmaboda Husinrede,\n\nEmmaboda.\n\nTillverkar byggnadssnickerier och\ninredningar vid snickerifabrik i Emmaboda\n(Kalmar l.).\n\nTelefon: 230. Postgiro: 172830. —\nAkt.-kap.: 87,000 kr. Antal industriarb.:\n20. Tillv.-värde pr år: 200,000 kr. —\nBolaget grundat 1940.\n\nDisp.: Arthur Tarre.\n\n* Emmaboda Möbelfabrik, Carlsson,\nSvensson &amp; Co., Emmaboda.\n\nTillverkar möbler samt inredningar.\nSpecialiteter: höj- och utdragbara bord\nsamt sängkammarmöbler.\n\nTelefon: 35. Postgiro: 22492. — Antal\nindustriarb.: 37. Tillv.-värde pr år:\n330,000 kr. — Firman etabl. 1907.\n\nÄgare o. chefer: fabr. Erik Svensson o.\nfabr. Osvald Carlsson.\n\n",
    "structured": {
        "1": {
            "name": "Elsvets—Enmiab oda AB",
            "location": "Göteborg",
            "business": "Tillverkar apparater och tillbehör för såväl gas- som elektr. svetsning, elektroder för elektr. ljusbågssvetsning och metallarmatur för svetsning samt framställer syrgas.",
            "contact": {
                "office": "Frigången",
                "telegraph": "El-gasvets, Göteborg",
                "phone": [
                    "Elgasvets"
                ],
                "postgiro": "44915",
                "sales_offices": [
                    {
                        "location": "Stockholm",
                        "phone": "328275"
                    },
                    {
                        "location": "Malmö",
                        "phone": "79345"
                    },
                    {
                        "location": "Sundsvall",
                        "phone": "58100"
                    }
                ]
            },
            "financials": {
                "capital": "250,000 kr",
                "employees": {
                    "industriarb": 110
                },
                "annual_turnover": "2,500,000 kr",
                "annual_production_value": "2,500,000 kr"
            },
            "foundation_year": 1938,
            "board": [
                {
                    "name": "Carl Alfredson",
                    "role": "ordf."
                },
                {
                    "name": "H. Benjaminson",
                    "role": "kamrer"
                },
                {
                    "name": "Rolf Olsson",
                    "role": "avd.-chef"
                },
                {
                    "name": "Yngve Åsberg",
                    "role": "verkm."
                }
            ],
            "director": "Carl Alfredson",
            "manager": "Carl Alfredson",
            "sales_manager": "B.-H. Berndtsson",
            "managing_director": "Carl Alfredson"
        },
        "2": {
            "name": "AB. Eltron",
            "location": "Stockholm",
            "business": "Elektromek. verkstad. Tillverkar elektr. motstånd, potentiometrar, mätinstrument, elektr. materiel samt bakelitdetaljer. Bolaget driver även engroshandel med radiomateriel.",
            "contact": {
                "head_office": "Stockholm, Kronobergsg. 19",
                "telegraph": "Eltron, Stockholm",
                "phone": [
                    "507993—94"
                ],
                "postgiro": "57325",
                "sales_offices": [
                    {
                        "location": "Göteborg",
                        "phone": "186718"
                    }
                ]
            },
            "financials": {
                "capital": "100,000 kr",
                "employees": {
                    "industriarb": 35
                },
                "annual_turnover": "250,000 kr",
                "annual_production_value": "250,000 kr"
            },
            "foundation_year": 1934,
            "director": "Paul Richter",
            "manager": "Paul Richter"
        },
        "3": {
            "name": "Elvärme AB.",
            "location": "Stockholm",
            "business": "Elektromek. verkstad. Tillverkar elektr. värmeapparater såsom spisar, kokplattor, kokhällar, kaminer, termostater och strykjärn samt värmeskåp.",
            "contact": {
                "office": "Ulvsunda",
                "phone": [
                    "Bröderna Engströms Elektr. AB., Stockholm, Tunnelg. 28 B"
                ],
                "postgiro": "57325"
            },
            "financials": {
                "capital": "50,000 kr",
                "employees": {
                    "industriarb": 50
                }
            },
            "foundation_year": 1938,
            "director": "Ernst Engström"
        },
        "4": {
            "name": "AB. Emaljskyltfabriken Svea",
            "location": "Fritsla",
            "business": "Tillverkar emaljerade plåtskyltar och emaljerade kopparbokstäver vid fabrik i Fritsla (Älvsb. l.)",
            "contact": {
                "phone": [
                    "Kinna 70059"
                ],
                "postgiro": "30390"
            },
            "financials": {
                "capital": "15,000 kr",
                "employees": {
                    "industriarb": 10
                }
            }
        },
        "5": {
            "name": "Eminentverktyg",
            "location": "Brandstad & Mon-teen, Torshälla",
            "business": "Järn- och metallmanufakturfabrik. Tillverkar verktyg samt hushållsartiklar",
            "contact": {
                "phone": [
                    "55111",
                    "55211"
                ],
                "postgiro": "84626"
            },
            "financials": {
                "employees": {
                    "industriarb": 96
                },
                "annual_turnover": "1,000,000 kr"
            }
        },
        "6": {
            "name": "AB. Emmaboda Clasverk",
            "location": "Emmaboda",
            "business": "Fönsterglasverk i Emmaboda (Kalmar 1.). Tillverkar maskindraget fönsterglas",
            "contact": {
                "telegraph": "Glasverket, Emmaboda",
                "phone": [
                    "40",
                    "200"
                ],
                "postgiro": "87345"
            },
            "financials": {
                "capital": "315,000 kr",
                "employees": {
                    "industriarb": 250
                },
                "annual_turnover": "6,000,000 kr"
            },
            "foundation_year": 1933
        },
        "7": {
            "name": "AB. Emmaboda Husinrede",
            "location": "Emmaboda",
            "business": "Tillverkar byggnadssnickerier och inredningar vid snickerifabrik i Emmaboda (Kalmar l.)",
            "contact": {
                "phone": [
                    "230"
                ],
                "postgiro": "172830"
            },
            "financials": {
                "capital": "87,000 kr",
                "employees": {
                    "industriarb": 20
                },
                "annual_turnover": "200,000 kr"
            },
            "foundation_year": 1940,
            "manager": "Arthur Tarre"
        },
        "8": {
            "name": "Emmaboda Möbelfabrik, Carlsson, Svensson & Co.",
            "location": "Emmaboda",
            "business": "Tillverkar möbler samt inredningar. Specialiteter: höj- och utdragbara bord samt sängkammarmöbler.",
            "contact": {
                "phone": [
                    "35"
                ],
                "postgiro": "22492"
            },
            "financials": {
                "employees": {
                    "industriarb": 37
                },
                "annual_turnover": "330,000 kr"
            }
        }
    }
}