{
    "original": "Gumpert—Gustavsberg\n\n*Gumperts AB., Göteborg.\n\nKontorsbokfabrik, boktryckeri, offset,\nlitografi och stämpelfabrik. Tillverkar\nkontors- och kopieböcker, brevsamlare,\ngummistämplar m. m. samt utför\naffärs-och värdepapperstryck. Firman driver\njämväl parti- och detaljhandel med\npapper, ritmateriel, kontorsförnödenheter,\nböcker o. d.\n\nKontor: S. Hamng. 35. Telegr.-adr. o.\ntelefon: Gumperts, Göteborg. Postgiro:\n40101. —■ Akt.-kap.: 384,000 kr. Antal\nindustriarb.: 50. — Firman etabl. 1808,\nbolag 1937.\n\nStyrelse: övering. Einar Schiller\n(ordf.), herr Karl Björklund, adv. Matts\nFallenius, dir. Carl-Erik Kindal, fru\nSigrid Kindal, herr P. O. Steen.\n\nVerkst. dir.: C.-E. Kindal.\n\nDir.-assist.: John Tengberg.\n\nT ryck er i förest.: Sven Nyström.\n\n*Gunnebo Bruks AB., Gunnebobruk.\n\nJärn- och stålmanufakturverk vid\nGun-nebo (Kalmar l.), Varberg och Sundsvall.\nTillverkar alla slag av dragen tråd,\ntrådspik, klippspik, kätting, snökedjor,\ntrådstängsel, trådduk, ståltrådslinor m. m.\n\nHuvudkontor: Gunnebobruk.\nTelegr.-adr.: Gunnebo, Västervik. Telefon:\n»Gunnebobruk», Västervik. Postgiro: 9036.\nFör-säljn.-kontor: Stockholm, Garvarg. 5,\ntelefon: 520530; Göteborg, ö. Hamng. 17,\ntelefon: 111007: Malmö, Västergatan 18,\ntelefon: 25565; Sundsvall, telefon: 55920.\n\nAkt.-kap.: 4,000,000 kr. Antal\nindustriarb.: 500. — Bolaget grundat 1889.\n\nStyrelse: generalmajoren frih. Göran\nGyllenstierna (ordf.), dir. Rich.\nHell-gren, disp. Rudolf Sunström, kanslisekr.\nAllan Tigerschiöld, dir. Folke\nWilhelmson.\n\nVerkst. dir.: Rudolf Sunström.\n\nÖvering.: Gunnar Delling.\n\nKamrer: Amandus Carlsson.\n\nInköpschef: Erik Nibell.\n\nFörsäljn.-chef: Waldemar Erikson.\n\n*AB. Gunnilse Tegel, Gunnilse.\n\nTegelbruk i Gunnilse (Älvsb. l.).\nTillverkar fasad- och murtegel, lättegel,\nlätt-tegelplattor, håltegel samt dräneringsrör.\n\nTelegr.-adr.: Tegelbruket, Gunnilse.\nTelefon: 70 o. 90.\n\nAkt.-kap.: 230,000 kr. Antal\nindustriarb.: 25. Årstillv.: 5 milj. st. tegelvaror.\n— Bolaget grundat 1937.\n\nVerkst. dir.: Erik Lindvall.\n\nFabrikschef: ing. Nils-Erik Lindvall.\n\nKamrer: Carl Johansson.\n\n*AB. Gusta Stenförädlingsverk,\n\nBrunflo.\n\nKalkstensbrott, stenförädlingsverk och\nkalkmjölskvarn i Brunflo (Jämtl. l.).\n\nTillverkar fasadarbeten, trappsteg, golv,\nväggbeklädnader, diskar, öppna spisar,\nelektr. apparatplattor, råblock och sågade\nskivor samt högprocentigt kalkstensmjöl\nför sulfitfabriker, väg- och\njordbruksändamål. Varumärke: »Gusta Sten».\n\nHuvudkontor: Brunflo. Telefon: 19 o.\n63. Postgiro: 88066. Avd.-kontor:\nStockholm, Kungsg. 15. Telegr.-adr.:\nGusta-sten, Stockholm. Telefon: 116621.\n\nAkt.-kap.: 207,500 kr. Antal\nindustriarb.: 80. Tillv.-värde pr år: 1,000,000 kr.\n— Bolaget grundat 1915.\n\nStyrelse: grevinnan Gunilla (Dicken)\nReuterskiöld (ordf.), frih. Gustaf\nLager-felt J:or, dir. Arvid Reuterskiöld.\nDisp.: Age Hellström.\nAvd.-chef i Stockholm: ing. Sven F.\nSamuelsson.\n\n*Gustafs Träindustri AB., Gustafs.\n\nTillverkar butiksinredningar, trälister\ntill ram- och guldlister samt\nbyggnadslister vid fabrik i Gustafs (Kopparb. l.).\n\nTelefon: Borlänge, »Gustafs\nTräindustri». Postgiro: 6787. — Akt.-kap.:\n100,400 kr. Tillv.-värde pr år: 900,000 kr.\n\nFirman etabl. 1913 under namn Gustafs\nSåg &amp; Möbelfabrik, A. Tunander, bolag\n\n0.\tnuv. namn 1939.\n\nStyrelse: fabr. Anders Tunander (ordf.),\ndisp. Folke Tunander, fabriksförm. Sune\nTunander.\n\nVerkst. dir. o. disp.: Folke Tunander.\n\n*AB. Custavsbergs Fabriker,\n\nGustavsberg.\n\nPorslinsfabrik vid Gustavsberg (Sthlms\n\n1.).\tTillverkar husgerådsporslin,\nkonst-och prydnadssaker, isolatorer,\npressporslin, högfrekvenskeramiska detaljer,\nsintrat sanitetsporslin, eldfast tegel m. m.\nBolaget idkar jämväl jordbruk,\nskogshantering, kvarn- och rederirörelse.\n\nTelegr.-adr.: Gustavsbergs, Stockholm.\nTelefon: Gustavsberg, »Porslinsfabriken».\nPostgiro: 36225. Utställnings- och\nförsäljningslokal i Stockholm, Birger Jarlsg.\n\n2.\ttelefon: 620371.\n\nAkt.-kap.: 6,000,000 kr. Antal\nindustriarb.: 1,000. Tillv.-värde pr år: 10,700,000\nkr.\n\nFabriken anlagd 1825, bolag 1875.\nBolaget tillhör Kooperativa Förbundet.\n\nStyrelse: dir. Albin Johansson (ordf.),\nfil. lic. M. Bonow, dir. Hj. Degerstedt,\n",
    "structured": {
        "1": {
            "name": "Gumperts AB.",
            "location": "Göteborg",
            "business": "Kontorsbokfabrik, boktryckeri, offset, litografi och stämpelfabrik",
            "contact": {
                "office": "S. Hamng. 35",
                "phone": [
                    "Gumperts, Göteborg"
                ],
                "postgiro": "40101"
            },
            "financials": {
                "capital": "384,000 kr",
                "employees": {
                    "industriarb": 50
                },
                "annual_turnover": null,
                "annual_production_value": null
            },
            "foundation_year": 1808,
            "current_name_year": 1937,
            "board": [
                {
                    "name": "Einar Schiller",
                    "role": "övering"
                },
                {
                    "name": "Karl Björklund",
                    "role": null
                },
                {
                    "name": "Matts Fallenius",
                    "role": "adv"
                },
                {
                    "name": "Carl-Erik Kindal",
                    "role": "dir"
                },
                {
                    "name": "Sigrid Kindal",
                    "role": "fru"
                },
                {
                    "name": "P. O. Steen",
                    "role": "herr"
                }
            ],
            "director": "C.-E. Kindal",
            "managing_director": null,
            "sales_manager": null,
            "manager": null
        },
        "2": {
            "name": "Gunnebo Bruks AB.",
            "location": "Gunnebobruk",
            "business": "Järn- och stålmanufakturverk",
            "contact": {
                "office": "Gunnebobruk",
                "phone": [
                    "»Gunnebobruk», Västervik"
                ],
                "postgiro": "9036",
                "sales_offices": [
                    {
                        "location": "Stockholm",
                        "phone": "520530"
                    },
                    {
                        "location": "Göteborg",
                        "phone": "111007"
                    },
                    {
                        "location": "Malmö",
                        "phone": "25565"
                    },
                    {
                        "location": "Sundsvall",
                        "phone": "55920"
                    }
                ]
            },
            "financials": {
                "capital": "4,000,000 kr",
                "employees": {
                    "industriarb": 500
                },
                "annual_turnover": null,
                "annual_production_value": null
            },
            "foundation_year": 1889,
            "board": [
                {
                    "name": "frih. Göran Gyllenstierna",
                    "role": "generalmajoren"
                },
                {
                    "name": "Rich. Hellgren",
                    "role": "disp"
                },
                {
                    "name": "Rudolf Sunström",
                    "role": "dir"
                },
                {
                    "name": "Allan Tigerschiöld",
                    "role": "kanslisekr"
                },
                {
                    "name": "Folke Wilhelmson",
                    "role": "dir"
                }
            ],
            "director": "Rudolf Sunström",
            "managing_director": null,
            "sales_manager": "Waldemar Erikson",
            "manager": null
        },
        "3": {
            "name": "AB. Gunnilse Tegel",
            "location": "Gunnilse",
            "business": "Tegelbruk",
            "contact": {
                "office": null,
                "phone": [
                    "70",
                    "90"
                ],
                "postgiro": null
            },
            "financials": {
                "capital": "230,000 kr",
                "employees": {
                    "industriarb": 25
                },
                "annual_turnover": null,
                "annual_production_value": "5 milj. st. tegelvaror"
            },
            "foundation_year": 1937,
            "board": null,
            "director": "Erik Lindvall",
            "managing_director": null,
            "sales_manager": null,
            "manager": null
        },
        "4": {
            "name": "AB. Gusta Stenförädlingsverk",
            "location": "Brunflo",
            "business": "Kalkstensbrott, stenförädlingsverk och kalkmjölskvarn",
            "contact": {
                "office": null,
                "phone": [
                    "19",
                    "63"
                ],
                "postgiro": "88066"
            },
            "financials": {
                "capital": "207,500 kr",
                "employees": {
                    "industriarb": 80
                },
                "annual_turnover": null,
                "annual_production_value": "1,000,000 kr"
            },
            "foundation_year": 1915,
            "board": [
                {
                    "name": "grevinnan Gunilla (Dicken) Reuterskiöld",
                    "role": "ordf"
                },
                {
                    "name": "frih. Gustaf Lagerfält J:or",
                    "role": null
                },
                {
                    "name": "Arvid Reuterskiöld",
                    "role": "dir"
                }
            ],
            "director": null,
            "managing_director": null,
            "sales_manager": null,
            "manager": null
        },
        "5": {
            "name": "Gustafs Träindustri AB.",
            "location": "Gustafs",
            "business": "Tillverkar butiksinredningar, trälister till ram- och guldlister samt byggnadslister",
            "contact": {
                "office": null,
                "phone": [
                    "Gustafs Träindustri"
                ],
                "postgiro": "6787"
            },
            "financials": {
                "capital": "100,400 kr",
                "employees": null,
                "annual_turnover": "900,000 kr",
                "annual_production_value": null
            },
            "foundation_year": 1913,
            "current_name_year": 1939,
            "board": [
                {
                    "name": "Anders Tunander",
                    "role": "fabr"
                },
                {
                    "name": "Folke Tunander",
                    "role": "disp"
                },
                {
                    "name": "Sune Tunander",
                    "role": "fabriksförm"
                }
            ],
            "director": null,
            "managing_director": "Folke Tunander",
            "sales_manager": null,
            "manager": null
        },
        "6": {
            "name": "AB. Custavsbergs Fabriker",
            "location": "Gustavsberg",
            "business": "Porslinsfabrik",
            "contact": {
                "office": null,
                "phone": [
                    "Gustavsberg, »Porslinsfabriken»"
                ],
                "postgiro": "36225",
                "sales_offices": [
                    {
                        "location": "Stockholm",
                        "phone": "620371"
                    }
                ]
            },
            "financials": {
                "capital": "6,000,000 kr",
                "employees": {
                    "industriarb": 1,
                    "l": 0
                },
                "annual_turnover": "10,700,000 kr",
                "annual_production_value": null
            },
            "foundation_year": 1825,
            "board": [
                {
                    "name": "Albin Johansson",
                    "role": "dir"
                },
                {
                    "name": "M. Bonow",
                    "role": "fil. lic"
                },
                {
                    "name": "Hj. Degerstedt",
                    "role": null
                }
            ],
            "director": null,
            "managing_director": null,
            "sales_manager": null,
            "manager": null
        }
    }
}