{
    "original": "S trandwall—S trumpfabrijc\n\nAB. Ake Strandwalls\nKonfektionsfabrik, SJcänninge.\n\nTillverkar arbetsskjortor, blåkläder,\nbyxor, barn- och gosskonfektion,\nskid-dräkter m. m. Firman driver även\nengroshandel med trikåvaror och vävnader.\n\nKontor: Skänninge. Telefon: 365.\nPostgiro: 75207. Avd.-kontor: Solna, telefon:\nStockholm 276643. — Akt.-kap.: 70,000\nkr. Tillv.-värde pr år: 250,000 kr. —\nFirman etabl. 1921, bolag l945.\n\nVerkst. dir.: fabr. Åke Strandwall.\n\nStrebelverken, Västervik.\n\nSe AB. Svenska Strebelverken,\nVästervik.\n\n* St r i bergs Grufve AB., Striberg.\n\nJärnmalmsgruvor i Dalkarlsbergs-,\nStri-bergs- och Åsbobergsfälten samt\nanrikningsverk i Dalkarlsberg och Åsboberg,\nsågverk i Striberg (samtl. i Örebro l.).\nBryter och anrikar järnmalm, tillverkar\nsågade och hyvlade trävaror samt driver\nskogsbruk.\n\nKontor: Striberg. Telegr.-adr.:\nGruvorna, Nora. Telefon: Striberg 10.\nPostgiro: 96700.\n\nAkt.-kap.: 2,200,000 kr. Antal\nindustriarb.: 345. Prod.-värde pr år: 3,000,000 kr.\n\nBolaget grundat 1886, aktiebolag 1919.\n\nStyrelse: dir. Evert Wijkander (ordf.),\ndisp. Åke Bergendal, disp. Bengt\nCarleson, disp. N. Arvid Ericsson, disp. W.\nRisberg.\n\nVerkst. dir. o. disp.: Åke Bergendal.\n\nKamrer: Erik Mandorf.\n\n*AB. A. R. Strid, Vetlanda.\n\nMek. verkstad och parkettfabrik.\nTillverkar maskiner för träbearbetning såsom\nklyvsågar, balanskapsågar och\npendelkap-sågar, specialmaskiner för tillverkning av\nmonteringsfärdiga trähus samt\nparkettgolv av ek.\n\nTelegr.-adr.: Stridar, Vetlanda.\nTelefon: 126. Postgiro: 94655.\n\nAkt.-kap.: 31,000 kr. Antal\nindustriarb.: 35. Tillv.-värde pr år: 475,000 kr.\n— Firman etabl. 1911, bolag 1941.\n\nStyrelse: överinsp. C. G. Wictorin\n(ordf.), fabr. Geijer Strid, ing. Nils\nStrid.\n\nVerkst. dir.: Geijer Strid.\n\n(Jfr annons nr 46.)\n\n*AB. Stridsberg &amp; Biörck,\n\nTrollhättan.\n\nSågblads- och maskinknivsfabrik med\nelektr. smältugnar, valsverk och meka-\n\n5*\n\nnisk verkstad (Gullöfors Bruk).\nTillverkar sågblad av alla slag, maskinhyveljärn\noch maskinknivar m. m.\n\nHuvudkontor: Trollhättan.\nTelegr.-adr.: Stridsbiörck, Trollhättan. Telefon:\n»Stridsberg &amp; Biörck». Postgiro: 6080.\nAvd.-kontor o. lager: Stockholm, Vasag.\n7, telegr.-adr.: Stridsbiörck, Stockholm,\ntelefon: 101398 o. 101378.\n\nAkt.-kap.: 2,000,000 kr. Antal\nindustriarb.: 500. Tillv.-värde pr år: 6,000,000 kr.\n\nFirman etabl. 1868, bolag 1911.\n\nStyrelse: ing. Gust. ödqvist (ordf.),\ning. Einar Egnell, dir. S. Stridsberg.\n\nVerkst. dir.: S. Stridsberg.\n\nFörsäljn.-chef: Gunnar Flink.\n\nInköpschef: Erik Adamson.\n\nDriftsingenjörer: G. Nordsten, U.\nWikström, V. Irénius o. Roland Åberg.\n\n*Stripa Cruv AB., Ludvika.\n\nJärnmalmsgruvor vid Stripa,\nGuldsmedshyttan (Örebro l.). Producerar\nkvartsrandig, fosforren blodstensmalm\noch fosforren järnmalmsslig.\n\nHuvudkontor: Ludvika. Telefon:\n»Ställ-bergsbolagen». Gruvkontor:\nGuldsmeids-hyttan. Telefon: 70 o. 100. Försäljningen\npå export av bolagets produkter\nhandha ves av Ställbergs Grufve AB., Ludvika.\n\nAkt.-kap.: 2,300,000 kr. Antal\nindustriarb.: 200. — Aktiebolaget grundat 1939.\n\nStyrelse: hovstallm. frih. G. A.\nKlingspor (ordf.), majoren frih. Carl S:son\nLeijonhufvud (v. ordf.), dir. Erik G.\nPehrsson, adv. Hugo Stenbeck.\n\nVerkst. dir. o. disp.: B. Stein.\n\növering.: Sven Dalhammar.\n\nPlatschef i Stripa: bergsing. Sven\nEdin.\n\nKamrer vid huvudkontoret: Axel\nFrövik.\n\nKamrer i Stripa: Uno Zachrisson.\n\n\"Strumpfabriken, AB. Nya Mek.,\n\nBorås.\n\nSe Nya Mek. Strumpfabriken AB.,\nBorås.\n\nStrumpfabriks AB. Kåge, Älvsered.\n\nTillverkar herrstrumpor vid fabrik i\nÄlvsered (Älvsb. l.).\n\nTelefon: 21. Postgiro: 95372. —\nAkt.-kap.: 10,000 kr. Antal industriarb.: 25.\nTillv.-värde pr år: 300,000 kr. — Bolaget\ngrundat 1933.\n\nStyrelse o. verkst. dir.: disp. Knut\nGustafsson.",
    "structured": {
        "1": {
            "name": "Strandwall—Strumpfabrijc AB",
            "location": "Sjänninge",
            "business": "Konfektionsfabrik",
            "products": "Tillverkar arbetsskjortor, blåkläder, byxor, barn- och gosskonfektion, skid-dräkter m. m.",
            "contact": {
                "office": "Skänninge",
                "phone": [
                    "365"
                ],
                "postgiro": "75207",
                "sales_offices": [
                    {
                        "location": "Solna",
                        "phone": "Stockholm 276643"
                    }
                ]
            },
            "financials": {
                "capital": "70,000 kr",
                "annual_turnover": "250,000 kr",
                "annual_production_value": "3,000,000 kr"
            },
            "foundation_year": 1921,
            "corporation_year": 1945,
            "board": [
                {
                    "name": "Åke Strandwall",
                    "role": "Verkst. dir."
                }
            ]
        },
        "2": {
            "name": "Stribergs Grufve AB",
            "location": "Striberg",
            "business": "Järnmalmsgruvor",
            "products": "Bryter och anrikar järnmalm, tillverkar sågade och hyvlade trävaror samt driver skogsbruk",
            "contact": {
                "office": "Striberg",
                "phone": [
                    "Striberg 10"
                ],
                "postgiro": "96700"
            },
            "financials": {
                "capital": "2,200,000 kr",
                "employees": {
                    "industriarb.": 345
                },
                "annual_production_value": "3,000,000 kr"
            },
            "foundation_year": 1886,
            "corporation_year": 1919,
            "board": [
                {
                    "name": "Evert Wijkander",
                    "role": "Styrelse: dir. (ordf.)"
                },
                {
                    "name": "Åke Bergendal",
                    "role": "Disp."
                },
                {
                    "name": "Bengt Carleson",
                    "role": "Disp."
                },
                {
                    "name": "N. Arvid Ericsson",
                    "role": "Disp."
                },
                {
                    "name": "W. Risberg",
                    "role": "Disp."
                }
            ],
            "director": "Verkst. dir. o. disp.: Åke Bergendal",
            "manager": "Kamrer: Erik Mandorf"
        },
        "3": {
            "name": "AB. A. R. Strid",
            "location": "Vetlanda",
            "business": "Mek. verkstad och parkettfabrik",
            "products": "Tillverkar maskiner för träbearbetning såsom klyvsågar, balanskapsågar och pendelkapsågar, specialmaskiner för tillverkning av monteringsfärdiga trähus samt parkettgolv av ek",
            "contact": {
                "office": "Stridar, Vetlanda",
                "phone": [
                    "126"
                ],
                "postgiro": "94655"
            },
            "financials": {
                "capital": "31,000 kr",
                "employees": {
                    "industriarb.": 35
                },
                "annual_production_value": "475,000 kr"
            },
            "foundation_year": 1911,
            "corporation_year": 1941,
            "board": [
                {
                    "name": "C. G. Wictorin",
                    "role": "Styrelse: överinsp. (ordf.)"
                },
                {
                    "name": "Geijer Strid",
                    "role": "Fabr."
                },
                {
                    "name": "Nils Strid",
                    "role": "Ing."
                }
            ],
            "director": "Verkst. dir.: Geijer Strid"
        },
        "4": {
            "name": "AB. Stridsberg & Biörck",
            "location": "Trollhättan",
            "business": "Sågblads- och maskinknivsfabrik",
            "products": "Tillverkar sågblad av alla slag, maskinhyveljärn och maskinknivar m. m.",
            "contact": {
                "office": "Trollhättan",
                "phone": [
                    "Stridsbiörck",
                    "Postgiro: 6080"
                ],
                "sales_offices": [
                    {
                        "location": "Stockholm",
                        "phone": "101398"
                    },
                    {
                        "location": "Stockholm",
                        "phone": "101378"
                    }
                ]
            },
            "financials": {
                "capital": "2,000,000 kr",
                "employees": {
                    "industriarb.": 500
                },
                "annual_production_value": "6,000,000 kr"
            },
            "foundation_year": 1868,
            "corporation_year": 1911,
            "board": [
                {
                    "name": "Gust. ödqvist",
                    "role": "Styrelse: (ordf.)"
                },
                {
                    "name": "Einar Egnell",
                    "role": "Ing."
                },
                {
                    "name": "S. Stridsberg",
                    "role": "Dir."
                }
            ],
            "director": "Verkst. dir.: S. Stridsberg",
            "sales_manager": "Försäljn.-chef: Gunnar Flink",
            "manager": "Inköpschef: Erik Adamson"
        },
        "5": {
            "name": "Stripa Cruv AB",
            "location": "Ludvika",
            "business": "Järnmalmsgruvor",
            "products": "Producerar kvartsrandig, fosforren blodstensmalm och fosforren järnmalmsslig",
            "contact": {
                "office": "Ludvika",
                "phone": [
                    "Ställ-bergsbolagen",
                    "Guldsmeids-hyttan: 70",
                    "Guldsmeids-hyttan: 100"
                ]
            },
            "financials": {
                "capital": "2,300,000 kr",
                "employees": {
                    "industriarb.": 200
                }
            },
            "corporation_year": 1939,
            "board": [
                {
                    "name": "G. A. Klingspor",
                    "role": "Styrelse: (ordf.)"
                },
                {
                    "name": "Carl S:son Leijonhufvud",
                    "role": "majoren (v. ordf.)"
                },
                {
                    "name": "Erik G. Pehrsson",
                    "role": "Dir."
                },
                {
                    "name": "Hugo Stenbeck",
                    "role": "Adv."
                }
            ],
            "director": "Verkst. dir. o. disp.: B. Stein",
            "manager": "Kamrer i Stripa: Uno Zachrisson",
            "sales_manager": "Kamrer vid huvudkontoret: Axel Frövik"
        },
        "6": {
            "name": "Strumpfabriks AB. Kåge",
            "location": "Älvsered",
            "business": "Tillverkar herrstrumpor",
            "products": "Tillv.-värde pr år: 300,000 kr",
            "contact": {
                "phone": [
                    "21"
                ],
                "postgiro": "95372"
            },
            "financials": {
                "capital": "10,000 kr",
                "employees": {
                    "industriarb.": 25
                }
            },
            "corporation_year": 1933,
            "board": [
                {
                    "name": "Knut Gustafsson",
                    "role": "Disp."
                }
            ]
        }
    }
}