{
    "original": "Södra-—Sörby\n\ngurd Edwards, Rörstrandsg. 4, telefon:\n307444.\n\nAkt.-kap.: 189,000 kr. Antal\nindustriarb.: 45. Tillv.-värde pr år: 800,000 kr.\n— Firman etabl. 1901, bolag 1942.\n\nStyrelse: fabr. Melchior Fagerlund\n(ordf.), disp. Gunnar Fagerlund, disp.\nLennart Fagerlund.\n\nVerkst. dir.: M. Fagerlund.\n\nDisponenter: G. Fagerlund o. L.\nFagerlund.\n\n*AB. Södra Dalarnes Gjuter! &amp;\nMaskin verkstad, Hedemora.\n\nSe AB. Hedemora Verkstäder,\nHedemora.\n\n\"Södra Snickerifabrikens AB., Borås.\n\nTillverkar sågade och hyvlade trävaror,\nlistverk, byggnadssnickerier, butiks- och\nkontorsinredningar, garverivalkar och\nfärgbaljor. Firman driver som\nhuvudrörelse handel med byggnadsmateriel.\n\nTelefon: 17500. Postgiro: 85885. —\nAkt.-kap.: 154,000 kr. Antal industriarb.:\n50. — Firman etabl. 1893, bolag 1908.\n\nStyrelse o. verkst. dir.: Axel F. Lind.\n\n\"AB. Södra Snickeri- &amp;\nMöbelfabriken i Svängsta, Svängsta.\n\nMöbelfabrik och tapetserarverkstäder i\nSvängsta (Blekinge l.) samt möbelfabrik\ni Djurslöv (Malmöh. l.). Tillverkar\nmöbler, fåtöljer och stolar samt såsom\nspecialitet möbelstommar. Varumärke: »SSM».\n\nHuvudkontor: Svängsta. Telefon: 47.\nPostgiro: 38498. Avd.-kontor: Djurslöv,\ntelefon: Malmö 45157.\n\nAkt.-kap.: 100,000 kr. Antal\nindustriarb.: 90. Tillv.-värde pr år: 675,000 kr. —\nFirman etabl. 1922, bolaget grundat 1936.\n\nVerkst. dir.: Hilding Ström.\n\n\"Sölvesborgs Bryggeri, Sölvesborg.\n\nSe AB. Skånebryggerier, Hälsingborg.\n\nAB. Sölvesborgs Glasbruk,\n\nSölvesborg.\n\nTillverkar tekn.- och medicinglas,\nhushållsglas, glas för läkemedelsindustrier\nm. m.\n\nTelefon: 10169. Postgiro: 33287. —\nAkt.-kap.: 57,500 kr. Antal industriarb.:\n100. Tillv.-värde pr år: 900,000 kr. —\nGlasbruket anlagt 1896, bolag 1933.\n\nStyrelse: dir. Frans Anderson, hyttm.\nFr. Fischer, dir. Peter Kockum, dir. Emil\nPehrsson, landsfiskal Seth Sandberg.\n\nVerkst. dir.: Peter Kockum.\n\nKontorschef: Harry Svensson.\n\nSölvesborgs Varvs- &amp; Rederi AB.,\n\nSölvesborg.\n\nSkeppsvarv med torrdocka, gjuteri och\nmek. verkstad. Utför nybyggnader och\nreparationer av ång- och motorfartyg\nsamt fiskebåtar. Specialitet: klassning av\nlastångfartyg.\n\nTelegr.-adr.: Varvet, Sölvesborg.\nTelefon: 10011. Postgiro: 20953.\n\nAkt.-kap.: 460,525 kr. Antal\nindustriarb.: 350. Tillv.-värde pr år: 2,660,000 kr.\n\n—\tBolaget grundat 1918.\n\nStyrelse: v. konsul Thure Carlsson\n(ordf.), handl. Emanuel Carlsson (v.\nordf.), övering. Oscar E. Carlson,\nlandstingsman Hugo Jeppsson, fabr. Per\nPåls-son, dir. Per Henrik Sjögren.\nVerkst. dir.: Thure Carlsson.\növering.: Oscar E. Carlson.\n\nAB. Sönnergrens Verkstäder,\n\nGöteborg.\n\nUtför massfabrikation av pressade,\nsvarvade och frästa metallvaror.\nSpecialiteter: stansverktyg och fixturer.\n\nKontor: Postgatan 57. Telegr.-adr.:\nSönnergrens, Göteborg. Telefon: 119044\n\n0.\t133294. Postgiro: 41484.\nAkt.-kap.: 26,000 kr. Antal\nindustriarb.: 23. Tillv.-värde pr år: 220,000 kr.\n\n—\tFirman etabl. 1895, bolag 1928.\nVerkst. dir.: fabr. Ture Sönnergren.\n\nErik Sörberg, Armaturfabrik,\n\nKungsör.\n\nTillverkar armatur för gas, vatten och\nvärme vid fabrik i Kungsör (Västmanl.\n\n1.).\tVarumärke: »SAF».\n\nTelefon: 193 o. 500. Postgiro: 98245.\n\n—\tAntal industriarb.: 65. Tillv.-värde pr\når: 700,000 kr. — Firman etabl. 1936.\n\nÄgare o. chef: ing. Erik Sörberg.\n\nSörby Mek. Verkstad, Örebro.\n\nTillverkar maskiner för bagerier,\nskofabriker m. fl., verktyg, spec.\npressverk-tyg, stålmöbler, pressningsarbeten m. m.\n\nTelefon: 16965. Postgiro: 99954.\n—-Antal industriarb.: 20. Tillv.-värde pr år:\n200,000 kr. — Firman etabl. 1936.\n\nÄgare o. chef: ing. Helmer Berglund.\n\n\"Sörby Tegelbruk, Kummelby.\n\nSe Nya AB. Sörby Tegelbruk,\nNorrköping.",
    "structured": {
        "1": {
            "name": "AB. Södra Dalarnes Gjuteri & Maskinverkstad",
            "location": "Hedemora",
            "business": "Tillverkning av gjutna produkter och maskiner",
            "financials": {
                "capital": "189,000 kr",
                "employees": {
                    "industriarb": 45
                },
                "annual_turnover": "Information saknas",
                "annual_production_value": "800,000 kr"
            },
            "foundation_year": 1901,
            "corporation_year": 1942,
            "board": [
                {
                    "name": "Melchior Fagerlund",
                    "role": "Ordförande"
                },
                {
                    "name": "Gunnar Fagerlund",
                    "role": "Disponent"
                },
                {
                    "name": "Lennart Fagerlund",
                    "role": "Disponent"
                }
            ],
            "director": "M. Fagerlund"
        },
        "2": {
            "name": "AB. Södra Snickerifabrikens",
            "location": "Borås",
            "business": "Tillverkning av trävaror, snickerier, kontorsinredningar och byggnadsmaterial",
            "products": "Sågade och hyvlade trävaror, listverk, byggnadssnickerier, butiks- och kontorsinredningar, garverivalkar och färgbaljor",
            "contact": {
                "phone": [
                    "17500"
                ],
                "postgiro": "85885"
            },
            "financials": {
                "capital": "154,000 kr",
                "employees": {
                    "industriarb": 50
                },
                "annual_production_value": "Information saknas"
            },
            "foundation_year": 1893,
            "corporation_year": 1908,
            "board": [
                {
                    "name": "Axel F. Lind",
                    "role": "Styrelse o. verkst. dir."
                }
            ]
        },
        "3": {
            "name": "AB. Södra Snickeri- & Möbelfabriken i Svängsta",
            "location": "Svängsta",
            "business": "Tillverkning av möbler och möbelstommar",
            "products": "Möbler, fåtöljer och stolar samt som specialitet möbelstommar",
            "contact": {
                "phone": [
                    "47"
                ],
                "postgiro": "38498",
                "sales_offices": [
                    {
                        "location": "Djurslöv",
                        "phone": "Malmö 45157"
                    }
                ]
            },
            "financials": {
                "capital": "100,000 kr",
                "employees": {
                    "industriarb": 90
                },
                "annual_production_value": "675,000 kr"
            },
            "foundation_year": 1922,
            "corporation_year": 1936,
            "director": "Hilding Ström"
        },
        "4": {
            "name": "AB. Sölvesborgs Glasbruk",
            "location": "Sölvesborg",
            "business": "Tillverkning av teknik- och medicinskt glas samt hushållsglas",
            "products": "Teknik- och medicinskt glas, hushållsglas, glas för läkemedelsindustrier m. m.",
            "contact": {
                "phone": [
                    "10169"
                ],
                "postgiro": "33287"
            },
            "financials": {
                "capital": "57,500 kr",
                "employees": {
                    "industriarb": 100
                },
                "annual_production_value": "900,000 kr"
            },
            "foundation_year": 1896,
            "corporation_year": 1933,
            "board": [
                {
                    "name": "Frans Anderson",
                    "role": "Styrelse"
                },
                {
                    "name": "Fr. Fischer",
                    "role": "Styrelse"
                },
                {
                    "name": "Peter Kockum",
                    "role": "Styrelse"
                },
                {
                    "name": "Emil Pehrsson",
                    "role": "Styrelse"
                },
                {
                    "name": "Seth Sandberg",
                    "role": "Landsfiskal"
                }
            ],
            "director": "Peter Kockum",
            "manager": "Harry Svensson"
        },
        "5": {
            "name": "Sölvesborgs Varvs- & Rederi AB.",
            "location": "Sölvesborg",
            "business": "Skeppsvarv med torrdocka, gjuteri och mek. verkstad",
            "products": "Nybyggnader och reparationer av ång- och motorfartyg samt fiskebåtar, klassning av lastångfartyg",
            "contact": {
                "telegraph": "Varvet, Sölvesborg",
                "phone": "10011",
                "postgiro": "20953"
            },
            "financials": {
                "capital": "460,525 kr",
                "employees": {
                    "industriarb": 350
                },
                "annual_production_value": "2,660,000 kr"
            },
            "corporation_year": 1918,
            "board": [
                {
                    "name": "Thure Carlsson",
                    "role": "Styrelse o. verkst. dir."
                },
                {
                    "name": "Oscar E. Carlson",
                    "role": "Övering."
                }
            ]
        },
        "6": {
            "name": "AB. Sönnergrens Verkstäder",
            "location": "Göteborg",
            "business": "Massfabrikation av pressade, svarvade och frästa metallvaror",
            "products": "Stansverktyg och fixturer",
            "contact": {
                "location": "Postgatan 57",
                "phone": [
                    "119044",
                    "133294"
                ],
                "postgiro": "41484"
            },
            "financials": {
                "capital": "26,000 kr",
                "employees": {
                    "industriarb": 23
                },
                "annual_production_value": "220,000 kr"
            },
            "corporation_year": 1928,
            "director": "Ture Sönnergren"
        },
        "7": {
            "name": "Erik Sörberg, Armaturfabrik",
            "location": "Kungsör",
            "business": "Tillverkning av armatur för gas, vatten och värme",
            "products": "Armatu",
            "contact": {
                "phone": [
                    "193",
                    "500"
                ],
                "postgiro": "98245"
            },
            "financials": {
                "employees": {
                    "industriarb": 65
                },
                "annual_production_value": "700,000 kr"
            },
            "corporation_year": 1936,
            "owner": "Erik Sörberg"
        },
        "8": {
            "name": "Sörby Mek. Verkstad",
            "location": "Örebro",
            "business": "Tillverkning av maskiner och verktyg",
            "products": "Maskiner för bagerier, skofabriker m. fl., verktyg, spec. pressverktyg, stålmöbler, pressningsarbeten m. m.",
            "contact": {
                "phone": [
                    "16965"
                ],
                "postgiro": "99954"
            },
            "financials": {
                "employees": {
                    "industriarb": 20
                },
                "annual_production_value": "200,000 kr"
            },
            "corporation_year": 1936,
            "owner": "Helmer Berglund"
        }
    }
}