{
    "original": "Edman—Edsvalla\n\n*Edmans Stolfabrik, Bröderna, Tibro.\nSe Bröderna Edmans Stolfabrik* Tibro.\n\nAB. Ednells Mek. Verkstad,\n\nDals Långed.\n\nMek. verkstad i Dals Långed (Älvsb.\n1.). Tillverkar maskiner för pappersbruk\nsåsom asfalteringsmaskiner,\nkräppmaski-ner, paraffineringsmaskiner,\ngummerings-maskiner, hylsmaskiner, rullmaskiner,\nvi-raregulatorer samt pappersmaskindelar\nm. m.\n\nTelefon: 68. Postgiro: 80194.\nAkt.-kap.: 22,100 kr. Antal\nindustriarb.: 15. Tillv.-värde pr år: 145,000 kr.\n\n—\tFirman etabl. 1930, bolag 1938.\nVerkst. dir.: fabr. Osear Ednell.\n\n* Edsbyns Industri AB., Edsbyn.\n\nJärnmanufakturverk i Edsbyn (Gävleb.\n\n1.).\tTillverkar sågar, sågblad och\nsågbå-gar, skogsverktyg, handredskap och\nverktyg, cykelstäil, slipstensställningar,\ndisk-torkställ m. m.\n\nTelegr.-adr.: Industribolaget, Edsbyn.\nTelefon: »Eiabolaget». Postgiro: 26550.\nFörsäljn.-kontor o. nederlag: Stockholm,\nRegeringsg. 45, telefon: 106079; Göteborg,\ntrollhätteg. 10, telefon: 194930; Malmö,\nÖsterg. 10, telefon: 78755.\n\nAkt.-kap.: 60,000 kr. Antal\nindustriarb.: 60. — Bolaget grundat 1929.\n\nStyrelse: dir. Leander Owén (ordf.),\ndisp. Nils Mure, verkm. Tobias\nWilhelmsson.\n\nVerkst. dir.: Leander Owén.\nDisp.: Nils Mure.\n\n*AB. Edsbyns Möbelfabrik,\n\nEdsbyn.\n\nTillverkar björk- och furumöbler samt\nsvarvade pinnstolar vid fabrik i Edsbyn\n(Gävleb. l.). Varumärke: »EMS».\n\nTelegr.-adr.: Edsbyverk, Edsbyn.\nTelefon: Edsby verken. Postgiro: 34144.\nFörsäljn.-kontor: Stockholm, Malmgårdsv.\n22, telefon: 401348; Göteborg, ö. Hamng.\n\n2,\ttelefon: 117304; Sundsvall, telefon:\n4843.\n\nAkt.-kap.: 150,000 kr. Antal\nindustriarb.: 226. Tillv.-värde pr år: 2,500,000 kr.\n\n—\tFirman etabl. 1899, bolag 1941.\nStyrelse: dir. L. Ivar Pettersson\n\n(ordf.), disp. Bengt I. Ivarsson.\nVerkst. dir.: L. Ivar Pettersson.\nDisp.: Bengt I. Ivarsson.\n\nAB. Edsbyns Skidfabrik, Edsbyn.\n\nTillverkar skidor vid fabrik i Edsbyn\n(Gävleb. l.). Varumärke: »ES».\n\nTelegr.-adr.: Edsbyverk, Edsbyn.\nTelefon: Edsby verken. Postgiro: 91172.\n\nAkt.-kap.: 150,000 kr. Antal\nindustriarb.: 75. Tillv.-värde pr år: 1,000,000 kr.\n— Firman etabl. 1899, bolag 1941.\nVerkst. dir.: L. Ivar Pettersson.\nFabrikschef: Thure öhman.\nDisp.: Bengt I. Ivarsson.\n\n* Edsbyns Träförädlings AB.,\n\nNorredsbyn.\n\nPlywoodfabrik vid Edsbyn (Gävleb. L).\nTillverkar kryssfanér (plywood) av björk,\nfuru och asp.\n\nTelegr.-adr.: Björkvik, Edsbyn.\nTelefon: Edsbyn 25. Postgiro: 70438. —\nAkt.-kap.: 180,000 kr. Antal industriarb.:\n30. Tillv.-värde pr år: 500,000 kr.\nBolaget grundat 1912.\n\nStyrelse: järnhandl. Johan G. Jonsson\n(ordf.), handl. O. Bergstrand, hemmånsäg.\nGustaf Olsson.\n\nDisp.: Valfrid Jeanson.\n\nEdsbyns Ullspinneri, Edsbyn.\n\nTillverkar strump-, väv- och\nstickgarner, raffelstopp och täckvadd,’ yllefloek\nsamt madrasser, kuddar och täcken vid\nfabrik i Edsbyn (Gävleb. l.). v\n\nTelefon: 115. Postgiro: 77947. -—\nAntal industriarb.: 14. — Firman etabl.\n1918.\n\nChef: fabr. Claes R. Pettersson.\n\nDisp.: Manne Rubrandt.\n\nAB. Edsbyns Ångsåg,\n\nEdsbyn.\n\nSågverk och hyvleri i Edsbyn (Gävleb.\n1.). Tillverkar sågade och hyvlade\nträvaror.\n\nTelegr.-adr.: Edsbysåg, Edsbyn.\nTelefon: »Edsbyverken». Postgiro: 36501. —\nAkt.-kap.: 80,000 kr. Antal industriarb.:\n35. Årstillv.: 1,700 stds trävaror. —\nBolaget grundat 1917.\n\nVerkst. dir.: L. Ivar Pettersson.\n\n*AB. Edsvalla Bruk, Edsvalla.\n\nSulfitfabrik i Edsvalla (Värml. l.).\nTillverkar blekt sulfitcellulosa.\n\nTelegr.-adr.: Edsvallabruket, Karlstad.\nTelefon: Karlstad 44100. Postgiro: 21043.\n\n",
    "structured": {
        "firms": [
            {
                "name": "Edmans Stolfabrik, Bröderna",
                "location": "Tibro",
                "business": "Tillverkar maskiner för pappersbruk",
                "products": "asfalteringsmaskiner, kräppmaskiner, paraffineringsmaskiner, gummieringsmaskiner, hylsmaskiner, rullmaskiner, vi-raregulatorer samt pappersmaskindelar m. m.",
                "contact": {
                    "office": "Dals Långed",
                    "phone": [
                        "68"
                    ],
                    "postgiro": "80194"
                },
                "financials": {
                    "capital": "22,100 kr",
                    "employees": {
                        "industriarb": 15
                    },
                    "annual_turnover": "145,000 kr",
                    "annual_production_value": "145,000 kr"
                },
                "foundation_year": 1930,
                "corporation_year": 1938,
                "board": [
                    {
                        "name": "fabr. Osear Ednell",
                        "role": "Verkst. dir."
                    }
                ]
            },
            {
                "name": "Edsbyns Industri AB.",
                "location": "Edsbyn",
                "business": "Tillverkar sågar, sågblad och sågbågar, skogsverktyg, handredskap och verktyg, cykelställ, slipstensställningar, disk-torkställ m. m.",
                "contact": {
                    "sales_offices": [
                        {
                            "location": "Stockholm",
                            "phone": "106079"
                        },
                        {
                            "location": "Göteborg",
                            "phone": "194930"
                        },
                        {
                            "location": "Malmö",
                            "phone": "78755"
                        }
                    ],
                    "postgiro": "26550"
                },
                "financials": {
                    "capital": "60,000 kr",
                    "employees": {
                        "industriarb": 60
                    }
                },
                "corporation_year": 1929,
                "board": [
                    {
                        "name": "Leander Owén",
                        "role": "Styrelse"
                    },
                    {
                        "name": "Nils Mure",
                        "role": "Disp."
                    }
                ],
                "owner": "Leander Owén",
                "director": "Leander Owén"
            },
            {
                "name": "AB. Edsbyns Möbelfabrik",
                "location": "Edsbyn",
                "business": "Tillverkar björk- och furumöbler samt svarvade pinnstolar",
                "products": "EMöbler",
                "contact": {
                    "sales_offices": [
                        {
                            "location": "Stockholm",
                            "phone": "401348"
                        },
                        {
                            "location": "Göteborg",
                            "phone": "117304"
                        },
                        {
                            "location": "Sundsvall",
                            "phone": "4843"
                        }
                    ],
                    "postgiro": "34144"
                },
                "financials": {
                    "capital": "150,000 kr",
                    "employees": {
                        "industriarb": 226
                    },
                    "annual_production_value": "2,500,000 kr"
                },
                "corporation_year": 1941,
                "board": [
                    {
                        "name": "L. Ivar Pettersson",
                        "role": "ordf."
                    },
                    {
                        "name": "Bengt I. Ivarsson",
                        "role": "Disp."
                    }
                ],
                "owner": "L. Ivar Pettersson",
                "director": "L. Ivar Pettersson"
            },
            {
                "name": "AB. Edsbyns Skidfabrik",
                "location": "Edsbyn",
                "business": "Tillverkar skidor",
                "products": "ES",
                "contact": {
                    "postgiro": "91172"
                },
                "financials": {
                    "capital": "150,000 kr",
                    "employees": {
                        "industriarb": 75
                    },
                    "annual_production_value": "1,000,000 kr"
                },
                "corporation_year": 1941,
                "director": "L. Ivar Pettersson",
                "sales_manager": "Thure öhman",
                "owner": "L. Ivar Pettersson"
            },
            {
                "name": "AB. Edsbyns Träförädlings AB.",
                "location": "Norredsbyn",
                "business": "Tillverkar kryssfanér (plywood) av björk, furu och asp",
                "contact": {
                    "postgiro": "70438"
                },
                "financials": {
                    "capital": "180,000 kr",
                    "employees": {
                        "industriarb": 30
                    },
                    "annual_production_value": "500,000 kr"
                },
                "board": [
                    {
                        "name": "Johan G. Jonsson",
                        "role": "ordf."
                    },
                    {
                        "name": "O. Bergstrand",
                        "role": "Disp."
                    }
                ],
                "director": "Claes R. Pettersson"
            },
            {
                "name": "Edsbyns Ullspinneri",
                "location": "Edsbyn",
                "business": "Tillverkar strump-, väv- och stickgarner, raffelstopp och täckvadd, yllefloek samt madrasser, kuddar och täcken",
                "contact": {
                    "postgiro": "77947"
                },
                "employees": {
                    "industriarb": 14
                },
                "director": "Claes R. Pettersson"
            },
            {
                "name": "AB. Edsbyns Ångsåg",
                "location": "Edsbyn",
                "business": "Tillverkar sågade och hyvlade trävaror"
            },
            {
                "name": "AB. Edsvalla Bruk",
                "location": "Edsvalla",
                "business": "Tillverkar blekt sulfitcellulosa",
                "contact": {
                    "postgiro": "21043"
                }
            }
        ]
    }
}