{
    "original": "Svenska\n\nbojar, radiofyrar och radiopejlapparater\nsamt optiska instrument såsom kikare,\navståndsmätare och periskop.\n\nvägövergångs- och trafiksignaler,\nljusapparater för järnvägssignaler,\nstrålkastare och signallyktor för såväl\nacetylen-dissousgas som för elektr. drift för\nmilitärt eller civilt bruk, apparater och\narmatur för acetylen-dissousgasbelysning för\njärnvägsvagnar och lokomotiv, axeldrivna\nelektriska generatoraggregat för\nbelysning i järnvägsvagnar, ångarmatur ^\n(system: »Vapor») för uppvärmning av\njärnvägsvagnar, elektr. reläer och\nlikriktar-aggregat, trafikmärken och vägvisare med\nreflexanordningar;\n\napparater för lustgasnarkos,\nförloss-ningsanalgesi, syrgas- och\nkarbogeniuha-lation; kovöser, elektroakustiska\nanläggningar, kolsyresläekare, militära\napparater ;\n\nkokseldade värmeackumulerande spisar\n(»AGA»-spisar);\n\napparater och maskiner för gas- och\nelektrisk svetsning samt apparater och\nmaskiner för gasskärning, ythärdning och\nsyrgashyvling ävensom plåtradiatorer och\nsvetsningsmaskiner för tillverkning av\ndylika.\n\nHuvudkontor: Lidingö—Skärsätra;\npostadr. : Stockholm—Lidingö. Telegr.-adr.:\nAgafaros, Stockholm. Telefon: »Aga».\nPostgiro: 591. Utställning: Stockholm,\nKungsg. 13. Filial: Göteborg, Postgatan\n2, telefon: »Aga». Repr. för södra\nSverige: AB. Aga-Faxius, Malmö, Lodg. 1,\ntelefon: 72400.\n\nAkt.-kap.: 28,600,000 kr. Antal\nindustriarb.: 850.\n\nBolaget, grundat 1904, har egna\nförsäljningsorganisationer i de flesta länder.\n\nStyrelse: disp. John Hedin (ordf.),\nbankdir. E. Browaldh, kabinettskammarh.\nRolf. v. Heidenstam, dir. Hans Th. Holm,\nf. d. kanslisekr. E. G. Zethelius.\nVerkst. dir.: Rolf v. Heidenstam.\nDirektörer: ing. Gunnar Dalén, ing.\nAxel Mellin o. ing. Gunnar Ehn.\nVerkstadschef: ing. Oscar Hedberg.\nAvd.-chefer:\n\nkontorschef: ing. Folke Aurell;\nför kameralavd.: H. Lennman;\nför skeppningsavd.: S. Malm;\nför gasförsäljn.: B. Elliot;\nför revisionsavd.: A. Burgé;\nför gasstationsanläggningar: ing.\nHerbert Lindblad;\n\nför fyrbelysningsavd. o. avd. för\njärnvägsbelysning, trafiksignaler o.\nstrålkastare: ing. O. Plass;\n\nför specialarbeten o. kalkylavdelning:\ning. Fritiof Lindblom;\n\nför svetsningsavd.: ing. B. F. Gorthon;\n\nför plåtradiatorer och maskiner för\ntillverkning därav: A. H. Befrits;\n\nför AGA-spisar: H. V. Stenberij;\n\nför medicinska apparater, militära\narbeten, strömningsmätare etc.: Sigurd\nLindholm;\n\nför reklamavd.: Olle Lidbeck;\n\nför ritkontoret: ing. H. Spiegelberg;\n\nför inköpsavd.: Sigurd Sjöberg.\n\nDriftschef för dissousgas- och\nsyrgas-stationen: ing. Josef S. Ericsson.\n\nSvenska Granitindustri AB.,\n\nKarlshamn.\n\nGranitbrott och stenhuggerier å olika\nplatser inom södra Sverige samt i Norge.\nTillverkar blocksten, byggnadssten,\nmonument och gravvårdar m. fl. polerade\noch slipade arbeten av granit.\n\nTelegr.-adr.: Granitindustri,\nKarlshamn. Telefon: 671 o. 672. Postgiro:\n5431.\n\nAkt.-kap.: 1.500,000 kr. Antal\nindustriarb.: 100. — Bolaget grundat 1896.\n\nStyrelse: dir. E. K. Fernström (ordf.),\nfru E. Fernström, disp. Holger\nFernström, kontorschef F. F. Guntsch, jur.\ndr Axel Roos.\n\nVerkst. dir.: Holger Fernström.\n\nKamrer: G. Kutzner.\n\nFörsäljn.-chef: Gösta E. Johansson.\n\n\"AB. Svenska Culdlistfabriken,\n\nKarlstad.\n\nTillverkar ram- och tapetlister,\nfotografiramar, ovala ramar, kornischer och\nportierstänger.\n\nTelegr.-adr.: Guldlisten, Karlstad.\nPostgiro: 6563. Representanter: Stockholm:\nG. Norling, Slussplan 5, telefon: 111074;\nGöteborg: AB. Lars Ahlberg, V:a Hamng.\n22, telefon: 116434; Malmö: Nilssons\nGuldlistfabrik, Gröneg. 60, telef.: 22023.\n\nAkt.-kap.: 150,000 kr. Antal\nindustriarb.: 40. — Bolaget grundat 1897.\n\nStyrelse: disp. Sigurd Neumann\n(ordf.), herr Viktor Arendorf, kapten\nAxel Törner.\n\nVerkst. dir.: Sigurd Neumann.\n\nV. verkst. dir.: Axel Törner.\n\n\"Svenska Gummifabriks AB.,\n\nGislaved.\n\nGummivarufabrik vid Gyllenfors,\nGislaved (Jönköp. l.). Tillverkar bil- och\ncykelgummi, alla slags gummiskodon,\nkilremmar samt latexprodukter.\n\nTelegr.-adr. o. telefon: Gummifabriken,\nGislaved. Postgiro: 22555.",
    "structured": {
        "firms": [
            {
                "name": "AGA AB",
                "location": "Stockholm—Lidingö",
                "business": "Tillverkning av radiofyrar, radiopejlapparater, optiska instrument, vägövergångs- och trafiksignaler, ljusapparater för järnvägssignaler, strålkastare och signallyktor, apparater för lustgasnarkos, kovöser, kokseldade värmeackumulerande spisar, apparater och maskiner för gas- och elektrisk svetsning samt apparater och maskiner för gasskärning, ythärdning och syrgashyvling ävensom plåtradiatorer och svetsningsmaskiner för tillverkning av dylika",
                "products": "Egna försäljningsorganisationer i de flesta länder",
                "contact": {
                    "office": "Lidingö—Skärsätra",
                    "phone": [
                        "Aga"
                    ],
                    "postgiro": "591",
                    "head_office": "Lidingö",
                    "sales_offices": [
                        {
                            "location": "Stockholm",
                            "phone": "Aga"
                        },
                        {
                            "location": "Göteborg",
                            "phone": "Aga"
                        }
                    ],
                    "telegraph": "Agafaros, Stockholm",
                    "factory_office": "Not specified",
                    "factory_phone": "Not specified"
                },
                "financials": {
                    "capital": "28,600,000 kr",
                    "employees": {
                        "industriarb": 850
                    }
                },
                "foundation_year": 1904,
                "board": [
                    {
                        "name": "disp. John Hedin",
                        "role": "ordförande"
                    },
                    {
                        "name": "bankdir. E. Browaldh",
                        "role": "Not specified"
                    },
                    {
                        "name": "kabinettskammarh. Rolf. v. Heidenstam",
                        "role": "Not specified"
                    },
                    {
                        "name": "dir. Hans Th. Holm",
                        "role": "Not specified"
                    },
                    {
                        "name": "f. d. kanslisekr. E. G. Zethelius",
                        "role": "Not specified"
                    }
                ]
            },
            {
                "name": "Svenska Granitindustri AB",
                "location": "Karlshamn",
                "business": "Tillverkning av blocksten, byggnadssten, monument, gravvårdar, polerade och slipade arbeten av granit",
                "products": "Not specified",
                "contact": {
                    "office": "Not specified",
                    "phone": [
                        "671",
                        "672"
                    ],
                    "postgiro": "5431",
                    "head_office": "Not specified",
                    "sales_offices": [],
                    "telegraph": "Granitindustri, Karlshamn",
                    "factory_office": "Not specified",
                    "factory_phone": "Not specified"
                },
                "financials": {
                    "capital": "1,500,000 kr",
                    "employees": {
                        "industriarb": 100
                    }
                },
                "foundation_year": 1896,
                "board": [
                    {
                        "name": "dir. E. K. Fernström",
                        "role": "ordförande"
                    },
                    {
                        "name": "fru E. Fernström",
                        "role": "Not specified"
                    },
                    {
                        "name": "disp. Holger Fernström",
                        "role": "Not specified"
                    },
                    {
                        "name": "kontorschef F. F. Guntsch",
                        "role": "Not specified"
                    },
                    {
                        "name": "jur. dr Axel Roos",
                        "role": "Not specified"
                    }
                ]
            },
            {
                "name": "AB. Svenska Guldlistfabriken",
                "location": "Karlstad",
                "business": "Tillverkning av ram- och tapetlister, fotografiramar, ovala ramar, kornischer och portierstänger",
                "products": "Not specified",
                "contact": {
                    "office": "Not specified",
                    "phone": [],
                    "postgiro": "6563",
                    "head_office": "Not specified",
                    "sales_offices": [
                        {
                            "location": "Stockholm",
                            "phone": "111074"
                        },
                        {
                            "location": "Göteborg",
                            "phone": "116434"
                        },
                        {
                            "location": "Malmö",
                            "phone": "22023"
                        }
                    ],
                    "telegraph": "Guldlisten, Karlstad",
                    "factory_office": "Not specified",
                    "factory_phone": "Not specified"
                },
                "financials": {
                    "capital": "150,000 kr",
                    "employees": {
                        "industriarb": 40
                    }
                },
                "foundation_year": 1897,
                "board": [
                    {
                        "name": "disp. Sigurd Neumann",
                        "role": "ordförande"
                    },
                    {
                        "name": "herr Viktor Arendorf",
                        "role": "Not specified"
                    },
                    {
                        "name": "kapten Axel Törner",
                        "role": "Not specified"
                    }
                ]
            },
            {
                "name": "Svenska Gummifabriks AB.",
                "location": "Gislaved",
                "business": "Tillverkning av bil- och cykelgummi, alla slags gummiskodon, kilremmar samt latexprodukter",
                "products": "Not specified",
                "contact": {
                    "office": "Gyllenfors, Gislaved",
                    "phone": [
                        "Gummifabriken"
                    ],
                    "postgiro": "22555",
                    "head_office": "Not specified",
                    "sales_offices": [],
                    "telegraph": "Gummifabriken, Gislaved",
                    "factory_office": "Not specified",
                    "factory_phone": "Not specified"
                },
                "financials": {
                    "capital": "Not specified",
                    "employees": {
                        "industriarb": "Not specified"
                    }
                },
                "foundation_year": "Not specified",
                "board": [
                    {
                        "name": "Not specified",
                        "role": "Not specified"
                    }
                ]
            }
        ]
    }
}