{
    "original": "Strömbergshyttan—Strömsfors\n\n\"AB. Strömbergshyttan,\n\nHovmantorp.\n\nGlasbruk vid Hovmantorp (Kronob. l.).\nTillverkar slätt och slipat samt vitt och\nfärgat prydnads- och hushållsglas.\nVarumärke: »Strömbergshyttan».\n\nTelegr.-adr.: Esshyttan, Växjö.\nTelefon: 32. Postgiro: 99131.\n\nAkt.-kap.: 60,000 kr. Antal\nindustriarb.: 60. Tillv.-värde pr år: 700,000 kr.\n— Firman etabl. 1933, bolag 1946.\n\nStyrelse: fru Asta Strömberg, disp.\nEric Strömberg.\n\nDisp.: Eric Strömberg.\n\n\"Strömma Bomulls Spinneri AB.,\n\nKarlshamn.\n\nSpinneri, väveri och färgeri. Tillverkar\nbomullsgarn samt oblekta, blekta,\nfärgade och kulörta bomullsvävnader.\n\nHuvudkontor: Karlshamn. Telegr.-adr.:\nStrömma, Karlshamn. Telefon: 65 o. 689.\nPostgiro: 8102. Avd.-kontor: Stockholm,\nApelbergsg. 50, telefon: 100342—45;\nGöteborg, Smedjeg. 2 &amp; 4, telefon: 170295.\n\nAkt.-kap.: 1,500,000 kr. Antal\nindustriarb.: 300. Tillv.-värde pr år: 6,000,000 kr.\n\nFirman, grundad 1831, bolag 1867,\näger AB. Strömma Trikåfabrik,\nKarlshamn.\n\nStyrelse: kommendör Sven Fredholm,\ngodsförvalt. Sven E. Hellerström, disp.\nHarald Hygrell, major Erik Janzén.\n\nDisp.: Harald Hygrell.\n\nAB. Strömma Trikåfabrik,\n\nKarlshamn.\n\nTillverkar strumpor vid fabrik i\nStrömma, Karlshamn (Blekinge l.).\n\nTelefon: 65 o. 689. — Akt.-kap.: 101,000\nkr. Antal industriarb.: 40. Tillv.-värde pr\når: 425,000 kr.\n\nFirman, etabl. 1911, är dotterbolag till\nStrömma Bomulls Spinneri AB.,\nKarlshamn, och försäljer hela sin tillverkning\ngenom detta bolag.\n\nStyrelse: kommendör Sven Fredholm,\ngodsförvalt. Sven E. Hellerström, disp.\nHarald Hygrell.\n\nVerkst. dir. o. disp.: Harald Hygrell.\n\n\"AB. Strömman &amp; Larsson, Göteborg.\n\nSnickerifabrik med lådfabrik och\nhyvleri i Backa s:n intill Göteborg.\nTillverkar byggnadssnickerier, listverk,\nekparkett, lamellträ, lamelldörrar, lådor m. m.\nsamt sågade och hyvlade trävaror.\n\nKontor: Tingstad; postadr.: Göteborg\n1. Telegr.-adr.: Stromlar, Göteborg.\nTelefon: 222190. Postgiro: 41752.\n\nAkt.-kap.: 600,000 kr. Antal\nindustriarb.: 100. — Bolaget bildat 1873,\nombil-dat 1930.\n\nStyrelse: avd.-chef Ingmar Hamberg,\ndir. Ragnar Hamberg, generalkonsul\nFolke Jonsson.\n\nVerkst. dir.: Ragnar Hamberg.\n\nAB. Strömmingskonserver, Uppsala.\nSe AB. Uplandsprodukter, Uppsala.\n\n\"Strömnäs AB., Kramfors.\n\nSågverk och hyvleri vid Strömnäs\n(Västernorrl. l.), vilka äro utarrenderade\ntill Kramfors AB., Kramfors (se detta\nbolag). Bolaget idkar skogshantering och\njordbruk.\n\nTelegr.-adr.: Strömnäsbolag, Kramfors.\nTelefon: Kramfors 2000. Postgiro: 5110.\n\nAkt.-kap.: 2,100,000 kr. Årskapacitet:\n18,000 stds sågade o. hyvlade trävaror.\n\nBolaget, som grundades 1877, är\nhuvudbolag för Sandö Sågverks AB. och Nensjö\nCellulosa AB.\n\nStyrelse: dir. Torsten Hérnod (ordf.),\nbankdir. P. F. Wåhlin (v. ordf.), dir. K.\nErik Nyberg, dir. A. Orrmell, dir. Gust.\nJ, Sahlin.\n\nVerkst. dir.: A. Orrmell.\nDisp.: R. Frölander.\növering.: U. Fryklund.\nSlcogschef: H. Swan.\nKontorschef: Gustaf Granquist.\n\n\"Strömsbro Spinneri, Strömsbro.\nSe Gefle Manufaktur AB., Strömsbro.\n\nStrömsfors Bruk, Strömsfors.\n\nMek. verkstad, gjuteri och sågverk vid\nStrömsfors (Älvsb. l.).\n\nTillverkar automatiska\netiketterings-maskiner för flaskor, burkar m. m. Vid\nbruket drives även kvarnrörelse.\n\nTelegr.-adr.: Strömsforsbruk,\nStrömsfors. Telefon: Svenljunga 27072.\nPostgiro: 76255.\n\nAntal industriarb.: 60. Tillv.-värde pr\når: 800,000 kr. — Verkstaden anlagd\n1884.\n\nÄgare: civiling. Axel Nyländer\n(Borås).\n\nPlatschef: ing. Th. Strömberg.\n\n517*",
    "structured": {
        "1": {
            "name": "AB. Strömbergshyttan",
            "location": "Hovmantorp",
            "business": "Glasbruk",
            "products": "Tillverkar slätt och slipat samt vitt och färgat prydnads- och hushållsglas.",
            "contact": {
                "office": "Glasbruk vid Hovmantorp (Kronob. l.)",
                "phone": [
                    "32"
                ],
                "postgiro": "99131",
                "telegraph": "Esshyttan, Växjö"
            },
            "financials": {
                "capital": "60,000 kr",
                "employees": {
                    "industriarb.": 60
                },
                "annual_turnover": "700,000 kr",
                "annual_production_value": "700,000 kr"
            },
            "foundation_year": 1933,
            "corporation_year": 1946,
            "board": [
                {
                    "name": "fru Asta Strömberg",
                    "role": ""
                },
                {
                    "name": "disp. Eric Strömberg",
                    "role": ""
                }
            ],
            "director": "Eric Strömberg"
        },
        "2": {
            "name": "Strömma Bomulls Spinneri AB.",
            "location": "Karlshamn",
            "business": "Spinneri, väveri och färgeri",
            "products": "Tillverkar bomullsgarn samt oblekta, blekta, färgade och kulörta bomullsvävnader.",
            "contact": {
                "office": "",
                "phone": [
                    "65",
                    "689"
                ],
                "postgiro": "8102",
                "sales_offices": [
                    {
                        "location": "Stockholm",
                        "phone": "100342—45"
                    },
                    {
                        "location": "Göteborg",
                        "phone": "170295"
                    }
                ]
            },
            "financials": {
                "capital": "1,500,000 kr",
                "employees": {
                    "industriarb.": 300
                },
                "annual_turnover": "6,000,000 kr",
                "annual_production_value": "6,000,000 kr"
            },
            "foundation_year": 1831,
            "corporation_year": 1867,
            "predecessor": "AB. Strömma Trikåfabrik, Karlshamn",
            "board": [
                {
                    "name": "kommendör Sven Fredholm",
                    "role": ""
                },
                {
                    "name": "godsförvalt. Sven E. Hellerström",
                    "role": "disp."
                },
                {
                    "name": "major Erik Janzén",
                    "role": ""
                }
            ],
            "director": "Harald Hygrell"
        },
        "3": {
            "name": "AB. Strömma Trikåfabrik",
            "location": "Karlshamn",
            "business": "Tillverkar strumpor vid fabrik i Strömma, Karlshamn (Blekinge l.)",
            "contact": {
                "phone": [
                    "65",
                    "689"
                ]
            },
            "financials": {
                "capital": "101,000 kr",
                "employees": {
                    "industriarb.": 40
                },
                "annual_turnover": "425,000 kr",
                "annual_production_value": "425,000 kr"
            },
            "foundation_year": 1911,
            "board": [
                {
                    "name": "kommendör Sven Fredholm",
                    "role": ""
                },
                {
                    "name": "godsförvalt. Sven E. Hellerström",
                    "role": "disp."
                },
                {
                    "name": "Harald Hygrell",
                    "role": ""
                }
            ],
            "managing_director": "Harald Hygrell"
        },
        "4": {
            "name": "AB. Strömman & Larsson",
            "location": "Göteborg",
            "business": "Snickerifabrik",
            "products": "Tillverkar byggnadssnickerier, listverk, ekparkett, lamellträ, lamelldörrar, lådor m. m. samt sågade och hyvlade trävaror.",
            "contact": {
                "office": "Backa s:n intill Göteborg",
                "phone": [
                    "222190"
                ],
                "postgiro": "41752",
                "telegraph": "Stromlar, Göteborg"
            },
            "financials": {
                "capital": "600,000 kr",
                "employees": {
                    "industriarb.": 100
                },
                "corporation_year": 1873
            },
            "board": [
                {
                    "name": "avd.-chef Ingmar Hamberg",
                    "role": ""
                },
                {
                    "name": "dir. Ragnar Hamberg",
                    "role": ""
                },
                {
                    "name": "generalkonsul Folke Jonsson",
                    "role": ""
                }
            ],
            "manager": "Ragnar Hamberg"
        },
        "5": {
            "name": "Strömnäs AB.",
            "location": "Kramfors",
            "business": "Sågverk och hyvleri",
            "contact": {
                "phone": [
                    "Kramfors 2000"
                ],
                "postgiro": "5110",
                "telegraph": "Strömnäsbolag, Kramfors"
            },
            "financials": {
                "capital": "2,100,000 kr",
                "annual_production_value": "18,000 stds sågade o. hyvlade trävaror"
            },
            "foundation_year": 1877,
            "board": [
                {
                    "name": "dir. Torsten Hérnod",
                    "role": "ordf."
                },
                {
                    "name": "bankdir. P. F. Wåhlin",
                    "role": "v. ordf."
                },
                {
                    "name": "dir. K. Erik Nyberg",
                    "role": ""
                },
                {
                    "name": "dir. A. Orrmell",
                    "role": ""
                },
                {
                    "name": "dir. Gust. J, Sahlin",
                    "role": ""
                }
            ],
            "director": "A. Orrmell"
        },
        "6": {
            "name": "Strömsfors Bruk",
            "location": "Strömsfors",
            "business": "Mek. verkstad, gjuteri och sågverk",
            "products": "Tillverkar automatiska etiketterings-maskiner för flaskor, burkar m. m.",
            "contact": {
                "office": "Strömsfors (Älvsb. l.)",
                "phone": [
                    "Svenljunga 27072"
                ],
                "postgiro": "76255"
            },
            "financials": {
                "employees": {
                    "industriarb.": 60
                },
                "annual_production_value": "800,000 kr"
            },
            "board": [
                {
                    "name": "civiling. Axel Nyländer",
                    "role": "Ägare"
                }
            ],
            "director": "ing. Th. Strömberg"
        }
    }
}