{
    "original": "Svenska\n\nSvensk Konsthartz industri, Gemla.\n\nBakelitpresseri i Gemla (Kronob. l.).\nTillverkar artiklar av pressat konstharts\nsåsom skruvlock, kapsyler, etuier, kulor,\nknappar m. m. samt specialdetaljer för\nolika industriändamål.\n\nTelefon: Växjö 67127. Postgiro: 97280.\n\n—\tAntal industriarb.: 50. Tillv.-värde pr\når: 350,000 kr. — Firman etabl. 1935.\n\nDelägare o. chef: fabr. Hugo Helmert.\nTehn. chef: Hans Wiillrich.\n\n*AB. Svensk Läderkonst,\n\nSollebrunn.\n\nMöbelfabrik i Sollebrunn (Älvsb. l.).\nTillverkar fåtöljer ocb soffor i skinn och\ntyg. Specialitet: Skinnmöbler.\n\nTelefon: 54 o. 74. Postgiro: 83151.\nAkt.-kap.: 35,000 kr. Antal\nindustriarb.: 60. Tillv.-värde pr år: 500,000 kr.\n\n—\tBolaget grundat 1932.\nDisponenter: Erik Danielson o. Karl\n\nEriksson.\n\nSvensk Metallförädfing AB.,\n\nSundbyberg.\n\nTillverkar rostfria kärl såsom kokkärl,\nbunkar, karotter, skopor m. m.\nVarumärke: »Svemab».\n\nTelefon: 284525 o. 281865. Postgiro:\n143886. — Akt.-kap.: 25,000 kr. Antal\nindustriarb.: 50. Tillv.-värde pr år:\n1,000,000 kr. — Bolaget grundat 1937.\nVerkst. dir.: Åke O. Lindblom.\n\nSvensk Pappersindustri, Järnfors &amp;\nHall AB., Sandared. .\n\nPappersförädlingsfabrik i Sandared\n(Älvsb. l.). Tillverkar papperstuber,\nspol-pipor, flänsrullar, skyddshylsor,\npappburkar samt formpressade artiklar såsom\ndockansikten, påskägg m. m.\n\nTelefon: Borås 55150. Postgiro: 170167.\n\n—\tAkt.-kap.: 50,000 kr. Antal\nindustriarb.: 60. Tillv.-värde pr år: 600,000 kr.\n\n—\tFirman etabl. 1935, bolag 1942.\nVerkst. dir.:, Sven Järnfors (Borås).\nDisp.: Albert Hall.\n\nDriftsing.: Gösta Järnfors.\n\n’Svensk Pälsskinnsberedning, J. F.\n\nLjungqvist, Tranås.\n\nBereder och färgar pälsskinn samt\ntillverkar dampälsar^ skinnhuvor, capes,\nskinnkragar och skinnpåsar.\n\nTelegr.-adr.: Pälsberedningen, Tranås.\nTelefon: 2134. Postgiro: 11664. — An-\n\n665*\n\ntal industriarb.: 50. — Firman etabl.\n1915.\n\nÄgare o. chef: fabr. J. F. Ljungqvist.\n\nKontorschef: Ragnar Ljungqvist.\n\n’AB. Svensk Rakklinga,\n\nSandviken.\n\nSe Swing Ltd. AB., Sandviken.\n\nAB. Svensk Skruv, Eskilstuna.\n\nTillverkar träskruv vid fabrik i Gnosjö\n(Jönköp. l.).\n\nKontor: Eskilstuna. Telefon: 30054.\nPostgiro: 13058.\n\nAkt.-kap.: 600,000 kr. Antal\nindustriarb.: 10. — Bolaget grundat 1943.\n\nStyrelse: fabr. David Bauréus, fru V.\nBauréus, disp. Eric Stålberg, dir. Gunnar\nStålberg.\n\nVerkst. dir.: Gunnar Stålberg.\n\nFörsäljn.-chef: kamrer Bernhard\nSöderström.\n\n*AB. Svensk Sprit, Stockholm.\n\nBolaget driver försäljning och\ndistribution av sulfitsprit.\n\nKontor: Wahrendorffsg. 6.\nTelegr.-adr.: Svensksprit, Stockholm. Telefon:\n232780. Postgiro: 1822. — Akt.-kap.:\n900.000 kr.\n\nBolaget grundat 1918 under namn\nFörsäljnings AB. Sulfitsprit, nuv. namn\n1922.\n\nStyrelse: dr Gunnar Sundblad (ordf.),\ndir. Gust. Göranson (v. ordf.), civiling.\nTore Bergström, dir. H. Dyster-Aas, dir.\nErik W. Eriksson, fil. dr Erik Kempe,\ndir. J. W. R. Lilliestråle, disp. Fabian\nLundquist, dir. Ragnar Sundfeldt.\n\nVerkst. dir.: Arthur Hellström.\n\n’Svensk Stålull AB., Stockholm.\n\nTillverkar stålull för industri,\nhantverk, lantbruk och hushåll vid fabrik i\nAneby (Jönköp. l.). Varumärke:\n»Kron-ull».\n\nKontor: Stockholm, Mäster Samuelsg.\n3. Telegr.-adr.: Kronull, Stockholm.\nTelefon: 202926 o. 202944. Postgiro: 191221.\n\nAkt.-kap.: 200,000 kr. Antal\nindustriarb.: 20. — Bolaget grundat 1941.\n\nStyrelse: kommerserådet S. Erik\nösterberg (ordf.), disp. Richard W. Gefeldt,\narkitekt Nils Malmborg, skeppsred. Ole\nSchröder.\n\nVerkst. dir.: Richard W. Gefeldt.\n\nFörsäljn.-chef: disp. Bernt Wahlström.",
    "structured": {
        "firms": [
            {
                "name": "Svensk Konsthartz industri, Gemla",
                "location": "Gemla",
                "business": "Tillverkar artiklar av pressat konstharts",
                "products": "såsom skruvlock, kapsyler, etuier, kulor, knappar m. m. samt specialdetaljer för olika industriändamål.",
                "contact": {
                    "phone": [
                        "Växjö 67127"
                    ],
                    "postgiro": "97280"
                },
                "financials": {
                    "capital": "The capital of the firm.",
                    "employees": {
                        "industriarb.": 50
                    },
                    "annual_turnover": "350,000 kr",
                    "annual_production_value": "350,000 kr"
                },
                "foundation_year": 1935,
                "owner": "fabr. Hugo Helmert",
                "director": "Hans Wiillrich"
            },
            {
                "name": "AB. Svensk Läderkonst, Sollebrunn",
                "location": "Sollebrunn",
                "business": "Möbelfabrik",
                "products": "i skinn och tyg. Specialitet: Skinnmöbler",
                "contact": {
                    "phone": [
                        "54",
                        "74"
                    ],
                    "postgiro": "83151"
                },
                "financials": {
                    "capital": "35,000 kr",
                    "employees": {
                        "industriarb.": 60
                    },
                    "annual_turnover": "500,000 kr",
                    "annual_production_value": "500,000 kr"
                },
                "foundation_year": 1932,
                "directors": [
                    "Erik Danielson",
                    "Karl Eriksson"
                ]
            },
            {
                "name": "Svensk Metallförädfing AB., Sundbyberg",
                "location": "Sundbyberg",
                "business": "Tillverkar rostfria kärl",
                "products": "såsom kokkärl, bunkar, karotter, skopor m. m. Varumärke: »Svemab».",
                "contact": {
                    "phone": [
                        "284525",
                        "281865"
                    ],
                    "postgiro": "143886"
                },
                "financials": {
                    "capital": "25,000 kr",
                    "employees": {
                        "industriarb.": 50
                    },
                    "annual_turnover": "1,000,000 kr",
                    "annual_production_value": "1,000,000 kr"
                },
                "foundation_year": 1937,
                "director": "Åke O. Lindblom"
            },
            {
                "name": "Svensk Pappersindustri, Järnfors & Hall AB., Sandared",
                "location": "Sandared",
                "business": "Pappersförädlingsfabrik",
                "products": "i Sandared (Älvsb. l.). Tillverkar papperstuber, spol-pipor, flänsrullar, skyddshylsor, pappburkar samt formpressade artiklar såsom dockansikten, påskägg m. m.",
                "contact": {
                    "phone": [
                        "Borås 55150"
                    ],
                    "postgiro": "170167"
                },
                "financials": {
                    "capital": "50,000 kr",
                    "employees": {
                        "industriarb.": 60
                    },
                    "annual_turnover": "600,000 kr",
                    "annual_production_value": "600,000 kr"
                },
                "foundation_year": 1935,
                "corporation_year": 1942,
                "director": "Sven Järnfors (Borås)",
                "sales_manager": "Albert Hall",
                "manager": "Gösta Järnfors"
            },
            {
                "name": "Svensk Pälsskinnsberedning, J. F. Ljungqvist, Tranås",
                "location": "Tranås",
                "business": "Bereder och färgar pälsskinn",
                "products": "samt tillverkar dampälsar^ skinnhuvor, capes, skinnkragar och skinnpåsar.",
                "contact": {
                    "telegraph": "Pälsberedningen, Tranås",
                    "phone": [
                        "2134"
                    ],
                    "postgiro": "11664"
                },
                "employees": {
                    "industriarb.": 50
                },
                "foundation_year": 1915,
                "owner": "fabr. J. F. Ljungqvist",
                "manager": "Ragnar Ljungqvist"
            },
            {
                "name": "AB. Svensk Skruv, Eskilstuna",
                "location": "Gnosjö (Jönköp. l.)",
                "business": "Tillverkar träskruv vid fabrik",
                "contact": {
                    "phone": [
                        "Eskilstuna 30054"
                    ],
                    "postgiro": "13058"
                },
                "financials": {
                    "capital": "600,000 kr",
                    "employees": {
                        "industriarb.": 10
                    },
                    "corporation_year": 1943
                },
                "board": [
                    {
                        "name": "fabr. David Bauréus",
                        "role": null
                    },
                    {
                        "name": "fru V. Bauréus",
                        "role": null
                    },
                    {
                        "name": "disp. Eric Stålberg",
                        "role": null
                    },
                    {
                        "name": "dir. Gunnar Stålberg",
                        "role": null
                    }
                ],
                "director": "Gunnar Stålberg",
                "sales_manager": "kamrer Bernhard Söderström"
            },
            {
                "name": "AB. Svensk Sprit, Stockholm",
                "location": "Wahrendorffsg. 6",
                "business": "Bolaget driver försäljning och distribution av sulfitsprit.",
                "contact": {
                    "telegraph": "Svensksprit, Stockholm",
                    "phone": [
                        "232780"
                    ],
                    "postgiro": "1822"
                },
                "financials": {
                    "capital": "900,000 kr"
                },
                "corporation_year": 1918,
                "current_name_year": 1922,
                "board": [
                    {
                        "name": "dr Gunnar Sundblad",
                        "role": "ordf."
                    },
                    {
                        "name": "dir. Gust. Göranson",
                        "role": "v. ordf."
                    },
                    {
                        "name": "civiling. Tore Bergström",
                        "role": null
                    },
                    {
                        "name": "dir. H. Dyster-Aas",
                        "role": null
                    },
                    {
                        "name": "dir. Erik W. Eriksson",
                        "role": null
                    },
                    {
                        "name": "fil. dr Erik Kempe",
                        "role": null
                    },
                    {
                        "name": "dir. J. W. R. Lilliestråle",
                        "role": null
                    },
                    {
                        "name": "disp. Fabian Lundquist",
                        "role": null
                    }
                ],
                "director": "Arthur Hellström"
            },
            {
                "name": "Svensk Stålull AB., Stockholm",
                "location": "Aneby (Jönköp. l.)",
                "business": "Tillverkar stålull för industri, hantverk, lantbruk och hushåll",
                "products": "Varumärke: »Kron-ull».",
                "contact": {
                    "phone": [
                        "Stockholm 202926",
                        "202944"
                    ],
                    "postgiro": "191221"
                },
                "financials": {
                    "capital": "200,000 kr",
                    "employees": {
                        "industriarb.": 20
                    },
                    "corporation_year": 1941
                },
                "board": [
                    {
                        "name": "kommerserådet S. Erik österberg",
                        "role": "ordf."
                    },
                    {
                        "name": "disp. Richard W. Gefeldt",
                        "role": null
                    },
                    {
                        "name": "arkitekt Nils Malmborg",
                        "role": null
                    },
                    {
                        "name": "skeppsred. Ole Schröder",
                        "role": null
                    }
                ],
                "director": "Richard W. Gefeldt",
                "sales_manager": "disp. Bernt Wahlström"
            }
        ]
    }
}