{
    "original": "Svartvik—Svea\n\nbankdir. P. F. Wåhlin.\n\nVerkst. dir.: Gust. Göranson.\n\nDriftsing.: I. Eidem.\n\nSågverks för v alt.: Erik Söderlund.\n\nAB. Svartviks Glycos, Alingsås.\n\nGlykosfabrik. Tillverkar glykos,\nflytande druvsocker och invertsocker.\n\nTelefon: 878. Postgiro: 265895. —\nAkt.-kap.: 100,000 kr. Antal industriarb.: 5.\n— Bolaget grundat 1909.\n\nVerkst. dir.: Clarence Brockman.\n\nFabrikschef: Josef Ebel.\n\nAB. Svartviks Grufvor,\n\nSilverhöjden.\n\nJärnmalmsgruvor vid Svartvik,\nStälldalen m. fl. platser i Örebro och\nKopparbergs län samt elektrisk kraftstation.\nGruvbrytningen f. n. nedlagd.\n\nDisponentkontor: Stockholm,\nVirvel-vindsv. 52, Höglandstorget. Telefon:\nStockholm 254097. Gruvkontor:\nSilverhöjden. Telefon: Hörken 50 o. 51.\n\nAkt.-kap.: 150,000 kr. — Firman\netablerad på 1840-talet, bolaget grundat 1887.\n\nStyrelse: disp. Fredrik Cassel (ordf.),\ndisp. Axel L:son Alarik, dir. Erik G.\nPehrsson.\n\nVerkst. dir.: Axel L:son Alarik (Sthlm).\n\nGruving.: Rolf Erikson (Silverhöjden).\n\n*d. G. Swartz, Norrköping.\n\nSe Kvarn AB. J. G. S., Norrköping.\n\n*Svartå Järnbruk, Svarta.\n\nSe Hasselfors Bruks AB., Hasselfors.\n\n\"Svea Armaturfabrik, Kungsör.\n\nSe AB. Armaturfabriken Svea, Kungsör.\n\nSvea Band &amp; Pappers AB.,\n\nLinköping.\n\nTillverkar reklamband, etiketter och\nmärklappar.\n\nTelefon: 25620. Postgiro: 15171. —\nAkt.-kap.: 60,000 kr. Antal industriarb.:\n35. Tillv.-värde pr år: 630,000 kr. —\nFirman etabl. 1919, bolag 1926.\n\nVerkst. dir.: Kurt Bendt.\n\n*AB. Sveabryggerier, Filipstad.\n\nBryggerier i Filipstad, Åmål (Åmåls\nNya Bryggeri AB.), Säffle, Borlänge\n(Wasabryggeriet), Ludvika, Amnerud\n(Vestby Bryggeri), Nore och Vansbro.\n\nTillverkar malt och maltdrycker,\nkolsy-rade mineralvatten och läskedrycker.\n\nTelegr.-adr. o. telefon: »Svea»,\nFilip-stad. Postgiro: 8509. — Akt.-kap.:\n2,472,000 kr. Antal industriarb.: 123.\n\nBolaget grundades 1897 under namn\nÅngbryggeri AB. Svea, namnförändring\n1931. Bolaget är intressent i AB. Falu\nÅngbryggeri, AB. Wermlandsbryggerier,\nKarlstad, Kristinehamns Bryggeri AB.,.\nBryggeri AB. Fryksdalen, Torsby och\nSunne, samt Mora Bryggeri AB., Mora,\nMalung, Rättvik och Leksand.\n\nStyrelse: disp. Nils G. Arvedson\n(ordf.), borgm. Stig Allsing, disp.\nRichard Arvedson, dir. A. Backlund,,\ndisp. Sven Jansson, disp. John Löfgren,»\ndisp. C. Gunnar Nilsson.\n\nVerkst. dir. o. disp.: John Löfgren.\n\nBryggmäst.: Åke Walden.\n\n\"AB. Svea Choklad, Norrköping.\n\nChoklad-, kakao- och konfityrfabrik.\nTillverkar choklad, kakao, dragéer,\nkarameller, kola, konfekt, lakrits, marmelad*\npastiller, tabletter, tuggummi,\nvanillin-socker m. m. Varumärken: »Svea» o.\n»Jockey».\n\nTelegr.-adr.: Svea, Norrköping.\nTelefon: 20253, 20451 o. 23170. Postgiro:\n28260\n\nAkt-kap.: 1,200,000 kr. Antal\nindustriarb. : 100. — Fabriken anlagd 1887.\n\nStyrelse: f. kapten B. Billsten (ordf.)*\nprof. Gösta Eberstein, fil. dr Hj.\nLundgren.\n\nDisp.: B. Billsten.\n\nSvea, Emaljskyltfabriken, Fritsla.\n\nSe Emaljskyltfabriken Svea, Fritsla.\n\n*Svea Manufakturbolag, Borås.\n\nSe Kilsunds AB., Borås.\n\n\"Svea Margarinfabrik, Kalmar.\n\nSe Margarin AB. Svea, Kalmar.\n\n\"Svea, Möbelfabriken, Eric\nTonebrand, Sävsjö.\n\nSe Möbelfabriken Svea, Eric\nTonebrand, Sävsjö.\n\n\"Svea Oljefabrik, Kalmar.\n\nSe Margarin AB. Svea, Kalmar.\n\n\"Svea, Skofabriken, Örebro.\n\nSe AB. Örebro Skofabrik, Örebro,",
    "structured": {
        "firms": [
            {
                "name": "AB. Svartviks Glycos, Alingsås",
                "location": "Alingsås",
                "business": "Glykosfabrik",
                "products": "Tillverkar glykos, flytande druvsocker och invertsocker",
                "contact": {
                    "phone": [
                        "878"
                    ],
                    "postgiro": "265895"
                },
                "financials": {
                    "capital": "100,000 kr",
                    "employees": {
                        "industriarb": 5
                    }
                },
                "foundation_year": 1909
            },
            {
                "name": "AB. Svartviks Grufvor, Silverhöjden",
                "location": "Silverhöjden",
                "business": "Järnmalmsgruvor",
                "description": "Järnmalmsgruvor vid Svartvik, Ställdalen m.fl. platser i Örebro och Kopparbergs län samt elektrisk kraftstation",
                "contact": {
                    "factory_phone": "Hörken 50 o. 51"
                },
                "financials": {
                    "capital": "150,000 kr"
                },
                "foundation_year": 1887
            },
            {
                "name": "Svea Band & Pappers AB., Linköping",
                "location": "Linköping",
                "business": "Tillverkar reklamband, etiketter och märklappar",
                "products": "Tillverkar reklamband, etiketter och märklappar",
                "contact": {
                    "phone": [
                        "25620"
                    ],
                    "postgiro": "15171"
                },
                "financials": {
                    "capital": "60,000 kr",
                    "employees": {
                        "industriarb": 35
                    },
                    "annual_production_value": "630,000 kr"
                },
                "foundation_year": 1926
            },
            {
                "name": "AB. Sveabryggerier, Filipstad",
                "location": "Filipstad",
                "business": "Bryggerier",
                "products": "Tillverkar malt och maltdrycker, kolsyrade mineralvatten och läskedrycker",
                "contact": {
                    "telegraph": "Svea",
                    "phone": [
                        "Filipstad"
                    ],
                    "postgiro": "8509"
                },
                "financials": {
                    "capital": "2,472,000 kr",
                    "employees": {
                        "industriarb": 123
                    }
                },
                "foundation_year": 1897
            },
            {
                "name": "AB. Svea Choklad, Norrköping",
                "location": "Norrköping",
                "business": "Choklad-, kakao- och konfityrfabrik",
                "products": "Tillverkar choklad, kakao, dragéer, karameller, kola, konfekt, lakrits, marmelad, pastiller, tabletter, tuggummi, vanillin-socker m.m.",
                "contact": {
                    "telegraph": "Svea",
                    "phone": [
                        "20253",
                        "20451",
                        "23170"
                    ],
                    "postgiro": "28260"
                },
                "financials": {
                    "capital": "1,200,000 kr",
                    "employees": {
                        "industriarb": 100
                    }
                },
                "foundation_year": 1887
            }
        ]
    }
}