{
    "original": "Stå l—Stä f v e sj ö\n\nmjöl och korngryn, fodermjöl, gröpe och\nkli samt kraftfoderblandningar. Bolaget\ndriver jämväl försäljning av artificiella\ngödningsämnen, hönsfoder m. m.\n\nHuvudkontor: Norrköping.\nTelegr.-adr.: Ståhlboms, Norrköping. Telefon:\n20007, 20028 o. 21446. Postgiro: 10281.\nAvd.-kontor: Mjölby. Telegr.-adr.:\nStåhlboms, Mjölby. Telefon: 190. Postgiro:\n9072.\n\nAkt.-kap.: 360,000 kr. Antal\nindustriarb.: 24. Prod.-värde pr år: 3,500,000 kr.\n\n—\tFirman etabl. 1863.\n\nStyrelse: dir. Fredrik Törnqvist, disp.\nOust. Törnqvist, fröken Märta Törnqvist.\n\nVerkst. direktörer: Gust. Törnqvist o.\nFredrik Törnqvist.\n\n*Stål &amp; Maskin AB., Uppsala.\n\nElektr. smältverk, hej ar smed ja,\nplåtslageri och mek. verkstad. Tillverkar\nelektro-tackjärn, värmebeständigt gjutgods,\nhejar-verktyg och hejarsmide upp till 20 kg\nstyckevikt samt plåtarbeten.\n\nTelegr.-adr.: Stålverket, Uppsala.\nTelefon: 32632 o. 32266. Postgiro: 5261. —\nAkt.-kap.: 300,000 kr. Antal industriarb.:\n45. — Bolaget grundat 1917.\n\nStyrelse: ing. Matts Vigborg (ordf.),\ndocent Erik Karlmark, adv. Nils\nMossberg.\n\nVerkst. dir.: Matts Vigborg.\n\nKamrer: Gunnar Wahman.\n\n*AB. Stålfjädrar, Stockholm.\n\nTillverkar spiral-, platt-, fason- och\nvridfjädrar i olika material, böjliga axlar,\nfjäderbrickor samt sängbottenkedjor.\n\nKontor: Gävleg. 12 B. Telefon: 332234,\n33-2236 o. 332205. Postgiro: 58880.\n\nAkt.-kap.: 85,200 kr. Antal\nindustriarb.: 60. Tillv.-värde pr år: 1,000,000 kr.\n\n—\tFirman etabl. 1934, bolag 1936.\n\nStyrelse: dir, Håkan Dahlerus (ordf.),\n\nadv. A. Boström, ing. Herman Kagan,\ndir. A. Savabini.\n\nVerkst. dir.: H. Kagan.\n\n*Sfålpressningsbolaget,\n\nOlof ström.\n\nSe Svenska Stålpressnings AB.\nOlofström, Olofström.\n\n*Stålstämpelfabriken, A. Edv. Olson,\n\nEskilstuna.\n\nTillverkar stålstämplar,\npräglingsstansar, pressverktyg, mätdon, formar för\nporslins-, gummi- och bakelitindustrien,\nstålstämpeltyper, nummerstämplingsverk,\n\nalfabet- och siffersatser, beslag, pressade\n\noch präglade massartiklar av stål, järn\noch metall samt slitsade rakbladsämnen.\n\nTelegr.-adr.: Stämpelfabriken,\nEskilstuna. Telefon: 30550 o. 30654. Postgiro:\n5378.\n\nAntal industriarb.: 20. Tillv.-värde pr\når: 250,000 kr.\n\nFirman etabl. 1907.\n\nÄgare o. chef: ing. A. Edv. Olson.\n\n*AB. Stålsvets, Tureberg.\n\nMek. verkstad och svetsningsverkstad\ni Tureberg (Sthlms l.). Tillverkar\napparater för cellulosa- och kem. industri,\nplåtsaxar samt ljuddämpare för bilar.\nSpecialitet: syrafasta arbeten.\n\nTelefon: Stockholm 352344—45.\nPostgiro: 155610. — Akt.-kap.: 95,000 kr.\nAntal industriarb.: 30. Tillv.-värde pr\når: 750,000 kr. — Firman etabl. 1938,\nbolag 1940.\n\nStyrelse: ing. Olof V. Cardell (ordf.),\ning. Olof Cardell, ing. Torsten Rarnén.\n\nVerkst. dir.: Olof Cardell.\n\nKamrer: Oscar Lagerstedt.\n\n\"Stålull AB., Svensk, Stockholm.\n\nSe Svensk Stålull AB., Stockholm.\n\n*AB. Ståluilfabriken, Stockholm.\n\nTillverkar stålull. Varumärke:\n»Stjärnull».\n\nKontor: Braheg. 28. Telefon: 618900.\nPostgiro: 192329. — Akt.-kap.: 25,000 kr.\nTillv.-värde pr år: 200,000 kr. —\nBolaget grundat 1941.\n\nStyrelse: dir. Axel Ljungqvist (ordf.),\nkamrer Karin Lindberg, dir. Sven\nWahlström.\n\nVerkst. dir.; S.-E. Engdahl.\n\nAB. Stångebro Möbelfabrik,\n\nLinköping.\n\nMöbelfabriker i Linköping och i\nFjugesta (Örebro l.). Tillverkar\nbäddmöbel-stommar.\n\nKontor: Linköping. Telefon: 23722.\nPostgiro: 160242. - Akt.-kap.: 12,000kr.\nTillv.-värde pr år: 425,000 kr. — Bolaget\ngrundat 1938.\n\nFabrikschefer: i Linköping: verkm.\nIvan Druidh; i Fjugesta: disp. D. E.\nGylling.\n\nStäfvesjö Tegelbruks AB.,\n\nAnderslöv.\n\nTillverkar fasadtegel, mur- och\ntaktegel, brunnstegel samt dräneringsrör vid\n\ntegelbruk i Stävesjö (Malmöh. l.).\n\n1’9*",
    "structured": {
        "1": {
            "name": "Ståhlboms",
            "location": "Norrköping",
            "business": "mjöl och korngryn, fodermjöl, gröpe och kli samt kraftfoderblandningar. Bolaget driver jämväl försäljning av artificiella gödningsämnen, hönsfoder m. m.",
            "contact": {
                "office": "Norrköping",
                "phone": [
                    "20007",
                    "20028",
                    "21446"
                ],
                "postgiro": "10281",
                "head_office": "Norrköping",
                "sales_offices": [
                    {
                        "location": "Mjölby",
                        "phone": "190"
                    }
                ],
                "telegraph": "Ståhlboms, Norrköping",
                "factory_office": "",
                "factory_phone": ""
            },
            "financials": {
                "capital": "360,000 kr",
                "employees": {
                    "industriarb": 24
                },
                "annual_turnover": "3,500,000 kr",
                "annual_production_value": "3,500,000 kr"
            },
            "foundation_year": 1863,
            "board": [
                {
                    "name": "Fredrik Törnqvist",
                    "role": "dir."
                },
                {
                    "name": "Oust. Törnqvist",
                    "role": "disp."
                },
                {
                    "name": "fröken Märta Törnqvist",
                    "role": ""
                }
            ],
            "owners": [],
            "director": "",
            "managing_director": "Gust. Törnqvist, Fredrik Törnqvist",
            "sales_manager": "",
            "manager": ""
        },
        "2": {
            "name": "Stål & Maskin AB.",
            "location": "Uppsala",
            "business": "Elektr. smältverk, hej ar smed ja, plåtslageri och mek. verkstad. Tillverkar elektro-tackjärn, värmebeständigt gjutgods, hejar-verktyg och hejarsmide upp till 20 kg styckevikt samt plåtarbeten.",
            "contact": {
                "office": "",
                "phone": [
                    "32632",
                    "32266"
                ],
                "postgiro": "5261",
                "head_office": "",
                "sales_offices": [],
                "telegraph": "Stålverket, Uppsala",
                "factory_office": "",
                "factory_phone": ""
            },
            "financials": {
                "capital": "300,000 kr",
                "employees": {
                    "industriarb": 45
                },
                "annual_turnover": "",
                "annual_production_value": ""
            },
            "foundation_year": 1917,
            "board": [
                {
                    "name": "Matts Vigborg",
                    "role": "ing. (ordf.)"
                },
                {
                    "name": "Erik Karlmark",
                    "role": "docent"
                },
                {
                    "name": "Nils Mossberg",
                    "role": "adv."
                }
            ],
            "owners": [],
            "director": "",
            "managing_director": "Matts Vigborg",
            "sales_manager": "",
            "manager": ""
        },
        "3": {
            "name": "AB. Stålfjädrar",
            "location": "Stockholm",
            "business": "Tillverkar spiral-, platt-, fason-och vridfjädrar i olika material, böjliga axlar, fjäderbrickor samt sängbottenkedjor.",
            "contact": {
                "office": "Gävleg. 12 B",
                "phone": [
                    "332234",
                    "33-2236",
                    "332205"
                ],
                "postgiro": "58880",
                "head_office": "",
                "sales_offices": [],
                "telegraph": "",
                "factory_office": "",
                "factory_phone": ""
            },
            "financials": {
                "capital": "85,200 kr",
                "employees": {
                    "industriarb": 60
                },
                "annual_turnover": "1,000,000 kr",
                "annual_production_value": "1,000,000 kr"
            },
            "foundation_year": 1934,
            "board": [
                {
                    "name": "Håkan Dahlerus",
                    "role": "dir."
                },
                {
                    "name": "A. Boström",
                    "role": "adv."
                },
                {
                    "name": "Herman Kagan",
                    "role": "ing."
                },
                {
                    "name": "A. Savabini",
                    "role": "dir."
                }
            ],
            "owners": [],
            "director": "",
            "managing_director": "H. Kagan",
            "sales_manager": "",
            "manager": ""
        },
        "4": {
            "name": "Stålpressningsbolaget",
            "location": "Olofström",
            "business": "Se Svenska Stålpressnings AB.",
            "contact": {
                "office": "",
                "phone": [],
                "postgiro": "",
                "head_office": "",
                "sales_offices": [],
                "telegraph": "",
                "factory_office": "",
                "factory_phone": ""
            },
            "financials": {},
            "foundation_year": 0,
            "board": [],
            "owners": [],
            "director": "",
            "managing_director": "",
            "sales_manager": "",
            "manager": ""
        },
        "5": {
            "name": "Stålstämpelfabriken",
            "location": "Eskilstuna",
            "business": "Tillverkar stålstämplar, präglingsstansar, pressverktyg, mätdon, formar för porslins-, gummi- och bakelitindustrien, stålstämpeltyper, nummerstämplingsverk, alfabet- och siffersatser, beslag, pressade och präglade massartiklar av stål, järn och metall samt slitsade rakbladsämnen.",
            "contact": {
                "office": "Eskilstuna",
                "phone": [
                    "30550",
                    "30654"
                ],
                "postgiro": "5378",
                "head_office": "",
                "sales_offices": [],
                "telegraph": "Stämpelfabriken, Eskilstuna",
                "factory_office": "",
                "factory_phone": ""
            },
            "financials": {},
            "foundation_year": 1907,
            "board": [],
            "owners": [
                "ing. A. Edv. Olson"
            ],
            "director": "",
            "managing_director": "",
            "sales_manager": "",
            "manager": "ing. A. Edv. Olson"
        },
        "6": {
            "name": "AB. Ståls vets",
            "location": "Tureberg",
            "business": "Mek. verkstad och svetsningsverkstad i Tureberg (Sthlms l.). Tillverkar apparater för cellulosa- och kem. industri, plåtsaxar samt ljuddämpare för bilar. Specialitet: syrafasta arbeten.",
            "contact": {
                "office": "",
                "phone": [
                    "352344-45"
                ],
                "postgiro": "155610",
                "head_office": "",
                "sales_offices": [],
                "telegraph": "",
                "factory_office": "",
                "factory_phone": ""
            },
            "financials": {
                "capital": "95,000 kr",
                "employees": {
                    "industriarb": 30
                },
                "annual_turnover": "750,000 kr",
                "annual_production_value": "750,000 kr"
            },
            "foundation_year": 1938,
            "board": [
                {
                    "name": "Olof V. Cardell",
                    "role": "ing. (ordf.)"
                },
                {
                    "name": "Olof Cardell",
                    "role": "ing."
                },
                {
                    "name": "Torsten Rarnén",
                    "role": "ing."
                }
            ],
            "owners": [],
            "director": "",
            "managing_director": "Olof Cardell",
            "sales_manager": "",
            "manager": ""
        },
        "7": {
            "name": "AB. Stålullfabriken",
            "location": "Stockholm",
            "business": "Tillverkar stålull. Varumärke: »Stjärnull».",
            "contact": {
                "office": "Braheg. 28",
                "phone": [
                    "618900"
                ],
                "postgiro": "192329",
                "head_office": "",
                "sales_offices": [],
                "telegraph": "",
                "factory_office": "",
                "factory_phone": ""
            },
            "financials": {
                "capital": "25,000 kr",
                "employees": {},
                "annual_turnover": "200,000 kr",
                "annual_production_value": "200,000 kr"
            },
            "foundation_year": 1941,
            "board": [
                {
                    "name": "Axel Ljungqvist",
                    "role": "dir."
                },
                {
                    "name": "Karin Lindberg",
                    "role": "kamrer"
                },
                {
                    "name": "Sven Wahlström",
                    "role": "dir."
                }
            ],
            "owners": [],
            "director": "",
            "managing_director": "S.-E. Engdahl",
            "sales_manager": "",
            "manager": ""
        },
        "8": {
            "name": "AB. Stångebro Möbelfabrik",
            "location": "Linköping",
            "business": "Möbelfabriker i Linköping och i Fjugesta (Örebro l.). Tillverkar bäddmöbel-stommar.",
            "contact": {
                "office": "Linköping",
                "phone": [
                    "23722"
                ],
                "postgiro": "160242",
                "head_office": "",
                "sales_offices": [],
                "telegraph": "",
                "factory_office": "",
                "factory_phone": ""
            },
            "financials": {
                "capital": "12,000kr",
                "employees": {},
                "annual_turnover": "425,000 kr",
                "annual_production_value": "425,000 kr"
            },
            "foundation_year": 1938,
            "board": [],
            "owners": [],
            "director": "",
            "managing_director": "verkm. Ivan Druidh",
            "sales_manager": "",
            "manager": "disp. D. E. Gylling"
        },
        "9": {
            "name": "Stäfvesjö Tegelbruks AB.",
            "location": "Anderslöv",
            "business": "Tillverkar fasadtegel, mur- och taktegel, brunnstegel samt dräneringsrör vid tegelbruk i Stävesjö (Malmöh. l.).",
            "contact": {
                "office": "",
                "phone": [],
                "postgiro": "",
                "head_office": "",
                "sales_offices": [],
                "telegraph": "",
                "factory_office": "",
                "factory_phone": ""
            },
            "financials": {},
            "foundation_year": 0,
            "board": [],
            "owners": [],
            "director": "",
            "managing_director": "",
            "sales_manager": "",
            "manager": ""
        }
    }
}