{
    "original": "Svensk—S venska\n\nAB. Svensk Torvförädling,\n\nSösdala.\n\nTillverkar torvbriketter vid fabrik i\nSösdala (Kristianst. l.).\n\nTelegr.-adr.: Kronbrikett, Sösdala.\nTelefon: Ljungarum 34, — Akt.-kap.:\n5,000,000 kr. Antal industriarb.: 100. —\nBolaget, grundat 1939, äges av Svenska\nStaten.\n\nStyrelse: f. d. hovrättsrådet Bernt\nLindskog (ordf.), f. d. byråchef Erik\nRendahl (v. ordf.), ombudsm. Ture Flyboo,\növerjägm. Erik Höjer, red. Albin Lind,\nprof. Lage Malm, sekr. Rudolf Meidner,\ndir. Olle Uddgren.\n\nVerkst. dir.: O. Uddgren.\n\n\"Svenska Ackumulator AB. Jungner,\n\nStockholm.\n\nFabriker i Stockholm, Oskarshamn och\nFliseryd (Kalmar l.). Tillverkar NIFE\nalkaliska ackumulatorer, signalapparater,\nstrålkastare, lyktor, kompletta\nbelysningsinstallationer för fiskebåtar,\nbog-serbåtar o. d., vind-elverk, förgasare,\nfilter, optiska instrument, linser och\nprismor, verktygsslipmaskiner samt aktivt\nkol; SAAJ blyackumulatorer för mobila\noch stationära ändamål, SAJO\ntorrbatterier samt SAL fartygsloggar.\n\nHuvudkontor: Stockholm, Riddarg. 17.\nTelegr.-adr.: Nife, Stockholm. Telefon:\n» Jungnerbolaget». Postgiro: 1547.\nUtställning: Stockholm, Birger Jarlsg. 15.\n\nFilialer o. laddningsstationer:\nStockholm, Riddarg. 17 o. Klarabergsg. 29;\nGöteborg, Malmö, Karlstad, Norrköping,\nSkellefteå o. Sundsvall.\n\nAkt.-kap.: 6,298,500 kr. Antal\nindustriarb.: 1,050. — Bolaget grundat 1910.\n\nStyrelse: generallöjtn. frih. Lars C:son\nSparre (ordf.), dir. Carl Ameln, civiling.\nRobert Ameln, civiling. Bengt Ingeström,\nciviling. Torsten Jung, civiling. F. G.\nLiljenroth.\n\nVerkst. dir.: Robert Ameln.\n\nFabrikschefer: i Oskarshamn: disp.\nGustaf Eriksson; i Fliseryd: ing. Carl\nTroilius; i Stockholm: ing. S.\nMalmström.\n\nFilial föreståndare: i Stockholm: H.\nBjörkander o. H. Hogstedt; i Göteborg:\ning. A. Westin; i Malmö: ing. V.\nJohnsson; i Karlstad: ing. S. Hjalmarson; i\nNorrköping: ing. S. Wennergård; i\nSkellefteå: S. Westrin; i Sundsvall: ing. G.\nNyländer.\n\n\"Svenska Aeroplan AB.,\n\nLinköping.\n\nMek. verkstäder i Linköping och\nTrollhättan. Tillverkar flygplan och\nflygplanstillbehör.\n\nHuvudkontor: Linköping. Telegr.-adr..\no. telefon: Saab, Linköping. Avd.-kontor:\nTrollhättan. Telefon: »Saab». Postgiron:\nLinköping: 160342; Trollhättan: 136599.\n\nAkt.-kap.: 21,000,000 kr. Antal\nindustriarb.: 2,500. — Bolaget grundat 1937.\n\nStyrelse: överståthållare Torsten\nNo-thin (ordf.), konsul Oscar Gullander, dir.\nGust. J. Sahlin, dir. Ragnar Wahrgren,.\nbankdir. Marcus Wallenberg, disp. Evert\nWijkander.\n\nVerkst. dir.: Ragnar Wahrgren.\n\nV. verkst. dir.: Sven Otterbeck.\n\növeringenjörer: Elis Nordquist, Hugo\nBertler o. Erik Rydberg.\n\nKamrer: John Nygren.\n\n\"Svenska Aloxidverken AB.,\n\nStockholm.\n\nTillverkar aluminiumoxid och\naluminium vid elektrokemisk fabrik i\nKubikenborg, Skönsmon.\n\nHuvudkontor: Stockholm, Kungsg. 28.\nTelegr.-adr.: Oxidverken, Stockholm.\nTelefon: 230920. Postgiro: 194558.\nFabrikskontor: Kubikenborg, Skönsmon. Tele*\nfon: Sundsvall 55670.\n\nAkt.-kap.: 3,000,000 kr. Antal\nindustriarb.: 150. — Bolaget, grundat 1941, är\nanslutet till AB. Svenska\nAluminiumkompaniet, Stockholm.\n\nStyrelse: kommerserådet Axel F.\nEn-ström (ordf.), höiesteretsadv. Herman\nChristiansen, konteramiral Helge Friis,.\ning. Plans J. Krogh, kommerserådet S.\nErik Österberg.\n\nVerkst. dir.: Herman Lund.\n\nPlatschef: i Kubikenborg: övering. M.\nHafstad.\n\n\"AB. Svenska Aluminiumkompaniet,\n\nStockholm.\n\nAluminiumfabrik i Månsbo, Avesta\n(Kopparb. l.). Tillverkar aluminium och\naluminiumlegeringar i tackor, valsämnen,\ntråd- och rörämnen m. m. Varumärke:\n»SAKO».\n\nFörsäljnings- och huvudkontor:\nStockholm, Kungsg. 28. Telegr.-adr.:\nSvealu-min, Stockholm och Avesta. Telefon:\n230920.o Postgiro: 150606.\nFabrikskontor: Månsbo; postadr.: Avesta. Telefon:\nKrylbo 5555.\n\nAkt.-kap.: 3,500,000 kr. Antal\nindustriarb.: 95. Tillv.-värde pr år: 3,000.000 kr.\n— Bolaget grundat 1934.",
    "structured": {
        "1": {
            "name": "AB Svensk Torvförädling",
            "location": "Sösdala",
            "business": "Tillverkar torvbriketter vid fabrik i Sösdala (Kristianst. l.)",
            "contact": {
                "telegraph": "Kronbrikett, Sösdala",
                "phone": [
                    "Ljungarum 34"
                ],
                "factory_office": "Address of factory office"
            },
            "financials": {
                "capital": "5,000,000 kr",
                "employees": {
                    "industriarb": 100
                },
                "foundation_year": 1939
            },
            "board": [
                {
                    "name": "Bernt Lindskog",
                    "role": "ordf."
                },
                {
                    "name": "Erik Rendahl",
                    "role": "v. ordf."
                },
                {
                    "name": "Ture Flyboo",
                    "role": "ombudsm."
                },
                {
                    "name": "Erik Höjer",
                    "role": "överjägm."
                },
                {
                    "name": "Albin Lind",
                    "role": "red."
                },
                {
                    "name": "Lage Malm",
                    "role": "prof."
                },
                {
                    "name": "Rudolf Meidner",
                    "role": "sekr."
                },
                {
                    "name": "Olle Uddgren",
                    "role": "dir."
                }
            ],
            "owners": [
                "Svenska Staten"
            ],
            "director": "O. Uddgren"
        },
        "2": {
            "name": "Svenska Ackumulator AB. Jungner",
            "location": "Stockholm",
            "business": "Tillverkar NIFE alkaliska ackumulatorer, signalapparater, strålkastare, lyktor, kompletta belysningsinstallationer för fiskebåtar, bog-serbåtar o. d., vind-elverk, förgasare, filter, optiska instrument, linser och prismor, verktygsslipmaskiner samt aktivt kol; SAAJ blyackumulatorer för mobila och stationära ändamål, SAJO torrbatterier samt SAL fartygsloggar",
            "contact": {
                "telegraph": "Nife, Stockholm",
                "phone": [
                    "» Jungnerbolaget»"
                ],
                "postgiro": "1547",
                "head_office": "Stockholm, Riddarg. 17"
            },
            "financials": {
                "capital": "6,298,500 kr",
                "employees": {
                    "industriarb": 1050
                },
                "foundation_year": 1910
            },
            "board": [
                {
                    "name": "Lars C:son Sparre",
                    "role": "ordf."
                },
                {
                    "name": "Carl Ameln",
                    "role": "dir."
                },
                {
                    "name": "Robert Ameln",
                    "role": "civiling."
                },
                {
                    "name": "Bengt Ingeström",
                    "role": "civiling."
                },
                {
                    "name": "Torsten Jung",
                    "role": "civiling."
                },
                {
                    "name": "F. G. Liljenroth",
                    "role": "civiling."
                }
            ],
            "director": "Robert Ameln"
        },
        "3": {
            "name": "Svenska Aeroplan AB.",
            "location": "Linköping",
            "business": "Tillverkar flygplan och flygplanstillbehör",
            "contact": {
                "telegraph": "Saab, Linköping",
                "phone": [
                    "Saab"
                ],
                "postgiro": {
                    "Linköping": "160342",
                    "Trollhättan": "136599"
                },
                "head_office": "Linköping"
            },
            "financials": {
                "capital": "21,000,000 kr",
                "employees": {
                    "industriarb": 2500
                },
                "foundation_year": 1937
            },
            "board": [
                {
                    "name": "Torsten Nothin",
                    "role": "ordf."
                },
                {
                    "name": "Oscar Gullander",
                    "role": "konsul"
                },
                {
                    "name": "Gust. J. Sahlin",
                    "role": "dir."
                },
                {
                    "name": "Ragnar Wahrgren",
                    "role": "dir."
                },
                {
                    "name": "Marcus Wallenberg",
                    "role": "bankdir."
                },
                {
                    "name": "Evert Wijkander",
                    "role": "disp."
                }
            ],
            "director": "Ragnar Wahrgren"
        },
        "4": {
            "name": "Svenska Aloxidverken AB.",
            "location": "Stockholm",
            "business": "Tillverkar aluminiumoxid och aluminium vid elektrokemisk fabrik i Kubikenborg, Skönsmon",
            "contact": {
                "telegraph": "Oxidverken, Stockholm",
                "phone": [
                    "230920"
                ],
                "postgiro": "194558",
                "head_office": "Stockholm, Kungsg. 28"
            },
            "financials": {
                "capital": "3,000,000 kr",
                "employees": {
                    "industriarb": 150
                },
                "foundation_year": 1941
            },
            "board": [
                {
                    "name": "Axel F. Enström",
                    "role": "kommerserådet"
                },
                {
                    "name": "Herman Christiansen",
                    "role": "höiesteretsadv."
                },
                {
                    "name": "Helge Friis",
                    "role": "konteramiral"
                },
                {
                    "name": "Plans J. Krogh",
                    "role": "ing."
                },
                {
                    "name": "S. Erik Österberg",
                    "role": "kommerserådet"
                }
            ],
            "director": "Herman Lund"
        },
        "5": {
            "name": "AB. Svenska Aluminiumkompaniet",
            "location": "Stockholm",
            "business": "Tillverkar aluminium och aluminiumlegeringar i tackor, valsämnen, tråd- och rörämnen m. m.",
            "contact": {
                "telegraph": "Svealu-min, Stockholm and Avesta",
                "phone": [
                    "230920"
                ],
                "postgiro": "150606",
                "head_office": "Stockholm, Kungsg. 28",
                "factory_office": "Månsbo, Avesta"
            },
            "financials": {
                "capital": "3,500,000 kr",
                "employees": {
                    "industriarb": 95
                },
                "annual_production_value": "3,000,000 kr",
                "foundation_year": 1934
            },
            "board": [],
            "director": ""
        }
    }
}