{
    "original": "S urte—S välling\n\ntackjärnsgjutgods, bromsblock, ringar för\nlokomotiv- och järnvägsvagnshjul,\nhjulsatser för järnvägs- och spårvagnar\nävensom trallvagnshjul samt pressad plåt\nsåsom ångpannebottnar och separatorkulor.\n\nHuvudkontor: Surahammar. Postgiro:\n13271. Hyttans # kontor: Kärrgruvan.\nEgendomsförvaltningens kontor:\nSurahammar.\n\nAkt.-kap.: 500,000 kr. Antal\nindustriarb.: 1,900. Tillv.-värde pr år: 30,000,000\nkr.\n\nBolaget, som grundades 1872, driver\nsedan 1918 såväl järnbruks-,\njordbruks-och skogsbruks- som sågverksrörelsen i\nkommission för Allmänna Svenska\nElektriska AB. i Västerås, som äger brukets\nsamtliga tillgångar.\n\nStyrelse: dir. J. S. Edström (ordf.),\ndir. Thorsten Ericson, disp. Helge\nSilverstolpe, disp. Claes Wahlund.\n\nDisp. o. verkst. dir.: Helge Silverstolpe.\n\nChefer: för järnverket: övering. Y.\nTörneman; för järnförsäljn.: intendent\nGustaf Johansson; för ekonomiavd.:\nkamrer Fritz Andersson; för hyttor o.\ngruvor: ing. Gustaf Wrangenberg; för\negendomsförvaltn.: jägm. Rickard\nAlexanderson.\n\n*AB. Surte Glasbruk, Surte.\n\nGlasbruk i Surte (Älvsb. l.) och\nKungälv (Göteb. o. Bohus l.). Tillverkar\nbuteljer, flaskor och burkar.\n\nHuvudkontor: Surte. Telegr.-adr.:\nSurte, Göteborg. Telefon: Göteborg\n174000 o. Surte 14 o. 125. Postgiro:\n77074. Ensamförsälj. för Sverige:\nButeljglasbrukens Försäljnings AB., Stockholm,\nBirger Jarlsg. 2. Telefon: 619920 o.\n619921.\n\nAkt.-kap.: 3,500,000 kr. Antal\nindustriarb.: 700. Tillv.-värde pr år: 12,000,000\nkr.\n\nFirman, etabl. 1862, bolag 1906, äger\nKongelfs Glasbruks AB.\n\nStyrelse: frih. C.-G. Langenskiöld\n(ordf.), löjtn. Oscar Ekman, dir. Per\nHemberg, dir. H. W. Söderman, dir. Ivar\nThrondsen.\n\nVerkst. dir.: Per Hemberg.\n\n*AB. Svagdricksbryggeriet Sundsvall,\n\nSundsvall.\n\nTillverkar svagdricka.\n\nTelefon: 4422. Postgiro: 31110. —\nAkt.-kap.: 100,000 kr. Arb.-antal: 6.\nTillv.-värde pr år: 95,000 kr. — Bolaget\ngrundat 1928.\n\nStyrelse:\tdir. L. Valentin (ordf.),\n\nbryggm. K.\tJohan Nilsson, disp. Bengt\nNygren.\n\nDisp.: K.\tJohan Nilsson.\n\nC. H. Swahn Cjuteri &amp; Mek.\nVerkstad AB., Borlänge.\n\nGjuteri och mek. verkstad i Borlänge\n(Kopparb. l.).\n\nTillverkar elektr. motorpumpar. Utför\nbrunnsborrningar i jord och berg samt\nentreprenörarbeten i gas, vatten och\nvärme.\n\nTelefon: Borlänge 10154 o. 10754.\nPostgiro: 11186. — Akt.-kap.: 50,000 kr.\nAntal industriarb.: 60. Tillv.-värde pr år:\n800,000 kr. — Firman etabl. 1903, bolag\n1945.\n\nVerkst. dir.: Carl H. Swahn.\n\nKontorschef: kamrer Bernh. Norström.\n\nIsidor Svahn Pappers-Industri,\n\nHälsingborg.\n\nSe AB. Kassablock, Isidor Svahn,\nPappersindustri, Hälsingborg.\n\nAB. Svalan Cykelfabrik, Falun.\n\nTillverkar cyklar. Varumärke:\n»Svalan».\n\nTelefon: 2402. Postgiro: 278547. —\nAkt.-kap.: 200,000 kr. Antal industriarb.:\n20. — Bolaget grundat 1944.\n\nStyrelse o. verkst. dir.: John Eriksson.\n\n*Erik Sval I ing, Eskilstuna.\n\nSmidesfabrik. Tillverkar\nskräddarsaxar, handplåtsaxar och trädgårdssaxar.\n\nTelegr.-adr.: Saxling, Eskilstuna.\nTelefon: 30165. Postgiro: 74550. — Antal\nindustriarb.: 20. — Firman etabl. 1905.\n\nChef: fabr. Erik A. Svalling.\n\nAB. N. Svalling, Eskilstuna.\n\nSmidesfabrik. Tillverkar kirurgiska\ninstrument, saxar och annat finsmide.\n\nTelefon: 34312. Postgiro: 171357.\nEnsamförsälj. av kirurgiska instrument:\nKirurgiska Instrument Fabriks AB.\nKifa, Stockholm, Regeringsg. 31, telefon:\nInstrument-Kifa.\n\nAkt.-kap.: 100,000 kr. Antal\nindustriarb.: 65. Tillv.-värde pr år: 500,000 kr.\n— Bolaget grundat 1938.\n\nStyrelse: disp. Nils Svalling (ordf.),\nverkstadschef Hugo Broberg, ing. Einar\nSärenholm.\n\nDisp.: N. Svalling.\n\nVerkstadschef: Hugo Broberg.",
    "structured": {
        "1": {
            "name": "S urte—S välling",
            "location": "Surahammar",
            "business": "tackjärnsgjutgods, bromsblock, ringar för lokomotiv- och järnvägsvagnshjul, hjulsatser för järnvägs- och spårvagnar, trallvagnshjul, pressad plåt ångpannebottnar, separatorkulor",
            "products": "Not provided",
            "contact": {
                "office": "Surahammar",
                "phone": [],
                "postgiro": "13271",
                "head_office": "Surahammar",
                "sales_offices": [],
                "telegraph": "Not provided",
                "factory_office": "Kärrgruvan",
                "factory_phone": "Not provided"
            },
            "financials": {
                "capital": "500,000 kr",
                "employees": {
                    "industriarb": 1900
                },
                "annual_turnover": "30,000,000 kr",
                "annual_production_value": "Not provided"
            },
            "foundation_year": 1872,
            "current_name_year": 1918,
            "predecessor": "Not provided",
            "original_name": "Not provided",
            "corporation_year": "Not provided",
            "board": [
                {
                    "name": "J. S. Edström",
                    "role": "ordf."
                },
                {
                    "name": "Thorsten Ericson",
                    "role": "Not provided"
                },
                {
                    "name": "Helge Silverstolpe",
                    "role": "disp."
                },
                {
                    "name": "Claes Wahlund",
                    "role": "disp."
                }
            ],
            "owners": [],
            "director": "Not provided",
            "managing_director": "Helge Silverstolpe",
            "sales_manager": "Not provided",
            "manager": "Not provided"
        },
        "2": {
            "name": "AB. Surte Glasbruk",
            "location": "Surte, Kungälv",
            "business": "buteljer, flaskor, burkar",
            "products": "Not provided",
            "contact": {
                "office": "Surte",
                "phone": [
                    "Göteborg 174000",
                    "Surte 14",
                    "Surte 125"
                ],
                "postgiro": "77074",
                "head_office": "Surte",
                "sales_offices": [],
                "telegraph": "Surte, Göteborg",
                "factory_office": "Not provided",
                "factory_phone": "Not provided"
            },
            "financials": {
                "capital": "3,500,000 kr",
                "employees": {
                    "industriarb": 700
                },
                "annual_turnover": "12,000,000 kr",
                "annual_production_value": "Not provided"
            },
            "foundation_year": 1862,
            "current_name_year": 1906,
            "predecessor": "Not provided",
            "original_name": "Not provided",
            "corporation_year": "Not provided",
            "board": [
                {
                    "name": "frih. C.-G. Langenskiöld",
                    "role": "ordf."
                },
                {
                    "name": "Oscar Ekman",
                    "role": "löjtn."
                },
                {
                    "name": "Per Hemberg",
                    "role": "dir."
                },
                {
                    "name": "H. W. Söderman",
                    "role": "dir."
                },
                {
                    "name": "Ivar Throndsen",
                    "role": "dir."
                }
            ],
            "owners": [],
            "director": "Not provided",
            "managing_director": "Per Hemberg",
            "sales_manager": "Not provided",
            "manager": "Not provided"
        },
        "3": {
            "name": "AB. Svagdricksbryggeriet Sundsvall",
            "location": "Sundsvall",
            "business": "svagdricka",
            "products": "Not provided",
            "contact": {
                "office": "Not provided",
                "phone": [
                    "4422"
                ],
                "postgiro": "31110",
                "head_office": "Not provided",
                "sales_offices": [],
                "telegraph": "Not provided",
                "factory_office": "Not provided",
                "factory_phone": "Not provided"
            },
            "financials": {
                "capital": "100,000 kr",
                "employees": {
                    "arb": 6
                },
                "annual_turnover": "95,000 kr",
                "annual_production_value": "Not provided"
            },
            "foundation_year": 1928,
            "current_name_year": "Not provided",
            "predecessor": "Not provided",
            "original_name": "Not provided",
            "corporation_year": "Not provided",
            "board": [
                {
                    "name": "L. Valentin",
                    "role": "dir."
                }
            ],
            "owners": [],
            "director": "Not provided",
            "managing_director": "Not provided",
            "sales_manager": "Not provided",
            "manager": "Not provided"
        },
        "4": {
            "name": "C. H. Swahn Cjuteri & Mek. Verkstad AB.",
            "location": "Borlänge",
            "business": "elektr. motorpumpar, brunnsborrningar i jord och berg, entreprenörarbeten gas, vatten och värme",
            "products": "Not provided",
            "contact": {
                "office": "Not provided",
                "phone": [
                    "Borlänge 10154",
                    "10754"
                ],
                "postgiro": "11186",
                "head_office": "Not provided",
                "sales_offices": [],
                "telegraph": "Not provided",
                "factory_office": "Not provided",
                "factory_phone": "Not provided"
            },
            "financials": {
                "capital": "50,000 kr",
                "employees": {
                    "industriarb": 60
                },
                "annual_turnover": "800,000 kr",
                "annual_production_value": "Not provided"
            },
            "foundation_year": 1903,
            "current_name_year": 1945,
            "predecessor": "Not provided",
            "original_name": "Not provided",
            "corporation_year": "Not provided",
            "board": [],
            "owners": [],
            "director": "Not provided",
            "managing_director": "Carl H. Swahn",
            "sales_manager": "Not provided",
            "manager": "Not provided"
        },
        "5": {
            "name": "Erik Sval I ing",
            "location": "Eskilstuna",
            "business": "smidesfabrik, skräddarsaxar, handplåtsaxar, trädgårdssaxar",
            "products": "Not provided",
            "contact": {
                "office": "Not provided",
                "phone": [
                    "30165"
                ],
                "postgiro": "74550",
                "head_office": "Not provided",
                "sales_offices": [],
                "telegraph": "Saxling, Eskilstuna",
                "factory_office": "Not provided",
                "factory_phone": "Not provided"
            },
            "financials": {
                "capital": "Not provided",
                "employees": {
                    "industriarb": 20
                },
                "annual_turnover": "Not provided",
                "annual_production_value": "Not provided"
            },
            "foundation_year": 1905,
            "current_name_year": "Not provided",
            "predecessor": "Not provided",
            "original_name": "Not provided",
            "corporation_year": "Not provided",
            "board": [],
            "owners": [],
            "director": "Not provided",
            "managing_director": "Erik A. Svalling",
            "sales_manager": "Not provided",
            "manager": "Not provided"
        },
        "6": {
            "name": "AB. N. Svalling",
            "location": "Eskilstuna",
            "business": "smidesfabrik, kirurgiska instrument, saxar, finsmide",
            "products": "Not provided",
            "contact": {
                "office": "Not provided",
                "phone": [
                    "34312"
                ],
                "postgiro": "171357",
                "head_office": "Not provided",
                "sales_offices": [
                    {
                        "location": "Stockholm, Regeringsg. 31",
                        "phone": "Instrument-Kifa"
                    }
                ],
                "telegraph": "Not provided",
                "factory_office": "Not provided",
                "factory_phone": "Not provided"
            },
            "financials": {
                "capital": "100,000 kr",
                "employees": {
                    "industriarb": 65
                },
                "annual_turnover": "500,000 kr",
                "annual_production_value": "Not provided"
            },
            "foundation_year": 1938,
            "current_name_year": "Not provided",
            "predecessor": "Not provided",
            "original_name": "Not provided",
            "corporation_year": "Not provided",
            "board": [],
            "owners": [],
            "director": "Not provided",
            "managing_director": "Not provided",
            "sales_manager": "Not provided",
            "manager": "Not provided"
        }
    }
}