{
    "original": "Standard—Staten\n\nPostadr.: Strängnäs. Telegr.-adr.:\nStal-farinda, S tallarholmen, Telefon:\n»Industribolaget», Stallarholmen. Postgiro:\n2308.\n\nAkt.-kap.: 45,000 kr. Antal\nindustriarb.: 30. Tillv.-värde pr år: 400,000 kr.\n— Firman etabl. 1908, ombildad 1934.\n\nStyrelse o. disp.: Gunnar Wahlgren.\n\n*Standard, Chokladfabriken,\n\nDandéryd.\n\nSö Ohokladfabriken Standard,\nDandéryd.\n\nStandard, Färg- &amp; Ferniss Fabriks\n\nAB., Trelleborg.\n\nSe Färg- &amp; Ferniss Fabriks AB.\nStandard, Trelleborg.\n\n\"Standard, AB. Skofabriken, Lund.\n\nSe AB. Skofabriken Standard, Lund.\n\nAB. Standardhjul, Norrköping.\n\nVagnfabrik. Tillverkar hästvagnar samt\nhjul med kullagernav och gummidäck.\n\nTelefon: 23881. Postgiro: 176524. —\nAkt.-kap.: 40,000 kr. Antal industriarb.:\n8. Tillv.-värde pr år: 250,000 kr. —\nBolaget grundat 1940.\n\nDisp.: Owe Nilsson.\n\nAB. Standardhus, Hultsfred.\n\nTillverkar monteringsfärdiga trähus\nvid snickerifabrik i Hultsfred\n(Kalmar l.).\n\nHuvudkontor: Hultsfred. Telegr.-adr.:\no. telefon: Standardhus, Hultsfred.\nAvd.-kontor i Stockholm, Stureplan 19.\nTelefon: 211470.\n\nAkt.-kap.: 100,000 kr. Tillv.-värde pr\når : 10,000,000 kr.\n\nFirman, etabl. 1927, ombildad 1935, är\ndotterbolag till Hultsfreds Träförädlings\nAB.\n\nVerkst. dir.: Gösta Edström (Växjö).\n\nPlatschef: disp. Torsten Wahlquist.\n\nAB. Standard Radiofabrik,\n\nTJlv sunda.\n\nTillverkar maskiner och apparater för\nTadiotelefoni och telegrafi, elektronrör,\nlikriktare m. m. vid fabrik i Ulvsunda,\nStockholm.\n\nKontor: Johannesfredsv. 9—11,\nUlv-sunda. Telegr.-adr.: Stanelco, Stockholm.\nTelefon: Stockholm 252610. Postgiro:\n156723.\n\nAkt.-kap.: 1,000,000 kr. Antal\nindustriarb.: 250. Tillv.-värde pr år: 3,000,000 kr.\n\n—\tBolaget grundat 1938. /\n\nStyrelse: f. d. generaldir. greve Adolf\nHamilton (ordf.), dir. Jens Bache-Wiig,\nciviling. Per Erikson, dir. Paul Hallgren,\nkapten Bertil af Klercker, dir. Pér-Olov\nÅhlén.\n\nVerkst. dir.: Per-Olov Åhlén.\nKamrer: Hans Dahl.\n\nStår, Kartongfabriken, Habo.\nSe Kartongfabriken Star, Habo.\n\n\"Starbo Bruksägares AB., Starbo.\nSe Avesta Jernverks AB., Avesta.\n\nAB. Starfors Säteri, Heby.\n\nTegelbruk och bränntorvfabrik i Heby\n(Västmanl. l.). Tillverkar taktegel och\ndräneringsrör samt bränntorv.\nVarumärke: »Starfors Heby Tegel».\n\nTelefon: » S t arf orstegel». Postgiro :\n144565. Repr.: Söderberg &amp; Haak AB.,\nStockholm, Göteborg o. Malmö.\n\nAkt.-kap.: 200,000 kr. Antal\nindustriarb.: 65. Årstillv.: 3,5 milj. st. tegelvaror.\n\n—\tTegelbruket anlagt 1905.\nDisp.: fil. lic. Bengt Hahr.\nFörvalt.: Filip Magnusson.\n\n\"Stark, Cruf AB., i Likv., Håksberg.\n\nSe Håksbergs Nya Gruv AB.,\nHåksberg.\n\n\"AB. Statens Skogsindustrier,\n\nStockholm.\n\nSågverk vid Sandvik pr Seskarö och\nvid Båtskärsnäs, sågverk, hyvleri och\nträhusfabrik vid Karlsborg pr\nKarlsborgs-verken, sågverk, hyvleri och trähusfabrik\nvid Lövholmen pr Piteå, sulfatfabrik med\nbiproduktsverk vid Karlsborg och\nträkemiska fabriker i Piteå (samtl. i Norrb. l.),\nlegosågning vid Sandviks sågverk pr\nHolmsund (Västerb. l.),\n\nsågverk, hyvleri, trähusfabrik,\nsnickerifabrik och träullsfabrik i Horndal,\nååg-verk och hyvleri vid Saxviken pr Mora\n(båda i Kopparb. l.),\n\nsågverk, hyvleri, lådfabrik,\nträhusfabrik och träkemiska fabriker i\nSkinn-skatteberg (Västmanl. l.),\n\nsågverk, hyvleri och trähusfabrik i\nValåsen (Örebro l.),\n\nsågverk i Kungsskogen pr ölme (Värml.\n]-)&gt;\n\nsågverk och hyvleri i Sjöbacka pr\nMas-pelösa (Östergötl. l.),\n\n503*",
    "structured": {
        "firms": [
            {
                "namn": "Standard—Staten",
                "plats": "Strängnäs",
                "postadress": "Strängnäs",
                "telegraf": "Stal-farinda",
                "telefon": [
                    "Industribolaget",
                    "Stallarholmen"
                ],
                "postgiro": "2308",
                "aktiekapital": "45,000 kr",
                "antal_industriarbetare": 30,
                "tillverkningsvärde_per_år": "400,000 kr",
                "grundat_år": 1908,
                "ombildat_år": 1934,
                "styrelse_och_disp": "Gunnar Wahlgren"
            },
            {
                "namn": "Standard, Chokladfabriken",
                "plats": "Dandéryd"
            },
            {
                "namn": "Standard, Färg- & Ferniss Fabriks AB.",
                "plats": "Trelleborg"
            },
            {
                "namn": "Standard, AB. Skofabriken",
                "plats": "Lund"
            },
            {
                "namn": "AB. Standardhjul",
                "plats": "Norrköping",
                "verksamhetsbeskrivning": "Vagnfabrik. Tillverkar hästvagnar samt hjul med kullagernav och gummidäck",
                "telefon": "23881",
                "postgiro": "176524",
                "aktiekapital": "40,000 kr",
                "antal_industriarbetare": 8,
                "tillverkningsvärde_per_år": "250,000 kr",
                "grundat_år": 1940,
                "disp": "Owe Nilsson"
            },
            {
                "namn": "AB. Standardhus",
                "plats": "Hultsfred",
                "verksamhetsbeskrivning": "Tillverkar monteringsfärdiga trähus vid snickerifabrik i Hultsfred (Kalmar l.)",
                "huvudkontor": "Hultsfred",
                "avdelningskontor": {
                    "plats": "Stockholm",
                    "telefon": "211470"
                },
                "aktiekapital": "100,000 kr",
                "tillverkningsvärde_per_år": "10,000,000 kr",
                "grundat_år": 1927,
                "ombildat_år": 1935,
                "dotterbolag": "Hultsfreds Träförädlings AB",
                "verkst_disp": "Gösta Edström (Växjö)",
                "platschef_disp": "Torsten Wahlquist"
            },
            {
                "namn": "AB. Standard Radiofabrik",
                "plats": "Ulv sunda",
                "verksamhetsbeskrivning": "Tillverkar maskiner och apparater för Tadiotelefoni och telegrafi, elektronrör, likriktare m. m. vid fabrik i Ulvsunda, Stockholm",
                "kontor": "Johannesfredsv. 9—11, Ulvsunda",
                "telefon": "Stockholm 252610",
                "postgiro": "156723",
                "aktiekapital": "1,000,000 kr",
                "antal_industriarbetare": 250,
                "tillverkningsvärde_per_år": "3,000,000 kr",
                "grundat_år": 1938,
                "styrelse": [
                    {
                        "namn": "f. d. generaldir. greve Adolf Hamilton",
                        "roll": "ordf."
                    },
                    {
                        "namn": "dir. Jens Bache-Wiig",
                        "roll": null
                    },
                    {
                        "namn": "civiling. Per Erikson",
                        "roll": null
                    },
                    {
                        "namn": "dir. Paul Hallgren",
                        "roll": null
                    },
                    {
                        "namn": "kapten Bertil af Klercker",
                        "roll": null
                    },
                    {
                        "namn": "dir. Pér-Olov Åhlén",
                        "roll": null
                    }
                ],
                "verkst_disp": "Per-Olov Åhlén",
                "kamrer": "Hans Dahl"
            },
            {
                "namn": "Starbo Bruksägares AB.",
                "plats": "Starbo"
            },
            {
                "namn": "AB. Starfors Säteri",
                "plats": "Heby",
                "verksamhetsbeskrivning": "Tegelbruk och bränntorvfabrik i Heby (Västmanl. l.). Tillverkar taktegel och dräneringsrör samt bränntorv"
            },
            {
                "namn": "Stark, Cruf AB.",
                "plats": "Håksberg"
            },
            {
                "namn": "AB. Statens Skogsindustrier",
                "plats": "Stockholm"
            }
        ]
    }
}