{
    "original": "Stockholm\n\n\"Stockholms Benmjölsfabriks AB.,\n\nStockholm.\n\nLim-, benmjöls- och benfettfabrik vid\nSandvik (Stockholm).\n\nTillverkar lim, limduk, tvättmedel\n(»Pärlglans»), skarvband för\npappersindustrien, benfett och benolja,\nmineralnäring (»Bovisan»), foderbenmjöl,\nåkerbenmjöl, hornmjöl, härdmjöl, härdgryn,\nhönsfoder, skumvätska samt\nkonstharts-lim.\n\nKontor: Sandvik; postadr.: Stockholm\n12. Telegr.-adr.: Benmjöl, Stockholm.\nTelefon: 252550. Postgiro: 1185.\n\nAkt.-kap.: 4,000,000 kr. Antal\nindustriarb.: 150. — Firman etabl. 1890.\n\nStyrelse: godsäg. Anders Bergengren,\ndir. Gösta Du Rietz, civiling. Gustaf\nEekerbom, civiling. Sune Lindahl,\nbank-ombudsm. Eric Paulson.\n\nVerkst. dir.: Gustaf Eekerbom.\n\nFörsäljn.-chef: N. Ryman.\n\nDriftsing.: Valter öhman.\n\nKamrer: Einar Levin.\n\n\"AB. Stockholms Bleckvarufabrik,\n\nAspudden.\n\nTillverkar bleckemballage och\nsparbössor vid fabrik i Aspudden. Stockholm.\n\nKontor: Aspudden; telefon: 450565.\nPostgiro: 51820. Ensamförsälj. för\nsparbössor: AB. Nordia, Stockholm, Kungsg.\n55; telefon: 114646.\n\nAkt.-kap.: 75,000 kr. Antal\nindustriarb.: 15. Tillv.-värde pr år: 350,000 kr.\n\n—\tFirman etabl. 1924, bolag 1929.\n\nStyrelse o. verkst. dir.: ing. Ernst E.\n\nAndersson.\n\nStockholms Blusfabrik AB.,\n\nTureberg.\n\nKonfektionsfabrik i Tureberg\n(Stockholms l.). Tillverkar damblusar.\n\nKontor: Tureberg. Telefon: Stockholm\n352398.\n\nAkt.-kap.: 25,000 kr. Antal\nindustriarb.: 20. Tillv.-värde pr år: 250,000 kr.\n\n—\tFirman etabl. 1944 under namn\nTurebergs Blusfabrik AB., namnförändring\n1945. Bolaget är dotterbolag till\nKonfektions AB. Salén.\n\nStyrelse: dir. Sven G. Salén (ordf.),\nadv. Gösta Ekelund, dir. Sixten Nilson.\n\nVerkst. dir.: Sven G. Salén.\n\n\"Stockholms Bomullsspinneri och\nVäfveri AB., Stockholm.\n\nBomullsspinneri och väveri,\nsidenvä-veri och berednings verk vid Barnängen,\n\nfärgeri, blekeri och trikåfabrik vid\nLiljeholmen (båda i Stockholm),\nbomullsspinneri och vigognespinneri vid\nTors-hag, Åby (östergotl. l.).\n\nTillverkar bomullsgarn, oblekta, blekta,\nfärgade och kulörta bomullsvävnader,\nsidenvävnader, sytråd, strumpor och\ntri-kåvaror alla slag; utför blekning och\nfärgning av bomullsgarn och vävnader,\nkonstsilke och ullgarn; bedriver\nlönfärg-ning.\n\nHuvudkontor: Stockholm, Barnängsg.\n23. Telegr.-adr.: Bomullsspinneri,\nStockholm. Telefon: »Stockholms\nBomullsspinneri».\n\nAkt.-kap.: 3,000,000 kr. Antal\nindustriarb.: 1,000. — Bolaget, grundat 1869,\näger Hargs Fabrikers AB., Nyköping.\n\nStyrelse: adv. Emil Heijne (ordf.),\ndisp. Bo Ericsson, disp. Folke Ericsson,\n»jur. kand. Sven Ericsson, dir. Torsten\nEricsson.\n\nVerkst. dir.: Sven Ericsson.\n\nStockholms Borstbinderi AB.,\n\nStockholm.\n\nTillverkar penslar vid fabrik i\nMariefred samt borstar och tandborstar vid\nfabrik i Vinslöv (Borstbinderibolagets\nFabriks AB.). Varumärke: »Kron».\n\nKontor: Stockholm, Stureg. 4.\nTelegr.-adr.: Borstbolag, Stockholm. Telefon:\n679085. Postgiro: 862.\n\nAkt.-kap.: 450,000 kr. Antal\nindustriarb.: 110. Tillv.-värde pr år: 1,000,000 kr.\n—: Bolaget grundat 1874.\n\nStyrelse: dir. Bengt Ahlberg (ordf.),\nfru Sally Ahlberg, adv. P. A. Weslien.\n\nVerkst. dir.: Bengt Ahlberg.\n\n\"AB. Stockholms Bryggerier,\n\nStockholm.\n\nTillverkar maltdrycker vid Hamburger\nBryggeriet, Surbrunnsg. 64, Grönwalls\nBryggeri och Miinchens Bryggeri, Torkel\nKnutsonsg. 2.\n\nHuvudkontor: Kungsg. 19.\nTelegr.-adr.: Bryggerierna, Stockholm. Telefon:\n»Stockholms Bryggerier». Postgiro: 2409.\nFilialer: Vaxholm, Upplands-Väsby och\nSigtuna.\n\nAkt.-kap.: 39,448,500 kr. Antal\nindustriarb.: 850. Försäljningsvärde pr år:\n38,000,000 kr.\n\nBolaget grundat 1889.\n\nStyrelse: kabinettskammarh. Eric\nHallin (ordf.), dr Ivar Anderson, dir. Harald\nEngström, grossh. Robert Ljunglöf, dir.\nSven Schwartz, disp. Nils Westerdahl.\n\nVerkst. dir.: Sven Schwartz.\n\nVice verkst. dir.: Harald Engström.\n\nTehn. dir.: civiling. G. G. Piehl.",
    "structured": {
        "1": {
            "name": "Stockholms Benmjölsfabriks AB.",
            "location": "Stockholm",
            "business": "Lim-, benmjöls- och benfettfabrik",
            "products": "Tillverkar lim, limduk, tvättmedel (»Pärlglans»), skarvband för pappersindustrien, benfett och benolja, mineralnäring (»Bovisan»), foderbenmjöl, åkerbenmjöl, hornmjöl, härdmjöl, härdgryn, hönsfoder, skumvätska samt konstharts-lim.",
            "contact": {
                "office": "Sandvik",
                "phone": [
                    "252550"
                ],
                "postgiro": "1185",
                "telegraph": "Benmjöl, Stockholm"
            },
            "financials": {
                "capital": "4,000,000 kr",
                "employees": {
                    "industriarb": 150
                },
                "annual_turnover": "Not available",
                "annual_production_value": "Not available"
            },
            "foundation_year": 1890,
            "board": [
                {
                    "name": "Anders Bergengren",
                    "role": "Styrelse"
                },
                {
                    "name": "Gösta Du Rietz",
                    "role": "dir."
                },
                {
                    "name": "Gustaf Eekerbom",
                    "role": "civiling."
                },
                {
                    "name": "Sune Lindahl",
                    "role": "civiling."
                },
                {
                    "name": "Eric Paulson",
                    "role": "bank-ombudsm."
                }
            ],
            "owners": [
                "Not available"
            ],
            "director": "Gustaf Eekerbom",
            "managing_director": "Not available",
            "sales_manager": "N. Ryman",
            "manager": "Einar Levin"
        },
        "2": {
            "name": "AB. Stockholms Bleckvarufabrik",
            "location": "Aspudden",
            "business": "Tillverkar bleckemballage och sparbössor",
            "contact": {
                "office": "Aspudden",
                "phone": [
                    "450565"
                ],
                "postgiro": "51820"
            },
            "financials": {
                "capital": "75,000 kr",
                "employees": {
                    "industriarb": 15
                },
                "annual_turnover": "350,000 kr",
                "annual_production_value": "Not available"
            },
            "foundation_year": 1924,
            "current_name_year": 1929,
            "board": [
                {
                    "name": "ing. Ernst E. Andersson",
                    "role": "Styrelse o. verkst. dir."
                }
            ],
            "owners": [
                "Not available"
            ],
            "director": "Not available",
            "managing_director": "Not available",
            "sales_manager": "Not available",
            "manager": "Not available"
        },
        "3": {
            "name": "Stockholms Blusfabrik AB.",
            "location": "Tureberg",
            "business": "Konfektionsfabrik",
            "contact": {
                "office": "Tureberg",
                "phone": [
                    "Stockholm 352398"
                ]
            },
            "financials": {
                "capital": "25,000 kr",
                "employees": {
                    "industriarb": 20
                },
                "annual_turnover": "250,000 kr",
                "annual_production_value": "Not available"
            },
            "foundation_year": 1944,
            "current_name_year": 1945,
            "board": [
                {
                    "name": "Sven G. Salén",
                    "role": "Styrelse"
                },
                {
                    "name": "Gösta Ekelund",
                    "role": "adv."
                },
                {
                    "name": "Sixten Nilson",
                    "role": "dir."
                }
            ],
            "owners": [
                "Not available"
            ],
            "director": "Sven G. Salén",
            "managing_director": "Not available",
            "sales_manager": "Not available",
            "manager": "Not available"
        },
        "4": {
            "name": "Stockholms Bomullsspinneri och Väfveri AB.",
            "location": "Stockholm",
            "business": "Bomullsspinneri och väveri",
            "products": "Tillverkar bomullsgarn, oblekta, blekta, färgade och kulörta bomullsvävnader, sidenvävnader, sytråd, strumpor och tri-kåvaror alla slag; utför blekning och färgning av bomullsgarn och vävnader, konstsilke och ullgarn; bedriver lönfärg-ning.",
            "contact": {
                "office": "Stockholm, Barnängsg. 23",
                "phone": [
                    "Not available"
                ],
                "telegraph": "Bomullsspinneri, Stockholm"
            },
            "financials": {
                "capital": "3,000,000 kr",
                "employees": {
                    "industriarb": 1,
                    "000": 1,
                    "Antal": 1
                },
                "annual_turnover": "Not available",
                "annual_production_value": "Not available"
            },
            "foundation_year": 1869,
            "board": [
                {
                    "name": "Emil Heijne",
                    "role": "adv."
                },
                {
                    "name": "Bo Ericsson",
                    "role": "disp."
                },
                {
                    "name": "Folke Ericsson",
                    "role": "disp."
                },
                {
                    "name": "Sven Ericsson",
                    "role": "»jur. kand."
                },
                {
                    "name": "Torsten Ericsson",
                    "role": "dir."
                }
            ],
            "owners": [
                "Not available"
            ],
            "director": "Sven Ericsson",
            "managing_director": "Not available",
            "sales_manager": "Not available",
            "manager": "Not available"
        },
        "5": {
            "name": "Stockholms Borstbinderi AB.",
            "location": "Stockholm",
            "business": "Tillverkar penslar, borstar och tandborstar",
            "contact": {
                "office": "Stockholm, Stureg. 4",
                "phone": [
                    "679085"
                ],
                "postgiro": "862"
            },
            "financials": {
                "capital": "450,000 kr",
                "employees": {
                    "industriarb": 110
                },
                "annual_turnover": "1,000,000 kr",
                "annual_production_value": "Not available"
            },
            "foundation_year": 1874,
            "board": [
                {
                    "name": "Bengt Ahlberg",
                    "role": "dir."
                },
                {
                    "name": "Sally Ahlberg",
                    "role": "fru"
                },
                {
                    "name": "P. A. Weslien",
                    "role": "adv."
                }
            ],
            "owners": [
                "Not available"
            ],
            "director": "Bengt Ahlberg",
            "managing_director": "Not available",
            "sales_manager": "Not available",
            "manager": "Not available"
        },
        "6": {
            "name": "AB. Stockholms Bryggerier",
            "location": "Stockholm",
            "business": "Tillverkar maltdrycker",
            "contact": {
                "office": "Kungsg. 19",
                "phone": [
                    "Not available"
                ],
                "postgiro": "2409"
            },
            "financials": {
                "capital": "39,448,500 kr",
                "employees": {
                    "industriarb": 850
                },
                "annual_turnover": "38,000,000 kr",
                "annual_production_value": "Not available"
            },
            "corporation_year": 1889,
            "board": [
                {
                    "name": "Eric Hallin",
                    "role": "kabinettskammarh."
                },
                {
                    "name": "Ivar Anderson",
                    "role": "dr"
                },
                {
                    "name": "Harald Engström",
                    "role": "dir."
                },
                {
                    "name": "Robert Ljunglöf",
                    "role": "grossh."
                },
                {
                    "name": "Sven Schwartz",
                    "role": "dir."
                },
                {
                    "name": "Nils Westerdahl",
                    "role": "disp."
                }
            ],
            "owners": [
                "Not available"
            ],
            "director": "Sven Schwartz",
            "managing_director": "Not available",
            "sales_manager": "Not available",
            "manager": "Not available"
        }
    }
}