{
    "original": "Stockho Im—Stokke bye\n\n(båda i Västernorrl. l.) samt i Trollhättan.\n\nTillverkar gödningsämnen, karbid,\nklo-rater, perklorater, överklorsyra,\nkväveprodukter, legeringar, konsthartser och\ndiverse kemikalier. Bryter kalksten vid\nFurillen (Gotl. l.) o. Mattmar (Jämtl. l.).\n\nKontor: Stockholm, Sturegatan 26.\nPost- o. telegr.-adr.: Fosfatbolaget,\nStockholm. Telefon: Fosfat. Postgiro: 92.\n\nAkt.-kap.: 15,000,000 kr. Antal\nindustriarb.: 1,750. Tillv.-värde pr år:\n35,000,000 kr.\n\nBolaget grundat 1871.\n\nStyrelse: fil. dr Harald Nordensop\n(ordf.), kabinettskammarh. Rolf v.\nHei-denstam, grossh. Robert Ljunglöf, dr\nSigurd Nauckhoff, f. d. landshövd. Joh.\nNilsson, disp. Ejnar Rödling, civiling.\nHans Rydin.\n\nVerkst. dir.: Hans Rydin.\n\nDriftschefer: i Ljungaverk: disp.\nGustav Carlsson; i Stockviks verken: disp. Bj.\nColbj örasen; i Trollhättan: disp. Thore\nRosendahl.\n\n*AB. Stockholms Tekniska\nPappersfabrik, Stockholm.\n\nKem.-tekn. fabrik för pappersförädling.\nTillverkar blåkopierings-,\nvitkopierings-och sepiakopieringspapper samt\nljus-känslig väv.\n\nKontor: Valhallavägen 140.\nTelegr.-adr.: Esstepa, Stockholm. Telefon: 622867.\nPostgiro: 52589.\n\nAkt.-kap.: 90,300 kr. Arb.-antal: 5.\nTillv.-värde pr år: 110,000 kr. — Firman\netabl. 1910, bolag 1929.\n\nStyrelse: verkm. Fritz Johansson,\nkommendörkapt. Gösta\nSjöberg-Silfver-ling.\n\nVerkst. dir.: Gösta Sjöberg-Silfverling.\n\nStockholms Transport- och\nBogserings AB., Stockholm.\n\nSkeppsvarv och mek. verkstad vid\nHög-marsö, Furusund (Sthlms l.).\n\nUtför nybyggnader och reparationer av\nfartyg^ upp till 600 ton dw. Utför jämväl\nbogseringar och pråmtransporter samt\ntimmerbogseringar ävensom\nbärgnings-och dykeri arbeten.\n\nKontor: Stadsgården 20; postadr.:\nStockholm 15. Telegr.-adr.:\nTransportbolag, Stockholm. Telefon:\n»Transportbolaget». Postgiro: 3140.\n\nAkt.-kap.: 800,000 kr. Antal varvsarb.:\n50.\n\nBolaget grundat 1870, ombildat 1924.\n\nStyrelse: dir. Nils Wahlberg (ordf.),\nkapten Erik Appelqvist, skeppsklarerare\nBörje Tägtmeijer.\n\nVerkst. dir.: Erik Appelqvist.\n\n*AB. Stockholms Vaddfabrik,\n\nLiljeholmen.\n\nVaddfabrik å Liljeholmen, Stockholm.\nTillverkar vadd och sängkläder.\nVarunamn: »Systern».\n\nTelefon: 451985—87. Postgiro: 8806.\nAkt.-kap.: 350,000 kr. Antal\nindustriarb.: 65. Tillv.-värde pr år: 1,000,000 kr.\n\nBolaget, grundat 1901, äger AB. Nya\nVaddfabriken, Liljeholmen.\n\nStyrelse: dir. Ernst Rudels (ordf.), dir.\nTorsten Brodin, överdir. Ryno Lundqvist.\nVerkst. dir.: Torsten Brodin.\nKontorschef: Ernst Söderberg.\n\n*AB. F. Stocklassas Borst- &amp;\nPenselfabrik, Stockholm.\n\nTillverkar borstar och penslar.\nKontor: Nytorgsg. 17. Telegr.-adr.:\nStocklassas, Stockholm. Telefon: 434817.\nPostgiro: 916.\n\nAkt.-kap.: 90,000 kr. Antal\nindustriarb.: 20. Tillv.-värde pr år: 300,000 kr.\n— Firman etabl. 1856.\n\nStyrelse: adv. Fredrik Blomdahl,\nkamrer Martin öhman, dir. Ture öhman.\nVerkst. dir. o. fabrikschef: Ture öhman.\n\n\"Stockviks Fabriker, Stockviksverken.\n\nSe Stockholms Superfosfat Fabriks\nAB., Stockholm.\n\n*AB. Stohne-Verken, Stockholm,\n\nElektromek. verkstad. Tillverkar\napparater, instrumenteringar,\nmanöverutrustningar, specialmotstånd och reläer; utför\nomlindningar samt reparationer av elektr.\nmotorer, transformatorer m. m.\n\nKontor: Lindhagensg. 128; postadr.:\nStockholm 30. Telegr.-adr.:\nElektro-stohne, Stockholm. Telefon: 520060.\nPostgiro: 199193.\n\nAkt.-kap.: 50,000 kr. Antal\nindustriarb.: 68. Tillv.-värde pr år: 800,000 kr. —\nFirman etabl. 1944 under namn Sandblom\n&amp; Stohne Verkstads AB., nuv. namn 1946.\n\nStyrelse o. verkst. dir.: ing. Bertil\nStohne.\n\nKamrer: Karl Ahnmarker.\nDriftsing.: Ansgar Hansen.\n\nP. 0. Stokkebyes Kvarn AB.,\n\nGöteborg.\n\nKvarnar samt oljeslageri och\nfoder-blandningsfabrik vid Agnesberg (Älvsb.\n1.). Tillverkar ångpreparerade havregryn,\nhavremjöl, havremust, krossgryn,\nvetemjöl, vetekli, risflingor, havrefodérmjol,\nkraftfoderblandningar, linolja och linfrö-\n\n648*",
    "structured": {
        "1": {
            "name": "AB Stockholms Tekniska Pappersfabrik",
            "location": "Stockholm",
            "business": "Kemisk-teknisk fabrik för pappersförädling",
            "contact": {
                "office": "Valhallavägen 140",
                "telegraph": "Esstepa, Stockholm",
                "phone": "622867",
                "postgiro": "52589"
            },
            "financials": {
                "capital": "90,300 kr",
                "employees": {
                    "Arb.-antal": 5
                },
                "annual_turnover": "110,000 kr"
            },
            "foundation_year": 1910,
            "current_name_year": 1929,
            "board": [
                {
                    "name": "verkm. Fritz Johansson",
                    "role": null
                },
                {
                    "name": "kommendörkapt. Gösta Sjöberg-Silfverling",
                    "role": null
                }
            ],
            "director": "Gösta Sjöberg-Silfverling"
        },
        "2": {
            "name": "Stockholms Transport- och Bogserings AB",
            "location": "Stockholm",
            "business": null,
            "contact": {
                "office": "Stadsgården 20",
                "telegraph": "Transportbolag, Stockholm",
                "phone": "Transportbolaget",
                "postgiro": "3140"
            },
            "financials": {
                "capital": "800,000 kr",
                "employees": {
                    "Antal varvsarb.": 50
                }
            },
            "foundation_year": 1870,
            "corporation_year": 1924,
            "board": [
                {
                    "name": "dir. Nils Wahlberg",
                    "role": "ordf."
                },
                {
                    "name": "kapten Erik Appelqvist",
                    "role": null
                },
                {
                    "name": "skeppsklarerare Börje Tägtmeijer",
                    "role": null
                }
            ],
            "director": "Erik Appelqvist"
        },
        "3": {
            "name": "AB Stockholms Vaddfabrik",
            "location": "Liljeholmen",
            "business": "Vaddfabrik",
            "contact": {
                "phone": "451985—87",
                "postgiro": "8806"
            },
            "financials": {
                "capital": "350,000 kr",
                "employees": {
                    "Antal industriarb.": 65
                },
                "annual_production_value": "1,000,000 kr"
            },
            "foundation_year": 1901,
            "board": [
                {
                    "name": "dir. Ernst Rudels",
                    "role": "ordf."
                },
                {
                    "name": "dir. Torsten Brodin",
                    "role": null
                },
                {
                    "name": "överdir. Ryno Lundqvist",
                    "role": null
                }
            ],
            "director": "Torsten Brodin",
            "manager": "Ernst Söderberg"
        },
        "4": {
            "name": "AB F. Stocklassas Borst- & Penselfabrik",
            "location": "Stockholm",
            "business": "Tillverkar borstar och penslar",
            "contact": {
                "office": "Nytorgsg. 17",
                "telegraph": "Stocklassas, Stockholm",
                "phone": "434817",
                "postgiro": "916"
            },
            "financials": {
                "capital": "90,000 kr",
                "employees": {
                    "Antal industriarb.": 20
                },
                "annual_production_value": "300,000 kr"
            },
            "foundation_year": 1856,
            "manager": "Ture öhman",
            "original_name": "F. Stocklassas Borst- & Penselfabrik"
        },
        "5": {
            "name": "AB. Stohne-Verken",
            "location": "Stockholm",
            "business": "Elektromek. verkstad",
            "contact": {
                "office": "Lindhagensg. 128",
                "telegraph": "Elektro-stohne, Stockholm",
                "phone": "520060",
                "postgiro": "199193"
            },
            "financials": {
                "capital": "50,000 kr",
                "employees": {
                    "Antal industriarb.": 68
                },
                "annual_production_value": "800,000 kr"
            },
            "foundation_year": 1944,
            "current_name_year": 1946,
            "board": [
                {
                    "name": "ing. Bertil Stohne",
                    "role": "verkst. dir."
                }
            ],
            "manager": "Karl Ahnmarker",
            "sales_manager": "Ansgar Hansen"
        },
        "6": {
            "name": "P. O. Stokkebyes Kvarn AB.",
            "location": "Göteborg",
            "business": "Tillverkar ångpreparerade havregryn, havremjöl",
            "contact": {
                "office": null,
                "telegraph": null,
                "phone": null,
                "postgiro": null
            },
            "financials": {
                "capital": null,
                "employees": null,
                "annual_production_value": null
            },
            "foundation_year": null,
            "predecessor": null,
            "original_name": "P. O. Stokkebyes Kvarn AB."
        }
    }
}