{
    "original": "Stens—Stiberg\n\nAki&amp;rk&amp;p.: 400,000 kr.^ Antal\nindustriarb.: 125. Tillv.-värde pr år: 1,500,000 kr.\n\n—\tFirman etabl. 1894, bolag 1927.\n\nVerkst. dir. o. disp.: Nils E. Erlandson.\n\nKamrer: Otto A. Persson.\n\nFörsäljn.-chef: Olle Olefeldt.\n\n*Stens Choklad. &amp; Konfektfabrik\nAB., Göteborg.\n\nTillverkar choklad, konfekt, marmelad,\nkarameller och dragéer.\n\nKontor: Åvägen 18. Telefon: 182116—\n18 o. 182138. Postgiro: 12250.\n\nAkt.-kap.: 82,500 kr. Antal\nindustriarb.: 85. — Firman etabl. 1924, bolag\n1930.\n\nStyrelse: dir. Olof Stenborg (ordf.),\ndisp. Ivar Stenborg, prokurist Nils\nSten-borg.\n\nVerkst. dir.: Olof Stenborg.\n\nDisp.: Ivar Stenborg.\n\n*Stensholms Fabriks AB., Huskvarna.\n\nMek. verkstad. Tillverkar\nindustritillbehör såsom oljetätningsr ingår, låsringar,\nhögtryckssmörj sprutor, eltermostater,\nströmställare, svänghjulsmagneter samt\nspistermometrar.\n\nTelegr.-adr.: Stensholm, Huskvarna.\nTelefon: 1200. Postgiro: 31812.\n\nAkt.-kap.: 82,000 kr. Antal\nindustriarb.: 270. Tillv.-värde pr år: 3,600,000 kr.\n\n—\tBolaget grundat 1890.\n\nStyrelse: dir. F. af Klercker, f. d.\nhovrättsrådet Johan Nordenfalk, ing. Percy\nH:sson Tamm, civiling. Stig Tham.\n\nVerkst. dir.: F. af Klercker.\n\n*AB. Stenströms Skjortfabrik,\n\nHälsingborg.\n\nTillverkar skjortor, kragar och\nmanschetter samt pyjamas.\n\nTelefon: 10627. Postgiro: 80080. —\nAkt.-kap.: 360,000 kr. Antal industriarb.:\n60. — Firman etabl. 1899, bolag 1901.\n\nStyrelse: assessor Henry Ljunggren\n(ordf.), fröken I. Stenström (v. ordf.),\nköpm. A. Ohrlander.\n\nVerkst. dir. o. disp.: fröken I.\nStenström.\n\n*Ch. Stenström AB., Norrköping.\n\nVaddfabrik och ullspinneri. Tillverkar\nvadd, flock, stoppmaterial, resårikuddar\noch madrasser, täcken, axelvaddar samt\nsvenskulls- och schoddygarner.\n\nTelegr.-adr.: Tebe, Norrköping.\nTelefon: 20829. Postgiro: 70733. Repr. i\nStockholm: Hugo Minten, Smedsbacksg.\n11, telefon: 619939.\n\nAkt.rkap,: 72,400 kr. Antal\nindustriarb.: 65. Tillv.-varde pr år: 1,200,000 kr.\n— Firman etabl. 1910, bolag 1944.\n\nStyrelse.: dir. Torsten Brodin (ordf.),\ning. Karl-Otto Lewander, disp. Ragnar\nÖländer.\n\nVerkst. dir.; Torsten Brodin.\n\nStensö Bandfabrik, Skillingaryd.\n\nBandfabrik vid Stensö, Skillingaryd\n(Jönköp. l.). Tillverkar jacquardband,\nindiaband, mössband, hattband, band för\ntrikå- och korsettfabriker samt vävda\netiketter m. m.\n\nTelefon: 88 a. Postgiro: 30131. —\nArb.-antal: 10. — Firman etabl. 1905.\n\nÄgare o. chef: fabr. Sven Hellberg.\n\nAB. Sterlo Sportläderindustri,\n\nGislaved.\t’\n\nTillverkar läderremmar och\nläderdetaljer, velocipedrockskydd, shoppingväskor\nm. m. samt artiklar av plastic såsom\nbabybyxor, badmössor, regnhuvor och kragar,\nskyddsförkläden, tobakspungar m. m. vid\nfabrik i Gislaved (Jönköp. l.).\nVarumärke : »Sterlo».\n\nTelefon: 241. Postgiro: 173454. —\nAkt.-kap.: 32,000 kr. Antal industriarb.: 20.\nTillv.-värde. pr år: 400,000 kr. — Bolaget\ngrundat 1941.\n\nStyrelse o. verkst. dir.: Gösta S tregård.\n\nKontorschef: Sture Lundqvist.\n\n\"Sterners Skofabrik, Leksand.\n\nSe Bröderna Sterner, Leksand.\n\nStiab, Svenska Textilindustri AB.,\n\nUlricehamn.\n\nSe Svenska Textilindustri AB. Stiab,\nUlricehamn.\n\n* St i bergs Konservfabriker AB.,\n\nGöteborg.\n\nCharkuteri- och konservfabrik i\nGöteborg. Tillverkar charkuterivaror samt\nkött- och fiskkonserver.\n\nKontor: Göteborg, Almedalsväg.,\npostadr.: Göteborg 14. Telegr.-adr.:\nStibergs, Göteborg. Telefon: 160423.\nPostgiro: 42403.\n\nAkt.-kap.: 250,000 kr. Antal\nindustriarb.: 25. Omsättn.-värde pr år: 1,700,000\nkr. — Firman etabl. 1916, bolag 1925.\n\nStyrelse: disp. Harald Jerndal, dir.\nHakon Stiberg, dir. Tage Stiberg.\n\nVerkst. dir.: H. Stiberg.\n\nDisp.: H. Jerndal.\n\nKontorschef: Gunnar Levin.",
    "structured": {
        "1": {
            "name": "Stens Choklad & Konfektfabrik AB",
            "location": "Göteborg",
            "business": "Tillverkar choklad, konfekt, marmelad, karameller och dragéer",
            "contact": {
                "office": "Åvägen 18",
                "phone": [
                    "182116-18",
                    "182138"
                ],
                "postgiro": "12250"
            },
            "financials": {
                "capital": "82,500 kr",
                "employees": {
                    "industriarb": 85
                },
                "annual_production_value": "1,500,000 kr"
            },
            "foundation_year": 1924,
            "corporation_year": 1930,
            "board": [
                {
                    "name": "Olof Stenborg",
                    "role": "ordf."
                },
                {
                    "name": "Ivar Stenborg",
                    "role": "disp."
                },
                {
                    "name": "Nils Stenborg",
                    "role": "prokurist"
                }
            ],
            "director": "Olof Stenborg"
        },
        "2": {
            "name": "Stensholms Fabriks AB",
            "location": "Huskvarna",
            "business": "Mek. verkstad. Tillverkar industritillbehör såsom oljetätningsr ingår, låsringar, högtryckssmörj sprutor, eltermostater, strömställare, svänghjulsmagneter samt spistermometrar.",
            "contact": {
                "factory_office": "Stensholm, Huskvarna",
                "factory_phone": "1200",
                "postgiro": "31812",
                "telegraph": "Stensholm, Huskvarna"
            },
            "financials": {
                "capital": "82,000 kr",
                "employees": {
                    "industriarb": 270
                },
                "annual_production_value": "3,600,000 kr"
            },
            "foundation_year": 1890,
            "board": [
                {
                    "name": "F. af Klercker",
                    "role": "dir."
                },
                {
                    "name": "Johan Nordenfalk",
                    "role": "f. d. hovrättsrådet"
                },
                {
                    "name": "Percy H:sson Tamm",
                    "role": "ing."
                },
                {
                    "name": "Stig Tham",
                    "role": "civiling."
                }
            ],
            "director": "F. af Klercker"
        },
        "3": {
            "name": "AB. Stenströms Skjortfabrik",
            "location": "Hälsingborg",
            "business": "Tillverkar skjortor, kragar och manschetter samt pyjamas",
            "contact": {
                "phone": "10627",
                "postgiro": "80080"
            },
            "financials": {
                "capital": "360,000 kr",
                "employees": {
                    "industriarb": 60
                }
            },
            "foundation_year": 1899,
            "corporation_year": 1901,
            "board": [
                {
                    "name": "Henry Ljunggren",
                    "role": "assessor"
                },
                {
                    "name": "I. Stenström",
                    "role": "fröken"
                },
                {
                    "name": "A. Ohrlander",
                    "role": "köpm."
                }
            ],
            "director": "fröken I. Stenström"
        },
        "4": {
            "name": "Ch. Stenström AB.",
            "location": "Norrköping",
            "business": "Vaddfabrik och ullspinneri. Tillverkar vadd, flock, stoppmaterial, resårikuddar och madrasser, täcken, axelvaddar samt svenskulls- och schoddygarner.",
            "contact": {
                "telegraph": "Tebe, Norrköping",
                "phone": "20829",
                "postgiro": "70733",
                "sales_offices": [
                    {
                        "location": "Stockholm",
                        "phone": "619939"
                    }
                ]
            },
            "financials": {
                "capital": "72,400 kr",
                "employees": {
                    "industriarb": 65
                },
                "annual_production_value": "1,200,000 kr"
            },
            "foundation_year": 1910,
            "corporation_year": 1944,
            "board": [
                {
                    "name": "Torsten Brodin",
                    "role": "dir."
                },
                {
                    "name": "Karl-Otto Lewander",
                    "role": "ing."
                },
                {
                    "name": "Ragnar Öländer",
                    "role": "disp."
                }
            ],
            "director": "Torsten Brodin"
        },
        "5": {
            "name": "Stensö Bandfabrik",
            "location": "Skillingaryd",
            "business": "Bandfabrik vid Stensö, Skillingaryd (Jönköp. l.). Tillverkar jacquardband, indiaband, mössband, hattband, band för trikå- och korsettfabriker samt vävda etiketter m. m.",
            "contact": {
                "telegraph": "Skillingaryd",
                "phone": "88 a",
                "postgiro": "30131"
            },
            "financials": {
                "employees": {
                    "industriarb": 10
                }
            },
            "foundation_year": 1905,
            "director": "fabr. Sven Hellberg"
        },
        "6": {
            "name": "AB. Sterlo Sportläderindustri",
            "location": "Gislaved",
            "business": "Tillverkar läderremmar och läderdetaljer, velocipedrockskydd, shoppingväskor m. m. samt artiklar av plastic såsom babybyxor, badmössor, regnhuvor och kragar, skyddsförkläden, tobakspungar m. m.",
            "contact": {
                "phone": "241",
                "postgiro": "173454"
            },
            "financials": {
                "capital": "32,000 kr",
                "employees": {
                    "industriarb": 20
                },
                "annual_production_value": "400,000 kr"
            },
            "foundation_year": 1941,
            "director": "Gösta Stregård",
            "manager": "Sture Lundqvist"
        },
        "7": {
            "name": "Stiab, Svenska Textilindustri AB.",
            "location": "Ulricehamn",
            "business": "Se Svenska Textilindustri AB. Stiab, Ulricehamn"
        },
        "8": {
            "name": "Stibergs Konservfabriker AB.",
            "location": "Göteborg",
            "business": "Charkuteri- och konservfabrik i Göteborg. Tillverkar charkuterivaror samt kött- och fiskkonserver",
            "contact": {
                "office": "Almedalsväg",
                "phone": "160423",
                "postgiro": "42403"
            },
            "financials": {
                "capital": "250,000 kr",
                "employees": {
                    "industriarb": 25
                },
                "annual_turnover": "1,700,000 kr"
            },
            "foundation_year": 1916,
            "corporation_year": 1925,
            "board": [
                {
                    "name": "Harald Jerndal",
                    "role": "disp."
                },
                {
                    "name": "Hakon Stiberg",
                    "role": "dir."
                },
                {
                    "name": "Tage Stiberg",
                    "role": "dir."
                }
            ],
            "director": "H. Stiberg",
            "sales_manager": "Gunnar Levin"
        }
    }
}