{
    "original": "Svenska\n\nkontorsmaskiner och -materiel samt alla\nslag av ljuskopieringspapper.\n\nKontor: llådmansg. 84. Telegr.-adr.:\nSka, Stockholm. Telefon: 310134.\nPostgiro: 51545.\n\nAkt.-kap.: 40,000 kr. Arb.-antal: 10.\n— Firman etabl. 1929.\n\nStyrelse: kontorschef Per Jacobson\n(ordf.), fabr. Ivar österberg.\n\nVerkst. dir.: Ivar österberg.\n\n(Jfr annons nr 90.)\n\nAB. Svenska Korsettfabriken,\nJansson St Co., Stockholm.\n\nTillverkar korsetter, korseletter.\nreformliv, bysthållare m. m. samt korsettfjädrar.\n\nKontor: Mästersamuelsg. 39. Telefon:\n106197 o. 200527. Postgiro: 710.\n\nAkt.-kap.: 120,000 kr. Antal\nindustriarb.: 35. Tillv.-värde pr år: 450,000 kr.\n■— Bolaget grundat 1896.\n\nVerkst. dir.: William Jansson.\n\nSvenska Krag- och Skjortfabriken\n\nAB., Linköping.\n\nTillverkar skjortor, kragar, pyjamas\nm. m. Varumärke: »S. K. å S.».\n\nTelegr.-adr.: Kragfabriken. Linköping.\nTelefon: 20921. Postgiro: 97700.\n\nAkt.-kap.: 90,000 kr. Antal\nindustriarb.: 74. — Firman etabl. 1926, bolag\n1946.\n\nDisp.: Nils Johansson.\n\nAB. Svenska Krutfaktorierna,\n\nLandskrona.\n\nKrutbruk och ammunitionsfabrik vid\nDösjöbro (Malmöh. l.).\n\nTelegr.-adr.: Normal, Lan elskrona. —\nAkt.-kap.: 350,000 kr. Tillv.-värde pr år:\n100,000 kr.\n\nBolaget, som grundades 1893, arbetar\nunder gemensam förvaltning med\nSkånska Bomullskrutfabriks AB., Landskrona.\n\nStyrelse: dir. Carl H. Tranchell (ordf.),\ndir. Harry Tranchell (v. ordf.), fil. dr\nA. Matteoschat, major B. Wessel, ing. G.\nA. Widström.\n\nVerkst. dir.: Harry Tranchell.\n\nDisp.: A. Matteoschat.\n\n*AB. Svenska Kullagerfabriken,\n\n(SKF), Göteborg.\n\nTillverkar kullager, rullager, stålager,\nhänglager. remskivor och andra\ntransmissionselement, transportkärrhjul,\nlänkrullar, slipade gängtappar, kugghjul,\ncykelkulor samt håltolkar. Varumärke:\n»SKF».\n\nHuvudkontor: Göteborg. Telegr.-adr.:\nKullager. Göteborg. Telefon* »Kullager».\nPostgiro: 9000. Avd.-kontor: Stockholm,\nGust. Adolfx torg 18—20; Malmö,\nRun-delsg. 16: Ludvika och Jönköping.\n\nAkt.-kap.: 65,000,000 kr. Antal\nindu-striarb. i Göteborg: 4,500.\n\nBolaget, som grundades 1907, äger\nfabriker i Amerika. England. Frankrike,\nTyskland och Tjeckoslovakien samt\nförsäljningsbolag eller representanter i de\nflesta länder. Bolaget äger Hofors Bruk\n(se nedan), Lidköpings Mek. Verkstads\nAB., samt gjuteri och verkstad i\nKatrineholm (se nedan).\n\nStyrelse: dr Sven Wingquist (ordf.),\ngrossh. Knut J:son Mark (v. ordf.), dir.\nHarald IIarnberg, dir. Sverre R:son\nSohl-man, konteramiral E. Wetter.\n\nDirektion:\n\nVerkst. dir.: Harald Ilamberg.\n\nV. verkst. dir . Joel Larsson.\n\nV. verkst. dir.: Einar Glimstedt.\n\nDirektör: dr Hilding Törnebohm.\n\nDirektör: llarald Boman.\n\nChef för Göteborgsverken: övering.\nPatrik Rydbeck.\n\n(Jfr annons å Pärmens 2:a sida.)\n\n*AB. Svenska Kullagerfabriken\nHofors Bruk, Hofors.\n\nJärnverk med sintringsverk,\nbläster-masugnar och elektrohytta. martinverk,\nelektrostålverk, göt-, medium-, band-,\ntråd- och finvalsverk, smedja med\nång-och knipphamrar. hydrauliska och\nexcen-terpressar, rörpressverk. ringvalsverk,\nglödgningsverk, tråddrageri,\ncenterless-slipavdelning. kallvalsverk, gjuteri och\nmekanisk verkstad, hästskofabrik «?amt\nsågverk och järngruvor. Bolaget driver\njämväl jordbruk och skogshantering.\n\nTillverkar valsat, smitt, draget och\ncen-terlesslipat stångstål, smide, tjockväggiga\nrör. kallvalsade band, hästskor, sågat och\nhyvlat virke.\n\nSpecialiteter: kullagerstål, massivt och\nihåligt borrstål, bandstål, valstråd, SKF\nämnesrör, smidda ringar samt\ncenterles-slipat stål.\n\nTelegr.-adr.: Iloforsbruk, Hofors.\nTelefon: »Bruket». — Antal industriarb.:\n2,700, varav vid järnhanteringen 2,400.\n\nBruket anlagt på 1600-talet.\n\nDisp.: Joel Larsson (Göteborg).\n\növering. o. platschef: Ivar Bohm.\n\nEhonomichef: Eric Nyberg.\n\nFörsäljn.-chef: intendent Gunnar\nFlog-ner.\n\nGruving.: H. Löwenhielm.\n\nShogsförvalt.: B. Wetterhall.",
    "structured": {
        "1": {
            "name": "Svenska Kontorsmaskiner",
            "location": "Stockholm",
            "business": "Kontorsmaskiner och -materiel samt alla slag av ljuskopieringspapper.",
            "contact": {
                "office": "llådmansg. 84",
                "phone": [
                    "310134"
                ],
                "postgiro": "51545",
                "telegraph": "Ska, Stockholm"
            },
            "financials": {
                "capital": "40,000 kr",
                "employees": {
                    "total": 10
                }
            },
            "foundation_year": 1929,
            "board": [
                {
                    "name": "Per Jacobson",
                    "role": "Kontorschef"
                },
                {
                    "name": "Ivar österberg",
                    "role": "Fabrikör"
                }
            ],
            "director": "Ivar österberg"
        },
        "2": {
            "name": "AB. Svenska Korsettfabriken, Jansson St Co.",
            "location": "Stockholm",
            "business": "Tillverkar korsetter, korseletter, reformliv, bysthållare m. m. samt korsettfjädrar.",
            "contact": {
                "office": "Mästersamuelsg. 39",
                "phone": [
                    "106197",
                    "200527"
                ],
                "postgiro": "710"
            },
            "financials": {
                "capital": "120,000 kr",
                "employees": {
                    "total": 35
                },
                "annual_production_value": "450,000 kr"
            },
            "foundation_year": 1896,
            "director": "William Jansson"
        },
        "3": {
            "name": "Svenska Krag- och Skjortfabriken AB.",
            "location": "Linköping",
            "business": "Tillverkar skjortor, kragar, pyjamas m. m.",
            "contact": {
                "office": "Mästersamuelsg. 39",
                "phone": [
                    "106197",
                    "200527"
                ],
                "postgiro": "710"
            },
            "financials": {
                "capital": "90,000 kr",
                "employees": {
                    "total": 74
                }
            },
            "foundation_year": 1926,
            "corporation_year": 1946,
            "director": "Nils Johansson"
        },
        "4": {
            "name": "AB. Svenska Krutfaktorierna",
            "location": "Landskrona",
            "business": "Krutbruk och ammunitionsfabrik",
            "contact": {
                "telegraph": "Normals, Landelskrona",
                "postgiro": "Not specified"
            },
            "financials": {
                "capital": "350,000 kr",
                "annual_production_value": "100,000 kr"
            },
            "foundation_year": 1893,
            "board": [
                {
                    "name": "Carl H. Tranchell",
                    "role": "Dir."
                },
                {
                    "name": "Harry Tranchell",
                    "role": "V. ordf."
                },
                {
                    "name": "A. Matteoschat",
                    "role": "Fil. dr"
                },
                {
                    "name": "B. Wessel",
                    "role": "Major"
                },
                {
                    "name": "G. A. Widström",
                    "role": "Ing."
                }
            ],
            "director": "Harry Tranchell"
        },
        "5": {
            "name": "AB. Svenska Kullagerfabriken (SKF)",
            "location": "Göteborg",
            "business": "Tillverkar kullager, rullager, stålager, hänglager, remskivor och andra transmissionselement, transportkärrhjul, länkrullar, slipade gängtappar, kugghjul, cykelkulor samt håltolkar.",
            "contact": {
                "office": "Gust. Adolfx torg 18-20",
                "phone": [
                    "Not specified"
                ],
                "postgiro": "9000",
                "sales_offices": [
                    {
                        "location": "Stockholm",
                        "phone": "Not specified"
                    },
                    {
                        "location": "Malmö",
                        "phone": "Not specified"
                    },
                    {
                        "location": "Ludvika",
                        "phone": "Not specified"
                    },
                    {
                        "location": "Jönköping",
                        "phone": "Not specified"
                    }
                ]
            },
            "financials": {
                "capital": "65,000,000 kr",
                "employees": {
                    "Göteborg": 4,
                    "countries": "Amerika, England, Frankrike, Tyskland och Tjeckoslovakien"
                }
            },
            "foundation_year": 1907,
            "board": [
                {
                    "name": "Sven Wingquist",
                    "role": "Dr."
                },
                {
                    "name": "Knut J:son Mark",
                    "role": "Grossh."
                },
                {
                    "name": "Harald Harnberg",
                    "role": "Dir."
                },
                {
                    "name": "Sverre R:son Sohlman",
                    "role": "Dir."
                },
                {
                    "name": "E. Wetter",
                    "role": "Konteramiral"
                }
            ],
            "director": "Harald Ilamberg"
        },
        "6": {
            "name": "AB. Svenska Kullagerfabriken Hofors Bruk",
            "location": "Hofors",
            "business": "Järnverk med sintringsverk, blästermasugnar och elektrohytta, martinverk, elektrostålverk, göt-, medium-, band-, tråd- och finvalsverk, smedja med ång-och knipphamrar, hydrauliska och excenterpressar, rörpressverk, ringvalsverk, glödgningsverk, tråddrageri, centerless-slipavdelning, kallvalsverk, gjuteri och mekanisk verkstad, hästskofabrik samt sågverk och järngruvor. Bolaget driver även jordbruk och skogshantering. Tillverkar valsat, smitt, draget och centerlesslipat stångstål, smide, tjockväggiga rör, kallvalsade band, hästskor, sågat och hyvlat virke. Specialiteter: kullagerstål, massivt och ihåligt borrstål, bandstål, valstråd, SKF ämnesrör, smidda ringar samt centerles-slipat stål.",
            "contact": {
                "telegraph": "Hoforsbruk, Hofors",
                "phone": [
                    "Not specified"
                ]
            },
            "financials": {
                "capital": "Not specified",
                "employees": {
                    "total": 2700,
                    "iron_handling": 2400
                }
            },
            "foundation_year": "1600-talet",
            "director": "Not specified"
        }
    }
}