{
    "original": "Svenska\n\nVerkst. dir.: Johan Edström.\n\nV. verkst. dir.: Harald A. Erikson.\n\nChefer: allm.^ ventilation: ing. A. F.\nRoseli; industriella anläggningar: ing.\nKarl Nilsson; ^ anläggningar för\ncellulosaindustrin: ing. Sven Wellmar;\ntorkning: ing. G. öholm; utlandsavd.: ing.\nStig Olsson; tekn. avd.: ing. S. Sylvan;\nekonomiavd.: Jönköping: kamrer H.\nStangenberg; Stockholm: kamrer H.\nNordkvist.\n\n^ J önhöpingsv erhstäderna: platschef:\ndisp. Sigurd Pettersson; verkstadschef:\ning. Harry Lindblom.\n\nInhöpschef: Ola Olsson.\n\n^ Filialchefer: Göteborg: insr. F.\nTene-lius; Malmö: ing. Sven Hellsten;\nNorrköping: ing. Sven Matti; Sundsvall: ing.\nGösta Angehed.\n\n’Svenska Formalin AB., Stockholm.\n\nTillverkar formalin och lösningsmedel\nvid fabrik i Sickla (Sthlms l.).\n\nPostadr.: Stockholm 11. Telegr.-adr.:\nSvenskf ormalin, Stockholm. Telefon:\n440800. Postgiro: 191869.\n\nAkt.-kap.: 400,000 kr. Antal\nindustriarb.: 15. Tillv.-värde pr år: 2,000,000 kr.\n— Bolaget grundat 1942.\n\nStyrelse: dir. Albin Johansson (ordf.),\ndisp. Lars Amundsen, ing. Petrus\nHell-man, disp. Gösta Osvald.\n\nVerkst. dir.: vakant.\n\nDriftsing.: Åke Karlsson.\n\n’Svenska Fruktföreningen u. p. a.,\n\nUrshult.\n\nFabrik för konservering av frukt i\nUrs-hult (Kronob. l.). Tillverkar äppelmos,\nmarmelad, sylt, saft samt fruktvin.\n\nKontor: Urshult. Telefon: 23 o. 24.\nPostgiro: 11436.\n\nAndelskap.: 45,000 kr. Antal\nindustriarb.: 60. Tillv.-värde pr år: 1,000,000 kr.\n\nFöretaget, grundat 1915, nuv. namn\n1920, är huvudintressent i AB. Sysmos.\nStockholm.\n\nStyrelse: dir. Harald Engström (ordf.),\ndir. Ivan Nordgren, kamrer Erik Stanler,\növerstelöjtn. Knut Stanler, ing. H.\nTar-stad.\n\nVerkst. dir.: Knut Stanler.\n\nKamrer: Erik Stanler.\n\nDriftsing.: H. Tarstad.\n\nAB. Svenska Färg- &amp; Kritverken,\n\nKvarnby.\n\nTillverkar slammad krita vid slammeri\ni Lärje vid Göteborg.\n\nHuvudkontor: Kvarnby (Malmöh. l.).\n\nTelefon: Malmö 490551—52.\nExp.-kon-tor: Göteborg, ö. Hamng. 2. Telefon:\n111955. Postgiro: 12108.\n\nAkt.-kap.: 150.000 kr. Antal\nindustriarb.: 11. — Bolaget grundat 1913. AB.\nKritbruksbolaget i Malmö är\nhuvudintressent i bolaget.\n\nVerkst. dir. - Sture Bengtsson.\n\nPlatschef i Lärje: förvalt. H. Lindblad.\n\nAB. Svenska Förnickfingsfabriken,\n\nStockholm.\n\nUtför fÖrnickling, förkromning,\nfosfa-tering, galvanisering och slipning.\n\nKontor: Tuleg. 19. Telefon: 235915.\nPostgiro: 52711.\n\nAkt.-kap.: 22,300 kr. Antal\nindustriarb.: 20. Prod.-värde pr år: 350,000 kr.\n— Firman etabl. 1931, bolag 1932.\n\nVerkst. dir.: A. Elvegård.\n\n’AB. Svenska Cardinfabriken,\n\nGöteborg.\n\nVäveri i Getebergsäng, Krokslätt\n(Göteb. o. Bohus l.). Tillverkar gardiner,\nstores, täcken m. m.\n\nKontor: Mölndalsvägen 26; postadr.:\nGöteborg 5. Telegr.-adr.:\nGardinfabriken, Göteborg. Telefon: 160628. Postgiro:\n9529.\n\nAkt.-kap.: 525.000 kr. Antal\nindustriarb.: 58. — Bolaget grundat 1894.\n\nStyrelse: adv. Wilhelm Kjellström\n(ordf.), dir. Ilugo Hasselbaleh,\nkammarherre Harry Hedenstierna.\n\nVerkst. dir.: Hugo Hasselbaleh.\n\nDisp.: Joh:s A. Andersen.\n\n’Svenska AB. Casaccumulator (Aga),\n\nStockholm-Lidingö.\n\nMek. och elektromek. verkstäder,\nglas-sliperi samt fabriker för framställning\noch komprimering av gaser vid Skärsätra,\nLidingö.\n\nBolaget tillverkar:\n\nacety lengas, syrgas, kvävgas, lustgas\n(kväveoxidul), komprimerad luft och\nkarbogen (syrgas med kolsyra);\n\nbehållare för acetylen-dissousgas\n(gasackumulatorer), ventiler till behållare för\nalla i tillverkningen ingående gaser,\nmaskinerier och apparater för framställning\nav acetylengas, syrgas och kvävgas;\n\nfyrar, fyrtorn, fyrskepp,\nflygfältsbelysningar och luftfyrar med ljusapparater\nför såväl acetylen-dissousgas som för\nelektr. drift, mistsirenmaskinerier för\nkomprimerad luft och elektr. si\nrenanläggningar. även för flyglarm, lysbojar för\nacetylen-dissousgas med eller utan\nkol-syredrivna slagverk, klock- och vissel-",
    "structured": {
        "firms": [
            {
                "name": "Svenska Formalin AB.",
                "location": "Stockholm",
                "business": "Tillverkar formalin och lösningsmedel",
                "contact": {
                    "office": "Sickla (Sthlms l.)",
                    "phone": [
                        "440800"
                    ],
                    "postgiro": "191869",
                    "telegraph": "Svenskf ormalin, Stockholm"
                },
                "financials": {
                    "capital": "400,000 kr",
                    "employees": {
                        "industriarb.": 15
                    },
                    "annual_turnover": "2,000,000 kr",
                    "annual_production_value": "2,000,000 kr"
                },
                "foundation_year": 1942,
                "board": [
                    {
                        "name": "Albin Johansson",
                        "role": "ordf."
                    },
                    {
                        "name": "Lars Amundsen",
                        "role": "disp."
                    },
                    {
                        "name": "Petrus Hell-man",
                        "role": "ing."
                    },
                    {
                        "name": "Gösta Osvald",
                        "role": "disp."
                    }
                ]
            },
            {
                "name": "Svenska Fruktföreningen u. p. a.",
                "location": "Urshult",
                "business": "Fabrik för konservering av frukt",
                "contact": {
                    "office": "Urshult",
                    "phone": [
                        "23",
                        "24"
                    ],
                    "postgiro": "11436"
                },
                "financials": {
                    "capital": "45,000 kr",
                    "employees": {
                        "industriarb.": 60
                    },
                    "annual_turnover": "1,000,000 kr",
                    "annual_production_value": "1,000,000 kr"
                },
                "foundation_year": 1915,
                "current_name_year": 1920,
                "predecessor": "AB. Sysmos",
                "board": [
                    {
                        "name": "Harald Engström",
                        "role": "ordf."
                    },
                    {
                        "name": "Ivan Nordgren",
                        "role": "dir."
                    },
                    {
                        "name": "Erik Stanler",
                        "role": "kamrer"
                    },
                    {
                        "name": "Knut Stanler",
                        "role": "överstelöjtn."
                    },
                    {
                        "name": "H. Tar-stad",
                        "role": "ing."
                    }
                ]
            },
            {
                "name": "AB. Svenska Färg- & Kritverken",
                "location": "Kvarnby",
                "business": "Tillverkar slammad krita",
                "contact": {
                    "office": "Lärje vid Göteborg",
                    "phone": [
                        "490551—52"
                    ],
                    "postgiro": "12108"
                },
                "financials": {
                    "capital": "150,000 kr",
                    "employees": {
                        "industriarb.": 11
                    }
                },
                "foundation_year": 1913,
                "board": [
                    {
                        "name": "Sture Bengtsson",
                        "role": "Verkst. dir."
                    }
                ]
            },
            {
                "name": "AB. Svenska Förnickfingsfabriken",
                "location": "Stockholm",
                "business": "Utför fÖrnickling, förkromning, fosfa-tering, galvanisering och slipning",
                "contact": {
                    "office": "Tuleg. 19",
                    "phone": [
                        "235915"
                    ],
                    "postgiro": "52711"
                },
                "financials": {
                    "capital": "22,300 kr",
                    "employees": {
                        "industriarb.": 20
                    },
                    "annual_turnover": "350,000 kr"
                },
                "foundation_year": 1931,
                "corporation_year": 1932,
                "board": [
                    {
                        "name": "A. Elvegård",
                        "role": "Verkst. dir."
                    }
                ]
            },
            {
                "name": "AB. Svenska Cardinfabriken",
                "location": "Göteborg",
                "business": "Tillverkar gardiner, stores, täcken m. m.",
                "contact": {
                    "office": "Krokslätt (Göteb. o. Bohus l.)",
                    "phone": [
                        "160628"
                    ],
                    "postgiro": "9529"
                },
                "financials": {
                    "capital": "525,000 kr",
                    "employees": {
                        "industriarb.": 58
                    }
                },
                "foundation_year": 1894,
                "board": [
                    {
                        "name": "Wilhelm Kjellström",
                        "role": "adv."
                    },
                    {
                        "name": "Ilugo Hasselbaleh",
                        "role": "dir."
                    },
                    {
                        "name": "Harry Hedenstierna",
                        "role": "kammarherre"
                    }
                ]
            },
            {
                "name": "AB. Svenska Casaccumulator (Aga)",
                "location": "Stockholm-Lidingö",
                "business": "Mek. och elektromek. verkstäder, glas-sliperi samt fabriker för framställning och komprimering av gaser",
                "contact": {
                    "office": "Skärsätra, Lidingö",
                    "phone": [],
                    "postgiro": ""
                },
                "financials": {
                    "capital": "n/a",
                    "employees": {
                        "n/a": null
                    }
                },
                "foundation_year": null,
                "corporation_year": 1932,
                "board": [
                    {
                        "name": "A. Elvegård",
                        "role": "Verkst. dir."
                    }
                ]
            }
        ]
    }
}