{
    "original": "Stora—Strand\n\nösteråker (Södermanl. l.). Bryter\njärnmalm och producerar järnmalmsslig oob\nkopparmalmsslig.\n\nKontor: Hedemora. Telegr.-adr.:\nStora-långvik, Hedemora. Telefon: Hedemora\n48 o. 749, Olshyttan 50 o. 62.\n\nAkt.-kap.: 400,000 kr. Antal\nindustriarb.: 110. — Bolaget grundat 1877.\n\nStyrelse: dir. Algot Goldkuhl,\nbergsing. Bengt Schseffer.\n\nKamrer: Eric Lind.\n\nStora Wörta Tegelbruk,\n\nNättrabyhamn.\n\nTillverkar mur-, fasad- och taktegel,\nhögporöst och lättegel samt dräneringsrör\nvid tegelbruk i Nättraby (Blekinge L).\nFirman driver även jordbruk.\n\nTelefon: Nättraby 1 o. 211. Postgiro:\n5476. — Antal industriarb.: 35. Årstillv.:\n2,3 milj. st. tegelvaror. — Tegelbruket\nanlagt omkr. år 1862.\n\nÄgare: fröken Elin Mattelin.\n\nChef: fabr. Eric Mattelin.\n\n\"Storebro Bruks AB., Storebro.\n\nMek. verkstad, gjuteri och motorfabrik\ni Storebro (Kalmar l.). Tillverkar\ngängskärnings- och snabbsvarvar, marina,\nstationära och transportabla råoljemotorer\n(»Samson», »Fix» o. »Eureka»),\nmotor-vinschar, stenbearbetningsmaskiner samt\nvärmepannor.\n\nTelefon: 3, 4 o. 8. Telegr.-adr.: Bruket,\nStorebro. Postgiro: 37469.\n\nAkt.-kap.: 180,000 kr. Antal\nindustriarb.: 110. Tillv.-värde pr år: 1,000,000 kr.\n\nBruket anlagt på 1720-talet, aktiebolag\n1930.\n\nStyrelse: bankdir. Nils E. Carlson,\nkamrer Georg Nyström, fru Agda\nSvensson.\n\nDisp.: Karl-Erik Eriksson.\n\nKamrer: Georg Nyström.\n\n\"Storfors Järnverk, Storfors.\n\nSe Uddeholms AB., Uddeholm.\n\n\"storgrufve ABKärrgruvan.\n\nSe Norbergs Grufförvaltning,\nKärrgruvan.\n\n\"Storviks Sulfit AB., Ockelbo.\n\nSulfitfabrik och sulfitspritfabrik vid\nStorviks Hammarby (Gävleb. l.) samt\nsulfit-, papp-, kartong- och wallboardfabrik\nvid Fors (Kopparb. l.). Tillverkar blekt\noch oblekt sulfitcellulosa, silkecellulosa\n\noch sulfitsprit, indunstad sulfitlut samt\npapp, kartong och wallboard.\n\nHuvudkontor: Ockelbo (Gävleb. l.),\nTelegr.-adr.: Kopparfors, Gävle. Telefon:\n»Kopparfors», Ockelbo. Postgiro: 136950.\n\nAkt.-kap.: 3,600,000 kr. Antal\nindustriarb.: 305. Årstillv.: 38,000 ton torr\nsulfitcellulosa. — Bolaget, grundat 1888, äges\nav Kopparfors AB. Bolaget har i sig\nupptagit f. d. AB. Fors Bruk, Fors.\n\nStyrelse: envoyé Axel Wallenberg\n(ordf.), disp. Sigbjörn Holgersson, dir..\nBertil Wallenberg, bankdir. Jacob\nWallenberg.\n\nVerkst. dir. o. disp.’. S. Holgersson.\n\nFörsäljn.-chef: M. Wallerström.\n\n\"AB. Storviks Tegelbruk,\n\nStorvik.\n\nTegelbruk, sågverk och hyvleri i\nStorvik (Gävleb. l.). Tillverkar murtegel,\ndräneringsrör samt sågade och hyvlade\nträvaror.\n\nTelefon: 44. Postgiro: 72202. —\nAkt.-kap.: 150,000 kr. Antal industriarb.: 25.\nÅrstillv.: 2 milj. st. tegelvaror, 200 stds\nträvaror. — Bolaget grundat 1913.\n\nStyrelse: ing. Lars Carrick, ing.\nRichard Carrick, v. konsul Robert Carrick..\n\nDriftsing.: Richard Carrick.\n\n\"Storviks Yxfabrik, Storvik.\n\nSe S. A. Wetterlings Manufaktur AB.,.\nStorvik.\n\nG. E. Strahls Nya Carveri &amp; Läder»\n\naffär, Eksjö.\n\nTillverkar kromplattläder,\nkipssmor-läder, bindsulläder, kruponger,\nskinnvaror m. m.\n\nTelefon: 618. Postgiro: 27944. —\nAntal industriarb.: 5. — Firman etabl.\n1921.\n\nÄgare o. chef: fabr. Gustaf Strahl.\n\n\"Strands Konfektions AB.,\n\nKatrineholm.\n\nTillverkar herr- och gosskläder.\n\nTelegr.-adr.: Strands, Katrineholm.\nTelefon: »Strands Konfektion». Postgiro:\n11228.\n\nAkt.-kap.: 200.000 kr. Antal\nindustriarb.: 140. Tillv.-värde pr år: 2,000,000 kr.\n— Bolaget grundat 1923.\n\nStyrelse: dir. Paul E:son Strand\n(ordf.), fru O. Strand, disp. Sven Störell.\n\nVerkst. dir.: Paul E:son Strand.\n\nDisp.: Sven Störell.",
    "structured": {
        "1": {
            "name": "Stora—Strand",
            "location": "österåker (Södermanl. l.)",
            "business": "Bryter järnmalm och producerar järnmalmsslig oob kopparmalmsslig",
            "contact": {
                "office": "Hedemora",
                "phone": [
                    "Hedemora 48",
                    "Hedemora 749",
                    "Olshyttan 50",
                    "Olshyttan 62"
                ],
                "telegraph": "Stora-långvik, Hedemora"
            },
            "financials": {
                "capital": "400,000 kr",
                "employees": {
                    "industriarb": 110
                }
            },
            "foundation_year": 1877,
            "board": [
                {
                    "name": "Algot Goldkuhl",
                    "role": "dir"
                },
                {
                    "name": "Bengt Schseffer",
                    "role": "bergsing"
                }
            ]
        },
        "2": {
            "name": "Stora Wörta Tegelbruk",
            "location": "Nättrabyhamn",
            "business": "Tillverkar mur-, fasad- och taktegel, högporöst och lättegel samt dräneringsrör vid tegelbruk i Nättraby (Blekinge L). Firman driver även jordbruk.",
            "contact": {
                "phone": [
                    "Nättraby 1",
                    "Nättraby 211"
                ],
                "postgiro": "5476"
            },
            "financials": {
                "employees": {
                    "industriarb": 35
                },
                "annual_production_value": "2,300,000 st. tegelvaror"
            },
            "original_name": "Ägare: fröken Elin Mattelin",
            "director": "Chef: fabr. Eric Mattelin"
        },
        "3": {
            "name": "Storebro Bruks AB",
            "location": "Storebro",
            "business": "Mek. verkstad, gjuteri och motorfabrik i Storebro (Kalmar l.). Tillverkar gängskärnings- och snabbsvarvar, marina, stationära och transportabla råoljemotorer (»Samson», »Fix» o. »Eureka»), motor-vinschar, stenbearbetningsmaskiner samt värmepannor",
            "contact": {
                "phone": [
                    "3",
                    "4",
                    "8"
                ],
                "postgiro": "37469"
            },
            "financials": {
                "capital": "180,000 kr",
                "employees": {
                    "industriarb": 110
                },
                "annual_turnover": "1,000,000 kr"
            },
            "foundation_year": 1930,
            "board": [
                {
                    "name": "Nils E. Carlson",
                    "role": "bankdir"
                },
                {
                    "name": "Georg Nyström",
                    "role": "kamrer"
                },
                {
                    "name": "Agda Svensson",
                    "role": "fru"
                }
            ],
            "director": "Disp.: Karl-Erik Eriksson",
            "manager": "Kamrer: Georg Nyström"
        },
        "4": {
            "name": "Storviks Sulfit AB",
            "location": "Ockelbo",
            "business": "Sulfitfabrik och sulfitspritfabrik vid Storviks Hammarby (Gävleb. l.) samt sulfit-, papp-, kartong- och wallboardfabrik vid Fors (Kopparb. l.). Tillverkar blekt och oblekt sulfitcellulosa, silkecellulosa och sulfitsprit, indunstad sulfitlut samt papp, kartong och wallboard",
            "contact": {
                "office": "Ockelbo (Gävleb. l.)",
                "phone": "»Kopparfors», Ockelbo",
                "postgiro": "136950"
            },
            "financials": {
                "capital": "3,600,000 kr",
                "employees": {
                    "industriarb": 305
                },
                "annual_turnover": "38,000 ton torr sulfitcellulosa"
            },
            "foundation_year": 1888,
            "board": [
                {
                    "name": "Axel Wallenberg",
                    "role": "envoyé"
                },
                {
                    "name": "Sigbjörn Holgersson",
                    "role": "disp."
                },
                {
                    "name": "Bertil Wallenberg",
                    "role": "dir."
                }
            ],
            "director": "Verkst. dir. o. disp.’. S. Holgersson"
        },
        "5": {
            "name": "AB. Storviks Tegelbruk",
            "location": "Storvik",
            "business": "Tegelbruk, sågverk och hyvleri i Storvik (Gävleb. l.). Tillverkar murtegel, dräneringsrör samt sågade och hyvlade trävaror",
            "contact": {
                "phone": "44",
                "postgiro": "72202"
            },
            "financials": {
                "capital": "150,000 kr",
                "employees": {
                    "industriarb": 25
                },
                "annual_production_value": "2 milj. st. tegelvaror, 200 stds trävaror"
            },
            "foundation_year": 1913,
            "board": [
                {
                    "name": "Lars Carrick",
                    "role": "ing."
                },
                {
                    "name": "Richard Carrick",
                    "role": "ing."
                },
                {
                    "name": "Robert Carrick",
                    "role": "v. konsul"
                }
            ],
            "director": "Driftsing.: Richard Carrick"
        },
        "6": {
            "name": "G. E. Strahls Nya Carveri & Läderaffär",
            "location": "Eksjö",
            "business": "Tillverkar kromplattläder, kipssmor-läder, bindsulläder, kruponger, skinnvaror m. m.",
            "contact": {
                "phone": "618",
                "postgiro": "27944"
            },
            "financials": {
                "employees": {
                    "industriarb": 5
                }
            },
            "owner": "Ägare o. chef: fabr. Gustaf Strahl"
        },
        "7": {
            "name": "Strands Konfektions AB.",
            "location": "Katrineholm",
            "business": "Tillverkar herr- och gosskläder",
            "contact": {
                "telegraph": "Strands, Katrineholm",
                "postgiro": "11228"
            },
            "financials": {
                "capital": "200,000 kr",
                "employees": {
                    "industriarb": 140
                },
                "annual_turnover": "2,000,000 kr"
            },
            "foundation_year": 1923,
            "board": [
                {
                    "name": "Paul E:son Strand",
                    "role": "ordf."
                },
                {
                    "name": "O. Strand",
                    "role": "fru"
                },
                {
                    "name": "Sven Störell",
                    "role": "disp."
                }
            ],
            "director": "Verkst. dir.: Paul E:son Strand",
            "manager": "Disp.: Sven Störell"
        }
    }
}