{
    "original": "Stidsvig-—Stjermfors\n\n*Stidsvigs &amp; Hälsingborgs Lim-\n\nfabriker AB., Hälsingborg.\n\nLim- och benmjölsfabrik i Stidsvig\n(Kristianst. l.). Tillverkar hudlim och\nIbenlim, foder- och gödselbenmjöl,\nhornmjöl, benfett m. m.\n\nKontor: Hälsingborg. Telegr.-adr.:\nLimfabrikerna, Hälsingborg. Telefon:\n20010. Postgiro: 14471.\n\nAkt.-kap.: 950,000 kr. Antal\nindustriarb.: 110. — Firman etabl. 1895.\n\nStyrelse: godsäg. Anders Bergengren\n(ordf.), dir. Gösta Du Rietz, dir. Gustaf\nJEckerbom, dir. G. Guggenheimer, ing.\nSune Lindahl, bankombudsm. Eric\nPaulson.\n\nVerkst. dir.: G. Guggenheimer.\n\nAB. Stiftet, Åstorp.\n\nFabrik för tillverkning av blyerts- och\nkopiepennor i Åstorp (Kristianst. l.).\n\nKontor: Åstorp. Telefon: 273.\nPostgiro: 250254.\n\nAkt.-kap.: 100,000 kr. Antal\nindustriarb.: 60. — Bolaget grundat 1943.\n\nStyrelse: major K. Aschan.\n\nDisp.: Georg Ringesten.\n\n\"Stigens AB., Stigen.\n\nUllspinneri, ylleväveri, färgeri och\nbe-redningsverk vid Stigen (Älvsb. l.).\nTillverkar ullgarn, hel- och halvyllevävnader,\nfiltar m. m. Bolaget äger tre vattenfall\nmed elektr. kraftstationer.\n\nPostadr.: Stigen. Telegr.-adr.:\nYlle-koncernen, Uddevalla. Telefon: F är\nge-landa 4. Postgiro: 72000.\n\nAkt.-kap.: 500,000 kr. Antal\nindustriarb.: 331. Tillv.-värde pr år: 2,500,000 kr.\n\nBolaget grundat 1897. Svenska\nYllekoncernen AB., Tidan, är huvudintressent\ni bolaget.\n\nStyrelse: bankdir. E. Löwenhard (ordf.),\ndisp. C. G. Lundberg.\n\nVerkst. dir.: C. G. Lundberg (Tidan).\n\nPlatschef: Sven Jakobsson.\n\n\"AB. Alf Stigens Färgeri, Sandared.\n\nFärgeri, appreteringsyerk och\nkonst-läderfabrik i Sandared (Älvsb. L). Utför\nfärgning, beredning, prägling, ruggning\noch skärning m. m. Specialiteter:\nförädling av sidenvävnader, konstläder,\nkonst-gummering å vävnader och trikå samt\nbokbinderi- och rullgardinsväv.\n\nTelegr.-adr.: Stigsfärg, Sandared.\nTelefon-Borås 55170. Postgiro: 92310.\n\nAkt.-kap.: 300,000 kr. Antal\nindustriarb.: 200. Tillv.-värde pr år: 4,000,000 kr.\n\n—\tFirman etabl. 1931.\n\nStyrelse: dir. Alf Stigen (ordf.), fru\nH. Stigen.\n\nVerkst. dir.: Alf Stigen.\n\nAB. Stilkorsetter, Borås.\n\nTillverkar korsetter och korseletter,\nhöfthållare samt strump- och bysthållare.\n\nTelefon: 15350. Postgiro: 132101. —\nAkt.-kap.: 52,000 kr. Antal industriarb.:\n20. Tillv.-värde pr år: 350,000 kr. —\nFirman etabl. 1937.\n\nDisp.: Folke Berntson.\n\n\"AB. Stille-Werner, Stockholm.\n\nInstrumentfabrik och mek. verkstad,\nförbands- och bandagefabrik. Tillverkar\nkirurgiska instrument, sjukhus- och\noperationsmöbler samt förbandsartiklar;\nutför hejarsmide.\n\nKontor: Bondeg. 21. Telegr.-adr.:\nStille, Stockholm. Telefon:\n»Stille-Werner». Postgiro: 3494.\n\nAkt.-kap.: 700,000 kr. Antal\nindustriarb.: 200. Tillv.-värde pr år: 2,000,000 kr.\n\n—\tFirman grundad 1841.\n\nStyrelse: disp, Nils Westerdahl (ordf.),\ndir. Olof Lindström (v. ordf.),^ dir.\nGunnar K. H. Andersson, dir. Gösta\nDied-richs, med. lic. Harald Nilsonne, med. dr\nEinar Perman, med. dr Georg öhngren.\n\nVerkst. dir.: Gunnar K. H. Andersson.\n\nVice dir.: kapten Hans Hedberg.\n\nKontorschef: H. Drugge.\n\nVerkstadschef: J. G. Böving.\n\nAB. Stilmöbler, Linköping.\n\nTillverkar möbler.\n\nTelegr.-adr.: Stilmöbler, Linköping.\nTelefon: 20823. Postgiro: 98700.\n\nAkt.-kap.: 61,600 kr. Antal\nindustriarb.: 35. Tillv.-varde pr år: 350,000 kr.\n\n—\tBolaget grundat 1934.\n\nChef: fabr. Carl Johansson.\n\n\"AB. Stjernfors-Ställdalen,\n\nStälldalen.\n\nMasugnar jämte anriknings- och\nsint-ringsverk vid Bredsjö; j\närnmalmsgru-vor vid ösjöbergs-, Rishöjdbergs- och\nSalbobergsfälten; sågverk och hyvleri vid\nSkäret, Kopparberg; sågverk och hyvleri\nvid Hjulsjö; masugn, pappersbruk och\nsulfitfabrik vid Ställdalen; elektr.\nkraftstationer vid S tjärnfors, Bredsjö m. fl.\nplatser (samtliga i; Örebro l.). ^ ■-\n\nBolaget bryter järnmalm samt tillverkar\ntackjärn, sågade och hyvlade trävaror,",
    "structured": {
        "firms": [
            {
                "name": "Stidsvigs & Hälsingborgs Limfabriker AB",
                "location": "Hälsingborg",
                "business": "Lim- och benmjölsfabrik",
                "products": "Tillverkar hudlim och benlim, foder- och gödselbenmjöl, hornmjöl, benfett m. m.",
                "contact": {
                    "office": "Hälsingborg",
                    "phone": [
                        "20010"
                    ],
                    "postgiro": "14471",
                    "telegraph": "Limfabrikerna, Hälsingborg"
                },
                "financials": {
                    "capital": "950,000 kr",
                    "employees": {
                        "industriarb": 110
                    },
                    "annual_turnover": "Not available",
                    "annual_production_value": "Not available"
                },
                "foundation_year": 1895,
                "board": [
                    {
                        "name": "godsäg. Anders Bergengren",
                        "role": "ordf."
                    },
                    {
                        "name": "dir. Gösta Du Rietz",
                        "role": "dir."
                    },
                    {
                        "name": "dir. Gustaf JEckerbom",
                        "role": "dir."
                    },
                    {
                        "name": "dir. G. Guggenheimer",
                        "role": "dir."
                    },
                    {
                        "name": "ing. Sune Lindahl",
                        "role": "Not available"
                    },
                    {
                        "name": "bankombudsm. Eric Paulson",
                        "role": "Not available"
                    }
                ],
                "manager": "G. Guggenheimer"
            },
            {
                "name": "AB. Stiftet",
                "location": "Åstorp",
                "business": "Fabrik för tillverkning av blyerts- och kopiepennor",
                "contact": {
                    "office": "Åstorp",
                    "phone": [
                        "273"
                    ],
                    "postgiro": "250254"
                },
                "financials": {
                    "capital": "100,000 kr",
                    "employees": {
                        "industriarb": 60
                    }
                },
                "foundation_year": 1943,
                "board": [
                    {
                        "name": "major K. Aschan",
                        "role": "Not available"
                    }
                ],
                "director": "Not available"
            },
            {
                "name": "Stigens AB.",
                "location": "Stigen",
                "business": "Ullspinneri, ylleväveri, färgeri och beredningsverk",
                "products": "Tillverkar ullgarn, hel- och halvyllevävnader, filtar m. m.",
                "contact": {
                    "office": "Stigen",
                    "phone": [
                        "Färge-landa 4"
                    ],
                    "postgiro": "72000",
                    "telegraph": "Ylle-koncernen, Uddevalla"
                },
                "financials": {
                    "capital": "500,000 kr",
                    "employees": {
                        "industriarb": 331
                    },
                    "annual_turnover": "2,500,000 kr",
                    "annual_production_value": "2,500,000 kr"
                },
                "foundation_year": 1897,
                "board": [
                    {
                        "name": "bankdir. E. Löwenhard",
                        "role": "ordf."
                    },
                    {
                        "name": "disp. C. G. Lundberg",
                        "role": "Not available"
                    }
                ],
                "director": "C. G. Lundberg (Tidan)"
            },
            {
                "name": "AB. Alf Stigens Färgeri",
                "location": "Sandared",
                "business": "Färgeri, appreteringsverk och konstläderfabrik",
                "products": "Utför färgning, beredning, prägling, ruggning och skärning m. m. Specialiteter: förädling av sidenvävnader, konstläder, konst-gummering å vävnader och trikå samt bokbinderi- och rullgardinsväv.",
                "contact": {
                    "office": "Sandared",
                    "phone": [
                        "Borås 55170"
                    ],
                    "postgiro": "92310"
                },
                "financials": {
                    "capital": "300,000 kr",
                    "employees": {
                        "industriarb": 200
                    },
                    "annual_turnover": "4,000,000 kr",
                    "annual_production_value": "4,000,000 kr"
                },
                "foundation_year": 1931,
                "board": [
                    {
                        "name": "dir. Alf Stigen",
                        "role": "ordf."
                    },
                    {
                        "name": "fru H. Stigen",
                        "role": "Not available"
                    }
                ],
                "director": "Alf Stigen"
            },
            {
                "name": "AB. Stilkorsetter",
                "location": "Borås",
                "business": "Tillverkar korsetter och korseletter, höfthållare samt strump- och bysthållare",
                "contact": {
                    "phone": [
                        "15350"
                    ],
                    "postgiro": "132101"
                },
                "financials": {
                    "capital": "52,000 kr",
                    "employees": {
                        "industriarb": 20
                    },
                    "annual_turnover": "350,000 kr"
                },
                "foundation_year": 1937,
                "director": "Not available"
            },
            {
                "name": "AB. Stille-Werner",
                "location": "Stockholm",
                "business": "Instrumentfabrik och mek. verkstad, förbands- och bandagefabrik",
                "products": "Tillverkar kirurgiska instrument, sjukhus- och operationsmöbler samt förbandsartiklar; utför hejarsmide.",
                "contact": {
                    "office": "Bondeg. 21",
                    "phone": [
                        "Not available"
                    ],
                    "postgiro": "3494",
                    "telegraph": "Stille, Stockholm"
                },
                "financials": {
                    "capital": "700,000 kr",
                    "employees": {
                        "industriarb": 200
                    },
                    "annual_turnover": "2,000,000 kr"
                },
                "foundation_year": 1841,
                "board": [
                    {
                        "name": "disp, Nils Westerdahl",
                        "role": "ordf."
                    },
                    {
                        "name": "dir. Olof Lindström",
                        "role": "v. ordf."
                    },
                    {
                        "name": "dir. Gunnar K. H. Andersson",
                        "role": "Not available"
                    },
                    {
                        "name": "dir. Gösta Died-richs",
                        "role": "Not available"
                    },
                    {
                        "name": "med. lic. Harald Nilsonne",
                        "role": "Not available"
                    },
                    {
                        "name": "med. dr Einar Perman",
                        "role": "Not available"
                    },
                    {
                        "name": "med. dr Georg öhngren",
                        "role": "Not available"
                    }
                ],
                "manager": "Gunnar K. H. Andersson"
            },
            {
                "name": "AB. Stilmöbler",
                "location": "Linköping",
                "business": "Tillverkar möbler",
                "contact": {
                    "phone": [
                        "20823"
                    ],
                    "postgiro": "98700"
                },
                "financials": {
                    "capital": "61,600 kr",
                    "employees": {
                        "industriarb": 35
                    },
                    "annual_turnover": "350,000 kr"
                },
                "foundation_year": 1934,
                "director": "Not available"
            },
            {
                "name": "AB. Stjernfors-Ställdalen",
                "location": "Ställdalen",
                "business": "Masugnar, järnmalmsgruvor, sågverk och hyvleri, pappersbruk och sulfitfabrik, elektr. kraftstationer",
                "contact": {
                    "phone": [
                        "Not available"
                    ],
                    "postgiro": "Not available"
                }
            }
        ]
    }
}