{
    "original": "S venljunga—Svensk\n\nsamt valkfat och hasplar för garverier\nm. m. vid fabrik i Svenljunga (Älvsb. l.).\n\nTelefon: 1107. Postgiro: 143160. —\nArb.-antal: 8. Tillv.-värde pr år: 80,000\nkr. — Firman etabl. 1923.\n\nÄgare o. chef: fabr. Oscar Reinholds.\n\nAB. Svenljunga Syfabrik,\n\nSvenljunga.\n\nTillverkar herr- och damkonfektion,\narbetskläder samt herrskjortor vid fabrik\ni Svenljunga (Älvsb. l.). Varumärken:\n»Jibe» o. »Ätra».\n\nTelefon: 1002. Postgiro: 5274. —\nAkt.-kap.: 300,000 kr. Tillv.-värde pr år:\n1,500,000 kr. — Firman etabl. 1920, bolag\n1921.\n\nDisp.: John Blomquist.\n\nAB. Svenljunga Trikåfabrik,\n\nSvenljunga.\n\nTillverkar flick- och damunderkläder\nvid trikåfabrik i Svenljunga (Älvsb. l.).\n\nTelefon: 1071. Postgiro: 85831. Repr. i\nStockholm: Asperén &amp; Åkesson AB.,\nKungsg. 56, telefon: 101250.\n\nAkt.-kap.: 50,100 kr. Antal\nindustriarb.: 25. Tillv.-värde pr år: 500,000 kr. —\nFirman etabl. 1937, bolag 1940.\n\nDisp.: Nils Widén.\n\n\"Svensk Celluloidindustri AB.,\n\nGislaved.\n\nKem.-teknisk fabrik och mek. verkstad\ni Gislaved (Jönköp. l.). Tillverkar\ncel-luloidvaror såsom slanglösa\nvelocipedpumpar, velocipedhandtag, dörrskydd,\nledkort, etuier, skyltar, reklamartiklar\nsamt celluloid i plattor, massartiklar av\nkonstmassor såsom kammar, tub- och\nflaskförskruvningar samt pressade och\nsvarvade massartiklar av metall.\n\nTelegr.-adr. o. telefon: Celluloid,\nGislaved. Postgiro: 99562.\n\nAkt.-kap.: 45,000 kr. Antal\nindustriarb.: 90. Tillv.-värde pr år: 1,900,000 kr.\n— Firman grundad 1920, bolag 1944.\n\nStyrelse o. verkst. dir.: Thure\nMårtenson.\n\n(Jfr annons nr 36.)\n\n\"AB. Svensk-Engelska\nHerrkonfek-tionsfabriken Hjelm, Örkelljunga.\n\nSe AB. Fabriken Hjelm, örkelljunga.\n\nAB. Svensk Filmindustri,\n\nStockholm.\n\nFilminspelningsateljéer och\nlaboratorier i Råsunda (Sthlms l.). Bolaget ut-\n\nför inspelning, framkallning och\nkopiering av biograf- och beställningsfilmer;\nuthyr och försäljer biograffilm i Sverige\noch utlandet samt driver biografrörelse\noch skolfilmverksamhet.\n\nKontor: Centrum. Telegr.-adr.:\nFilmindustri, Stockholm. Telefon: »Svensk\nFilmindustri». Postgiro: 630. —\nAkt.-kap.: 8,000,010 kr.\n\nFirman etabl. 1919 genom\nsammanslagning av AB. Svenska Biograf teatern,\nbildat 1907, och Filmindustri AB.\nSkan-dia, bildat 1918.\n\nStyrelse: häradshövd. G. Siljeström\n(ordf.), dir. Olof Andersson, jur. dr E.\nBroms, bankdir. P. Brundell, fil. lic. C.\nA. Dymling, dir. Hugo B. Hintze, dir.\nAxel Lindberg, adv. J. Listander.\n\nVerkst. dir.: C. A. Dymling.\n\n\"Svensk Fjäder- &amp; Dunindustri AB.,\n\nS tallarholmen.\n\nFörädlar fjäder och dun samt\ntillverkar stoppningsmaterial och sängkläder vid\nfabrik i Stallarholmen (Södermanl. !.).\nVarumärke: »Sana».\n\nTelegr.-adr.: Sanadun, Stallarholmen.\nTelefon: 10. Postgiro: 57661.\n\nAkt.-kap.: 60,000 kr. Antal\nindustriarb.: 20. — Bolaget grundat 1933.\n\nStyrelse: disp. Karl Jönsson, dir. A.\nKreibom, fru Elsa Seidel.\n\nDisp.: Karl Jönsson.\n\nAB. Svensk Grammofonindustri,\n\nStockholm.\n\nTillverkar grammofonskivemassa och\nmatriser samt utför pressning av\ngrammofonskivor vid fabrik i Bro (Uppsala\n1.). Varumärke: »Toni».\n\nKontor: Stockholm, Vasag. 26.\nTelefon: 106367 o. 211007. Postgiro: 39941.\n\nAkt.-kap.: 120,000 kr. Antal\nindustriarb.: 30. Tillv.-värde pr år: 625,000 kr. —\nBolaget grundat 1937.\n\nDir.: Emil Pettersson.\n\nDisp..- Tage Andersson.\n\nKamrer: Harry Svalfors.\n\n\"AB. Svensk Knappindustri,\n\nSträngnäs.\n\nTillverkar stennötsknappar.\n\nTelegr.-adr.: Knappindustri,\nSträngnäs. Telefon: 309. Postgiro: 88890.\n\nAkt.-kap.: 50,000 kr. Antal\nindustriarb.: 60. — Firman etabl. 1934, bolag\n1941.\n\nStyrelse o. verkst. dir.: Gustav B.\nLarson.\n\n528*",
    "structured": {
        "1": {
            "name": "AB. Svensk Syfabrik",
            "location": "Svenljunga",
            "business": "Tillverkar herr- och damkonfektion, arbetskläder samt herrskjortor",
            "products": "Varumärken: »Jibe» o. »Ätra».",
            "contact": {
                "office": "Svenljunga",
                "phone": [
                    "1002"
                ],
                "postgiro": "5274",
                "telegraph": "Svensk Syfabrik, Svenljunga."
            },
            "financials": {
                "capital": "300,000 kr",
                "annual_turnover": "1,500,000 kr"
            },
            "foundation_year": 1920,
            "corporation_year": 1921,
            "board": [
                {
                    "name": "John Blomquist",
                    "role": "Disp."
                }
            ]
        },
        "2": {
            "name": "AB. Svenljunga Trikåfabrik",
            "location": "Svenljunga",
            "business": "Tillverkar flick- och damunderkläder",
            "contact": {
                "office": "Svenljunga",
                "phone": [
                    "1071"
                ],
                "postgiro": "85831",
                "sales_offices": [
                    {
                        "location": "Stockholm",
                        "phone": "Asperén & Åkesson AB., Kungsg. 56, telefon: 101250"
                    }
                ]
            },
            "financials": {
                "capital": "50,100 kr",
                "annual_turnover": "500,000 kr"
            },
            "foundation_year": 1937,
            "corporation_year": 1940,
            "board": [
                {
                    "name": "Nils Widén",
                    "role": "Disp."
                }
            ]
        },
        "3": {
            "name": "Svensk Celluloidindustri AB.",
            "location": "Gislaved",
            "business": "Kem.-teknisk fabrik och mek. verkstad",
            "products": "Tillverkar cel-luloidvaror såsom slanglösa velocipedpumpar, velocipedhandtag, dörrskydd, ledkort, etuier, skyltar, reklamartiklar samt celluloid i plattor, massartiklar av konstmassor såsom kammar, tub- och flaskförskruvningar samt pressade och svarvade massartiklar av metall.",
            "contact": {
                "office": "Gislaved",
                "phone": [
                    "Celluloid"
                ],
                "postgiro": "99562"
            },
            "financials": {
                "capital": "45,000 kr",
                "annual_turnover": "1,900,000 kr"
            },
            "foundation_year": 1920,
            "corporation_year": 1944,
            "board": [
                {
                    "name": "Thure Mårtenson",
                    "role": "Styrelse o. verkst. dir."
                }
            ]
        },
        "4": {
            "name": "AB. Svensk Filmindustri",
            "location": "Stockholm",
            "business": "Filminspelningsateljéer och laboratorier",
            "products": "Bolaget utför inspelning, framkallning och kopiering av biograf- och beställningsfilmer; uthyr och försäljer biograffilm i Sverige och utlandet samt driver biografrörelse och skolfilmverksamhet.",
            "contact": {
                "office": "Centrum",
                "telegraph": "Filmindustri, Stockholm",
                "phone": [
                    "Svensk Filmindustri"
                ],
                "postgiro": "630"
            },
            "financials": {
                "capital": "8,000,010 kr"
            },
            "foundation_year": 1919,
            "board": [
                {
                    "name": "G. Siljeström",
                    "role": "Styrelse"
                },
                {
                    "name": "Olof Andersson",
                    "role": "Styrelse"
                },
                {
                    "name": "E. Broms",
                    "role": "Styrelse"
                },
                {
                    "name": "P. Brundell",
                    "role": "Styrelse"
                },
                {
                    "name": "C. A. Dymling",
                    "role": "Styrelse"
                },
                {
                    "name": "Hugo B. Hintze",
                    "role": "Styrelse"
                },
                {
                    "name": "Axel Lindberg",
                    "role": "Styrelse"
                },
                {
                    "name": "J. Listander",
                    "role": "Styrelse"
                },
                {
                    "name": "C. A. Dymling",
                    "role": "Verkst. dir."
                }
            ]
        },
        "5": {
            "name": "Svensk Fjäder- & Dunindustri AB.",
            "location": "Stallarholmen",
            "business": "Förädlar fjäder och dun samt tillverkar stoppningsmaterial och sängkläder",
            "products": "Varumärke: »Sana».",
            "contact": {
                "office": "Stallarholmen",
                "telegraph": "Sanadun, Stallarholmen",
                "phone": [
                    "10"
                ],
                "postgiro": "57661"
            },
            "financials": {
                "capital": "60,000 kr"
            },
            "foundation_year": 1933,
            "board": [
                {
                    "name": "Karl Jönsson",
                    "role": "Disp."
                },
                {
                    "name": "A. Kreibom",
                    "role": "dir."
                },
                {
                    "name": "Elsa Seidel",
                    "role": "fru"
                }
            ]
        },
        "6": {
            "name": "AB. Svensk Grammofonindustri",
            "location": "Stockholm",
            "business": "Tillverkar grammofonskivemassa och matriser samt utför pressning av grammofonskivor",
            "products": "Varumärke: »Toni».",
            "contact": {
                "office": "Stockholm, Vasag. 26",
                "phone": [
                    "106367",
                    "211007"
                ],
                "postgiro": "39941"
            },
            "financials": {
                "capital": "120,000 kr",
                "annual_turnover": "625,000 kr"
            },
            "foundation_year": 1937,
            "board": [
                {
                    "name": "Emil Pettersson",
                    "role": "Dir."
                },
                {
                    "name": "Tage Andersson",
                    "role": "Disp."
                },
                {
                    "name": "Harry Svalfors",
                    "role": "Kamrer"
                }
            ]
        },
        "7": {
            "name": "AB. Svensk Knappindustri",
            "location": "Strängnäs",
            "business": "Tillverkar stennötsknappar",
            "contact": {
                "office": "Strängnäs",
                "phone": [
                    "309"
                ],
                "postgiro": "88890"
            },
            "financials": {
                "capital": "50,000 kr"
            },
            "foundation_year": 1934,
            "corporation_year": 1941,
            "board": [
                {
                    "name": "Gustav B. Larson",
                    "role": "Styrelse o. verkst. dir."
                }
            ]
        }
    }
}