{
    "original": "Svenska\n\nSvenska AB. Bromsregulator,\n\nMalmö.\n\nKonstruerar bromsregulatorer,\nlast-växelanordningar och fjädrande hjul för\nrälsfordon samt bilbromsar.\n\nKontor: Adeler. 5. Telegr.-adr.:\nBromsregulator, Malmö. Telefon: 28066, 28076,\n28096 o. 28689. Postgiro: 39039.\n\nAkt.-kap.: 1,200,000 kr. — Bolaget\ngrundat 1916.\n\nStyrelse: jur. dr Axel Roos (ordf.),\ndisp. A. Alfelt, ing. Ernhold Lundström,\nciviling. O. A. Nilsson.\n\nVerkst. dir.: E. Lundström.\n\nAB. Svenska Carbidkontoret,\n\nGötebon7.\n\nMek. verkstad. Tillverkar\nacetylengas-verk för svetsning, skärning,\nuppvärmning m. m. samt svets- och skärbrännare\nm. fl. tillbehör för svetsning.\nVarumärken: »Nordsvets» o. »S. C. K.» Bolaget\ndriver även försäljning av karbid för\nmoderbolaget, Stockholms Superfosfat\nFabriks AB., Stockholm.\n\nKontor: Fabriksg. 38—42. Telegr.-adr.\no. telefon: »Carbidkontoret», Göteborg.\nPostgiro: 5155. Filialkontor: Stockholm,\nOlofsg. 10: telefon: 108732.\n\nAkt.-kap.: 100,000 kr. Antal\nindustriarb.: 70. Tillv.-värde pr år (egen\ntillverkning) : 1,500,000 kr. — Bolaget\ngrundat 1917.\n\nStyrelse: fil. dr Harald Nordenson\n(ordf.), dr Sigurd Nauckhoff, civiling.\nHans Rydin.\n\nVerkst. dir.: Sven Wiklund.\n\nKamrer: Gunnar Malmborg.\n\nVerkstadschef: civiling. Sixten\nNordholm.\n\nSvenska Cellbetong AB.,\n\nFalköping.\n\nFabrik för tillverkning av ånghärdad,\nhögporös lättbetong (varumärke:\n»Cell-tong»). Utför gjutning av icke ånghärdad\ncellbetong direkt på de delar i\nbyggnaden, där stora krav ställas på isolering\nmot temperaturväxlingar; tillverkar\nbeläggningsmassa för tennisbanor\n(varumärke: »Lawnit»).\n\nPost- o. telegr.-adr. samt telefon:\nCell-tong, Falköping. — Akt.-kap.: 150,000\nkr. Antal industriarb.: 15. — Bolaget\ngrundat 1938.\n\nStyrelse: dir. G. W. Nymberg (ordf.),\nadv. E. D. Halbert.\n\nVerkst. dir.: G. W. Nymberg.\n\nDriftsing.: K. G. Ringdahl.\n\n\"Svenska Cellulosa AB.,\n\nStockholm.\n\nBolaget utgör holding company för\nbl. a. följande företag:\n\nAB. Cellulosatransport, Stockholm,\nCellufix AB., Sundsvall,\nEssviks AB., Sundsvall,\nHolmsunds AB., Holmsund,\nKramfors AB., Kramfors,\nMunksunds AB., Luleå,\nNensjö Cellulosa AB., Kramfors,\nNyhamns AB., Sundsvall,\nSkönviks AB., Sundsvall,\nStrömnäs AB., Kramfors,\nSunds AB., Sundsvall,\nSundsvalls Perspektivfönster AB.,\n\nStockholm,\nSvartviks AB., Sundsvall,\nTorpshammars AB., Sundsvall,\nUlvviks AB., Kramfors,\nAB. östrands Sulfatfabrik, Sundsvall.\nBolaget handhar överledningen av dessa\nföretag och verkställer inköp av\nföretagens större rekvisita samt är\nensamförsäljare av resp. företags tillverkningar av\nsulfit-, sulfat- och silkecellulosa,\nbiprodukter samt slipmassa.\n\nBolaget samarbetar i kommersiellt\navseende med Bergvik &amp; Ala Nya AB.y\nSöderhamn, Hammarforsens Kraft AB.,\nSundsvall, och Wii Elektriska AB.,\nSundsvall.\n\nHuvudkontor: Stockholm, V.\nTräd-gårdsg. 15. Telegr.-adr.: Pulpco,\nStockholm. Telefon: »Cellulosabolaget».\n\nAkt.-kap.: 50,000,000 kr. — Bolaget\ngrundat 1929.\n\nStyrelse: f. d. generaldir. Gösta Malm\n(ordf.), bankdir. E. Browaldh, dir.\nTorsten Hérnod, dir. Gust. J. Sahlin,\nciviling. Sten Westerberg, bankdir. P. F.\nWåhlin.\n\nVerkst. dir.: Torsten Hérnod.\nV. verkst. dir.: Gust. Göranson.\nDirektörsassist.: jur. kand. S.\nSilje-ström.\n\nDir. o. chef för avd. för industriella o.\nkamerala angelägenheter: ing. K. Erik\nNyberg.\n\nOmbudsm.: jur. kand. Gösta Carlberg.\nShogl. ärenden: jägmäst. E. W. Ronge.\nElehtr. ing.: H. Ny len.\nInhöpschef: F. Forsström.\nKamrer: L. Eriksson.\nChef för tekniska byrån: ing. Erland\nWaldenström.\n\nPatentärenden: ing. B. Birke.\nFörsal jn.-dir. o. v. verkst. dir.: Einar\nFlygt.\n\nBitr. f örsäl jn.-dir.: Sverker Kastrup.\n\n532*",
    "structured": {
        "1": {
            "name": "Svenska AB",
            "location": "Malmö",
            "business": "Konstruerar bromsregulatorer, last-växelanordningar och fjädrande hjul för rälsfordon samt bilbromsar",
            "products": "N/A",
            "contact": {
                "office": "Adeler. 5",
                "phone": [
                    "28066",
                    "28076",
                    "28096",
                    "28689"
                ],
                "postgiro": "39039",
                "telegraph": "Bromsregulator, Malmö"
            },
            "financials": {
                "capital": "1,200,000 kr",
                "employees": {
                    "total": 0,
                    "manufacturing": 0,
                    "administration": 0
                },
                "annual_turnover": "N/A",
                "annual_production_value": "N/A"
            },
            "foundation_year": 1916,
            "board": [
                {
                    "name": "jur. dr Axel Roos",
                    "role": "ordf."
                },
                {
                    "name": "disp. A. Alfelt",
                    "role": "disp."
                },
                {
                    "name": "ing. Ernhold Lundström",
                    "role": "N/A"
                },
                {
                    "name": "civiling. O. A. Nilsson",
                    "role": "N/A"
                }
            ],
            "director": "N/A",
            "managing_director": "E. Lundström",
            "sales_manager": "N/A",
            "manager": "N/A"
        },
        "2": {
            "name": "Svenska Carbidkontoret AB",
            "location": "Götebon7",
            "business": "Mek. verkstad. Tillverkar acetylengas-verk för svetsning, skärning, uppvärmning m. m. samt svets- och skärbrännare m. fl. tillbehör för svetsning",
            "products": "Nordsvets, S. C. K.",
            "contact": {
                "office": "Fabriksg. 38—42",
                "phone": "N/A",
                "postgiro": "5155",
                "telegraph": "Carbidkontoret, Göteborg"
            },
            "financials": {
                "capital": "100,000 kr",
                "employees": {
                    "total": 70
                },
                "annual_turnover": "N/A",
                "annual_production_value": "1,500,000 kr"
            },
            "foundation_year": 1917,
            "board": [
                {
                    "name": "fil. dr Harald Nordenson",
                    "role": "ordf."
                },
                {
                    "name": "dr Sigurd Nauckhoff",
                    "role": "N/A"
                },
                {
                    "name": "civiling. Hans Rydin",
                    "role": "N/A"
                }
            ],
            "director": "N/A",
            "managing_director": "Sven Wiklund",
            "sales_manager": "N/A",
            "manager": "Gunnar Malmborg"
        },
        "3": {
            "name": "Svenska Cellbetong AB",
            "location": "Falköping",
            "business": "Fabrik för tillverkning av ånghärdad, högporös lättbetong (varumärke: Cell-tong), beläggningsmassa för tennisbanor (varumärke: Lawnit)",
            "products": "N/A",
            "contact": {
                "office": "N/A",
                "phone": "N/A",
                "postgiro": "N/A",
                "telegraph": "Cell-tong, Falköping"
            },
            "financials": {
                "capital": "150,000 kr",
                "employees": {
                    "total": 15
                },
                "annual_turnover": "N/A",
                "annual_production_value": "N/A"
            },
            "foundation_year": 1938,
            "board": [
                {
                    "name": "dir. G. W. Nymberg",
                    "role": "ordf."
                },
                {
                    "name": "adv. E. D. Halbert",
                    "role": "N/A"
                }
            ],
            "director": "N/A",
            "managing_director": "G. W. Nymberg",
            "sales_manager": "N/A",
            "manager": "N/A"
        },
        "4": {
            "name": "Svenska Cellulosa AB",
            "location": "Stockholm",
            "business": "Holding company för bl. a. följande företag",
            "products": "N/A",
            "contact": {
                "office": "V. Träd-gårdsg. 15",
                "phone": "N/A",
                "telegraph": "Pulpco, Stockholm"
            },
            "financials": {
                "capital": "50,000,000 kr",
                "employees": {
                    "total": 0
                },
                "annual_turnover": "N/A",
                "annual_production_value": "N/A"
            },
            "foundation_year": 1929,
            "board": [
                {
                    "name": "f. d. generaldir. Gösta Malm",
                    "role": "ordf."
                },
                {
                    "name": "bankdir. E. Browaldh",
                    "role": "N/A"
                },
                {
                    "name": "dir. Torsten Hérnod",
                    "role": "N/A"
                },
                {
                    "name": "dir. Gust. J. Sahlin",
                    "role": "N/A"
                },
                {
                    "name": "civiling. Sten Westerberg",
                    "role": "N/A"
                },
                {
                    "name": "bankdir. P. F. Wåhlin",
                    "role": "N/A"
                }
            ],
            "director": "N/A",
            "managing_director": "Torsten Hérnod",
            "sales_manager": "N/A",
            "manager": "N/A"
        }
    }
}