{
    "original": "Svenska\n\nvid fabrik i Stockholm (Firma\nDrangel-konfektion).\n\nKontor: Valhallav. 10. Telegr.-adr.:\nKapok, Stockholm. Telefon: 328077.\nPostgiro: 53170.\n\nAkt.-kap.: 75,000 kr. Antal\nindustriarb.: 50. — Firman etabl. 1930, bolag\n1940.\n\nStyrelse: disp. Hugo Bergqvist, adv.\nO.-G. Hedström, kamrer Erik Holmberg.\n\nVerkst. dir.: Hugo Bergqvist.\n\nKamrer: Erik Holmberg.\n\n*AB. Svenska Kappfabriken,\n\nM almö.\n\nTillverkar damkappor och dräkter.\n\nKontor- Södra Promenaden 51.\nTelegr.-adr.: Kappfabriken. Malmö. Telefon:\n26535 o. 23535. Postgiro: 148940.\n\nAkt.-kap.: 312,500 kr. Antal\nindustriarb.: 70. Tillv.-värde pr år: 1,000,000 kr.\n— Firman etabl. 1907, bolag 1911.\n\nStyrelse: fru F. Hartz, grossh. Hektor\nKiaer, polismästare Y, Schaar.\n\nVerkst. dir.: fru F. Hartz.\n\nKontorschef: Alfred Nilsson.\n\n\"AB. Svenska Kapsyifabriken,\n\nStockholm.\n\nTillverkar kapsyler för flaskor och\nburkar, skruvlock. aluminiumhylsor,\naluminium-, bly- och tenn tuber m. fl.\nmetallartiklar.\n\nKontor: Tjärhovsg. 44. Telegr.-adr.:\nKapsyl, Stockholm. Telefon: 414322,\n418838 o. 433387. Postgiro: 3771.\n\nAkt.-kap.: 300,000 kr. Antal\nindustriarb.: 40. — Bolaget grundat 1888.\n\nStyrelse: f. d. taxeringskom. Sven\nEkman, disp. Folke Gill.\n\nVerkst. dir.: Folke Gill.\n\n\"Svenska Karosseri Verkstäderna\nAB., Katrineholm.\n\n^ Karos^erifabrik. Tillverkar karosserier\nför omnibusar.\n\nTelegr.-adr.: Karossen, Katrineholm.\nTelefon: 825, 826 o. 836. Postgiro: 8516.\n\nAkt.-kap.: 150,000 kr. Antal\nindustriarb.: 200. Tillv.-värde pr år: 2,000,000 kr.\n— Bolaget grundat 1927.\n\nStyrelse: disp. Alfred Jönsson, adv.\nVilh. Moberg.\n\nDisp.: Alfred Jönsson.\nFörsäljn.-chef: Nils Manning.\nInköpschef: Einar Jonsson.\n\nSvenska Kassaskåpsfabriken,\n\nStockholm.\n\nTillverkar kassaskåp, valvdörrar,\nbranddörrar m. m.\n\nKontor: Hornsg. 35. Telefon: 436654\no. 437604. Postgiro: 54538. — Antal\nindustriarb.: 18. Tillv.-värde pr år: 300,000\nkr. — Firman etabl. 1895.\n\nÄgare o. chef: ing. K. R. Berglund.\nKamrer: Nils Berglund.\n\n\"Svenska Kolsyrefabriken,\n\nStockholm.\n\nSe De Förenade Kolsyrefabrikernas\nAB., Stockholm.\n\nSvenska Konfektionsfabriken, Carl\nHögström AB-, Göteborg.\n\nTillverkar damunderkläder såsom\nnattlinnen och pyjamas.\n\nKontor: Järntorgsg. 12—14. Telefon:\n115270. Postgiro: 40459. — Akt.-kap.:\n40,000 kr. Antal industriarb.: 25. —\nFirman etabl. 1919, bolag 1941.\nVerkst. dir.: Carl Högström.\n\n\"AB. Svenska Konstgödnings- &amp;\nSvavelsyrefabrikerna, Malmö.\n\nSe AB. Förenade Superfosfatfabriker,\nHälsingborg.\n\nAB. Svenska Konservfabriken\nClobus, Stockholm.\n\nTillverkar tomatprodukter, frukt- och\ngrönsakskonserver, marmelader, bageriar-*\ntiklar m. m. vid fabrik i Hälsingborg.\nVarumärke: »Globus».\n\nHuvudkontor o. ensamförsälj.: AB.\nBanan-Kompaniet, Stockholm,\nFrihamnen, telegr.-adr. o. telefon: Bananer,\nStockholm, med avd.-kontor i Göteborg,\nMalmö o. Hälsingborg.\n\nAkt.-kap.: 5,000 kr. Antal\nindustriarb.: 60. — Bolaget grundat 1945.\n\nStyrelse: dir. Carl Matthiessen (ordf.),\ndir. Ernst Holmström, skeppsredare Sven\nG. Salén.\n\nDisp.: Erik Nilsson.\n\n\"Svenska Kopierings AB.,\n\nStockholm.\n\nt Mek. verkstad. Tillverkar stycklist- och\nljuskopieringsmaskiner, båglampor för\nkopierings- och fotoändamål samt\nframkall-ningsmaskiner. Varumärke: »S. K. A.».\nFirman driver även engroshandel med rit-",
    "structured": {
        "firms": [
            {
                "name": "Firma Drangel-konfektion",
                "location": "Stockholm",
                "business": "Konfektion",
                "contact": {
                    "office": "Valhallav. 10",
                    "phone": [
                        "328077"
                    ],
                    "postgiro": "53170"
                },
                "financials": {
                    "capital": "75,000 kr",
                    "employees": {
                        "industriarb": 50
                    },
                    "foundation_year": 1930,
                    "corporation_year": 1940
                },
                "board": [
                    {
                        "name": "Hugo Bergqvist",
                        "role": "disp."
                    },
                    {
                        "name": "O.-G. Hedström",
                        "role": "adv."
                    },
                    {
                        "name": "Erik Holmberg",
                        "role": "kamrer"
                    }
                ],
                "director": "Hugo Bergqvist"
            },
            {
                "name": "AB. Svenska Kappfabriken",
                "location": "Malmö",
                "business": "Damkappor och dräkter",
                "contact": {
                    "office": "Södra Promenaden 51",
                    "phone": [
                        "26535",
                        "23535"
                    ],
                    "postgiro": "148940"
                },
                "financials": {
                    "capital": "312,500 kr",
                    "employees": {
                        "industriarb": 70
                    },
                    "annual_production_value": "1,000,000 kr",
                    "foundation_year": 1907,
                    "corporation_year": 1911
                },
                "board": [
                    {
                        "name": "fru F. Hartz",
                        "role": "fru"
                    },
                    {
                        "name": "Hektor Kiaer",
                        "role": "grossh."
                    },
                    {
                        "name": "Y, Schaar",
                        "role": "polismästare"
                    }
                ],
                "director": "fru F. Hartz",
                "manager": "Alfred Nilsson"
            },
            {
                "name": "AB. Svenska Kapsyifabriken",
                "location": "Stockholm",
                "business": "Kapsyler för flaskor och burkar, skruvlock, aluminiumhylsor, aluminium-, bly- och tenn tuber m. fl. metallartiklar",
                "contact": {
                    "office": "Tjärhovsg. 44",
                    "phone": [
                        "414322",
                        "418838",
                        "433387"
                    ],
                    "postgiro": "3771"
                },
                "financials": {
                    "capital": "300,000 kr",
                    "employees": {
                        "industriarb": 40
                    },
                    "foundation_year": 1888
                },
                "board": [
                    {
                        "name": "Sven Ekman",
                        "role": "f.d. taxeringskom."
                    },
                    {
                        "name": "Folke Gill",
                        "role": "disp."
                    }
                ],
                "director": "Folke Gill"
            },
            {
                "name": "Svenska Karosseri Verkstäderna AB.",
                "location": "Katrineholm",
                "business": "Karosserier för omnibusar",
                "contact": {
                    "telegraph": "Karossen, Katrineholm",
                    "phone": [
                        "825",
                        "826",
                        "836"
                    ],
                    "postgiro": "8516"
                },
                "financials": {
                    "capital": "150,000 kr",
                    "employees": {
                        "industriarb": 200
                    },
                    "annual_production_value": "2,000,000 kr",
                    "foundation_year": 1927
                },
                "board": [
                    {
                        "name": "Alfred Jönsson",
                        "role": "disp."
                    },
                    {
                        "name": "Vilh. Moberg",
                        "role": "adv."
                    }
                ],
                "director": "Alfred Jönsson",
                "sales_manager": "Nils Manning",
                "manager": "Einar Jonsson"
            },
            {
                "name": "Svenska Kassaskåpsfabriken",
                "location": "Stockholm",
                "business": "Kassaskåp, valvdörrar, branddörrar m. m.",
                "contact": {
                    "office": "Hornsg. 35",
                    "phone": [
                        "436654",
                        "437604"
                    ],
                    "postgiro": "54538"
                },
                "financials": {
                    "employees": {
                        "industriarb": 18
                    },
                    "annual_production_value": "300,000 kr",
                    "foundation_year": 1895
                },
                "owners": [
                    "ing. K. R. Berglund"
                ],
                "manager": "Nils Berglund"
            },
            {
                "name": "Svenska Konfektionsfabriken, Carl Högström AB",
                "location": "Göteborg",
                "business": "Damunderkläder såsom nattlinnen och pyjamas",
                "contact": {
                    "office": "Järntorgsg. 12—14",
                    "phone": [
                        "115270"
                    ],
                    "postgiro": "40459"
                },
                "financials": {
                    "capital": "40,000 kr",
                    "employees": {
                        "industriarb": 25
                    },
                    "foundation_year": 1919,
                    "corporation_year": 1941
                },
                "director": "Carl Högström"
            },
            {
                "name": "AB. Svenska Konservfabriken Clobus",
                "location": "Stockholm",
                "business": "Tomatprodukter, frukt- och grönsakskonserver, marmelader, bageriar-tiklar m. m.",
                "contact": {
                    "office": "Hälsingborg",
                    "postgiro": "40459"
                },
                "financials": {
                    "capital": "5,000 kr",
                    "employees": {
                        "industriarb": 60
                    },
                    "foundation_year": 1945
                },
                "board": [
                    {
                        "name": "Carl Matthiessen",
                        "role": "dir."
                    },
                    {
                        "name": "Ernst Holmström",
                        "role": "dir."
                    },
                    {
                        "name": "Sven G. Salén",
                        "role": "skeppsredare"
                    }
                ],
                "director": "Erik Nilsson"
            },
            {
                "name": "Svenska Kopierings AB.",
                "location": "Stockholm",
                "business": "Stycklist- och ljuskopieringsmaskiner, båglampor för kopierings- och fotoändamål samt framkall-ningsmaskiner",
                "contact": {
                    "telegraph": "S. K. A."
                }
            }
        ]
    }
}